Compiled from "DubboBootstrap.java"
public final class org.apache.dubbo.config.bootstrap.DubboBootstrap {
  private static final java.lang.String NAME;

  private static final org.apache.dubbo.common.logger.Logger logger;

  private static final java.util.concurrent.ConcurrentMap<org.apache.dubbo.rpc.model.ApplicationModel, org.apache.dubbo.config.bootstrap.DubboBootstrap> instanceMap;

  private static volatile org.apache.dubbo.config.bootstrap.DubboBootstrap instance;

  private final java.util.concurrent.atomic.AtomicBoolean awaited;

  private volatile org.apache.dubbo.config.bootstrap.BootstrapTakeoverMode takeoverMode;

  private final java.util.concurrent.locks.Lock lock;

  private final java.util.concurrent.locks.Condition condition;

  private final org.apache.dubbo.common.threadpool.manager.ExecutorRepository executorRepository;

  private final org.apache.dubbo.common.config.Environment environment;

  private final org.apache.dubbo.rpc.model.ApplicationModel applicationModel;

  private final org.apache.dubbo.config.context.ConfigManager configManager;

  private final org.apache.dubbo.common.deploy.ApplicationDeployer applicationDeployer;

  public static org.apache.dubbo.config.bootstrap.DubboBootstrap getInstance();
    Code:
       0: getstatic     #7                  // Field instance:Lorg/apache/dubbo/config/bootstrap/DubboBootstrap;
       3: ifnonnull     36
       6: ldc           #8                  // class org/apache/dubbo/config/bootstrap/DubboBootstrap
       8: dup
       9: astore_0
      10: monitorenter
      11: getstatic     #7                  // Field instance:Lorg/apache/dubbo/config/bootstrap/DubboBootstrap;
      14: ifnonnull     26
      17: invokestatic  #9                  // Method org/apache/dubbo/rpc/model/ApplicationModel.defaultModel:()Lorg/apache/dubbo/rpc/model/ApplicationModel;
      20: invokestatic  #10                 // Method getInstance:(Lorg/apache/dubbo/rpc/model/ApplicationModel;)Lorg/apache/dubbo/config/bootstrap/DubboBootstrap;
      23: putstatic     #7                  // Field instance:Lorg/apache/dubbo/config/bootstrap/DubboBootstrap;
      26: aload_0
      27: monitorexit
      28: goto          36
      31: astore_1
      32: aload_0
      33: monitorexit
      34: aload_1
      35: athrow
      36: getstatic     #7                  // Field instance:Lorg/apache/dubbo/config/bootstrap/DubboBootstrap;
      39: areturn
    Exception table:
       from    to  target type
          11    28    31   any
          31    34    31   any

  public static org.apache.dubbo.config.bootstrap.DubboBootstrap getInstance(org.apache.dubbo.rpc.model.ApplicationModel);
    Code:
       0: getstatic     #11                 // Field instanceMap:Ljava/util/concurrent/ConcurrentMap;
       3: aload_0
       4: aload_0
       5: invokedynamic #12,  0             // InvokeDynamic #0:apply:(Lorg/apache/dubbo/rpc/model/ApplicationModel;)Ljava/util/function/Function;
      10: invokestatic  #13                 // Method org/apache/dubbo/common/utils/ConcurrentHashMapUtils.computeIfAbsent:(Ljava/util/concurrent/ConcurrentMap;Ljava/lang/Object;Ljava/util/function/Function;)Ljava/lang/Object;
      13: checkcast     #8                  // class org/apache/dubbo/config/bootstrap/DubboBootstrap
      16: areturn

  public static org.apache.dubbo.config.bootstrap.DubboBootstrap newInstance();
    Code:
       0: invokestatic  #14                 // Method org/apache/dubbo/rpc/model/FrameworkModel.defaultModel:()Lorg/apache/dubbo/rpc/model/FrameworkModel;
       3: invokevirtual #15                 // Method org/apache/dubbo/rpc/model/FrameworkModel.newApplication:()Lorg/apache/dubbo/rpc/model/ApplicationModel;
       6: invokestatic  #10                 // Method getInstance:(Lorg/apache/dubbo/rpc/model/ApplicationModel;)Lorg/apache/dubbo/config/bootstrap/DubboBootstrap;
       9: areturn

  public static org.apache.dubbo.config.bootstrap.DubboBootstrap newInstance(org.apache.dubbo.rpc.model.FrameworkModel);
    Code:
       0: aload_0
       1: invokevirtual #15                 // Method org/apache/dubbo/rpc/model/FrameworkModel.newApplication:()Lorg/apache/dubbo/rpc/model/ApplicationModel;
       4: invokestatic  #10                 // Method getInstance:(Lorg/apache/dubbo/rpc/model/ApplicationModel;)Lorg/apache/dubbo/config/bootstrap/DubboBootstrap;
       7: areturn

  public static void reset();
    Code:
       0: iconst_1
       1: invokestatic  #16                 // Method reset:(Z)V
       4: return

  public static void reset(boolean);
    Code:
       0: iload_0
       1: ifeq          26
       4: getstatic     #7                  // Field instance:Lorg/apache/dubbo/config/bootstrap/DubboBootstrap;
       7: ifnull        20
      10: getstatic     #7                  // Field instance:Lorg/apache/dubbo/config/bootstrap/DubboBootstrap;
      13: invokevirtual #17                 // Method destroy:()V
      16: aconst_null
      17: putstatic     #7                  // Field instance:Lorg/apache/dubbo/config/bootstrap/DubboBootstrap;
      20: invokestatic  #18                 // Method org/apache/dubbo/rpc/model/FrameworkModel.destroyAll:()V
      23: goto          30
      26: aconst_null
      27: putstatic     #7                  // Field instance:Lorg/apache/dubbo/config/bootstrap/DubboBootstrap;
      30: invokestatic  #19                 // Method org/apache/dubbo/rpc/model/ApplicationModel.reset:()V
      33: return

  private org.apache.dubbo.config.bootstrap.DubboBootstrap(org.apache.dubbo.rpc.model.ApplicationModel);
    Code:
       0: aload_0
       1: invokespecial #20                 // Method java/lang/Object."<init>":()V
       4: aload_0
       5: new           #21                 // class java/util/concurrent/atomic/AtomicBoolean
       8: dup
       9: iconst_0
      10: invokespecial #22                 // Method java/util/concurrent/atomic/AtomicBoolean."<init>":(Z)V
      13: putfield      #23                 // Field awaited:Ljava/util/concurrent/atomic/AtomicBoolean;
      16: aload_0
      17: getstatic     #24                 // Field org/apache/dubbo/config/bootstrap/BootstrapTakeoverMode.AUTO:Lorg/apache/dubbo/config/bootstrap/BootstrapTakeoverMode;
      20: putfield      #25                 // Field takeoverMode:Lorg/apache/dubbo/config/bootstrap/BootstrapTakeoverMode;
      23: aload_0
      24: new           #26                 // class java/util/concurrent/locks/ReentrantLock
      27: dup
      28: invokespecial #27                 // Method java/util/concurrent/locks/ReentrantLock."<init>":()V
      31: putfield      #28                 // Field lock:Ljava/util/concurrent/locks/Lock;
      34: aload_0
      35: aload_0
      36: getfield      #28                 // Field lock:Ljava/util/concurrent/locks/Lock;
      39: invokeinterface #29,  1           // InterfaceMethod java/util/concurrent/locks/Lock.newCondition:()Ljava/util/concurrent/locks/Condition;
      44: putfield      #30                 // Field condition:Ljava/util/concurrent/locks/Condition;
      47: aload_0
      48: aload_1
      49: putfield      #31                 // Field applicationModel:Lorg/apache/dubbo/rpc/model/ApplicationModel;
      52: aload_0
      53: aload_1
      54: invokevirtual #32                 // Method org/apache/dubbo/rpc/model/ApplicationModel.getApplicationConfigManager:()Lorg/apache/dubbo/config/context/ConfigManager;
      57: putfield      #33                 // Field configManager:Lorg/apache/dubbo/config/context/ConfigManager;
      60: aload_0
      61: aload_1
      62: invokevirtual #34                 // Method org/apache/dubbo/rpc/model/ApplicationModel.getModelEnvironment:()Lorg/apache/dubbo/common/config/Environment;
      65: putfield      #35                 // Field environment:Lorg/apache/dubbo/common/config/Environment;
      68: aload_0
      69: aload_1
      70: invokestatic  #36                 // InterfaceMethod org/apache/dubbo/common/threadpool/manager/ExecutorRepository.getInstance:(Lorg/apache/dubbo/rpc/model/ApplicationModel;)Lorg/apache/dubbo/common/threadpool/manager/ExecutorRepository;
      73: putfield      #37                 // Field executorRepository:Lorg/apache/dubbo/common/threadpool/manager/ExecutorRepository;
      76: aload_0
      77: aload_1
      78: invokevirtual #38                 // Method org/apache/dubbo/rpc/model/ApplicationModel.getDeployer:()Lorg/apache/dubbo/common/deploy/ApplicationDeployer;
      81: putfield      #39                 // Field applicationDeployer:Lorg/apache/dubbo/common/deploy/ApplicationDeployer;
      84: aload_0
      85: getfield      #39                 // Field applicationDeployer:Lorg/apache/dubbo/common/deploy/ApplicationDeployer;
      88: new           #40                 // class org/apache/dubbo/config/bootstrap/DubboBootstrap$1
      91: dup
      92: aload_0
      93: aload_1
      94: invokespecial #41                 // Method org/apache/dubbo/config/bootstrap/DubboBootstrap$1."<init>":(Lorg/apache/dubbo/config/bootstrap/DubboBootstrap;Lorg/apache/dubbo/rpc/model/ApplicationModel;)V
      97: invokeinterface #42,  2           // InterfaceMethod org/apache/dubbo/common/deploy/ApplicationDeployer.addDeployListener:(Lorg/apache/dubbo/common/deploy/DeployListener;)V
     102: aload_1
     103: invokevirtual #43                 // Method org/apache/dubbo/rpc/model/ApplicationModel.getBeanFactory:()Lorg/apache/dubbo/common/beans/factory/ScopeBeanFactory;
     106: aload_0
     107: invokevirtual #44                 // Method org/apache/dubbo/common/beans/factory/ScopeBeanFactory.registerBean:(Ljava/lang/Object;)V
     110: return

  private void notifyStarted(org.apache.dubbo.rpc.model.ApplicationModel);
    Code:
       0: aload_1
       1: ldc           #45                 // class org/apache/dubbo/config/bootstrap/DubboBootstrapStartStopListener
       3: invokevirtual #46                 // Method org/apache/dubbo/rpc/model/ApplicationModel.getExtensionLoader:(Ljava/lang/Class;)Lorg/apache/dubbo/common/extension/ExtensionLoader;
       6: astore_2
       7: aload_2
       8: invokevirtual #47                 // Method org/apache/dubbo/common/extension/ExtensionLoader.getSupportedExtensionInstances:()Ljava/util/Set;
      11: aload_0
      12: invokedynamic #48,  0             // InvokeDynamic #1:accept:(Lorg/apache/dubbo/config/bootstrap/DubboBootstrap;)Ljava/util/function/Consumer;
      17: invokeinterface #49,  2           // InterfaceMethod java/util/Set.forEach:(Ljava/util/function/Consumer;)V
      22: return

  private void notifyStopped(org.apache.dubbo.rpc.model.ApplicationModel);
    Code:
       0: aload_1
       1: ldc           #45                 // class org/apache/dubbo/config/bootstrap/DubboBootstrapStartStopListener
       3: invokevirtual #46                 // Method org/apache/dubbo/rpc/model/ApplicationModel.getExtensionLoader:(Ljava/lang/Class;)Lorg/apache/dubbo/common/extension/ExtensionLoader;
       6: astore_2
       7: aload_2
       8: invokevirtual #47                 // Method org/apache/dubbo/common/extension/ExtensionLoader.getSupportedExtensionInstances:()Ljava/util/Set;
      11: aload_0
      12: invokedynamic #50,  0             // InvokeDynamic #2:accept:(Lorg/apache/dubbo/config/bootstrap/DubboBootstrap;)Ljava/util/function/Consumer;
      17: invokeinterface #49,  2           // InterfaceMethod java/util/Set.forEach:(Ljava/util/function/Consumer;)V
      22: aload_0
      23: aload_0
      24: invokedynamic #51,  0             // InvokeDynamic #3:run:(Lorg/apache/dubbo/config/bootstrap/DubboBootstrap;)Ljava/lang/Runnable;
      29: invokespecial #52                 // Method executeMutually:(Ljava/lang/Runnable;)V
      32: getstatic     #11                 // Field instanceMap:Ljava/util/concurrent/ConcurrentMap;
      35: aload_1
      36: invokeinterface #53,  2           // InterfaceMethod java/util/concurrent/ConcurrentMap.remove:(Ljava/lang/Object;)Ljava/lang/Object;
      41: pop
      42: return

  public void initialize();
    Code:
       0: aload_0
       1: getfield      #39                 // Field applicationDeployer:Lorg/apache/dubbo/common/deploy/ApplicationDeployer;
       4: invokeinterface #54,  1           // InterfaceMethod org/apache/dubbo/common/deploy/ApplicationDeployer.initialize:()V
       9: return

  public org.apache.dubbo.config.bootstrap.DubboBootstrap start();
    Code:
       0: aload_0
       1: iconst_1
       2: invokevirtual #55                 // Method start:(Z)Lorg/apache/dubbo/config/bootstrap/DubboBootstrap;
       5: pop
       6: aload_0
       7: areturn

  public org.apache.dubbo.config.bootstrap.DubboBootstrap start(boolean);
    Code:
       0: aload_0
       1: getfield      #39                 // Field applicationDeployer:Lorg/apache/dubbo/common/deploy/ApplicationDeployer;
       4: invokeinterface #56,  1           // InterfaceMethod org/apache/dubbo/common/deploy/ApplicationDeployer.start:()Ljava/util/concurrent/Future;
       9: astore_2
      10: iload_1
      11: ifeq          36
      14: aload_2
      15: invokeinterface #57,  1           // InterfaceMethod java/util/concurrent/Future.get:()Ljava/lang/Object;
      20: pop
      21: goto          36
      24: astore_3
      25: new           #59                 // class java/lang/IllegalStateException
      28: dup
      29: ldc           #60                 // String await dubbo application start finish failure
      31: aload_3
      32: invokespecial #61                 // Method java/lang/IllegalStateException."<init>":(Ljava/lang/String;Ljava/lang/Throwable;)V
      35: athrow
      36: aload_0
      37: areturn
    Exception table:
       from    to  target type
          14    21    24   Class java/lang/Exception

  public java.util.concurrent.Future asyncStart();
    Code:
       0: aload_0
       1: getfield      #39                 // Field applicationDeployer:Lorg/apache/dubbo/common/deploy/ApplicationDeployer;
       4: invokeinterface #56,  1           // InterfaceMethod org/apache/dubbo/common/deploy/ApplicationDeployer.start:()Ljava/util/concurrent/Future;
       9: areturn

  public org.apache.dubbo.config.bootstrap.DubboBootstrap stop() throws java.lang.IllegalStateException;
    Code:
       0: aload_0
       1: invokevirtual #17                 // Method destroy:()V
       4: aload_0
       5: areturn

  public void destroy();
    Code:
       0: aload_0
       1: getfield      #31                 // Field applicationModel:Lorg/apache/dubbo/rpc/model/ApplicationModel;
       4: invokevirtual #62                 // Method org/apache/dubbo/rpc/model/ApplicationModel.destroy:()V
       7: return

  public boolean isInitialized();
    Code:
       0: aload_0
       1: getfield      #39                 // Field applicationDeployer:Lorg/apache/dubbo/common/deploy/ApplicationDeployer;
       4: invokeinterface #63,  1           // InterfaceMethod org/apache/dubbo/common/deploy/ApplicationDeployer.isInitialized:()Z
       9: ireturn

  public boolean isPending();
    Code:
       0: aload_0
       1: getfield      #39                 // Field applicationDeployer:Lorg/apache/dubbo/common/deploy/ApplicationDeployer;
       4: invokeinterface #64,  1           // InterfaceMethod org/apache/dubbo/common/deploy/ApplicationDeployer.isPending:()Z
       9: ireturn

  public boolean isRunning();
    Code:
       0: aload_0
       1: getfield      #39                 // Field applicationDeployer:Lorg/apache/dubbo/common/deploy/ApplicationDeployer;
       4: invokeinterface #65,  1           // InterfaceMethod org/apache/dubbo/common/deploy/ApplicationDeployer.isRunning:()Z
       9: ireturn

  public boolean isStarting();
    Code:
       0: aload_0
       1: getfield      #39                 // Field applicationDeployer:Lorg/apache/dubbo/common/deploy/ApplicationDeployer;
       4: invokeinterface #66,  1           // InterfaceMethod org/apache/dubbo/common/deploy/ApplicationDeployer.isStarting:()Z
       9: ireturn

  public boolean isStarted();
    Code:
       0: aload_0
       1: getfield      #39                 // Field applicationDeployer:Lorg/apache/dubbo/common/deploy/ApplicationDeployer;
       4: invokeinterface #67,  1           // InterfaceMethod org/apache/dubbo/common/deploy/ApplicationDeployer.isStarted:()Z
       9: ireturn

  public boolean isStopping();
    Code:
       0: aload_0
       1: getfield      #39                 // Field applicationDeployer:Lorg/apache/dubbo/common/deploy/ApplicationDeployer;
       4: invokeinterface #68,  1           // InterfaceMethod org/apache/dubbo/common/deploy/ApplicationDeployer.isStopping:()Z
       9: ireturn

  public boolean isStopped();
    Code:
       0: aload_0
       1: getfield      #39                 // Field applicationDeployer:Lorg/apache/dubbo/common/deploy/ApplicationDeployer;
       4: invokeinterface #69,  1           // InterfaceMethod org/apache/dubbo/common/deploy/ApplicationDeployer.isStopped:()Z
       9: ireturn

  public org.apache.dubbo.config.bootstrap.DubboBootstrap await();
    Code:
       0: aload_0
       1: getfield      #23                 // Field awaited:Ljava/util/concurrent/atomic/AtomicBoolean;
       4: invokevirtual #70                 // Method java/util/concurrent/atomic/AtomicBoolean.get:()Z
       7: ifne          27
      10: aload_0
      11: invokevirtual #71                 // Method isStopped:()Z
      14: ifne          27
      17: aload_0
      18: aload_0
      19: invokedynamic #72,  0             // InvokeDynamic #4:run:(Lorg/apache/dubbo/config/bootstrap/DubboBootstrap;)Ljava/lang/Runnable;
      24: invokespecial #52                 // Method executeMutually:(Ljava/lang/Runnable;)V
      27: aload_0
      28: areturn

  public org.apache.dubbo.common.config.ReferenceCache getCache();
    Code:
       0: aload_0
       1: getfield      #39                 // Field applicationDeployer:Lorg/apache/dubbo/common/deploy/ApplicationDeployer;
       4: invokeinterface #73,  1           // InterfaceMethod org/apache/dubbo/common/deploy/ApplicationDeployer.getReferenceCache:()Lorg/apache/dubbo/common/config/ReferenceCache;
       9: areturn

  private void executeMutually(java.lang.Runnable);
    Code:
       0: aload_0
       1: getfield      #28                 // Field lock:Ljava/util/concurrent/locks/Lock;
       4: invokeinterface #74,  1           // InterfaceMethod java/util/concurrent/locks/Lock.lock:()V
       9: aload_1
      10: invokeinterface #75,  1           // InterfaceMethod java/lang/Runnable.run:()V
      15: aload_0
      16: getfield      #28                 // Field lock:Ljava/util/concurrent/locks/Lock;
      19: invokeinterface #76,  1           // InterfaceMethod java/util/concurrent/locks/Lock.unlock:()V
      24: goto          39
      27: astore_2
      28: aload_0
      29: getfield      #28                 // Field lock:Ljava/util/concurrent/locks/Lock;
      32: invokeinterface #76,  1           // InterfaceMethod java/util/concurrent/locks/Lock.unlock:()V
      37: aload_2
      38: athrow
      39: return
    Exception table:
       from    to  target type
           0    15    27   any

  public org.apache.dubbo.config.ApplicationConfig getApplication();
    Code:
       0: aload_0
       1: getfield      #33                 // Field configManager:Lorg/apache/dubbo/config/context/ConfigManager;
       4: invokevirtual #77                 // Method org/apache/dubbo/config/context/ConfigManager.getApplicationOrElseThrow:()Lorg/apache/dubbo/config/ApplicationConfig;
       7: areturn

  public void setTakeoverMode(org.apache.dubbo.config.bootstrap.BootstrapTakeoverMode);
    Code:
       0: aload_0
       1: aload_1
       2: putfield      #25                 // Field takeoverMode:Lorg/apache/dubbo/config/bootstrap/BootstrapTakeoverMode;
       5: return

  public org.apache.dubbo.config.bootstrap.BootstrapTakeoverMode getTakeoverMode();
    Code:
       0: aload_0
       1: getfield      #25                 // Field takeoverMode:Lorg/apache/dubbo/config/bootstrap/BootstrapTakeoverMode;
       4: areturn

  public org.apache.dubbo.rpc.model.ApplicationModel getApplicationModel();
    Code:
       0: aload_0
       1: getfield      #31                 // Field applicationModel:Lorg/apache/dubbo/rpc/model/ApplicationModel;
       4: areturn

  public org.apache.dubbo.config.context.ConfigManager getConfigManager();
    Code:
       0: aload_0
       1: getfield      #33                 // Field configManager:Lorg/apache/dubbo/config/context/ConfigManager;
       4: areturn

  public org.apache.dubbo.config.bootstrap.DubboBootstrap metadataReport(java.util.function.Consumer<org.apache.dubbo.config.bootstrap.builders.MetadataReportBuilder>);
    Code:
       0: aload_0
       1: aconst_null
       2: aload_1
       3: invokevirtual #78                 // Method metadataReport:(Ljava/lang/String;Ljava/util/function/Consumer;)Lorg/apache/dubbo/config/bootstrap/DubboBootstrap;
       6: areturn

  public org.apache.dubbo.config.bootstrap.DubboBootstrap metadataReport(java.lang.String, java.util.function.Consumer<org.apache.dubbo.config.bootstrap.builders.MetadataReportBuilder>);
    Code:
       0: aload_0
       1: aload_1
       2: invokespecial #79                 // Method createMetadataReportBuilder:(Ljava/lang/String;)Lorg/apache/dubbo/config/bootstrap/builders/MetadataReportBuilder;
       5: astore_3
       6: aload_2
       7: aload_3
       8: invokeinterface #80,  2           // InterfaceMethod java/util/function/Consumer.accept:(Ljava/lang/Object;)V
      13: aload_0
      14: areturn

  public org.apache.dubbo.config.bootstrap.DubboBootstrap metadataReport(org.apache.dubbo.config.MetadataReportConfig);
    Code:
       0: aload_0
       1: getfield      #33                 // Field configManager:Lorg/apache/dubbo/config/context/ConfigManager;
       4: aload_1
       5: invokevirtual #81                 // Method org/apache/dubbo/config/context/ConfigManager.addMetadataReport:(Lorg/apache/dubbo/config/MetadataReportConfig;)V
       8: aload_0
       9: areturn

  public org.apache.dubbo.config.bootstrap.DubboBootstrap metadataReports(java.util.List<org.apache.dubbo.config.MetadataReportConfig>);
    Code:
       0: aload_1
       1: invokestatic  #82                 // Method org/apache/dubbo/common/utils/CollectionUtils.isEmpty:(Ljava/util/Collection;)Z
       4: ifeq          9
       7: aload_0
       8: areturn
       9: aload_0
      10: getfield      #33                 // Field configManager:Lorg/apache/dubbo/config/context/ConfigManager;
      13: aload_1
      14: invokevirtual #83                 // Method org/apache/dubbo/config/context/ConfigManager.addMetadataReports:(Ljava/lang/Iterable;)V
      17: aload_0
      18: areturn

  public org.apache.dubbo.config.bootstrap.DubboBootstrap application(java.lang.String);
    Code:
       0: aload_0
       1: aload_1
       2: invokedynamic #84,  0             // InvokeDynamic #5:accept:()Ljava/util/function/Consumer;
       7: invokevirtual #85                 // Method application:(Ljava/lang/String;Ljava/util/function/Consumer;)Lorg/apache/dubbo/config/bootstrap/DubboBootstrap;
      10: areturn

  public org.apache.dubbo.config.bootstrap.DubboBootstrap application(java.lang.String, java.util.function.Consumer<org.apache.dubbo.config.bootstrap.builders.ApplicationBuilder>);
    Code:
       0: aload_0
       1: aload_1
       2: invokespecial #86                 // Method createApplicationBuilder:(Ljava/lang/String;)Lorg/apache/dubbo/config/bootstrap/builders/ApplicationBuilder;
       5: astore_3
       6: aload_2
       7: aload_3
       8: invokeinterface #80,  2           // InterfaceMethod java/util/function/Consumer.accept:(Ljava/lang/Object;)V
      13: aload_0
      14: aload_3
      15: invokevirtual #87                 // Method org/apache/dubbo/config/bootstrap/builders/ApplicationBuilder.build:()Lorg/apache/dubbo/config/ApplicationConfig;
      18: invokevirtual #88                 // Method application:(Lorg/apache/dubbo/config/ApplicationConfig;)Lorg/apache/dubbo/config/bootstrap/DubboBootstrap;
      21: areturn

  public org.apache.dubbo.config.bootstrap.DubboBootstrap application(org.apache.dubbo.config.ApplicationConfig);
    Code:
       0: aload_1
       1: aload_0
       2: getfield      #31                 // Field applicationModel:Lorg/apache/dubbo/rpc/model/ApplicationModel;
       5: invokevirtual #89                 // Method org/apache/dubbo/config/ApplicationConfig.setScopeModel:(Lorg/apache/dubbo/rpc/model/ScopeModel;)V
       8: aload_0
       9: getfield      #33                 // Field configManager:Lorg/apache/dubbo/config/context/ConfigManager;
      12: aload_1
      13: invokevirtual #90                 // Method org/apache/dubbo/config/context/ConfigManager.setApplication:(Lorg/apache/dubbo/config/ApplicationConfig;)V
      16: aload_0
      17: areturn

  public org.apache.dubbo.config.bootstrap.DubboBootstrap registry(java.util.function.Consumer<org.apache.dubbo.config.bootstrap.builders.RegistryBuilder>);
    Code:
       0: aload_0
       1: aconst_null
       2: aload_1
       3: invokevirtual #91                 // Method registry:(Ljava/lang/String;Ljava/util/function/Consumer;)Lorg/apache/dubbo/config/bootstrap/DubboBootstrap;
       6: areturn

  public org.apache.dubbo.config.bootstrap.DubboBootstrap registry(java.lang.String, java.util.function.Consumer<org.apache.dubbo.config.bootstrap.builders.RegistryBuilder>);
    Code:
       0: aload_0
       1: aload_1
       2: invokespecial #92                 // Method createRegistryBuilder:(Ljava/lang/String;)Lorg/apache/dubbo/config/bootstrap/builders/RegistryBuilder;
       5: astore_3
       6: aload_2
       7: aload_3
       8: invokeinterface #80,  2           // InterfaceMethod java/util/function/Consumer.accept:(Ljava/lang/Object;)V
      13: aload_0
      14: aload_3
      15: invokevirtual #93                 // Method org/apache/dubbo/config/bootstrap/builders/RegistryBuilder.build:()Lorg/apache/dubbo/config/RegistryConfig;
      18: invokevirtual #94                 // Method registry:(Lorg/apache/dubbo/config/RegistryConfig;)Lorg/apache/dubbo/config/bootstrap/DubboBootstrap;
      21: areturn

  public org.apache.dubbo.config.bootstrap.DubboBootstrap registry(org.apache.dubbo.config.RegistryConfig);
    Code:
       0: aload_1
       1: aload_0
       2: getfield      #31                 // Field applicationModel:Lorg/apache/dubbo/rpc/model/ApplicationModel;
       5: invokevirtual #95                 // Method org/apache/dubbo/config/RegistryConfig.setScopeModel:(Lorg/apache/dubbo/rpc/model/ScopeModel;)V
       8: aload_0
       9: getfield      #33                 // Field configManager:Lorg/apache/dubbo/config/context/ConfigManager;
      12: aload_1
      13: invokevirtual #96                 // Method org/apache/dubbo/config/context/ConfigManager.addRegistry:(Lorg/apache/dubbo/config/RegistryConfig;)V
      16: aload_0
      17: areturn

  public org.apache.dubbo.config.bootstrap.DubboBootstrap registries(java.util.List<org.apache.dubbo.config.RegistryConfig>);
    Code:
       0: aload_1
       1: invokestatic  #82                 // Method org/apache/dubbo/common/utils/CollectionUtils.isEmpty:(Ljava/util/Collection;)Z
       4: ifeq          9
       7: aload_0
       8: areturn
       9: aload_1
      10: aload_0
      11: invokedynamic #97,  0             // InvokeDynamic #6:accept:(Lorg/apache/dubbo/config/bootstrap/DubboBootstrap;)Ljava/util/function/Consumer;
      16: invokeinterface #98,  2           // InterfaceMethod java/util/List.forEach:(Ljava/util/function/Consumer;)V
      21: aload_0
      22: areturn

  public org.apache.dubbo.config.bootstrap.DubboBootstrap protocol(java.util.function.Consumer<org.apache.dubbo.config.bootstrap.builders.ProtocolBuilder>);
    Code:
       0: aload_0
       1: aconst_null
       2: aload_1
       3: invokevirtual #99                 // Method protocol:(Ljava/lang/String;Ljava/util/function/Consumer;)Lorg/apache/dubbo/config/bootstrap/DubboBootstrap;
       6: areturn

  public org.apache.dubbo.config.bootstrap.DubboBootstrap protocol(java.lang.String, java.util.function.Consumer<org.apache.dubbo.config.bootstrap.builders.ProtocolBuilder>);
    Code:
       0: aload_0
       1: aload_1
       2: invokespecial #100                // Method createProtocolBuilder:(Ljava/lang/String;)Lorg/apache/dubbo/config/bootstrap/builders/ProtocolBuilder;
       5: astore_3
       6: aload_2
       7: aload_3
       8: invokeinterface #80,  2           // InterfaceMethod java/util/function/Consumer.accept:(Ljava/lang/Object;)V
      13: aload_0
      14: aload_3
      15: invokevirtual #101                // Method org/apache/dubbo/config/bootstrap/builders/ProtocolBuilder.build:()Lorg/apache/dubbo/config/ProtocolConfig;
      18: invokevirtual #102                // Method protocol:(Lorg/apache/dubbo/config/ProtocolConfig;)Lorg/apache/dubbo/config/bootstrap/DubboBootstrap;
      21: areturn

  public org.apache.dubbo.config.bootstrap.DubboBootstrap protocol(org.apache.dubbo.config.ProtocolConfig);
    Code:
       0: aload_0
       1: aload_1
       2: invokestatic  #103                // Method java/util/Collections.singletonList:(Ljava/lang/Object;)Ljava/util/List;
       5: invokevirtual #104                // Method protocols:(Ljava/util/List;)Lorg/apache/dubbo/config/bootstrap/DubboBootstrap;
       8: areturn

  public org.apache.dubbo.config.bootstrap.DubboBootstrap protocols(java.util.List<org.apache.dubbo.config.ProtocolConfig>);
    Code:
       0: aload_1
       1: invokestatic  #82                 // Method org/apache/dubbo/common/utils/CollectionUtils.isEmpty:(Ljava/util/Collection;)Z
       4: ifeq          9
       7: aload_0
       8: areturn
       9: aload_1
      10: invokeinterface #105,  1          // InterfaceMethod java/util/List.iterator:()Ljava/util/Iterator;
      15: astore_2
      16: aload_2
      17: invokeinterface #106,  1          // InterfaceMethod java/util/Iterator.hasNext:()Z
      22: ifeq          54
      25: aload_2
      26: invokeinterface #107,  1          // InterfaceMethod java/util/Iterator.next:()Ljava/lang/Object;
      31: checkcast     #108                // class org/apache/dubbo/config/ProtocolConfig
      34: astore_3
      35: aload_3
      36: aload_0
      37: getfield      #31                 // Field applicationModel:Lorg/apache/dubbo/rpc/model/ApplicationModel;
      40: invokevirtual #109                // Method org/apache/dubbo/config/ProtocolConfig.setScopeModel:(Lorg/apache/dubbo/rpc/model/ScopeModel;)V
      43: aload_0
      44: getfield      #33                 // Field configManager:Lorg/apache/dubbo/config/context/ConfigManager;
      47: aload_3
      48: invokevirtual #110                // Method org/apache/dubbo/config/context/ConfigManager.addProtocol:(Lorg/apache/dubbo/config/ProtocolConfig;)V
      51: goto          16
      54: aload_0
      55: areturn

  public <S> org.apache.dubbo.config.bootstrap.DubboBootstrap service(java.util.function.Consumer<org.apache.dubbo.config.bootstrap.builders.ServiceBuilder<S>>);
    Code:
       0: aload_0
       1: aconst_null
       2: aload_1
       3: invokevirtual #111                // Method service:(Ljava/lang/String;Ljava/util/function/Consumer;)Lorg/apache/dubbo/config/bootstrap/DubboBootstrap;
       6: areturn

  public <S> org.apache.dubbo.config.bootstrap.DubboBootstrap service(java.lang.String, java.util.function.Consumer<org.apache.dubbo.config.bootstrap.builders.ServiceBuilder<S>>);
    Code:
       0: aload_0
       1: aload_0
       2: aload_1
       3: aload_2
       4: invokespecial #4                  // Method createServiceConfig:(Ljava/lang/String;Ljava/util/function/Consumer;)Lorg/apache/dubbo/config/ServiceConfig;
       7: invokevirtual #112                // Method service:(Lorg/apache/dubbo/config/ServiceConfig;)Lorg/apache/dubbo/config/bootstrap/DubboBootstrap;
      10: areturn

  private <S> org.apache.dubbo.config.ServiceConfig createServiceConfig(java.lang.String, java.util.function.Consumer<org.apache.dubbo.config.bootstrap.builders.ServiceBuilder<S>>);
    Code:
       0: aload_0
       1: aload_1
       2: invokespecial #113                // Method createServiceBuilder:(Ljava/lang/String;)Lorg/apache/dubbo/config/bootstrap/builders/ServiceBuilder;
       5: astore_3
       6: aload_2
       7: aload_3
       8: invokeinterface #80,  2           // InterfaceMethod java/util/function/Consumer.accept:(Ljava/lang/Object;)V
      13: aload_3
      14: invokevirtual #114                // Method org/apache/dubbo/config/bootstrap/builders/ServiceBuilder.build:()Lorg/apache/dubbo/config/ServiceConfig;
      17: astore        4
      19: aload         4
      21: areturn

  public org.apache.dubbo.config.bootstrap.DubboBootstrap services(java.util.List<org.apache.dubbo.config.ServiceConfig>);
    Code:
       0: aload_1
       1: invokestatic  #82                 // Method org/apache/dubbo/common/utils/CollectionUtils.isEmpty:(Ljava/util/Collection;)Z
       4: ifeq          9
       7: aload_0
       8: areturn
       9: aload_1
      10: invokeinterface #105,  1          // InterfaceMethod java/util/List.iterator:()Ljava/util/Iterator;
      15: astore_2
      16: aload_2
      17: invokeinterface #106,  1          // InterfaceMethod java/util/Iterator.hasNext:()Z
      22: ifeq          44
      25: aload_2
      26: invokeinterface #107,  1          // InterfaceMethod java/util/Iterator.next:()Ljava/lang/Object;
      31: checkcast     #115                // class org/apache/dubbo/config/ServiceConfig
      34: astore_3
      35: aload_0
      36: aload_3
      37: invokevirtual #112                // Method service:(Lorg/apache/dubbo/config/ServiceConfig;)Lorg/apache/dubbo/config/bootstrap/DubboBootstrap;
      40: pop
      41: goto          16
      44: aload_0
      45: areturn

  public org.apache.dubbo.config.bootstrap.DubboBootstrap service(org.apache.dubbo.config.ServiceConfig<?>);
    Code:
       0: aload_0
       1: aload_1
       2: aload_0
       3: getfield      #31                 // Field applicationModel:Lorg/apache/dubbo/rpc/model/ApplicationModel;
       6: invokevirtual #116                // Method org/apache/dubbo/rpc/model/ApplicationModel.getDefaultModule:()Lorg/apache/dubbo/rpc/model/ModuleModel;
       9: invokevirtual #117                // Method service:(Lorg/apache/dubbo/config/ServiceConfig;Lorg/apache/dubbo/rpc/model/ModuleModel;)Lorg/apache/dubbo/config/bootstrap/DubboBootstrap;
      12: pop
      13: aload_0
      14: areturn

  public org.apache.dubbo.config.bootstrap.DubboBootstrap service(org.apache.dubbo.config.ServiceConfig<?>, org.apache.dubbo.rpc.model.ModuleModel);
    Code:
       0: aload_1
       1: aload_2
       2: invokevirtual #118                // Method org/apache/dubbo/config/ServiceConfig.setScopeModel:(Lorg/apache/dubbo/rpc/model/ScopeModel;)V
       5: aload_2
       6: invokevirtual #119                // Method org/apache/dubbo/rpc/model/ModuleModel.getConfigManager:()Lorg/apache/dubbo/config/context/ModuleConfigManager;
       9: aload_1
      10: invokevirtual #120                // Method org/apache/dubbo/config/context/ModuleConfigManager.addService:(Lorg/apache/dubbo/config/ServiceConfigBase;)V
      13: aload_0
      14: areturn

  public <S> org.apache.dubbo.config.bootstrap.DubboBootstrap reference(java.util.function.Consumer<org.apache.dubbo.config.bootstrap.builders.ReferenceBuilder<S>>);
    Code:
       0: aload_0
       1: aconst_null
       2: aload_1
       3: invokevirtual #121                // Method reference:(Ljava/lang/String;Ljava/util/function/Consumer;)Lorg/apache/dubbo/config/bootstrap/DubboBootstrap;
       6: areturn

  public <S> org.apache.dubbo.config.bootstrap.DubboBootstrap reference(java.lang.String, java.util.function.Consumer<org.apache.dubbo.config.bootstrap.builders.ReferenceBuilder<S>>);
    Code:
       0: aload_0
       1: aload_0
       2: aload_1
       3: aload_2
       4: invokespecial #3                  // Method createReferenceConfig:(Ljava/lang/String;Ljava/util/function/Consumer;)Lorg/apache/dubbo/config/ReferenceConfig;
       7: invokevirtual #122                // Method reference:(Lorg/apache/dubbo/config/ReferenceConfig;)Lorg/apache/dubbo/config/bootstrap/DubboBootstrap;
      10: areturn

  private <S> org.apache.dubbo.config.ReferenceConfig createReferenceConfig(java.lang.String, java.util.function.Consumer<org.apache.dubbo.config.bootstrap.builders.ReferenceBuilder<S>>);
    Code:
       0: aload_0
       1: aload_1
       2: invokespecial #123                // Method createReferenceBuilder:(Ljava/lang/String;)Lorg/apache/dubbo/config/bootstrap/builders/ReferenceBuilder;
       5: astore_3
       6: aload_2
       7: aload_3
       8: invokeinterface #80,  2           // InterfaceMethod java/util/function/Consumer.accept:(Ljava/lang/Object;)V
      13: aload_3
      14: invokevirtual #124                // Method org/apache/dubbo/config/bootstrap/builders/ReferenceBuilder.build:()Lorg/apache/dubbo/config/ReferenceConfig;
      17: astore        4
      19: aload         4
      21: areturn

  public org.apache.dubbo.config.bootstrap.DubboBootstrap references(java.util.List<org.apache.dubbo.config.ReferenceConfig>);
    Code:
       0: aload_1
       1: invokestatic  #82                 // Method org/apache/dubbo/common/utils/CollectionUtils.isEmpty:(Ljava/util/Collection;)Z
       4: ifeq          9
       7: aload_0
       8: areturn
       9: aload_1
      10: invokeinterface #105,  1          // InterfaceMethod java/util/List.iterator:()Ljava/util/Iterator;
      15: astore_2
      16: aload_2
      17: invokeinterface #106,  1          // InterfaceMethod java/util/Iterator.hasNext:()Z
      22: ifeq          44
      25: aload_2
      26: invokeinterface #107,  1          // InterfaceMethod java/util/Iterator.next:()Ljava/lang/Object;
      31: checkcast     #125                // class org/apache/dubbo/config/ReferenceConfig
      34: astore_3
      35: aload_0
      36: aload_3
      37: invokevirtual #122                // Method reference:(Lorg/apache/dubbo/config/ReferenceConfig;)Lorg/apache/dubbo/config/bootstrap/DubboBootstrap;
      40: pop
      41: goto          16
      44: aload_0
      45: areturn

  public org.apache.dubbo.config.bootstrap.DubboBootstrap reference(org.apache.dubbo.config.ReferenceConfig<?>);
    Code:
       0: aload_0
       1: aload_1
       2: aload_0
       3: getfield      #31                 // Field applicationModel:Lorg/apache/dubbo/rpc/model/ApplicationModel;
       6: invokevirtual #116                // Method org/apache/dubbo/rpc/model/ApplicationModel.getDefaultModule:()Lorg/apache/dubbo/rpc/model/ModuleModel;
       9: invokevirtual #126                // Method reference:(Lorg/apache/dubbo/config/ReferenceConfig;Lorg/apache/dubbo/rpc/model/ModuleModel;)Lorg/apache/dubbo/config/bootstrap/DubboBootstrap;
      12: areturn

  public org.apache.dubbo.config.bootstrap.DubboBootstrap reference(org.apache.dubbo.config.ReferenceConfig<?>, org.apache.dubbo.rpc.model.ModuleModel);
    Code:
       0: aload_1
       1: aload_2
       2: invokevirtual #127                // Method org/apache/dubbo/config/ReferenceConfig.setScopeModel:(Lorg/apache/dubbo/rpc/model/ScopeModel;)V
       5: aload_2
       6: invokevirtual #119                // Method org/apache/dubbo/rpc/model/ModuleModel.getConfigManager:()Lorg/apache/dubbo/config/context/ModuleConfigManager;
       9: aload_1
      10: invokevirtual #128                // Method org/apache/dubbo/config/context/ModuleConfigManager.addReference:(Lorg/apache/dubbo/config/ReferenceConfigBase;)V
      13: aload_0
      14: areturn

  public org.apache.dubbo.config.bootstrap.DubboBootstrap provider(java.util.function.Consumer<org.apache.dubbo.config.bootstrap.builders.ProviderBuilder>);
    Code:
       0: aload_0
       1: aconst_null
       2: aload_1
       3: invokevirtual #129                // Method provider:(Ljava/lang/String;Ljava/util/function/Consumer;)Lorg/apache/dubbo/config/bootstrap/DubboBootstrap;
       6: pop
       7: aload_0
       8: areturn

  public org.apache.dubbo.config.bootstrap.DubboBootstrap provider(java.lang.String, java.util.function.Consumer<org.apache.dubbo.config.bootstrap.builders.ProviderBuilder>);
    Code:
       0: aload_0
       1: aload_0
       2: aload_1
       3: aload_2
       4: invokespecial #2                  // Method createProviderConfig:(Ljava/lang/String;Ljava/util/function/Consumer;)Lorg/apache/dubbo/config/ProviderConfig;
       7: invokevirtual #130                // Method provider:(Lorg/apache/dubbo/config/ProviderConfig;)Lorg/apache/dubbo/config/bootstrap/DubboBootstrap;
      10: pop
      11: aload_0
      12: areturn

  private org.apache.dubbo.config.ProviderConfig createProviderConfig(java.lang.String, java.util.function.Consumer<org.apache.dubbo.config.bootstrap.builders.ProviderBuilder>);
    Code:
       0: aload_0
       1: aload_1
       2: invokespecial #131                // Method createProviderBuilder:(Ljava/lang/String;)Lorg/apache/dubbo/config/bootstrap/builders/ProviderBuilder;
       5: astore_3
       6: aload_2
       7: aload_3
       8: invokeinterface #80,  2           // InterfaceMethod java/util/function/Consumer.accept:(Ljava/lang/Object;)V
      13: aload_3
      14: invokevirtual #132                // Method org/apache/dubbo/config/bootstrap/builders/ProviderBuilder.build:()Lorg/apache/dubbo/config/ProviderConfig;
      17: astore        4
      19: aload         4
      21: areturn

  public org.apache.dubbo.config.bootstrap.DubboBootstrap provider(org.apache.dubbo.config.ProviderConfig);
    Code:
       0: aload_0
       1: aload_1
       2: aload_0
       3: getfield      #31                 // Field applicationModel:Lorg/apache/dubbo/rpc/model/ApplicationModel;
       6: invokevirtual #116                // Method org/apache/dubbo/rpc/model/ApplicationModel.getDefaultModule:()Lorg/apache/dubbo/rpc/model/ModuleModel;
       9: invokevirtual #133                // Method provider:(Lorg/apache/dubbo/config/ProviderConfig;Lorg/apache/dubbo/rpc/model/ModuleModel;)Lorg/apache/dubbo/config/bootstrap/DubboBootstrap;
      12: areturn

  public org.apache.dubbo.config.bootstrap.DubboBootstrap providers(java.util.List<org.apache.dubbo.config.ProviderConfig>);
    Code:
       0: aload_1
       1: invokeinterface #105,  1          // InterfaceMethod java/util/List.iterator:()Ljava/util/Iterator;
       6: astore_2
       7: aload_2
       8: invokeinterface #106,  1          // InterfaceMethod java/util/Iterator.hasNext:()Z
      13: ifeq          42
      16: aload_2
      17: invokeinterface #107,  1          // InterfaceMethod java/util/Iterator.next:()Ljava/lang/Object;
      22: checkcast     #134                // class org/apache/dubbo/config/ProviderConfig
      25: astore_3
      26: aload_0
      27: aload_3
      28: aload_0
      29: getfield      #31                 // Field applicationModel:Lorg/apache/dubbo/rpc/model/ApplicationModel;
      32: invokevirtual #116                // Method org/apache/dubbo/rpc/model/ApplicationModel.getDefaultModule:()Lorg/apache/dubbo/rpc/model/ModuleModel;
      35: invokevirtual #133                // Method provider:(Lorg/apache/dubbo/config/ProviderConfig;Lorg/apache/dubbo/rpc/model/ModuleModel;)Lorg/apache/dubbo/config/bootstrap/DubboBootstrap;
      38: pop
      39: goto          7
      42: aload_0
      43: areturn

  public org.apache.dubbo.config.bootstrap.DubboBootstrap provider(org.apache.dubbo.config.ProviderConfig, org.apache.dubbo.rpc.model.ModuleModel);
    Code:
       0: aload_1
       1: aload_2
       2: invokevirtual #135                // Method org/apache/dubbo/config/ProviderConfig.setScopeModel:(Lorg/apache/dubbo/rpc/model/ScopeModel;)V
       5: aload_2
       6: invokevirtual #119                // Method org/apache/dubbo/rpc/model/ModuleModel.getConfigManager:()Lorg/apache/dubbo/config/context/ModuleConfigManager;
       9: aload_1
      10: invokevirtual #136                // Method org/apache/dubbo/config/context/ModuleConfigManager.addProvider:(Lorg/apache/dubbo/config/ProviderConfig;)V
      13: aload_0
      14: areturn

  public org.apache.dubbo.config.bootstrap.DubboBootstrap consumer(java.util.function.Consumer<org.apache.dubbo.config.bootstrap.builders.ConsumerBuilder>);
    Code:
       0: aload_0
       1: aconst_null
       2: aload_1
       3: invokevirtual #137                // Method consumer:(Ljava/lang/String;Ljava/util/function/Consumer;)Lorg/apache/dubbo/config/bootstrap/DubboBootstrap;
       6: areturn

  public org.apache.dubbo.config.bootstrap.DubboBootstrap consumer(java.lang.String, java.util.function.Consumer<org.apache.dubbo.config.bootstrap.builders.ConsumerBuilder>);
    Code:
       0: aload_0
       1: aload_0
       2: aload_1
       3: aload_2
       4: invokespecial #1                  // Method createConsumerConfig:(Ljava/lang/String;Ljava/util/function/Consumer;)Lorg/apache/dubbo/config/ConsumerConfig;
       7: invokevirtual #138                // Method consumer:(Lorg/apache/dubbo/config/ConsumerConfig;)Lorg/apache/dubbo/config/bootstrap/DubboBootstrap;
      10: areturn

  private org.apache.dubbo.config.ConsumerConfig createConsumerConfig(java.lang.String, java.util.function.Consumer<org.apache.dubbo.config.bootstrap.builders.ConsumerBuilder>);
    Code:
       0: aload_0
       1: aload_1
       2: invokespecial #139                // Method createConsumerBuilder:(Ljava/lang/String;)Lorg/apache/dubbo/config/bootstrap/builders/ConsumerBuilder;
       5: astore_3
       6: aload_2
       7: aload_3
       8: invokeinterface #80,  2           // InterfaceMethod java/util/function/Consumer.accept:(Ljava/lang/Object;)V
      13: aload_3
      14: invokevirtual #140                // Method org/apache/dubbo/config/bootstrap/builders/ConsumerBuilder.build:()Lorg/apache/dubbo/config/ConsumerConfig;
      17: astore        4
      19: aload         4
      21: areturn

  public org.apache.dubbo.config.bootstrap.DubboBootstrap consumer(org.apache.dubbo.config.ConsumerConfig);
    Code:
       0: aload_0
       1: aload_1
       2: aload_0
       3: getfield      #31                 // Field applicationModel:Lorg/apache/dubbo/rpc/model/ApplicationModel;
       6: invokevirtual #116                // Method org/apache/dubbo/rpc/model/ApplicationModel.getDefaultModule:()Lorg/apache/dubbo/rpc/model/ModuleModel;
       9: invokevirtual #141                // Method consumer:(Lorg/apache/dubbo/config/ConsumerConfig;Lorg/apache/dubbo/rpc/model/ModuleModel;)Lorg/apache/dubbo/config/bootstrap/DubboBootstrap;
      12: areturn

  public org.apache.dubbo.config.bootstrap.DubboBootstrap consumers(java.util.List<org.apache.dubbo.config.ConsumerConfig>);
    Code:
       0: aload_1
       1: invokeinterface #105,  1          // InterfaceMethod java/util/List.iterator:()Ljava/util/Iterator;
       6: astore_2
       7: aload_2
       8: invokeinterface #106,  1          // InterfaceMethod java/util/Iterator.hasNext:()Z
      13: ifeq          42
      16: aload_2
      17: invokeinterface #107,  1          // InterfaceMethod java/util/Iterator.next:()Ljava/lang/Object;
      22: checkcast     #142                // class org/apache/dubbo/config/ConsumerConfig
      25: astore_3
      26: aload_0
      27: aload_3
      28: aload_0
      29: getfield      #31                 // Field applicationModel:Lorg/apache/dubbo/rpc/model/ApplicationModel;
      32: invokevirtual #116                // Method org/apache/dubbo/rpc/model/ApplicationModel.getDefaultModule:()Lorg/apache/dubbo/rpc/model/ModuleModel;
      35: invokevirtual #141                // Method consumer:(Lorg/apache/dubbo/config/ConsumerConfig;Lorg/apache/dubbo/rpc/model/ModuleModel;)Lorg/apache/dubbo/config/bootstrap/DubboBootstrap;
      38: pop
      39: goto          7
      42: aload_0
      43: areturn

  public org.apache.dubbo.config.bootstrap.DubboBootstrap consumer(org.apache.dubbo.config.ConsumerConfig, org.apache.dubbo.rpc.model.ModuleModel);
    Code:
       0: aload_1
       1: aload_2
       2: invokevirtual #143                // Method org/apache/dubbo/config/ConsumerConfig.setScopeModel:(Lorg/apache/dubbo/rpc/model/ScopeModel;)V
       5: aload_2
       6: invokevirtual #119                // Method org/apache/dubbo/rpc/model/ModuleModel.getConfigManager:()Lorg/apache/dubbo/config/context/ModuleConfigManager;
       9: aload_1
      10: invokevirtual #144                // Method org/apache/dubbo/config/context/ModuleConfigManager.addConsumer:(Lorg/apache/dubbo/config/ConsumerConfig;)V
      13: aload_0
      14: areturn

  public org.apache.dubbo.config.bootstrap.DubboBootstrap module(org.apache.dubbo.config.ModuleConfig);
    Code:
       0: aload_0
       1: aload_1
       2: aload_0
       3: getfield      #31                 // Field applicationModel:Lorg/apache/dubbo/rpc/model/ApplicationModel;
       6: invokevirtual #116                // Method org/apache/dubbo/rpc/model/ApplicationModel.getDefaultModule:()Lorg/apache/dubbo/rpc/model/ModuleModel;
       9: invokevirtual #145                // Method module:(Lorg/apache/dubbo/config/ModuleConfig;Lorg/apache/dubbo/rpc/model/ModuleModel;)Lorg/apache/dubbo/config/bootstrap/DubboBootstrap;
      12: pop
      13: aload_0
      14: areturn

  public org.apache.dubbo.config.bootstrap.DubboBootstrap module(org.apache.dubbo.config.ModuleConfig, org.apache.dubbo.rpc.model.ModuleModel);
    Code:
       0: aload_1
       1: aload_2
       2: invokevirtual #146                // Method org/apache/dubbo/config/ModuleConfig.setScopeModel:(Lorg/apache/dubbo/rpc/model/ScopeModel;)V
       5: aload_2
       6: invokevirtual #119                // Method org/apache/dubbo/rpc/model/ModuleModel.getConfigManager:()Lorg/apache/dubbo/config/context/ModuleConfigManager;
       9: aload_1
      10: invokevirtual #147                // Method org/apache/dubbo/config/context/ModuleConfigManager.setModule:(Lorg/apache/dubbo/config/ModuleConfig;)V
      13: aload_0
      14: areturn

  public org.apache.dubbo.config.bootstrap.DubboBootstrap configCenter(java.util.function.Consumer<org.apache.dubbo.config.bootstrap.builders.ConfigCenterBuilder>);
    Code:
       0: aload_0
       1: aconst_null
       2: aload_1
       3: invokevirtual #148                // Method configCenter:(Ljava/lang/String;Ljava/util/function/Consumer;)Lorg/apache/dubbo/config/bootstrap/DubboBootstrap;
       6: areturn

  public org.apache.dubbo.config.bootstrap.DubboBootstrap configCenter(java.lang.String, java.util.function.Consumer<org.apache.dubbo.config.bootstrap.builders.ConfigCenterBuilder>);
    Code:
       0: aload_0
       1: aload_1
       2: invokespecial #149                // Method createConfigCenterBuilder:(Ljava/lang/String;)Lorg/apache/dubbo/config/bootstrap/builders/ConfigCenterBuilder;
       5: astore_3
       6: aload_2
       7: aload_3
       8: invokeinterface #80,  2           // InterfaceMethod java/util/function/Consumer.accept:(Ljava/lang/Object;)V
      13: aload_0
      14: areturn

  public org.apache.dubbo.config.bootstrap.DubboBootstrap configCenter(org.apache.dubbo.config.ConfigCenterConfig);
    Code:
       0: aload_1
       1: aload_0
       2: getfield      #31                 // Field applicationModel:Lorg/apache/dubbo/rpc/model/ApplicationModel;
       5: invokevirtual #150                // Method org/apache/dubbo/config/ConfigCenterConfig.setScopeModel:(Lorg/apache/dubbo/rpc/model/ScopeModel;)V
       8: aload_0
       9: getfield      #33                 // Field configManager:Lorg/apache/dubbo/config/context/ConfigManager;
      12: aload_1
      13: invokevirtual #151                // Method org/apache/dubbo/config/context/ConfigManager.addConfigCenter:(Lorg/apache/dubbo/config/ConfigCenterConfig;)V
      16: aload_0
      17: areturn

  public org.apache.dubbo.config.bootstrap.DubboBootstrap configCenters(java.util.List<org.apache.dubbo.config.ConfigCenterConfig>);
    Code:
       0: aload_1
       1: invokestatic  #82                 // Method org/apache/dubbo/common/utils/CollectionUtils.isEmpty:(Ljava/util/Collection;)Z
       4: ifeq          9
       7: aload_0
       8: areturn
       9: aload_1
      10: invokeinterface #105,  1          // InterfaceMethod java/util/List.iterator:()Ljava/util/Iterator;
      15: astore_2
      16: aload_2
      17: invokeinterface #106,  1          // InterfaceMethod java/util/Iterator.hasNext:()Z
      22: ifeq          44
      25: aload_2
      26: invokeinterface #107,  1          // InterfaceMethod java/util/Iterator.next:()Ljava/lang/Object;
      31: checkcast     #152                // class org/apache/dubbo/config/ConfigCenterConfig
      34: astore_3
      35: aload_0
      36: aload_3
      37: invokevirtual #153                // Method configCenter:(Lorg/apache/dubbo/config/ConfigCenterConfig;)Lorg/apache/dubbo/config/bootstrap/DubboBootstrap;
      40: pop
      41: goto          16
      44: aload_0
      45: areturn

  public org.apache.dubbo.config.bootstrap.DubboBootstrap monitor(org.apache.dubbo.config.MonitorConfig);
    Code:
       0: aload_1
       1: aload_0
       2: getfield      #31                 // Field applicationModel:Lorg/apache/dubbo/rpc/model/ApplicationModel;
       5: invokevirtual #154                // Method org/apache/dubbo/config/MonitorConfig.setScopeModel:(Lorg/apache/dubbo/rpc/model/ScopeModel;)V
       8: aload_0
       9: getfield      #33                 // Field configManager:Lorg/apache/dubbo/config/context/ConfigManager;
      12: aload_1
      13: invokevirtual #155                // Method org/apache/dubbo/config/context/ConfigManager.setMonitor:(Lorg/apache/dubbo/config/MonitorConfig;)V
      16: aload_0
      17: areturn

  public org.apache.dubbo.config.bootstrap.DubboBootstrap metrics(org.apache.dubbo.config.MetricsConfig);
    Code:
       0: aload_1
       1: aload_0
       2: getfield      #31                 // Field applicationModel:Lorg/apache/dubbo/rpc/model/ApplicationModel;
       5: invokevirtual #156                // Method org/apache/dubbo/config/MetricsConfig.setScopeModel:(Lorg/apache/dubbo/rpc/model/ScopeModel;)V
       8: aload_0
       9: getfield      #33                 // Field configManager:Lorg/apache/dubbo/config/context/ConfigManager;
      12: aload_1
      13: invokevirtual #157                // Method org/apache/dubbo/config/context/ConfigManager.setMetrics:(Lorg/apache/dubbo/config/MetricsConfig;)V
      16: aload_0
      17: areturn

  public org.apache.dubbo.config.bootstrap.DubboBootstrap tracing(org.apache.dubbo.config.TracingConfig);
    Code:
       0: aload_1
       1: aload_0
       2: getfield      #31                 // Field applicationModel:Lorg/apache/dubbo/rpc/model/ApplicationModel;
       5: invokevirtual #158                // Method org/apache/dubbo/config/TracingConfig.setScopeModel:(Lorg/apache/dubbo/rpc/model/ScopeModel;)V
       8: aload_0
       9: getfield      #33                 // Field configManager:Lorg/apache/dubbo/config/context/ConfigManager;
      12: aload_1
      13: invokevirtual #159                // Method org/apache/dubbo/config/context/ConfigManager.setTracing:(Lorg/apache/dubbo/config/TracingConfig;)V
      16: aload_0
      17: areturn

  public org.apache.dubbo.config.bootstrap.DubboBootstrap ssl(org.apache.dubbo.config.SslConfig);
    Code:
       0: aload_1
       1: aload_0
       2: getfield      #31                 // Field applicationModel:Lorg/apache/dubbo/rpc/model/ApplicationModel;
       5: invokevirtual #160                // Method org/apache/dubbo/config/SslConfig.setScopeModel:(Lorg/apache/dubbo/rpc/model/ScopeModel;)V
       8: aload_0
       9: getfield      #33                 // Field configManager:Lorg/apache/dubbo/config/context/ConfigManager;
      12: aload_1
      13: invokevirtual #161                // Method org/apache/dubbo/config/context/ConfigManager.setSsl:(Lorg/apache/dubbo/config/SslConfig;)V
      16: aload_0
      17: areturn

  private org.apache.dubbo.config.bootstrap.builders.ApplicationBuilder createApplicationBuilder(java.lang.String);
    Code:
       0: new           #162                // class org/apache/dubbo/config/bootstrap/builders/ApplicationBuilder
       3: dup
       4: invokespecial #163                // Method org/apache/dubbo/config/bootstrap/builders/ApplicationBuilder."<init>":()V
       7: aload_1
       8: invokevirtual #164                // Method org/apache/dubbo/config/bootstrap/builders/ApplicationBuilder.name:(Ljava/lang/String;)Lorg/apache/dubbo/config/bootstrap/builders/ApplicationBuilder;
      11: areturn

  private org.apache.dubbo.config.bootstrap.builders.RegistryBuilder createRegistryBuilder(java.lang.String);
    Code:
       0: new           #165                // class org/apache/dubbo/config/bootstrap/builders/RegistryBuilder
       3: dup
       4: invokespecial #166                // Method org/apache/dubbo/config/bootstrap/builders/RegistryBuilder."<init>":()V
       7: aload_1
       8: invokevirtual #167                // Method org/apache/dubbo/config/bootstrap/builders/RegistryBuilder.id:(Ljava/lang/String;)Lorg/apache/dubbo/config/bootstrap/builders/RegistryBuilder;
      11: areturn

  private org.apache.dubbo.config.bootstrap.builders.MetadataReportBuilder createMetadataReportBuilder(java.lang.String);
    Code:
       0: new           #168                // class org/apache/dubbo/config/bootstrap/builders/MetadataReportBuilder
       3: dup
       4: invokespecial #169                // Method org/apache/dubbo/config/bootstrap/builders/MetadataReportBuilder."<init>":()V
       7: aload_1
       8: invokevirtual #170                // Method org/apache/dubbo/config/bootstrap/builders/MetadataReportBuilder.id:(Ljava/lang/String;)Lorg/apache/dubbo/config/bootstrap/builders/AbstractBuilder;
      11: checkcast     #168                // class org/apache/dubbo/config/bootstrap/builders/MetadataReportBuilder
      14: areturn

  private org.apache.dubbo.config.bootstrap.builders.ConfigCenterBuilder createConfigCenterBuilder(java.lang.String);
    Code:
       0: new           #171                // class org/apache/dubbo/config/bootstrap/builders/ConfigCenterBuilder
       3: dup
       4: invokespecial #172                // Method org/apache/dubbo/config/bootstrap/builders/ConfigCenterBuilder."<init>":()V
       7: aload_1
       8: invokevirtual #173                // Method org/apache/dubbo/config/bootstrap/builders/ConfigCenterBuilder.id:(Ljava/lang/String;)Lorg/apache/dubbo/config/bootstrap/builders/AbstractBuilder;
      11: checkcast     #171                // class org/apache/dubbo/config/bootstrap/builders/ConfigCenterBuilder
      14: areturn

  private org.apache.dubbo.config.bootstrap.builders.ProtocolBuilder createProtocolBuilder(java.lang.String);
    Code:
       0: new           #174                // class org/apache/dubbo/config/bootstrap/builders/ProtocolBuilder
       3: dup
       4: invokespecial #175                // Method org/apache/dubbo/config/bootstrap/builders/ProtocolBuilder."<init>":()V
       7: aload_1
       8: invokevirtual #176                // Method org/apache/dubbo/config/bootstrap/builders/ProtocolBuilder.id:(Ljava/lang/String;)Lorg/apache/dubbo/config/bootstrap/builders/ProtocolBuilder;
      11: areturn

  private org.apache.dubbo.config.bootstrap.builders.ServiceBuilder createServiceBuilder(java.lang.String);
    Code:
       0: new           #177                // class org/apache/dubbo/config/bootstrap/builders/ServiceBuilder
       3: dup
       4: invokespecial #178                // Method org/apache/dubbo/config/bootstrap/builders/ServiceBuilder."<init>":()V
       7: aload_1
       8: invokevirtual #179                // Method org/apache/dubbo/config/bootstrap/builders/ServiceBuilder.id:(Ljava/lang/String;)Lorg/apache/dubbo/config/bootstrap/builders/ServiceBuilder;
      11: areturn

  private org.apache.dubbo.config.bootstrap.builders.ReferenceBuilder createReferenceBuilder(java.lang.String);
    Code:
       0: new           #180                // class org/apache/dubbo/config/bootstrap/builders/ReferenceBuilder
       3: dup
       4: invokespecial #181                // Method org/apache/dubbo/config/bootstrap/builders/ReferenceBuilder."<init>":()V
       7: aload_1
       8: invokevirtual #182                // Method org/apache/dubbo/config/bootstrap/builders/ReferenceBuilder.id:(Ljava/lang/String;)Lorg/apache/dubbo/config/bootstrap/builders/ReferenceBuilder;
      11: areturn

  private org.apache.dubbo.config.bootstrap.builders.ProviderBuilder createProviderBuilder(java.lang.String);
    Code:
       0: new           #183                // class org/apache/dubbo/config/bootstrap/builders/ProviderBuilder
       3: dup
       4: invokespecial #184                // Method org/apache/dubbo/config/bootstrap/builders/ProviderBuilder."<init>":()V
       7: aload_1
       8: invokevirtual #185                // Method org/apache/dubbo/config/bootstrap/builders/ProviderBuilder.id:(Ljava/lang/String;)Lorg/apache/dubbo/config/bootstrap/builders/AbstractBuilder;
      11: checkcast     #183                // class org/apache/dubbo/config/bootstrap/builders/ProviderBuilder
      14: areturn

  private org.apache.dubbo.config.bootstrap.builders.ConsumerBuilder createConsumerBuilder(java.lang.String);
    Code:
       0: new           #186                // class org/apache/dubbo/config/bootstrap/builders/ConsumerBuilder
       3: dup
       4: invokespecial #187                // Method org/apache/dubbo/config/bootstrap/builders/ConsumerBuilder."<init>":()V
       7: aload_1
       8: invokevirtual #188                // Method org/apache/dubbo/config/bootstrap/builders/ConsumerBuilder.id:(Ljava/lang/String;)Lorg/apache/dubbo/config/bootstrap/builders/AbstractBuilder;
      11: checkcast     #186                // class org/apache/dubbo/config/bootstrap/builders/ConsumerBuilder
      14: areturn

  public org.apache.dubbo.config.bootstrap.DubboBootstrap$Module newModule();
    Code:
       0: new           #189                // class org/apache/dubbo/config/bootstrap/DubboBootstrap$Module
       3: dup
       4: aload_0
       5: aload_0
       6: getfield      #31                 // Field applicationModel:Lorg/apache/dubbo/rpc/model/ApplicationModel;
       9: invokevirtual #190                // Method org/apache/dubbo/rpc/model/ApplicationModel.newModule:()Lorg/apache/dubbo/rpc/model/ModuleModel;
      12: invokespecial #191                // Method org/apache/dubbo/config/bootstrap/DubboBootstrap$Module."<init>":(Lorg/apache/dubbo/config/bootstrap/DubboBootstrap;Lorg/apache/dubbo/rpc/model/ModuleModel;)V
      15: areturn

  public org.apache.dubbo.config.bootstrap.DubboBootstrap$Module newModule(org.apache.dubbo.config.ModuleConfig);
    Code:
       0: aload_0
       1: getfield      #31                 // Field applicationModel:Lorg/apache/dubbo/rpc/model/ApplicationModel;
       4: invokevirtual #190                // Method org/apache/dubbo/rpc/model/ApplicationModel.newModule:()Lorg/apache/dubbo/rpc/model/ModuleModel;
       7: astore_2
       8: aload_1
       9: aload_2
      10: invokevirtual #146                // Method org/apache/dubbo/config/ModuleConfig.setScopeModel:(Lorg/apache/dubbo/rpc/model/ScopeModel;)V
      13: aload_2
      14: invokevirtual #119                // Method org/apache/dubbo/rpc/model/ModuleModel.getConfigManager:()Lorg/apache/dubbo/config/context/ModuleConfigManager;
      17: aload_1
      18: invokevirtual #147                // Method org/apache/dubbo/config/context/ModuleConfigManager.setModule:(Lorg/apache/dubbo/config/ModuleConfig;)V
      21: new           #189                // class org/apache/dubbo/config/bootstrap/DubboBootstrap$Module
      24: dup
      25: aload_0
      26: aload_2
      27: invokespecial #191                // Method org/apache/dubbo/config/bootstrap/DubboBootstrap$Module."<init>":(Lorg/apache/dubbo/config/bootstrap/DubboBootstrap;Lorg/apache/dubbo/rpc/model/ModuleModel;)V
      30: areturn

  public org.apache.dubbo.config.bootstrap.DubboBootstrap endModule();
    Code:
       0: aload_0
       1: areturn

  private static void lambda$application$5(org.apache.dubbo.config.bootstrap.builders.ApplicationBuilder);
    Code:
       0: return

  private void lambda$await$4();
    Code:
       0: aload_0
       1: getfield      #23                 // Field awaited:Ljava/util/concurrent/atomic/AtomicBoolean;
       4: invokevirtual #70                 // Method java/util/concurrent/atomic/AtomicBoolean.get:()Z
       7: ifne          72
      10: getstatic     #192                // Field logger:Lorg/apache/dubbo/common/logger/Logger;
      13: invokeinterface #193,  1          // InterfaceMethod org/apache/dubbo/common/logger/Logger.isInfoEnabled:()Z
      18: ifeq          50
      21: getstatic     #192                // Field logger:Lorg/apache/dubbo/common/logger/Logger;
      24: new           #194                // class java/lang/StringBuilder
      27: dup
      28: invokespecial #195                // Method java/lang/StringBuilder."<init>":()V
      31: getstatic     #196                // Field NAME:Ljava/lang/String;
      34: invokevirtual #197                // Method java/lang/StringBuilder.append:(Ljava/lang/String;)Ljava/lang/StringBuilder;
      37: ldc           #198                // String  awaiting ...
      39: invokevirtual #197                // Method java/lang/StringBuilder.append:(Ljava/lang/String;)Ljava/lang/StringBuilder;
      42: invokevirtual #199                // Method java/lang/StringBuilder.toString:()Ljava/lang/String;
      45: invokeinterface #200,  2          // InterfaceMethod org/apache/dubbo/common/logger/Logger.info:(Ljava/lang/String;)V
      50: aload_0
      51: getfield      #30                 // Field condition:Ljava/util/concurrent/locks/Condition;
      54: invokeinterface #201,  1          // InterfaceMethod java/util/concurrent/locks/Condition.await:()V
      59: goto          0
      62: astore_1
      63: invokestatic  #203                // Method java/lang/Thread.currentThread:()Ljava/lang/Thread;
      66: invokevirtual #204                // Method java/lang/Thread.interrupt:()V
      69: goto          0
      72: return
    Exception table:
       from    to  target type
          50    59    62   Class java/lang/InterruptedException

  private void lambda$notifyStopped$3();
    Code:
       0: aload_0
       1: getfield      #23                 // Field awaited:Ljava/util/concurrent/atomic/AtomicBoolean;
       4: iconst_1
       5: invokevirtual #205                // Method java/util/concurrent/atomic/AtomicBoolean.set:(Z)V
       8: aload_0
       9: getfield      #30                 // Field condition:Ljava/util/concurrent/locks/Condition;
      12: invokeinterface #206,  1          // InterfaceMethod java/util/concurrent/locks/Condition.signalAll:()V
      17: return

  private void lambda$notifyStopped$2(org.apache.dubbo.config.bootstrap.DubboBootstrapStartStopListener);
    Code:
       0: aload_1
       1: aload_0
       2: invokeinterface #207,  2          // InterfaceMethod org/apache/dubbo/config/bootstrap/DubboBootstrapStartStopListener.onStop:(Lorg/apache/dubbo/config/bootstrap/DubboBootstrap;)V
       7: return

  private void lambda$notifyStarted$1(org.apache.dubbo.config.bootstrap.DubboBootstrapStartStopListener);
    Code:
       0: aload_1
       1: aload_0
       2: invokeinterface #208,  2          // InterfaceMethod org/apache/dubbo/config/bootstrap/DubboBootstrapStartStopListener.onStart:(Lorg/apache/dubbo/config/bootstrap/DubboBootstrap;)V
       7: return

  private static org.apache.dubbo.config.bootstrap.DubboBootstrap lambda$getInstance$0(org.apache.dubbo.rpc.model.ApplicationModel, org.apache.dubbo.rpc.model.ApplicationModel);
    Code:
       0: new           #8                  // class org/apache/dubbo/config/bootstrap/DubboBootstrap
       3: dup
       4: aload_0
       5: invokespecial #209                // Method "<init>":(Lorg/apache/dubbo/rpc/model/ApplicationModel;)V
       8: areturn

  static void access$000(org.apache.dubbo.config.bootstrap.DubboBootstrap, org.apache.dubbo.rpc.model.ApplicationModel);
    Code:
       0: aload_0
       1: aload_1
       2: invokespecial #6                  // Method notifyStarted:(Lorg/apache/dubbo/rpc/model/ApplicationModel;)V
       5: return

  static void access$100(org.apache.dubbo.config.bootstrap.DubboBootstrap, org.apache.dubbo.rpc.model.ApplicationModel);
    Code:
       0: aload_0
       1: aload_1
       2: invokespecial #5                  // Method notifyStopped:(Lorg/apache/dubbo/rpc/model/ApplicationModel;)V
       5: return

  static org.apache.dubbo.config.ServiceConfig access$200(org.apache.dubbo.config.bootstrap.DubboBootstrap, java.lang.String, java.util.function.Consumer);
    Code:
       0: aload_0
       1: aload_1
       2: aload_2
       3: invokespecial #4                  // Method createServiceConfig:(Ljava/lang/String;Ljava/util/function/Consumer;)Lorg/apache/dubbo/config/ServiceConfig;
       6: areturn

  static org.apache.dubbo.config.ReferenceConfig access$300(org.apache.dubbo.config.bootstrap.DubboBootstrap, java.lang.String, java.util.function.Consumer);
    Code:
       0: aload_0
       1: aload_1
       2: aload_2
       3: invokespecial #3                  // Method createReferenceConfig:(Ljava/lang/String;Ljava/util/function/Consumer;)Lorg/apache/dubbo/config/ReferenceConfig;
       6: areturn

  static org.apache.dubbo.config.ProviderConfig access$400(org.apache.dubbo.config.bootstrap.DubboBootstrap, java.lang.String, java.util.function.Consumer);
    Code:
       0: aload_0
       1: aload_1
       2: aload_2
       3: invokespecial #2                  // Method createProviderConfig:(Ljava/lang/String;Ljava/util/function/Consumer;)Lorg/apache/dubbo/config/ProviderConfig;
       6: areturn

  static org.apache.dubbo.config.ConsumerConfig access$500(org.apache.dubbo.config.bootstrap.DubboBootstrap, java.lang.String, java.util.function.Consumer);
    Code:
       0: aload_0
       1: aload_1
       2: aload_2
       3: invokespecial #1                  // Method createConsumerConfig:(Ljava/lang/String;Ljava/util/function/Consumer;)Lorg/apache/dubbo/config/ConsumerConfig;
       6: areturn

  static {};
    Code:
       0: ldc           #8                  // class org/apache/dubbo/config/bootstrap/DubboBootstrap
       2: invokevirtual #210                // Method java/lang/Class.getSimpleName:()Ljava/lang/String;
       5: putstatic     #196                // Field NAME:Ljava/lang/String;
       8: ldc           #8                  // class org/apache/dubbo/config/bootstrap/DubboBootstrap
      10: invokestatic  #211                // Method org/apache/dubbo/common/logger/LoggerFactory.getLogger:(Ljava/lang/Class;)Lorg/apache/dubbo/common/logger/Logger;
      13: putstatic     #192                // Field logger:Lorg/apache/dubbo/common/logger/Logger;
      16: new           #212                // class java/util/concurrent/ConcurrentHashMap
      19: dup
      20: invokespecial #213                // Method java/util/concurrent/ConcurrentHashMap."<init>":()V
      23: putstatic     #11                 // Field instanceMap:Ljava/util/concurrent/ConcurrentMap;
      26: return
}
