Compiled from "DubboBootstrap.java"
public class org.apache.dubbo.config.bootstrap.DubboBootstrap$Module {
  private org.apache.dubbo.rpc.model.ModuleModel moduleModel;

  private org.apache.dubbo.config.bootstrap.DubboBootstrap bootstrap;

  final org.apache.dubbo.config.bootstrap.DubboBootstrap this$0;

  public org.apache.dubbo.config.bootstrap.DubboBootstrap$Module(org.apache.dubbo.config.bootstrap.DubboBootstrap, org.apache.dubbo.rpc.model.ModuleModel);
    Code:
       0: aload_0
       1: aload_1
       2: putfield      #1                  // Field this$0:Lorg/apache/dubbo/config/bootstrap/DubboBootstrap;
       5: aload_0
       6: invokespecial #2                  // Method java/lang/Object."<init>":()V
       9: aload_0
      10: aload_2
      11: putfield      #3                  // Field moduleModel:Lorg/apache/dubbo/rpc/model/ModuleModel;
      14: aload_0
      15: aload_1
      16: putfield      #4                  // Field bootstrap:Lorg/apache/dubbo/config/bootstrap/DubboBootstrap;
      19: return

  public org.apache.dubbo.config.bootstrap.DubboBootstrap endModule();
    Code:
       0: aload_0
       1: getfield      #4                  // Field bootstrap:Lorg/apache/dubbo/config/bootstrap/DubboBootstrap;
       4: invokevirtual #5                  // Method org/apache/dubbo/config/bootstrap/DubboBootstrap.endModule:()Lorg/apache/dubbo/config/bootstrap/DubboBootstrap;
       7: areturn

  public org.apache.dubbo.rpc.model.ModuleModel getModuleModel();
    Code:
       0: aload_0
       1: getfield      #3                  // Field moduleModel:Lorg/apache/dubbo/rpc/model/ModuleModel;
       4: areturn

  public org.apache.dubbo.config.bootstrap.DubboBootstrap$Module config(org.apache.dubbo.config.ModuleConfig);
    Code:
       0: aload_0
       1: getfield      #3                  // Field moduleModel:Lorg/apache/dubbo/rpc/model/ModuleModel;
       4: invokevirtual #6                  // Method org/apache/dubbo/rpc/model/ModuleModel.getConfigManager:()Lorg/apache/dubbo/config/context/ModuleConfigManager;
       7: aload_1
       8: invokevirtual #7                  // Method org/apache/dubbo/config/context/ModuleConfigManager.setModule:(Lorg/apache/dubbo/config/ModuleConfig;)V
      11: aload_0
      12: areturn

  public <S> org.apache.dubbo.config.bootstrap.DubboBootstrap$Module service(java.util.function.Consumer<org.apache.dubbo.config.bootstrap.builders.ServiceBuilder<S>>);
    Code:
       0: aload_0
       1: aconst_null
       2: aload_1
       3: invokevirtual #8                  // Method service:(Ljava/lang/String;Ljava/util/function/Consumer;)Lorg/apache/dubbo/config/bootstrap/DubboBootstrap$Module;
       6: areturn

  public <S> org.apache.dubbo.config.bootstrap.DubboBootstrap$Module service(java.lang.String, java.util.function.Consumer<org.apache.dubbo.config.bootstrap.builders.ServiceBuilder<S>>);
    Code:
       0: aload_0
       1: aload_0
       2: getfield      #1                  // Field this$0:Lorg/apache/dubbo/config/bootstrap/DubboBootstrap;
       5: aload_1
       6: aload_2
       7: invokestatic  #9                  // Method org/apache/dubbo/config/bootstrap/DubboBootstrap.access$200:(Lorg/apache/dubbo/config/bootstrap/DubboBootstrap;Ljava/lang/String;Ljava/util/function/Consumer;)Lorg/apache/dubbo/config/ServiceConfig;
      10: invokevirtual #10                 // Method service:(Lorg/apache/dubbo/config/ServiceConfig;)Lorg/apache/dubbo/config/bootstrap/DubboBootstrap$Module;
      13: areturn

  public org.apache.dubbo.config.bootstrap.DubboBootstrap$Module services(java.util.List<org.apache.dubbo.config.ServiceConfig>);
    Code:
       0: aload_1
       1: invokestatic  #11                 // Method org/apache/dubbo/common/utils/CollectionUtils.isEmpty:(Ljava/util/Collection;)Z
       4: ifeq          9
       7: aload_0
       8: areturn
       9: aload_1
      10: invokeinterface #12,  1           // InterfaceMethod java/util/List.iterator:()Ljava/util/Iterator;
      15: astore_2
      16: aload_2
      17: invokeinterface #13,  1           // InterfaceMethod java/util/Iterator.hasNext:()Z
      22: ifeq          44
      25: aload_2
      26: invokeinterface #14,  1           // InterfaceMethod java/util/Iterator.next:()Ljava/lang/Object;
      31: checkcast     #15                 // class org/apache/dubbo/config/ServiceConfig
      34: astore_3
      35: aload_0
      36: aload_3
      37: invokevirtual #10                 // Method service:(Lorg/apache/dubbo/config/ServiceConfig;)Lorg/apache/dubbo/config/bootstrap/DubboBootstrap$Module;
      40: pop
      41: goto          16
      44: aload_0
      45: areturn

  public org.apache.dubbo.config.bootstrap.DubboBootstrap$Module service(org.apache.dubbo.config.ServiceConfig<?>);
    Code:
       0: aload_0
       1: getfield      #1                  // Field this$0:Lorg/apache/dubbo/config/bootstrap/DubboBootstrap;
       4: aload_1
       5: aload_0
       6: getfield      #3                  // Field moduleModel:Lorg/apache/dubbo/rpc/model/ModuleModel;
       9: invokevirtual #16                 // Method org/apache/dubbo/config/bootstrap/DubboBootstrap.service:(Lorg/apache/dubbo/config/ServiceConfig;Lorg/apache/dubbo/rpc/model/ModuleModel;)Lorg/apache/dubbo/config/bootstrap/DubboBootstrap;
      12: pop
      13: aload_0
      14: areturn

  public <S> org.apache.dubbo.config.bootstrap.DubboBootstrap$Module reference(java.util.function.Consumer<org.apache.dubbo.config.bootstrap.builders.ReferenceBuilder<S>>);
    Code:
       0: aload_0
       1: aconst_null
       2: aload_1
       3: invokevirtual #17                 // Method reference:(Ljava/lang/String;Ljava/util/function/Consumer;)Lorg/apache/dubbo/config/bootstrap/DubboBootstrap$Module;
       6: areturn

  public <S> org.apache.dubbo.config.bootstrap.DubboBootstrap$Module reference(java.lang.String, java.util.function.Consumer<org.apache.dubbo.config.bootstrap.builders.ReferenceBuilder<S>>);
    Code:
       0: aload_0
       1: aload_0
       2: getfield      #1                  // Field this$0:Lorg/apache/dubbo/config/bootstrap/DubboBootstrap;
       5: aload_1
       6: aload_2
       7: invokestatic  #18                 // Method org/apache/dubbo/config/bootstrap/DubboBootstrap.access$300:(Lorg/apache/dubbo/config/bootstrap/DubboBootstrap;Ljava/lang/String;Ljava/util/function/Consumer;)Lorg/apache/dubbo/config/ReferenceConfig;
      10: invokevirtual #19                 // Method reference:(Lorg/apache/dubbo/config/ReferenceConfig;)Lorg/apache/dubbo/config/bootstrap/DubboBootstrap$Module;
      13: areturn

  public org.apache.dubbo.config.bootstrap.DubboBootstrap$Module reference(org.apache.dubbo.config.ReferenceConfig<?>);
    Code:
       0: aload_0
       1: getfield      #1                  // Field this$0:Lorg/apache/dubbo/config/bootstrap/DubboBootstrap;
       4: aload_1
       5: aload_0
       6: getfield      #3                  // Field moduleModel:Lorg/apache/dubbo/rpc/model/ModuleModel;
       9: invokevirtual #20                 // Method org/apache/dubbo/config/bootstrap/DubboBootstrap.reference:(Lorg/apache/dubbo/config/ReferenceConfig;Lorg/apache/dubbo/rpc/model/ModuleModel;)Lorg/apache/dubbo/config/bootstrap/DubboBootstrap;
      12: pop
      13: aload_0
      14: areturn

  public org.apache.dubbo.config.bootstrap.DubboBootstrap$Module references(java.util.List<org.apache.dubbo.config.ReferenceConfig>);
    Code:
       0: aload_1
       1: invokestatic  #11                 // Method org/apache/dubbo/common/utils/CollectionUtils.isEmpty:(Ljava/util/Collection;)Z
       4: ifeq          9
       7: aload_0
       8: areturn
       9: aload_1
      10: invokeinterface #12,  1           // InterfaceMethod java/util/List.iterator:()Ljava/util/Iterator;
      15: astore_2
      16: aload_2
      17: invokeinterface #13,  1           // InterfaceMethod java/util/Iterator.hasNext:()Z
      22: ifeq          44
      25: aload_2
      26: invokeinterface #14,  1           // InterfaceMethod java/util/Iterator.next:()Ljava/lang/Object;
      31: checkcast     #21                 // class org/apache/dubbo/config/ReferenceConfig
      34: astore_3
      35: aload_0
      36: aload_3
      37: invokevirtual #19                 // Method reference:(Lorg/apache/dubbo/config/ReferenceConfig;)Lorg/apache/dubbo/config/bootstrap/DubboBootstrap$Module;
      40: pop
      41: goto          16
      44: aload_0
      45: areturn

  public org.apache.dubbo.config.bootstrap.DubboBootstrap$Module provider(java.util.function.Consumer<org.apache.dubbo.config.bootstrap.builders.ProviderBuilder>);
    Code:
       0: aload_0
       1: aconst_null
       2: aload_1
       3: invokevirtual #22                 // Method provider:(Ljava/lang/String;Ljava/util/function/Consumer;)Lorg/apache/dubbo/config/bootstrap/DubboBootstrap$Module;
       6: areturn

  public org.apache.dubbo.config.bootstrap.DubboBootstrap$Module provider(java.lang.String, java.util.function.Consumer<org.apache.dubbo.config.bootstrap.builders.ProviderBuilder>);
    Code:
       0: aload_0
       1: aload_0
       2: getfield      #1                  // Field this$0:Lorg/apache/dubbo/config/bootstrap/DubboBootstrap;
       5: aload_1
       6: aload_2
       7: invokestatic  #23                 // Method org/apache/dubbo/config/bootstrap/DubboBootstrap.access$400:(Lorg/apache/dubbo/config/bootstrap/DubboBootstrap;Ljava/lang/String;Ljava/util/function/Consumer;)Lorg/apache/dubbo/config/ProviderConfig;
      10: invokevirtual #24                 // Method provider:(Lorg/apache/dubbo/config/ProviderConfig;)Lorg/apache/dubbo/config/bootstrap/DubboBootstrap$Module;
      13: areturn

  public org.apache.dubbo.config.bootstrap.DubboBootstrap$Module provider(org.apache.dubbo.config.ProviderConfig);
    Code:
       0: aload_0
       1: getfield      #1                  // Field this$0:Lorg/apache/dubbo/config/bootstrap/DubboBootstrap;
       4: aload_1
       5: aload_0
       6: getfield      #3                  // Field moduleModel:Lorg/apache/dubbo/rpc/model/ModuleModel;
       9: invokevirtual #25                 // Method org/apache/dubbo/config/bootstrap/DubboBootstrap.provider:(Lorg/apache/dubbo/config/ProviderConfig;Lorg/apache/dubbo/rpc/model/ModuleModel;)Lorg/apache/dubbo/config/bootstrap/DubboBootstrap;
      12: pop
      13: aload_0
      14: areturn

  public org.apache.dubbo.config.bootstrap.DubboBootstrap$Module providers(java.util.List<org.apache.dubbo.config.ProviderConfig>);
    Code:
       0: aload_1
       1: invokestatic  #11                 // Method org/apache/dubbo/common/utils/CollectionUtils.isEmpty:(Ljava/util/Collection;)Z
       4: ifeq          9
       7: aload_0
       8: areturn
       9: aload_1
      10: invokeinterface #12,  1           // InterfaceMethod java/util/List.iterator:()Ljava/util/Iterator;
      15: astore_2
      16: aload_2
      17: invokeinterface #13,  1           // InterfaceMethod java/util/Iterator.hasNext:()Z
      22: ifeq          51
      25: aload_2
      26: invokeinterface #14,  1           // InterfaceMethod java/util/Iterator.next:()Ljava/lang/Object;
      31: checkcast     #26                 // class org/apache/dubbo/config/ProviderConfig
      34: astore_3
      35: aload_0
      36: getfield      #1                  // Field this$0:Lorg/apache/dubbo/config/bootstrap/DubboBootstrap;
      39: aload_3
      40: aload_0
      41: getfield      #3                  // Field moduleModel:Lorg/apache/dubbo/rpc/model/ModuleModel;
      44: invokevirtual #25                 // Method org/apache/dubbo/config/bootstrap/DubboBootstrap.provider:(Lorg/apache/dubbo/config/ProviderConfig;Lorg/apache/dubbo/rpc/model/ModuleModel;)Lorg/apache/dubbo/config/bootstrap/DubboBootstrap;
      47: pop
      48: goto          16
      51: aload_0
      52: areturn

  public org.apache.dubbo.config.bootstrap.DubboBootstrap$Module consumer(java.util.function.Consumer<org.apache.dubbo.config.bootstrap.builders.ConsumerBuilder>);
    Code:
       0: aload_0
       1: aconst_null
       2: aload_1
       3: invokevirtual #27                 // Method consumer:(Ljava/lang/String;Ljava/util/function/Consumer;)Lorg/apache/dubbo/config/bootstrap/DubboBootstrap$Module;
       6: areturn

  public org.apache.dubbo.config.bootstrap.DubboBootstrap$Module consumer(java.lang.String, java.util.function.Consumer<org.apache.dubbo.config.bootstrap.builders.ConsumerBuilder>);
    Code:
       0: aload_0
       1: aload_0
       2: getfield      #1                  // Field this$0:Lorg/apache/dubbo/config/bootstrap/DubboBootstrap;
       5: aload_1
       6: aload_2
       7: invokestatic  #28                 // Method org/apache/dubbo/config/bootstrap/DubboBootstrap.access$500:(Lorg/apache/dubbo/config/bootstrap/DubboBootstrap;Ljava/lang/String;Ljava/util/function/Consumer;)Lorg/apache/dubbo/config/ConsumerConfig;
      10: invokevirtual #29                 // Method consumer:(Lorg/apache/dubbo/config/ConsumerConfig;)Lorg/apache/dubbo/config/bootstrap/DubboBootstrap$Module;
      13: areturn

  public org.apache.dubbo.config.bootstrap.DubboBootstrap$Module consumer(org.apache.dubbo.config.ConsumerConfig);
    Code:
       0: aload_0
       1: getfield      #1                  // Field this$0:Lorg/apache/dubbo/config/bootstrap/DubboBootstrap;
       4: aload_1
       5: aload_0
       6: getfield      #3                  // Field moduleModel:Lorg/apache/dubbo/rpc/model/ModuleModel;
       9: invokevirtual #30                 // Method org/apache/dubbo/config/bootstrap/DubboBootstrap.consumer:(Lorg/apache/dubbo/config/ConsumerConfig;Lorg/apache/dubbo/rpc/model/ModuleModel;)Lorg/apache/dubbo/config/bootstrap/DubboBootstrap;
      12: pop
      13: aload_0
      14: areturn

  public org.apache.dubbo.config.bootstrap.DubboBootstrap$Module consumers(java.util.List<org.apache.dubbo.config.ConsumerConfig>);
    Code:
       0: aload_1
       1: invokestatic  #11                 // Method org/apache/dubbo/common/utils/CollectionUtils.isEmpty:(Ljava/util/Collection;)Z
       4: ifeq          9
       7: aload_0
       8: areturn
       9: aload_1
      10: invokeinterface #12,  1           // InterfaceMethod java/util/List.iterator:()Ljava/util/Iterator;
      15: astore_2
      16: aload_2
      17: invokeinterface #13,  1           // InterfaceMethod java/util/Iterator.hasNext:()Z
      22: ifeq          51
      25: aload_2
      26: invokeinterface #14,  1           // InterfaceMethod java/util/Iterator.next:()Ljava/lang/Object;
      31: checkcast     #31                 // class org/apache/dubbo/config/ConsumerConfig
      34: astore_3
      35: aload_0
      36: getfield      #1                  // Field this$0:Lorg/apache/dubbo/config/bootstrap/DubboBootstrap;
      39: aload_3
      40: aload_0
      41: getfield      #3                  // Field moduleModel:Lorg/apache/dubbo/rpc/model/ModuleModel;
      44: invokevirtual #30                 // Method org/apache/dubbo/config/bootstrap/DubboBootstrap.consumer:(Lorg/apache/dubbo/config/ConsumerConfig;Lorg/apache/dubbo/rpc/model/ModuleModel;)Lorg/apache/dubbo/config/bootstrap/DubboBootstrap;
      47: pop
      48: goto          16
      51: aload_0
      52: areturn
}
