Compiled from "DefaultApplicationDeployer.java"
public class org.apache.dubbo.config.deploy.DefaultApplicationDeployer extends org.apache.dubbo.common.deploy.AbstractDeployer<org.apache.dubbo.rpc.model.ApplicationModel> implements org.apache.dubbo.common.deploy.ApplicationDeployer {
  private static final org.apache.dubbo.common.logger.ErrorTypeAwareLogger logger;

  private final org.apache.dubbo.rpc.model.ApplicationModel applicationModel;

  private final org.apache.dubbo.config.context.ConfigManager configManager;

  private final org.apache.dubbo.common.config.Environment environment;

  private final org.apache.dubbo.common.config.ReferenceCache referenceCache;

  private final org.apache.dubbo.common.threadpool.manager.FrameworkExecutorRepository frameworkExecutorRepository;

  private final org.apache.dubbo.common.threadpool.manager.ExecutorRepository executorRepository;

  private final java.util.concurrent.atomic.AtomicBoolean hasPreparedApplicationInstance;

  private volatile boolean hasPreparedInternalModule;

  private java.util.concurrent.ScheduledFuture<?> asyncMetadataFuture;

  private volatile java.util.concurrent.CompletableFuture<java.lang.Boolean> startFuture;

  private final org.apache.dubbo.config.DubboShutdownHook dubboShutdownHook;

  private volatile org.apache.dubbo.metrics.service.MetricsServiceExporter metricsServiceExporter;

  private final java.lang.Object stateLock;

  private final java.lang.Object startLock;

  private final java.lang.Object destroyLock;

  private final java.lang.Object internalModuleLock;

  private volatile boolean registered;

  private final java.util.concurrent.atomic.AtomicInteger instanceRefreshScheduleTimes;

  private final java.util.concurrent.atomic.AtomicInteger serviceRefreshState;

  public org.apache.dubbo.config.deploy.DefaultApplicationDeployer(org.apache.dubbo.rpc.model.ApplicationModel);
    Code:
       0: aload_0
       1: aload_1
       2: invokespecial #6                  // Method org/apache/dubbo/common/deploy/AbstractDeployer."<init>":(Lorg/apache/dubbo/rpc/model/ScopeModel;)V
       5: aload_0
       6: new           #7                  // class java/util/concurrent/atomic/AtomicBoolean
       9: dup
      10: iconst_0
      11: invokespecial #8                  // Method java/util/concurrent/atomic/AtomicBoolean."<init>":(Z)V
      14: putfield      #9                  // Field hasPreparedApplicationInstance:Ljava/util/concurrent/atomic/AtomicBoolean;
      17: aload_0
      18: iconst_0
      19: putfield      #10                 // Field hasPreparedInternalModule:Z
      22: aload_0
      23: new           #11                 // class java/lang/Object
      26: dup
      27: invokespecial #12                 // Method java/lang/Object."<init>":()V
      30: putfield      #13                 // Field stateLock:Ljava/lang/Object;
      33: aload_0
      34: new           #11                 // class java/lang/Object
      37: dup
      38: invokespecial #12                 // Method java/lang/Object."<init>":()V
      41: putfield      #14                 // Field startLock:Ljava/lang/Object;
      44: aload_0
      45: new           #11                 // class java/lang/Object
      48: dup
      49: invokespecial #12                 // Method java/lang/Object."<init>":()V
      52: putfield      #15                 // Field destroyLock:Ljava/lang/Object;
      55: aload_0
      56: new           #11                 // class java/lang/Object
      59: dup
      60: invokespecial #12                 // Method java/lang/Object."<init>":()V
      63: putfield      #16                 // Field internalModuleLock:Ljava/lang/Object;
      66: aload_0
      67: new           #17                 // class java/util/concurrent/atomic/AtomicInteger
      70: dup
      71: iconst_0
      72: invokespecial #18                 // Method java/util/concurrent/atomic/AtomicInteger."<init>":(I)V
      75: putfield      #19                 // Field instanceRefreshScheduleTimes:Ljava/util/concurrent/atomic/AtomicInteger;
      78: aload_0
      79: new           #17                 // class java/util/concurrent/atomic/AtomicInteger
      82: dup
      83: iconst_0
      84: invokespecial #18                 // Method java/util/concurrent/atomic/AtomicInteger."<init>":(I)V
      87: putfield      #20                 // Field serviceRefreshState:Ljava/util/concurrent/atomic/AtomicInteger;
      90: aload_0
      91: aload_1
      92: putfield      #21                 // Field applicationModel:Lorg/apache/dubbo/rpc/model/ApplicationModel;
      95: aload_0
      96: aload_1
      97: invokevirtual #22                 // Method org/apache/dubbo/rpc/model/ApplicationModel.getApplicationConfigManager:()Lorg/apache/dubbo/config/context/ConfigManager;
     100: putfield      #23                 // Field configManager:Lorg/apache/dubbo/config/context/ConfigManager;
     103: aload_0
     104: aload_1
     105: invokevirtual #24                 // Method org/apache/dubbo/rpc/model/ApplicationModel.getModelEnvironment:()Lorg/apache/dubbo/common/config/Environment;
     108: putfield      #25                 // Field environment:Lorg/apache/dubbo/common/config/Environment;
     111: aload_0
     112: new           #26                 // class org/apache/dubbo/config/utils/CompositeReferenceCache
     115: dup
     116: aload_1
     117: invokespecial #27                 // Method org/apache/dubbo/config/utils/CompositeReferenceCache."<init>":(Lorg/apache/dubbo/rpc/model/ApplicationModel;)V
     120: putfield      #28                 // Field referenceCache:Lorg/apache/dubbo/common/config/ReferenceCache;
     123: aload_0
     124: aload_1
     125: invokevirtual #29                 // Method org/apache/dubbo/rpc/model/ApplicationModel.getFrameworkModel:()Lorg/apache/dubbo/rpc/model/FrameworkModel;
     128: invokevirtual #30                 // Method org/apache/dubbo/rpc/model/FrameworkModel.getBeanFactory:()Lorg/apache/dubbo/common/beans/factory/ScopeBeanFactory;
     131: ldc           #31                 // class org/apache/dubbo/common/threadpool/manager/FrameworkExecutorRepository
     133: invokevirtual #32                 // Method org/apache/dubbo/common/beans/factory/ScopeBeanFactory.getBean:(Ljava/lang/Class;)Ljava/lang/Object;
     136: checkcast     #31                 // class org/apache/dubbo/common/threadpool/manager/FrameworkExecutorRepository
     139: putfield      #33                 // Field frameworkExecutorRepository:Lorg/apache/dubbo/common/threadpool/manager/FrameworkExecutorRepository;
     142: aload_0
     143: aload_1
     144: invokestatic  #34                 // InterfaceMethod org/apache/dubbo/common/threadpool/manager/ExecutorRepository.getInstance:(Lorg/apache/dubbo/rpc/model/ApplicationModel;)Lorg/apache/dubbo/common/threadpool/manager/ExecutorRepository;
     147: putfield      #35                 // Field executorRepository:Lorg/apache/dubbo/common/threadpool/manager/ExecutorRepository;
     150: aload_0
     151: new           #36                 // class org/apache/dubbo/config/DubboShutdownHook
     154: dup
     155: aload_1
     156: invokespecial #37                 // Method org/apache/dubbo/config/DubboShutdownHook."<init>":(Lorg/apache/dubbo/rpc/model/ApplicationModel;)V
     159: putfield      #38                 // Field dubboShutdownHook:Lorg/apache/dubbo/config/DubboShutdownHook;
     162: aload_1
     163: ldc           #39                 // class org/apache/dubbo/common/deploy/ApplicationDeployListener
     165: invokevirtual #40                 // Method org/apache/dubbo/rpc/model/ApplicationModel.getExtensionLoader:(Ljava/lang/Class;)Lorg/apache/dubbo/common/extension/ExtensionLoader;
     168: invokevirtual #41                 // Method org/apache/dubbo/common/extension/ExtensionLoader.getSupportedExtensionInstances:()Ljava/util/Set;
     171: astore_2
     172: aload_2
     173: invokeinterface #42,  1           // InterfaceMethod java/util/Set.iterator:()Ljava/util/Iterator;
     178: astore_3
     179: aload_3
     180: invokeinterface #43,  1           // InterfaceMethod java/util/Iterator.hasNext:()Z
     185: ifeq          208
     188: aload_3
     189: invokeinterface #44,  1           // InterfaceMethod java/util/Iterator.next:()Ljava/lang/Object;
     194: checkcast     #39                 // class org/apache/dubbo/common/deploy/ApplicationDeployListener
     197: astore        4
     199: aload_0
     200: aload         4
     202: invokevirtual #45                 // Method addDeployListener:(Lorg/apache/dubbo/common/deploy/DeployListener;)V
     205: goto          179
     208: return

  public static org.apache.dubbo.common.deploy.ApplicationDeployer get(org.apache.dubbo.rpc.model.ScopeModel);
    Code:
       0: aload_0
       1: invokestatic  #46                 // Method org/apache/dubbo/rpc/model/ScopeModelUtil.getApplicationModel:(Lorg/apache/dubbo/rpc/model/ScopeModel;)Lorg/apache/dubbo/rpc/model/ApplicationModel;
       4: astore_1
       5: aload_1
       6: invokevirtual #47                 // Method org/apache/dubbo/rpc/model/ApplicationModel.getDeployer:()Lorg/apache/dubbo/common/deploy/ApplicationDeployer;
       9: astore_2
      10: aload_2
      11: ifnonnull     27
      14: aload_1
      15: invokevirtual #48                 // Method org/apache/dubbo/rpc/model/ApplicationModel.getBeanFactory:()Lorg/apache/dubbo/common/beans/factory/ScopeBeanFactory;
      18: ldc           #49                 // class org/apache/dubbo/config/deploy/DefaultApplicationDeployer
      20: invokevirtual #50                 // Method org/apache/dubbo/common/beans/factory/ScopeBeanFactory.getOrRegisterBean:(Ljava/lang/Class;)Ljava/lang/Object;
      23: checkcast     #51                 // class org/apache/dubbo/common/deploy/ApplicationDeployer
      26: astore_2
      27: aload_2
      28: areturn

  public org.apache.dubbo.rpc.model.ApplicationModel getApplicationModel();
    Code:
       0: aload_0
       1: getfield      #21                 // Field applicationModel:Lorg/apache/dubbo/rpc/model/ApplicationModel;
       4: areturn

  private <T> org.apache.dubbo.common.extension.ExtensionLoader<T> getExtensionLoader(java.lang.Class<T>);
    Code:
       0: aload_0
       1: getfield      #21                 // Field applicationModel:Lorg/apache/dubbo/rpc/model/ApplicationModel;
       4: aload_1
       5: invokevirtual #40                 // Method org/apache/dubbo/rpc/model/ApplicationModel.getExtensionLoader:(Ljava/lang/Class;)Lorg/apache/dubbo/common/extension/ExtensionLoader;
       8: areturn

  private void unRegisterShutdownHook();
    Code:
       0: aload_0
       1: getfield      #38                 // Field dubboShutdownHook:Lorg/apache/dubbo/config/DubboShutdownHook;
       4: invokevirtual #52                 // Method org/apache/dubbo/config/DubboShutdownHook.unregister:()V
       7: return

  private boolean isRegisterConsumerInstance();
    Code:
       0: aload_0
       1: invokespecial #53                 // Method getApplication:()Lorg/apache/dubbo/config/ApplicationConfig;
       4: invokevirtual #54                 // Method org/apache/dubbo/config/ApplicationConfig.getRegisterConsumer:()Ljava/lang/Boolean;
       7: astore_1
       8: aload_1
       9: ifnonnull     14
      12: iconst_1
      13: ireturn
      14: getstatic     #55                 // Field java/lang/Boolean.TRUE:Ljava/lang/Boolean;
      17: aload_1
      18: invokevirtual #56                 // Method java/lang/Boolean.equals:(Ljava/lang/Object;)Z
      21: ireturn

  public org.apache.dubbo.common.config.ReferenceCache getReferenceCache();
    Code:
       0: aload_0
       1: getfield      #28                 // Field referenceCache:Lorg/apache/dubbo/common/config/ReferenceCache;
       4: areturn

  public void initialize();
    Code:
       0: aload_0
       1: getfield      #57                 // Field initialized:Z
       4: ifeq          8
       7: return
       8: aload_0
       9: getfield      #14                 // Field startLock:Ljava/lang/Object;
      12: dup
      13: astore_1
      14: monitorenter
      15: aload_0
      16: getfield      #57                 // Field initialized:Z
      19: ifeq          25
      22: aload_1
      23: monitorexit
      24: return
      25: aload_0
      26: invokespecial #58                 // Method onInitialize:()V
      29: aload_0
      30: invokespecial #59                 // Method registerShutdownHook:()V
      33: aload_0
      34: invokespecial #60                 // Method startConfigCenter:()V
      37: aload_0
      38: invokespecial #61                 // Method loadApplicationConfigs:()V
      41: aload_0
      42: invokespecial #62                 // Method initModuleDeployers:()V
      45: aload_0
      46: invokespecial #63                 // Method initMetricsReporter:()V
      49: aload_0
      50: invokespecial #64                 // Method initMetricsService:()V
      53: aload_0
      54: invokespecial #65                 // Method startMetadataCenter:()V
      57: aload_0
      58: iconst_1
      59: putfield      #57                 // Field initialized:Z
      62: getstatic     #66                 // Field logger:Lorg/apache/dubbo/common/logger/ErrorTypeAwareLogger;
      65: invokeinterface #67,  1           // InterfaceMethod org/apache/dubbo/common/logger/ErrorTypeAwareLogger.isInfoEnabled:()Z
      70: ifeq          103
      73: getstatic     #66                 // Field logger:Lorg/apache/dubbo/common/logger/ErrorTypeAwareLogger;
      76: new           #68                 // class java/lang/StringBuilder
      79: dup
      80: invokespecial #69                 // Method java/lang/StringBuilder."<init>":()V
      83: aload_0
      84: invokevirtual #70                 // Method getIdentifier:()Ljava/lang/String;
      87: invokevirtual #71                 // Method java/lang/StringBuilder.append:(Ljava/lang/String;)Ljava/lang/StringBuilder;
      90: ldc           #72                 // String  has been initialized!
      92: invokevirtual #71                 // Method java/lang/StringBuilder.append:(Ljava/lang/String;)Ljava/lang/StringBuilder;
      95: invokevirtual #73                 // Method java/lang/StringBuilder.toString:()Ljava/lang/String;
      98: invokeinterface #74,  2           // InterfaceMethod org/apache/dubbo/common/logger/ErrorTypeAwareLogger.info:(Ljava/lang/String;)V
     103: aload_1
     104: monitorexit
     105: goto          113
     108: astore_2
     109: aload_1
     110: monitorexit
     111: aload_2
     112: athrow
     113: return
    Exception table:
       from    to  target type
          15    24   108   any
          25   105   108   any
         108   111   108   any

  private void registerShutdownHook();
    Code:
       0: aload_0
       1: getfield      #38                 // Field dubboShutdownHook:Lorg/apache/dubbo/config/DubboShutdownHook;
       4: invokevirtual #75                 // Method org/apache/dubbo/config/DubboShutdownHook.register:()V
       7: return

  private void initModuleDeployers();
    Code:
       0: aload_0
       1: getfield      #21                 // Field applicationModel:Lorg/apache/dubbo/rpc/model/ApplicationModel;
       4: invokevirtual #76                 // Method org/apache/dubbo/rpc/model/ApplicationModel.getDefaultModule:()Lorg/apache/dubbo/rpc/model/ModuleModel;
       7: pop
       8: aload_0
       9: getfield      #21                 // Field applicationModel:Lorg/apache/dubbo/rpc/model/ApplicationModel;
      12: invokevirtual #77                 // Method org/apache/dubbo/rpc/model/ApplicationModel.getModuleModels:()Ljava/util/List;
      15: invokeinterface #78,  1           // InterfaceMethod java/util/List.iterator:()Ljava/util/Iterator;
      20: astore_1
      21: aload_1
      22: invokeinterface #43,  1           // InterfaceMethod java/util/Iterator.hasNext:()Z
      27: ifeq          52
      30: aload_1
      31: invokeinterface #44,  1           // InterfaceMethod java/util/Iterator.next:()Ljava/lang/Object;
      36: checkcast     #79                 // class org/apache/dubbo/rpc/model/ModuleModel
      39: astore_2
      40: aload_2
      41: invokevirtual #80                 // Method org/apache/dubbo/rpc/model/ModuleModel.getDeployer:()Lorg/apache/dubbo/common/deploy/ModuleDeployer;
      44: invokeinterface #81,  1           // InterfaceMethod org/apache/dubbo/common/deploy/ModuleDeployer.initialize:()V
      49: goto          21
      52: return

  private void loadApplicationConfigs();
    Code:
       0: aload_0
       1: getfield      #23                 // Field configManager:Lorg/apache/dubbo/config/context/ConfigManager;
       4: invokevirtual #82                 // Method org/apache/dubbo/config/context/ConfigManager.loadConfigs:()V
       7: return

  private void startConfigCenter();
    Code:
       0: aload_0
       1: getfield      #23                 // Field configManager:Lorg/apache/dubbo/config/context/ConfigManager;
       4: ldc           #83                 // class org/apache/dubbo/config/ApplicationConfig
       6: invokevirtual #84                 // Method org/apache/dubbo/config/context/ConfigManager.loadConfigsOfTypeFromProps:(Ljava/lang/Class;)Ljava/util/List;
       9: pop
      10: aload_0
      11: getfield      #21                 // Field applicationModel:Lorg/apache/dubbo/rpc/model/ApplicationModel;
      14: invokevirtual #85                 // Method org/apache/dubbo/rpc/model/ApplicationModel.getModelName:()Ljava/lang/String;
      17: invokestatic  #86                 // Method org/apache/dubbo/common/utils/StringUtils.isBlank:(Ljava/lang/CharSequence;)Z
      20: ifeq          37
      23: aload_0
      24: getfield      #21                 // Field applicationModel:Lorg/apache/dubbo/rpc/model/ApplicationModel;
      27: aload_0
      28: getfield      #21                 // Field applicationModel:Lorg/apache/dubbo/rpc/model/ApplicationModel;
      31: invokevirtual #87                 // Method org/apache/dubbo/rpc/model/ApplicationModel.tryGetApplicationName:()Ljava/lang/String;
      34: invokevirtual #88                 // Method org/apache/dubbo/rpc/model/ApplicationModel.setModelName:(Ljava/lang/String;)V
      37: aload_0
      38: getfield      #23                 // Field configManager:Lorg/apache/dubbo/config/context/ConfigManager;
      41: ldc           #89                 // class org/apache/dubbo/config/ConfigCenterConfig
      43: invokevirtual #84                 // Method org/apache/dubbo/config/context/ConfigManager.loadConfigsOfTypeFromProps:(Ljava/lang/Class;)Ljava/util/List;
      46: pop
      47: aload_0
      48: invokespecial #90                 // Method useRegistryAsConfigCenterIfNecessary:()V
      51: aload_0
      52: getfield      #23                 // Field configManager:Lorg/apache/dubbo/config/context/ConfigManager;
      55: invokevirtual #91                 // Method org/apache/dubbo/config/context/ConfigManager.getConfigCenters:()Ljava/util/Collection;
      58: astore_1
      59: aload_1
      60: invokestatic  #92                 // Method org/apache/dubbo/common/utils/CollectionUtils.isEmpty:(Ljava/util/Collection;)Z
      63: ifeq          116
      66: new           #89                 // class org/apache/dubbo/config/ConfigCenterConfig
      69: dup
      70: invokespecial #93                 // Method org/apache/dubbo/config/ConfigCenterConfig."<init>":()V
      73: astore_2
      74: aload_2
      75: aload_0
      76: getfield      #21                 // Field applicationModel:Lorg/apache/dubbo/rpc/model/ApplicationModel;
      79: invokevirtual #94                 // Method org/apache/dubbo/config/ConfigCenterConfig.setScopeModel:(Lorg/apache/dubbo/rpc/model/ScopeModel;)V
      82: aload_2
      83: invokevirtual #95                 // Method org/apache/dubbo/config/ConfigCenterConfig.refresh:()V
      86: aload_2
      87: invokestatic  #96                 // Method org/apache/dubbo/config/utils/ConfigValidationUtils.validateConfigCenterConfig:(Lorg/apache/dubbo/config/ConfigCenterConfig;)V
      90: aload_2
      91: invokevirtual #97                 // Method org/apache/dubbo/config/ConfigCenterConfig.isValid:()Z
      94: ifeq          113
      97: aload_0
      98: getfield      #23                 // Field configManager:Lorg/apache/dubbo/config/context/ConfigManager;
     101: aload_2
     102: invokevirtual #98                 // Method org/apache/dubbo/config/context/ConfigManager.addConfigCenter:(Lorg/apache/dubbo/config/ConfigCenterConfig;)V
     105: aload_0
     106: getfield      #23                 // Field configManager:Lorg/apache/dubbo/config/context/ConfigManager;
     109: invokevirtual #91                 // Method org/apache/dubbo/config/context/ConfigManager.getConfigCenters:()Ljava/util/Collection;
     112: astore_1
     113: goto          153
     116: aload_1
     117: invokeinterface #99,  1           // InterfaceMethod java/util/Collection.iterator:()Ljava/util/Iterator;
     122: astore_2
     123: aload_2
     124: invokeinterface #43,  1           // InterfaceMethod java/util/Iterator.hasNext:()Z
     129: ifeq          153
     132: aload_2
     133: invokeinterface #44,  1           // InterfaceMethod java/util/Iterator.next:()Ljava/lang/Object;
     138: checkcast     #89                 // class org/apache/dubbo/config/ConfigCenterConfig
     141: astore_3
     142: aload_3
     143: invokevirtual #95                 // Method org/apache/dubbo/config/ConfigCenterConfig.refresh:()V
     146: aload_3
     147: invokestatic  #96                 // Method org/apache/dubbo/config/utils/ConfigValidationUtils.validateConfigCenterConfig:(Lorg/apache/dubbo/config/ConfigCenterConfig;)V
     150: goto          123
     153: aload_1
     154: invokestatic  #100                // Method org/apache/dubbo/common/utils/CollectionUtils.isNotEmpty:(Ljava/util/Collection;)Z
     157: ifeq          240
     160: new           #101                // class org/apache/dubbo/common/config/configcenter/wrapper/CompositeDynamicConfiguration
     163: dup
     164: invokespecial #102                // Method org/apache/dubbo/common/config/configcenter/wrapper/CompositeDynamicConfiguration."<init>":()V
     167: astore_2
     168: aload_1
     169: invokeinterface #99,  1           // InterfaceMethod java/util/Collection.iterator:()Ljava/util/Iterator;
     174: astore_3
     175: aload_3
     176: invokeinterface #43,  1           // InterfaceMethod java/util/Iterator.hasNext:()Z
     181: ifeq          232
     184: aload_3
     185: invokeinterface #44,  1           // InterfaceMethod java/util/Iterator.next:()Ljava/lang/Object;
     190: checkcast     #89                 // class org/apache/dubbo/config/ConfigCenterConfig
     193: astore        4
     195: aload_0
     196: getfield      #25                 // Field environment:Lorg/apache/dubbo/common/config/Environment;
     199: aload         4
     201: invokevirtual #103                // Method org/apache/dubbo/config/ConfigCenterConfig.getExternalConfiguration:()Ljava/util/Map;
     204: invokevirtual #104                // Method org/apache/dubbo/common/config/Environment.updateExternalConfigMap:(Ljava/util/Map;)V
     207: aload_0
     208: getfield      #25                 // Field environment:Lorg/apache/dubbo/common/config/Environment;
     211: aload         4
     213: invokevirtual #105                // Method org/apache/dubbo/config/ConfigCenterConfig.getAppExternalConfiguration:()Ljava/util/Map;
     216: invokevirtual #106                // Method org/apache/dubbo/common/config/Environment.updateAppExternalConfigMap:(Ljava/util/Map;)V
     219: aload_2
     220: aload_0
     221: aload         4
     223: invokespecial #107                // Method prepareEnvironment:(Lorg/apache/dubbo/config/ConfigCenterConfig;)Lorg/apache/dubbo/common/config/configcenter/DynamicConfiguration;
     226: invokevirtual #108                // Method org/apache/dubbo/common/config/configcenter/wrapper/CompositeDynamicConfiguration.addConfiguration:(Lorg/apache/dubbo/common/config/configcenter/DynamicConfiguration;)V
     229: goto          175
     232: aload_0
     233: getfield      #25                 // Field environment:Lorg/apache/dubbo/common/config/Environment;
     236: aload_2
     237: invokevirtual #109                // Method org/apache/dubbo/common/config/Environment.setDynamicConfiguration:(Lorg/apache/dubbo/common/config/configcenter/DynamicConfiguration;)V
     240: return

  private void startMetadataCenter();
    Code:
       0: aload_0
       1: invokespecial #110                // Method useRegistryAsMetadataCenterIfNecessary:()V
       4: aload_0
       5: invokespecial #53                 // Method getApplication:()Lorg/apache/dubbo/config/ApplicationConfig;
       8: astore_1
       9: aload_1
      10: invokevirtual #111                // Method org/apache/dubbo/config/ApplicationConfig.getMetadataType:()Ljava/lang/String;
      13: astore_2
      14: aload_0
      15: getfield      #23                 // Field configManager:Lorg/apache/dubbo/config/context/ConfigManager;
      18: invokevirtual #112                // Method org/apache/dubbo/config/context/ConfigManager.getMetadataConfigs:()Ljava/util/Collection;
      21: astore_3
      22: aload_3
      23: invokestatic  #92                 // Method org/apache/dubbo/common/utils/CollectionUtils.isEmpty:(Ljava/util/Collection;)Z
      26: ifeq          49
      29: ldc           #113                // String remote
      31: aload_2
      32: invokevirtual #114                // Method java/lang/String.equals:(Ljava/lang/Object;)Z
      35: ifeq          48
      38: new           #115                // class java/lang/IllegalStateException
      41: dup
      42: ldc           #116                // String No MetadataConfig found, Metadata Center address is required when \'metadata=remote\' is enabled.
      44: invokespecial #117                // Method java/lang/IllegalStateException."<init>":(Ljava/lang/String;)V
      47: athrow
      48: return
      49: aload_0
      50: getfield      #21                 // Field applicationModel:Lorg/apache/dubbo/rpc/model/ApplicationModel;
      53: invokevirtual #48                 // Method org/apache/dubbo/rpc/model/ApplicationModel.getBeanFactory:()Lorg/apache/dubbo/common/beans/factory/ScopeBeanFactory;
      56: ldc           #118                // class org/apache/dubbo/metadata/report/MetadataReportInstance
      58: invokevirtual #32                 // Method org/apache/dubbo/common/beans/factory/ScopeBeanFactory.getBean:(Ljava/lang/Class;)Ljava/lang/Object;
      61: checkcast     #118                // class org/apache/dubbo/metadata/report/MetadataReportInstance
      64: astore        4
      66: new           #119                // class java/util/ArrayList
      69: dup
      70: aload_3
      71: invokeinterface #120,  1          // InterfaceMethod java/util/Collection.size:()I
      76: invokespecial #121                // Method java/util/ArrayList."<init>":(I)V
      79: astore        5
      81: aload_3
      82: invokeinterface #99,  1           // InterfaceMethod java/util/Collection.iterator:()Ljava/util/Iterator;
      87: astore        6
      89: aload         6
      91: invokeinterface #43,  1           // InterfaceMethod java/util/Iterator.hasNext:()Z
      96: ifeq          137
      99: aload         6
     101: invokeinterface #44,  1           // InterfaceMethod java/util/Iterator.next:()Ljava/lang/Object;
     106: checkcast     #122                // class org/apache/dubbo/config/MetadataReportConfig
     109: astore        7
     111: aload         7
     113: invokestatic  #123                // Method org/apache/dubbo/config/utils/ConfigValidationUtils.isValidMetadataConfig:(Lorg/apache/dubbo/config/MetadataReportConfig;)Z
     116: ifeq          134
     119: aload         7
     121: invokestatic  #124                // Method org/apache/dubbo/config/utils/ConfigValidationUtils.validateMetadataConfig:(Lorg/apache/dubbo/config/MetadataReportConfig;)V
     124: aload         5
     126: aload         7
     128: invokeinterface #125,  2          // InterfaceMethod java/util/List.add:(Ljava/lang/Object;)Z
     133: pop
     134: goto          89
     137: aload         4
     139: aload         5
     141: invokevirtual #126                // Method org/apache/dubbo/metadata/report/MetadataReportInstance.init:(Ljava/util/List;)V
     144: aload         4
     146: invokevirtual #127                // Method org/apache/dubbo/metadata/report/MetadataReportInstance.inited:()Z
     149: ifne          181
     152: new           #115                // class java/lang/IllegalStateException
     155: dup
     156: ldc           #128                // String %s MetadataConfigs found, but none of them is valid.
     158: iconst_1
     159: anewarray     #11                 // class java/lang/Object
     162: dup
     163: iconst_0
     164: aload_3
     165: invokeinterface #120,  1          // InterfaceMethod java/util/Collection.size:()I
     170: invokestatic  #129                // Method java/lang/Integer.valueOf:(I)Ljava/lang/Integer;
     173: aastore
     174: invokestatic  #130                // Method java/lang/String.format:(Ljava/lang/String;[Ljava/lang/Object;)Ljava/lang/String;
     177: invokespecial #117                // Method java/lang/IllegalStateException."<init>":(Ljava/lang/String;)V
     180: athrow
     181: return

  private void useRegistryAsConfigCenterIfNecessary();
    Code:
       0: aload_0
       1: getfield      #25                 // Field environment:Lorg/apache/dubbo/common/config/Environment;
       4: invokevirtual #131                // Method org/apache/dubbo/common/config/Environment.getDynamicConfiguration:()Ljava/util/Optional;
       7: invokevirtual #132                // Method java/util/Optional.isPresent:()Z
      10: ifeq          14
      13: return
      14: aload_0
      15: getfield      #23                 // Field configManager:Lorg/apache/dubbo/config/context/ConfigManager;
      18: invokevirtual #91                 // Method org/apache/dubbo/config/context/ConfigManager.getConfigCenters:()Ljava/util/Collection;
      21: invokestatic  #100                // Method org/apache/dubbo/common/utils/CollectionUtils.isNotEmpty:(Ljava/util/Collection;)Z
      24: ifeq          28
      27: return
      28: aload_0
      29: getfield      #23                 // Field configManager:Lorg/apache/dubbo/config/context/ConfigManager;
      32: ldc           #133                // class org/apache/dubbo/config/RegistryConfig
      34: invokevirtual #84                 // Method org/apache/dubbo/config/context/ConfigManager.loadConfigsOfTypeFromProps:(Ljava/lang/Class;)Ljava/util/List;
      37: pop
      38: aload_0
      39: getfield      #23                 // Field configManager:Lorg/apache/dubbo/config/context/ConfigManager;
      42: invokevirtual #134                // Method org/apache/dubbo/config/context/ConfigManager.getDefaultRegistries:()Ljava/util/List;
      45: astore_1
      46: aload_1
      47: invokeinterface #135,  1          // InterfaceMethod java/util/List.size:()I
      52: ifle          94
      55: aload_1
      56: invokeinterface #136,  1          // InterfaceMethod java/util/List.stream:()Ljava/util/stream/Stream;
      61: aload_0
      62: invokedynamic #137,  0            // InvokeDynamic #0:test:(Lorg/apache/dubbo/config/deploy/DefaultApplicationDeployer;)Ljava/util/function/Predicate;
      67: invokeinterface #138,  2          // InterfaceMethod java/util/stream/Stream.filter:(Ljava/util/function/Predicate;)Ljava/util/stream/Stream;
      72: aload_0
      73: invokedynamic #139,  0            // InvokeDynamic #1:apply:(Lorg/apache/dubbo/config/deploy/DefaultApplicationDeployer;)Ljava/util/function/Function;
      78: invokeinterface #140,  2          // InterfaceMethod java/util/stream/Stream.map:(Ljava/util/function/Function;)Ljava/util/stream/Stream;
      83: aload_0
      84: invokedynamic #141,  0            // InvokeDynamic #2:accept:(Lorg/apache/dubbo/config/deploy/DefaultApplicationDeployer;)Ljava/util/function/Consumer;
      89: invokeinterface #142,  2          // InterfaceMethod java/util/stream/Stream.forEach:(Ljava/util/function/Consumer;)V
      94: return

  private void initMetricsService();
    Code:
       0: aload_0
       1: aload_0
       2: ldc           #143                // class org/apache/dubbo/metrics/service/MetricsServiceExporter
       4: invokespecial #144                // Method getExtensionLoader:(Ljava/lang/Class;)Lorg/apache/dubbo/common/extension/ExtensionLoader;
       7: invokevirtual #145                // Method org/apache/dubbo/common/extension/ExtensionLoader.getDefaultExtension:()Ljava/lang/Object;
      10: checkcast     #143                // class org/apache/dubbo/metrics/service/MetricsServiceExporter
      13: putfield      #146                // Field metricsServiceExporter:Lorg/apache/dubbo/metrics/service/MetricsServiceExporter;
      16: aload_0
      17: getfield      #146                // Field metricsServiceExporter:Lorg/apache/dubbo/metrics/service/MetricsServiceExporter;
      20: invokeinterface #147,  1          // InterfaceMethod org/apache/dubbo/metrics/service/MetricsServiceExporter.init:()V
      25: return

  private void initMetricsReporter();
    Code:
       0: aload_0
       1: getfield      #21                 // Field applicationModel:Lorg/apache/dubbo/rpc/model/ApplicationModel;
       4: invokevirtual #48                 // Method org/apache/dubbo/rpc/model/ApplicationModel.getBeanFactory:()Lorg/apache/dubbo/common/beans/factory/ScopeBeanFactory;
       7: ldc           #148                // class org/apache/dubbo/metrics/collector/DefaultMetricsCollector
       9: invokevirtual #32                 // Method org/apache/dubbo/common/beans/factory/ScopeBeanFactory.getBean:(Ljava/lang/Class;)Ljava/lang/Object;
      12: checkcast     #148                // class org/apache/dubbo/metrics/collector/DefaultMetricsCollector
      15: astore_1
      16: aload_0
      17: getfield      #23                 // Field configManager:Lorg/apache/dubbo/config/context/ConfigManager;
      20: invokevirtual #149                // Method org/apache/dubbo/config/context/ConfigManager.getMetrics:()Ljava/util/Optional;
      23: astore_2
      24: invokestatic  #150                // Method isSupportPrometheus:()Z
      27: ifne          31
      30: return
      31: aload_2
      32: new           #151                // class org/apache/dubbo/config/MetricsConfig
      35: dup
      36: aload_0
      37: getfield      #21                 // Field applicationModel:Lorg/apache/dubbo/rpc/model/ApplicationModel;
      40: invokespecial #152                // Method org/apache/dubbo/config/MetricsConfig."<init>":(Lorg/apache/dubbo/rpc/model/ApplicationModel;)V
      43: invokevirtual #153                // Method java/util/Optional.orElse:(Ljava/lang/Object;)Ljava/lang/Object;
      46: checkcast     #151                // class org/apache/dubbo/config/MetricsConfig
      49: astore_3
      50: aload_3
      51: invokevirtual #154                // Method org/apache/dubbo/config/MetricsConfig.getProtocol:()Ljava/lang/String;
      54: invokestatic  #86                 // Method org/apache/dubbo/common/utils/StringUtils.isBlank:(Ljava/lang/CharSequence;)Z
      57: ifeq          66
      60: aload_3
      61: ldc           #155                // String prometheus
      63: invokevirtual #156                // Method org/apache/dubbo/config/MetricsConfig.setProtocol:(Ljava/lang/String;)V
      66: aload_1
      67: iconst_1
      68: invokestatic  #157                // Method java/lang/Boolean.valueOf:(Z)Ljava/lang/Boolean;
      71: invokevirtual #158                // Method org/apache/dubbo/metrics/collector/DefaultMetricsCollector.setCollectEnabled:(Ljava/lang/Boolean;)V
      74: aload_1
      75: invokevirtual #159                // Method org/apache/dubbo/metrics/collector/DefaultMetricsCollector.collectApplication:()V
      78: aload_1
      79: aload_3
      80: invokevirtual #160                // Method org/apache/dubbo/config/MetricsConfig.getEnableThreadpool:()Ljava/lang/Boolean;
      83: invokestatic  #161                // Method java/util/Optional.ofNullable:(Ljava/lang/Object;)Ljava/util/Optional;
      86: iconst_1
      87: invokestatic  #157                // Method java/lang/Boolean.valueOf:(Z)Ljava/lang/Boolean;
      90: invokevirtual #153                // Method java/util/Optional.orElse:(Ljava/lang/Object;)Ljava/lang/Object;
      93: checkcast     #162                // class java/lang/Boolean
      96: invokevirtual #163                // Method java/lang/Boolean.booleanValue:()Z
      99: invokevirtual #164                // Method org/apache/dubbo/metrics/collector/DefaultMetricsCollector.setThreadpoolCollectEnabled:(Z)V
     102: aload_0
     103: ldc           #165                // class org/apache/dubbo/metrics/report/MetricsReporterFactory
     105: invokespecial #144                // Method getExtensionLoader:(Ljava/lang/Class;)Lorg/apache/dubbo/common/extension/ExtensionLoader;
     108: invokevirtual #166                // Method org/apache/dubbo/common/extension/ExtensionLoader.getAdaptiveExtension:()Ljava/lang/Object;
     111: checkcast     #165                // class org/apache/dubbo/metrics/report/MetricsReporterFactory
     114: astore        4
     116: aload         4
     118: aload_3
     119: invokevirtual #167                // Method org/apache/dubbo/config/MetricsConfig.toUrl:()Lorg/apache/dubbo/common/URL;
     122: invokeinterface #168,  2          // InterfaceMethod org/apache/dubbo/metrics/report/MetricsReporterFactory.createMetricsReporter:(Lorg/apache/dubbo/common/URL;)Lorg/apache/dubbo/metrics/report/MetricsReporter;
     127: astore        5
     129: aload         5
     131: invokeinterface #169,  1          // InterfaceMethod org/apache/dubbo/metrics/report/MetricsReporter.init:()V
     136: aload_0
     137: getfield      #21                 // Field applicationModel:Lorg/apache/dubbo/rpc/model/ApplicationModel;
     140: invokevirtual #48                 // Method org/apache/dubbo/rpc/model/ApplicationModel.getBeanFactory:()Lorg/apache/dubbo/common/beans/factory/ScopeBeanFactory;
     143: aload         5
     145: invokevirtual #170                // Method org/apache/dubbo/common/beans/factory/ScopeBeanFactory.registerBean:(Ljava/lang/Object;)V
     148: return

  public static boolean isSupportPrometheus();
    Code:
       0: ldc           #171                // String io.micrometer.prometheus.PrometheusConfig
       2: invokestatic  #172                // Method isClassPresent:(Ljava/lang/String;)Z
       5: ifeq          36
       8: ldc           #173                // String io.prometheus.client.exporter.BasicAuthHttpConnectionFactory
      10: invokestatic  #172                // Method isClassPresent:(Ljava/lang/String;)Z
      13: ifeq          36
      16: ldc           #174                // String io.prometheus.client.exporter.HttpConnectionFactory
      18: invokestatic  #172                // Method isClassPresent:(Ljava/lang/String;)Z
      21: ifeq          36
      24: ldc           #175                // String io.prometheus.client.exporter.PushGateway
      26: invokestatic  #172                // Method isClassPresent:(Ljava/lang/String;)Z
      29: ifeq          36
      32: iconst_1
      33: goto          37
      36: iconst_0
      37: ireturn

  private static boolean isClassPresent(java.lang.String);
    Code:
       0: aload_0
       1: ldc           #49                 // class org/apache/dubbo/config/deploy/DefaultApplicationDeployer
       3: invokevirtual #176                // Method java/lang/Class.getClassLoader:()Ljava/lang/ClassLoader;
       6: invokestatic  #177                // Method org/apache/dubbo/common/utils/ClassUtils.isPresent:(Ljava/lang/String;Ljava/lang/ClassLoader;)Z
       9: ireturn

  private boolean isUsedRegistryAsConfigCenter(org.apache.dubbo.config.RegistryConfig);
    Code:
       0: aload_0
       1: aload_1
       2: aload_1
       3: dup
       4: invokevirtual #178                // Method java/lang/Object.getClass:()Ljava/lang/Class;
       7: pop
       8: invokedynamic #179,  0            // InvokeDynamic #3:get:(Lorg/apache/dubbo/config/RegistryConfig;)Ljava/util/function/Supplier;
      13: ldc           #180                // String config
      15: ldc           #181                // class org/apache/dubbo/common/config/configcenter/DynamicConfigurationFactory
      17: invokespecial #182                // Method isUsedRegistryAsCenter:(Lorg/apache/dubbo/config/RegistryConfig;Ljava/util/function/Supplier;Ljava/lang/String;Ljava/lang/Class;)Z
      20: ireturn

  private org.apache.dubbo.config.ConfigCenterConfig registryAsConfigCenter(org.apache.dubbo.config.RegistryConfig);
    Code:
       0: aload_1
       1: invokevirtual #183                // Method org/apache/dubbo/config/RegistryConfig.getProtocol:()Ljava/lang/String;
       4: astore_2
       5: aload_1
       6: invokevirtual #184                // Method org/apache/dubbo/config/RegistryConfig.getPort:()Ljava/lang/Integer;
       9: astore_3
      10: aload_1
      11: invokevirtual #185                // Method org/apache/dubbo/config/RegistryConfig.getAddress:()Ljava/lang/String;
      14: aload_1
      15: invokevirtual #186                // Method org/apache/dubbo/config/RegistryConfig.getScopeModel:()Lorg/apache/dubbo/rpc/model/ScopeModel;
      18: invokestatic  #187                // Method org/apache/dubbo/common/URL.valueOf:(Ljava/lang/String;Lorg/apache/dubbo/rpc/model/ScopeModel;)Lorg/apache/dubbo/common/URL;
      21: astore        4
      23: new           #68                 // class java/lang/StringBuilder
      26: dup
      27: invokespecial #69                 // Method java/lang/StringBuilder."<init>":()V
      30: ldc           #188                // String config-center-
      32: invokevirtual #71                 // Method java/lang/StringBuilder.append:(Ljava/lang/String;)Ljava/lang/StringBuilder;
      35: aload_2
      36: invokevirtual #71                 // Method java/lang/StringBuilder.append:(Ljava/lang/String;)Ljava/lang/StringBuilder;
      39: ldc           #189                // String -
      41: invokevirtual #71                 // Method java/lang/StringBuilder.append:(Ljava/lang/String;)Ljava/lang/StringBuilder;
      44: aload         4
      46: invokevirtual #190                // Method org/apache/dubbo/common/URL.getHost:()Ljava/lang/String;
      49: invokevirtual #71                 // Method java/lang/StringBuilder.append:(Ljava/lang/String;)Ljava/lang/StringBuilder;
      52: ldc           #189                // String -
      54: invokevirtual #71                 // Method java/lang/StringBuilder.append:(Ljava/lang/String;)Ljava/lang/StringBuilder;
      57: aload_3
      58: invokevirtual #191                // Method java/lang/StringBuilder.append:(Ljava/lang/Object;)Ljava/lang/StringBuilder;
      61: invokevirtual #73                 // Method java/lang/StringBuilder.toString:()Ljava/lang/String;
      64: astore        5
      66: new           #89                 // class org/apache/dubbo/config/ConfigCenterConfig
      69: dup
      70: invokespecial #93                 // Method org/apache/dubbo/config/ConfigCenterConfig."<init>":()V
      73: astore        6
      75: aload         6
      77: aload         5
      79: invokevirtual #192                // Method org/apache/dubbo/config/ConfigCenterConfig.setId:(Ljava/lang/String;)V
      82: aload         6
      84: aload_0
      85: getfield      #21                 // Field applicationModel:Lorg/apache/dubbo/rpc/model/ApplicationModel;
      88: invokevirtual #94                 // Method org/apache/dubbo/config/ConfigCenterConfig.setScopeModel:(Lorg/apache/dubbo/rpc/model/ScopeModel;)V
      91: aload         6
      93: invokevirtual #193                // Method org/apache/dubbo/config/ConfigCenterConfig.getParameters:()Ljava/util/Map;
      96: ifnonnull     111
      99: aload         6
     101: new           #194                // class java/util/HashMap
     104: dup
     105: invokespecial #195                // Method java/util/HashMap."<init>":()V
     108: invokevirtual #196                // Method org/apache/dubbo/config/ConfigCenterConfig.setParameters:(Ljava/util/Map;)V
     111: aload_1
     112: invokevirtual #197                // Method org/apache/dubbo/config/RegistryConfig.getParameters:()Ljava/util/Map;
     115: invokestatic  #198                // Method org/apache/dubbo/common/utils/CollectionUtils.isNotEmptyMap:(Ljava/util/Map;)Z
     118: ifeq          135
     121: aload         6
     123: invokevirtual #193                // Method org/apache/dubbo/config/ConfigCenterConfig.getParameters:()Ljava/util/Map;
     126: aload_1
     127: invokevirtual #197                // Method org/apache/dubbo/config/RegistryConfig.getParameters:()Ljava/util/Map;
     130: invokeinterface #199,  2          // InterfaceMethod java/util/Map.putAll:(Ljava/util/Map;)V
     135: aload         6
     137: invokevirtual #193                // Method org/apache/dubbo/config/ConfigCenterConfig.getParameters:()Ljava/util/Map;
     140: ldc           #200                // String client
     142: aload_1
     143: invokevirtual #201                // Method org/apache/dubbo/config/RegistryConfig.getClient:()Ljava/lang/String;
     146: invokeinterface #202,  3          // InterfaceMethod java/util/Map.put:(Ljava/lang/Object;Ljava/lang/Object;)Ljava/lang/Object;
     151: pop
     152: aload         6
     154: aload_2
     155: invokevirtual #203                // Method org/apache/dubbo/config/ConfigCenterConfig.setProtocol:(Ljava/lang/String;)V
     158: aload         6
     160: aload_3
     161: invokevirtual #204                // Method org/apache/dubbo/config/ConfigCenterConfig.setPort:(Ljava/lang/Integer;)V
     164: aload_1
     165: invokevirtual #205                // Method org/apache/dubbo/config/RegistryConfig.getGroup:()Ljava/lang/String;
     168: invokestatic  #206                // Method org/apache/dubbo/common/utils/StringUtils.isNotEmpty:(Ljava/lang/String;)Z
     171: ifeq          183
     174: aload         6
     176: aload_1
     177: invokevirtual #205                // Method org/apache/dubbo/config/RegistryConfig.getGroup:()Ljava/lang/String;
     180: invokevirtual #207                // Method org/apache/dubbo/config/ConfigCenterConfig.setGroup:(Ljava/lang/String;)V
     183: aload         6
     185: aload_0
     186: aload_1
     187: invokespecial #208                // Method getRegistryCompatibleAddress:(Lorg/apache/dubbo/config/RegistryConfig;)Ljava/lang/String;
     190: invokevirtual #209                // Method org/apache/dubbo/config/ConfigCenterConfig.setAddress:(Ljava/lang/String;)V
     193: aload         6
     195: aload_1
     196: invokevirtual #205                // Method org/apache/dubbo/config/RegistryConfig.getGroup:()Ljava/lang/String;
     199: invokevirtual #210                // Method org/apache/dubbo/config/ConfigCenterConfig.setNamespace:(Ljava/lang/String;)V
     202: aload         6
     204: aload_1
     205: invokevirtual #211                // Method org/apache/dubbo/config/RegistryConfig.getUsername:()Ljava/lang/String;
     208: invokevirtual #212                // Method org/apache/dubbo/config/ConfigCenterConfig.setUsername:(Ljava/lang/String;)V
     211: aload         6
     213: aload_1
     214: invokevirtual #213                // Method org/apache/dubbo/config/RegistryConfig.getPassword:()Ljava/lang/String;
     217: invokevirtual #214                // Method org/apache/dubbo/config/ConfigCenterConfig.setPassword:(Ljava/lang/String;)V
     220: aload_1
     221: invokevirtual #215                // Method org/apache/dubbo/config/RegistryConfig.getTimeout:()Ljava/lang/Integer;
     224: ifnull        242
     227: aload         6
     229: aload_1
     230: invokevirtual #215                // Method org/apache/dubbo/config/RegistryConfig.getTimeout:()Ljava/lang/Integer;
     233: invokevirtual #216                // Method java/lang/Integer.longValue:()J
     236: invokestatic  #217                // Method java/lang/Long.valueOf:(J)Ljava/lang/Long;
     239: invokevirtual #218                // Method org/apache/dubbo/config/ConfigCenterConfig.setTimeout:(Ljava/lang/Long;)V
     242: aload         6
     244: iconst_0
     245: invokestatic  #157                // Method java/lang/Boolean.valueOf:(Z)Ljava/lang/Boolean;
     248: invokevirtual #219                // Method org/apache/dubbo/config/ConfigCenterConfig.setHighestPriority:(Ljava/lang/Boolean;)V
     251: aload         6
     253: areturn

  private void useRegistryAsMetadataCenterIfNecessary();
    Code:
       0: aload_0
       1: getfield      #23                 // Field configManager:Lorg/apache/dubbo/config/context/ConfigManager;
       4: invokevirtual #112                // Method org/apache/dubbo/config/context/ConfigManager.getMetadataConfigs:()Ljava/util/Collection;
       7: astore_1
       8: aload_1
       9: invokeinterface #220,  1          // InterfaceMethod java/util/Collection.stream:()Ljava/util/stream/Stream;
      14: invokedynamic #221,  0            // InvokeDynamic #4:test:()Ljava/util/function/Predicate;
      19: invokeinterface #222,  2          // InterfaceMethod java/util/stream/Stream.anyMatch:(Ljava/util/function/Predicate;)Z
      24: ifeq          28
      27: return
      28: aload_1
      29: invokeinterface #220,  1          // InterfaceMethod java/util/Collection.stream:()Ljava/util/stream/Stream;
      34: invokedynamic #223,  0            // InvokeDynamic #5:test:()Ljava/util/function/Predicate;
      39: invokeinterface #138,  2          // InterfaceMethod java/util/stream/Stream.filter:(Ljava/util/function/Predicate;)Ljava/util/stream/Stream;
      44: invokestatic  #224                // Method java/util/stream/Collectors.toList:()Ljava/util/stream/Collector;
      47: invokeinterface #225,  2          // InterfaceMethod java/util/stream/Stream.collect:(Ljava/util/stream/Collector;)Ljava/lang/Object;
      52: checkcast     #226                // class java/util/Collection
      55: astore_2
      56: aload_2
      57: invokeinterface #120,  1          // InterfaceMethod java/util/Collection.size:()I
      62: iconst_1
      63: if_icmple     67
      66: return
      67: aload_2
      68: invokeinterface #220,  1          // InterfaceMethod java/util/Collection.stream:()Ljava/util/stream/Stream;
      73: invokeinterface #227,  1          // InterfaceMethod java/util/stream/Stream.findFirst:()Ljava/util/Optional;
      78: aconst_null
      79: invokevirtual #153                // Method java/util/Optional.orElse:(Ljava/lang/Object;)Ljava/lang/Object;
      82: checkcast     #122                // class org/apache/dubbo/config/MetadataReportConfig
      85: astore_3
      86: aload_0
      87: getfield      #23                 // Field configManager:Lorg/apache/dubbo/config/context/ConfigManager;
      90: invokevirtual #134                // Method org/apache/dubbo/config/context/ConfigManager.getDefaultRegistries:()Ljava/util/List;
      93: astore        4
      95: aload         4
      97: invokeinterface #228,  1          // InterfaceMethod java/util/List.isEmpty:()Z
     102: ifne          147
     105: aload         4
     107: invokeinterface #136,  1          // InterfaceMethod java/util/List.stream:()Ljava/util/stream/Stream;
     112: aload_0
     113: invokedynamic #229,  0            // InvokeDynamic #6:test:(Lorg/apache/dubbo/config/deploy/DefaultApplicationDeployer;)Ljava/util/function/Predicate;
     118: invokeinterface #138,  2          // InterfaceMethod java/util/stream/Stream.filter:(Ljava/util/function/Predicate;)Ljava/util/stream/Stream;
     123: aload_0
     124: aload_3
     125: invokedynamic #230,  0            // InvokeDynamic #7:apply:(Lorg/apache/dubbo/config/deploy/DefaultApplicationDeployer;Lorg/apache/dubbo/config/MetadataReportConfig;)Ljava/util/function/Function;
     130: invokeinterface #140,  2          // InterfaceMethod java/util/stream/Stream.map:(Ljava/util/function/Function;)Ljava/util/stream/Stream;
     135: aload_0
     136: aload_3
     137: invokedynamic #231,  0            // InvokeDynamic #8:accept:(Lorg/apache/dubbo/config/deploy/DefaultApplicationDeployer;Lorg/apache/dubbo/config/MetadataReportConfig;)Ljava/util/function/Consumer;
     142: invokeinterface #142,  2          // InterfaceMethod java/util/stream/Stream.forEach:(Ljava/util/function/Consumer;)V
     147: return

  private void overrideMetadataReportConfig(org.apache.dubbo.config.MetadataReportConfig, org.apache.dubbo.config.MetadataReportConfig);
    Code:
       0: aload_2
       1: invokevirtual #232                // Method org/apache/dubbo/config/MetadataReportConfig.getId:()Ljava/lang/String;
       4: ifnonnull     99
       7: aload_0
       8: getfield      #23                 // Field configManager:Lorg/apache/dubbo/config/context/ConfigManager;
      11: invokevirtual #112                // Method org/apache/dubbo/config/context/ConfigManager.getMetadataConfigs:()Ljava/util/Collection;
      14: astore_3
      15: aload_3
      16: invokestatic  #100                // Method org/apache/dubbo/common/utils/CollectionUtils.isNotEmpty:(Ljava/util/Collection;)Z
      19: ifeq          79
      22: aload_3
      23: invokeinterface #99,  1           // InterfaceMethod java/util/Collection.iterator:()Ljava/util/Iterator;
      28: astore        4
      30: aload         4
      32: invokeinterface #43,  1           // InterfaceMethod java/util/Iterator.hasNext:()Z
      37: ifeq          79
      40: aload         4
      42: invokeinterface #44,  1           // InterfaceMethod java/util/Iterator.next:()Ljava/lang/Object;
      47: checkcast     #122                // class org/apache/dubbo/config/MetadataReportConfig
      50: astore        5
      52: aload         5
      54: invokevirtual #232                // Method org/apache/dubbo/config/MetadataReportConfig.getId:()Ljava/lang/String;
      57: ifnonnull     76
      60: aload         5
      62: invokevirtual #233                // Method org/apache/dubbo/config/MetadataReportConfig.getAddress:()Ljava/lang/String;
      65: aload_2
      66: invokevirtual #233                // Method org/apache/dubbo/config/MetadataReportConfig.getAddress:()Ljava/lang/String;
      69: invokevirtual #114                // Method java/lang/String.equals:(Ljava/lang/Object;)Z
      72: ifeq          76
      75: return
      76: goto          30
      79: aload_0
      80: getfield      #23                 // Field configManager:Lorg/apache/dubbo/config/context/ConfigManager;
      83: aload_1
      84: invokevirtual #234                // Method org/apache/dubbo/config/context/ConfigManager.removeConfig:(Lorg/apache/dubbo/config/AbstractConfig;)Z
      87: pop
      88: aload_0
      89: getfield      #23                 // Field configManager:Lorg/apache/dubbo/config/context/ConfigManager;
      92: aload_2
      93: invokevirtual #235                // Method org/apache/dubbo/config/context/ConfigManager.addMetadataReport:(Lorg/apache/dubbo/config/MetadataReportConfig;)V
      96: goto          138
      99: aload_0
     100: getfield      #23                 // Field configManager:Lorg/apache/dubbo/config/context/ConfigManager;
     103: ldc           #122                // class org/apache/dubbo/config/MetadataReportConfig
     105: aload_2
     106: invokevirtual #232                // Method org/apache/dubbo/config/MetadataReportConfig.getId:()Ljava/lang/String;
     109: invokevirtual #236                // Method org/apache/dubbo/config/context/ConfigManager.getConfig:(Ljava/lang/Class;Ljava/lang/String;)Ljava/util/Optional;
     112: astore_3
     113: aload_3
     114: invokevirtual #132                // Method java/util/Optional.isPresent:()Z
     117: ifeq          121
     120: return
     121: aload_0
     122: getfield      #23                 // Field configManager:Lorg/apache/dubbo/config/context/ConfigManager;
     125: aload_1
     126: invokevirtual #234                // Method org/apache/dubbo/config/context/ConfigManager.removeConfig:(Lorg/apache/dubbo/config/AbstractConfig;)Z
     129: pop
     130: aload_0
     131: getfield      #23                 // Field configManager:Lorg/apache/dubbo/config/context/ConfigManager;
     134: aload_2
     135: invokevirtual #235                // Method org/apache/dubbo/config/context/ConfigManager.addMetadataReport:(Lorg/apache/dubbo/config/MetadataReportConfig;)V
     138: getstatic     #66                 // Field logger:Lorg/apache/dubbo/common/logger/ErrorTypeAwareLogger;
     141: new           #68                 // class java/lang/StringBuilder
     144: dup
     145: invokespecial #69                 // Method java/lang/StringBuilder."<init>":()V
     148: ldc           #237                // String use registry as metadata-center:
     150: invokevirtual #71                 // Method java/lang/StringBuilder.append:(Ljava/lang/String;)Ljava/lang/StringBuilder;
     153: aload_2
     154: invokevirtual #191                // Method java/lang/StringBuilder.append:(Ljava/lang/Object;)Ljava/lang/StringBuilder;
     157: invokevirtual #73                 // Method java/lang/StringBuilder.toString:()Ljava/lang/String;
     160: invokeinterface #74,  2           // InterfaceMethod org/apache/dubbo/common/logger/ErrorTypeAwareLogger.info:(Ljava/lang/String;)V
     165: return

  private boolean isUsedRegistryAsMetadataCenter(org.apache.dubbo.config.RegistryConfig);
    Code:
       0: aload_0
       1: aload_1
       2: aload_1
       3: dup
       4: invokevirtual #178                // Method java/lang/Object.getClass:()Ljava/lang/Class;
       7: pop
       8: invokedynamic #238,  0            // InvokeDynamic #9:get:(Lorg/apache/dubbo/config/RegistryConfig;)Ljava/util/function/Supplier;
      13: ldc           #239                // String metadata
      15: ldc           #240                // class org/apache/dubbo/metadata/report/MetadataReportFactory
      17: invokespecial #182                // Method isUsedRegistryAsCenter:(Lorg/apache/dubbo/config/RegistryConfig;Ljava/util/function/Supplier;Ljava/lang/String;Ljava/lang/Class;)Z
      20: ireturn

  private boolean isUsedRegistryAsCenter(org.apache.dubbo.config.RegistryConfig, java.util.function.Supplier<java.lang.Boolean>, java.lang.String, java.lang.Class<?>);
    Code:
       0: aload_2
       1: invokeinterface #241,  1          // InterfaceMethod java/util/function/Supplier.get:()Ljava/lang/Object;
       6: checkcast     #162                // class java/lang/Boolean
       9: astore        6
      11: aload         6
      13: ifnull        26
      16: aload         6
      18: invokevirtual #163                // Method java/lang/Boolean.booleanValue:()Z
      21: istore        5
      23: goto          102
      26: aload_1
      27: invokevirtual #183                // Method org/apache/dubbo/config/RegistryConfig.getProtocol:()Ljava/lang/String;
      30: astore        7
      32: aload_0
      33: aload         4
      35: aload         7
      37: invokespecial #242                // Method supportsExtension:(Ljava/lang/Class;Ljava/lang/String;)Z
      40: istore        5
      42: getstatic     #66                 // Field logger:Lorg/apache/dubbo/common/logger/ErrorTypeAwareLogger;
      45: invokeinterface #67,  1           // InterfaceMethod org/apache/dubbo/common/logger/ErrorTypeAwareLogger.isInfoEnabled:()Z
      50: ifeq          102
      53: getstatic     #66                 // Field logger:Lorg/apache/dubbo/common/logger/ErrorTypeAwareLogger;
      56: ldc           #243                // String No value is configured in the registry, the %s extension[name : %s] %s as the %s center
      58: iconst_4
      59: anewarray     #11                 // class java/lang/Object
      62: dup
      63: iconst_0
      64: aload         4
      66: invokevirtual #244                // Method java/lang/Class.getSimpleName:()Ljava/lang/String;
      69: aastore
      70: dup
      71: iconst_1
      72: aload         7
      74: aastore
      75: dup
      76: iconst_2
      77: iload         5
      79: ifeq          87
      82: ldc           #245                // String supports
      84: goto          89
      87: ldc           #246                // String does not support
      89: aastore
      90: dup
      91: iconst_3
      92: aload_3
      93: aastore
      94: invokestatic  #130                // Method java/lang/String.format:(Ljava/lang/String;[Ljava/lang/Object;)Ljava/lang/String;
      97: invokeinterface #74,  2           // InterfaceMethod org/apache/dubbo/common/logger/ErrorTypeAwareLogger.info:(Ljava/lang/String;)V
     102: getstatic     #66                 // Field logger:Lorg/apache/dubbo/common/logger/ErrorTypeAwareLogger;
     105: invokeinterface #67,  1           // InterfaceMethod org/apache/dubbo/common/logger/ErrorTypeAwareLogger.isInfoEnabled:()Z
     110: ifeq          153
     113: getstatic     #66                 // Field logger:Lorg/apache/dubbo/common/logger/ErrorTypeAwareLogger;
     116: ldc           #247                // String The registry[%s] will be %s as the %s center
     118: iconst_3
     119: anewarray     #11                 // class java/lang/Object
     122: dup
     123: iconst_0
     124: aload_1
     125: aastore
     126: dup
     127: iconst_1
     128: iload         5
     130: ifeq          138
     133: ldc           #248                // String used
     135: goto          140
     138: ldc           #249                // String not used
     140: aastore
     141: dup
     142: iconst_2
     143: aload_3
     144: aastore
     145: invokestatic  #130                // Method java/lang/String.format:(Ljava/lang/String;[Ljava/lang/Object;)Ljava/lang/String;
     148: invokeinterface #74,  2           // InterfaceMethod org/apache/dubbo/common/logger/ErrorTypeAwareLogger.info:(Ljava/lang/String;)V
     153: iload         5
     155: ireturn

  private boolean supportsExtension(java.lang.Class<?>, java.lang.String);
    Code:
       0: aload_2
       1: invokestatic  #206                // Method org/apache/dubbo/common/utils/StringUtils.isNotEmpty:(Ljava/lang/String;)Z
       4: ifeq          19
       7: aload_0
       8: aload_1
       9: invokespecial #144                // Method getExtensionLoader:(Ljava/lang/Class;)Lorg/apache/dubbo/common/extension/ExtensionLoader;
      12: astore_3
      13: aload_3
      14: aload_2
      15: invokevirtual #250                // Method org/apache/dubbo/common/extension/ExtensionLoader.hasExtension:(Ljava/lang/String;)Z
      18: ireturn
      19: iconst_0
      20: ireturn

  private org.apache.dubbo.config.MetadataReportConfig registryAsMetadataCenter(org.apache.dubbo.config.RegistryConfig, org.apache.dubbo.config.MetadataReportConfig);
    Code:
       0: aload_2
       1: ifnonnull     18
       4: new           #122                // class org/apache/dubbo/config/MetadataReportConfig
       7: dup
       8: aload_1
       9: invokevirtual #251                // Method org/apache/dubbo/config/RegistryConfig.getApplicationModel:()Lorg/apache/dubbo/rpc/model/ApplicationModel;
      12: invokespecial #252                // Method org/apache/dubbo/config/MetadataReportConfig."<init>":(Lorg/apache/dubbo/rpc/model/ApplicationModel;)V
      15: goto          19
      18: aload_2
      19: astore_3
      20: aload_3
      21: invokevirtual #232                // Method org/apache/dubbo/config/MetadataReportConfig.getId:()Ljava/lang/String;
      24: ifnonnull     35
      27: aload_3
      28: aload_1
      29: invokevirtual #253                // Method org/apache/dubbo/config/RegistryConfig.getId:()Ljava/lang/String;
      32: invokevirtual #254                // Method org/apache/dubbo/config/MetadataReportConfig.setId:(Ljava/lang/String;)V
      35: aload_3
      36: aload_0
      37: getfield      #21                 // Field applicationModel:Lorg/apache/dubbo/rpc/model/ApplicationModel;
      40: invokevirtual #255                // Method org/apache/dubbo/config/MetadataReportConfig.setScopeModel:(Lorg/apache/dubbo/rpc/model/ScopeModel;)V
      43: aload_3
      44: invokevirtual #256                // Method org/apache/dubbo/config/MetadataReportConfig.getParameters:()Ljava/util/Map;
      47: ifnonnull     61
      50: aload_3
      51: new           #194                // class java/util/HashMap
      54: dup
      55: invokespecial #195                // Method java/util/HashMap."<init>":()V
      58: invokevirtual #257                // Method org/apache/dubbo/config/MetadataReportConfig.setParameters:(Ljava/util/Map;)V
      61: aload_1
      62: invokevirtual #197                // Method org/apache/dubbo/config/RegistryConfig.getParameters:()Ljava/util/Map;
      65: invokestatic  #198                // Method org/apache/dubbo/common/utils/CollectionUtils.isNotEmptyMap:(Ljava/util/Map;)Z
      68: ifeq          136
      71: aload_1
      72: invokevirtual #197                // Method org/apache/dubbo/config/RegistryConfig.getParameters:()Ljava/util/Map;
      75: invokeinterface #258,  1          // InterfaceMethod java/util/Map.entrySet:()Ljava/util/Set;
      80: invokeinterface #42,  1           // InterfaceMethod java/util/Set.iterator:()Ljava/util/Iterator;
      85: astore        4
      87: aload         4
      89: invokeinterface #43,  1           // InterfaceMethod java/util/Iterator.hasNext:()Z
      94: ifeq          136
      97: aload         4
      99: invokeinterface #44,  1           // InterfaceMethod java/util/Iterator.next:()Ljava/lang/Object;
     104: checkcast     #259                // class java/util/Map$Entry
     107: astore        5
     109: aload_3
     110: invokevirtual #256                // Method org/apache/dubbo/config/MetadataReportConfig.getParameters:()Ljava/util/Map;
     113: aload         5
     115: invokeinterface #260,  1          // InterfaceMethod java/util/Map$Entry.getKey:()Ljava/lang/Object;
     120: aload         5
     122: invokeinterface #261,  1          // InterfaceMethod java/util/Map$Entry.getValue:()Ljava/lang/Object;
     127: invokeinterface #262,  3          // InterfaceMethod java/util/Map.putIfAbsent:(Ljava/lang/Object;Ljava/lang/Object;)Ljava/lang/Object;
     132: pop
     133: goto          87
     136: aload_3
     137: invokevirtual #256                // Method org/apache/dubbo/config/MetadataReportConfig.getParameters:()Ljava/util/Map;
     140: ldc           #200                // String client
     142: aload_1
     143: invokevirtual #201                // Method org/apache/dubbo/config/RegistryConfig.getClient:()Ljava/lang/String;
     146: invokeinterface #202,  3          // InterfaceMethod java/util/Map.put:(Ljava/lang/Object;Ljava/lang/Object;)Ljava/lang/Object;
     151: pop
     152: aload_3
     153: invokevirtual #263                // Method org/apache/dubbo/config/MetadataReportConfig.getGroup:()Ljava/lang/String;
     156: ifnonnull     167
     159: aload_3
     160: aload_1
     161: invokevirtual #205                // Method org/apache/dubbo/config/RegistryConfig.getGroup:()Ljava/lang/String;
     164: invokevirtual #264                // Method org/apache/dubbo/config/MetadataReportConfig.setGroup:(Ljava/lang/String;)V
     167: aload_3
     168: invokevirtual #233                // Method org/apache/dubbo/config/MetadataReportConfig.getAddress:()Ljava/lang/String;
     171: ifnonnull     183
     174: aload_3
     175: aload_0
     176: aload_1
     177: invokespecial #208                // Method getRegistryCompatibleAddress:(Lorg/apache/dubbo/config/RegistryConfig;)Ljava/lang/String;
     180: invokevirtual #265                // Method org/apache/dubbo/config/MetadataReportConfig.setAddress:(Ljava/lang/String;)V
     183: aload_3
     184: invokevirtual #266                // Method org/apache/dubbo/config/MetadataReportConfig.getUsername:()Ljava/lang/String;
     187: ifnonnull     198
     190: aload_3
     191: aload_1
     192: invokevirtual #211                // Method org/apache/dubbo/config/RegistryConfig.getUsername:()Ljava/lang/String;
     195: invokevirtual #267                // Method org/apache/dubbo/config/MetadataReportConfig.setUsername:(Ljava/lang/String;)V
     198: aload_3
     199: invokevirtual #268                // Method org/apache/dubbo/config/MetadataReportConfig.getPassword:()Ljava/lang/String;
     202: ifnonnull     213
     205: aload_3
     206: aload_1
     207: invokevirtual #213                // Method org/apache/dubbo/config/RegistryConfig.getPassword:()Ljava/lang/String;
     210: invokevirtual #269                // Method org/apache/dubbo/config/MetadataReportConfig.setPassword:(Ljava/lang/String;)V
     213: aload_3
     214: invokevirtual #270                // Method org/apache/dubbo/config/MetadataReportConfig.getTimeout:()Ljava/lang/Integer;
     217: ifnonnull     228
     220: aload_3
     221: aload_1
     222: invokevirtual #215                // Method org/apache/dubbo/config/RegistryConfig.getTimeout:()Ljava/lang/Integer;
     225: invokevirtual #271                // Method org/apache/dubbo/config/MetadataReportConfig.setTimeout:(Ljava/lang/Integer;)V
     228: aload_3
     229: areturn

  private java.lang.String getRegistryCompatibleAddress(org.apache.dubbo.config.RegistryConfig);
    Code:
       0: aload_1
       1: invokevirtual #185                // Method org/apache/dubbo/config/RegistryConfig.getAddress:()Ljava/lang/String;
       4: astore_2
       5: getstatic     #272                // Field org/apache/dubbo/common/constants/CommonConstants.REGISTRY_SPLIT_PATTERN:Ljava/util/regex/Pattern;
       8: aload_2
       9: invokevirtual #273                // Method java/util/regex/Pattern.split:(Ljava/lang/CharSequence;)[Ljava/lang/String;
      12: astore_3
      13: aload_3
      14: invokestatic  #274                // Method org/apache/dubbo/common/utils/ArrayUtils.isEmpty:([Ljava/lang/Object;)Z
      17: ifeq          31
      20: new           #115                // class java/lang/IllegalStateException
      23: dup
      24: ldc_w         #275                // String Invalid registry address found.
      27: invokespecial #117                // Method java/lang/IllegalStateException."<init>":(Ljava/lang/String;)V
      30: athrow
      31: aload_3
      32: iconst_0
      33: aaload
      34: astore        4
      36: new           #68                 // class java/lang/StringBuilder
      39: dup
      40: invokespecial #69                 // Method java/lang/StringBuilder."<init>":()V
      43: astore        5
      45: aload         4
      47: aload_1
      48: invokevirtual #186                // Method org/apache/dubbo/config/RegistryConfig.getScopeModel:()Lorg/apache/dubbo/rpc/model/ScopeModel;
      51: invokestatic  #187                // Method org/apache/dubbo/common/URL.valueOf:(Ljava/lang/String;Lorg/apache/dubbo/rpc/model/ScopeModel;)Lorg/apache/dubbo/common/URL;
      54: astore        6
      56: aload         6
      58: invokevirtual #276                // Method org/apache/dubbo/common/URL.getProtocol:()Ljava/lang/String;
      61: astore        7
      63: aload         7
      65: invokestatic  #277                // Method org/apache/dubbo/common/utils/StringUtils.isEmpty:(Ljava/lang/String;)Z
      68: ifeq          91
      71: aload_1
      72: invokevirtual #183                // Method org/apache/dubbo/config/RegistryConfig.getProtocol:()Ljava/lang/String;
      75: astore        8
      77: aload         5
      79: aload         8
      81: invokevirtual #71                 // Method java/lang/StringBuilder.append:(Ljava/lang/String;)Ljava/lang/StringBuilder;
      84: ldc_w         #278                // String ://
      87: invokevirtual #71                 // Method java/lang/StringBuilder.append:(Ljava/lang/String;)Ljava/lang/StringBuilder;
      90: pop
      91: aload         5
      93: aload         4
      95: invokevirtual #71                 // Method java/lang/StringBuilder.append:(Ljava/lang/String;)Ljava/lang/StringBuilder;
      98: pop
      99: aload         5
     101: invokevirtual #73                 // Method java/lang/StringBuilder.toString:()Ljava/lang/String;
     104: areturn

  public java.util.concurrent.Future start();
    Code:
       0: aload_0
       1: getfield      #14                 // Field startLock:Ljava/lang/Object;
       4: dup
       5: astore_1
       6: monitorenter
       7: aload_0
       8: invokevirtual #279                // Method isStopping:()Z
      11: ifne          28
      14: aload_0
      15: invokevirtual #280                // Method isStopped:()Z
      18: ifne          28
      21: aload_0
      22: invokevirtual #281                // Method isFailed:()Z
      25: ifeq          59
      28: new           #115                // class java/lang/IllegalStateException
      31: dup
      32: new           #68                 // class java/lang/StringBuilder
      35: dup
      36: invokespecial #69                 // Method java/lang/StringBuilder."<init>":()V
      39: aload_0
      40: invokevirtual #70                 // Method getIdentifier:()Ljava/lang/String;
      43: invokevirtual #71                 // Method java/lang/StringBuilder.append:(Ljava/lang/String;)Ljava/lang/StringBuilder;
      46: ldc_w         #282                // String  is stopping or stopped, can not start again
      49: invokevirtual #71                 // Method java/lang/StringBuilder.append:(Ljava/lang/String;)Ljava/lang/StringBuilder;
      52: invokevirtual #73                 // Method java/lang/StringBuilder.toString:()Ljava/lang/String;
      55: invokespecial #117                // Method java/lang/IllegalStateException."<init>":(Ljava/lang/String;)V
      58: athrow
      59: aload_0
      60: invokespecial #283                // Method hasPendingModule:()Z
      63: istore_2
      64: aload_0
      65: invokevirtual #284                // Method isStarting:()Z
      68: ifeq          86
      71: iload_2
      72: ifeq          79
      75: aload_0
      76: invokespecial #285                // Method startModules:()V
      79: aload_0
      80: getfield      #286                // Field startFuture:Ljava/util/concurrent/CompletableFuture;
      83: aload_1
      84: monitorexit
      85: areturn
      86: aload_0
      87: invokevirtual #287                // Method isStarted:()Z
      90: ifeq          107
      93: iload_2
      94: ifne          107
      97: iconst_0
      98: invokestatic  #157                // Method java/lang/Boolean.valueOf:(Z)Ljava/lang/Boolean;
     101: invokestatic  #288                // Method java/util/concurrent/CompletableFuture.completedFuture:(Ljava/lang/Object;)Ljava/util/concurrent/CompletableFuture;
     104: aload_1
     105: monitorexit
     106: areturn
     107: aload_0
     108: invokespecial #289                // Method onStarting:()V
     111: aload_0
     112: invokevirtual #290                // Method initialize:()V
     115: aload_0
     116: invokespecial #291                // Method doStart:()V
     119: goto          153
     122: astore_2
     123: aload_0
     124: new           #68                 // class java/lang/StringBuilder
     127: dup
     128: invokespecial #69                 // Method java/lang/StringBuilder."<init>":()V
     131: aload_0
     132: invokevirtual #70                 // Method getIdentifier:()Ljava/lang/String;
     135: invokevirtual #71                 // Method java/lang/StringBuilder.append:(Ljava/lang/String;)Ljava/lang/StringBuilder;
     138: ldc_w         #293                // String  start failure
     141: invokevirtual #71                 // Method java/lang/StringBuilder.append:(Ljava/lang/String;)Ljava/lang/StringBuilder;
     144: invokevirtual #73                 // Method java/lang/StringBuilder.toString:()Ljava/lang/String;
     147: aload_2
     148: invokespecial #294                // Method onFailed:(Ljava/lang/String;Ljava/lang/Throwable;)V
     151: aload_2
     152: athrow
     153: aload_0
     154: getfield      #286                // Field startFuture:Ljava/util/concurrent/CompletableFuture;
     157: aload_1
     158: monitorexit
     159: areturn
     160: astore_3
     161: aload_1
     162: monitorexit
     163: aload_3
     164: athrow
    Exception table:
       from    to  target type
          59    83   122   Class java/lang/Throwable
          86   104   122   Class java/lang/Throwable
         107   119   122   Class java/lang/Throwable
           7    85   160   any
          86   106   160   any
         107   159   160   any
         160   163   160   any

  private boolean hasPendingModule();
    Code:
       0: iconst_0
       1: istore_1
       2: aload_0
       3: getfield      #21                 // Field applicationModel:Lorg/apache/dubbo/rpc/model/ApplicationModel;
       6: invokevirtual #77                 // Method org/apache/dubbo/rpc/model/ApplicationModel.getModuleModels:()Ljava/util/List;
       9: invokeinterface #78,  1           // InterfaceMethod java/util/List.iterator:()Ljava/util/Iterator;
      14: astore_2
      15: aload_2
      16: invokeinterface #43,  1           // InterfaceMethod java/util/Iterator.hasNext:()Z
      21: ifeq          54
      24: aload_2
      25: invokeinterface #44,  1           // InterfaceMethod java/util/Iterator.next:()Ljava/lang/Object;
      30: checkcast     #79                 // class org/apache/dubbo/rpc/model/ModuleModel
      33: astore_3
      34: aload_3
      35: invokevirtual #80                 // Method org/apache/dubbo/rpc/model/ModuleModel.getDeployer:()Lorg/apache/dubbo/common/deploy/ModuleDeployer;
      38: invokeinterface #295,  1          // InterfaceMethod org/apache/dubbo/common/deploy/ModuleDeployer.isPending:()Z
      43: ifeq          51
      46: iconst_1
      47: istore_1
      48: goto          54
      51: goto          15
      54: iload_1
      55: ireturn

  public java.util.concurrent.Future getStartFuture();
    Code:
       0: aload_0
       1: getfield      #286                // Field startFuture:Ljava/util/concurrent/CompletableFuture;
       4: areturn

  private void doStart();
    Code:
       0: aload_0
       1: invokespecial #285                // Method startModules:()V
       4: return

  private void startModules();
    Code:
       0: aload_0
       1: invokevirtual #296                // Method prepareInternalModule:()V
       4: aload_0
       5: getfield      #21                 // Field applicationModel:Lorg/apache/dubbo/rpc/model/ApplicationModel;
       8: invokevirtual #77                 // Method org/apache/dubbo/rpc/model/ApplicationModel.getModuleModels:()Ljava/util/List;
      11: invokeinterface #78,  1           // InterfaceMethod java/util/List.iterator:()Ljava/util/Iterator;
      16: astore_1
      17: aload_1
      18: invokeinterface #43,  1           // InterfaceMethod java/util/Iterator.hasNext:()Z
      23: ifeq          61
      26: aload_1
      27: invokeinterface #44,  1           // InterfaceMethod java/util/Iterator.next:()Ljava/lang/Object;
      32: checkcast     #79                 // class org/apache/dubbo/rpc/model/ModuleModel
      35: astore_2
      36: aload_2
      37: invokevirtual #80                 // Method org/apache/dubbo/rpc/model/ModuleModel.getDeployer:()Lorg/apache/dubbo/common/deploy/ModuleDeployer;
      40: invokeinterface #295,  1          // InterfaceMethod org/apache/dubbo/common/deploy/ModuleDeployer.isPending:()Z
      45: ifeq          58
      48: aload_2
      49: invokevirtual #80                 // Method org/apache/dubbo/rpc/model/ModuleModel.getDeployer:()Lorg/apache/dubbo/common/deploy/ModuleDeployer;
      52: invokeinterface #297,  1          // InterfaceMethod org/apache/dubbo/common/deploy/ModuleDeployer.start:()Ljava/util/concurrent/Future;
      57: pop
      58: goto          17
      61: return

  public void prepareApplicationInstance();
    Code:
       0: aload_0
       1: getfield      #9                  // Field hasPreparedApplicationInstance:Ljava/util/concurrent/atomic/AtomicBoolean;
       4: invokevirtual #298                // Method java/util/concurrent/atomic/AtomicBoolean.get:()Z
       7: ifeq          11
      10: return
      11: aload_0
      12: invokespecial #299                // Method exportMetricsService:()V
      15: aload_0
      16: invokespecial #300                // Method isRegisterConsumerInstance:()Z
      19: ifeq          42
      22: aload_0
      23: invokespecial #301                // Method exportMetadataService:()V
      26: aload_0
      27: getfield      #9                  // Field hasPreparedApplicationInstance:Ljava/util/concurrent/atomic/AtomicBoolean;
      30: iconst_0
      31: iconst_1
      32: invokevirtual #302                // Method java/util/concurrent/atomic/AtomicBoolean.compareAndSet:(ZZ)Z
      35: ifeq          42
      38: aload_0
      39: invokespecial #303                // Method registerServiceInstance:()V
      42: return

  public void prepareInternalModule();
    Code:
       0: aload_0
       1: getfield      #10                 // Field hasPreparedInternalModule:Z
       4: ifeq          8
       7: return
       8: aload_0
       9: getfield      #16                 // Field internalModuleLock:Ljava/lang/Object;
      12: dup
      13: astore_1
      14: monitorenter
      15: aload_0
      16: getfield      #10                 // Field hasPreparedInternalModule:Z
      19: ifeq          25
      22: aload_1
      23: monitorexit
      24: return
      25: aload_0
      26: getfield      #21                 // Field applicationModel:Lorg/apache/dubbo/rpc/model/ApplicationModel;
      29: invokevirtual #304                // Method org/apache/dubbo/rpc/model/ApplicationModel.getInternalModule:()Lorg/apache/dubbo/rpc/model/ModuleModel;
      32: invokevirtual #80                 // Method org/apache/dubbo/rpc/model/ModuleModel.getDeployer:()Lorg/apache/dubbo/common/deploy/ModuleDeployer;
      35: astore_2
      36: aload_2
      37: invokeinterface #305,  1          // InterfaceMethod org/apache/dubbo/common/deploy/ModuleDeployer.isStarted:()Z
      42: ifne          118
      45: aload_2
      46: invokeinterface #297,  1          // InterfaceMethod org/apache/dubbo/common/deploy/ModuleDeployer.start:()Ljava/util/concurrent/Future;
      51: astore_3
      52: aload_3
      53: ldc2_w        #306                // long 5l
      56: getstatic     #308                // Field java/util/concurrent/TimeUnit.SECONDS:Ljava/util/concurrent/TimeUnit;
      59: invokeinterface #309,  4          // InterfaceMethod java/util/concurrent/Future.get:(JLjava/util/concurrent/TimeUnit;)Ljava/lang/Object;
      64: pop
      65: aload_0
      66: iconst_1
      67: putfield      #10                 // Field hasPreparedInternalModule:Z
      70: goto          118
      73: astore        4
      75: getstatic     #66                 // Field logger:Lorg/apache/dubbo/common/logger/ErrorTypeAwareLogger;
      78: ldc_w         #311                // String 5-14
      81: ldc_w         #312                // String
      84: ldc_w         #312                // String
      87: new           #68                 // class java/lang/StringBuilder
      90: dup
      91: invokespecial #69                 // Method java/lang/StringBuilder."<init>":()V
      94: ldc_w         #313                // String wait for internal module startup failed:
      97: invokevirtual #71                 // Method java/lang/StringBuilder.append:(Ljava/lang/String;)Ljava/lang/StringBuilder;
     100: aload         4
     102: invokevirtual #314                // Method java/lang/Exception.getMessage:()Ljava/lang/String;
     105: invokevirtual #71                 // Method java/lang/StringBuilder.append:(Ljava/lang/String;)Ljava/lang/StringBuilder;
     108: invokevirtual #73                 // Method java/lang/StringBuilder.toString:()Ljava/lang/String;
     111: aload         4
     113: invokeinterface #315,  6          // InterfaceMethod org/apache/dubbo/common/logger/ErrorTypeAwareLogger.warn:(Ljava/lang/String;Ljava/lang/String;Ljava/lang/String;Ljava/lang/String;Ljava/lang/Throwable;)V
     118: aload_1
     119: monitorexit
     120: goto          130
     123: astore        5
     125: aload_1
     126: monitorexit
     127: aload         5
     129: athrow
     130: return
    Exception table:
       from    to  target type
          52    70    73   Class java/lang/Exception
          15    24   123   any
          25   120   123   any
         123   127   123   any

  private void exportMetricsService();
    Code:
       0: aload_0
       1: getfield      #21                 // Field applicationModel:Lorg/apache/dubbo/rpc/model/ApplicationModel;
       4: invokevirtual #22                 // Method org/apache/dubbo/rpc/model/ApplicationModel.getApplicationConfigManager:()Lorg/apache/dubbo/config/context/ConfigManager;
       7: invokevirtual #149                // Method org/apache/dubbo/config/context/ConfigManager.getMetrics:()Ljava/util/Optional;
      10: invokedynamic #316,  0            // InvokeDynamic #10:apply:()Ljava/util/function/Function;
      15: invokevirtual #317                // Method java/util/Optional.map:(Ljava/util/function/Function;)Ljava/util/Optional;
      18: iconst_1
      19: invokestatic  #157                // Method java/lang/Boolean.valueOf:(Z)Ljava/lang/Boolean;
      22: invokevirtual #153                // Method java/util/Optional.orElse:(Ljava/lang/Object;)Ljava/lang/Object;
      25: checkcast     #162                // class java/lang/Boolean
      28: invokevirtual #163                // Method java/lang/Boolean.booleanValue:()Z
      31: istore_1
      32: iload_1
      33: ifeq          71
      36: aload_0
      37: getfield      #146                // Field metricsServiceExporter:Lorg/apache/dubbo/metrics/service/MetricsServiceExporter;
      40: invokeinterface #318,  1          // InterfaceMethod org/apache/dubbo/metrics/service/MetricsServiceExporter.export:()Lorg/apache/dubbo/metrics/service/MetricsServiceExporter;
      45: pop
      46: goto          71
      49: astore_2
      50: getstatic     #66                 // Field logger:Lorg/apache/dubbo/common/logger/ErrorTypeAwareLogger;
      53: ldc_w         #319                // String 0-13
      56: ldc_w         #312                // String
      59: ldc_w         #312                // String
      62: ldc_w         #320                // String exportMetricsService an exception occurred when handle starting event
      65: aload_2
      66: invokeinterface #321,  6          // InterfaceMethod org/apache/dubbo/common/logger/ErrorTypeAwareLogger.error:(Ljava/lang/String;Ljava/lang/String;Ljava/lang/String;Ljava/lang/String;Ljava/lang/Throwable;)V
      71: return
    Exception table:
       from    to  target type
          36    46    49   Class java/lang/Exception

  private void unexportMetricsService();
    Code:
       0: aload_0
       1: getfield      #146                // Field metricsServiceExporter:Lorg/apache/dubbo/metrics/service/MetricsServiceExporter;
       4: ifnull        21
       7: aload_0
       8: getfield      #146                // Field metricsServiceExporter:Lorg/apache/dubbo/metrics/service/MetricsServiceExporter;
      11: invokeinterface #322,  1          // InterfaceMethod org/apache/dubbo/metrics/service/MetricsServiceExporter.unexport:()Lorg/apache/dubbo/metrics/service/MetricsServiceExporter;
      16: pop
      17: goto          21
      20: astore_1
      21: return
    Exception table:
       from    to  target type
           7    17    20   Class java/lang/Exception

  private boolean hasExportedServices();
    Code:
       0: aload_0
       1: getfield      #21                 // Field applicationModel:Lorg/apache/dubbo/rpc/model/ApplicationModel;
       4: invokevirtual #77                 // Method org/apache/dubbo/rpc/model/ApplicationModel.getModuleModels:()Ljava/util/List;
       7: invokeinterface #78,  1           // InterfaceMethod java/util/List.iterator:()Ljava/util/Iterator;
      12: astore_1
      13: aload_1
      14: invokeinterface #43,  1           // InterfaceMethod java/util/Iterator.hasNext:()Z
      19: ifeq          50
      22: aload_1
      23: invokeinterface #44,  1           // InterfaceMethod java/util/Iterator.next:()Ljava/lang/Object;
      28: checkcast     #79                 // class org/apache/dubbo/rpc/model/ModuleModel
      31: astore_2
      32: aload_2
      33: invokevirtual #323                // Method org/apache/dubbo/rpc/model/ModuleModel.getConfigManager:()Lorg/apache/dubbo/config/context/ModuleConfigManager;
      36: invokevirtual #324                // Method org/apache/dubbo/config/context/ModuleConfigManager.getServices:()Ljava/util/Collection;
      39: invokestatic  #100                // Method org/apache/dubbo/common/utils/CollectionUtils.isNotEmpty:(Ljava/util/Collection;)Z
      42: ifeq          47
      45: iconst_1
      46: ireturn
      47: goto          13
      50: iconst_0
      51: ireturn

  public boolean isBackground();
    Code:
       0: aload_0
       1: getfield      #21                 // Field applicationModel:Lorg/apache/dubbo/rpc/model/ApplicationModel;
       4: invokevirtual #77                 // Method org/apache/dubbo/rpc/model/ApplicationModel.getModuleModels:()Ljava/util/List;
       7: invokeinterface #78,  1           // InterfaceMethod java/util/List.iterator:()Ljava/util/Iterator;
      12: astore_1
      13: aload_1
      14: invokeinterface #43,  1           // InterfaceMethod java/util/Iterator.hasNext:()Z
      19: ifeq          49
      22: aload_1
      23: invokeinterface #44,  1           // InterfaceMethod java/util/Iterator.next:()Ljava/lang/Object;
      28: checkcast     #79                 // class org/apache/dubbo/rpc/model/ModuleModel
      31: astore_2
      32: aload_2
      33: invokevirtual #80                 // Method org/apache/dubbo/rpc/model/ModuleModel.getDeployer:()Lorg/apache/dubbo/common/deploy/ModuleDeployer;
      36: invokeinterface #325,  1          // InterfaceMethod org/apache/dubbo/common/deploy/ModuleDeployer.isBackground:()Z
      41: ifeq          46
      44: iconst_1
      45: ireturn
      46: goto          13
      49: iconst_0
      50: ireturn

  private org.apache.dubbo.common.config.configcenter.DynamicConfiguration prepareEnvironment(org.apache.dubbo.config.ConfigCenterConfig);
    Code:
       0: aload_1
       1: invokevirtual #97                 // Method org/apache/dubbo/config/ConfigCenterConfig.isValid:()Z
       4: ifeq          286
       7: aload_1
       8: iconst_1
       9: invokevirtual #326                // Method org/apache/dubbo/config/ConfigCenterConfig.checkOrUpdateInitialized:(Z)Z
      12: ifne          17
      15: aconst_null
      16: areturn
      17: aload_0
      18: aload_1
      19: invokevirtual #327                // Method org/apache/dubbo/config/ConfigCenterConfig.toUrl:()Lorg/apache/dubbo/common/URL;
      22: invokespecial #328                // Method getDynamicConfiguration:(Lorg/apache/dubbo/common/URL;)Lorg/apache/dubbo/common/config/configcenter/DynamicConfiguration;
      25: astore_2
      26: goto          77
      29: astore_3
      30: aload_1
      31: invokevirtual #329                // Method org/apache/dubbo/config/ConfigCenterConfig.isCheck:()Ljava/lang/Boolean;
      34: invokevirtual #163                // Method java/lang/Boolean.booleanValue:()Z
      37: ifne          68
      40: getstatic     #66                 // Field logger:Lorg/apache/dubbo/common/logger/ErrorTypeAwareLogger;
      43: ldc_w         #330                // String 5-22
      46: ldc_w         #312                // String
      49: ldc_w         #312                // String
      52: ldc_w         #331                // String The configuration center failed to initialize
      55: aload_3
      56: invokeinterface #315,  6          // InterfaceMethod org/apache/dubbo/common/logger/ErrorTypeAwareLogger.warn:(Ljava/lang/String;Ljava/lang/String;Ljava/lang/String;Ljava/lang/String;Ljava/lang/Throwable;)V
      61: aload_1
      62: iconst_0
      63: invokevirtual #332                // Method org/apache/dubbo/config/ConfigCenterConfig.setInitialized:(Z)V
      66: aconst_null
      67: areturn
      68: new           #115                // class java/lang/IllegalStateException
      71: dup
      72: aload_3
      73: invokespecial #333                // Method java/lang/IllegalStateException."<init>":(Ljava/lang/Throwable;)V
      76: athrow
      77: aload_0
      78: invokevirtual #334                // Method getApplicationModel:()Lorg/apache/dubbo/rpc/model/ApplicationModel;
      81: astore_3
      82: aload_1
      83: invokevirtual #335                // Method org/apache/dubbo/config/ConfigCenterConfig.getConfigFile:()Ljava/lang/String;
      86: invokestatic  #206                // Method org/apache/dubbo/common/utils/StringUtils.isNotEmpty:(Ljava/lang/String;)Z
      89: ifeq          284
      92: aload_2
      93: aload_1
      94: invokevirtual #335                // Method org/apache/dubbo/config/ConfigCenterConfig.getConfigFile:()Ljava/lang/String;
      97: aload_1
      98: invokevirtual #336                // Method org/apache/dubbo/config/ConfigCenterConfig.getGroup:()Ljava/lang/String;
     101: invokeinterface #337,  3          // InterfaceMethod org/apache/dubbo/common/config/configcenter/DynamicConfiguration.getProperties:(Ljava/lang/String;Ljava/lang/String;)Ljava/lang/String;
     106: astore        4
     108: aload_0
     109: invokespecial #53                 // Method getApplication:()Lorg/apache/dubbo/config/ApplicationConfig;
     112: invokevirtual #338                // Method org/apache/dubbo/config/ApplicationConfig.getName:()Ljava/lang/String;
     115: astore        5
     117: aconst_null
     118: astore        6
     120: aconst_null
     121: astore        7
     123: aload         5
     125: invokestatic  #206                // Method org/apache/dubbo/common/utils/StringUtils.isNotEmpty:(Ljava/lang/String;)Z
     128: ifeq          166
     131: aload_1
     132: invokevirtual #339                // Method org/apache/dubbo/config/ConfigCenterConfig.getAppConfigFile:()Ljava/lang/String;
     135: invokestatic  #206                // Method org/apache/dubbo/common/utils/StringUtils.isNotEmpty:(Ljava/lang/String;)Z
     138: ifeq          148
     141: aload_1
     142: invokevirtual #339                // Method org/apache/dubbo/config/ConfigCenterConfig.getAppConfigFile:()Ljava/lang/String;
     145: goto          152
     148: aload_1
     149: invokevirtual #335                // Method org/apache/dubbo/config/ConfigCenterConfig.getConfigFile:()Ljava/lang/String;
     152: astore        7
     154: aload_2
     155: aload         7
     157: aload         5
     159: invokeinterface #337,  3          // InterfaceMethod org/apache/dubbo/common/config/configcenter/DynamicConfiguration.getProperties:(Ljava/lang/String;Ljava/lang/String;)Ljava/lang/String;
     164: astore        6
     166: aload         4
     168: invokestatic  #340                // Method org/apache/dubbo/common/config/ConfigurationUtils.parseProperties:(Ljava/lang/String;)Ljava/util/Map;
     171: astore        8
     173: aload         6
     175: invokestatic  #340                // Method org/apache/dubbo/common/config/ConfigurationUtils.parseProperties:(Ljava/lang/String;)Ljava/util/Map;
     178: astore        9
     180: aload_0
     181: getfield      #25                 // Field environment:Lorg/apache/dubbo/common/config/Environment;
     184: aload         8
     186: invokevirtual #104                // Method org/apache/dubbo/common/config/Environment.updateExternalConfigMap:(Ljava/util/Map;)V
     189: aload_0
     190: getfield      #25                 // Field environment:Lorg/apache/dubbo/common/config/Environment;
     193: aload         9
     195: invokevirtual #106                // Method org/apache/dubbo/common/config/Environment.updateAppExternalConfigMap:(Ljava/util/Map;)V
     198: aload_3
     199: aload_1
     200: invokevirtual #335                // Method org/apache/dubbo/config/ConfigCenterConfig.getConfigFile:()Ljava/lang/String;
     203: aload_1
     204: invokevirtual #336                // Method org/apache/dubbo/config/ConfigCenterConfig.getGroup:()Ljava/lang/String;
     207: aload_1
     208: invokevirtual #341                // Method org/apache/dubbo/config/ConfigCenterConfig.getProtocol:()Ljava/lang/String;
     211: getstatic     #342                // Field org/apache/dubbo/common/config/configcenter/ConfigChangeType.ADDED:Lorg/apache/dubbo/common/config/configcenter/ConfigChangeType;
     214: invokevirtual #343                // Method org/apache/dubbo/common/config/configcenter/ConfigChangeType.name:()Ljava/lang/String;
     217: aload         8
     219: invokeinterface #344,  1          // InterfaceMethod java/util/Map.size:()I
     224: invokestatic  #345                // Method org/apache/dubbo/metrics/config/event/ConfigCenterEvent.toChangeEvent:(Lorg/apache/dubbo/rpc/model/ApplicationModel;Ljava/lang/String;Ljava/lang/String;Ljava/lang/String;Ljava/lang/String;I)Lorg/apache/dubbo/metrics/config/event/ConfigCenterEvent;
     227: invokestatic  #346                // Method org/apache/dubbo/metrics/event/MetricsEventBus.publish:(Lorg/apache/dubbo/metrics/event/MetricsEvent;)V
     230: aload         5
     232: invokestatic  #206                // Method org/apache/dubbo/common/utils/StringUtils.isNotEmpty:(Ljava/lang/String;)Z
     235: ifeq          266
     238: aload_3
     239: aload         7
     241: aload         5
     243: aload_1
     244: invokevirtual #341                // Method org/apache/dubbo/config/ConfigCenterConfig.getProtocol:()Ljava/lang/String;
     247: getstatic     #342                // Field org/apache/dubbo/common/config/configcenter/ConfigChangeType.ADDED:Lorg/apache/dubbo/common/config/configcenter/ConfigChangeType;
     250: invokevirtual #343                // Method org/apache/dubbo/common/config/configcenter/ConfigChangeType.name:()Ljava/lang/String;
     253: aload         9
     255: invokeinterface #344,  1          // InterfaceMethod java/util/Map.size:()I
     260: invokestatic  #345                // Method org/apache/dubbo/metrics/config/event/ConfigCenterEvent.toChangeEvent:(Lorg/apache/dubbo/rpc/model/ApplicationModel;Ljava/lang/String;Ljava/lang/String;Ljava/lang/String;Ljava/lang/String;I)Lorg/apache/dubbo/metrics/config/event/ConfigCenterEvent;
     263: invokestatic  #346                // Method org/apache/dubbo/metrics/event/MetricsEventBus.publish:(Lorg/apache/dubbo/metrics/event/MetricsEvent;)V
     266: goto          284
     269: astore        8
     271: new           #115                // class java/lang/IllegalStateException
     274: dup
     275: ldc_w         #348                // String Failed to parse configurations from Config Center.
     278: aload         8
     280: invokespecial #349                // Method java/lang/IllegalStateException."<init>":(Ljava/lang/String;Ljava/lang/Throwable;)V
     283: athrow
     284: aload_2
     285: areturn
     286: aconst_null
     287: areturn
    Exception table:
       from    to  target type
          17    26    29   Class java/lang/Exception
         166   266   269   Class java/io/IOException

  private org.apache.dubbo.common.config.configcenter.DynamicConfiguration getDynamicConfiguration(org.apache.dubbo.common.URL);
    Code:
       0: aload_1
       1: invokevirtual #276                // Method org/apache/dubbo/common/URL.getProtocol:()Ljava/lang/String;
       4: astore_2
       5: aload_0
       6: getfield      #21                 // Field applicationModel:Lorg/apache/dubbo/rpc/model/ApplicationModel;
       9: aload_2
      10: invokestatic  #350                // Method org/apache/dubbo/common/config/ConfigurationUtils.getDynamicConfigurationFactory:(Lorg/apache/dubbo/common/extension/ExtensionAccessor;Ljava/lang/String;)Lorg/apache/dubbo/common/config/configcenter/DynamicConfigurationFactory;
      13: astore_3
      14: aload_3
      15: aload_1
      16: invokeinterface #351,  2          // InterfaceMethod org/apache/dubbo/common/config/configcenter/DynamicConfigurationFactory.getDynamicConfiguration:(Lorg/apache/dubbo/common/URL;)Lorg/apache/dubbo/common/config/configcenter/DynamicConfiguration;
      21: areturn

  private void registerServiceInstance();
    Code:
       0: aload_0
       1: iconst_1
       2: putfield      #352                // Field registered:Z
       5: aload_0
       6: getfield      #21                 // Field applicationModel:Lorg/apache/dubbo/rpc/model/ApplicationModel;
       9: invokestatic  #353                // Method org/apache/dubbo/metrics/registry/event/RegistryEvent.toRegisterEvent:(Lorg/apache/dubbo/rpc/model/ApplicationModel;)Lorg/apache/dubbo/metrics/registry/event/RegistryEvent;
      12: aload_0
      13: invokedynamic #354,  0            // InvokeDynamic #11:get:(Lorg/apache/dubbo/config/deploy/DefaultApplicationDeployer;)Ljava/util/function/Supplier;
      18: invokestatic  #355                // Method org/apache/dubbo/metrics/event/MetricsEventBus.post:(Lorg/apache/dubbo/metrics/event/MetricsEvent;Ljava/util/function/Supplier;)Ljava/lang/Object;
      21: pop
      22: goto          47
      25: astore_1
      26: getstatic     #66                 // Field logger:Lorg/apache/dubbo/common/logger/ErrorTypeAwareLogger;
      29: ldc_w         #356                // String 5-11
      32: ldc_w         #357                // String configuration server disconnected
      35: ldc_w         #312                // String
      38: ldc_w         #358                // String Register instance error.
      41: aload_1
      42: invokeinterface #321,  6          // InterfaceMethod org/apache/dubbo/common/logger/ErrorTypeAwareLogger.error:(Ljava/lang/String;Ljava/lang/String;Ljava/lang/String;Ljava/lang/String;Ljava/lang/Throwable;)V
      47: aload_0
      48: getfield      #352                // Field registered:Z
      51: ifeq          94
      54: aload_0
      55: aload_0
      56: getfield      #33                 // Field frameworkExecutorRepository:Lorg/apache/dubbo/common/threadpool/manager/FrameworkExecutorRepository;
      59: invokevirtual #359                // Method org/apache/dubbo/common/threadpool/manager/FrameworkExecutorRepository.getSharedScheduledExecutor:()Ljava/util/concurrent/ScheduledExecutorService;
      62: aload_0
      63: invokedynamic #360,  0            // InvokeDynamic #12:run:(Lorg/apache/dubbo/config/deploy/DefaultApplicationDeployer;)Ljava/lang/Runnable;
      68: lconst_0
      69: aload_0
      70: getfield      #21                 // Field applicationModel:Lorg/apache/dubbo/rpc/model/ApplicationModel;
      73: ldc_w         #361                // String dubbo.application.metadata.publish.delay
      76: sipush        1000
      79: invokestatic  #362                // Method org/apache/dubbo/common/config/ConfigurationUtils.get:(Lorg/apache/dubbo/rpc/model/ScopeModel;Ljava/lang/String;I)I
      82: i2l
      83: getstatic     #363                // Field java/util/concurrent/TimeUnit.MILLISECONDS:Ljava/util/concurrent/TimeUnit;
      86: invokeinterface #364,  7          // InterfaceMethod java/util/concurrent/ScheduledExecutorService.scheduleWithFixedDelay:(Ljava/lang/Runnable;JJLjava/util/concurrent/TimeUnit;)Ljava/util/concurrent/ScheduledFuture;
      91: putfield      #365                // Field asyncMetadataFuture:Ljava/util/concurrent/ScheduledFuture;
      94: return
    Exception table:
       from    to  target type
           0    22    25   Class java/lang/Exception

  public void increaseServiceRefreshCount();
    Code:
       0: aload_0
       1: getfield      #20                 // Field serviceRefreshState:Ljava/util/concurrent/atomic/AtomicInteger;
       4: invokevirtual #366                // Method java/util/concurrent/atomic/AtomicInteger.incrementAndGet:()I
       7: pop
       8: return

  public void decreaseServiceRefreshCount();
    Code:
       0: aload_0
       1: getfield      #20                 // Field serviceRefreshState:Ljava/util/concurrent/atomic/AtomicInteger;
       4: invokevirtual #367                // Method java/util/concurrent/atomic/AtomicInteger.decrementAndGet:()I
       7: pop
       8: return

  private void unregisterServiceInstance();
    Code:
       0: aload_0
       1: getfield      #352                // Field registered:Z
       4: ifeq          14
       7: aload_0
       8: getfield      #21                 // Field applicationModel:Lorg/apache/dubbo/rpc/model/ApplicationModel;
      11: invokestatic  #368                // Method org/apache/dubbo/registry/client/metadata/ServiceInstanceMetadataUtils.unregisterMetadataAndInstance:(Lorg/apache/dubbo/rpc/model/ApplicationModel;)V
      14: return

  public void stop();
    Code:
       0: aload_0
       1: getfield      #21                 // Field applicationModel:Lorg/apache/dubbo/rpc/model/ApplicationModel;
       4: invokevirtual #369                // Method org/apache/dubbo/rpc/model/ApplicationModel.destroy:()V
       7: return

  public void preDestroy();
    Code:
       0: aload_0
       1: getfield      #15                 // Field destroyLock:Ljava/lang/Object;
       4: dup
       5: astore_1
       6: monitorenter
       7: aload_0
       8: invokevirtual #279                // Method isStopping:()Z
      11: ifne          21
      14: aload_0
      15: invokevirtual #280                // Method isStopped:()Z
      18: ifeq          24
      21: aload_1
      22: monitorexit
      23: return
      24: aload_0
      25: invokespecial #370                // Method onStopping:()V
      28: aload_0
      29: invokespecial #371                // Method offline:()V
      32: aload_0
      33: invokespecial #372                // Method unregisterServiceInstance:()V
      36: aload_0
      37: invokespecial #373                // Method unexportMetricsService:()V
      40: aload_0
      41: invokespecial #374                // Method unRegisterShutdownHook:()V
      44: aload_0
      45: getfield      #365                // Field asyncMetadataFuture:Ljava/util/concurrent/ScheduledFuture;
      48: ifnull        62
      51: aload_0
      52: getfield      #365                // Field asyncMetadataFuture:Ljava/util/concurrent/ScheduledFuture;
      55: iconst_1
      56: invokeinterface #375,  2          // InterfaceMethod java/util/concurrent/ScheduledFuture.cancel:(Z)Z
      61: pop
      62: aload_1
      63: monitorexit
      64: goto          72
      67: astore_2
      68: aload_1
      69: monitorexit
      70: aload_2
      71: athrow
      72: return
    Exception table:
       from    to  target type
           7    23    67   any
          24    64    67   any
          67    70    67   any

  private void offline();
    Code:
       0: aload_0
       1: getfield      #21                 // Field applicationModel:Lorg/apache/dubbo/rpc/model/ApplicationModel;
       4: invokevirtual #77                 // Method org/apache/dubbo/rpc/model/ApplicationModel.getModuleModels:()Ljava/util/List;
       7: invokeinterface #78,  1           // InterfaceMethod java/util/List.iterator:()Ljava/util/Iterator;
      12: astore_1
      13: aload_1
      14: invokeinterface #43,  1           // InterfaceMethod java/util/Iterator.hasNext:()Z
      19: ifeq          135
      22: aload_1
      23: invokeinterface #44,  1           // InterfaceMethod java/util/Iterator.next:()Ljava/lang/Object;
      28: checkcast     #79                 // class org/apache/dubbo/rpc/model/ModuleModel
      31: astore_2
      32: aload_2
      33: invokevirtual #376                // Method org/apache/dubbo/rpc/model/ModuleModel.getServiceRepository:()Lorg/apache/dubbo/rpc/model/ModuleServiceRepository;
      36: astore_3
      37: aload_3
      38: invokevirtual #377                // Method org/apache/dubbo/rpc/model/ModuleServiceRepository.getExportedServices:()Ljava/util/List;
      41: astore        4
      43: aload         4
      45: invokeinterface #78,  1           // InterfaceMethod java/util/List.iterator:()Ljava/util/Iterator;
      50: astore        5
      52: aload         5
      54: invokeinterface #43,  1           // InterfaceMethod java/util/Iterator.hasNext:()Z
      59: ifeq          132
      62: aload         5
      64: invokeinterface #44,  1           // InterfaceMethod java/util/Iterator.next:()Ljava/lang/Object;
      69: checkcast     #378                // class org/apache/dubbo/rpc/model/ProviderModel
      72: astore        6
      74: aload         6
      76: invokevirtual #379                // Method org/apache/dubbo/rpc/model/ProviderModel.getStatedUrl:()Ljava/util/List;
      79: astore        7
      81: aload         7
      83: invokeinterface #78,  1           // InterfaceMethod java/util/List.iterator:()Ljava/util/Iterator;
      88: astore        8
      90: aload         8
      92: invokeinterface #43,  1           // InterfaceMethod java/util/Iterator.hasNext:()Z
      97: ifeq          129
     100: aload         8
     102: invokeinterface #44,  1           // InterfaceMethod java/util/Iterator.next:()Ljava/lang/Object;
     107: checkcast     #380                // class org/apache/dubbo/rpc/model/ProviderModel$RegisterStatedURL
     110: astore        9
     112: aload         9
     114: invokevirtual #381                // Method org/apache/dubbo/rpc/model/ProviderModel$RegisterStatedURL.isRegistered:()Z
     117: ifeq          126
     120: aload_0
     121: aload         9
     123: invokespecial #382                // Method doOffline:(Lorg/apache/dubbo/rpc/model/ProviderModel$RegisterStatedURL;)V
     126: goto          90
     129: goto          52
     132: goto          13
     135: goto          160
     138: astore_1
     139: getstatic     #66                 // Field logger:Lorg/apache/dubbo/common/logger/ErrorTypeAwareLogger;
     142: ldc_w         #383                // String 99-0
     145: ldc_w         #312                // String
     148: ldc_w         #312                // String
     151: ldc_w         #384                // String Exceptions occurred when unregister services.
     154: aload_1
     155: invokeinterface #321,  6          // InterfaceMethod org/apache/dubbo/common/logger/ErrorTypeAwareLogger.error:(Ljava/lang/String;Ljava/lang/String;Ljava/lang/String;Ljava/lang/String;Ljava/lang/Throwable;)V
     160: return
    Exception table:
       from    to  target type
           0   135   138   Class java/lang/Throwable

  private void doOffline(org.apache.dubbo.rpc.model.ProviderModel$RegisterStatedURL);
    Code:
       0: aload_1
       1: invokevirtual #385                // Method org/apache/dubbo/rpc/model/ProviderModel$RegisterStatedURL.getRegistryUrl:()Lorg/apache/dubbo/common/URL;
       4: invokevirtual #386                // Method org/apache/dubbo/common/URL.getOrDefaultApplicationModel:()Lorg/apache/dubbo/rpc/model/ApplicationModel;
       7: ldc_w         #387                // class org/apache/dubbo/registry/RegistryFactory
      10: invokevirtual #40                 // Method org/apache/dubbo/rpc/model/ApplicationModel.getExtensionLoader:(Ljava/lang/Class;)Lorg/apache/dubbo/common/extension/ExtensionLoader;
      13: invokevirtual #166                // Method org/apache/dubbo/common/extension/ExtensionLoader.getAdaptiveExtension:()Ljava/lang/Object;
      16: checkcast     #387                // class org/apache/dubbo/registry/RegistryFactory
      19: astore_2
      20: aload_2
      21: aload_1
      22: invokevirtual #385                // Method org/apache/dubbo/rpc/model/ProviderModel$RegisterStatedURL.getRegistryUrl:()Lorg/apache/dubbo/common/URL;
      25: invokeinterface #388,  2          // InterfaceMethod org/apache/dubbo/registry/RegistryFactory.getRegistry:(Lorg/apache/dubbo/common/URL;)Lorg/apache/dubbo/registry/Registry;
      30: astore_3
      31: aload_3
      32: aload_1
      33: invokevirtual #389                // Method org/apache/dubbo/rpc/model/ProviderModel$RegisterStatedURL.getProviderUrl:()Lorg/apache/dubbo/common/URL;
      36: invokeinterface #390,  2          // InterfaceMethod org/apache/dubbo/registry/Registry.unregister:(Lorg/apache/dubbo/common/URL;)V
      41: aload_1
      42: iconst_0
      43: invokevirtual #391                // Method org/apache/dubbo/rpc/model/ProviderModel$RegisterStatedURL.setRegistered:(Z)V
      46: return

  public void postDestroy();
    Code:
       0: aload_0
       1: getfield      #15                 // Field destroyLock:Ljava/lang/Object;
       4: dup
       5: astore_1
       6: monitorenter
       7: aload_0
       8: invokevirtual #280                // Method isStopped:()Z
      11: ifeq          17
      14: aload_1
      15: monitorexit
      16: return
      17: aload_0
      18: invokespecial #392                // Method destroyRegistries:()V
      21: aload_0
      22: invokespecial #393                // Method destroyMetadataReports:()V
      25: aload_0
      26: invokespecial #394                // Method executeShutdownCallbacks:()V
      29: aload_0
      30: invokespecial #395                // Method destroyExecutorRepository:()V
      33: aload_0
      34: invokespecial #396                // Method onStopped:()V
      37: goto          78
      40: astore_2
      41: new           #68                 // class java/lang/StringBuilder
      44: dup
      45: invokespecial #69                 // Method java/lang/StringBuilder."<init>":()V
      48: aload_0
      49: invokevirtual #70                 // Method getIdentifier:()Ljava/lang/String;
      52: invokevirtual #71                 // Method java/lang/StringBuilder.append:(Ljava/lang/String;)Ljava/lang/StringBuilder;
      55: ldc_w         #397                // String  an error occurred while stopping application:
      58: invokevirtual #71                 // Method java/lang/StringBuilder.append:(Ljava/lang/String;)Ljava/lang/StringBuilder;
      61: aload_2
      62: invokevirtual #398                // Method java/lang/Throwable.getMessage:()Ljava/lang/String;
      65: invokevirtual #71                 // Method java/lang/StringBuilder.append:(Ljava/lang/String;)Ljava/lang/StringBuilder;
      68: invokevirtual #73                 // Method java/lang/StringBuilder.toString:()Ljava/lang/String;
      71: astore_3
      72: aload_0
      73: aload_3
      74: aload_2
      75: invokespecial #294                // Method onFailed:(Ljava/lang/String;Ljava/lang/Throwable;)V
      78: aload_1
      79: monitorexit
      80: goto          90
      83: astore        4
      85: aload_1
      86: monitorexit
      87: aload         4
      89: athrow
      90: return
    Exception table:
       from    to  target type
          17    37    40   Class java/lang/Throwable
           7    16    83   any
          17    80    83   any
          83    87    83   any

  private void executeShutdownCallbacks();
    Code:
       0: aload_0
       1: getfield      #21                 // Field applicationModel:Lorg/apache/dubbo/rpc/model/ApplicationModel;
       4: invokevirtual #48                 // Method org/apache/dubbo/rpc/model/ApplicationModel.getBeanFactory:()Lorg/apache/dubbo/common/beans/factory/ScopeBeanFactory;
       7: ldc_w         #399                // class org/apache/dubbo/common/lang/ShutdownHookCallbacks
      10: invokevirtual #32                 // Method org/apache/dubbo/common/beans/factory/ScopeBeanFactory.getBean:(Ljava/lang/Class;)Ljava/lang/Object;
      13: checkcast     #399                // class org/apache/dubbo/common/lang/ShutdownHookCallbacks
      16: astore_1
      17: aload_1
      18: invokevirtual #400                // Method org/apache/dubbo/common/lang/ShutdownHookCallbacks.callback:()V
      21: return

  public void notifyModuleChanged(org.apache.dubbo.rpc.model.ModuleModel, org.apache.dubbo.common.deploy.DeployState);
    Code:
       0: aload_0
       1: aload_1
       2: aload_2
       3: invokevirtual #401                // Method checkState:(Lorg/apache/dubbo/rpc/model/ModuleModel;Lorg/apache/dubbo/common/deploy/DeployState;)V
       6: aload_0
       7: getfield      #13                 // Field stateLock:Ljava/lang/Object;
      10: dup
      11: astore_3
      12: monitorenter
      13: aload_0
      14: getfield      #13                 // Field stateLock:Ljava/lang/Object;
      17: invokevirtual #402                // Method java/lang/Object.notifyAll:()V
      20: aload_3
      21: monitorexit
      22: goto          32
      25: astore        4
      27: aload_3
      28: monitorexit
      29: aload         4
      31: athrow
      32: return
    Exception table:
       from    to  target type
          13    22    25   any
          25    29    25   any

  public void checkState(org.apache.dubbo.rpc.model.ModuleModel, org.apache.dubbo.common.deploy.DeployState);
    Code:
       0: aload_0
       1: getfield      #13                 // Field stateLock:Ljava/lang/Object;
       4: dup
       5: astore_3
       6: monitorenter
       7: aload_1
       8: invokevirtual #403                // Method org/apache/dubbo/rpc/model/ModuleModel.isInternal:()Z
      11: ifne          25
      14: aload_2
      15: getstatic     #404                // Field org/apache/dubbo/common/deploy/DeployState.STARTED:Lorg/apache/dubbo/common/deploy/DeployState;
      18: if_acmpne     25
      21: aload_0
      22: invokevirtual #405                // Method prepareApplicationInstance:()V
      25: aload_0
      26: invokespecial #406                // Method calculateState:()Lorg/apache/dubbo/common/deploy/DeployState;
      29: astore        4
      31: getstatic     #407                // Field org/apache/dubbo/config/deploy/DefaultApplicationDeployer$1.$SwitchMap$org$apache$dubbo$common$deploy$DeployState:[I
      34: aload         4
      36: invokevirtual #408                // Method org/apache/dubbo/common/deploy/DeployState.ordinal:()I
      39: iaload
      40: tableswitch   { // 1 to 6
                     1: 80
                     2: 87
                     3: 94
                     4: 101
                     5: 108
                     6: 236
               default: 236
          }
      80: aload_0
      81: invokespecial #409                // Method onStarted:()V
      84: goto          236
      87: aload_0
      88: invokespecial #289                // Method onStarting:()V
      91: goto          236
      94: aload_0
      95: invokespecial #370                // Method onStopping:()V
      98: goto          236
     101: aload_0
     102: invokespecial #396                // Method onStopped:()V
     105: goto          236
     108: aconst_null
     109: astore        5
     111: aconst_null
     112: astore        6
     114: aload_0
     115: getfield      #21                 // Field applicationModel:Lorg/apache/dubbo/rpc/model/ApplicationModel;
     118: invokevirtual #77                 // Method org/apache/dubbo/rpc/model/ApplicationModel.getModuleModels:()Ljava/util/List;
     121: invokeinterface #78,  1           // InterfaceMethod java/util/List.iterator:()Ljava/util/Iterator;
     126: astore        7
     128: aload         7
     130: invokeinterface #43,  1           // InterfaceMethod java/util/Iterator.hasNext:()Z
     135: ifeq          196
     138: aload         7
     140: invokeinterface #44,  1           // InterfaceMethod java/util/Iterator.next:()Ljava/lang/Object;
     145: checkcast     #79                 // class org/apache/dubbo/rpc/model/ModuleModel
     148: astore        8
     150: aload         8
     152: invokevirtual #80                 // Method org/apache/dubbo/rpc/model/ModuleModel.getDeployer:()Lorg/apache/dubbo/common/deploy/ModuleDeployer;
     155: astore        9
     157: aload         9
     159: invokeinterface #410,  1          // InterfaceMethod org/apache/dubbo/common/deploy/ModuleDeployer.isFailed:()Z
     164: ifeq          193
     167: aload         9
     169: invokeinterface #411,  1          // InterfaceMethod org/apache/dubbo/common/deploy/ModuleDeployer.getError:()Ljava/lang/Throwable;
     174: ifnull        193
     177: aload         9
     179: invokeinterface #411,  1          // InterfaceMethod org/apache/dubbo/common/deploy/ModuleDeployer.getError:()Ljava/lang/Throwable;
     184: astore        5
     186: aload         8
     188: astore        6
     190: goto          196
     193: goto          128
     196: aload_0
     197: new           #68                 // class java/lang/StringBuilder
     200: dup
     201: invokespecial #69                 // Method java/lang/StringBuilder."<init>":()V
     204: aload_0
     205: invokevirtual #70                 // Method getIdentifier:()Ljava/lang/String;
     208: invokevirtual #71                 // Method java/lang/StringBuilder.append:(Ljava/lang/String;)Ljava/lang/StringBuilder;
     211: ldc_w         #412                // String  found failed module:
     214: invokevirtual #71                 // Method java/lang/StringBuilder.append:(Ljava/lang/String;)Ljava/lang/StringBuilder;
     217: aload         6
     219: invokevirtual #413                // Method org/apache/dubbo/rpc/model/ModuleModel.getDesc:()Ljava/lang/String;
     222: invokevirtual #71                 // Method java/lang/StringBuilder.append:(Ljava/lang/String;)Ljava/lang/StringBuilder;
     225: invokevirtual #73                 // Method java/lang/StringBuilder.toString:()Ljava/lang/String;
     228: aload         5
     230: invokespecial #294                // Method onFailed:(Ljava/lang/String;Ljava/lang/Throwable;)V
     233: goto          236
     236: aload_3
     237: monitorexit
     238: goto          248
     241: astore        10
     243: aload_3
     244: monitorexit
     245: aload         10
     247: athrow
     248: return
    Exception table:
       from    to  target type
           7   238   241   any
         241   245   241   any

  private org.apache.dubbo.common.deploy.DeployState calculateState();
    Code:
       0: getstatic     #414                // Field org/apache/dubbo/common/deploy/DeployState.UNKNOWN:Lorg/apache/dubbo/common/deploy/DeployState;
       3: astore_1
       4: iconst_0
       5: istore_2
       6: iconst_0
       7: istore_3
       8: iconst_0
       9: istore        4
      11: iconst_0
      12: istore        5
      14: iconst_0
      15: istore        6
      17: iconst_0
      18: istore        7
      20: aload_0
      21: getfield      #21                 // Field applicationModel:Lorg/apache/dubbo/rpc/model/ApplicationModel;
      24: invokevirtual #77                 // Method org/apache/dubbo/rpc/model/ApplicationModel.getModuleModels:()Ljava/util/List;
      27: invokeinterface #78,  1           // InterfaceMethod java/util/List.iterator:()Ljava/util/Iterator;
      32: astore        8
      34: aload         8
      36: invokeinterface #43,  1           // InterfaceMethod java/util/Iterator.hasNext:()Z
      41: ifeq          170
      44: aload         8
      46: invokeinterface #44,  1           // InterfaceMethod java/util/Iterator.next:()Ljava/lang/Object;
      51: checkcast     #79                 // class org/apache/dubbo/rpc/model/ModuleModel
      54: astore        9
      56: aload         9
      58: invokevirtual #80                 // Method org/apache/dubbo/rpc/model/ModuleModel.getDeployer:()Lorg/apache/dubbo/common/deploy/ModuleDeployer;
      61: astore        10
      63: aload         10
      65: ifnonnull     74
      68: iinc          2, 1
      71: goto          167
      74: aload         10
      76: invokeinterface #295,  1          // InterfaceMethod org/apache/dubbo/common/deploy/ModuleDeployer.isPending:()Z
      81: ifeq          90
      84: iinc          2, 1
      87: goto          167
      90: aload         10
      92: invokeinterface #415,  1          // InterfaceMethod org/apache/dubbo/common/deploy/ModuleDeployer.isStarting:()Z
      97: ifeq          106
     100: iinc          3, 1
     103: goto          167
     106: aload         10
     108: invokeinterface #305,  1          // InterfaceMethod org/apache/dubbo/common/deploy/ModuleDeployer.isStarted:()Z
     113: ifeq          122
     116: iinc          4, 1
     119: goto          167
     122: aload         10
     124: invokeinterface #416,  1          // InterfaceMethod org/apache/dubbo/common/deploy/ModuleDeployer.isStopping:()Z
     129: ifeq          138
     132: iinc          5, 1
     135: goto          167
     138: aload         10
     140: invokeinterface #417,  1          // InterfaceMethod org/apache/dubbo/common/deploy/ModuleDeployer.isStopped:()Z
     145: ifeq          154
     148: iinc          6, 1
     151: goto          167
     154: aload         10
     156: invokeinterface #410,  1          // InterfaceMethod org/apache/dubbo/common/deploy/ModuleDeployer.isFailed:()Z
     161: ifeq          167
     164: iinc          7, 1
     167: goto          34
     170: iload         7
     172: ifle          182
     175: getstatic     #418                // Field org/apache/dubbo/common/deploy/DeployState.FAILED:Lorg/apache/dubbo/common/deploy/DeployState;
     178: astore_1
     179: goto          304
     182: iload         4
     184: ifle          234
     187: iload_2
     188: iload_3
     189: iadd
     190: iload         5
     192: iadd
     193: iload         6
     195: iadd
     196: ifne          206
     199: getstatic     #404                // Field org/apache/dubbo/common/deploy/DeployState.STARTED:Lorg/apache/dubbo/common/deploy/DeployState;
     202: astore_1
     203: goto          304
     206: iload_2
     207: iload_3
     208: iadd
     209: ifle          219
     212: getstatic     #419                // Field org/apache/dubbo/common/deploy/DeployState.STARTING:Lorg/apache/dubbo/common/deploy/DeployState;
     215: astore_1
     216: goto          304
     219: iload         5
     221: iload         6
     223: iadd
     224: ifle          304
     227: getstatic     #420                // Field org/apache/dubbo/common/deploy/DeployState.STOPPING:Lorg/apache/dubbo/common/deploy/DeployState;
     230: astore_1
     231: goto          304
     234: iload_3
     235: ifle          245
     238: getstatic     #419                // Field org/apache/dubbo/common/deploy/DeployState.STARTING:Lorg/apache/dubbo/common/deploy/DeployState;
     241: astore_1
     242: goto          304
     245: iload_2
     246: ifle          283
     249: iload_3
     250: iload_3
     251: iadd
     252: iload         5
     254: iadd
     255: iload         6
     257: iadd
     258: ifne          268
     261: getstatic     #421                // Field org/apache/dubbo/common/deploy/DeployState.PENDING:Lorg/apache/dubbo/common/deploy/DeployState;
     264: astore_1
     265: goto          304
     268: iload         5
     270: iload         6
     272: iadd
     273: ifle          304
     276: getstatic     #420                // Field org/apache/dubbo/common/deploy/DeployState.STOPPING:Lorg/apache/dubbo/common/deploy/DeployState;
     279: astore_1
     280: goto          304
     283: iload         5
     285: ifle          295
     288: getstatic     #420                // Field org/apache/dubbo/common/deploy/DeployState.STOPPING:Lorg/apache/dubbo/common/deploy/DeployState;
     291: astore_1
     292: goto          304
     295: iload         6
     297: ifle          304
     300: getstatic     #422                // Field org/apache/dubbo/common/deploy/DeployState.STOPPED:Lorg/apache/dubbo/common/deploy/DeployState;
     303: astore_1
     304: aload_1
     305: areturn

  private void onInitialize();
    Code:
       0: aload_0
       1: getfield      #423                // Field listeners:Ljava/util/List;
       4: invokeinterface #78,  1           // InterfaceMethod java/util/List.iterator:()Ljava/util/Iterator;
       9: astore_1
      10: aload_1
      11: invokeinterface #43,  1           // InterfaceMethod java/util/Iterator.hasNext:()Z
      16: ifeq          87
      19: aload_1
      20: invokeinterface #44,  1           // InterfaceMethod java/util/Iterator.next:()Ljava/lang/Object;
      25: checkcast     #424                // class org/apache/dubbo/common/deploy/DeployListener
      28: astore_2
      29: aload_2
      30: aload_0
      31: getfield      #21                 // Field applicationModel:Lorg/apache/dubbo/rpc/model/ApplicationModel;
      34: invokeinterface #425,  2          // InterfaceMethod org/apache/dubbo/common/deploy/DeployListener.onInitialize:(Lorg/apache/dubbo/rpc/model/ScopeModel;)V
      39: goto          84
      42: astore_3
      43: getstatic     #66                 // Field logger:Lorg/apache/dubbo/common/logger/ErrorTypeAwareLogger;
      46: ldc_w         #311                // String 5-14
      49: ldc_w         #312                // String
      52: ldc_w         #312                // String
      55: new           #68                 // class java/lang/StringBuilder
      58: dup
      59: invokespecial #69                 // Method java/lang/StringBuilder."<init>":()V
      62: aload_0
      63: invokevirtual #70                 // Method getIdentifier:()Ljava/lang/String;
      66: invokevirtual #71                 // Method java/lang/StringBuilder.append:(Ljava/lang/String;)Ljava/lang/StringBuilder;
      69: ldc_w         #426                // String  an exception occurred when handle initialize event
      72: invokevirtual #71                 // Method java/lang/StringBuilder.append:(Ljava/lang/String;)Ljava/lang/StringBuilder;
      75: invokevirtual #73                 // Method java/lang/StringBuilder.toString:()Ljava/lang/String;
      78: aload_3
      79: invokeinterface #321,  6          // InterfaceMethod org/apache/dubbo/common/logger/ErrorTypeAwareLogger.error:(Ljava/lang/String;Ljava/lang/String;Ljava/lang/String;Ljava/lang/String;Ljava/lang/Throwable;)V
      84: goto          10
      87: return
    Exception table:
       from    to  target type
          29    39    42   Class java/lang/Throwable

  private void exportMetadataService();
    Code:
       0: aload_0
       1: invokevirtual #284                // Method isStarting:()Z
       4: ifne          8
       7: return
       8: aload_0
       9: getfield      #423                // Field listeners:Ljava/util/List;
      12: invokeinterface #78,  1           // InterfaceMethod java/util/List.iterator:()Ljava/util/Iterator;
      17: astore_1
      18: aload_1
      19: invokeinterface #43,  1           // InterfaceMethod java/util/Iterator.hasNext:()Z
      24: ifeq          105
      27: aload_1
      28: invokeinterface #44,  1           // InterfaceMethod java/util/Iterator.next:()Ljava/lang/Object;
      33: checkcast     #424                // class org/apache/dubbo/common/deploy/DeployListener
      36: astore_2
      37: aload_2
      38: instanceof    #39                 // class org/apache/dubbo/common/deploy/ApplicationDeployListener
      41: ifeq          57
      44: aload_2
      45: checkcast     #39                 // class org/apache/dubbo/common/deploy/ApplicationDeployListener
      48: aload_0
      49: getfield      #21                 // Field applicationModel:Lorg/apache/dubbo/rpc/model/ApplicationModel;
      52: invokeinterface #427,  2          // InterfaceMethod org/apache/dubbo/common/deploy/ApplicationDeployListener.onModuleStarted:(Lorg/apache/dubbo/rpc/model/ApplicationModel;)V
      57: goto          102
      60: astore_3
      61: getstatic     #66                 // Field logger:Lorg/apache/dubbo/common/logger/ErrorTypeAwareLogger;
      64: ldc_w         #311                // String 5-14
      67: ldc_w         #312                // String
      70: ldc_w         #312                // String
      73: new           #68                 // class java/lang/StringBuilder
      76: dup
      77: invokespecial #69                 // Method java/lang/StringBuilder."<init>":()V
      80: aload_0
      81: invokevirtual #70                 // Method getIdentifier:()Ljava/lang/String;
      84: invokevirtual #71                 // Method java/lang/StringBuilder.append:(Ljava/lang/String;)Ljava/lang/StringBuilder;
      87: ldc_w         #428                // String  an exception occurred when handle starting event
      90: invokevirtual #71                 // Method java/lang/StringBuilder.append:(Ljava/lang/String;)Ljava/lang/StringBuilder;
      93: invokevirtual #73                 // Method java/lang/StringBuilder.toString:()Ljava/lang/String;
      96: aload_3
      97: invokeinterface #321,  6          // InterfaceMethod org/apache/dubbo/common/logger/ErrorTypeAwareLogger.error:(Ljava/lang/String;Ljava/lang/String;Ljava/lang/String;Ljava/lang/String;Ljava/lang/Throwable;)V
     102: goto          18
     105: return
    Exception table:
       from    to  target type
          37    57    60   Class java/lang/Throwable

  private void onStarting();
    Code:
       0: aload_0
       1: invokevirtual #429                // Method isPending:()Z
       4: ifne          15
       7: aload_0
       8: invokevirtual #287                // Method isStarted:()Z
      11: ifne          15
      14: return
      15: aload_0
      16: invokevirtual #430                // Method setStarting:()V
      19: aload_0
      20: new           #431                // class java/util/concurrent/CompletableFuture
      23: dup
      24: invokespecial #432                // Method java/util/concurrent/CompletableFuture."<init>":()V
      27: putfield      #286                // Field startFuture:Ljava/util/concurrent/CompletableFuture;
      30: getstatic     #66                 // Field logger:Lorg/apache/dubbo/common/logger/ErrorTypeAwareLogger;
      33: invokeinterface #67,  1           // InterfaceMethod org/apache/dubbo/common/logger/ErrorTypeAwareLogger.isInfoEnabled:()Z
      38: ifeq          72
      41: getstatic     #66                 // Field logger:Lorg/apache/dubbo/common/logger/ErrorTypeAwareLogger;
      44: new           #68                 // class java/lang/StringBuilder
      47: dup
      48: invokespecial #69                 // Method java/lang/StringBuilder."<init>":()V
      51: aload_0
      52: invokevirtual #70                 // Method getIdentifier:()Ljava/lang/String;
      55: invokevirtual #71                 // Method java/lang/StringBuilder.append:(Ljava/lang/String;)Ljava/lang/StringBuilder;
      58: ldc_w         #433                // String  is starting.
      61: invokevirtual #71                 // Method java/lang/StringBuilder.append:(Ljava/lang/String;)Ljava/lang/StringBuilder;
      64: invokevirtual #73                 // Method java/lang/StringBuilder.toString:()Ljava/lang/String;
      67: invokeinterface #74,  2           // InterfaceMethod org/apache/dubbo/common/logger/ErrorTypeAwareLogger.info:(Ljava/lang/String;)V
      72: return

  private void onStarted();
    Code:
       0: aload_0
       1: invokevirtual #284                // Method isStarting:()Z
       4: ifne          13
       7: aload_0
       8: iconst_1
       9: invokespecial #434                // Method completeStartFuture:(Z)V
      12: return
      13: aload_0
      14: invokevirtual #435                // Method setStarted:()V
      17: aload_0
      18: invokespecial #436                // Method startMetricsCollector:()V
      21: getstatic     #66                 // Field logger:Lorg/apache/dubbo/common/logger/ErrorTypeAwareLogger;
      24: invokeinterface #67,  1           // InterfaceMethod org/apache/dubbo/common/logger/ErrorTypeAwareLogger.isInfoEnabled:()Z
      29: ifeq          63
      32: getstatic     #66                 // Field logger:Lorg/apache/dubbo/common/logger/ErrorTypeAwareLogger;
      35: new           #68                 // class java/lang/StringBuilder
      38: dup
      39: invokespecial #69                 // Method java/lang/StringBuilder."<init>":()V
      42: aload_0
      43: invokevirtual #70                 // Method getIdentifier:()Ljava/lang/String;
      46: invokevirtual #71                 // Method java/lang/StringBuilder.append:(Ljava/lang/String;)Ljava/lang/StringBuilder;
      49: ldc_w         #437                // String  is ready.
      52: invokevirtual #71                 // Method java/lang/StringBuilder.append:(Ljava/lang/String;)Ljava/lang/StringBuilder;
      55: invokevirtual #73                 // Method java/lang/StringBuilder.toString:()Ljava/lang/String;
      58: invokeinterface #74,  2           // InterfaceMethod org/apache/dubbo/common/logger/ErrorTypeAwareLogger.info:(Ljava/lang/String;)V
      63: aload_0
      64: getfield      #352                // Field registered:Z
      67: ifeq          77
      70: aload_0
      71: getfield      #21                 // Field applicationModel:Lorg/apache/dubbo/rpc/model/ApplicationModel;
      74: invokestatic  #438                // Method org/apache/dubbo/registry/client/metadata/ServiceInstanceMetadataUtils.refreshMetadataAndInstance:(Lorg/apache/dubbo/rpc/model/ApplicationModel;)V
      77: goto          102
      80: astore_1
      81: getstatic     #66                 // Field logger:Lorg/apache/dubbo/common/logger/ErrorTypeAwareLogger;
      84: ldc_w         #439                // String 5-12
      87: ldc_w         #312                // String
      90: ldc_w         #312                // String
      93: ldc_w         #440                // String Refresh instance and metadata error.
      96: aload_1
      97: invokeinterface #321,  6          // InterfaceMethod org/apache/dubbo/common/logger/ErrorTypeAwareLogger.error:(Ljava/lang/String;Ljava/lang/String;Ljava/lang/String;Ljava/lang/String;Ljava/lang/Throwable;)V
     102: aload_0
     103: iconst_1
     104: invokespecial #434                // Method completeStartFuture:(Z)V
     107: goto          118
     110: astore_2
     111: aload_0
     112: iconst_1
     113: invokespecial #434                // Method completeStartFuture:(Z)V
     116: aload_2
     117: athrow
     118: return
    Exception table:
       from    to  target type
          63    77    80   Class java/lang/Exception
           0     7   110   any
          13   102   110   any

  private void startMetricsCollector();
    Code:
       0: aload_0
       1: getfield      #21                 // Field applicationModel:Lorg/apache/dubbo/rpc/model/ApplicationModel;
       4: invokevirtual #48                 // Method org/apache/dubbo/rpc/model/ApplicationModel.getBeanFactory:()Lorg/apache/dubbo/common/beans/factory/ScopeBeanFactory;
       7: ldc           #148                // class org/apache/dubbo/metrics/collector/DefaultMetricsCollector
       9: invokevirtual #32                 // Method org/apache/dubbo/common/beans/factory/ScopeBeanFactory.getBean:(Ljava/lang/Class;)Ljava/lang/Object;
      12: checkcast     #148                // class org/apache/dubbo/metrics/collector/DefaultMetricsCollector
      15: astore_1
      16: aload_1
      17: invokestatic  #441                // Method java/util/Objects.nonNull:(Ljava/lang/Object;)Z
      20: ifeq          34
      23: aload_1
      24: invokevirtual #442                // Method org/apache/dubbo/metrics/collector/DefaultMetricsCollector.isThreadpoolCollectEnabled:()Z
      27: ifeq          34
      30: aload_1
      31: invokevirtual #443                // Method org/apache/dubbo/metrics/collector/DefaultMetricsCollector.registryDefaultSample:()V
      34: return

  private void completeStartFuture(boolean);
    Code:
       0: aload_0
       1: getfield      #286                // Field startFuture:Ljava/util/concurrent/CompletableFuture;
       4: ifnull        19
       7: aload_0
       8: getfield      #286                // Field startFuture:Ljava/util/concurrent/CompletableFuture;
      11: iload_1
      12: invokestatic  #157                // Method java/lang/Boolean.valueOf:(Z)Ljava/lang/Boolean;
      15: invokevirtual #444                // Method java/util/concurrent/CompletableFuture.complete:(Ljava/lang/Object;)Z
      18: pop
      19: return

  private void onStopping();
    Code:
       0: aload_0
       1: invokevirtual #279                // Method isStopping:()Z
       4: ifne          14
       7: aload_0
       8: invokevirtual #280                // Method isStopped:()Z
      11: ifeq          20
      14: aload_0
      15: iconst_0
      16: invokespecial #434                // Method completeStartFuture:(Z)V
      19: return
      20: aload_0
      21: invokevirtual #445                // Method setStopping:()V
      24: getstatic     #66                 // Field logger:Lorg/apache/dubbo/common/logger/ErrorTypeAwareLogger;
      27: invokeinterface #67,  1           // InterfaceMethod org/apache/dubbo/common/logger/ErrorTypeAwareLogger.isInfoEnabled:()Z
      32: ifeq          66
      35: getstatic     #66                 // Field logger:Lorg/apache/dubbo/common/logger/ErrorTypeAwareLogger;
      38: new           #68                 // class java/lang/StringBuilder
      41: dup
      42: invokespecial #69                 // Method java/lang/StringBuilder."<init>":()V
      45: aload_0
      46: invokevirtual #70                 // Method getIdentifier:()Ljava/lang/String;
      49: invokevirtual #71                 // Method java/lang/StringBuilder.append:(Ljava/lang/String;)Ljava/lang/StringBuilder;
      52: ldc_w         #446                // String  is stopping.
      55: invokevirtual #71                 // Method java/lang/StringBuilder.append:(Ljava/lang/String;)Ljava/lang/StringBuilder;
      58: invokevirtual #73                 // Method java/lang/StringBuilder.toString:()Ljava/lang/String;
      61: invokeinterface #74,  2           // InterfaceMethod org/apache/dubbo/common/logger/ErrorTypeAwareLogger.info:(Ljava/lang/String;)V
      66: aload_0
      67: iconst_0
      68: invokespecial #434                // Method completeStartFuture:(Z)V
      71: goto          82
      74: astore_1
      75: aload_0
      76: iconst_0
      77: invokespecial #434                // Method completeStartFuture:(Z)V
      80: aload_1
      81: athrow
      82: return
    Exception table:
       from    to  target type
           0    14    74   any
          20    66    74   any

  private void onStopped();
    Code:
       0: aload_0
       1: invokevirtual #280                // Method isStopped:()Z
       4: ifeq          13
       7: aload_0
       8: iconst_0
       9: invokespecial #434                // Method completeStartFuture:(Z)V
      12: return
      13: aload_0
      14: invokevirtual #447                // Method setStopped:()V
      17: getstatic     #66                 // Field logger:Lorg/apache/dubbo/common/logger/ErrorTypeAwareLogger;
      20: invokeinterface #67,  1           // InterfaceMethod org/apache/dubbo/common/logger/ErrorTypeAwareLogger.isInfoEnabled:()Z
      25: ifeq          59
      28: getstatic     #66                 // Field logger:Lorg/apache/dubbo/common/logger/ErrorTypeAwareLogger;
      31: new           #68                 // class java/lang/StringBuilder
      34: dup
      35: invokespecial #69                 // Method java/lang/StringBuilder."<init>":()V
      38: aload_0
      39: invokevirtual #70                 // Method getIdentifier:()Ljava/lang/String;
      42: invokevirtual #71                 // Method java/lang/StringBuilder.append:(Ljava/lang/String;)Ljava/lang/StringBuilder;
      45: ldc_w         #448                // String  has stopped.
      48: invokevirtual #71                 // Method java/lang/StringBuilder.append:(Ljava/lang/String;)Ljava/lang/StringBuilder;
      51: invokevirtual #73                 // Method java/lang/StringBuilder.toString:()Ljava/lang/String;
      54: invokeinterface #74,  2           // InterfaceMethod org/apache/dubbo/common/logger/ErrorTypeAwareLogger.info:(Ljava/lang/String;)V
      59: aload_0
      60: iconst_0
      61: invokespecial #434                // Method completeStartFuture:(Z)V
      64: goto          75
      67: astore_1
      68: aload_0
      69: iconst_0
      70: invokespecial #434                // Method completeStartFuture:(Z)V
      73: aload_1
      74: athrow
      75: return
    Exception table:
       from    to  target type
           0     7    67   any
          13    59    67   any

  private void onFailed(java.lang.String, java.lang.Throwable);
    Code:
       0: aload_0
       1: aload_2
       2: invokevirtual #449                // Method setFailed:(Ljava/lang/Throwable;)V
       5: getstatic     #66                 // Field logger:Lorg/apache/dubbo/common/logger/ErrorTypeAwareLogger;
       8: ldc_w         #311                // String 5-14
      11: ldc_w         #312                // String
      14: ldc_w         #312                // String
      17: aload_1
      18: aload_2
      19: invokeinterface #321,  6          // InterfaceMethod org/apache/dubbo/common/logger/ErrorTypeAwareLogger.error:(Ljava/lang/String;Ljava/lang/String;Ljava/lang/String;Ljava/lang/String;Ljava/lang/Throwable;)V
      24: aload_0
      25: iconst_0
      26: invokespecial #434                // Method completeStartFuture:(Z)V
      29: goto          40
      32: astore_3
      33: aload_0
      34: iconst_0
      35: invokespecial #434                // Method completeStartFuture:(Z)V
      38: aload_3
      39: athrow
      40: return
    Exception table:
       from    to  target type
           0    24    32   any

  private void destroyExecutorRepository();
    Code:
       0: aload_0
       1: getfield      #35                 // Field executorRepository:Lorg/apache/dubbo/common/threadpool/manager/ExecutorRepository;
       4: invokeinterface #450,  1          // InterfaceMethod org/apache/dubbo/common/threadpool/manager/ExecutorRepository.shutdownServiceExportExecutor:()V
       9: aload_0
      10: getfield      #35                 // Field executorRepository:Lorg/apache/dubbo/common/threadpool/manager/ExecutorRepository;
      13: invokeinterface #451,  1          // InterfaceMethod org/apache/dubbo/common/threadpool/manager/ExecutorRepository.shutdownServiceReferExecutor:()V
      18: aload_0
      19: getfield      #21                 // Field applicationModel:Lorg/apache/dubbo/rpc/model/ApplicationModel;
      22: invokestatic  #34                 // InterfaceMethod org/apache/dubbo/common/threadpool/manager/ExecutorRepository.getInstance:(Lorg/apache/dubbo/rpc/model/ApplicationModel;)Lorg/apache/dubbo/common/threadpool/manager/ExecutorRepository;
      25: invokeinterface #452,  1          // InterfaceMethod org/apache/dubbo/common/threadpool/manager/ExecutorRepository.destroyAll:()V
      30: return

  private void destroyRegistries();
    Code:
       0: aload_0
       1: getfield      #21                 // Field applicationModel:Lorg/apache/dubbo/rpc/model/ApplicationModel;
       4: invokestatic  #453                // Method org/apache/dubbo/registry/support/RegistryManager.getInstance:(Lorg/apache/dubbo/rpc/model/ApplicationModel;)Lorg/apache/dubbo/registry/support/RegistryManager;
       7: invokevirtual #454                // Method org/apache/dubbo/registry/support/RegistryManager.destroyAll:()V
      10: return

  private void destroyServiceDiscoveries();
    Code:
       0: aload_0
       1: getfield      #21                 // Field applicationModel:Lorg/apache/dubbo/rpc/model/ApplicationModel;
       4: invokestatic  #453                // Method org/apache/dubbo/registry/support/RegistryManager.getInstance:(Lorg/apache/dubbo/rpc/model/ApplicationModel;)Lorg/apache/dubbo/registry/support/RegistryManager;
       7: invokevirtual #455                // Method org/apache/dubbo/registry/support/RegistryManager.getServiceDiscoveries:()Ljava/util/List;
      10: invokedynamic #456,  0            // InvokeDynamic #13:accept:()Ljava/util/function/Consumer;
      15: invokeinterface #457,  2          // InterfaceMethod java/util/List.forEach:(Ljava/util/function/Consumer;)V
      20: getstatic     #66                 // Field logger:Lorg/apache/dubbo/common/logger/ErrorTypeAwareLogger;
      23: invokeinterface #458,  1          // InterfaceMethod org/apache/dubbo/common/logger/ErrorTypeAwareLogger.isDebugEnabled:()Z
      28: ifeq          62
      31: getstatic     #66                 // Field logger:Lorg/apache/dubbo/common/logger/ErrorTypeAwareLogger;
      34: new           #68                 // class java/lang/StringBuilder
      37: dup
      38: invokespecial #69                 // Method java/lang/StringBuilder."<init>":()V
      41: aload_0
      42: invokevirtual #70                 // Method getIdentifier:()Ljava/lang/String;
      45: invokevirtual #71                 // Method java/lang/StringBuilder.append:(Ljava/lang/String;)Ljava/lang/StringBuilder;
      48: ldc_w         #459                // String \'s all ServiceDiscoveries have been destroyed.
      51: invokevirtual #71                 // Method java/lang/StringBuilder.append:(Ljava/lang/String;)Ljava/lang/StringBuilder;
      54: invokevirtual #73                 // Method java/lang/StringBuilder.toString:()Ljava/lang/String;
      57: invokeinterface #460,  2          // InterfaceMethod org/apache/dubbo/common/logger/ErrorTypeAwareLogger.debug:(Ljava/lang/String;)V
      62: return

  private void destroyMetadataReports();
    Code:
       0: aload_0
       1: ldc           #240                // class org/apache/dubbo/metadata/report/MetadataReportFactory
       3: invokespecial #144                // Method getExtensionLoader:(Ljava/lang/Class;)Lorg/apache/dubbo/common/extension/ExtensionLoader;
       6: invokevirtual #461                // Method org/apache/dubbo/common/extension/ExtensionLoader.getLoadedExtensionInstances:()Ljava/util/List;
       9: astore_1
      10: aload_1
      11: invokeinterface #78,  1           // InterfaceMethod java/util/List.iterator:()Ljava/util/Iterator;
      16: astore_2
      17: aload_2
      18: invokeinterface #43,  1           // InterfaceMethod java/util/Iterator.hasNext:()Z
      23: ifeq          45
      26: aload_2
      27: invokeinterface #44,  1           // InterfaceMethod java/util/Iterator.next:()Ljava/lang/Object;
      32: checkcast     #240                // class org/apache/dubbo/metadata/report/MetadataReportFactory
      35: astore_3
      36: aload_3
      37: invokeinterface #462,  1          // InterfaceMethod org/apache/dubbo/metadata/report/MetadataReportFactory.destroy:()V
      42: goto          17
      45: return

  private org.apache.dubbo.config.ApplicationConfig getApplication();
    Code:
       0: aload_0
       1: getfield      #23                 // Field configManager:Lorg/apache/dubbo/config/context/ConfigManager;
       4: invokevirtual #463                // Method org/apache/dubbo/config/context/ConfigManager.getApplicationOrElseThrow:()Lorg/apache/dubbo/config/ApplicationConfig;
       7: areturn

  private static void lambda$destroyServiceDiscoveries$7(org.apache.dubbo.registry.client.ServiceDiscovery);
    Code:
       0: aload_0
       1: invokeinterface #464,  1          // InterfaceMethod org/apache/dubbo/registry/client/ServiceDiscovery.destroy:()V
       6: goto          32
       9: astore_1
      10: getstatic     #66                 // Field logger:Lorg/apache/dubbo/common/logger/ErrorTypeAwareLogger;
      13: ldc_w         #465                // String 5-21
      16: ldc_w         #312                // String
      19: ldc_w         #312                // String
      22: aload_1
      23: invokevirtual #398                // Method java/lang/Throwable.getMessage:()Ljava/lang/String;
      26: aload_1
      27: invokeinterface #315,  6          // InterfaceMethod org/apache/dubbo/common/logger/ErrorTypeAwareLogger.warn:(Ljava/lang/String;Ljava/lang/String;Ljava/lang/String;Ljava/lang/String;Ljava/lang/Throwable;)V
      32: return
    Exception table:
       from    to  target type
           0     6     9   Class java/lang/Throwable

  private void lambda$registerServiceInstance$6();
    Code:
       0: aload_0
       1: getfield      #21                 // Field applicationModel:Lorg/apache/dubbo/rpc/model/ApplicationModel;
       4: invokevirtual #466                // Method org/apache/dubbo/rpc/model/ApplicationModel.isDestroyed:()Z
       7: ifeq          11
      10: return
      11: aload_0
      12: getfield      #19                 // Field instanceRefreshScheduleTimes:Ljava/util/concurrent/atomic/AtomicInteger;
      15: invokevirtual #366                // Method java/util/concurrent/atomic/AtomicInteger.incrementAndGet:()I
      18: bipush        30
      20: irem
      21: ifeq          32
      24: aload_0
      25: invokevirtual #287                // Method isStarted:()Z
      28: ifne          32
      31: return
      32: aload_0
      33: getfield      #20                 // Field serviceRefreshState:Ljava/util/concurrent/atomic/AtomicInteger;
      36: invokevirtual #467                // Method java/util/concurrent/atomic/AtomicInteger.get:()I
      39: ifeq          55
      42: aload_0
      43: getfield      #19                 // Field instanceRefreshScheduleTimes:Ljava/util/concurrent/atomic/AtomicInteger;
      46: invokevirtual #467                // Method java/util/concurrent/atomic/AtomicInteger.get:()I
      49: iconst_5
      50: irem
      51: ifeq          55
      54: return
      55: aload_0
      56: getfield      #21                 // Field applicationModel:Lorg/apache/dubbo/rpc/model/ApplicationModel;
      59: invokevirtual #466                // Method org/apache/dubbo/rpc/model/ApplicationModel.isDestroyed:()Z
      62: ifne          79
      65: aload_0
      66: getfield      #352                // Field registered:Z
      69: ifeq          79
      72: aload_0
      73: getfield      #21                 // Field applicationModel:Lorg/apache/dubbo/rpc/model/ApplicationModel;
      76: invokestatic  #438                // Method org/apache/dubbo/registry/client/metadata/ServiceInstanceMetadataUtils.refreshMetadataAndInstance:(Lorg/apache/dubbo/rpc/model/ApplicationModel;)V
      79: goto          114
      82: astore_1
      83: aload_0
      84: getfield      #21                 // Field applicationModel:Lorg/apache/dubbo/rpc/model/ApplicationModel;
      87: invokevirtual #466                // Method org/apache/dubbo/rpc/model/ApplicationModel.isDestroyed:()Z
      90: ifne          114
      93: getstatic     #66                 // Field logger:Lorg/apache/dubbo/common/logger/ErrorTypeAwareLogger;
      96: ldc_w         #439                // String 5-12
      99: ldc_w         #312                // String
     102: ldc_w         #312                // String
     105: ldc_w         #440                // String Refresh instance and metadata error.
     108: aload_1
     109: invokeinterface #321,  6          // InterfaceMethod org/apache/dubbo/common/logger/ErrorTypeAwareLogger.error:(Ljava/lang/String;Ljava/lang/String;Ljava/lang/String;Ljava/lang/String;Ljava/lang/Throwable;)V
     114: return
    Exception table:
       from    to  target type
          55    79    82   Class java/lang/Exception

  private java.lang.Object lambda$registerServiceInstance$5();
    Code:
       0: aload_0
       1: getfield      #21                 // Field applicationModel:Lorg/apache/dubbo/rpc/model/ApplicationModel;
       4: invokestatic  #468                // Method org/apache/dubbo/registry/client/metadata/ServiceInstanceMetadataUtils.registerMetadataAndInstance:(Lorg/apache/dubbo/rpc/model/ApplicationModel;)V
       7: aconst_null
       8: areturn

  private void lambda$useRegistryAsMetadataCenterIfNecessary$4(org.apache.dubbo.config.MetadataReportConfig, org.apache.dubbo.config.MetadataReportConfig);
    Code:
       0: aload_0
       1: aload_1
       2: aload_2
       3: invokespecial #469                // Method overrideMetadataReportConfig:(Lorg/apache/dubbo/config/MetadataReportConfig;Lorg/apache/dubbo/config/MetadataReportConfig;)V
       6: return

  private org.apache.dubbo.config.MetadataReportConfig lambda$useRegistryAsMetadataCenterIfNecessary$3(org.apache.dubbo.config.MetadataReportConfig, org.apache.dubbo.config.RegistryConfig);
    Code:
       0: aload_0
       1: aload_2
       2: aload_1
       3: invokespecial #470                // Method registryAsMetadataCenter:(Lorg/apache/dubbo/config/RegistryConfig;Lorg/apache/dubbo/config/MetadataReportConfig;)Lorg/apache/dubbo/config/MetadataReportConfig;
       6: areturn

  private static boolean lambda$useRegistryAsMetadataCenterIfNecessary$2(org.apache.dubbo.config.MetadataReportConfig);
    Code:
       0: aload_0
       1: invokevirtual #233                // Method org/apache/dubbo/config/MetadataReportConfig.getAddress:()Ljava/lang/String;
       4: invokestatic  #471                // Method java/util/Objects.isNull:(Ljava/lang/Object;)Z
       7: ireturn

  private static boolean lambda$useRegistryAsMetadataCenterIfNecessary$1(org.apache.dubbo.config.MetadataReportConfig);
    Code:
       0: aload_0
       1: invokevirtual #233                // Method org/apache/dubbo/config/MetadataReportConfig.getAddress:()Ljava/lang/String;
       4: invokestatic  #441                // Method java/util/Objects.nonNull:(Ljava/lang/Object;)Z
       7: ireturn

  private void lambda$useRegistryAsConfigCenterIfNecessary$0(org.apache.dubbo.config.ConfigCenterConfig);
    Code:
       0: aload_0
       1: getfield      #23                 // Field configManager:Lorg/apache/dubbo/config/context/ConfigManager;
       4: aload_1
       5: invokevirtual #472                // Method org/apache/dubbo/config/ConfigCenterConfig.getId:()Ljava/lang/String;
       8: invokevirtual #473                // Method org/apache/dubbo/config/context/ConfigManager.getConfigCenter:(Ljava/lang/String;)Ljava/util/Optional;
      11: invokevirtual #132                // Method java/util/Optional.isPresent:()Z
      14: ifeq          18
      17: return
      18: aload_0
      19: getfield      #23                 // Field configManager:Lorg/apache/dubbo/config/context/ConfigManager;
      22: aload_1
      23: invokevirtual #98                 // Method org/apache/dubbo/config/context/ConfigManager.addConfigCenter:(Lorg/apache/dubbo/config/ConfigCenterConfig;)V
      26: getstatic     #66                 // Field logger:Lorg/apache/dubbo/common/logger/ErrorTypeAwareLogger;
      29: new           #68                 // class java/lang/StringBuilder
      32: dup
      33: invokespecial #69                 // Method java/lang/StringBuilder."<init>":()V
      36: ldc_w         #474                // String use registry as config-center:
      39: invokevirtual #71                 // Method java/lang/StringBuilder.append:(Ljava/lang/String;)Ljava/lang/StringBuilder;
      42: aload_1
      43: invokevirtual #191                // Method java/lang/StringBuilder.append:(Ljava/lang/Object;)Ljava/lang/StringBuilder;
      46: invokevirtual #73                 // Method java/lang/StringBuilder.toString:()Ljava/lang/String;
      49: invokeinterface #74,  2           // InterfaceMethod org/apache/dubbo/common/logger/ErrorTypeAwareLogger.info:(Ljava/lang/String;)V
      54: return

  static {};
    Code:
       0: ldc           #49                 // class org/apache/dubbo/config/deploy/DefaultApplicationDeployer
       2: invokestatic  #475                // Method org/apache/dubbo/common/logger/LoggerFactory.getErrorTypeAwareLogger:(Ljava/lang/Class;)Lorg/apache/dubbo/common/logger/ErrorTypeAwareLogger;
       5: putstatic     #66                 // Field logger:Lorg/apache/dubbo/common/logger/ErrorTypeAwareLogger;
       8: return
}
