Compiled from "DefaultModuleDeployer.java"
public class org.apache.dubbo.config.deploy.DefaultModuleDeployer extends org.apache.dubbo.common.deploy.AbstractDeployer<org.apache.dubbo.rpc.model.ModuleModel> implements org.apache.dubbo.common.deploy.ModuleDeployer {
  private static final org.apache.dubbo.common.logger.ErrorTypeAwareLogger logger;

  private final java.util.List<java.util.concurrent.CompletableFuture<?>> asyncExportingFutures;

  private final java.util.List<java.util.concurrent.CompletableFuture<?>> asyncReferringFutures;

  private final java.util.List<org.apache.dubbo.config.ServiceConfigBase<?>> exportedServices;

  private final org.apache.dubbo.rpc.model.ModuleModel moduleModel;

  private final org.apache.dubbo.common.threadpool.manager.FrameworkExecutorRepository frameworkExecutorRepository;

  private final org.apache.dubbo.common.threadpool.manager.ExecutorRepository executorRepository;

  private final org.apache.dubbo.config.context.ModuleConfigManager configManager;

  private final org.apache.dubbo.config.utils.SimpleReferenceCache referenceCache;

  private final org.apache.dubbo.common.deploy.ApplicationDeployer applicationDeployer;

  private java.util.concurrent.CompletableFuture startFuture;

  private java.lang.Boolean background;

  private java.lang.Boolean exportAsync;

  private java.lang.Boolean referAsync;

  private java.util.concurrent.CompletableFuture<?> exportFuture;

  private java.util.concurrent.CompletableFuture<?> referFuture;

  public org.apache.dubbo.config.deploy.DefaultModuleDeployer(org.apache.dubbo.rpc.model.ModuleModel);
    Code:
       0: aload_0
       1: aload_1
       2: invokespecial #2                  // Method org/apache/dubbo/common/deploy/AbstractDeployer."<init>":(Lorg/apache/dubbo/rpc/model/ScopeModel;)V
       5: aload_0
       6: new           #3                  // class java/util/ArrayList
       9: dup
      10: invokespecial #4                  // Method java/util/ArrayList."<init>":()V
      13: putfield      #5                  // Field asyncExportingFutures:Ljava/util/List;
      16: aload_0
      17: new           #3                  // class java/util/ArrayList
      20: dup
      21: invokespecial #4                  // Method java/util/ArrayList."<init>":()V
      24: putfield      #6                  // Field asyncReferringFutures:Ljava/util/List;
      27: aload_0
      28: new           #3                  // class java/util/ArrayList
      31: dup
      32: invokespecial #4                  // Method java/util/ArrayList."<init>":()V
      35: putfield      #7                  // Field exportedServices:Ljava/util/List;
      38: aload_0
      39: aload_1
      40: putfield      #8                  // Field moduleModel:Lorg/apache/dubbo/rpc/model/ModuleModel;
      43: aload_0
      44: aload_1
      45: invokevirtual #9                  // Method org/apache/dubbo/rpc/model/ModuleModel.getConfigManager:()Lorg/apache/dubbo/config/context/ModuleConfigManager;
      48: putfield      #10                 // Field configManager:Lorg/apache/dubbo/config/context/ModuleConfigManager;
      51: aload_0
      52: aload_1
      53: invokevirtual #11                 // Method org/apache/dubbo/rpc/model/ModuleModel.getApplicationModel:()Lorg/apache/dubbo/rpc/model/ApplicationModel;
      56: invokevirtual #12                 // Method org/apache/dubbo/rpc/model/ApplicationModel.getFrameworkModel:()Lorg/apache/dubbo/rpc/model/FrameworkModel;
      59: invokevirtual #13                 // Method org/apache/dubbo/rpc/model/FrameworkModel.getBeanFactory:()Lorg/apache/dubbo/common/beans/factory/ScopeBeanFactory;
      62: ldc           #14                 // class org/apache/dubbo/common/threadpool/manager/FrameworkExecutorRepository
      64: invokevirtual #15                 // Method org/apache/dubbo/common/beans/factory/ScopeBeanFactory.getBean:(Ljava/lang/Class;)Ljava/lang/Object;
      67: checkcast     #14                 // class org/apache/dubbo/common/threadpool/manager/FrameworkExecutorRepository
      70: putfield      #16                 // Field frameworkExecutorRepository:Lorg/apache/dubbo/common/threadpool/manager/FrameworkExecutorRepository;
      73: aload_0
      74: aload_1
      75: invokevirtual #11                 // Method org/apache/dubbo/rpc/model/ModuleModel.getApplicationModel:()Lorg/apache/dubbo/rpc/model/ApplicationModel;
      78: invokestatic  #17                 // InterfaceMethod org/apache/dubbo/common/threadpool/manager/ExecutorRepository.getInstance:(Lorg/apache/dubbo/rpc/model/ApplicationModel;)Lorg/apache/dubbo/common/threadpool/manager/ExecutorRepository;
      81: putfield      #18                 // Field executorRepository:Lorg/apache/dubbo/common/threadpool/manager/ExecutorRepository;
      84: aload_0
      85: invokestatic  #19                 // Method org/apache/dubbo/config/utils/SimpleReferenceCache.newCache:()Lorg/apache/dubbo/config/utils/SimpleReferenceCache;
      88: putfield      #20                 // Field referenceCache:Lorg/apache/dubbo/config/utils/SimpleReferenceCache;
      91: aload_0
      92: aload_1
      93: invokestatic  #21                 // Method org/apache/dubbo/config/deploy/DefaultApplicationDeployer.get:(Lorg/apache/dubbo/rpc/model/ScopeModel;)Lorg/apache/dubbo/common/deploy/ApplicationDeployer;
      96: putfield      #22                 // Field applicationDeployer:Lorg/apache/dubbo/common/deploy/ApplicationDeployer;
      99: aload_1
     100: ldc           #23                 // class org/apache/dubbo/common/deploy/ModuleDeployListener
     102: invokevirtual #24                 // Method org/apache/dubbo/rpc/model/ModuleModel.getExtensionLoader:(Ljava/lang/Class;)Lorg/apache/dubbo/common/extension/ExtensionLoader;
     105: invokevirtual #25                 // Method org/apache/dubbo/common/extension/ExtensionLoader.getSupportedExtensionInstances:()Ljava/util/Set;
     108: astore_2
     109: aload_2
     110: invokeinterface #26,  1           // InterfaceMethod java/util/Set.iterator:()Ljava/util/Iterator;
     115: astore_3
     116: aload_3
     117: invokeinterface #27,  1           // InterfaceMethod java/util/Iterator.hasNext:()Z
     122: ifeq          145
     125: aload_3
     126: invokeinterface #28,  1           // InterfaceMethod java/util/Iterator.next:()Ljava/lang/Object;
     131: checkcast     #23                 // class org/apache/dubbo/common/deploy/ModuleDeployListener
     134: astore        4
     136: aload_0
     137: aload         4
     139: invokevirtual #29                 // Method addDeployListener:(Lorg/apache/dubbo/common/deploy/DeployListener;)V
     142: goto          116
     145: return

  public void initialize() throws java.lang.IllegalStateException;
    Code:
       0: aload_0
       1: getfield      #30                 // Field initialized:Z
       4: ifeq          8
       7: return
       8: aload_0
       9: dup
      10: astore_1
      11: monitorenter
      12: aload_0
      13: getfield      #30                 // Field initialized:Z
      16: ifeq          22
      19: aload_1
      20: monitorexit
      21: return
      22: aload_0
      23: invokespecial #31                 // Method onInitialize:()V
      26: aload_0
      27: invokespecial #32                 // Method loadConfigs:()V
      30: aload_0
      31: getfield      #8                  // Field moduleModel:Lorg/apache/dubbo/rpc/model/ModuleModel;
      34: invokevirtual #9                  // Method org/apache/dubbo/rpc/model/ModuleModel.getConfigManager:()Lorg/apache/dubbo/config/context/ModuleConfigManager;
      37: invokevirtual #33                 // Method org/apache/dubbo/config/context/ModuleConfigManager.getModule:()Ljava/util/Optional;
      40: invokedynamic #34,  0             // InvokeDynamic #0:get:()Ljava/util/function/Supplier;
      45: invokevirtual #35                 // Method java/util/Optional.orElseThrow:(Ljava/util/function/Supplier;)Ljava/lang/Object;
      48: checkcast     #36                 // class org/apache/dubbo/config/ModuleConfig
      51: astore_2
      52: aload_0
      53: getstatic     #37                 // Field java/lang/Boolean.TRUE:Ljava/lang/Boolean;
      56: aload_2
      57: invokevirtual #38                 // Method org/apache/dubbo/config/ModuleConfig.getExportAsync:()Ljava/lang/Boolean;
      60: invokevirtual #39                 // Method java/lang/Boolean.equals:(Ljava/lang/Object;)Z
      63: invokestatic  #40                 // Method java/lang/Boolean.valueOf:(Z)Ljava/lang/Boolean;
      66: putfield      #41                 // Field exportAsync:Ljava/lang/Boolean;
      69: aload_0
      70: getstatic     #37                 // Field java/lang/Boolean.TRUE:Ljava/lang/Boolean;
      73: aload_2
      74: invokevirtual #42                 // Method org/apache/dubbo/config/ModuleConfig.getReferAsync:()Ljava/lang/Boolean;
      77: invokevirtual #39                 // Method java/lang/Boolean.equals:(Ljava/lang/Object;)Z
      80: invokestatic  #40                 // Method java/lang/Boolean.valueOf:(Z)Ljava/lang/Boolean;
      83: putfield      #43                 // Field referAsync:Ljava/lang/Boolean;
      86: aload_0
      87: aload_2
      88: invokevirtual #44                 // Method org/apache/dubbo/config/ModuleConfig.getBackground:()Ljava/lang/Boolean;
      91: putfield      #45                 // Field background:Ljava/lang/Boolean;
      94: aload_0
      95: getfield      #45                 // Field background:Ljava/lang/Boolean;
      98: ifnonnull     127
     101: aload_0
     102: aload_0
     103: invokespecial #46                 // Method isExportBackground:()Z
     106: ifne          116
     109: aload_0
     110: invokespecial #47                 // Method isReferBackground:()Z
     113: ifeq          120
     116: iconst_1
     117: goto          121
     120: iconst_0
     121: invokestatic  #40                 // Method java/lang/Boolean.valueOf:(Z)Ljava/lang/Boolean;
     124: putfield      #45                 // Field background:Ljava/lang/Boolean;
     127: aload_0
     128: iconst_1
     129: putfield      #30                 // Field initialized:Z
     132: getstatic     #48                 // Field logger:Lorg/apache/dubbo/common/logger/ErrorTypeAwareLogger;
     135: invokeinterface #49,  1           // InterfaceMethod org/apache/dubbo/common/logger/ErrorTypeAwareLogger.isInfoEnabled:()Z
     140: ifeq          173
     143: getstatic     #48                 // Field logger:Lorg/apache/dubbo/common/logger/ErrorTypeAwareLogger;
     146: new           #50                 // class java/lang/StringBuilder
     149: dup
     150: invokespecial #51                 // Method java/lang/StringBuilder."<init>":()V
     153: aload_0
     154: invokevirtual #52                 // Method getIdentifier:()Ljava/lang/String;
     157: invokevirtual #53                 // Method java/lang/StringBuilder.append:(Ljava/lang/String;)Ljava/lang/StringBuilder;
     160: ldc           #54                 // String  has been initialized!
     162: invokevirtual #53                 // Method java/lang/StringBuilder.append:(Ljava/lang/String;)Ljava/lang/StringBuilder;
     165: invokevirtual #55                 // Method java/lang/StringBuilder.toString:()Ljava/lang/String;
     168: invokeinterface #56,  2           // InterfaceMethod org/apache/dubbo/common/logger/ErrorTypeAwareLogger.info:(Ljava/lang/String;)V
     173: aload_1
     174: monitorexit
     175: goto          183
     178: astore_3
     179: aload_1
     180: monitorexit
     181: aload_3
     182: athrow
     183: return
    Exception table:
       from    to  target type
          12    21   178   any
          22   175   178   any
         178   181   178   any

  public java.util.concurrent.Future start() throws java.lang.IllegalStateException;
    Code:
       0: aload_0
       1: getfield      #22                 // Field applicationDeployer:Lorg/apache/dubbo/common/deploy/ApplicationDeployer;
       4: invokeinterface #57,  1           // InterfaceMethod org/apache/dubbo/common/deploy/ApplicationDeployer.initialize:()V
       9: aload_0
      10: invokespecial #58                 // Method startSync:()Ljava/util/concurrent/Future;
      13: areturn

  private synchronized java.util.concurrent.Future startSync() throws java.lang.IllegalStateException;
    Code:
       0: aload_0
       1: invokevirtual #59                 // Method isStopping:()Z
       4: ifne          21
       7: aload_0
       8: invokevirtual #60                 // Method isStopped:()Z
      11: ifne          21
      14: aload_0
      15: invokevirtual #61                 // Method isFailed:()Z
      18: ifeq          51
      21: new           #62                 // class java/lang/IllegalStateException
      24: dup
      25: new           #50                 // class java/lang/StringBuilder
      28: dup
      29: invokespecial #51                 // Method java/lang/StringBuilder."<init>":()V
      32: aload_0
      33: invokevirtual #52                 // Method getIdentifier:()Ljava/lang/String;
      36: invokevirtual #53                 // Method java/lang/StringBuilder.append:(Ljava/lang/String;)Ljava/lang/StringBuilder;
      39: ldc           #63                 // String  is stopping or stopped, can not start again
      41: invokevirtual #53                 // Method java/lang/StringBuilder.append:(Ljava/lang/String;)Ljava/lang/StringBuilder;
      44: invokevirtual #55                 // Method java/lang/StringBuilder.toString:()Ljava/lang/String;
      47: invokespecial #64                 // Method java/lang/IllegalStateException."<init>":(Ljava/lang/String;)V
      50: athrow
      51: aload_0
      52: invokevirtual #65                 // Method isStarting:()Z
      55: ifne          65
      58: aload_0
      59: invokevirtual #66                 // Method isStarted:()Z
      62: ifeq          70
      65: aload_0
      66: getfield      #67                 // Field startFuture:Ljava/util/concurrent/CompletableFuture;
      69: areturn
      70: aload_0
      71: invokespecial #68                 // Method onModuleStarting:()V
      74: aload_0
      75: invokevirtual #69                 // Method initialize:()V
      78: aload_0
      79: invokespecial #70                 // Method exportServices:()V
      82: aload_0
      83: getfield      #8                  // Field moduleModel:Lorg/apache/dubbo/rpc/model/ModuleModel;
      86: aload_0
      87: getfield      #8                  // Field moduleModel:Lorg/apache/dubbo/rpc/model/ModuleModel;
      90: invokevirtual #11                 // Method org/apache/dubbo/rpc/model/ModuleModel.getApplicationModel:()Lorg/apache/dubbo/rpc/model/ApplicationModel;
      93: invokevirtual #71                 // Method org/apache/dubbo/rpc/model/ApplicationModel.getInternalModule:()Lorg/apache/dubbo/rpc/model/ModuleModel;
      96: if_acmpeq     108
      99: aload_0
     100: getfield      #22                 // Field applicationDeployer:Lorg/apache/dubbo/common/deploy/ApplicationDeployer;
     103: invokeinterface #72,  1           // InterfaceMethod org/apache/dubbo/common/deploy/ApplicationDeployer.prepareInternalModule:()V
     108: aload_0
     109: invokespecial #73                 // Method referServices:()V
     112: aload_0
     113: getfield      #5                  // Field asyncExportingFutures:Ljava/util/List;
     116: invokeinterface #74,  1           // InterfaceMethod java/util/List.isEmpty:()Z
     121: ifeq          143
     124: aload_0
     125: getfield      #6                  // Field asyncReferringFutures:Ljava/util/List;
     128: invokeinterface #74,  1           // InterfaceMethod java/util/List.isEmpty:()Z
     133: ifeq          143
     136: aload_0
     137: invokespecial #75                 // Method onModuleStarted:()V
     140: goto          162
     143: aload_0
     144: getfield      #16                 // Field frameworkExecutorRepository:Lorg/apache/dubbo/common/threadpool/manager/FrameworkExecutorRepository;
     147: invokevirtual #76                 // Method org/apache/dubbo/common/threadpool/manager/FrameworkExecutorRepository.getSharedExecutor:()Ljava/util/concurrent/ExecutorService;
     150: aload_0
     151: invokedynamic #77,  0             // InvokeDynamic #1:run:(Lorg/apache/dubbo/config/deploy/DefaultModuleDeployer;)Ljava/lang/Runnable;
     156: invokeinterface #78,  2           // InterfaceMethod java/util/concurrent/ExecutorService.submit:(Ljava/lang/Runnable;)Ljava/util/concurrent/Future;
     161: pop
     162: goto          199
     165: astore_1
     166: aload_0
     167: new           #50                 // class java/lang/StringBuilder
     170: dup
     171: invokespecial #51                 // Method java/lang/StringBuilder."<init>":()V
     174: aload_0
     175: invokevirtual #52                 // Method getIdentifier:()Ljava/lang/String;
     178: invokevirtual #53                 // Method java/lang/StringBuilder.append:(Ljava/lang/String;)Ljava/lang/StringBuilder;
     181: ldc           #80                 // String  start failed:
     183: invokevirtual #53                 // Method java/lang/StringBuilder.append:(Ljava/lang/String;)Ljava/lang/StringBuilder;
     186: aload_1
     187: invokevirtual #81                 // Method java/lang/StringBuilder.append:(Ljava/lang/Object;)Ljava/lang/StringBuilder;
     190: invokevirtual #55                 // Method java/lang/StringBuilder.toString:()Ljava/lang/String;
     193: aload_1
     194: invokespecial #82                 // Method onModuleFailed:(Ljava/lang/String;Ljava/lang/Throwable;)V
     197: aload_1
     198: athrow
     199: aload_0
     200: getfield      #67                 // Field startFuture:Ljava/util/concurrent/CompletableFuture;
     203: areturn
    Exception table:
       from    to  target type
          51    69   165   Class java/lang/Throwable
          70   162   165   Class java/lang/Throwable

  public java.util.concurrent.Future getStartFuture();
    Code:
       0: aload_0
       1: getfield      #67                 // Field startFuture:Ljava/util/concurrent/CompletableFuture;
       4: areturn

  private boolean hasExportedServices();
    Code:
       0: aload_0
       1: getfield      #10                 // Field configManager:Lorg/apache/dubbo/config/context/ModuleConfigManager;
       4: invokevirtual #83                 // Method org/apache/dubbo/config/context/ModuleConfigManager.getServices:()Ljava/util/Collection;
       7: invokeinterface #84,  1           // InterfaceMethod java/util/Collection.size:()I
      12: ifle          19
      15: iconst_1
      16: goto          20
      19: iconst_0
      20: ireturn

  public void stop() throws java.lang.IllegalStateException;
    Code:
       0: aload_0
       1: getfield      #8                  // Field moduleModel:Lorg/apache/dubbo/rpc/model/ModuleModel;
       4: invokevirtual #85                 // Method org/apache/dubbo/rpc/model/ModuleModel.destroy:()V
       7: return

  public void preDestroy() throws java.lang.IllegalStateException;
    Code:
       0: aload_0
       1: invokevirtual #59                 // Method isStopping:()Z
       4: ifne          14
       7: aload_0
       8: invokevirtual #60                 // Method isStopped:()Z
      11: ifeq          15
      14: return
      15: aload_0
      16: invokespecial #86                 // Method onModuleStopping:()V
      19: aload_0
      20: invokespecial #87                 // Method offline:()V
      23: return

  private void offline();
    Code:
       0: aload_0
       1: getfield      #8                  // Field moduleModel:Lorg/apache/dubbo/rpc/model/ModuleModel;
       4: invokevirtual #88                 // Method org/apache/dubbo/rpc/model/ModuleModel.getServiceRepository:()Lorg/apache/dubbo/rpc/model/ModuleServiceRepository;
       7: astore_1
       8: aload_1
       9: invokevirtual #89                 // Method org/apache/dubbo/rpc/model/ModuleServiceRepository.getExportedServices:()Ljava/util/List;
      12: astore_2
      13: aload_2
      14: invokeinterface #90,  1           // InterfaceMethod java/util/List.iterator:()Ljava/util/Iterator;
      19: astore_3
      20: aload_3
      21: invokeinterface #27,  1           // InterfaceMethod java/util/Iterator.hasNext:()Z
      26: ifeq          98
      29: aload_3
      30: invokeinterface #28,  1           // InterfaceMethod java/util/Iterator.next:()Ljava/lang/Object;
      35: checkcast     #91                 // class org/apache/dubbo/rpc/model/ProviderModel
      38: astore        4
      40: aload         4
      42: invokevirtual #92                 // Method org/apache/dubbo/rpc/model/ProviderModel.getStatedUrl:()Ljava/util/List;
      45: astore        5
      47: aload         5
      49: invokeinterface #90,  1           // InterfaceMethod java/util/List.iterator:()Ljava/util/Iterator;
      54: astore        6
      56: aload         6
      58: invokeinterface #27,  1           // InterfaceMethod java/util/Iterator.hasNext:()Z
      63: ifeq          95
      66: aload         6
      68: invokeinterface #28,  1           // InterfaceMethod java/util/Iterator.next:()Ljava/lang/Object;
      73: checkcast     #93                 // class org/apache/dubbo/rpc/model/ProviderModel$RegisterStatedURL
      76: astore        7
      78: aload         7
      80: invokevirtual #94                 // Method org/apache/dubbo/rpc/model/ProviderModel$RegisterStatedURL.isRegistered:()Z
      83: ifeq          92
      86: aload_0
      87: aload         7
      89: invokespecial #95                 // Method doOffline:(Lorg/apache/dubbo/rpc/model/ProviderModel$RegisterStatedURL;)V
      92: goto          56
      95: goto          20
      98: goto          119
     101: astore_1
     102: getstatic     #48                 // Field logger:Lorg/apache/dubbo/common/logger/ErrorTypeAwareLogger;
     105: ldc           #96                 // String 99-0
     107: ldc           #97                 // String
     109: ldc           #97                 // String
     111: ldc           #98                 // String Exceptions occurred when unregister services.
     113: aload_1
     114: invokeinterface #99,  6           // InterfaceMethod org/apache/dubbo/common/logger/ErrorTypeAwareLogger.error:(Ljava/lang/String;Ljava/lang/String;Ljava/lang/String;Ljava/lang/String;Ljava/lang/Throwable;)V
     119: return
    Exception table:
       from    to  target type
           0    98   101   Class java/lang/Throwable

  private void doOffline(org.apache.dubbo.rpc.model.ProviderModel$RegisterStatedURL);
    Code:
       0: aload_1
       1: invokevirtual #100                // Method org/apache/dubbo/rpc/model/ProviderModel$RegisterStatedURL.getRegistryUrl:()Lorg/apache/dubbo/common/URL;
       4: invokevirtual #101                // Method org/apache/dubbo/common/URL.getOrDefaultApplicationModel:()Lorg/apache/dubbo/rpc/model/ApplicationModel;
       7: ldc           #102                // class org/apache/dubbo/registry/RegistryFactory
       9: invokevirtual #103                // Method org/apache/dubbo/rpc/model/ApplicationModel.getExtensionLoader:(Ljava/lang/Class;)Lorg/apache/dubbo/common/extension/ExtensionLoader;
      12: invokevirtual #104                // Method org/apache/dubbo/common/extension/ExtensionLoader.getAdaptiveExtension:()Ljava/lang/Object;
      15: checkcast     #102                // class org/apache/dubbo/registry/RegistryFactory
      18: astore_2
      19: aload_2
      20: aload_1
      21: invokevirtual #100                // Method org/apache/dubbo/rpc/model/ProviderModel$RegisterStatedURL.getRegistryUrl:()Lorg/apache/dubbo/common/URL;
      24: invokeinterface #105,  2          // InterfaceMethod org/apache/dubbo/registry/RegistryFactory.getRegistry:(Lorg/apache/dubbo/common/URL;)Lorg/apache/dubbo/registry/Registry;
      29: astore_3
      30: aload_3
      31: aload_1
      32: invokevirtual #106                // Method org/apache/dubbo/rpc/model/ProviderModel$RegisterStatedURL.getProviderUrl:()Lorg/apache/dubbo/common/URL;
      35: invokeinterface #107,  2          // InterfaceMethod org/apache/dubbo/registry/Registry.unregister:(Lorg/apache/dubbo/common/URL;)V
      40: aload_1
      41: iconst_0
      42: invokevirtual #108                // Method org/apache/dubbo/rpc/model/ProviderModel$RegisterStatedURL.setRegistered:(Z)V
      45: return

  public synchronized void postDestroy() throws java.lang.IllegalStateException;
    Code:
       0: aload_0
       1: invokevirtual #60                 // Method isStopped:()Z
       4: ifeq          8
       7: return
       8: aload_0
       9: invokespecial #109                // Method unexportServices:()V
      12: aload_0
      13: invokespecial #110                // Method unreferServices:()V
      16: aload_0
      17: getfield      #8                  // Field moduleModel:Lorg/apache/dubbo/rpc/model/ModuleModel;
      20: invokevirtual #88                 // Method org/apache/dubbo/rpc/model/ModuleModel.getServiceRepository:()Lorg/apache/dubbo/rpc/model/ModuleServiceRepository;
      23: astore_1
      24: aload_1
      25: ifnull        187
      28: aload_1
      29: invokevirtual #111                // Method org/apache/dubbo/rpc/model/ModuleServiceRepository.getReferredServices:()Ljava/util/List;
      32: astore_2
      33: aload_2
      34: invokeinterface #90,  1           // InterfaceMethod java/util/List.iterator:()Ljava/util/Iterator;
      39: astore_3
      40: aload_3
      41: invokeinterface #27,  1           // InterfaceMethod java/util/Iterator.hasNext:()Z
      46: ifeq          104
      49: aload_3
      50: invokeinterface #28,  1           // InterfaceMethod java/util/Iterator.next:()Ljava/lang/Object;
      55: checkcast     #112                // class org/apache/dubbo/rpc/model/ConsumerModel
      58: astore        4
      60: aload         4
      62: invokevirtual #113                // Method org/apache/dubbo/rpc/model/ConsumerModel.getDestroyRunner:()Ljava/lang/Runnable;
      65: ifnull        78
      68: aload         4
      70: invokevirtual #113                // Method org/apache/dubbo/rpc/model/ConsumerModel.getDestroyRunner:()Ljava/lang/Runnable;
      73: invokeinterface #114,  1          // InterfaceMethod java/lang/Runnable.run:()V
      78: goto          101
      81: astore        5
      83: getstatic     #48                 // Field logger:Lorg/apache/dubbo/common/logger/ErrorTypeAwareLogger;
      86: ldc           #115                // String 5-13
      88: ldc           #116                // String there are problems with the custom implementation.
      90: ldc           #97                 // String
      92: ldc           #117                // String Unable to destroy model: consumerModel.
      94: aload         5
      96: invokeinterface #99,  6           // InterfaceMethod org/apache/dubbo/common/logger/ErrorTypeAwareLogger.error:(Ljava/lang/String;Ljava/lang/String;Ljava/lang/String;Ljava/lang/String;Ljava/lang/Throwable;)V
     101: goto          40
     104: aload_1
     105: invokevirtual #89                 // Method org/apache/dubbo/rpc/model/ModuleServiceRepository.getExportedServices:()Ljava/util/List;
     108: astore_3
     109: aload_3
     110: invokeinterface #90,  1           // InterfaceMethod java/util/List.iterator:()Ljava/util/Iterator;
     115: astore        4
     117: aload         4
     119: invokeinterface #27,  1           // InterfaceMethod java/util/Iterator.hasNext:()Z
     124: ifeq          183
     127: aload         4
     129: invokeinterface #28,  1           // InterfaceMethod java/util/Iterator.next:()Ljava/lang/Object;
     134: checkcast     #91                 // class org/apache/dubbo/rpc/model/ProviderModel
     137: astore        5
     139: aload         5
     141: invokevirtual #118                // Method org/apache/dubbo/rpc/model/ProviderModel.getDestroyRunner:()Ljava/lang/Runnable;
     144: ifnull        157
     147: aload         5
     149: invokevirtual #118                // Method org/apache/dubbo/rpc/model/ProviderModel.getDestroyRunner:()Ljava/lang/Runnable;
     152: invokeinterface #114,  1          // InterfaceMethod java/lang/Runnable.run:()V
     157: goto          180
     160: astore        6
     162: getstatic     #48                 // Field logger:Lorg/apache/dubbo/common/logger/ErrorTypeAwareLogger;
     165: ldc           #115                // String 5-13
     167: ldc           #116                // String there are problems with the custom implementation.
     169: ldc           #97                 // String
     171: ldc           #119                // String Unable to destroy model: providerModel.
     173: aload         6
     175: invokeinterface #99,  6           // InterfaceMethod org/apache/dubbo/common/logger/ErrorTypeAwareLogger.error:(Ljava/lang/String;Ljava/lang/String;Ljava/lang/String;Ljava/lang/String;Ljava/lang/Throwable;)V
     180: goto          117
     183: aload_1
     184: invokevirtual #120                // Method org/apache/dubbo/rpc/model/ModuleServiceRepository.destroy:()V
     187: aload_0
     188: invokespecial #121                // Method onModuleStopped:()V
     191: return
    Exception table:
       from    to  target type
          60    78    81   Class java/lang/Throwable
         139   157   160   Class java/lang/Throwable

  private void onInitialize();
    Code:
       0: aload_0
       1: getfield      #122                // Field listeners:Ljava/util/List;
       4: invokeinterface #90,  1           // InterfaceMethod java/util/List.iterator:()Ljava/util/Iterator;
       9: astore_1
      10: aload_1
      11: invokeinterface #27,  1           // InterfaceMethod java/util/Iterator.hasNext:()Z
      16: ifeq          83
      19: aload_1
      20: invokeinterface #28,  1           // InterfaceMethod java/util/Iterator.next:()Ljava/lang/Object;
      25: checkcast     #123                // class org/apache/dubbo/common/deploy/DeployListener
      28: astore_2
      29: aload_2
      30: aload_0
      31: getfield      #8                  // Field moduleModel:Lorg/apache/dubbo/rpc/model/ModuleModel;
      34: invokeinterface #124,  2          // InterfaceMethod org/apache/dubbo/common/deploy/DeployListener.onInitialize:(Lorg/apache/dubbo/rpc/model/ScopeModel;)V
      39: goto          80
      42: astore_3
      43: getstatic     #48                 // Field logger:Lorg/apache/dubbo/common/logger/ErrorTypeAwareLogger;
      46: ldc           #125                // String 5-14
      48: ldc           #97                 // String
      50: ldc           #97                 // String
      52: new           #50                 // class java/lang/StringBuilder
      55: dup
      56: invokespecial #51                 // Method java/lang/StringBuilder."<init>":()V
      59: aload_0
      60: invokevirtual #52                 // Method getIdentifier:()Ljava/lang/String;
      63: invokevirtual #53                 // Method java/lang/StringBuilder.append:(Ljava/lang/String;)Ljava/lang/StringBuilder;
      66: ldc           #126                // String  an exception occurred when handle initialize event
      68: invokevirtual #53                 // Method java/lang/StringBuilder.append:(Ljava/lang/String;)Ljava/lang/StringBuilder;
      71: invokevirtual #55                 // Method java/lang/StringBuilder.toString:()Ljava/lang/String;
      74: aload_3
      75: invokeinterface #99,  6           // InterfaceMethod org/apache/dubbo/common/logger/ErrorTypeAwareLogger.error:(Ljava/lang/String;Ljava/lang/String;Ljava/lang/String;Ljava/lang/String;Ljava/lang/Throwable;)V
      80: goto          10
      83: return
    Exception table:
       from    to  target type
          29    39    42   Class java/lang/Throwable

  private void onModuleStarting();
    Code:
       0: aload_0
       1: invokevirtual #127                // Method setStarting:()V
       4: aload_0
       5: new           #128                // class java/util/concurrent/CompletableFuture
       8: dup
       9: invokespecial #129                // Method java/util/concurrent/CompletableFuture."<init>":()V
      12: putfield      #67                 // Field startFuture:Ljava/util/concurrent/CompletableFuture;
      15: getstatic     #48                 // Field logger:Lorg/apache/dubbo/common/logger/ErrorTypeAwareLogger;
      18: new           #50                 // class java/lang/StringBuilder
      21: dup
      22: invokespecial #51                 // Method java/lang/StringBuilder."<init>":()V
      25: aload_0
      26: invokevirtual #52                 // Method getIdentifier:()Ljava/lang/String;
      29: invokevirtual #53                 // Method java/lang/StringBuilder.append:(Ljava/lang/String;)Ljava/lang/StringBuilder;
      32: ldc           #130                // String  is starting.
      34: invokevirtual #53                 // Method java/lang/StringBuilder.append:(Ljava/lang/String;)Ljava/lang/StringBuilder;
      37: invokevirtual #55                 // Method java/lang/StringBuilder.toString:()Ljava/lang/String;
      40: invokeinterface #56,  2           // InterfaceMethod org/apache/dubbo/common/logger/ErrorTypeAwareLogger.info:(Ljava/lang/String;)V
      45: aload_0
      46: getfield      #22                 // Field applicationDeployer:Lorg/apache/dubbo/common/deploy/ApplicationDeployer;
      49: aload_0
      50: getfield      #8                  // Field moduleModel:Lorg/apache/dubbo/rpc/model/ModuleModel;
      53: getstatic     #131                // Field org/apache/dubbo/common/deploy/DeployState.STARTING:Lorg/apache/dubbo/common/deploy/DeployState;
      56: invokeinterface #132,  3          // InterfaceMethod org/apache/dubbo/common/deploy/ApplicationDeployer.notifyModuleChanged:(Lorg/apache/dubbo/rpc/model/ModuleModel;Lorg/apache/dubbo/common/deploy/DeployState;)V
      61: return

  private void onModuleStarted();
    Code:
       0: aload_0
       1: invokevirtual #65                 // Method isStarting:()Z
       4: ifeq          57
       7: aload_0
       8: invokevirtual #133                // Method setStarted:()V
      11: getstatic     #48                 // Field logger:Lorg/apache/dubbo/common/logger/ErrorTypeAwareLogger;
      14: new           #50                 // class java/lang/StringBuilder
      17: dup
      18: invokespecial #51                 // Method java/lang/StringBuilder."<init>":()V
      21: aload_0
      22: invokevirtual #52                 // Method getIdentifier:()Ljava/lang/String;
      25: invokevirtual #53                 // Method java/lang/StringBuilder.append:(Ljava/lang/String;)Ljava/lang/StringBuilder;
      28: ldc           #134                // String  has started.
      30: invokevirtual #53                 // Method java/lang/StringBuilder.append:(Ljava/lang/String;)Ljava/lang/StringBuilder;
      33: invokevirtual #55                 // Method java/lang/StringBuilder.toString:()Ljava/lang/String;
      36: invokeinterface #56,  2           // InterfaceMethod org/apache/dubbo/common/logger/ErrorTypeAwareLogger.info:(Ljava/lang/String;)V
      41: aload_0
      42: getfield      #22                 // Field applicationDeployer:Lorg/apache/dubbo/common/deploy/ApplicationDeployer;
      45: aload_0
      46: getfield      #8                  // Field moduleModel:Lorg/apache/dubbo/rpc/model/ModuleModel;
      49: getstatic     #135                // Field org/apache/dubbo/common/deploy/DeployState.STARTED:Lorg/apache/dubbo/common/deploy/DeployState;
      52: invokeinterface #132,  3          // InterfaceMethod org/apache/dubbo/common/deploy/ApplicationDeployer.notifyModuleChanged:(Lorg/apache/dubbo/rpc/model/ModuleModel;Lorg/apache/dubbo/common/deploy/DeployState;)V
      57: aload_0
      58: iconst_1
      59: invokespecial #136                // Method completeStartFuture:(Z)V
      62: goto          73
      65: astore_1
      66: aload_0
      67: iconst_1
      68: invokespecial #136                // Method completeStartFuture:(Z)V
      71: aload_1
      72: athrow
      73: return
    Exception table:
       from    to  target type
           0    57    65   any

  private void onModuleFailed(java.lang.String, java.lang.Throwable);
    Code:
       0: aload_0
       1: aload_2
       2: invokevirtual #137                // Method setFailed:(Ljava/lang/Throwable;)V
       5: getstatic     #48                 // Field logger:Lorg/apache/dubbo/common/logger/ErrorTypeAwareLogger;
       8: ldc           #125                // String 5-14
      10: ldc           #97                 // String
      12: ldc           #97                 // String
      14: new           #50                 // class java/lang/StringBuilder
      17: dup
      18: invokespecial #51                 // Method java/lang/StringBuilder."<init>":()V
      21: ldc           #138                // String Model start failed:
      23: invokevirtual #53                 // Method java/lang/StringBuilder.append:(Ljava/lang/String;)Ljava/lang/StringBuilder;
      26: aload_1
      27: invokevirtual #53                 // Method java/lang/StringBuilder.append:(Ljava/lang/String;)Ljava/lang/StringBuilder;
      30: invokevirtual #55                 // Method java/lang/StringBuilder.toString:()Ljava/lang/String;
      33: aload_2
      34: invokeinterface #99,  6           // InterfaceMethod org/apache/dubbo/common/logger/ErrorTypeAwareLogger.error:(Ljava/lang/String;Ljava/lang/String;Ljava/lang/String;Ljava/lang/String;Ljava/lang/Throwable;)V
      39: aload_0
      40: getfield      #22                 // Field applicationDeployer:Lorg/apache/dubbo/common/deploy/ApplicationDeployer;
      43: aload_0
      44: getfield      #8                  // Field moduleModel:Lorg/apache/dubbo/rpc/model/ModuleModel;
      47: getstatic     #139                // Field org/apache/dubbo/common/deploy/DeployState.FAILED:Lorg/apache/dubbo/common/deploy/DeployState;
      50: invokeinterface #132,  3          // InterfaceMethod org/apache/dubbo/common/deploy/ApplicationDeployer.notifyModuleChanged:(Lorg/apache/dubbo/rpc/model/ModuleModel;Lorg/apache/dubbo/common/deploy/DeployState;)V
      55: aload_0
      56: iconst_0
      57: invokespecial #136                // Method completeStartFuture:(Z)V
      60: goto          71
      63: astore_3
      64: aload_0
      65: iconst_0
      66: invokespecial #136                // Method completeStartFuture:(Z)V
      69: aload_3
      70: athrow
      71: return
    Exception table:
       from    to  target type
           0    55    63   any

  private void completeStartFuture(boolean);
    Code:
       0: aload_0
       1: getfield      #67                 // Field startFuture:Ljava/util/concurrent/CompletableFuture;
       4: ifnull        29
       7: aload_0
       8: getfield      #67                 // Field startFuture:Ljava/util/concurrent/CompletableFuture;
      11: invokevirtual #140                // Method java/util/concurrent/CompletableFuture.isDone:()Z
      14: ifne          29
      17: aload_0
      18: getfield      #67                 // Field startFuture:Ljava/util/concurrent/CompletableFuture;
      21: iload_1
      22: invokestatic  #40                 // Method java/lang/Boolean.valueOf:(Z)Ljava/lang/Boolean;
      25: invokevirtual #141                // Method java/util/concurrent/CompletableFuture.complete:(Ljava/lang/Object;)Z
      28: pop
      29: aload_0
      30: getfield      #142                // Field exportFuture:Ljava/util/concurrent/CompletableFuture;
      33: ifnull        55
      36: aload_0
      37: getfield      #142                // Field exportFuture:Ljava/util/concurrent/CompletableFuture;
      40: invokevirtual #140                // Method java/util/concurrent/CompletableFuture.isDone:()Z
      43: ifne          55
      46: aload_0
      47: getfield      #142                // Field exportFuture:Ljava/util/concurrent/CompletableFuture;
      50: iconst_1
      51: invokevirtual #143                // Method java/util/concurrent/CompletableFuture.cancel:(Z)Z
      54: pop
      55: aload_0
      56: getfield      #144                // Field referFuture:Ljava/util/concurrent/CompletableFuture;
      59: ifnull        81
      62: aload_0
      63: getfield      #144                // Field referFuture:Ljava/util/concurrent/CompletableFuture;
      66: invokevirtual #140                // Method java/util/concurrent/CompletableFuture.isDone:()Z
      69: ifne          81
      72: aload_0
      73: getfield      #144                // Field referFuture:Ljava/util/concurrent/CompletableFuture;
      76: iconst_1
      77: invokevirtual #143                // Method java/util/concurrent/CompletableFuture.cancel:(Z)Z
      80: pop
      81: return

  private void onModuleStopping();
    Code:
       0: aload_0
       1: invokevirtual #145                // Method setStopping:()V
       4: getstatic     #48                 // Field logger:Lorg/apache/dubbo/common/logger/ErrorTypeAwareLogger;
       7: new           #50                 // class java/lang/StringBuilder
      10: dup
      11: invokespecial #51                 // Method java/lang/StringBuilder."<init>":()V
      14: aload_0
      15: invokevirtual #52                 // Method getIdentifier:()Ljava/lang/String;
      18: invokevirtual #53                 // Method java/lang/StringBuilder.append:(Ljava/lang/String;)Ljava/lang/StringBuilder;
      21: ldc           #146                // String  is stopping.
      23: invokevirtual #53                 // Method java/lang/StringBuilder.append:(Ljava/lang/String;)Ljava/lang/StringBuilder;
      26: invokevirtual #55                 // Method java/lang/StringBuilder.toString:()Ljava/lang/String;
      29: invokeinterface #56,  2           // InterfaceMethod org/apache/dubbo/common/logger/ErrorTypeAwareLogger.info:(Ljava/lang/String;)V
      34: aload_0
      35: getfield      #22                 // Field applicationDeployer:Lorg/apache/dubbo/common/deploy/ApplicationDeployer;
      38: aload_0
      39: getfield      #8                  // Field moduleModel:Lorg/apache/dubbo/rpc/model/ModuleModel;
      42: getstatic     #147                // Field org/apache/dubbo/common/deploy/DeployState.STOPPING:Lorg/apache/dubbo/common/deploy/DeployState;
      45: invokeinterface #132,  3          // InterfaceMethod org/apache/dubbo/common/deploy/ApplicationDeployer.notifyModuleChanged:(Lorg/apache/dubbo/rpc/model/ModuleModel;Lorg/apache/dubbo/common/deploy/DeployState;)V
      50: aload_0
      51: iconst_0
      52: invokespecial #136                // Method completeStartFuture:(Z)V
      55: goto          66
      58: astore_1
      59: aload_0
      60: iconst_0
      61: invokespecial #136                // Method completeStartFuture:(Z)V
      64: aload_1
      65: athrow
      66: return
    Exception table:
       from    to  target type
           0    50    58   any

  private void onModuleStopped();
    Code:
       0: aload_0
       1: invokevirtual #148                // Method setStopped:()V
       4: getstatic     #48                 // Field logger:Lorg/apache/dubbo/common/logger/ErrorTypeAwareLogger;
       7: new           #50                 // class java/lang/StringBuilder
      10: dup
      11: invokespecial #51                 // Method java/lang/StringBuilder."<init>":()V
      14: aload_0
      15: invokevirtual #52                 // Method getIdentifier:()Ljava/lang/String;
      18: invokevirtual #53                 // Method java/lang/StringBuilder.append:(Ljava/lang/String;)Ljava/lang/StringBuilder;
      21: ldc           #149                // String  has stopped.
      23: invokevirtual #53                 // Method java/lang/StringBuilder.append:(Ljava/lang/String;)Ljava/lang/StringBuilder;
      26: invokevirtual #55                 // Method java/lang/StringBuilder.toString:()Ljava/lang/String;
      29: invokeinterface #56,  2           // InterfaceMethod org/apache/dubbo/common/logger/ErrorTypeAwareLogger.info:(Ljava/lang/String;)V
      34: aload_0
      35: getfield      #22                 // Field applicationDeployer:Lorg/apache/dubbo/common/deploy/ApplicationDeployer;
      38: aload_0
      39: getfield      #8                  // Field moduleModel:Lorg/apache/dubbo/rpc/model/ModuleModel;
      42: getstatic     #150                // Field org/apache/dubbo/common/deploy/DeployState.STOPPED:Lorg/apache/dubbo/common/deploy/DeployState;
      45: invokeinterface #132,  3          // InterfaceMethod org/apache/dubbo/common/deploy/ApplicationDeployer.notifyModuleChanged:(Lorg/apache/dubbo/rpc/model/ModuleModel;Lorg/apache/dubbo/common/deploy/DeployState;)V
      50: aload_0
      51: iconst_0
      52: invokespecial #136                // Method completeStartFuture:(Z)V
      55: goto          66
      58: astore_1
      59: aload_0
      60: iconst_0
      61: invokespecial #136                // Method completeStartFuture:(Z)V
      64: aload_1
      65: athrow
      66: return
    Exception table:
       from    to  target type
           0    50    58   any

  private void loadConfigs();
    Code:
       0: aload_0
       1: getfield      #8                  // Field moduleModel:Lorg/apache/dubbo/rpc/model/ModuleModel;
       4: invokevirtual #9                  // Method org/apache/dubbo/rpc/model/ModuleModel.getConfigManager:()Lorg/apache/dubbo/config/context/ModuleConfigManager;
       7: invokevirtual #151                // Method org/apache/dubbo/config/context/ModuleConfigManager.loadConfigs:()V
      10: aload_0
      11: getfield      #8                  // Field moduleModel:Lorg/apache/dubbo/rpc/model/ModuleModel;
      14: invokevirtual #9                  // Method org/apache/dubbo/rpc/model/ModuleModel.getConfigManager:()Lorg/apache/dubbo/config/context/ModuleConfigManager;
      17: invokevirtual #152                // Method org/apache/dubbo/config/context/ModuleConfigManager.refreshAll:()V
      20: return

  private void exportServices();
    Code:
       0: aload_0
       1: getfield      #10                 // Field configManager:Lorg/apache/dubbo/config/context/ModuleConfigManager;
       4: invokevirtual #83                 // Method org/apache/dubbo/config/context/ModuleConfigManager.getServices:()Ljava/util/Collection;
       7: invokeinterface #153,  1          // InterfaceMethod java/util/Collection.iterator:()Ljava/util/Iterator;
      12: astore_1
      13: aload_1
      14: invokeinterface #27,  1           // InterfaceMethod java/util/Iterator.hasNext:()Z
      19: ifeq          40
      22: aload_1
      23: invokeinterface #28,  1           // InterfaceMethod java/util/Iterator.next:()Ljava/lang/Object;
      28: checkcast     #154                // class org/apache/dubbo/config/ServiceConfigBase
      31: astore_2
      32: aload_0
      33: aload_2
      34: invokespecial #155                // Method exportServiceInternal:(Lorg/apache/dubbo/config/ServiceConfigBase;)V
      37: goto          13
      40: return

  private void exportServiceInternal(org.apache.dubbo.config.ServiceConfigBase);
    Code:
       0: aload_1
       1: checkcast     #156                // class org/apache/dubbo/config/ServiceConfig
       4: astore_2
       5: aload_2
       6: invokevirtual #157                // Method org/apache/dubbo/config/ServiceConfig.isRefreshed:()Z
       9: ifne          16
      12: aload_2
      13: invokevirtual #158                // Method org/apache/dubbo/config/ServiceConfig.refresh:()V
      16: aload_1
      17: invokevirtual #159                // Method org/apache/dubbo/config/ServiceConfigBase.isExported:()Z
      20: ifeq          24
      23: return
      24: aload_0
      25: getfield      #41                 // Field exportAsync:Ljava/lang/Boolean;
      28: invokevirtual #160                // Method java/lang/Boolean.booleanValue:()Z
      31: ifne          44
      34: aload_1
      35: invokevirtual #161                // Method org/apache/dubbo/config/ServiceConfigBase.shouldExportAsync:()Ljava/lang/Boolean;
      38: invokevirtual #160                // Method java/lang/Boolean.booleanValue:()Z
      41: ifeq          82
      44: aload_0
      45: getfield      #18                 // Field executorRepository:Lorg/apache/dubbo/common/threadpool/manager/ExecutorRepository;
      48: invokeinterface #162,  1          // InterfaceMethod org/apache/dubbo/common/threadpool/manager/ExecutorRepository.getServiceExportExecutor:()Ljava/util/concurrent/ScheduledExecutorService;
      53: astore_3
      54: aload_0
      55: aload_1
      56: invokedynamic #163,  0            // InvokeDynamic #2:run:(Lorg/apache/dubbo/config/deploy/DefaultModuleDeployer;Lorg/apache/dubbo/config/ServiceConfigBase;)Ljava/lang/Runnable;
      61: aload_3
      62: invokestatic  #164                // Method java/util/concurrent/CompletableFuture.runAsync:(Ljava/lang/Runnable;Ljava/util/concurrent/Executor;)Ljava/util/concurrent/CompletableFuture;
      65: astore        4
      67: aload_0
      68: getfield      #5                  // Field asyncExportingFutures:Ljava/util/List;
      71: aload         4
      73: invokeinterface #165,  2          // InterfaceMethod java/util/List.add:(Ljava/lang/Object;)Z
      78: pop
      79: goto          104
      82: aload_1
      83: invokevirtual #159                // Method org/apache/dubbo/config/ServiceConfigBase.isExported:()Z
      86: ifne          104
      89: aload_1
      90: invokevirtual #166                // Method org/apache/dubbo/config/ServiceConfigBase.export:()V
      93: aload_0
      94: getfield      #7                  // Field exportedServices:Ljava/util/List;
      97: aload_1
      98: invokeinterface #165,  2          // InterfaceMethod java/util/List.add:(Ljava/lang/Object;)Z
     103: pop
     104: return

  private void unexportServices();
    Code:
       0: aload_0
       1: getfield      #7                  // Field exportedServices:Ljava/util/List;
       4: aload_0
       5: invokedynamic #167,  0            // InvokeDynamic #3:accept:(Lorg/apache/dubbo/config/deploy/DefaultModuleDeployer;)Ljava/util/function/Consumer;
      10: invokeinterface #168,  2          // InterfaceMethod java/util/List.forEach:(Ljava/util/function/Consumer;)V
      15: aload_0
      16: getfield      #7                  // Field exportedServices:Ljava/util/List;
      19: invokeinterface #169,  1          // InterfaceMethod java/util/List.clear:()V
      24: aload_0
      25: getfield      #5                  // Field asyncExportingFutures:Ljava/util/List;
      28: invokedynamic #170,  0            // InvokeDynamic #4:accept:()Ljava/util/function/Consumer;
      33: invokeinterface #168,  2          // InterfaceMethod java/util/List.forEach:(Ljava/util/function/Consumer;)V
      38: aload_0
      39: getfield      #5                  // Field asyncExportingFutures:Ljava/util/List;
      42: invokeinterface #169,  1          // InterfaceMethod java/util/List.clear:()V
      47: return

  private void referServices();
    Code:
       0: aload_0
       1: getfield      #10                 // Field configManager:Lorg/apache/dubbo/config/context/ModuleConfigManager;
       4: invokevirtual #171                // Method org/apache/dubbo/config/context/ModuleConfigManager.getReferences:()Ljava/util/Collection;
       7: aload_0
       8: invokedynamic #172,  0            // InvokeDynamic #5:accept:(Lorg/apache/dubbo/config/deploy/DefaultModuleDeployer;)Ljava/util/function/Consumer;
      13: invokeinterface #173,  2          // InterfaceMethod java/util/Collection.forEach:(Ljava/util/function/Consumer;)V
      18: return

  private void unreferServices();
    Code:
       0: aload_0
       1: getfield      #6                  // Field asyncReferringFutures:Ljava/util/List;
       4: invokedynamic #174,  0            // InvokeDynamic #6:accept:()Ljava/util/function/Consumer;
       9: invokeinterface #168,  2          // InterfaceMethod java/util/List.forEach:(Ljava/util/function/Consumer;)V
      14: aload_0
      15: getfield      #6                  // Field asyncReferringFutures:Ljava/util/List;
      18: invokeinterface #169,  1          // InterfaceMethod java/util/List.clear:()V
      23: aload_0
      24: getfield      #20                 // Field referenceCache:Lorg/apache/dubbo/config/utils/SimpleReferenceCache;
      27: invokevirtual #175                // Method org/apache/dubbo/config/utils/SimpleReferenceCache.destroyAll:()V
      30: goto          34
      33: astore_1
      34: return
    Exception table:
       from    to  target type
           0    30    33   Class java/lang/Exception

  private void waitExportFinish();
    Code:
       0: getstatic     #48                 // Field logger:Lorg/apache/dubbo/common/logger/ErrorTypeAwareLogger;
       3: new           #50                 // class java/lang/StringBuilder
       6: dup
       7: invokespecial #51                 // Method java/lang/StringBuilder."<init>":()V
      10: aload_0
      11: invokevirtual #52                 // Method getIdentifier:()Ljava/lang/String;
      14: invokevirtual #53                 // Method java/lang/StringBuilder.append:(Ljava/lang/String;)Ljava/lang/StringBuilder;
      17: ldc           #177                // String  waiting services exporting ...
      19: invokevirtual #53                 // Method java/lang/StringBuilder.append:(Ljava/lang/String;)Ljava/lang/StringBuilder;
      22: invokevirtual #55                 // Method java/lang/StringBuilder.toString:()Ljava/lang/String;
      25: invokeinterface #56,  2           // InterfaceMethod org/apache/dubbo/common/logger/ErrorTypeAwareLogger.info:(Ljava/lang/String;)V
      30: aload_0
      31: aload_0
      32: getfield      #5                  // Field asyncExportingFutures:Ljava/util/List;
      35: iconst_0
      36: anewarray     #128                // class java/util/concurrent/CompletableFuture
      39: invokeinterface #178,  2          // InterfaceMethod java/util/List.toArray:([Ljava/lang/Object;)[Ljava/lang/Object;
      44: checkcast     #179                // class "[Ljava/util/concurrent/CompletableFuture;"
      47: invokestatic  #180                // Method java/util/concurrent/CompletableFuture.allOf:([Ljava/util/concurrent/CompletableFuture;)Ljava/util/concurrent/CompletableFuture;
      50: putfield      #142                // Field exportFuture:Ljava/util/concurrent/CompletableFuture;
      53: aload_0
      54: getfield      #142                // Field exportFuture:Ljava/util/concurrent/CompletableFuture;
      57: invokevirtual #181                // Method java/util/concurrent/CompletableFuture.get:()Ljava/lang/Object;
      60: pop
      61: getstatic     #48                 // Field logger:Lorg/apache/dubbo/common/logger/ErrorTypeAwareLogger;
      64: new           #50                 // class java/lang/StringBuilder
      67: dup
      68: invokespecial #51                 // Method java/lang/StringBuilder."<init>":()V
      71: aload_0
      72: invokevirtual #52                 // Method getIdentifier:()Ljava/lang/String;
      75: invokevirtual #53                 // Method java/lang/StringBuilder.append:(Ljava/lang/String;)Ljava/lang/StringBuilder;
      78: ldc           #182                // String  export services finished.
      80: invokevirtual #53                 // Method java/lang/StringBuilder.append:(Ljava/lang/String;)Ljava/lang/StringBuilder;
      83: invokevirtual #55                 // Method java/lang/StringBuilder.toString:()Ljava/lang/String;
      86: invokeinterface #56,  2           // InterfaceMethod org/apache/dubbo/common/logger/ErrorTypeAwareLogger.info:(Ljava/lang/String;)V
      91: aload_0
      92: getfield      #5                  // Field asyncExportingFutures:Ljava/util/List;
      95: invokeinterface #169,  1          // InterfaceMethod java/util/List.clear:()V
     100: goto          231
     103: astore_1
     104: getstatic     #48                 // Field logger:Lorg/apache/dubbo/common/logger/ErrorTypeAwareLogger;
     107: ldc           #183                // String 5-9
     109: ldc           #97                 // String
     111: ldc           #97                 // String
     113: new           #50                 // class java/lang/StringBuilder
     116: dup
     117: invokespecial #51                 // Method java/lang/StringBuilder."<init>":()V
     120: aload_0
     121: invokevirtual #52                 // Method getIdentifier:()Ljava/lang/String;
     124: invokevirtual #53                 // Method java/lang/StringBuilder.append:(Ljava/lang/String;)Ljava/lang/StringBuilder;
     127: ldc           #184                // String  export services occurred an exception:
     129: invokevirtual #53                 // Method java/lang/StringBuilder.append:(Ljava/lang/String;)Ljava/lang/StringBuilder;
     132: aload_1
     133: invokevirtual #185                // Method java/lang/Throwable.toString:()Ljava/lang/String;
     136: invokevirtual #53                 // Method java/lang/StringBuilder.append:(Ljava/lang/String;)Ljava/lang/StringBuilder;
     139: invokevirtual #55                 // Method java/lang/StringBuilder.toString:()Ljava/lang/String;
     142: invokeinterface #186,  5          // InterfaceMethod org/apache/dubbo/common/logger/ErrorTypeAwareLogger.warn:(Ljava/lang/String;Ljava/lang/String;Ljava/lang/String;Ljava/lang/String;)V
     147: getstatic     #48                 // Field logger:Lorg/apache/dubbo/common/logger/ErrorTypeAwareLogger;
     150: new           #50                 // class java/lang/StringBuilder
     153: dup
     154: invokespecial #51                 // Method java/lang/StringBuilder."<init>":()V
     157: aload_0
     158: invokevirtual #52                 // Method getIdentifier:()Ljava/lang/String;
     161: invokevirtual #53                 // Method java/lang/StringBuilder.append:(Ljava/lang/String;)Ljava/lang/StringBuilder;
     164: ldc           #182                // String  export services finished.
     166: invokevirtual #53                 // Method java/lang/StringBuilder.append:(Ljava/lang/String;)Ljava/lang/StringBuilder;
     169: invokevirtual #55                 // Method java/lang/StringBuilder.toString:()Ljava/lang/String;
     172: invokeinterface #56,  2           // InterfaceMethod org/apache/dubbo/common/logger/ErrorTypeAwareLogger.info:(Ljava/lang/String;)V
     177: aload_0
     178: getfield      #5                  // Field asyncExportingFutures:Ljava/util/List;
     181: invokeinterface #169,  1          // InterfaceMethod java/util/List.clear:()V
     186: goto          231
     189: astore_2
     190: getstatic     #48                 // Field logger:Lorg/apache/dubbo/common/logger/ErrorTypeAwareLogger;
     193: new           #50                 // class java/lang/StringBuilder
     196: dup
     197: invokespecial #51                 // Method java/lang/StringBuilder."<init>":()V
     200: aload_0
     201: invokevirtual #52                 // Method getIdentifier:()Ljava/lang/String;
     204: invokevirtual #53                 // Method java/lang/StringBuilder.append:(Ljava/lang/String;)Ljava/lang/StringBuilder;
     207: ldc           #182                // String  export services finished.
     209: invokevirtual #53                 // Method java/lang/StringBuilder.append:(Ljava/lang/String;)Ljava/lang/StringBuilder;
     212: invokevirtual #55                 // Method java/lang/StringBuilder.toString:()Ljava/lang/String;
     215: invokeinterface #56,  2           // InterfaceMethod org/apache/dubbo/common/logger/ErrorTypeAwareLogger.info:(Ljava/lang/String;)V
     220: aload_0
     221: getfield      #5                  // Field asyncExportingFutures:Ljava/util/List;
     224: invokeinterface #169,  1          // InterfaceMethod java/util/List.clear:()V
     229: aload_2
     230: athrow
     231: return
    Exception table:
       from    to  target type
           0    61   103   Class java/lang/Throwable
           0    61   189   any
         103   147   189   any

  private void waitReferFinish();
    Code:
       0: getstatic     #48                 // Field logger:Lorg/apache/dubbo/common/logger/ErrorTypeAwareLogger;
       3: new           #50                 // class java/lang/StringBuilder
       6: dup
       7: invokespecial #51                 // Method java/lang/StringBuilder."<init>":()V
      10: aload_0
      11: invokevirtual #52                 // Method getIdentifier:()Ljava/lang/String;
      14: invokevirtual #53                 // Method java/lang/StringBuilder.append:(Ljava/lang/String;)Ljava/lang/StringBuilder;
      17: ldc           #187                // String  waiting services referring ...
      19: invokevirtual #53                 // Method java/lang/StringBuilder.append:(Ljava/lang/String;)Ljava/lang/StringBuilder;
      22: invokevirtual #55                 // Method java/lang/StringBuilder.toString:()Ljava/lang/String;
      25: invokeinterface #56,  2           // InterfaceMethod org/apache/dubbo/common/logger/ErrorTypeAwareLogger.info:(Ljava/lang/String;)V
      30: aload_0
      31: aload_0
      32: getfield      #6                  // Field asyncReferringFutures:Ljava/util/List;
      35: iconst_0
      36: anewarray     #128                // class java/util/concurrent/CompletableFuture
      39: invokeinterface #178,  2          // InterfaceMethod java/util/List.toArray:([Ljava/lang/Object;)[Ljava/lang/Object;
      44: checkcast     #179                // class "[Ljava/util/concurrent/CompletableFuture;"
      47: invokestatic  #180                // Method java/util/concurrent/CompletableFuture.allOf:([Ljava/util/concurrent/CompletableFuture;)Ljava/util/concurrent/CompletableFuture;
      50: putfield      #144                // Field referFuture:Ljava/util/concurrent/CompletableFuture;
      53: aload_0
      54: getfield      #144                // Field referFuture:Ljava/util/concurrent/CompletableFuture;
      57: invokevirtual #181                // Method java/util/concurrent/CompletableFuture.get:()Ljava/lang/Object;
      60: pop
      61: getstatic     #48                 // Field logger:Lorg/apache/dubbo/common/logger/ErrorTypeAwareLogger;
      64: new           #50                 // class java/lang/StringBuilder
      67: dup
      68: invokespecial #51                 // Method java/lang/StringBuilder."<init>":()V
      71: aload_0
      72: invokevirtual #52                 // Method getIdentifier:()Ljava/lang/String;
      75: invokevirtual #53                 // Method java/lang/StringBuilder.append:(Ljava/lang/String;)Ljava/lang/StringBuilder;
      78: ldc           #188                // String  refer services finished.
      80: invokevirtual #53                 // Method java/lang/StringBuilder.append:(Ljava/lang/String;)Ljava/lang/StringBuilder;
      83: invokevirtual #55                 // Method java/lang/StringBuilder.toString:()Ljava/lang/String;
      86: invokeinterface #56,  2           // InterfaceMethod org/apache/dubbo/common/logger/ErrorTypeAwareLogger.info:(Ljava/lang/String;)V
      91: aload_0
      92: getfield      #6                  // Field asyncReferringFutures:Ljava/util/List;
      95: invokeinterface #169,  1          // InterfaceMethod java/util/List.clear:()V
     100: goto          231
     103: astore_1
     104: getstatic     #48                 // Field logger:Lorg/apache/dubbo/common/logger/ErrorTypeAwareLogger;
     107: ldc           #189                // String 5-24
     109: ldc           #97                 // String
     111: ldc           #97                 // String
     113: new           #50                 // class java/lang/StringBuilder
     116: dup
     117: invokespecial #51                 // Method java/lang/StringBuilder."<init>":()V
     120: aload_0
     121: invokevirtual #52                 // Method getIdentifier:()Ljava/lang/String;
     124: invokevirtual #53                 // Method java/lang/StringBuilder.append:(Ljava/lang/String;)Ljava/lang/StringBuilder;
     127: ldc           #190                // String  refer services occurred an exception:
     129: invokevirtual #53                 // Method java/lang/StringBuilder.append:(Ljava/lang/String;)Ljava/lang/StringBuilder;
     132: aload_1
     133: invokevirtual #185                // Method java/lang/Throwable.toString:()Ljava/lang/String;
     136: invokevirtual #53                 // Method java/lang/StringBuilder.append:(Ljava/lang/String;)Ljava/lang/StringBuilder;
     139: invokevirtual #55                 // Method java/lang/StringBuilder.toString:()Ljava/lang/String;
     142: invokeinterface #186,  5          // InterfaceMethod org/apache/dubbo/common/logger/ErrorTypeAwareLogger.warn:(Ljava/lang/String;Ljava/lang/String;Ljava/lang/String;Ljava/lang/String;)V
     147: getstatic     #48                 // Field logger:Lorg/apache/dubbo/common/logger/ErrorTypeAwareLogger;
     150: new           #50                 // class java/lang/StringBuilder
     153: dup
     154: invokespecial #51                 // Method java/lang/StringBuilder."<init>":()V
     157: aload_0
     158: invokevirtual #52                 // Method getIdentifier:()Ljava/lang/String;
     161: invokevirtual #53                 // Method java/lang/StringBuilder.append:(Ljava/lang/String;)Ljava/lang/StringBuilder;
     164: ldc           #188                // String  refer services finished.
     166: invokevirtual #53                 // Method java/lang/StringBuilder.append:(Ljava/lang/String;)Ljava/lang/StringBuilder;
     169: invokevirtual #55                 // Method java/lang/StringBuilder.toString:()Ljava/lang/String;
     172: invokeinterface #56,  2           // InterfaceMethod org/apache/dubbo/common/logger/ErrorTypeAwareLogger.info:(Ljava/lang/String;)V
     177: aload_0
     178: getfield      #6                  // Field asyncReferringFutures:Ljava/util/List;
     181: invokeinterface #169,  1          // InterfaceMethod java/util/List.clear:()V
     186: goto          231
     189: astore_2
     190: getstatic     #48                 // Field logger:Lorg/apache/dubbo/common/logger/ErrorTypeAwareLogger;
     193: new           #50                 // class java/lang/StringBuilder
     196: dup
     197: invokespecial #51                 // Method java/lang/StringBuilder."<init>":()V
     200: aload_0
     201: invokevirtual #52                 // Method getIdentifier:()Ljava/lang/String;
     204: invokevirtual #53                 // Method java/lang/StringBuilder.append:(Ljava/lang/String;)Ljava/lang/StringBuilder;
     207: ldc           #188                // String  refer services finished.
     209: invokevirtual #53                 // Method java/lang/StringBuilder.append:(Ljava/lang/String;)Ljava/lang/StringBuilder;
     212: invokevirtual #55                 // Method java/lang/StringBuilder.toString:()Ljava/lang/String;
     215: invokeinterface #56,  2           // InterfaceMethod org/apache/dubbo/common/logger/ErrorTypeAwareLogger.info:(Ljava/lang/String;)V
     220: aload_0
     221: getfield      #6                  // Field asyncReferringFutures:Ljava/util/List;
     224: invokeinterface #169,  1          // InterfaceMethod java/util/List.clear:()V
     229: aload_2
     230: athrow
     231: return
    Exception table:
       from    to  target type
           0    61   103   Class java/lang/Throwable
           0    61   189   any
         103   147   189   any

  public boolean isBackground();
    Code:
       0: aload_0
       1: getfield      #45                 // Field background:Ljava/lang/Boolean;
       4: invokevirtual #160                // Method java/lang/Boolean.booleanValue:()Z
       7: ireturn

  private boolean isExportBackground();
    Code:
       0: aload_0
       1: getfield      #8                  // Field moduleModel:Lorg/apache/dubbo/rpc/model/ModuleModel;
       4: invokevirtual #9                  // Method org/apache/dubbo/rpc/model/ModuleModel.getConfigManager:()Lorg/apache/dubbo/config/context/ModuleConfigManager;
       7: invokevirtual #191                // Method org/apache/dubbo/config/context/ModuleConfigManager.getProviders:()Ljava/util/Collection;
      10: invokeinterface #192,  1          // InterfaceMethod java/util/Collection.stream:()Ljava/util/stream/Stream;
      15: invokedynamic #193,  0            // InvokeDynamic #7:apply:()Ljava/util/function/Function;
      20: invokeinterface #194,  2          // InterfaceMethod java/util/stream/Stream.map:(Ljava/util/function/Function;)Ljava/util/stream/Stream;
      25: invokedynamic #195,  0            // InvokeDynamic #8:test:()Ljava/util/function/Predicate;
      30: invokeinterface #196,  2          // InterfaceMethod java/util/stream/Stream.anyMatch:(Ljava/util/function/Predicate;)Z
      35: ireturn

  private boolean isReferBackground();
    Code:
       0: aload_0
       1: getfield      #8                  // Field moduleModel:Lorg/apache/dubbo/rpc/model/ModuleModel;
       4: invokevirtual #9                  // Method org/apache/dubbo/rpc/model/ModuleModel.getConfigManager:()Lorg/apache/dubbo/config/context/ModuleConfigManager;
       7: invokevirtual #197                // Method org/apache/dubbo/config/context/ModuleConfigManager.getConsumers:()Ljava/util/Collection;
      10: invokeinterface #192,  1          // InterfaceMethod java/util/Collection.stream:()Ljava/util/stream/Stream;
      15: invokedynamic #198,  0            // InvokeDynamic #9:apply:()Ljava/util/function/Function;
      20: invokeinterface #194,  2          // InterfaceMethod java/util/stream/Stream.map:(Ljava/util/function/Function;)Ljava/util/stream/Stream;
      25: invokedynamic #199,  0            // InvokeDynamic #10:test:()Ljava/util/function/Predicate;
      30: invokeinterface #196,  2          // InterfaceMethod java/util/stream/Stream.anyMatch:(Ljava/util/function/Predicate;)Z
      35: ireturn

  public org.apache.dubbo.common.config.ReferenceCache getReferenceCache();
    Code:
       0: aload_0
       1: getfield      #20                 // Field referenceCache:Lorg/apache/dubbo/config/utils/SimpleReferenceCache;
       4: areturn

  public void prepare();
    Code:
       0: aload_0
       1: getfield      #22                 // Field applicationDeployer:Lorg/apache/dubbo/common/deploy/ApplicationDeployer;
       4: invokeinterface #57,  1           // InterfaceMethod org/apache/dubbo/common/deploy/ApplicationDeployer.initialize:()V
       9: aload_0
      10: invokevirtual #69                 // Method initialize:()V
      13: return

  private static boolean lambda$isReferBackground$9(java.lang.Boolean);
    Code:
       0: aload_0
       1: ifnull        15
       4: aload_0
       5: invokevirtual #160                // Method java/lang/Boolean.booleanValue:()Z
       8: ifeq          15
      11: iconst_1
      12: goto          16
      15: iconst_0
      16: ireturn

  private static boolean lambda$isExportBackground$8(java.lang.Boolean);
    Code:
       0: aload_0
       1: ifnull        15
       4: aload_0
       5: invokevirtual #160                // Method java/lang/Boolean.booleanValue:()Z
       8: ifeq          15
      11: iconst_1
      12: goto          16
      15: iconst_0
      16: ireturn

  private static void lambda$unreferServices$7(java.util.concurrent.CompletableFuture);
    Code:
       0: aload_0
       1: invokevirtual #140                // Method java/util/concurrent/CompletableFuture.isDone:()Z
       4: ifne          13
       7: aload_0
       8: iconst_1
       9: invokevirtual #143                // Method java/util/concurrent/CompletableFuture.cancel:(Z)Z
      12: pop
      13: return

  private void lambda$referServices$6(org.apache.dubbo.config.ReferenceConfigBase);
    Code:
       0: aload_1
       1: checkcast     #200                // class org/apache/dubbo/config/ReferenceConfig
       4: astore_2
       5: aload_2
       6: invokevirtual #201                // Method org/apache/dubbo/config/ReferenceConfig.isRefreshed:()Z
       9: ifne          16
      12: aload_2
      13: invokevirtual #202                // Method org/apache/dubbo/config/ReferenceConfig.refresh:()V
      16: aload_1
      17: invokevirtual #203                // Method org/apache/dubbo/config/ReferenceConfigBase.shouldInit:()Z
      20: ifeq          90
      23: aload_0
      24: getfield      #43                 // Field referAsync:Ljava/lang/Boolean;
      27: invokevirtual #160                // Method java/lang/Boolean.booleanValue:()Z
      30: ifne          43
      33: aload_1
      34: invokevirtual #204                // Method org/apache/dubbo/config/ReferenceConfigBase.shouldReferAsync:()Ljava/lang/Boolean;
      37: invokevirtual #160                // Method java/lang/Boolean.booleanValue:()Z
      40: ifeq          81
      43: aload_0
      44: getfield      #18                 // Field executorRepository:Lorg/apache/dubbo/common/threadpool/manager/ExecutorRepository;
      47: invokeinterface #205,  1          // InterfaceMethod org/apache/dubbo/common/threadpool/manager/ExecutorRepository.getServiceReferExecutor:()Ljava/util/concurrent/ExecutorService;
      52: astore_3
      53: aload_0
      54: aload_1
      55: invokedynamic #206,  0            // InvokeDynamic #11:run:(Lorg/apache/dubbo/config/deploy/DefaultModuleDeployer;Lorg/apache/dubbo/config/ReferenceConfigBase;)Ljava/lang/Runnable;
      60: aload_3
      61: invokestatic  #164                // Method java/util/concurrent/CompletableFuture.runAsync:(Ljava/lang/Runnable;Ljava/util/concurrent/Executor;)Ljava/util/concurrent/CompletableFuture;
      64: astore        4
      66: aload_0
      67: getfield      #6                  // Field asyncReferringFutures:Ljava/util/List;
      70: aload         4
      72: invokeinterface #165,  2          // InterfaceMethod java/util/List.add:(Ljava/lang/Object;)Z
      77: pop
      78: goto          90
      81: aload_0
      82: getfield      #20                 // Field referenceCache:Lorg/apache/dubbo/config/utils/SimpleReferenceCache;
      85: aload_1
      86: invokevirtual #207                // Method org/apache/dubbo/config/utils/SimpleReferenceCache.get:(Lorg/apache/dubbo/config/ReferenceConfigBase;)Ljava/lang/Object;
      89: pop
      90: goto          153
      93: astore_2
      94: getstatic     #48                 // Field logger:Lorg/apache/dubbo/common/logger/ErrorTypeAwareLogger;
      97: ldc           #208                // String 5-15
      99: ldc           #97                 // String
     101: ldc           #97                 // String
     103: new           #50                 // class java/lang/StringBuilder
     106: dup
     107: invokespecial #51                 // Method java/lang/StringBuilder."<init>":()V
     110: ldc           #209                // String Model reference failed:
     112: invokevirtual #53                 // Method java/lang/StringBuilder.append:(Ljava/lang/String;)Ljava/lang/StringBuilder;
     115: aload_0
     116: invokevirtual #52                 // Method getIdentifier:()Ljava/lang/String;
     119: invokevirtual #53                 // Method java/lang/StringBuilder.append:(Ljava/lang/String;)Ljava/lang/StringBuilder;
     122: ldc           #210                // String  , catch error :
     124: invokevirtual #53                 // Method java/lang/StringBuilder.append:(Ljava/lang/String;)Ljava/lang/StringBuilder;
     127: aload_2
     128: invokevirtual #211                // Method java/lang/Throwable.getMessage:()Ljava/lang/String;
     131: invokevirtual #53                 // Method java/lang/StringBuilder.append:(Ljava/lang/String;)Ljava/lang/StringBuilder;
     134: invokevirtual #55                 // Method java/lang/StringBuilder.toString:()Ljava/lang/String;
     137: aload_2
     138: invokeinterface #99,  6           // InterfaceMethod org/apache/dubbo/common/logger/ErrorTypeAwareLogger.error:(Ljava/lang/String;Ljava/lang/String;Ljava/lang/String;Ljava/lang/String;Ljava/lang/Throwable;)V
     143: aload_0
     144: getfield      #20                 // Field referenceCache:Lorg/apache/dubbo/config/utils/SimpleReferenceCache;
     147: aload_1
     148: invokevirtual #212                // Method org/apache/dubbo/config/utils/SimpleReferenceCache.destroy:(Lorg/apache/dubbo/config/ReferenceConfigBase;)V
     151: aload_2
     152: athrow
     153: return
    Exception table:
       from    to  target type
           0    90    93   Class java/lang/Throwable

  private void lambda$null$5(org.apache.dubbo.config.ReferenceConfigBase);
    Code:
       0: aload_0
       1: getfield      #20                 // Field referenceCache:Lorg/apache/dubbo/config/utils/SimpleReferenceCache;
       4: aload_1
       5: invokevirtual #207                // Method org/apache/dubbo/config/utils/SimpleReferenceCache.get:(Lorg/apache/dubbo/config/ReferenceConfigBase;)Ljava/lang/Object;
       8: pop
       9: goto          62
      12: astore_2
      13: getstatic     #48                 // Field logger:Lorg/apache/dubbo/common/logger/ErrorTypeAwareLogger;
      16: ldc           #183                // String 5-9
      18: ldc           #97                 // String
      20: ldc           #97                 // String
      22: new           #50                 // class java/lang/StringBuilder
      25: dup
      26: invokespecial #51                 // Method java/lang/StringBuilder."<init>":()V
      29: ldc           #213                // String Failed to async export service config:
      31: invokevirtual #53                 // Method java/lang/StringBuilder.append:(Ljava/lang/String;)Ljava/lang/StringBuilder;
      34: aload_0
      35: invokevirtual #52                 // Method getIdentifier:()Ljava/lang/String;
      38: invokevirtual #53                 // Method java/lang/StringBuilder.append:(Ljava/lang/String;)Ljava/lang/StringBuilder;
      41: ldc           #210                // String  , catch error :
      43: invokevirtual #53                 // Method java/lang/StringBuilder.append:(Ljava/lang/String;)Ljava/lang/StringBuilder;
      46: aload_2
      47: invokevirtual #211                // Method java/lang/Throwable.getMessage:()Ljava/lang/String;
      50: invokevirtual #53                 // Method java/lang/StringBuilder.append:(Ljava/lang/String;)Ljava/lang/StringBuilder;
      53: invokevirtual #55                 // Method java/lang/StringBuilder.toString:()Ljava/lang/String;
      56: aload_2
      57: invokeinterface #99,  6           // InterfaceMethod org/apache/dubbo/common/logger/ErrorTypeAwareLogger.error:(Ljava/lang/String;Ljava/lang/String;Ljava/lang/String;Ljava/lang/String;Ljava/lang/Throwable;)V
      62: return
    Exception table:
       from    to  target type
           0     9    12   Class java/lang/Throwable

  private static void lambda$unexportServices$4(java.util.concurrent.CompletableFuture);
    Code:
       0: aload_0
       1: invokevirtual #140                // Method java/util/concurrent/CompletableFuture.isDone:()Z
       4: ifne          13
       7: aload_0
       8: iconst_1
       9: invokevirtual #143                // Method java/util/concurrent/CompletableFuture.cancel:(Z)Z
      12: pop
      13: return

  private void lambda$unexportServices$3(org.apache.dubbo.config.ServiceConfigBase);
    Code:
       0: aload_0
       1: getfield      #10                 // Field configManager:Lorg/apache/dubbo/config/context/ModuleConfigManager;
       4: aload_1
       5: invokevirtual #214                // Method org/apache/dubbo/config/context/ModuleConfigManager.removeConfig:(Lorg/apache/dubbo/config/AbstractConfig;)Z
       8: pop
       9: aload_1
      10: invokevirtual #215                // Method org/apache/dubbo/config/ServiceConfigBase.unexport:()V
      13: goto          17
      16: astore_2
      17: return
    Exception table:
       from    to  target type
           0    13    16   Class java/lang/Exception

  private void lambda$exportServiceInternal$2(org.apache.dubbo.config.ServiceConfigBase);
    Code:
       0: aload_1
       1: invokevirtual #159                // Method org/apache/dubbo/config/ServiceConfigBase.isExported:()Z
       4: ifne          22
       7: aload_1
       8: invokevirtual #166                // Method org/apache/dubbo/config/ServiceConfigBase.export:()V
      11: aload_0
      12: getfield      #7                  // Field exportedServices:Ljava/util/List;
      15: aload_1
      16: invokeinterface #165,  2          // InterfaceMethod java/util/List.add:(Ljava/lang/Object;)Z
      21: pop
      22: goto          75
      25: astore_2
      26: getstatic     #48                 // Field logger:Lorg/apache/dubbo/common/logger/ErrorTypeAwareLogger;
      29: ldc           #183                // String 5-9
      31: ldc           #97                 // String
      33: ldc           #97                 // String
      35: new           #50                 // class java/lang/StringBuilder
      38: dup
      39: invokespecial #51                 // Method java/lang/StringBuilder."<init>":()V
      42: ldc           #213                // String Failed to async export service config:
      44: invokevirtual #53                 // Method java/lang/StringBuilder.append:(Ljava/lang/String;)Ljava/lang/StringBuilder;
      47: aload_0
      48: invokevirtual #52                 // Method getIdentifier:()Ljava/lang/String;
      51: invokevirtual #53                 // Method java/lang/StringBuilder.append:(Ljava/lang/String;)Ljava/lang/StringBuilder;
      54: ldc           #210                // String  , catch error :
      56: invokevirtual #53                 // Method java/lang/StringBuilder.append:(Ljava/lang/String;)Ljava/lang/StringBuilder;
      59: aload_2
      60: invokevirtual #211                // Method java/lang/Throwable.getMessage:()Ljava/lang/String;
      63: invokevirtual #53                 // Method java/lang/StringBuilder.append:(Ljava/lang/String;)Ljava/lang/StringBuilder;
      66: invokevirtual #55                 // Method java/lang/StringBuilder.toString:()Ljava/lang/String;
      69: aload_2
      70: invokeinterface #99,  6           // InterfaceMethod org/apache/dubbo/common/logger/ErrorTypeAwareLogger.error:(Ljava/lang/String;Ljava/lang/String;Ljava/lang/String;Ljava/lang/String;Ljava/lang/Throwable;)V
      75: return
    Exception table:
       from    to  target type
           0    22    25   Class java/lang/Throwable

  private void lambda$startSync$1();
    Code:
       0: aload_0
       1: invokespecial #216                // Method waitExportFinish:()V
       4: aload_0
       5: invokespecial #217                // Method waitReferFinish:()V
       8: aload_0
       9: invokespecial #75                 // Method onModuleStarted:()V
      12: goto          47
      15: astore_1
      16: getstatic     #48                 // Field logger:Lorg/apache/dubbo/common/logger/ErrorTypeAwareLogger;
      19: ldc           #218                // String 5-23
      21: ldc           #97                 // String
      23: ldc           #97                 // String
      25: ldc           #219                // String wait for export/refer services occurred an exception
      27: aload_1
      28: invokeinterface #220,  6          // InterfaceMethod org/apache/dubbo/common/logger/ErrorTypeAwareLogger.warn:(Ljava/lang/String;Ljava/lang/String;Ljava/lang/String;Ljava/lang/String;Ljava/lang/Throwable;)V
      33: aload_0
      34: invokespecial #75                 // Method onModuleStarted:()V
      37: goto          47
      40: astore_2
      41: aload_0
      42: invokespecial #75                 // Method onModuleStarted:()V
      45: aload_2
      46: athrow
      47: return
    Exception table:
       from    to  target type
           0     8    15   Class java/lang/Throwable
           0     8    40   any
          15    33    40   any

  private static java.lang.IllegalStateException lambda$initialize$0();
    Code:
       0: new           #62                 // class java/lang/IllegalStateException
       3: dup
       4: ldc           #221                // String Default module config is not initialized
       6: invokespecial #64                 // Method java/lang/IllegalStateException."<init>":(Ljava/lang/String;)V
       9: areturn

  static {};
    Code:
       0: ldc           #222                // class org/apache/dubbo/config/deploy/DefaultModuleDeployer
       2: invokestatic  #223                // Method org/apache/dubbo/common/logger/LoggerFactory.getErrorTypeAwareLogger:(Ljava/lang/Class;)Lorg/apache/dubbo/common/logger/ErrorTypeAwareLogger;
       5: putstatic     #48                 // Field logger:Lorg/apache/dubbo/common/logger/ErrorTypeAwareLogger;
       8: return
}
