Compiled from "DefaultMetricsServiceExporter.java"
public class org.apache.dubbo.config.deploy.DefaultMetricsServiceExporter implements org.apache.dubbo.metrics.service.MetricsServiceExporter,org.apache.dubbo.rpc.model.ScopeModelAware {
  private final org.apache.dubbo.common.logger.ErrorTypeAwareLogger logger;

  private org.apache.dubbo.rpc.model.ApplicationModel applicationModel;

  private org.apache.dubbo.metrics.service.MetricsService metricsService;

  private volatile org.apache.dubbo.config.ServiceConfig<org.apache.dubbo.metrics.service.MetricsService> serviceConfig;

  public org.apache.dubbo.config.deploy.DefaultMetricsServiceExporter();
    Code:
       0: aload_0
       1: invokespecial #3                  // Method java/lang/Object."<init>":()V
       4: aload_0
       5: aload_0
       6: invokevirtual #4                  // Method java/lang/Object.getClass:()Ljava/lang/Class;
       9: invokestatic  #5                  // Method org/apache/dubbo/common/logger/LoggerFactory.getErrorTypeAwareLogger:(Ljava/lang/Class;)Lorg/apache/dubbo/common/logger/ErrorTypeAwareLogger;
      12: putfield      #6                  // Field logger:Lorg/apache/dubbo/common/logger/ErrorTypeAwareLogger;
      15: return

  public void init();
    Code:
       0: aload_0
       1: invokespecial #7                  // Method initialize:()V
       4: return

  private void initialize();
    Code:
       0: aload_0
       1: getfield      #8                  // Field applicationModel:Lorg/apache/dubbo/rpc/model/ApplicationModel;
       4: invokevirtual #9                  // Method org/apache/dubbo/rpc/model/ApplicationModel.getApplicationConfigManager:()Lorg/apache/dubbo/config/context/ConfigManager;
       7: invokevirtual #10                 // Method org/apache/dubbo/config/context/ConfigManager.getMetrics:()Ljava/util/Optional;
      10: aconst_null
      11: invokevirtual #11                 // Method java/util/Optional.orElse:(Ljava/lang/Object;)Ljava/lang/Object;
      14: checkcast     #12                 // class org/apache/dubbo/config/MetricsConfig
      17: astore_1
      18: aload_1
      19: ifnull        105
      22: aload_0
      23: getfield      #13                 // Field metricsService:Lorg/apache/dubbo/metrics/service/MetricsService;
      26: ifnonnull     105
      29: ldc           #14                 // String prometheus
      31: aload_1
      32: invokevirtual #15                 // Method org/apache/dubbo/config/MetricsConfig.getProtocol:()Ljava/lang/String;
      35: invokevirtual #16                 // Method java/lang/String.equals:(Ljava/lang/Object;)Z
      38: ifeq          63
      41: aload_0
      42: aload_0
      43: getfield      #8                  // Field applicationModel:Lorg/apache/dubbo/rpc/model/ApplicationModel;
      46: ldc           #17                 // class org/apache/dubbo/metrics/service/MetricsService
      48: invokevirtual #18                 // Method org/apache/dubbo/rpc/model/ApplicationModel.getExtensionLoader:(Ljava/lang/Class;)Lorg/apache/dubbo/common/extension/ExtensionLoader;
      51: invokevirtual #19                 // Method org/apache/dubbo/common/extension/ExtensionLoader.getDefaultExtension:()Ljava/lang/Object;
      54: checkcast     #17                 // class org/apache/dubbo/metrics/service/MetricsService
      57: putfield      #13                 // Field metricsService:Lorg/apache/dubbo/metrics/service/MetricsService;
      60: goto          105
      63: aload_0
      64: getfield      #6                  // Field logger:Lorg/apache/dubbo/common/logger/ErrorTypeAwareLogger;
      67: ldc           #20                 // String 0-13
      69: ldc           #21                 // String
      71: ldc           #21                 // String
      73: new           #22                 // class java/lang/StringBuilder
      76: dup
      77: invokespecial #23                 // Method java/lang/StringBuilder."<init>":()V
      80: ldc           #24                 // String Protocol
      82: invokevirtual #25                 // Method java/lang/StringBuilder.append:(Ljava/lang/String;)Ljava/lang/StringBuilder;
      85: aload_1
      86: invokevirtual #15                 // Method org/apache/dubbo/config/MetricsConfig.getProtocol:()Ljava/lang/String;
      89: invokevirtual #25                 // Method java/lang/StringBuilder.append:(Ljava/lang/String;)Ljava/lang/StringBuilder;
      92: ldc           #26                 // String  not support for new metrics mechanism. Using old metrics mechanism instead.
      94: invokevirtual #25                 // Method java/lang/StringBuilder.append:(Ljava/lang/String;)Ljava/lang/StringBuilder;
      97: invokevirtual #27                 // Method java/lang/StringBuilder.toString:()Ljava/lang/String;
     100: invokeinterface #28,  5           // InterfaceMethod org/apache/dubbo/common/logger/ErrorTypeAwareLogger.warn:(Ljava/lang/String;Ljava/lang/String;Ljava/lang/String;Ljava/lang/String;)V
     105: return

  public void setApplicationModel(org.apache.dubbo.rpc.model.ApplicationModel);
    Code:
       0: aload_0
       1: aload_1
       2: putfield      #8                  // Field applicationModel:Lorg/apache/dubbo/rpc/model/ApplicationModel;
       5: return

  public org.apache.dubbo.metrics.service.MetricsServiceExporter export();
    Code:
       0: aload_0
       1: getfield      #13                 // Field metricsService:Lorg/apache/dubbo/metrics/service/MetricsService;
       4: ifnull        198
       7: aload_0
       8: invokespecial #29                 // Method isExported:()Z
      11: ifne          143
      14: aload_0
      15: getfield      #8                  // Field applicationModel:Lorg/apache/dubbo/rpc/model/ApplicationModel;
      18: invokevirtual #30                 // Method org/apache/dubbo/rpc/model/ApplicationModel.getFrameworkModel:()Lorg/apache/dubbo/rpc/model/FrameworkModel;
      21: invokevirtual #31                 // Method org/apache/dubbo/rpc/model/FrameworkModel.getBeanFactory:()Lorg/apache/dubbo/common/beans/factory/ScopeBeanFactory;
      24: ldc           #32                 // class org/apache/dubbo/common/threadpool/manager/FrameworkExecutorRepository
      26: invokevirtual #33                 // Method org/apache/dubbo/common/beans/factory/ScopeBeanFactory.getBean:(Ljava/lang/Class;)Ljava/lang/Object;
      29: checkcast     #32                 // class org/apache/dubbo/common/threadpool/manager/FrameworkExecutorRepository
      32: invokevirtual #34                 // Method org/apache/dubbo/common/threadpool/manager/FrameworkExecutorRepository.getInternalServiceExecutor:()Ljava/util/concurrent/ExecutorService;
      35: astore_1
      36: aload_0
      37: getfield      #8                  // Field applicationModel:Lorg/apache/dubbo/rpc/model/ApplicationModel;
      40: invokestatic  #35                 // Method org/apache/dubbo/config/bootstrap/builders/InternalServiceConfigBuilder.newBuilder:(Lorg/apache/dubbo/rpc/model/ApplicationModel;)Lorg/apache/dubbo/config/bootstrap/builders/InternalServiceConfigBuilder;
      43: ldc           #17                 // class org/apache/dubbo/metrics/service/MetricsService
      45: invokevirtual #36                 // Method org/apache/dubbo/config/bootstrap/builders/InternalServiceConfigBuilder.interfaceClass:(Ljava/lang/Class;)Lorg/apache/dubbo/config/bootstrap/builders/InternalServiceConfigBuilder;
      48: aload_0
      49: invokespecial #37                 // Method getMetricsConfig:()Lorg/apache/dubbo/config/MetricsConfig;
      52: invokevirtual #38                 // Method org/apache/dubbo/config/MetricsConfig.getExportServiceProtocol:()Ljava/lang/String;
      55: invokevirtual #39                 // Method org/apache/dubbo/config/bootstrap/builders/InternalServiceConfigBuilder.protocol:(Ljava/lang/String;)Lorg/apache/dubbo/config/bootstrap/builders/InternalServiceConfigBuilder;
      58: aload_0
      59: invokespecial #37                 // Method getMetricsConfig:()Lorg/apache/dubbo/config/MetricsConfig;
      62: invokevirtual #40                 // Method org/apache/dubbo/config/MetricsConfig.getExportServicePort:()Ljava/lang/Integer;
      65: invokevirtual #41                 // Method org/apache/dubbo/config/bootstrap/builders/InternalServiceConfigBuilder.port:(Ljava/lang/Integer;)Lorg/apache/dubbo/config/bootstrap/builders/InternalServiceConfigBuilder;
      68: aload_1
      69: invokevirtual #42                 // Method org/apache/dubbo/config/bootstrap/builders/InternalServiceConfigBuilder.executor:(Ljava/util/concurrent/Executor;)Lorg/apache/dubbo/config/bootstrap/builders/InternalServiceConfigBuilder;
      72: aload_0
      73: getfield      #13                 // Field metricsService:Lorg/apache/dubbo/metrics/service/MetricsService;
      76: invokevirtual #43                 // Method org/apache/dubbo/config/bootstrap/builders/InternalServiceConfigBuilder.ref:(Ljava/lang/Object;)Lorg/apache/dubbo/config/bootstrap/builders/InternalServiceConfigBuilder;
      79: ldc           #44                 // String internal-metrics-registry
      81: invokevirtual #45                 // Method org/apache/dubbo/config/bootstrap/builders/InternalServiceConfigBuilder.registryId:(Ljava/lang/String;)Lorg/apache/dubbo/config/bootstrap/builders/InternalServiceConfigBuilder;
      84: invokevirtual #46                 // Method org/apache/dubbo/config/bootstrap/builders/InternalServiceConfigBuilder.build:()Lorg/apache/dubbo/config/ServiceConfig;
      87: astore_2
      88: aload_2
      89: invokevirtual #47                 // Method org/apache/dubbo/config/ServiceConfig.export:()V
      92: aload_0
      93: getfield      #6                  // Field logger:Lorg/apache/dubbo/common/logger/ErrorTypeAwareLogger;
      96: invokeinterface #48,  1           // InterfaceMethod org/apache/dubbo/common/logger/ErrorTypeAwareLogger.isInfoEnabled:()Z
     101: ifeq          135
     104: aload_0
     105: getfield      #6                  // Field logger:Lorg/apache/dubbo/common/logger/ErrorTypeAwareLogger;
     108: new           #22                 // class java/lang/StringBuilder
     111: dup
     112: invokespecial #23                 // Method java/lang/StringBuilder."<init>":()V
     115: ldc           #49                 // String The MetricsService exports urls :
     117: invokevirtual #25                 // Method java/lang/StringBuilder.append:(Ljava/lang/String;)Ljava/lang/StringBuilder;
     120: aload_2
     121: invokevirtual #50                 // Method org/apache/dubbo/config/ServiceConfig.getExportedUrls:()Ljava/util/List;
     124: invokevirtual #51                 // Method java/lang/StringBuilder.append:(Ljava/lang/Object;)Ljava/lang/StringBuilder;
     127: invokevirtual #27                 // Method java/lang/StringBuilder.toString:()Ljava/lang/String;
     130: invokeinterface #52,  2           // InterfaceMethod org/apache/dubbo/common/logger/ErrorTypeAwareLogger.info:(Ljava/lang/String;)V
     135: aload_0
     136: aload_2
     137: putfield      #53                 // Field serviceConfig:Lorg/apache/dubbo/config/ServiceConfig;
     140: goto          221
     143: aload_0
     144: getfield      #6                  // Field logger:Lorg/apache/dubbo/common/logger/ErrorTypeAwareLogger;
     147: invokeinterface #54,  1           // InterfaceMethod org/apache/dubbo/common/logger/ErrorTypeAwareLogger.isWarnEnabled:()Z
     152: ifeq          221
     155: aload_0
     156: getfield      #6                  // Field logger:Lorg/apache/dubbo/common/logger/ErrorTypeAwareLogger;
     159: ldc           #55                 // String 99-0
     161: ldc           #21                 // String
     163: ldc           #21                 // String
     165: new           #22                 // class java/lang/StringBuilder
     168: dup
     169: invokespecial #23                 // Method java/lang/StringBuilder."<init>":()V
     172: ldc           #56                 // String The MetricsService has been exported :
     174: invokevirtual #25                 // Method java/lang/StringBuilder.append:(Ljava/lang/String;)Ljava/lang/StringBuilder;
     177: aload_0
     178: getfield      #53                 // Field serviceConfig:Lorg/apache/dubbo/config/ServiceConfig;
     181: invokevirtual #50                 // Method org/apache/dubbo/config/ServiceConfig.getExportedUrls:()Ljava/util/List;
     184: invokevirtual #51                 // Method java/lang/StringBuilder.append:(Ljava/lang/Object;)Ljava/lang/StringBuilder;
     187: invokevirtual #27                 // Method java/lang/StringBuilder.toString:()Ljava/lang/String;
     190: invokeinterface #28,  5           // InterfaceMethod org/apache/dubbo/common/logger/ErrorTypeAwareLogger.warn:(Ljava/lang/String;Ljava/lang/String;Ljava/lang/String;Ljava/lang/String;)V
     195: goto          221
     198: aload_0
     199: getfield      #6                  // Field logger:Lorg/apache/dubbo/common/logger/ErrorTypeAwareLogger;
     202: invokeinterface #48,  1           // InterfaceMethod org/apache/dubbo/common/logger/ErrorTypeAwareLogger.isInfoEnabled:()Z
     207: ifeq          221
     210: aload_0
     211: getfield      #6                  // Field logger:Lorg/apache/dubbo/common/logger/ErrorTypeAwareLogger;
     214: ldc           #57                 // String The MetricsConfig not exist, will not export metrics service.
     216: invokeinterface #52,  2           // InterfaceMethod org/apache/dubbo/common/logger/ErrorTypeAwareLogger.info:(Ljava/lang/String;)V
     221: aload_0
     222: areturn

  public org.apache.dubbo.metrics.service.MetricsServiceExporter unexport();
    Code:
       0: aload_0
       1: invokespecial #29                 // Method isExported:()Z
       4: ifeq          14
       7: aload_0
       8: getfield      #53                 // Field serviceConfig:Lorg/apache/dubbo/config/ServiceConfig;
      11: invokevirtual #58                 // Method org/apache/dubbo/config/ServiceConfig.unexport:()V
      14: aload_0
      15: areturn

  private org.apache.dubbo.config.MetricsConfig getMetricsConfig();
    Code:
       0: aload_0
       1: getfield      #8                  // Field applicationModel:Lorg/apache/dubbo/rpc/model/ApplicationModel;
       4: invokevirtual #9                  // Method org/apache/dubbo/rpc/model/ApplicationModel.getApplicationConfigManager:()Lorg/apache/dubbo/config/context/ConfigManager;
       7: invokevirtual #10                 // Method org/apache/dubbo/config/context/ConfigManager.getMetrics:()Ljava/util/Optional;
      10: astore_1
      11: aload_1
      12: invokevirtual #59                 // Method java/util/Optional.isPresent:()Z
      15: ifeq          26
      18: aload_1
      19: invokevirtual #60                 // Method java/util/Optional.get:()Ljava/lang/Object;
      22: checkcast     #12                 // class org/apache/dubbo/config/MetricsConfig
      25: areturn
      26: new           #61                 // class java/lang/IllegalStateException
      29: dup
      30: ldc           #62                 // String There\'s no MetricsConfig specified.
      32: invokespecial #63                 // Method java/lang/IllegalStateException."<init>":(Ljava/lang/String;)V
      35: athrow

  private boolean isExported();
    Code:
       0: aload_0
       1: getfield      #53                 // Field serviceConfig:Lorg/apache/dubbo/config/ServiceConfig;
       4: ifnull        31
       7: aload_0
       8: getfield      #53                 // Field serviceConfig:Lorg/apache/dubbo/config/ServiceConfig;
      11: invokevirtual #64                 // Method org/apache/dubbo/config/ServiceConfig.isExported:()Z
      14: ifeq          31
      17: aload_0
      18: getfield      #53                 // Field serviceConfig:Lorg/apache/dubbo/config/ServiceConfig;
      21: invokevirtual #65                 // Method org/apache/dubbo/config/ServiceConfig.isUnexported:()Z
      24: ifne          31
      27: iconst_1
      28: goto          32
      31: iconst_0
      32: ireturn
}
