Compiled from "FrameworkModelCleaner.java"
public class org.apache.dubbo.config.deploy.FrameworkModelCleaner implements org.apache.dubbo.rpc.model.ScopeModelDestroyListener<org.apache.dubbo.rpc.model.FrameworkModel> {
  private static final org.apache.dubbo.common.logger.ErrorTypeAwareLogger logger;

  private final java.util.concurrent.atomic.AtomicBoolean protocolDestroyed;

  public org.apache.dubbo.config.deploy.FrameworkModelCleaner();
    Code:
       0: aload_0
       1: invokespecial #2                  // Method java/lang/Object."<init>":()V
       4: aload_0
       5: new           #3                  // class java/util/concurrent/atomic/AtomicBoolean
       8: dup
       9: iconst_0
      10: invokespecial #4                  // Method java/util/concurrent/atomic/AtomicBoolean."<init>":(Z)V
      13: putfield      #5                  // Field protocolDestroyed:Ljava/util/concurrent/atomic/AtomicBoolean;
      16: return

  public boolean isProtocol();
    Code:
       0: iconst_1
       1: ireturn

  public void onDestroy(org.apache.dubbo.rpc.model.FrameworkModel);
    Code:
       0: aload_0
       1: aload_1
       2: invokespecial #6                  // Method destroyFrameworkResources:(Lorg/apache/dubbo/rpc/model/FrameworkModel;)V
       5: return

  private void destroyFrameworkResources(org.apache.dubbo.rpc.model.FrameworkModel);
    Code:
       0: aload_0
       1: aload_1
       2: invokespecial #7                  // Method destroyProtocols:(Lorg/apache/dubbo/rpc/model/FrameworkModel;)V
       5: return

  private void destroyProtocols(org.apache.dubbo.rpc.model.FrameworkModel);
    Code:
       0: aload_0
       1: getfield      #5                  // Field protocolDestroyed:Ljava/util/concurrent/atomic/AtomicBoolean;
       4: iconst_0
       5: iconst_1
       6: invokevirtual #8                  // Method java/util/concurrent/atomic/AtomicBoolean.compareAndSet:(ZZ)Z
       9: ifeq          101
      12: aload_1
      13: ldc           #9                  // class org/apache/dubbo/rpc/Protocol
      15: invokevirtual #10                 // Method org/apache/dubbo/rpc/model/FrameworkModel.getExtensionLoader:(Ljava/lang/Class;)Lorg/apache/dubbo/common/extension/ExtensionLoader;
      18: astore_2
      19: aload_2
      20: invokevirtual #11                 // Method org/apache/dubbo/common/extension/ExtensionLoader.getLoadedExtensions:()Ljava/util/Set;
      23: invokeinterface #12,  1           // InterfaceMethod java/util/Set.iterator:()Ljava/util/Iterator;
      28: astore_3
      29: aload_3
      30: invokeinterface #13,  1           // InterfaceMethod java/util/Iterator.hasNext:()Z
      35: ifeq          101
      38: aload_3
      39: invokeinterface #14,  1           // InterfaceMethod java/util/Iterator.next:()Ljava/lang/Object;
      44: checkcast     #15                 // class java/lang/String
      47: astore        4
      49: aload_2
      50: aload         4
      52: invokevirtual #16                 // Method org/apache/dubbo/common/extension/ExtensionLoader.getLoadedExtension:(Ljava/lang/String;)Ljava/lang/Object;
      55: checkcast     #9                  // class org/apache/dubbo/rpc/Protocol
      58: astore        5
      60: aload         5
      62: ifnull        72
      65: aload         5
      67: invokeinterface #17,  1           // InterfaceMethod org/apache/dubbo/rpc/Protocol.destroy:()V
      72: goto          98
      75: astore        5
      77: getstatic     #19                 // Field logger:Lorg/apache/dubbo/common/logger/ErrorTypeAwareLogger;
      80: ldc           #20                 // String 5-25
      82: ldc           #21                 // String
      84: ldc           #21                 // String
      86: aload         5
      88: invokevirtual #22                 // Method java/lang/Throwable.getMessage:()Ljava/lang/String;
      91: aload         5
      93: invokeinterface #23,  6           // InterfaceMethod org/apache/dubbo/common/logger/ErrorTypeAwareLogger.warn:(Ljava/lang/String;Ljava/lang/String;Ljava/lang/String;Ljava/lang/String;Ljava/lang/Throwable;)V
      98: goto          29
     101: return
    Exception table:
       from    to  target type
          49    72    75   Class java/lang/Throwable

  public void onDestroy(org.apache.dubbo.rpc.model.ScopeModel);
    Code:
       0: aload_0
       1: aload_1
       2: checkcast     #24                 // class org/apache/dubbo/rpc/model/FrameworkModel
       5: invokevirtual #25                 // Method onDestroy:(Lorg/apache/dubbo/rpc/model/FrameworkModel;)V
       8: return

  static {};
    Code:
       0: ldc           #26                 // class org/apache/dubbo/config/deploy/FrameworkModelCleaner
       2: invokestatic  #27                 // Method org/apache/dubbo/common/logger/LoggerFactory.getErrorTypeAwareLogger:(Ljava/lang/Class;)Lorg/apache/dubbo/common/logger/ErrorTypeAwareLogger;
       5: putstatic     #19                 // Field logger:Lorg/apache/dubbo/common/logger/ErrorTypeAwareLogger;
       8: return
}
