Compiled from "URL.java"
public class com.alibaba.dubbo.common.URL extends org.apache.dubbo.common.URL {
  protected com.alibaba.dubbo.common.URL();
    Code:
       0: aload_0
       1: invokespecial #1                  // Method org/apache/dubbo/common/URL."<init>":()V
       4: return

  public com.alibaba.dubbo.common.URL(org.apache.dubbo.common.URL);
    Code:
       0: aload_0
       1: aload_1
       2: invokevirtual #2                  // Method org/apache/dubbo/common/URL.getProtocol:()Ljava/lang/String;
       5: aload_1
       6: invokevirtual #3                  // Method org/apache/dubbo/common/URL.getUsername:()Ljava/lang/String;
       9: aload_1
      10: invokevirtual #4                  // Method org/apache/dubbo/common/URL.getPassword:()Ljava/lang/String;
      13: aload_1
      14: invokevirtual #5                  // Method org/apache/dubbo/common/URL.getHost:()Ljava/lang/String;
      17: aload_1
      18: invokevirtual #6                  // Method org/apache/dubbo/common/URL.getPort:()I
      21: aload_1
      22: invokevirtual #7                  // Method org/apache/dubbo/common/URL.getPath:()Ljava/lang/String;
      25: aload_1
      26: invokevirtual #8                  // Method org/apache/dubbo/common/URL.getParameters:()Ljava/util/Map;
      29: invokespecial #9                  // Method org/apache/dubbo/common/URL."<init>":(Ljava/lang/String;Ljava/lang/String;Ljava/lang/String;Ljava/lang/String;ILjava/lang/String;Ljava/util/Map;)V
      32: return

  public com.alibaba.dubbo.common.URL(java.lang.String, java.lang.String, int);
    Code:
       0: aload_0
       1: aload_1
       2: aconst_null
       3: aconst_null
       4: aload_2
       5: iload_3
       6: aconst_null
       7: aconst_null
       8: checkcast     #10                 // class java/util/Map
      11: invokespecial #9                  // Method org/apache/dubbo/common/URL."<init>":(Ljava/lang/String;Ljava/lang/String;Ljava/lang/String;Ljava/lang/String;ILjava/lang/String;Ljava/util/Map;)V
      14: return

  public com.alibaba.dubbo.common.URL(java.lang.String, java.lang.String, int, java.lang.String[]);
    Code:
       0: aload_0
       1: aload_1
       2: aconst_null
       3: aconst_null
       4: aload_2
       5: iload_3
       6: aconst_null
       7: aload         4
       9: invokestatic  #11                 // Method org/apache/dubbo/common/utils/CollectionUtils.toStringMap:([Ljava/lang/String;)Ljava/util/Map;
      12: invokespecial #9                  // Method org/apache/dubbo/common/URL."<init>":(Ljava/lang/String;Ljava/lang/String;Ljava/lang/String;Ljava/lang/String;ILjava/lang/String;Ljava/util/Map;)V
      15: return

  public com.alibaba.dubbo.common.URL(java.lang.String, java.lang.String, int, java.util.Map<java.lang.String, java.lang.String>);
    Code:
       0: aload_0
       1: aload_1
       2: aconst_null
       3: aconst_null
       4: aload_2
       5: iload_3
       6: aconst_null
       7: aload         4
       9: invokespecial #9                  // Method org/apache/dubbo/common/URL."<init>":(Ljava/lang/String;Ljava/lang/String;Ljava/lang/String;Ljava/lang/String;ILjava/lang/String;Ljava/util/Map;)V
      12: return

  public com.alibaba.dubbo.common.URL(java.lang.String, java.lang.String, int, java.lang.String);
    Code:
       0: aload_0
       1: aload_1
       2: aconst_null
       3: aconst_null
       4: aload_2
       5: iload_3
       6: aload         4
       8: aconst_null
       9: checkcast     #10                 // class java/util/Map
      12: invokespecial #9                  // Method org/apache/dubbo/common/URL."<init>":(Ljava/lang/String;Ljava/lang/String;Ljava/lang/String;Ljava/lang/String;ILjava/lang/String;Ljava/util/Map;)V
      15: return

  public com.alibaba.dubbo.common.URL(java.lang.String, java.lang.String, int, java.lang.String, java.lang.String...);
    Code:
       0: aload_0
       1: aload_1
       2: aconst_null
       3: aconst_null
       4: aload_2
       5: iload_3
       6: aload         4
       8: aload         5
      10: invokestatic  #11                 // Method org/apache/dubbo/common/utils/CollectionUtils.toStringMap:([Ljava/lang/String;)Ljava/util/Map;
      13: invokespecial #9                  // Method org/apache/dubbo/common/URL."<init>":(Ljava/lang/String;Ljava/lang/String;Ljava/lang/String;Ljava/lang/String;ILjava/lang/String;Ljava/util/Map;)V
      16: return

  public com.alibaba.dubbo.common.URL(java.lang.String, java.lang.String, int, java.lang.String, java.util.Map<java.lang.String, java.lang.String>);
    Code:
       0: aload_0
       1: aload_1
       2: aconst_null
       3: aconst_null
       4: aload_2
       5: iload_3
       6: aload         4
       8: aload         5
      10: invokespecial #9                  // Method org/apache/dubbo/common/URL."<init>":(Ljava/lang/String;Ljava/lang/String;Ljava/lang/String;Ljava/lang/String;ILjava/lang/String;Ljava/util/Map;)V
      13: return

  public com.alibaba.dubbo.common.URL(java.lang.String, java.lang.String, java.lang.String, java.lang.String, int, java.lang.String);
    Code:
       0: aload_0
       1: aload_1
       2: aload_2
       3: aload_3
       4: aload         4
       6: iload         5
       8: aload         6
      10: aconst_null
      11: checkcast     #10                 // class java/util/Map
      14: invokespecial #9                  // Method org/apache/dubbo/common/URL."<init>":(Ljava/lang/String;Ljava/lang/String;Ljava/lang/String;Ljava/lang/String;ILjava/lang/String;Ljava/util/Map;)V
      17: return

  public com.alibaba.dubbo.common.URL(java.lang.String, java.lang.String, java.lang.String, java.lang.String, int, java.lang.String, java.lang.String...);
    Code:
       0: aload_0
       1: aload_1
       2: aload_2
       3: aload_3
       4: aload         4
       6: iload         5
       8: aload         6
      10: aload         7
      12: invokestatic  #11                 // Method org/apache/dubbo/common/utils/CollectionUtils.toStringMap:([Ljava/lang/String;)Ljava/util/Map;
      15: invokespecial #9                  // Method org/apache/dubbo/common/URL."<init>":(Ljava/lang/String;Ljava/lang/String;Ljava/lang/String;Ljava/lang/String;ILjava/lang/String;Ljava/util/Map;)V
      18: return

  public com.alibaba.dubbo.common.URL(java.lang.String, java.lang.String, java.lang.String, java.lang.String, int, java.lang.String, java.util.Map<java.lang.String, java.lang.String>);
    Code:
       0: aload_0
       1: aload_1
       2: aload_2
       3: aload_3
       4: aload         4
       6: iload         5
       8: aload         6
      10: aload         7
      12: invokespecial #9                  // Method org/apache/dubbo/common/URL."<init>":(Ljava/lang/String;Ljava/lang/String;Ljava/lang/String;Ljava/lang/String;ILjava/lang/String;Ljava/util/Map;)V
      15: return

  public static com.alibaba.dubbo.common.URL valueOf(java.lang.String);
    Code:
       0: aload_0
       1: invokestatic  #12                 // Method org/apache/dubbo/common/URL.valueOf:(Ljava/lang/String;)Lorg/apache/dubbo/common/URL;
       4: astore_1
       5: new           #13                 // class com/alibaba/dubbo/common/URL
       8: dup
       9: aload_1
      10: invokespecial #14                 // Method "<init>":(Lorg/apache/dubbo/common/URL;)V
      13: areturn

  public static java.lang.String encode(java.lang.String);
    Code:
       0: aload_0
       1: invokestatic  #15                 // Method org/apache/dubbo/common/URL.encode:(Ljava/lang/String;)Ljava/lang/String;
       4: areturn

  public static java.lang.String decode(java.lang.String);
    Code:
       0: aload_0
       1: invokestatic  #16                 // Method org/apache/dubbo/common/URL.decode:(Ljava/lang/String;)Ljava/lang/String;
       4: areturn

  public java.lang.String getProtocol();
    Code:
       0: aload_0
       1: invokespecial #2                  // Method org/apache/dubbo/common/URL.getProtocol:()Ljava/lang/String;
       4: areturn

  public com.alibaba.dubbo.common.URL setProtocol(java.lang.String);
    Code:
       0: new           #13                 // class com/alibaba/dubbo/common/URL
       3: dup
       4: aload_1
       5: aload_0
       6: invokespecial #3                  // Method org/apache/dubbo/common/URL.getUsername:()Ljava/lang/String;
       9: aload_0
      10: invokespecial #4                  // Method org/apache/dubbo/common/URL.getPassword:()Ljava/lang/String;
      13: aload_0
      14: invokespecial #5                  // Method org/apache/dubbo/common/URL.getHost:()Ljava/lang/String;
      17: aload_0
      18: invokespecial #6                  // Method org/apache/dubbo/common/URL.getPort:()I
      21: aload_0
      22: invokespecial #7                  // Method org/apache/dubbo/common/URL.getPath:()Ljava/lang/String;
      25: aload_0
      26: invokespecial #8                  // Method org/apache/dubbo/common/URL.getParameters:()Ljava/util/Map;
      29: invokespecial #17                 // Method "<init>":(Ljava/lang/String;Ljava/lang/String;Ljava/lang/String;Ljava/lang/String;ILjava/lang/String;Ljava/util/Map;)V
      32: areturn

  public java.lang.String getUsername();
    Code:
       0: aload_0
       1: invokespecial #3                  // Method org/apache/dubbo/common/URL.getUsername:()Ljava/lang/String;
       4: areturn

  public com.alibaba.dubbo.common.URL setUsername(java.lang.String);
    Code:
       0: new           #13                 // class com/alibaba/dubbo/common/URL
       3: dup
       4: aload_0
       5: invokespecial #2                  // Method org/apache/dubbo/common/URL.getProtocol:()Ljava/lang/String;
       8: aload_1
       9: aload_0
      10: invokespecial #4                  // Method org/apache/dubbo/common/URL.getPassword:()Ljava/lang/String;
      13: aload_0
      14: invokespecial #5                  // Method org/apache/dubbo/common/URL.getHost:()Ljava/lang/String;
      17: aload_0
      18: invokespecial #6                  // Method org/apache/dubbo/common/URL.getPort:()I
      21: aload_0
      22: invokespecial #7                  // Method org/apache/dubbo/common/URL.getPath:()Ljava/lang/String;
      25: aload_0
      26: invokespecial #8                  // Method org/apache/dubbo/common/URL.getParameters:()Ljava/util/Map;
      29: invokespecial #17                 // Method "<init>":(Ljava/lang/String;Ljava/lang/String;Ljava/lang/String;Ljava/lang/String;ILjava/lang/String;Ljava/util/Map;)V
      32: areturn

  public java.lang.String getPassword();
    Code:
       0: aload_0
       1: invokespecial #4                  // Method org/apache/dubbo/common/URL.getPassword:()Ljava/lang/String;
       4: areturn

  public com.alibaba.dubbo.common.URL setPassword(java.lang.String);
    Code:
       0: new           #13                 // class com/alibaba/dubbo/common/URL
       3: dup
       4: aload_0
       5: invokespecial #2                  // Method org/apache/dubbo/common/URL.getProtocol:()Ljava/lang/String;
       8: aload_0
       9: invokespecial #3                  // Method org/apache/dubbo/common/URL.getUsername:()Ljava/lang/String;
      12: aload_1
      13: aload_0
      14: invokespecial #5                  // Method org/apache/dubbo/common/URL.getHost:()Ljava/lang/String;
      17: aload_0
      18: invokespecial #6                  // Method org/apache/dubbo/common/URL.getPort:()I
      21: aload_0
      22: invokespecial #7                  // Method org/apache/dubbo/common/URL.getPath:()Ljava/lang/String;
      25: aload_0
      26: invokespecial #8                  // Method org/apache/dubbo/common/URL.getParameters:()Ljava/util/Map;
      29: invokespecial #17                 // Method "<init>":(Ljava/lang/String;Ljava/lang/String;Ljava/lang/String;Ljava/lang/String;ILjava/lang/String;Ljava/util/Map;)V
      32: areturn

  public java.lang.String getAuthority();
    Code:
       0: aload_0
       1: invokespecial #18                 // Method org/apache/dubbo/common/URL.getUserInformation:()Ljava/lang/String;
       4: areturn

  public java.lang.String getHost();
    Code:
       0: aload_0
       1: invokespecial #5                  // Method org/apache/dubbo/common/URL.getHost:()Ljava/lang/String;
       4: areturn

  public com.alibaba.dubbo.common.URL setHost(java.lang.String);
    Code:
       0: new           #13                 // class com/alibaba/dubbo/common/URL
       3: dup
       4: aload_0
       5: invokespecial #2                  // Method org/apache/dubbo/common/URL.getProtocol:()Ljava/lang/String;
       8: aload_0
       9: invokespecial #3                  // Method org/apache/dubbo/common/URL.getUsername:()Ljava/lang/String;
      12: aload_0
      13: invokespecial #4                  // Method org/apache/dubbo/common/URL.getPassword:()Ljava/lang/String;
      16: aload_1
      17: aload_0
      18: invokespecial #6                  // Method org/apache/dubbo/common/URL.getPort:()I
      21: aload_0
      22: invokespecial #7                  // Method org/apache/dubbo/common/URL.getPath:()Ljava/lang/String;
      25: aload_0
      26: invokespecial #8                  // Method org/apache/dubbo/common/URL.getParameters:()Ljava/util/Map;
      29: invokespecial #17                 // Method "<init>":(Ljava/lang/String;Ljava/lang/String;Ljava/lang/String;Ljava/lang/String;ILjava/lang/String;Ljava/util/Map;)V
      32: areturn

  public java.lang.String getIp();
    Code:
       0: aload_0
       1: invokespecial #19                 // Method org/apache/dubbo/common/URL.getIp:()Ljava/lang/String;
       4: areturn

  public int getPort();
    Code:
       0: aload_0
       1: invokespecial #6                  // Method org/apache/dubbo/common/URL.getPort:()I
       4: ireturn

  public com.alibaba.dubbo.common.URL setPort(int);
    Code:
       0: new           #13                 // class com/alibaba/dubbo/common/URL
       3: dup
       4: aload_0
       5: invokespecial #2                  // Method org/apache/dubbo/common/URL.getProtocol:()Ljava/lang/String;
       8: aload_0
       9: invokespecial #3                  // Method org/apache/dubbo/common/URL.getUsername:()Ljava/lang/String;
      12: aload_0
      13: invokespecial #4                  // Method org/apache/dubbo/common/URL.getPassword:()Ljava/lang/String;
      16: aload_0
      17: invokespecial #5                  // Method org/apache/dubbo/common/URL.getHost:()Ljava/lang/String;
      20: iload_1
      21: aload_0
      22: invokespecial #7                  // Method org/apache/dubbo/common/URL.getPath:()Ljava/lang/String;
      25: aload_0
      26: invokespecial #8                  // Method org/apache/dubbo/common/URL.getParameters:()Ljava/util/Map;
      29: invokespecial #17                 // Method "<init>":(Ljava/lang/String;Ljava/lang/String;Ljava/lang/String;Ljava/lang/String;ILjava/lang/String;Ljava/util/Map;)V
      32: areturn

  public int getPort(int);
    Code:
       0: aload_0
       1: invokespecial #6                  // Method org/apache/dubbo/common/URL.getPort:()I
       4: ireturn

  public java.lang.String getAddress();
    Code:
       0: aload_0
       1: invokespecial #20                 // Method org/apache/dubbo/common/URL.getAddress:()Ljava/lang/String;
       4: areturn

  public com.alibaba.dubbo.common.URL setAddress(java.lang.String);
    Code:
       0: aload_0
       1: aload_1
       2: invokespecial #21                 // Method org/apache/dubbo/common/URL.setAddress:(Ljava/lang/String;)Lorg/apache/dubbo/common/URL;
       5: astore_2
       6: new           #13                 // class com/alibaba/dubbo/common/URL
       9: dup
      10: aload_2
      11: invokespecial #14                 // Method "<init>":(Lorg/apache/dubbo/common/URL;)V
      14: areturn

  public java.lang.String getBackupAddress();
    Code:
       0: aload_0
       1: invokespecial #22                 // Method org/apache/dubbo/common/URL.getBackupAddress:()Ljava/lang/String;
       4: areturn

  public java.lang.String getBackupAddress(int);
    Code:
       0: aload_0
       1: iload_1
       2: invokespecial #23                 // Method org/apache/dubbo/common/URL.getBackupAddress:(I)Ljava/lang/String;
       5: areturn

  public java.lang.String getPath();
    Code:
       0: aload_0
       1: invokespecial #7                  // Method org/apache/dubbo/common/URL.getPath:()Ljava/lang/String;
       4: areturn

  public com.alibaba.dubbo.common.URL setPath(java.lang.String);
    Code:
       0: new           #13                 // class com/alibaba/dubbo/common/URL
       3: dup
       4: aload_0
       5: invokespecial #2                  // Method org/apache/dubbo/common/URL.getProtocol:()Ljava/lang/String;
       8: aload_0
       9: invokespecial #3                  // Method org/apache/dubbo/common/URL.getUsername:()Ljava/lang/String;
      12: aload_0
      13: invokespecial #4                  // Method org/apache/dubbo/common/URL.getPassword:()Ljava/lang/String;
      16: aload_0
      17: invokespecial #5                  // Method org/apache/dubbo/common/URL.getHost:()Ljava/lang/String;
      20: aload_0
      21: invokespecial #6                  // Method org/apache/dubbo/common/URL.getPort:()I
      24: aload_1
      25: aload_0
      26: invokespecial #8                  // Method org/apache/dubbo/common/URL.getParameters:()Ljava/util/Map;
      29: invokespecial #17                 // Method "<init>":(Ljava/lang/String;Ljava/lang/String;Ljava/lang/String;Ljava/lang/String;ILjava/lang/String;Ljava/util/Map;)V
      32: areturn

  public java.lang.String getAbsolutePath();
    Code:
       0: aload_0
       1: invokespecial #24                 // Method org/apache/dubbo/common/URL.getAbsolutePath:()Ljava/lang/String;
       4: areturn

  public java.util.Map<java.lang.String, java.lang.String> getParameters();
    Code:
       0: aload_0
       1: invokespecial #8                  // Method org/apache/dubbo/common/URL.getParameters:()Ljava/util/Map;
       4: areturn

  public java.lang.String getParameterAndDecoded(java.lang.String);
    Code:
       0: aload_0
       1: aload_1
       2: invokespecial #25                 // Method org/apache/dubbo/common/URL.getParameterAndDecoded:(Ljava/lang/String;)Ljava/lang/String;
       5: areturn

  public java.lang.String getParameterAndDecoded(java.lang.String, java.lang.String);
    Code:
       0: aload_0
       1: aload_1
       2: aload_2
       3: invokevirtual #26                 // Method getParameter:(Ljava/lang/String;Ljava/lang/String;)Ljava/lang/String;
       6: invokestatic  #16                 // Method org/apache/dubbo/common/URL.decode:(Ljava/lang/String;)Ljava/lang/String;
       9: areturn

  public java.lang.String getParameter(java.lang.String);
    Code:
       0: aload_0
       1: aload_1
       2: invokespecial #27                 // Method org/apache/dubbo/common/URL.getParameter:(Ljava/lang/String;)Ljava/lang/String;
       5: areturn

  public java.lang.String getParameter(java.lang.String, java.lang.String);
    Code:
       0: aload_0
       1: aload_1
       2: aload_2
       3: invokespecial #28                 // Method org/apache/dubbo/common/URL.getParameter:(Ljava/lang/String;Ljava/lang/String;)Ljava/lang/String;
       6: areturn

  public java.lang.String[] getParameter(java.lang.String, java.lang.String[]);
    Code:
       0: aload_0
       1: aload_1
       2: aload_2
       3: invokespecial #29                 // Method org/apache/dubbo/common/URL.getParameter:(Ljava/lang/String;[Ljava/lang/String;)[Ljava/lang/String;
       6: areturn

  public com.alibaba.dubbo.common.URL getUrlParameter(java.lang.String);
    Code:
       0: aload_0
       1: aload_1
       2: invokespecial #30                 // Method org/apache/dubbo/common/URL.getUrlParameter:(Ljava/lang/String;)Lorg/apache/dubbo/common/URL;
       5: astore_2
       6: new           #13                 // class com/alibaba/dubbo/common/URL
       9: dup
      10: aload_2
      11: invokespecial #14                 // Method "<init>":(Lorg/apache/dubbo/common/URL;)V
      14: areturn

  public double getParameter(java.lang.String, double);
    Code:
       0: aload_0
       1: aload_1
       2: dload_2
       3: invokespecial #31                 // Method org/apache/dubbo/common/URL.getParameter:(Ljava/lang/String;D)D
       6: dreturn

  public float getParameter(java.lang.String, float);
    Code:
       0: aload_0
       1: aload_1
       2: fload_2
       3: invokespecial #32                 // Method org/apache/dubbo/common/URL.getParameter:(Ljava/lang/String;F)F
       6: freturn

  public long getParameter(java.lang.String, long);
    Code:
       0: aload_0
       1: aload_1
       2: lload_2
       3: invokespecial #33                 // Method org/apache/dubbo/common/URL.getParameter:(Ljava/lang/String;J)J
       6: lreturn

  public int getParameter(java.lang.String, int);
    Code:
       0: aload_0
       1: aload_1
       2: iload_2
       3: invokespecial #34                 // Method org/apache/dubbo/common/URL.getParameter:(Ljava/lang/String;I)I
       6: ireturn

  public short getParameter(java.lang.String, short);
    Code:
       0: aload_0
       1: aload_1
       2: iload_2
       3: invokespecial #35                 // Method org/apache/dubbo/common/URL.getParameter:(Ljava/lang/String;S)S
       6: ireturn

  public byte getParameter(java.lang.String, byte);
    Code:
       0: aload_0
       1: aload_1
       2: iload_2
       3: invokespecial #36                 // Method org/apache/dubbo/common/URL.getParameter:(Ljava/lang/String;B)B
       6: ireturn

  public float getPositiveParameter(java.lang.String, float);
    Code:
       0: aload_0
       1: aload_1
       2: fload_2
       3: invokespecial #37                 // Method org/apache/dubbo/common/URL.getPositiveParameter:(Ljava/lang/String;F)F
       6: freturn

  public double getPositiveParameter(java.lang.String, double);
    Code:
       0: aload_0
       1: aload_1
       2: dload_2
       3: invokespecial #38                 // Method org/apache/dubbo/common/URL.getPositiveParameter:(Ljava/lang/String;D)D
       6: dreturn

  public long getPositiveParameter(java.lang.String, long);
    Code:
       0: aload_0
       1: aload_1
       2: lload_2
       3: invokespecial #39                 // Method org/apache/dubbo/common/URL.getPositiveParameter:(Ljava/lang/String;J)J
       6: lreturn

  public int getPositiveParameter(java.lang.String, int);
    Code:
       0: aload_0
       1: aload_1
       2: iload_2
       3: invokespecial #40                 // Method org/apache/dubbo/common/URL.getPositiveParameter:(Ljava/lang/String;I)I
       6: ireturn

  public short getPositiveParameter(java.lang.String, short);
    Code:
       0: aload_0
       1: aload_1
       2: iload_2
       3: invokespecial #41                 // Method org/apache/dubbo/common/URL.getPositiveParameter:(Ljava/lang/String;S)S
       6: ireturn

  public byte getPositiveParameter(java.lang.String, byte);
    Code:
       0: aload_0
       1: aload_1
       2: iload_2
       3: invokespecial #42                 // Method org/apache/dubbo/common/URL.getPositiveParameter:(Ljava/lang/String;B)B
       6: ireturn

  public char getParameter(java.lang.String, char);
    Code:
       0: aload_0
       1: aload_1
       2: iload_2
       3: invokespecial #43                 // Method org/apache/dubbo/common/URL.getParameter:(Ljava/lang/String;C)C
       6: ireturn

  public boolean getParameter(java.lang.String, boolean);
    Code:
       0: aload_0
       1: aload_1
       2: iload_2
       3: invokespecial #44                 // Method org/apache/dubbo/common/URL.getParameter:(Ljava/lang/String;Z)Z
       6: ireturn

  public boolean hasParameter(java.lang.String);
    Code:
       0: aload_0
       1: aload_1
       2: invokespecial #45                 // Method org/apache/dubbo/common/URL.hasParameter:(Ljava/lang/String;)Z
       5: ireturn

  public java.lang.String getMethodParameterAndDecoded(java.lang.String, java.lang.String);
    Code:
       0: aload_0
       1: aload_1
       2: aload_2
       3: invokespecial #46                 // Method org/apache/dubbo/common/URL.getMethodParameterAndDecoded:(Ljava/lang/String;Ljava/lang/String;)Ljava/lang/String;
       6: areturn

  public java.lang.String getMethodParameterAndDecoded(java.lang.String, java.lang.String, java.lang.String);
    Code:
       0: aload_0
       1: aload_1
       2: aload_2
       3: aload_3
       4: invokespecial #47                 // Method org/apache/dubbo/common/URL.getMethodParameterAndDecoded:(Ljava/lang/String;Ljava/lang/String;Ljava/lang/String;)Ljava/lang/String;
       7: areturn

  public java.lang.String getMethodParameter(java.lang.String, java.lang.String);
    Code:
       0: aload_0
       1: aload_1
       2: aload_2
       3: invokespecial #48                 // Method org/apache/dubbo/common/URL.getMethodParameter:(Ljava/lang/String;Ljava/lang/String;)Ljava/lang/String;
       6: areturn

  public java.lang.String getMethodParameter(java.lang.String, java.lang.String, java.lang.String);
    Code:
       0: aload_0
       1: aload_1
       2: aload_2
       3: aload_3
       4: invokespecial #49                 // Method org/apache/dubbo/common/URL.getMethodParameter:(Ljava/lang/String;Ljava/lang/String;Ljava/lang/String;)Ljava/lang/String;
       7: areturn

  public double getMethodParameter(java.lang.String, java.lang.String, double);
    Code:
       0: aload_0
       1: aload_1
       2: aload_2
       3: dload_3
       4: invokespecial #50                 // Method org/apache/dubbo/common/URL.getMethodParameter:(Ljava/lang/String;Ljava/lang/String;D)D
       7: dreturn

  public float getMethodParameter(java.lang.String, java.lang.String, float);
    Code:
       0: aload_0
       1: aload_1
       2: aload_2
       3: fload_3
       4: invokespecial #51                 // Method org/apache/dubbo/common/URL.getMethodParameter:(Ljava/lang/String;Ljava/lang/String;F)F
       7: freturn

  public long getMethodParameter(java.lang.String, java.lang.String, long);
    Code:
       0: aload_0
       1: aload_1
       2: aload_2
       3: lload_3
       4: invokespecial #52                 // Method org/apache/dubbo/common/URL.getMethodParameter:(Ljava/lang/String;Ljava/lang/String;J)J
       7: lreturn

  public int getMethodParameter(java.lang.String, java.lang.String, int);
    Code:
       0: aload_0
       1: aload_1
       2: aload_2
       3: iload_3
       4: invokespecial #53                 // Method org/apache/dubbo/common/URL.getMethodParameter:(Ljava/lang/String;Ljava/lang/String;I)I
       7: ireturn

  public short getMethodParameter(java.lang.String, java.lang.String, short);
    Code:
       0: aload_0
       1: aload_1
       2: aload_2
       3: iload_3
       4: invokespecial #54                 // Method org/apache/dubbo/common/URL.getMethodParameter:(Ljava/lang/String;Ljava/lang/String;S)S
       7: ireturn

  public byte getMethodParameter(java.lang.String, java.lang.String, byte);
    Code:
       0: aload_0
       1: aload_1
       2: aload_2
       3: iload_3
       4: invokespecial #55                 // Method org/apache/dubbo/common/URL.getMethodParameter:(Ljava/lang/String;Ljava/lang/String;B)B
       7: ireturn

  public double getMethodPositiveParameter(java.lang.String, java.lang.String, double);
    Code:
       0: aload_0
       1: aload_1
       2: aload_2
       3: dload_3
       4: invokespecial #56                 // Method org/apache/dubbo/common/URL.getMethodPositiveParameter:(Ljava/lang/String;Ljava/lang/String;D)D
       7: dreturn

  public float getMethodPositiveParameter(java.lang.String, java.lang.String, float);
    Code:
       0: aload_0
       1: aload_1
       2: aload_2
       3: fload_3
       4: invokespecial #57                 // Method org/apache/dubbo/common/URL.getMethodPositiveParameter:(Ljava/lang/String;Ljava/lang/String;F)F
       7: freturn

  public long getMethodPositiveParameter(java.lang.String, java.lang.String, long);
    Code:
       0: aload_0
       1: aload_1
       2: aload_2
       3: lload_3
       4: invokespecial #58                 // Method org/apache/dubbo/common/URL.getMethodPositiveParameter:(Ljava/lang/String;Ljava/lang/String;J)J
       7: lreturn

  public int getMethodPositiveParameter(java.lang.String, java.lang.String, int);
    Code:
       0: aload_0
       1: aload_1
       2: aload_2
       3: iload_3
       4: invokespecial #59                 // Method org/apache/dubbo/common/URL.getMethodPositiveParameter:(Ljava/lang/String;Ljava/lang/String;I)I
       7: ireturn

  public short getMethodPositiveParameter(java.lang.String, java.lang.String, short);
    Code:
       0: aload_0
       1: aload_1
       2: aload_2
       3: iload_3
       4: invokespecial #60                 // Method org/apache/dubbo/common/URL.getMethodPositiveParameter:(Ljava/lang/String;Ljava/lang/String;S)S
       7: ireturn

  public byte getMethodPositiveParameter(java.lang.String, java.lang.String, byte);
    Code:
       0: aload_0
       1: aload_1
       2: aload_2
       3: iload_3
       4: invokespecial #61                 // Method org/apache/dubbo/common/URL.getMethodPositiveParameter:(Ljava/lang/String;Ljava/lang/String;B)B
       7: ireturn

  public char getMethodParameter(java.lang.String, java.lang.String, char);
    Code:
       0: aload_0
       1: aload_1
       2: aload_2
       3: iload_3
       4: invokespecial #62                 // Method org/apache/dubbo/common/URL.getMethodParameter:(Ljava/lang/String;Ljava/lang/String;C)C
       7: ireturn

  public boolean getMethodParameter(java.lang.String, java.lang.String, boolean);
    Code:
       0: aload_0
       1: aload_1
       2: aload_2
       3: iload_3
       4: invokespecial #63                 // Method org/apache/dubbo/common/URL.getMethodParameter:(Ljava/lang/String;Ljava/lang/String;Z)Z
       7: ireturn

  public boolean hasMethodParameter(java.lang.String, java.lang.String);
    Code:
       0: aload_0
       1: aload_1
       2: aload_2
       3: invokespecial #64                 // Method org/apache/dubbo/common/URL.hasMethodParameter:(Ljava/lang/String;Ljava/lang/String;)Z
       6: ireturn

  public boolean isLocalHost();
    Code:
       0: aload_0
       1: invokespecial #65                 // Method org/apache/dubbo/common/URL.isLocalHost:()Z
       4: ireturn

  public boolean isAnyHost();
    Code:
       0: aload_0
       1: invokespecial #66                 // Method org/apache/dubbo/common/URL.isAnyHost:()Z
       4: ireturn

  public com.alibaba.dubbo.common.URL addParameterAndEncoded(java.lang.String, java.lang.String);
    Code:
       0: aload_2
       1: invokestatic  #67                 // Method org/apache/dubbo/common/utils/StringUtils.isEmpty:(Ljava/lang/String;)Z
       4: ifeq          9
       7: aload_0
       8: areturn
       9: aload_0
      10: aload_1
      11: aload_2
      12: invokestatic  #68                 // Method encode:(Ljava/lang/String;)Ljava/lang/String;
      15: invokevirtual #69                 // Method addParameter:(Ljava/lang/String;Ljava/lang/String;)Lcom/alibaba/dubbo/common/URL;
      18: areturn

  public com.alibaba.dubbo.common.URL addParameter(java.lang.String, boolean);
    Code:
       0: aload_0
       1: aload_1
       2: iload_2
       3: invokestatic  #70                 // Method java/lang/String.valueOf:(Z)Ljava/lang/String;
       6: invokevirtual #69                 // Method addParameter:(Ljava/lang/String;Ljava/lang/String;)Lcom/alibaba/dubbo/common/URL;
       9: areturn

  public com.alibaba.dubbo.common.URL addParameter(java.lang.String, char);
    Code:
       0: aload_0
       1: aload_1
       2: iload_2
       3: invokestatic  #71                 // Method java/lang/String.valueOf:(C)Ljava/lang/String;
       6: invokevirtual #69                 // Method addParameter:(Ljava/lang/String;Ljava/lang/String;)Lcom/alibaba/dubbo/common/URL;
       9: areturn

  public com.alibaba.dubbo.common.URL addParameter(java.lang.String, byte);
    Code:
       0: aload_0
       1: aload_1
       2: iload_2
       3: invokestatic  #72                 // Method java/lang/String.valueOf:(I)Ljava/lang/String;
       6: invokevirtual #69                 // Method addParameter:(Ljava/lang/String;Ljava/lang/String;)Lcom/alibaba/dubbo/common/URL;
       9: areturn

  public com.alibaba.dubbo.common.URL addParameter(java.lang.String, short);
    Code:
       0: aload_0
       1: aload_1
       2: iload_2
       3: invokestatic  #72                 // Method java/lang/String.valueOf:(I)Ljava/lang/String;
       6: invokevirtual #69                 // Method addParameter:(Ljava/lang/String;Ljava/lang/String;)Lcom/alibaba/dubbo/common/URL;
       9: areturn

  public com.alibaba.dubbo.common.URL addParameter(java.lang.String, int);
    Code:
       0: aload_0
       1: aload_1
       2: iload_2
       3: invokestatic  #72                 // Method java/lang/String.valueOf:(I)Ljava/lang/String;
       6: invokevirtual #69                 // Method addParameter:(Ljava/lang/String;Ljava/lang/String;)Lcom/alibaba/dubbo/common/URL;
       9: areturn

  public com.alibaba.dubbo.common.URL addParameter(java.lang.String, long);
    Code:
       0: aload_0
       1: aload_1
       2: lload_2
       3: invokestatic  #73                 // Method java/lang/String.valueOf:(J)Ljava/lang/String;
       6: invokevirtual #69                 // Method addParameter:(Ljava/lang/String;Ljava/lang/String;)Lcom/alibaba/dubbo/common/URL;
       9: areturn

  public com.alibaba.dubbo.common.URL addParameter(java.lang.String, float);
    Code:
       0: aload_0
       1: aload_1
       2: fload_2
       3: invokestatic  #74                 // Method java/lang/String.valueOf:(F)Ljava/lang/String;
       6: invokevirtual #69                 // Method addParameter:(Ljava/lang/String;Ljava/lang/String;)Lcom/alibaba/dubbo/common/URL;
       9: areturn

  public com.alibaba.dubbo.common.URL addParameter(java.lang.String, double);
    Code:
       0: aload_0
       1: aload_1
       2: dload_2
       3: invokestatic  #75                 // Method java/lang/String.valueOf:(D)Ljava/lang/String;
       6: invokevirtual #69                 // Method addParameter:(Ljava/lang/String;Ljava/lang/String;)Lcom/alibaba/dubbo/common/URL;
       9: areturn

  public com.alibaba.dubbo.common.URL addParameter(java.lang.String, java.lang.Enum<?>);
    Code:
       0: aload_2
       1: ifnonnull     6
       4: aload_0
       5: areturn
       6: aload_0
       7: aload_1
       8: aload_2
       9: invokestatic  #76                 // Method java/lang/String.valueOf:(Ljava/lang/Object;)Ljava/lang/String;
      12: invokevirtual #69                 // Method addParameter:(Ljava/lang/String;Ljava/lang/String;)Lcom/alibaba/dubbo/common/URL;
      15: areturn

  public com.alibaba.dubbo.common.URL addParameter(java.lang.String, java.lang.Number);
    Code:
       0: aload_2
       1: ifnonnull     6
       4: aload_0
       5: areturn
       6: aload_0
       7: aload_1
       8: aload_2
       9: invokestatic  #76                 // Method java/lang/String.valueOf:(Ljava/lang/Object;)Ljava/lang/String;
      12: invokevirtual #69                 // Method addParameter:(Ljava/lang/String;Ljava/lang/String;)Lcom/alibaba/dubbo/common/URL;
      15: areturn

  public com.alibaba.dubbo.common.URL addParameter(java.lang.String, java.lang.CharSequence);
    Code:
       0: aload_2
       1: ifnull        13
       4: aload_2
       5: invokeinterface #77,  1           // InterfaceMethod java/lang/CharSequence.length:()I
      10: ifne          15
      13: aload_0
      14: areturn
      15: aload_0
      16: aload_1
      17: aload_2
      18: invokestatic  #76                 // Method java/lang/String.valueOf:(Ljava/lang/Object;)Ljava/lang/String;
      21: invokevirtual #69                 // Method addParameter:(Ljava/lang/String;Ljava/lang/String;)Lcom/alibaba/dubbo/common/URL;
      24: areturn

  public com.alibaba.dubbo.common.URL addParameter(java.lang.String, java.lang.String);
    Code:
       0: aload_0
       1: aload_1
       2: aload_2
       3: invokespecial #78                 // Method org/apache/dubbo/common/URL.addParameter:(Ljava/lang/String;Ljava/lang/String;)Lorg/apache/dubbo/common/URL;
       6: astore_3
       7: new           #13                 // class com/alibaba/dubbo/common/URL
      10: dup
      11: aload_3
      12: invokespecial #14                 // Method "<init>":(Lorg/apache/dubbo/common/URL;)V
      15: areturn

  public com.alibaba.dubbo.common.URL addParameterIfAbsent(java.lang.String, java.lang.String);
    Code:
       0: aload_0
       1: aload_1
       2: aload_2
       3: invokespecial #79                 // Method org/apache/dubbo/common/URL.addParameterIfAbsent:(Ljava/lang/String;Ljava/lang/String;)Lorg/apache/dubbo/common/URL;
       6: astore_3
       7: new           #13                 // class com/alibaba/dubbo/common/URL
      10: dup
      11: aload_3
      12: invokespecial #14                 // Method "<init>":(Lorg/apache/dubbo/common/URL;)V
      15: areturn

  public com.alibaba.dubbo.common.URL addParameters(java.util.Map<java.lang.String, java.lang.String>);
    Code:
       0: aload_0
       1: aload_1
       2: invokespecial #80                 // Method org/apache/dubbo/common/URL.addParameters:(Ljava/util/Map;)Lorg/apache/dubbo/common/URL;
       5: astore_2
       6: new           #13                 // class com/alibaba/dubbo/common/URL
       9: dup
      10: aload_2
      11: invokespecial #14                 // Method "<init>":(Lorg/apache/dubbo/common/URL;)V
      14: areturn

  public com.alibaba.dubbo.common.URL addParametersIfAbsent(java.util.Map<java.lang.String, java.lang.String>);
    Code:
       0: aload_0
       1: aload_1
       2: invokespecial #81                 // Method org/apache/dubbo/common/URL.addParametersIfAbsent:(Ljava/util/Map;)Lorg/apache/dubbo/common/URL;
       5: astore_2
       6: new           #13                 // class com/alibaba/dubbo/common/URL
       9: dup
      10: aload_2
      11: invokespecial #14                 // Method "<init>":(Lorg/apache/dubbo/common/URL;)V
      14: areturn

  public com.alibaba.dubbo.common.URL addParameters(java.lang.String...);
    Code:
       0: aload_0
       1: aload_1
       2: invokespecial #82                 // Method org/apache/dubbo/common/URL.addParameters:([Ljava/lang/String;)Lorg/apache/dubbo/common/URL;
       5: astore_2
       6: new           #13                 // class com/alibaba/dubbo/common/URL
       9: dup
      10: aload_2
      11: invokespecial #14                 // Method "<init>":(Lorg/apache/dubbo/common/URL;)V
      14: areturn

  public com.alibaba.dubbo.common.URL addParameterString(java.lang.String);
    Code:
       0: aload_0
       1: aload_1
       2: invokespecial #83                 // Method org/apache/dubbo/common/URL.addParameterString:(Ljava/lang/String;)Lorg/apache/dubbo/common/URL;
       5: astore_2
       6: new           #13                 // class com/alibaba/dubbo/common/URL
       9: dup
      10: aload_2
      11: invokespecial #14                 // Method "<init>":(Lorg/apache/dubbo/common/URL;)V
      14: areturn

  public com.alibaba.dubbo.common.URL removeParameter(java.lang.String);
    Code:
       0: aload_0
       1: aload_1
       2: invokespecial #84                 // Method org/apache/dubbo/common/URL.removeParameter:(Ljava/lang/String;)Lorg/apache/dubbo/common/URL;
       5: astore_2
       6: new           #13                 // class com/alibaba/dubbo/common/URL
       9: dup
      10: aload_2
      11: invokespecial #14                 // Method "<init>":(Lorg/apache/dubbo/common/URL;)V
      14: areturn

  public com.alibaba.dubbo.common.URL removeParameters(java.util.Collection<java.lang.String>);
    Code:
       0: aload_0
       1: aload_1
       2: invokespecial #85                 // Method org/apache/dubbo/common/URL.removeParameters:(Ljava/util/Collection;)Lorg/apache/dubbo/common/URL;
       5: astore_2
       6: new           #13                 // class com/alibaba/dubbo/common/URL
       9: dup
      10: aload_2
      11: invokespecial #14                 // Method "<init>":(Lorg/apache/dubbo/common/URL;)V
      14: areturn

  public com.alibaba.dubbo.common.URL removeParameters(java.lang.String...);
    Code:
       0: aload_0
       1: aload_1
       2: invokespecial #86                 // Method org/apache/dubbo/common/URL.removeParameters:([Ljava/lang/String;)Lorg/apache/dubbo/common/URL;
       5: astore_2
       6: new           #13                 // class com/alibaba/dubbo/common/URL
       9: dup
      10: aload_2
      11: invokespecial #14                 // Method "<init>":(Lorg/apache/dubbo/common/URL;)V
      14: areturn

  public com.alibaba.dubbo.common.URL clearParameters();
    Code:
       0: aload_0
       1: invokespecial #87                 // Method org/apache/dubbo/common/URL.clearParameters:()Lorg/apache/dubbo/common/URL;
       4: astore_1
       5: new           #13                 // class com/alibaba/dubbo/common/URL
       8: dup
       9: aload_1
      10: invokespecial #14                 // Method "<init>":(Lorg/apache/dubbo/common/URL;)V
      13: areturn

  public java.lang.String getRawParameter(java.lang.String);
    Code:
       0: aload_0
       1: aload_1
       2: invokespecial #88                 // Method org/apache/dubbo/common/URL.getRawParameter:(Ljava/lang/String;)Ljava/lang/String;
       5: areturn

  public java.util.Map<java.lang.String, java.lang.String> toMap();
    Code:
       0: aload_0
       1: invokespecial #89                 // Method org/apache/dubbo/common/URL.toMap:()Ljava/util/Map;
       4: areturn

  public java.lang.String toString();
    Code:
       0: aload_0
       1: invokespecial #90                 // Method org/apache/dubbo/common/URL.toString:()Ljava/lang/String;
       4: areturn

  public java.lang.String toString(java.lang.String...);
    Code:
       0: aload_0
       1: aload_1
       2: invokespecial #91                 // Method org/apache/dubbo/common/URL.toString:([Ljava/lang/String;)Ljava/lang/String;
       5: areturn

  public java.lang.String toIdentityString();
    Code:
       0: aload_0
       1: invokespecial #92                 // Method org/apache/dubbo/common/URL.toIdentityString:()Ljava/lang/String;
       4: areturn

  public java.lang.String toIdentityString(java.lang.String...);
    Code:
       0: aload_0
       1: aload_1
       2: invokespecial #93                 // Method org/apache/dubbo/common/URL.toIdentityString:([Ljava/lang/String;)Ljava/lang/String;
       5: areturn

  public java.lang.String toFullString();
    Code:
       0: aload_0
       1: invokespecial #94                 // Method org/apache/dubbo/common/URL.toFullString:()Ljava/lang/String;
       4: areturn

  public java.lang.String toFullString(java.lang.String...);
    Code:
       0: aload_0
       1: aload_1
       2: invokespecial #95                 // Method org/apache/dubbo/common/URL.toFullString:([Ljava/lang/String;)Ljava/lang/String;
       5: areturn

  public java.lang.String toParameterString();
    Code:
       0: aload_0
       1: invokespecial #96                 // Method org/apache/dubbo/common/URL.toParameterString:()Ljava/lang/String;
       4: areturn

  public java.lang.String toParameterString(java.lang.String...);
    Code:
       0: aload_0
       1: aload_1
       2: invokespecial #97                 // Method org/apache/dubbo/common/URL.toParameterString:([Ljava/lang/String;)Ljava/lang/String;
       5: areturn

  public java.net.URL toJavaURL();
    Code:
       0: aload_0
       1: invokespecial #98                 // Method org/apache/dubbo/common/URL.toJavaURL:()Ljava/net/URL;
       4: areturn

  public java.net.InetSocketAddress toInetSocketAddress();
    Code:
       0: aload_0
       1: invokespecial #99                 // Method org/apache/dubbo/common/URL.toInetSocketAddress:()Ljava/net/InetSocketAddress;
       4: areturn

  public java.lang.String getServiceKey();
    Code:
       0: aload_0
       1: invokespecial #100                // Method org/apache/dubbo/common/URL.getServiceKey:()Ljava/lang/String;
       4: areturn

  public java.lang.String toServiceStringWithoutResolving();
    Code:
       0: aload_0
       1: invokespecial #101                // Method org/apache/dubbo/common/URL.toServiceStringWithoutResolving:()Ljava/lang/String;
       4: areturn

  public java.lang.String toServiceString();
    Code:
       0: aload_0
       1: invokespecial #102                // Method org/apache/dubbo/common/URL.toServiceString:()Ljava/lang/String;
       4: areturn

  public java.lang.String getServiceInterface();
    Code:
       0: aload_0
       1: invokespecial #103                // Method org/apache/dubbo/common/URL.getServiceInterface:()Ljava/lang/String;
       4: areturn

  public com.alibaba.dubbo.common.URL setServiceInterface(java.lang.String);
    Code:
       0: aload_0
       1: aload_1
       2: invokespecial #104                // Method org/apache/dubbo/common/URL.setServiceInterface:(Ljava/lang/String;)Lorg/apache/dubbo/common/URL;
       5: astore_2
       6: new           #13                 // class com/alibaba/dubbo/common/URL
       9: dup
      10: aload_2
      11: invokespecial #14                 // Method "<init>":(Lorg/apache/dubbo/common/URL;)V
      14: areturn

  public org.apache.dubbo.common.URL getOriginalURL();
    Code:
       0: new           #105                // class org/apache/dubbo/common/URL
       3: dup
       4: aload_0
       5: invokespecial #2                  // Method org/apache/dubbo/common/URL.getProtocol:()Ljava/lang/String;
       8: aload_0
       9: invokespecial #3                  // Method org/apache/dubbo/common/URL.getUsername:()Ljava/lang/String;
      12: aload_0
      13: invokespecial #4                  // Method org/apache/dubbo/common/URL.getPassword:()Ljava/lang/String;
      16: aload_0
      17: invokespecial #5                  // Method org/apache/dubbo/common/URL.getHost:()Ljava/lang/String;
      20: aload_0
      21: invokespecial #6                  // Method org/apache/dubbo/common/URL.getPort:()I
      24: aload_0
      25: invokespecial #7                  // Method org/apache/dubbo/common/URL.getPath:()Ljava/lang/String;
      28: aload_0
      29: invokespecial #8                  // Method org/apache/dubbo/common/URL.getParameters:()Ljava/util/Map;
      32: invokespecial #9                  // Method org/apache/dubbo/common/URL."<init>":(Ljava/lang/String;Ljava/lang/String;Ljava/lang/String;Ljava/lang/String;ILjava/lang/String;Ljava/util/Map;)V
      35: areturn

  public org.apache.dubbo.common.URL setServiceInterface(java.lang.String);
    Code:
       0: aload_0
       1: aload_1
       2: invokevirtual #106                // Method setServiceInterface:(Ljava/lang/String;)Lcom/alibaba/dubbo/common/URL;
       5: areturn

  public org.apache.dubbo.common.URL clearParameters();
    Code:
       0: aload_0
       1: invokevirtual #107                // Method clearParameters:()Lcom/alibaba/dubbo/common/URL;
       4: areturn

  public org.apache.dubbo.common.URL removeParameters(java.lang.String[]);
    Code:
       0: aload_0
       1: aload_1
       2: invokevirtual #108                // Method removeParameters:([Ljava/lang/String;)Lcom/alibaba/dubbo/common/URL;
       5: areturn

  public org.apache.dubbo.common.URL removeParameters(java.util.Collection);
    Code:
       0: aload_0
       1: aload_1
       2: invokevirtual #109                // Method removeParameters:(Ljava/util/Collection;)Lcom/alibaba/dubbo/common/URL;
       5: areturn

  public org.apache.dubbo.common.URL removeParameter(java.lang.String);
    Code:
       0: aload_0
       1: aload_1
       2: invokevirtual #110                // Method removeParameter:(Ljava/lang/String;)Lcom/alibaba/dubbo/common/URL;
       5: areturn

  public org.apache.dubbo.common.URL addParameterString(java.lang.String);
    Code:
       0: aload_0
       1: aload_1
       2: invokevirtual #111                // Method addParameterString:(Ljava/lang/String;)Lcom/alibaba/dubbo/common/URL;
       5: areturn

  public org.apache.dubbo.common.URL addParameters(java.lang.String[]);
    Code:
       0: aload_0
       1: aload_1
       2: invokevirtual #112                // Method addParameters:([Ljava/lang/String;)Lcom/alibaba/dubbo/common/URL;
       5: areturn

  public org.apache.dubbo.common.URL addParametersIfAbsent(java.util.Map);
    Code:
       0: aload_0
       1: aload_1
       2: invokevirtual #113                // Method addParametersIfAbsent:(Ljava/util/Map;)Lcom/alibaba/dubbo/common/URL;
       5: areturn

  public org.apache.dubbo.common.URL addParameters(java.util.Map);
    Code:
       0: aload_0
       1: aload_1
       2: invokevirtual #114                // Method addParameters:(Ljava/util/Map;)Lcom/alibaba/dubbo/common/URL;
       5: areturn

  public org.apache.dubbo.common.URL addParameterIfAbsent(java.lang.String, java.lang.String);
    Code:
       0: aload_0
       1: aload_1
       2: aload_2
       3: invokevirtual #115                // Method addParameterIfAbsent:(Ljava/lang/String;Ljava/lang/String;)Lcom/alibaba/dubbo/common/URL;
       6: areturn

  public org.apache.dubbo.common.URL addParameter(java.lang.String, java.lang.String);
    Code:
       0: aload_0
       1: aload_1
       2: aload_2
       3: invokevirtual #69                 // Method addParameter:(Ljava/lang/String;Ljava/lang/String;)Lcom/alibaba/dubbo/common/URL;
       6: areturn

  public org.apache.dubbo.common.URL addParameter(java.lang.String, java.lang.CharSequence);
    Code:
       0: aload_0
       1: aload_1
       2: aload_2
       3: invokevirtual #116                // Method addParameter:(Ljava/lang/String;Ljava/lang/CharSequence;)Lcom/alibaba/dubbo/common/URL;
       6: areturn

  public org.apache.dubbo.common.URL addParameter(java.lang.String, java.lang.Number);
    Code:
       0: aload_0
       1: aload_1
       2: aload_2
       3: invokevirtual #117                // Method addParameter:(Ljava/lang/String;Ljava/lang/Number;)Lcom/alibaba/dubbo/common/URL;
       6: areturn

  public org.apache.dubbo.common.URL addParameter(java.lang.String, java.lang.Enum);
    Code:
       0: aload_0
       1: aload_1
       2: aload_2
       3: invokevirtual #118                // Method addParameter:(Ljava/lang/String;Ljava/lang/Enum;)Lcom/alibaba/dubbo/common/URL;
       6: areturn

  public org.apache.dubbo.common.URL addParameter(java.lang.String, double);
    Code:
       0: aload_0
       1: aload_1
       2: dload_2
       3: invokevirtual #119                // Method addParameter:(Ljava/lang/String;D)Lcom/alibaba/dubbo/common/URL;
       6: areturn

  public org.apache.dubbo.common.URL addParameter(java.lang.String, float);
    Code:
       0: aload_0
       1: aload_1
       2: fload_2
       3: invokevirtual #120                // Method addParameter:(Ljava/lang/String;F)Lcom/alibaba/dubbo/common/URL;
       6: areturn

  public org.apache.dubbo.common.URL addParameter(java.lang.String, long);
    Code:
       0: aload_0
       1: aload_1
       2: lload_2
       3: invokevirtual #121                // Method addParameter:(Ljava/lang/String;J)Lcom/alibaba/dubbo/common/URL;
       6: areturn

  public org.apache.dubbo.common.URL addParameter(java.lang.String, int);
    Code:
       0: aload_0
       1: aload_1
       2: iload_2
       3: invokevirtual #122                // Method addParameter:(Ljava/lang/String;I)Lcom/alibaba/dubbo/common/URL;
       6: areturn

  public org.apache.dubbo.common.URL addParameter(java.lang.String, short);
    Code:
       0: aload_0
       1: aload_1
       2: iload_2
       3: invokevirtual #123                // Method addParameter:(Ljava/lang/String;S)Lcom/alibaba/dubbo/common/URL;
       6: areturn

  public org.apache.dubbo.common.URL addParameter(java.lang.String, byte);
    Code:
       0: aload_0
       1: aload_1
       2: iload_2
       3: invokevirtual #124                // Method addParameter:(Ljava/lang/String;B)Lcom/alibaba/dubbo/common/URL;
       6: areturn

  public org.apache.dubbo.common.URL addParameter(java.lang.String, char);
    Code:
       0: aload_0
       1: aload_1
       2: iload_2
       3: invokevirtual #125                // Method addParameter:(Ljava/lang/String;C)Lcom/alibaba/dubbo/common/URL;
       6: areturn

  public org.apache.dubbo.common.URL addParameter(java.lang.String, boolean);
    Code:
       0: aload_0
       1: aload_1
       2: iload_2
       3: invokevirtual #126                // Method addParameter:(Ljava/lang/String;Z)Lcom/alibaba/dubbo/common/URL;
       6: areturn

  public org.apache.dubbo.common.URL addParameterAndEncoded(java.lang.String, java.lang.String);
    Code:
       0: aload_0
       1: aload_1
       2: aload_2
       3: invokevirtual #127                // Method addParameterAndEncoded:(Ljava/lang/String;Ljava/lang/String;)Lcom/alibaba/dubbo/common/URL;
       6: areturn

  public org.apache.dubbo.common.URL getUrlParameter(java.lang.String);
    Code:
       0: aload_0
       1: aload_1
       2: invokevirtual #128                // Method getUrlParameter:(Ljava/lang/String;)Lcom/alibaba/dubbo/common/URL;
       5: areturn

  public org.apache.dubbo.common.URL setPath(java.lang.String);
    Code:
       0: aload_0
       1: aload_1
       2: invokevirtual #129                // Method setPath:(Ljava/lang/String;)Lcom/alibaba/dubbo/common/URL;
       5: areturn

  public org.apache.dubbo.common.URL setAddress(java.lang.String);
    Code:
       0: aload_0
       1: aload_1
       2: invokevirtual #130                // Method setAddress:(Ljava/lang/String;)Lcom/alibaba/dubbo/common/URL;
       5: areturn

  public org.apache.dubbo.common.URL setPort(int);
    Code:
       0: aload_0
       1: iload_1
       2: invokevirtual #131                // Method setPort:(I)Lcom/alibaba/dubbo/common/URL;
       5: areturn

  public org.apache.dubbo.common.URL setHost(java.lang.String);
    Code:
       0: aload_0
       1: aload_1
       2: invokevirtual #132                // Method setHost:(Ljava/lang/String;)Lcom/alibaba/dubbo/common/URL;
       5: areturn

  public org.apache.dubbo.common.URL setPassword(java.lang.String);
    Code:
       0: aload_0
       1: aload_1
       2: invokevirtual #133                // Method setPassword:(Ljava/lang/String;)Lcom/alibaba/dubbo/common/URL;
       5: areturn

  public org.apache.dubbo.common.URL setUsername(java.lang.String);
    Code:
       0: aload_0
       1: aload_1
       2: invokevirtual #134                // Method setUsername:(Ljava/lang/String;)Lcom/alibaba/dubbo/common/URL;
       5: areturn

  public org.apache.dubbo.common.URL setProtocol(java.lang.String);
    Code:
       0: aload_0
       1: aload_1
       2: invokevirtual #135                // Method setProtocol:(Ljava/lang/String;)Lcom/alibaba/dubbo/common/URL;
       5: areturn
}
