Compiled from "ByteBuddyProxy.java"
class org.apache.dubbo.rpc.proxy.bytebuddy.ByteBuddyProxy$CacheKey {
  private final java.lang.Class<?>[] classes;

  private org.apache.dubbo.rpc.proxy.bytebuddy.ByteBuddyProxy$CacheKey(java.lang.Class<?>[]);
    Code:
       0: aload_0
       1: invokespecial #2                  // Method java/lang/Object."<init>":()V
       4: aload_0
       5: aload_1
       6: putfield      #3                  // Field classes:[Ljava/lang/Class;
       9: return

  public java.lang.Class<?>[] getClasses();
    Code:
       0: aload_0
       1: getfield      #3                  // Field classes:[Ljava/lang/Class;
       4: areturn

  public boolean equals(java.lang.Object);
    Code:
       0: aload_0
       1: aload_1
       2: if_acmpne     7
       5: iconst_1
       6: ireturn
       7: aload_1
       8: ifnull        22
      11: aload_0
      12: invokevirtual #4                  // Method java/lang/Object.getClass:()Ljava/lang/Class;
      15: aload_1
      16: invokevirtual #4                  // Method java/lang/Object.getClass:()Ljava/lang/Class;
      19: if_acmpeq     24
      22: iconst_0
      23: ireturn
      24: aload_1
      25: checkcast     #5                  // class org/apache/dubbo/rpc/proxy/bytebuddy/ByteBuddyProxy$CacheKey
      28: astore_2
      29: aload_0
      30: getfield      #3                  // Field classes:[Ljava/lang/Class;
      33: aload_2
      34: getfield      #3                  // Field classes:[Ljava/lang/Class;
      37: invokestatic  #6                  // Method java/util/Arrays.equals:([Ljava/lang/Object;[Ljava/lang/Object;)Z
      40: ireturn

  public int hashCode();
    Code:
       0: aload_0
       1: getfield      #3                  // Field classes:[Ljava/lang/Class;
       4: invokestatic  #7                  // Method java/util/Arrays.hashCode:([Ljava/lang/Object;)I
       7: ireturn

  org.apache.dubbo.rpc.proxy.bytebuddy.ByteBuddyProxy$CacheKey(java.lang.Class[], org.apache.dubbo.rpc.proxy.bytebuddy.ByteBuddyProxy$1);
    Code:
       0: aload_0
       1: aload_1
       2: invokespecial #1                  // Method "<init>":([Ljava/lang/Class;)V
       5: return
}
