Compiled from "ByteBuddyProxyInvoker.java"
class org.apache.dubbo.rpc.proxy.bytebuddy.ByteBuddyProxyInvoker<T> extends org.apache.dubbo.rpc.proxy.AbstractProxyInvoker<T> {
  private final org.apache.dubbo.rpc.proxy.MethodInvoker methodInvoker;

  private org.apache.dubbo.rpc.proxy.bytebuddy.ByteBuddyProxyInvoker(T, java.lang.Class<T>, org.apache.dubbo.common.URL, org.apache.dubbo.rpc.proxy.MethodInvoker);
    Code:
       0: aload_0
       1: aload_1
       2: aload_2
       3: aload_3
       4: invokespecial #1                  // Method org/apache/dubbo/rpc/proxy/AbstractProxyInvoker."<init>":(Ljava/lang/Object;Ljava/lang/Class;Lorg/apache/dubbo/common/URL;)V
       7: aload_0
       8: aload         4
      10: putfield      #2                  // Field methodInvoker:Lorg/apache/dubbo/rpc/proxy/MethodInvoker;
      13: return

  protected java.lang.Object doInvoke(T, java.lang.String, java.lang.Class<?>[], java.lang.Object[]) throws java.lang.Throwable;
    Code:
       0: ldc           #3                  // String getClass
       2: aload_2
       3: invokevirtual #4                  // Method java/lang/String.equals:(Ljava/lang/Object;)Z
       6: ifeq          14
       9: aload_1
      10: invokevirtual #5                  // Method java/lang/Object.getClass:()Ljava/lang/Class;
      13: areturn
      14: ldc           #6                  // String hashCode
      16: aload_2
      17: invokevirtual #4                  // Method java/lang/String.equals:(Ljava/lang/Object;)Z
      20: ifeq          31
      23: aload_1
      24: invokevirtual #7                  // Method java/lang/Object.hashCode:()I
      27: invokestatic  #8                  // Method java/lang/Integer.valueOf:(I)Ljava/lang/Integer;
      30: areturn
      31: ldc           #9                  // String toString
      33: aload_2
      34: invokevirtual #4                  // Method java/lang/String.equals:(Ljava/lang/Object;)Z
      37: ifeq          45
      40: aload_1
      41: invokevirtual #10                 // Method java/lang/Object.toString:()Ljava/lang/String;
      44: areturn
      45: ldc           #11                 // String equals
      47: aload_2
      48: invokevirtual #4                  // Method java/lang/String.equals:(Ljava/lang/Object;)Z
      51: ifeq          105
      54: aload         4
      56: arraylength
      57: iconst_1
      58: if_icmpne     73
      61: aload_1
      62: aload         4
      64: iconst_0
      65: aaload
      66: invokevirtual #12                 // Method java/lang/Object.equals:(Ljava/lang/Object;)Z
      69: invokestatic  #13                 // Method java/lang/Boolean.valueOf:(Z)Ljava/lang/Boolean;
      72: areturn
      73: new           #14                 // class java/lang/IllegalArgumentException
      76: dup
      77: new           #15                 // class java/lang/StringBuilder
      80: dup
      81: invokespecial #16                 // Method java/lang/StringBuilder."<init>":()V
      84: ldc           #17                 // String Invoke method [
      86: invokevirtual #18                 // Method java/lang/StringBuilder.append:(Ljava/lang/String;)Ljava/lang/StringBuilder;
      89: aload_2
      90: invokevirtual #18                 // Method java/lang/StringBuilder.append:(Ljava/lang/String;)Ljava/lang/StringBuilder;
      93: ldc           #19                 // String ] argument number error.
      95: invokevirtual #18                 // Method java/lang/StringBuilder.append:(Ljava/lang/String;)Ljava/lang/StringBuilder;
      98: invokevirtual #20                 // Method java/lang/StringBuilder.toString:()Ljava/lang/String;
     101: invokespecial #21                 // Method java/lang/IllegalArgumentException."<init>":(Ljava/lang/String;)V
     104: athrow
     105: aload_0
     106: getfield      #2                  // Field methodInvoker:Lorg/apache/dubbo/rpc/proxy/MethodInvoker;
     109: aload_1
     110: aload_2
     111: aload_3
     112: aload         4
     114: invokeinterface #22,  5           // InterfaceMethod org/apache/dubbo/rpc/proxy/MethodInvoker.invoke:(Ljava/lang/Object;Ljava/lang/String;[Ljava/lang/Class;[Ljava/lang/Object;)Ljava/lang/Object;
     119: areturn

  static <T> org.apache.dubbo.rpc.proxy.bytebuddy.ByteBuddyProxyInvoker<T> newInstance(T, java.lang.Class<T>, org.apache.dubbo.common.URL);
    Code:
       0: new           #23                 // class org/apache/dubbo/rpc/proxy/bytebuddy/ByteBuddyProxyInvoker
       3: dup
       4: aload_0
       5: aload_1
       6: aload_2
       7: aload_0
       8: invokevirtual #5                  // Method java/lang/Object.getClass:()Ljava/lang/Class;
      11: invokestatic  #24                 // InterfaceMethod org/apache/dubbo/rpc/proxy/MethodInvoker.newInstance:(Ljava/lang/Class;)Lorg/apache/dubbo/rpc/proxy/MethodInvoker;
      14: invokespecial #25                 // Method "<init>":(Ljava/lang/Object;Ljava/lang/Class;Lorg/apache/dubbo/common/URL;Lorg/apache/dubbo/rpc/proxy/MethodInvoker;)V
      17: areturn
}
