Compiled from "ByteBuddyProxy.java"
public class org.apache.dubbo.rpc.proxy.bytebuddy.ByteBuddyProxy {
  private static final java.util.Map<java.lang.ClassLoader, java.util.Map<org.apache.dubbo.rpc.proxy.bytebuddy.ByteBuddyProxy$CacheKey, org.apache.dubbo.rpc.proxy.bytebuddy.ByteBuddyProxy>> PROXY_CACHE_MAP;

  private final java.lang.Class<?> proxyClass;

  private final java.lang.reflect.InvocationHandler handler;

  private org.apache.dubbo.rpc.proxy.bytebuddy.ByteBuddyProxy(java.lang.Class<?>, java.lang.reflect.InvocationHandler);
    Code:
       0: aload_0
       1: invokespecial #2                  // Method java/lang/Object."<init>":()V
       4: aload_0
       5: aload_1
       6: putfield      #3                  // Field proxyClass:Ljava/lang/Class;
       9: aload_0
      10: aload_2
      11: putfield      #4                  // Field handler:Ljava/lang/reflect/InvocationHandler;
      14: return

  public static java.lang.Object newInstance(java.lang.ClassLoader, java.lang.Class<?>[], java.lang.reflect.InvocationHandler);
    Code:
       0: aload_0
       1: aload_1
       2: aload_2
       3: invokestatic  #5                  // Method getProxy:(Ljava/lang/ClassLoader;[Ljava/lang/Class;Ljava/lang/reflect/InvocationHandler;)Lorg/apache/dubbo/rpc/proxy/bytebuddy/ByteBuddyProxy;
       6: invokespecial #6                  // Method newInstance:()Ljava/lang/Object;
       9: areturn

  private static org.apache.dubbo.rpc.proxy.bytebuddy.ByteBuddyProxy getProxy(java.lang.ClassLoader, java.lang.Class<?>[], java.lang.reflect.InvocationHandler);
    Code:
       0: aload_1
       1: arraylength
       2: ldc           #7                  // int 65535
       4: if_icmple     17
       7: new           #8                  // class java/lang/IllegalArgumentException
      10: dup
      11: ldc           #9                  // String interface limit exceeded
      13: invokespecial #10                 // Method java/lang/IllegalArgumentException."<init>":(Ljava/lang/String;)V
      16: athrow
      17: aload_1
      18: invokevirtual #11                 // Method "[Ljava/lang/Class;".clone:()Ljava/lang/Object;
      21: checkcast     #12                 // class "[Ljava/lang/Class;"
      24: astore_1
      25: aload_1
      26: invokedynamic #13,  0             // InvokeDynamic #0:apply:()Ljava/util/function/Function;
      31: invokestatic  #14                 // InterfaceMethod java/util/Comparator.comparing:(Ljava/util/function/Function;)Ljava/util/Comparator;
      34: invokestatic  #15                 // Method java/util/Arrays.sort:([Ljava/lang/Object;Ljava/util/Comparator;)V
      37: new           #16                 // class org/apache/dubbo/rpc/proxy/bytebuddy/ByteBuddyProxy$CacheKey
      40: dup
      41: aload_1
      42: aconst_null
      43: invokespecial #17                 // Method org/apache/dubbo/rpc/proxy/bytebuddy/ByteBuddyProxy$CacheKey."<init>":([Ljava/lang/Class;Lorg/apache/dubbo/rpc/proxy/bytebuddy/ByteBuddyProxy$1;)V
      46: astore_3
      47: getstatic     #18                 // Field PROXY_CACHE_MAP:Ljava/util/Map;
      50: dup
      51: astore        5
      53: monitorenter
      54: getstatic     #18                 // Field PROXY_CACHE_MAP:Ljava/util/Map;
      57: aload_0
      58: invokedynamic #19,  0             // InvokeDynamic #1:apply:()Ljava/util/function/Function;
      63: invokeinterface #20,  3           // InterfaceMethod java/util/Map.computeIfAbsent:(Ljava/lang/Object;Ljava/util/function/Function;)Ljava/lang/Object;
      68: checkcast     #21                 // class java/util/Map
      71: astore        4
      73: aload         5
      75: monitorexit
      76: goto          87
      79: astore        6
      81: aload         5
      83: monitorexit
      84: aload         6
      86: athrow
      87: aload         4
      89: aload_3
      90: invokeinterface #22,  2           // InterfaceMethod java/util/Map.get:(Ljava/lang/Object;)Ljava/lang/Object;
      95: checkcast     #23                 // class org/apache/dubbo/rpc/proxy/bytebuddy/ByteBuddyProxy
      98: astore        5
     100: aload         5
     102: ifnonnull     171
     105: aload_1
     106: iconst_0
     107: aaload
     108: dup
     109: astore        6
     111: monitorenter
     112: aload         4
     114: aload_3
     115: invokeinterface #22,  2           // InterfaceMethod java/util/Map.get:(Ljava/lang/Object;)Ljava/lang/Object;
     120: checkcast     #23                 // class org/apache/dubbo/rpc/proxy/bytebuddy/ByteBuddyProxy
     123: astore        5
     125: aload         5
     127: ifnonnull     157
     130: new           #23                 // class org/apache/dubbo/rpc/proxy/bytebuddy/ByteBuddyProxy
     133: dup
     134: aload_0
     135: aload_1
     136: aload_2
     137: invokestatic  #24                 // Method buildProxyClass:(Ljava/lang/ClassLoader;[Ljava/lang/Class;Ljava/lang/reflect/InvocationHandler;)Ljava/lang/Class;
     140: aload_2
     141: invokespecial #25                 // Method "<init>":(Ljava/lang/Class;Ljava/lang/reflect/InvocationHandler;)V
     144: astore        5
     146: aload         4
     148: aload_3
     149: aload         5
     151: invokeinterface #26,  3           // InterfaceMethod java/util/Map.put:(Ljava/lang/Object;Ljava/lang/Object;)Ljava/lang/Object;
     156: pop
     157: aload         6
     159: monitorexit
     160: goto          171
     163: astore        7
     165: aload         6
     167: monitorexit
     168: aload         7
     170: athrow
     171: aload         5
     173: areturn
    Exception table:
       from    to  target type
          54    76    79   any
          79    84    79   any
         112   160   163   any
         163   168   163   any

  private java.lang.Object newInstance();
    Code:
       0: aload_0
       1: getfield      #3                  // Field proxyClass:Ljava/lang/Class;
       4: iconst_1
       5: anewarray     #27                 // class java/lang/Class
       8: dup
       9: iconst_0
      10: ldc           #28                 // class java/lang/reflect/InvocationHandler
      12: aastore
      13: invokevirtual #29                 // Method java/lang/Class.getDeclaredConstructor:([Ljava/lang/Class;)Ljava/lang/reflect/Constructor;
      16: astore_1
      17: aload_1
      18: iconst_1
      19: anewarray     #30                 // class java/lang/Object
      22: dup
      23: iconst_0
      24: aload_0
      25: getfield      #4                  // Field handler:Ljava/lang/reflect/InvocationHandler;
      28: aastore
      29: invokevirtual #31                 // Method java/lang/reflect/Constructor.newInstance:([Ljava/lang/Object;)Ljava/lang/Object;
      32: areturn
      33: astore_1
      34: new           #33                 // class java/lang/RuntimeException
      37: dup
      38: aload_1
      39: invokespecial #34                 // Method java/lang/RuntimeException."<init>":(Ljava/lang/Throwable;)V
      42: athrow
    Exception table:
       from    to  target type
           0    32    33   Class java/lang/ReflectiveOperationException

  private static java.lang.Class<?> buildProxyClass(java.lang.ClassLoader, java.lang.Class<?>[], java.lang.reflect.InvocationHandler);
    Code:
       0: aload_1
       1: invokestatic  #35                 // Method java/util/Arrays.stream:([Ljava/lang/Object;)Ljava/util/stream/Stream;
       4: invokedynamic #36,  0             // InvokeDynamic #2:apply:()Ljava/util/function/Function;
       9: invokeinterface #37,  2           // InterfaceMethod java/util/stream/Stream.map:(Ljava/util/function/Function;)Ljava/util/stream/Stream;
      14: invokedynamic #38,  0             // InvokeDynamic #3:apply:()Ljava/util/function/BinaryOperator;
      19: invokeinterface #39,  2           // InterfaceMethod java/util/stream/Stream.reduce:(Ljava/util/function/BinaryOperator;)Ljava/util/Optional;
      24: invokestatic  #40                 // Method net/bytebuddy/matcher/ElementMatchers.none:()Lnet/bytebuddy/matcher/ElementMatcher$Junction;
      27: invokevirtual #41                 // Method java/util/Optional.orElse:(Ljava/lang/Object;)Ljava/lang/Object;
      30: checkcast     #42                 // class net/bytebuddy/matcher/ElementMatcher$Junction
      33: ldc           #30                 // class java/lang/Object
      35: invokestatic  #43                 // Method net/bytebuddy/matcher/ElementMatchers.isDeclaredBy:(Ljava/lang/Class;)Lnet/bytebuddy/matcher/ElementMatcher$Junction;
      38: invokestatic  #44                 // Method net/bytebuddy/matcher/ElementMatchers.not:(Lnet/bytebuddy/matcher/ElementMatcher;)Lnet/bytebuddy/matcher/ElementMatcher$Junction;
      41: invokeinterface #45,  2           // InterfaceMethod net/bytebuddy/matcher/ElementMatcher$Junction.and:(Lnet/bytebuddy/matcher/ElementMatcher;)Lnet/bytebuddy/matcher/ElementMatcher$Junction;
      46: astore_3
      47: new           #46                 // class net/bytebuddy/ByteBuddy
      50: dup
      51: invokespecial #47                 // Method net/bytebuddy/ByteBuddy."<init>":()V
      54: ldc           #48                 // class java/lang/reflect/Proxy
      56: invokevirtual #49                 // Method net/bytebuddy/ByteBuddy.subclass:(Ljava/lang/Class;)Lnet/bytebuddy/dynamic/DynamicType$Builder;
      59: aload_1
      60: invokeinterface #50,  2           // InterfaceMethod net/bytebuddy/dynamic/DynamicType$Builder.implement:([Ljava/lang/reflect/Type;)Lnet/bytebuddy/dynamic/DynamicType$Builder$MethodDefinition$ImplementationDefinition$Optional;
      65: aload_3
      66: invokeinterface #51,  2           // InterfaceMethod net/bytebuddy/dynamic/DynamicType$Builder$MethodDefinition$ImplementationDefinition$Optional.method:(Lnet/bytebuddy/matcher/ElementMatcher;)Lnet/bytebuddy/dynamic/DynamicType$Builder$MethodDefinition$ImplementationDefinition;
      71: new           #52                 // class org/apache/dubbo/rpc/proxy/bytebuddy/ByteBuddyInterceptor
      74: dup
      75: aload_2
      76: invokespecial #53                 // Method org/apache/dubbo/rpc/proxy/bytebuddy/ByteBuddyInterceptor."<init>":(Ljava/lang/reflect/InvocationHandler;)V
      79: invokestatic  #54                 // Method net/bytebuddy/implementation/MethodDelegation.to:(Ljava/lang/Object;)Lnet/bytebuddy/implementation/MethodDelegation;
      82: invokeinterface #55,  2           // InterfaceMethod net/bytebuddy/dynamic/DynamicType$Builder$MethodDefinition$ImplementationDefinition.intercept:(Lnet/bytebuddy/implementation/Implementation;)Lnet/bytebuddy/dynamic/DynamicType$Builder$MethodDefinition$ReceiverTypeDefinition;
      87: invokeinterface #56,  1           // InterfaceMethod net/bytebuddy/dynamic/DynamicType$Builder$MethodDefinition$ReceiverTypeDefinition.make:()Lnet/bytebuddy/dynamic/DynamicType$Unloaded;
      92: aload_0
      93: invokeinterface #57,  2           // InterfaceMethod net/bytebuddy/dynamic/DynamicType$Unloaded.load:(Ljava/lang/ClassLoader;)Lnet/bytebuddy/dynamic/DynamicType$Loaded;
      98: invokeinterface #58,  1           // InterfaceMethod net/bytebuddy/dynamic/DynamicType$Loaded.getLoaded:()Ljava/lang/Class;
     103: areturn

  private static java.util.Map lambda$getProxy$0(java.lang.ClassLoader);
    Code:
       0: new           #59                 // class java/util/concurrent/ConcurrentHashMap
       3: dup
       4: invokespecial #60                 // Method java/util/concurrent/ConcurrentHashMap."<init>":()V
       7: areturn

  static {};
    Code:
       0: new           #61                 // class java/util/WeakHashMap
       3: dup
       4: invokespecial #62                 // Method java/util/WeakHashMap."<init>":()V
       7: putstatic     #18                 // Field PROXY_CACHE_MAP:Ljava/util/Map;
      10: return
}
