Compiled from "ByteBuddyInterceptor.java"
public class org.apache.dubbo.rpc.proxy.bytebuddy.ByteBuddyInterceptor {
  private final java.lang.reflect.InvocationHandler handler;

  org.apache.dubbo.rpc.proxy.bytebuddy.ByteBuddyInterceptor(java.lang.reflect.InvocationHandler);
    Code:
       0: aload_0
       1: invokespecial #1                  // Method java/lang/Object."<init>":()V
       4: aload_0
       5: aload_1
       6: putfield      #2                  // Field handler:Ljava/lang/reflect/InvocationHandler;
       9: return

  public java.lang.Object intercept(java.lang.Object, java.lang.Object[], java.lang.reflect.Method) throws java.lang.Throwable;
    Code:
       0: aload_0
       1: getfield      #2                  // Field handler:Ljava/lang/reflect/InvocationHandler;
       4: aload_1
       5: aload_3
       6: aload_2
       7: invokeinterface #3,  4            // InterfaceMethod java/lang/reflect/InvocationHandler.invoke:(Ljava/lang/Object;Ljava/lang/reflect/Method;[Ljava/lang/Object;)Ljava/lang/Object;
      12: areturn
}
