Compiled from "ByteBuddyProxyFactory.java"
public class org.apache.dubbo.rpc.proxy.bytebuddy.ByteBuddyProxyFactory extends org.apache.dubbo.rpc.proxy.AbstractFallbackJdkProxyFactory {
  public org.apache.dubbo.rpc.proxy.bytebuddy.ByteBuddyProxyFactory();
    Code:
       0: aload_0
       1: invokespecial #1                  // Method org/apache/dubbo/rpc/proxy/AbstractFallbackJdkProxyFactory."<init>":()V
       4: return

  protected <T> org.apache.dubbo.rpc.Invoker<T> doGetInvoker(T, java.lang.Class<T>, org.apache.dubbo.common.URL);
    Code:
       0: aload_1
       1: aload_2
       2: aload_3
       3: invokestatic  #2                  // Method org/apache/dubbo/rpc/proxy/bytebuddy/ByteBuddyProxyInvoker.newInstance:(Ljava/lang/Object;Ljava/lang/Class;Lorg/apache/dubbo/common/URL;)Lorg/apache/dubbo/rpc/proxy/bytebuddy/ByteBuddyProxyInvoker;
       6: areturn

  protected <T> T doGetProxy(org.apache.dubbo.rpc.Invoker<T>, java.lang.Class<?>[]);
    Code:
       0: aload_1
       1: invokeinterface #3,  1            // InterfaceMethod org/apache/dubbo/rpc/Invoker.getInterface:()Ljava/lang/Class;
       6: invokevirtual #4                  // Method java/lang/Class.getClassLoader:()Ljava/lang/ClassLoader;
       9: astore_3
      10: aload_3
      11: aload_2
      12: new           #5                  // class org/apache/dubbo/rpc/proxy/InvokerInvocationHandler
      15: dup
      16: aload_1
      17: invokespecial #6                  // Method org/apache/dubbo/rpc/proxy/InvokerInvocationHandler."<init>":(Lorg/apache/dubbo/rpc/Invoker;)V
      20: invokestatic  #7                  // Method org/apache/dubbo/rpc/proxy/bytebuddy/ByteBuddyProxy.newInstance:(Ljava/lang/ClassLoader;[Ljava/lang/Class;Ljava/lang/reflect/InvocationHandler;)Ljava/lang/Object;
      23: areturn
}
