Compiled from "BasicJsonParser.java"
public class org.springframework.boot.json.BasicJsonParser extends org.springframework.boot.json.AbstractJsonParser {
  private static final int MAX_DEPTH;

  public org.springframework.boot.json.BasicJsonParser();
    Code:
       0: aload_0
       1: invokespecial #1                  // Method org/springframework/boot/json/AbstractJsonParser."<init>":()V
       4: return

  public java.util.Map<java.lang.String, java.lang.Object> parseMap(java.lang.String);
    Code:
       0: aload_0
       1: aload_0
       2: aload_1
       3: invokedynamic #7,  0              // InvokeDynamic #0:call:(Lorg/springframework/boot/json/BasicJsonParser;Ljava/lang/String;)Ljava/util/concurrent/Callable;
       8: ldc           #11                 // class java/lang/Exception
      10: invokevirtual #13                 // Method tryParse:(Ljava/util/concurrent/Callable;Ljava/lang/Class;)Ljava/lang/Object;
      13: checkcast     #19                 // class java/util/Map
      16: areturn

  public java.util.List<java.lang.Object> parseList(java.lang.String);
    Code:
       0: aload_0
       1: aload_0
       2: aload_1
       3: invokedynamic #21,  0             // InvokeDynamic #1:call:(Lorg/springframework/boot/json/BasicJsonParser;Ljava/lang/String;)Ljava/util/concurrent/Callable;
       8: ldc           #11                 // class java/lang/Exception
      10: invokevirtual #13                 // Method tryParse:(Ljava/util/concurrent/Callable;Ljava/lang/Class;)Ljava/lang/Object;
      13: checkcast     #22                 // class java/util/List
      16: areturn

  private java.util.List<java.lang.Object> parseListInternal(int, java.lang.String);
    Code:
       0: new           #24                 // class java/util/ArrayList
       3: dup
       4: invokespecial #26                 // Method java/util/ArrayList."<init>":()V
       7: astore_3
       8: aload_2
       9: bipush        93
      11: invokestatic  #27                 // Method trimTrailingCharacter:(Ljava/lang/String;C)Ljava/lang/String;
      14: bipush        91
      16: invokestatic  #31                 // Method trimLeadingCharacter:(Ljava/lang/String;C)Ljava/lang/String;
      19: invokevirtual #34                 // Method java/lang/String.trim:()Ljava/lang/String;
      22: astore_2
      23: aload_0
      24: aload_2
      25: invokevirtual #40                 // Method tokenize:(Ljava/lang/String;)Ljava/util/List;
      28: invokeinterface #44,  1           // InterfaceMethod java/util/List.iterator:()Ljava/util/Iterator;
      33: astore        4
      35: aload         4
      37: invokeinterface #48,  1           // InterfaceMethod java/util/Iterator.hasNext:()Z
      42: ifeq          76
      45: aload         4
      47: invokeinterface #54,  1           // InterfaceMethod java/util/Iterator.next:()Ljava/lang/Object;
      52: checkcast     #35                 // class java/lang/String
      55: astore        5
      57: aload_3
      58: aload_0
      59: iload_1
      60: iconst_1
      61: iadd
      62: aload         5
      64: invokevirtual #58                 // Method parseInternal:(ILjava/lang/String;)Ljava/lang/Object;
      67: invokeinterface #62,  2           // InterfaceMethod java/util/List.add:(Ljava/lang/Object;)Z
      72: pop
      73: goto          35
      76: aload_3
      77: areturn

  private java.lang.Object parseInternal(int, java.lang.String);
    Code:
       0: iload_1
       1: sipush        1000
       4: if_icmple     17
       7: new           #66                 // class java/lang/IllegalStateException
      10: dup
      11: ldc           #68                 // String JSON is too deeply nested
      13: invokespecial #70                 // Method java/lang/IllegalStateException."<init>":(Ljava/lang/String;)V
      16: athrow
      17: aload_2
      18: ldc           #73                 // String [
      20: invokevirtual #75                 // Method java/lang/String.startsWith:(Ljava/lang/String;)Z
      23: ifeq          35
      26: aload_0
      27: iload_1
      28: iconst_1
      29: iadd
      30: aload_2
      31: invokevirtual #79                 // Method parseListInternal:(ILjava/lang/String;)Ljava/util/List;
      34: areturn
      35: aload_2
      36: ldc           #83                 // String {
      38: invokevirtual #75                 // Method java/lang/String.startsWith:(Ljava/lang/String;)Z
      41: ifeq          53
      44: aload_0
      45: iload_1
      46: iconst_1
      47: iadd
      48: aload_2
      49: invokevirtual #85                 // Method parseMapInternal:(ILjava/lang/String;)Ljava/util/Map;
      52: areturn
      53: aload_2
      54: ldc           #89                 // String \"
      56: invokevirtual #75                 // Method java/lang/String.startsWith:(Ljava/lang/String;)Z
      59: ifeq          74
      62: aload_2
      63: bipush        34
      65: invokestatic  #31                 // Method trimLeadingCharacter:(Ljava/lang/String;C)Ljava/lang/String;
      68: bipush        34
      70: invokestatic  #27                 // Method trimTrailingCharacter:(Ljava/lang/String;C)Ljava/lang/String;
      73: areturn
      74: aload_2
      75: invokestatic  #91                 // Method java/lang/Long.valueOf:(Ljava/lang/String;)Ljava/lang/Long;
      78: areturn
      79: astore_3
      80: aload_2
      81: invokestatic  #99                 // Method java/lang/Double.valueOf:(Ljava/lang/String;)Ljava/lang/Double;
      84: areturn
      85: astore_3
      86: aload_2
      87: areturn
    Exception table:
       from    to  target type
          74    78    79   Class java/lang/NumberFormatException
          80    84    85   Class java/lang/NumberFormatException

  private java.util.Map<java.lang.String, java.lang.Object> parseMapInternal(int, java.lang.String);
    Code:
       0: new           #104                // class java/util/LinkedHashMap
       3: dup
       4: invokespecial #106                // Method java/util/LinkedHashMap."<init>":()V
       7: astore_3
       8: aload_2
       9: bipush        125
      11: invokestatic  #27                 // Method trimTrailingCharacter:(Ljava/lang/String;C)Ljava/lang/String;
      14: bipush        123
      16: invokestatic  #31                 // Method trimLeadingCharacter:(Ljava/lang/String;C)Ljava/lang/String;
      19: invokevirtual #34                 // Method java/lang/String.trim:()Ljava/lang/String;
      22: astore_2
      23: aload_0
      24: aload_2
      25: invokevirtual #40                 // Method tokenize:(Ljava/lang/String;)Ljava/util/List;
      28: invokeinterface #44,  1           // InterfaceMethod java/util/List.iterator:()Ljava/util/Iterator;
      33: astore        4
      35: aload         4
      37: invokeinterface #48,  1           // InterfaceMethod java/util/Iterator.hasNext:()Z
      42: ifeq          144
      45: aload         4
      47: invokeinterface #54,  1           // InterfaceMethod java/util/Iterator.next:()Ljava/lang/Object;
      52: checkcast     #35                 // class java/lang/String
      55: astore        5
      57: aload         5
      59: ldc           #107                // String :
      61: invokestatic  #109                // Method org/springframework/util/StringUtils.split:(Ljava/lang/String;Ljava/lang/String;)[Ljava/lang/String;
      64: invokestatic  #115                // Method org/springframework/util/StringUtils.trimArrayElements:([Ljava/lang/String;)[Ljava/lang/String;
      67: astore        6
      69: aload         6
      71: iconst_0
      72: aaload
      73: ldc           #89                 // String \"
      75: invokevirtual #75                 // Method java/lang/String.startsWith:(Ljava/lang/String;)Z
      78: ifeq          97
      81: aload         6
      83: iconst_0
      84: aaload
      85: ldc           #89                 // String \"
      87: invokevirtual #119                // Method java/lang/String.endsWith:(Ljava/lang/String;)Z
      90: ifeq          97
      93: iconst_1
      94: goto          98
      97: iconst_0
      98: ldc           #122                // String Expecting double-quotes around field names
     100: invokestatic  #124                // Method org/springframework/util/Assert.state:(ZLjava/lang/String;)V
     103: aload         6
     105: iconst_0
     106: aaload
     107: bipush        34
     109: invokestatic  #27                 // Method trimTrailingCharacter:(Ljava/lang/String;C)Ljava/lang/String;
     112: bipush        34
     114: invokestatic  #31                 // Method trimLeadingCharacter:(Ljava/lang/String;C)Ljava/lang/String;
     117: astore        7
     119: aload_0
     120: iload_1
     121: aload         6
     123: iconst_1
     124: aaload
     125: invokevirtual #58                 // Method parseInternal:(ILjava/lang/String;)Ljava/lang/Object;
     128: astore        8
     130: aload_3
     131: aload         7
     133: aload         8
     135: invokeinterface #130,  3          // InterfaceMethod java/util/Map.put:(Ljava/lang/Object;Ljava/lang/Object;)Ljava/lang/Object;
     140: pop
     141: goto          35
     144: aload_3
     145: areturn

  private static java.lang.String trimTrailingCharacter(java.lang.String, char);
    Code:
       0: aload_0
       1: invokevirtual #134                // Method java/lang/String.isEmpty:()Z
       4: ifne          33
       7: aload_0
       8: aload_0
       9: invokevirtual #137                // Method java/lang/String.length:()I
      12: iconst_1
      13: isub
      14: invokevirtual #141                // Method java/lang/String.charAt:(I)C
      17: iload_1
      18: if_icmpne     33
      21: aload_0
      22: iconst_0
      23: aload_0
      24: invokevirtual #137                // Method java/lang/String.length:()I
      27: iconst_1
      28: isub
      29: invokevirtual #145                // Method java/lang/String.substring:(II)Ljava/lang/String;
      32: areturn
      33: aload_0
      34: areturn

  private static java.lang.String trimLeadingCharacter(java.lang.String, char);
    Code:
       0: aload_0
       1: invokevirtual #134                // Method java/lang/String.isEmpty:()Z
       4: ifne          22
       7: aload_0
       8: iconst_0
       9: invokevirtual #141                // Method java/lang/String.charAt:(I)C
      12: iload_1
      13: if_icmpne     22
      16: aload_0
      17: iconst_1
      18: invokevirtual #149                // Method java/lang/String.substring:(I)Ljava/lang/String;
      21: areturn
      22: aload_0
      23: areturn

  private java.util.List<java.lang.String> tokenize(java.lang.String);
    Code:
       0: new           #24                 // class java/util/ArrayList
       3: dup
       4: invokespecial #26                 // Method java/util/ArrayList."<init>":()V
       7: astore_2
       8: iconst_0
       9: istore_3
      10: iconst_0
      11: istore        4
      13: iconst_0
      14: istore        5
      16: iconst_0
      17: istore        6
      19: iconst_0
      20: istore        7
      22: new           #152                // class java/lang/StringBuilder
      25: dup
      26: invokespecial #154                // Method java/lang/StringBuilder."<init>":()V
      29: astore        8
      31: iload_3
      32: aload_1
      33: invokevirtual #137                // Method java/lang/String.length:()I
      36: if_icmpge     197
      39: aload_1
      40: iload_3
      41: invokevirtual #141                // Method java/lang/String.charAt:(I)C
      44: istore        9
      46: iload         7
      48: ifeq          68
      51: aload         8
      53: iload         9
      55: invokevirtual #155                // Method java/lang/StringBuilder.append:(C)Ljava/lang/StringBuilder;
      58: pop
      59: iinc          3, 1
      62: iconst_0
      63: istore        7
      65: goto          31
      68: iload         9
      70: bipush        123
      72: if_icmpne     78
      75: iinc          4, 1
      78: iload         9
      80: bipush        125
      82: if_icmpne     88
      85: iinc          4, -1
      88: iload         9
      90: bipush        91
      92: if_icmpne     98
      95: iinc          5, 1
      98: iload         9
     100: bipush        93
     102: if_icmpne     108
     105: iinc          5, -1
     108: iload         9
     110: bipush        34
     112: if_icmpne     127
     115: iload         6
     117: ifne          124
     120: iconst_1
     121: goto          125
     124: iconst_0
     125: istore        6
     127: iload         9
     129: bipush        44
     131: if_icmpne     170
     134: iload         4
     136: ifne          170
     139: iload         5
     141: ifne          170
     144: iload         6
     146: ifne          170
     149: aload_2
     150: aload         8
     152: invokevirtual #159                // Method java/lang/StringBuilder.toString:()Ljava/lang/String;
     155: invokeinterface #62,  2           // InterfaceMethod java/util/List.add:(Ljava/lang/Object;)Z
     160: pop
     161: aload         8
     163: iconst_0
     164: invokevirtual #162                // Method java/lang/StringBuilder.setLength:(I)V
     167: goto          191
     170: iload         9
     172: bipush        92
     174: if_icmpne     183
     177: iconst_1
     178: istore        7
     180: goto          191
     183: aload         8
     185: iload         9
     187: invokevirtual #155                // Method java/lang/StringBuilder.append:(C)Ljava/lang/StringBuilder;
     190: pop
     191: iinc          3, 1
     194: goto          31
     197: aload         8
     199: invokevirtual #166                // Method java/lang/StringBuilder.length:()I
     202: ifle          220
     205: aload_2
     206: aload         8
     208: invokevirtual #159                // Method java/lang/StringBuilder.toString:()Ljava/lang/String;
     211: invokevirtual #34                 // Method java/lang/String.trim:()Ljava/lang/String;
     214: invokeinterface #62,  2           // InterfaceMethod java/util/List.add:(Ljava/lang/Object;)Z
     219: pop
     220: aload_2
     221: areturn

  private java.util.List lambda$parseList$3(java.lang.String) throws java.lang.Exception;
    Code:
       0: aload_0
       1: aload_1
       2: aload_0
       3: invokedynamic #167,  0            // InvokeDynamic #2:apply:(Lorg/springframework/boot/json/BasicJsonParser;)Ljava/util/function/Function;
       8: invokevirtual #171                // Method parseList:(Ljava/lang/String;Ljava/util/function/Function;)Ljava/util/List;
      11: areturn

  private java.util.List lambda$parseList$2(java.lang.String);
    Code:
       0: aload_0
       1: iconst_0
       2: aload_1
       3: invokevirtual #79                 // Method parseListInternal:(ILjava/lang/String;)Ljava/util/List;
       6: areturn

  private java.util.Map lambda$parseMap$1(java.lang.String) throws java.lang.Exception;
    Code:
       0: aload_0
       1: aload_1
       2: aload_0
       3: invokedynamic #175,  0            // InvokeDynamic #3:apply:(Lorg/springframework/boot/json/BasicJsonParser;)Ljava/util/function/Function;
       8: invokevirtual #176                // Method parseMap:(Ljava/lang/String;Ljava/util/function/Function;)Ljava/util/Map;
      11: areturn

  private java.util.Map lambda$parseMap$0(java.lang.String);
    Code:
       0: aload_0
       1: iconst_0
       2: aload_1
       3: invokevirtual #85                 // Method parseMapInternal:(ILjava/lang/String;)Ljava/util/Map;
       6: areturn
}
