Compiled from "GsonJsonParser.java"
public class org.springframework.boot.json.GsonJsonParser extends org.springframework.boot.json.AbstractJsonParser {
  private static final com.google.gson.reflect.TypeToken<?> MAP_TYPE;

  private static final com.google.gson.reflect.TypeToken<?> LIST_TYPE;

  private final com.google.gson.Gson gson;

  public org.springframework.boot.json.GsonJsonParser();
    Code:
       0: aload_0
       1: invokespecial #1                  // Method org/springframework/boot/json/AbstractJsonParser."<init>":()V
       4: aload_0
       5: new           #7                  // class com/google/gson/GsonBuilder
       8: dup
       9: invokespecial #9                  // Method com/google/gson/GsonBuilder."<init>":()V
      12: invokevirtual #10                 // Method com/google/gson/GsonBuilder.create:()Lcom/google/gson/Gson;
      15: putfield      #14                 // Field gson:Lcom/google/gson/Gson;
      18: return

  public java.util.Map<java.lang.String, java.lang.Object> parseMap(java.lang.String);
    Code:
       0: aload_0
       1: aload_0
       2: aload_1
       3: invokedynamic #20,  0             // InvokeDynamic #0:call:(Lorg/springframework/boot/json/GsonJsonParser;Ljava/lang/String;)Ljava/util/concurrent/Callable;
       8: ldc           #24                 // class java/lang/Exception
      10: invokevirtual #26                 // Method tryParse:(Ljava/util/concurrent/Callable;Ljava/lang/Class;)Ljava/lang/Object;
      13: checkcast     #30                 // class java/util/Map
      16: areturn

  public java.util.List<java.lang.Object> parseList(java.lang.String);
    Code:
       0: aload_0
       1: aload_0
       2: aload_1
       3: invokedynamic #32,  0             // InvokeDynamic #1:call:(Lorg/springframework/boot/json/GsonJsonParser;Ljava/lang/String;)Ljava/util/concurrent/Callable;
       8: ldc           #24                 // class java/lang/Exception
      10: invokevirtual #26                 // Method tryParse:(Ljava/util/concurrent/Callable;Ljava/lang/Class;)Ljava/lang/Object;
      13: checkcast     #33                 // class java/util/List
      16: areturn

  private java.util.List lambda$parseList$3(java.lang.String) throws java.lang.Exception;
    Code:
       0: aload_0
       1: aload_1
       2: aload_0
       3: invokedynamic #35,  0             // InvokeDynamic #2:apply:(Lorg/springframework/boot/json/GsonJsonParser;)Ljava/util/function/Function;
       8: invokevirtual #39                 // Method parseList:(Ljava/lang/String;Ljava/util/function/Function;)Ljava/util/List;
      11: areturn

  private java.util.List lambda$parseList$2(java.lang.String);
    Code:
       0: aload_0
       1: getfield      #14                 // Field gson:Lcom/google/gson/Gson;
       4: aload_1
       5: getstatic     #43                 // Field LIST_TYPE:Lcom/google/gson/reflect/TypeToken;
       8: invokevirtual #47                 // Method com/google/gson/reflect/TypeToken.getType:()Ljava/lang/reflect/Type;
      11: invokevirtual #53                 // Method com/google/gson/Gson.fromJson:(Ljava/lang/String;Ljava/lang/reflect/Type;)Ljava/lang/Object;
      14: checkcast     #33                 // class java/util/List
      17: areturn

  private java.util.Map lambda$parseMap$1(java.lang.String) throws java.lang.Exception;
    Code:
       0: aload_0
       1: aload_1
       2: aload_0
       3: invokedynamic #59,  0             // InvokeDynamic #3:apply:(Lorg/springframework/boot/json/GsonJsonParser;)Ljava/util/function/Function;
       8: invokevirtual #60                 // Method parseMap:(Ljava/lang/String;Ljava/util/function/Function;)Ljava/util/Map;
      11: areturn

  private java.util.Map lambda$parseMap$0(java.lang.String);
    Code:
       0: aload_0
       1: getfield      #14                 // Field gson:Lcom/google/gson/Gson;
       4: aload_1
       5: getstatic     #64                 // Field MAP_TYPE:Lcom/google/gson/reflect/TypeToken;
       8: invokevirtual #47                 // Method com/google/gson/reflect/TypeToken.getType:()Ljava/lang/reflect/Type;
      11: invokevirtual #53                 // Method com/google/gson/Gson.fromJson:(Ljava/lang/String;Ljava/lang/reflect/Type;)Ljava/lang/Object;
      14: checkcast     #30                 // class java/util/Map
      17: areturn

  static {};
    Code:
       0: new           #67                 // class org/springframework/boot/json/GsonJsonParser$MapTypeToken
       3: dup
       4: invokespecial #69                 // Method org/springframework/boot/json/GsonJsonParser$MapTypeToken."<init>":()V
       7: putstatic     #64                 // Field MAP_TYPE:Lcom/google/gson/reflect/TypeToken;
      10: new           #70                 // class org/springframework/boot/json/GsonJsonParser$ListTypeToken
      13: dup
      14: invokespecial #72                 // Method org/springframework/boot/json/GsonJsonParser$ListTypeToken."<init>":()V
      17: putstatic     #43                 // Field LIST_TYPE:Lcom/google/gson/reflect/TypeToken;
      20: return
}
