Compiled from "JacksonRuntimeHints.java"
class org.springframework.boot.json.JacksonRuntimeHints implements org.springframework.aot.hint.RuntimeHintsRegistrar {
  org.springframework.boot.json.JacksonRuntimeHints();
    Code:
       0: aload_0
       1: invokespecial #1                  // Method java/lang/Object."<init>":()V
       4: return

  public void registerHints(org.springframework.aot.hint.RuntimeHints, java.lang.ClassLoader);
    Code:
       0: ldc           #7                  // String com.fasterxml.jackson.databind.ser.BasicSerializerFactory
       2: aload_2
       3: invokestatic  #9                  // Method org/springframework/util/ClassUtils.isPresent:(Ljava/lang/String;Ljava/lang/ClassLoader;)Z
       6: ifne          10
       9: return
      10: aload_0
      11: aload_1
      12: invokevirtual #15                 // Method org/springframework/aot/hint/RuntimeHints.reflection:()Lorg/springframework/aot/hint/ReflectionHints;
      15: invokevirtual #21                 // Method registerSerializers:(Lorg/springframework/aot/hint/ReflectionHints;)V
      18: return

  private void registerSerializers(org.springframework.aot.hint.ReflectionHints);
    Code:
       0: aload_1
       1: bipush        6
       3: anewarray     #27                 // class java/lang/Class
       6: dup
       7: iconst_0
       8: ldc           #29                 // class com/fasterxml/jackson/databind/ser/std/StdJdkSerializers$AtomicBooleanSerializer
      10: aastore
      11: dup
      12: iconst_1
      13: ldc           #31                 // class com/fasterxml/jackson/databind/ser/std/StdJdkSerializers$AtomicIntegerSerializer
      15: aastore
      16: dup
      17: iconst_2
      18: ldc           #33                 // class com/fasterxml/jackson/databind/ser/std/StdJdkSerializers$AtomicLongSerializer
      20: aastore
      21: dup
      22: iconst_3
      23: ldc           #35                 // class com/fasterxml/jackson/databind/ser/std/FileSerializer
      25: aastore
      26: dup
      27: iconst_4
      28: ldc           #37                 // class com/fasterxml/jackson/databind/ser/std/ClassSerializer
      30: aastore
      31: dup
      32: iconst_5
      33: ldc           #39                 // class com/fasterxml/jackson/databind/ser/std/TokenBufferSerializer
      35: aastore
      36: invokestatic  #41                 // InterfaceMethod org/springframework/aot/hint/TypeReference.listOf:([Ljava/lang/Class;)Ljava/util/List;
      39: iconst_1
      40: anewarray     #47                 // class org/springframework/aot/hint/MemberCategory
      43: dup
      44: iconst_0
      45: getstatic     #49                 // Field org/springframework/aot/hint/MemberCategory.INVOKE_PUBLIC_CONSTRUCTORS:Lorg/springframework/aot/hint/MemberCategory;
      48: aastore
      49: invokestatic  #53                 // Method org/springframework/aot/hint/TypeHint.builtWith:([Lorg/springframework/aot/hint/MemberCategory;)Ljava/util/function/Consumer;
      52: invokevirtual #59                 // Method org/springframework/aot/hint/ReflectionHints.registerTypes:(Ljava/lang/Iterable;Ljava/util/function/Consumer;)Lorg/springframework/aot/hint/ReflectionHints;
      55: pop
      56: return
}
