Compiled from "JavaBeanAccessor.java"
public final class org.apache.dubbo.common.beanutil.JavaBeanAccessor extends java.lang.Enum<org.apache.dubbo.common.beanutil.JavaBeanAccessor> {
  public static final org.apache.dubbo.common.beanutil.JavaBeanAccessor FIELD;

  public static final org.apache.dubbo.common.beanutil.JavaBeanAccessor METHOD;

  public static final org.apache.dubbo.common.beanutil.JavaBeanAccessor ALL;

  private static final org.apache.dubbo.common.beanutil.JavaBeanAccessor[] $VALUES;

  public static org.apache.dubbo.common.beanutil.JavaBeanAccessor[] values();
    Code:
       0: getstatic     #1                  // Field $VALUES:[Lorg/apache/dubbo/common/beanutil/JavaBeanAccessor;
       3: invokevirtual #2                  // Method "[Lorg/apache/dubbo/common/beanutil/JavaBeanAccessor;".clone:()Ljava/lang/Object;
       6: checkcast     #3                  // class "[Lorg/apache/dubbo/common/beanutil/JavaBeanAccessor;"
       9: areturn

  public static org.apache.dubbo.common.beanutil.JavaBeanAccessor valueOf(java.lang.String);
    Code:
       0: ldc           #4                  // class org/apache/dubbo/common/beanutil/JavaBeanAccessor
       2: aload_0
       3: invokestatic  #5                  // Method java/lang/Enum.valueOf:(Ljava/lang/Class;Ljava/lang/String;)Ljava/lang/Enum;
       6: checkcast     #4                  // class org/apache/dubbo/common/beanutil/JavaBeanAccessor
       9: areturn

  private org.apache.dubbo.common.beanutil.JavaBeanAccessor();
    Code:
       0: aload_0
       1: aload_1
       2: iload_2
       3: invokespecial #6                  // Method java/lang/Enum."<init>":(Ljava/lang/String;I)V
       6: return

  public static boolean isAccessByMethod(org.apache.dubbo.common.beanutil.JavaBeanAccessor);
    Code:
       0: getstatic     #7                  // Field METHOD:Lorg/apache/dubbo/common/beanutil/JavaBeanAccessor;
       3: aload_0
       4: invokevirtual #8                  // Method equals:(Ljava/lang/Object;)Z
       7: ifne          20
      10: getstatic     #9                  // Field ALL:Lorg/apache/dubbo/common/beanutil/JavaBeanAccessor;
      13: aload_0
      14: invokevirtual #8                  // Method equals:(Ljava/lang/Object;)Z
      17: ifeq          24
      20: iconst_1
      21: goto          25
      24: iconst_0
      25: ireturn

  public static boolean isAccessByField(org.apache.dubbo.common.beanutil.JavaBeanAccessor);
    Code:
       0: getstatic     #10                 // Field FIELD:Lorg/apache/dubbo/common/beanutil/JavaBeanAccessor;
       3: aload_0
       4: invokevirtual #8                  // Method equals:(Ljava/lang/Object;)Z
       7: ifne          20
      10: getstatic     #9                  // Field ALL:Lorg/apache/dubbo/common/beanutil/JavaBeanAccessor;
      13: aload_0
      14: invokevirtual #8                  // Method equals:(Ljava/lang/Object;)Z
      17: ifeq          24
      20: iconst_1
      21: goto          25
      24: iconst_0
      25: ireturn

  static {};
    Code:
       0: new           #4                  // class org/apache/dubbo/common/beanutil/JavaBeanAccessor
       3: dup
       4: ldc           #11                 // String FIELD
       6: iconst_0
       7: invokespecial #12                 // Method "<init>":(Ljava/lang/String;I)V
      10: putstatic     #10                 // Field FIELD:Lorg/apache/dubbo/common/beanutil/JavaBeanAccessor;
      13: new           #4                  // class org/apache/dubbo/common/beanutil/JavaBeanAccessor
      16: dup
      17: ldc           #13                 // String METHOD
      19: iconst_1
      20: invokespecial #12                 // Method "<init>":(Ljava/lang/String;I)V
      23: putstatic     #7                  // Field METHOD:Lorg/apache/dubbo/common/beanutil/JavaBeanAccessor;
      26: new           #4                  // class org/apache/dubbo/common/beanutil/JavaBeanAccessor
      29: dup
      30: ldc           #14                 // String ALL
      32: iconst_2
      33: invokespecial #12                 // Method "<init>":(Ljava/lang/String;I)V
      36: putstatic     #9                  // Field ALL:Lorg/apache/dubbo/common/beanutil/JavaBeanAccessor;
      39: iconst_3
      40: anewarray     #4                  // class org/apache/dubbo/common/beanutil/JavaBeanAccessor
      43: dup
      44: iconst_0
      45: getstatic     #10                 // Field FIELD:Lorg/apache/dubbo/common/beanutil/JavaBeanAccessor;
      48: aastore
      49: dup
      50: iconst_1
      51: getstatic     #7                  // Field METHOD:Lorg/apache/dubbo/common/beanutil/JavaBeanAccessor;
      54: aastore
      55: dup
      56: iconst_2
      57: getstatic     #9                  // Field ALL:Lorg/apache/dubbo/common/beanutil/JavaBeanAccessor;
      60: aastore
      61: putstatic     #1                  // Field $VALUES:[Lorg/apache/dubbo/common/beanutil/JavaBeanAccessor;
      64: return
}
