Compiled from "MethodDefinitionBuilder.java"
public class org.apache.dubbo.metadata.definition.MethodDefinitionBuilder {
  private final org.apache.dubbo.metadata.definition.TypeDefinitionBuilder builder;

  public org.apache.dubbo.metadata.definition.MethodDefinitionBuilder(org.apache.dubbo.metadata.definition.TypeDefinitionBuilder);
    Code:
       0: aload_0
       1: invokespecial #1                  // Method java/lang/Object."<init>":()V
       4: aload_0
       5: aload_1
       6: putfield      #2                  // Field builder:Lorg/apache/dubbo/metadata/definition/TypeDefinitionBuilder;
       9: return

  public org.apache.dubbo.metadata.definition.MethodDefinitionBuilder();
    Code:
       0: aload_0
       1: invokespecial #1                  // Method java/lang/Object."<init>":()V
       4: aload_0
       5: new           #3                  // class org/apache/dubbo/metadata/definition/TypeDefinitionBuilder
       8: dup
       9: invokespecial #4                  // Method org/apache/dubbo/metadata/definition/TypeDefinitionBuilder."<init>":()V
      12: putfield      #2                  // Field builder:Lorg/apache/dubbo/metadata/definition/TypeDefinitionBuilder;
      15: return

  public org.apache.dubbo.metadata.definition.model.MethodDefinition build(java.lang.reflect.Method);
    Code:
       0: new           #5                  // class org/apache/dubbo/metadata/definition/model/MethodDefinition
       3: dup
       4: invokespecial #6                  // Method org/apache/dubbo/metadata/definition/model/MethodDefinition."<init>":()V
       7: astore_2
       8: aload_2
       9: aload_1
      10: invokevirtual #7                  // Method java/lang/reflect/Method.getName:()Ljava/lang/String;
      13: invokevirtual #8                  // Method org/apache/dubbo/metadata/definition/model/MethodDefinition.setName:(Ljava/lang/String;)V
      16: aload_1
      17: invokevirtual #9                  // Method java/lang/reflect/Method.getParameterTypes:()[Ljava/lang/Class;
      20: astore_3
      21: aload_1
      22: invokevirtual #10                 // Method java/lang/reflect/Method.getGenericParameterTypes:()[Ljava/lang/reflect/Type;
      25: astore        4
      27: aload_3
      28: arraylength
      29: istore        5
      31: iload         5
      33: anewarray     #11                 // class java/lang/String
      36: astore        6
      38: new           #12                 // class java/util/ArrayList
      41: dup
      42: iload         5
      44: invokespecial #13                 // Method java/util/ArrayList."<init>":(I)V
      47: astore        7
      49: iconst_0
      50: istore        8
      52: iload         8
      54: iload         5
      56: if_icmpge     103
      59: aload_0
      60: getfield      #2                  // Field builder:Lorg/apache/dubbo/metadata/definition/TypeDefinitionBuilder;
      63: aload         4
      65: iload         8
      67: aaload
      68: aload_3
      69: iload         8
      71: aaload
      72: invokevirtual #14                 // Method org/apache/dubbo/metadata/definition/TypeDefinitionBuilder.build:(Ljava/lang/reflect/Type;Ljava/lang/Class;)Lorg/apache/dubbo/metadata/definition/model/TypeDefinition;
      75: astore        9
      77: aload         6
      79: iload         8
      81: aload         9
      83: invokevirtual #15                 // Method org/apache/dubbo/metadata/definition/model/TypeDefinition.getType:()Ljava/lang/String;
      86: aastore
      87: aload         7
      89: aload         9
      91: invokeinterface #16,  2           // InterfaceMethod java/util/List.add:(Ljava/lang/Object;)Z
      96: pop
      97: iinc          8, 1
     100: goto          52
     103: aload_2
     104: aload         6
     106: invokevirtual #17                 // Method org/apache/dubbo/metadata/definition/model/MethodDefinition.setParameterTypes:([Ljava/lang/String;)V
     109: aload_2
     110: aload         7
     112: invokevirtual #18                 // Method org/apache/dubbo/metadata/definition/model/MethodDefinition.setParameters:(Ljava/util/List;)V
     115: aload_0
     116: getfield      #2                  // Field builder:Lorg/apache/dubbo/metadata/definition/TypeDefinitionBuilder;
     119: aload_1
     120: invokevirtual #19                 // Method java/lang/reflect/Method.getGenericReturnType:()Ljava/lang/reflect/Type;
     123: aload_1
     124: invokevirtual #20                 // Method java/lang/reflect/Method.getReturnType:()Ljava/lang/Class;
     127: invokevirtual #14                 // Method org/apache/dubbo/metadata/definition/TypeDefinitionBuilder.build:(Ljava/lang/reflect/Type;Ljava/lang/Class;)Lorg/apache/dubbo/metadata/definition/model/TypeDefinition;
     130: astore        8
     132: aload_2
     133: aload         8
     135: invokevirtual #15                 // Method org/apache/dubbo/metadata/definition/model/TypeDefinition.getType:()Ljava/lang/String;
     138: invokevirtual #21                 // Method org/apache/dubbo/metadata/definition/model/MethodDefinition.setReturnType:(Ljava/lang/String;)V
     141: aload_2
     142: areturn
}
