Compiled from "ServiceDefinitionBuilder.java"
public final class org.apache.dubbo.metadata.definition.ServiceDefinitionBuilder {
  public static org.apache.dubbo.metadata.definition.model.ServiceDefinition build(java.lang.Class<?>);
    Code:
       0: new           #1                  // class org/apache/dubbo/metadata/definition/model/ServiceDefinition
       3: dup
       4: invokespecial #2                  // Method org/apache/dubbo/metadata/definition/model/ServiceDefinition."<init>":()V
       7: astore_1
       8: aload_1
       9: aload_0
      10: invokestatic  #3                  // Method build:(Lorg/apache/dubbo/metadata/definition/model/ServiceDefinition;Ljava/lang/Class;)V
      13: aload_1
      14: areturn

  public static org.apache.dubbo.metadata.definition.model.FullServiceDefinition buildFullDefinition(java.lang.Class<?>);
    Code:
       0: new           #4                  // class org/apache/dubbo/metadata/definition/model/FullServiceDefinition
       3: dup
       4: invokespecial #5                  // Method org/apache/dubbo/metadata/definition/model/FullServiceDefinition."<init>":()V
       7: astore_1
       8: aload_1
       9: aload_0
      10: invokestatic  #3                  // Method build:(Lorg/apache/dubbo/metadata/definition/model/ServiceDefinition;Ljava/lang/Class;)V
      13: aload_1
      14: areturn

  public static org.apache.dubbo.metadata.definition.model.FullServiceDefinition buildFullDefinition(java.lang.Class<?>, java.util.Map<java.lang.String, java.lang.String>);
    Code:
       0: new           #4                  // class org/apache/dubbo/metadata/definition/model/FullServiceDefinition
       3: dup
       4: invokespecial #5                  // Method org/apache/dubbo/metadata/definition/model/FullServiceDefinition."<init>":()V
       7: astore_2
       8: aload_2
       9: aload_0
      10: invokestatic  #3                  // Method build:(Lorg/apache/dubbo/metadata/definition/model/ServiceDefinition;Ljava/lang/Class;)V
      13: aload_2
      14: aload_1
      15: invokevirtual #6                  // Method org/apache/dubbo/metadata/definition/model/FullServiceDefinition.setParameters:(Ljava/util/Map;)V
      18: aload_2
      19: areturn

  public static <T extends org.apache.dubbo.metadata.definition.model.ServiceDefinition> void build(T, java.lang.Class<?>);
    Code:
       0: aload_0
       1: aload_1
       2: invokevirtual #7                  // Method java/lang/Class.getCanonicalName:()Ljava/lang/String;
       5: invokevirtual #8                  // Method org/apache/dubbo/metadata/definition/model/ServiceDefinition.setCanonicalName:(Ljava/lang/String;)V
       8: aload_0
       9: aload_1
      10: invokestatic  #9                  // Method org/apache/dubbo/metadata/definition/util/ClassUtils.getCodeSource:(Ljava/lang/Class;)Ljava/lang/String;
      13: invokevirtual #10                 // Method org/apache/dubbo/metadata/definition/model/ServiceDefinition.setCodeSource:(Ljava/lang/String;)V
      16: aload_1
      17: invokevirtual #11                 // Method java/lang/Class.getAnnotations:()[Ljava/lang/annotation/Annotation;
      20: astore_2
      21: aload_0
      22: aload_2
      23: invokestatic  #12                 // Method annotationToStringList:([Ljava/lang/annotation/Annotation;)Ljava/util/List;
      26: invokevirtual #13                 // Method org/apache/dubbo/metadata/definition/model/ServiceDefinition.setAnnotations:(Ljava/util/List;)V
      29: new           #14                 // class org/apache/dubbo/metadata/definition/TypeDefinitionBuilder
      32: dup
      33: invokespecial #15                 // Method org/apache/dubbo/metadata/definition/TypeDefinitionBuilder."<init>":()V
      36: astore_3
      37: aload_1
      38: invokestatic  #16                 // Method org/apache/dubbo/metadata/definition/util/ClassUtils.getPublicNonStaticMethods:(Ljava/lang/Class;)Ljava/util/List;
      41: astore        4
      43: aload         4
      45: invokeinterface #17,  1           // InterfaceMethod java/util/List.iterator:()Ljava/util/Iterator;
      50: astore        5
      52: aload         5
      54: invokeinterface #18,  1           // InterfaceMethod java/util/Iterator.hasNext:()Z
      59: ifeq          223
      62: aload         5
      64: invokeinterface #19,  1           // InterfaceMethod java/util/Iterator.next:()Ljava/lang/Object;
      69: checkcast     #20                 // class java/lang/reflect/Method
      72: astore        6
      74: new           #21                 // class org/apache/dubbo/metadata/definition/model/MethodDefinition
      77: dup
      78: invokespecial #22                 // Method org/apache/dubbo/metadata/definition/model/MethodDefinition."<init>":()V
      81: astore        7
      83: aload         7
      85: aload         6
      87: invokevirtual #23                 // Method java/lang/reflect/Method.getName:()Ljava/lang/String;
      90: invokevirtual #24                 // Method org/apache/dubbo/metadata/definition/model/MethodDefinition.setName:(Ljava/lang/String;)V
      93: aload         6
      95: invokevirtual #25                 // Method java/lang/reflect/Method.getAnnotations:()[Ljava/lang/annotation/Annotation;
      98: astore        8
     100: aload         7
     102: aload         8
     104: invokestatic  #12                 // Method annotationToStringList:([Ljava/lang/annotation/Annotation;)Ljava/util/List;
     107: invokevirtual #26                 // Method org/apache/dubbo/metadata/definition/model/MethodDefinition.setAnnotations:(Ljava/util/List;)V
     110: aload         6
     112: invokevirtual #27                 // Method java/lang/reflect/Method.getParameterTypes:()[Ljava/lang/Class;
     115: astore        9
     117: aload         6
     119: invokevirtual #28                 // Method java/lang/reflect/Method.getGenericParameterTypes:()[Ljava/lang/reflect/Type;
     122: astore        10
     124: aload         9
     126: arraylength
     127: anewarray     #29                 // class java/lang/String
     130: astore        11
     132: iconst_0
     133: istore        12
     135: iload         12
     137: aload         9
     139: arraylength
     140: if_icmpge     175
     143: aload_3
     144: aload         10
     146: iload         12
     148: aaload
     149: aload         9
     151: iload         12
     153: aaload
     154: invokevirtual #30                 // Method org/apache/dubbo/metadata/definition/TypeDefinitionBuilder.build:(Ljava/lang/reflect/Type;Ljava/lang/Class;)Lorg/apache/dubbo/metadata/definition/model/TypeDefinition;
     157: astore        13
     159: aload         11
     161: iload         12
     163: aload         13
     165: invokevirtual #31                 // Method org/apache/dubbo/metadata/definition/model/TypeDefinition.getType:()Ljava/lang/String;
     168: aastore
     169: iinc          12, 1
     172: goto          135
     175: aload         7
     177: aload         11
     179: invokevirtual #32                 // Method org/apache/dubbo/metadata/definition/model/MethodDefinition.setParameterTypes:([Ljava/lang/String;)V
     182: aload_3
     183: aload         6
     185: invokevirtual #33                 // Method java/lang/reflect/Method.getGenericReturnType:()Ljava/lang/reflect/Type;
     188: aload         6
     190: invokevirtual #34                 // Method java/lang/reflect/Method.getReturnType:()Ljava/lang/Class;
     193: invokevirtual #30                 // Method org/apache/dubbo/metadata/definition/TypeDefinitionBuilder.build:(Ljava/lang/reflect/Type;Ljava/lang/Class;)Lorg/apache/dubbo/metadata/definition/model/TypeDefinition;
     196: astore        12
     198: aload         7
     200: aload         12
     202: invokevirtual #31                 // Method org/apache/dubbo/metadata/definition/model/TypeDefinition.getType:()Ljava/lang/String;
     205: invokevirtual #35                 // Method org/apache/dubbo/metadata/definition/model/MethodDefinition.setReturnType:(Ljava/lang/String;)V
     208: aload_0
     209: invokevirtual #36                 // Method org/apache/dubbo/metadata/definition/model/ServiceDefinition.getMethods:()Ljava/util/List;
     212: aload         7
     214: invokeinterface #37,  2           // InterfaceMethod java/util/List.add:(Ljava/lang/Object;)Z
     219: pop
     220: goto          52
     223: aload_0
     224: aload_3
     225: invokevirtual #38                 // Method org/apache/dubbo/metadata/definition/TypeDefinitionBuilder.getTypeDefinitions:()Ljava/util/List;
     228: invokevirtual #39                 // Method org/apache/dubbo/metadata/definition/model/ServiceDefinition.setTypes:(Ljava/util/List;)V
     231: return

  private static java.util.List<java.lang.String> annotationToStringList(java.lang.annotation.Annotation[]);
    Code:
       0: aload_0
       1: ifnonnull     8
       4: invokestatic  #40                 // Method java/util/Collections.emptyList:()Ljava/util/List;
       7: areturn
       8: new           #41                 // class java/util/ArrayList
      11: dup
      12: invokespecial #42                 // Method java/util/ArrayList."<init>":()V
      15: astore_1
      16: aload_0
      17: astore_2
      18: aload_2
      19: arraylength
      20: istore_3
      21: iconst_0
      22: istore        4
      24: iload         4
      26: iload_3
      27: if_icmpge     56
      30: aload_2
      31: iload         4
      33: aaload
      34: astore        5
      36: aload_1
      37: aload         5
      39: invokeinterface #43,  1           // InterfaceMethod java/lang/annotation/Annotation.toString:()Ljava/lang/String;
      44: invokeinterface #37,  2           // InterfaceMethod java/util/List.add:(Ljava/lang/Object;)Z
      49: pop
      50: iinc          4, 1
      53: goto          24
      56: aload_1
      57: areturn

  public static java.lang.String schema(java.lang.Class<?>);
    Code:
       0: aload_0
       1: invokestatic  #44                 // Method build:(Ljava/lang/Class;)Lorg/apache/dubbo/metadata/definition/model/ServiceDefinition;
       4: astore_1
       5: aload_1
       6: invokestatic  #45                 // Method org/apache/dubbo/common/utils/JsonUtils.toJson:(Ljava/lang/Object;)Ljava/lang/String;
       9: areturn

  private org.apache.dubbo.metadata.definition.ServiceDefinitionBuilder();
    Code:
       0: aload_0
       1: invokespecial #46                 // Method java/lang/Object."<init>":()V
       4: return
}
