Compiled from "DefaultExecutorSupport.java"
public class org.apache.dubbo.rpc.executor.DefaultExecutorSupport implements org.apache.dubbo.rpc.executor.ExecutorSupport {
  private final org.apache.dubbo.common.threadpool.manager.ExecutorRepository executorRepository;

  private final org.apache.dubbo.common.URL url;

  public org.apache.dubbo.rpc.executor.DefaultExecutorSupport(org.apache.dubbo.common.URL);
    Code:
       0: aload_0
       1: invokespecial #1                  // Method java/lang/Object."<init>":()V
       4: aload_0
       5: aload_1
       6: putfield      #2                  // Field url:Lorg/apache/dubbo/common/URL;
       9: aload_0
      10: aload_1
      11: invokevirtual #3                  // Method org/apache/dubbo/common/URL.getOrDefaultApplicationModel:()Lorg/apache/dubbo/rpc/model/ApplicationModel;
      14: invokestatic  #4                  // InterfaceMethod org/apache/dubbo/common/threadpool/manager/ExecutorRepository.getInstance:(Lorg/apache/dubbo/rpc/model/ApplicationModel;)Lorg/apache/dubbo/common/threadpool/manager/ExecutorRepository;
      17: putfield      #5                  // Field executorRepository:Lorg/apache/dubbo/common/threadpool/manager/ExecutorRepository;
      20: return

  public java.util.concurrent.Executor getExecutor(java.lang.Object);
    Code:
       0: aload_0
       1: getfield      #5                  // Field executorRepository:Lorg/apache/dubbo/common/threadpool/manager/ExecutorRepository;
       4: aload_0
       5: getfield      #2                  // Field url:Lorg/apache/dubbo/common/URL;
       8: invokeinterface #6,  2            // InterfaceMethod org/apache/dubbo/common/threadpool/manager/ExecutorRepository.getExecutor:(Lorg/apache/dubbo/common/URL;)Ljava/util/concurrent/ExecutorService;
      13: areturn
}
