Compiled from "IsolationExecutorSupportFactory.java"
public interface org.apache.dubbo.rpc.executor.IsolationExecutorSupportFactory {
  public abstract org.apache.dubbo.rpc.executor.ExecutorSupport createIsolationExecutorSupport(org.apache.dubbo.common.URL);

  public static org.apache.dubbo.rpc.executor.ExecutorSupport getIsolationExecutorSupport(org.apache.dubbo.common.URL);
    Code:
       0: aload_0
       1: invokevirtual #1                  // Method org/apache/dubbo/common/URL.getOrDefaultApplicationModel:()Lorg/apache/dubbo/rpc/model/ApplicationModel;
       4: astore_1
       5: aload_1
       6: ldc           #2                  // class org/apache/dubbo/rpc/executor/IsolationExecutorSupportFactory
       8: invokevirtual #3                  // Method org/apache/dubbo/rpc/model/ApplicationModel.getExtensionLoader:(Ljava/lang/Class;)Lorg/apache/dubbo/common/extension/ExtensionLoader;
      11: astore_2
      12: aload_2
      13: aload_0
      14: invokevirtual #4                  // Method org/apache/dubbo/common/URL.getProtocol:()Ljava/lang/String;
      17: invokevirtual #5                  // Method org/apache/dubbo/common/extension/ExtensionLoader.getOrDefaultExtension:(Ljava/lang/String;)Ljava/lang/Object;
      20: checkcast     #2                  // class org/apache/dubbo/rpc/executor/IsolationExecutorSupportFactory
      23: astore_3
      24: aload_3
      25: aload_0
      26: invokeinterface #6,  2            // InterfaceMethod createIsolationExecutorSupport:(Lorg/apache/dubbo/common/URL;)Lorg/apache/dubbo/rpc/executor/ExecutorSupport;
      31: areturn
}
