Compiled from "SpringContainer.java"
public class org.apache.dubbo.container.spring.SpringContainer implements org.apache.dubbo.container.Container {
  public static final java.lang.String SPRING_CONFIG;

  public static final java.lang.String DEFAULT_SPRING_CONFIG;

  private static final org.apache.dubbo.common.logger.ErrorTypeAwareLogger logger;

  static org.springframework.context.support.ClassPathXmlApplicationContext context;

  public org.apache.dubbo.container.spring.SpringContainer();
    Code:
       0: aload_0
       1: invokespecial #2                  // Method java/lang/Object."<init>":()V
       4: return

  public static org.springframework.context.support.ClassPathXmlApplicationContext getContext();
    Code:
       0: getstatic     #3                  // Field context:Lorg/springframework/context/support/ClassPathXmlApplicationContext;
       3: areturn

  public void start();
    Code:
       0: ldc           #5                  // String dubbo.spring.config
       2: invokestatic  #6                  // Method java/lang/System.getProperty:(Ljava/lang/String;)Ljava/lang/String;
       5: astore_1
       6: aload_1
       7: invokestatic  #7                  // Method org/apache/dubbo/common/utils/StringUtils.isEmpty:(Ljava/lang/String;)Z
      10: ifeq          16
      13: ldc           #8                  // String classpath*:META-INF/spring/*.xml
      15: astore_1
      16: new           #9                  // class org/springframework/context/support/ClassPathXmlApplicationContext
      19: dup
      20: aload_1
      21: ldc           #10                 // String [,\\s]+
      23: invokevirtual #11                 // Method java/lang/String.split:(Ljava/lang/String;)[Ljava/lang/String;
      26: iconst_0
      27: invokespecial #12                 // Method org/springframework/context/support/ClassPathXmlApplicationContext."<init>":([Ljava/lang/String;Z)V
      30: putstatic     #3                  // Field context:Lorg/springframework/context/support/ClassPathXmlApplicationContext;
      33: getstatic     #3                  // Field context:Lorg/springframework/context/support/ClassPathXmlApplicationContext;
      36: invokevirtual #13                 // Method org/springframework/context/support/ClassPathXmlApplicationContext.refresh:()V
      39: getstatic     #3                  // Field context:Lorg/springframework/context/support/ClassPathXmlApplicationContext;
      42: invokevirtual #14                 // Method org/springframework/context/support/ClassPathXmlApplicationContext.start:()V
      45: return

  public void stop();
    Code:
       0: getstatic     #3                  // Field context:Lorg/springframework/context/support/ClassPathXmlApplicationContext;
       3: ifnull        22
       6: getstatic     #3                  // Field context:Lorg/springframework/context/support/ClassPathXmlApplicationContext;
       9: invokevirtual #15                 // Method org/springframework/context/support/ClassPathXmlApplicationContext.stop:()V
      12: getstatic     #3                  // Field context:Lorg/springframework/context/support/ClassPathXmlApplicationContext;
      15: invokevirtual #16                 // Method org/springframework/context/support/ClassPathXmlApplicationContext.close:()V
      18: aconst_null
      19: putstatic     #3                  // Field context:Lorg/springframework/context/support/ClassPathXmlApplicationContext;
      22: goto          45
      25: astore_1
      26: getstatic     #18                 // Field logger:Lorg/apache/dubbo/common/logger/ErrorTypeAwareLogger;
      29: ldc           #19                 // String 5-20
      31: ldc           #20                 // String
      33: ldc           #20                 // String
      35: aload_1
      36: invokevirtual #21                 // Method java/lang/Throwable.getMessage:()Ljava/lang/String;
      39: aload_1
      40: invokeinterface #22,  6           // InterfaceMethod org/apache/dubbo/common/logger/ErrorTypeAwareLogger.error:(Ljava/lang/String;Ljava/lang/String;Ljava/lang/String;Ljava/lang/String;Ljava/lang/Throwable;)V
      45: return
    Exception table:
       from    to  target type
           0    22    25   Class java/lang/Throwable

  static {};
    Code:
       0: ldc           #4                  // class org/apache/dubbo/container/spring/SpringContainer
       2: invokestatic  #23                 // Method org/apache/dubbo/common/logger/LoggerFactory.getErrorTypeAwareLogger:(Ljava/lang/Class;)Lorg/apache/dubbo/common/logger/ErrorTypeAwareLogger;
       5: putstatic     #18                 // Field logger:Lorg/apache/dubbo/common/logger/ErrorTypeAwareLogger;
       8: return
}
