Compiled from "BaseTestConsumer.java"
public abstract class io.reactivex.rxjava3.observers.BaseTestConsumer<T, U extends io.reactivex.rxjava3.observers.BaseTestConsumer<T, U>> {
  protected final java.util.concurrent.CountDownLatch done;

  protected final java.util.List<T> values;

  protected final java.util.List<java.lang.Throwable> errors;

  protected long completions;

  protected java.lang.Thread lastThread;

  protected boolean checkSubscriptionOnce;

  protected java.lang.CharSequence tag;

  protected boolean timeout;

  public io.reactivex.rxjava3.observers.BaseTestConsumer();
    Code:
       0: aload_0
       1: invokespecial #1                  // Method java/lang/Object."<init>":()V
       4: aload_0
       5: new           #2                  // class io/reactivex/rxjava3/internal/util/VolatileSizeArrayList
       8: dup
       9: invokespecial #3                  // Method io/reactivex/rxjava3/internal/util/VolatileSizeArrayList."<init>":()V
      12: putfield      #4                  // Field values:Ljava/util/List;
      15: aload_0
      16: new           #2                  // class io/reactivex/rxjava3/internal/util/VolatileSizeArrayList
      19: dup
      20: invokespecial #3                  // Method io/reactivex/rxjava3/internal/util/VolatileSizeArrayList."<init>":()V
      23: putfield      #5                  // Field errors:Ljava/util/List;
      26: aload_0
      27: new           #6                  // class java/util/concurrent/CountDownLatch
      30: dup
      31: iconst_1
      32: invokespecial #7                  // Method java/util/concurrent/CountDownLatch."<init>":(I)V
      35: putfield      #8                  // Field done:Ljava/util/concurrent/CountDownLatch;
      38: return

  public final java.util.List<T> values();
    Code:
       0: aload_0
       1: getfield      #4                  // Field values:Ljava/util/List;
       4: areturn

  protected final java.lang.AssertionError fail(java.lang.String);
    Code:
       0: new           #9                  // class java/lang/StringBuilder
       3: dup
       4: bipush        64
       6: aload_1
       7: invokevirtual #10                 // Method java/lang/String.length:()I
      10: iadd
      11: invokespecial #11                 // Method java/lang/StringBuilder."<init>":(I)V
      14: astore_2
      15: aload_2
      16: aload_1
      17: invokevirtual #12                 // Method java/lang/StringBuilder.append:(Ljava/lang/String;)Ljava/lang/StringBuilder;
      20: pop
      21: aload_2
      22: ldc           #13                 // String  (
      24: invokevirtual #12                 // Method java/lang/StringBuilder.append:(Ljava/lang/String;)Ljava/lang/StringBuilder;
      27: ldc           #14                 // String latch =
      29: invokevirtual #12                 // Method java/lang/StringBuilder.append:(Ljava/lang/String;)Ljava/lang/StringBuilder;
      32: aload_0
      33: getfield      #8                  // Field done:Ljava/util/concurrent/CountDownLatch;
      36: invokevirtual #15                 // Method java/util/concurrent/CountDownLatch.getCount:()J
      39: invokevirtual #16                 // Method java/lang/StringBuilder.append:(J)Ljava/lang/StringBuilder;
      42: ldc           #17                 // String ,
      44: invokevirtual #12                 // Method java/lang/StringBuilder.append:(Ljava/lang/String;)Ljava/lang/StringBuilder;
      47: ldc           #18                 // String values =
      49: invokevirtual #12                 // Method java/lang/StringBuilder.append:(Ljava/lang/String;)Ljava/lang/StringBuilder;
      52: aload_0
      53: getfield      #4                  // Field values:Ljava/util/List;
      56: invokeinterface #19,  1           // InterfaceMethod java/util/List.size:()I
      61: invokevirtual #20                 // Method java/lang/StringBuilder.append:(I)Ljava/lang/StringBuilder;
      64: ldc           #17                 // String ,
      66: invokevirtual #12                 // Method java/lang/StringBuilder.append:(Ljava/lang/String;)Ljava/lang/StringBuilder;
      69: ldc           #21                 // String errors =
      71: invokevirtual #12                 // Method java/lang/StringBuilder.append:(Ljava/lang/String;)Ljava/lang/StringBuilder;
      74: aload_0
      75: getfield      #5                  // Field errors:Ljava/util/List;
      78: invokeinterface #19,  1           // InterfaceMethod java/util/List.size:()I
      83: invokevirtual #20                 // Method java/lang/StringBuilder.append:(I)Ljava/lang/StringBuilder;
      86: ldc           #17                 // String ,
      88: invokevirtual #12                 // Method java/lang/StringBuilder.append:(Ljava/lang/String;)Ljava/lang/StringBuilder;
      91: ldc           #22                 // String completions =
      93: invokevirtual #12                 // Method java/lang/StringBuilder.append:(Ljava/lang/String;)Ljava/lang/StringBuilder;
      96: aload_0
      97: getfield      #23                 // Field completions:J
     100: invokevirtual #16                 // Method java/lang/StringBuilder.append:(J)Ljava/lang/StringBuilder;
     103: pop
     104: aload_0
     105: getfield      #24                 // Field timeout:Z
     108: ifeq          118
     111: aload_2
     112: ldc           #25                 // String , timeout!
     114: invokevirtual #12                 // Method java/lang/StringBuilder.append:(Ljava/lang/String;)Ljava/lang/StringBuilder;
     117: pop
     118: aload_0
     119: invokevirtual #26                 // Method isDisposed:()Z
     122: ifeq          132
     125: aload_2
     126: ldc           #27                 // String , disposed!
     128: invokevirtual #12                 // Method java/lang/StringBuilder.append:(Ljava/lang/String;)Ljava/lang/StringBuilder;
     131: pop
     132: aload_0
     133: getfield      #28                 // Field tag:Ljava/lang/CharSequence;
     136: astore_3
     137: aload_3
     138: ifnull        152
     141: aload_2
     142: ldc           #29                 // String , tag =
     144: invokevirtual #12                 // Method java/lang/StringBuilder.append:(Ljava/lang/String;)Ljava/lang/StringBuilder;
     147: aload_3
     148: invokevirtual #30                 // Method java/lang/StringBuilder.append:(Ljava/lang/CharSequence;)Ljava/lang/StringBuilder;
     151: pop
     152: aload_2
     153: bipush        41
     155: invokevirtual #31                 // Method java/lang/StringBuilder.append:(C)Ljava/lang/StringBuilder;
     158: pop
     159: new           #32                 // class java/lang/AssertionError
     162: dup
     163: aload_2
     164: invokevirtual #33                 // Method java/lang/StringBuilder.toString:()Ljava/lang/String;
     167: invokespecial #34                 // Method java/lang/AssertionError."<init>":(Ljava/lang/Object;)V
     170: astore        4
     172: aload_0
     173: getfield      #5                  // Field errors:Ljava/util/List;
     176: invokeinterface #35,  1           // InterfaceMethod java/util/List.isEmpty:()Z
     181: ifne          240
     184: aload_0
     185: getfield      #5                  // Field errors:Ljava/util/List;
     188: invokeinterface #19,  1           // InterfaceMethod java/util/List.size:()I
     193: iconst_1
     194: if_icmpne     219
     197: aload         4
     199: aload_0
     200: getfield      #5                  // Field errors:Ljava/util/List;
     203: iconst_0
     204: invokeinterface #36,  2           // InterfaceMethod java/util/List.get:(I)Ljava/lang/Object;
     209: checkcast     #37                 // class java/lang/Throwable
     212: invokevirtual #38                 // Method java/lang/AssertionError.initCause:(Ljava/lang/Throwable;)Ljava/lang/Throwable;
     215: pop
     216: goto          240
     219: new           #39                 // class io/reactivex/rxjava3/exceptions/CompositeException
     222: dup
     223: aload_0
     224: getfield      #5                  // Field errors:Ljava/util/List;
     227: invokespecial #40                 // Method io/reactivex/rxjava3/exceptions/CompositeException."<init>":(Ljava/lang/Iterable;)V
     230: astore        5
     232: aload         4
     234: aload         5
     236: invokevirtual #38                 // Method java/lang/AssertionError.initCause:(Ljava/lang/Throwable;)Ljava/lang/Throwable;
     239: pop
     240: aload         4
     242: areturn

  public final U await() throws java.lang.InterruptedException;
    Code:
       0: aload_0
       1: getfield      #8                  // Field done:Ljava/util/concurrent/CountDownLatch;
       4: invokevirtual #15                 // Method java/util/concurrent/CountDownLatch.getCount:()J
       7: lconst_0
       8: lcmp
       9: ifne          14
      12: aload_0
      13: areturn
      14: aload_0
      15: getfield      #8                  // Field done:Ljava/util/concurrent/CountDownLatch;
      18: invokevirtual #41                 // Method java/util/concurrent/CountDownLatch.await:()V
      21: aload_0
      22: areturn

  public final boolean await(long, java.util.concurrent.TimeUnit) throws java.lang.InterruptedException;
    Code:
       0: aload_0
       1: getfield      #8                  // Field done:Ljava/util/concurrent/CountDownLatch;
       4: invokevirtual #15                 // Method java/util/concurrent/CountDownLatch.getCount:()J
       7: lconst_0
       8: lcmp
       9: ifeq          24
      12: aload_0
      13: getfield      #8                  // Field done:Ljava/util/concurrent/CountDownLatch;
      16: lload_1
      17: aload_3
      18: invokevirtual #42                 // Method java/util/concurrent/CountDownLatch.await:(JLjava/util/concurrent/TimeUnit;)Z
      21: ifeq          28
      24: iconst_1
      25: goto          29
      28: iconst_0
      29: istore        4
      31: aload_0
      32: iload         4
      34: ifne          41
      37: iconst_1
      38: goto          42
      41: iconst_0
      42: putfield      #24                 // Field timeout:Z
      45: iload         4
      47: ireturn

  public final U assertComplete();
    Code:
       0: aload_0
       1: getfield      #23                 // Field completions:J
       4: lstore_1
       5: lload_1
       6: lconst_0
       7: lcmp
       8: ifne          18
      11: aload_0
      12: ldc           #43                 // String Not completed
      14: invokevirtual #44                 // Method fail:(Ljava/lang/String;)Ljava/lang/AssertionError;
      17: athrow
      18: lload_1
      19: lconst_1
      20: lcmp
      21: ifle          48
      24: aload_0
      25: new           #9                  // class java/lang/StringBuilder
      28: dup
      29: invokespecial #45                 // Method java/lang/StringBuilder."<init>":()V
      32: ldc           #46                 // String Multiple completions:
      34: invokevirtual #12                 // Method java/lang/StringBuilder.append:(Ljava/lang/String;)Ljava/lang/StringBuilder;
      37: lload_1
      38: invokevirtual #16                 // Method java/lang/StringBuilder.append:(J)Ljava/lang/StringBuilder;
      41: invokevirtual #33                 // Method java/lang/StringBuilder.toString:()Ljava/lang/String;
      44: invokevirtual #44                 // Method fail:(Ljava/lang/String;)Ljava/lang/AssertionError;
      47: athrow
      48: aload_0
      49: areturn

  public final U assertNotComplete();
    Code:
       0: aload_0
       1: getfield      #23                 // Field completions:J
       4: lstore_1
       5: lload_1
       6: lconst_1
       7: lcmp
       8: ifne          18
      11: aload_0
      12: ldc           #47                 // String Completed!
      14: invokevirtual #44                 // Method fail:(Ljava/lang/String;)Ljava/lang/AssertionError;
      17: athrow
      18: lload_1
      19: lconst_1
      20: lcmp
      21: ifle          48
      24: aload_0
      25: new           #9                  // class java/lang/StringBuilder
      28: dup
      29: invokespecial #45                 // Method java/lang/StringBuilder."<init>":()V
      32: ldc           #46                 // String Multiple completions:
      34: invokevirtual #12                 // Method java/lang/StringBuilder.append:(Ljava/lang/String;)Ljava/lang/StringBuilder;
      37: lload_1
      38: invokevirtual #16                 // Method java/lang/StringBuilder.append:(J)Ljava/lang/StringBuilder;
      41: invokevirtual #33                 // Method java/lang/StringBuilder.toString:()Ljava/lang/String;
      44: invokevirtual #44                 // Method fail:(Ljava/lang/String;)Ljava/lang/AssertionError;
      47: athrow
      48: aload_0
      49: areturn

  public final U assertNoErrors();
    Code:
       0: aload_0
       1: getfield      #5                  // Field errors:Ljava/util/List;
       4: invokeinterface #19,  1           // InterfaceMethod java/util/List.size:()I
       9: istore_1
      10: iload_1
      11: ifeq          41
      14: aload_0
      15: new           #9                  // class java/lang/StringBuilder
      18: dup
      19: invokespecial #45                 // Method java/lang/StringBuilder."<init>":()V
      22: ldc           #48                 // String Error(s) present:
      24: invokevirtual #12                 // Method java/lang/StringBuilder.append:(Ljava/lang/String;)Ljava/lang/StringBuilder;
      27: aload_0
      28: getfield      #5                  // Field errors:Ljava/util/List;
      31: invokevirtual #49                 // Method java/lang/StringBuilder.append:(Ljava/lang/Object;)Ljava/lang/StringBuilder;
      34: invokevirtual #33                 // Method java/lang/StringBuilder.toString:()Ljava/lang/String;
      37: invokevirtual #44                 // Method fail:(Ljava/lang/String;)Ljava/lang/AssertionError;
      40: athrow
      41: aload_0
      42: areturn

  public final U assertError(java.lang.Throwable);
    Code:
       0: aload_0
       1: aload_1
       2: invokestatic  #50                 // Method io/reactivex/rxjava3/internal/functions/Functions.equalsWith:(Ljava/lang/Object;)Lio/reactivex/rxjava3/functions/Predicate;
       5: iconst_1
       6: invokespecial #51                 // Method assertError:(Lio/reactivex/rxjava3/functions/Predicate;Z)Lio/reactivex/rxjava3/observers/BaseTestConsumer;
       9: areturn

  public final U assertError(java.lang.Class<? extends java.lang.Throwable>);
    Code:
       0: aload_0
       1: aload_1
       2: invokestatic  #52                 // Method io/reactivex/rxjava3/internal/functions/Functions.isInstanceOf:(Ljava/lang/Class;)Lio/reactivex/rxjava3/functions/Predicate;
       5: iconst_1
       6: invokespecial #51                 // Method assertError:(Lio/reactivex/rxjava3/functions/Predicate;Z)Lio/reactivex/rxjava3/observers/BaseTestConsumer;
       9: areturn

  public final U assertError(io.reactivex.rxjava3.functions.Predicate<java.lang.Throwable>);
    Code:
       0: aload_0
       1: aload_1
       2: iconst_0
       3: invokespecial #51                 // Method assertError:(Lio/reactivex/rxjava3/functions/Predicate;Z)Lio/reactivex/rxjava3/observers/BaseTestConsumer;
       6: areturn

  private U assertError(io.reactivex.rxjava3.functions.Predicate<java.lang.Throwable>, boolean);
    Code:
       0: aload_0
       1: getfield      #5                  // Field errors:Ljava/util/List;
       4: invokeinterface #19,  1           // InterfaceMethod java/util/List.size:()I
       9: istore_3
      10: iload_3
      11: ifne          21
      14: aload_0
      15: ldc           #53                 // String No errors
      17: invokevirtual #44                 // Method fail:(Ljava/lang/String;)Ljava/lang/AssertionError;
      20: athrow
      21: iconst_0
      22: istore        4
      24: aload_0
      25: getfield      #5                  // Field errors:Ljava/util/List;
      28: invokeinterface #54,  1           // InterfaceMethod java/util/List.iterator:()Ljava/util/Iterator;
      33: astore        5
      35: aload         5
      37: invokeinterface #55,  1           // InterfaceMethod java/util/Iterator.hasNext:()Z
      42: ifeq          88
      45: aload         5
      47: invokeinterface #56,  1           // InterfaceMethod java/util/Iterator.next:()Ljava/lang/Object;
      52: checkcast     #37                 // class java/lang/Throwable
      55: astore        6
      57: aload_1
      58: aload         6
      60: invokeinterface #57,  2           // InterfaceMethod io/reactivex/rxjava3/functions/Predicate.test:(Ljava/lang/Object;)Z
      65: ifeq          74
      68: iconst_1
      69: istore        4
      71: goto          88
      74: goto          85
      77: astore        7
      79: aload         7
      81: invokestatic  #58                 // Method io/reactivex/rxjava3/internal/util/ExceptionHelper.wrapOrThrow:(Ljava/lang/Throwable;)Ljava/lang/RuntimeException;
      84: athrow
      85: goto          35
      88: iload         4
      90: ifeq          116
      93: iload_3
      94: iconst_1
      95: if_icmpeq     134
      98: iload_2
      99: ifeq          109
     102: aload_0
     103: ldc           #59                 // String Error present but other errors as well
     105: invokevirtual #44                 // Method fail:(Ljava/lang/String;)Ljava/lang/AssertionError;
     108: athrow
     109: aload_0
     110: ldc           #60                 // String One error passed the predicate but other errors are present as well
     112: invokevirtual #44                 // Method fail:(Ljava/lang/String;)Ljava/lang/AssertionError;
     115: athrow
     116: iload_2
     117: ifeq          127
     120: aload_0
     121: ldc           #61                 // String Error not present
     123: invokevirtual #44                 // Method fail:(Ljava/lang/String;)Ljava/lang/AssertionError;
     126: athrow
     127: aload_0
     128: ldc           #62                 // String No error(s) passed the predicate
     130: invokevirtual #44                 // Method fail:(Ljava/lang/String;)Ljava/lang/AssertionError;
     133: athrow
     134: aload_0
     135: areturn
    Exception table:
       from    to  target type
          57    71    77   Class java/lang/Throwable

  public final U assertValue(T);
    Code:
       0: aload_0
       1: getfield      #4                  // Field values:Ljava/util/List;
       4: invokeinterface #19,  1           // InterfaceMethod java/util/List.size:()I
       9: istore_2
      10: iload_2
      11: iconst_1
      12: if_icmpeq     54
      15: aload_0
      16: new           #9                  // class java/lang/StringBuilder
      19: dup
      20: invokespecial #45                 // Method java/lang/StringBuilder."<init>":()V
      23: ldc           #63                 // String \nexpected:
      25: invokevirtual #12                 // Method java/lang/StringBuilder.append:(Ljava/lang/String;)Ljava/lang/StringBuilder;
      28: aload_1
      29: invokestatic  #64                 // Method valueAndClass:(Ljava/lang/Object;)Ljava/lang/String;
      32: invokevirtual #12                 // Method java/lang/StringBuilder.append:(Ljava/lang/String;)Ljava/lang/StringBuilder;
      35: ldc           #65                 // String \ngot:
      37: invokevirtual #12                 // Method java/lang/StringBuilder.append:(Ljava/lang/String;)Ljava/lang/StringBuilder;
      40: aload_0
      41: getfield      #4                  // Field values:Ljava/util/List;
      44: invokevirtual #49                 // Method java/lang/StringBuilder.append:(Ljava/lang/Object;)Ljava/lang/StringBuilder;
      47: invokevirtual #33                 // Method java/lang/StringBuilder.toString:()Ljava/lang/String;
      50: invokevirtual #44                 // Method fail:(Ljava/lang/String;)Ljava/lang/AssertionError;
      53: athrow
      54: aload_0
      55: getfield      #4                  // Field values:Ljava/util/List;
      58: iconst_0
      59: invokeinterface #36,  2           // InterfaceMethod java/util/List.get:(I)Ljava/lang/Object;
      64: astore_3
      65: aload_1
      66: aload_3
      67: invokestatic  #66                 // Method java/util/Objects.equals:(Ljava/lang/Object;Ljava/lang/Object;)Z
      70: ifne          112
      73: aload_0
      74: new           #9                  // class java/lang/StringBuilder
      77: dup
      78: invokespecial #45                 // Method java/lang/StringBuilder."<init>":()V
      81: ldc           #63                 // String \nexpected:
      83: invokevirtual #12                 // Method java/lang/StringBuilder.append:(Ljava/lang/String;)Ljava/lang/StringBuilder;
      86: aload_1
      87: invokestatic  #64                 // Method valueAndClass:(Ljava/lang/Object;)Ljava/lang/String;
      90: invokevirtual #12                 // Method java/lang/StringBuilder.append:(Ljava/lang/String;)Ljava/lang/StringBuilder;
      93: ldc           #65                 // String \ngot:
      95: invokevirtual #12                 // Method java/lang/StringBuilder.append:(Ljava/lang/String;)Ljava/lang/StringBuilder;
      98: aload_3
      99: invokestatic  #64                 // Method valueAndClass:(Ljava/lang/Object;)Ljava/lang/String;
     102: invokevirtual #12                 // Method java/lang/StringBuilder.append:(Ljava/lang/String;)Ljava/lang/StringBuilder;
     105: invokevirtual #33                 // Method java/lang/StringBuilder.toString:()Ljava/lang/String;
     108: invokevirtual #44                 // Method fail:(Ljava/lang/String;)Ljava/lang/AssertionError;
     111: athrow
     112: aload_0
     113: areturn

  public final U assertValue(io.reactivex.rxjava3.functions.Predicate<T>);
    Code:
       0: aload_0
       1: iconst_0
       2: aload_1
       3: invokevirtual #67                 // Method assertValueAt:(ILio/reactivex/rxjava3/functions/Predicate;)Lio/reactivex/rxjava3/observers/BaseTestConsumer;
       6: pop
       7: aload_0
       8: getfield      #4                  // Field values:Ljava/util/List;
      11: invokeinterface #19,  1           // InterfaceMethod java/util/List.size:()I
      16: iconst_1
      17: if_icmple     27
      20: aload_0
      21: ldc           #68                 // String The first value passed the predicate but this consumer received more than one value
      23: invokevirtual #44                 // Method fail:(Ljava/lang/String;)Ljava/lang/AssertionError;
      26: athrow
      27: aload_0
      28: areturn

  public final U assertValueAt(int, T);
    Code:
       0: aload_0
       1: getfield      #4                  // Field values:Ljava/util/List;
       4: invokeinterface #19,  1           // InterfaceMethod java/util/List.size:()I
       9: istore_3
      10: iload_3
      11: ifne          21
      14: aload_0
      15: ldc           #69                 // String No values
      17: invokevirtual #44                 // Method fail:(Ljava/lang/String;)Ljava/lang/AssertionError;
      20: athrow
      21: iload_1
      22: iflt          30
      25: iload_1
      26: iload_3
      27: if_icmplt     68
      30: aload_0
      31: new           #9                  // class java/lang/StringBuilder
      34: dup
      35: invokespecial #45                 // Method java/lang/StringBuilder."<init>":()V
      38: ldc           #70                 // String Index
      40: invokevirtual #12                 // Method java/lang/StringBuilder.append:(Ljava/lang/String;)Ljava/lang/StringBuilder;
      43: iload_1
      44: invokevirtual #20                 // Method java/lang/StringBuilder.append:(I)Ljava/lang/StringBuilder;
      47: ldc           #71                 // String  is out of range [0,
      49: invokevirtual #12                 // Method java/lang/StringBuilder.append:(Ljava/lang/String;)Ljava/lang/StringBuilder;
      52: iload_3
      53: invokevirtual #20                 // Method java/lang/StringBuilder.append:(I)Ljava/lang/StringBuilder;
      56: ldc           #72                 // String )
      58: invokevirtual #12                 // Method java/lang/StringBuilder.append:(Ljava/lang/String;)Ljava/lang/StringBuilder;
      61: invokevirtual #33                 // Method java/lang/StringBuilder.toString:()Ljava/lang/String;
      64: invokevirtual #44                 // Method fail:(Ljava/lang/String;)Ljava/lang/AssertionError;
      67: athrow
      68: aload_0
      69: getfield      #4                  // Field values:Ljava/util/List;
      72: iload_1
      73: invokeinterface #36,  2           // InterfaceMethod java/util/List.get:(I)Ljava/lang/Object;
      78: astore        4
      80: aload_2
      81: aload         4
      83: invokestatic  #66                 // Method java/util/Objects.equals:(Ljava/lang/Object;Ljava/lang/Object;)Z
      86: ifne          143
      89: aload_0
      90: new           #9                  // class java/lang/StringBuilder
      93: dup
      94: invokespecial #45                 // Method java/lang/StringBuilder."<init>":()V
      97: ldc           #63                 // String \nexpected:
      99: invokevirtual #12                 // Method java/lang/StringBuilder.append:(Ljava/lang/String;)Ljava/lang/StringBuilder;
     102: aload_2
     103: invokestatic  #64                 // Method valueAndClass:(Ljava/lang/Object;)Ljava/lang/String;
     106: invokevirtual #12                 // Method java/lang/StringBuilder.append:(Ljava/lang/String;)Ljava/lang/StringBuilder;
     109: ldc           #65                 // String \ngot:
     111: invokevirtual #12                 // Method java/lang/StringBuilder.append:(Ljava/lang/String;)Ljava/lang/StringBuilder;
     114: aload         4
     116: invokestatic  #64                 // Method valueAndClass:(Ljava/lang/Object;)Ljava/lang/String;
     119: invokevirtual #12                 // Method java/lang/StringBuilder.append:(Ljava/lang/String;)Ljava/lang/StringBuilder;
     122: ldc           #73                 // String ; Value at position
     124: invokevirtual #12                 // Method java/lang/StringBuilder.append:(Ljava/lang/String;)Ljava/lang/StringBuilder;
     127: iload_1
     128: invokevirtual #20                 // Method java/lang/StringBuilder.append:(I)Ljava/lang/StringBuilder;
     131: ldc           #74                 // String  differ
     133: invokevirtual #12                 // Method java/lang/StringBuilder.append:(Ljava/lang/String;)Ljava/lang/StringBuilder;
     136: invokevirtual #33                 // Method java/lang/StringBuilder.toString:()Ljava/lang/String;
     139: invokevirtual #44                 // Method fail:(Ljava/lang/String;)Ljava/lang/AssertionError;
     142: athrow
     143: aload_0
     144: areturn

  public final U assertValueAt(int, io.reactivex.rxjava3.functions.Predicate<T>);
    Code:
       0: aload_0
       1: getfield      #4                  // Field values:Ljava/util/List;
       4: invokeinterface #19,  1           // InterfaceMethod java/util/List.size:()I
       9: istore_3
      10: iload_3
      11: ifne          21
      14: aload_0
      15: ldc           #69                 // String No values
      17: invokevirtual #44                 // Method fail:(Ljava/lang/String;)Ljava/lang/AssertionError;
      20: athrow
      21: iload_1
      22: iflt          30
      25: iload_1
      26: iload_3
      27: if_icmplt     68
      30: aload_0
      31: new           #9                  // class java/lang/StringBuilder
      34: dup
      35: invokespecial #45                 // Method java/lang/StringBuilder."<init>":()V
      38: ldc           #70                 // String Index
      40: invokevirtual #12                 // Method java/lang/StringBuilder.append:(Ljava/lang/String;)Ljava/lang/StringBuilder;
      43: iload_1
      44: invokevirtual #20                 // Method java/lang/StringBuilder.append:(I)Ljava/lang/StringBuilder;
      47: ldc           #71                 // String  is out of range [0,
      49: invokevirtual #12                 // Method java/lang/StringBuilder.append:(Ljava/lang/String;)Ljava/lang/StringBuilder;
      52: iload_3
      53: invokevirtual #20                 // Method java/lang/StringBuilder.append:(I)Ljava/lang/StringBuilder;
      56: ldc           #72                 // String )
      58: invokevirtual #12                 // Method java/lang/StringBuilder.append:(Ljava/lang/String;)Ljava/lang/StringBuilder;
      61: invokevirtual #33                 // Method java/lang/StringBuilder.toString:()Ljava/lang/String;
      64: invokevirtual #44                 // Method fail:(Ljava/lang/String;)Ljava/lang/AssertionError;
      67: athrow
      68: iconst_0
      69: istore        4
      71: aload_0
      72: getfield      #4                  // Field values:Ljava/util/List;
      75: iload_1
      76: invokeinterface #36,  2           // InterfaceMethod java/util/List.get:(I)Ljava/lang/Object;
      81: astore        5
      83: aload_2
      84: aload         5
      86: invokeinterface #57,  2           // InterfaceMethod io/reactivex/rxjava3/functions/Predicate.test:(Ljava/lang/Object;)Z
      91: ifeq          97
      94: iconst_1
      95: istore        4
      97: goto          108
     100: astore        6
     102: aload         6
     104: invokestatic  #58                 // Method io/reactivex/rxjava3/internal/util/ExceptionHelper.wrapOrThrow:(Ljava/lang/Throwable;)Ljava/lang/RuntimeException;
     107: athrow
     108: iload         4
     110: ifne          155
     113: aload_0
     114: new           #9                  // class java/lang/StringBuilder
     117: dup
     118: invokespecial #45                 // Method java/lang/StringBuilder."<init>":()V
     121: ldc           #75                 // String Value
     123: invokevirtual #12                 // Method java/lang/StringBuilder.append:(Ljava/lang/String;)Ljava/lang/StringBuilder;
     126: aload         5
     128: invokestatic  #64                 // Method valueAndClass:(Ljava/lang/Object;)Ljava/lang/String;
     131: invokevirtual #12                 // Method java/lang/StringBuilder.append:(Ljava/lang/String;)Ljava/lang/StringBuilder;
     134: ldc           #76                 // String  at position
     136: invokevirtual #12                 // Method java/lang/StringBuilder.append:(Ljava/lang/String;)Ljava/lang/StringBuilder;
     139: iload_1
     140: invokevirtual #20                 // Method java/lang/StringBuilder.append:(I)Ljava/lang/StringBuilder;
     143: ldc           #77                 // String  did not pass the predicate
     145: invokevirtual #12                 // Method java/lang/StringBuilder.append:(Ljava/lang/String;)Ljava/lang/StringBuilder;
     148: invokevirtual #33                 // Method java/lang/StringBuilder.toString:()Ljava/lang/String;
     151: invokevirtual #44                 // Method fail:(Ljava/lang/String;)Ljava/lang/AssertionError;
     154: athrow
     155: aload_0
     156: areturn
    Exception table:
       from    to  target type
          83    97   100   Class java/lang/Throwable

  public static java.lang.String valueAndClass(java.lang.Object);
    Code:
       0: aload_0
       1: ifnull        39
       4: new           #9                  // class java/lang/StringBuilder
       7: dup
       8: invokespecial #45                 // Method java/lang/StringBuilder."<init>":()V
      11: aload_0
      12: invokevirtual #49                 // Method java/lang/StringBuilder.append:(Ljava/lang/Object;)Ljava/lang/StringBuilder;
      15: ldc           #78                 // String  (class:
      17: invokevirtual #12                 // Method java/lang/StringBuilder.append:(Ljava/lang/String;)Ljava/lang/StringBuilder;
      20: aload_0
      21: invokevirtual #79                 // Method java/lang/Object.getClass:()Ljava/lang/Class;
      24: invokevirtual #80                 // Method java/lang/Class.getSimpleName:()Ljava/lang/String;
      27: invokevirtual #12                 // Method java/lang/StringBuilder.append:(Ljava/lang/String;)Ljava/lang/StringBuilder;
      30: ldc           #72                 // String )
      32: invokevirtual #12                 // Method java/lang/StringBuilder.append:(Ljava/lang/String;)Ljava/lang/StringBuilder;
      35: invokevirtual #33                 // Method java/lang/StringBuilder.toString:()Ljava/lang/String;
      38: areturn
      39: ldc           #81                 // String null
      41: areturn

  public final U assertValueCount(int);
    Code:
       0: aload_0
       1: getfield      #4                  // Field values:Ljava/util/List;
       4: invokeinterface #19,  1           // InterfaceMethod java/util/List.size:()I
       9: istore_2
      10: iload_2
      11: iload_1
      12: if_icmpeq     53
      15: aload_0
      16: new           #9                  // class java/lang/StringBuilder
      19: dup
      20: invokespecial #45                 // Method java/lang/StringBuilder."<init>":()V
      23: ldc           #63                 // String \nexpected:
      25: invokevirtual #12                 // Method java/lang/StringBuilder.append:(Ljava/lang/String;)Ljava/lang/StringBuilder;
      28: iload_1
      29: invokevirtual #20                 // Method java/lang/StringBuilder.append:(I)Ljava/lang/StringBuilder;
      32: ldc           #65                 // String \ngot:
      34: invokevirtual #12                 // Method java/lang/StringBuilder.append:(Ljava/lang/String;)Ljava/lang/StringBuilder;
      37: iload_2
      38: invokevirtual #20                 // Method java/lang/StringBuilder.append:(I)Ljava/lang/StringBuilder;
      41: ldc           #82                 // String ; Value counts differ
      43: invokevirtual #12                 // Method java/lang/StringBuilder.append:(Ljava/lang/String;)Ljava/lang/StringBuilder;
      46: invokevirtual #33                 // Method java/lang/StringBuilder.toString:()Ljava/lang/String;
      49: invokevirtual #44                 // Method fail:(Ljava/lang/String;)Ljava/lang/AssertionError;
      52: athrow
      53: aload_0
      54: areturn

  public final U assertNoValues();
    Code:
       0: aload_0
       1: iconst_0
       2: invokevirtual #83                 // Method assertValueCount:(I)Lio/reactivex/rxjava3/observers/BaseTestConsumer;
       5: areturn

  public final U assertValues(T...);
    Code:
       0: aload_0
       1: getfield      #4                  // Field values:Ljava/util/List;
       4: invokeinterface #19,  1           // InterfaceMethod java/util/List.size:()I
       9: istore_2
      10: iload_2
      11: aload_1
      12: arraylength
      13: if_icmpeq     79
      16: aload_0
      17: new           #9                  // class java/lang/StringBuilder
      20: dup
      21: invokespecial #45                 // Method java/lang/StringBuilder."<init>":()V
      24: ldc           #63                 // String \nexpected:
      26: invokevirtual #12                 // Method java/lang/StringBuilder.append:(Ljava/lang/String;)Ljava/lang/StringBuilder;
      29: aload_1
      30: arraylength
      31: invokevirtual #20                 // Method java/lang/StringBuilder.append:(I)Ljava/lang/StringBuilder;
      34: ldc           #84                 // String
      36: invokevirtual #12                 // Method java/lang/StringBuilder.append:(Ljava/lang/String;)Ljava/lang/StringBuilder;
      39: aload_1
      40: invokestatic  #85                 // Method java/util/Arrays.toString:([Ljava/lang/Object;)Ljava/lang/String;
      43: invokevirtual #12                 // Method java/lang/StringBuilder.append:(Ljava/lang/String;)Ljava/lang/StringBuilder;
      46: ldc           #65                 // String \ngot:
      48: invokevirtual #12                 // Method java/lang/StringBuilder.append:(Ljava/lang/String;)Ljava/lang/StringBuilder;
      51: iload_2
      52: invokevirtual #20                 // Method java/lang/StringBuilder.append:(I)Ljava/lang/StringBuilder;
      55: ldc           #84                 // String
      57: invokevirtual #12                 // Method java/lang/StringBuilder.append:(Ljava/lang/String;)Ljava/lang/StringBuilder;
      60: aload_0
      61: getfield      #4                  // Field values:Ljava/util/List;
      64: invokevirtual #49                 // Method java/lang/StringBuilder.append:(Ljava/lang/Object;)Ljava/lang/StringBuilder;
      67: ldc           #86                 // String ; Value count differs
      69: invokevirtual #12                 // Method java/lang/StringBuilder.append:(Ljava/lang/String;)Ljava/lang/StringBuilder;
      72: invokevirtual #33                 // Method java/lang/StringBuilder.toString:()Ljava/lang/String;
      75: invokevirtual #44                 // Method fail:(Ljava/lang/String;)Ljava/lang/AssertionError;
      78: athrow
      79: iconst_0
      80: istore_3
      81: iload_3
      82: iload_2
      83: if_icmpge     174
      86: aload_0
      87: getfield      #4                  // Field values:Ljava/util/List;
      90: iload_3
      91: invokeinterface #36,  2           // InterfaceMethod java/util/List.get:(I)Ljava/lang/Object;
      96: astore        4
      98: aload_1
      99: iload_3
     100: aaload
     101: astore        5
     103: aload         5
     105: aload         4
     107: invokestatic  #66                 // Method java/util/Objects.equals:(Ljava/lang/Object;Ljava/lang/Object;)Z
     110: ifne          168
     113: aload_0
     114: new           #9                  // class java/lang/StringBuilder
     117: dup
     118: invokespecial #45                 // Method java/lang/StringBuilder."<init>":()V
     121: ldc           #63                 // String \nexpected:
     123: invokevirtual #12                 // Method java/lang/StringBuilder.append:(Ljava/lang/String;)Ljava/lang/StringBuilder;
     126: aload         5
     128: invokestatic  #64                 // Method valueAndClass:(Ljava/lang/Object;)Ljava/lang/String;
     131: invokevirtual #12                 // Method java/lang/StringBuilder.append:(Ljava/lang/String;)Ljava/lang/StringBuilder;
     134: ldc           #65                 // String \ngot:
     136: invokevirtual #12                 // Method java/lang/StringBuilder.append:(Ljava/lang/String;)Ljava/lang/StringBuilder;
     139: aload         4
     141: invokestatic  #64                 // Method valueAndClass:(Ljava/lang/Object;)Ljava/lang/String;
     144: invokevirtual #12                 // Method java/lang/StringBuilder.append:(Ljava/lang/String;)Ljava/lang/StringBuilder;
     147: ldc           #73                 // String ; Value at position
     149: invokevirtual #12                 // Method java/lang/StringBuilder.append:(Ljava/lang/String;)Ljava/lang/StringBuilder;
     152: iload_3
     153: invokevirtual #20                 // Method java/lang/StringBuilder.append:(I)Ljava/lang/StringBuilder;
     156: ldc           #74                 // String  differ
     158: invokevirtual #12                 // Method java/lang/StringBuilder.append:(Ljava/lang/String;)Ljava/lang/StringBuilder;
     161: invokevirtual #33                 // Method java/lang/StringBuilder.toString:()Ljava/lang/String;
     164: invokevirtual #44                 // Method fail:(Ljava/lang/String;)Ljava/lang/AssertionError;
     167: athrow
     168: iinc          3, 1
     171: goto          81
     174: aload_0
     175: areturn

  public final U assertValuesOnly(T...);
    Code:
       0: aload_0
       1: invokevirtual #87                 // Method assertSubscribed:()Lio/reactivex/rxjava3/observers/BaseTestConsumer;
       4: aload_1
       5: invokevirtual #88                 // Method assertValues:([Ljava/lang/Object;)Lio/reactivex/rxjava3/observers/BaseTestConsumer;
       8: invokevirtual #89                 // Method assertNoErrors:()Lio/reactivex/rxjava3/observers/BaseTestConsumer;
      11: invokevirtual #90                 // Method assertNotComplete:()Lio/reactivex/rxjava3/observers/BaseTestConsumer;
      14: areturn

  public final U assertValueSequence(java.lang.Iterable<? extends T>);
    Code:
       0: iconst_0
       1: istore_2
       2: aload_0
       3: getfield      #4                  // Field values:Ljava/util/List;
       6: invokeinterface #54,  1           // InterfaceMethod java/util/List.iterator:()Ljava/util/Iterator;
      11: astore_3
      12: aload_1
      13: invokeinterface #91,  1           // InterfaceMethod java/lang/Iterable.iterator:()Ljava/util/Iterator;
      18: astore        4
      20: aload         4
      22: invokeinterface #55,  1           // InterfaceMethod java/util/Iterator.hasNext:()Z
      27: istore        6
      29: aload_3
      30: invokeinterface #55,  1           // InterfaceMethod java/util/Iterator.hasNext:()Z
      35: istore        5
      37: iload         5
      39: ifeq          138
      42: iload         6
      44: ifne          50
      47: goto          138
      50: aload         4
      52: invokeinterface #56,  1           // InterfaceMethod java/util/Iterator.next:()Ljava/lang/Object;
      57: astore        7
      59: aload_3
      60: invokeinterface #56,  1           // InterfaceMethod java/util/Iterator.next:()Ljava/lang/Object;
      65: astore        8
      67: aload         7
      69: aload         8
      71: invokestatic  #66                 // Method java/util/Objects.equals:(Ljava/lang/Object;Ljava/lang/Object;)Z
      74: ifne          132
      77: aload_0
      78: new           #9                  // class java/lang/StringBuilder
      81: dup
      82: invokespecial #45                 // Method java/lang/StringBuilder."<init>":()V
      85: ldc           #63                 // String \nexpected:
      87: invokevirtual #12                 // Method java/lang/StringBuilder.append:(Ljava/lang/String;)Ljava/lang/StringBuilder;
      90: aload         7
      92: invokestatic  #64                 // Method valueAndClass:(Ljava/lang/Object;)Ljava/lang/String;
      95: invokevirtual #12                 // Method java/lang/StringBuilder.append:(Ljava/lang/String;)Ljava/lang/StringBuilder;
      98: ldc           #65                 // String \ngot:
     100: invokevirtual #12                 // Method java/lang/StringBuilder.append:(Ljava/lang/String;)Ljava/lang/StringBuilder;
     103: aload         8
     105: invokestatic  #64                 // Method valueAndClass:(Ljava/lang/Object;)Ljava/lang/String;
     108: invokevirtual #12                 // Method java/lang/StringBuilder.append:(Ljava/lang/String;)Ljava/lang/StringBuilder;
     111: ldc           #73                 // String ; Value at position
     113: invokevirtual #12                 // Method java/lang/StringBuilder.append:(Ljava/lang/String;)Ljava/lang/StringBuilder;
     116: iload_2
     117: invokevirtual #20                 // Method java/lang/StringBuilder.append:(I)Ljava/lang/StringBuilder;
     120: ldc           #74                 // String  differ
     122: invokevirtual #12                 // Method java/lang/StringBuilder.append:(Ljava/lang/String;)Ljava/lang/StringBuilder;
     125: invokevirtual #33                 // Method java/lang/StringBuilder.toString:()Ljava/lang/String;
     128: invokevirtual #44                 // Method fail:(Ljava/lang/String;)Ljava/lang/AssertionError;
     131: athrow
     132: iinc          2, 1
     135: goto          20
     138: iload         5
     140: ifeq          172
     143: aload_0
     144: new           #9                  // class java/lang/StringBuilder
     147: dup
     148: invokespecial #45                 // Method java/lang/StringBuilder."<init>":()V
     151: ldc           #92                 // String More values received than expected (
     153: invokevirtual #12                 // Method java/lang/StringBuilder.append:(Ljava/lang/String;)Ljava/lang/StringBuilder;
     156: iload_2
     157: invokevirtual #20                 // Method java/lang/StringBuilder.append:(I)Ljava/lang/StringBuilder;
     160: ldc           #72                 // String )
     162: invokevirtual #12                 // Method java/lang/StringBuilder.append:(Ljava/lang/String;)Ljava/lang/StringBuilder;
     165: invokevirtual #33                 // Method java/lang/StringBuilder.toString:()Ljava/lang/String;
     168: invokevirtual #44                 // Method fail:(Ljava/lang/String;)Ljava/lang/AssertionError;
     171: athrow
     172: iload         6
     174: ifeq          206
     177: aload_0
     178: new           #9                  // class java/lang/StringBuilder
     181: dup
     182: invokespecial #45                 // Method java/lang/StringBuilder."<init>":()V
     185: ldc           #93                 // String Fewer values received than expected (
     187: invokevirtual #12                 // Method java/lang/StringBuilder.append:(Ljava/lang/String;)Ljava/lang/StringBuilder;
     190: iload_2
     191: invokevirtual #20                 // Method java/lang/StringBuilder.append:(I)Ljava/lang/StringBuilder;
     194: ldc           #72                 // String )
     196: invokevirtual #12                 // Method java/lang/StringBuilder.append:(Ljava/lang/String;)Ljava/lang/StringBuilder;
     199: invokevirtual #33                 // Method java/lang/StringBuilder.toString:()Ljava/lang/String;
     202: invokevirtual #44                 // Method fail:(Ljava/lang/String;)Ljava/lang/AssertionError;
     205: athrow
     206: aload_0
     207: areturn

  protected abstract U assertSubscribed();

  public final U assertResult(T...);
    Code:
       0: aload_0
       1: invokevirtual #87                 // Method assertSubscribed:()Lio/reactivex/rxjava3/observers/BaseTestConsumer;
       4: aload_1
       5: invokevirtual #88                 // Method assertValues:([Ljava/lang/Object;)Lio/reactivex/rxjava3/observers/BaseTestConsumer;
       8: invokevirtual #89                 // Method assertNoErrors:()Lio/reactivex/rxjava3/observers/BaseTestConsumer;
      11: invokevirtual #94                 // Method assertComplete:()Lio/reactivex/rxjava3/observers/BaseTestConsumer;
      14: areturn

  public final U assertFailure(java.lang.Class<? extends java.lang.Throwable>, T...);
    Code:
       0: aload_0
       1: invokevirtual #87                 // Method assertSubscribed:()Lio/reactivex/rxjava3/observers/BaseTestConsumer;
       4: aload_2
       5: invokevirtual #88                 // Method assertValues:([Ljava/lang/Object;)Lio/reactivex/rxjava3/observers/BaseTestConsumer;
       8: aload_1
       9: invokevirtual #95                 // Method assertError:(Ljava/lang/Class;)Lio/reactivex/rxjava3/observers/BaseTestConsumer;
      12: invokevirtual #90                 // Method assertNotComplete:()Lio/reactivex/rxjava3/observers/BaseTestConsumer;
      15: areturn

  public final U awaitDone(long, java.util.concurrent.TimeUnit);
    Code:
       0: aload_0
       1: getfield      #8                  // Field done:Ljava/util/concurrent/CountDownLatch;
       4: lload_1
       5: aload_3
       6: invokevirtual #42                 // Method java/util/concurrent/CountDownLatch.await:(JLjava/util/concurrent/TimeUnit;)Z
       9: ifne          21
      12: aload_0
      13: iconst_1
      14: putfield      #24                 // Field timeout:Z
      17: aload_0
      18: invokevirtual #96                 // Method dispose:()V
      21: goto          36
      24: astore        4
      26: aload_0
      27: invokevirtual #96                 // Method dispose:()V
      30: aload         4
      32: invokestatic  #58                 // Method io/reactivex/rxjava3/internal/util/ExceptionHelper.wrapOrThrow:(Ljava/lang/Throwable;)Ljava/lang/RuntimeException;
      35: athrow
      36: aload_0
      37: areturn
    Exception table:
       from    to  target type
           0    21    24   Class java/lang/InterruptedException

  public final U assertEmpty();
    Code:
       0: aload_0
       1: invokevirtual #87                 // Method assertSubscribed:()Lio/reactivex/rxjava3/observers/BaseTestConsumer;
       4: invokevirtual #98                 // Method assertNoValues:()Lio/reactivex/rxjava3/observers/BaseTestConsumer;
       7: invokevirtual #89                 // Method assertNoErrors:()Lio/reactivex/rxjava3/observers/BaseTestConsumer;
      10: invokevirtual #90                 // Method assertNotComplete:()Lio/reactivex/rxjava3/observers/BaseTestConsumer;
      13: areturn

  public final U withTag(java.lang.CharSequence);
    Code:
       0: aload_0
       1: aload_1
       2: putfield      #28                 // Field tag:Ljava/lang/CharSequence;
       5: aload_0
       6: areturn

  public final U awaitCount(int);
    Code:
       0: invokestatic  #99                 // Method java/lang/System.currentTimeMillis:()J
       3: lstore_2
       4: ldc2_w        #100                // long 5000l
       7: lstore        4
       9: invokestatic  #99                 // Method java/lang/System.currentTimeMillis:()J
      12: lload_2
      13: lsub
      14: lload         4
      16: lcmp
      17: iflt          28
      20: aload_0
      21: iconst_1
      22: putfield      #24                 // Field timeout:Z
      25: goto          80
      28: aload_0
      29: getfield      #8                  // Field done:Ljava/util/concurrent/CountDownLatch;
      32: invokevirtual #15                 // Method java/util/concurrent/CountDownLatch.getCount:()J
      35: lconst_0
      36: lcmp
      37: ifne          43
      40: goto          80
      43: aload_0
      44: getfield      #4                  // Field values:Ljava/util/List;
      47: invokeinterface #19,  1           // InterfaceMethod java/util/List.size:()I
      52: iload_1
      53: if_icmplt     59
      56: goto          80
      59: ldc2_w        #102                // long 10l
      62: invokestatic  #104                // Method java/lang/Thread.sleep:(J)V
      65: goto          9
      68: astore        6
      70: new           #105                // class java/lang/RuntimeException
      73: dup
      74: aload         6
      76: invokespecial #106                // Method java/lang/RuntimeException."<init>":(Ljava/lang/Throwable;)V
      79: athrow
      80: aload_0
      81: areturn
    Exception table:
       from    to  target type
          59    65    68   Class java/lang/InterruptedException

  protected abstract boolean isDisposed();

  protected abstract void dispose();
}
