Compiled from "DefaultObserver.java"
public abstract class io.reactivex.rxjava3.observers.DefaultObserver<T> implements io.reactivex.rxjava3.core.Observer<T> {
  private io.reactivex.rxjava3.disposables.Disposable upstream;

  public io.reactivex.rxjava3.observers.DefaultObserver();
    Code:
       0: aload_0
       1: invokespecial #1                  // Method java/lang/Object."<init>":()V
       4: return

  public final void onSubscribe(io.reactivex.rxjava3.disposables.Disposable);
    Code:
       0: aload_0
       1: getfield      #2                  // Field upstream:Lio/reactivex/rxjava3/disposables/Disposable;
       4: aload_1
       5: aload_0
       6: invokevirtual #3                  // Method java/lang/Object.getClass:()Ljava/lang/Class;
       9: invokestatic  #4                  // Method io/reactivex/rxjava3/internal/util/EndConsumerHelper.validate:(Lio/reactivex/rxjava3/disposables/Disposable;Lio/reactivex/rxjava3/disposables/Disposable;Ljava/lang/Class;)Z
      12: ifeq          24
      15: aload_0
      16: aload_1
      17: putfield      #2                  // Field upstream:Lio/reactivex/rxjava3/disposables/Disposable;
      20: aload_0
      21: invokevirtual #5                  // Method onStart:()V
      24: return

  protected final void cancel();
    Code:
       0: aload_0
       1: getfield      #2                  // Field upstream:Lio/reactivex/rxjava3/disposables/Disposable;
       4: astore_1
       5: aload_0
       6: getstatic     #6                  // Field io/reactivex/rxjava3/internal/disposables/DisposableHelper.DISPOSED:Lio/reactivex/rxjava3/internal/disposables/DisposableHelper;
       9: putfield      #2                  // Field upstream:Lio/reactivex/rxjava3/disposables/Disposable;
      12: aload_1
      13: invokeinterface #7,  1            // InterfaceMethod io/reactivex/rxjava3/disposables/Disposable.dispose:()V
      18: return

  protected void onStart();
    Code:
       0: return
}
