Compiled from "ResourceCompletableObserver.java"
public abstract class io.reactivex.rxjava3.observers.ResourceCompletableObserver implements io.reactivex.rxjava3.core.CompletableObserver,io.reactivex.rxjava3.disposables.Disposable {
  private final java.util.concurrent.atomic.AtomicReference<io.reactivex.rxjava3.disposables.Disposable> upstream;

  private final io.reactivex.rxjava3.internal.disposables.ListCompositeDisposable resources;

  public io.reactivex.rxjava3.observers.ResourceCompletableObserver();
    Code:
       0: aload_0
       1: invokespecial #1                  // Method java/lang/Object."<init>":()V
       4: aload_0
       5: new           #2                  // class java/util/concurrent/atomic/AtomicReference
       8: dup
       9: invokespecial #3                  // Method java/util/concurrent/atomic/AtomicReference."<init>":()V
      12: putfield      #4                  // Field upstream:Ljava/util/concurrent/atomic/AtomicReference;
      15: aload_0
      16: new           #5                  // class io/reactivex/rxjava3/internal/disposables/ListCompositeDisposable
      19: dup
      20: invokespecial #6                  // Method io/reactivex/rxjava3/internal/disposables/ListCompositeDisposable."<init>":()V
      23: putfield      #7                  // Field resources:Lio/reactivex/rxjava3/internal/disposables/ListCompositeDisposable;
      26: return

  public final void add(io.reactivex.rxjava3.disposables.Disposable);
    Code:
       0: aload_1
       1: ldc           #8                  // String resource is null
       3: invokestatic  #9                  // Method java/util/Objects.requireNonNull:(Ljava/lang/Object;Ljava/lang/String;)Ljava/lang/Object;
       6: pop
       7: aload_0
       8: getfield      #7                  // Field resources:Lio/reactivex/rxjava3/internal/disposables/ListCompositeDisposable;
      11: aload_1
      12: invokevirtual #10                 // Method io/reactivex/rxjava3/internal/disposables/ListCompositeDisposable.add:(Lio/reactivex/rxjava3/disposables/Disposable;)Z
      15: pop
      16: return

  public final void onSubscribe(io.reactivex.rxjava3.disposables.Disposable);
    Code:
       0: aload_0
       1: getfield      #4                  // Field upstream:Ljava/util/concurrent/atomic/AtomicReference;
       4: aload_1
       5: aload_0
       6: invokevirtual #11                 // Method java/lang/Object.getClass:()Ljava/lang/Class;
       9: invokestatic  #12                 // Method io/reactivex/rxjava3/internal/util/EndConsumerHelper.setOnce:(Ljava/util/concurrent/atomic/AtomicReference;Lio/reactivex/rxjava3/disposables/Disposable;Ljava/lang/Class;)Z
      12: ifeq          19
      15: aload_0
      16: invokevirtual #13                 // Method onStart:()V
      19: return

  protected void onStart();
    Code:
       0: return

  public final void dispose();
    Code:
       0: aload_0
       1: getfield      #4                  // Field upstream:Ljava/util/concurrent/atomic/AtomicReference;
       4: invokestatic  #14                 // Method io/reactivex/rxjava3/internal/disposables/DisposableHelper.dispose:(Ljava/util/concurrent/atomic/AtomicReference;)Z
       7: ifeq          17
      10: aload_0
      11: getfield      #7                  // Field resources:Lio/reactivex/rxjava3/internal/disposables/ListCompositeDisposable;
      14: invokevirtual #15                 // Method io/reactivex/rxjava3/internal/disposables/ListCompositeDisposable.dispose:()V
      17: return

  public final boolean isDisposed();
    Code:
       0: aload_0
       1: getfield      #4                  // Field upstream:Ljava/util/concurrent/atomic/AtomicReference;
       4: invokevirtual #16                 // Method java/util/concurrent/atomic/AtomicReference.get:()Ljava/lang/Object;
       7: checkcast     #17                 // class io/reactivex/rxjava3/disposables/Disposable
      10: invokestatic  #18                 // Method io/reactivex/rxjava3/internal/disposables/DisposableHelper.isDisposed:(Lio/reactivex/rxjava3/disposables/Disposable;)Z
      13: ireturn
}
