Compiled from "SerializedObserver.java"
public final class io.reactivex.rxjava3.observers.SerializedObserver<T> implements io.reactivex.rxjava3.core.Observer<T>, io.reactivex.rxjava3.disposables.Disposable {
  final io.reactivex.rxjava3.core.Observer<? super T> downstream;

  final boolean delayError;

  static final int QUEUE_LINK_SIZE;

  io.reactivex.rxjava3.disposables.Disposable upstream;

  boolean emitting;

  io.reactivex.rxjava3.internal.util.AppendOnlyLinkedArrayList<java.lang.Object> queue;

  volatile boolean done;

  public io.reactivex.rxjava3.observers.SerializedObserver(io.reactivex.rxjava3.core.Observer<? super T>);
    Code:
       0: aload_0
       1: aload_1
       2: iconst_0
       3: invokespecial #1                  // Method "<init>":(Lio/reactivex/rxjava3/core/Observer;Z)V
       6: return

  public io.reactivex.rxjava3.observers.SerializedObserver(io.reactivex.rxjava3.core.Observer<? super T>, boolean);
    Code:
       0: aload_0
       1: invokespecial #2                  // Method java/lang/Object."<init>":()V
       4: aload_0
       5: aload_1
       6: putfield      #3                  // Field downstream:Lio/reactivex/rxjava3/core/Observer;
       9: aload_0
      10: iload_2
      11: putfield      #4                  // Field delayError:Z
      14: return

  public void onSubscribe(io.reactivex.rxjava3.disposables.Disposable);
    Code:
       0: aload_0
       1: getfield      #5                  // Field upstream:Lio/reactivex/rxjava3/disposables/Disposable;
       4: aload_1
       5: invokestatic  #6                  // Method io/reactivex/rxjava3/internal/disposables/DisposableHelper.validate:(Lio/reactivex/rxjava3/disposables/Disposable;Lio/reactivex/rxjava3/disposables/Disposable;)Z
       8: ifeq          26
      11: aload_0
      12: aload_1
      13: putfield      #5                  // Field upstream:Lio/reactivex/rxjava3/disposables/Disposable;
      16: aload_0
      17: getfield      #3                  // Field downstream:Lio/reactivex/rxjava3/core/Observer;
      20: aload_0
      21: invokeinterface #7,  2            // InterfaceMethod io/reactivex/rxjava3/core/Observer.onSubscribe:(Lio/reactivex/rxjava3/disposables/Disposable;)V
      26: return

  public void dispose();
    Code:
       0: aload_0
       1: iconst_1
       2: putfield      #8                  // Field done:Z
       5: aload_0
       6: getfield      #5                  // Field upstream:Lio/reactivex/rxjava3/disposables/Disposable;
       9: invokeinterface #9,  1            // InterfaceMethod io/reactivex/rxjava3/disposables/Disposable.dispose:()V
      14: return

  public boolean isDisposed();
    Code:
       0: aload_0
       1: getfield      #5                  // Field upstream:Lio/reactivex/rxjava3/disposables/Disposable;
       4: invokeinterface #10,  1           // InterfaceMethod io/reactivex/rxjava3/disposables/Disposable.isDisposed:()Z
       9: ireturn

  public void onNext(T);
    Code:
       0: aload_0
       1: getfield      #8                  // Field done:Z
       4: ifeq          8
       7: return
       8: aload_1
       9: ifnonnull     31
      12: aload_0
      13: getfield      #5                  // Field upstream:Lio/reactivex/rxjava3/disposables/Disposable;
      16: invokeinterface #9,  1            // InterfaceMethod io/reactivex/rxjava3/disposables/Disposable.dispose:()V
      21: aload_0
      22: ldc           #11                 // String onNext called with a null value.
      24: invokestatic  #12                 // Method io/reactivex/rxjava3/internal/util/ExceptionHelper.createNullPointerException:(Ljava/lang/String;)Ljava/lang/NullPointerException;
      27: invokevirtual #13                 // Method onError:(Ljava/lang/Throwable;)V
      30: return
      31: aload_0
      32: dup
      33: astore_2
      34: monitorenter
      35: aload_0
      36: getfield      #8                  // Field done:Z
      39: ifeq          45
      42: aload_2
      43: monitorexit
      44: return
      45: aload_0
      46: getfield      #14                 // Field emitting:Z
      49: ifeq          86
      52: aload_0
      53: getfield      #15                 // Field queue:Lio/reactivex/rxjava3/internal/util/AppendOnlyLinkedArrayList;
      56: astore_3
      57: aload_3
      58: ifnonnull     75
      61: new           #16                 // class io/reactivex/rxjava3/internal/util/AppendOnlyLinkedArrayList
      64: dup
      65: iconst_4
      66: invokespecial #18                 // Method io/reactivex/rxjava3/internal/util/AppendOnlyLinkedArrayList."<init>":(I)V
      69: astore_3
      70: aload_0
      71: aload_3
      72: putfield      #15                 // Field queue:Lio/reactivex/rxjava3/internal/util/AppendOnlyLinkedArrayList;
      75: aload_3
      76: aload_1
      77: invokestatic  #19                 // Method io/reactivex/rxjava3/internal/util/NotificationLite.next:(Ljava/lang/Object;)Ljava/lang/Object;
      80: invokevirtual #20                 // Method io/reactivex/rxjava3/internal/util/AppendOnlyLinkedArrayList.add:(Ljava/lang/Object;)V
      83: aload_2
      84: monitorexit
      85: return
      86: aload_0
      87: iconst_1
      88: putfield      #14                 // Field emitting:Z
      91: aload_2
      92: monitorexit
      93: goto          103
      96: astore        4
      98: aload_2
      99: monitorexit
     100: aload         4
     102: athrow
     103: aload_0
     104: getfield      #3                  // Field downstream:Lio/reactivex/rxjava3/core/Observer;
     107: aload_1
     108: invokeinterface #21,  2           // InterfaceMethod io/reactivex/rxjava3/core/Observer.onNext:(Ljava/lang/Object;)V
     113: aload_0
     114: invokevirtual #22                 // Method emitLoop:()V
     117: return
    Exception table:
       from    to  target type
          35    44    96   any
          45    85    96   any
          86    93    96   any
          96   100    96   any

  public void onError(java.lang.Throwable);
    Code:
       0: aload_0
       1: getfield      #8                  // Field done:Z
       4: ifeq          12
       7: aload_1
       8: invokestatic  #23                 // Method io/reactivex/rxjava3/plugins/RxJavaPlugins.onError:(Ljava/lang/Throwable;)V
      11: return
      12: aload_0
      13: dup
      14: astore_3
      15: monitorenter
      16: aload_0
      17: getfield      #8                  // Field done:Z
      20: ifeq          28
      23: iconst_1
      24: istore_2
      25: goto          112
      28: aload_0
      29: getfield      #14                 // Field emitting:Z
      32: ifeq          100
      35: aload_0
      36: iconst_1
      37: putfield      #8                  // Field done:Z
      40: aload_0
      41: getfield      #15                 // Field queue:Lio/reactivex/rxjava3/internal/util/AppendOnlyLinkedArrayList;
      44: astore        4
      46: aload         4
      48: ifnonnull     67
      51: new           #16                 // class io/reactivex/rxjava3/internal/util/AppendOnlyLinkedArrayList
      54: dup
      55: iconst_4
      56: invokespecial #18                 // Method io/reactivex/rxjava3/internal/util/AppendOnlyLinkedArrayList."<init>":(I)V
      59: astore        4
      61: aload_0
      62: aload         4
      64: putfield      #15                 // Field queue:Lio/reactivex/rxjava3/internal/util/AppendOnlyLinkedArrayList;
      67: aload_1
      68: invokestatic  #24                 // Method io/reactivex/rxjava3/internal/util/NotificationLite.error:(Ljava/lang/Throwable;)Ljava/lang/Object;
      71: astore        5
      73: aload_0
      74: getfield      #4                  // Field delayError:Z
      77: ifeq          90
      80: aload         4
      82: aload         5
      84: invokevirtual #20                 // Method io/reactivex/rxjava3/internal/util/AppendOnlyLinkedArrayList.add:(Ljava/lang/Object;)V
      87: goto          97
      90: aload         4
      92: aload         5
      94: invokevirtual #25                 // Method io/reactivex/rxjava3/internal/util/AppendOnlyLinkedArrayList.setFirst:(Ljava/lang/Object;)V
      97: aload_3
      98: monitorexit
      99: return
     100: aload_0
     101: iconst_1
     102: putfield      #8                  // Field done:Z
     105: aload_0
     106: iconst_1
     107: putfield      #14                 // Field emitting:Z
     110: iconst_0
     111: istore_2
     112: aload_3
     113: monitorexit
     114: goto          124
     117: astore        6
     119: aload_3
     120: monitorexit
     121: aload         6
     123: athrow
     124: iload_2
     125: ifeq          133
     128: aload_1
     129: invokestatic  #23                 // Method io/reactivex/rxjava3/plugins/RxJavaPlugins.onError:(Ljava/lang/Throwable;)V
     132: return
     133: aload_0
     134: getfield      #3                  // Field downstream:Lio/reactivex/rxjava3/core/Observer;
     137: aload_1
     138: invokeinterface #26,  2           // InterfaceMethod io/reactivex/rxjava3/core/Observer.onError:(Ljava/lang/Throwable;)V
     143: return
    Exception table:
       from    to  target type
          16    99   117   any
         100   114   117   any
         117   121   117   any

  public void onComplete();
    Code:
       0: aload_0
       1: getfield      #8                  // Field done:Z
       4: ifeq          8
       7: return
       8: aload_0
       9: dup
      10: astore_1
      11: monitorenter
      12: aload_0
      13: getfield      #8                  // Field done:Z
      16: ifeq          22
      19: aload_1
      20: monitorexit
      21: return
      22: aload_0
      23: getfield      #14                 // Field emitting:Z
      26: ifeq          62
      29: aload_0
      30: getfield      #15                 // Field queue:Lio/reactivex/rxjava3/internal/util/AppendOnlyLinkedArrayList;
      33: astore_2
      34: aload_2
      35: ifnonnull     52
      38: new           #16                 // class io/reactivex/rxjava3/internal/util/AppendOnlyLinkedArrayList
      41: dup
      42: iconst_4
      43: invokespecial #18                 // Method io/reactivex/rxjava3/internal/util/AppendOnlyLinkedArrayList."<init>":(I)V
      46: astore_2
      47: aload_0
      48: aload_2
      49: putfield      #15                 // Field queue:Lio/reactivex/rxjava3/internal/util/AppendOnlyLinkedArrayList;
      52: aload_2
      53: invokestatic  #27                 // Method io/reactivex/rxjava3/internal/util/NotificationLite.complete:()Ljava/lang/Object;
      56: invokevirtual #20                 // Method io/reactivex/rxjava3/internal/util/AppendOnlyLinkedArrayList.add:(Ljava/lang/Object;)V
      59: aload_1
      60: monitorexit
      61: return
      62: aload_0
      63: iconst_1
      64: putfield      #8                  // Field done:Z
      67: aload_0
      68: iconst_1
      69: putfield      #14                 // Field emitting:Z
      72: aload_1
      73: monitorexit
      74: goto          82
      77: astore_3
      78: aload_1
      79: monitorexit
      80: aload_3
      81: athrow
      82: aload_0
      83: getfield      #3                  // Field downstream:Lio/reactivex/rxjava3/core/Observer;
      86: invokeinterface #28,  1           // InterfaceMethod io/reactivex/rxjava3/core/Observer.onComplete:()V
      91: return
    Exception table:
       from    to  target type
          12    21    77   any
          22    61    77   any
          62    74    77   any
          77    80    77   any

  void emitLoop();
    Code:
       0: aload_0
       1: dup
       2: astore_2
       3: monitorenter
       4: aload_0
       5: getfield      #15                 // Field queue:Lio/reactivex/rxjava3/internal/util/AppendOnlyLinkedArrayList;
       8: astore_1
       9: aload_1
      10: ifnonnull     21
      13: aload_0
      14: iconst_0
      15: putfield      #14                 // Field emitting:Z
      18: aload_2
      19: monitorexit
      20: return
      21: aload_0
      22: aconst_null
      23: putfield      #15                 // Field queue:Lio/reactivex/rxjava3/internal/util/AppendOnlyLinkedArrayList;
      26: aload_2
      27: monitorexit
      28: goto          36
      31: astore_3
      32: aload_2
      33: monitorexit
      34: aload_3
      35: athrow
      36: aload_1
      37: aload_0
      38: getfield      #3                  // Field downstream:Lio/reactivex/rxjava3/core/Observer;
      41: invokevirtual #29                 // Method io/reactivex/rxjava3/internal/util/AppendOnlyLinkedArrayList.accept:(Lio/reactivex/rxjava3/core/Observer;)Z
      44: ifeq          48
      47: return
      48: goto          0
    Exception table:
       from    to  target type
           4    20    31   any
          21    28    31   any
          31    34    31   any
}
