Compiled from "AbstractDubboConfigBinder.java"
public abstract class org.apache.dubbo.config.spring.context.properties.AbstractDubboConfigBinder implements org.apache.dubbo.config.spring.context.properties.DubboConfigBinder {
  private java.lang.Iterable<org.springframework.core.env.PropertySource<?>> propertySources;

  private boolean ignoreUnknownFields;

  private boolean ignoreInvalidFields;

  public org.apache.dubbo.config.spring.context.properties.AbstractDubboConfigBinder();
    Code:
       0: aload_0
       1: invokespecial #1                  // Method java/lang/Object."<init>":()V
       4: aload_0
       5: iconst_1
       6: putfield      #2                  // Field ignoreUnknownFields:Z
       9: aload_0
      10: iconst_0
      11: putfield      #3                  // Field ignoreInvalidFields:Z
      14: return

  protected java.lang.Iterable<org.springframework.core.env.PropertySource<?>> getPropertySources();
    Code:
       0: aload_0
       1: getfield      #4                  // Field propertySources:Ljava/lang/Iterable;
       4: areturn

  public boolean isIgnoreUnknownFields();
    Code:
       0: aload_0
       1: getfield      #2                  // Field ignoreUnknownFields:Z
       4: ireturn

  public void setIgnoreUnknownFields(boolean);
    Code:
       0: aload_0
       1: iload_1
       2: putfield      #2                  // Field ignoreUnknownFields:Z
       5: return

  public boolean isIgnoreInvalidFields();
    Code:
       0: aload_0
       1: getfield      #3                  // Field ignoreInvalidFields:Z
       4: ireturn

  public void setIgnoreInvalidFields(boolean);
    Code:
       0: aload_0
       1: iload_1
       2: putfield      #3                  // Field ignoreInvalidFields:Z
       5: return

  public final void setEnvironment(org.springframework.core.env.Environment);
    Code:
       0: aload_1
       1: instanceof    #5                  // class org/springframework/core/env/ConfigurableEnvironment
       4: ifeq          20
       7: aload_0
       8: aload_1
       9: checkcast     #5                  // class org/springframework/core/env/ConfigurableEnvironment
      12: invokeinterface #6,  1            // InterfaceMethod org/springframework/core/env/ConfigurableEnvironment.getPropertySources:()Lorg/springframework/core/env/MutablePropertySources;
      17: putfield      #4                  // Field propertySources:Ljava/lang/Iterable;
      20: return
}
