Compiled from "DefaultDubboConfigBinder.java"
public class org.apache.dubbo.config.spring.context.properties.DefaultDubboConfigBinder extends org.apache.dubbo.config.spring.context.properties.AbstractDubboConfigBinder {
  public org.apache.dubbo.config.spring.context.properties.DefaultDubboConfigBinder();
    Code:
       0: aload_0
       1: invokespecial #1                  // Method org/apache/dubbo/config/spring/context/properties/AbstractDubboConfigBinder."<init>":()V
       4: return

  public <C extends org.apache.dubbo.config.AbstractConfig> void bind(java.lang.String, C);
    Code:
       0: new           #2                  // class org/springframework/validation/DataBinder
       3: dup
       4: aload_2
       5: invokespecial #3                  // Method org/springframework/validation/DataBinder."<init>":(Ljava/lang/Object;)V
       8: astore_3
       9: aload_3
      10: aload_0
      11: invokevirtual #4                  // Method isIgnoreInvalidFields:()Z
      14: invokevirtual #5                  // Method org/springframework/validation/DataBinder.setIgnoreInvalidFields:(Z)V
      17: aload_3
      18: aload_0
      19: invokevirtual #6                  // Method isIgnoreUnknownFields:()Z
      22: invokevirtual #7                  // Method org/springframework/validation/DataBinder.setIgnoreUnknownFields:(Z)V
      25: aload_0
      26: invokevirtual #8                  // Method getPropertySources:()Ljava/lang/Iterable;
      29: aload_1
      30: invokestatic  #9                  // Method com/alibaba/spring/util/PropertySourcesUtils.getSubProperties:(Ljava/lang/Iterable;Ljava/lang/String;)Ljava/util/Map;
      33: astore        4
      35: new           #10                 // class org/springframework/beans/MutablePropertyValues
      38: dup
      39: aload         4
      41: invokespecial #11                 // Method org/springframework/beans/MutablePropertyValues."<init>":(Ljava/util/Map;)V
      44: astore        5
      46: aload_3
      47: aload         5
      49: invokevirtual #12                 // Method org/springframework/validation/DataBinder.bind:(Lorg/springframework/beans/PropertyValues;)V
      52: aload_3
      53: invokevirtual #13                 // Method org/springframework/validation/DataBinder.getBindingResult:()Lorg/springframework/validation/BindingResult;
      56: astore        6
      58: aload         6
      60: invokeinterface #14,  1           // InterfaceMethod org/springframework/validation/BindingResult.hasGlobalErrors:()Z
      65: ifeq          106
      68: new           #15                 // class java/lang/RuntimeException
      71: dup
      72: new           #16                 // class java/lang/StringBuilder
      75: dup
      76: invokespecial #17                 // Method java/lang/StringBuilder."<init>":()V
      79: ldc           #18                 // String Data bind global error, please check config. config:
      81: invokevirtual #19                 // Method java/lang/StringBuilder.append:(Ljava/lang/String;)Ljava/lang/StringBuilder;
      84: aload         6
      86: invokeinterface #20,  1           // InterfaceMethod org/springframework/validation/BindingResult.getGlobalError:()Lorg/springframework/validation/ObjectError;
      91: invokevirtual #21                 // Method java/lang/StringBuilder.append:(Ljava/lang/Object;)Ljava/lang/StringBuilder;
      94: ldc           #22                 // String
      96: invokevirtual #19                 // Method java/lang/StringBuilder.append:(Ljava/lang/String;)Ljava/lang/StringBuilder;
      99: invokevirtual #23                 // Method java/lang/StringBuilder.toString:()Ljava/lang/String;
     102: invokespecial #24                 // Method java/lang/RuntimeException."<init>":(Ljava/lang/String;)V
     105: athrow
     106: aload         6
     108: invokeinterface #25,  1           // InterfaceMethod org/springframework/validation/BindingResult.hasFieldErrors:()Z
     113: ifeq          143
     116: new           #15                 // class java/lang/RuntimeException
     119: dup
     120: aload_0
     121: aload         6
     123: invokeinterface #26,  1           // InterfaceMethod org/springframework/validation/BindingResult.getFieldErrors:()Ljava/util/List;
     128: aload_1
     129: aload_2
     130: invokevirtual #27                 // Method java/lang/Object.getClass:()Ljava/lang/Class;
     133: invokevirtual #28                 // Method java/lang/Class.getSimpleName:()Ljava/lang/String;
     136: invokespecial #29                 // Method buildErrorMsg:(Ljava/util/List;Ljava/lang/String;Ljava/lang/String;)Ljava/lang/String;
     139: invokespecial #24                 // Method java/lang/RuntimeException."<init>":(Ljava/lang/String;)V
     142: athrow
     143: return

  private java.lang.String buildErrorMsg(java.util.List<org.springframework.validation.FieldError>, java.lang.String, java.lang.String);
    Code:
       0: new           #16                 // class java/lang/StringBuilder
       3: dup
       4: new           #16                 // class java/lang/StringBuilder
       7: dup
       8: invokespecial #17                 // Method java/lang/StringBuilder."<init>":()V
      11: ldc           #30                 // String Data bind error, please check config. config:
      13: invokevirtual #19                 // Method java/lang/StringBuilder.append:(Ljava/lang/String;)Ljava/lang/StringBuilder;
      16: aload_3
      17: invokevirtual #19                 // Method java/lang/StringBuilder.append:(Ljava/lang/String;)Ljava/lang/StringBuilder;
      20: ldc           #31                 // String , prefix:
      22: invokevirtual #19                 // Method java/lang/StringBuilder.append:(Ljava/lang/String;)Ljava/lang/StringBuilder;
      25: aload_2
      26: invokevirtual #19                 // Method java/lang/StringBuilder.append:(Ljava/lang/String;)Ljava/lang/StringBuilder;
      29: ldc           #32                 // String  , error fields: [
      31: invokevirtual #19                 // Method java/lang/StringBuilder.append:(Ljava/lang/String;)Ljava/lang/StringBuilder;
      34: aload_1
      35: iconst_0
      36: invokeinterface #33,  2           // InterfaceMethod java/util/List.get:(I)Ljava/lang/Object;
      41: checkcast     #34                 // class org/springframework/validation/FieldError
      44: invokevirtual #35                 // Method org/springframework/validation/FieldError.getField:()Ljava/lang/String;
      47: invokevirtual #19                 // Method java/lang/StringBuilder.append:(Ljava/lang/String;)Ljava/lang/StringBuilder;
      50: invokevirtual #23                 // Method java/lang/StringBuilder.toString:()Ljava/lang/String;
      53: invokespecial #36                 // Method java/lang/StringBuilder."<init>":(Ljava/lang/String;)V
      56: astore        4
      58: aload_1
      59: invokeinterface #37,  1           // InterfaceMethod java/util/List.size:()I
      64: iconst_1
      65: if_icmple     91
      68: iconst_1
      69: aload_1
      70: invokeinterface #37,  1           // InterfaceMethod java/util/List.size:()I
      75: invokestatic  #38                 // InterfaceMethod java/util/stream/IntStream.range:(II)Ljava/util/stream/IntStream;
      78: aload         4
      80: aload_1
      81: invokedynamic #39,  0             // InvokeDynamic #0:accept:(Ljava/lang/StringBuilder;Ljava/util/List;)Ljava/util/function/IntConsumer;
      86: invokeinterface #40,  2           // InterfaceMethod java/util/stream/IntStream.forEach:(Ljava/util/function/IntConsumer;)V
      91: aload         4
      93: bipush        93
      95: invokevirtual #41                 // Method java/lang/StringBuilder.append:(C)Ljava/lang/StringBuilder;
      98: pop
      99: aload         4
     101: invokevirtual #23                 // Method java/lang/StringBuilder.toString:()Ljava/lang/String;
     104: areturn

  private static void lambda$buildErrorMsg$0(java.lang.StringBuilder, java.util.List, int);
    Code:
       0: aload_0
       1: new           #16                 // class java/lang/StringBuilder
       4: dup
       5: invokespecial #17                 // Method java/lang/StringBuilder."<init>":()V
       8: ldc           #42                 // String ,
      10: invokevirtual #19                 // Method java/lang/StringBuilder.append:(Ljava/lang/String;)Ljava/lang/StringBuilder;
      13: aload_1
      14: iload_2
      15: invokeinterface #33,  2           // InterfaceMethod java/util/List.get:(I)Ljava/lang/Object;
      20: checkcast     #34                 // class org/springframework/validation/FieldError
      23: invokevirtual #35                 // Method org/springframework/validation/FieldError.getField:()Ljava/lang/String;
      26: invokevirtual #19                 // Method java/lang/StringBuilder.append:(Ljava/lang/String;)Ljava/lang/StringBuilder;
      29: invokevirtual #23                 // Method java/lang/StringBuilder.toString:()Ljava/lang/String;
      32: invokevirtual #19                 // Method java/lang/StringBuilder.append:(Ljava/lang/String;)Ljava/lang/StringBuilder;
      35: pop
      36: return
}
