Compiled from "DebugAgentEnvironmentPostProcessor.java"
public class org.springframework.boot.reactor.DebugAgentEnvironmentPostProcessor implements org.springframework.boot.env.EnvironmentPostProcessor,org.springframework.core.Ordered {
  private static final java.lang.String REACTOR_DEBUGAGENT_CLASS;

  private static final java.lang.String DEBUGAGENT_ENABLED_CONFIG_KEY;

  public org.springframework.boot.reactor.DebugAgentEnvironmentPostProcessor();
    Code:
       0: aload_0
       1: invokespecial #1                  // Method java/lang/Object."<init>":()V
       4: return

  public void postProcessEnvironment(org.springframework.core.env.ConfigurableEnvironment, org.springframework.boot.SpringApplication);
    Code:
       0: ldc           #9                  // String reactor.tools.agent.ReactorDebugAgent
       2: aconst_null
       3: invokestatic  #11                 // Method org/springframework/util/ClassUtils.isPresent:(Ljava/lang/String;Ljava/lang/ClassLoader;)Z
       6: ifeq          74
       9: aload_1
      10: ldc           #17                 // String spring.reactor.debug-agent.enabled
      12: ldc           #19                 // class java/lang/Boolean
      14: invokeinterface #21,  3           // InterfaceMethod org/springframework/core/env/ConfigurableEnvironment.getProperty:(Ljava/lang/String;Ljava/lang/Class;)Ljava/lang/Object;
      19: checkcast     #19                 // class java/lang/Boolean
      22: astore_3
      23: aload_3
      24: getstatic     #27                 // Field java/lang/Boolean.FALSE:Ljava/lang/Boolean;
      27: if_acmpeq     74
      30: ldc           #9                  // String reactor.tools.agent.ReactorDebugAgent
      32: invokestatic  #31                 // Method java/lang/Class.forName:(Ljava/lang/String;)Ljava/lang/Class;
      35: astore        4
      37: aload         4
      39: ldc           #37                 // String init
      41: iconst_0
      42: anewarray     #32                 // class java/lang/Class
      45: invokevirtual #39                 // Method java/lang/Class.getMethod:(Ljava/lang/String;[Ljava/lang/Class;)Ljava/lang/reflect/Method;
      48: aconst_null
      49: iconst_0
      50: anewarray     #2                  // class java/lang/Object
      53: invokevirtual #43                 // Method java/lang/reflect/Method.invoke:(Ljava/lang/Object;[Ljava/lang/Object;)Ljava/lang/Object;
      56: pop
      57: goto          74
      60: astore        4
      62: new           #51                 // class java/lang/RuntimeException
      65: dup
      66: ldc           #53                 // String Failed to init Reactor\'s debug agent
      68: aload         4
      70: invokespecial #55                 // Method java/lang/RuntimeException."<init>":(Ljava/lang/String;Ljava/lang/Throwable;)V
      73: athrow
      74: return
    Exception table:
       from    to  target type
          30    57    60   Class java/lang/Exception

  public int getOrder();
    Code:
       0: ldc           #60                 // int 2147483647
       2: ireturn
}
