Compiled from "CollectCollectors.java"
final class com.google.common.collect.CollectCollectors$EnumSetAccumulator<E extends java.lang.Enum<E>> {
  static final java.util.stream.Collector<java.lang.Enum<?>, ?, com.google.common.collect.ImmutableSet<? extends java.lang.Enum<?>>> TO_IMMUTABLE_ENUM_SET;

  private java.util.EnumSet<E> set;

  private com.google.common.collect.CollectCollectors$EnumSetAccumulator();
    Code:
       0: aload_0
       1: invokespecial #2                  // Method java/lang/Object."<init>":()V
       4: return

  void add(E);
    Code:
       0: aload_0
       1: getfield      #3                  // Field set:Ljava/util/EnumSet;
       4: ifnonnull     18
       7: aload_0
       8: aload_1
       9: invokestatic  #4                  // Method java/util/EnumSet.of:(Ljava/lang/Enum;)Ljava/util/EnumSet;
      12: putfield      #3                  // Field set:Ljava/util/EnumSet;
      15: goto          27
      18: aload_0
      19: getfield      #3                  // Field set:Ljava/util/EnumSet;
      22: aload_1
      23: invokevirtual #5                  // Method java/util/EnumSet.add:(Ljava/lang/Object;)Z
      26: pop
      27: return

  com.google.common.collect.CollectCollectors$EnumSetAccumulator<E> combine(com.google.common.collect.CollectCollectors$EnumSetAccumulator<E>);
    Code:
       0: aload_0
       1: getfield      #3                  // Field set:Ljava/util/EnumSet;
       4: ifnonnull     9
       7: aload_1
       8: areturn
       9: aload_1
      10: getfield      #3                  // Field set:Ljava/util/EnumSet;
      13: ifnonnull     18
      16: aload_0
      17: areturn
      18: aload_0
      19: getfield      #3                  // Field set:Ljava/util/EnumSet;
      22: aload_1
      23: getfield      #3                  // Field set:Ljava/util/EnumSet;
      26: invokevirtual #6                  // Method java/util/EnumSet.addAll:(Ljava/util/Collection;)Z
      29: pop
      30: aload_0
      31: areturn

  com.google.common.collect.ImmutableSet<E> toImmutableSet();
    Code:
       0: aload_0
       1: getfield      #3                  // Field set:Ljava/util/EnumSet;
       4: ifnonnull     11
       7: invokestatic  #7                  // Method com/google/common/collect/ImmutableSet.of:()Lcom/google/common/collect/ImmutableSet;
      10: areturn
      11: aload_0
      12: getfield      #3                  // Field set:Ljava/util/EnumSet;
      15: invokestatic  #8                  // Method com/google/common/collect/ImmutableEnumSet.asImmutable:(Ljava/util/EnumSet;)Lcom/google/common/collect/ImmutableSet;
      18: astore_1
      19: aload_0
      20: aconst_null
      21: putfield      #3                  // Field set:Ljava/util/EnumSet;
      24: aload_1
      25: areturn

  com.google.common.collect.CollectCollectors$EnumSetAccumulator(com.google.common.collect.CollectCollectors$1);
    Code:
       0: aload_0
       1: invokespecial #1                  // Method "<init>":()V
       4: return

  static {};
    Code:
       0: invokestatic  #9                  // Method com/google/common/collect/CollectCollectors.access$000:()Ljava/util/stream/Collector;
       3: putstatic     #10                 // Field TO_IMMUTABLE_ENUM_SET:Ljava/util/stream/Collector;
       6: return
}
