Compiled from "EmptyImmutableSetMultimap.java"
class com.google.common.collect.EmptyImmutableSetMultimap extends com.google.common.collect.ImmutableSetMultimap<java.lang.Object, java.lang.Object> {
  static final com.google.common.collect.EmptyImmutableSetMultimap INSTANCE;

  private static final long serialVersionUID;

  private com.google.common.collect.EmptyImmutableSetMultimap();
    Code:
       0: aload_0
       1: invokestatic  #1                  // Method com/google/common/collect/ImmutableMap.of:()Lcom/google/common/collect/ImmutableMap;
       4: iconst_0
       5: aconst_null
       6: invokespecial #2                  // Method com/google/common/collect/ImmutableSetMultimap."<init>":(Lcom/google/common/collect/ImmutableMap;ILjava/util/Comparator;)V
       9: return

  public com.google.common.collect.ImmutableMap<java.lang.Object, java.util.Collection<java.lang.Object>> asMap();
    Code:
       0: aload_0
       1: invokespecial #3                  // Method com/google/common/collect/ImmutableSetMultimap.asMap:()Lcom/google/common/collect/ImmutableMap;
       4: areturn

  private java.lang.Object readResolve();
    Code:
       0: getstatic     #4                  // Field INSTANCE:Lcom/google/common/collect/EmptyImmutableSetMultimap;
       3: areturn

  public java.util.Map asMap();
    Code:
       0: aload_0
       1: invokevirtual #5                  // Method asMap:()Lcom/google/common/collect/ImmutableMap;
       4: areturn

  static {};
    Code:
       0: new           #6                  // class com/google/common/collect/EmptyImmutableSetMultimap
       3: dup
       4: invokespecial #7                  // Method "<init>":()V
       7: putstatic     #4                  // Field INSTANCE:Lcom/google/common/collect/EmptyImmutableSetMultimap;
      10: return
}
