Compiled from "EnumBiMap.java"
public final class com.google.common.collect.EnumBiMap<K extends java.lang.Enum<K>, V extends java.lang.Enum<V>> extends com.google.common.collect.AbstractBiMap<K, V> {
  transient java.lang.Class<K> keyTypeOrObjectUnderJ2cl;

  transient java.lang.Class<V> valueTypeOrObjectUnderJ2cl;

  private static final long serialVersionUID;

  public static <K extends java.lang.Enum<K>, V extends java.lang.Enum<V>> com.google.common.collect.EnumBiMap<K, V> create(java.lang.Class<K>, java.lang.Class<V>);
    Code:
       0: new           #1                  // class com/google/common/collect/EnumBiMap
       3: dup
       4: aload_0
       5: aload_1
       6: invokespecial #2                  // Method "<init>":(Ljava/lang/Class;Ljava/lang/Class;)V
       9: areturn

  public static <K extends java.lang.Enum<K>, V extends java.lang.Enum<V>> com.google.common.collect.EnumBiMap<K, V> create(java.util.Map<K, V>);
    Code:
       0: aload_0
       1: invokestatic  #3                  // Method inferKeyTypeOrObjectUnderJ2cl:(Ljava/util/Map;)Ljava/lang/Class;
       4: aload_0
       5: invokestatic  #4                  // Method inferValueTypeOrObjectUnderJ2cl:(Ljava/util/Map;)Ljava/lang/Class;
       8: invokestatic  #5                  // Method create:(Ljava/lang/Class;Ljava/lang/Class;)Lcom/google/common/collect/EnumBiMap;
      11: astore_1
      12: aload_1
      13: aload_0
      14: invokevirtual #6                  // Method putAll:(Ljava/util/Map;)V
      17: aload_1
      18: areturn

  private com.google.common.collect.EnumBiMap(java.lang.Class<K>, java.lang.Class<V>);
    Code:
       0: aload_0
       1: new           #7                  // class java/util/EnumMap
       4: dup
       5: aload_1
       6: invokespecial #8                  // Method java/util/EnumMap."<init>":(Ljava/lang/Class;)V
       9: new           #7                  // class java/util/EnumMap
      12: dup
      13: aload_2
      14: invokespecial #8                  // Method java/util/EnumMap."<init>":(Ljava/lang/Class;)V
      17: invokespecial #9                  // Method com/google/common/collect/AbstractBiMap."<init>":(Ljava/util/Map;Ljava/util/Map;)V
      20: aload_0
      21: aload_1
      22: putfield      #10                 // Field keyTypeOrObjectUnderJ2cl:Ljava/lang/Class;
      25: aload_0
      26: aload_2
      27: putfield      #11                 // Field valueTypeOrObjectUnderJ2cl:Ljava/lang/Class;
      30: return

  static <K extends java.lang.Enum<K>> java.lang.Class<K> inferKeyTypeOrObjectUnderJ2cl(java.util.Map<K, ?>);
    Code:
       0: aload_0
       1: instanceof    #1                  // class com/google/common/collect/EnumBiMap
       4: ifeq          15
       7: aload_0
       8: checkcast     #1                  // class com/google/common/collect/EnumBiMap
      11: getfield      #10                 // Field keyTypeOrObjectUnderJ2cl:Ljava/lang/Class;
      14: areturn
      15: aload_0
      16: instanceof    #12                 // class com/google/common/collect/EnumHashBiMap
      19: ifeq          30
      22: aload_0
      23: checkcast     #12                 // class com/google/common/collect/EnumHashBiMap
      26: getfield      #13                 // Field com/google/common/collect/EnumHashBiMap.keyTypeOrObjectUnderJ2cl:Ljava/lang/Class;
      29: areturn
      30: aload_0
      31: invokeinterface #14,  1           // InterfaceMethod java/util/Map.isEmpty:()Z
      36: ifne          43
      39: iconst_1
      40: goto          44
      43: iconst_0
      44: invokestatic  #15                 // Method com/google/common/base/Preconditions.checkArgument:(Z)V
      47: aload_0
      48: invokeinterface #16,  1           // InterfaceMethod java/util/Map.keySet:()Ljava/util/Set;
      53: invokeinterface #17,  1           // InterfaceMethod java/util/Set.iterator:()Ljava/util/Iterator;
      58: invokeinterface #18,  1           // InterfaceMethod java/util/Iterator.next:()Ljava/lang/Object;
      63: checkcast     #19                 // class java/lang/Enum
      66: invokestatic  #20                 // Method com/google/common/collect/Platform.getDeclaringClassOrObjectForJ2cl:(Ljava/lang/Enum;)Ljava/lang/Class;
      69: areturn

  private static <V extends java.lang.Enum<V>> java.lang.Class<V> inferValueTypeOrObjectUnderJ2cl(java.util.Map<?, V>);
    Code:
       0: aload_0
       1: instanceof    #1                  // class com/google/common/collect/EnumBiMap
       4: ifeq          15
       7: aload_0
       8: checkcast     #1                  // class com/google/common/collect/EnumBiMap
      11: getfield      #11                 // Field valueTypeOrObjectUnderJ2cl:Ljava/lang/Class;
      14: areturn
      15: aload_0
      16: invokeinterface #14,  1           // InterfaceMethod java/util/Map.isEmpty:()Z
      21: ifne          28
      24: iconst_1
      25: goto          29
      28: iconst_0
      29: invokestatic  #15                 // Method com/google/common/base/Preconditions.checkArgument:(Z)V
      32: aload_0
      33: invokeinterface #21,  1           // InterfaceMethod java/util/Map.values:()Ljava/util/Collection;
      38: invokeinterface #22,  1           // InterfaceMethod java/util/Collection.iterator:()Ljava/util/Iterator;
      43: invokeinterface #18,  1           // InterfaceMethod java/util/Iterator.next:()Ljava/lang/Object;
      48: checkcast     #19                 // class java/lang/Enum
      51: invokestatic  #20                 // Method com/google/common/collect/Platform.getDeclaringClassOrObjectForJ2cl:(Ljava/lang/Enum;)Ljava/lang/Class;
      54: areturn

  public java.lang.Class<K> keyType();
    Code:
       0: aload_0
       1: getfield      #10                 // Field keyTypeOrObjectUnderJ2cl:Ljava/lang/Class;
       4: areturn

  public java.lang.Class<V> valueType();
    Code:
       0: aload_0
       1: getfield      #11                 // Field valueTypeOrObjectUnderJ2cl:Ljava/lang/Class;
       4: areturn

  K checkKey(K);
    Code:
       0: aload_1
       1: invokestatic  #23                 // Method com/google/common/base/Preconditions.checkNotNull:(Ljava/lang/Object;)Ljava/lang/Object;
       4: checkcast     #19                 // class java/lang/Enum
       7: areturn

  V checkValue(V);
    Code:
       0: aload_1
       1: invokestatic  #23                 // Method com/google/common/base/Preconditions.checkNotNull:(Ljava/lang/Object;)Ljava/lang/Object;
       4: checkcast     #19                 // class java/lang/Enum
       7: areturn

  private void writeObject(java.io.ObjectOutputStream) throws java.io.IOException;
    Code:
       0: aload_1
       1: invokevirtual #24                 // Method java/io/ObjectOutputStream.defaultWriteObject:()V
       4: aload_1
       5: aload_0
       6: getfield      #10                 // Field keyTypeOrObjectUnderJ2cl:Ljava/lang/Class;
       9: invokevirtual #25                 // Method java/io/ObjectOutputStream.writeObject:(Ljava/lang/Object;)V
      12: aload_1
      13: aload_0
      14: getfield      #11                 // Field valueTypeOrObjectUnderJ2cl:Ljava/lang/Class;
      17: invokevirtual #25                 // Method java/io/ObjectOutputStream.writeObject:(Ljava/lang/Object;)V
      20: aload_0
      21: aload_1
      22: invokestatic  #26                 // Method com/google/common/collect/Serialization.writeMap:(Ljava/util/Map;Ljava/io/ObjectOutputStream;)V
      25: return

  private void readObject(java.io.ObjectInputStream) throws java.io.IOException, java.lang.ClassNotFoundException;
    Code:
       0: aload_1
       1: invokevirtual #27                 // Method java/io/ObjectInputStream.defaultReadObject:()V
       4: aload_0
       5: aload_1
       6: invokevirtual #28                 // Method java/io/ObjectInputStream.readObject:()Ljava/lang/Object;
       9: checkcast     #29                 // class java/lang/Class
      12: putfield      #10                 // Field keyTypeOrObjectUnderJ2cl:Ljava/lang/Class;
      15: aload_0
      16: aload_1
      17: invokevirtual #28                 // Method java/io/ObjectInputStream.readObject:()Ljava/lang/Object;
      20: checkcast     #29                 // class java/lang/Class
      23: putfield      #11                 // Field valueTypeOrObjectUnderJ2cl:Ljava/lang/Class;
      26: aload_0
      27: new           #7                  // class java/util/EnumMap
      30: dup
      31: aload_0
      32: getfield      #10                 // Field keyTypeOrObjectUnderJ2cl:Ljava/lang/Class;
      35: invokespecial #8                  // Method java/util/EnumMap."<init>":(Ljava/lang/Class;)V
      38: new           #7                  // class java/util/EnumMap
      41: dup
      42: aload_0
      43: getfield      #11                 // Field valueTypeOrObjectUnderJ2cl:Ljava/lang/Class;
      46: invokespecial #8                  // Method java/util/EnumMap."<init>":(Ljava/lang/Class;)V
      49: invokevirtual #30                 // Method setDelegates:(Ljava/util/Map;Ljava/util/Map;)V
      52: aload_0
      53: aload_1
      54: invokestatic  #31                 // Method com/google/common/collect/Serialization.populateMap:(Ljava/util/Map;Ljava/io/ObjectInputStream;)V
      57: return

  public java.util.Set entrySet();
    Code:
       0: aload_0
       1: invokespecial #32                 // Method com/google/common/collect/AbstractBiMap.entrySet:()Ljava/util/Set;
       4: areturn

  public java.util.Set values();
    Code:
       0: aload_0
       1: invokespecial #33                 // Method com/google/common/collect/AbstractBiMap.values:()Ljava/util/Set;
       4: areturn

  public java.util.Set keySet();
    Code:
       0: aload_0
       1: invokespecial #34                 // Method com/google/common/collect/AbstractBiMap.keySet:()Ljava/util/Set;
       4: areturn

  public com.google.common.collect.BiMap inverse();
    Code:
       0: aload_0
       1: invokespecial #35                 // Method com/google/common/collect/AbstractBiMap.inverse:()Lcom/google/common/collect/BiMap;
       4: areturn

  public void clear();
    Code:
       0: aload_0
       1: invokespecial #36                 // Method com/google/common/collect/AbstractBiMap.clear:()V
       4: return

  public void replaceAll(java.util.function.BiFunction);
    Code:
       0: aload_0
       1: aload_1
       2: invokespecial #37                 // Method com/google/common/collect/AbstractBiMap.replaceAll:(Ljava/util/function/BiFunction;)V
       5: return

  public void putAll(java.util.Map);
    Code:
       0: aload_0
       1: aload_1
       2: invokespecial #38                 // Method com/google/common/collect/AbstractBiMap.putAll:(Ljava/util/Map;)V
       5: return

  public java.lang.Object remove(java.lang.Object);
    Code:
       0: aload_0
       1: aload_1
       2: invokespecial #39                 // Method com/google/common/collect/AbstractBiMap.remove:(Ljava/lang/Object;)Ljava/lang/Object;
       5: areturn

  public java.lang.Object forcePut(java.lang.Object, java.lang.Object);
    Code:
       0: aload_0
       1: aload_1
       2: aload_2
       3: invokespecial #40                 // Method com/google/common/collect/AbstractBiMap.forcePut:(Ljava/lang/Object;Ljava/lang/Object;)Ljava/lang/Object;
       6: areturn

  public java.lang.Object put(java.lang.Object, java.lang.Object);
    Code:
       0: aload_0
       1: aload_1
       2: aload_2
       3: invokespecial #41                 // Method com/google/common/collect/AbstractBiMap.put:(Ljava/lang/Object;Ljava/lang/Object;)Ljava/lang/Object;
       6: areturn

  public boolean containsValue(java.lang.Object);
    Code:
       0: aload_0
       1: aload_1
       2: invokespecial #42                 // Method com/google/common/collect/AbstractBiMap.containsValue:(Ljava/lang/Object;)Z
       5: ireturn

  java.lang.Object checkValue(java.lang.Object);
    Code:
       0: aload_0
       1: aload_1
       2: checkcast     #19                 // class java/lang/Enum
       5: invokevirtual #43                 // Method checkValue:(Ljava/lang/Enum;)Ljava/lang/Enum;
       8: areturn

  java.lang.Object checkKey(java.lang.Object);
    Code:
       0: aload_0
       1: aload_1
       2: checkcast     #19                 // class java/lang/Enum
       5: invokevirtual #44                 // Method checkKey:(Ljava/lang/Enum;)Ljava/lang/Enum;
       8: areturn
}
