Compiled from "ImmutableEnumSet.java"
final class com.google.common.collect.ImmutableEnumSet<E extends java.lang.Enum<E>> extends com.google.common.collect.ImmutableSet<E> {
  private final transient java.util.EnumSet<E> delegate;

  private transient int hashCode;

  static <E extends java.lang.Enum<E>> com.google.common.collect.ImmutableSet<E> asImmutable(java.util.EnumSet<E>);
    Code:
       0: aload_0
       1: invokevirtual #2                  // Method java/util/EnumSet.size:()I
       4: lookupswitch  { // 2
                     0: 32
                     1: 36
               default: 47
          }
      32: invokestatic  #3                  // Method com/google/common/collect/ImmutableSet.of:()Lcom/google/common/collect/ImmutableSet;
      35: areturn
      36: aload_0
      37: invokestatic  #4                  // Method com/google/common/collect/Iterables.getOnlyElement:(Ljava/lang/Iterable;)Ljava/lang/Object;
      40: checkcast     #5                  // class java/lang/Enum
      43: invokestatic  #6                  // Method com/google/common/collect/ImmutableSet.of:(Ljava/lang/Object;)Lcom/google/common/collect/ImmutableSet;
      46: areturn
      47: new           #7                  // class com/google/common/collect/ImmutableEnumSet
      50: dup
      51: aload_0
      52: invokespecial #1                  // Method "<init>":(Ljava/util/EnumSet;)V
      55: areturn

  private com.google.common.collect.ImmutableEnumSet(java.util.EnumSet<E>);
    Code:
       0: aload_0
       1: invokespecial #8                  // Method com/google/common/collect/ImmutableSet."<init>":()V
       4: aload_0
       5: aload_1
       6: putfield      #9                  // Field delegate:Ljava/util/EnumSet;
       9: return

  boolean isPartialView();
    Code:
       0: iconst_0
       1: ireturn

  public com.google.common.collect.UnmodifiableIterator<E> iterator();
    Code:
       0: aload_0
       1: getfield      #9                  // Field delegate:Ljava/util/EnumSet;
       4: invokevirtual #10                 // Method java/util/EnumSet.iterator:()Ljava/util/Iterator;
       7: invokestatic  #11                 // Method com/google/common/collect/Iterators.unmodifiableIterator:(Ljava/util/Iterator;)Lcom/google/common/collect/UnmodifiableIterator;
      10: areturn

  public java.util.Spliterator<E> spliterator();
    Code:
       0: aload_0
       1: getfield      #9                  // Field delegate:Ljava/util/EnumSet;
       4: invokevirtual #12                 // Method java/util/EnumSet.spliterator:()Ljava/util/Spliterator;
       7: areturn

  public void forEach(java.util.function.Consumer<? super E>);
    Code:
       0: aload_0
       1: getfield      #9                  // Field delegate:Ljava/util/EnumSet;
       4: aload_1
       5: invokevirtual #13                 // Method java/util/EnumSet.forEach:(Ljava/util/function/Consumer;)V
       8: return

  public int size();
    Code:
       0: aload_0
       1: getfield      #9                  // Field delegate:Ljava/util/EnumSet;
       4: invokevirtual #2                  // Method java/util/EnumSet.size:()I
       7: ireturn

  public boolean contains(java.lang.Object);
    Code:
       0: aload_0
       1: getfield      #9                  // Field delegate:Ljava/util/EnumSet;
       4: aload_1
       5: invokevirtual #14                 // Method java/util/EnumSet.contains:(Ljava/lang/Object;)Z
       8: ireturn

  public boolean containsAll(java.util.Collection<?>);
    Code:
       0: aload_1
       1: instanceof    #7                  // class com/google/common/collect/ImmutableEnumSet
       4: ifeq          15
       7: aload_1
       8: checkcast     #7                  // class com/google/common/collect/ImmutableEnumSet
      11: getfield      #9                  // Field delegate:Ljava/util/EnumSet;
      14: astore_1
      15: aload_0
      16: getfield      #9                  // Field delegate:Ljava/util/EnumSet;
      19: aload_1
      20: invokevirtual #15                 // Method java/util/EnumSet.containsAll:(Ljava/util/Collection;)Z
      23: ireturn

  public boolean isEmpty();
    Code:
       0: aload_0
       1: getfield      #9                  // Field delegate:Ljava/util/EnumSet;
       4: invokevirtual #16                 // Method java/util/EnumSet.isEmpty:()Z
       7: ireturn

  public boolean equals(java.lang.Object);
    Code:
       0: aload_1
       1: aload_0
       2: if_acmpne     7
       5: iconst_1
       6: ireturn
       7: aload_1
       8: instanceof    #7                  // class com/google/common/collect/ImmutableEnumSet
      11: ifeq          22
      14: aload_1
      15: checkcast     #7                  // class com/google/common/collect/ImmutableEnumSet
      18: getfield      #9                  // Field delegate:Ljava/util/EnumSet;
      21: astore_1
      22: aload_0
      23: getfield      #9                  // Field delegate:Ljava/util/EnumSet;
      26: aload_1
      27: invokevirtual #17                 // Method java/util/EnumSet.equals:(Ljava/lang/Object;)Z
      30: ireturn

  boolean isHashCodeFast();
    Code:
       0: iconst_1
       1: ireturn

  public int hashCode();
    Code:
       0: aload_0
       1: getfield      #18                 // Field hashCode:I
       4: istore_1
       5: iload_1
       6: ifne          24
       9: aload_0
      10: aload_0
      11: getfield      #9                  // Field delegate:Ljava/util/EnumSet;
      14: invokevirtual #19                 // Method java/util/EnumSet.hashCode:()I
      17: dup_x1
      18: putfield      #18                 // Field hashCode:I
      21: goto          25
      24: iload_1
      25: ireturn

  public java.lang.String toString();
    Code:
       0: aload_0
       1: getfield      #9                  // Field delegate:Ljava/util/EnumSet;
       4: invokevirtual #20                 // Method java/util/EnumSet.toString:()Ljava/lang/String;
       7: areturn

  java.lang.Object writeReplace();
    Code:
       0: new           #21                 // class com/google/common/collect/ImmutableEnumSet$EnumSerializedForm
       3: dup
       4: aload_0
       5: getfield      #9                  // Field delegate:Ljava/util/EnumSet;
       8: invokespecial #22                 // Method com/google/common/collect/ImmutableEnumSet$EnumSerializedForm."<init>":(Ljava/util/EnumSet;)V
      11: areturn

  private void readObject(java.io.ObjectInputStream) throws java.io.InvalidObjectException;
    Code:
       0: new           #23                 // class java/io/InvalidObjectException
       3: dup
       4: ldc           #24                 // String Use SerializedForm
       6: invokespecial #25                 // Method java/io/InvalidObjectException."<init>":(Ljava/lang/String;)V
       9: athrow

  public java.util.Iterator iterator();
    Code:
       0: aload_0
       1: invokevirtual #26                 // Method iterator:()Lcom/google/common/collect/UnmodifiableIterator;
       4: areturn

  com.google.common.collect.ImmutableEnumSet(java.util.EnumSet, com.google.common.collect.ImmutableEnumSet$1);
    Code:
       0: aload_0
       1: aload_1
       2: invokespecial #1                  // Method "<init>":(Ljava/util/EnumSet;)V
       5: return
}
