Compiled from "MapMakerInternalMap.java"
final class com.google.common.collect.MapMakerInternalMap$WeakKeyDummyValueEntry$Helper<K> implements com.google.common.collect.MapMakerInternalMap$InternalEntryHelper<K, com.google.common.collect.MapMaker$Dummy, com.google.common.collect.MapMakerInternalMap$WeakKeyDummyValueEntry<K>, com.google.common.collect.MapMakerInternalMap$WeakKeyDummyValueSegment<K>> {
  private static final com.google.common.collect.MapMakerInternalMap$WeakKeyDummyValueEntry$Helper<?> INSTANCE;

  com.google.common.collect.MapMakerInternalMap$WeakKeyDummyValueEntry$Helper();
    Code:
       0: aload_0
       1: invokespecial #1                  // Method java/lang/Object."<init>":()V
       4: return

  static <K> com.google.common.collect.MapMakerInternalMap$WeakKeyDummyValueEntry$Helper<K> instance();
    Code:
       0: getstatic     #2                  // Field INSTANCE:Lcom/google/common/collect/MapMakerInternalMap$WeakKeyDummyValueEntry$Helper;
       3: areturn

  public com.google.common.collect.MapMakerInternalMap$Strength keyStrength();
    Code:
       0: getstatic     #3                  // Field com/google/common/collect/MapMakerInternalMap$Strength.WEAK:Lcom/google/common/collect/MapMakerInternalMap$Strength;
       3: areturn

  public com.google.common.collect.MapMakerInternalMap$Strength valueStrength();
    Code:
       0: getstatic     #4                  // Field com/google/common/collect/MapMakerInternalMap$Strength.STRONG:Lcom/google/common/collect/MapMakerInternalMap$Strength;
       3: areturn

  public com.google.common.collect.MapMakerInternalMap$WeakKeyDummyValueSegment<K> newSegment(com.google.common.collect.MapMakerInternalMap<K, com.google.common.collect.MapMaker$Dummy, com.google.common.collect.MapMakerInternalMap$WeakKeyDummyValueEntry<K>, com.google.common.collect.MapMakerInternalMap$WeakKeyDummyValueSegment<K>>, int);
    Code:
       0: new           #5                  // class com/google/common/collect/MapMakerInternalMap$WeakKeyDummyValueSegment
       3: dup
       4: aload_1
       5: iload_2
       6: invokespecial #6                  // Method com/google/common/collect/MapMakerInternalMap$WeakKeyDummyValueSegment."<init>":(Lcom/google/common/collect/MapMakerInternalMap;I)V
       9: areturn

  public com.google.common.collect.MapMakerInternalMap$WeakKeyDummyValueEntry<K> copy(com.google.common.collect.MapMakerInternalMap$WeakKeyDummyValueSegment<K>, com.google.common.collect.MapMakerInternalMap$WeakKeyDummyValueEntry<K>, com.google.common.collect.MapMakerInternalMap$WeakKeyDummyValueEntry<K>);
    Code:
       0: aload_2
       1: invokevirtual #7                  // Method com/google/common/collect/MapMakerInternalMap$WeakKeyDummyValueEntry.getKey:()Ljava/lang/Object;
       4: astore        4
       6: aload         4
       8: ifnonnull     13
      11: aconst_null
      12: areturn
      13: aload_0
      14: aload_1
      15: aload         4
      17: aload_2
      18: getfield      #8                  // Field com/google/common/collect/MapMakerInternalMap$WeakKeyDummyValueEntry.hash:I
      21: aload_3
      22: invokevirtual #9                  // Method newEntry:(Lcom/google/common/collect/MapMakerInternalMap$WeakKeyDummyValueSegment;Ljava/lang/Object;ILcom/google/common/collect/MapMakerInternalMap$WeakKeyDummyValueEntry;)Lcom/google/common/collect/MapMakerInternalMap$WeakKeyDummyValueEntry;
      25: areturn

  public void setValue(com.google.common.collect.MapMakerInternalMap$WeakKeyDummyValueSegment<K>, com.google.common.collect.MapMakerInternalMap$WeakKeyDummyValueEntry<K>, com.google.common.collect.MapMaker$Dummy);
    Code:
       0: return

  public com.google.common.collect.MapMakerInternalMap$WeakKeyDummyValueEntry<K> newEntry(com.google.common.collect.MapMakerInternalMap$WeakKeyDummyValueSegment<K>, K, int, com.google.common.collect.MapMakerInternalMap$WeakKeyDummyValueEntry<K>);
    Code:
       0: aload         4
       2: ifnonnull     22
       5: new           #10                 // class com/google/common/collect/MapMakerInternalMap$WeakKeyDummyValueEntry
       8: dup
       9: aload_1
      10: invokestatic  #11                 // Method com/google/common/collect/MapMakerInternalMap$WeakKeyDummyValueSegment.access$800:(Lcom/google/common/collect/MapMakerInternalMap$WeakKeyDummyValueSegment;)Ljava/lang/ref/ReferenceQueue;
      13: aload_2
      14: iload_3
      15: aconst_null
      16: invokespecial #12                 // Method com/google/common/collect/MapMakerInternalMap$WeakKeyDummyValueEntry."<init>":(Ljava/lang/ref/ReferenceQueue;Ljava/lang/Object;ILcom/google/common/collect/MapMakerInternalMap$1;)V
      19: goto          38
      22: new           #13                 // class com/google/common/collect/MapMakerInternalMap$WeakKeyDummyValueEntry$LinkedWeakKeyDummyValueEntry
      25: dup
      26: aload_1
      27: invokestatic  #11                 // Method com/google/common/collect/MapMakerInternalMap$WeakKeyDummyValueSegment.access$800:(Lcom/google/common/collect/MapMakerInternalMap$WeakKeyDummyValueSegment;)Ljava/lang/ref/ReferenceQueue;
      30: aload_2
      31: iload_3
      32: aload         4
      34: aconst_null
      35: invokespecial #14                 // Method com/google/common/collect/MapMakerInternalMap$WeakKeyDummyValueEntry$LinkedWeakKeyDummyValueEntry."<init>":(Ljava/lang/ref/ReferenceQueue;Ljava/lang/Object;ILcom/google/common/collect/MapMakerInternalMap$WeakKeyDummyValueEntry;Lcom/google/common/collect/MapMakerInternalMap$1;)V
      38: areturn

  public void setValue(com.google.common.collect.MapMakerInternalMap$Segment, com.google.common.collect.MapMakerInternalMap$InternalEntry, java.lang.Object);
    Code:
       0: aload_0
       1: aload_1
       2: checkcast     #5                  // class com/google/common/collect/MapMakerInternalMap$WeakKeyDummyValueSegment
       5: aload_2
       6: checkcast     #10                 // class com/google/common/collect/MapMakerInternalMap$WeakKeyDummyValueEntry
       9: aload_3
      10: checkcast     #15                 // class com/google/common/collect/MapMaker$Dummy
      13: invokevirtual #16                 // Method setValue:(Lcom/google/common/collect/MapMakerInternalMap$WeakKeyDummyValueSegment;Lcom/google/common/collect/MapMakerInternalMap$WeakKeyDummyValueEntry;Lcom/google/common/collect/MapMaker$Dummy;)V
      16: return

  public com.google.common.collect.MapMakerInternalMap$InternalEntry copy(com.google.common.collect.MapMakerInternalMap$Segment, com.google.common.collect.MapMakerInternalMap$InternalEntry, com.google.common.collect.MapMakerInternalMap$InternalEntry);
    Code:
       0: aload_0
       1: aload_1
       2: checkcast     #5                  // class com/google/common/collect/MapMakerInternalMap$WeakKeyDummyValueSegment
       5: aload_2
       6: checkcast     #10                 // class com/google/common/collect/MapMakerInternalMap$WeakKeyDummyValueEntry
       9: aload_3
      10: checkcast     #10                 // class com/google/common/collect/MapMakerInternalMap$WeakKeyDummyValueEntry
      13: invokevirtual #17                 // Method copy:(Lcom/google/common/collect/MapMakerInternalMap$WeakKeyDummyValueSegment;Lcom/google/common/collect/MapMakerInternalMap$WeakKeyDummyValueEntry;Lcom/google/common/collect/MapMakerInternalMap$WeakKeyDummyValueEntry;)Lcom/google/common/collect/MapMakerInternalMap$WeakKeyDummyValueEntry;
      16: areturn

  public com.google.common.collect.MapMakerInternalMap$InternalEntry newEntry(com.google.common.collect.MapMakerInternalMap$Segment, java.lang.Object, int, com.google.common.collect.MapMakerInternalMap$InternalEntry);
    Code:
       0: aload_0
       1: aload_1
       2: checkcast     #5                  // class com/google/common/collect/MapMakerInternalMap$WeakKeyDummyValueSegment
       5: aload_2
       6: iload_3
       7: aload         4
       9: checkcast     #10                 // class com/google/common/collect/MapMakerInternalMap$WeakKeyDummyValueEntry
      12: invokevirtual #9                  // Method newEntry:(Lcom/google/common/collect/MapMakerInternalMap$WeakKeyDummyValueSegment;Ljava/lang/Object;ILcom/google/common/collect/MapMakerInternalMap$WeakKeyDummyValueEntry;)Lcom/google/common/collect/MapMakerInternalMap$WeakKeyDummyValueEntry;
      15: areturn

  public com.google.common.collect.MapMakerInternalMap$Segment newSegment(com.google.common.collect.MapMakerInternalMap, int);
    Code:
       0: aload_0
       1: aload_1
       2: iload_2
       3: invokevirtual #18                 // Method newSegment:(Lcom/google/common/collect/MapMakerInternalMap;I)Lcom/google/common/collect/MapMakerInternalMap$WeakKeyDummyValueSegment;
       6: areturn

  static {};
    Code:
       0: new           #19                 // class com/google/common/collect/MapMakerInternalMap$WeakKeyDummyValueEntry$Helper
       3: dup
       4: invokespecial #20                 // Method "<init>":()V
       7: putstatic     #2                  // Field INSTANCE:Lcom/google/common/collect/MapMakerInternalMap$WeakKeyDummyValueEntry$Helper;
      10: return
}
