Compiled from "MapMakerInternalMap.java"
final class com.google.common.collect.MapMakerInternalMap$StrongKeyStrongValueEntry$LinkedStrongKeyStrongValueEntry<K, V> extends com.google.common.collect.MapMakerInternalMap$StrongKeyStrongValueEntry<K, V> {
  private final com.google.common.collect.MapMakerInternalMap$StrongKeyStrongValueEntry<K, V> next;

  com.google.common.collect.MapMakerInternalMap$StrongKeyStrongValueEntry$LinkedStrongKeyStrongValueEntry(K, int, com.google.common.collect.MapMakerInternalMap$StrongKeyStrongValueEntry<K, V>);
    Code:
       0: aload_0
       1: aload_1
       2: iload_2
       3: aconst_null
       4: invokespecial #1                  // Method com/google/common/collect/MapMakerInternalMap$StrongKeyStrongValueEntry."<init>":(Ljava/lang/Object;ILcom/google/common/collect/MapMakerInternalMap$1;)V
       7: aload_0
       8: aload_3
       9: putfield      #2                  // Field next:Lcom/google/common/collect/MapMakerInternalMap$StrongKeyStrongValueEntry;
      12: return

  public com.google.common.collect.MapMakerInternalMap$StrongKeyStrongValueEntry<K, V> getNext();
    Code:
       0: aload_0
       1: getfield      #2                  // Field next:Lcom/google/common/collect/MapMakerInternalMap$StrongKeyStrongValueEntry;
       4: areturn

  public com.google.common.collect.MapMakerInternalMap$InternalEntry getNext();
    Code:
       0: aload_0
       1: invokevirtual #3                  // Method getNext:()Lcom/google/common/collect/MapMakerInternalMap$StrongKeyStrongValueEntry;
       4: areturn
}
