Compiled from "MapMakerInternalMap.java"
final class com.google.common.collect.MapMakerInternalMap$WeakKeyWeakValueEntry$LinkedWeakKeyWeakValueEntry<K, V> extends com.google.common.collect.MapMakerInternalMap$WeakKeyWeakValueEntry<K, V> {
  private final com.google.common.collect.MapMakerInternalMap$WeakKeyWeakValueEntry<K, V> next;

  com.google.common.collect.MapMakerInternalMap$WeakKeyWeakValueEntry$LinkedWeakKeyWeakValueEntry(java.lang.ref.ReferenceQueue<K>, K, int, com.google.common.collect.MapMakerInternalMap$WeakKeyWeakValueEntry<K, V>);
    Code:
       0: aload_0
       1: aload_1
       2: aload_2
       3: iload_3
       4: invokespecial #1                  // Method com/google/common/collect/MapMakerInternalMap$WeakKeyWeakValueEntry."<init>":(Ljava/lang/ref/ReferenceQueue;Ljava/lang/Object;I)V
       7: aload_0
       8: aload         4
      10: putfield      #2                  // Field next:Lcom/google/common/collect/MapMakerInternalMap$WeakKeyWeakValueEntry;
      13: return

  public com.google.common.collect.MapMakerInternalMap$WeakKeyWeakValueEntry<K, V> getNext();
    Code:
       0: aload_0
       1: getfield      #2                  // Field next:Lcom/google/common/collect/MapMakerInternalMap$WeakKeyWeakValueEntry;
       4: areturn

  public com.google.common.collect.MapMakerInternalMap$InternalEntry getNext();
    Code:
       0: aload_0
       1: invokevirtual #3                  // Method getNext:()Lcom/google/common/collect/MapMakerInternalMap$WeakKeyWeakValueEntry;
       4: areturn
}
