Compiled from "MapMakerInternalMap.java"
final class com.google.common.collect.MapMakerInternalMap$StrongKeyDummyValueEntry$LinkedStrongKeyDummyValueEntry<K> extends com.google.common.collect.MapMakerInternalMap$StrongKeyDummyValueEntry<K> {
  private final com.google.common.collect.MapMakerInternalMap$StrongKeyDummyValueEntry<K> next;

  com.google.common.collect.MapMakerInternalMap$StrongKeyDummyValueEntry$LinkedStrongKeyDummyValueEntry(K, int, com.google.common.collect.MapMakerInternalMap$StrongKeyDummyValueEntry<K>);
    Code:
       0: aload_0
       1: aload_1
       2: iload_2
       3: aconst_null
       4: invokespecial #1                  // Method com/google/common/collect/MapMakerInternalMap$StrongKeyDummyValueEntry."<init>":(Ljava/lang/Object;ILcom/google/common/collect/MapMakerInternalMap$1;)V
       7: aload_0
       8: aload_3
       9: putfield      #2                  // Field next:Lcom/google/common/collect/MapMakerInternalMap$StrongKeyDummyValueEntry;
      12: return

  public com.google.common.collect.MapMakerInternalMap$StrongKeyDummyValueEntry<K> getNext();
    Code:
       0: aload_0
       1: getfield      #2                  // Field next:Lcom/google/common/collect/MapMakerInternalMap$StrongKeyDummyValueEntry;
       4: areturn

  public java.lang.Object getValue();
    Code:
       0: aload_0
       1: invokespecial #3                  // Method com/google/common/collect/MapMakerInternalMap$StrongKeyDummyValueEntry.getValue:()Lcom/google/common/collect/MapMaker$Dummy;
       4: areturn

  public com.google.common.collect.MapMakerInternalMap$InternalEntry getNext();
    Code:
       0: aload_0
       1: invokevirtual #4                  // Method getNext:()Lcom/google/common/collect/MapMakerInternalMap$StrongKeyDummyValueEntry;
       4: areturn
}
