Compiled from "MapMakerInternalMap.java"
final class com.google.common.collect.MapMakerInternalMap$WeakKeyDummyValueEntry$LinkedWeakKeyDummyValueEntry<K> extends com.google.common.collect.MapMakerInternalMap$WeakKeyDummyValueEntry<K> {
  private final com.google.common.collect.MapMakerInternalMap$WeakKeyDummyValueEntry<K> next;

  private com.google.common.collect.MapMakerInternalMap$WeakKeyDummyValueEntry$LinkedWeakKeyDummyValueEntry(java.lang.ref.ReferenceQueue<K>, K, int, com.google.common.collect.MapMakerInternalMap$WeakKeyDummyValueEntry<K>);
    Code:
       0: aload_0
       1: aload_1
       2: aload_2
       3: iload_3
       4: aconst_null
       5: invokespecial #2                  // Method com/google/common/collect/MapMakerInternalMap$WeakKeyDummyValueEntry."<init>":(Ljava/lang/ref/ReferenceQueue;Ljava/lang/Object;ILcom/google/common/collect/MapMakerInternalMap$1;)V
       8: aload_0
       9: aload         4
      11: putfield      #3                  // Field next:Lcom/google/common/collect/MapMakerInternalMap$WeakKeyDummyValueEntry;
      14: return

  public com.google.common.collect.MapMakerInternalMap$WeakKeyDummyValueEntry<K> getNext();
    Code:
       0: aload_0
       1: getfield      #3                  // Field next:Lcom/google/common/collect/MapMakerInternalMap$WeakKeyDummyValueEntry;
       4: areturn

  public java.lang.Object getValue();
    Code:
       0: aload_0
       1: invokespecial #4                  // Method com/google/common/collect/MapMakerInternalMap$WeakKeyDummyValueEntry.getValue:()Lcom/google/common/collect/MapMaker$Dummy;
       4: areturn

  public com.google.common.collect.MapMakerInternalMap$InternalEntry getNext();
    Code:
       0: aload_0
       1: invokevirtual #5                  // Method getNext:()Lcom/google/common/collect/MapMakerInternalMap$WeakKeyDummyValueEntry;
       4: areturn

  com.google.common.collect.MapMakerInternalMap$WeakKeyDummyValueEntry$LinkedWeakKeyDummyValueEntry(java.lang.ref.ReferenceQueue, java.lang.Object, int, com.google.common.collect.MapMakerInternalMap$WeakKeyDummyValueEntry, com.google.common.collect.MapMakerInternalMap$1);
    Code:
       0: aload_0
       1: aload_1
       2: aload_2
       3: iload_3
       4: aload         4
       6: invokespecial #1                  // Method "<init>":(Ljava/lang/ref/ReferenceQueue;Ljava/lang/Object;ILcom/google/common/collect/MapMakerInternalMap$WeakKeyDummyValueEntry;)V
       9: return
}
