Compiled from "MapMakerInternalMap.java"
final class com.google.common.collect.MapMakerInternalMap$WeakKeyStrongValueEntry$LinkedWeakKeyStrongValueEntry<K, V> extends com.google.common.collect.MapMakerInternalMap$WeakKeyStrongValueEntry<K, V> {
  private final com.google.common.collect.MapMakerInternalMap$WeakKeyStrongValueEntry<K, V> next;

  private com.google.common.collect.MapMakerInternalMap$WeakKeyStrongValueEntry$LinkedWeakKeyStrongValueEntry(java.lang.ref.ReferenceQueue<K>, K, int, com.google.common.collect.MapMakerInternalMap$WeakKeyStrongValueEntry<K, V>);
    Code:
       0: aload_0
       1: aload_1
       2: aload_2
       3: iload_3
       4: aconst_null
       5: invokespecial #2                  // Method com/google/common/collect/MapMakerInternalMap$WeakKeyStrongValueEntry."<init>":(Ljava/lang/ref/ReferenceQueue;Ljava/lang/Object;ILcom/google/common/collect/MapMakerInternalMap$1;)V
       8: aload_0
       9: aload         4
      11: putfield      #3                  // Field next:Lcom/google/common/collect/MapMakerInternalMap$WeakKeyStrongValueEntry;
      14: return

  public com.google.common.collect.MapMakerInternalMap$WeakKeyStrongValueEntry<K, V> getNext();
    Code:
       0: aload_0
       1: getfield      #3                  // Field next:Lcom/google/common/collect/MapMakerInternalMap$WeakKeyStrongValueEntry;
       4: areturn

  public com.google.common.collect.MapMakerInternalMap$InternalEntry getNext();
    Code:
       0: aload_0
       1: invokevirtual #4                  // Method getNext:()Lcom/google/common/collect/MapMakerInternalMap$WeakKeyStrongValueEntry;
       4: areturn

  com.google.common.collect.MapMakerInternalMap$WeakKeyStrongValueEntry$LinkedWeakKeyStrongValueEntry(java.lang.ref.ReferenceQueue, java.lang.Object, int, com.google.common.collect.MapMakerInternalMap$WeakKeyStrongValueEntry, com.google.common.collect.MapMakerInternalMap$1);
    Code:
       0: aload_0
       1: aload_1
       2: aload_2
       3: iload_3
       4: aload         4
       6: invokespecial #1                  // Method "<init>":(Ljava/lang/ref/ReferenceQueue;Ljava/lang/Object;ILcom/google/common/collect/MapMakerInternalMap$WeakKeyStrongValueEntry;)V
       9: return
}
