Compiled from "MapMakerInternalMap.java"
final class com.google.common.collect.MapMakerInternalMap$WeakKeyWeakValueEntry$Helper<K, V> implements com.google.common.collect.MapMakerInternalMap$InternalEntryHelper<K, V, com.google.common.collect.MapMakerInternalMap$WeakKeyWeakValueEntry<K, V>, com.google.common.collect.MapMakerInternalMap$WeakKeyWeakValueSegment<K, V>> {
  private static final com.google.common.collect.MapMakerInternalMap$WeakKeyWeakValueEntry$Helper<?, ?> INSTANCE;

  com.google.common.collect.MapMakerInternalMap$WeakKeyWeakValueEntry$Helper();
    Code:
       0: aload_0
       1: invokespecial #1                  // Method java/lang/Object."<init>":()V
       4: return

  static <K, V> com.google.common.collect.MapMakerInternalMap$WeakKeyWeakValueEntry$Helper<K, V> instance();
    Code:
       0: getstatic     #2                  // Field INSTANCE:Lcom/google/common/collect/MapMakerInternalMap$WeakKeyWeakValueEntry$Helper;
       3: areturn

  public com.google.common.collect.MapMakerInternalMap$Strength keyStrength();
    Code:
       0: getstatic     #3                  // Field com/google/common/collect/MapMakerInternalMap$Strength.WEAK:Lcom/google/common/collect/MapMakerInternalMap$Strength;
       3: areturn

  public com.google.common.collect.MapMakerInternalMap$Strength valueStrength();
    Code:
       0: getstatic     #3                  // Field com/google/common/collect/MapMakerInternalMap$Strength.WEAK:Lcom/google/common/collect/MapMakerInternalMap$Strength;
       3: areturn

  public com.google.common.collect.MapMakerInternalMap$WeakKeyWeakValueSegment<K, V> newSegment(com.google.common.collect.MapMakerInternalMap<K, V, com.google.common.collect.MapMakerInternalMap$WeakKeyWeakValueEntry<K, V>, com.google.common.collect.MapMakerInternalMap$WeakKeyWeakValueSegment<K, V>>, int);
    Code:
       0: new           #4                  // class com/google/common/collect/MapMakerInternalMap$WeakKeyWeakValueSegment
       3: dup
       4: aload_1
       5: iload_2
       6: invokespecial #5                  // Method com/google/common/collect/MapMakerInternalMap$WeakKeyWeakValueSegment."<init>":(Lcom/google/common/collect/MapMakerInternalMap;I)V
       9: areturn

  public com.google.common.collect.MapMakerInternalMap$WeakKeyWeakValueEntry<K, V> copy(com.google.common.collect.MapMakerInternalMap$WeakKeyWeakValueSegment<K, V>, com.google.common.collect.MapMakerInternalMap$WeakKeyWeakValueEntry<K, V>, com.google.common.collect.MapMakerInternalMap$WeakKeyWeakValueEntry<K, V>);
    Code:
       0: aload_2
       1: invokevirtual #6                  // Method com/google/common/collect/MapMakerInternalMap$WeakKeyWeakValueEntry.getKey:()Ljava/lang/Object;
       4: astore        4
       6: aload         4
       8: ifnonnull     13
      11: aconst_null
      12: areturn
      13: aload_2
      14: invokestatic  #7                  // Method com/google/common/collect/MapMakerInternalMap$Segment.isCollected:(Lcom/google/common/collect/MapMakerInternalMap$InternalEntry;)Z
      17: ifeq          22
      20: aconst_null
      21: areturn
      22: aload_0
      23: aload_1
      24: aload         4
      26: aload_2
      27: getfield      #8                  // Field com/google/common/collect/MapMakerInternalMap$WeakKeyWeakValueEntry.hash:I
      30: aload_3
      31: invokevirtual #9                  // Method newEntry:(Lcom/google/common/collect/MapMakerInternalMap$WeakKeyWeakValueSegment;Ljava/lang/Object;ILcom/google/common/collect/MapMakerInternalMap$WeakKeyWeakValueEntry;)Lcom/google/common/collect/MapMakerInternalMap$WeakKeyWeakValueEntry;
      34: astore        5
      36: aload         5
      38: aload_2
      39: invokestatic  #10                 // Method com/google/common/collect/MapMakerInternalMap$WeakKeyWeakValueEntry.access$1400:(Lcom/google/common/collect/MapMakerInternalMap$WeakKeyWeakValueEntry;)Lcom/google/common/collect/MapMakerInternalMap$WeakValueReference;
      42: aload_1
      43: invokestatic  #11                 // Method com/google/common/collect/MapMakerInternalMap$WeakKeyWeakValueSegment.access$1500:(Lcom/google/common/collect/MapMakerInternalMap$WeakKeyWeakValueSegment;)Ljava/lang/ref/ReferenceQueue;
      46: aload         5
      48: invokeinterface #12,  3           // InterfaceMethod com/google/common/collect/MapMakerInternalMap$WeakValueReference.copyFor:(Ljava/lang/ref/ReferenceQueue;Lcom/google/common/collect/MapMakerInternalMap$InternalEntry;)Lcom/google/common/collect/MapMakerInternalMap$WeakValueReference;
      53: invokestatic  #13                 // Method com/google/common/collect/MapMakerInternalMap$WeakKeyWeakValueEntry.access$1402:(Lcom/google/common/collect/MapMakerInternalMap$WeakKeyWeakValueEntry;Lcom/google/common/collect/MapMakerInternalMap$WeakValueReference;)Lcom/google/common/collect/MapMakerInternalMap$WeakValueReference;
      56: pop
      57: aload         5
      59: areturn

  public void setValue(com.google.common.collect.MapMakerInternalMap$WeakKeyWeakValueSegment<K, V>, com.google.common.collect.MapMakerInternalMap$WeakKeyWeakValueEntry<K, V>, V);
    Code:
       0: aload_2
       1: invokestatic  #10                 // Method com/google/common/collect/MapMakerInternalMap$WeakKeyWeakValueEntry.access$1400:(Lcom/google/common/collect/MapMakerInternalMap$WeakKeyWeakValueEntry;)Lcom/google/common/collect/MapMakerInternalMap$WeakValueReference;
       4: astore        4
       6: aload_2
       7: new           #14                 // class com/google/common/collect/MapMakerInternalMap$WeakValueReferenceImpl
      10: dup
      11: aload_1
      12: invokestatic  #11                 // Method com/google/common/collect/MapMakerInternalMap$WeakKeyWeakValueSegment.access$1500:(Lcom/google/common/collect/MapMakerInternalMap$WeakKeyWeakValueSegment;)Ljava/lang/ref/ReferenceQueue;
      15: aload_3
      16: aload_2
      17: invokespecial #15                 // Method com/google/common/collect/MapMakerInternalMap$WeakValueReferenceImpl."<init>":(Ljava/lang/ref/ReferenceQueue;Ljava/lang/Object;Lcom/google/common/collect/MapMakerInternalMap$InternalEntry;)V
      20: invokestatic  #13                 // Method com/google/common/collect/MapMakerInternalMap$WeakKeyWeakValueEntry.access$1402:(Lcom/google/common/collect/MapMakerInternalMap$WeakKeyWeakValueEntry;Lcom/google/common/collect/MapMakerInternalMap$WeakValueReference;)Lcom/google/common/collect/MapMakerInternalMap$WeakValueReference;
      23: pop
      24: aload         4
      26: invokeinterface #16,  1           // InterfaceMethod com/google/common/collect/MapMakerInternalMap$WeakValueReference.clear:()V
      31: return

  public com.google.common.collect.MapMakerInternalMap$WeakKeyWeakValueEntry<K, V> newEntry(com.google.common.collect.MapMakerInternalMap$WeakKeyWeakValueSegment<K, V>, K, int, com.google.common.collect.MapMakerInternalMap$WeakKeyWeakValueEntry<K, V>);
    Code:
       0: aload         4
       2: ifnonnull     21
       5: new           #17                 // class com/google/common/collect/MapMakerInternalMap$WeakKeyWeakValueEntry
       8: dup
       9: aload_1
      10: invokestatic  #18                 // Method com/google/common/collect/MapMakerInternalMap$WeakKeyWeakValueSegment.access$1600:(Lcom/google/common/collect/MapMakerInternalMap$WeakKeyWeakValueSegment;)Ljava/lang/ref/ReferenceQueue;
      13: aload_2
      14: iload_3
      15: invokespecial #19                 // Method com/google/common/collect/MapMakerInternalMap$WeakKeyWeakValueEntry."<init>":(Ljava/lang/ref/ReferenceQueue;Ljava/lang/Object;I)V
      18: goto          36
      21: new           #20                 // class com/google/common/collect/MapMakerInternalMap$WeakKeyWeakValueEntry$LinkedWeakKeyWeakValueEntry
      24: dup
      25: aload_1
      26: invokestatic  #18                 // Method com/google/common/collect/MapMakerInternalMap$WeakKeyWeakValueSegment.access$1600:(Lcom/google/common/collect/MapMakerInternalMap$WeakKeyWeakValueSegment;)Ljava/lang/ref/ReferenceQueue;
      29: aload_2
      30: iload_3
      31: aload         4
      33: invokespecial #21                 // Method com/google/common/collect/MapMakerInternalMap$WeakKeyWeakValueEntry$LinkedWeakKeyWeakValueEntry."<init>":(Ljava/lang/ref/ReferenceQueue;Ljava/lang/Object;ILcom/google/common/collect/MapMakerInternalMap$WeakKeyWeakValueEntry;)V
      36: areturn

  public void setValue(com.google.common.collect.MapMakerInternalMap$Segment, com.google.common.collect.MapMakerInternalMap$InternalEntry, java.lang.Object);
    Code:
       0: aload_0
       1: aload_1
       2: checkcast     #4                  // class com/google/common/collect/MapMakerInternalMap$WeakKeyWeakValueSegment
       5: aload_2
       6: checkcast     #17                 // class com/google/common/collect/MapMakerInternalMap$WeakKeyWeakValueEntry
       9: aload_3
      10: invokevirtual #22                 // Method setValue:(Lcom/google/common/collect/MapMakerInternalMap$WeakKeyWeakValueSegment;Lcom/google/common/collect/MapMakerInternalMap$WeakKeyWeakValueEntry;Ljava/lang/Object;)V
      13: return

  public com.google.common.collect.MapMakerInternalMap$InternalEntry copy(com.google.common.collect.MapMakerInternalMap$Segment, com.google.common.collect.MapMakerInternalMap$InternalEntry, com.google.common.collect.MapMakerInternalMap$InternalEntry);
    Code:
       0: aload_0
       1: aload_1
       2: checkcast     #4                  // class com/google/common/collect/MapMakerInternalMap$WeakKeyWeakValueSegment
       5: aload_2
       6: checkcast     #17                 // class com/google/common/collect/MapMakerInternalMap$WeakKeyWeakValueEntry
       9: aload_3
      10: checkcast     #17                 // class com/google/common/collect/MapMakerInternalMap$WeakKeyWeakValueEntry
      13: invokevirtual #23                 // Method copy:(Lcom/google/common/collect/MapMakerInternalMap$WeakKeyWeakValueSegment;Lcom/google/common/collect/MapMakerInternalMap$WeakKeyWeakValueEntry;Lcom/google/common/collect/MapMakerInternalMap$WeakKeyWeakValueEntry;)Lcom/google/common/collect/MapMakerInternalMap$WeakKeyWeakValueEntry;
      16: areturn

  public com.google.common.collect.MapMakerInternalMap$InternalEntry newEntry(com.google.common.collect.MapMakerInternalMap$Segment, java.lang.Object, int, com.google.common.collect.MapMakerInternalMap$InternalEntry);
    Code:
       0: aload_0
       1: aload_1
       2: checkcast     #4                  // class com/google/common/collect/MapMakerInternalMap$WeakKeyWeakValueSegment
       5: aload_2
       6: iload_3
       7: aload         4
       9: checkcast     #17                 // class com/google/common/collect/MapMakerInternalMap$WeakKeyWeakValueEntry
      12: invokevirtual #9                  // Method newEntry:(Lcom/google/common/collect/MapMakerInternalMap$WeakKeyWeakValueSegment;Ljava/lang/Object;ILcom/google/common/collect/MapMakerInternalMap$WeakKeyWeakValueEntry;)Lcom/google/common/collect/MapMakerInternalMap$WeakKeyWeakValueEntry;
      15: areturn

  public com.google.common.collect.MapMakerInternalMap$Segment newSegment(com.google.common.collect.MapMakerInternalMap, int);
    Code:
       0: aload_0
       1: aload_1
       2: iload_2
       3: invokevirtual #24                 // Method newSegment:(Lcom/google/common/collect/MapMakerInternalMap;I)Lcom/google/common/collect/MapMakerInternalMap$WeakKeyWeakValueSegment;
       6: areturn

  static {};
    Code:
       0: new           #25                 // class com/google/common/collect/MapMakerInternalMap$WeakKeyWeakValueEntry$Helper
       3: dup
       4: invokespecial #26                 // Method "<init>":()V
       7: putstatic     #2                  // Field INSTANCE:Lcom/google/common/collect/MapMakerInternalMap$WeakKeyWeakValueEntry$Helper;
      10: return
}
