Compiled from "MapMakerInternalMap.java"
final class com.google.common.collect.MapMakerInternalMap$WeakKeyStrongValueEntry$Helper<K, V> implements com.google.common.collect.MapMakerInternalMap$InternalEntryHelper<K, V, com.google.common.collect.MapMakerInternalMap$WeakKeyStrongValueEntry<K, V>, com.google.common.collect.MapMakerInternalMap$WeakKeyStrongValueSegment<K, V>> {
  private static final com.google.common.collect.MapMakerInternalMap$WeakKeyStrongValueEntry$Helper<?, ?> INSTANCE;

  com.google.common.collect.MapMakerInternalMap$WeakKeyStrongValueEntry$Helper();
    Code:
       0: aload_0
       1: invokespecial #1                  // Method java/lang/Object."<init>":()V
       4: return

  static <K, V> com.google.common.collect.MapMakerInternalMap$WeakKeyStrongValueEntry$Helper<K, V> instance();
    Code:
       0: getstatic     #2                  // Field INSTANCE:Lcom/google/common/collect/MapMakerInternalMap$WeakKeyStrongValueEntry$Helper;
       3: areturn

  public com.google.common.collect.MapMakerInternalMap$Strength keyStrength();
    Code:
       0: getstatic     #3                  // Field com/google/common/collect/MapMakerInternalMap$Strength.WEAK:Lcom/google/common/collect/MapMakerInternalMap$Strength;
       3: areturn

  public com.google.common.collect.MapMakerInternalMap$Strength valueStrength();
    Code:
       0: getstatic     #4                  // Field com/google/common/collect/MapMakerInternalMap$Strength.STRONG:Lcom/google/common/collect/MapMakerInternalMap$Strength;
       3: areturn

  public com.google.common.collect.MapMakerInternalMap$WeakKeyStrongValueSegment<K, V> newSegment(com.google.common.collect.MapMakerInternalMap<K, V, com.google.common.collect.MapMakerInternalMap$WeakKeyStrongValueEntry<K, V>, com.google.common.collect.MapMakerInternalMap$WeakKeyStrongValueSegment<K, V>>, int);
    Code:
       0: new           #5                  // class com/google/common/collect/MapMakerInternalMap$WeakKeyStrongValueSegment
       3: dup
       4: aload_1
       5: iload_2
       6: invokespecial #6                  // Method com/google/common/collect/MapMakerInternalMap$WeakKeyStrongValueSegment."<init>":(Lcom/google/common/collect/MapMakerInternalMap;I)V
       9: areturn

  public com.google.common.collect.MapMakerInternalMap$WeakKeyStrongValueEntry<K, V> copy(com.google.common.collect.MapMakerInternalMap$WeakKeyStrongValueSegment<K, V>, com.google.common.collect.MapMakerInternalMap$WeakKeyStrongValueEntry<K, V>, com.google.common.collect.MapMakerInternalMap$WeakKeyStrongValueEntry<K, V>);
    Code:
       0: aload_2
       1: invokevirtual #7                  // Method com/google/common/collect/MapMakerInternalMap$WeakKeyStrongValueEntry.getKey:()Ljava/lang/Object;
       4: astore        4
       6: aload         4
       8: ifnonnull     13
      11: aconst_null
      12: areturn
      13: aload_0
      14: aload_1
      15: aload         4
      17: aload_2
      18: getfield      #8                  // Field com/google/common/collect/MapMakerInternalMap$WeakKeyStrongValueEntry.hash:I
      21: aload_3
      22: invokevirtual #9                  // Method newEntry:(Lcom/google/common/collect/MapMakerInternalMap$WeakKeyStrongValueSegment;Ljava/lang/Object;ILcom/google/common/collect/MapMakerInternalMap$WeakKeyStrongValueEntry;)Lcom/google/common/collect/MapMakerInternalMap$WeakKeyStrongValueEntry;
      25: astore        5
      27: aload         5
      29: aload_2
      30: invokestatic  #10                 // Method com/google/common/collect/MapMakerInternalMap$WeakKeyStrongValueEntry.access$1100:(Lcom/google/common/collect/MapMakerInternalMap$WeakKeyStrongValueEntry;)Ljava/lang/Object;
      33: invokestatic  #11                 // Method com/google/common/collect/MapMakerInternalMap$WeakKeyStrongValueEntry.access$1102:(Lcom/google/common/collect/MapMakerInternalMap$WeakKeyStrongValueEntry;Ljava/lang/Object;)Ljava/lang/Object;
      36: pop
      37: aload         5
      39: areturn

  public void setValue(com.google.common.collect.MapMakerInternalMap$WeakKeyStrongValueSegment<K, V>, com.google.common.collect.MapMakerInternalMap$WeakKeyStrongValueEntry<K, V>, V);
    Code:
       0: aload_2
       1: aload_3
       2: invokestatic  #11                 // Method com/google/common/collect/MapMakerInternalMap$WeakKeyStrongValueEntry.access$1102:(Lcom/google/common/collect/MapMakerInternalMap$WeakKeyStrongValueEntry;Ljava/lang/Object;)Ljava/lang/Object;
       5: pop
       6: return

  public com.google.common.collect.MapMakerInternalMap$WeakKeyStrongValueEntry<K, V> newEntry(com.google.common.collect.MapMakerInternalMap$WeakKeyStrongValueSegment<K, V>, K, int, com.google.common.collect.MapMakerInternalMap$WeakKeyStrongValueEntry<K, V>);
    Code:
       0: aload         4
       2: ifnonnull     22
       5: new           #12                 // class com/google/common/collect/MapMakerInternalMap$WeakKeyStrongValueEntry
       8: dup
       9: aload_1
      10: invokestatic  #13                 // Method com/google/common/collect/MapMakerInternalMap$WeakKeyStrongValueSegment.access$1200:(Lcom/google/common/collect/MapMakerInternalMap$WeakKeyStrongValueSegment;)Ljava/lang/ref/ReferenceQueue;
      13: aload_2
      14: iload_3
      15: aconst_null
      16: invokespecial #14                 // Method com/google/common/collect/MapMakerInternalMap$WeakKeyStrongValueEntry."<init>":(Ljava/lang/ref/ReferenceQueue;Ljava/lang/Object;ILcom/google/common/collect/MapMakerInternalMap$1;)V
      19: goto          38
      22: new           #15                 // class com/google/common/collect/MapMakerInternalMap$WeakKeyStrongValueEntry$LinkedWeakKeyStrongValueEntry
      25: dup
      26: aload_1
      27: invokestatic  #13                 // Method com/google/common/collect/MapMakerInternalMap$WeakKeyStrongValueSegment.access$1200:(Lcom/google/common/collect/MapMakerInternalMap$WeakKeyStrongValueSegment;)Ljava/lang/ref/ReferenceQueue;
      30: aload_2
      31: iload_3
      32: aload         4
      34: aconst_null
      35: invokespecial #16                 // Method com/google/common/collect/MapMakerInternalMap$WeakKeyStrongValueEntry$LinkedWeakKeyStrongValueEntry."<init>":(Ljava/lang/ref/ReferenceQueue;Ljava/lang/Object;ILcom/google/common/collect/MapMakerInternalMap$WeakKeyStrongValueEntry;Lcom/google/common/collect/MapMakerInternalMap$1;)V
      38: areturn

  public void setValue(com.google.common.collect.MapMakerInternalMap$Segment, com.google.common.collect.MapMakerInternalMap$InternalEntry, java.lang.Object);
    Code:
       0: aload_0
       1: aload_1
       2: checkcast     #5                  // class com/google/common/collect/MapMakerInternalMap$WeakKeyStrongValueSegment
       5: aload_2
       6: checkcast     #12                 // class com/google/common/collect/MapMakerInternalMap$WeakKeyStrongValueEntry
       9: aload_3
      10: invokevirtual #17                 // Method setValue:(Lcom/google/common/collect/MapMakerInternalMap$WeakKeyStrongValueSegment;Lcom/google/common/collect/MapMakerInternalMap$WeakKeyStrongValueEntry;Ljava/lang/Object;)V
      13: return

  public com.google.common.collect.MapMakerInternalMap$InternalEntry copy(com.google.common.collect.MapMakerInternalMap$Segment, com.google.common.collect.MapMakerInternalMap$InternalEntry, com.google.common.collect.MapMakerInternalMap$InternalEntry);
    Code:
       0: aload_0
       1: aload_1
       2: checkcast     #5                  // class com/google/common/collect/MapMakerInternalMap$WeakKeyStrongValueSegment
       5: aload_2
       6: checkcast     #12                 // class com/google/common/collect/MapMakerInternalMap$WeakKeyStrongValueEntry
       9: aload_3
      10: checkcast     #12                 // class com/google/common/collect/MapMakerInternalMap$WeakKeyStrongValueEntry
      13: invokevirtual #18                 // Method copy:(Lcom/google/common/collect/MapMakerInternalMap$WeakKeyStrongValueSegment;Lcom/google/common/collect/MapMakerInternalMap$WeakKeyStrongValueEntry;Lcom/google/common/collect/MapMakerInternalMap$WeakKeyStrongValueEntry;)Lcom/google/common/collect/MapMakerInternalMap$WeakKeyStrongValueEntry;
      16: areturn

  public com.google.common.collect.MapMakerInternalMap$InternalEntry newEntry(com.google.common.collect.MapMakerInternalMap$Segment, java.lang.Object, int, com.google.common.collect.MapMakerInternalMap$InternalEntry);
    Code:
       0: aload_0
       1: aload_1
       2: checkcast     #5                  // class com/google/common/collect/MapMakerInternalMap$WeakKeyStrongValueSegment
       5: aload_2
       6: iload_3
       7: aload         4
       9: checkcast     #12                 // class com/google/common/collect/MapMakerInternalMap$WeakKeyStrongValueEntry
      12: invokevirtual #9                  // Method newEntry:(Lcom/google/common/collect/MapMakerInternalMap$WeakKeyStrongValueSegment;Ljava/lang/Object;ILcom/google/common/collect/MapMakerInternalMap$WeakKeyStrongValueEntry;)Lcom/google/common/collect/MapMakerInternalMap$WeakKeyStrongValueEntry;
      15: areturn

  public com.google.common.collect.MapMakerInternalMap$Segment newSegment(com.google.common.collect.MapMakerInternalMap, int);
    Code:
       0: aload_0
       1: aload_1
       2: iload_2
       3: invokevirtual #19                 // Method newSegment:(Lcom/google/common/collect/MapMakerInternalMap;I)Lcom/google/common/collect/MapMakerInternalMap$WeakKeyStrongValueSegment;
       6: areturn

  static {};
    Code:
       0: new           #20                 // class com/google/common/collect/MapMakerInternalMap$WeakKeyStrongValueEntry$Helper
       3: dup
       4: invokespecial #21                 // Method "<init>":()V
       7: putstatic     #2                  // Field INSTANCE:Lcom/google/common/collect/MapMakerInternalMap$WeakKeyStrongValueEntry$Helper;
      10: return
}
