Compiled from "Multimaps.java"
class com.google.common.collect.Multimaps$AsMap$EntrySet extends com.google.common.collect.Maps$EntrySet<K, java.util.Collection<V>> {
  final com.google.common.collect.Multimaps$AsMap this$0;

  com.google.common.collect.Multimaps$AsMap$EntrySet(com.google.common.collect.Multimaps$AsMap);
    Code:
       0: aload_0
       1: aload_1
       2: putfield      #1                  // Field this$0:Lcom/google/common/collect/Multimaps$AsMap;
       5: aload_0
       6: invokespecial #2                  // Method com/google/common/collect/Maps$EntrySet."<init>":()V
       9: return

  java.util.Map<K, java.util.Collection<V>> map();
    Code:
       0: aload_0
       1: getfield      #1                  // Field this$0:Lcom/google/common/collect/Multimaps$AsMap;
       4: areturn

  public java.util.Iterator<java.util.Map$Entry<K, java.util.Collection<V>>> iterator();
    Code:
       0: aload_0
       1: getfield      #1                  // Field this$0:Lcom/google/common/collect/Multimaps$AsMap;
       4: invokestatic  #3                  // Method com/google/common/collect/Multimaps$AsMap.access$200:(Lcom/google/common/collect/Multimaps$AsMap;)Lcom/google/common/collect/Multimap;
       7: invokeinterface #4,  1            // InterfaceMethod com/google/common/collect/Multimap.keySet:()Ljava/util/Set;
      12: aload_0
      13: invokedynamic #5,  0              // InvokeDynamic #0:apply:(Lcom/google/common/collect/Multimaps$AsMap$EntrySet;)Lcom/google/common/base/Function;
      18: invokestatic  #6                  // Method com/google/common/collect/Maps.asMapEntryIterator:(Ljava/util/Set;Lcom/google/common/base/Function;)Ljava/util/Iterator;
      21: areturn

  public boolean remove(java.lang.Object);
    Code:
       0: aload_0
       1: aload_1
       2: invokevirtual #7                  // Method contains:(Ljava/lang/Object;)Z
       5: ifne          10
       8: iconst_0
       9: ireturn
      10: aload_1
      11: checkcast     #8                  // class java/util/Map$Entry
      14: invokestatic  #9                  // Method java/util/Objects.requireNonNull:(Ljava/lang/Object;)Ljava/lang/Object;
      17: checkcast     #8                  // class java/util/Map$Entry
      20: astore_2
      21: aload_0
      22: getfield      #1                  // Field this$0:Lcom/google/common/collect/Multimaps$AsMap;
      25: aload_2
      26: invokeinterface #10,  1           // InterfaceMethod java/util/Map$Entry.getKey:()Ljava/lang/Object;
      31: invokevirtual #11                 // Method com/google/common/collect/Multimaps$AsMap.removeValuesForKey:(Ljava/lang/Object;)V
      34: iconst_1
      35: ireturn

  private java.util.Collection lambda$iterator$0(java.lang.Object);
    Code:
       0: aload_0
       1: getfield      #1                  // Field this$0:Lcom/google/common/collect/Multimaps$AsMap;
       4: invokestatic  #3                  // Method com/google/common/collect/Multimaps$AsMap.access$200:(Lcom/google/common/collect/Multimaps$AsMap;)Lcom/google/common/collect/Multimap;
       7: aload_1
       8: invokeinterface #12,  2           // InterfaceMethod com/google/common/collect/Multimap.get:(Ljava/lang/Object;)Ljava/util/Collection;
      13: areturn
}
