Compiled from "AbstractRouter.java"
public abstract class org.apache.dubbo.rpc.cluster.router.AbstractRouter implements org.apache.dubbo.rpc.cluster.Router {
  private int priority;

  private boolean force;

  private org.apache.dubbo.common.URL url;

  private org.apache.dubbo.rpc.cluster.governance.GovernanceRuleRepository ruleRepository;

  public org.apache.dubbo.rpc.cluster.router.AbstractRouter(org.apache.dubbo.common.URL);
    Code:
       0: aload_0
       1: invokespecial #1                  // Method java/lang/Object."<init>":()V
       4: aload_0
       5: ldc           #3                  // int 2147483647
       7: putfield      #4                  // Field priority:I
      10: aload_0
      11: iconst_0
      12: putfield      #5                  // Field force:Z
      15: aload_0
      16: aload_1
      17: invokevirtual #6                  // Method org/apache/dubbo/common/URL.getOrDefaultModuleModel:()Lorg/apache/dubbo/rpc/model/ModuleModel;
      20: ldc           #7                  // class org/apache/dubbo/rpc/cluster/governance/GovernanceRuleRepository
      22: invokevirtual #8                  // Method org/apache/dubbo/rpc/model/ModuleModel.getExtensionLoader:(Ljava/lang/Class;)Lorg/apache/dubbo/common/extension/ExtensionLoader;
      25: invokevirtual #9                  // Method org/apache/dubbo/common/extension/ExtensionLoader.getDefaultExtension:()Ljava/lang/Object;
      28: checkcast     #7                  // class org/apache/dubbo/rpc/cluster/governance/GovernanceRuleRepository
      31: putfield      #10                 // Field ruleRepository:Lorg/apache/dubbo/rpc/cluster/governance/GovernanceRuleRepository;
      34: aload_0
      35: aload_1
      36: putfield      #11                 // Field url:Lorg/apache/dubbo/common/URL;
      39: return

  public org.apache.dubbo.rpc.cluster.router.AbstractRouter();
    Code:
       0: aload_0
       1: invokespecial #1                  // Method java/lang/Object."<init>":()V
       4: aload_0
       5: ldc           #3                  // int 2147483647
       7: putfield      #4                  // Field priority:I
      10: aload_0
      11: iconst_0
      12: putfield      #5                  // Field force:Z
      15: return

  public org.apache.dubbo.common.URL getUrl();
    Code:
       0: aload_0
       1: getfield      #11                 // Field url:Lorg/apache/dubbo/common/URL;
       4: areturn

  public void setUrl(org.apache.dubbo.common.URL);
    Code:
       0: aload_0
       1: aload_1
       2: putfield      #11                 // Field url:Lorg/apache/dubbo/common/URL;
       5: return

  public boolean isRuntime();
    Code:
       0: iconst_1
       1: ireturn

  public boolean isForce();
    Code:
       0: aload_0
       1: getfield      #5                  // Field force:Z
       4: ireturn

  public void setForce(boolean);
    Code:
       0: aload_0
       1: iload_1
       2: putfield      #5                  // Field force:Z
       5: return

  public int getPriority();
    Code:
       0: aload_0
       1: getfield      #4                  // Field priority:I
       4: ireturn

  public void setPriority(int);
    Code:
       0: aload_0
       1: iload_1
       2: putfield      #4                  // Field priority:I
       5: return

  public org.apache.dubbo.rpc.cluster.governance.GovernanceRuleRepository getRuleRepository();
    Code:
       0: aload_0
       1: getfield      #10                 // Field ruleRepository:Lorg/apache/dubbo/rpc/cluster/governance/GovernanceRuleRepository;
       4: areturn
}
