Compiled from "RouterResult.java"
public class org.apache.dubbo.rpc.cluster.router.RouterResult<T> {
  private final boolean needContinueRoute;

  private final java.util.List<T> result;

  private final java.lang.String message;

  public org.apache.dubbo.rpc.cluster.router.RouterResult(java.util.List<T>);
    Code:
       0: aload_0
       1: invokespecial #1                  // Method java/lang/Object."<init>":()V
       4: aload_0
       5: iconst_1
       6: putfield      #2                  // Field needContinueRoute:Z
       9: aload_0
      10: aload_1
      11: putfield      #3                  // Field result:Ljava/util/List;
      14: aload_0
      15: aconst_null
      16: putfield      #4                  // Field message:Ljava/lang/String;
      19: return

  public org.apache.dubbo.rpc.cluster.router.RouterResult(java.util.List<T>, java.lang.String);
    Code:
       0: aload_0
       1: invokespecial #1                  // Method java/lang/Object."<init>":()V
       4: aload_0
       5: iconst_1
       6: putfield      #2                  // Field needContinueRoute:Z
       9: aload_0
      10: aload_1
      11: putfield      #3                  // Field result:Ljava/util/List;
      14: aload_0
      15: aload_2
      16: putfield      #4                  // Field message:Ljava/lang/String;
      19: return

  public org.apache.dubbo.rpc.cluster.router.RouterResult(boolean, java.util.List<T>, java.lang.String);
    Code:
       0: aload_0
       1: invokespecial #1                  // Method java/lang/Object."<init>":()V
       4: aload_0
       5: iload_1
       6: putfield      #2                  // Field needContinueRoute:Z
       9: aload_0
      10: aload_2
      11: putfield      #3                  // Field result:Ljava/util/List;
      14: aload_0
      15: aload_3
      16: putfield      #4                  // Field message:Ljava/lang/String;
      19: return

  public boolean isNeedContinueRoute();
    Code:
       0: aload_0
       1: getfield      #2                  // Field needContinueRoute:Z
       4: ireturn

  public java.util.List<T> getResult();
    Code:
       0: aload_0
       1: getfield      #3                  // Field result:Ljava/util/List;
       4: areturn

  public java.lang.String getMessage();
    Code:
       0: aload_0
       1: getfield      #4                  // Field message:Ljava/lang/String;
       4: areturn
}
