Compiled from "RouterSnapshotSwitcher.java"
public class org.apache.dubbo.rpc.cluster.router.RouterSnapshotSwitcher {
  private volatile boolean enable;

  private final java.util.Set<java.lang.String> enabledService;

  private static final int MAX_LENGTH;

  private final java.util.concurrent.atomic.AtomicInteger offset;

  private volatile java.lang.String[] recentSnapshot;

  public org.apache.dubbo.rpc.cluster.router.RouterSnapshotSwitcher();
    Code:
       0: aload_0
       1: invokespecial #1                  // Method java/lang/Object."<init>":()V
       4: aload_0
       5: new           #2                  // class org/apache/dubbo/common/utils/ConcurrentHashSet
       8: dup
       9: invokespecial #3                  // Method org/apache/dubbo/common/utils/ConcurrentHashSet."<init>":()V
      12: putfield      #4                  // Field enabledService:Ljava/util/Set;
      15: aload_0
      16: new           #5                  // class java/util/concurrent/atomic/AtomicInteger
      19: dup
      20: iconst_0
      21: invokespecial #6                  // Method java/util/concurrent/atomic/AtomicInteger."<init>":(I)V
      24: putfield      #7                  // Field offset:Ljava/util/concurrent/atomic/AtomicInteger;
      27: aload_0
      28: bipush        32
      30: anewarray     #9                  // class java/lang/String
      33: putfield      #10                 // Field recentSnapshot:[Ljava/lang/String;
      36: return

  public boolean isEnable();
    Code:
       0: aload_0
       1: getfield      #11                 // Field enable:Z
       4: ireturn

  public synchronized void addEnabledService(java.lang.String);
    Code:
       0: aload_0
       1: getfield      #4                  // Field enabledService:Ljava/util/Set;
       4: aload_1
       5: invokeinterface #12,  2           // InterfaceMethod java/util/Set.add:(Ljava/lang/Object;)Z
      10: pop
      11: aload_0
      12: iconst_1
      13: putfield      #11                 // Field enable:Z
      16: aload_0
      17: bipush        32
      19: anewarray     #9                  // class java/lang/String
      22: putfield      #10                 // Field recentSnapshot:[Ljava/lang/String;
      25: return

  public boolean isEnable(java.lang.String);
    Code:
       0: aload_0
       1: getfield      #4                  // Field enabledService:Ljava/util/Set;
       4: aload_1
       5: invokeinterface #13,  2           // InterfaceMethod java/util/Set.contains:(Ljava/lang/Object;)Z
      10: ireturn

  public synchronized void removeEnabledService(java.lang.String);
    Code:
       0: aload_0
       1: getfield      #4                  // Field enabledService:Ljava/util/Set;
       4: aload_1
       5: invokeinterface #14,  2           // InterfaceMethod java/util/Set.remove:(Ljava/lang/Object;)Z
      10: pop
      11: aload_0
      12: aload_0
      13: getfield      #4                  // Field enabledService:Ljava/util/Set;
      16: invokeinterface #15,  1           // InterfaceMethod java/util/Set.size:()I
      21: ifle          28
      24: iconst_1
      25: goto          29
      28: iconst_0
      29: putfield      #11                 // Field enable:Z
      32: aload_0
      33: bipush        32
      35: anewarray     #9                  // class java/lang/String
      38: putfield      #10                 // Field recentSnapshot:[Ljava/lang/String;
      41: return

  public synchronized java.util.Set<java.lang.String> getEnabledService();
    Code:
       0: aload_0
       1: getfield      #4                  // Field enabledService:Ljava/util/Set;
       4: invokestatic  #16                 // Method java/util/Collections.unmodifiableSet:(Ljava/util/Set;)Ljava/util/Set;
       7: areturn

  public void setSnapshot(java.lang.String);
    Code:
       0: aload_0
       1: getfield      #11                 // Field enable:Z
       4: ifeq          47
       7: aload_0
       8: getfield      #10                 // Field recentSnapshot:[Ljava/lang/String;
      11: aload_0
      12: getfield      #7                  // Field offset:Ljava/util/concurrent/atomic/AtomicInteger;
      15: invokevirtual #17                 // Method java/util/concurrent/atomic/AtomicInteger.getAndIncrement:()I
      18: bipush        32
      20: irem
      21: new           #18                 // class java/lang/StringBuilder
      24: dup
      25: invokespecial #19                 // Method java/lang/StringBuilder."<init>":()V
      28: invokestatic  #20                 // Method java/lang/System.currentTimeMillis:()J
      31: invokevirtual #21                 // Method java/lang/StringBuilder.append:(J)Ljava/lang/StringBuilder;
      34: ldc           #22                 // String  -
      36: invokevirtual #23                 // Method java/lang/StringBuilder.append:(Ljava/lang/String;)Ljava/lang/StringBuilder;
      39: aload_1
      40: invokevirtual #23                 // Method java/lang/StringBuilder.append:(Ljava/lang/String;)Ljava/lang/StringBuilder;
      43: invokevirtual #24                 // Method java/lang/StringBuilder.toString:()Ljava/lang/String;
      46: aastore
      47: return

  public java.lang.String[] cloneSnapshot();
    Code:
       0: bipush        32
       2: anewarray     #9                  // class java/lang/String
       5: astore_1
       6: iconst_0
       7: istore_2
       8: iload_2
       9: bipush        32
      11: if_icmpge     29
      14: aload_1
      15: iload_2
      16: aload_0
      17: getfield      #10                 // Field recentSnapshot:[Ljava/lang/String;
      20: iload_2
      21: aaload
      22: aastore
      23: iinc          2, 1
      26: goto          8
      29: aload_1
      30: areturn
}
