Compiled from "RouterSnapshotFilter.java"
public class org.apache.dubbo.rpc.cluster.router.RouterSnapshotFilter implements org.apache.dubbo.rpc.cluster.filter.ClusterFilter,org.apache.dubbo.rpc.BaseFilter$Listener {
  private final org.apache.dubbo.rpc.cluster.router.RouterSnapshotSwitcher switcher;

  private static final org.apache.dubbo.common.logger.Logger logger;

  public org.apache.dubbo.rpc.cluster.router.RouterSnapshotFilter(org.apache.dubbo.rpc.model.FrameworkModel);
    Code:
       0: aload_0
       1: invokespecial #1                  // Method java/lang/Object."<init>":()V
       4: aload_0
       5: aload_1
       6: invokevirtual #2                  // Method org/apache/dubbo/rpc/model/FrameworkModel.getBeanFactory:()Lorg/apache/dubbo/common/beans/factory/ScopeBeanFactory;
       9: ldc           #3                  // class org/apache/dubbo/rpc/cluster/router/RouterSnapshotSwitcher
      11: invokevirtual #4                  // Method org/apache/dubbo/common/beans/factory/ScopeBeanFactory.getBean:(Ljava/lang/Class;)Ljava/lang/Object;
      14: checkcast     #3                  // class org/apache/dubbo/rpc/cluster/router/RouterSnapshotSwitcher
      17: putfield      #5                  // Field switcher:Lorg/apache/dubbo/rpc/cluster/router/RouterSnapshotSwitcher;
      20: return

  public org.apache.dubbo.rpc.Result invoke(org.apache.dubbo.rpc.Invoker<?>, org.apache.dubbo.rpc.Invocation) throws org.apache.dubbo.rpc.RpcException;
    Code:
       0: aload_0
       1: getfield      #5                  // Field switcher:Lorg/apache/dubbo/rpc/cluster/router/RouterSnapshotSwitcher;
       4: invokevirtual #6                  // Method org/apache/dubbo/rpc/cluster/router/RouterSnapshotSwitcher.isEnable:()Z
       7: ifne          18
      10: aload_1
      11: aload_2
      12: invokeinterface #7,  2            // InterfaceMethod org/apache/dubbo/rpc/Invoker.invoke:(Lorg/apache/dubbo/rpc/Invocation;)Lorg/apache/dubbo/rpc/Result;
      17: areturn
      18: getstatic     #8                  // Field logger:Lorg/apache/dubbo/common/logger/Logger;
      21: invokeinterface #9,  1            // InterfaceMethod org/apache/dubbo/common/logger/Logger.isInfoEnabled:()Z
      26: ifne          37
      29: aload_1
      30: aload_2
      31: invokeinterface #7,  2            // InterfaceMethod org/apache/dubbo/rpc/Invoker.invoke:(Lorg/apache/dubbo/rpc/Invocation;)Lorg/apache/dubbo/rpc/Result;
      36: areturn
      37: aload_0
      38: getfield      #5                  // Field switcher:Lorg/apache/dubbo/rpc/cluster/router/RouterSnapshotSwitcher;
      41: aload_2
      42: invokeinterface #10,  1           // InterfaceMethod org/apache/dubbo/rpc/Invocation.getServiceModel:()Lorg/apache/dubbo/rpc/model/ServiceModel;
      47: invokevirtual #11                 // Method org/apache/dubbo/rpc/model/ServiceModel.getServiceKey:()Ljava/lang/String;
      50: invokevirtual #12                 // Method org/apache/dubbo/rpc/cluster/router/RouterSnapshotSwitcher.isEnable:(Ljava/lang/String;)Z
      53: ifne          64
      56: aload_1
      57: aload_2
      58: invokeinterface #7,  2            // InterfaceMethod org/apache/dubbo/rpc/Invoker.invoke:(Lorg/apache/dubbo/rpc/Invocation;)Lorg/apache/dubbo/rpc/Result;
      63: areturn
      64: invokestatic  #13                 // Method org/apache/dubbo/rpc/RpcContext.getServiceContext:()Lorg/apache/dubbo/rpc/RpcServiceContext;
      67: iconst_1
      68: invokevirtual #14                 // Method org/apache/dubbo/rpc/RpcServiceContext.setNeedPrintRouterSnapshot:(Z)V
      71: aload_1
      72: aload_2
      73: invokeinterface #7,  2            // InterfaceMethod org/apache/dubbo/rpc/Invoker.invoke:(Lorg/apache/dubbo/rpc/Invocation;)Lorg/apache/dubbo/rpc/Result;
      78: areturn

  public void onResponse(org.apache.dubbo.rpc.Result, org.apache.dubbo.rpc.Invoker<?>, org.apache.dubbo.rpc.Invocation);
    Code:
       0: invokestatic  #13                 // Method org/apache/dubbo/rpc/RpcContext.getServiceContext:()Lorg/apache/dubbo/rpc/RpcServiceContext;
       3: iconst_0
       4: invokevirtual #14                 // Method org/apache/dubbo/rpc/RpcServiceContext.setNeedPrintRouterSnapshot:(Z)V
       7: return

  public void onError(java.lang.Throwable, org.apache.dubbo.rpc.Invoker<?>, org.apache.dubbo.rpc.Invocation);
    Code:
       0: invokestatic  #13                 // Method org/apache/dubbo/rpc/RpcContext.getServiceContext:()Lorg/apache/dubbo/rpc/RpcServiceContext;
       3: iconst_0
       4: invokevirtual #14                 // Method org/apache/dubbo/rpc/RpcServiceContext.setNeedPrintRouterSnapshot:(Z)V
       7: return

  static {};
    Code:
       0: ldc           #15                 // class org/apache/dubbo/rpc/cluster/router/RouterSnapshotFilter
       2: invokestatic  #16                 // Method org/apache/dubbo/common/logger/LoggerFactory.getLogger:(Ljava/lang/Class;)Lorg/apache/dubbo/common/logger/Logger;
       5: putstatic     #8                  // Field logger:Lorg/apache/dubbo/common/logger/Logger;
       8: return
}
