Compiled from "RouterSnapshotNode.java"
public class org.apache.dubbo.rpc.cluster.router.RouterSnapshotNode<T> {
  private final java.lang.String name;

  private final int beforeSize;

  private int nodeOutputSize;

  private int chainOutputSize;

  private java.lang.String routerMessage;

  private final java.util.List<org.apache.dubbo.rpc.Invoker<T>> inputInvokers;

  private java.util.List<org.apache.dubbo.rpc.Invoker<T>> nodeOutputInvokers;

  private java.util.List<org.apache.dubbo.rpc.Invoker<T>> chainOutputInvokers;

  private final java.util.List<org.apache.dubbo.rpc.cluster.router.RouterSnapshotNode<T>> nextNode;

  private org.apache.dubbo.rpc.cluster.router.RouterSnapshotNode<T> parentNode;

  public org.apache.dubbo.rpc.cluster.router.RouterSnapshotNode(java.lang.String, java.util.List<org.apache.dubbo.rpc.Invoker<T>>);
    Code:
       0: aload_0
       1: invokespecial #1                  // Method java/lang/Object."<init>":()V
       4: aload_0
       5: new           #2                  // class java/util/LinkedList
       8: dup
       9: invokespecial #3                  // Method java/util/LinkedList."<init>":()V
      12: putfield      #4                  // Field nextNode:Ljava/util/List;
      15: aload_0
      16: aload_1
      17: putfield      #5                  // Field name:Ljava/lang/String;
      20: aload_0
      21: aload_2
      22: invokeinterface #6,  1            // InterfaceMethod java/util/List.size:()I
      27: putfield      #7                  // Field beforeSize:I
      30: aload_2
      31: instanceof    #8                  // class org/apache/dubbo/rpc/cluster/router/state/BitList
      34: ifeq          45
      37: aload_0
      38: aload_2
      39: putfield      #9                  // Field inputInvokers:Ljava/util/List;
      42: goto          94
      45: aload_0
      46: new           #10                 // class java/util/ArrayList
      49: dup
      50: iconst_5
      51: invokespecial #11                 // Method java/util/ArrayList."<init>":(I)V
      54: putfield      #9                  // Field inputInvokers:Ljava/util/List;
      57: iconst_0
      58: istore_3
      59: iload_3
      60: iconst_5
      61: aload_0
      62: getfield      #7                  // Field beforeSize:I
      65: invokestatic  #12                 // Method java/lang/Math.min:(II)I
      68: if_icmpge     94
      71: aload_0
      72: getfield      #9                  // Field inputInvokers:Ljava/util/List;
      75: aload_2
      76: iload_3
      77: invokeinterface #13,  2           // InterfaceMethod java/util/List.get:(I)Ljava/lang/Object;
      82: invokeinterface #14,  2           // InterfaceMethod java/util/List.add:(Ljava/lang/Object;)Z
      87: pop
      88: iinc          3, 1
      91: goto          59
      94: aload_0
      95: iconst_0
      96: putfield      #15                 // Field nodeOutputSize:I
      99: return

  public java.lang.String getName();
    Code:
       0: aload_0
       1: getfield      #5                  // Field name:Ljava/lang/String;
       4: areturn

  public int getBeforeSize();
    Code:
       0: aload_0
       1: getfield      #7                  // Field beforeSize:I
       4: ireturn

  public int getNodeOutputSize();
    Code:
       0: aload_0
       1: getfield      #15                 // Field nodeOutputSize:I
       4: ireturn

  public java.lang.String getRouterMessage();
    Code:
       0: aload_0
       1: getfield      #16                 // Field routerMessage:Ljava/lang/String;
       4: areturn

  public void setRouterMessage(java.lang.String);
    Code:
       0: aload_0
       1: aload_1
       2: putfield      #16                 // Field routerMessage:Ljava/lang/String;
       5: return

  public java.util.List<org.apache.dubbo.rpc.Invoker<T>> getNodeOutputInvokers();
    Code:
       0: aload_0
       1: getfield      #17                 // Field nodeOutputInvokers:Ljava/util/List;
       4: areturn

  public void setNodeOutputInvokers(java.util.List<org.apache.dubbo.rpc.Invoker<T>>);
    Code:
       0: aload_0
       1: aload_1
       2: putfield      #17                 // Field nodeOutputInvokers:Ljava/util/List;
       5: aload_0
       6: aload_1
       7: ifnonnull     14
      10: iconst_0
      11: goto          20
      14: aload_1
      15: invokeinterface #6,  1            // InterfaceMethod java/util/List.size:()I
      20: putfield      #15                 // Field nodeOutputSize:I
      23: return

  public void setChainOutputInvokers(java.util.List<org.apache.dubbo.rpc.Invoker<T>>);
    Code:
       0: aload_0
       1: aload_1
       2: putfield      #18                 // Field chainOutputInvokers:Ljava/util/List;
       5: aload_0
       6: aload_1
       7: ifnonnull     14
      10: iconst_0
      11: goto          20
      14: aload_1
      15: invokeinterface #6,  1            // InterfaceMethod java/util/List.size:()I
      20: putfield      #19                 // Field chainOutputSize:I
      23: return

  public int getChainOutputSize();
    Code:
       0: aload_0
       1: getfield      #19                 // Field chainOutputSize:I
       4: ireturn

  public java.util.List<org.apache.dubbo.rpc.Invoker<T>> getChainOutputInvokers();
    Code:
       0: aload_0
       1: getfield      #18                 // Field chainOutputInvokers:Ljava/util/List;
       4: areturn

  public java.util.List<org.apache.dubbo.rpc.cluster.router.RouterSnapshotNode<T>> getNextNode();
    Code:
       0: aload_0
       1: getfield      #4                  // Field nextNode:Ljava/util/List;
       4: areturn

  public org.apache.dubbo.rpc.cluster.router.RouterSnapshotNode<T> getParentNode();
    Code:
       0: aload_0
       1: getfield      #20                 // Field parentNode:Lorg/apache/dubbo/rpc/cluster/router/RouterSnapshotNode;
       4: areturn

  public void appendNode(org.apache.dubbo.rpc.cluster.router.RouterSnapshotNode<T>);
    Code:
       0: aload_0
       1: getfield      #4                  // Field nextNode:Ljava/util/List;
       4: aload_1
       5: invokeinterface #14,  2           // InterfaceMethod java/util/List.add:(Ljava/lang/Object;)Z
      10: pop
      11: aload_1
      12: aload_0
      13: putfield      #20                 // Field parentNode:Lorg/apache/dubbo/rpc/cluster/router/RouterSnapshotNode;
      16: return

  public java.lang.String toString();
    Code:
       0: aload_0
       1: iconst_1
       2: invokevirtual #21                 // Method toString:(I)Ljava/lang/String;
       5: areturn

  public java.lang.String toString(int);
    Code:
       0: new           #22                 // class java/lang/StringBuilder
       3: dup
       4: invokespecial #23                 // Method java/lang/StringBuilder."<init>":()V
       7: astore_2
       8: aload_2
       9: ldc           #24                 // String [
      11: invokevirtual #25                 // Method java/lang/StringBuilder.append:(Ljava/lang/String;)Ljava/lang/StringBuilder;
      14: aload_0
      15: getfield      #5                  // Field name:Ljava/lang/String;
      18: invokevirtual #25                 // Method java/lang/StringBuilder.append:(Ljava/lang/String;)Ljava/lang/StringBuilder;
      21: bipush        32
      23: invokevirtual #26                 // Method java/lang/StringBuilder.append:(C)Ljava/lang/StringBuilder;
      26: ldc           #27                 // String (Input:
      28: invokevirtual #25                 // Method java/lang/StringBuilder.append:(Ljava/lang/String;)Ljava/lang/StringBuilder;
      31: aload_0
      32: getfield      #7                  // Field beforeSize:I
      35: invokevirtual #28                 // Method java/lang/StringBuilder.append:(I)Ljava/lang/StringBuilder;
      38: ldc           #29                 // String )
      40: invokevirtual #25                 // Method java/lang/StringBuilder.append:(Ljava/lang/String;)Ljava/lang/StringBuilder;
      43: ldc           #30                 // String (Current Node Output:
      45: invokevirtual #25                 // Method java/lang/StringBuilder.append:(Ljava/lang/String;)Ljava/lang/StringBuilder;
      48: aload_0
      49: getfield      #15                 // Field nodeOutputSize:I
      52: invokevirtual #28                 // Method java/lang/StringBuilder.append:(I)Ljava/lang/StringBuilder;
      55: ldc           #29                 // String )
      57: invokevirtual #25                 // Method java/lang/StringBuilder.append:(Ljava/lang/String;)Ljava/lang/StringBuilder;
      60: ldc           #31                 // String (Chain Node Output:
      62: invokevirtual #25                 // Method java/lang/StringBuilder.append:(Ljava/lang/String;)Ljava/lang/StringBuilder;
      65: aload_0
      66: getfield      #19                 // Field chainOutputSize:I
      69: invokevirtual #28                 // Method java/lang/StringBuilder.append:(I)Ljava/lang/StringBuilder;
      72: bipush        41
      74: invokevirtual #26                 // Method java/lang/StringBuilder.append:(C)Ljava/lang/StringBuilder;
      77: aload_0
      78: getfield      #16                 // Field routerMessage:Ljava/lang/String;
      81: ifnonnull     89
      84: ldc           #32                 // String
      86: goto          91
      89: ldc           #33                 // String  Router message:
      91: invokevirtual #25                 // Method java/lang/StringBuilder.append:(Ljava/lang/String;)Ljava/lang/StringBuilder;
      94: aload_0
      95: getfield      #16                 // Field routerMessage:Ljava/lang/String;
      98: ifnonnull     106
     101: ldc           #32                 // String
     103: goto          110
     106: aload_0
     107: getfield      #16                 // Field routerMessage:Ljava/lang/String;
     110: invokevirtual #25                 // Method java/lang/StringBuilder.append:(Ljava/lang/String;)Ljava/lang/StringBuilder;
     113: ldc           #34                 // String  ]
     115: invokevirtual #25                 // Method java/lang/StringBuilder.append:(Ljava/lang/String;)Ljava/lang/StringBuilder;
     118: pop
     119: iload_1
     120: iconst_1
     121: if_icmpne     304
     124: aload_2
     125: ldc           #35                 // String Input:
     127: invokevirtual #25                 // Method java/lang/StringBuilder.append:(Ljava/lang/String;)Ljava/lang/StringBuilder;
     130: aload_0
     131: getfield      #9                  // Field inputInvokers:Ljava/util/List;
     134: invokestatic  #36                 // Method org/apache/dubbo/common/utils/CollectionUtils.isEmpty:(Ljava/util/Collection;)Z
     137: ifeq          145
     140: ldc           #37                 // String Empty
     142: goto          206
     145: aload_0
     146: getfield      #9                  // Field inputInvokers:Ljava/util/List;
     149: iconst_0
     150: iconst_5
     151: aload_0
     152: getfield      #9                  // Field inputInvokers:Ljava/util/List;
     155: invokeinterface #6,  1            // InterfaceMethod java/util/List.size:()I
     160: invokestatic  #12                 // Method java/lang/Math.min:(II)I
     163: invokeinterface #38,  3           // InterfaceMethod java/util/List.subList:(II)Ljava/util/List;
     168: invokeinterface #39,  1           // InterfaceMethod java/util/List.stream:()Ljava/util/stream/Stream;
     173: invokedynamic #40,  0             // InvokeDynamic #0:apply:()Ljava/util/function/Function;
     178: invokeinterface #41,  2           // InterfaceMethod java/util/stream/Stream.map:(Ljava/util/function/Function;)Ljava/util/stream/Stream;
     183: invokedynamic #42,  0             // InvokeDynamic #1:apply:()Ljava/util/function/Function;
     188: invokeinterface #41,  2           // InterfaceMethod java/util/stream/Stream.map:(Ljava/util/function/Function;)Ljava/util/stream/Stream;
     193: ldc           #43                 // String ,
     195: invokestatic  #44                 // Method java/util/stream/Collectors.joining:(Ljava/lang/CharSequence;)Ljava/util/stream/Collector;
     198: invokeinterface #45,  2           // InterfaceMethod java/util/stream/Stream.collect:(Ljava/util/stream/Collector;)Ljava/lang/Object;
     203: checkcast     #46                 // class java/lang/String
     206: invokevirtual #25                 // Method java/lang/StringBuilder.append:(Ljava/lang/String;)Ljava/lang/StringBuilder;
     209: ldc           #47                 // String  ->
     211: invokevirtual #25                 // Method java/lang/StringBuilder.append:(Ljava/lang/String;)Ljava/lang/StringBuilder;
     214: pop
     215: aload_2
     216: ldc           #48                 // String Chain Node Output:
     218: invokevirtual #25                 // Method java/lang/StringBuilder.append:(Ljava/lang/String;)Ljava/lang/StringBuilder;
     221: aload_0
     222: getfield      #18                 // Field chainOutputInvokers:Ljava/util/List;
     225: invokestatic  #36                 // Method org/apache/dubbo/common/utils/CollectionUtils.isEmpty:(Ljava/util/Collection;)Z
     228: ifeq          236
     231: ldc           #37                 // String Empty
     233: goto          297
     236: aload_0
     237: getfield      #18                 // Field chainOutputInvokers:Ljava/util/List;
     240: iconst_0
     241: iconst_5
     242: aload_0
     243: getfield      #18                 // Field chainOutputInvokers:Ljava/util/List;
     246: invokeinterface #6,  1            // InterfaceMethod java/util/List.size:()I
     251: invokestatic  #12                 // Method java/lang/Math.min:(II)I
     254: invokeinterface #38,  3           // InterfaceMethod java/util/List.subList:(II)Ljava/util/List;
     259: invokeinterface #39,  1           // InterfaceMethod java/util/List.stream:()Ljava/util/stream/Stream;
     264: invokedynamic #40,  0             // InvokeDynamic #0:apply:()Ljava/util/function/Function;
     269: invokeinterface #41,  2           // InterfaceMethod java/util/stream/Stream.map:(Ljava/util/function/Function;)Ljava/util/stream/Stream;
     274: invokedynamic #42,  0             // InvokeDynamic #1:apply:()Ljava/util/function/Function;
     279: invokeinterface #41,  2           // InterfaceMethod java/util/stream/Stream.map:(Ljava/util/function/Function;)Ljava/util/stream/Stream;
     284: ldc           #43                 // String ,
     286: invokestatic  #44                 // Method java/util/stream/Collectors.joining:(Ljava/lang/CharSequence;)Ljava/util/stream/Collector;
     289: invokeinterface #45,  2           // InterfaceMethod java/util/stream/Stream.collect:(Ljava/util/stream/Collector;)Ljava/lang/Object;
     294: checkcast     #46                 // class java/lang/String
     297: invokevirtual #25                 // Method java/lang/StringBuilder.append:(Ljava/lang/String;)Ljava/lang/StringBuilder;
     300: pop
     301: goto          390
     304: aload_2
     305: ldc           #49                 // String Current Node Output:
     307: invokevirtual #25                 // Method java/lang/StringBuilder.append:(Ljava/lang/String;)Ljava/lang/StringBuilder;
     310: aload_0
     311: getfield      #17                 // Field nodeOutputInvokers:Ljava/util/List;
     314: invokestatic  #36                 // Method org/apache/dubbo/common/utils/CollectionUtils.isEmpty:(Ljava/util/Collection;)Z
     317: ifeq          325
     320: ldc           #37                 // String Empty
     322: goto          386
     325: aload_0
     326: getfield      #17                 // Field nodeOutputInvokers:Ljava/util/List;
     329: iconst_0
     330: iconst_5
     331: aload_0
     332: getfield      #17                 // Field nodeOutputInvokers:Ljava/util/List;
     335: invokeinterface #6,  1            // InterfaceMethod java/util/List.size:()I
     340: invokestatic  #12                 // Method java/lang/Math.min:(II)I
     343: invokeinterface #38,  3           // InterfaceMethod java/util/List.subList:(II)Ljava/util/List;
     348: invokeinterface #39,  1           // InterfaceMethod java/util/List.stream:()Ljava/util/stream/Stream;
     353: invokedynamic #40,  0             // InvokeDynamic #0:apply:()Ljava/util/function/Function;
     358: invokeinterface #41,  2           // InterfaceMethod java/util/stream/Stream.map:(Ljava/util/function/Function;)Ljava/util/stream/Stream;
     363: invokedynamic #42,  0             // InvokeDynamic #1:apply:()Ljava/util/function/Function;
     368: invokeinterface #41,  2           // InterfaceMethod java/util/stream/Stream.map:(Ljava/util/function/Function;)Ljava/util/stream/Stream;
     373: ldc           #43                 // String ,
     375: invokestatic  #44                 // Method java/util/stream/Collectors.joining:(Ljava/lang/CharSequence;)Ljava/util/stream/Collector;
     378: invokeinterface #45,  2           // InterfaceMethod java/util/stream/Stream.collect:(Ljava/util/stream/Collector;)Ljava/lang/Object;
     383: checkcast     #46                 // class java/lang/String
     386: invokevirtual #25                 // Method java/lang/StringBuilder.append:(Ljava/lang/String;)Ljava/lang/StringBuilder;
     389: pop
     390: aload_0
     391: getfield      #17                 // Field nodeOutputInvokers:Ljava/util/List;
     394: ifnull        417
     397: aload_0
     398: getfield      #17                 // Field nodeOutputInvokers:Ljava/util/List;
     401: invokeinterface #6,  1            // InterfaceMethod java/util/List.size:()I
     406: iconst_5
     407: if_icmple     417
     410: aload_2
     411: ldc           #50                 // String ...
     413: invokevirtual #25                 // Method java/lang/StringBuilder.append:(Ljava/lang/String;)Ljava/lang/StringBuilder;
     416: pop
     417: aload_0
     418: getfield      #4                  // Field nextNode:Ljava/util/List;
     421: invokeinterface #51,  1           // InterfaceMethod java/util/List.iterator:()Ljava/util/Iterator;
     426: astore_3
     427: aload_3
     428: invokeinterface #52,  1           // InterfaceMethod java/util/Iterator.hasNext:()Z
     433: ifeq          492
     436: aload_3
     437: invokeinterface #53,  1           // InterfaceMethod java/util/Iterator.next:()Ljava/lang/Object;
     442: checkcast     #54                 // class org/apache/dubbo/rpc/cluster/router/RouterSnapshotNode
     445: astore        4
     447: aload_2
     448: ldc           #55                 // String \n
     450: invokevirtual #25                 // Method java/lang/StringBuilder.append:(Ljava/lang/String;)Ljava/lang/StringBuilder;
     453: pop
     454: iconst_0
     455: istore        5
     457: iload         5
     459: iload_1
     460: if_icmpge     476
     463: aload_2
     464: ldc           #56                 // String
     466: invokevirtual #25                 // Method java/lang/StringBuilder.append:(Ljava/lang/String;)Ljava/lang/StringBuilder;
     469: pop
     470: iinc          5, 1
     473: goto          457
     476: aload_2
     477: aload         4
     479: iload_1
     480: iconst_1
     481: iadd
     482: invokevirtual #21                 // Method toString:(I)Ljava/lang/String;
     485: invokevirtual #25                 // Method java/lang/StringBuilder.append:(Ljava/lang/String;)Ljava/lang/StringBuilder;
     488: pop
     489: goto          427
     492: aload_2
     493: invokevirtual #57                 // Method java/lang/StringBuilder.toString:()Ljava/lang/String;
     496: areturn
}
