Compiled from "MetadataMetricsConstants.java"
public interface org.apache.dubbo.metrics.metadata.MetadataMetricsConstants {
  public static final org.apache.dubbo.metrics.model.key.MetricsPlaceValue OP_TYPE_PUSH;

  public static final org.apache.dubbo.metrics.model.key.MetricsPlaceValue OP_TYPE_SUBSCRIBE;

  public static final org.apache.dubbo.metrics.model.key.MetricsPlaceValue OP_TYPE_STORE_PROVIDER_INTERFACE;

  public static final java.util.List<org.apache.dubbo.metrics.model.key.MetricsKey> APP_LEVEL_KEYS;

  public static final java.util.List<org.apache.dubbo.metrics.model.key.MetricsKeyWrapper> SERVICE_LEVEL_KEYS;

  static {};
    Code:
       0: ldc           #1                  // String push
       2: getstatic     #2                  // Field org/apache/dubbo/metrics/model/key/MetricsLevel.APP:Lorg/apache/dubbo/metrics/model/key/MetricsLevel;
       5: invokestatic  #3                  // Method org/apache/dubbo/metrics/model/key/MetricsPlaceValue.of:(Ljava/lang/String;Lorg/apache/dubbo/metrics/model/key/MetricsLevel;)Lorg/apache/dubbo/metrics/model/key/MetricsPlaceValue;
       8: putstatic     #4                  // Field OP_TYPE_PUSH:Lorg/apache/dubbo/metrics/model/key/MetricsPlaceValue;
      11: ldc           #5                  // String subscribe
      13: getstatic     #2                  // Field org/apache/dubbo/metrics/model/key/MetricsLevel.APP:Lorg/apache/dubbo/metrics/model/key/MetricsLevel;
      16: invokestatic  #3                  // Method org/apache/dubbo/metrics/model/key/MetricsPlaceValue.of:(Ljava/lang/String;Lorg/apache/dubbo/metrics/model/key/MetricsLevel;)Lorg/apache/dubbo/metrics/model/key/MetricsPlaceValue;
      19: putstatic     #6                  // Field OP_TYPE_SUBSCRIBE:Lorg/apache/dubbo/metrics/model/key/MetricsPlaceValue;
      22: ldc           #7                  // String store.provider.interface
      24: getstatic     #8                  // Field org/apache/dubbo/metrics/model/key/MetricsLevel.SERVICE:Lorg/apache/dubbo/metrics/model/key/MetricsLevel;
      27: invokestatic  #3                  // Method org/apache/dubbo/metrics/model/key/MetricsPlaceValue.of:(Ljava/lang/String;Lorg/apache/dubbo/metrics/model/key/MetricsLevel;)Lorg/apache/dubbo/metrics/model/key/MetricsPlaceValue;
      30: putstatic     #9                  // Field OP_TYPE_STORE_PROVIDER_INTERFACE:Lorg/apache/dubbo/metrics/model/key/MetricsPlaceValue;
      33: bipush        6
      35: anewarray     #10                 // class org/apache/dubbo/metrics/model/key/MetricsKey
      38: dup
      39: iconst_0
      40: getstatic     #11                 // Field org/apache/dubbo/metrics/model/key/MetricsKey.METADATA_PUSH_METRIC_NUM:Lorg/apache/dubbo/metrics/model/key/MetricsKey;
      43: aastore
      44: dup
      45: iconst_1
      46: getstatic     #12                 // Field org/apache/dubbo/metrics/model/key/MetricsKey.METADATA_PUSH_METRIC_NUM_SUCCEED:Lorg/apache/dubbo/metrics/model/key/MetricsKey;
      49: aastore
      50: dup
      51: iconst_2
      52: getstatic     #13                 // Field org/apache/dubbo/metrics/model/key/MetricsKey.METADATA_PUSH_METRIC_NUM_FAILED:Lorg/apache/dubbo/metrics/model/key/MetricsKey;
      55: aastore
      56: dup
      57: iconst_3
      58: getstatic     #14                 // Field org/apache/dubbo/metrics/model/key/MetricsKey.METADATA_SUBSCRIBE_METRIC_NUM:Lorg/apache/dubbo/metrics/model/key/MetricsKey;
      61: aastore
      62: dup
      63: iconst_4
      64: getstatic     #15                 // Field org/apache/dubbo/metrics/model/key/MetricsKey.METADATA_SUBSCRIBE_METRIC_NUM_SUCCEED:Lorg/apache/dubbo/metrics/model/key/MetricsKey;
      67: aastore
      68: dup
      69: iconst_5
      70: getstatic     #16                 // Field org/apache/dubbo/metrics/model/key/MetricsKey.METADATA_SUBSCRIBE_METRIC_NUM_FAILED:Lorg/apache/dubbo/metrics/model/key/MetricsKey;
      73: aastore
      74: invokestatic  #17                 // Method java/util/Arrays.asList:([Ljava/lang/Object;)Ljava/util/List;
      77: putstatic     #18                 // Field APP_LEVEL_KEYS:Ljava/util/List;
      80: iconst_3
      81: anewarray     #19                 // class org/apache/dubbo/metrics/model/key/MetricsKeyWrapper
      84: dup
      85: iconst_0
      86: new           #19                 // class org/apache/dubbo/metrics/model/key/MetricsKeyWrapper
      89: dup
      90: getstatic     #20                 // Field org/apache/dubbo/metrics/model/key/MetricsKey.STORE_PROVIDER_METADATA:Lorg/apache/dubbo/metrics/model/key/MetricsKey;
      93: getstatic     #9                  // Field OP_TYPE_STORE_PROVIDER_INTERFACE:Lorg/apache/dubbo/metrics/model/key/MetricsPlaceValue;
      96: invokespecial #21                 // Method org/apache/dubbo/metrics/model/key/MetricsKeyWrapper."<init>":(Lorg/apache/dubbo/metrics/model/key/MetricsKey;Lorg/apache/dubbo/metrics/model/key/MetricsPlaceValue;)V
      99: aastore
     100: dup
     101: iconst_1
     102: new           #19                 // class org/apache/dubbo/metrics/model/key/MetricsKeyWrapper
     105: dup
     106: getstatic     #22                 // Field org/apache/dubbo/metrics/model/key/MetricsKey.STORE_PROVIDER_METADATA_SUCCEED:Lorg/apache/dubbo/metrics/model/key/MetricsKey;
     109: getstatic     #9                  // Field OP_TYPE_STORE_PROVIDER_INTERFACE:Lorg/apache/dubbo/metrics/model/key/MetricsPlaceValue;
     112: invokespecial #21                 // Method org/apache/dubbo/metrics/model/key/MetricsKeyWrapper."<init>":(Lorg/apache/dubbo/metrics/model/key/MetricsKey;Lorg/apache/dubbo/metrics/model/key/MetricsPlaceValue;)V
     115: aastore
     116: dup
     117: iconst_2
     118: new           #19                 // class org/apache/dubbo/metrics/model/key/MetricsKeyWrapper
     121: dup
     122: getstatic     #23                 // Field org/apache/dubbo/metrics/model/key/MetricsKey.STORE_PROVIDER_METADATA_FAILED:Lorg/apache/dubbo/metrics/model/key/MetricsKey;
     125: getstatic     #9                  // Field OP_TYPE_STORE_PROVIDER_INTERFACE:Lorg/apache/dubbo/metrics/model/key/MetricsPlaceValue;
     128: invokespecial #21                 // Method org/apache/dubbo/metrics/model/key/MetricsKeyWrapper."<init>":(Lorg/apache/dubbo/metrics/model/key/MetricsKey;Lorg/apache/dubbo/metrics/model/key/MetricsPlaceValue;)V
     131: aastore
     132: invokestatic  #17                 // Method java/util/Arrays.asList:([Ljava/lang/Object;)Ljava/util/List;
     135: putstatic     #24                 // Field SERVICE_LEVEL_KEYS:Ljava/util/List;
     138: return
}
