Compiled from "RedisMetadataReport.java"
public class org.apache.dubbo.metadata.store.redis.RedisMetadataReport extends org.apache.dubbo.metadata.report.support.AbstractMetadataReport {
  private static final java.lang.String REDIS_DATABASE_KEY;

  private static final org.apache.dubbo.common.logger.ErrorTypeAwareLogger logger;

  protected redis.clients.jedis.JedisPool pool;

  private java.util.Set<redis.clients.jedis.HostAndPort> jedisClusterNodes;

  private int timeout;

  private java.lang.String password;

  public org.apache.dubbo.metadata.store.redis.RedisMetadataReport(org.apache.dubbo.common.URL);
    Code:
       0: aload_0
       1: aload_1
       2: invokespecial #4                  // Method org/apache/dubbo/metadata/report/support/AbstractMetadataReport."<init>":(Lorg/apache/dubbo/common/URL;)V
       5: aload_0
       6: aload_1
       7: ldc           #5                  // String timeout
       9: sipush        1000
      12: invokevirtual #6                  // Method org/apache/dubbo/common/URL.getParameter:(Ljava/lang/String;I)I
      15: putfield      #7                  // Field timeout:I
      18: aload_0
      19: aload_1
      20: invokevirtual #8                  // Method org/apache/dubbo/common/URL.getPassword:()Ljava/lang/String;
      23: putfield      #9                  // Field password:Ljava/lang/String;
      26: aload_1
      27: ldc           #10                 // String cluster
      29: iconst_0
      30: invokevirtual #11                 // Method org/apache/dubbo/common/URL.getParameter:(Ljava/lang/String;Z)Z
      33: ifeq          112
      36: aload_0
      37: new           #12                 // class java/util/HashSet
      40: dup
      41: invokespecial #13                 // Method java/util/HashSet."<init>":()V
      44: putfield      #14                 // Field jedisClusterNodes:Ljava/util/Set;
      47: aload_1
      48: invokevirtual #15                 // Method org/apache/dubbo/common/URL.getBackupUrls:()Ljava/util/List;
      51: astore_2
      52: aload_2
      53: invokeinterface #16,  1           // InterfaceMethod java/util/List.iterator:()Ljava/util/Iterator;
      58: astore_3
      59: aload_3
      60: invokeinterface #17,  1           // InterfaceMethod java/util/Iterator.hasNext:()Z
      65: ifeq          109
      68: aload_3
      69: invokeinterface #18,  1           // InterfaceMethod java/util/Iterator.next:()Ljava/lang/Object;
      74: checkcast     #19                 // class org/apache/dubbo/common/URL
      77: astore        4
      79: aload_0
      80: getfield      #14                 // Field jedisClusterNodes:Ljava/util/Set;
      83: new           #20                 // class redis/clients/jedis/HostAndPort
      86: dup
      87: aload         4
      89: invokevirtual #21                 // Method org/apache/dubbo/common/URL.getHost:()Ljava/lang/String;
      92: aload         4
      94: invokevirtual #22                 // Method org/apache/dubbo/common/URL.getPort:()I
      97: invokespecial #23                 // Method redis/clients/jedis/HostAndPort."<init>":(Ljava/lang/String;I)V
     100: invokeinterface #24,  2           // InterfaceMethod java/util/Set.add:(Ljava/lang/Object;)Z
     105: pop
     106: goto          59
     109: goto          155
     112: aload_1
     113: ldc           #26                 // String database
     115: iconst_0
     116: invokevirtual #6                  // Method org/apache/dubbo/common/URL.getParameter:(Ljava/lang/String;I)I
     119: istore_2
     120: aload_0
     121: new           #27                 // class redis/clients/jedis/JedisPool
     124: dup
     125: new           #28                 // class redis/clients/jedis/JedisPoolConfig
     128: dup
     129: invokespecial #29                 // Method redis/clients/jedis/JedisPoolConfig."<init>":()V
     132: aload_1
     133: invokevirtual #21                 // Method org/apache/dubbo/common/URL.getHost:()Ljava/lang/String;
     136: aload_1
     137: invokevirtual #22                 // Method org/apache/dubbo/common/URL.getPort:()I
     140: aload_0
     141: getfield      #7                  // Field timeout:I
     144: aload_0
     145: getfield      #9                  // Field password:Ljava/lang/String;
     148: iload_2
     149: invokespecial #30                 // Method redis/clients/jedis/JedisPool."<init>":(Lorg/apache/commons/pool2/impl/GenericObjectPoolConfig;Ljava/lang/String;IILjava/lang/String;I)V
     152: putfield      #31                 // Field pool:Lredis/clients/jedis/JedisPool;
     155: return

  protected void doStoreProviderMetadata(org.apache.dubbo.metadata.report.identifier.MetadataIdentifier, java.lang.String);
    Code:
       0: aload_0
       1: aload_1
       2: aload_2
       3: invokespecial #32                 // Method storeMetadata:(Lorg/apache/dubbo/metadata/report/identifier/BaseMetadataIdentifier;Ljava/lang/String;)V
       6: return

  protected void doStoreConsumerMetadata(org.apache.dubbo.metadata.report.identifier.MetadataIdentifier, java.lang.String);
    Code:
       0: aload_0
       1: aload_1
       2: aload_2
       3: invokespecial #32                 // Method storeMetadata:(Lorg/apache/dubbo/metadata/report/identifier/BaseMetadataIdentifier;Ljava/lang/String;)V
       6: return

  protected void doSaveMetadata(org.apache.dubbo.metadata.report.identifier.ServiceMetadataIdentifier, org.apache.dubbo.common.URL);
    Code:
       0: aload_0
       1: aload_1
       2: aload_2
       3: invokevirtual #33                 // Method org/apache/dubbo/common/URL.toFullString:()Ljava/lang/String;
       6: invokestatic  #34                 // Method org/apache/dubbo/common/URL.encode:(Ljava/lang/String;)Ljava/lang/String;
       9: invokespecial #32                 // Method storeMetadata:(Lorg/apache/dubbo/metadata/report/identifier/BaseMetadataIdentifier;Ljava/lang/String;)V
      12: return

  protected void doRemoveMetadata(org.apache.dubbo.metadata.report.identifier.ServiceMetadataIdentifier);
    Code:
       0: aload_0
       1: aload_1
       2: invokespecial #35                 // Method deleteMetadata:(Lorg/apache/dubbo/metadata/report/identifier/BaseMetadataIdentifier;)V
       5: return

  protected java.util.List<java.lang.String> doGetExportedURLs(org.apache.dubbo.metadata.report.identifier.ServiceMetadataIdentifier);
    Code:
       0: aload_0
       1: aload_1
       2: invokespecial #36                 // Method getMetadata:(Lorg/apache/dubbo/metadata/report/identifier/BaseMetadataIdentifier;)Ljava/lang/String;
       5: astore_2
       6: aload_2
       7: invokestatic  #37                 // Method org/apache/dubbo/common/utils/StringUtils.isEmpty:(Ljava/lang/String;)Z
      10: ifeq          17
      13: invokestatic  #38                 // Method java/util/Collections.emptyList:()Ljava/util/List;
      16: areturn
      17: new           #39                 // class java/util/ArrayList
      20: dup
      21: iconst_1
      22: anewarray     #40                 // class java/lang/String
      25: dup
      26: iconst_0
      27: aload_2
      28: invokestatic  #41                 // Method org/apache/dubbo/common/URL.decode:(Ljava/lang/String;)Ljava/lang/String;
      31: aastore
      32: invokestatic  #42                 // Method java/util/Arrays.asList:([Ljava/lang/Object;)Ljava/util/List;
      35: invokespecial #43                 // Method java/util/ArrayList."<init>":(Ljava/util/Collection;)V
      38: areturn

  protected void doSaveSubscriberData(org.apache.dubbo.metadata.report.identifier.SubscriberMetadataIdentifier, java.lang.String);
    Code:
       0: aload_0
       1: aload_1
       2: aload_2
       3: invokespecial #32                 // Method storeMetadata:(Lorg/apache/dubbo/metadata/report/identifier/BaseMetadataIdentifier;Ljava/lang/String;)V
       6: return

  protected java.lang.String doGetSubscribedURLs(org.apache.dubbo.metadata.report.identifier.SubscriberMetadataIdentifier);
    Code:
       0: aload_0
       1: aload_1
       2: invokespecial #36                 // Method getMetadata:(Lorg/apache/dubbo/metadata/report/identifier/BaseMetadataIdentifier;)Ljava/lang/String;
       5: areturn

  public java.lang.String getServiceDefinition(org.apache.dubbo.metadata.report.identifier.MetadataIdentifier);
    Code:
       0: aload_0
       1: aload_1
       2: invokespecial #36                 // Method getMetadata:(Lorg/apache/dubbo/metadata/report/identifier/BaseMetadataIdentifier;)Ljava/lang/String;
       5: areturn

  private void storeMetadata(org.apache.dubbo.metadata.report.identifier.BaseMetadataIdentifier, java.lang.String);
    Code:
       0: aload_0
       1: getfield      #31                 // Field pool:Lredis/clients/jedis/JedisPool;
       4: ifnull        16
       7: aload_0
       8: aload_1
       9: aload_2
      10: invokespecial #44                 // Method storeMetadataStandalone:(Lorg/apache/dubbo/metadata/report/identifier/BaseMetadataIdentifier;Ljava/lang/String;)V
      13: goto          22
      16: aload_0
      17: aload_1
      18: aload_2
      19: invokespecial #45                 // Method storeMetadataInCluster:(Lorg/apache/dubbo/metadata/report/identifier/BaseMetadataIdentifier;Ljava/lang/String;)V
      22: return

  private void storeMetadataInCluster(org.apache.dubbo.metadata.report.identifier.BaseMetadataIdentifier, java.lang.String);
    Code:
       0: new           #46                 // class redis/clients/jedis/JedisCluster
       3: dup
       4: aload_0
       5: getfield      #14                 // Field jedisClusterNodes:Ljava/util/Set;
       8: aload_0
       9: getfield      #7                  // Field timeout:I
      12: aload_0
      13: getfield      #7                  // Field timeout:I
      16: iconst_2
      17: aload_0
      18: getfield      #9                  // Field password:Ljava/lang/String;
      21: new           #47                 // class org/apache/commons/pool2/impl/GenericObjectPoolConfig
      24: dup
      25: invokespecial #48                 // Method org/apache/commons/pool2/impl/GenericObjectPoolConfig."<init>":()V
      28: invokespecial #49                 // Method redis/clients/jedis/JedisCluster."<init>":(Ljava/util/Set;IIILjava/lang/String;Lorg/apache/commons/pool2/impl/GenericObjectPoolConfig;)V
      31: astore_3
      32: aconst_null
      33: astore        4
      35: aload_3
      36: new           #50                 // class java/lang/StringBuilder
      39: dup
      40: invokespecial #51                 // Method java/lang/StringBuilder."<init>":()V
      43: aload_1
      44: invokeinterface #52,  1           // InterfaceMethod org/apache/dubbo/metadata/report/identifier/BaseMetadataIdentifier.getIdentifierKey:()Ljava/lang/String;
      49: invokevirtual #53                 // Method java/lang/StringBuilder.append:(Ljava/lang/String;)Ljava/lang/StringBuilder;
      52: ldc           #54                 // String .metaData
      54: invokevirtual #53                 // Method java/lang/StringBuilder.append:(Ljava/lang/String;)Ljava/lang/StringBuilder;
      57: invokevirtual #55                 // Method java/lang/StringBuilder.toString:()Ljava/lang/String;
      60: aload_2
      61: invokevirtual #56                 // Method redis/clients/jedis/JedisCluster.set:(Ljava/lang/String;Ljava/lang/String;)Ljava/lang/String;
      64: pop
      65: aload_3
      66: ifnull        146
      69: aload         4
      71: ifnull        93
      74: aload_3
      75: invokevirtual #57                 // Method redis/clients/jedis/JedisCluster.close:()V
      78: goto          146
      81: astore        5
      83: aload         4
      85: aload         5
      87: invokevirtual #59                 // Method java/lang/Throwable.addSuppressed:(Ljava/lang/Throwable;)V
      90: goto          146
      93: aload_3
      94: invokevirtual #57                 // Method redis/clients/jedis/JedisCluster.close:()V
      97: goto          146
     100: astore        5
     102: aload         5
     104: astore        4
     106: aload         5
     108: athrow
     109: astore        6
     111: aload_3
     112: ifnull        143
     115: aload         4
     117: ifnull        139
     120: aload_3
     121: invokevirtual #57                 // Method redis/clients/jedis/JedisCluster.close:()V
     124: goto          143
     127: astore        7
     129: aload         4
     131: aload         7
     133: invokevirtual #59                 // Method java/lang/Throwable.addSuppressed:(Ljava/lang/Throwable;)V
     136: goto          143
     139: aload_3
     140: invokevirtual #57                 // Method redis/clients/jedis/JedisCluster.close:()V
     143: aload         6
     145: athrow
     146: goto          220
     149: astore_3
     150: new           #50                 // class java/lang/StringBuilder
     153: dup
     154: invokespecial #51                 // Method java/lang/StringBuilder."<init>":()V
     157: ldc           #60                 // String Failed to put
     159: invokevirtual #53                 // Method java/lang/StringBuilder.append:(Ljava/lang/String;)Ljava/lang/StringBuilder;
     162: aload_1
     163: invokevirtual #61                 // Method java/lang/StringBuilder.append:(Ljava/lang/Object;)Ljava/lang/StringBuilder;
     166: ldc           #62                 // String  to redis cluster
     168: invokevirtual #53                 // Method java/lang/StringBuilder.append:(Ljava/lang/String;)Ljava/lang/StringBuilder;
     171: aload_2
     172: invokevirtual #53                 // Method java/lang/StringBuilder.append:(Ljava/lang/String;)Ljava/lang/StringBuilder;
     175: ldc           #63                 // String , cause:
     177: invokevirtual #53                 // Method java/lang/StringBuilder.append:(Ljava/lang/String;)Ljava/lang/StringBuilder;
     180: aload_3
     181: invokevirtual #64                 // Method java/lang/Throwable.getMessage:()Ljava/lang/String;
     184: invokevirtual #53                 // Method java/lang/StringBuilder.append:(Ljava/lang/String;)Ljava/lang/StringBuilder;
     187: invokevirtual #55                 // Method java/lang/StringBuilder.toString:()Ljava/lang/String;
     190: astore        4
     192: getstatic     #65                 // Field logger:Lorg/apache/dubbo/common/logger/ErrorTypeAwareLogger;
     195: ldc           #66                 // String 6-14
     197: ldc           #67                 // String
     199: ldc           #67                 // String
     201: aload         4
     203: aload_3
     204: invokeinterface #68,  6           // InterfaceMethod org/apache/dubbo/common/logger/ErrorTypeAwareLogger.error:(Ljava/lang/String;Ljava/lang/String;Ljava/lang/String;Ljava/lang/String;Ljava/lang/Throwable;)V
     209: new           #69                 // class org/apache/dubbo/rpc/RpcException
     212: dup
     213: aload         4
     215: aload_3
     216: invokespecial #70                 // Method org/apache/dubbo/rpc/RpcException."<init>":(Ljava/lang/String;Ljava/lang/Throwable;)V
     219: athrow
     220: return
    Exception table:
       from    to  target type
          74    78    81   Class java/lang/Throwable
          35    65   100   Class java/lang/Throwable
          35    65   109   any
         120   124   127   Class java/lang/Throwable
         100   111   109   any
           0   146   149   Class java/lang/Throwable

  private void storeMetadataStandalone(org.apache.dubbo.metadata.report.identifier.BaseMetadataIdentifier, java.lang.String);
    Code:
       0: aload_0
       1: getfield      #31                 // Field pool:Lredis/clients/jedis/JedisPool;
       4: invokevirtual #71                 // Method redis/clients/jedis/JedisPool.getResource:()Lredis/clients/jedis/Jedis;
       7: astore_3
       8: aconst_null
       9: astore        4
      11: aload_3
      12: aload_1
      13: getstatic     #72                 // Field org/apache/dubbo/metadata/report/identifier/KeyTypeEnum.UNIQUE_KEY:Lorg/apache/dubbo/metadata/report/identifier/KeyTypeEnum;
      16: invokeinterface #73,  2           // InterfaceMethod org/apache/dubbo/metadata/report/identifier/BaseMetadataIdentifier.getUniqueKey:(Lorg/apache/dubbo/metadata/report/identifier/KeyTypeEnum;)Ljava/lang/String;
      21: aload_2
      22: invokevirtual #74                 // Method redis/clients/jedis/Jedis.set:(Ljava/lang/String;Ljava/lang/String;)Ljava/lang/String;
      25: pop
      26: aload_3
      27: ifnull        107
      30: aload         4
      32: ifnull        54
      35: aload_3
      36: invokevirtual #75                 // Method redis/clients/jedis/Jedis.close:()V
      39: goto          107
      42: astore        5
      44: aload         4
      46: aload         5
      48: invokevirtual #59                 // Method java/lang/Throwable.addSuppressed:(Ljava/lang/Throwable;)V
      51: goto          107
      54: aload_3
      55: invokevirtual #75                 // Method redis/clients/jedis/Jedis.close:()V
      58: goto          107
      61: astore        5
      63: aload         5
      65: astore        4
      67: aload         5
      69: athrow
      70: astore        6
      72: aload_3
      73: ifnull        104
      76: aload         4
      78: ifnull        100
      81: aload_3
      82: invokevirtual #75                 // Method redis/clients/jedis/Jedis.close:()V
      85: goto          104
      88: astore        7
      90: aload         4
      92: aload         7
      94: invokevirtual #59                 // Method java/lang/Throwable.addSuppressed:(Ljava/lang/Throwable;)V
      97: goto          104
     100: aload_3
     101: invokevirtual #75                 // Method redis/clients/jedis/Jedis.close:()V
     104: aload         6
     106: athrow
     107: goto          181
     110: astore_3
     111: new           #50                 // class java/lang/StringBuilder
     114: dup
     115: invokespecial #51                 // Method java/lang/StringBuilder."<init>":()V
     118: ldc           #60                 // String Failed to put
     120: invokevirtual #53                 // Method java/lang/StringBuilder.append:(Ljava/lang/String;)Ljava/lang/StringBuilder;
     123: aload_1
     124: invokevirtual #61                 // Method java/lang/StringBuilder.append:(Ljava/lang/Object;)Ljava/lang/StringBuilder;
     127: ldc           #76                 // String  to redis
     129: invokevirtual #53                 // Method java/lang/StringBuilder.append:(Ljava/lang/String;)Ljava/lang/StringBuilder;
     132: aload_2
     133: invokevirtual #53                 // Method java/lang/StringBuilder.append:(Ljava/lang/String;)Ljava/lang/StringBuilder;
     136: ldc           #63                 // String , cause:
     138: invokevirtual #53                 // Method java/lang/StringBuilder.append:(Ljava/lang/String;)Ljava/lang/StringBuilder;
     141: aload_3
     142: invokevirtual #64                 // Method java/lang/Throwable.getMessage:()Ljava/lang/String;
     145: invokevirtual #53                 // Method java/lang/StringBuilder.append:(Ljava/lang/String;)Ljava/lang/StringBuilder;
     148: invokevirtual #55                 // Method java/lang/StringBuilder.toString:()Ljava/lang/String;
     151: astore        4
     153: getstatic     #65                 // Field logger:Lorg/apache/dubbo/common/logger/ErrorTypeAwareLogger;
     156: ldc           #66                 // String 6-14
     158: ldc           #67                 // String
     160: ldc           #67                 // String
     162: aload         4
     164: aload_3
     165: invokeinterface #68,  6           // InterfaceMethod org/apache/dubbo/common/logger/ErrorTypeAwareLogger.error:(Ljava/lang/String;Ljava/lang/String;Ljava/lang/String;Ljava/lang/String;Ljava/lang/Throwable;)V
     170: new           #69                 // class org/apache/dubbo/rpc/RpcException
     173: dup
     174: aload         4
     176: aload_3
     177: invokespecial #70                 // Method org/apache/dubbo/rpc/RpcException."<init>":(Ljava/lang/String;Ljava/lang/Throwable;)V
     180: athrow
     181: return
    Exception table:
       from    to  target type
          35    39    42   Class java/lang/Throwable
          11    26    61   Class java/lang/Throwable
          11    26    70   any
          81    85    88   Class java/lang/Throwable
          61    72    70   any
           0   107   110   Class java/lang/Throwable

  private void deleteMetadata(org.apache.dubbo.metadata.report.identifier.BaseMetadataIdentifier);
    Code:
       0: aload_0
       1: getfield      #31                 // Field pool:Lredis/clients/jedis/JedisPool;
       4: ifnull        15
       7: aload_0
       8: aload_1
       9: invokespecial #77                 // Method deleteMetadataStandalone:(Lorg/apache/dubbo/metadata/report/identifier/BaseMetadataIdentifier;)V
      12: goto          20
      15: aload_0
      16: aload_1
      17: invokespecial #78                 // Method deleteMetadataInCluster:(Lorg/apache/dubbo/metadata/report/identifier/BaseMetadataIdentifier;)V
      20: return

  private void deleteMetadataInCluster(org.apache.dubbo.metadata.report.identifier.BaseMetadataIdentifier);
    Code:
       0: new           #46                 // class redis/clients/jedis/JedisCluster
       3: dup
       4: aload_0
       5: getfield      #14                 // Field jedisClusterNodes:Ljava/util/Set;
       8: aload_0
       9: getfield      #7                  // Field timeout:I
      12: aload_0
      13: getfield      #7                  // Field timeout:I
      16: iconst_2
      17: aload_0
      18: getfield      #9                  // Field password:Ljava/lang/String;
      21: new           #47                 // class org/apache/commons/pool2/impl/GenericObjectPoolConfig
      24: dup
      25: invokespecial #48                 // Method org/apache/commons/pool2/impl/GenericObjectPoolConfig."<init>":()V
      28: invokespecial #49                 // Method redis/clients/jedis/JedisCluster."<init>":(Ljava/util/Set;IIILjava/lang/String;Lorg/apache/commons/pool2/impl/GenericObjectPoolConfig;)V
      31: astore_2
      32: aconst_null
      33: astore_3
      34: aload_2
      35: new           #50                 // class java/lang/StringBuilder
      38: dup
      39: invokespecial #51                 // Method java/lang/StringBuilder."<init>":()V
      42: aload_1
      43: invokeinterface #52,  1           // InterfaceMethod org/apache/dubbo/metadata/report/identifier/BaseMetadataIdentifier.getIdentifierKey:()Ljava/lang/String;
      48: invokevirtual #53                 // Method java/lang/StringBuilder.append:(Ljava/lang/String;)Ljava/lang/StringBuilder;
      51: ldc           #54                 // String .metaData
      53: invokevirtual #53                 // Method java/lang/StringBuilder.append:(Ljava/lang/String;)Ljava/lang/StringBuilder;
      56: invokevirtual #55                 // Method java/lang/StringBuilder.toString:()Ljava/lang/String;
      59: invokevirtual #79                 // Method redis/clients/jedis/JedisCluster.del:(Ljava/lang/String;)Ljava/lang/Long;
      62: pop
      63: aload_2
      64: ifnull        139
      67: aload_3
      68: ifnull        89
      71: aload_2
      72: invokevirtual #57                 // Method redis/clients/jedis/JedisCluster.close:()V
      75: goto          139
      78: astore        4
      80: aload_3
      81: aload         4
      83: invokevirtual #59                 // Method java/lang/Throwable.addSuppressed:(Ljava/lang/Throwable;)V
      86: goto          139
      89: aload_2
      90: invokevirtual #57                 // Method redis/clients/jedis/JedisCluster.close:()V
      93: goto          139
      96: astore        4
      98: aload         4
     100: astore_3
     101: aload         4
     103: athrow
     104: astore        5
     106: aload_2
     107: ifnull        136
     110: aload_3
     111: ifnull        132
     114: aload_2
     115: invokevirtual #57                 // Method redis/clients/jedis/JedisCluster.close:()V
     118: goto          136
     121: astore        6
     123: aload_3
     124: aload         6
     126: invokevirtual #59                 // Method java/lang/Throwable.addSuppressed:(Ljava/lang/Throwable;)V
     129: goto          136
     132: aload_2
     133: invokevirtual #57                 // Method redis/clients/jedis/JedisCluster.close:()V
     136: aload         5
     138: athrow
     139: goto          201
     142: astore_2
     143: new           #50                 // class java/lang/StringBuilder
     146: dup
     147: invokespecial #51                 // Method java/lang/StringBuilder."<init>":()V
     150: ldc           #80                 // String Failed to delete
     152: invokevirtual #53                 // Method java/lang/StringBuilder.append:(Ljava/lang/String;)Ljava/lang/StringBuilder;
     155: aload_1
     156: invokevirtual #61                 // Method java/lang/StringBuilder.append:(Ljava/lang/Object;)Ljava/lang/StringBuilder;
     159: ldc           #81                 // String  from redis cluster , cause:
     161: invokevirtual #53                 // Method java/lang/StringBuilder.append:(Ljava/lang/String;)Ljava/lang/StringBuilder;
     164: aload_2
     165: invokevirtual #64                 // Method java/lang/Throwable.getMessage:()Ljava/lang/String;
     168: invokevirtual #53                 // Method java/lang/StringBuilder.append:(Ljava/lang/String;)Ljava/lang/StringBuilder;
     171: invokevirtual #55                 // Method java/lang/StringBuilder.toString:()Ljava/lang/String;
     174: astore_3
     175: getstatic     #65                 // Field logger:Lorg/apache/dubbo/common/logger/ErrorTypeAwareLogger;
     178: ldc           #66                 // String 6-14
     180: ldc           #67                 // String
     182: ldc           #67                 // String
     184: aload_3
     185: aload_2
     186: invokeinterface #68,  6           // InterfaceMethod org/apache/dubbo/common/logger/ErrorTypeAwareLogger.error:(Ljava/lang/String;Ljava/lang/String;Ljava/lang/String;Ljava/lang/String;Ljava/lang/Throwable;)V
     191: new           #69                 // class org/apache/dubbo/rpc/RpcException
     194: dup
     195: aload_3
     196: aload_2
     197: invokespecial #70                 // Method org/apache/dubbo/rpc/RpcException."<init>":(Ljava/lang/String;Ljava/lang/Throwable;)V
     200: athrow
     201: return
    Exception table:
       from    to  target type
          71    75    78   Class java/lang/Throwable
          34    63    96   Class java/lang/Throwable
          34    63   104   any
         114   118   121   Class java/lang/Throwable
          96   106   104   any
           0   139   142   Class java/lang/Throwable

  private void deleteMetadataStandalone(org.apache.dubbo.metadata.report.identifier.BaseMetadataIdentifier);
    Code:
       0: aload_0
       1: getfield      #31                 // Field pool:Lredis/clients/jedis/JedisPool;
       4: invokevirtual #71                 // Method redis/clients/jedis/JedisPool.getResource:()Lredis/clients/jedis/Jedis;
       7: astore_2
       8: aconst_null
       9: astore_3
      10: aload_2
      11: aload_1
      12: getstatic     #72                 // Field org/apache/dubbo/metadata/report/identifier/KeyTypeEnum.UNIQUE_KEY:Lorg/apache/dubbo/metadata/report/identifier/KeyTypeEnum;
      15: invokeinterface #73,  2           // InterfaceMethod org/apache/dubbo/metadata/report/identifier/BaseMetadataIdentifier.getUniqueKey:(Lorg/apache/dubbo/metadata/report/identifier/KeyTypeEnum;)Ljava/lang/String;
      20: invokevirtual #82                 // Method redis/clients/jedis/Jedis.del:(Ljava/lang/String;)Ljava/lang/Long;
      23: pop
      24: aload_2
      25: ifnull        100
      28: aload_3
      29: ifnull        50
      32: aload_2
      33: invokevirtual #75                 // Method redis/clients/jedis/Jedis.close:()V
      36: goto          100
      39: astore        4
      41: aload_3
      42: aload         4
      44: invokevirtual #59                 // Method java/lang/Throwable.addSuppressed:(Ljava/lang/Throwable;)V
      47: goto          100
      50: aload_2
      51: invokevirtual #75                 // Method redis/clients/jedis/Jedis.close:()V
      54: goto          100
      57: astore        4
      59: aload         4
      61: astore_3
      62: aload         4
      64: athrow
      65: astore        5
      67: aload_2
      68: ifnull        97
      71: aload_3
      72: ifnull        93
      75: aload_2
      76: invokevirtual #75                 // Method redis/clients/jedis/Jedis.close:()V
      79: goto          97
      82: astore        6
      84: aload_3
      85: aload         6
      87: invokevirtual #59                 // Method java/lang/Throwable.addSuppressed:(Ljava/lang/Throwable;)V
      90: goto          97
      93: aload_2
      94: invokevirtual #75                 // Method redis/clients/jedis/Jedis.close:()V
      97: aload         5
      99: athrow
     100: goto          162
     103: astore_2
     104: new           #50                 // class java/lang/StringBuilder
     107: dup
     108: invokespecial #51                 // Method java/lang/StringBuilder."<init>":()V
     111: ldc           #80                 // String Failed to delete
     113: invokevirtual #53                 // Method java/lang/StringBuilder.append:(Ljava/lang/String;)Ljava/lang/StringBuilder;
     116: aload_1
     117: invokevirtual #61                 // Method java/lang/StringBuilder.append:(Ljava/lang/Object;)Ljava/lang/StringBuilder;
     120: ldc           #83                 // String  from redis , cause:
     122: invokevirtual #53                 // Method java/lang/StringBuilder.append:(Ljava/lang/String;)Ljava/lang/StringBuilder;
     125: aload_2
     126: invokevirtual #64                 // Method java/lang/Throwable.getMessage:()Ljava/lang/String;
     129: invokevirtual #53                 // Method java/lang/StringBuilder.append:(Ljava/lang/String;)Ljava/lang/StringBuilder;
     132: invokevirtual #55                 // Method java/lang/StringBuilder.toString:()Ljava/lang/String;
     135: astore_3
     136: getstatic     #65                 // Field logger:Lorg/apache/dubbo/common/logger/ErrorTypeAwareLogger;
     139: ldc           #66                 // String 6-14
     141: ldc           #67                 // String
     143: ldc           #67                 // String
     145: aload_3
     146: aload_2
     147: invokeinterface #68,  6           // InterfaceMethod org/apache/dubbo/common/logger/ErrorTypeAwareLogger.error:(Ljava/lang/String;Ljava/lang/String;Ljava/lang/String;Ljava/lang/String;Ljava/lang/Throwable;)V
     152: new           #69                 // class org/apache/dubbo/rpc/RpcException
     155: dup
     156: aload_3
     157: aload_2
     158: invokespecial #70                 // Method org/apache/dubbo/rpc/RpcException."<init>":(Ljava/lang/String;Ljava/lang/Throwable;)V
     161: athrow
     162: return
    Exception table:
       from    to  target type
          32    36    39   Class java/lang/Throwable
          10    24    57   Class java/lang/Throwable
          10    24    65   any
          75    79    82   Class java/lang/Throwable
          57    67    65   any
           0   100   103   Class java/lang/Throwable

  private java.lang.String getMetadata(org.apache.dubbo.metadata.report.identifier.BaseMetadataIdentifier);
    Code:
       0: aload_0
       1: getfield      #31                 // Field pool:Lredis/clients/jedis/JedisPool;
       4: ifnull        13
       7: aload_0
       8: aload_1
       9: invokespecial #84                 // Method getMetadataStandalone:(Lorg/apache/dubbo/metadata/report/identifier/BaseMetadataIdentifier;)Ljava/lang/String;
      12: areturn
      13: aload_0
      14: aload_1
      15: invokespecial #85                 // Method getMetadataInCluster:(Lorg/apache/dubbo/metadata/report/identifier/BaseMetadataIdentifier;)Ljava/lang/String;
      18: areturn

  private java.lang.String getMetadataInCluster(org.apache.dubbo.metadata.report.identifier.BaseMetadataIdentifier);
    Code:
       0: new           #46                 // class redis/clients/jedis/JedisCluster
       3: dup
       4: aload_0
       5: getfield      #14                 // Field jedisClusterNodes:Ljava/util/Set;
       8: aload_0
       9: getfield      #7                  // Field timeout:I
      12: aload_0
      13: getfield      #7                  // Field timeout:I
      16: iconst_2
      17: aload_0
      18: getfield      #9                  // Field password:Ljava/lang/String;
      21: new           #47                 // class org/apache/commons/pool2/impl/GenericObjectPoolConfig
      24: dup
      25: invokespecial #48                 // Method org/apache/commons/pool2/impl/GenericObjectPoolConfig."<init>":()V
      28: invokespecial #49                 // Method redis/clients/jedis/JedisCluster."<init>":(Ljava/util/Set;IIILjava/lang/String;Lorg/apache/commons/pool2/impl/GenericObjectPoolConfig;)V
      31: astore_2
      32: aconst_null
      33: astore_3
      34: aload_2
      35: new           #50                 // class java/lang/StringBuilder
      38: dup
      39: invokespecial #51                 // Method java/lang/StringBuilder."<init>":()V
      42: aload_1
      43: invokeinterface #52,  1           // InterfaceMethod org/apache/dubbo/metadata/report/identifier/BaseMetadataIdentifier.getIdentifierKey:()Ljava/lang/String;
      48: invokevirtual #53                 // Method java/lang/StringBuilder.append:(Ljava/lang/String;)Ljava/lang/StringBuilder;
      51: ldc           #54                 // String .metaData
      53: invokevirtual #53                 // Method java/lang/StringBuilder.append:(Ljava/lang/String;)Ljava/lang/StringBuilder;
      56: invokevirtual #55                 // Method java/lang/StringBuilder.toString:()Ljava/lang/String;
      59: invokevirtual #86                 // Method redis/clients/jedis/JedisCluster.get:(Ljava/lang/String;)Ljava/lang/String;
      62: astore        4
      64: aload_2
      65: ifnull        94
      68: aload_3
      69: ifnull        90
      72: aload_2
      73: invokevirtual #57                 // Method redis/clients/jedis/JedisCluster.close:()V
      76: goto          94
      79: astore        5
      81: aload_3
      82: aload         5
      84: invokevirtual #59                 // Method java/lang/Throwable.addSuppressed:(Ljava/lang/Throwable;)V
      87: goto          94
      90: aload_2
      91: invokevirtual #57                 // Method redis/clients/jedis/JedisCluster.close:()V
      94: aload         4
      96: areturn
      97: astore        4
      99: aload         4
     101: astore_3
     102: aload         4
     104: athrow
     105: astore        6
     107: aload_2
     108: ifnull        137
     111: aload_3
     112: ifnull        133
     115: aload_2
     116: invokevirtual #57                 // Method redis/clients/jedis/JedisCluster.close:()V
     119: goto          137
     122: astore        7
     124: aload_3
     125: aload         7
     127: invokevirtual #59                 // Method java/lang/Throwable.addSuppressed:(Ljava/lang/Throwable;)V
     130: goto          137
     133: aload_2
     134: invokevirtual #57                 // Method redis/clients/jedis/JedisCluster.close:()V
     137: aload         6
     139: athrow
     140: astore_2
     141: new           #50                 // class java/lang/StringBuilder
     144: dup
     145: invokespecial #51                 // Method java/lang/StringBuilder."<init>":()V
     148: ldc           #87                 // String Failed to get
     150: invokevirtual #53                 // Method java/lang/StringBuilder.append:(Ljava/lang/String;)Ljava/lang/StringBuilder;
     153: aload_1
     154: invokevirtual #61                 // Method java/lang/StringBuilder.append:(Ljava/lang/Object;)Ljava/lang/StringBuilder;
     157: ldc           #81                 // String  from redis cluster , cause:
     159: invokevirtual #53                 // Method java/lang/StringBuilder.append:(Ljava/lang/String;)Ljava/lang/StringBuilder;
     162: aload_2
     163: invokevirtual #64                 // Method java/lang/Throwable.getMessage:()Ljava/lang/String;
     166: invokevirtual #53                 // Method java/lang/StringBuilder.append:(Ljava/lang/String;)Ljava/lang/StringBuilder;
     169: invokevirtual #55                 // Method java/lang/StringBuilder.toString:()Ljava/lang/String;
     172: astore_3
     173: getstatic     #65                 // Field logger:Lorg/apache/dubbo/common/logger/ErrorTypeAwareLogger;
     176: ldc           #66                 // String 6-14
     178: ldc           #67                 // String
     180: ldc           #67                 // String
     182: aload_3
     183: aload_2
     184: invokeinterface #68,  6           // InterfaceMethod org/apache/dubbo/common/logger/ErrorTypeAwareLogger.error:(Ljava/lang/String;Ljava/lang/String;Ljava/lang/String;Ljava/lang/String;Ljava/lang/Throwable;)V
     189: new           #69                 // class org/apache/dubbo/rpc/RpcException
     192: dup
     193: aload_3
     194: aload_2
     195: invokespecial #70                 // Method org/apache/dubbo/rpc/RpcException."<init>":(Ljava/lang/String;Ljava/lang/Throwable;)V
     198: athrow
    Exception table:
       from    to  target type
          72    76    79   Class java/lang/Throwable
          34    64    97   Class java/lang/Throwable
          34    64   105   any
         115   119   122   Class java/lang/Throwable
          97   107   105   any
           0    94   140   Class java/lang/Throwable
          97   140   140   Class java/lang/Throwable

  private java.lang.String getMetadataStandalone(org.apache.dubbo.metadata.report.identifier.BaseMetadataIdentifier);
    Code:
       0: aload_0
       1: getfield      #31                 // Field pool:Lredis/clients/jedis/JedisPool;
       4: invokevirtual #71                 // Method redis/clients/jedis/JedisPool.getResource:()Lredis/clients/jedis/Jedis;
       7: astore_2
       8: aconst_null
       9: astore_3
      10: aload_2
      11: aload_1
      12: getstatic     #72                 // Field org/apache/dubbo/metadata/report/identifier/KeyTypeEnum.UNIQUE_KEY:Lorg/apache/dubbo/metadata/report/identifier/KeyTypeEnum;
      15: invokeinterface #73,  2           // InterfaceMethod org/apache/dubbo/metadata/report/identifier/BaseMetadataIdentifier.getUniqueKey:(Lorg/apache/dubbo/metadata/report/identifier/KeyTypeEnum;)Ljava/lang/String;
      20: invokevirtual #88                 // Method redis/clients/jedis/Jedis.get:(Ljava/lang/String;)Ljava/lang/String;
      23: astore        4
      25: aload_2
      26: ifnull        55
      29: aload_3
      30: ifnull        51
      33: aload_2
      34: invokevirtual #75                 // Method redis/clients/jedis/Jedis.close:()V
      37: goto          55
      40: astore        5
      42: aload_3
      43: aload         5
      45: invokevirtual #59                 // Method java/lang/Throwable.addSuppressed:(Ljava/lang/Throwable;)V
      48: goto          55
      51: aload_2
      52: invokevirtual #75                 // Method redis/clients/jedis/Jedis.close:()V
      55: aload         4
      57: areturn
      58: astore        4
      60: aload         4
      62: astore_3
      63: aload         4
      65: athrow
      66: astore        6
      68: aload_2
      69: ifnull        98
      72: aload_3
      73: ifnull        94
      76: aload_2
      77: invokevirtual #75                 // Method redis/clients/jedis/Jedis.close:()V
      80: goto          98
      83: astore        7
      85: aload_3
      86: aload         7
      88: invokevirtual #59                 // Method java/lang/Throwable.addSuppressed:(Ljava/lang/Throwable;)V
      91: goto          98
      94: aload_2
      95: invokevirtual #75                 // Method redis/clients/jedis/Jedis.close:()V
      98: aload         6
     100: athrow
     101: astore_2
     102: new           #50                 // class java/lang/StringBuilder
     105: dup
     106: invokespecial #51                 // Method java/lang/StringBuilder."<init>":()V
     109: ldc           #87                 // String Failed to get
     111: invokevirtual #53                 // Method java/lang/StringBuilder.append:(Ljava/lang/String;)Ljava/lang/StringBuilder;
     114: aload_1
     115: invokevirtual #61                 // Method java/lang/StringBuilder.append:(Ljava/lang/Object;)Ljava/lang/StringBuilder;
     118: ldc           #83                 // String  from redis , cause:
     120: invokevirtual #53                 // Method java/lang/StringBuilder.append:(Ljava/lang/String;)Ljava/lang/StringBuilder;
     123: aload_2
     124: invokevirtual #64                 // Method java/lang/Throwable.getMessage:()Ljava/lang/String;
     127: invokevirtual #53                 // Method java/lang/StringBuilder.append:(Ljava/lang/String;)Ljava/lang/StringBuilder;
     130: invokevirtual #55                 // Method java/lang/StringBuilder.toString:()Ljava/lang/String;
     133: astore_3
     134: getstatic     #65                 // Field logger:Lorg/apache/dubbo/common/logger/ErrorTypeAwareLogger;
     137: ldc           #66                 // String 6-14
     139: ldc           #67                 // String
     141: ldc           #67                 // String
     143: aload_3
     144: aload_2
     145: invokeinterface #68,  6           // InterfaceMethod org/apache/dubbo/common/logger/ErrorTypeAwareLogger.error:(Ljava/lang/String;Ljava/lang/String;Ljava/lang/String;Ljava/lang/String;Ljava/lang/Throwable;)V
     150: new           #69                 // class org/apache/dubbo/rpc/RpcException
     153: dup
     154: aload_3
     155: aload_2
     156: invokespecial #70                 // Method org/apache/dubbo/rpc/RpcException."<init>":(Ljava/lang/String;Ljava/lang/Throwable;)V
     159: athrow
    Exception table:
       from    to  target type
          33    37    40   Class java/lang/Throwable
          10    25    58   Class java/lang/Throwable
          10    25    66   any
          76    80    83   Class java/lang/Throwable
          58    68    66   any
           0    55   101   Class java/lang/Throwable
          58   101   101   Class java/lang/Throwable

  static {};
    Code:
       0: ldc           #25                 // class org/apache/dubbo/metadata/store/redis/RedisMetadataReport
       2: invokestatic  #89                 // Method org/apache/dubbo/common/logger/LoggerFactory.getErrorTypeAwareLogger:(Ljava/lang/Class;)Lorg/apache/dubbo/common/logger/ErrorTypeAwareLogger;
       5: putstatic     #65                 // Field logger:Lorg/apache/dubbo/common/logger/ErrorTypeAwareLogger;
       8: return
}
