Compiled from "RedisMetadataReportFactory.java"
public class org.apache.dubbo.metadata.store.redis.RedisMetadataReportFactory extends org.apache.dubbo.metadata.report.support.AbstractMetadataReportFactory {
  public org.apache.dubbo.metadata.store.redis.RedisMetadataReportFactory();
    Code:
       0: aload_0
       1: invokespecial #1                  // Method org/apache/dubbo/metadata/report/support/AbstractMetadataReportFactory."<init>":()V
       4: return

  public org.apache.dubbo.metadata.report.MetadataReport createMetadataReport(org.apache.dubbo.common.URL);
    Code:
       0: new           #2                  // class org/apache/dubbo/metadata/store/redis/RedisMetadataReport
       3: dup
       4: aload_1
       5: invokespecial #3                  // Method org/apache/dubbo/metadata/store/redis/RedisMetadataReport."<init>":(Lorg/apache/dubbo/common/URL;)V
       8: areturn
}
