Compiled from "ConfigCenterMetricsCollector.java"
public class org.apache.dubbo.metrics.config.collector.ConfigCenterMetricsCollector extends org.apache.dubbo.metrics.collector.CombMetricsCollector<org.apache.dubbo.metrics.config.event.ConfigCenterEvent> {
  private java.lang.Boolean collectEnabled;

  private final org.apache.dubbo.rpc.model.ApplicationModel applicationModel;

  private final java.util.Map<org.apache.dubbo.metrics.model.ConfigCenterMetric, java.util.concurrent.atomic.AtomicLong> updatedMetrics;

  public org.apache.dubbo.metrics.config.collector.ConfigCenterMetricsCollector(org.apache.dubbo.rpc.model.ApplicationModel);
    Code:
       0: aload_0
       1: aconst_null
       2: invokespecial #1                  // Method org/apache/dubbo/metrics/collector/CombMetricsCollector."<init>":(Lorg/apache/dubbo/metrics/data/BaseStatComposite;)V
       5: aload_0
       6: aconst_null
       7: putfield      #2                  // Field collectEnabled:Ljava/lang/Boolean;
      10: aload_0
      11: new           #3                  // class java/util/concurrent/ConcurrentHashMap
      14: dup
      15: invokespecial #4                  // Method java/util/concurrent/ConcurrentHashMap."<init>":()V
      18: putfield      #5                  // Field updatedMetrics:Ljava/util/Map;
      21: aload_0
      22: aload_1
      23: putfield      #6                  // Field applicationModel:Lorg/apache/dubbo/rpc/model/ApplicationModel;
      26: aload_0
      27: new           #7                  // class org/apache/dubbo/metrics/config/event/ConfigCenterSubDispatcher
      30: dup
      31: aload_0
      32: invokespecial #8                  // Method org/apache/dubbo/metrics/config/event/ConfigCenterSubDispatcher."<init>":(Lorg/apache/dubbo/metrics/config/collector/ConfigCenterMetricsCollector;)V
      35: invokespecial #9                  // Method org/apache/dubbo/metrics/collector/CombMetricsCollector.setEventMulticaster:(Lorg/apache/dubbo/metrics/event/MetricsEventMulticaster;)V
      38: return

  public void setCollectEnabled(java.lang.Boolean);
    Code:
       0: aload_1
       1: ifnull        9
       4: aload_0
       5: aload_1
       6: putfield      #2                  // Field collectEnabled:Ljava/lang/Boolean;
       9: return

  public boolean isCollectEnabled();
    Code:
       0: aload_0
       1: getfield      #2                  // Field collectEnabled:Ljava/lang/Boolean;
       4: ifnonnull     28
       7: aload_0
       8: getfield      #6                  // Field applicationModel:Lorg/apache/dubbo/rpc/model/ApplicationModel;
      11: invokevirtual #10                 // Method org/apache/dubbo/rpc/model/ApplicationModel.getApplicationConfigManager:()Lorg/apache/dubbo/config/context/ConfigManager;
      14: astore_1
      15: aload_1
      16: invokevirtual #11                 // Method org/apache/dubbo/config/context/ConfigManager.getMetrics:()Ljava/util/Optional;
      19: aload_0
      20: invokedynamic #12,  0             // InvokeDynamic #0:accept:(Lorg/apache/dubbo/metrics/config/collector/ConfigCenterMetricsCollector;)Ljava/util/function/Consumer;
      25: invokevirtual #13                 // Method java/util/Optional.ifPresent:(Ljava/util/function/Consumer;)V
      28: aload_0
      29: getfield      #2                  // Field collectEnabled:Ljava/lang/Boolean;
      32: invokestatic  #14                 // Method java/util/Optional.ofNullable:(Ljava/lang/Object;)Ljava/util/Optional;
      35: iconst_1
      36: invokestatic  #15                 // Method java/lang/Boolean.valueOf:(Z)Ljava/lang/Boolean;
      39: invokevirtual #16                 // Method java/util/Optional.orElse:(Ljava/lang/Object;)Ljava/lang/Object;
      42: checkcast     #17                 // class java/lang/Boolean
      45: invokevirtual #18                 // Method java/lang/Boolean.booleanValue:()Z
      48: ireturn

  public void increase(java.lang.String, java.lang.String, java.lang.String, java.lang.String, int);
    Code:
       0: aload_0
       1: invokevirtual #19                 // Method isCollectEnabled:()Z
       4: ifne          8
       7: return
       8: new           #20                 // class org/apache/dubbo/metrics/model/ConfigCenterMetric
      11: dup
      12: aload_0
      13: getfield      #6                  // Field applicationModel:Lorg/apache/dubbo/rpc/model/ApplicationModel;
      16: invokevirtual #21                 // Method org/apache/dubbo/rpc/model/ApplicationModel.getApplicationName:()Ljava/lang/String;
      19: aload_1
      20: aload_2
      21: aload_3
      22: aload         4
      24: invokespecial #22                 // Method org/apache/dubbo/metrics/model/ConfigCenterMetric."<init>":(Ljava/lang/String;Ljava/lang/String;Ljava/lang/String;Ljava/lang/String;Ljava/lang/String;)V
      27: astore        6
      29: aload_0
      30: getfield      #5                  // Field updatedMetrics:Ljava/util/Map;
      33: aload         6
      35: invokedynamic #23,  0             // InvokeDynamic #1:apply:()Ljava/util/function/Function;
      40: invokeinterface #24,  3           // InterfaceMethod java/util/Map.computeIfAbsent:(Ljava/lang/Object;Ljava/util/function/Function;)Ljava/lang/Object;
      45: checkcast     #25                 // class java/util/concurrent/atomic/AtomicLong
      48: iload         5
      50: i2l
      51: invokevirtual #26                 // Method java/util/concurrent/atomic/AtomicLong.addAndGet:(J)J
      54: pop2
      55: return

  public java.util.List<org.apache.dubbo.metrics.model.sample.MetricSample> collect();
    Code:
       0: new           #27                 // class java/util/ArrayList
       3: dup
       4: invokespecial #28                 // Method java/util/ArrayList."<init>":()V
       7: astore_1
       8: aload_0
       9: invokevirtual #19                 // Method isCollectEnabled:()Z
      12: ifne          17
      15: aload_1
      16: areturn
      17: aload_0
      18: getfield      #5                  // Field updatedMetrics:Ljava/util/Map;
      21: aload_1
      22: invokedynamic #29,  0             // InvokeDynamic #2:accept:(Ljava/util/List;)Ljava/util/function/BiConsumer;
      27: invokeinterface #30,  2           // InterfaceMethod java/util/Map.forEach:(Ljava/util/function/BiConsumer;)V
      32: aload_1
      33: areturn

  private static void lambda$collect$2(java.util.List, org.apache.dubbo.metrics.model.ConfigCenterMetric, java.util.concurrent.atomic.AtomicLong);
    Code:
       0: aload_0
       1: new           #31                 // class org/apache/dubbo/metrics/model/sample/GaugeMetricSample
       4: dup
       5: getstatic     #32                 // Field org/apache/dubbo/metrics/model/key/MetricsKey.CONFIGCENTER_METRIC_TOTAL:Lorg/apache/dubbo/metrics/model/key/MetricsKey;
       8: aload_1
       9: invokevirtual #33                 // Method org/apache/dubbo/metrics/model/ConfigCenterMetric.getTags:()Ljava/util/Map;
      12: getstatic     #34                 // Field org/apache/dubbo/metrics/model/MetricsCategory.CONFIGCENTER:Lorg/apache/dubbo/metrics/model/MetricsCategory;
      15: aload_2
      16: invokedynamic #35,  0             // InvokeDynamic #3:applyAsDouble:()Ljava/util/function/ToDoubleFunction;
      21: invokespecial #36                 // Method org/apache/dubbo/metrics/model/sample/GaugeMetricSample."<init>":(Lorg/apache/dubbo/metrics/model/key/MetricsKey;Ljava/util/Map;Lorg/apache/dubbo/metrics/model/MetricsCategory;Ljava/lang/Object;Ljava/util/function/ToDoubleFunction;)V
      24: invokeinterface #37,  2           // InterfaceMethod java/util/List.add:(Ljava/lang/Object;)Z
      29: pop
      30: return

  private static java.util.concurrent.atomic.AtomicLong lambda$increase$1(org.apache.dubbo.metrics.model.ConfigCenterMetric);
    Code:
       0: new           #25                 // class java/util/concurrent/atomic/AtomicLong
       3: dup
       4: lconst_0
       5: invokespecial #38                 // Method java/util/concurrent/atomic/AtomicLong."<init>":(J)V
       8: areturn

  private void lambda$isCollectEnabled$0(org.apache.dubbo.config.MetricsConfig);
    Code:
       0: aload_0
       1: aload_1
       2: invokevirtual #39                 // Method org/apache/dubbo/config/MetricsConfig.getEnableMetadata:()Ljava/lang/Boolean;
       5: invokevirtual #40                 // Method setCollectEnabled:(Ljava/lang/Boolean;)V
       8: return
}
