Compiled from "AbstractServiceDiscovery.java"
class org.apache.dubbo.registry.client.AbstractServiceDiscovery$MetadataInfoStat {
  private final org.apache.dubbo.metadata.MetadataInfo metadataInfo;

  private final long updateTime;

  public org.apache.dubbo.registry.client.AbstractServiceDiscovery$MetadataInfoStat(org.apache.dubbo.metadata.MetadataInfo);
    Code:
       0: aload_0
       1: invokespecial #1                  // Method java/lang/Object."<init>":()V
       4: aload_0
       5: invokestatic  #2                  // Method java/lang/System.currentTimeMillis:()J
       8: putfield      #3                  // Field updateTime:J
      11: aload_0
      12: aload_1
      13: putfield      #4                  // Field metadataInfo:Lorg/apache/dubbo/metadata/MetadataInfo;
      16: return

  public org.apache.dubbo.metadata.MetadataInfo getMetadataInfo();
    Code:
       0: aload_0
       1: getfield      #4                  // Field metadataInfo:Lorg/apache/dubbo/metadata/MetadataInfo;
       4: areturn

  public long getUpdateTime();
    Code:
       0: aload_0
       1: getfield      #3                  // Field updateTime:J
       4: lreturn
}
