Compiled from "AbstractServiceDiscovery.java"
public abstract class org.apache.dubbo.registry.client.AbstractServiceDiscovery implements org.apache.dubbo.registry.client.ServiceDiscovery {
  private final org.apache.dubbo.common.logger.ErrorTypeAwareLogger logger;

  private volatile boolean isDestroy;

  protected final java.lang.String serviceName;

  protected volatile org.apache.dubbo.registry.client.ServiceInstance serviceInstance;

  protected volatile org.apache.dubbo.metadata.MetadataInfo metadataInfo;

  protected final java.util.concurrent.ConcurrentHashMap<java.lang.String, org.apache.dubbo.registry.client.AbstractServiceDiscovery$MetadataInfoStat> metadataInfos;

  protected final java.util.concurrent.ScheduledFuture<?> refreshCacheFuture;

  protected org.apache.dubbo.metadata.report.MetadataReport metadataReport;

  protected java.lang.String metadataType;

  protected final org.apache.dubbo.registry.client.metadata.store.MetaCacheManager metaCacheManager;

  protected org.apache.dubbo.common.URL registryURL;

  protected java.util.Set<org.apache.dubbo.registry.client.event.listener.ServiceInstancesChangedListener> instanceListeners;

  protected org.apache.dubbo.rpc.model.ApplicationModel applicationModel;

  public org.apache.dubbo.registry.client.AbstractServiceDiscovery(org.apache.dubbo.rpc.model.ApplicationModel, org.apache.dubbo.common.URL);
    Code:
       0: aload_0
       1: aload_1
       2: aload_1
       3: invokevirtual #6                  // Method org/apache/dubbo/rpc/model/ApplicationModel.getApplicationName:()Ljava/lang/String;
       6: aload_2
       7: invokespecial #7                  // Method "<init>":(Lorg/apache/dubbo/rpc/model/ApplicationModel;Ljava/lang/String;Lorg/apache/dubbo/common/URL;)V
      10: aload_1
      11: invokevirtual #8                  // Method org/apache/dubbo/rpc/model/ApplicationModel.getBeanFactory:()Lorg/apache/dubbo/common/beans/factory/ScopeBeanFactory;
      14: ldc           #9                  // class org/apache/dubbo/metadata/report/MetadataReportInstance
      16: invokevirtual #10                 // Method org/apache/dubbo/common/beans/factory/ScopeBeanFactory.getBean:(Ljava/lang/Class;)Ljava/lang/Object;
      19: checkcast     #9                  // class org/apache/dubbo/metadata/report/MetadataReportInstance
      22: astore_3
      23: aload_0
      24: aload_3
      25: invokevirtual #11                 // Method org/apache/dubbo/metadata/report/MetadataReportInstance.getMetadataType:()Ljava/lang/String;
      28: putfield      #12                 // Field metadataType:Ljava/lang/String;
      31: aload_0
      32: aload_3
      33: aload_2
      34: ldc           #13                 // String REGISTRY_CLUSTER
      36: invokevirtual #14                 // Method org/apache/dubbo/common/URL.getParameter:(Ljava/lang/String;)Ljava/lang/String;
      39: invokevirtual #15                 // Method org/apache/dubbo/metadata/report/MetadataReportInstance.getMetadataReport:(Ljava/lang/String;)Lorg/apache/dubbo/metadata/report/MetadataReport;
      42: putfield      #16                 // Field metadataReport:Lorg/apache/dubbo/metadata/report/MetadataReport;
      45: return

  public org.apache.dubbo.registry.client.AbstractServiceDiscovery(java.lang.String, org.apache.dubbo.common.URL);
    Code:
       0: aload_0
       1: invokestatic  #17                 // Method org/apache/dubbo/rpc/model/ApplicationModel.defaultModel:()Lorg/apache/dubbo/rpc/model/ApplicationModel;
       4: aload_1
       5: aload_2
       6: invokespecial #7                  // Method "<init>":(Lorg/apache/dubbo/rpc/model/ApplicationModel;Ljava/lang/String;Lorg/apache/dubbo/common/URL;)V
       9: return

  private org.apache.dubbo.registry.client.AbstractServiceDiscovery(org.apache.dubbo.rpc.model.ApplicationModel, java.lang.String, org.apache.dubbo.common.URL);
    Code:
       0: aload_0
       1: invokespecial #18                 // Method java/lang/Object."<init>":()V
       4: aload_0
       5: ldc           #19                 // class org/apache/dubbo/registry/client/AbstractServiceDiscovery
       7: invokestatic  #20                 // Method org/apache/dubbo/common/logger/LoggerFactory.getErrorTypeAwareLogger:(Ljava/lang/Class;)Lorg/apache/dubbo/common/logger/ErrorTypeAwareLogger;
      10: putfield      #21                 // Field logger:Lorg/apache/dubbo/common/logger/ErrorTypeAwareLogger;
      13: aload_0
      14: new           #22                 // class java/util/concurrent/ConcurrentHashMap
      17: dup
      18: invokespecial #23                 // Method java/util/concurrent/ConcurrentHashMap."<init>":()V
      21: putfield      #24                 // Field metadataInfos:Ljava/util/concurrent/ConcurrentHashMap;
      24: aload_0
      25: new           #25                 // class org/apache/dubbo/common/utils/ConcurrentHashSet
      28: dup
      29: invokespecial #26                 // Method org/apache/dubbo/common/utils/ConcurrentHashSet."<init>":()V
      32: putfield      #27                 // Field instanceListeners:Ljava/util/Set;
      35: aload_0
      36: aload_1
      37: putfield      #28                 // Field applicationModel:Lorg/apache/dubbo/rpc/model/ApplicationModel;
      40: aload_0
      41: aload_2
      42: putfield      #29                 // Field serviceName:Ljava/lang/String;
      45: aload_0
      46: aload_3
      47: putfield      #30                 // Field registryURL:Lorg/apache/dubbo/common/URL;
      50: aload_0
      51: new           #31                 // class org/apache/dubbo/metadata/MetadataInfo
      54: dup
      55: aload_2
      56: invokespecial #32                 // Method org/apache/dubbo/metadata/MetadataInfo."<init>":(Ljava/lang/String;)V
      59: putfield      #33                 // Field metadataInfo:Lorg/apache/dubbo/metadata/MetadataInfo;
      62: aload_3
      63: ldc           #34                 // String file-cache
      65: iconst_1
      66: invokevirtual #35                 // Method org/apache/dubbo/common/URL.getParameter:(Ljava/lang/String;Z)Z
      69: istore        4
      71: aload_0
      72: new           #36                 // class org/apache/dubbo/registry/client/metadata/store/MetaCacheManager
      75: dup
      76: iload         4
      78: aload_0
      79: invokespecial #37                 // Method getCacheNameSuffix:()Ljava/lang/String;
      82: aload_1
      83: invokevirtual #38                 // Method org/apache/dubbo/rpc/model/ApplicationModel.getFrameworkModel:()Lorg/apache/dubbo/rpc/model/FrameworkModel;
      86: invokevirtual #39                 // Method org/apache/dubbo/rpc/model/FrameworkModel.getBeanFactory:()Lorg/apache/dubbo/common/beans/factory/ScopeBeanFactory;
      89: ldc           #40                 // class org/apache/dubbo/common/threadpool/manager/FrameworkExecutorRepository
      91: invokevirtual #10                 // Method org/apache/dubbo/common/beans/factory/ScopeBeanFactory.getBean:(Ljava/lang/Class;)Ljava/lang/Object;
      94: checkcast     #40                 // class org/apache/dubbo/common/threadpool/manager/FrameworkExecutorRepository
      97: invokevirtual #41                 // Method org/apache/dubbo/common/threadpool/manager/FrameworkExecutorRepository.getCacheRefreshingScheduledExecutor:()Ljava/util/concurrent/ScheduledExecutorService;
     100: invokespecial #42                 // Method org/apache/dubbo/registry/client/metadata/store/MetaCacheManager."<init>":(ZLjava/lang/String;Ljava/util/concurrent/ScheduledExecutorService;)V
     103: putfield      #43                 // Field metaCacheManager:Lorg/apache/dubbo/registry/client/metadata/store/MetaCacheManager;
     106: aload_3
     107: ldc           #44                 // String metadata-info-cache.expire
     109: ldc           #45                 // int 600000
     111: invokevirtual #46                 // Method org/apache/dubbo/common/URL.getParameter:(Ljava/lang/String;I)I
     114: istore        5
     116: aload_3
     117: ldc           #47                 // String metadata-info-cache.size
     119: bipush        16
     121: invokevirtual #46                 // Method org/apache/dubbo/common/URL.getParameter:(Ljava/lang/String;I)I
     124: istore        6
     126: aload_0
     127: aload_1
     128: invokevirtual #38                 // Method org/apache/dubbo/rpc/model/ApplicationModel.getFrameworkModel:()Lorg/apache/dubbo/rpc/model/FrameworkModel;
     131: invokevirtual #39                 // Method org/apache/dubbo/rpc/model/FrameworkModel.getBeanFactory:()Lorg/apache/dubbo/common/beans/factory/ScopeBeanFactory;
     134: ldc           #40                 // class org/apache/dubbo/common/threadpool/manager/FrameworkExecutorRepository
     136: invokevirtual #10                 // Method org/apache/dubbo/common/beans/factory/ScopeBeanFactory.getBean:(Ljava/lang/Class;)Ljava/lang/Object;
     139: checkcast     #40                 // class org/apache/dubbo/common/threadpool/manager/FrameworkExecutorRepository
     142: invokevirtual #48                 // Method org/apache/dubbo/common/threadpool/manager/FrameworkExecutorRepository.getSharedScheduledExecutor:()Ljava/util/concurrent/ScheduledExecutorService;
     145: aload_0
     146: iload         6
     148: iload         5
     150: invokedynamic #49,  0             // InvokeDynamic #0:run:(Lorg/apache/dubbo/registry/client/AbstractServiceDiscovery;II)Ljava/lang/Runnable;
     155: iload         5
     157: iconst_2
     158: idiv
     159: i2l
     160: iload         5
     162: iconst_2
     163: idiv
     164: i2l
     165: getstatic     #50                 // Field java/util/concurrent/TimeUnit.MILLISECONDS:Ljava/util/concurrent/TimeUnit;
     168: invokeinterface #51,  7           // InterfaceMethod java/util/concurrent/ScheduledExecutorService.scheduleAtFixedRate:(Ljava/lang/Runnable;JJLjava/util/concurrent/TimeUnit;)Ljava/util/concurrent/ScheduledFuture;
     173: putfield      #52                 // Field refreshCacheFuture:Ljava/util/concurrent/ScheduledFuture;
     176: return

  public synchronized void register() throws java.lang.RuntimeException;
    Code:
       0: aload_0
       1: getfield      #53                 // Field isDestroy:Z
       4: ifeq          8
       7: return
       8: aload_0
       9: aload_0
      10: getfield      #33                 // Field metadataInfo:Lorg/apache/dubbo/metadata/MetadataInfo;
      13: invokevirtual #54                 // Method createServiceInstance:(Lorg/apache/dubbo/metadata/MetadataInfo;)Lorg/apache/dubbo/registry/client/ServiceInstance;
      16: astore_1
      17: aload_1
      18: invokestatic  #55                 // Method org/apache/dubbo/registry/client/metadata/ServiceInstanceMetadataUtils.isValidInstance:(Lorg/apache/dubbo/registry/client/ServiceInstance;)Z
      21: ifne          25
      24: return
      25: aload_0
      26: aload_1
      27: putfield      #56                 // Field serviceInstance:Lorg/apache/dubbo/registry/client/ServiceInstance;
      30: aload_0
      31: aload_0
      32: getfield      #56                 // Field serviceInstance:Lorg/apache/dubbo/registry/client/ServiceInstance;
      35: invokevirtual #57                 // Method calOrUpdateInstanceRevision:(Lorg/apache/dubbo/registry/client/ServiceInstance;)Z
      38: istore_2
      39: iload_2
      40: ifeq          59
      43: aload_0
      44: aload_0
      45: getfield      #33                 // Field metadataInfo:Lorg/apache/dubbo/metadata/MetadataInfo;
      48: invokevirtual #58                 // Method reportMetadata:(Lorg/apache/dubbo/metadata/MetadataInfo;)V
      51: aload_0
      52: aload_0
      53: getfield      #56                 // Field serviceInstance:Lorg/apache/dubbo/registry/client/ServiceInstance;
      56: invokevirtual #59                 // Method doRegister:(Lorg/apache/dubbo/registry/client/ServiceInstance;)V
      59: return

  public synchronized void update() throws java.lang.RuntimeException;
    Code:
       0: aload_0
       1: getfield      #53                 // Field isDestroy:Z
       4: ifeq          8
       7: return
       8: aload_0
       9: getfield      #56                 // Field serviceInstance:Lorg/apache/dubbo/registry/client/ServiceInstance;
      12: ifnonnull     19
      15: aload_0
      16: invokevirtual #60                 // Method register:()V
      19: aload_0
      20: getfield      #56                 // Field serviceInstance:Lorg/apache/dubbo/registry/client/ServiceInstance;
      23: invokestatic  #55                 // Method org/apache/dubbo/registry/client/metadata/ServiceInstanceMetadataUtils.isValidInstance:(Lorg/apache/dubbo/registry/client/ServiceInstance;)Z
      26: ifne          30
      29: return
      30: aload_0
      31: getfield      #56                 // Field serviceInstance:Lorg/apache/dubbo/registry/client/ServiceInstance;
      34: astore_1
      35: new           #61                 // class org/apache/dubbo/registry/client/DefaultServiceInstance
      38: dup
      39: aload_1
      40: checkcast     #61                 // class org/apache/dubbo/registry/client/DefaultServiceInstance
      43: invokespecial #62                 // Method org/apache/dubbo/registry/client/DefaultServiceInstance."<init>":(Lorg/apache/dubbo/registry/client/DefaultServiceInstance;)V
      46: astore_2
      47: aload_0
      48: aload_2
      49: invokevirtual #57                 // Method calOrUpdateInstanceRevision:(Lorg/apache/dubbo/registry/client/ServiceInstance;)Z
      52: istore_3
      53: iload_3
      54: ifeq          96
      57: aload_0
      58: getfield      #21                 // Field logger:Lorg/apache/dubbo/common/logger/ErrorTypeAwareLogger;
      61: ldc           #63                 // String Metadata of instance changed, updating instance with revision %s.
      63: iconst_1
      64: anewarray     #64                 // class java/lang/Object
      67: dup
      68: iconst_0
      69: aload_2
      70: invokevirtual #65                 // Method org/apache/dubbo/registry/client/DefaultServiceInstance.getServiceMetadata:()Lorg/apache/dubbo/metadata/MetadataInfo;
      73: invokevirtual #66                 // Method org/apache/dubbo/metadata/MetadataInfo.getRevision:()Ljava/lang/String;
      76: aastore
      77: invokestatic  #67                 // Method java/lang/String.format:(Ljava/lang/String;[Ljava/lang/Object;)Ljava/lang/String;
      80: invokeinterface #68,  2           // InterfaceMethod org/apache/dubbo/common/logger/ErrorTypeAwareLogger.info:(Ljava/lang/String;)V
      85: aload_0
      86: aload_1
      87: aload_2
      88: invokevirtual #69                 // Method doUpdate:(Lorg/apache/dubbo/registry/client/ServiceInstance;Lorg/apache/dubbo/registry/client/ServiceInstance;)V
      91: aload_0
      92: aload_2
      93: putfield      #56                 // Field serviceInstance:Lorg/apache/dubbo/registry/client/ServiceInstance;
      96: return

  public synchronized void unregister() throws java.lang.RuntimeException;
    Code:
       0: aload_0
       1: getfield      #53                 // Field isDestroy:Z
       4: ifeq          8
       7: return
       8: aload_0
       9: getfield      #56                 // Field serviceInstance:Lorg/apache/dubbo/registry/client/ServiceInstance;
      12: invokestatic  #55                 // Method org/apache/dubbo/registry/client/metadata/ServiceInstanceMetadataUtils.isValidInstance:(Lorg/apache/dubbo/registry/client/ServiceInstance;)Z
      15: ifne          19
      18: return
      19: aload_0
      20: aload_0
      21: getfield      #56                 // Field serviceInstance:Lorg/apache/dubbo/registry/client/ServiceInstance;
      24: invokevirtual #70                 // Method doUnregister:(Lorg/apache/dubbo/registry/client/ServiceInstance;)V
      27: return

  public final org.apache.dubbo.registry.client.ServiceInstance getLocalInstance();
    Code:
       0: aload_0
       1: getfield      #56                 // Field serviceInstance:Lorg/apache/dubbo/registry/client/ServiceInstance;
       4: areturn

  public org.apache.dubbo.metadata.MetadataInfo getLocalMetadata();
    Code:
       0: aload_0
       1: getfield      #33                 // Field metadataInfo:Lorg/apache/dubbo/metadata/MetadataInfo;
       4: areturn

  public org.apache.dubbo.metadata.MetadataInfo getLocalMetadata(java.lang.String);
    Code:
       0: aload_0
       1: getfield      #24                 // Field metadataInfos:Ljava/util/concurrent/ConcurrentHashMap;
       4: aload_1
       5: invokevirtual #71                 // Method java/util/concurrent/ConcurrentHashMap.get:(Ljava/lang/Object;)Ljava/lang/Object;
       8: checkcast     #72                 // class org/apache/dubbo/registry/client/AbstractServiceDiscovery$MetadataInfoStat
      11: astore_2
      12: aload_2
      13: ifnull        21
      16: aload_2
      17: invokevirtual #73                 // Method org/apache/dubbo/registry/client/AbstractServiceDiscovery$MetadataInfoStat.getMetadataInfo:()Lorg/apache/dubbo/metadata/MetadataInfo;
      20: areturn
      21: aconst_null
      22: areturn

  public org.apache.dubbo.metadata.MetadataInfo getRemoteMetadata(java.lang.String, java.util.List<org.apache.dubbo.registry.client.ServiceInstance>);
    Code:
       0: aload_0
       1: getfield      #43                 // Field metaCacheManager:Lorg/apache/dubbo/registry/client/metadata/store/MetaCacheManager;
       4: aload_1
       5: invokevirtual #74                 // Method org/apache/dubbo/registry/client/metadata/store/MetaCacheManager.get:(Ljava/lang/String;)Ljava/lang/Object;
       8: checkcast     #31                 // class org/apache/dubbo/metadata/MetadataInfo
      11: astore_3
      12: aload_3
      13: ifnull        78
      16: aload_3
      17: getstatic     #75                 // Field org/apache/dubbo/metadata/MetadataInfo.EMPTY:Lorg/apache/dubbo/metadata/MetadataInfo;
      20: if_acmpeq     78
      23: aload_3
      24: invokevirtual #76                 // Method org/apache/dubbo/metadata/MetadataInfo.init:()V
      27: aload_0
      28: getfield      #21                 // Field logger:Lorg/apache/dubbo/common/logger/ErrorTypeAwareLogger;
      31: invokeinterface #77,  1           // InterfaceMethod org/apache/dubbo/common/logger/ErrorTypeAwareLogger.isDebugEnabled:()Z
      36: ifeq          76
      39: aload_0
      40: getfield      #21                 // Field logger:Lorg/apache/dubbo/common/logger/ErrorTypeAwareLogger;
      43: new           #78                 // class java/lang/StringBuilder
      46: dup
      47: invokespecial #79                 // Method java/lang/StringBuilder."<init>":()V
      50: ldc           #80                 // String MetadataInfo for revision=
      52: invokevirtual #81                 // Method java/lang/StringBuilder.append:(Ljava/lang/String;)Ljava/lang/StringBuilder;
      55: aload_1
      56: invokevirtual #81                 // Method java/lang/StringBuilder.append:(Ljava/lang/String;)Ljava/lang/StringBuilder;
      59: ldc           #82                 // String ,
      61: invokevirtual #81                 // Method java/lang/StringBuilder.append:(Ljava/lang/String;)Ljava/lang/StringBuilder;
      64: aload_3
      65: invokevirtual #83                 // Method java/lang/StringBuilder.append:(Ljava/lang/Object;)Ljava/lang/StringBuilder;
      68: invokevirtual #84                 // Method java/lang/StringBuilder.toString:()Ljava/lang/String;
      71: invokeinterface #85,  2           // InterfaceMethod org/apache/dubbo/common/logger/ErrorTypeAwareLogger.debug:(Ljava/lang/String;)V
      76: aload_3
      77: areturn
      78: aload_0
      79: getfield      #43                 // Field metaCacheManager:Lorg/apache/dubbo/registry/client/metadata/store/MetaCacheManager;
      82: dup
      83: astore        4
      85: monitorenter
      86: iconst_0
      87: istore        5
      89: iload         5
      91: iconst_3
      92: if_icmpge     208
      95: aload_0
      96: getfield      #28                 // Field applicationModel:Lorg/apache/dubbo/rpc/model/ApplicationModel;
      99: invokestatic  #86                 // Method org/apache/dubbo/metrics/metadata/event/MetadataEvent.toSubscribeEvent:(Lorg/apache/dubbo/rpc/model/ApplicationModel;)Lorg/apache/dubbo/metrics/metadata/event/MetadataEvent;
     102: aload_0
     103: aload_1
     104: aload_2
     105: invokedynamic #87,  0             // InvokeDynamic #1:get:(Lorg/apache/dubbo/registry/client/AbstractServiceDiscovery;Ljava/lang/String;Ljava/util/List;)Ljava/util/function/Supplier;
     110: invokedynamic #88,  0             // InvokeDynamic #2:apply:()Ljava/util/function/Function;
     115: invokestatic  #89                 // Method org/apache/dubbo/metrics/event/MetricsEventBus.post:(Lorg/apache/dubbo/metrics/event/MetricsEvent;Ljava/util/function/Supplier;Ljava/util/function/Function;)Ljava/lang/Object;
     118: checkcast     #31                 // class org/apache/dubbo/metadata/MetadataInfo
     121: astore_3
     122: aload_3
     123: getstatic     #75                 // Field org/apache/dubbo/metadata/MetadataInfo.EMPTY:Lorg/apache/dubbo/metadata/MetadataInfo;
     126: if_acmpeq     136
     129: aload_3
     130: invokevirtual #76                 // Method org/apache/dubbo/metadata/MetadataInfo.init:()V
     133: goto          208
     136: iload         5
     138: ifle          191
     141: aload_0
     142: getfield      #21                 // Field logger:Lorg/apache/dubbo/common/logger/ErrorTypeAwareLogger;
     145: invokeinterface #77,  1           // InterfaceMethod org/apache/dubbo/common/logger/ErrorTypeAwareLogger.isDebugEnabled:()Z
     150: ifeq          191
     153: aload_0
     154: getfield      #21                 // Field logger:Lorg/apache/dubbo/common/logger/ErrorTypeAwareLogger;
     157: new           #78                 // class java/lang/StringBuilder
     160: dup
     161: invokespecial #79                 // Method java/lang/StringBuilder."<init>":()V
     164: ldc           #90                 // String Retry the
     166: invokevirtual #81                 // Method java/lang/StringBuilder.append:(Ljava/lang/String;)Ljava/lang/StringBuilder;
     169: iload         5
     171: invokevirtual #91                 // Method java/lang/StringBuilder.append:(I)Ljava/lang/StringBuilder;
     174: ldc           #92                 // String  times to get metadata for revision=
     176: invokevirtual #81                 // Method java/lang/StringBuilder.append:(Ljava/lang/String;)Ljava/lang/StringBuilder;
     179: aload_1
     180: invokevirtual #81                 // Method java/lang/StringBuilder.append:(Ljava/lang/String;)Ljava/lang/StringBuilder;
     183: invokevirtual #84                 // Method java/lang/StringBuilder.toString:()Ljava/lang/String;
     186: invokeinterface #85,  2           // InterfaceMethod org/apache/dubbo/common/logger/ErrorTypeAwareLogger.debug:(Ljava/lang/String;)V
     191: iinc          5, 1
     194: ldc2_w        #93                 // long 1000l
     197: invokestatic  #95                 // Method java/lang/Thread.sleep:(J)V
     200: goto          89
     203: astore        6
     205: goto          89
     208: aload_3
     209: getstatic     #75                 // Field org/apache/dubbo/metadata/MetadataInfo.EMPTY:Lorg/apache/dubbo/metadata/MetadataInfo;
     212: if_acmpne     252
     215: aload_0
     216: getfield      #21                 // Field logger:Lorg/apache/dubbo/common/logger/ErrorTypeAwareLogger;
     219: ldc           #97                 // String 1-39
     221: ldc           #98                 // String
     223: ldc           #98                 // String
     225: new           #78                 // class java/lang/StringBuilder
     228: dup
     229: invokespecial #79                 // Method java/lang/StringBuilder."<init>":()V
     232: ldc           #99                 // String Failed to get metadata for revision after 3 retries, revision=
     234: invokevirtual #81                 // Method java/lang/StringBuilder.append:(Ljava/lang/String;)Ljava/lang/StringBuilder;
     237: aload_1
     238: invokevirtual #81                 // Method java/lang/StringBuilder.append:(Ljava/lang/String;)Ljava/lang/StringBuilder;
     241: invokevirtual #84                 // Method java/lang/StringBuilder.toString:()Ljava/lang/String;
     244: invokeinterface #100,  5          // InterfaceMethod org/apache/dubbo/common/logger/ErrorTypeAwareLogger.error:(Ljava/lang/String;Ljava/lang/String;Ljava/lang/String;Ljava/lang/String;)V
     249: goto          261
     252: aload_0
     253: getfield      #43                 // Field metaCacheManager:Lorg/apache/dubbo/registry/client/metadata/store/MetaCacheManager;
     256: aload_1
     257: aload_3
     258: invokevirtual #101                // Method org/apache/dubbo/registry/client/metadata/store/MetaCacheManager.put:(Ljava/lang/String;Ljava/lang/Object;)V
     261: aload         4
     263: monitorexit
     264: goto          275
     267: astore        7
     269: aload         4
     271: monitorexit
     272: aload         7
     274: athrow
     275: aload_3
     276: areturn
    Exception table:
       from    to  target type
         194   200   203   Class java/lang/InterruptedException
          86   264   267   any
         267   272   267   any

  public org.apache.dubbo.metadata.MetadataInfo getRemoteMetadata(java.lang.String);
    Code:
       0: aload_0
       1: getfield      #43                 // Field metaCacheManager:Lorg/apache/dubbo/registry/client/metadata/store/MetaCacheManager;
       4: aload_1
       5: invokevirtual #74                 // Method org/apache/dubbo/registry/client/metadata/store/MetaCacheManager.get:(Ljava/lang/String;)Ljava/lang/Object;
       8: checkcast     #31                 // class org/apache/dubbo/metadata/MetadataInfo
      11: areturn

  public final void destroy() throws java.lang.Exception;
    Code:
       0: aload_0
       1: iconst_1
       2: putfield      #53                 // Field isDestroy:Z
       5: aload_0
       6: getfield      #43                 // Field metaCacheManager:Lorg/apache/dubbo/registry/client/metadata/store/MetaCacheManager;
       9: invokevirtual #102                // Method org/apache/dubbo/registry/client/metadata/store/MetaCacheManager.destroy:()V
      12: aload_0
      13: getfield      #52                 // Field refreshCacheFuture:Ljava/util/concurrent/ScheduledFuture;
      16: iconst_1
      17: invokeinterface #103,  2          // InterfaceMethod java/util/concurrent/ScheduledFuture.cancel:(Z)Z
      22: pop
      23: aload_0
      24: invokevirtual #104                // Method doDestroy:()V
      27: return

  public final boolean isDestroy();
    Code:
       0: aload_0
       1: getfield      #53                 // Field isDestroy:Z
       4: ireturn

  public void register(org.apache.dubbo.common.URL);
    Code:
       0: aload_0
       1: getfield      #33                 // Field metadataInfo:Lorg/apache/dubbo/metadata/MetadataInfo;
       4: aload_1
       5: invokevirtual #105                // Method org/apache/dubbo/metadata/MetadataInfo.addService:(Lorg/apache/dubbo/common/URL;)V
       8: return

  public void unregister(org.apache.dubbo.common.URL);
    Code:
       0: aload_0
       1: getfield      #33                 // Field metadataInfo:Lorg/apache/dubbo/metadata/MetadataInfo;
       4: aload_1
       5: invokevirtual #106                // Method org/apache/dubbo/metadata/MetadataInfo.removeService:(Lorg/apache/dubbo/common/URL;)V
       8: return

  public void subscribe(org.apache.dubbo.common.URL, org.apache.dubbo.registry.NotifyListener);
    Code:
       0: aload_0
       1: getfield      #33                 // Field metadataInfo:Lorg/apache/dubbo/metadata/MetadataInfo;
       4: aload_1
       5: invokevirtual #107                // Method org/apache/dubbo/metadata/MetadataInfo.addSubscribedURL:(Lorg/apache/dubbo/common/URL;)V
       8: return

  public void unsubscribe(org.apache.dubbo.common.URL, org.apache.dubbo.registry.NotifyListener);
    Code:
       0: aload_0
       1: getfield      #33                 // Field metadataInfo:Lorg/apache/dubbo/metadata/MetadataInfo;
       4: aload_1
       5: invokevirtual #108                // Method org/apache/dubbo/metadata/MetadataInfo.removeSubscribedURL:(Lorg/apache/dubbo/common/URL;)Z
       8: pop
       9: return

  public java.util.List<org.apache.dubbo.common.URL> lookup(org.apache.dubbo.common.URL);
    Code:
       0: new           #109                // class java/lang/UnsupportedOperationException
       3: dup
       4: ldc           #110                // String Service discovery implementation does not support lookup of url list.
       6: invokespecial #111                // Method java/lang/UnsupportedOperationException."<init>":(Ljava/lang/String;)V
       9: athrow

  protected void doUpdate(org.apache.dubbo.registry.client.ServiceInstance, org.apache.dubbo.registry.client.ServiceInstance);
    Code:
       0: aload_0
       1: aload_1
       2: invokevirtual #70                 // Method doUnregister:(Lorg/apache/dubbo/registry/client/ServiceInstance;)V
       5: aload_0
       6: aload_2
       7: putfield      #56                 // Field serviceInstance:Lorg/apache/dubbo/registry/client/ServiceInstance;
      10: ldc           #112                // String 0
      12: aload_2
      13: invokestatic  #113                // Method org/apache/dubbo/registry/client/metadata/ServiceInstanceMetadataUtils.getExportedServicesRevision:(Lorg/apache/dubbo/registry/client/ServiceInstance;)Ljava/lang/String;
      16: invokevirtual #114                // Method java/lang/String.equals:(Ljava/lang/Object;)Z
      19: ifne          37
      22: aload_0
      23: aload_2
      24: invokeinterface #115,  1          // InterfaceMethod org/apache/dubbo/registry/client/ServiceInstance.getServiceMetadata:()Lorg/apache/dubbo/metadata/MetadataInfo;
      29: invokevirtual #58                 // Method reportMetadata:(Lorg/apache/dubbo/metadata/MetadataInfo;)V
      32: aload_0
      33: aload_2
      34: invokevirtual #59                 // Method doRegister:(Lorg/apache/dubbo/registry/client/ServiceInstance;)V
      37: return

  public org.apache.dubbo.common.URL getUrl();
    Code:
       0: aload_0
       1: getfield      #30                 // Field registryURL:Lorg/apache/dubbo/common/URL;
       4: areturn

  protected abstract void doRegister(org.apache.dubbo.registry.client.ServiceInstance) throws java.lang.RuntimeException;

  protected abstract void doUnregister(org.apache.dubbo.registry.client.ServiceInstance);

  protected abstract void doDestroy() throws java.lang.Exception;

  protected org.apache.dubbo.registry.client.ServiceInstance createServiceInstance(org.apache.dubbo.metadata.MetadataInfo);
    Code:
       0: new           #61                 // class org/apache/dubbo/registry/client/DefaultServiceInstance
       3: dup
       4: aload_0
       5: getfield      #29                 // Field serviceName:Ljava/lang/String;
       8: aload_0
       9: getfield      #28                 // Field applicationModel:Lorg/apache/dubbo/rpc/model/ApplicationModel;
      12: invokespecial #116                // Method org/apache/dubbo/registry/client/DefaultServiceInstance."<init>":(Ljava/lang/String;Lorg/apache/dubbo/rpc/model/ApplicationModel;)V
      15: astore_2
      16: aload_2
      17: aload_1
      18: invokevirtual #117                // Method org/apache/dubbo/registry/client/DefaultServiceInstance.setServiceMetadata:(Lorg/apache/dubbo/metadata/MetadataInfo;)V
      21: aload_2
      22: aload_0
      23: getfield      #12                 // Field metadataType:Ljava/lang/String;
      26: invokestatic  #118                // Method org/apache/dubbo/registry/client/metadata/ServiceInstanceMetadataUtils.setMetadataStorageType:(Lorg/apache/dubbo/registry/client/ServiceInstance;Ljava/lang/String;)V
      29: aload_2
      30: aload_0
      31: getfield      #28                 // Field applicationModel:Lorg/apache/dubbo/rpc/model/ApplicationModel;
      34: invokestatic  #119                // Method org/apache/dubbo/registry/client/metadata/ServiceInstanceMetadataUtils.customizeInstance:(Lorg/apache/dubbo/registry/client/ServiceInstance;Lorg/apache/dubbo/rpc/model/ApplicationModel;)V
      37: aload_2
      38: areturn

  protected boolean calOrUpdateInstanceRevision(org.apache.dubbo.registry.client.ServiceInstance);
    Code:
       0: aload_1
       1: invokestatic  #113                // Method org/apache/dubbo/registry/client/metadata/ServiceInstanceMetadataUtils.getExportedServicesRevision:(Lorg/apache/dubbo/registry/client/ServiceInstance;)Ljava/lang/String;
       4: astore_2
       5: aload_1
       6: invokeinterface #115,  1          // InterfaceMethod org/apache/dubbo/registry/client/ServiceInstance.getServiceMetadata:()Lorg/apache/dubbo/metadata/MetadataInfo;
      11: astore_3
      12: aload_3
      13: invokevirtual #120                // Method org/apache/dubbo/metadata/MetadataInfo.calAndGetRevision:()Ljava/lang/String;
      16: astore        4
      18: aload         4
      20: aload_2
      21: invokevirtual #114                // Method java/lang/String.equals:(Ljava/lang/Object;)Z
      24: ifne          47
      27: aload_1
      28: invokeinterface #121,  1          // InterfaceMethod org/apache/dubbo/registry/client/ServiceInstance.getMetadata:()Ljava/util/Map;
      33: ldc           #122                // String dubbo.metadata.revision
      35: aload_3
      36: invokevirtual #66                 // Method org/apache/dubbo/metadata/MetadataInfo.getRevision:()Ljava/lang/String;
      39: invokeinterface #123,  3          // InterfaceMethod java/util/Map.put:(Ljava/lang/Object;Ljava/lang/Object;)Ljava/lang/Object;
      44: pop
      45: iconst_1
      46: ireturn
      47: iconst_0
      48: ireturn

  protected void reportMetadata(org.apache.dubbo.metadata.MetadataInfo);
    Code:
       0: aload_1
       1: ifnonnull     5
       4: return
       5: aload_0
       6: getfield      #16                 // Field metadataReport:Lorg/apache/dubbo/metadata/report/MetadataReport;
       9: ifnull        83
      12: new           #124                // class org/apache/dubbo/metadata/report/identifier/SubscriberMetadataIdentifier
      15: dup
      16: aload_0
      17: getfield      #29                 // Field serviceName:Ljava/lang/String;
      20: aload_1
      21: invokevirtual #66                 // Method org/apache/dubbo/metadata/MetadataInfo.getRevision:()Ljava/lang/String;
      24: invokespecial #125                // Method org/apache/dubbo/metadata/report/identifier/SubscriberMetadataIdentifier."<init>":(Ljava/lang/String;Ljava/lang/String;)V
      27: astore_2
      28: ldc           #126                // String local
      30: aload_0
      31: getfield      #12                 // Field metadataType:Ljava/lang/String;
      34: invokevirtual #114                // Method java/lang/String.equals:(Ljava/lang/Object;)Z
      37: ifeq          52
      40: aload_0
      41: getfield      #16                 // Field metadataReport:Lorg/apache/dubbo/metadata/report/MetadataReport;
      44: invokeinterface #127,  1          // InterfaceMethod org/apache/dubbo/metadata/report/MetadataReport.shouldReportMetadata:()Z
      49: ifne          64
      52: ldc           #128                // String remote
      54: aload_0
      55: getfield      #12                 // Field metadataType:Ljava/lang/String;
      58: invokevirtual #114                // Method java/lang/String.equals:(Ljava/lang/Object;)Z
      61: ifeq          83
      64: aload_0
      65: getfield      #28                 // Field applicationModel:Lorg/apache/dubbo/rpc/model/ApplicationModel;
      68: invokestatic  #129                // Method org/apache/dubbo/metrics/metadata/event/MetadataEvent.toPushEvent:(Lorg/apache/dubbo/rpc/model/ApplicationModel;)Lorg/apache/dubbo/metrics/metadata/event/MetadataEvent;
      71: aload_0
      72: aload_2
      73: aload_1
      74: invokedynamic #130,  0            // InvokeDynamic #3:get:(Lorg/apache/dubbo/registry/client/AbstractServiceDiscovery;Lorg/apache/dubbo/metadata/report/identifier/SubscriberMetadataIdentifier;Lorg/apache/dubbo/metadata/MetadataInfo;)Ljava/util/function/Supplier;
      79: invokestatic  #131                // Method org/apache/dubbo/metrics/event/MetricsEventBus.post:(Lorg/apache/dubbo/metrics/event/MetricsEvent;Ljava/util/function/Supplier;)Ljava/lang/Object;
      82: pop
      83: aload_1
      84: invokevirtual #132                // Method org/apache/dubbo/metadata/MetadataInfo.clone:()Lorg/apache/dubbo/metadata/MetadataInfo;
      87: astore_2
      88: aload_0
      89: getfield      #24                 // Field metadataInfos:Ljava/util/concurrent/ConcurrentHashMap;
      92: aload_1
      93: invokevirtual #66                 // Method org/apache/dubbo/metadata/MetadataInfo.getRevision:()Ljava/lang/String;
      96: new           #72                 // class org/apache/dubbo/registry/client/AbstractServiceDiscovery$MetadataInfoStat
      99: dup
     100: aload_2
     101: invokespecial #133                // Method org/apache/dubbo/registry/client/AbstractServiceDiscovery$MetadataInfoStat."<init>":(Lorg/apache/dubbo/metadata/MetadataInfo;)V
     104: invokevirtual #134                // Method java/util/concurrent/ConcurrentHashMap.put:(Ljava/lang/Object;Ljava/lang/Object;)Ljava/lang/Object;
     107: pop
     108: return

  protected void unReportMetadata(org.apache.dubbo.metadata.MetadataInfo);
    Code:
       0: aload_0
       1: getfield      #16                 // Field metadataReport:Lorg/apache/dubbo/metadata/report/MetadataReport;
       4: ifnull        70
       7: new           #124                // class org/apache/dubbo/metadata/report/identifier/SubscriberMetadataIdentifier
      10: dup
      11: aload_0
      12: getfield      #29                 // Field serviceName:Ljava/lang/String;
      15: aload_1
      16: invokevirtual #66                 // Method org/apache/dubbo/metadata/MetadataInfo.getRevision:()Ljava/lang/String;
      19: invokespecial #125                // Method org/apache/dubbo/metadata/report/identifier/SubscriberMetadataIdentifier."<init>":(Ljava/lang/String;Ljava/lang/String;)V
      22: astore_2
      23: ldc           #126                // String local
      25: aload_0
      26: getfield      #12                 // Field metadataType:Ljava/lang/String;
      29: invokevirtual #114                // Method java/lang/String.equals:(Ljava/lang/Object;)Z
      32: ifeq          47
      35: aload_0
      36: getfield      #16                 // Field metadataReport:Lorg/apache/dubbo/metadata/report/MetadataReport;
      39: invokeinterface #127,  1          // InterfaceMethod org/apache/dubbo/metadata/report/MetadataReport.shouldReportMetadata:()Z
      44: ifne          59
      47: ldc           #128                // String remote
      49: aload_0
      50: getfield      #12                 // Field metadataType:Ljava/lang/String;
      53: invokevirtual #114                // Method java/lang/String.equals:(Ljava/lang/Object;)Z
      56: ifeq          70
      59: aload_0
      60: getfield      #16                 // Field metadataReport:Lorg/apache/dubbo/metadata/report/MetadataReport;
      63: aload_2
      64: aload_1
      65: invokeinterface #135,  3          // InterfaceMethod org/apache/dubbo/metadata/report/MetadataReport.unPublishAppMetadata:(Lorg/apache/dubbo/metadata/report/identifier/SubscriberMetadataIdentifier;Lorg/apache/dubbo/metadata/MetadataInfo;)V
      70: return

  private java.lang.String getCacheNameSuffix();
    Code:
       0: aload_0
       1: invokevirtual #136                // Method java/lang/Object.getClass:()Ljava/lang/Class;
       4: invokevirtual #137                // Method java/lang/Class.getSimpleName:()Ljava/lang/String;
       7: astore_1
       8: aload_1
       9: ldc           #138                // class org/apache/dubbo/registry/client/ServiceDiscovery
      11: invokevirtual #137                // Method java/lang/Class.getSimpleName:()Ljava/lang/String;
      14: invokevirtual #139                // Method java/lang/String.indexOf:(Ljava/lang/String;)I
      17: istore_2
      18: iload_2
      19: iconst_m1
      20: if_icmpeq     30
      23: aload_1
      24: iconst_0
      25: iload_2
      26: invokevirtual #140                // Method java/lang/String.substring:(II)Ljava/lang/String;
      29: astore_1
      30: new           #78                 // class java/lang/StringBuilder
      33: dup
      34: sipush        128
      37: invokespecial #141                // Method java/lang/StringBuilder."<init>":(I)V
      40: astore_3
      41: aload_0
      42: getfield      #28                 // Field applicationModel:Lorg/apache/dubbo/rpc/model/ApplicationModel;
      45: invokevirtual #142                // Method org/apache/dubbo/rpc/model/ApplicationModel.getApplicationConfigManager:()Lorg/apache/dubbo/config/context/ConfigManager;
      48: invokevirtual #143                // Method org/apache/dubbo/config/context/ConfigManager.getApplication:()Ljava/util/Optional;
      51: astore        4
      53: aload         4
      55: invokevirtual #144                // Method java/util/Optional.isPresent:()Z
      58: ifeq          84
      61: aload_3
      62: aload         4
      64: invokevirtual #145                // Method java/util/Optional.get:()Ljava/lang/Object;
      67: checkcast     #146                // class org/apache/dubbo/config/ApplicationConfig
      70: invokevirtual #147                // Method org/apache/dubbo/config/ApplicationConfig.getName:()Ljava/lang/String;
      73: invokevirtual #81                 // Method java/lang/StringBuilder.append:(Ljava/lang/String;)Ljava/lang/StringBuilder;
      76: pop
      77: aload_3
      78: ldc           #148                // String .
      80: invokevirtual #81                 // Method java/lang/StringBuilder.append:(Ljava/lang/String;)Ljava/lang/StringBuilder;
      83: pop
      84: aload_3
      85: aload_1
      86: invokevirtual #149                // Method java/lang/String.toLowerCase:()Ljava/lang/String;
      89: invokevirtual #81                 // Method java/lang/StringBuilder.append:(Ljava/lang/String;)Ljava/lang/StringBuilder;
      92: pop
      93: aload_0
      94: invokevirtual #150                // Method getUrl:()Lorg/apache/dubbo/common/URL;
      97: astore        5
      99: aload         5
     101: ifnull        121
     104: aload_3
     105: ldc           #148                // String .
     107: invokevirtual #81                 // Method java/lang/StringBuilder.append:(Ljava/lang/String;)Ljava/lang/StringBuilder;
     110: pop
     111: aload_3
     112: aload         5
     114: invokevirtual #151                // Method org/apache/dubbo/common/URL.getBackupAddress:()Ljava/lang/String;
     117: invokevirtual #81                 // Method java/lang/StringBuilder.append:(Ljava/lang/String;)Ljava/lang/StringBuilder;
     120: pop
     121: aload_3
     122: invokevirtual #84                 // Method java/lang/StringBuilder.toString:()Ljava/lang/String;
     125: areturn

  private java.lang.Object lambda$reportMetadata$4(org.apache.dubbo.metadata.report.identifier.SubscriberMetadataIdentifier, org.apache.dubbo.metadata.MetadataInfo);
    Code:
       0: aload_0
       1: getfield      #16                 // Field metadataReport:Lorg/apache/dubbo/metadata/report/MetadataReport;
       4: aload_1
       5: aload_2
       6: invokeinterface #152,  3          // InterfaceMethod org/apache/dubbo/metadata/report/MetadataReport.publishAppMetadata:(Lorg/apache/dubbo/metadata/report/identifier/SubscriberMetadataIdentifier;Lorg/apache/dubbo/metadata/MetadataInfo;)V
      11: aconst_null
      12: areturn

  private static java.lang.Boolean lambda$getRemoteMetadata$3(org.apache.dubbo.metadata.MetadataInfo);
    Code:
       0: aload_0
       1: getstatic     #75                 // Field org/apache/dubbo/metadata/MetadataInfo.EMPTY:Lorg/apache/dubbo/metadata/MetadataInfo;
       4: if_acmpeq     11
       7: iconst_1
       8: goto          12
      11: iconst_0
      12: invokestatic  #153                // Method java/lang/Boolean.valueOf:(Z)Ljava/lang/Boolean;
      15: areturn

  private org.apache.dubbo.metadata.MetadataInfo lambda$getRemoteMetadata$2(java.lang.String, java.util.List);
    Code:
       0: aload_1
       1: aload_2
       2: aload_0
       3: getfield      #16                 // Field metadataReport:Lorg/apache/dubbo/metadata/report/MetadataReport;
       6: invokestatic  #154                // Method org/apache/dubbo/registry/client/metadata/MetadataUtils.getRemoteMetadata:(Ljava/lang/String;Ljava/util/List;Lorg/apache/dubbo/metadata/report/MetadataReport;)Lorg/apache/dubbo/metadata/MetadataInfo;
       9: areturn

  private void lambda$new$1(int, int);
    Code:
       0: aload_0
       1: getfield      #24                 // Field metadataInfos:Ljava/util/concurrent/ConcurrentHashMap;
       4: invokevirtual #155                // Method java/util/concurrent/ConcurrentHashMap.size:()I
       7: iload_1
       8: if_icmple     72
      11: new           #156                // class java/util/concurrent/atomic/AtomicReference
      14: dup
      15: invokespecial #157                // Method java/util/concurrent/atomic/AtomicReference."<init>":()V
      18: astore_3
      19: new           #156                // class java/util/concurrent/atomic/AtomicReference
      22: dup
      23: invokespecial #157                // Method java/util/concurrent/atomic/AtomicReference."<init>":()V
      26: astore        4
      28: aload_0
      29: getfield      #24                 // Field metadataInfos:Ljava/util/concurrent/ConcurrentHashMap;
      32: iload_2
      33: aload         4
      35: aload_3
      36: invokedynamic #158,  0            // InvokeDynamic #4:accept:(ILjava/util/concurrent/atomic/AtomicReference;Ljava/util/concurrent/atomic/AtomicReference;)Ljava/util/function/BiConsumer;
      41: invokevirtual #159                // Method java/util/concurrent/ConcurrentHashMap.forEach:(Ljava/util/function/BiConsumer;)V
      44: aload         4
      46: invokevirtual #160                // Method java/util/concurrent/atomic/AtomicReference.get:()Ljava/lang/Object;
      49: ifnull        69
      52: aload_0
      53: getfield      #24                 // Field metadataInfos:Ljava/util/concurrent/ConcurrentHashMap;
      56: aload_3
      57: invokevirtual #160                // Method java/util/concurrent/atomic/AtomicReference.get:()Ljava/lang/Object;
      60: aload         4
      62: invokevirtual #160                // Method java/util/concurrent/atomic/AtomicReference.get:()Ljava/lang/Object;
      65: invokevirtual #161                // Method java/util/concurrent/ConcurrentHashMap.remove:(Ljava/lang/Object;Ljava/lang/Object;)Z
      68: pop
      69: goto          0
      72: goto          94
      75: astore_3
      76: aload_0
      77: getfield      #21                 // Field logger:Lorg/apache/dubbo/common/logger/ErrorTypeAwareLogger;
      80: ldc           #163                // String 99-0
      82: ldc           #98                 // String
      84: ldc           #98                 // String
      86: ldc           #164                // String Error occurred when clean up metadata info cache.
      88: aload_3
      89: invokeinterface #165,  6          // InterfaceMethod org/apache/dubbo/common/logger/ErrorTypeAwareLogger.error:(Ljava/lang/String;Ljava/lang/String;Ljava/lang/String;Ljava/lang/String;Ljava/lang/Throwable;)V
      94: return
    Exception table:
       from    to  target type
           0    72    75   Class java/lang/Throwable

  private static void lambda$null$0(int, java.util.concurrent.atomic.AtomicReference, java.util.concurrent.atomic.AtomicReference, java.lang.String, org.apache.dubbo.registry.client.AbstractServiceDiscovery$MetadataInfoStat);
    Code:
       0: invokestatic  #166                // Method java/lang/System.currentTimeMillis:()J
       3: aload         4
       5: invokevirtual #167                // Method org/apache/dubbo/registry/client/AbstractServiceDiscovery$MetadataInfoStat.getUpdateTime:()J
       8: lsub
       9: iload_0
      10: i2l
      11: lcmp
      12: ifle          52
      15: aload_1
      16: invokevirtual #160                // Method java/util/concurrent/atomic/AtomicReference.get:()Ljava/lang/Object;
      19: ifnull        41
      22: aload_1
      23: invokevirtual #160                // Method java/util/concurrent/atomic/AtomicReference.get:()Ljava/lang/Object;
      26: checkcast     #72                 // class org/apache/dubbo/registry/client/AbstractServiceDiscovery$MetadataInfoStat
      29: invokevirtual #167                // Method org/apache/dubbo/registry/client/AbstractServiceDiscovery$MetadataInfoStat.getUpdateTime:()J
      32: aload         4
      34: invokevirtual #167                // Method org/apache/dubbo/registry/client/AbstractServiceDiscovery$MetadataInfoStat.getUpdateTime:()J
      37: lcmp
      38: ifle          52
      41: aload_2
      42: aload_3
      43: invokevirtual #168                // Method java/util/concurrent/atomic/AtomicReference.set:(Ljava/lang/Object;)V
      46: aload_1
      47: aload         4
      49: invokevirtual #168                // Method java/util/concurrent/atomic/AtomicReference.set:(Ljava/lang/Object;)V
      52: return
}
