Compiled from "DefaultServiceInstance.java"
public class org.apache.dubbo.registry.client.DefaultServiceInstance$Endpoint {
  int port;

  java.lang.String protocol;

  public org.apache.dubbo.registry.client.DefaultServiceInstance$Endpoint();
    Code:
       0: aload_0
       1: invokespecial #1                  // Method java/lang/Object."<init>":()V
       4: return

  public org.apache.dubbo.registry.client.DefaultServiceInstance$Endpoint(int, java.lang.String);
    Code:
       0: aload_0
       1: invokespecial #1                  // Method java/lang/Object."<init>":()V
       4: aload_0
       5: iload_1
       6: putfield      #2                  // Field port:I
       9: aload_0
      10: aload_2
      11: putfield      #3                  // Field protocol:Ljava/lang/String;
      14: return

  public int getPort();
    Code:
       0: aload_0
       1: getfield      #2                  // Field port:I
       4: ireturn

  public void setPort(int);
    Code:
       0: aload_0
       1: iload_1
       2: putfield      #2                  // Field port:I
       5: return

  public java.lang.String getProtocol();
    Code:
       0: aload_0
       1: getfield      #3                  // Field protocol:Ljava/lang/String;
       4: areturn

  public void setProtocol(java.lang.String);
    Code:
       0: aload_0
       1: aload_1
       2: putfield      #3                  // Field protocol:Ljava/lang/String;
       5: return
}
