Compiled from "DefaultRegistryClusterIdentifier.java"
public class org.apache.dubbo.registry.client.DefaultRegistryClusterIdentifier implements org.apache.dubbo.registry.client.RegistryClusterIdentifier {
  public org.apache.dubbo.registry.client.DefaultRegistryClusterIdentifier();
    Code:
       0: aload_0
       1: invokespecial #2                  // Method java/lang/Object."<init>":()V
       4: return

  public java.lang.String providerKey(org.apache.dubbo.common.URL);
    Code:
       0: aload_1
       1: ldc           #3                  // String REGISTRY_CLUSTER
       3: invokevirtual #4                  // Method org/apache/dubbo/common/URL.getParameter:(Ljava/lang/String;)Ljava/lang/String;
       6: areturn

  public java.lang.String consumerKey(org.apache.dubbo.common.URL);
    Code:
       0: aload_1
       1: ldc           #3                  // String REGISTRY_CLUSTER
       3: invokevirtual #4                  // Method org/apache/dubbo/common/URL.getParameter:(Ljava/lang/String;)Ljava/lang/String;
       6: areturn
}
