Compiled from "DefaultServiceDiscoveryFactory.java"
public class org.apache.dubbo.registry.client.DefaultServiceDiscoveryFactory extends org.apache.dubbo.registry.client.AbstractServiceDiscoveryFactory {
  public org.apache.dubbo.registry.client.DefaultServiceDiscoveryFactory();
    Code:
       0: aload_0
       1: invokespecial #1                  // Method org/apache/dubbo/registry/client/AbstractServiceDiscoveryFactory."<init>":()V
       4: return

  protected org.apache.dubbo.registry.client.ServiceDiscovery createDiscovery(org.apache.dubbo.common.URL);
    Code:
       0: new           #2                  // class org/apache/dubbo/registry/client/NopServiceDiscovery
       3: dup
       4: aload_1
       5: invokevirtual #3                  // Method org/apache/dubbo/common/URL.getApplicationModel:()Lorg/apache/dubbo/rpc/model/ApplicationModel;
       8: aload_1
       9: invokespecial #4                  // Method org/apache/dubbo/registry/client/NopServiceDiscovery."<init>":(Lorg/apache/dubbo/rpc/model/ApplicationModel;Lorg/apache/dubbo/common/URL;)V
      12: areturn
}
