Compiled from "InstanceAddressURL.java"
public class org.apache.dubbo.registry.client.InstanceAddressURL extends org.apache.dubbo.common.URL {
  private final org.apache.dubbo.registry.client.ServiceInstance instance;

  private final org.apache.dubbo.metadata.MetadataInfo metadataInfo;

  private volatile transient java.util.Set<java.lang.String> providerFirstParams;

  private final transient java.lang.String protocol;

  protected org.apache.dubbo.registry.client.InstanceAddressURL();
    Code:
       0: aload_0
       1: aconst_null
       2: aconst_null
       3: aconst_null
       4: invokespecial #2                  // Method "<init>":(Lorg/apache/dubbo/registry/client/ServiceInstance;Lorg/apache/dubbo/metadata/MetadataInfo;Ljava/lang/String;)V
       7: return

  public org.apache.dubbo.registry.client.InstanceAddressURL(org.apache.dubbo.registry.client.ServiceInstance, org.apache.dubbo.metadata.MetadataInfo);
    Code:
       0: aload_0
       1: invokespecial #3                  // Method org/apache/dubbo/common/URL."<init>":()V
       4: aload_0
       5: aload_1
       6: putfield      #4                  // Field instance:Lorg/apache/dubbo/registry/client/ServiceInstance;
       9: aload_0
      10: aload_2
      11: putfield      #5                  // Field metadataInfo:Lorg/apache/dubbo/metadata/MetadataInfo;
      14: aload_0
      15: ldc           #6                  // String dubbo
      17: putfield      #7                  // Field protocol:Ljava/lang/String;
      20: return

  public org.apache.dubbo.registry.client.InstanceAddressURL(org.apache.dubbo.registry.client.ServiceInstance, org.apache.dubbo.metadata.MetadataInfo, java.lang.String);
    Code:
       0: aload_0
       1: invokespecial #3                  // Method org/apache/dubbo/common/URL."<init>":()V
       4: aload_0
       5: aload_1
       6: putfield      #4                  // Field instance:Lorg/apache/dubbo/registry/client/ServiceInstance;
       9: aload_0
      10: aload_2
      11: putfield      #5                  // Field metadataInfo:Lorg/apache/dubbo/metadata/MetadataInfo;
      14: aload_0
      15: aload_3
      16: putfield      #7                  // Field protocol:Ljava/lang/String;
      19: return

  public org.apache.dubbo.registry.client.ServiceInstance getInstance();
    Code:
       0: aload_0
       1: getfield      #4                  // Field instance:Lorg/apache/dubbo/registry/client/ServiceInstance;
       4: areturn

  public org.apache.dubbo.metadata.MetadataInfo getMetadataInfo();
    Code:
       0: aload_0
       1: getfield      #5                  // Field metadataInfo:Lorg/apache/dubbo/metadata/MetadataInfo;
       4: areturn

  public java.lang.String getServiceInterface();
    Code:
       0: invokestatic  #8                  // Method org/apache/dubbo/rpc/RpcContext.getServiceContext:()Lorg/apache/dubbo/rpc/RpcServiceContext;
       3: invokevirtual #9                  // Method org/apache/dubbo/rpc/RpcServiceContext.getInterfaceName:()Ljava/lang/String;
       6: areturn

  public java.lang.String getGroup();
    Code:
       0: invokestatic  #8                  // Method org/apache/dubbo/rpc/RpcContext.getServiceContext:()Lorg/apache/dubbo/rpc/RpcServiceContext;
       3: invokevirtual #10                 // Method org/apache/dubbo/rpc/RpcServiceContext.getGroup:()Ljava/lang/String;
       6: areturn

  public java.lang.String getVersion();
    Code:
       0: invokestatic  #8                  // Method org/apache/dubbo/rpc/RpcContext.getServiceContext:()Lorg/apache/dubbo/rpc/RpcServiceContext;
       3: invokevirtual #11                 // Method org/apache/dubbo/rpc/RpcServiceContext.getVersion:()Ljava/lang/String;
       6: areturn

  public java.lang.String getProtocol();
    Code:
       0: aload_0
       1: getfield      #7                  // Field protocol:Ljava/lang/String;
       4: areturn

  public java.lang.String getProtocolServiceKey();
    Code:
       0: invokestatic  #8                  // Method org/apache/dubbo/rpc/RpcContext.getServiceContext:()Lorg/apache/dubbo/rpc/RpcServiceContext;
       3: invokevirtual #12                 // Method org/apache/dubbo/rpc/RpcServiceContext.getConsumerUrl:()Lorg/apache/dubbo/common/URL;
       6: astore_1
       7: aload_1
       8: ifnonnull     15
      11: aconst_null
      12: goto          19
      15: aload_1
      16: invokevirtual #13                 // Method org/apache/dubbo/common/URL.getProtocol:()Ljava/lang/String;
      19: astore_2
      20: aload_2
      21: ldc           #14                 // String consumer
      23: invokestatic  #15                 // Method org/apache/dubbo/common/utils/StringUtils.isEquals:(Ljava/lang/String;Ljava/lang/String;)Z
      26: ifeq          36
      29: invokestatic  #8                  // Method org/apache/dubbo/rpc/RpcContext.getServiceContext:()Lorg/apache/dubbo/rpc/RpcServiceContext;
      32: invokevirtual #16                 // Method org/apache/dubbo/rpc/RpcServiceContext.getServiceKey:()Ljava/lang/String;
      35: areturn
      36: invokestatic  #8                  // Method org/apache/dubbo/rpc/RpcContext.getServiceContext:()Lorg/apache/dubbo/rpc/RpcServiceContext;
      39: invokevirtual #17                 // Method org/apache/dubbo/rpc/RpcServiceContext.getProtocolServiceKey:()Ljava/lang/String;
      42: areturn

  public java.lang.String getServiceKey();
    Code:
       0: invokestatic  #8                  // Method org/apache/dubbo/rpc/RpcContext.getServiceContext:()Lorg/apache/dubbo/rpc/RpcServiceContext;
       3: invokevirtual #16                 // Method org/apache/dubbo/rpc/RpcServiceContext.getServiceKey:()Ljava/lang/String;
       6: areturn

  public org.apache.dubbo.common.URL setProtocol(java.lang.String);
    Code:
       0: new           #18                 // class org/apache/dubbo/common/url/component/ServiceConfigURL
       3: dup
       4: aload_1
       5: aload_0
       6: invokevirtual #19                 // Method getUsername:()Ljava/lang/String;
       9: aload_0
      10: invokevirtual #20                 // Method getPassword:()Ljava/lang/String;
      13: aload_0
      14: invokevirtual #21                 // Method getHost:()Ljava/lang/String;
      17: aload_0
      18: invokevirtual #22                 // Method getPort:()I
      21: aload_0
      22: invokevirtual #23                 // Method getPath:()Ljava/lang/String;
      25: aload_0
      26: invokevirtual #24                 // Method getParameters:()Ljava/util/Map;
      29: aload_0
      30: getfield      #25                 // Field attributes:Ljava/util/Map;
      33: invokespecial #26                 // Method org/apache/dubbo/common/url/component/ServiceConfigURL."<init>":(Ljava/lang/String;Ljava/lang/String;Ljava/lang/String;Ljava/lang/String;ILjava/lang/String;Ljava/util/Map;Ljava/util/Map;)V
      36: areturn

  public org.apache.dubbo.common.URL setHost(java.lang.String);
    Code:
       0: new           #18                 // class org/apache/dubbo/common/url/component/ServiceConfigURL
       3: dup
       4: aload_0
       5: invokevirtual #27                 // Method getProtocol:()Ljava/lang/String;
       8: aload_0
       9: invokevirtual #19                 // Method getUsername:()Ljava/lang/String;
      12: aload_0
      13: invokevirtual #20                 // Method getPassword:()Ljava/lang/String;
      16: aload_1
      17: aload_0
      18: invokevirtual #22                 // Method getPort:()I
      21: aload_0
      22: invokevirtual #23                 // Method getPath:()Ljava/lang/String;
      25: aload_0
      26: invokevirtual #24                 // Method getParameters:()Ljava/util/Map;
      29: aload_0
      30: getfield      #25                 // Field attributes:Ljava/util/Map;
      33: invokespecial #26                 // Method org/apache/dubbo/common/url/component/ServiceConfigURL."<init>":(Ljava/lang/String;Ljava/lang/String;Ljava/lang/String;Ljava/lang/String;ILjava/lang/String;Ljava/util/Map;Ljava/util/Map;)V
      36: areturn

  public org.apache.dubbo.common.URL setPort(int);
    Code:
       0: new           #18                 // class org/apache/dubbo/common/url/component/ServiceConfigURL
       3: dup
       4: aload_0
       5: invokevirtual #27                 // Method getProtocol:()Ljava/lang/String;
       8: aload_0
       9: invokevirtual #19                 // Method getUsername:()Ljava/lang/String;
      12: aload_0
      13: invokevirtual #20                 // Method getPassword:()Ljava/lang/String;
      16: aload_0
      17: invokevirtual #21                 // Method getHost:()Ljava/lang/String;
      20: iload_1
      21: aload_0
      22: invokevirtual #23                 // Method getPath:()Ljava/lang/String;
      25: aload_0
      26: invokevirtual #24                 // Method getParameters:()Ljava/util/Map;
      29: aload_0
      30: getfield      #25                 // Field attributes:Ljava/util/Map;
      33: invokespecial #26                 // Method org/apache/dubbo/common/url/component/ServiceConfigURL."<init>":(Ljava/lang/String;Ljava/lang/String;Ljava/lang/String;Ljava/lang/String;ILjava/lang/String;Ljava/util/Map;Ljava/util/Map;)V
      36: areturn

  public org.apache.dubbo.common.URL setPath(java.lang.String);
    Code:
       0: new           #18                 // class org/apache/dubbo/common/url/component/ServiceConfigURL
       3: dup
       4: aload_0
       5: invokevirtual #27                 // Method getProtocol:()Ljava/lang/String;
       8: aload_0
       9: invokevirtual #19                 // Method getUsername:()Ljava/lang/String;
      12: aload_0
      13: invokevirtual #20                 // Method getPassword:()Ljava/lang/String;
      16: aload_0
      17: invokevirtual #21                 // Method getHost:()Ljava/lang/String;
      20: aload_0
      21: invokevirtual #22                 // Method getPort:()I
      24: aload_1
      25: aload_0
      26: invokevirtual #24                 // Method getParameters:()Ljava/util/Map;
      29: aload_0
      30: getfield      #25                 // Field attributes:Ljava/util/Map;
      33: invokespecial #26                 // Method org/apache/dubbo/common/url/component/ServiceConfigURL."<init>":(Ljava/lang/String;Ljava/lang/String;Ljava/lang/String;Ljava/lang/String;ILjava/lang/String;Ljava/util/Map;Ljava/util/Map;)V
      36: areturn

  public java.lang.String getAddress();
    Code:
       0: aload_0
       1: getfield      #4                  // Field instance:Lorg/apache/dubbo/registry/client/ServiceInstance;
       4: invokeinterface #28,  1           // InterfaceMethod org/apache/dubbo/registry/client/ServiceInstance.getAddress:()Ljava/lang/String;
       9: areturn

  public java.lang.String getHost();
    Code:
       0: aload_0
       1: getfield      #4                  // Field instance:Lorg/apache/dubbo/registry/client/ServiceInstance;
       4: invokeinterface #29,  1           // InterfaceMethod org/apache/dubbo/registry/client/ServiceInstance.getHost:()Ljava/lang/String;
       9: areturn

  public int getPort();
    Code:
       0: aload_0
       1: getfield      #4                  // Field instance:Lorg/apache/dubbo/registry/client/ServiceInstance;
       4: invokeinterface #30,  1           // InterfaceMethod org/apache/dubbo/registry/client/ServiceInstance.getPort:()I
       9: ireturn

  public java.lang.String getIp();
    Code:
       0: aload_0
       1: getfield      #4                  // Field instance:Lorg/apache/dubbo/registry/client/ServiceInstance;
       4: invokeinterface #29,  1           // InterfaceMethod org/apache/dubbo/registry/client/ServiceInstance.getHost:()Ljava/lang/String;
       9: areturn

  public java.lang.String getRemoteApplication();
    Code:
       0: aload_0
       1: getfield      #4                  // Field instance:Lorg/apache/dubbo/registry/client/ServiceInstance;
       4: invokeinterface #31,  1           // InterfaceMethod org/apache/dubbo/registry/client/ServiceInstance.getServiceName:()Ljava/lang/String;
       9: areturn

  public java.lang.String getSide();
    Code:
       0: ldc           #14                 // String consumer
       2: areturn

  public java.lang.String getPath();
    Code:
       0: aconst_null
       1: astore_1
       2: aload_0
       3: invokevirtual #32                 // Method getProtocolServiceKey:()Ljava/lang/String;
       6: astore_2
       7: aload_2
       8: invokestatic  #33                 // Method org/apache/dubbo/common/utils/StringUtils.isNotEmpty:(Ljava/lang/String;)Z
      11: ifeq          20
      14: aload_0
      15: aload_2
      16: invokespecial #34                 // Method getServiceInfo:(Ljava/lang/String;)Lorg/apache/dubbo/metadata/MetadataInfo$ServiceInfo;
      19: astore_1
      20: aload_1
      21: ifnonnull     29
      24: aload_0
      25: invokevirtual #35                 // Method getServiceInterface:()Ljava/lang/String;
      28: areturn
      29: aload_1
      30: invokevirtual #36                 // Method org/apache/dubbo/metadata/MetadataInfo$ServiceInfo.getPath:()Ljava/lang/String;
      33: areturn

  public java.lang.String getOriginalParameter(java.lang.String);
    Code:
       0: ldc           #37                 // String version
       2: aload_1
       3: invokevirtual #38                 // Method java/lang/String.equals:(Ljava/lang/Object;)Z
       6: ifeq          14
       9: aload_0
      10: invokevirtual #39                 // Method getVersion:()Ljava/lang/String;
      13: areturn
      14: ldc           #40                 // String group
      16: aload_1
      17: invokevirtual #38                 // Method java/lang/String.equals:(Ljava/lang/Object;)Z
      20: ifeq          28
      23: aload_0
      24: invokevirtual #41                 // Method getGroup:()Ljava/lang/String;
      27: areturn
      28: ldc           #42                 // String interface
      30: aload_1
      31: invokevirtual #38                 // Method java/lang/String.equals:(Ljava/lang/Object;)Z
      34: ifeq          42
      37: aload_0
      38: invokevirtual #35                 // Method getServiceInterface:()Ljava/lang/String;
      41: areturn
      42: ldc           #43                 // String remote.application
      44: aload_1
      45: invokevirtual #38                 // Method java/lang/String.equals:(Ljava/lang/Object;)Z
      48: ifeq          61
      51: aload_0
      52: getfield      #4                  // Field instance:Lorg/apache/dubbo/registry/client/ServiceInstance;
      55: invokeinterface #31,  1           // InterfaceMethod org/apache/dubbo/registry/client/ServiceInstance.getServiceName:()Ljava/lang/String;
      60: areturn
      61: ldc           #44                 // String side
      63: aload_1
      64: invokevirtual #38                 // Method java/lang/String.equals:(Ljava/lang/Object;)Z
      67: ifeq          75
      70: aload_0
      71: invokevirtual #45                 // Method getSide:()Ljava/lang/String;
      74: areturn
      75: aload_0
      76: invokevirtual #32                 // Method getProtocolServiceKey:()Ljava/lang/String;
      79: astore_2
      80: aload_2
      81: invokestatic  #46                 // Method org/apache/dubbo/common/utils/StringUtils.isEmpty:(Ljava/lang/String;)Z
      84: ifeq          93
      87: aload_0
      88: aload_1
      89: invokespecial #47                 // Method getInstanceParameter:(Ljava/lang/String;)Ljava/lang/String;
      92: areturn
      93: aload_0
      94: aload_2
      95: aload_1
      96: invokevirtual #48                 // Method getServiceParameter:(Ljava/lang/String;Ljava/lang/String;)Ljava/lang/String;
      99: areturn

  public java.lang.String getParameter(java.lang.String);
    Code:
       0: ldc           #37                 // String version
       2: aload_1
       3: invokevirtual #38                 // Method java/lang/String.equals:(Ljava/lang/Object;)Z
       6: ifeq          14
       9: aload_0
      10: invokevirtual #39                 // Method getVersion:()Ljava/lang/String;
      13: areturn
      14: ldc           #40                 // String group
      16: aload_1
      17: invokevirtual #38                 // Method java/lang/String.equals:(Ljava/lang/Object;)Z
      20: ifeq          28
      23: aload_0
      24: invokevirtual #41                 // Method getGroup:()Ljava/lang/String;
      27: areturn
      28: ldc           #42                 // String interface
      30: aload_1
      31: invokevirtual #38                 // Method java/lang/String.equals:(Ljava/lang/Object;)Z
      34: ifeq          42
      37: aload_0
      38: invokevirtual #35                 // Method getServiceInterface:()Ljava/lang/String;
      41: areturn
      42: ldc           #43                 // String remote.application
      44: aload_1
      45: invokevirtual #38                 // Method java/lang/String.equals:(Ljava/lang/Object;)Z
      48: ifeq          61
      51: aload_0
      52: getfield      #4                  // Field instance:Lorg/apache/dubbo/registry/client/ServiceInstance;
      55: invokeinterface #31,  1           // InterfaceMethod org/apache/dubbo/registry/client/ServiceInstance.getServiceName:()Ljava/lang/String;
      60: areturn
      61: ldc           #44                 // String side
      63: aload_1
      64: invokevirtual #38                 // Method java/lang/String.equals:(Ljava/lang/Object;)Z
      67: ifeq          75
      70: aload_0
      71: invokevirtual #45                 // Method getSide:()Ljava/lang/String;
      74: areturn
      75: aload_0
      76: aload_1
      77: invokespecial #49                 // Method consumerParamFirst:(Ljava/lang/String;)Z
      80: ifeq          109
      83: invokestatic  #8                  // Method org/apache/dubbo/rpc/RpcContext.getServiceContext:()Lorg/apache/dubbo/rpc/RpcServiceContext;
      86: invokevirtual #12                 // Method org/apache/dubbo/rpc/RpcServiceContext.getConsumerUrl:()Lorg/apache/dubbo/common/URL;
      89: astore_2
      90: aload_2
      91: ifnull        109
      94: aload_2
      95: aload_1
      96: invokevirtual #50                 // Method org/apache/dubbo/common/URL.getParameter:(Ljava/lang/String;)Ljava/lang/String;
      99: astore_3
     100: aload_3
     101: invokestatic  #33                 // Method org/apache/dubbo/common/utils/StringUtils.isNotEmpty:(Ljava/lang/String;)Z
     104: ifeq          109
     107: aload_3
     108: areturn
     109: aload_0
     110: invokevirtual #32                 // Method getProtocolServiceKey:()Ljava/lang/String;
     113: astore_2
     114: aload_2
     115: invokestatic  #46                 // Method org/apache/dubbo/common/utils/StringUtils.isEmpty:(Ljava/lang/String;)Z
     118: ifeq          127
     121: aload_0
     122: aload_1
     123: invokespecial #47                 // Method getInstanceParameter:(Ljava/lang/String;)Ljava/lang/String;
     126: areturn
     127: aload_0
     128: aload_2
     129: aload_1
     130: invokevirtual #48                 // Method getServiceParameter:(Ljava/lang/String;Ljava/lang/String;)Ljava/lang/String;
     133: areturn

  public java.lang.String getOriginalServiceParameter(java.lang.String, java.lang.String);
    Code:
       0: aload_0
       1: getfield      #5                  // Field metadataInfo:Lorg/apache/dubbo/metadata/MetadataInfo;
       4: ifnull        26
       7: aload_0
       8: getfield      #5                  // Field metadataInfo:Lorg/apache/dubbo/metadata/MetadataInfo;
      11: aload_2
      12: aload_1
      13: invokevirtual #51                 // Method org/apache/dubbo/metadata/MetadataInfo.getParameter:(Ljava/lang/String;Ljava/lang/String;)Ljava/lang/String;
      16: astore_3
      17: aload_3
      18: invokestatic  #33                 // Method org/apache/dubbo/common/utils/StringUtils.isNotEmpty:(Ljava/lang/String;)Z
      21: ifeq          26
      24: aload_3
      25: areturn
      26: aload_0
      27: aload_2
      28: invokespecial #47                 // Method getInstanceParameter:(Ljava/lang/String;)Ljava/lang/String;
      31: areturn

  public java.lang.String getServiceParameter(java.lang.String, java.lang.String);
    Code:
       0: aload_0
       1: aload_2
       2: invokespecial #49                 // Method consumerParamFirst:(Ljava/lang/String;)Z
       5: ifeq          38
       8: invokestatic  #8                  // Method org/apache/dubbo/rpc/RpcContext.getServiceContext:()Lorg/apache/dubbo/rpc/RpcServiceContext;
      11: invokevirtual #12                 // Method org/apache/dubbo/rpc/RpcServiceContext.getConsumerUrl:()Lorg/apache/dubbo/common/URL;
      14: astore_3
      15: aload_3
      16: ifnull        38
      19: aload_3
      20: aload_1
      21: aload_2
      22: invokevirtual #52                 // Method org/apache/dubbo/common/URL.getServiceParameter:(Ljava/lang/String;Ljava/lang/String;)Ljava/lang/String;
      25: astore        4
      27: aload         4
      29: invokestatic  #33                 // Method org/apache/dubbo/common/utils/StringUtils.isNotEmpty:(Ljava/lang/String;)Z
      32: ifeq          38
      35: aload         4
      37: areturn
      38: aload_0
      39: getfield      #5                  // Field metadataInfo:Lorg/apache/dubbo/metadata/MetadataInfo;
      42: ifnull        64
      45: aload_0
      46: getfield      #5                  // Field metadataInfo:Lorg/apache/dubbo/metadata/MetadataInfo;
      49: aload_2
      50: aload_1
      51: invokevirtual #51                 // Method org/apache/dubbo/metadata/MetadataInfo.getParameter:(Ljava/lang/String;Ljava/lang/String;)Ljava/lang/String;
      54: astore_3
      55: aload_3
      56: invokestatic  #33                 // Method org/apache/dubbo/common/utils/StringUtils.isNotEmpty:(Ljava/lang/String;)Z
      59: ifeq          64
      62: aload_3
      63: areturn
      64: aload_0
      65: aload_2
      66: invokespecial #47                 // Method getInstanceParameter:(Ljava/lang/String;)Ljava/lang/String;
      69: areturn

  public java.lang.String getServiceMethodParameter(java.lang.String, java.lang.String, java.lang.String);
    Code:
       0: aload_0
       1: aload_3
       2: invokespecial #49                 // Method consumerParamFirst:(Ljava/lang/String;)Z
       5: ifeq          42
       8: invokestatic  #8                  // Method org/apache/dubbo/rpc/RpcContext.getServiceContext:()Lorg/apache/dubbo/rpc/RpcServiceContext;
      11: invokevirtual #12                 // Method org/apache/dubbo/rpc/RpcServiceContext.getConsumerUrl:()Lorg/apache/dubbo/common/URL;
      14: astore        4
      16: aload         4
      18: ifnull        42
      21: aload         4
      23: aload_1
      24: aload_2
      25: aload_3
      26: invokevirtual #53                 // Method org/apache/dubbo/common/URL.getServiceMethodParameter:(Ljava/lang/String;Ljava/lang/String;Ljava/lang/String;)Ljava/lang/String;
      29: astore        5
      31: aload         5
      33: invokestatic  #33                 // Method org/apache/dubbo/common/utils/StringUtils.isNotEmpty:(Ljava/lang/String;)Z
      36: ifeq          42
      39: aload         5
      41: areturn
      42: aload_0
      43: aload_1
      44: invokespecial #34                 // Method getServiceInfo:(Ljava/lang/String;)Lorg/apache/dubbo/metadata/MetadataInfo$ServiceInfo;
      47: astore        4
      49: aconst_null
      50: aload         4
      52: if_acmpne     61
      55: aload_0
      56: aload_3
      57: invokevirtual #54                 // Method getParameter:(Ljava/lang/String;)Ljava/lang/String;
      60: areturn
      61: aload         4
      63: aload_2
      64: aload_3
      65: aconst_null
      66: invokevirtual #55                 // Method org/apache/dubbo/metadata/MetadataInfo$ServiceInfo.getMethodParameter:(Ljava/lang/String;Ljava/lang/String;Ljava/lang/String;)Ljava/lang/String;
      69: astore        5
      71: aload         5
      73: invokestatic  #33                 // Method org/apache/dubbo/common/utils/StringUtils.isNotEmpty:(Ljava/lang/String;)Z
      76: ifeq          82
      79: aload         5
      81: areturn
      82: aload_0
      83: aload_3
      84: invokevirtual #54                 // Method getParameter:(Ljava/lang/String;)Ljava/lang/String;
      87: areturn

  public java.lang.String getMethodParameter(java.lang.String, java.lang.String);
    Code:
       0: aload_0
       1: aload_2
       2: invokespecial #49                 // Method consumerParamFirst:(Ljava/lang/String;)Z
       5: ifeq          38
       8: invokestatic  #8                  // Method org/apache/dubbo/rpc/RpcContext.getServiceContext:()Lorg/apache/dubbo/rpc/RpcServiceContext;
      11: invokevirtual #12                 // Method org/apache/dubbo/rpc/RpcServiceContext.getConsumerUrl:()Lorg/apache/dubbo/common/URL;
      14: astore_3
      15: aload_3
      16: ifnull        38
      19: aload_3
      20: aload_1
      21: aload_2
      22: invokevirtual #56                 // Method org/apache/dubbo/common/URL.getMethodParameter:(Ljava/lang/String;Ljava/lang/String;)Ljava/lang/String;
      25: astore        4
      27: aload         4
      29: invokestatic  #33                 // Method org/apache/dubbo/common/utils/StringUtils.isNotEmpty:(Ljava/lang/String;)Z
      32: ifeq          38
      35: aload         4
      37: areturn
      38: aload_0
      39: invokevirtual #32                 // Method getProtocolServiceKey:()Ljava/lang/String;
      42: astore_3
      43: aload_3
      44: invokestatic  #46                 // Method org/apache/dubbo/common/utils/StringUtils.isEmpty:(Ljava/lang/String;)Z
      47: ifeq          52
      50: aconst_null
      51: areturn
      52: aload_0
      53: aload_3
      54: aload_1
      55: aload_2
      56: invokevirtual #57                 // Method getServiceMethodParameter:(Ljava/lang/String;Ljava/lang/String;Ljava/lang/String;)Ljava/lang/String;
      59: areturn

  public boolean hasServiceMethodParameter(java.lang.String, java.lang.String, java.lang.String);
    Code:
       0: aload_0
       1: aload_3
       2: invokespecial #49                 // Method consumerParamFirst:(Ljava/lang/String;)Z
       5: ifeq          34
       8: invokestatic  #8                  // Method org/apache/dubbo/rpc/RpcContext.getServiceContext:()Lorg/apache/dubbo/rpc/RpcServiceContext;
      11: invokevirtual #12                 // Method org/apache/dubbo/rpc/RpcServiceContext.getConsumerUrl:()Lorg/apache/dubbo/common/URL;
      14: astore        4
      16: aload         4
      18: ifnull        34
      21: aload         4
      23: aload_1
      24: aload_2
      25: aload_3
      26: invokevirtual #58                 // Method org/apache/dubbo/common/URL.hasServiceMethodParameter:(Ljava/lang/String;Ljava/lang/String;Ljava/lang/String;)Z
      29: ifeq          34
      32: iconst_1
      33: ireturn
      34: aload_0
      35: aload_1
      36: invokespecial #34                 // Method getServiceInfo:(Ljava/lang/String;)Lorg/apache/dubbo/metadata/MetadataInfo$ServiceInfo;
      39: astore        4
      41: aload_2
      42: invokestatic  #46                 // Method org/apache/dubbo/common/utils/StringUtils.isEmpty:(Ljava/lang/String;)Z
      45: ifeq          124
      48: new           #59                 // class java/lang/StringBuilder
      51: dup
      52: invokespecial #60                 // Method java/lang/StringBuilder."<init>":()V
      55: ldc           #61                 // String .
      57: invokevirtual #62                 // Method java/lang/StringBuilder.append:(Ljava/lang/String;)Ljava/lang/StringBuilder;
      60: aload_3
      61: invokevirtual #62                 // Method java/lang/StringBuilder.append:(Ljava/lang/String;)Ljava/lang/StringBuilder;
      64: invokevirtual #63                 // Method java/lang/StringBuilder.toString:()Ljava/lang/String;
      67: astore        5
      69: aload_0
      70: invokevirtual #24                 // Method getParameters:()Ljava/util/Map;
      73: invokeinterface #64,  1           // InterfaceMethod java/util/Map.keySet:()Ljava/util/Set;
      78: invokeinterface #65,  1           // InterfaceMethod java/util/Set.iterator:()Ljava/util/Iterator;
      83: astore        6
      85: aload         6
      87: invokeinterface #66,  1           // InterfaceMethod java/util/Iterator.hasNext:()Z
      92: ifeq          122
      95: aload         6
      97: invokeinterface #67,  1           // InterfaceMethod java/util/Iterator.next:()Ljava/lang/Object;
     102: checkcast     #68                 // class java/lang/String
     105: astore        7
     107: aload         7
     109: aload         5
     111: invokevirtual #69                 // Method java/lang/String.endsWith:(Ljava/lang/String;)Z
     114: ifeq          119
     117: iconst_1
     118: ireturn
     119: goto          85
     122: iconst_0
     123: ireturn
     124: aload_3
     125: invokestatic  #46                 // Method org/apache/dubbo/common/utils/StringUtils.isEmpty:(Ljava/lang/String;)Z
     128: ifeq          207
     131: new           #59                 // class java/lang/StringBuilder
     134: dup
     135: invokespecial #60                 // Method java/lang/StringBuilder."<init>":()V
     138: aload_2
     139: invokevirtual #62                 // Method java/lang/StringBuilder.append:(Ljava/lang/String;)Ljava/lang/StringBuilder;
     142: ldc           #61                 // String .
     144: invokevirtual #62                 // Method java/lang/StringBuilder.append:(Ljava/lang/String;)Ljava/lang/StringBuilder;
     147: invokevirtual #63                 // Method java/lang/StringBuilder.toString:()Ljava/lang/String;
     150: astore        5
     152: aload_0
     153: invokevirtual #24                 // Method getParameters:()Ljava/util/Map;
     156: invokeinterface #64,  1           // InterfaceMethod java/util/Map.keySet:()Ljava/util/Set;
     161: invokeinterface #65,  1           // InterfaceMethod java/util/Set.iterator:()Ljava/util/Iterator;
     166: astore        6
     168: aload         6
     170: invokeinterface #66,  1           // InterfaceMethod java/util/Iterator.hasNext:()Z
     175: ifeq          205
     178: aload         6
     180: invokeinterface #67,  1           // InterfaceMethod java/util/Iterator.next:()Ljava/lang/Object;
     185: checkcast     #68                 // class java/lang/String
     188: astore        7
     190: aload         7
     192: aload         5
     194: invokevirtual #70                 // Method java/lang/String.startsWith:(Ljava/lang/String;)Z
     197: ifeq          202
     200: iconst_1
     201: ireturn
     202: goto          168
     205: iconst_0
     206: ireturn
     207: aconst_null
     208: aload         4
     210: if_acmpne     215
     213: iconst_0
     214: ireturn
     215: aload         4
     217: aload_2
     218: aload_3
     219: invokevirtual #71                 // Method org/apache/dubbo/metadata/MetadataInfo$ServiceInfo.hasMethodParameter:(Ljava/lang/String;Ljava/lang/String;)Z
     222: ireturn

  public boolean hasMethodParameter(java.lang.String, java.lang.String);
    Code:
       0: aload_0
       1: aload_2
       2: invokespecial #49                 // Method consumerParamFirst:(Ljava/lang/String;)Z
       5: ifeq          30
       8: invokestatic  #8                  // Method org/apache/dubbo/rpc/RpcContext.getServiceContext:()Lorg/apache/dubbo/rpc/RpcServiceContext;
      11: invokevirtual #12                 // Method org/apache/dubbo/rpc/RpcServiceContext.getConsumerUrl:()Lorg/apache/dubbo/common/URL;
      14: astore_3
      15: aload_3
      16: ifnull        30
      19: aload_3
      20: aload_1
      21: aload_2
      22: invokevirtual #72                 // Method org/apache/dubbo/common/URL.hasMethodParameter:(Ljava/lang/String;Ljava/lang/String;)Z
      25: ifeq          30
      28: iconst_1
      29: ireturn
      30: aload_0
      31: invokevirtual #32                 // Method getProtocolServiceKey:()Ljava/lang/String;
      34: astore_3
      35: aload_3
      36: invokestatic  #46                 // Method org/apache/dubbo/common/utils/StringUtils.isEmpty:(Ljava/lang/String;)Z
      39: ifeq          44
      42: iconst_0
      43: ireturn
      44: aload_0
      45: aload_3
      46: aload_1
      47: aload_2
      48: invokevirtual #73                 // Method hasServiceMethodParameter:(Ljava/lang/String;Ljava/lang/String;Ljava/lang/String;)Z
      51: ireturn

  public boolean hasServiceMethodParameter(java.lang.String, java.lang.String);
    Code:
       0: invokestatic  #8                  // Method org/apache/dubbo/rpc/RpcContext.getServiceContext:()Lorg/apache/dubbo/rpc/RpcServiceContext;
       3: invokevirtual #12                 // Method org/apache/dubbo/rpc/RpcServiceContext.getConsumerUrl:()Lorg/apache/dubbo/common/URL;
       6: astore_3
       7: aload_3
       8: ifnull        22
      11: aload_3
      12: aload_1
      13: aload_2
      14: invokevirtual #74                 // Method org/apache/dubbo/common/URL.hasServiceMethodParameter:(Ljava/lang/String;Ljava/lang/String;)Z
      17: ifeq          22
      20: iconst_1
      21: ireturn
      22: aload_0
      23: aload_1
      24: invokespecial #34                 // Method getServiceInfo:(Ljava/lang/String;)Lorg/apache/dubbo/metadata/MetadataInfo$ServiceInfo;
      27: astore        4
      29: aconst_null
      30: aload         4
      32: if_acmpne     37
      35: iconst_0
      36: ireturn
      37: aload         4
      39: aload_2
      40: invokevirtual #75                 // Method org/apache/dubbo/metadata/MetadataInfo$ServiceInfo.hasMethodParameter:(Ljava/lang/String;)Z
      43: ireturn

  public boolean hasMethodParameter(java.lang.String);
    Code:
       0: invokestatic  #8                  // Method org/apache/dubbo/rpc/RpcContext.getServiceContext:()Lorg/apache/dubbo/rpc/RpcServiceContext;
       3: invokevirtual #12                 // Method org/apache/dubbo/rpc/RpcServiceContext.getConsumerUrl:()Lorg/apache/dubbo/common/URL;
       6: astore_2
       7: aload_2
       8: ifnull        21
      11: aload_2
      12: aload_1
      13: invokevirtual #76                 // Method org/apache/dubbo/common/URL.hasMethodParameter:(Ljava/lang/String;)Z
      16: ifeq          21
      19: iconst_1
      20: ireturn
      21: aload_0
      22: invokevirtual #32                 // Method getProtocolServiceKey:()Ljava/lang/String;
      25: astore_3
      26: aload_3
      27: invokestatic  #46                 // Method org/apache/dubbo/common/utils/StringUtils.isEmpty:(Ljava/lang/String;)Z
      30: ifeq          35
      33: iconst_0
      34: ireturn
      35: aload_0
      36: aload_3
      37: aload_1
      38: invokevirtual #77                 // Method hasServiceMethodParameter:(Ljava/lang/String;Ljava/lang/String;)Z
      41: ireturn

  public java.util.Map<java.lang.String, java.lang.String> getOriginalServiceParameters(java.lang.String);
    Code:
       0: aload_0
       1: invokevirtual #78                 // Method getInstance:()Lorg/apache/dubbo/registry/client/ServiceInstance;
       4: invokeinterface #79,  1           // InterfaceMethod org/apache/dubbo/registry/client/ServiceInstance.getAllParams:()Ljava/util/Map;
       9: astore_2
      10: aload_0
      11: getfield      #5                  // Field metadataInfo:Lorg/apache/dubbo/metadata/MetadataInfo;
      14: ifnonnull     27
      17: new           #80                 // class java/util/HashMap
      20: dup
      21: invokespecial #81                 // Method java/util/HashMap."<init>":()V
      24: goto          35
      27: aload_0
      28: getfield      #5                  // Field metadataInfo:Lorg/apache/dubbo/metadata/MetadataInfo;
      31: aload_1
      32: invokevirtual #82                 // Method org/apache/dubbo/metadata/MetadataInfo.getParameters:(Ljava/lang/String;)Ljava/util/Map;
      35: astore_3
      36: aload_2
      37: ifnonnull     44
      40: iconst_0
      41: goto          50
      44: aload_2
      45: invokeinterface #83,  1           // InterfaceMethod java/util/Map.size:()I
      50: istore        4
      52: aload_3
      53: ifnonnull     60
      56: iconst_0
      57: goto          66
      60: aload_3
      61: invokeinterface #83,  1           // InterfaceMethod java/util/Map.size:()I
      66: istore        5
      68: new           #80                 // class java/util/HashMap
      71: dup
      72: iload         4
      74: iload         5
      76: iadd
      77: i2d
      78: ldc2_w        #84                 // double 0.75d
      81: ddiv
      82: d2i
      83: iconst_1
      84: iadd
      85: invokespecial #86                 // Method java/util/HashMap."<init>":(I)V
      88: astore        6
      90: aload_2
      91: ifnull        102
      94: aload         6
      96: aload_2
      97: invokeinterface #87,  2           // InterfaceMethod java/util/Map.putAll:(Ljava/util/Map;)V
     102: aload_3
     103: ifnull        114
     106: aload         6
     108: aload_3
     109: invokeinterface #87,  2           // InterfaceMethod java/util/Map.putAll:(Ljava/util/Map;)V
     114: aload         6
     116: areturn

  public java.util.Map<java.lang.String, java.lang.String> getServiceParameters(java.lang.String);
    Code:
       0: aload_0
       1: invokevirtual #78                 // Method getInstance:()Lorg/apache/dubbo/registry/client/ServiceInstance;
       4: invokeinterface #79,  1           // InterfaceMethod org/apache/dubbo/registry/client/ServiceInstance.getAllParams:()Ljava/util/Map;
       9: astore_2
      10: aload_0
      11: getfield      #5                  // Field metadataInfo:Lorg/apache/dubbo/metadata/MetadataInfo;
      14: ifnonnull     27
      17: new           #80                 // class java/util/HashMap
      20: dup
      21: invokespecial #81                 // Method java/util/HashMap."<init>":()V
      24: goto          35
      27: aload_0
      28: getfield      #5                  // Field metadataInfo:Lorg/apache/dubbo/metadata/MetadataInfo;
      31: aload_1
      32: invokevirtual #82                 // Method org/apache/dubbo/metadata/MetadataInfo.getParameters:(Ljava/lang/String;)Ljava/util/Map;
      35: astore_3
      36: aload_2
      37: ifnonnull     44
      40: iconst_0
      41: goto          50
      44: aload_2
      45: invokeinterface #83,  1           // InterfaceMethod java/util/Map.size:()I
      50: istore        4
      52: aload_3
      53: ifnonnull     60
      56: iconst_0
      57: goto          66
      60: aload_3
      61: invokeinterface #83,  1           // InterfaceMethod java/util/Map.size:()I
      66: istore        5
      68: new           #80                 // class java/util/HashMap
      71: dup
      72: iload         4
      74: iload         5
      76: iadd
      77: i2d
      78: ldc2_w        #84                 // double 0.75d
      81: ddiv
      82: d2i
      83: iconst_1
      84: iadd
      85: invokespecial #86                 // Method java/util/HashMap."<init>":(I)V
      88: astore        6
      90: aload_2
      91: ifnull        102
      94: aload         6
      96: aload_2
      97: invokeinterface #87,  2           // InterfaceMethod java/util/Map.putAll:(Ljava/util/Map;)V
     102: aload_3
     103: ifnull        114
     106: aload         6
     108: aload_3
     109: invokeinterface #87,  2           // InterfaceMethod java/util/Map.putAll:(Ljava/util/Map;)V
     114: invokestatic  #8                  // Method org/apache/dubbo/rpc/RpcContext.getServiceContext:()Lorg/apache/dubbo/rpc/RpcServiceContext;
     117: invokevirtual #12                 // Method org/apache/dubbo/rpc/RpcServiceContext.getConsumerUrl:()Lorg/apache/dubbo/common/URL;
     120: astore        7
     122: aload         7
     124: ifnull        181
     127: new           #80                 // class java/util/HashMap
     130: dup
     131: aload         7
     133: invokevirtual #88                 // Method org/apache/dubbo/common/URL.getParameters:()Ljava/util/Map;
     136: invokespecial #89                 // Method java/util/HashMap."<init>":(Ljava/util/Map;)V
     139: astore        8
     141: aload_0
     142: getfield      #90                 // Field providerFirstParams:Ljava/util/Set;
     145: invokestatic  #91                 // Method org/apache/dubbo/common/utils/CollectionUtils.isNotEmpty:(Ljava/util/Collection;)Z
     148: ifeq          172
     151: aload_0
     152: getfield      #90                 // Field providerFirstParams:Ljava/util/Set;
     155: aload         8
     157: dup
     158: invokevirtual #92                 // Method java/lang/Object.getClass:()Ljava/lang/Class;
     161: pop
     162: invokedynamic #93,  0             // InvokeDynamic #0:accept:(Ljava/util/Map;)Ljava/util/function/Consumer;
     167: invokeinterface #94,  2           // InterfaceMethod java/util/Set.forEach:(Ljava/util/function/Consumer;)V
     172: aload         6
     174: aload         8
     176: invokeinterface #87,  2           // InterfaceMethod java/util/Map.putAll:(Ljava/util/Map;)V
     181: aload         6
     183: areturn

  public java.util.Map<java.lang.String, java.lang.String> getOriginalParameters();
    Code:
       0: aload_0
       1: invokevirtual #32                 // Method getProtocolServiceKey:()Ljava/lang/String;
       4: astore_1
       5: aload_1
       6: invokestatic  #46                 // Method org/apache/dubbo/common/utils/StringUtils.isEmpty:(Ljava/lang/String;)Z
       9: ifeq          22
      12: aload_0
      13: invokevirtual #78                 // Method getInstance:()Lorg/apache/dubbo/registry/client/ServiceInstance;
      16: invokeinterface #79,  1           // InterfaceMethod org/apache/dubbo/registry/client/ServiceInstance.getAllParams:()Ljava/util/Map;
      21: areturn
      22: aload_0
      23: aload_1
      24: invokevirtual #95                 // Method getOriginalServiceParameters:(Ljava/lang/String;)Ljava/util/Map;
      27: areturn

  public java.util.Map<java.lang.String, java.lang.String> getParameters();
    Code:
       0: aload_0
       1: invokevirtual #32                 // Method getProtocolServiceKey:()Ljava/lang/String;
       4: astore_1
       5: aload_1
       6: invokestatic  #46                 // Method org/apache/dubbo/common/utils/StringUtils.isEmpty:(Ljava/lang/String;)Z
       9: ifeq          22
      12: aload_0
      13: invokevirtual #78                 // Method getInstance:()Lorg/apache/dubbo/registry/client/ServiceInstance;
      16: invokeinterface #79,  1           // InterfaceMethod org/apache/dubbo/registry/client/ServiceInstance.getAllParams:()Ljava/util/Map;
      21: areturn
      22: aload_0
      23: aload_1
      24: invokevirtual #96                 // Method getServiceParameters:(Ljava/lang/String;)Ljava/util/Map;
      27: areturn

  public org.apache.dubbo.common.URL addParameter(java.lang.String, java.lang.String);
    Code:
       0: aload_1
       1: invokestatic  #46                 // Method org/apache/dubbo/common/utils/StringUtils.isEmpty:(Ljava/lang/String;)Z
       4: ifne          14
       7: aload_2
       8: invokestatic  #46                 // Method org/apache/dubbo/common/utils/StringUtils.isEmpty:(Ljava/lang/String;)Z
      11: ifeq          16
      14: aload_0
      15: areturn
      16: aload_0
      17: invokevirtual #78                 // Method getInstance:()Lorg/apache/dubbo/registry/client/ServiceInstance;
      20: aload_1
      21: aload_2
      22: invokeinterface #97,  3           // InterfaceMethod org/apache/dubbo/registry/client/ServiceInstance.putExtendParam:(Ljava/lang/String;Ljava/lang/String;)Ljava/lang/String;
      27: pop
      28: aload_0
      29: areturn

  public org.apache.dubbo.common.URL addParameterIfAbsent(java.lang.String, java.lang.String);
    Code:
       0: aload_1
       1: invokestatic  #46                 // Method org/apache/dubbo/common/utils/StringUtils.isEmpty:(Ljava/lang/String;)Z
       4: ifne          14
       7: aload_2
       8: invokestatic  #46                 // Method org/apache/dubbo/common/utils/StringUtils.isEmpty:(Ljava/lang/String;)Z
      11: ifeq          16
      14: aload_0
      15: areturn
      16: aload_0
      17: invokevirtual #78                 // Method getInstance:()Lorg/apache/dubbo/registry/client/ServiceInstance;
      20: aload_1
      21: aload_2
      22: invokeinterface #98,  3           // InterfaceMethod org/apache/dubbo/registry/client/ServiceInstance.putExtendParamIfAbsent:(Ljava/lang/String;Ljava/lang/String;)Ljava/lang/String;
      27: pop
      28: aload_0
      29: areturn

  public org.apache.dubbo.common.URL addServiceParameter(java.lang.String, java.lang.String, java.lang.String);
    Code:
       0: aload_2
       1: invokestatic  #46                 // Method org/apache/dubbo/common/utils/StringUtils.isEmpty:(Ljava/lang/String;)Z
       4: ifne          14
       7: aload_3
       8: invokestatic  #46                 // Method org/apache/dubbo/common/utils/StringUtils.isEmpty:(Ljava/lang/String;)Z
      11: ifeq          16
      14: aload_0
      15: areturn
      16: aload_0
      17: aload_1
      18: invokespecial #34                 // Method getServiceInfo:(Ljava/lang/String;)Lorg/apache/dubbo/metadata/MetadataInfo$ServiceInfo;
      21: astore        4
      23: aconst_null
      24: aload         4
      26: if_acmpeq     36
      29: aload         4
      31: aload_2
      32: aload_3
      33: invokevirtual #99                 // Method org/apache/dubbo/metadata/MetadataInfo$ServiceInfo.addParameter:(Ljava/lang/String;Ljava/lang/String;)V
      36: aload_0
      37: areturn

  public org.apache.dubbo.common.URL addServiceParameterIfAbsent(java.lang.String, java.lang.String, java.lang.String);
    Code:
       0: aload_2
       1: invokestatic  #46                 // Method org/apache/dubbo/common/utils/StringUtils.isEmpty:(Ljava/lang/String;)Z
       4: ifne          14
       7: aload_3
       8: invokestatic  #46                 // Method org/apache/dubbo/common/utils/StringUtils.isEmpty:(Ljava/lang/String;)Z
      11: ifeq          16
      14: aload_0
      15: areturn
      16: aload_0
      17: aload_1
      18: invokespecial #34                 // Method getServiceInfo:(Ljava/lang/String;)Lorg/apache/dubbo/metadata/MetadataInfo$ServiceInfo;
      21: astore        4
      23: aconst_null
      24: aload         4
      26: if_acmpeq     36
      29: aload         4
      31: aload_2
      32: aload_3
      33: invokevirtual #100                // Method org/apache/dubbo/metadata/MetadataInfo$ServiceInfo.addParameterIfAbsent:(Ljava/lang/String;Ljava/lang/String;)V
      36: aload_0
      37: areturn

  public org.apache.dubbo.common.URL addConsumerParams(java.lang.String, java.util.Map<java.lang.String, java.lang.String>);
    Code:
       0: aload_0
       1: aload_1
       2: invokespecial #34                 // Method getServiceInfo:(Ljava/lang/String;)Lorg/apache/dubbo/metadata/MetadataInfo$ServiceInfo;
       5: astore_3
       6: aconst_null
       7: aload_3
       8: if_acmpeq     16
      11: aload_3
      12: aload_2
      13: invokevirtual #101                // Method org/apache/dubbo/metadata/MetadataInfo$ServiceInfo.addConsumerParams:(Ljava/util/Map;)V
      16: aload_0
      17: areturn

  public java.lang.String getAnyMethodParameter(java.lang.String);
    Code:
       0: new           #59                 // class java/lang/StringBuilder
       3: dup
       4: invokespecial #60                 // Method java/lang/StringBuilder."<init>":()V
       7: ldc           #61                 // String .
       9: invokevirtual #62                 // Method java/lang/StringBuilder.append:(Ljava/lang/String;)Ljava/lang/StringBuilder;
      12: aload_1
      13: invokevirtual #62                 // Method java/lang/StringBuilder.append:(Ljava/lang/String;)Ljava/lang/StringBuilder;
      16: invokevirtual #63                 // Method java/lang/StringBuilder.toString:()Ljava/lang/String;
      19: astore_2
      20: aload_0
      21: invokevirtual #32                 // Method getProtocolServiceKey:()Ljava/lang/String;
      24: astore_3
      25: aload_3
      26: invokestatic  #33                 // Method org/apache/dubbo/common/utils/StringUtils.isNotEmpty:(Ljava/lang/String;)Z
      29: ifeq          105
      32: aload_0
      33: aload_3
      34: invokespecial #34                 // Method getServiceInfo:(Ljava/lang/String;)Lorg/apache/dubbo/metadata/MetadataInfo$ServiceInfo;
      37: astore        4
      39: aconst_null
      40: aload         4
      42: if_acmpne     47
      45: aconst_null
      46: areturn
      47: aload         4
      49: invokevirtual #102                // Method org/apache/dubbo/metadata/MetadataInfo$ServiceInfo.getAllParams:()Ljava/util/Map;
      52: invokeinterface #64,  1           // InterfaceMethod java/util/Map.keySet:()Ljava/util/Set;
      57: invokeinterface #65,  1           // InterfaceMethod java/util/Set.iterator:()Ljava/util/Iterator;
      62: astore        5
      64: aload         5
      66: invokeinterface #66,  1           // InterfaceMethod java/util/Iterator.hasNext:()Z
      71: ifeq          105
      74: aload         5
      76: invokeinterface #67,  1           // InterfaceMethod java/util/Iterator.next:()Ljava/lang/Object;
      81: checkcast     #68                 // class java/lang/String
      84: astore        6
      86: aload         6
      88: aload_2
      89: invokevirtual #69                 // Method java/lang/String.endsWith:(Ljava/lang/String;)Z
      92: ifeq          102
      95: aload_0
      96: aload         6
      98: invokevirtual #54                 // Method getParameter:(Ljava/lang/String;)Ljava/lang/String;
     101: areturn
     102: goto          64
     105: aconst_null
     106: areturn

  public org.apache.dubbo.common.url.component.URLParam getUrlParam();
    Code:
       0: new           #103                // class java/lang/UnsupportedOperationException
       3: dup
       4: ldc           #104                // String URLParam is replaced with MetadataInfo in instance url
       6: invokespecial #105                // Method java/lang/UnsupportedOperationException."<init>":(Ljava/lang/String;)V
       9: athrow

  public org.apache.dubbo.common.url.component.URLAddress getUrlAddress();
    Code:
       0: new           #103                // class java/lang/UnsupportedOperationException
       3: dup
       4: ldc           #106                // String URLAddress is replaced with ServiceInstance in instance url
       6: invokespecial #105                // Method java/lang/UnsupportedOperationException."<init>":(Ljava/lang/String;)V
       9: athrow

  private org.apache.dubbo.metadata.MetadataInfo$ServiceInfo getServiceInfo(java.lang.String);
    Code:
       0: aload_0
       1: getfield      #5                  // Field metadataInfo:Lorg/apache/dubbo/metadata/MetadataInfo;
       4: aload_1
       5: invokevirtual #107                // Method org/apache/dubbo/metadata/MetadataInfo.getValidServiceInfo:(Ljava/lang/String;)Lorg/apache/dubbo/metadata/MetadataInfo$ServiceInfo;
       8: areturn

  private java.lang.String getInstanceParameter(java.lang.String);
    Code:
       0: aload_0
       1: getfield      #4                  // Field instance:Lorg/apache/dubbo/registry/client/ServiceInstance;
       4: invokeinterface #108,  1          // InterfaceMethod org/apache/dubbo/registry/client/ServiceInstance.getMetadata:()Ljava/util/Map;
       9: aload_1
      10: invokeinterface #109,  2          // InterfaceMethod java/util/Map.get:(Ljava/lang/Object;)Ljava/lang/Object;
      15: checkcast     #68                 // class java/lang/String
      18: astore_2
      19: aload_2
      20: invokestatic  #33                 // Method org/apache/dubbo/common/utils/StringUtils.isNotEmpty:(Ljava/lang/String;)Z
      23: ifeq          28
      26: aload_2
      27: areturn
      28: aload_0
      29: getfield      #4                  // Field instance:Lorg/apache/dubbo/registry/client/ServiceInstance;
      32: aload_1
      33: invokeinterface #110,  2          // InterfaceMethod org/apache/dubbo/registry/client/ServiceInstance.getExtendParam:(Ljava/lang/String;)Ljava/lang/String;
      38: areturn

  private java.util.Map<java.lang.String, java.lang.String> getInstanceMetadata();
    Code:
       0: aload_0
       1: getfield      #4                  // Field instance:Lorg/apache/dubbo/registry/client/ServiceInstance;
       4: invokeinterface #108,  1          // InterfaceMethod org/apache/dubbo/registry/client/ServiceInstance.getMetadata:()Ljava/util/Map;
       9: areturn

  public org.apache.dubbo.rpc.model.FrameworkModel getOrDefaultFrameworkModel();
    Code:
       0: aload_0
       1: getfield      #4                  // Field instance:Lorg/apache/dubbo/registry/client/ServiceInstance;
       4: invokeinterface #111,  1          // InterfaceMethod org/apache/dubbo/registry/client/ServiceInstance.getOrDefaultApplicationModel:()Lorg/apache/dubbo/rpc/model/ApplicationModel;
       9: invokevirtual #112                // Method org/apache/dubbo/rpc/model/ApplicationModel.getFrameworkModel:()Lorg/apache/dubbo/rpc/model/FrameworkModel;
      12: areturn

  public org.apache.dubbo.rpc.model.ApplicationModel getOrDefaultApplicationModel();
    Code:
       0: aload_0
       1: getfield      #4                  // Field instance:Lorg/apache/dubbo/registry/client/ServiceInstance;
       4: invokeinterface #111,  1          // InterfaceMethod org/apache/dubbo/registry/client/ServiceInstance.getOrDefaultApplicationModel:()Lorg/apache/dubbo/rpc/model/ApplicationModel;
       9: areturn

  public org.apache.dubbo.rpc.model.ApplicationModel getApplicationModel();
    Code:
       0: aload_0
       1: getfield      #4                  // Field instance:Lorg/apache/dubbo/registry/client/ServiceInstance;
       4: invokeinterface #113,  1          // InterfaceMethod org/apache/dubbo/registry/client/ServiceInstance.getApplicationModel:()Lorg/apache/dubbo/rpc/model/ApplicationModel;
       9: areturn

  public org.apache.dubbo.rpc.model.ScopeModel getScopeModel();
    Code:
       0: invokestatic  #8                  // Method org/apache/dubbo/rpc/RpcContext.getServiceContext:()Lorg/apache/dubbo/rpc/RpcServiceContext;
       3: invokevirtual #12                 // Method org/apache/dubbo/rpc/RpcServiceContext.getConsumerUrl:()Lorg/apache/dubbo/common/URL;
       6: invokestatic  #114                // Method java/util/Optional.ofNullable:(Ljava/lang/Object;)Ljava/util/Optional;
       9: invokedynamic #115,  0            // InvokeDynamic #1:apply:()Ljava/util/function/Function;
      14: invokevirtual #116                // Method java/util/Optional.map:(Ljava/util/function/Function;)Ljava/util/Optional;
      17: aload_0
      18: invokespecial #117                // Method org/apache/dubbo/common/URL.getScopeModel:()Lorg/apache/dubbo/rpc/model/ScopeModel;
      21: invokevirtual #118                // Method java/util/Optional.orElse:(Ljava/lang/Object;)Ljava/lang/Object;
      24: checkcast     #119                // class org/apache/dubbo/rpc/model/ScopeModel
      27: areturn

  public org.apache.dubbo.rpc.model.ServiceModel getServiceModel();
    Code:
       0: invokestatic  #8                  // Method org/apache/dubbo/rpc/RpcContext.getServiceContext:()Lorg/apache/dubbo/rpc/RpcServiceContext;
       3: invokevirtual #12                 // Method org/apache/dubbo/rpc/RpcServiceContext.getConsumerUrl:()Lorg/apache/dubbo/common/URL;
       6: invokevirtual #120                // Method org/apache/dubbo/common/URL.getServiceModel:()Lorg/apache/dubbo/rpc/model/ServiceModel;
       9: areturn

  public java.util.Set<java.lang.String> getProviderFirstParams();
    Code:
       0: aload_0
       1: getfield      #90                 // Field providerFirstParams:Ljava/util/Set;
       4: areturn

  public void setProviderFirstParams(java.util.Set<java.lang.String>);
    Code:
       0: aload_0
       1: aload_1
       2: putfield      #90                 // Field providerFirstParams:Ljava/util/Set;
       5: return

  private boolean consumerParamFirst(java.lang.String);
    Code:
       0: aload_0
       1: getfield      #90                 // Field providerFirstParams:Ljava/util/Set;
       4: invokestatic  #91                 // Method org/apache/dubbo/common/utils/CollectionUtils.isNotEmpty:(Ljava/util/Collection;)Z
       7: ifeq          29
      10: aload_0
      11: getfield      #90                 // Field providerFirstParams:Ljava/util/Set;
      14: aload_1
      15: invokeinterface #121,  2          // InterfaceMethod java/util/Set.contains:(Ljava/lang/Object;)Z
      20: ifne          27
      23: iconst_1
      24: goto          28
      27: iconst_0
      28: ireturn
      29: iconst_1
      30: ireturn

  public boolean equals(java.lang.Object);
    Code:
       0: aload_1
       1: ifnonnull     6
       4: iconst_0
       5: ireturn
       6: aload_1
       7: instanceof    #122                // class org/apache/dubbo/registry/client/InstanceAddressURL
      10: ifne          15
      13: iconst_0
      14: ireturn
      15: aload_1
      16: checkcast     #122                // class org/apache/dubbo/registry/client/InstanceAddressURL
      19: astore_2
      20: aload_0
      21: invokevirtual #78                 // Method getInstance:()Lorg/apache/dubbo/registry/client/ServiceInstance;
      24: aload_2
      25: invokevirtual #78                 // Method getInstance:()Lorg/apache/dubbo/registry/client/ServiceInstance;
      28: invokevirtual #123                // Method java/lang/Object.equals:(Ljava/lang/Object;)Z
      31: ireturn

  public int hashCode();
    Code:
       0: aload_0
       1: invokevirtual #78                 // Method getInstance:()Lorg/apache/dubbo/registry/client/ServiceInstance;
       4: invokevirtual #124                // Method java/lang/Object.hashCode:()I
       7: ireturn

  public java.lang.String toString();
    Code:
       0: aload_0
       1: getfield      #4                  // Field instance:Lorg/apache/dubbo/registry/client/ServiceInstance;
       4: ifnonnull     10
       7: ldc           #125                // String {}
       9: areturn
      10: aload_0
      11: getfield      #5                  // Field metadataInfo:Lorg/apache/dubbo/metadata/MetadataInfo;
      14: ifnonnull     25
      17: aload_0
      18: getfield      #4                  // Field instance:Lorg/apache/dubbo/registry/client/ServiceInstance;
      21: invokevirtual #126                // Method java/lang/Object.toString:()Ljava/lang/String;
      24: areturn
      25: aload_0
      26: invokevirtual #32                 // Method getProtocolServiceKey:()Ljava/lang/String;
      29: astore_1
      30: aload_1
      31: invokestatic  #33                 // Method org/apache/dubbo/common/utils/StringUtils.isNotEmpty:(Ljava/lang/String;)Z
      34: ifeq          74
      37: new           #59                 // class java/lang/StringBuilder
      40: dup
      41: invokespecial #60                 // Method java/lang/StringBuilder."<init>":()V
      44: aload_0
      45: getfield      #4                  // Field instance:Lorg/apache/dubbo/registry/client/ServiceInstance;
      48: invokevirtual #126                // Method java/lang/Object.toString:()Ljava/lang/String;
      51: invokevirtual #62                 // Method java/lang/StringBuilder.append:(Ljava/lang/String;)Ljava/lang/StringBuilder;
      54: ldc           #127                // String ,
      56: invokevirtual #62                 // Method java/lang/StringBuilder.append:(Ljava/lang/String;)Ljava/lang/StringBuilder;
      59: aload_0
      60: getfield      #5                  // Field metadataInfo:Lorg/apache/dubbo/metadata/MetadataInfo;
      63: aload_1
      64: invokevirtual #128                // Method org/apache/dubbo/metadata/MetadataInfo.getServiceString:(Ljava/lang/String;)Ljava/lang/String;
      67: invokevirtual #62                 // Method java/lang/StringBuilder.append:(Ljava/lang/String;)Ljava/lang/StringBuilder;
      70: invokevirtual #63                 // Method java/lang/StringBuilder.toString:()Ljava/lang/String;
      73: areturn
      74: aload_0
      75: getfield      #4                  // Field instance:Lorg/apache/dubbo/registry/client/ServiceInstance;
      78: invokevirtual #126                // Method java/lang/Object.toString:()Ljava/lang/String;
      81: areturn
}
