Compiled from "OverrideInstanceAddressURL.java"
public class org.apache.dubbo.registry.client.OverrideInstanceAddressURL extends org.apache.dubbo.registry.client.InstanceAddressURL {
  private static final long serialVersionUID;

  private final org.apache.dubbo.common.url.component.URLParam overrideParams;

  private final org.apache.dubbo.registry.client.InstanceAddressURL originUrl;

  public org.apache.dubbo.registry.client.OverrideInstanceAddressURL(org.apache.dubbo.registry.client.InstanceAddressURL);
    Code:
       0: aload_0
       1: invokespecial #1                  // Method org/apache/dubbo/registry/client/InstanceAddressURL."<init>":()V
       4: aload_0
       5: aload_1
       6: putfield      #2                  // Field originUrl:Lorg/apache/dubbo/registry/client/InstanceAddressURL;
       9: aload_0
      10: ldc           #3                  // String
      12: invokestatic  #4                  // Method org/apache/dubbo/common/url/component/URLParam.parse:(Ljava/lang/String;)Lorg/apache/dubbo/common/url/component/URLParam;
      15: putfield      #5                  // Field overrideParams:Lorg/apache/dubbo/common/url/component/URLParam;
      18: return

  public org.apache.dubbo.registry.client.OverrideInstanceAddressURL(org.apache.dubbo.registry.client.InstanceAddressURL, org.apache.dubbo.common.url.component.URLParam);
    Code:
       0: aload_0
       1: invokespecial #1                  // Method org/apache/dubbo/registry/client/InstanceAddressURL."<init>":()V
       4: aload_0
       5: aload_1
       6: putfield      #2                  // Field originUrl:Lorg/apache/dubbo/registry/client/InstanceAddressURL;
       9: aload_0
      10: aload_2
      11: putfield      #5                  // Field overrideParams:Lorg/apache/dubbo/common/url/component/URLParam;
      14: return

  public org.apache.dubbo.registry.client.ServiceInstance getInstance();
    Code:
       0: aload_0
       1: getfield      #2                  // Field originUrl:Lorg/apache/dubbo/registry/client/InstanceAddressURL;
       4: invokevirtual #6                  // Method org/apache/dubbo/registry/client/InstanceAddressURL.getInstance:()Lorg/apache/dubbo/registry/client/ServiceInstance;
       7: areturn

  public org.apache.dubbo.metadata.MetadataInfo getMetadataInfo();
    Code:
       0: aload_0
       1: getfield      #2                  // Field originUrl:Lorg/apache/dubbo/registry/client/InstanceAddressURL;
       4: invokevirtual #7                  // Method org/apache/dubbo/registry/client/InstanceAddressURL.getMetadataInfo:()Lorg/apache/dubbo/metadata/MetadataInfo;
       7: areturn

  public java.lang.String getServiceInterface();
    Code:
       0: aload_0
       1: getfield      #2                  // Field originUrl:Lorg/apache/dubbo/registry/client/InstanceAddressURL;
       4: invokevirtual #8                  // Method org/apache/dubbo/registry/client/InstanceAddressURL.getServiceInterface:()Ljava/lang/String;
       7: areturn

  public java.lang.String getGroup();
    Code:
       0: aload_0
       1: getfield      #2                  // Field originUrl:Lorg/apache/dubbo/registry/client/InstanceAddressURL;
       4: invokevirtual #9                  // Method org/apache/dubbo/registry/client/InstanceAddressURL.getGroup:()Ljava/lang/String;
       7: areturn

  public java.lang.String getVersion();
    Code:
       0: aload_0
       1: getfield      #2                  // Field originUrl:Lorg/apache/dubbo/registry/client/InstanceAddressURL;
       4: invokevirtual #10                 // Method org/apache/dubbo/registry/client/InstanceAddressURL.getVersion:()Ljava/lang/String;
       7: areturn

  public java.lang.String getProtocol();
    Code:
       0: aload_0
       1: getfield      #2                  // Field originUrl:Lorg/apache/dubbo/registry/client/InstanceAddressURL;
       4: invokevirtual #11                 // Method org/apache/dubbo/registry/client/InstanceAddressURL.getProtocol:()Ljava/lang/String;
       7: areturn

  public java.lang.String getProtocolServiceKey();
    Code:
       0: aload_0
       1: getfield      #2                  // Field originUrl:Lorg/apache/dubbo/registry/client/InstanceAddressURL;
       4: invokevirtual #12                 // Method org/apache/dubbo/registry/client/InstanceAddressURL.getProtocolServiceKey:()Ljava/lang/String;
       7: areturn

  public java.lang.String getServiceKey();
    Code:
       0: aload_0
       1: getfield      #2                  // Field originUrl:Lorg/apache/dubbo/registry/client/InstanceAddressURL;
       4: invokevirtual #13                 // Method org/apache/dubbo/registry/client/InstanceAddressURL.getServiceKey:()Ljava/lang/String;
       7: areturn

  public java.lang.String getAddress();
    Code:
       0: aload_0
       1: getfield      #2                  // Field originUrl:Lorg/apache/dubbo/registry/client/InstanceAddressURL;
       4: invokevirtual #14                 // Method org/apache/dubbo/registry/client/InstanceAddressURL.getAddress:()Ljava/lang/String;
       7: areturn

  public java.lang.String getHost();
    Code:
       0: aload_0
       1: getfield      #2                  // Field originUrl:Lorg/apache/dubbo/registry/client/InstanceAddressURL;
       4: invokevirtual #15                 // Method org/apache/dubbo/registry/client/InstanceAddressURL.getHost:()Ljava/lang/String;
       7: areturn

  public int getPort();
    Code:
       0: aload_0
       1: getfield      #2                  // Field originUrl:Lorg/apache/dubbo/registry/client/InstanceAddressURL;
       4: invokevirtual #16                 // Method org/apache/dubbo/registry/client/InstanceAddressURL.getPort:()I
       7: ireturn

  public java.lang.String getIp();
    Code:
       0: aload_0
       1: getfield      #2                  // Field originUrl:Lorg/apache/dubbo/registry/client/InstanceAddressURL;
       4: invokevirtual #17                 // Method org/apache/dubbo/registry/client/InstanceAddressURL.getIp:()Ljava/lang/String;
       7: areturn

  public java.lang.String getPath();
    Code:
       0: aload_0
       1: getfield      #2                  // Field originUrl:Lorg/apache/dubbo/registry/client/InstanceAddressURL;
       4: invokevirtual #18                 // Method org/apache/dubbo/registry/client/InstanceAddressURL.getPath:()Ljava/lang/String;
       7: areturn

  public java.lang.String getParameter(java.lang.String);
    Code:
       0: aload_0
       1: getfield      #5                  // Field overrideParams:Lorg/apache/dubbo/common/url/component/URLParam;
       4: aload_1
       5: invokevirtual #19                 // Method org/apache/dubbo/common/url/component/URLParam.getParameter:(Ljava/lang/String;)Ljava/lang/String;
       8: astore_2
       9: aload_2
      10: invokestatic  #20                 // Method org/apache/dubbo/common/utils/StringUtils.isNotEmpty:(Ljava/lang/String;)Z
      13: ifeq          20
      16: aload_2
      17: goto          28
      20: aload_0
      21: getfield      #2                  // Field originUrl:Lorg/apache/dubbo/registry/client/InstanceAddressURL;
      24: aload_1
      25: invokevirtual #21                 // Method org/apache/dubbo/registry/client/InstanceAddressURL.getParameter:(Ljava/lang/String;)Ljava/lang/String;
      28: areturn

  public java.lang.String getServiceParameter(java.lang.String, java.lang.String);
    Code:
       0: aload_0
       1: getfield      #5                  // Field overrideParams:Lorg/apache/dubbo/common/url/component/URLParam;
       4: aload_2
       5: invokevirtual #19                 // Method org/apache/dubbo/common/url/component/URLParam.getParameter:(Ljava/lang/String;)Ljava/lang/String;
       8: astore_3
       9: aload_3
      10: invokestatic  #20                 // Method org/apache/dubbo/common/utils/StringUtils.isNotEmpty:(Ljava/lang/String;)Z
      13: ifeq          20
      16: aload_3
      17: goto          29
      20: aload_0
      21: getfield      #2                  // Field originUrl:Lorg/apache/dubbo/registry/client/InstanceAddressURL;
      24: aload_1
      25: aload_2
      26: invokevirtual #22                 // Method org/apache/dubbo/registry/client/InstanceAddressURL.getServiceParameter:(Ljava/lang/String;Ljava/lang/String;)Ljava/lang/String;
      29: areturn

  public java.lang.String getServiceMethodParameter(java.lang.String, java.lang.String, java.lang.String);
    Code:
       0: aload_0
       1: getfield      #5                  // Field overrideParams:Lorg/apache/dubbo/common/url/component/URLParam;
       4: aload_2
       5: aload_3
       6: invokevirtual #23                 // Method org/apache/dubbo/common/url/component/URLParam.getMethodParameter:(Ljava/lang/String;Ljava/lang/String;)Ljava/lang/String;
       9: astore        4
      11: aload         4
      13: invokestatic  #20                 // Method org/apache/dubbo/common/utils/StringUtils.isNotEmpty:(Ljava/lang/String;)Z
      16: ifeq          24
      19: aload         4
      21: goto          34
      24: aload_0
      25: getfield      #2                  // Field originUrl:Lorg/apache/dubbo/registry/client/InstanceAddressURL;
      28: aload_1
      29: aload_2
      30: aload_3
      31: invokevirtual #24                 // Method org/apache/dubbo/registry/client/InstanceAddressURL.getServiceMethodParameter:(Ljava/lang/String;Ljava/lang/String;Ljava/lang/String;)Ljava/lang/String;
      34: areturn

  public java.lang.String getMethodParameter(java.lang.String, java.lang.String);
    Code:
       0: aload_0
       1: getfield      #5                  // Field overrideParams:Lorg/apache/dubbo/common/url/component/URLParam;
       4: aload_1
       5: aload_2
       6: invokevirtual #23                 // Method org/apache/dubbo/common/url/component/URLParam.getMethodParameter:(Ljava/lang/String;Ljava/lang/String;)Ljava/lang/String;
       9: astore_3
      10: aload_3
      11: invokestatic  #20                 // Method org/apache/dubbo/common/utils/StringUtils.isNotEmpty:(Ljava/lang/String;)Z
      14: ifeq          21
      17: aload_3
      18: goto          30
      21: aload_0
      22: getfield      #2                  // Field originUrl:Lorg/apache/dubbo/registry/client/InstanceAddressURL;
      25: aload_1
      26: aload_2
      27: invokevirtual #25                 // Method org/apache/dubbo/registry/client/InstanceAddressURL.getMethodParameter:(Ljava/lang/String;Ljava/lang/String;)Ljava/lang/String;
      30: areturn

  public boolean hasServiceMethodParameter(java.lang.String, java.lang.String, java.lang.String);
    Code:
       0: aload_0
       1: getfield      #5                  // Field overrideParams:Lorg/apache/dubbo/common/url/component/URLParam;
       4: aload_2
       5: aload_3
       6: invokevirtual #23                 // Method org/apache/dubbo/common/url/component/URLParam.getMethodParameter:(Ljava/lang/String;Ljava/lang/String;)Ljava/lang/String;
       9: invokestatic  #20                 // Method org/apache/dubbo/common/utils/StringUtils.isNotEmpty:(Ljava/lang/String;)Z
      12: ifne          28
      15: aload_0
      16: getfield      #2                  // Field originUrl:Lorg/apache/dubbo/registry/client/InstanceAddressURL;
      19: aload_1
      20: aload_2
      21: aload_3
      22: invokevirtual #26                 // Method org/apache/dubbo/registry/client/InstanceAddressURL.hasServiceMethodParameter:(Ljava/lang/String;Ljava/lang/String;Ljava/lang/String;)Z
      25: ifeq          32
      28: iconst_1
      29: goto          33
      32: iconst_0
      33: ireturn

  public boolean hasMethodParameter(java.lang.String, java.lang.String);
    Code:
       0: aload_0
       1: getfield      #5                  // Field overrideParams:Lorg/apache/dubbo/common/url/component/URLParam;
       4: aload_1
       5: aload_2
       6: invokevirtual #23                 // Method org/apache/dubbo/common/url/component/URLParam.getMethodParameter:(Ljava/lang/String;Ljava/lang/String;)Ljava/lang/String;
       9: invokestatic  #20                 // Method org/apache/dubbo/common/utils/StringUtils.isNotEmpty:(Ljava/lang/String;)Z
      12: ifne          27
      15: aload_0
      16: getfield      #2                  // Field originUrl:Lorg/apache/dubbo/registry/client/InstanceAddressURL;
      19: aload_1
      20: aload_2
      21: invokevirtual #27                 // Method org/apache/dubbo/registry/client/InstanceAddressURL.hasMethodParameter:(Ljava/lang/String;Ljava/lang/String;)Z
      24: ifeq          31
      27: iconst_1
      28: goto          32
      31: iconst_0
      32: ireturn

  public boolean hasServiceMethodParameter(java.lang.String, java.lang.String);
    Code:
       0: aload_0
       1: getfield      #5                  // Field overrideParams:Lorg/apache/dubbo/common/url/component/URLParam;
       4: aload_2
       5: invokevirtual #28                 // Method org/apache/dubbo/common/url/component/URLParam.hasMethodParameter:(Ljava/lang/String;)Z
       8: ifne          23
      11: aload_0
      12: getfield      #2                  // Field originUrl:Lorg/apache/dubbo/registry/client/InstanceAddressURL;
      15: aload_1
      16: aload_2
      17: invokevirtual #29                 // Method org/apache/dubbo/registry/client/InstanceAddressURL.hasServiceMethodParameter:(Ljava/lang/String;Ljava/lang/String;)Z
      20: ifeq          27
      23: iconst_1
      24: goto          28
      27: iconst_0
      28: ireturn

  public boolean hasMethodParameter(java.lang.String);
    Code:
       0: aload_0
       1: getfield      #5                  // Field overrideParams:Lorg/apache/dubbo/common/url/component/URLParam;
       4: aload_1
       5: invokevirtual #28                 // Method org/apache/dubbo/common/url/component/URLParam.hasMethodParameter:(Ljava/lang/String;)Z
       8: ifne          22
      11: aload_0
      12: getfield      #2                  // Field originUrl:Lorg/apache/dubbo/registry/client/InstanceAddressURL;
      15: aload_1
      16: invokevirtual #30                 // Method org/apache/dubbo/registry/client/InstanceAddressURL.hasMethodParameter:(Ljava/lang/String;)Z
      19: ifeq          26
      22: iconst_1
      23: goto          27
      26: iconst_0
      27: ireturn

  public java.util.Map<java.lang.String, java.lang.String> getServiceParameters(java.lang.String);
    Code:
       0: aload_0
       1: getfield      #2                  // Field originUrl:Lorg/apache/dubbo/registry/client/InstanceAddressURL;
       4: aload_1
       5: invokevirtual #31                 // Method org/apache/dubbo/registry/client/InstanceAddressURL.getServiceParameters:(Ljava/lang/String;)Ljava/util/Map;
       8: astore_2
       9: aload_0
      10: getfield      #5                  // Field overrideParams:Lorg/apache/dubbo/common/url/component/URLParam;
      13: invokevirtual #32                 // Method org/apache/dubbo/common/url/component/URLParam.getParameters:()Ljava/util/Map;
      16: astore_3
      17: new           #33                 // class java/util/HashMap
      20: dup
      21: aload_2
      22: invokeinterface #34,  1           // InterfaceMethod java/util/Map.size:()I
      27: i2f
      28: aload_3
      29: invokeinterface #34,  1           // InterfaceMethod java/util/Map.size:()I
      34: i2f
      35: ldc           #35                 // float 0.75f
      37: fdiv
      38: fadd
      39: f2i
      40: iconst_1
      41: iadd
      42: invokespecial #36                 // Method java/util/HashMap."<init>":(I)V
      45: astore        4
      47: aload         4
      49: aload_2
      50: invokeinterface #37,  2           // InterfaceMethod java/util/Map.putAll:(Ljava/util/Map;)V
      55: aload         4
      57: aload_3
      58: invokeinterface #37,  2           // InterfaceMethod java/util/Map.putAll:(Ljava/util/Map;)V
      63: aload         4
      65: areturn

  public java.util.Map<java.lang.String, java.lang.String> getParameters();
    Code:
       0: aload_0
       1: getfield      #2                  // Field originUrl:Lorg/apache/dubbo/registry/client/InstanceAddressURL;
       4: invokevirtual #38                 // Method org/apache/dubbo/registry/client/InstanceAddressURL.getParameters:()Ljava/util/Map;
       7: astore_1
       8: aload_0
       9: getfield      #5                  // Field overrideParams:Lorg/apache/dubbo/common/url/component/URLParam;
      12: invokevirtual #32                 // Method org/apache/dubbo/common/url/component/URLParam.getParameters:()Ljava/util/Map;
      15: astore_2
      16: new           #33                 // class java/util/HashMap
      19: dup
      20: aload_1
      21: invokeinterface #34,  1           // InterfaceMethod java/util/Map.size:()I
      26: i2f
      27: aload_2
      28: invokeinterface #34,  1           // InterfaceMethod java/util/Map.size:()I
      33: i2f
      34: ldc           #35                 // float 0.75f
      36: fdiv
      37: fadd
      38: f2i
      39: iconst_1
      40: iadd
      41: invokespecial #36                 // Method java/util/HashMap."<init>":(I)V
      44: astore_3
      45: aload_3
      46: aload_1
      47: invokeinterface #37,  2           // InterfaceMethod java/util/Map.putAll:(Ljava/util/Map;)V
      52: aload_3
      53: aload_2
      54: invokeinterface #37,  2           // InterfaceMethod java/util/Map.putAll:(Ljava/util/Map;)V
      59: aload_3
      60: areturn

  public org.apache.dubbo.common.URL addParameter(java.lang.String, java.lang.String);
    Code:
       0: new           #39                 // class org/apache/dubbo/registry/client/OverrideInstanceAddressURL
       3: dup
       4: aload_0
       5: getfield      #2                  // Field originUrl:Lorg/apache/dubbo/registry/client/InstanceAddressURL;
       8: aload_0
       9: getfield      #5                  // Field overrideParams:Lorg/apache/dubbo/common/url/component/URLParam;
      12: aload_1
      13: aload_2
      14: invokevirtual #40                 // Method org/apache/dubbo/common/url/component/URLParam.addParameter:(Ljava/lang/String;Ljava/lang/String;)Lorg/apache/dubbo/common/url/component/URLParam;
      17: invokespecial #41                 // Method "<init>":(Lorg/apache/dubbo/registry/client/InstanceAddressURL;Lorg/apache/dubbo/common/url/component/URLParam;)V
      20: areturn

  public org.apache.dubbo.common.URL addParameterIfAbsent(java.lang.String, java.lang.String);
    Code:
       0: new           #39                 // class org/apache/dubbo/registry/client/OverrideInstanceAddressURL
       3: dup
       4: aload_0
       5: getfield      #2                  // Field originUrl:Lorg/apache/dubbo/registry/client/InstanceAddressURL;
       8: aload_0
       9: getfield      #5                  // Field overrideParams:Lorg/apache/dubbo/common/url/component/URLParam;
      12: aload_1
      13: aload_2
      14: invokevirtual #42                 // Method org/apache/dubbo/common/url/component/URLParam.addParameterIfAbsent:(Ljava/lang/String;Ljava/lang/String;)Lorg/apache/dubbo/common/url/component/URLParam;
      17: invokespecial #41                 // Method "<init>":(Lorg/apache/dubbo/registry/client/InstanceAddressURL;Lorg/apache/dubbo/common/url/component/URLParam;)V
      20: areturn

  public org.apache.dubbo.common.URL addServiceParameter(java.lang.String, java.lang.String, java.lang.String);
    Code:
       0: aload_0
       1: getfield      #2                  // Field originUrl:Lorg/apache/dubbo/registry/client/InstanceAddressURL;
       4: aload_1
       5: aload_2
       6: aload_3
       7: invokevirtual #43                 // Method org/apache/dubbo/registry/client/InstanceAddressURL.addServiceParameter:(Ljava/lang/String;Ljava/lang/String;Ljava/lang/String;)Lorg/apache/dubbo/common/URL;
      10: areturn

  public org.apache.dubbo.common.URL addServiceParameterIfAbsent(java.lang.String, java.lang.String, java.lang.String);
    Code:
       0: aload_0
       1: getfield      #2                  // Field originUrl:Lorg/apache/dubbo/registry/client/InstanceAddressURL;
       4: aload_1
       5: aload_2
       6: aload_3
       7: invokevirtual #44                 // Method org/apache/dubbo/registry/client/InstanceAddressURL.addServiceParameterIfAbsent:(Ljava/lang/String;Ljava/lang/String;Ljava/lang/String;)Lorg/apache/dubbo/common/URL;
      10: areturn

  public org.apache.dubbo.common.URL addConsumerParams(java.lang.String, java.util.Map<java.lang.String, java.lang.String>);
    Code:
       0: aload_0
       1: getfield      #2                  // Field originUrl:Lorg/apache/dubbo/registry/client/InstanceAddressURL;
       4: aload_1
       5: aload_2
       6: invokevirtual #45                 // Method org/apache/dubbo/registry/client/InstanceAddressURL.addConsumerParams:(Ljava/lang/String;Ljava/util/Map;)Lorg/apache/dubbo/common/URL;
       9: areturn

  public java.lang.String getAnyMethodParameter(java.lang.String);
    Code:
       0: aload_0
       1: getfield      #5                  // Field overrideParams:Lorg/apache/dubbo/common/url/component/URLParam;
       4: aload_1
       5: invokevirtual #46                 // Method org/apache/dubbo/common/url/component/URLParam.getAnyMethodParameter:(Ljava/lang/String;)Ljava/lang/String;
       8: astore_2
       9: aload_2
      10: invokestatic  #20                 // Method org/apache/dubbo/common/utils/StringUtils.isNotEmpty:(Ljava/lang/String;)Z
      13: ifeq          20
      16: aload_2
      17: goto          28
      20: aload_0
      21: getfield      #2                  // Field originUrl:Lorg/apache/dubbo/registry/client/InstanceAddressURL;
      24: aload_1
      25: invokevirtual #47                 // Method org/apache/dubbo/registry/client/InstanceAddressURL.getAnyMethodParameter:(Ljava/lang/String;)Ljava/lang/String;
      28: areturn

  public org.apache.dubbo.common.URL addParameters(java.util.Map<java.lang.String, java.lang.String>);
    Code:
       0: new           #39                 // class org/apache/dubbo/registry/client/OverrideInstanceAddressURL
       3: dup
       4: aload_0
       5: getfield      #2                  // Field originUrl:Lorg/apache/dubbo/registry/client/InstanceAddressURL;
       8: aload_0
       9: getfield      #5                  // Field overrideParams:Lorg/apache/dubbo/common/url/component/URLParam;
      12: aload_1
      13: invokevirtual #48                 // Method org/apache/dubbo/common/url/component/URLParam.addParameters:(Ljava/util/Map;)Lorg/apache/dubbo/common/url/component/URLParam;
      16: invokespecial #41                 // Method "<init>":(Lorg/apache/dubbo/registry/client/InstanceAddressURL;Lorg/apache/dubbo/common/url/component/URLParam;)V
      19: areturn

  public org.apache.dubbo.common.URL addParametersIfAbsent(java.util.Map<java.lang.String, java.lang.String>);
    Code:
       0: new           #39                 // class org/apache/dubbo/registry/client/OverrideInstanceAddressURL
       3: dup
       4: aload_0
       5: getfield      #2                  // Field originUrl:Lorg/apache/dubbo/registry/client/InstanceAddressURL;
       8: aload_0
       9: getfield      #5                  // Field overrideParams:Lorg/apache/dubbo/common/url/component/URLParam;
      12: aload_1
      13: invokevirtual #49                 // Method org/apache/dubbo/common/url/component/URLParam.addParametersIfAbsent:(Ljava/util/Map;)Lorg/apache/dubbo/common/url/component/URLParam;
      16: invokespecial #41                 // Method "<init>":(Lorg/apache/dubbo/registry/client/InstanceAddressURL;Lorg/apache/dubbo/common/url/component/URLParam;)V
      19: areturn

  public org.apache.dubbo.common.url.component.URLParam getUrlParam();
    Code:
       0: aload_0
       1: getfield      #2                  // Field originUrl:Lorg/apache/dubbo/registry/client/InstanceAddressURL;
       4: invokevirtual #50                 // Method org/apache/dubbo/registry/client/InstanceAddressURL.getUrlParam:()Lorg/apache/dubbo/common/url/component/URLParam;
       7: areturn

  public org.apache.dubbo.common.url.component.URLAddress getUrlAddress();
    Code:
       0: aload_0
       1: getfield      #2                  // Field originUrl:Lorg/apache/dubbo/registry/client/InstanceAddressURL;
       4: invokevirtual #51                 // Method org/apache/dubbo/registry/client/InstanceAddressURL.getUrlAddress:()Lorg/apache/dubbo/common/url/component/URLAddress;
       7: areturn

  public org.apache.dubbo.common.url.component.URLParam getOverrideParams();
    Code:
       0: aload_0
       1: getfield      #5                  // Field overrideParams:Lorg/apache/dubbo/common/url/component/URLParam;
       4: areturn

  public java.lang.String getRemoteApplication();
    Code:
       0: aload_0
       1: getfield      #2                  // Field originUrl:Lorg/apache/dubbo/registry/client/InstanceAddressURL;
       4: invokevirtual #52                 // Method org/apache/dubbo/registry/client/InstanceAddressURL.getRemoteApplication:()Ljava/lang/String;
       7: areturn

  public java.lang.String getSide();
    Code:
       0: aload_0
       1: getfield      #2                  // Field originUrl:Lorg/apache/dubbo/registry/client/InstanceAddressURL;
       4: invokevirtual #53                 // Method org/apache/dubbo/registry/client/InstanceAddressURL.getSide:()Ljava/lang/String;
       7: areturn

  public org.apache.dubbo.rpc.model.ScopeModel getScopeModel();
    Code:
       0: aload_0
       1: getfield      #2                  // Field originUrl:Lorg/apache/dubbo/registry/client/InstanceAddressURL;
       4: invokevirtual #54                 // Method org/apache/dubbo/registry/client/InstanceAddressURL.getScopeModel:()Lorg/apache/dubbo/rpc/model/ScopeModel;
       7: areturn

  public org.apache.dubbo.rpc.model.FrameworkModel getOrDefaultFrameworkModel();
    Code:
       0: aload_0
       1: getfield      #2                  // Field originUrl:Lorg/apache/dubbo/registry/client/InstanceAddressURL;
       4: invokevirtual #55                 // Method org/apache/dubbo/registry/client/InstanceAddressURL.getOrDefaultFrameworkModel:()Lorg/apache/dubbo/rpc/model/FrameworkModel;
       7: areturn

  public org.apache.dubbo.rpc.model.ApplicationModel getOrDefaultApplicationModel();
    Code:
       0: aload_0
       1: getfield      #2                  // Field originUrl:Lorg/apache/dubbo/registry/client/InstanceAddressURL;
       4: invokevirtual #56                 // Method org/apache/dubbo/registry/client/InstanceAddressURL.getOrDefaultApplicationModel:()Lorg/apache/dubbo/rpc/model/ApplicationModel;
       7: areturn

  public org.apache.dubbo.rpc.model.ApplicationModel getApplicationModel();
    Code:
       0: aload_0
       1: getfield      #2                  // Field originUrl:Lorg/apache/dubbo/registry/client/InstanceAddressURL;
       4: invokevirtual #57                 // Method org/apache/dubbo/registry/client/InstanceAddressURL.getApplicationModel:()Lorg/apache/dubbo/rpc/model/ApplicationModel;
       7: areturn

  public org.apache.dubbo.rpc.model.ModuleModel getOrDefaultModuleModel();
    Code:
       0: aload_0
       1: getfield      #2                  // Field originUrl:Lorg/apache/dubbo/registry/client/InstanceAddressURL;
       4: invokevirtual #58                 // Method org/apache/dubbo/registry/client/InstanceAddressURL.getOrDefaultModuleModel:()Lorg/apache/dubbo/rpc/model/ModuleModel;
       7: areturn

  public org.apache.dubbo.rpc.model.ServiceModel getServiceModel();
    Code:
       0: aload_0
       1: getfield      #2                  // Field originUrl:Lorg/apache/dubbo/registry/client/InstanceAddressURL;
       4: invokevirtual #59                 // Method org/apache/dubbo/registry/client/InstanceAddressURL.getServiceModel:()Lorg/apache/dubbo/rpc/model/ServiceModel;
       7: areturn

  public java.util.Set<java.lang.String> getProviderFirstParams();
    Code:
       0: aload_0
       1: getfield      #2                  // Field originUrl:Lorg/apache/dubbo/registry/client/InstanceAddressURL;
       4: invokevirtual #60                 // Method org/apache/dubbo/registry/client/InstanceAddressURL.getProviderFirstParams:()Ljava/util/Set;
       7: areturn

  public void setProviderFirstParams(java.util.Set<java.lang.String>);
    Code:
       0: aload_0
       1: getfield      #2                  // Field originUrl:Lorg/apache/dubbo/registry/client/InstanceAddressURL;
       4: aload_1
       5: invokevirtual #61                 // Method org/apache/dubbo/registry/client/InstanceAddressURL.setProviderFirstParams:(Ljava/util/Set;)V
       8: return

  public boolean equals(java.lang.Object);
    Code:
       0: aload_0
       1: aload_1
       2: if_acmpne     7
       5: iconst_1
       6: ireturn
       7: aload_1
       8: ifnull        22
      11: aload_0
      12: invokevirtual #62                 // Method java/lang/Object.getClass:()Ljava/lang/Class;
      15: aload_1
      16: invokevirtual #62                 // Method java/lang/Object.getClass:()Ljava/lang/Class;
      19: if_acmpeq     24
      22: iconst_0
      23: ireturn
      24: aload_0
      25: aload_1
      26: invokespecial #63                 // Method org/apache/dubbo/registry/client/InstanceAddressURL.equals:(Ljava/lang/Object;)Z
      29: ifne          34
      32: iconst_0
      33: ireturn
      34: aload_1
      35: checkcast     #39                 // class org/apache/dubbo/registry/client/OverrideInstanceAddressURL
      38: astore_2
      39: aload_0
      40: getfield      #5                  // Field overrideParams:Lorg/apache/dubbo/common/url/component/URLParam;
      43: aload_2
      44: getfield      #5                  // Field overrideParams:Lorg/apache/dubbo/common/url/component/URLParam;
      47: invokestatic  #64                 // Method java/util/Objects.equals:(Ljava/lang/Object;Ljava/lang/Object;)Z
      50: ifeq          71
      53: aload_0
      54: getfield      #2                  // Field originUrl:Lorg/apache/dubbo/registry/client/InstanceAddressURL;
      57: aload_2
      58: getfield      #2                  // Field originUrl:Lorg/apache/dubbo/registry/client/InstanceAddressURL;
      61: invokestatic  #64                 // Method java/util/Objects.equals:(Ljava/lang/Object;Ljava/lang/Object;)Z
      64: ifeq          71
      67: iconst_1
      68: goto          72
      71: iconst_0
      72: ireturn

  public int hashCode();
    Code:
       0: iconst_3
       1: anewarray     #65                 // class java/lang/Object
       4: dup
       5: iconst_0
       6: aload_0
       7: invokespecial #66                 // Method org/apache/dubbo/registry/client/InstanceAddressURL.hashCode:()I
      10: invokestatic  #67                 // Method java/lang/Integer.valueOf:(I)Ljava/lang/Integer;
      13: aastore
      14: dup
      15: iconst_1
      16: aload_0
      17: getfield      #5                  // Field overrideParams:Lorg/apache/dubbo/common/url/component/URLParam;
      20: aastore
      21: dup
      22: iconst_2
      23: aload_0
      24: getfield      #2                  // Field originUrl:Lorg/apache/dubbo/registry/client/InstanceAddressURL;
      27: aastore
      28: invokestatic  #68                 // Method java/util/Objects.hash:([Ljava/lang/Object;)I
      31: ireturn

  public java.lang.String toString();
    Code:
       0: new           #69                 // class java/lang/StringBuilder
       3: dup
       4: invokespecial #70                 // Method java/lang/StringBuilder."<init>":()V
       7: aload_0
       8: getfield      #2                  // Field originUrl:Lorg/apache/dubbo/registry/client/InstanceAddressURL;
      11: invokevirtual #71                 // Method org/apache/dubbo/registry/client/InstanceAddressURL.toString:()Ljava/lang/String;
      14: invokevirtual #72                 // Method java/lang/StringBuilder.append:(Ljava/lang/String;)Ljava/lang/StringBuilder;
      17: ldc           #73                 // String , overrideParams:
      19: invokevirtual #72                 // Method java/lang/StringBuilder.append:(Ljava/lang/String;)Ljava/lang/StringBuilder;
      22: aload_0
      23: getfield      #5                  // Field overrideParams:Lorg/apache/dubbo/common/url/component/URLParam;
      26: invokevirtual #74                 // Method org/apache/dubbo/common/url/component/URLParam.toString:()Ljava/lang/String;
      29: invokevirtual #72                 // Method java/lang/StringBuilder.append:(Ljava/lang/String;)Ljava/lang/StringBuilder;
      32: invokevirtual #75                 // Method java/lang/StringBuilder.toString:()Ljava/lang/String;
      35: areturn

  private java.lang.Object readResolve();
    Code:
       0: new           #39                 // class org/apache/dubbo/registry/client/OverrideInstanceAddressURL
       3: dup
       4: aload_0
       5: getfield      #2                  // Field originUrl:Lorg/apache/dubbo/registry/client/InstanceAddressURL;
       8: aload_0
       9: getfield      #5                  // Field overrideParams:Lorg/apache/dubbo/common/url/component/URLParam;
      12: invokespecial #41                 // Method "<init>":(Lorg/apache/dubbo/registry/client/InstanceAddressURL;Lorg/apache/dubbo/common/url/component/URLParam;)V
      15: areturn

  protected org.apache.dubbo.registry.client.OverrideInstanceAddressURL newURL(org.apache.dubbo.common.url.component.URLAddress, org.apache.dubbo.common.url.component.URLParam);
    Code:
       0: new           #39                 // class org/apache/dubbo/registry/client/OverrideInstanceAddressURL
       3: dup
       4: aload_0
       5: getfield      #2                  // Field originUrl:Lorg/apache/dubbo/registry/client/InstanceAddressURL;
       8: aload_0
       9: getfield      #5                  // Field overrideParams:Lorg/apache/dubbo/common/url/component/URLParam;
      12: invokespecial #41                 // Method "<init>":(Lorg/apache/dubbo/registry/client/InstanceAddressURL;Lorg/apache/dubbo/common/url/component/URLParam;)V
      15: areturn

  protected org.apache.dubbo.common.URL newURL(org.apache.dubbo.common.url.component.URLAddress, org.apache.dubbo.common.url.component.URLParam);
    Code:
       0: aload_0
       1: aload_1
       2: aload_2
       3: invokevirtual #76                 // Method newURL:(Lorg/apache/dubbo/common/url/component/URLAddress;Lorg/apache/dubbo/common/url/component/URLParam;)Lorg/apache/dubbo/registry/client/OverrideInstanceAddressURL;
       6: areturn
}
