Compiled from "ReflectionBasedServiceDiscovery.java"
public class org.apache.dubbo.registry.client.ReflectionBasedServiceDiscovery extends org.apache.dubbo.registry.client.AbstractServiceDiscovery {
  private final org.apache.dubbo.common.logger.ErrorTypeAwareLogger logger;

  private final java.util.concurrent.ScheduledExecutorService echoCheckExecutor;

  private java.lang.String lastMetadataRevision;

  private final java.util.concurrent.ConcurrentHashMap<java.lang.String, java.lang.String> metadataMap;

  private final java.util.concurrent.ConcurrentHashMap<java.lang.String, java.util.List<org.apache.dubbo.registry.client.ServiceInstance>> cachedServiceInstances;

  private final org.apache.dubbo.registry.client.metadata.MetadataServiceDelegation metadataService;

  public java.util.concurrent.ConcurrentMap<java.lang.String, org.apache.dubbo.metadata.MetadataService> metadataServiceProxies;

  private final java.util.concurrent.ConcurrentHashMap<java.lang.String, java.lang.String> serviceInstanceRevisionMap;

  public org.apache.dubbo.registry.client.ReflectionBasedServiceDiscovery(org.apache.dubbo.rpc.model.ApplicationModel, org.apache.dubbo.common.URL);
    Code:
       0: aload_0
       1: aload_1
       2: aload_2
       3: invokespecial #2                  // Method org/apache/dubbo/registry/client/AbstractServiceDiscovery."<init>":(Lorg/apache/dubbo/rpc/model/ApplicationModel;Lorg/apache/dubbo/common/URL;)V
       6: aload_0
       7: aload_0
       8: invokevirtual #3                  // Method java/lang/Object.getClass:()Ljava/lang/Class;
      11: invokestatic  #4                  // Method org/apache/dubbo/common/logger/LoggerFactory.getErrorTypeAwareLogger:(Ljava/lang/Class;)Lorg/apache/dubbo/common/logger/ErrorTypeAwareLogger;
      14: putfield      #5                  // Field logger:Lorg/apache/dubbo/common/logger/ErrorTypeAwareLogger;
      17: aload_0
      18: iconst_1
      19: new           #6                  // class org/apache/dubbo/common/utils/NamedThreadFactory
      22: dup
      23: ldc           #7                  // String Dubbo-Registry-EchoCheck-Consumer
      25: invokespecial #8                  // Method org/apache/dubbo/common/utils/NamedThreadFactory."<init>":(Ljava/lang/String;)V
      28: invokestatic  #9                  // Method java/util/concurrent/Executors.newScheduledThreadPool:(ILjava/util/concurrent/ThreadFactory;)Ljava/util/concurrent/ScheduledExecutorService;
      31: putfield      #10                 // Field echoCheckExecutor:Ljava/util/concurrent/ScheduledExecutorService;
      34: aload_0
      35: new           #11                 // class java/util/concurrent/ConcurrentHashMap
      38: dup
      39: invokespecial #12                 // Method java/util/concurrent/ConcurrentHashMap."<init>":()V
      42: putfield      #13                 // Field metadataMap:Ljava/util/concurrent/ConcurrentHashMap;
      45: aload_0
      46: new           #11                 // class java/util/concurrent/ConcurrentHashMap
      49: dup
      50: invokespecial #12                 // Method java/util/concurrent/ConcurrentHashMap."<init>":()V
      53: putfield      #14                 // Field cachedServiceInstances:Ljava/util/concurrent/ConcurrentHashMap;
      56: aload_0
      57: new           #11                 // class java/util/concurrent/ConcurrentHashMap
      60: dup
      61: invokespecial #12                 // Method java/util/concurrent/ConcurrentHashMap."<init>":()V
      64: putfield      #15                 // Field metadataServiceProxies:Ljava/util/concurrent/ConcurrentMap;
      67: aload_0
      68: new           #11                 // class java/util/concurrent/ConcurrentHashMap
      71: dup
      72: invokespecial #12                 // Method java/util/concurrent/ConcurrentHashMap."<init>":()V
      75: putfield      #16                 // Field serviceInstanceRevisionMap:Ljava/util/concurrent/ConcurrentHashMap;
      78: aload_2
      79: ldc           #18                 // String echoPollingCycle
      81: ldc           #19                 // int 60000
      83: invokevirtual #20                 // Method org/apache/dubbo/common/URL.getParameter:(Ljava/lang/String;I)I
      86: i2l
      87: lstore_3
      88: aload_0
      89: aload_1
      90: invokevirtual #21                 // Method org/apache/dubbo/rpc/model/ApplicationModel.getBeanFactory:()Lorg/apache/dubbo/common/beans/factory/ScopeBeanFactory;
      93: ldc           #22                 // class org/apache/dubbo/registry/client/metadata/MetadataServiceDelegation
      95: invokevirtual #23                 // Method org/apache/dubbo/common/beans/factory/ScopeBeanFactory.getOrRegisterBean:(Ljava/lang/Class;)Ljava/lang/Object;
      98: checkcast     #22                 // class org/apache/dubbo/registry/client/metadata/MetadataServiceDelegation
     101: putfield      #24                 // Field metadataService:Lorg/apache/dubbo/registry/client/metadata/MetadataServiceDelegation;
     104: aload_0
     105: getfield      #10                 // Field echoCheckExecutor:Ljava/util/concurrent/ScheduledExecutorService;
     108: aload_0
     109: invokedynamic #25,  0             // InvokeDynamic #0:run:(Lorg/apache/dubbo/registry/client/ReflectionBasedServiceDiscovery;)Ljava/lang/Runnable;
     114: lload_3
     115: lload_3
     116: getstatic     #26                 // Field java/util/concurrent/TimeUnit.MILLISECONDS:Ljava/util/concurrent/TimeUnit;
     119: invokeinterface #27,  7           // InterfaceMethod java/util/concurrent/ScheduledExecutorService.scheduleAtFixedRate:(Ljava/lang/Runnable;JJLjava/util/concurrent/TimeUnit;)Ljava/util/concurrent/ScheduledFuture;
     124: pop
     125: return

  public void doInitialize(org.apache.dubbo.common.URL);
    Code:
       0: return

  public void doDestroy() throws java.lang.Exception;
    Code:
       0: aload_0
       1: getfield      #13                 // Field metadataMap:Ljava/util/concurrent/ConcurrentHashMap;
       4: invokevirtual #28                 // Method java/util/concurrent/ConcurrentHashMap.clear:()V
       7: aload_0
       8: getfield      #16                 // Field serviceInstanceRevisionMap:Ljava/util/concurrent/ConcurrentHashMap;
      11: invokevirtual #28                 // Method java/util/concurrent/ConcurrentHashMap.clear:()V
      14: aload_0
      15: getfield      #10                 // Field echoCheckExecutor:Ljava/util/concurrent/ScheduledExecutorService;
      18: invokeinterface #29,  1           // InterfaceMethod java/util/concurrent/ScheduledExecutorService.shutdown:()V
      23: return

  private void updateInstanceMetadata(org.apache.dubbo.registry.client.ServiceInstance);
    Code:
       0: aload_1
       1: invokeinterface #30,  1           // InterfaceMethod org/apache/dubbo/registry/client/ServiceInstance.getMetadata:()Ljava/util/Map;
       6: invokestatic  #31                 // Method org/apache/dubbo/common/utils/JsonUtils.toJson:(Ljava/lang/Object;)Ljava/lang/String;
       9: astore_2
      10: aload_2
      11: invokestatic  #32                 // Method org/apache/dubbo/metadata/RevisionResolver.calRevision:(Ljava/lang/String;)Ljava/lang/String;
      14: astore_3
      15: aload_3
      16: aload_0
      17: getfield      #33                 // Field lastMetadataRevision:Ljava/lang/String;
      20: invokevirtual #34                 // Method java/lang/String.equalsIgnoreCase:(Ljava/lang/String;)Z
      23: ifne          172
      26: aload_0
      27: getfield      #5                  // Field logger:Lorg/apache/dubbo/common/logger/ErrorTypeAwareLogger;
      30: invokeinterface #35,  1           // InterfaceMethod org/apache/dubbo/common/logger/ErrorTypeAwareLogger.isDebugEnabled:()Z
      35: ifeq          66
      38: aload_0
      39: getfield      #5                  // Field logger:Lorg/apache/dubbo/common/logger/ErrorTypeAwareLogger;
      42: new           #36                 // class java/lang/StringBuilder
      45: dup
      46: invokespecial #37                 // Method java/lang/StringBuilder."<init>":()V
      49: ldc           #38                 // String Update Service Instance Metadata of DNS registry. Newer metadata:
      51: invokevirtual #39                 // Method java/lang/StringBuilder.append:(Ljava/lang/String;)Ljava/lang/StringBuilder;
      54: aload_2
      55: invokevirtual #39                 // Method java/lang/StringBuilder.append:(Ljava/lang/String;)Ljava/lang/StringBuilder;
      58: invokevirtual #40                 // Method java/lang/StringBuilder.toString:()Ljava/lang/String;
      61: invokeinterface #41,  2           // InterfaceMethod org/apache/dubbo/common/logger/ErrorTypeAwareLogger.debug:(Ljava/lang/String;)V
      66: aload_0
      67: aload_3
      68: putfield      #33                 // Field lastMetadataRevision:Ljava/lang/String;
      71: aload_0
      72: getfield      #24                 // Field metadataService:Lorg/apache/dubbo/registry/client/metadata/MetadataServiceDelegation;
      75: aload_2
      76: invokevirtual #42                 // Method org/apache/dubbo/registry/client/metadata/MetadataServiceDelegation.exportInstanceMetadata:(Ljava/lang/String;)V
      79: aload_0
      80: getfield      #24                 // Field metadataService:Lorg/apache/dubbo/registry/client/metadata/MetadataServiceDelegation;
      83: invokevirtual #43                 // Method org/apache/dubbo/registry/client/metadata/MetadataServiceDelegation.getInstanceMetadataChangedListenerMap:()Ljava/util/Map;
      86: astore        4
      88: aload         4
      90: invokeinterface #44,  1           // InterfaceMethod java/util/Map.entrySet:()Ljava/util/Set;
      95: invokeinterface #45,  1           // InterfaceMethod java/util/Set.iterator:()Ljava/util/Iterator;
     100: astore        5
     102: aload         5
     104: invokeinterface #46,  1           // InterfaceMethod java/util/Iterator.hasNext:()Z
     109: ifeq          172
     112: aload         5
     114: invokeinterface #47,  1           // InterfaceMethod java/util/Iterator.next:()Ljava/lang/Object;
     119: checkcast     #48                 // class java/util/Map$Entry
     122: astore        6
     124: aload         6
     126: invokeinterface #49,  1           // InterfaceMethod java/util/Map$Entry.getValue:()Ljava/lang/Object;
     131: checkcast     #50                 // class org/apache/dubbo/metadata/InstanceMetadataChangedListener
     134: aload_2
     135: invokeinterface #51,  2           // InterfaceMethod org/apache/dubbo/metadata/InstanceMetadataChangedListener.onEvent:(Ljava/lang/String;)V
     140: goto          169
     143: astore        7
     145: aload_0
     146: getfield      #5                  // Field logger:Lorg/apache/dubbo/common/logger/ErrorTypeAwareLogger;
     149: ldc           #53                 // String 1-7
     151: ldc           #54                 // String consumer is offline
     153: ldc           #55                 // String
     155: ldc           #56                 // String Notify to consumer error, removing listener.
     157: invokeinterface #57,  5           // InterfaceMethod org/apache/dubbo/common/logger/ErrorTypeAwareLogger.warn:(Ljava/lang/String;Ljava/lang/String;Ljava/lang/String;Ljava/lang/String;)V
     162: aload         5
     164: invokeinterface #58,  1           // InterfaceMethod java/util/Iterator.remove:()V
     169: goto          102
     172: return
    Exception table:
       from    to  target type
         124   140   143   Class org/apache/dubbo/rpc/RpcException

  public void doRegister(org.apache.dubbo.registry.client.ServiceInstance) throws java.lang.RuntimeException;
    Code:
       0: aload_0
       1: aload_1
       2: invokespecial #59                 // Method updateInstanceMetadata:(Lorg/apache/dubbo/registry/client/ServiceInstance;)V
       5: return

  public void doUnregister(org.apache.dubbo.registry.client.ServiceInstance) throws java.lang.RuntimeException;
    Code:
       0: aload_0
       1: getfield      #24                 // Field metadataService:Lorg/apache/dubbo/registry/client/metadata/MetadataServiceDelegation;
       4: ldc           #55                 // String
       6: invokevirtual #42                 // Method org/apache/dubbo/registry/client/metadata/MetadataServiceDelegation.exportInstanceMetadata:(Ljava/lang/String;)V
       9: aload_0
      10: getfield      #24                 // Field metadataService:Lorg/apache/dubbo/registry/client/metadata/MetadataServiceDelegation;
      13: invokevirtual #43                 // Method org/apache/dubbo/registry/client/metadata/MetadataServiceDelegation.getInstanceMetadataChangedListenerMap:()Ljava/util/Map;
      16: invokedynamic #60,  0             // InvokeDynamic #1:accept:()Ljava/util/function/BiConsumer;
      21: invokeinterface #61,  2           // InterfaceMethod java/util/Map.forEach:(Ljava/util/function/BiConsumer;)V
      26: aload_0
      27: getfield      #24                 // Field metadataService:Lorg/apache/dubbo/registry/client/metadata/MetadataServiceDelegation;
      30: invokevirtual #43                 // Method org/apache/dubbo/registry/client/metadata/MetadataServiceDelegation.getInstanceMetadataChangedListenerMap:()Ljava/util/Map;
      33: invokeinterface #62,  1           // InterfaceMethod java/util/Map.clear:()V
      38: return

  public final void fillServiceInstance(org.apache.dubbo.registry.client.DefaultServiceInstance);
    Code:
       0: aload_1
       1: invokevirtual #63                 // Method org/apache/dubbo/registry/client/DefaultServiceInstance.getAddress:()Ljava/lang/String;
       4: astore_2
       5: aload_0
       6: getfield      #13                 // Field metadataMap:Ljava/util/concurrent/ConcurrentHashMap;
       9: aload_2
      10: invokevirtual #64                 // Method java/util/concurrent/ConcurrentHashMap.containsKey:(Ljava/lang/Object;)Z
      13: ifeq          44
      16: aload_0
      17: getfield      #13                 // Field metadataMap:Ljava/util/concurrent/ConcurrentHashMap;
      20: aload_2
      21: invokevirtual #65                 // Method java/util/concurrent/ConcurrentHashMap.get:(Ljava/lang/Object;)Ljava/lang/Object;
      24: checkcast     #66                 // class java/lang/String
      27: astore_3
      28: aload_1
      29: aload_3
      30: ldc           #67                 // class java/util/Map
      32: invokestatic  #68                 // Method org/apache/dubbo/common/utils/JsonUtils.toJavaObject:(Ljava/lang/String;Ljava/lang/reflect/Type;)Ljava/lang/Object;
      35: checkcast     #67                 // class java/util/Map
      38: invokevirtual #69                 // Method org/apache/dubbo/registry/client/DefaultServiceInstance.setMetadata:(Ljava/util/Map;)V
      41: goto          127
      44: aload_0
      45: aload_1
      46: invokespecial #70                 // Method getMetadataServiceProxy:(Lorg/apache/dubbo/registry/client/ServiceInstance;)Lorg/apache/dubbo/metadata/MetadataService;
      49: astore_3
      50: new           #36                 // class java/lang/StringBuilder
      53: dup
      54: invokespecial #37                 // Method java/lang/StringBuilder."<init>":()V
      57: aload_0
      58: getfield      #71                 // Field registryURL:Lorg/apache/dubbo/common/URL;
      61: invokevirtual #72                 // Method org/apache/dubbo/common/URL.getScopeModel:()Lorg/apache/dubbo/rpc/model/ScopeModel;
      64: invokestatic  #73                 // Method org/apache/dubbo/rpc/model/ScopeModelUtil.getApplicationModel:(Lorg/apache/dubbo/rpc/model/ScopeModel;)Lorg/apache/dubbo/rpc/model/ApplicationModel;
      67: invokevirtual #74                 // Method org/apache/dubbo/rpc/model/ApplicationModel.getApplicationName:()Ljava/lang/String;
      70: invokevirtual #39                 // Method java/lang/StringBuilder.append:(Ljava/lang/String;)Ljava/lang/StringBuilder;
      73: invokestatic  #75                 // Method org/apache/dubbo/common/utils/NetUtils.getLocalHost:()Ljava/lang/String;
      76: invokevirtual #39                 // Method java/lang/StringBuilder.append:(Ljava/lang/String;)Ljava/lang/StringBuilder;
      79: invokevirtual #40                 // Method java/lang/StringBuilder.toString:()Ljava/lang/String;
      82: astore        4
      84: aload_3
      85: aload         4
      87: aload_0
      88: aload_1
      89: aload_2
      90: invokedynamic #76,  0             // InvokeDynamic #2:onEvent:(Lorg/apache/dubbo/registry/client/ReflectionBasedServiceDiscovery;Lorg/apache/dubbo/registry/client/DefaultServiceInstance;Ljava/lang/String;)Lorg/apache/dubbo/metadata/InstanceMetadataChangedListener;
      95: invokeinterface #77,  3           // InterfaceMethod org/apache/dubbo/metadata/MetadataService.getAndListenInstanceMetadata:(Ljava/lang/String;Lorg/apache/dubbo/metadata/InstanceMetadataChangedListener;)Ljava/lang/String;
     100: astore        5
     102: aload_0
     103: getfield      #13                 // Field metadataMap:Ljava/util/concurrent/ConcurrentHashMap;
     106: aload_2
     107: aload         5
     109: invokevirtual #78                 // Method java/util/concurrent/ConcurrentHashMap.put:(Ljava/lang/Object;Ljava/lang/Object;)Ljava/lang/Object;
     112: pop
     113: aload_1
     114: aload         5
     116: ldc           #67                 // class java/util/Map
     118: invokestatic  #68                 // Method org/apache/dubbo/common/utils/JsonUtils.toJavaObject:(Ljava/lang/String;Ljava/lang/reflect/Type;)Ljava/lang/Object;
     121: checkcast     #67                 // class java/util/Map
     124: invokevirtual #69                 // Method org/apache/dubbo/registry/client/DefaultServiceInstance.setMetadata:(Ljava/util/Map;)V
     127: return

  public final void notifyListener(java.lang.String, org.apache.dubbo.registry.client.event.listener.ServiceInstancesChangedListener, java.util.List<org.apache.dubbo.registry.client.ServiceInstance>);
    Code:
       0: aload_3
       1: invokestatic  #31                 // Method org/apache/dubbo/common/utils/JsonUtils.toJson:(Ljava/lang/Object;)Ljava/lang/String;
       4: invokestatic  #32                 // Method org/apache/dubbo/metadata/RevisionResolver.calRevision:(Ljava/lang/String;)Ljava/lang/String;
       7: astore        4
       9: aload         4
      11: aload_0
      12: getfield      #16                 // Field serviceInstanceRevisionMap:Ljava/util/concurrent/ConcurrentHashMap;
      15: aload_1
      16: aload         4
      18: invokevirtual #78                 // Method java/util/concurrent/ConcurrentHashMap.put:(Ljava/lang/Object;Ljava/lang/Object;)Ljava/lang/Object;
      21: checkcast     #66                 // class java/lang/String
      24: invokevirtual #34                 // Method java/lang/String.equalsIgnoreCase:(Ljava/lang/String;)Z
      27: ifne          34
      30: iconst_1
      31: goto          35
      34: iconst_0
      35: istore        5
      37: aload_0
      38: getfield      #5                  // Field logger:Lorg/apache/dubbo/common/logger/ErrorTypeAwareLogger;
      41: invokeinterface #35,  1           // InterfaceMethod org/apache/dubbo/common/logger/ErrorTypeAwareLogger.isDebugEnabled:()Z
      46: ifeq          87
      49: aload_0
      50: getfield      #5                  // Field logger:Lorg/apache/dubbo/common/logger/ErrorTypeAwareLogger;
      53: new           #36                 // class java/lang/StringBuilder
      56: dup
      57: invokespecial #37                 // Method java/lang/StringBuilder."<init>":()V
      60: ldc           #79                 // String Service changed event received (possibly because of DNS polling). Service Instance changed:
      62: invokevirtual #39                 // Method java/lang/StringBuilder.append:(Ljava/lang/String;)Ljava/lang/StringBuilder;
      65: iload         5
      67: invokevirtual #80                 // Method java/lang/StringBuilder.append:(Z)Ljava/lang/StringBuilder;
      70: ldc           #81                 // String  Service Name:
      72: invokevirtual #39                 // Method java/lang/StringBuilder.append:(Ljava/lang/String;)Ljava/lang/StringBuilder;
      75: aload_1
      76: invokevirtual #39                 // Method java/lang/StringBuilder.append:(Ljava/lang/String;)Ljava/lang/StringBuilder;
      79: invokevirtual #40                 // Method java/lang/StringBuilder.toString:()Ljava/lang/String;
      82: invokeinterface #41,  2           // InterfaceMethod org/apache/dubbo/common/logger/ErrorTypeAwareLogger.debug:(Ljava/lang/String;)V
      87: iload         5
      89: ifeq          209
      92: aload_0
      93: getfield      #14                 // Field cachedServiceInstances:Ljava/util/concurrent/ConcurrentHashMap;
      96: aload_1
      97: new           #82                 // class java/util/LinkedList
     100: dup
     101: invokespecial #83                 // Method java/util/LinkedList."<init>":()V
     104: invokevirtual #84                 // Method java/util/concurrent/ConcurrentHashMap.getOrDefault:(Ljava/lang/Object;Ljava/lang/Object;)Ljava/lang/Object;
     107: checkcast     #85                 // class java/util/List
     110: astore        6
     112: new           #86                 // class java/util/HashSet
     115: dup
     116: aload         6
     118: invokeinterface #87,  1           // InterfaceMethod java/util/List.size:()I
     123: aload_3
     124: invokeinterface #87,  1           // InterfaceMethod java/util/List.size:()I
     129: iadd
     130: invokespecial #88                 // Method java/util/HashSet."<init>":(I)V
     133: astore        7
     135: aload         7
     137: aload         6
     139: invokeinterface #89,  2           // InterfaceMethod java/util/Set.addAll:(Ljava/util/Collection;)Z
     144: pop
     145: aload         7
     147: aload_3
     148: invokeinterface #89,  2           // InterfaceMethod java/util/Set.addAll:(Ljava/util/Collection;)Z
     153: pop
     154: aload         6
     156: aload         7
     158: dup
     159: invokevirtual #3                  // Method java/lang/Object.getClass:()Ljava/lang/Class;
     162: pop
     163: invokedynamic #90,  0             // InvokeDynamic #3:accept:(Ljava/util/Set;)Ljava/util/function/Consumer;
     168: invokeinterface #91,  2           // InterfaceMethod java/util/List.forEach:(Ljava/util/function/Consumer;)V
     173: aload         7
     175: aload_0
     176: invokedynamic #92,  0             // InvokeDynamic #4:accept:(Lorg/apache/dubbo/registry/client/ReflectionBasedServiceDiscovery;)Ljava/util/function/Consumer;
     181: invokeinterface #93,  2           // InterfaceMethod java/util/Set.forEach:(Ljava/util/function/Consumer;)V
     186: aload_0
     187: getfield      #14                 // Field cachedServiceInstances:Ljava/util/concurrent/ConcurrentHashMap;
     190: aload_1
     191: aload_3
     192: invokevirtual #78                 // Method java/util/concurrent/ConcurrentHashMap.put:(Ljava/lang/Object;Ljava/lang/Object;)Ljava/lang/Object;
     195: pop
     196: aload_2
     197: new           #94                 // class org/apache/dubbo/registry/client/event/ServiceInstancesChangedEvent
     200: dup
     201: aload_1
     202: aload_3
     203: invokespecial #95                 // Method org/apache/dubbo/registry/client/event/ServiceInstancesChangedEvent."<init>":(Ljava/lang/String;Ljava/util/List;)V
     206: invokevirtual #96                 // Method org/apache/dubbo/registry/client/event/listener/ServiceInstancesChangedListener.onEvent:(Lorg/apache/dubbo/registry/client/event/ServiceInstancesChangedEvent;)V
     209: return

  public java.util.Set<java.lang.String> getServices();
    Code:
       0: invokestatic  #97                 // Method java/util/Collections.emptySet:()Ljava/util/Set;
       3: areturn

  public java.util.List<org.apache.dubbo.registry.client.ServiceInstance> getInstances(java.lang.String) throws java.lang.NullPointerException;
    Code:
       0: invokestatic  #98                 // Method java/util/Collections.emptyList:()Ljava/util/List;
       3: areturn

  private java.lang.String computeKey(org.apache.dubbo.registry.client.ServiceInstance);
    Code:
       0: new           #36                 // class java/lang/StringBuilder
       3: dup
       4: invokespecial #37                 // Method java/lang/StringBuilder."<init>":()V
       7: aload_1
       8: invokeinterface #99,  1           // InterfaceMethod org/apache/dubbo/registry/client/ServiceInstance.getServiceName:()Ljava/lang/String;
      13: invokevirtual #39                 // Method java/lang/StringBuilder.append:(Ljava/lang/String;)Ljava/lang/StringBuilder;
      16: ldc           #100                // String ##
      18: invokevirtual #39                 // Method java/lang/StringBuilder.append:(Ljava/lang/String;)Ljava/lang/StringBuilder;
      21: aload_1
      22: invokeinterface #101,  1          // InterfaceMethod org/apache/dubbo/registry/client/ServiceInstance.getAddress:()Ljava/lang/String;
      27: invokevirtual #39                 // Method java/lang/StringBuilder.append:(Ljava/lang/String;)Ljava/lang/StringBuilder;
      30: ldc           #100                // String ##
      32: invokevirtual #39                 // Method java/lang/StringBuilder.append:(Ljava/lang/String;)Ljava/lang/StringBuilder;
      35: aload_1
      36: invokestatic  #102                // Method org/apache/dubbo/registry/client/metadata/ServiceInstanceMetadataUtils.getExportedServicesRevision:(Lorg/apache/dubbo/registry/client/ServiceInstance;)Ljava/lang/String;
      39: invokevirtual #39                 // Method java/lang/StringBuilder.append:(Ljava/lang/String;)Ljava/lang/StringBuilder;
      42: invokevirtual #40                 // Method java/lang/StringBuilder.toString:()Ljava/lang/String;
      45: areturn

  private synchronized org.apache.dubbo.metadata.MetadataService getMetadataServiceProxy(org.apache.dubbo.registry.client.ServiceInstance);
    Code:
       0: aload_0
       1: getfield      #15                 // Field metadataServiceProxies:Ljava/util/concurrent/ConcurrentMap;
       4: aload_0
       5: aload_1
       6: invokespecial #103                // Method computeKey:(Lorg/apache/dubbo/registry/client/ServiceInstance;)Ljava/lang/String;
       9: aload_1
      10: invokedynamic #104,  0            // InvokeDynamic #5:apply:(Lorg/apache/dubbo/registry/client/ServiceInstance;)Ljava/util/function/Function;
      15: invokestatic  #105                // Method org/apache/dubbo/common/utils/ConcurrentHashMapUtils.computeIfAbsent:(Ljava/util/concurrent/ConcurrentMap;Ljava/lang/Object;Ljava/util/function/Function;)Ljava/lang/Object;
      18: checkcast     #106                // class org/apache/dubbo/metadata/MetadataService
      21: areturn

  private synchronized void destroyMetadataServiceProxy(org.apache.dubbo.registry.client.ServiceInstance);
    Code:
       0: aload_0
       1: aload_1
       2: invokespecial #103                // Method computeKey:(Lorg/apache/dubbo/registry/client/ServiceInstance;)Ljava/lang/String;
       5: astore_2
       6: aload_0
       7: getfield      #15                 // Field metadataServiceProxies:Ljava/util/concurrent/ConcurrentMap;
      10: aload_2
      11: invokeinterface #107,  2          // InterfaceMethod java/util/concurrent/ConcurrentMap.containsKey:(Ljava/lang/Object;)Z
      16: ifeq          46
      19: aload_0
      20: getfield      #15                 // Field metadataServiceProxies:Ljava/util/concurrent/ConcurrentMap;
      23: aload_2
      24: invokeinterface #108,  2          // InterfaceMethod java/util/concurrent/ConcurrentMap.remove:(Ljava/lang/Object;)Ljava/lang/Object;
      29: astore_3
      30: aload_3
      31: instanceof    #109                // class org/apache/dubbo/rpc/service/Destroyable
      34: ifeq          46
      37: aload_3
      38: checkcast     #109                // class org/apache/dubbo/rpc/service/Destroyable
      41: invokeinterface #110,  1          // InterfaceMethod org/apache/dubbo/rpc/service/Destroyable.$destroy:()V
      46: return

  public final java.util.concurrent.ConcurrentHashMap<java.lang.String, java.util.List<org.apache.dubbo.registry.client.ServiceInstance>> getCachedServiceInstances();
    Code:
       0: aload_0
       1: getfield      #14                 // Field cachedServiceInstances:Ljava/util/concurrent/ConcurrentHashMap;
       4: areturn

  private static org.apache.dubbo.metadata.MetadataService lambda$getMetadataServiceProxy$3(org.apache.dubbo.registry.client.ServiceInstance, java.lang.String);
    Code:
       0: aload_0
       1: invokestatic  #111                // Method org/apache/dubbo/registry/client/metadata/MetadataUtils.referProxy:(Lorg/apache/dubbo/registry/client/ServiceInstance;)Lorg/apache/dubbo/registry/client/metadata/MetadataUtils$ProxyHolder;
       4: invokevirtual #112                // Method org/apache/dubbo/registry/client/metadata/MetadataUtils$ProxyHolder.getProxy:()Lorg/apache/dubbo/metadata/MetadataService;
       7: areturn

  private void lambda$fillServiceInstance$2(org.apache.dubbo.registry.client.DefaultServiceInstance, java.lang.String, java.lang.String);
    Code:
       0: aload_0
       1: getfield      #5                  // Field logger:Lorg/apache/dubbo/common/logger/ErrorTypeAwareLogger;
       4: invokeinterface #35,  1           // InterfaceMethod org/apache/dubbo/common/logger/ErrorTypeAwareLogger.isDebugEnabled:()Z
       9: ifeq          44
      12: aload_0
      13: getfield      #5                  // Field logger:Lorg/apache/dubbo/common/logger/ErrorTypeAwareLogger;
      16: new           #36                 // class java/lang/StringBuilder
      19: dup
      20: invokespecial #37                 // Method java/lang/StringBuilder."<init>":()V
      23: ldc           #113                // String Receive callback:
      25: invokevirtual #39                 // Method java/lang/StringBuilder.append:(Ljava/lang/String;)Ljava/lang/StringBuilder;
      28: aload_3
      29: invokevirtual #39                 // Method java/lang/StringBuilder.append:(Ljava/lang/String;)Ljava/lang/StringBuilder;
      32: aload_1
      33: invokevirtual #114                // Method java/lang/StringBuilder.append:(Ljava/lang/Object;)Ljava/lang/StringBuilder;
      36: invokevirtual #40                 // Method java/lang/StringBuilder.toString:()Ljava/lang/String;
      39: invokeinterface #41,  2           // InterfaceMethod org/apache/dubbo/common/logger/ErrorTypeAwareLogger.debug:(Ljava/lang/String;)V
      44: aload_3
      45: invokestatic  #115                // Method org/apache/dubbo/common/utils/StringUtils.isEmpty:(Ljava/lang/String;)Z
      48: ifeq          63
      51: aload_0
      52: getfield      #13                 // Field metadataMap:Ljava/util/concurrent/ConcurrentHashMap;
      55: aload_2
      56: invokevirtual #116                // Method java/util/concurrent/ConcurrentHashMap.remove:(Ljava/lang/Object;)Ljava/lang/Object;
      59: pop
      60: goto          73
      63: aload_0
      64: getfield      #13                 // Field metadataMap:Ljava/util/concurrent/ConcurrentHashMap;
      67: aload_2
      68: aload_3
      69: invokevirtual #78                 // Method java/util/concurrent/ConcurrentHashMap.put:(Ljava/lang/Object;Ljava/lang/Object;)Ljava/lang/Object;
      72: pop
      73: return

  private static void lambda$doUnregister$1(java.lang.String, org.apache.dubbo.metadata.InstanceMetadataChangedListener);
    Code:
       0: aload_1
       1: ldc           #55                 // String
       3: invokeinterface #51,  2           // InterfaceMethod org/apache/dubbo/metadata/InstanceMetadataChangedListener.onEvent:(Ljava/lang/String;)V
       8: return

  private void lambda$new$0();
    Code:
       0: aload_0
       1: getfield      #24                 // Field metadataService:Lorg/apache/dubbo/registry/client/metadata/MetadataServiceDelegation;
       4: invokevirtual #43                 // Method org/apache/dubbo/registry/client/metadata/MetadataServiceDelegation.getInstanceMetadataChangedListenerMap:()Ljava/util/Map;
       7: astore_1
       8: aload_1
       9: invokeinterface #44,  1           // InterfaceMethod java/util/Map.entrySet:()Ljava/util/Set;
      14: invokeinterface #45,  1           // InterfaceMethod java/util/Set.iterator:()Ljava/util/Iterator;
      19: astore_2
      20: aload_2
      21: invokeinterface #46,  1           // InterfaceMethod java/util/Iterator.hasNext:()Z
      26: ifeq          93
      29: aload_2
      30: invokeinterface #47,  1           // InterfaceMethod java/util/Iterator.next:()Ljava/lang/Object;
      35: checkcast     #48                 // class java/util/Map$Entry
      38: astore_3
      39: aload_3
      40: invokeinterface #49,  1           // InterfaceMethod java/util/Map$Entry.getValue:()Ljava/lang/Object;
      45: checkcast     #50                 // class org/apache/dubbo/metadata/InstanceMetadataChangedListener
      48: ldc           #118                // String dubbo
      50: invokeinterface #119,  2          // InterfaceMethod org/apache/dubbo/metadata/InstanceMetadataChangedListener.echo:(Ljava/lang/String;)Ljava/lang/String;
      55: pop
      56: goto          90
      59: astore        4
      61: aload_0
      62: getfield      #5                  // Field logger:Lorg/apache/dubbo/common/logger/ErrorTypeAwareLogger;
      65: invokeinterface #120,  1          // InterfaceMethod org/apache/dubbo/common/logger/ErrorTypeAwareLogger.isInfoEnabled:()Z
      70: ifeq          84
      73: aload_0
      74: getfield      #5                  // Field logger:Lorg/apache/dubbo/common/logger/ErrorTypeAwareLogger;
      77: ldc           #121                // String Send echo message to consumer error. Possible cause: consumer is offline.
      79: invokeinterface #122,  2          // InterfaceMethod org/apache/dubbo/common/logger/ErrorTypeAwareLogger.info:(Ljava/lang/String;)V
      84: aload_2
      85: invokeinterface #58,  1           // InterfaceMethod java/util/Iterator.remove:()V
      90: goto          20
      93: return
    Exception table:
       from    to  target type
          39    56    59   Class org/apache/dubbo/rpc/RpcException
}
