Compiled from "RegistryClusterIdentifier.java"
public interface org.apache.dubbo.registry.client.RegistryClusterIdentifier {
  public abstract java.lang.String providerKey(org.apache.dubbo.common.URL);

  public abstract java.lang.String consumerKey(org.apache.dubbo.common.URL);

  public static org.apache.dubbo.registry.client.RegistryClusterIdentifier getExtension(org.apache.dubbo.common.URL);
    Code:
       0: ldc           #2                  // class org/apache/dubbo/registry/client/RegistryClusterIdentifier
       2: aload_0
       3: invokevirtual #3                  // Method org/apache/dubbo/common/URL.getScopeModel:()Lorg/apache/dubbo/rpc/model/ScopeModel;
       6: invokestatic  #4                  // Method org/apache/dubbo/rpc/model/ScopeModelUtil.getExtensionLoader:(Ljava/lang/Class;Lorg/apache/dubbo/rpc/model/ScopeModel;)Lorg/apache/dubbo/common/extension/ExtensionLoader;
       9: astore_1
      10: aload_1
      11: aload_0
      12: ldc           #5                  // String registry-cluster-type
      14: ldc           #6                  // String default
      16: invokevirtual #7                  // Method org/apache/dubbo/common/URL.getParameter:(Ljava/lang/String;Ljava/lang/String;)Ljava/lang/String;
      19: invokevirtual #8                  // Method org/apache/dubbo/common/extension/ExtensionLoader.getExtension:(Ljava/lang/String;)Ljava/lang/Object;
      22: checkcast     #2                  // class org/apache/dubbo/registry/client/RegistryClusterIdentifier
      25: areturn
}
