Compiled from "ServiceDiscoveryRegistryDirectory.java"
public final class org.apache.dubbo.registry.client.ServiceDiscoveryRegistryDirectory$InstanceWrappedInvoker<T> implements org.apache.dubbo.rpc.Invoker<T> {
  private final org.apache.dubbo.rpc.Invoker<T> originInvoker;

  private final org.apache.dubbo.common.URL newConsumerUrl;

  private final org.apache.dubbo.common.ProtocolServiceKey protocolServiceKey;

  public org.apache.dubbo.registry.client.ServiceDiscoveryRegistryDirectory$InstanceWrappedInvoker(org.apache.dubbo.rpc.Invoker<T>, org.apache.dubbo.common.URL, org.apache.dubbo.common.ProtocolServiceKey);
    Code:
       0: aload_0
       1: invokespecial #1                  // Method java/lang/Object."<init>":()V
       4: aload_0
       5: aload_1
       6: putfield      #2                  // Field originInvoker:Lorg/apache/dubbo/rpc/Invoker;
       9: aload_0
      10: aload_2
      11: putfield      #3                  // Field newConsumerUrl:Lorg/apache/dubbo/common/URL;
      14: aload_0
      15: aload_3
      16: putfield      #4                  // Field protocolServiceKey:Lorg/apache/dubbo/common/ProtocolServiceKey;
      19: return

  public java.lang.Class<T> getInterface();
    Code:
       0: aload_0
       1: getfield      #2                  // Field originInvoker:Lorg/apache/dubbo/rpc/Invoker;
       4: invokeinterface #5,  1            // InterfaceMethod org/apache/dubbo/rpc/Invoker.getInterface:()Ljava/lang/Class;
       9: areturn

  public org.apache.dubbo.rpc.Result invoke(org.apache.dubbo.rpc.Invocation) throws org.apache.dubbo.rpc.RpcException;
    Code:
       0: invokestatic  #6                  // Method org/apache/dubbo/rpc/RpcContext.getServiceContext:()Lorg/apache/dubbo/rpc/RpcServiceContext;
       3: aload_0
       4: getfield      #3                  // Field newConsumerUrl:Lorg/apache/dubbo/common/URL;
       7: invokevirtual #7                  // Method org/apache/dubbo/rpc/RpcServiceContext.setConsumerUrl:(Lorg/apache/dubbo/common/URL;)V
      10: new           #8                  // class org/apache/dubbo/rpc/RpcInvocation
      13: dup
      14: aload_1
      15: invokeinterface #9,  1            // InterfaceMethod org/apache/dubbo/rpc/Invocation.getTargetServiceUniqueName:()Ljava/lang/String;
      20: aload_1
      21: invokeinterface #10,  1           // InterfaceMethod org/apache/dubbo/rpc/Invocation.getServiceModel:()Lorg/apache/dubbo/rpc/model/ServiceModel;
      26: aload_1
      27: invokeinterface #11,  1           // InterfaceMethod org/apache/dubbo/rpc/Invocation.getMethodName:()Ljava/lang/String;
      32: aload_1
      33: invokeinterface #12,  1           // InterfaceMethod org/apache/dubbo/rpc/Invocation.getServiceName:()Ljava/lang/String;
      38: aload_0
      39: getfield      #4                  // Field protocolServiceKey:Lorg/apache/dubbo/common/ProtocolServiceKey;
      42: invokevirtual #13                 // Method org/apache/dubbo/common/ProtocolServiceKey.toString:()Ljava/lang/String;
      45: aload_1
      46: invokeinterface #14,  1           // InterfaceMethod org/apache/dubbo/rpc/Invocation.getParameterTypes:()[Ljava/lang/Class;
      51: aload_1
      52: invokeinterface #15,  1           // InterfaceMethod org/apache/dubbo/rpc/Invocation.getArguments:()[Ljava/lang/Object;
      57: aload_1
      58: invokeinterface #16,  1           // InterfaceMethod org/apache/dubbo/rpc/Invocation.getObjectAttachments:()Ljava/util/Map;
      63: aload_1
      64: invokeinterface #17,  1           // InterfaceMethod org/apache/dubbo/rpc/Invocation.getInvoker:()Lorg/apache/dubbo/rpc/Invoker;
      69: aload_1
      70: invokeinterface #18,  1           // InterfaceMethod org/apache/dubbo/rpc/Invocation.getAttributes:()Ljava/util/Map;
      75: aload_1
      76: instanceof    #8                  // class org/apache/dubbo/rpc/RpcInvocation
      79: ifeq          92
      82: aload_1
      83: checkcast     #8                  // class org/apache/dubbo/rpc/RpcInvocation
      86: invokevirtual #19                 // Method org/apache/dubbo/rpc/RpcInvocation.getInvokeMode:()Lorg/apache/dubbo/rpc/InvokeMode;
      89: goto          93
      92: aconst_null
      93: invokespecial #20                 // Method org/apache/dubbo/rpc/RpcInvocation."<init>":(Ljava/lang/String;Lorg/apache/dubbo/rpc/model/ServiceModel;Ljava/lang/String;Ljava/lang/String;Ljava/lang/String;[Ljava/lang/Class;[Ljava/lang/Object;Ljava/util/Map;Lorg/apache/dubbo/rpc/Invoker;Ljava/util/Map;Lorg/apache/dubbo/rpc/InvokeMode;)V
      96: astore_2
      97: aload_2
      98: ldc           #22                 // String group
     100: aload_0
     101: getfield      #4                  // Field protocolServiceKey:Lorg/apache/dubbo/common/ProtocolServiceKey;
     104: invokevirtual #23                 // Method org/apache/dubbo/common/ProtocolServiceKey.getGroup:()Ljava/lang/String;
     107: invokevirtual #24                 // Method org/apache/dubbo/rpc/RpcInvocation.setObjectAttachment:(Ljava/lang/String;Ljava/lang/Object;)V
     110: aload_2
     111: ldc           #25                 // String version
     113: aload_0
     114: getfield      #4                  // Field protocolServiceKey:Lorg/apache/dubbo/common/ProtocolServiceKey;
     117: invokevirtual #26                 // Method org/apache/dubbo/common/ProtocolServiceKey.getVersion:()Ljava/lang/String;
     120: invokevirtual #24                 // Method org/apache/dubbo/rpc/RpcInvocation.setObjectAttachment:(Ljava/lang/String;Ljava/lang/Object;)V
     123: aload_0
     124: getfield      #2                  // Field originInvoker:Lorg/apache/dubbo/rpc/Invoker;
     127: aload_2
     128: invokeinterface #27,  2           // InterfaceMethod org/apache/dubbo/rpc/Invoker.invoke:(Lorg/apache/dubbo/rpc/Invocation;)Lorg/apache/dubbo/rpc/Result;
     133: areturn

  public org.apache.dubbo.common.URL getUrl();
    Code:
       0: invokestatic  #6                  // Method org/apache/dubbo/rpc/RpcContext.getServiceContext:()Lorg/apache/dubbo/rpc/RpcServiceContext;
       3: aload_0
       4: getfield      #3                  // Field newConsumerUrl:Lorg/apache/dubbo/common/URL;
       7: invokevirtual #7                  // Method org/apache/dubbo/rpc/RpcServiceContext.setConsumerUrl:(Lorg/apache/dubbo/common/URL;)V
      10: aload_0
      11: getfield      #2                  // Field originInvoker:Lorg/apache/dubbo/rpc/Invoker;
      14: invokeinterface #28,  1           // InterfaceMethod org/apache/dubbo/rpc/Invoker.getUrl:()Lorg/apache/dubbo/common/URL;
      19: areturn

  public boolean isAvailable();
    Code:
       0: invokestatic  #6                  // Method org/apache/dubbo/rpc/RpcContext.getServiceContext:()Lorg/apache/dubbo/rpc/RpcServiceContext;
       3: aload_0
       4: getfield      #3                  // Field newConsumerUrl:Lorg/apache/dubbo/common/URL;
       7: invokevirtual #7                  // Method org/apache/dubbo/rpc/RpcServiceContext.setConsumerUrl:(Lorg/apache/dubbo/common/URL;)V
      10: aload_0
      11: getfield      #2                  // Field originInvoker:Lorg/apache/dubbo/rpc/Invoker;
      14: invokeinterface #29,  1           // InterfaceMethod org/apache/dubbo/rpc/Invoker.isAvailable:()Z
      19: ireturn

  public void destroy();
    Code:
       0: invokestatic  #6                  // Method org/apache/dubbo/rpc/RpcContext.getServiceContext:()Lorg/apache/dubbo/rpc/RpcServiceContext;
       3: aload_0
       4: getfield      #3                  // Field newConsumerUrl:Lorg/apache/dubbo/common/URL;
       7: invokevirtual #7                  // Method org/apache/dubbo/rpc/RpcServiceContext.setConsumerUrl:(Lorg/apache/dubbo/common/URL;)V
      10: aload_0
      11: getfield      #2                  // Field originInvoker:Lorg/apache/dubbo/rpc/Invoker;
      14: invokeinterface #30,  1           // InterfaceMethod org/apache/dubbo/rpc/Invoker.destroy:()V
      19: return
}
