Compiled from "ServiceDiscoveryRegistryDirectory.java"
public final class org.apache.dubbo.registry.client.ServiceDiscoveryRegistryDirectory$ProtocolServiceKeyWithAddress extends org.apache.dubbo.common.ProtocolServiceKey {
  private final java.lang.String address;

  public org.apache.dubbo.registry.client.ServiceDiscoveryRegistryDirectory$ProtocolServiceKeyWithAddress(org.apache.dubbo.common.ProtocolServiceKey, java.lang.String);
    Code:
       0: aload_0
       1: aload_1
       2: invokevirtual #1                  // Method org/apache/dubbo/common/ProtocolServiceKey.getInterfaceName:()Ljava/lang/String;
       5: aload_1
       6: invokevirtual #2                  // Method org/apache/dubbo/common/ProtocolServiceKey.getVersion:()Ljava/lang/String;
       9: aload_1
      10: invokevirtual #3                  // Method org/apache/dubbo/common/ProtocolServiceKey.getGroup:()Ljava/lang/String;
      13: aload_1
      14: invokevirtual #4                  // Method org/apache/dubbo/common/ProtocolServiceKey.getProtocol:()Ljava/lang/String;
      17: invokespecial #5                  // Method org/apache/dubbo/common/ProtocolServiceKey."<init>":(Ljava/lang/String;Ljava/lang/String;Ljava/lang/String;Ljava/lang/String;)V
      20: aload_0
      21: aload_2
      22: putfield      #6                  // Field address:Ljava/lang/String;
      25: return

  public java.lang.String getAddress();
    Code:
       0: aload_0
       1: getfield      #6                  // Field address:Ljava/lang/String;
       4: areturn

  public boolean equals(java.lang.Object);
    Code:
       0: aload_0
       1: aload_1
       2: if_acmpne     7
       5: iconst_1
       6: ireturn
       7: aload_1
       8: ifnull        22
      11: aload_0
      12: invokevirtual #7                  // Method java/lang/Object.getClass:()Ljava/lang/Class;
      15: aload_1
      16: invokevirtual #7                  // Method java/lang/Object.getClass:()Ljava/lang/Class;
      19: if_acmpeq     24
      22: iconst_0
      23: ireturn
      24: aload_0
      25: aload_1
      26: invokespecial #8                  // Method org/apache/dubbo/common/ProtocolServiceKey.equals:(Ljava/lang/Object;)Z
      29: ifne          34
      32: iconst_0
      33: ireturn
      34: aload_1
      35: checkcast     #9                  // class org/apache/dubbo/registry/client/ServiceDiscoveryRegistryDirectory$ProtocolServiceKeyWithAddress
      38: astore_2
      39: aload_0
      40: getfield      #6                  // Field address:Ljava/lang/String;
      43: aload_2
      44: getfield      #6                  // Field address:Ljava/lang/String;
      47: invokestatic  #10                 // Method java/util/Objects.equals:(Ljava/lang/Object;Ljava/lang/Object;)Z
      50: ireturn

  public int hashCode();
    Code:
       0: iconst_2
       1: anewarray     #11                 // class java/lang/Object
       4: dup
       5: iconst_0
       6: aload_0
       7: invokespecial #12                 // Method org/apache/dubbo/common/ProtocolServiceKey.hashCode:()I
      10: invokestatic  #13                 // Method java/lang/Integer.valueOf:(I)Ljava/lang/Integer;
      13: aastore
      14: dup
      15: iconst_1
      16: aload_0
      17: getfield      #6                  // Field address:Ljava/lang/String;
      20: aastore
      21: invokestatic  #14                 // Method java/util/Objects.hash:([Ljava/lang/Object;)I
      24: ireturn
}
