Compiled from "ServiceDiscoveryFactory.java"
public interface org.apache.dubbo.registry.client.ServiceDiscoveryFactory {
  public abstract org.apache.dubbo.registry.client.ServiceDiscovery getServiceDiscovery(org.apache.dubbo.common.URL);

  public static org.apache.dubbo.registry.client.ServiceDiscoveryFactory getExtension(org.apache.dubbo.common.URL);
    Code:
       0: aload_0
       1: invokevirtual #1                  // Method org/apache/dubbo/common/URL.getProtocol:()Ljava/lang/String;
       4: astore_1
       5: aload_0
       6: invokevirtual #2                  // Method org/apache/dubbo/common/URL.getOrDefaultApplicationModel:()Lorg/apache/dubbo/rpc/model/ApplicationModel;
       9: ldc           #3                  // class org/apache/dubbo/registry/client/ServiceDiscoveryFactory
      11: invokevirtual #4                  // Method org/apache/dubbo/rpc/model/ApplicationModel.getExtensionLoader:(Ljava/lang/Class;)Lorg/apache/dubbo/common/extension/ExtensionLoader;
      14: astore_2
      15: aload_2
      16: aload_1
      17: invokevirtual #5                  // Method org/apache/dubbo/common/extension/ExtensionLoader.getOrDefaultExtension:(Ljava/lang/String;)Ljava/lang/Object;
      20: checkcast     #3                  // class org/apache/dubbo/registry/client/ServiceDiscoveryFactory
      23: areturn
}
