Compiled from "ServiceDiscoveryRegistry.java"
public class org.apache.dubbo.registry.client.ServiceDiscoveryRegistry extends org.apache.dubbo.registry.support.FailbackRegistry {
  protected final org.apache.dubbo.common.logger.ErrorTypeAwareLogger logger;

  private final org.apache.dubbo.registry.client.ServiceDiscovery serviceDiscovery;

  private final org.apache.dubbo.metadata.AbstractServiceNameMapping serviceNameMapping;

  private final java.util.Map<java.lang.String, org.apache.dubbo.registry.client.event.listener.ServiceInstancesChangedListener> serviceListeners;

  private final java.util.Map<java.lang.String, org.apache.dubbo.metadata.MappingListener> mappingListeners;

  private final java.util.concurrent.ConcurrentMap<java.lang.String, java.util.concurrent.locks.Lock> appSubscriptionLocks;

  public org.apache.dubbo.registry.client.ServiceDiscoveryRegistry(org.apache.dubbo.common.URL, org.apache.dubbo.rpc.model.ApplicationModel);
    Code:
       0: aload_0
       1: aload_1
       2: invokespecial #5                  // Method org/apache/dubbo/registry/support/FailbackRegistry."<init>":(Lorg/apache/dubbo/common/URL;)V
       5: aload_0
       6: aload_0
       7: invokevirtual #6                  // Method java/lang/Object.getClass:()Ljava/lang/Class;
      10: invokestatic  #7                  // Method org/apache/dubbo/common/logger/LoggerFactory.getErrorTypeAwareLogger:(Ljava/lang/Class;)Lorg/apache/dubbo/common/logger/ErrorTypeAwareLogger;
      13: putfield      #8                  // Field logger:Lorg/apache/dubbo/common/logger/ErrorTypeAwareLogger;
      16: aload_0
      17: new           #9                  // class java/util/concurrent/ConcurrentHashMap
      20: dup
      21: invokespecial #10                 // Method java/util/concurrent/ConcurrentHashMap."<init>":()V
      24: putfield      #11                 // Field serviceListeners:Ljava/util/Map;
      27: aload_0
      28: new           #9                  // class java/util/concurrent/ConcurrentHashMap
      31: dup
      32: invokespecial #10                 // Method java/util/concurrent/ConcurrentHashMap."<init>":()V
      35: putfield      #12                 // Field mappingListeners:Ljava/util/Map;
      38: aload_0
      39: new           #9                  // class java/util/concurrent/ConcurrentHashMap
      42: dup
      43: invokespecial #10                 // Method java/util/concurrent/ConcurrentHashMap."<init>":()V
      46: putfield      #13                 // Field appSubscriptionLocks:Ljava/util/concurrent/ConcurrentMap;
      49: aload_0
      50: aload_0
      51: aload_1
      52: invokevirtual #14                 // Method createServiceDiscovery:(Lorg/apache/dubbo/common/URL;)Lorg/apache/dubbo/registry/client/ServiceDiscovery;
      55: putfield      #15                 // Field serviceDiscovery:Lorg/apache/dubbo/registry/client/ServiceDiscovery;
      58: aload_0
      59: aload_1
      60: invokevirtual #16                 // Method org/apache/dubbo/common/URL.getScopeModel:()Lorg/apache/dubbo/rpc/model/ScopeModel;
      63: invokestatic  #17                 // InterfaceMethod org/apache/dubbo/metadata/ServiceNameMapping.getDefaultExtension:(Lorg/apache/dubbo/rpc/model/ScopeModel;)Lorg/apache/dubbo/metadata/ServiceNameMapping;
      66: checkcast     #18                 // class org/apache/dubbo/metadata/AbstractServiceNameMapping
      69: putfield      #4                  // Field serviceNameMapping:Lorg/apache/dubbo/metadata/AbstractServiceNameMapping;
      72: aload_0
      73: aload_2
      74: putfield      #19                 // Field org/apache/dubbo/registry/support/FailbackRegistry.applicationModel:Lorg/apache/dubbo/rpc/model/ApplicationModel;
      77: return

  protected org.apache.dubbo.registry.client.ServiceDiscoveryRegistry(org.apache.dubbo.common.URL, org.apache.dubbo.registry.client.ServiceDiscovery, org.apache.dubbo.metadata.ServiceNameMapping);
    Code:
       0: aload_0
       1: aload_1
       2: invokespecial #5                  // Method org/apache/dubbo/registry/support/FailbackRegistry."<init>":(Lorg/apache/dubbo/common/URL;)V
       5: aload_0
       6: aload_0
       7: invokevirtual #6                  // Method java/lang/Object.getClass:()Ljava/lang/Class;
      10: invokestatic  #7                  // Method org/apache/dubbo/common/logger/LoggerFactory.getErrorTypeAwareLogger:(Ljava/lang/Class;)Lorg/apache/dubbo/common/logger/ErrorTypeAwareLogger;
      13: putfield      #8                  // Field logger:Lorg/apache/dubbo/common/logger/ErrorTypeAwareLogger;
      16: aload_0
      17: new           #9                  // class java/util/concurrent/ConcurrentHashMap
      20: dup
      21: invokespecial #10                 // Method java/util/concurrent/ConcurrentHashMap."<init>":()V
      24: putfield      #11                 // Field serviceListeners:Ljava/util/Map;
      27: aload_0
      28: new           #9                  // class java/util/concurrent/ConcurrentHashMap
      31: dup
      32: invokespecial #10                 // Method java/util/concurrent/ConcurrentHashMap."<init>":()V
      35: putfield      #12                 // Field mappingListeners:Ljava/util/Map;
      38: aload_0
      39: new           #9                  // class java/util/concurrent/ConcurrentHashMap
      42: dup
      43: invokespecial #10                 // Method java/util/concurrent/ConcurrentHashMap."<init>":()V
      46: putfield      #13                 // Field appSubscriptionLocks:Ljava/util/concurrent/ConcurrentMap;
      49: aload_0
      50: aload_2
      51: putfield      #15                 // Field serviceDiscovery:Lorg/apache/dubbo/registry/client/ServiceDiscovery;
      54: aload_0
      55: aload_3
      56: checkcast     #18                 // class org/apache/dubbo/metadata/AbstractServiceNameMapping
      59: putfield      #4                  // Field serviceNameMapping:Lorg/apache/dubbo/metadata/AbstractServiceNameMapping;
      62: return

  public org.apache.dubbo.registry.client.ServiceDiscovery getServiceDiscovery();
    Code:
       0: aload_0
       1: getfield      #15                 // Field serviceDiscovery:Lorg/apache/dubbo/registry/client/ServiceDiscovery;
       4: areturn

  protected org.apache.dubbo.registry.client.ServiceDiscovery createServiceDiscovery(org.apache.dubbo.common.URL);
    Code:
       0: aload_0
       1: aload_1
       2: ldc           #20                 // String interface
       4: ldc           #21                 // class org/apache/dubbo/registry/client/ServiceDiscovery
       6: invokevirtual #22                 // Method java/lang/Class.getName:()Ljava/lang/String;
       9: invokevirtual #23                 // Method org/apache/dubbo/common/URL.addParameter:(Ljava/lang/String;Ljava/lang/String;)Lorg/apache/dubbo/common/URL;
      12: ldc           #24                 // String registry-type
      14: invokevirtual #25                 // Method org/apache/dubbo/common/URL.removeParameter:(Ljava/lang/String;)Lorg/apache/dubbo/common/URL;
      17: invokespecial #26                 // Method getServiceDiscovery:(Lorg/apache/dubbo/common/URL;)Lorg/apache/dubbo/registry/client/ServiceDiscovery;
      20: areturn

  private org.apache.dubbo.registry.client.ServiceDiscovery getServiceDiscovery(org.apache.dubbo.common.URL);
    Code:
       0: aload_1
       1: invokestatic  #27                 // InterfaceMethod org/apache/dubbo/registry/client/ServiceDiscoveryFactory.getExtension:(Lorg/apache/dubbo/common/URL;)Lorg/apache/dubbo/registry/client/ServiceDiscoveryFactory;
       4: astore_2
       5: aload_2
       6: aload_1
       7: invokeinterface #28,  2           // InterfaceMethod org/apache/dubbo/registry/client/ServiceDiscoveryFactory.getServiceDiscovery:(Lorg/apache/dubbo/common/URL;)Lorg/apache/dubbo/registry/client/ServiceDiscovery;
      12: areturn

  protected boolean shouldRegister(org.apache.dubbo.common.URL);
    Code:
       0: aload_1
       1: invokevirtual #29                 // Method org/apache/dubbo/common/URL.getSide:()Ljava/lang/String;
       4: astore_2
       5: ldc           #30                 // String provider
       7: aload_2
       8: invokevirtual #31                 // Method java/lang/String.equals:(Ljava/lang/Object;)Z
      11: istore_3
      12: iload_3
      13: ifne          50
      16: aload_0
      17: getfield      #8                  // Field logger:Lorg/apache/dubbo/common/logger/ErrorTypeAwareLogger;
      20: invokeinterface #32,  1           // InterfaceMethod org/apache/dubbo/common/logger/ErrorTypeAwareLogger.isDebugEnabled:()Z
      25: ifeq          50
      28: aload_0
      29: getfield      #8                  // Field logger:Lorg/apache/dubbo/common/logger/ErrorTypeAwareLogger;
      32: ldc           #33                 // String The URL[%s] should not be registered.
      34: iconst_1
      35: anewarray     #34                 // class java/lang/Object
      38: dup
      39: iconst_0
      40: aload_1
      41: aastore
      42: invokestatic  #35                 // Method java/lang/String.format:(Ljava/lang/String;[Ljava/lang/Object;)Ljava/lang/String;
      45: invokeinterface #36,  2           // InterfaceMethod org/apache/dubbo/common/logger/ErrorTypeAwareLogger.debug:(Ljava/lang/String;)V
      50: aload_0
      51: aload_1
      52: invokevirtual #37                 // Method acceptable:(Lorg/apache/dubbo/common/URL;)Z
      55: ifne          105
      58: aload_0
      59: getfield      #8                  // Field logger:Lorg/apache/dubbo/common/logger/ErrorTypeAwareLogger;
      62: new           #38                 // class java/lang/StringBuilder
      65: dup
      66: invokespecial #39                 // Method java/lang/StringBuilder."<init>":()V
      69: ldc           #40                 // String URL
      71: invokevirtual #41                 // Method java/lang/StringBuilder.append:(Ljava/lang/String;)Ljava/lang/StringBuilder;
      74: aload_1
      75: invokevirtual #42                 // Method java/lang/StringBuilder.append:(Ljava/lang/Object;)Ljava/lang/StringBuilder;
      78: ldc           #43                 // String  will not be registered to Registry. Registry
      80: invokevirtual #41                 // Method java/lang/StringBuilder.append:(Ljava/lang/String;)Ljava/lang/StringBuilder;
      83: aload_0
      84: invokevirtual #44                 // Method getUrl:()Lorg/apache/dubbo/common/URL;
      87: invokevirtual #42                 // Method java/lang/StringBuilder.append:(Ljava/lang/Object;)Ljava/lang/StringBuilder;
      90: ldc           #45                 // String  does not accept service of this protocol type.
      92: invokevirtual #41                 // Method java/lang/StringBuilder.append:(Ljava/lang/String;)Ljava/lang/StringBuilder;
      95: invokevirtual #46                 // Method java/lang/StringBuilder.toString:()Ljava/lang/String;
      98: invokeinterface #47,  2           // InterfaceMethod org/apache/dubbo/common/logger/ErrorTypeAwareLogger.info:(Ljava/lang/String;)V
     103: iconst_0
     104: ireturn
     105: iload_3
     106: ireturn

  protected boolean shouldSubscribe(org.apache.dubbo.common.URL);
    Code:
       0: aload_0
       1: aload_1
       2: invokevirtual #48                 // Method shouldRegister:(Lorg/apache/dubbo/common/URL;)Z
       5: ifne          12
       8: iconst_1
       9: goto          13
      12: iconst_0
      13: ireturn

  public final void register(org.apache.dubbo.common.URL);
    Code:
       0: aload_0
       1: aload_1
       2: invokevirtual #48                 // Method shouldRegister:(Lorg/apache/dubbo/common/URL;)Z
       5: ifne          9
       8: return
       9: aload_0
      10: aload_1
      11: invokevirtual #49                 // Method doRegister:(Lorg/apache/dubbo/common/URL;)V
      14: return

  public void doRegister(org.apache.dubbo.common.URL);
    Code:
       0: aload_0
       1: aload_1
       2: invokespecial #50                 // Method addRegistryClusterKey:(Lorg/apache/dubbo/common/URL;)Lorg/apache/dubbo/common/URL;
       5: astore_1
       6: aload_0
       7: getfield      #15                 // Field serviceDiscovery:Lorg/apache/dubbo/registry/client/ServiceDiscovery;
      10: aload_1
      11: invokeinterface #51,  2           // InterfaceMethod org/apache/dubbo/registry/client/ServiceDiscovery.register:(Lorg/apache/dubbo/common/URL;)V
      16: return

  public final void unregister(org.apache.dubbo.common.URL);
    Code:
       0: aload_0
       1: aload_1
       2: invokevirtual #48                 // Method shouldRegister:(Lorg/apache/dubbo/common/URL;)Z
       5: ifne          9
       8: return
       9: aload_0
      10: aload_1
      11: invokevirtual #52                 // Method doUnregister:(Lorg/apache/dubbo/common/URL;)V
      14: return

  public void doUnregister(org.apache.dubbo.common.URL);
    Code:
       0: aload_0
       1: aload_1
       2: invokespecial #50                 // Method addRegistryClusterKey:(Lorg/apache/dubbo/common/URL;)Lorg/apache/dubbo/common/URL;
       5: astore_1
       6: aload_0
       7: getfield      #15                 // Field serviceDiscovery:Lorg/apache/dubbo/registry/client/ServiceDiscovery;
      10: aload_1
      11: invokeinterface #53,  2           // InterfaceMethod org/apache/dubbo/registry/client/ServiceDiscovery.unregister:(Lorg/apache/dubbo/common/URL;)V
      16: return

  public final void subscribe(org.apache.dubbo.common.URL, org.apache.dubbo.registry.NotifyListener);
    Code:
       0: aload_0
       1: aload_1
       2: invokevirtual #54                 // Method shouldSubscribe:(Lorg/apache/dubbo/common/URL;)Z
       5: ifne          9
       8: return
       9: aload_0
      10: aload_1
      11: aload_2
      12: invokevirtual #55                 // Method doSubscribe:(Lorg/apache/dubbo/common/URL;Lorg/apache/dubbo/registry/NotifyListener;)V
      15: return

  public void doSubscribe(org.apache.dubbo.common.URL, org.apache.dubbo.registry.NotifyListener);
    Code:
       0: aload_0
       1: aload_1
       2: invokespecial #50                 // Method addRegistryClusterKey:(Lorg/apache/dubbo/common/URL;)Lorg/apache/dubbo/common/URL;
       5: astore_1
       6: aload_0
       7: getfield      #15                 // Field serviceDiscovery:Lorg/apache/dubbo/registry/client/ServiceDiscovery;
      10: aload_1
      11: aload_2
      12: invokeinterface #56,  3           // InterfaceMethod org/apache/dubbo/registry/client/ServiceDiscovery.subscribe:(Lorg/apache/dubbo/common/URL;Lorg/apache/dubbo/registry/NotifyListener;)V
      17: aload_1
      18: invokestatic  #57                 // InterfaceMethod org/apache/dubbo/metadata/ServiceNameMapping.getMappingByUrl:(Lorg/apache/dubbo/common/URL;)Ljava/util/Set;
      21: astore_3
      22: aload_1
      23: invokestatic  #58                 // InterfaceMethod org/apache/dubbo/metadata/ServiceNameMapping.buildMappingKey:(Lorg/apache/dubbo/common/URL;)Ljava/lang/String;
      26: astore        4
      28: aload_3
      29: ifnonnull     217
      32: aload_0
      33: getfield      #4                  // Field serviceNameMapping:Lorg/apache/dubbo/metadata/AbstractServiceNameMapping;
      36: aload         4
      38: invokevirtual #59                 // Method org/apache/dubbo/metadata/AbstractServiceNameMapping.getMappingLock:(Ljava/lang/String;)Ljava/util/concurrent/locks/Lock;
      41: astore        5
      43: aload         5
      45: invokeinterface #60,  1           // InterfaceMethod java/util/concurrent/locks/Lock.lock:()V
      50: aload_0
      51: getfield      #4                  // Field serviceNameMapping:Lorg/apache/dubbo/metadata/AbstractServiceNameMapping;
      54: aload_1
      55: invokevirtual #61                 // Method org/apache/dubbo/metadata/AbstractServiceNameMapping.getMapping:(Lorg/apache/dubbo/common/URL;)Ljava/util/Set;
      58: astore_3
      59: new           #62                 // class org/apache/dubbo/registry/client/ServiceDiscoveryRegistry$DefaultMappingListener
      62: dup
      63: aload_0
      64: aload_1
      65: aload_3
      66: aload_2
      67: invokespecial #63                 // Method org/apache/dubbo/registry/client/ServiceDiscoveryRegistry$DefaultMappingListener."<init>":(Lorg/apache/dubbo/registry/client/ServiceDiscoveryRegistry;Lorg/apache/dubbo/common/URL;Ljava/util/Set;Lorg/apache/dubbo/registry/NotifyListener;)V
      70: astore        6
      72: aload_0
      73: getfield      #4                  // Field serviceNameMapping:Lorg/apache/dubbo/metadata/AbstractServiceNameMapping;
      76: aload_0
      77: invokevirtual #44                 // Method getUrl:()Lorg/apache/dubbo/common/URL;
      80: aload_1
      81: aload         6
      83: invokevirtual #64                 // Method org/apache/dubbo/metadata/AbstractServiceNameMapping.getAndListen:(Lorg/apache/dubbo/common/URL;Lorg/apache/dubbo/common/URL;Lorg/apache/dubbo/metadata/MappingListener;)Ljava/util/Set;
      86: astore_3
      87: aload_0
      88: getfield      #12                 // Field mappingListeners:Ljava/util/Map;
      91: aload_1
      92: invokevirtual #65                 // Method org/apache/dubbo/common/URL.getProtocolServiceKey:()Ljava/lang/String;
      95: aload         6
      97: invokeinterface #66,  3           // InterfaceMethod java/util/Map.put:(Ljava/lang/Object;Ljava/lang/Object;)Ljava/lang/Object;
     102: pop
     103: goto          152
     106: astore        6
     108: aload_0
     109: getfield      #8                  // Field logger:Lorg/apache/dubbo/common/logger/ErrorTypeAwareLogger;
     112: ldc           #68                 // String 99-0
     114: ldc           #69                 // String
     116: ldc           #69                 // String
     118: new           #38                 // class java/lang/StringBuilder
     121: dup
     122: invokespecial #39                 // Method java/lang/StringBuilder."<init>":()V
     125: ldc           #70                 // String Cannot find app mapping for service
     127: invokevirtual #41                 // Method java/lang/StringBuilder.append:(Ljava/lang/String;)Ljava/lang/StringBuilder;
     130: aload_1
     131: invokevirtual #71                 // Method org/apache/dubbo/common/URL.getServiceInterface:()Ljava/lang/String;
     134: invokevirtual #41                 // Method java/lang/StringBuilder.append:(Ljava/lang/String;)Ljava/lang/StringBuilder;
     137: ldc           #72                 // String , will not migrate.
     139: invokevirtual #41                 // Method java/lang/StringBuilder.append:(Ljava/lang/String;)Ljava/lang/StringBuilder;
     142: invokevirtual #46                 // Method java/lang/StringBuilder.toString:()Ljava/lang/String;
     145: aload         6
     147: invokeinterface #73,  6           // InterfaceMethod org/apache/dubbo/common/logger/ErrorTypeAwareLogger.warn:(Ljava/lang/String;Ljava/lang/String;Ljava/lang/String;Ljava/lang/String;Ljava/lang/Throwable;)V
     152: aload_3
     153: invokestatic  #74                 // Method org/apache/dubbo/common/utils/CollectionUtils.isEmpty:(Ljava/util/Collection;)Z
     156: ifeq          195
     159: aload_0
     160: getfield      #8                  // Field logger:Lorg/apache/dubbo/common/logger/ErrorTypeAwareLogger;
     163: new           #38                 // class java/lang/StringBuilder
     166: dup
     167: invokespecial #39                 // Method java/lang/StringBuilder."<init>":()V
     170: ldc           #75                 // String No interface-apps mapping found in local cache, stop subscribing, will automatically wait for mapping listener callback:
     172: invokevirtual #41                 // Method java/lang/StringBuilder.append:(Ljava/lang/String;)Ljava/lang/StringBuilder;
     175: aload_1
     176: invokevirtual #42                 // Method java/lang/StringBuilder.append:(Ljava/lang/Object;)Ljava/lang/StringBuilder;
     179: invokevirtual #46                 // Method java/lang/StringBuilder.toString:()Ljava/lang/String;
     182: invokeinterface #47,  2           // InterfaceMethod org/apache/dubbo/common/logger/ErrorTypeAwareLogger.info:(Ljava/lang/String;)V
     187: aload         5
     189: invokeinterface #76,  1           // InterfaceMethod java/util/concurrent/locks/Lock.unlock:()V
     194: return
     195: aload         5
     197: invokeinterface #76,  1           // InterfaceMethod java/util/concurrent/locks/Lock.unlock:()V
     202: goto          217
     205: astore        7
     207: aload         5
     209: invokeinterface #76,  1           // InterfaceMethod java/util/concurrent/locks/Lock.unlock:()V
     214: aload         7
     216: athrow
     217: aload_0
     218: aload_1
     219: aload_2
     220: aload_3
     221: invokevirtual #77                 // Method subscribeURLs:(Lorg/apache/dubbo/common/URL;Lorg/apache/dubbo/registry/NotifyListener;Ljava/util/Set;)V
     224: return
    Exception table:
       from    to  target type
          59   103   106   Class java/lang/Exception
          43   187   205   any
         205   207   205   any

  public final void unsubscribe(org.apache.dubbo.common.URL, org.apache.dubbo.registry.NotifyListener);
    Code:
       0: aload_0
       1: aload_1
       2: invokevirtual #54                 // Method shouldSubscribe:(Lorg/apache/dubbo/common/URL;)Z
       5: ifne          9
       8: return
       9: aload_0
      10: aload_1
      11: invokespecial #50                 // Method addRegistryClusterKey:(Lorg/apache/dubbo/common/URL;)Lorg/apache/dubbo/common/URL;
      14: astore_1
      15: aload_0
      16: aload_1
      17: aload_2
      18: invokevirtual #78                 // Method doUnsubscribe:(Lorg/apache/dubbo/common/URL;Lorg/apache/dubbo/registry/NotifyListener;)V
      21: return

  private org.apache.dubbo.common.URL addRegistryClusterKey(org.apache.dubbo.common.URL);
    Code:
       0: aload_0
       1: getfield      #15                 // Field serviceDiscovery:Lorg/apache/dubbo/registry/client/ServiceDiscovery;
       4: invokeinterface #79,  1           // InterfaceMethod org/apache/dubbo/registry/client/ServiceDiscovery.getUrl:()Lorg/apache/dubbo/common/URL;
       9: ldc           #80                 // String REGISTRY_CLUSTER
      11: invokevirtual #81                 // Method org/apache/dubbo/common/URL.getParameter:(Ljava/lang/String;)Ljava/lang/String;
      14: astore_2
      15: aload_2
      16: ifnull        36
      19: aload_1
      20: ldc           #80                 // String REGISTRY_CLUSTER
      22: invokevirtual #81                 // Method org/apache/dubbo/common/URL.getParameter:(Ljava/lang/String;)Ljava/lang/String;
      25: ifnonnull     36
      28: aload_1
      29: ldc           #80                 // String REGISTRY_CLUSTER
      31: aload_2
      32: invokevirtual #23                 // Method org/apache/dubbo/common/URL.addParameter:(Ljava/lang/String;Ljava/lang/String;)Lorg/apache/dubbo/common/URL;
      35: astore_1
      36: aload_1
      37: areturn

  public void doUnsubscribe(org.apache.dubbo.common.URL, org.apache.dubbo.registry.NotifyListener);
    Code:
       0: aload_0
       1: getfield      #15                 // Field serviceDiscovery:Lorg/apache/dubbo/registry/client/ServiceDiscovery;
       4: aload_1
       5: aload_2
       6: invokeinterface #82,  3           // InterfaceMethod org/apache/dubbo/registry/client/ServiceDiscovery.unsubscribe:(Lorg/apache/dubbo/common/URL;Lorg/apache/dubbo/registry/NotifyListener;)V
      11: aload_1
      12: invokevirtual #65                 // Method org/apache/dubbo/common/URL.getProtocolServiceKey:()Ljava/lang/String;
      15: astore_3
      16: aload_0
      17: getfield      #4                  // Field serviceNameMapping:Lorg/apache/dubbo/metadata/AbstractServiceNameMapping;
      20: aload_1
      21: invokevirtual #61                 // Method org/apache/dubbo/metadata/AbstractServiceNameMapping.getMapping:(Lorg/apache/dubbo/common/URL;)Ljava/util/Set;
      24: astore        4
      26: aload_0
      27: getfield      #4                  // Field serviceNameMapping:Lorg/apache/dubbo/metadata/AbstractServiceNameMapping;
      30: aload_1
      31: aload_0
      32: getfield      #12                 // Field mappingListeners:Ljava/util/Map;
      35: aload_3
      36: invokeinterface #83,  2           // InterfaceMethod java/util/Map.remove:(Ljava/lang/Object;)Ljava/lang/Object;
      41: checkcast     #84                 // class org/apache/dubbo/metadata/MappingListener
      44: invokevirtual #85                 // Method org/apache/dubbo/metadata/AbstractServiceNameMapping.stopListen:(Lorg/apache/dubbo/common/URL;Lorg/apache/dubbo/metadata/MappingListener;)Lorg/apache/dubbo/metadata/MappingListener;
      47: pop
      48: aload         4
      50: invokestatic  #86                 // Method org/apache/dubbo/common/utils/CollectionUtils.isNotEmpty:(Ljava/util/Collection;)Z
      53: ifeq          159
      56: aload         4
      58: invokestatic  #87                 // InterfaceMethod org/apache/dubbo/metadata/ServiceNameMapping.toStringKeys:(Ljava/util/Set;)Ljava/lang/String;
      61: astore        5
      63: aload_0
      64: aload         5
      66: invokevirtual #88                 // Method getAppSubscription:(Ljava/lang/String;)Ljava/util/concurrent/locks/Lock;
      69: astore        6
      71: aload         6
      73: invokeinterface #60,  1           // InterfaceMethod java/util/concurrent/locks/Lock.lock:()V
      78: aload_0
      79: getfield      #11                 // Field serviceListeners:Ljava/util/Map;
      82: aload         5
      84: invokeinterface #89,  2           // InterfaceMethod java/util/Map.get:(Ljava/lang/Object;)Ljava/lang/Object;
      89: checkcast     #90                 // class org/apache/dubbo/registry/client/event/listener/ServiceInstancesChangedListener
      92: astore        7
      94: aload         7
      96: ifnull        137
      99: aload         7
     101: aload_3
     102: aload_2
     103: invokevirtual #91                 // Method org/apache/dubbo/registry/client/event/listener/ServiceInstancesChangedListener.removeListener:(Ljava/lang/String;Lorg/apache/dubbo/registry/NotifyListener;)V
     106: aload         7
     108: invokevirtual #92                 // Method org/apache/dubbo/registry/client/event/listener/ServiceInstancesChangedListener.hasListeners:()Z
     111: ifne          137
     114: aload         7
     116: invokevirtual #93                 // Method org/apache/dubbo/registry/client/event/listener/ServiceInstancesChangedListener.destroy:()V
     119: aload_0
     120: getfield      #11                 // Field serviceListeners:Ljava/util/Map;
     123: aload         5
     125: invokeinterface #83,  2           // InterfaceMethod java/util/Map.remove:(Ljava/lang/Object;)Ljava/lang/Object;
     130: pop
     131: aload_0
     132: aload         5
     134: invokevirtual #94                 // Method removeAppSubscriptionLock:(Ljava/lang/String;)V
     137: aload         6
     139: invokeinterface #76,  1           // InterfaceMethod java/util/concurrent/locks/Lock.unlock:()V
     144: goto          159
     147: astore        8
     149: aload         6
     151: invokeinterface #76,  1           // InterfaceMethod java/util/concurrent/locks/Lock.unlock:()V
     156: aload         8
     158: athrow
     159: return
    Exception table:
       from    to  target type
          71   137   147   any
         147   149   147   any

  public java.util.List<org.apache.dubbo.common.URL> lookup(org.apache.dubbo.common.URL);
    Code:
       0: new           #95                 // class java/lang/UnsupportedOperationException
       3: dup
       4: ldc           #69                 // String
       6: invokespecial #96                 // Method java/lang/UnsupportedOperationException."<init>":(Ljava/lang/String;)V
       9: athrow

  public boolean isAvailable();
    Code:
       0: aload_0
       1: getfield      #15                 // Field serviceDiscovery:Lorg/apache/dubbo/registry/client/ServiceDiscovery;
       4: instanceof    #97                 // class org/apache/dubbo/registry/client/NopServiceDiscovery
       7: ifeq          12
      10: iconst_1
      11: ireturn
      12: aload_0
      13: getfield      #15                 // Field serviceDiscovery:Lorg/apache/dubbo/registry/client/ServiceDiscovery;
      16: invokeinterface #98,  1           // InterfaceMethod org/apache/dubbo/registry/client/ServiceDiscovery.isDestroy:()Z
      21: ifne          45
      24: aload_0
      25: getfield      #15                 // Field serviceDiscovery:Lorg/apache/dubbo/registry/client/ServiceDiscovery;
      28: invokeinterface #99,  1           // InterfaceMethod org/apache/dubbo/registry/client/ServiceDiscovery.getServices:()Ljava/util/Set;
      33: invokeinterface #100,  1          // InterfaceMethod java/util/Set.isEmpty:()Z
      38: ifne          45
      41: iconst_1
      42: goto          46
      45: iconst_0
      46: ireturn

  public void destroy();
    Code:
       0: aload_0
       1: getfield      #101                // Field registryManager:Lorg/apache/dubbo/registry/support/RegistryManager;
       4: aload_0
       5: invokevirtual #102                // Method org/apache/dubbo/registry/support/RegistryManager.removeDestroyedRegistry:(Lorg/apache/dubbo/registry/Registry;)V
       8: aload_0
       9: getfield      #15                 // Field serviceDiscovery:Lorg/apache/dubbo/registry/client/ServiceDiscovery;
      12: dup
      13: invokevirtual #6                  // Method java/lang/Object.getClass:()Ljava/lang/Class;
      16: pop
      17: invokedynamic #103,  0            // InvokeDynamic #0:execute:(Lorg/apache/dubbo/registry/client/ServiceDiscovery;)Lorg/apache/dubbo/common/function/ThrowableAction;
      22: invokestatic  #104                // InterfaceMethod org/apache/dubbo/common/function/ThrowableAction.execute:(Lorg/apache/dubbo/common/function/ThrowableAction;)V
      25: aload_0
      26: getfield      #11                 // Field serviceListeners:Ljava/util/Map;
      29: invokeinterface #105,  1          // InterfaceMethod java/util/Map.values:()Ljava/util/Collection;
      34: invokeinterface #106,  1          // InterfaceMethod java/util/Collection.iterator:()Ljava/util/Iterator;
      39: astore_1
      40: aload_1
      41: invokeinterface #107,  1          // InterfaceMethod java/util/Iterator.hasNext:()Z
      46: ifeq          66
      49: aload_1
      50: invokeinterface #108,  1          // InterfaceMethod java/util/Iterator.next:()Ljava/lang/Object;
      55: checkcast     #90                 // class org/apache/dubbo/registry/client/event/listener/ServiceInstancesChangedListener
      58: astore_2
      59: aload_2
      60: invokevirtual #93                 // Method org/apache/dubbo/registry/client/event/listener/ServiceInstancesChangedListener.destroy:()V
      63: goto          40
      66: aload_0
      67: getfield      #13                 // Field appSubscriptionLocks:Ljava/util/concurrent/ConcurrentMap;
      70: invokeinterface #109,  1          // InterfaceMethod java/util/concurrent/ConcurrentMap.clear:()V
      75: aload_0
      76: getfield      #11                 // Field serviceListeners:Ljava/util/Map;
      79: invokeinterface #110,  1          // InterfaceMethod java/util/Map.clear:()V
      84: aload_0
      85: getfield      #12                 // Field mappingListeners:Ljava/util/Map;
      88: invokeinterface #110,  1          // InterfaceMethod java/util/Map.clear:()V
      93: return

  public boolean isServiceDiscovery();
    Code:
       0: iconst_1
       1: ireturn

  protected void subscribeURLs(org.apache.dubbo.common.URL, org.apache.dubbo.registry.NotifyListener, java.util.Set<java.lang.String>);
    Code:
       0: aload_3
       1: invokestatic  #111                // Method org/apache/dubbo/common/utils/CollectionUtils.toTreeSet:(Ljava/util/Set;)Ljava/util/Set;
       4: astore_3
       5: aload_3
       6: invokestatic  #87                 // InterfaceMethod org/apache/dubbo/metadata/ServiceNameMapping.toStringKeys:(Ljava/util/Set;)Ljava/lang/String;
       9: astore        4
      11: aload_1
      12: invokevirtual #112                // Method org/apache/dubbo/common/URL.getServiceKey:()Ljava/lang/String;
      15: astore        5
      17: aload_0
      18: getfield      #8                  // Field logger:Lorg/apache/dubbo/common/logger/ErrorTypeAwareLogger;
      21: ldc           #113                // String Trying to subscribe from apps %s for service key %s,
      23: iconst_2
      24: anewarray     #34                 // class java/lang/Object
      27: dup
      28: iconst_0
      29: aload         4
      31: aastore
      32: dup
      33: iconst_1
      34: aload         5
      36: aastore
      37: invokestatic  #35                 // Method java/lang/String.format:(Ljava/lang/String;[Ljava/lang/Object;)Ljava/lang/String;
      40: invokeinterface #47,  2           // InterfaceMethod org/apache/dubbo/common/logger/ErrorTypeAwareLogger.info:(Ljava/lang/String;)V
      45: aload_0
      46: aload         4
      48: invokevirtual #88                 // Method getAppSubscription:(Ljava/lang/String;)Ljava/util/concurrent/locks/Lock;
      51: astore        6
      53: aload         6
      55: invokeinterface #60,  1           // InterfaceMethod java/util/concurrent/locks/Lock.lock:()V
      60: aload_0
      61: getfield      #11                 // Field serviceListeners:Ljava/util/Map;
      64: aload         4
      66: invokeinterface #89,  2           // InterfaceMethod java/util/Map.get:(Ljava/lang/Object;)Ljava/lang/Object;
      71: checkcast     #90                 // class org/apache/dubbo/registry/client/event/listener/ServiceInstancesChangedListener
      74: astore        7
      76: aload         7
      78: ifnonnull     177
      81: aload_0
      82: getfield      #15                 // Field serviceDiscovery:Lorg/apache/dubbo/registry/client/ServiceDiscovery;
      85: aload_3
      86: invokeinterface #114,  2          // InterfaceMethod org/apache/dubbo/registry/client/ServiceDiscovery.createListener:(Ljava/util/Set;)Lorg/apache/dubbo/registry/client/event/listener/ServiceInstancesChangedListener;
      91: astore        7
      93: aload_3
      94: invokeinterface #115,  1          // InterfaceMethod java/util/Set.iterator:()Ljava/util/Iterator;
      99: astore        8
     101: aload         8
     103: invokeinterface #107,  1          // InterfaceMethod java/util/Iterator.hasNext:()Z
     108: ifeq          163
     111: aload         8
     113: invokeinterface #108,  1          // InterfaceMethod java/util/Iterator.next:()Ljava/lang/Object;
     118: checkcast     #116                // class java/lang/String
     121: astore        9
     123: aload_0
     124: getfield      #15                 // Field serviceDiscovery:Lorg/apache/dubbo/registry/client/ServiceDiscovery;
     127: aload         9
     129: invokeinterface #117,  2          // InterfaceMethod org/apache/dubbo/registry/client/ServiceDiscovery.getInstances:(Ljava/lang/String;)Ljava/util/List;
     134: astore        10
     136: aload         10
     138: invokestatic  #86                 // Method org/apache/dubbo/common/utils/CollectionUtils.isNotEmpty:(Ljava/util/Collection;)Z
     141: ifeq          160
     144: aload         7
     146: new           #118                // class org/apache/dubbo/registry/client/event/ServiceInstancesChangedEvent
     149: dup
     150: aload         9
     152: aload         10
     154: invokespecial #119                // Method org/apache/dubbo/registry/client/event/ServiceInstancesChangedEvent."<init>":(Ljava/lang/String;Ljava/util/List;)V
     157: invokevirtual #120                // Method org/apache/dubbo/registry/client/event/listener/ServiceInstancesChangedListener.onEvent:(Lorg/apache/dubbo/registry/client/event/ServiceInstancesChangedEvent;)V
     160: goto          101
     163: aload_0
     164: getfield      #11                 // Field serviceListeners:Ljava/util/Map;
     167: aload         4
     169: aload         7
     171: invokeinterface #66,  3           // InterfaceMethod java/util/Map.put:(Ljava/lang/Object;Ljava/lang/Object;)Ljava/lang/Object;
     176: pop
     177: aload         7
     179: invokevirtual #121                // Method org/apache/dubbo/registry/client/event/listener/ServiceInstancesChangedListener.isDestroyed:()Z
     182: ifne          228
     185: aload_2
     186: aload         7
     188: invokeinterface #122,  2          // InterfaceMethod org/apache/dubbo/registry/NotifyListener.addServiceListener:(Lorg/apache/dubbo/registry/client/event/listener/ServiceInstancesChangedListener;)V
     193: aload         7
     195: aload_1
     196: aload_2
     197: invokevirtual #123                // Method org/apache/dubbo/registry/client/event/listener/ServiceInstancesChangedListener.addListenerAndNotify:(Lorg/apache/dubbo/common/URL;Lorg/apache/dubbo/registry/NotifyListener;)V
     200: aload         7
     202: astore        8
     204: aload_1
     205: invokevirtual #124                // Method org/apache/dubbo/common/URL.getApplicationModel:()Lorg/apache/dubbo/rpc/model/ApplicationModel;
     208: aload         5
     210: invokestatic  #125                // Method org/apache/dubbo/metrics/registry/event/RegistryEvent.toSsEvent:(Lorg/apache/dubbo/rpc/model/ApplicationModel;Ljava/lang/String;)Lorg/apache/dubbo/metrics/registry/event/RegistryEvent;
     213: aload_0
     214: aload         8
     216: invokedynamic #126,  0            // InvokeDynamic #1:get:(Lorg/apache/dubbo/registry/client/ServiceDiscoveryRegistry;Lorg/apache/dubbo/registry/client/event/listener/ServiceInstancesChangedListener;)Ljava/util/function/Supplier;
     221: invokestatic  #127                // Method org/apache/dubbo/metrics/event/MetricsEventBus.post:(Lorg/apache/dubbo/metrics/event/MetricsEvent;Ljava/util/function/Supplier;)Ljava/lang/Object;
     224: pop
     225: goto          263
     228: aload_0
     229: getfield      #8                  // Field logger:Lorg/apache/dubbo/common/logger/ErrorTypeAwareLogger;
     232: ldc           #128                // String Listener of %s has been destroyed by another thread.
     234: iconst_1
     235: anewarray     #34                 // class java/lang/Object
     238: dup
     239: iconst_0
     240: aload         4
     242: aastore
     243: invokestatic  #35                 // Method java/lang/String.format:(Ljava/lang/String;[Ljava/lang/Object;)Ljava/lang/String;
     246: invokeinterface #47,  2           // InterfaceMethod org/apache/dubbo/common/logger/ErrorTypeAwareLogger.info:(Ljava/lang/String;)V
     251: aload_0
     252: getfield      #11                 // Field serviceListeners:Ljava/util/Map;
     255: aload         4
     257: invokeinterface #83,  2           // InterfaceMethod java/util/Map.remove:(Ljava/lang/Object;)Ljava/lang/Object;
     262: pop
     263: aload         6
     265: invokeinterface #76,  1           // InterfaceMethod java/util/concurrent/locks/Lock.unlock:()V
     270: goto          285
     273: astore        11
     275: aload         6
     277: invokeinterface #76,  1           // InterfaceMethod java/util/concurrent/locks/Lock.unlock:()V
     282: aload         11
     284: athrow
     285: return
    Exception table:
       from    to  target type
          53   263   273   any
         273   275   273   any

  public static boolean supports(org.apache.dubbo.common.URL);
    Code:
       0: ldc           #129                // String service
       2: aload_0
       3: ldc           #24                 // String registry-type
       5: invokevirtual #81                 // Method org/apache/dubbo/common/URL.getParameter:(Ljava/lang/String;)Ljava/lang/String;
       8: invokevirtual #130                // Method java/lang/String.equalsIgnoreCase:(Ljava/lang/String;)Z
      11: ireturn

  public java.util.Map<java.lang.String, org.apache.dubbo.registry.client.event.listener.ServiceInstancesChangedListener> getServiceListeners();
    Code:
       0: aload_0
       1: getfield      #11                 // Field serviceListeners:Ljava/util/Map;
       4: areturn

  public java.util.concurrent.locks.Lock getAppSubscription(java.lang.String);
    Code:
       0: aload_0
       1: getfield      #13                 // Field appSubscriptionLocks:Ljava/util/concurrent/ConcurrentMap;
       4: aload_1
       5: invokedynamic #131,  0            // InvokeDynamic #2:apply:()Ljava/util/function/Function;
      10: invokestatic  #132                // Method org/apache/dubbo/common/utils/ConcurrentHashMapUtils.computeIfAbsent:(Ljava/util/concurrent/ConcurrentMap;Ljava/lang/Object;Ljava/util/function/Function;)Ljava/lang/Object;
      13: checkcast     #133                // class java/util/concurrent/locks/Lock
      16: areturn

  public void removeAppSubscriptionLock(java.lang.String);
    Code:
       0: aload_0
       1: getfield      #13                 // Field appSubscriptionLocks:Ljava/util/concurrent/ConcurrentMap;
       4: aload_1
       5: invokeinterface #134,  2          // InterfaceMethod java/util/concurrent/ConcurrentMap.get:(Ljava/lang/Object;)Ljava/lang/Object;
      10: checkcast     #133                // class java/util/concurrent/locks/Lock
      13: astore_2
      14: aload_2
      15: ifnull        53
      18: aload_2
      19: invokeinterface #60,  1           // InterfaceMethod java/util/concurrent/locks/Lock.lock:()V
      24: aload_0
      25: getfield      #13                 // Field appSubscriptionLocks:Ljava/util/concurrent/ConcurrentMap;
      28: aload_1
      29: invokeinterface #135,  2          // InterfaceMethod java/util/concurrent/ConcurrentMap.remove:(Ljava/lang/Object;)Ljava/lang/Object;
      34: pop
      35: aload_2
      36: invokeinterface #76,  1           // InterfaceMethod java/util/concurrent/locks/Lock.unlock:()V
      41: goto          53
      44: astore_3
      45: aload_2
      46: invokeinterface #76,  1           // InterfaceMethod java/util/concurrent/locks/Lock.unlock:()V
      51: aload_3
      52: athrow
      53: return
    Exception table:
       from    to  target type
          18    35    44   any

  private static java.util.concurrent.locks.Lock lambda$getAppSubscription$1(java.lang.String);
    Code:
       0: new           #136                // class java/util/concurrent/locks/ReentrantLock
       3: dup
       4: invokespecial #137                // Method java/util/concurrent/locks/ReentrantLock."<init>":()V
       7: areturn

  private java.lang.Object lambda$subscribeURLs$0(org.apache.dubbo.registry.client.event.listener.ServiceInstancesChangedListener);
    Code:
       0: aload_0
       1: getfield      #15                 // Field serviceDiscovery:Lorg/apache/dubbo/registry/client/ServiceDiscovery;
       4: aload_1
       5: invokeinterface #138,  2          // InterfaceMethod org/apache/dubbo/registry/client/ServiceDiscovery.addServiceInstancesChangedListener:(Lorg/apache/dubbo/registry/client/event/listener/ServiceInstancesChangedListener;)V
      10: aconst_null
      11: areturn

  static org.apache.dubbo.metadata.AbstractServiceNameMapping access$000(org.apache.dubbo.registry.client.ServiceDiscoveryRegistry);
    Code:
       0: aload_0
       1: getfield      #4                  // Field serviceNameMapping:Lorg/apache/dubbo/metadata/AbstractServiceNameMapping;
       4: areturn
}
