Compiled from "ServiceDiscoveryRegistryFactory.java"
public class org.apache.dubbo.registry.client.ServiceDiscoveryRegistryFactory extends org.apache.dubbo.registry.support.AbstractRegistryFactory {
  public org.apache.dubbo.registry.client.ServiceDiscoveryRegistryFactory();
    Code:
       0: aload_0
       1: invokespecial #3                  // Method org/apache/dubbo/registry/support/AbstractRegistryFactory."<init>":()V
       4: return

  protected org.apache.dubbo.registry.Registry createRegistry(org.apache.dubbo.common.URL);
    Code:
       0: aload_1
       1: invokestatic  #4                  // Method org/apache/dubbo/common/utils/UrlUtils.hasServiceDiscoveryRegistryProtocol:(Lorg/apache/dubbo/common/URL;)Z
       4: ifeq          27
       7: aload_1
       8: ldc           #5                  // String registry
      10: ldc           #6                  // String dubbo
      12: invokevirtual #7                  // Method org/apache/dubbo/common/URL.getParameter:(Ljava/lang/String;Ljava/lang/String;)Ljava/lang/String;
      15: astore_2
      16: aload_1
      17: aload_2
      18: invokevirtual #8                  // Method org/apache/dubbo/common/URL.setProtocol:(Ljava/lang/String;)Lorg/apache/dubbo/common/URL;
      21: ldc           #5                  // String registry
      23: invokevirtual #9                  // Method org/apache/dubbo/common/URL.removeParameter:(Ljava/lang/String;)Lorg/apache/dubbo/common/URL;
      26: astore_1
      27: new           #10                 // class org/apache/dubbo/registry/client/ServiceDiscoveryRegistry
      30: dup
      31: aload_1
      32: aload_0
      33: getfield      #11                 // Field applicationModel:Lorg/apache/dubbo/rpc/model/ApplicationModel;
      36: invokespecial #12                 // Method org/apache/dubbo/registry/client/ServiceDiscoveryRegistry."<init>":(Lorg/apache/dubbo/common/URL;Lorg/apache/dubbo/rpc/model/ApplicationModel;)V
      39: areturn
}
