Compiled from "ServiceDiscoveryRegistryDirectory.java"
public class org.apache.dubbo.registry.client.ServiceDiscoveryRegistryDirectory<T> extends org.apache.dubbo.registry.integration.DynamicDirectory<T> {
  private static final org.apache.dubbo.common.logger.ErrorTypeAwareLogger logger;

  private volatile java.util.Map<org.apache.dubbo.registry.client.ServiceDiscoveryRegistryDirectory$ProtocolServiceKeyWithAddress, org.apache.dubbo.rpc.Invoker<T>> urlInvokerMap;

  private volatile org.apache.dubbo.registry.client.ServiceDiscoveryRegistryDirectory<T>.ReferenceConfigurationListener referenceConfigurationListener;

  private volatile boolean enableConfigurationListen;

  private volatile java.util.List<org.apache.dubbo.common.URL> originalUrls;

  private volatile java.util.Map<java.lang.String, java.lang.String> overrideQueryMap;

  private final java.util.Set<java.lang.String> providerFirstParams;

  private final org.apache.dubbo.rpc.model.ModuleModel moduleModel;

  private final org.apache.dubbo.common.ProtocolServiceKey consumerProtocolServiceKey;

  private final java.util.concurrent.ConcurrentMap<org.apache.dubbo.common.ProtocolServiceKey, org.apache.dubbo.common.URL> customizedConsumerUrlMap;

  public org.apache.dubbo.registry.client.ServiceDiscoveryRegistryDirectory(java.lang.Class<T>, org.apache.dubbo.common.URL);
    Code:
       0: aload_0
       1: aload_1
       2: aload_2
       3: invokespecial #5                  // Method org/apache/dubbo/registry/integration/DynamicDirectory."<init>":(Ljava/lang/Class;Lorg/apache/dubbo/common/URL;)V
       6: aload_0
       7: iconst_1
       8: putfield      #6                  // Field enableConfigurationListen:Z
      11: aload_0
      12: aconst_null
      13: putfield      #4                  // Field originalUrls:Ljava/util/List;
      16: aload_0
      17: new           #7                  // class java/util/concurrent/ConcurrentHashMap
      20: dup
      21: invokespecial #8                  // Method java/util/concurrent/ConcurrentHashMap."<init>":()V
      24: putfield      #9                  // Field customizedConsumerUrlMap:Ljava/util/concurrent/ConcurrentMap;
      27: aload_0
      28: aload_2
      29: invokevirtual #10                 // Method org/apache/dubbo/common/URL.getScopeModel:()Lorg/apache/dubbo/rpc/model/ScopeModel;
      32: invokestatic  #11                 // Method org/apache/dubbo/rpc/model/ScopeModelUtil.getModuleModel:(Lorg/apache/dubbo/rpc/model/ScopeModel;)Lorg/apache/dubbo/rpc/model/ModuleModel;
      35: putfield      #12                 // Field moduleModel:Lorg/apache/dubbo/rpc/model/ModuleModel;
      38: aload_2
      39: invokevirtual #13                 // Method org/apache/dubbo/common/URL.getOrDefaultApplicationModel:()Lorg/apache/dubbo/rpc/model/ApplicationModel;
      42: ldc           #14                 // class org/apache/dubbo/registry/ProviderFirstParams
      44: invokevirtual #15                 // Method org/apache/dubbo/rpc/model/ApplicationModel.getExtensionLoader:(Ljava/lang/Class;)Lorg/apache/dubbo/common/extension/ExtensionLoader;
      47: invokevirtual #16                 // Method org/apache/dubbo/common/extension/ExtensionLoader.getSupportedExtensionInstances:()Ljava/util/Set;
      50: astore_3
      51: aload_3
      52: invokestatic  #17                 // Method org/apache/dubbo/common/utils/CollectionUtils.isEmpty:(Ljava/util/Collection;)Z
      55: ifeq          66
      58: aload_0
      59: aconst_null
      60: putfield      #18                 // Field providerFirstParams:Ljava/util/Set;
      63: goto          184
      66: aload_3
      67: invokeinterface #19,  1           // InterfaceMethod java/util/Set.size:()I
      72: iconst_1
      73: if_icmpne     105
      76: aload_0
      77: aload_3
      78: invokeinterface #20,  1           // InterfaceMethod java/util/Set.iterator:()Ljava/util/Iterator;
      83: invokeinterface #21,  1           // InterfaceMethod java/util/Iterator.next:()Ljava/lang/Object;
      88: checkcast     #14                 // class org/apache/dubbo/registry/ProviderFirstParams
      91: invokeinterface #22,  1           // InterfaceMethod org/apache/dubbo/registry/ProviderFirstParams.params:()Ljava/util/Set;
      96: invokestatic  #23                 // Method java/util/Collections.unmodifiableSet:(Ljava/util/Set;)Ljava/util/Set;
      99: putfield      #18                 // Field providerFirstParams:Ljava/util/Set;
     102: goto          184
     105: new           #24                 // class java/util/HashSet
     108: dup
     109: invokespecial #25                 // Method java/util/HashSet."<init>":()V
     112: astore        4
     114: aload_3
     115: invokeinterface #20,  1           // InterfaceMethod java/util/Set.iterator:()Ljava/util/Iterator;
     120: astore        5
     122: aload         5
     124: invokeinterface #26,  1           // InterfaceMethod java/util/Iterator.hasNext:()Z
     129: ifeq          175
     132: aload         5
     134: invokeinterface #21,  1           // InterfaceMethod java/util/Iterator.next:()Ljava/lang/Object;
     139: checkcast     #14                 // class org/apache/dubbo/registry/ProviderFirstParams
     142: astore        6
     144: aload         6
     146: invokeinterface #22,  1           // InterfaceMethod org/apache/dubbo/registry/ProviderFirstParams.params:()Ljava/util/Set;
     151: ifnonnull     157
     154: goto          175
     157: aload         4
     159: aload         6
     161: invokeinterface #22,  1           // InterfaceMethod org/apache/dubbo/registry/ProviderFirstParams.params:()Ljava/util/Set;
     166: invokeinterface #27,  2           // InterfaceMethod java/util/Set.addAll:(Ljava/util/Collection;)Z
     171: pop
     172: goto          122
     175: aload_0
     176: aload         4
     178: invokestatic  #23                 // Method java/util/Collections.unmodifiableSet:(Ljava/util/Set;)Ljava/util/Set;
     181: putfield      #18                 // Field providerFirstParams:Ljava/util/Set;
     184: aload_0
     185: getfield      #28                 // Field consumerUrl:Lorg/apache/dubbo/common/URL;
     188: ldc           #29                 // String protocol
     190: aload_0
     191: getfield      #28                 // Field consumerUrl:Lorg/apache/dubbo/common/URL;
     194: invokevirtual #30                 // Method org/apache/dubbo/common/URL.getProtocol:()Ljava/lang/String;
     197: invokevirtual #31                 // Method org/apache/dubbo/common/URL.getParameter:(Ljava/lang/String;Ljava/lang/String;)Ljava/lang/String;
     200: astore        4
     202: aload_0
     203: new           #32                 // class org/apache/dubbo/common/ProtocolServiceKey
     206: dup
     207: aload_0
     208: getfield      #28                 // Field consumerUrl:Lorg/apache/dubbo/common/URL;
     211: invokevirtual #33                 // Method org/apache/dubbo/common/URL.getServiceInterface:()Ljava/lang/String;
     214: aload_0
     215: getfield      #28                 // Field consumerUrl:Lorg/apache/dubbo/common/URL;
     218: invokevirtual #34                 // Method org/apache/dubbo/common/URL.getVersion:()Ljava/lang/String;
     221: aload_0
     222: getfield      #28                 // Field consumerUrl:Lorg/apache/dubbo/common/URL;
     225: invokevirtual #35                 // Method org/apache/dubbo/common/URL.getGroup:()Ljava/lang/String;
     228: ldc           #36                 // String consumer
     230: aload         4
     232: invokevirtual #37                 // Method java/lang/String.equals:(Ljava/lang/Object;)Z
     235: ifne          243
     238: aload         4
     240: goto          244
     243: aconst_null
     244: invokespecial #38                 // Method org/apache/dubbo/common/ProtocolServiceKey."<init>":(Ljava/lang/String;Ljava/lang/String;Ljava/lang/String;Ljava/lang/String;)V
     247: putfield      #39                 // Field consumerProtocolServiceKey:Lorg/apache/dubbo/common/ProtocolServiceKey;
     250: return

  public void subscribe(org.apache.dubbo.common.URL);
    Code:
       0: aload_0
       1: getfield      #12                 // Field moduleModel:Lorg/apache/dubbo/rpc/model/ModuleModel;
       4: invokevirtual #40                 // Method org/apache/dubbo/rpc/model/ModuleModel.getModelEnvironment:()Lorg/apache/dubbo/common/config/ModuleEnvironment;
       7: invokevirtual #41                 // Method org/apache/dubbo/common/config/ModuleEnvironment.getConfiguration:()Lorg/apache/dubbo/common/config/CompositeConfiguration;
      10: ldc           #42                 // class java/lang/Boolean
      12: ldc           #44                 // String enable-configuration-listen
      14: iconst_1
      15: invokestatic  #45                 // Method java/lang/Boolean.valueOf:(Z)Ljava/lang/Boolean;
      18: invokevirtual #46                 // Method org/apache/dubbo/common/config/CompositeConfiguration.convert:(Ljava/lang/Class;Ljava/lang/String;Ljava/lang/Object;)Ljava/lang/Object;
      21: checkcast     #42                 // class java/lang/Boolean
      24: invokevirtual #47                 // Method java/lang/Boolean.booleanValue:()Z
      27: ifeq          68
      30: aload_0
      31: iconst_1
      32: putfield      #6                  // Field enableConfigurationListen:Z
      35: aload_0
      36: aload_0
      37: getfield      #12                 // Field moduleModel:Lorg/apache/dubbo/rpc/model/ModuleModel;
      40: invokespecial #48                 // Method getConsumerConfigurationListener:(Lorg/apache/dubbo/rpc/model/ModuleModel;)Lorg/apache/dubbo/registry/client/ServiceDiscoveryRegistryDirectory$ConsumerConfigurationListener;
      43: aload_0
      44: invokevirtual #49                 // Method org/apache/dubbo/registry/client/ServiceDiscoveryRegistryDirectory$ConsumerConfigurationListener.addNotifyListener:(Lorg/apache/dubbo/registry/client/ServiceDiscoveryRegistryDirectory;)V
      47: aload_0
      48: new           #50                 // class org/apache/dubbo/registry/client/ServiceDiscoveryRegistryDirectory$ReferenceConfigurationListener
      51: dup
      52: aload_0
      53: aload_0
      54: getfield      #12                 // Field moduleModel:Lorg/apache/dubbo/rpc/model/ModuleModel;
      57: aload_0
      58: aload_1
      59: invokespecial #51                 // Method org/apache/dubbo/registry/client/ServiceDiscoveryRegistryDirectory$ReferenceConfigurationListener."<init>":(Lorg/apache/dubbo/registry/client/ServiceDiscoveryRegistryDirectory;Lorg/apache/dubbo/rpc/model/ModuleModel;Lorg/apache/dubbo/registry/client/ServiceDiscoveryRegistryDirectory;Lorg/apache/dubbo/common/URL;)V
      62: putfield      #52                 // Field referenceConfigurationListener:Lorg/apache/dubbo/registry/client/ServiceDiscoveryRegistryDirectory$ReferenceConfigurationListener;
      65: goto          73
      68: aload_0
      69: iconst_0
      70: putfield      #6                  // Field enableConfigurationListen:Z
      73: aload_0
      74: aload_1
      75: invokespecial #53                 // Method org/apache/dubbo/registry/integration/DynamicDirectory.subscribe:(Lorg/apache/dubbo/common/URL;)V
      78: return

  private org.apache.dubbo.registry.client.ServiceDiscoveryRegistryDirectory$ConsumerConfigurationListener getConsumerConfigurationListener(org.apache.dubbo.rpc.model.ModuleModel);
    Code:
       0: aload_1
       1: invokevirtual #54                 // Method org/apache/dubbo/rpc/model/ModuleModel.getBeanFactory:()Lorg/apache/dubbo/common/beans/factory/ScopeBeanFactory;
       4: ldc           #55                 // class org/apache/dubbo/registry/client/ServiceDiscoveryRegistryDirectory$ConsumerConfigurationListener
       6: aload_1
       7: invokedynamic #56,  0             // InvokeDynamic #0:apply:(Lorg/apache/dubbo/rpc/model/ModuleModel;)Ljava/util/function/Function;
      12: invokevirtual #57                 // Method org/apache/dubbo/common/beans/factory/ScopeBeanFactory.getOrRegisterBean:(Ljava/lang/Class;Ljava/util/function/Function;)Ljava/lang/Object;
      15: checkcast     #55                 // class org/apache/dubbo/registry/client/ServiceDiscoveryRegistryDirectory$ConsumerConfigurationListener
      18: areturn

  public void unSubscribe(org.apache.dubbo.common.URL);
    Code:
       0: aload_0
       1: aload_1
       2: invokespecial #58                 // Method org/apache/dubbo/registry/integration/DynamicDirectory.unSubscribe:(Lorg/apache/dubbo/common/URL;)V
       5: aload_0
       6: aconst_null
       7: putfield      #4                  // Field originalUrls:Ljava/util/List;
      10: aload_0
      11: getfield      #12                 // Field moduleModel:Lorg/apache/dubbo/rpc/model/ModuleModel;
      14: invokevirtual #40                 // Method org/apache/dubbo/rpc/model/ModuleModel.getModelEnvironment:()Lorg/apache/dubbo/common/config/ModuleEnvironment;
      17: invokevirtual #41                 // Method org/apache/dubbo/common/config/ModuleEnvironment.getConfiguration:()Lorg/apache/dubbo/common/config/CompositeConfiguration;
      20: ldc           #42                 // class java/lang/Boolean
      22: ldc           #44                 // String enable-configuration-listen
      24: iconst_1
      25: invokestatic  #45                 // Method java/lang/Boolean.valueOf:(Z)Ljava/lang/Boolean;
      28: invokevirtual #46                 // Method org/apache/dubbo/common/config/CompositeConfiguration.convert:(Ljava/lang/Class;Ljava/lang/String;Ljava/lang/Object;)Ljava/lang/Object;
      31: checkcast     #42                 // class java/lang/Boolean
      34: invokevirtual #47                 // Method java/lang/Boolean.booleanValue:()Z
      37: ifeq          59
      40: aload_0
      41: aload_0
      42: getfield      #12                 // Field moduleModel:Lorg/apache/dubbo/rpc/model/ModuleModel;
      45: invokespecial #48                 // Method getConsumerConfigurationListener:(Lorg/apache/dubbo/rpc/model/ModuleModel;)Lorg/apache/dubbo/registry/client/ServiceDiscoveryRegistryDirectory$ConsumerConfigurationListener;
      48: aload_0
      49: invokevirtual #59                 // Method org/apache/dubbo/registry/client/ServiceDiscoveryRegistryDirectory$ConsumerConfigurationListener.removeNotifyListener:(Lorg/apache/dubbo/registry/client/ServiceDiscoveryRegistryDirectory;)V
      52: aload_0
      53: getfield      #52                 // Field referenceConfigurationListener:Lorg/apache/dubbo/registry/client/ServiceDiscoveryRegistryDirectory$ReferenceConfigurationListener;
      56: invokevirtual #60                 // Method org/apache/dubbo/registry/client/ServiceDiscoveryRegistryDirectory$ReferenceConfigurationListener.stop:()V
      59: return

  public void destroy();
    Code:
       0: aload_0
       1: invokespecial #61                 // Method org/apache/dubbo/registry/integration/DynamicDirectory.destroy:()V
       4: aload_0
       5: getfield      #12                 // Field moduleModel:Lorg/apache/dubbo/rpc/model/ModuleModel;
       8: invokevirtual #40                 // Method org/apache/dubbo/rpc/model/ModuleModel.getModelEnvironment:()Lorg/apache/dubbo/common/config/ModuleEnvironment;
      11: invokevirtual #41                 // Method org/apache/dubbo/common/config/ModuleEnvironment.getConfiguration:()Lorg/apache/dubbo/common/config/CompositeConfiguration;
      14: ldc           #42                 // class java/lang/Boolean
      16: ldc           #44                 // String enable-configuration-listen
      18: iconst_1
      19: invokestatic  #45                 // Method java/lang/Boolean.valueOf:(Z)Ljava/lang/Boolean;
      22: invokevirtual #46                 // Method org/apache/dubbo/common/config/CompositeConfiguration.convert:(Ljava/lang/Class;Ljava/lang/String;Ljava/lang/Object;)Ljava/lang/Object;
      25: checkcast     #42                 // class java/lang/Boolean
      28: invokevirtual #47                 // Method java/lang/Boolean.booleanValue:()Z
      31: ifeq          53
      34: aload_0
      35: aload_0
      36: getfield      #12                 // Field moduleModel:Lorg/apache/dubbo/rpc/model/ModuleModel;
      39: invokespecial #48                 // Method getConsumerConfigurationListener:(Lorg/apache/dubbo/rpc/model/ModuleModel;)Lorg/apache/dubbo/registry/client/ServiceDiscoveryRegistryDirectory$ConsumerConfigurationListener;
      42: aload_0
      43: invokevirtual #59                 // Method org/apache/dubbo/registry/client/ServiceDiscoveryRegistryDirectory$ConsumerConfigurationListener.removeNotifyListener:(Lorg/apache/dubbo/registry/client/ServiceDiscoveryRegistryDirectory;)V
      46: aload_0
      47: getfield      #52                 // Field referenceConfigurationListener:Lorg/apache/dubbo/registry/client/ServiceDiscoveryRegistryDirectory$ReferenceConfigurationListener;
      50: invokevirtual #60                 // Method org/apache/dubbo/registry/client/ServiceDiscoveryRegistryDirectory$ReferenceConfigurationListener.stop:()V
      53: return

  public void buildRouterChain(org.apache.dubbo.common.URL);
    Code:
       0: aload_0
       1: aload_0
       2: invokevirtual #62                 // Method getInterface:()Ljava/lang/Class;
       5: aload_1
       6: ldc           #63                 // String registry-type
       8: ldc           #64                 // String service
      10: invokevirtual #65                 // Method org/apache/dubbo/common/URL.addParameter:(Ljava/lang/String;Ljava/lang/String;)Lorg/apache/dubbo/common/URL;
      13: invokestatic  #66                 // Method org/apache/dubbo/rpc/cluster/RouterChain.buildChain:(Ljava/lang/Class;Lorg/apache/dubbo/common/URL;)Lorg/apache/dubbo/rpc/cluster/RouterChain;
      16: invokevirtual #67                 // Method setRouterChain:(Lorg/apache/dubbo/rpc/cluster/RouterChain;)V
      19: return

  public synchronized void notify(java.util.List<org.apache.dubbo.common.URL>);
    Code:
       0: aload_0
       1: invokevirtual #68                 // Method isDestroyed:()Z
       4: ifeq          8
       7: return
       8: invokestatic  #69                 // Method org/apache/dubbo/rpc/RpcServiceContext.getServiceContext:()Lorg/apache/dubbo/rpc/RpcServiceContext;
      11: aload_0
      12: invokevirtual #70                 // Method getConsumerUrl:()Lorg/apache/dubbo/common/URL;
      15: invokevirtual #71                 // Method org/apache/dubbo/rpc/RpcServiceContext.setConsumerUrl:(Lorg/apache/dubbo/common/URL;)V
      18: aload_0
      19: invokevirtual #72                 // Method getUrl:()Lorg/apache/dubbo/common/URL;
      22: invokevirtual #73                 // Method org/apache/dubbo/common/URL.getOrDefaultModuleModel:()Lorg/apache/dubbo/rpc/model/ModuleModel;
      25: ldc           #74                 // class org/apache/dubbo/registry/AddressListener
      27: invokevirtual #75                 // Method org/apache/dubbo/rpc/model/ModuleModel.getExtensionLoader:(Ljava/lang/Class;)Lorg/apache/dubbo/common/extension/ExtensionLoader;
      30: astore_2
      31: aload_2
      32: aload_0
      33: invokevirtual #72                 // Method getUrl:()Lorg/apache/dubbo/common/URL;
      36: aconst_null
      37: checkcast     #76                 // class "[Ljava/lang/String;"
      40: invokevirtual #77                 // Method org/apache/dubbo/common/extension/ExtensionLoader.getActivateExtension:(Lorg/apache/dubbo/common/URL;[Ljava/lang/String;)Ljava/util/List;
      43: astore_3
      44: aload_3
      45: ifnull        104
      48: aload_3
      49: invokeinterface #78,  1           // InterfaceMethod java/util/List.isEmpty:()Z
      54: ifne          104
      57: aload_3
      58: invokeinterface #79,  1           // InterfaceMethod java/util/List.iterator:()Ljava/util/Iterator;
      63: astore        4
      65: aload         4
      67: invokeinterface #26,  1           // InterfaceMethod java/util/Iterator.hasNext:()Z
      72: ifeq          104
      75: aload         4
      77: invokeinterface #21,  1           // InterfaceMethod java/util/Iterator.next:()Ljava/lang/Object;
      82: checkcast     #74                 // class org/apache/dubbo/registry/AddressListener
      85: astore        5
      87: aload         5
      89: aload_1
      90: aload_0
      91: invokevirtual #70                 // Method getConsumerUrl:()Lorg/apache/dubbo/common/URL;
      94: aload_0
      95: invokeinterface #80,  4           // InterfaceMethod org/apache/dubbo/registry/AddressListener.notify:(Ljava/util/List;Lorg/apache/dubbo/common/URL;Lorg/apache/dubbo/rpc/cluster/Directory;)Ljava/util/List;
     100: astore_1
     101: goto          65
     104: aload_0
     105: aload_1
     106: invokevirtual #81                 // Method refreshOverrideAndInvoker:(Ljava/util/List;)V
     109: return

  protected synchronized void refreshOverrideAndInvoker(java.util.List<org.apache.dubbo.common.URL>);
    Code:
       0: aload_0
       1: aload_0
       2: aload_0
       3: invokevirtual #82                 // Method getOriginalConsumerUrl:()Lorg/apache/dubbo/common/URL;
       6: invokevirtual #83                 // Method overrideDirectoryWithConfigurator:(Lorg/apache/dubbo/common/URL;)Lorg/apache/dubbo/common/URL;
       9: putfield      #84                 // Field directoryUrl:Lorg/apache/dubbo/common/URL;
      12: aload_0
      13: aload_1
      14: invokespecial #85                 // Method refreshInvoker:(Ljava/util/List;)V
      17: return

  protected org.apache.dubbo.common.URL overrideDirectoryWithConfigurator(org.apache.dubbo.common.URL);
    Code:
       0: aload_0
       1: aload_0
       2: aload_0
       3: getfield      #12                 // Field moduleModel:Lorg/apache/dubbo/rpc/model/ModuleModel;
       6: invokespecial #48                 // Method getConsumerConfigurationListener:(Lorg/apache/dubbo/rpc/model/ModuleModel;)Lorg/apache/dubbo/registry/client/ServiceDiscoveryRegistryDirectory$ConsumerConfigurationListener;
       9: invokevirtual #86                 // Method org/apache/dubbo/registry/client/ServiceDiscoveryRegistryDirectory$ConsumerConfigurationListener.getConfigurators:()Ljava/util/List;
      12: aload_1
      13: invokespecial #87                 // Method overrideWithConfigurators:(Ljava/util/List;Lorg/apache/dubbo/common/URL;)Lorg/apache/dubbo/common/URL;
      16: astore_1
      17: aload_0
      18: getfield      #52                 // Field referenceConfigurationListener:Lorg/apache/dubbo/registry/client/ServiceDiscoveryRegistryDirectory$ReferenceConfigurationListener;
      21: ifnull        37
      24: aload_0
      25: aload_0
      26: getfield      #52                 // Field referenceConfigurationListener:Lorg/apache/dubbo/registry/client/ServiceDiscoveryRegistryDirectory$ReferenceConfigurationListener;
      29: invokevirtual #88                 // Method org/apache/dubbo/registry/client/ServiceDiscoveryRegistryDirectory$ReferenceConfigurationListener.getConfigurators:()Ljava/util/List;
      32: aload_1
      33: invokespecial #87                 // Method overrideWithConfigurators:(Ljava/util/List;Lorg/apache/dubbo/common/URL;)Lorg/apache/dubbo/common/URL;
      36: astore_1
      37: aload_1
      38: areturn

  private org.apache.dubbo.common.URL overrideWithConfigurators(java.util.List<org.apache.dubbo.rpc.cluster.Configurator>, org.apache.dubbo.common.URL);
    Code:
       0: aload_1
       1: invokestatic  #89                 // Method org/apache/dubbo/common/utils/CollectionUtils.isNotEmpty:(Ljava/util/Collection;)Z
       4: ifeq          179
       7: aload_2
       8: instanceof    #90                 // class org/apache/dubbo/common/url/component/DubboServiceAddressURL
      11: ifeq          140
      14: aload_2
      15: checkcast     #90                 // class org/apache/dubbo/common/url/component/DubboServiceAddressURL
      18: astore_3
      19: aload_3
      20: invokevirtual #91                 // Method org/apache/dubbo/common/url/component/DubboServiceAddressURL.getOverrideURL:()Lorg/apache/dubbo/common/url/component/ServiceConfigURL;
      23: astore        4
      25: aload         4
      27: ifnonnull     68
      30: aload_3
      31: invokevirtual #92                 // Method org/apache/dubbo/common/url/component/DubboServiceAddressURL.getApplication:()Ljava/lang/String;
      34: astore        5
      36: aload_3
      37: invokevirtual #93                 // Method org/apache/dubbo/common/url/component/DubboServiceAddressURL.getSide:()Ljava/lang/String;
      40: astore        6
      42: aload_3
      43: invokestatic  #94                 // Method org/apache/dubbo/common/URLBuilder.from:(Lorg/apache/dubbo/common/URL;)Lorg/apache/dubbo/common/URLBuilder;
      46: invokevirtual #95                 // Method org/apache/dubbo/common/URLBuilder.clearParameters:()Lorg/apache/dubbo/common/URLBuilder;
      49: ldc           #96                 // String application
      51: aload         5
      53: invokevirtual #97                 // Method org/apache/dubbo/common/URLBuilder.addParameter:(Ljava/lang/String;Ljava/lang/String;)Lorg/apache/dubbo/common/URLBuilder;
      56: ldc           #98                 // String side
      58: aload         6
      60: invokevirtual #97                 // Method org/apache/dubbo/common/URLBuilder.addParameter:(Ljava/lang/String;Ljava/lang/String;)Lorg/apache/dubbo/common/URLBuilder;
      63: invokevirtual #99                 // Method org/apache/dubbo/common/URLBuilder.build:()Lorg/apache/dubbo/common/url/component/ServiceConfigURL;
      66: astore        4
      68: aload_1
      69: invokeinterface #79,  1           // InterfaceMethod java/util/List.iterator:()Ljava/util/Iterator;
      74: astore        5
      76: aload         5
      78: invokeinterface #26,  1           // InterfaceMethod java/util/Iterator.hasNext:()Z
      83: ifeq          112
      86: aload         5
      88: invokeinterface #21,  1           // InterfaceMethod java/util/Iterator.next:()Ljava/lang/Object;
      93: checkcast     #100                // class org/apache/dubbo/rpc/cluster/Configurator
      96: astore        6
      98: aload         6
     100: aload         4
     102: invokeinterface #101,  2          // InterfaceMethod org/apache/dubbo/rpc/cluster/Configurator.configure:(Lorg/apache/dubbo/common/URL;)Lorg/apache/dubbo/common/URL;
     107: astore        4
     109: goto          76
     112: new           #90                 // class org/apache/dubbo/common/url/component/DubboServiceAddressURL
     115: dup
     116: aload_3
     117: invokevirtual #102                // Method org/apache/dubbo/common/url/component/DubboServiceAddressURL.getUrlAddress:()Lorg/apache/dubbo/common/url/component/URLAddress;
     120: aload_3
     121: invokevirtual #103                // Method org/apache/dubbo/common/url/component/DubboServiceAddressURL.getUrlParam:()Lorg/apache/dubbo/common/url/component/URLParam;
     124: aload_3
     125: invokevirtual #104                // Method org/apache/dubbo/common/url/component/DubboServiceAddressURL.getConsumerURL:()Lorg/apache/dubbo/common/URL;
     128: aload         4
     130: checkcast     #105                // class org/apache/dubbo/common/url/component/ServiceConfigURL
     133: invokespecial #106                // Method org/apache/dubbo/common/url/component/DubboServiceAddressURL."<init>":(Lorg/apache/dubbo/common/url/component/URLAddress;Lorg/apache/dubbo/common/url/component/URLParam;Lorg/apache/dubbo/common/URL;Lorg/apache/dubbo/common/url/component/ServiceConfigURL;)V
     136: astore_2
     137: goto          179
     140: aload_1
     141: invokeinterface #79,  1           // InterfaceMethod java/util/List.iterator:()Ljava/util/Iterator;
     146: astore_3
     147: aload_3
     148: invokeinterface #26,  1           // InterfaceMethod java/util/Iterator.hasNext:()Z
     153: ifeq          179
     156: aload_3
     157: invokeinterface #21,  1           // InterfaceMethod java/util/Iterator.next:()Ljava/lang/Object;
     162: checkcast     #100                // class org/apache/dubbo/rpc/cluster/Configurator
     165: astore        4
     167: aload         4
     169: aload_2
     170: invokeinterface #101,  2          // InterfaceMethod org/apache/dubbo/rpc/cluster/Configurator.configure:(Lorg/apache/dubbo/common/URL;)Lorg/apache/dubbo/common/URL;
     175: astore_2
     176: goto          147
     179: aload_2
     180: areturn

  protected org.apache.dubbo.registry.client.InstanceAddressURL overrideWithConfigurator(org.apache.dubbo.registry.client.InstanceAddressURL);
    Code:
       0: aload_0
       1: aload_0
       2: aload_0
       3: getfield      #12                 // Field moduleModel:Lorg/apache/dubbo/rpc/model/ModuleModel;
       6: invokespecial #48                 // Method getConsumerConfigurationListener:(Lorg/apache/dubbo/rpc/model/ModuleModel;)Lorg/apache/dubbo/registry/client/ServiceDiscoveryRegistryDirectory$ConsumerConfigurationListener;
       9: invokevirtual #86                 // Method org/apache/dubbo/registry/client/ServiceDiscoveryRegistryDirectory$ConsumerConfigurationListener.getConfigurators:()Ljava/util/List;
      12: aload_1
      13: invokespecial #107                // Method overrideWithConfigurators:(Ljava/util/List;Lorg/apache/dubbo/registry/client/InstanceAddressURL;)Lorg/apache/dubbo/registry/client/InstanceAddressURL;
      16: astore_1
      17: aload_0
      18: getfield      #52                 // Field referenceConfigurationListener:Lorg/apache/dubbo/registry/client/ServiceDiscoveryRegistryDirectory$ReferenceConfigurationListener;
      21: ifnull        37
      24: aload_0
      25: aload_0
      26: getfield      #52                 // Field referenceConfigurationListener:Lorg/apache/dubbo/registry/client/ServiceDiscoveryRegistryDirectory$ReferenceConfigurationListener;
      29: invokevirtual #88                 // Method org/apache/dubbo/registry/client/ServiceDiscoveryRegistryDirectory$ReferenceConfigurationListener.getConfigurators:()Ljava/util/List;
      32: aload_1
      33: invokespecial #107                // Method overrideWithConfigurators:(Ljava/util/List;Lorg/apache/dubbo/registry/client/InstanceAddressURL;)Lorg/apache/dubbo/registry/client/InstanceAddressURL;
      36: astore_1
      37: aload_1
      38: areturn

  private org.apache.dubbo.registry.client.InstanceAddressURL overrideWithConfigurators(java.util.List<org.apache.dubbo.rpc.cluster.Configurator>, org.apache.dubbo.registry.client.InstanceAddressURL);
    Code:
       0: aload_1
       1: invokestatic  #89                 // Method org/apache/dubbo/common/utils/CollectionUtils.isNotEmpty:(Ljava/util/Collection;)Z
       4: ifeq          82
       7: new           #108                // class org/apache/dubbo/registry/client/OverrideInstanceAddressURL
      10: dup
      11: aload_2
      12: invokespecial #109                // Method org/apache/dubbo/registry/client/OverrideInstanceAddressURL."<init>":(Lorg/apache/dubbo/registry/client/InstanceAddressURL;)V
      15: astore_3
      16: aload_0
      17: getfield      #110                // Field overrideQueryMap:Ljava/util/Map;
      20: ifnull        35
      23: aload_3
      24: aload_0
      25: getfield      #110                // Field overrideQueryMap:Ljava/util/Map;
      28: invokevirtual #111                // Method org/apache/dubbo/registry/client/OverrideInstanceAddressURL.addParameters:(Ljava/util/Map;)Lorg/apache/dubbo/common/URL;
      31: checkcast     #108                // class org/apache/dubbo/registry/client/OverrideInstanceAddressURL
      34: astore_3
      35: aload_1
      36: invokeinterface #79,  1           // InterfaceMethod java/util/List.iterator:()Ljava/util/Iterator;
      41: astore        4
      43: aload         4
      45: invokeinterface #26,  1           // InterfaceMethod java/util/Iterator.hasNext:()Z
      50: ifeq          80
      53: aload         4
      55: invokeinterface #21,  1           // InterfaceMethod java/util/Iterator.next:()Ljava/lang/Object;
      60: checkcast     #100                // class org/apache/dubbo/rpc/cluster/Configurator
      63: astore        5
      65: aload         5
      67: aload_3
      68: invokeinterface #101,  2          // InterfaceMethod org/apache/dubbo/rpc/cluster/Configurator.configure:(Lorg/apache/dubbo/common/URL;)Lorg/apache/dubbo/common/URL;
      73: checkcast     #108                // class org/apache/dubbo/registry/client/OverrideInstanceAddressURL
      76: astore_3
      77: goto          43
      80: aload_3
      81: areturn
      82: aload_2
      83: areturn

  public boolean isServiceDiscovery();
    Code:
       0: iconst_1
       1: ireturn

  public boolean isNotificationReceived();
    Code:
       0: aload_0
       1: getfield      #112                // Field serviceListener:Lorg/apache/dubbo/registry/client/event/listener/ServiceInstancesChangedListener;
       4: ifnull        44
       7: aload_0
       8: getfield      #112                // Field serviceListener:Lorg/apache/dubbo/registry/client/event/listener/ServiceInstancesChangedListener;
      11: invokevirtual #113                // Method org/apache/dubbo/registry/client/event/listener/ServiceInstancesChangedListener.isDestroyed:()Z
      14: ifne          44
      17: aload_0
      18: getfield      #112                // Field serviceListener:Lorg/apache/dubbo/registry/client/event/listener/ServiceInstancesChangedListener;
      21: invokevirtual #114                // Method org/apache/dubbo/registry/client/event/listener/ServiceInstancesChangedListener.getAllInstances:()Ljava/util/Map;
      24: invokeinterface #115,  1          // InterfaceMethod java/util/Map.size:()I
      29: aload_0
      30: getfield      #112                // Field serviceListener:Lorg/apache/dubbo/registry/client/event/listener/ServiceInstancesChangedListener;
      33: invokevirtual #116                // Method org/apache/dubbo/registry/client/event/listener/ServiceInstancesChangedListener.getServiceNames:()Ljava/util/Set;
      36: invokeinterface #19,  1           // InterfaceMethod java/util/Set.size:()I
      41: if_icmpne     48
      44: iconst_1
      45: goto          49
      48: iconst_0
      49: ireturn

  private void refreshInvoker(java.util.List<org.apache.dubbo.common.URL>);
    Code:
       0: aload_1
       1: ldc           #117                // String invokerUrls should not be null, use EMPTY url to clear current addresses.
       3: invokestatic  #118                // Method org/apache/dubbo/common/utils/Assert.notNull:(Ljava/lang/Object;Ljava/lang/String;)V
       6: aload_0
       7: aload_1
       8: putfield      #4                  // Field originalUrls:Ljava/util/List;
      11: aload_1
      12: invokeinterface #119,  1          // InterfaceMethod java/util/List.size:()I
      17: iconst_1
      18: if_icmpne     78
      21: ldc           #120                // String empty
      23: aload_1
      24: iconst_0
      25: invokeinterface #121,  2          // InterfaceMethod java/util/List.get:(I)Ljava/lang/Object;
      30: checkcast     #122                // class org/apache/dubbo/common/URL
      33: invokevirtual #30                 // Method org/apache/dubbo/common/URL.getProtocol:()Ljava/lang/String;
      36: invokevirtual #37                 // Method java/lang/String.equals:(Ljava/lang/Object;)Z
      39: ifeq          78
      42: getstatic     #123                // Field logger:Lorg/apache/dubbo/common/logger/ErrorTypeAwareLogger;
      45: ldc           #124                // String 4-1
      47: ldc           #125                // String
      49: ldc           #125                // String
      51: ldc           #126                // String Received url with EMPTY protocol, will clear all available addresses.
      53: invokeinterface #127,  5          // InterfaceMethod org/apache/dubbo/common/logger/ErrorTypeAwareLogger.warn:(Ljava/lang/String;Ljava/lang/String;Ljava/lang/String;Ljava/lang/String;)V
      58: aload_0
      59: invokestatic  #128                // Method org/apache/dubbo/rpc/cluster/router/state/BitList.emptyList:()Lorg/apache/dubbo/rpc/cluster/router/state/BitList;
      62: aload_0
      63: invokedynamic #129,  0            // InvokeDynamic #1:run:(Lorg/apache/dubbo/registry/client/ServiceDiscoveryRegistryDirectory;)Ljava/lang/Runnable;
      68: invokevirtual #130                // Method refreshRouter:(Lorg/apache/dubbo/rpc/cluster/router/state/BitList;Ljava/lang/Runnable;)V
      71: aload_0
      72: invokevirtual #131                // Method destroyAllInvokers:()V
      75: goto          370
      78: aload_0
      79: iconst_0
      80: putfield      #132                // Field forbidden:Z
      83: aload_1
      84: invokestatic  #17                 // Method org/apache/dubbo/common/utils/CollectionUtils.isEmpty:(Ljava/util/Collection;)Z
      87: ifeq          107
      90: getstatic     #123                // Field logger:Lorg/apache/dubbo/common/logger/ErrorTypeAwareLogger;
      93: ldc           #124                // String 4-1
      95: ldc           #125                // String
      97: ldc           #125                // String
      99: ldc           #133                // String Received empty url list, will ignore for protection purpose.
     101: invokeinterface #127,  5          // InterfaceMethod org/apache/dubbo/common/logger/ErrorTypeAwareLogger.warn:(Ljava/lang/String;Ljava/lang/String;Ljava/lang/String;Ljava/lang/String;)V
     106: return
     107: aload_0
     108: getfield      #134                // Field urlInvokerMap:Ljava/util/Map;
     111: astore_2
     112: aconst_null
     113: astore_3
     114: aload_2
     115: ifnull        158
     118: new           #135                // class java/util/LinkedHashMap
     121: dup
     122: fconst_1
     123: aload_2
     124: invokeinterface #115,  1          // InterfaceMethod java/util/Map.size:()I
     129: i2f
     130: ldc           #136                // float 0.75f
     132: fdiv
     133: fadd
     134: invokestatic  #137                // Method java/lang/Math.round:(F)I
     137: invokespecial #138                // Method java/util/LinkedHashMap."<init>":(I)V
     140: astore_3
     141: aload_2
     142: aload_3
     143: dup
     144: invokevirtual #139                // Method java/lang/Object.getClass:()Ljava/lang/Class;
     147: pop
     148: invokedynamic #140,  0            // InvokeDynamic #2:accept:(Ljava/util/Map;)Ljava/util/function/BiConsumer;
     153: invokeinterface #141,  2          // InterfaceMethod java/util/Map.forEach:(Ljava/util/function/BiConsumer;)V
     158: aload_0
     159: aload_3
     160: aload_1
     161: invokespecial #142                // Method toInvokers:(Ljava/util/Map;Ljava/util/List;)Ljava/util/Map;
     164: astore        4
     166: getstatic     #123                // Field logger:Lorg/apache/dubbo/common/logger/ErrorTypeAwareLogger;
     169: new           #143                // class java/lang/StringBuilder
     172: dup
     173: invokespecial #144                // Method java/lang/StringBuilder."<init>":()V
     176: ldc           #145                // String Refreshed invoker size
     178: invokevirtual #146                // Method java/lang/StringBuilder.append:(Ljava/lang/String;)Ljava/lang/StringBuilder;
     181: aload         4
     183: invokeinterface #115,  1          // InterfaceMethod java/util/Map.size:()I
     188: invokevirtual #147                // Method java/lang/StringBuilder.append:(I)Ljava/lang/StringBuilder;
     191: invokevirtual #148                // Method java/lang/StringBuilder.toString:()Ljava/lang/String;
     194: invokeinterface #149,  2          // InterfaceMethod org/apache/dubbo/common/logger/ErrorTypeAwareLogger.info:(Ljava/lang/String;)V
     199: aload         4
     201: invokestatic  #150                // Method org/apache/dubbo/common/utils/CollectionUtils.isEmptyMap:(Ljava/util/Map;)Z
     204: ifeq          260
     207: getstatic     #123                // Field logger:Lorg/apache/dubbo/common/logger/ErrorTypeAwareLogger;
     210: ldc           #124                // String 4-1
     212: ldc           #125                // String
     214: ldc           #125                // String
     216: ldc           #151                // String Unsupported protocol.
     218: new           #152                // class java/lang/IllegalStateException
     221: dup
     222: new           #143                // class java/lang/StringBuilder
     225: dup
     226: invokespecial #144                // Method java/lang/StringBuilder."<init>":()V
     229: ldc           #153                // String Cannot create invokers from url address list (total
     231: invokevirtual #146                // Method java/lang/StringBuilder.append:(Ljava/lang/String;)Ljava/lang/StringBuilder;
     234: aload_1
     235: invokeinterface #119,  1          // InterfaceMethod java/util/List.size:()I
     240: invokevirtual #147                // Method java/lang/StringBuilder.append:(I)Ljava/lang/StringBuilder;
     243: ldc           #154                // String )
     245: invokevirtual #146                // Method java/lang/StringBuilder.append:(Ljava/lang/String;)Ljava/lang/StringBuilder;
     248: invokevirtual #148                // Method java/lang/StringBuilder.toString:()Ljava/lang/String;
     251: invokespecial #155                // Method java/lang/IllegalStateException."<init>":(Ljava/lang/String;)V
     254: invokeinterface #156,  6          // InterfaceMethod org/apache/dubbo/common/logger/ErrorTypeAwareLogger.error:(Ljava/lang/String;Ljava/lang/String;Ljava/lang/String;Ljava/lang/String;Ljava/lang/Throwable;)V
     259: return
     260: new           #157                // class java/util/ArrayList
     263: dup
     264: aload         4
     266: invokeinterface #158,  1          // InterfaceMethod java/util/Map.values:()Ljava/util/Collection;
     271: invokespecial #159                // Method java/util/ArrayList."<init>":(Ljava/util/Collection;)V
     274: invokestatic  #160                // Method java/util/Collections.unmodifiableList:(Ljava/util/List;)Ljava/util/List;
     277: astore        5
     279: aload_0
     280: getfield      #161                // Field multiGroup:Z
     283: ifeq          302
     286: new           #162                // class org/apache/dubbo/rpc/cluster/router/state/BitList
     289: dup
     290: aload_0
     291: aload         5
     293: invokespecial #163                // Method toMergeInvokerList:(Ljava/util/List;)Ljava/util/List;
     296: invokespecial #164                // Method org/apache/dubbo/rpc/cluster/router/state/BitList."<init>":(Ljava/util/List;)V
     299: goto          311
     302: new           #162                // class org/apache/dubbo/rpc/cluster/router/state/BitList
     305: dup
     306: aload         5
     308: invokespecial #164                // Method org/apache/dubbo/rpc/cluster/router/state/BitList."<init>":(Ljava/util/List;)V
     311: astore        6
     313: aload_0
     314: aload         6
     316: invokevirtual #165                // Method org/apache/dubbo/rpc/cluster/router/state/BitList.clone:()Lorg/apache/dubbo/rpc/cluster/router/state/BitList;
     319: aload_0
     320: aload         6
     322: invokedynamic #166,  0            // InvokeDynamic #3:run:(Lorg/apache/dubbo/registry/client/ServiceDiscoveryRegistryDirectory;Lorg/apache/dubbo/rpc/cluster/router/state/BitList;)Ljava/lang/Runnable;
     327: invokevirtual #130                // Method refreshRouter:(Lorg/apache/dubbo/rpc/cluster/router/state/BitList;Ljava/lang/Runnable;)V
     330: aload_0
     331: aload         4
     333: putfield      #134                // Field urlInvokerMap:Ljava/util/Map;
     336: aload_3
     337: ifnull        370
     340: aload_0
     341: aload_3
     342: aload         4
     344: invokespecial #167                // Method destroyUnusedInvokers:(Ljava/util/Map;Ljava/util/Map;)V
     347: goto          370
     350: astore        7
     352: getstatic     #123                // Field logger:Lorg/apache/dubbo/common/logger/ErrorTypeAwareLogger;
     355: ldc           #169                // String 4-17
     357: ldc           #125                // String
     359: ldc           #125                // String
     361: ldc           #170                // String destroyUnusedInvokers error.
     363: aload         7
     365: invokeinterface #171,  6          // InterfaceMethod org/apache/dubbo/common/logger/ErrorTypeAwareLogger.warn:(Ljava/lang/String;Ljava/lang/String;Ljava/lang/String;Ljava/lang/String;Ljava/lang/Throwable;)V
     370: aload_0
     371: invokevirtual #172                // Method invokersChanged:()V
     374: getstatic     #123                // Field logger:Lorg/apache/dubbo/common/logger/ErrorTypeAwareLogger;
     377: new           #143                // class java/lang/StringBuilder
     380: dup
     381: invokespecial #144                // Method java/lang/StringBuilder."<init>":()V
     384: ldc           #173                // String Received invokers changed event from registry. Registry type: instance. Service Key:
     386: invokevirtual #146                // Method java/lang/StringBuilder.append:(Ljava/lang/String;)Ljava/lang/StringBuilder;
     389: aload_0
     390: invokevirtual #70                 // Method getConsumerUrl:()Lorg/apache/dubbo/common/URL;
     393: invokevirtual #174                // Method org/apache/dubbo/common/URL.getServiceKey:()Ljava/lang/String;
     396: invokevirtual #146                // Method java/lang/StringBuilder.append:(Ljava/lang/String;)Ljava/lang/StringBuilder;
     399: ldc           #175                // String . Urls Size :
     401: invokevirtual #146                // Method java/lang/StringBuilder.append:(Ljava/lang/String;)Ljava/lang/StringBuilder;
     404: aload_1
     405: invokeinterface #119,  1          // InterfaceMethod java/util/List.size:()I
     410: invokevirtual #147                // Method java/lang/StringBuilder.append:(I)Ljava/lang/StringBuilder;
     413: ldc           #176                // String . Invokers Size :
     415: invokevirtual #146                // Method java/lang/StringBuilder.append:(Ljava/lang/String;)Ljava/lang/StringBuilder;
     418: aload_0
     419: invokevirtual #177                // Method getInvokers:()Lorg/apache/dubbo/rpc/cluster/router/state/BitList;
     422: invokevirtual #178                // Method org/apache/dubbo/rpc/cluster/router/state/BitList.size:()I
     425: invokevirtual #147                // Method java/lang/StringBuilder.append:(I)Ljava/lang/StringBuilder;
     428: ldc           #179                // String . Available Size:
     430: invokevirtual #146                // Method java/lang/StringBuilder.append:(Ljava/lang/String;)Ljava/lang/StringBuilder;
     433: aload_0
     434: invokevirtual #180                // Method getValidInvokers:()Lorg/apache/dubbo/rpc/cluster/router/state/BitList;
     437: invokevirtual #178                // Method org/apache/dubbo/rpc/cluster/router/state/BitList.size:()I
     440: invokevirtual #147                // Method java/lang/StringBuilder.append:(I)Ljava/lang/StringBuilder;
     443: ldc           #181                // String . Available Invokers :
     445: invokevirtual #146                // Method java/lang/StringBuilder.append:(Ljava/lang/String;)Ljava/lang/StringBuilder;
     448: aload_0
     449: invokevirtual #182                // Method joinValidInvokerAddresses:()Ljava/lang/String;
     452: invokevirtual #146                // Method java/lang/StringBuilder.append:(Ljava/lang/String;)Ljava/lang/StringBuilder;
     455: invokevirtual #148                // Method java/lang/StringBuilder.toString:()Ljava/lang/String;
     458: invokeinterface #149,  2          // InterfaceMethod org/apache/dubbo/common/logger/ErrorTypeAwareLogger.info:(Ljava/lang/String;)V
     463: return
    Exception table:
       from    to  target type
         340   347   350   Class java/lang/Exception

  private java.util.Map<org.apache.dubbo.registry.client.ServiceDiscoveryRegistryDirectory$ProtocolServiceKeyWithAddress, org.apache.dubbo.rpc.Invoker<T>> toInvokers(java.util.Map<org.apache.dubbo.registry.client.ServiceDiscoveryRegistryDirectory$ProtocolServiceKeyWithAddress, org.apache.dubbo.rpc.Invoker<T>>, java.util.List<org.apache.dubbo.common.URL>);
    Code:
       0: new           #7                  // class java/util/concurrent/ConcurrentHashMap
       3: dup
       4: aload_2
       5: ifnonnull     12
       8: iconst_1
       9: goto          25
      12: aload_2
      13: invokeinterface #119,  1          // InterfaceMethod java/util/List.size:()I
      18: i2f
      19: ldc           #136                // float 0.75f
      21: fdiv
      22: fconst_1
      23: fadd
      24: f2i
      25: invokespecial #183                // Method java/util/concurrent/ConcurrentHashMap."<init>":(I)V
      28: astore_3
      29: aload_2
      30: ifnull        42
      33: aload_2
      34: invokeinterface #78,  1           // InterfaceMethod java/util/List.isEmpty:()Z
      39: ifeq          44
      42: aload_3
      43: areturn
      44: aload_2
      45: invokeinterface #79,  1           // InterfaceMethod java/util/List.iterator:()Ljava/util/Iterator;
      50: astore        4
      52: aload         4
      54: invokeinterface #26,  1           // InterfaceMethod java/util/Iterator.hasNext:()Z
      59: ifeq          676
      62: aload         4
      64: invokeinterface #21,  1           // InterfaceMethod java/util/Iterator.next:()Ljava/lang/Object;
      69: checkcast     #122                // class org/apache/dubbo/common/URL
      72: astore        5
      74: aload         5
      76: checkcast     #184                // class org/apache/dubbo/registry/client/InstanceAddressURL
      79: astore        6
      81: ldc           #120                // String empty
      83: aload         6
      85: invokevirtual #185                // Method org/apache/dubbo/registry/client/InstanceAddressURL.getProtocol:()Ljava/lang/String;
      88: invokevirtual #37                 // Method java/lang/String.equals:(Ljava/lang/Object;)Z
      91: ifeq          97
      94: goto          52
      97: aload_0
      98: invokevirtual #72                 // Method getUrl:()Lorg/apache/dubbo/common/URL;
     101: invokevirtual #186                // Method org/apache/dubbo/common/URL.getOrDefaultFrameworkModel:()Lorg/apache/dubbo/rpc/model/FrameworkModel;
     104: ldc           #187                // class org/apache/dubbo/rpc/Protocol
     106: invokevirtual #188                // Method org/apache/dubbo/rpc/model/FrameworkModel.getExtensionLoader:(Ljava/lang/Class;)Lorg/apache/dubbo/common/extension/ExtensionLoader;
     109: aload         6
     111: invokevirtual #185                // Method org/apache/dubbo/registry/client/InstanceAddressURL.getProtocol:()Ljava/lang/String;
     114: invokevirtual #189                // Method org/apache/dubbo/common/extension/ExtensionLoader.hasExtension:(Ljava/lang/String;)Z
     117: ifne          228
     120: getstatic     #123                // Field logger:Lorg/apache/dubbo/common/logger/ErrorTypeAwareLogger;
     123: ldc           #124                // String 4-1
     125: ldc           #190                // String protocol extension does not installed
     127: ldc           #125                // String
     129: ldc           #151                // String Unsupported protocol.
     131: new           #152                // class java/lang/IllegalStateException
     134: dup
     135: new           #143                // class java/lang/StringBuilder
     138: dup
     139: invokespecial #144                // Method java/lang/StringBuilder."<init>":()V
     142: ldc           #191                // String Unsupported protocol
     144: invokevirtual #146                // Method java/lang/StringBuilder.append:(Ljava/lang/String;)Ljava/lang/StringBuilder;
     147: aload         6
     149: invokevirtual #185                // Method org/apache/dubbo/registry/client/InstanceAddressURL.getProtocol:()Ljava/lang/String;
     152: invokevirtual #146                // Method java/lang/StringBuilder.append:(Ljava/lang/String;)Ljava/lang/StringBuilder;
     155: ldc           #192                // String  in notified url:
     157: invokevirtual #146                // Method java/lang/StringBuilder.append:(Ljava/lang/String;)Ljava/lang/StringBuilder;
     160: aload         6
     162: invokevirtual #193                // Method java/lang/StringBuilder.append:(Ljava/lang/Object;)Ljava/lang/StringBuilder;
     165: ldc           #194                // String  from registry
     167: invokevirtual #146                // Method java/lang/StringBuilder.append:(Ljava/lang/String;)Ljava/lang/StringBuilder;
     170: aload_0
     171: invokevirtual #72                 // Method getUrl:()Lorg/apache/dubbo/common/URL;
     174: invokevirtual #195                // Method org/apache/dubbo/common/URL.getAddress:()Ljava/lang/String;
     177: invokevirtual #146                // Method java/lang/StringBuilder.append:(Ljava/lang/String;)Ljava/lang/StringBuilder;
     180: ldc           #196                // String  to consumer
     182: invokevirtual #146                // Method java/lang/StringBuilder.append:(Ljava/lang/String;)Ljava/lang/StringBuilder;
     185: invokestatic  #197                // Method org/apache/dubbo/common/utils/NetUtils.getLocalHost:()Ljava/lang/String;
     188: invokevirtual #146                // Method java/lang/StringBuilder.append:(Ljava/lang/String;)Ljava/lang/StringBuilder;
     191: ldc           #198                // String , supported protocol:
     193: invokevirtual #146                // Method java/lang/StringBuilder.append:(Ljava/lang/String;)Ljava/lang/StringBuilder;
     196: aload_0
     197: invokevirtual #72                 // Method getUrl:()Lorg/apache/dubbo/common/URL;
     200: invokevirtual #186                // Method org/apache/dubbo/common/URL.getOrDefaultFrameworkModel:()Lorg/apache/dubbo/rpc/model/FrameworkModel;
     203: ldc           #187                // class org/apache/dubbo/rpc/Protocol
     205: invokevirtual #188                // Method org/apache/dubbo/rpc/model/FrameworkModel.getExtensionLoader:(Ljava/lang/Class;)Lorg/apache/dubbo/common/extension/ExtensionLoader;
     208: invokevirtual #199                // Method org/apache/dubbo/common/extension/ExtensionLoader.getSupportedExtensions:()Ljava/util/Set;
     211: invokevirtual #193                // Method java/lang/StringBuilder.append:(Ljava/lang/Object;)Ljava/lang/StringBuilder;
     214: invokevirtual #148                // Method java/lang/StringBuilder.toString:()Ljava/lang/String;
     217: invokespecial #155                // Method java/lang/IllegalStateException."<init>":(Ljava/lang/String;)V
     220: invokeinterface #156,  6          // InterfaceMethod org/apache/dubbo/common/logger/ErrorTypeAwareLogger.error:(Ljava/lang/String;Ljava/lang/String;Ljava/lang/String;Ljava/lang/String;Ljava/lang/Throwable;)V
     225: goto          52
     228: aload         6
     230: aload_0
     231: getfield      #18                 // Field providerFirstParams:Ljava/util/Set;
     234: invokevirtual #200                // Method org/apache/dubbo/registry/client/InstanceAddressURL.setProviderFirstParams:(Ljava/util/Set;)V
     237: aload_0
     238: getfield      #6                  // Field enableConfigurationListen:Z
     241: ifeq          252
     244: aload_0
     245: aload         6
     247: invokevirtual #201                // Method overrideWithConfigurator:(Lorg/apache/dubbo/registry/client/InstanceAddressURL;)Lorg/apache/dubbo/registry/client/InstanceAddressURL;
     250: astore        6
     252: aload         6
     254: invokevirtual #202                // Method org/apache/dubbo/registry/client/InstanceAddressURL.getPort:()I
     257: istore        7
     259: aload         6
     261: invokevirtual #203                // Method org/apache/dubbo/registry/client/InstanceAddressURL.getMetadataInfo:()Lorg/apache/dubbo/metadata/MetadataInfo;
     264: aload_0
     265: getfield      #39                 // Field consumerProtocolServiceKey:Lorg/apache/dubbo/common/ProtocolServiceKey;
     268: invokevirtual #204                // Method org/apache/dubbo/metadata/MetadataInfo.getMatchedServiceInfos:(Lorg/apache/dubbo/common/ProtocolServiceKey;)Ljava/util/List;
     271: invokeinterface #205,  1          // InterfaceMethod java/util/List.stream:()Ljava/util/stream/Stream;
     276: iload         7
     278: invokedynamic #206,  0            // InvokeDynamic #4:test:(I)Ljava/util/function/Predicate;
     283: invokeinterface #207,  2          // InterfaceMethod java/util/stream/Stream.filter:(Ljava/util/function/Predicate;)Ljava/util/stream/Stream;
     288: invokedynamic #208,  0            // InvokeDynamic #5:apply:()Ljava/util/function/Function;
     293: invokeinterface #209,  2          // InterfaceMethod java/util/stream/Stream.map:(Ljava/util/function/Function;)Ljava/util/stream/Stream;
     298: invokestatic  #210                // Method java/util/stream/Collectors.toList:()Ljava/util/stream/Collector;
     301: invokeinterface #211,  2          // InterfaceMethod java/util/stream/Stream.collect:(Ljava/util/stream/Collector;)Ljava/lang/Object;
     306: checkcast     #212                // class java/util/List
     309: astore        8
     311: aload         8
     313: invokeinterface #119,  1          // InterfaceMethod java/util/List.size:()I
     318: iconst_1
     319: if_icmpne     343
     322: aload_0
     323: getfield      #39                 // Field consumerProtocolServiceKey:Lorg/apache/dubbo/common/ProtocolServiceKey;
     326: aload         8
     328: iconst_0
     329: invokeinterface #121,  2          // InterfaceMethod java/util/List.get:(I)Ljava/lang/Object;
     334: checkcast     #32                 // class org/apache/dubbo/common/ProtocolServiceKey
     337: invokevirtual #213                // Method org/apache/dubbo/common/ProtocolServiceKey.isSameWith:(Lorg/apache/dubbo/common/ProtocolServiceKey;)Z
     340: ifne          347
     343: iconst_1
     344: goto          348
     347: iconst_0
     348: istore        9
     350: aload         8
     352: invokeinterface #79,  1           // InterfaceMethod java/util/List.iterator:()Ljava/util/Iterator;
     357: astore        10
     359: aload         10
     361: invokeinterface #26,  1           // InterfaceMethod java/util/Iterator.hasNext:()Z
     366: ifeq          673
     369: aload         10
     371: invokeinterface #21,  1           // InterfaceMethod java/util/Iterator.next:()Ljava/lang/Object;
     376: checkcast     #32                 // class org/apache/dubbo/common/ProtocolServiceKey
     379: astore        11
     381: new           #214                // class org/apache/dubbo/registry/client/ServiceDiscoveryRegistryDirectory$ProtocolServiceKeyWithAddress
     384: dup
     385: aload         11
     387: aload         6
     389: invokevirtual #215                // Method org/apache/dubbo/registry/client/InstanceAddressURL.getAddress:()Ljava/lang/String;
     392: invokespecial #216                // Method org/apache/dubbo/registry/client/ServiceDiscoveryRegistryDirectory$ProtocolServiceKeyWithAddress."<init>":(Lorg/apache/dubbo/common/ProtocolServiceKey;Ljava/lang/String;)V
     395: astore        12
     397: aload_1
     398: ifnonnull     405
     401: aconst_null
     402: goto          416
     405: aload_1
     406: aload         12
     408: invokeinterface #217,  2          // InterfaceMethod java/util/Map.get:(Ljava/lang/Object;)Ljava/lang/Object;
     413: checkcast     #218                // class org/apache/dubbo/rpc/Invoker
     416: astore        13
     418: aload         13
     420: ifnull        436
     423: aload_0
     424: aload         13
     426: aload         6
     428: aload         11
     430: invokespecial #219                // Method urlChanged:(Lorg/apache/dubbo/rpc/Invoker;Lorg/apache/dubbo/registry/client/InstanceAddressURL;Lorg/apache/dubbo/common/ProtocolServiceKey;)Z
     433: ifeq          648
     436: aload         6
     438: ldc           #220                // String disabled
     440: invokevirtual #221                // Method org/apache/dubbo/registry/client/InstanceAddressURL.hasParameter:(Ljava/lang/String;)Z
     443: ifeq          467
     446: aload         6
     448: ldc           #220                // String disabled
     450: iconst_0
     451: invokevirtual #222                // Method org/apache/dubbo/registry/client/InstanceAddressURL.getParameter:(Ljava/lang/String;Z)Z
     454: ifne          461
     457: iconst_1
     458: goto          462
     461: iconst_0
     462: istore        14
     464: goto          477
     467: aload         6
     469: ldc           #223                // String enabled
     471: iconst_1
     472: invokevirtual #222                // Method org/apache/dubbo/registry/client/InstanceAddressURL.getParameter:(Ljava/lang/String;Z)Z
     475: istore        14
     477: iload         14
     479: ifeq          563
     482: iload         9
     484: ifeq          546
     487: aload_0
     488: getfield      #9                  // Field customizedConsumerUrlMap:Ljava/util/concurrent/ConcurrentMap;
     491: aload         11
     493: aload_0
     494: invokedynamic #224,  0            // InvokeDynamic #6:apply:(Lorg/apache/dubbo/registry/client/ServiceDiscoveryRegistryDirectory;)Ljava/util/function/Function;
     499: invokestatic  #225                // Method org/apache/dubbo/common/utils/ConcurrentHashMapUtils.computeIfAbsent:(Ljava/util/concurrent/ConcurrentMap;Ljava/lang/Object;Ljava/util/function/Function;)Ljava/lang/Object;
     502: checkcast     #122                // class org/apache/dubbo/common/URL
     505: astore        15
     507: invokestatic  #226                // Method org/apache/dubbo/rpc/RpcContext.getServiceContext:()Lorg/apache/dubbo/rpc/RpcServiceContext;
     510: aload         15
     512: invokevirtual #71                 // Method org/apache/dubbo/rpc/RpcServiceContext.setConsumerUrl:(Lorg/apache/dubbo/common/URL;)V
     515: new           #227                // class org/apache/dubbo/registry/client/ServiceDiscoveryRegistryDirectory$InstanceWrappedInvoker
     518: dup
     519: aload_0
     520: getfield      #228                // Field protocol:Lorg/apache/dubbo/rpc/Protocol;
     523: aload_0
     524: getfield      #229                // Field serviceType:Ljava/lang/Class;
     527: aload         6
     529: invokeinterface #230,  3          // InterfaceMethod org/apache/dubbo/rpc/Protocol.refer:(Ljava/lang/Class;Lorg/apache/dubbo/common/URL;)Lorg/apache/dubbo/rpc/Invoker;
     534: aload         15
     536: aload         11
     538: invokespecial #231                // Method org/apache/dubbo/registry/client/ServiceDiscoveryRegistryDirectory$InstanceWrappedInvoker."<init>":(Lorg/apache/dubbo/rpc/Invoker;Lorg/apache/dubbo/common/URL;Lorg/apache/dubbo/common/ProtocolServiceKey;)V
     541: astore        13
     543: goto          563
     546: aload_0
     547: getfield      #228                // Field protocol:Lorg/apache/dubbo/rpc/Protocol;
     550: aload_0
     551: getfield      #229                // Field serviceType:Ljava/lang/Class;
     554: aload         6
     556: invokeinterface #230,  3          // InterfaceMethod org/apache/dubbo/rpc/Protocol.refer:(Ljava/lang/Class;Lorg/apache/dubbo/common/URL;)Lorg/apache/dubbo/rpc/Invoker;
     561: astore        13
     563: goto          629
     566: astore        14
     568: getstatic     #123                // Field logger:Lorg/apache/dubbo/common/logger/ErrorTypeAwareLogger;
     571: ldc           #233                // String 4-3
     573: ldc           #125                // String
     575: ldc           #125                // String
     577: new           #143                // class java/lang/StringBuilder
     580: dup
     581: invokespecial #144                // Method java/lang/StringBuilder."<init>":()V
     584: ldc           #234                // String Failed to refer invoker for interface:
     586: invokevirtual #146                // Method java/lang/StringBuilder.append:(Ljava/lang/String;)Ljava/lang/StringBuilder;
     589: aload_0
     590: getfield      #229                // Field serviceType:Ljava/lang/Class;
     593: invokevirtual #193                // Method java/lang/StringBuilder.append:(Ljava/lang/Object;)Ljava/lang/StringBuilder;
     596: ldc           #235                // String ,url:(
     598: invokevirtual #146                // Method java/lang/StringBuilder.append:(Ljava/lang/String;)Ljava/lang/StringBuilder;
     601: aload         6
     603: invokevirtual #193                // Method java/lang/StringBuilder.append:(Ljava/lang/Object;)Ljava/lang/StringBuilder;
     606: ldc           #154                // String )
     608: invokevirtual #146                // Method java/lang/StringBuilder.append:(Ljava/lang/String;)Ljava/lang/StringBuilder;
     611: aload         14
     613: invokevirtual #236                // Method java/lang/Throwable.getMessage:()Ljava/lang/String;
     616: invokevirtual #146                // Method java/lang/StringBuilder.append:(Ljava/lang/String;)Ljava/lang/StringBuilder;
     619: invokevirtual #148                // Method java/lang/StringBuilder.toString:()Ljava/lang/String;
     622: aload         14
     624: invokeinterface #156,  6          // InterfaceMethod org/apache/dubbo/common/logger/ErrorTypeAwareLogger.error:(Ljava/lang/String;Ljava/lang/String;Ljava/lang/String;Ljava/lang/String;Ljava/lang/Throwable;)V
     629: aload         13
     631: ifnull        670
     634: aload_3
     635: aload         12
     637: aload         13
     639: invokeinterface #237,  3          // InterfaceMethod java/util/Map.put:(Ljava/lang/Object;Ljava/lang/Object;)Ljava/lang/Object;
     644: pop
     645: goto          670
     648: aload_3
     649: aload         12
     651: aload         13
     653: invokeinterface #237,  3          // InterfaceMethod java/util/Map.put:(Ljava/lang/Object;Ljava/lang/Object;)Ljava/lang/Object;
     658: pop
     659: aload_1
     660: aload         12
     662: aload         13
     664: invokeinterface #238,  3          // InterfaceMethod java/util/Map.remove:(Ljava/lang/Object;Ljava/lang/Object;)Z
     669: pop
     670: goto          359
     673: goto          52
     676: aload_3
     677: areturn
    Exception table:
       from    to  target type
         436   563   566   Class java/lang/Throwable

  private boolean urlChanged(org.apache.dubbo.rpc.Invoker<T>, org.apache.dubbo.registry.client.InstanceAddressURL, org.apache.dubbo.common.ProtocolServiceKey);
    Code:
       0: aload_1
       1: invokeinterface #239,  1          // InterfaceMethod org/apache/dubbo/rpc/Invoker.getUrl:()Lorg/apache/dubbo/common/URL;
       6: checkcast     #184                // class org/apache/dubbo/registry/client/InstanceAddressURL
       9: astore        4
      11: aload_2
      12: invokevirtual #240                // Method org/apache/dubbo/registry/client/InstanceAddressURL.getInstance:()Lorg/apache/dubbo/registry/client/ServiceInstance;
      15: aload         4
      17: invokevirtual #240                // Method org/apache/dubbo/registry/client/InstanceAddressURL.getInstance:()Lorg/apache/dubbo/registry/client/ServiceInstance;
      20: invokevirtual #241                // Method java/lang/Object.equals:(Ljava/lang/Object;)Z
      23: ifne          28
      26: iconst_1
      27: ireturn
      28: aload         4
      30: instanceof    #108                // class org/apache/dubbo/registry/client/OverrideInstanceAddressURL
      33: ifne          43
      36: aload_2
      37: instanceof    #108                // class org/apache/dubbo/registry/client/OverrideInstanceAddressURL
      40: ifeq          83
      43: aload         4
      45: instanceof    #108                // class org/apache/dubbo/registry/client/OverrideInstanceAddressURL
      48: ifeq          58
      51: aload_2
      52: instanceof    #108                // class org/apache/dubbo/registry/client/OverrideInstanceAddressURL
      55: ifne          60
      58: iconst_1
      59: ireturn
      60: aload         4
      62: checkcast     #108                // class org/apache/dubbo/registry/client/OverrideInstanceAddressURL
      65: invokevirtual #242                // Method org/apache/dubbo/registry/client/OverrideInstanceAddressURL.getOverrideParams:()Lorg/apache/dubbo/common/url/component/URLParam;
      68: aload_2
      69: checkcast     #108                // class org/apache/dubbo/registry/client/OverrideInstanceAddressURL
      72: invokevirtual #242                // Method org/apache/dubbo/registry/client/OverrideInstanceAddressURL.getOverrideParams:()Lorg/apache/dubbo/common/url/component/URLParam;
      75: invokevirtual #243                // Method org/apache/dubbo/common/url/component/URLParam.equals:(Ljava/lang/Object;)Z
      78: ifne          83
      81: iconst_1
      82: ireturn
      83: aload         4
      85: invokevirtual #203                // Method org/apache/dubbo/registry/client/InstanceAddressURL.getMetadataInfo:()Lorg/apache/dubbo/metadata/MetadataInfo;
      88: aload_3
      89: invokevirtual #244                // Method org/apache/dubbo/common/ProtocolServiceKey.toString:()Ljava/lang/String;
      92: invokevirtual #245                // Method org/apache/dubbo/metadata/MetadataInfo.getValidServiceInfo:(Ljava/lang/String;)Lorg/apache/dubbo/metadata/MetadataInfo$ServiceInfo;
      95: astore        5
      97: aconst_null
      98: aload         5
     100: if_acmpne     105
     103: iconst_0
     104: ireturn
     105: aload         5
     107: aload_2
     108: invokevirtual #203                // Method org/apache/dubbo/registry/client/InstanceAddressURL.getMetadataInfo:()Lorg/apache/dubbo/metadata/MetadataInfo;
     111: aload_3
     112: invokevirtual #244                // Method org/apache/dubbo/common/ProtocolServiceKey.toString:()Ljava/lang/String;
     115: invokevirtual #245                // Method org/apache/dubbo/metadata/MetadataInfo.getValidServiceInfo:(Ljava/lang/String;)Lorg/apache/dubbo/metadata/MetadataInfo$ServiceInfo;
     118: invokevirtual #246                // Method org/apache/dubbo/metadata/MetadataInfo$ServiceInfo.equals:(Ljava/lang/Object;)Z
     121: ifne          128
     124: iconst_1
     125: goto          129
     128: iconst_0
     129: ireturn

  private java.util.List<org.apache.dubbo.rpc.Invoker<T>> toMergeInvokerList(java.util.List<org.apache.dubbo.rpc.Invoker<T>>);
    Code:
       0: new           #157                // class java/util/ArrayList
       3: dup
       4: invokespecial #247                // Method java/util/ArrayList."<init>":()V
       7: astore_2
       8: new           #248                // class java/util/HashMap
      11: dup
      12: invokespecial #249                // Method java/util/HashMap."<init>":()V
      15: astore_3
      16: aload_1
      17: invokeinterface #79,  1           // InterfaceMethod java/util/List.iterator:()Ljava/util/Iterator;
      22: astore        4
      24: aload         4
      26: invokeinterface #26,  1           // InterfaceMethod java/util/Iterator.hasNext:()Z
      31: ifeq          96
      34: aload         4
      36: invokeinterface #21,  1           // InterfaceMethod java/util/Iterator.next:()Ljava/lang/Object;
      41: checkcast     #218                // class org/apache/dubbo/rpc/Invoker
      44: astore        5
      46: aload         5
      48: invokeinterface #239,  1          // InterfaceMethod org/apache/dubbo/rpc/Invoker.getUrl:()Lorg/apache/dubbo/common/URL;
      53: ldc           #125                // String
      55: invokevirtual #250                // Method org/apache/dubbo/common/URL.getGroup:(Ljava/lang/String;)Ljava/lang/String;
      58: astore        6
      60: aload_3
      61: aload         6
      63: invokedynamic #251,  0            // InvokeDynamic #7:apply:()Ljava/util/function/Function;
      68: invokeinterface #252,  3          // InterfaceMethod java/util/Map.computeIfAbsent:(Ljava/lang/Object;Ljava/util/function/Function;)Ljava/lang/Object;
      73: pop
      74: aload_3
      75: aload         6
      77: invokeinterface #217,  2          // InterfaceMethod java/util/Map.get:(Ljava/lang/Object;)Ljava/lang/Object;
      82: checkcast     #212                // class java/util/List
      85: aload         5
      87: invokeinterface #253,  2          // InterfaceMethod java/util/List.add:(Ljava/lang/Object;)Z
      92: pop
      93: goto          24
      96: aload_3
      97: invokeinterface #115,  1          // InterfaceMethod java/util/Map.size:()I
     102: iconst_1
     103: if_icmpne     135
     106: aload_2
     107: aload_3
     108: invokeinterface #158,  1          // InterfaceMethod java/util/Map.values:()Ljava/util/Collection;
     113: invokeinterface #254,  1          // InterfaceMethod java/util/Collection.iterator:()Ljava/util/Iterator;
     118: invokeinterface #21,  1           // InterfaceMethod java/util/Iterator.next:()Ljava/lang/Object;
     123: checkcast     #255                // class java/util/Collection
     126: invokeinterface #256,  2          // InterfaceMethod java/util/List.addAll:(Ljava/util/Collection;)Z
     131: pop
     132: goto          223
     135: aload_3
     136: invokeinterface #115,  1          // InterfaceMethod java/util/Map.size:()I
     141: iconst_1
     142: if_icmple     221
     145: aload_3
     146: invokeinterface #158,  1          // InterfaceMethod java/util/Map.values:()Ljava/util/Collection;
     151: invokeinterface #254,  1          // InterfaceMethod java/util/Collection.iterator:()Ljava/util/Iterator;
     156: astore        4
     158: aload         4
     160: invokeinterface #26,  1           // InterfaceMethod java/util/Iterator.hasNext:()Z
     165: ifeq          218
     168: aload         4
     170: invokeinterface #21,  1           // InterfaceMethod java/util/Iterator.next:()Ljava/lang/Object;
     175: checkcast     #212                // class java/util/List
     178: astore        5
     180: new           #257                // class org/apache/dubbo/rpc/cluster/directory/StaticDirectory
     183: dup
     184: aload         5
     186: invokespecial #258                // Method org/apache/dubbo/rpc/cluster/directory/StaticDirectory."<init>":(Ljava/util/List;)V
     189: astore        6
     191: aload         6
     193: invokevirtual #259                // Method org/apache/dubbo/rpc/cluster/directory/StaticDirectory.buildRouterChain:()V
     196: aload_2
     197: aload_0
     198: getfield      #260                // Field cluster:Lorg/apache/dubbo/rpc/cluster/Cluster;
     201: aload         6
     203: iconst_0
     204: invokeinterface #261,  3          // InterfaceMethod org/apache/dubbo/rpc/cluster/Cluster.join:(Lorg/apache/dubbo/rpc/cluster/Directory;Z)Lorg/apache/dubbo/rpc/Invoker;
     209: invokeinterface #253,  2          // InterfaceMethod java/util/List.add:(Ljava/lang/Object;)Z
     214: pop
     215: goto          158
     218: goto          223
     221: aload_1
     222: astore_2
     223: aload_2
     224: areturn

  protected void destroyAllInvokers();
    Code:
       0: aload_0
       1: getfield      #134                // Field urlInvokerMap:Ljava/util/Map;
       4: astore_1
       5: aload_1
       6: ifnull        119
       9: new           #157                // class java/util/ArrayList
      12: dup
      13: aload_1
      14: invokeinterface #158,  1          // InterfaceMethod java/util/Map.values:()Ljava/util/Collection;
      19: invokespecial #159                // Method java/util/ArrayList."<init>":(Ljava/util/Collection;)V
      22: invokevirtual #262                // Method java/util/ArrayList.iterator:()Ljava/util/Iterator;
      25: astore_2
      26: aload_2
      27: invokeinterface #26,  1           // InterfaceMethod java/util/Iterator.hasNext:()Z
      32: ifeq          113
      35: aload_2
      36: invokeinterface #21,  1           // InterfaceMethod java/util/Iterator.next:()Ljava/lang/Object;
      41: checkcast     #218                // class org/apache/dubbo/rpc/Invoker
      44: astore_3
      45: aload_3
      46: invokeinterface #263,  1          // InterfaceMethod org/apache/dubbo/rpc/Invoker.destroy:()V
      51: goto          110
      54: astore        4
      56: getstatic     #123                // Field logger:Lorg/apache/dubbo/common/logger/ErrorTypeAwareLogger;
      59: ldc           #169                // String 4-17
      61: ldc           #125                // String
      63: ldc           #125                // String
      65: new           #143                // class java/lang/StringBuilder
      68: dup
      69: invokespecial #144                // Method java/lang/StringBuilder."<init>":()V
      72: ldc_w         #264                // String Failed to destroy service
      75: invokevirtual #146                // Method java/lang/StringBuilder.append:(Ljava/lang/String;)Ljava/lang/StringBuilder;
      78: aload_0
      79: getfield      #265                // Field serviceKey:Ljava/lang/String;
      82: invokevirtual #146                // Method java/lang/StringBuilder.append:(Ljava/lang/String;)Ljava/lang/StringBuilder;
      85: ldc_w         #266                // String  to provider
      88: invokevirtual #146                // Method java/lang/StringBuilder.append:(Ljava/lang/String;)Ljava/lang/StringBuilder;
      91: aload_3
      92: invokeinterface #239,  1          // InterfaceMethod org/apache/dubbo/rpc/Invoker.getUrl:()Lorg/apache/dubbo/common/URL;
      97: invokevirtual #193                // Method java/lang/StringBuilder.append:(Ljava/lang/Object;)Ljava/lang/StringBuilder;
     100: invokevirtual #148                // Method java/lang/StringBuilder.toString:()Ljava/lang/String;
     103: aload         4
     105: invokeinterface #171,  6          // InterfaceMethod org/apache/dubbo/common/logger/ErrorTypeAwareLogger.warn:(Ljava/lang/String;Ljava/lang/String;Ljava/lang/String;Ljava/lang/String;Ljava/lang/Throwable;)V
     110: goto          26
     113: aload_1
     114: invokeinterface #267,  1          // InterfaceMethod java/util/Map.clear:()V
     119: aload_0
     120: aconst_null
     121: putfield      #134                // Field urlInvokerMap:Ljava/util/Map;
     124: aload_0
     125: invokevirtual #268                // Method destroyInvokers:()V
     128: return
    Exception table:
       from    to  target type
          45    51    54   Class java/lang/Throwable

  private void destroyUnusedInvokers(java.util.Map<org.apache.dubbo.registry.client.ServiceDiscoveryRegistryDirectory$ProtocolServiceKeyWithAddress, org.apache.dubbo.rpc.Invoker<T>>, java.util.Map<org.apache.dubbo.registry.client.ServiceDiscoveryRegistryDirectory$ProtocolServiceKeyWithAddress, org.apache.dubbo.rpc.Invoker<T>>);
    Code:
       0: aload_2
       1: ifnull        13
       4: aload_2
       5: invokeinterface #115,  1          // InterfaceMethod java/util/Map.size:()I
      10: ifne          18
      13: aload_0
      14: invokevirtual #131                // Method destroyAllInvokers:()V
      17: return
      18: aload_1
      19: ifnull        31
      22: aload_1
      23: invokeinterface #115,  1          // InterfaceMethod java/util/Map.size:()I
      28: ifne          32
      31: return
      32: aload_1
      33: invokeinterface #269,  1          // InterfaceMethod java/util/Map.entrySet:()Ljava/util/Set;
      38: invokeinterface #20,  1           // InterfaceMethod java/util/Set.iterator:()Ljava/util/Iterator;
      43: astore_3
      44: aload_3
      45: invokeinterface #26,  1           // InterfaceMethod java/util/Iterator.hasNext:()Z
      50: ifeq          203
      53: aload_3
      54: invokeinterface #21,  1           // InterfaceMethod java/util/Iterator.next:()Ljava/lang/Object;
      59: checkcast     #270                // class java/util/Map$Entry
      62: astore        4
      64: aload         4
      66: invokeinterface #271,  1          // InterfaceMethod java/util/Map$Entry.getValue:()Ljava/lang/Object;
      71: checkcast     #218                // class org/apache/dubbo/rpc/Invoker
      74: astore        5
      76: aload         5
      78: ifnull        200
      81: aload         5
      83: invokeinterface #263,  1          // InterfaceMethod org/apache/dubbo/rpc/Invoker.destroy:()V
      88: getstatic     #123                // Field logger:Lorg/apache/dubbo/common/logger/ErrorTypeAwareLogger;
      91: invokeinterface #272,  1          // InterfaceMethod org/apache/dubbo/common/logger/ErrorTypeAwareLogger.isDebugEnabled:()Z
      96: ifeq          139
      99: getstatic     #123                // Field logger:Lorg/apache/dubbo/common/logger/ErrorTypeAwareLogger;
     102: new           #143                // class java/lang/StringBuilder
     105: dup
     106: invokespecial #144                // Method java/lang/StringBuilder."<init>":()V
     109: ldc_w         #273                // String destroy invoker[
     112: invokevirtual #146                // Method java/lang/StringBuilder.append:(Ljava/lang/String;)Ljava/lang/StringBuilder;
     115: aload         5
     117: invokeinterface #239,  1          // InterfaceMethod org/apache/dubbo/rpc/Invoker.getUrl:()Lorg/apache/dubbo/common/URL;
     122: invokevirtual #193                // Method java/lang/StringBuilder.append:(Ljava/lang/Object;)Ljava/lang/StringBuilder;
     125: ldc_w         #274                // String ] success.
     128: invokevirtual #146                // Method java/lang/StringBuilder.append:(Ljava/lang/String;)Ljava/lang/StringBuilder;
     131: invokevirtual #148                // Method java/lang/StringBuilder.toString:()Ljava/lang/String;
     134: invokeinterface #275,  2          // InterfaceMethod org/apache/dubbo/common/logger/ErrorTypeAwareLogger.debug:(Ljava/lang/String;)V
     139: goto          200
     142: astore        6
     144: getstatic     #123                // Field logger:Lorg/apache/dubbo/common/logger/ErrorTypeAwareLogger;
     147: ldc           #169                // String 4-17
     149: ldc           #125                // String
     151: ldc           #125                // String
     153: new           #143                // class java/lang/StringBuilder
     156: dup
     157: invokespecial #144                // Method java/lang/StringBuilder."<init>":()V
     160: ldc_w         #273                // String destroy invoker[
     163: invokevirtual #146                // Method java/lang/StringBuilder.append:(Ljava/lang/String;)Ljava/lang/StringBuilder;
     166: aload         5
     168: invokeinterface #239,  1          // InterfaceMethod org/apache/dubbo/rpc/Invoker.getUrl:()Lorg/apache/dubbo/common/URL;
     173: invokevirtual #193                // Method java/lang/StringBuilder.append:(Ljava/lang/Object;)Ljava/lang/StringBuilder;
     176: ldc_w         #276                // String ]failed.
     179: invokevirtual #146                // Method java/lang/StringBuilder.append:(Ljava/lang/String;)Ljava/lang/StringBuilder;
     182: aload         6
     184: invokevirtual #277                // Method java/lang/Exception.getMessage:()Ljava/lang/String;
     187: invokevirtual #146                // Method java/lang/StringBuilder.append:(Ljava/lang/String;)Ljava/lang/StringBuilder;
     190: invokevirtual #148                // Method java/lang/StringBuilder.toString:()Ljava/lang/String;
     193: aload         6
     195: invokeinterface #171,  6          // InterfaceMethod org/apache/dubbo/common/logger/ErrorTypeAwareLogger.warn:(Ljava/lang/String;Ljava/lang/String;Ljava/lang/String;Ljava/lang/String;Ljava/lang/Throwable;)V
     200: goto          44
     203: getstatic     #123                // Field logger:Lorg/apache/dubbo/common/logger/ErrorTypeAwareLogger;
     206: new           #143                // class java/lang/StringBuilder
     209: dup
     210: invokespecial #144                // Method java/lang/StringBuilder."<init>":()V
     213: aload_1
     214: invokeinterface #115,  1          // InterfaceMethod java/util/Map.size:()I
     219: invokevirtual #147                // Method java/lang/StringBuilder.append:(I)Ljava/lang/StringBuilder;
     222: ldc_w         #278                // String  deprecated invokers deleted.
     225: invokevirtual #146                // Method java/lang/StringBuilder.append:(Ljava/lang/String;)Ljava/lang/StringBuilder;
     228: invokevirtual #148                // Method java/lang/StringBuilder.toString:()Ljava/lang/String;
     231: invokeinterface #149,  2          // InterfaceMethod org/apache/dubbo/common/logger/ErrorTypeAwareLogger.info:(Ljava/lang/String;)V
     236: return
    Exception table:
       from    to  target type
          81   139   142   Class java/lang/Exception

  private static java.util.List lambda$toMergeInvokerList$5(java.lang.String);
    Code:
       0: new           #157                // class java/util/ArrayList
       3: dup
       4: invokespecial #247                // Method java/util/ArrayList."<init>":()V
       7: areturn

  private org.apache.dubbo.common.URL lambda$toInvokers$4(org.apache.dubbo.common.ProtocolServiceKey);
    Code:
       0: aload_0
       1: getfield      #28                 // Field consumerUrl:Lorg/apache/dubbo/common/URL;
       4: aload_1
       5: invokevirtual #279                // Method org/apache/dubbo/common/ProtocolServiceKey.getProtocol:()Ljava/lang/String;
       8: invokevirtual #280                // Method org/apache/dubbo/common/URL.setProtocol:(Ljava/lang/String;)Lorg/apache/dubbo/common/URL;
      11: ldc_w         #281                // String group
      14: aload_1
      15: invokevirtual #282                // Method org/apache/dubbo/common/ProtocolServiceKey.getGroup:()Ljava/lang/String;
      18: invokevirtual #65                 // Method org/apache/dubbo/common/URL.addParameter:(Ljava/lang/String;Ljava/lang/String;)Lorg/apache/dubbo/common/URL;
      21: ldc_w         #283                // String version
      24: aload_1
      25: invokevirtual #284                // Method org/apache/dubbo/common/ProtocolServiceKey.getVersion:()Ljava/lang/String;
      28: invokevirtual #65                 // Method org/apache/dubbo/common/URL.addParameter:(Ljava/lang/String;Ljava/lang/String;)Lorg/apache/dubbo/common/URL;
      31: areturn

  private static boolean lambda$toInvokers$3(int, org.apache.dubbo.metadata.MetadataInfo$ServiceInfo);
    Code:
       0: aload_1
       1: invokevirtual #285                // Method org/apache/dubbo/metadata/MetadataInfo$ServiceInfo.getPort:()I
       4: ifle          15
       7: aload_1
       8: invokevirtual #285                // Method org/apache/dubbo/metadata/MetadataInfo$ServiceInfo.getPort:()I
      11: iload_0
      12: if_icmpne     19
      15: iconst_1
      16: goto          20
      19: iconst_0
      20: ireturn

  private void lambda$refreshInvoker$2(org.apache.dubbo.rpc.cluster.router.state.BitList);
    Code:
       0: aload_0
       1: aload_1
       2: invokevirtual #286                // Method setInvokers:(Lorg/apache/dubbo/rpc/cluster/router/state/BitList;)V
       5: return

  private void lambda$refreshInvoker$1();
    Code:
       0: aload_0
       1: iconst_1
       2: putfield      #132                // Field forbidden:Z
       5: return

  private static org.apache.dubbo.registry.client.ServiceDiscoveryRegistryDirectory$ConsumerConfigurationListener lambda$getConsumerConfigurationListener$0(org.apache.dubbo.rpc.model.ModuleModel, java.lang.Class);
    Code:
       0: new           #55                 // class org/apache/dubbo/registry/client/ServiceDiscoveryRegistryDirectory$ConsumerConfigurationListener
       3: dup
       4: aload_0
       5: invokespecial #287                // Method org/apache/dubbo/registry/client/ServiceDiscoveryRegistryDirectory$ConsumerConfigurationListener."<init>":(Lorg/apache/dubbo/rpc/model/ModuleModel;)V
       8: areturn

  static java.util.List access$000(org.apache.dubbo.registry.client.ServiceDiscoveryRegistryDirectory);
    Code:
       0: aload_0
       1: getfield      #4                  // Field originalUrls:Ljava/util/List;
       4: areturn

  static {};
    Code:
       0: ldc_w         #288                // class org/apache/dubbo/registry/client/ServiceDiscoveryRegistryDirectory
       3: invokestatic  #289                // Method org/apache/dubbo/common/logger/LoggerFactory.getErrorTypeAwareLogger:(Ljava/lang/Class;)Lorg/apache/dubbo/common/logger/ErrorTypeAwareLogger;
       6: putstatic     #123                // Field logger:Lorg/apache/dubbo/common/logger/ErrorTypeAwareLogger;
       9: return
}
