Compiled from "ServiceInstance.java"
public interface org.apache.dubbo.registry.client.ServiceInstance extends java.io.Serializable {
  public abstract java.lang.String getServiceName();

  public abstract java.lang.String getHost();

  public abstract int getPort();

  public abstract java.lang.String getAddress();

  public default boolean isEnabled();
    Code:
       0: iconst_1
       1: ireturn

  public default boolean isHealthy();
    Code:
       0: iconst_1
       1: ireturn

  public abstract java.util.Map<java.lang.String, java.lang.String> getMetadata();

  public abstract java.util.SortedMap<java.lang.String, java.lang.String> getSortedMetadata();

  public abstract java.lang.String getRegistryCluster();

  public abstract void setRegistryCluster(java.lang.String);

  public abstract java.util.Map<java.lang.String, java.lang.String> getExtendParams();

  public abstract java.lang.String getExtendParam(java.lang.String);

  public abstract java.lang.String putExtendParam(java.lang.String, java.lang.String);

  public abstract java.lang.String putExtendParamIfAbsent(java.lang.String, java.lang.String);

  public abstract java.lang.String removeExtendParam(java.lang.String);

  public abstract java.util.Map<java.lang.String, java.lang.String> getAllParams();

  public abstract void setApplicationModel(org.apache.dubbo.rpc.model.ApplicationModel);

  public abstract org.apache.dubbo.rpc.model.ApplicationModel getApplicationModel();

  public default org.apache.dubbo.rpc.model.ApplicationModel getOrDefaultApplicationModel();
    Code:
       0: aload_0
       1: invokeinterface #1,  1            // InterfaceMethod getApplicationModel:()Lorg/apache/dubbo/rpc/model/ApplicationModel;
       6: invokestatic  #2                  // Method org/apache/dubbo/rpc/model/ScopeModelUtil.getApplicationModel:(Lorg/apache/dubbo/rpc/model/ScopeModel;)Lorg/apache/dubbo/rpc/model/ApplicationModel;
       9: areturn

  public default java.lang.String getMetadata(java.lang.String);
    Code:
       0: aload_0
       1: aload_1
       2: aconst_null
       3: invokeinterface #3,  3            // InterfaceMethod getMetadata:(Ljava/lang/String;Ljava/lang/String;)Ljava/lang/String;
       8: areturn

  public default java.lang.String getMetadata(java.lang.String, java.lang.String);
    Code:
       0: aload_0
       1: invokeinterface #4,  1            // InterfaceMethod getMetadata:()Ljava/util/Map;
       6: aload_1
       7: aload_2
       8: invokeinterface #5,  3            // InterfaceMethod java/util/Map.getOrDefault:(Ljava/lang/Object;Ljava/lang/Object;)Ljava/lang/Object;
      13: checkcast     #6                  // class java/lang/String
      16: areturn

  public abstract org.apache.dubbo.metadata.MetadataInfo getServiceMetadata();

  public abstract void setServiceMetadata(org.apache.dubbo.metadata.MetadataInfo);

  public abstract org.apache.dubbo.registry.client.InstanceAddressURL toURL(java.lang.String);
}
