Compiled from "ServiceDiscovery.java"
public interface org.apache.dubbo.registry.client.ServiceDiscovery extends org.apache.dubbo.registry.RegistryService,org.apache.dubbo.common.lang.Prioritized {
  public abstract void register() throws java.lang.RuntimeException;

  public abstract void update() throws java.lang.RuntimeException;

  public abstract void unregister() throws java.lang.RuntimeException;

  public abstract java.util.Set<java.lang.String> getServices();

  public abstract java.util.List<org.apache.dubbo.registry.client.ServiceInstance> getInstances(java.lang.String) throws java.lang.NullPointerException;

  public default void addServiceInstancesChangedListener(org.apache.dubbo.registry.client.event.listener.ServiceInstancesChangedListener) throws java.lang.NullPointerException, java.lang.IllegalArgumentException;
    Code:
       0: return

  public default void removeServiceInstancesChangedListener(org.apache.dubbo.registry.client.event.listener.ServiceInstancesChangedListener) throws java.lang.IllegalArgumentException;
    Code:
       0: return

  public default org.apache.dubbo.registry.client.event.listener.ServiceInstancesChangedListener createListener(java.util.Set<java.lang.String>);
    Code:
       0: new           #2                  // class org/apache/dubbo/registry/client/event/listener/ServiceInstancesChangedListener
       3: dup
       4: aload_1
       5: aload_0
       6: invokespecial #3                  // Method org/apache/dubbo/registry/client/event/listener/ServiceInstancesChangedListener."<init>":(Ljava/util/Set;Lorg/apache/dubbo/registry/client/ServiceDiscovery;)V
       9: areturn

  public abstract org.apache.dubbo.registry.client.ServiceInstance getLocalInstance();

  public abstract org.apache.dubbo.metadata.MetadataInfo getLocalMetadata();

  public default org.apache.dubbo.metadata.MetadataInfo getLocalMetadata(java.lang.String);
    Code:
       0: aload_0
       1: invokeinterface #4,  1            // InterfaceMethod getLocalMetadata:()Lorg/apache/dubbo/metadata/MetadataInfo;
       6: areturn

  public abstract org.apache.dubbo.metadata.MetadataInfo getRemoteMetadata(java.lang.String);

  public abstract org.apache.dubbo.metadata.MetadataInfo getRemoteMetadata(java.lang.String, java.util.List<org.apache.dubbo.registry.client.ServiceInstance>);

  public abstract void destroy() throws java.lang.Exception;

  public abstract boolean isDestroy();

  public default org.apache.dubbo.common.URL getUrl();
    Code:
       0: aconst_null
       1: areturn

  public default long getDelay();
    Code:
       0: aload_0
       1: invokeinterface #5,  1            // InterfaceMethod getUrl:()Lorg/apache/dubbo/common/URL;
       6: ldc           #6                  // String delay-notification
       8: sipush        5000
      11: invokevirtual #7                  // Method org/apache/dubbo/common/URL.getParameter:(Ljava/lang/String;I)I
      14: i2l
      15: lreturn

  public abstract java.lang.String toString();
}
