Compiled from "ServiceDiscoveryRegistryDirectory.java"
class org.apache.dubbo.registry.client.ServiceDiscoveryRegistryDirectory$ConsumerConfigurationListener extends org.apache.dubbo.registry.integration.AbstractConfiguratorListener {
  private final java.util.List<org.apache.dubbo.registry.client.ServiceDiscoveryRegistryDirectory<?>> listeners;

  org.apache.dubbo.registry.client.ServiceDiscoveryRegistryDirectory$ConsumerConfigurationListener(org.apache.dubbo.rpc.model.ModuleModel);
    Code:
       0: aload_0
       1: aload_1
       2: invokespecial #2                  // Method org/apache/dubbo/registry/integration/AbstractConfiguratorListener."<init>":(Lorg/apache/dubbo/rpc/model/ModuleModel;)V
       5: aload_0
       6: new           #3                  // class java/util/ArrayList
       9: dup
      10: invokespecial #4                  // Method java/util/ArrayList."<init>":()V
      13: putfield      #5                  // Field listeners:Ljava/util/List;
      16: return

  void addNotifyListener(org.apache.dubbo.registry.client.ServiceDiscoveryRegistryDirectory<?>);
    Code:
       0: aload_0
       1: getfield      #5                  // Field listeners:Ljava/util/List;
       4: invokeinterface #6,  1            // InterfaceMethod java/util/List.size:()I
       9: ifne          44
      12: aload_0
      13: new           #7                  // class java/lang/StringBuilder
      16: dup
      17: invokespecial #8                  // Method java/lang/StringBuilder."<init>":()V
      20: aload_0
      21: getfield      #9                  // Field moduleModel:Lorg/apache/dubbo/rpc/model/ModuleModel;
      24: invokevirtual #10                 // Method org/apache/dubbo/rpc/model/ModuleModel.getApplicationModel:()Lorg/apache/dubbo/rpc/model/ApplicationModel;
      27: invokevirtual #11                 // Method org/apache/dubbo/rpc/model/ApplicationModel.getApplicationName:()Ljava/lang/String;
      30: invokevirtual #12                 // Method java/lang/StringBuilder.append:(Ljava/lang/String;)Ljava/lang/StringBuilder;
      33: ldc           #13                 // String .configurators
      35: invokevirtual #12                 // Method java/lang/StringBuilder.append:(Ljava/lang/String;)Ljava/lang/StringBuilder;
      38: invokevirtual #14                 // Method java/lang/StringBuilder.toString:()Ljava/lang/String;
      41: invokevirtual #15                 // Method initWith:(Ljava/lang/String;)V
      44: aload_0
      45: getfield      #5                  // Field listeners:Ljava/util/List;
      48: aload_1
      49: invokeinterface #16,  2           // InterfaceMethod java/util/List.add:(Ljava/lang/Object;)Z
      54: pop
      55: return

  void removeNotifyListener(org.apache.dubbo.registry.client.ServiceDiscoveryRegistryDirectory<?>);
    Code:
       0: aload_0
       1: getfield      #5                  // Field listeners:Ljava/util/List;
       4: aload_1
       5: invokeinterface #17,  2           // InterfaceMethod java/util/List.remove:(Ljava/lang/Object;)Z
      10: pop
      11: aload_0
      12: getfield      #5                  // Field listeners:Ljava/util/List;
      15: invokeinterface #6,  1            // InterfaceMethod java/util/List.size:()I
      20: ifne          55
      23: aload_0
      24: new           #7                  // class java/lang/StringBuilder
      27: dup
      28: invokespecial #8                  // Method java/lang/StringBuilder."<init>":()V
      31: aload_0
      32: getfield      #9                  // Field moduleModel:Lorg/apache/dubbo/rpc/model/ModuleModel;
      35: invokevirtual #10                 // Method org/apache/dubbo/rpc/model/ModuleModel.getApplicationModel:()Lorg/apache/dubbo/rpc/model/ApplicationModel;
      38: invokevirtual #11                 // Method org/apache/dubbo/rpc/model/ApplicationModel.getApplicationName:()Ljava/lang/String;
      41: invokevirtual #12                 // Method java/lang/StringBuilder.append:(Ljava/lang/String;)Ljava/lang/StringBuilder;
      44: ldc           #13                 // String .configurators
      46: invokevirtual #12                 // Method java/lang/StringBuilder.append:(Ljava/lang/String;)Ljava/lang/StringBuilder;
      49: invokevirtual #14                 // Method java/lang/StringBuilder.toString:()Ljava/lang/String;
      52: invokevirtual #18                 // Method stopListen:(Ljava/lang/String;)V
      55: return

  protected void notifyOverrides();
    Code:
       0: aload_0
       1: getfield      #5                  // Field listeners:Ljava/util/List;
       4: invokedynamic #19,  0             // InvokeDynamic #0:accept:()Ljava/util/function/Consumer;
       9: invokeinterface #20,  2           // InterfaceMethod java/util/List.forEach:(Ljava/util/function/Consumer;)V
      14: return

  private static void lambda$notifyOverrides$0(org.apache.dubbo.registry.client.ServiceDiscoveryRegistryDirectory);
    Code:
       0: aload_0
       1: invokestatic  #21                 // Method org/apache/dubbo/registry/client/ServiceDiscoveryRegistryDirectory.access$000:(Lorg/apache/dubbo/registry/client/ServiceDiscoveryRegistryDirectory;)Ljava/util/List;
       4: ifnull        39
       7: invokestatic  #22                 // Method org/apache/dubbo/rpc/RpcContext.getServiceContext:()Lorg/apache/dubbo/rpc/RpcServiceContext;
      10: invokevirtual #23                 // Method org/apache/dubbo/rpc/RpcServiceContext.getConsumerUrl:()Lorg/apache/dubbo/common/URL;
      13: astore_1
      14: invokestatic  #22                 // Method org/apache/dubbo/rpc/RpcContext.getServiceContext:()Lorg/apache/dubbo/rpc/RpcServiceContext;
      17: aload_0
      18: invokevirtual #24                 // Method org/apache/dubbo/registry/client/ServiceDiscoveryRegistryDirectory.getConsumerUrl:()Lorg/apache/dubbo/common/URL;
      21: invokevirtual #25                 // Method org/apache/dubbo/rpc/RpcServiceContext.setConsumerUrl:(Lorg/apache/dubbo/common/URL;)V
      24: aload_0
      25: aload_0
      26: invokestatic  #21                 // Method org/apache/dubbo/registry/client/ServiceDiscoveryRegistryDirectory.access$000:(Lorg/apache/dubbo/registry/client/ServiceDiscoveryRegistryDirectory;)Ljava/util/List;
      29: invokevirtual #26                 // Method org/apache/dubbo/registry/client/ServiceDiscoveryRegistryDirectory.refreshOverrideAndInvoker:(Ljava/util/List;)V
      32: invokestatic  #22                 // Method org/apache/dubbo/rpc/RpcContext.getServiceContext:()Lorg/apache/dubbo/rpc/RpcServiceContext;
      35: aload_1
      36: invokevirtual #25                 // Method org/apache/dubbo/rpc/RpcServiceContext.setConsumerUrl:(Lorg/apache/dubbo/common/URL;)V
      39: return
}
