Compiled from "ServiceDiscoveryRegistryDirectory.java"
class org.apache.dubbo.registry.client.ServiceDiscoveryRegistryDirectory$ReferenceConfigurationListener extends org.apache.dubbo.registry.integration.AbstractConfiguratorListener {
  private final org.apache.dubbo.registry.client.ServiceDiscoveryRegistryDirectory<?> directory;

  private final org.apache.dubbo.common.URL url;

  final org.apache.dubbo.registry.client.ServiceDiscoveryRegistryDirectory this$0;

  org.apache.dubbo.registry.client.ServiceDiscoveryRegistryDirectory$ReferenceConfigurationListener(org.apache.dubbo.rpc.model.ModuleModel, org.apache.dubbo.registry.client.ServiceDiscoveryRegistryDirectory<?>, org.apache.dubbo.common.URL);
    Code:
       0: aload_0
       1: aload_1
       2: putfield      #2                  // Field this$0:Lorg/apache/dubbo/registry/client/ServiceDiscoveryRegistryDirectory;
       5: aload_0
       6: aload_2
       7: invokespecial #3                  // Method org/apache/dubbo/registry/integration/AbstractConfiguratorListener."<init>":(Lorg/apache/dubbo/rpc/model/ModuleModel;)V
      10: aload_0
      11: aload_3
      12: putfield      #4                  // Field directory:Lorg/apache/dubbo/registry/client/ServiceDiscoveryRegistryDirectory;
      15: aload_0
      16: aload         4
      18: putfield      #5                  // Field url:Lorg/apache/dubbo/common/URL;
      21: aload_0
      22: new           #6                  // class java/lang/StringBuilder
      25: dup
      26: invokespecial #7                  // Method java/lang/StringBuilder."<init>":()V
      29: aload         4
      31: invokestatic  #8                  // InterfaceMethod org/apache/dubbo/common/config/configcenter/DynamicConfiguration.getRuleKey:(Lorg/apache/dubbo/common/URL;)Ljava/lang/String;
      34: invokevirtual #9                  // Method java/lang/StringBuilder.append:(Ljava/lang/String;)Ljava/lang/StringBuilder;
      37: ldc           #10                 // String .configurators
      39: invokevirtual #9                  // Method java/lang/StringBuilder.append:(Ljava/lang/String;)Ljava/lang/StringBuilder;
      42: invokevirtual #11                 // Method java/lang/StringBuilder.toString:()Ljava/lang/String;
      45: invokevirtual #12                 // Method initWith:(Ljava/lang/String;)V
      48: return

  void stop();
    Code:
       0: aload_0
       1: new           #6                  // class java/lang/StringBuilder
       4: dup
       5: invokespecial #7                  // Method java/lang/StringBuilder."<init>":()V
       8: aload_0
       9: getfield      #5                  // Field url:Lorg/apache/dubbo/common/URL;
      12: invokestatic  #8                  // InterfaceMethod org/apache/dubbo/common/config/configcenter/DynamicConfiguration.getRuleKey:(Lorg/apache/dubbo/common/URL;)Ljava/lang/String;
      15: invokevirtual #9                  // Method java/lang/StringBuilder.append:(Ljava/lang/String;)Ljava/lang/StringBuilder;
      18: ldc           #10                 // String .configurators
      20: invokevirtual #9                  // Method java/lang/StringBuilder.append:(Ljava/lang/String;)Ljava/lang/StringBuilder;
      23: invokevirtual #11                 // Method java/lang/StringBuilder.toString:()Ljava/lang/String;
      26: invokevirtual #13                 // Method stopListen:(Ljava/lang/String;)V
      29: return

  protected void notifyOverrides();
    Code:
       0: aload_0
       1: getfield      #4                  // Field directory:Lorg/apache/dubbo/registry/client/ServiceDiscoveryRegistryDirectory;
       4: invokestatic  #14                 // Method org/apache/dubbo/registry/client/ServiceDiscoveryRegistryDirectory.access$000:(Lorg/apache/dubbo/registry/client/ServiceDiscoveryRegistryDirectory;)Ljava/util/List;
       7: ifnull        51
      10: invokestatic  #15                 // Method org/apache/dubbo/rpc/RpcContext.getServiceContext:()Lorg/apache/dubbo/rpc/RpcServiceContext;
      13: invokevirtual #16                 // Method org/apache/dubbo/rpc/RpcServiceContext.getConsumerUrl:()Lorg/apache/dubbo/common/URL;
      16: astore_1
      17: invokestatic  #15                 // Method org/apache/dubbo/rpc/RpcContext.getServiceContext:()Lorg/apache/dubbo/rpc/RpcServiceContext;
      20: aload_0
      21: getfield      #4                  // Field directory:Lorg/apache/dubbo/registry/client/ServiceDiscoveryRegistryDirectory;
      24: invokevirtual #17                 // Method org/apache/dubbo/registry/client/ServiceDiscoveryRegistryDirectory.getConsumerUrl:()Lorg/apache/dubbo/common/URL;
      27: invokevirtual #18                 // Method org/apache/dubbo/rpc/RpcServiceContext.setConsumerUrl:(Lorg/apache/dubbo/common/URL;)V
      30: aload_0
      31: getfield      #4                  // Field directory:Lorg/apache/dubbo/registry/client/ServiceDiscoveryRegistryDirectory;
      34: aload_0
      35: getfield      #4                  // Field directory:Lorg/apache/dubbo/registry/client/ServiceDiscoveryRegistryDirectory;
      38: invokestatic  #14                 // Method org/apache/dubbo/registry/client/ServiceDiscoveryRegistryDirectory.access$000:(Lorg/apache/dubbo/registry/client/ServiceDiscoveryRegistryDirectory;)Ljava/util/List;
      41: invokevirtual #19                 // Method org/apache/dubbo/registry/client/ServiceDiscoveryRegistryDirectory.refreshOverrideAndInvoker:(Ljava/util/List;)V
      44: invokestatic  #15                 // Method org/apache/dubbo/rpc/RpcContext.getServiceContext:()Lorg/apache/dubbo/rpc/RpcServiceContext;
      47: aload_1
      48: invokevirtual #18                 // Method org/apache/dubbo/rpc/RpcServiceContext.setConsumerUrl:(Lorg/apache/dubbo/common/URL;)V
      51: return
}
