Compiled from "SSLConfigCertProvider.java"
public class org.apache.dubbo.common.ssl.impl.SSLConfigCertProvider implements org.apache.dubbo.common.ssl.CertProvider {
  private final org.apache.dubbo.common.logger.ErrorTypeAwareLogger logger;

  public org.apache.dubbo.common.ssl.impl.SSLConfigCertProvider();
    Code:
       0: aload_0
       1: invokespecial #1                  // Method java/lang/Object."<init>":()V
       4: aload_0
       5: ldc           #2                  // class org/apache/dubbo/common/ssl/impl/SSLConfigCertProvider
       7: invokestatic  #3                  // Method org/apache/dubbo/common/logger/LoggerFactory.getErrorTypeAwareLogger:(Ljava/lang/Class;)Lorg/apache/dubbo/common/logger/ErrorTypeAwareLogger;
      10: putfield      #4                  // Field logger:Lorg/apache/dubbo/common/logger/ErrorTypeAwareLogger;
      13: return

  public boolean isSupport(org.apache.dubbo.common.URL);
    Code:
       0: aload_1
       1: invokevirtual #5                  // Method org/apache/dubbo/common/URL.getOrDefaultApplicationModel:()Lorg/apache/dubbo/rpc/model/ApplicationModel;
       4: invokevirtual #6                  // Method org/apache/dubbo/rpc/model/ApplicationModel.getApplicationConfigManager:()Lorg/apache/dubbo/config/context/ConfigManager;
       7: invokevirtual #7                  // Method org/apache/dubbo/config/context/ConfigManager.getSsl:()Ljava/util/Optional;
      10: invokevirtual #8                  // Method java/util/Optional.isPresent:()Z
      13: ireturn

  public org.apache.dubbo.common.ssl.ProviderCert getProviderConnectionConfig(org.apache.dubbo.common.URL);
    Code:
       0: aload_1
       1: invokevirtual #5                  // Method org/apache/dubbo/common/URL.getOrDefaultApplicationModel:()Lorg/apache/dubbo/rpc/model/ApplicationModel;
       4: invokevirtual #6                  // Method org/apache/dubbo/rpc/model/ApplicationModel.getApplicationConfigManager:()Lorg/apache/dubbo/config/context/ConfigManager;
       7: invokevirtual #7                  // Method org/apache/dubbo/config/context/ConfigManager.getSsl:()Ljava/util/Optional;
      10: invokedynamic #9,  0              // InvokeDynamic #0:test:()Ljava/util/function/Predicate;
      15: invokevirtual #10                 // Method java/util/Optional.filter:(Ljava/util/function/Predicate;)Ljava/util/Optional;
      18: invokedynamic #11,  0             // InvokeDynamic #1:test:()Ljava/util/function/Predicate;
      23: invokevirtual #10                 // Method java/util/Optional.filter:(Ljava/util/function/Predicate;)Ljava/util/Optional;
      26: aload_0
      27: invokedynamic #12,  0             // InvokeDynamic #2:apply:(Lorg/apache/dubbo/common/ssl/impl/SSLConfigCertProvider;)Ljava/util/function/Function;
      32: invokevirtual #13                 // Method java/util/Optional.map:(Ljava/util/function/Function;)Ljava/util/Optional;
      35: aconst_null
      36: invokevirtual #14                 // Method java/util/Optional.orElse:(Ljava/lang/Object;)Ljava/lang/Object;
      39: checkcast     #15                 // class org/apache/dubbo/common/ssl/ProviderCert
      42: areturn

  public org.apache.dubbo.common.ssl.Cert getConsumerConnectionConfig(org.apache.dubbo.common.URL);
    Code:
       0: aload_1
       1: invokevirtual #5                  // Method org/apache/dubbo/common/URL.getOrDefaultApplicationModel:()Lorg/apache/dubbo/rpc/model/ApplicationModel;
       4: invokevirtual #6                  // Method org/apache/dubbo/rpc/model/ApplicationModel.getApplicationConfigManager:()Lorg/apache/dubbo/config/context/ConfigManager;
       7: invokevirtual #7                  // Method org/apache/dubbo/config/context/ConfigManager.getSsl:()Ljava/util/Optional;
      10: invokedynamic #16,  0             // InvokeDynamic #3:test:()Ljava/util/function/Predicate;
      15: invokevirtual #10                 // Method java/util/Optional.filter:(Ljava/util/function/Predicate;)Ljava/util/Optional;
      18: invokedynamic #17,  0             // InvokeDynamic #4:test:()Ljava/util/function/Predicate;
      23: invokevirtual #10                 // Method java/util/Optional.filter:(Ljava/util/function/Predicate;)Ljava/util/Optional;
      26: aload_0
      27: invokedynamic #18,  0             // InvokeDynamic #5:apply:(Lorg/apache/dubbo/common/ssl/impl/SSLConfigCertProvider;)Ljava/util/function/Function;
      32: invokevirtual #13                 // Method java/util/Optional.map:(Ljava/util/function/Function;)Ljava/util/Optional;
      35: aconst_null
      36: invokevirtual #14                 // Method java/util/Optional.orElse:(Ljava/lang/Object;)Ljava/lang/Object;
      39: checkcast     #19                 // class org/apache/dubbo/common/ssl/Cert
      42: areturn

  private org.apache.dubbo.common.ssl.Cert lambda$getConsumerConnectionConfig$5(org.apache.dubbo.config.SslConfig);
    Code:
       0: new           #19                 // class org/apache/dubbo/common/ssl/Cert
       3: dup
       4: aload_1
       5: invokevirtual #20                 // Method org/apache/dubbo/config/SslConfig.getClientKeyCertChainPathStream:()Ljava/io/InputStream;
       8: invokestatic  #21                 // Method org/apache/dubbo/common/utils/IOUtils.toByteArray:(Ljava/io/InputStream;)[B
      11: aload_1
      12: invokevirtual #22                 // Method org/apache/dubbo/config/SslConfig.getClientPrivateKeyPathStream:()Ljava/io/InputStream;
      15: invokestatic  #21                 // Method org/apache/dubbo/common/utils/IOUtils.toByteArray:(Ljava/io/InputStream;)[B
      18: aload_1
      19: invokevirtual #23                 // Method org/apache/dubbo/config/SslConfig.getClientTrustCertCollectionPath:()Ljava/lang/String;
      22: ifnull        35
      25: aload_1
      26: invokevirtual #24                 // Method org/apache/dubbo/config/SslConfig.getClientTrustCertCollectionPathStream:()Ljava/io/InputStream;
      29: invokestatic  #21                 // Method org/apache/dubbo/common/utils/IOUtils.toByteArray:(Ljava/io/InputStream;)[B
      32: goto          36
      35: aconst_null
      36: aload_1
      37: invokevirtual #25                 // Method org/apache/dubbo/config/SslConfig.getClientKeyPassword:()Ljava/lang/String;
      40: invokespecial #26                 // Method org/apache/dubbo/common/ssl/Cert."<init>":([B[B[BLjava/lang/String;)V
      43: areturn
      44: astore_2
      45: aload_0
      46: getfield      #4                  // Field logger:Lorg/apache/dubbo/common/logger/ErrorTypeAwareLogger;
      49: ldc           #29                 // String 5-41
      51: ldc           #30                 // String
      53: ldc           #30                 // String
      55: ldc           #31                 // String Failed to load ssl config.
      57: aload_2
      58: invokeinterface #32,  6           // InterfaceMethod org/apache/dubbo/common/logger/ErrorTypeAwareLogger.warn:(Ljava/lang/String;Ljava/lang/String;Ljava/lang/String;Ljava/lang/String;Ljava/lang/Throwable;)V
      63: aconst_null
      64: areturn
    Exception table:
       from    to  target type
           0    43    44   Class java/io/IOException

  private static boolean lambda$getConsumerConnectionConfig$4(org.apache.dubbo.config.SslConfig);
    Code:
       0: aload_0
       1: invokevirtual #33                 // Method org/apache/dubbo/config/SslConfig.getClientPrivateKeyPath:()Ljava/lang/String;
       4: invokestatic  #34                 // Method java/util/Objects.nonNull:(Ljava/lang/Object;)Z
       7: ireturn

  private static boolean lambda$getConsumerConnectionConfig$3(org.apache.dubbo.config.SslConfig);
    Code:
       0: aload_0
       1: invokevirtual #35                 // Method org/apache/dubbo/config/SslConfig.getClientKeyCertChainPath:()Ljava/lang/String;
       4: invokestatic  #34                 // Method java/util/Objects.nonNull:(Ljava/lang/Object;)Z
       7: ireturn

  private org.apache.dubbo.common.ssl.ProviderCert lambda$getProviderConnectionConfig$2(org.apache.dubbo.config.SslConfig);
    Code:
       0: new           #15                 // class org/apache/dubbo/common/ssl/ProviderCert
       3: dup
       4: aload_1
       5: invokevirtual #36                 // Method org/apache/dubbo/config/SslConfig.getServerKeyCertChainPathStream:()Ljava/io/InputStream;
       8: invokestatic  #21                 // Method org/apache/dubbo/common/utils/IOUtils.toByteArray:(Ljava/io/InputStream;)[B
      11: aload_1
      12: invokevirtual #37                 // Method org/apache/dubbo/config/SslConfig.getServerPrivateKeyPathStream:()Ljava/io/InputStream;
      15: invokestatic  #21                 // Method org/apache/dubbo/common/utils/IOUtils.toByteArray:(Ljava/io/InputStream;)[B
      18: aload_1
      19: invokevirtual #38                 // Method org/apache/dubbo/config/SslConfig.getServerTrustCertCollectionPath:()Ljava/lang/String;
      22: ifnull        35
      25: aload_1
      26: invokevirtual #39                 // Method org/apache/dubbo/config/SslConfig.getServerTrustCertCollectionPathStream:()Ljava/io/InputStream;
      29: invokestatic  #21                 // Method org/apache/dubbo/common/utils/IOUtils.toByteArray:(Ljava/io/InputStream;)[B
      32: goto          36
      35: aconst_null
      36: aload_1
      37: invokevirtual #40                 // Method org/apache/dubbo/config/SslConfig.getServerKeyPassword:()Ljava/lang/String;
      40: getstatic     #41                 // Field org/apache/dubbo/common/ssl/AuthPolicy.CLIENT_AUTH:Lorg/apache/dubbo/common/ssl/AuthPolicy;
      43: invokespecial #42                 // Method org/apache/dubbo/common/ssl/ProviderCert."<init>":([B[B[BLjava/lang/String;Lorg/apache/dubbo/common/ssl/AuthPolicy;)V
      46: areturn
      47: astore_2
      48: aload_0
      49: getfield      #4                  // Field logger:Lorg/apache/dubbo/common/logger/ErrorTypeAwareLogger;
      52: ldc           #29                 // String 5-41
      54: ldc           #30                 // String
      56: ldc           #30                 // String
      58: ldc           #31                 // String Failed to load ssl config.
      60: aload_2
      61: invokeinterface #32,  6           // InterfaceMethod org/apache/dubbo/common/logger/ErrorTypeAwareLogger.warn:(Ljava/lang/String;Ljava/lang/String;Ljava/lang/String;Ljava/lang/String;Ljava/lang/Throwable;)V
      66: aconst_null
      67: areturn
    Exception table:
       from    to  target type
           0    46    47   Class java/io/IOException

  private static boolean lambda$getProviderConnectionConfig$1(org.apache.dubbo.config.SslConfig);
    Code:
       0: aload_0
       1: invokevirtual #43                 // Method org/apache/dubbo/config/SslConfig.getServerPrivateKeyPath:()Ljava/lang/String;
       4: invokestatic  #34                 // Method java/util/Objects.nonNull:(Ljava/lang/Object;)Z
       7: ireturn

  private static boolean lambda$getProviderConnectionConfig$0(org.apache.dubbo.config.SslConfig);
    Code:
       0: aload_0
       1: invokevirtual #44                 // Method org/apache/dubbo/config/SslConfig.getServerKeyCertChainPath:()Ljava/lang/String;
       4: invokestatic  #34                 // Method java/util/Objects.nonNull:(Ljava/lang/Object;)Z
       7: ireturn
}
