Compiled from "RegistryNotifier.java"
public class org.apache.dubbo.registry.RegistryNotifier$NotificationTask implements java.lang.Runnable {
  private final org.apache.dubbo.registry.RegistryNotifier listener;

  private final long time;

  public org.apache.dubbo.registry.RegistryNotifier$NotificationTask(org.apache.dubbo.registry.RegistryNotifier, long);
    Code:
       0: aload_0
       1: invokespecial #2                  // Method java/lang/Object."<init>":()V
       4: aload_0
       5: aload_1
       6: putfield      #3                  // Field listener:Lorg/apache/dubbo/registry/RegistryNotifier;
       9: aload_0
      10: lload_2
      11: putfield      #4                  // Field time:J
      14: return

  public void run();
    Code:
       0: aload_0
       1: getfield      #4                  // Field time:J
       4: aload_0
       5: getfield      #3                  // Field listener:Lorg/apache/dubbo/registry/RegistryNotifier;
       8: invokestatic  #5                  // Method org/apache/dubbo/registry/RegistryNotifier.access$000:(Lorg/apache/dubbo/registry/RegistryNotifier;)J
      11: lcmp
      12: ifne          81
      15: aload_0
      16: getfield      #3                  // Field listener:Lorg/apache/dubbo/registry/RegistryNotifier;
      19: aload_0
      20: getfield      #3                  // Field listener:Lorg/apache/dubbo/registry/RegistryNotifier;
      23: invokestatic  #6                  // Method org/apache/dubbo/registry/RegistryNotifier.access$100:(Lorg/apache/dubbo/registry/RegistryNotifier;)Ljava/lang/Object;
      26: invokevirtual #7                  // Method org/apache/dubbo/registry/RegistryNotifier.doNotify:(Ljava/lang/Object;)V
      29: aload_0
      30: getfield      #3                  // Field listener:Lorg/apache/dubbo/registry/RegistryNotifier;
      33: invokestatic  #8                  // Method java/lang/System.currentTimeMillis:()J
      36: invokestatic  #9                  // Method org/apache/dubbo/registry/RegistryNotifier.access$202:(Lorg/apache/dubbo/registry/RegistryNotifier;J)J
      39: pop2
      40: aload_0
      41: getfield      #3                  // Field listener:Lorg/apache/dubbo/registry/RegistryNotifier;
      44: dup
      45: astore_1
      46: monitorenter
      47: aload_0
      48: getfield      #4                  // Field time:J
      51: aload_0
      52: getfield      #3                  // Field listener:Lorg/apache/dubbo/registry/RegistryNotifier;
      55: invokestatic  #5                  // Method org/apache/dubbo/registry/RegistryNotifier.access$000:(Lorg/apache/dubbo/registry/RegistryNotifier;)J
      58: lcmp
      59: ifne          71
      62: aload_0
      63: getfield      #3                  // Field listener:Lorg/apache/dubbo/registry/RegistryNotifier;
      66: aconst_null
      67: invokestatic  #10                 // Method org/apache/dubbo/registry/RegistryNotifier.access$102:(Lorg/apache/dubbo/registry/RegistryNotifier;Ljava/lang/Object;)Ljava/lang/Object;
      70: pop
      71: aload_1
      72: monitorexit
      73: goto          81
      76: astore_2
      77: aload_1
      78: monitorexit
      79: aload_2
      80: athrow
      81: goto          102
      84: astore_1
      85: invokestatic  #12                 // Method org/apache/dubbo/registry/RegistryNotifier.access$300:()Lorg/apache/dubbo/common/logger/ErrorTypeAwareLogger;
      88: ldc           #13                 // String 1-7
      90: ldc           #14                 // String
      92: ldc           #14                 // String
      94: ldc           #15                 // String Error occurred when notify directory.
      96: aload_1
      97: invokeinterface #16,  6           // InterfaceMethod org/apache/dubbo/common/logger/ErrorTypeAwareLogger.error:(Ljava/lang/String;Ljava/lang/String;Ljava/lang/String;Ljava/lang/String;Ljava/lang/Throwable;)V
     102: return
    Exception table:
       from    to  target type
          47    73    76   any
          76    79    76   any
           0    81    84   Class java/lang/Throwable
}
