Compiled from "Registry.java"
public interface org.apache.dubbo.registry.Registry extends org.apache.dubbo.common.Node,org.apache.dubbo.registry.RegistryService {
  public default int getDelay();
    Code:
       0: aload_0
       1: invokeinterface #2,  1            // InterfaceMethod getUrl:()Lorg/apache/dubbo/common/URL;
       6: ldc           #3                  // String delay-notification
       8: sipush        5000
      11: invokevirtual #4                  // Method org/apache/dubbo/common/URL.getParameter:(Ljava/lang/String;I)I
      14: ireturn

  public default boolean isServiceDiscovery();
    Code:
       0: iconst_0
       1: ireturn

  public default void reExportRegister(org.apache.dubbo.common.URL);
    Code:
       0: aload_0
       1: aload_1
       2: invokeinterface #5,  2            // InterfaceMethod register:(Lorg/apache/dubbo/common/URL;)V
       7: return

  public default void reExportUnregister(org.apache.dubbo.common.URL);
    Code:
       0: aload_0
       1: aload_1
       2: invokeinterface #6,  2            // InterfaceMethod unregister:(Lorg/apache/dubbo/common/URL;)V
       7: return
}
