Compiled from "RegistryNotifier.java"
public abstract class org.apache.dubbo.registry.RegistryNotifier {
  private static final org.apache.dubbo.common.logger.ErrorTypeAwareLogger logger;

  private volatile long lastExecuteTime;

  private volatile long lastEventTime;

  private java.lang.Object rawAddresses;

  private long delayTime;

  private final java.util.concurrent.atomic.AtomicBoolean shouldDelay;

  private final java.util.concurrent.atomic.AtomicInteger executeTime;

  private java.util.concurrent.ScheduledExecutorService scheduler;

  public org.apache.dubbo.registry.RegistryNotifier(org.apache.dubbo.common.URL, long);
    Code:
       0: aload_0
       1: aload_1
       2: lload_2
       3: aconst_null
       4: invokespecial #6                  // Method "<init>":(Lorg/apache/dubbo/common/URL;JLjava/util/concurrent/ScheduledExecutorService;)V
       7: return

  public org.apache.dubbo.registry.RegistryNotifier(org.apache.dubbo.common.URL, long, java.util.concurrent.ScheduledExecutorService);
    Code:
       0: aload_0
       1: invokespecial #7                  // Method java/lang/Object."<init>":()V
       4: aload_0
       5: new           #8                  // class java/util/concurrent/atomic/AtomicBoolean
       8: dup
       9: iconst_0
      10: invokespecial #9                  // Method java/util/concurrent/atomic/AtomicBoolean."<init>":(Z)V
      13: putfield      #10                 // Field shouldDelay:Ljava/util/concurrent/atomic/AtomicBoolean;
      16: aload_0
      17: new           #11                 // class java/util/concurrent/atomic/AtomicInteger
      20: dup
      21: iconst_0
      22: invokespecial #12                 // Method java/util/concurrent/atomic/AtomicInteger."<init>":(I)V
      25: putfield      #13                 // Field executeTime:Ljava/util/concurrent/atomic/AtomicInteger;
      28: aload_0
      29: lload_2
      30: putfield      #14                 // Field delayTime:J
      33: aload         4
      35: ifnonnull     63
      38: aload_0
      39: aload_1
      40: invokevirtual #15                 // Method org/apache/dubbo/common/URL.getOrDefaultFrameworkModel:()Lorg/apache/dubbo/rpc/model/FrameworkModel;
      43: invokevirtual #16                 // Method org/apache/dubbo/rpc/model/FrameworkModel.getBeanFactory:()Lorg/apache/dubbo/common/beans/factory/ScopeBeanFactory;
      46: ldc           #17                 // class org/apache/dubbo/common/threadpool/manager/FrameworkExecutorRepository
      48: invokevirtual #18                 // Method org/apache/dubbo/common/beans/factory/ScopeBeanFactory.getBean:(Ljava/lang/Class;)Ljava/lang/Object;
      51: checkcast     #17                 // class org/apache/dubbo/common/threadpool/manager/FrameworkExecutorRepository
      54: invokevirtual #19                 // Method org/apache/dubbo/common/threadpool/manager/FrameworkExecutorRepository.getRegistryNotificationExecutor:()Ljava/util/concurrent/ScheduledExecutorService;
      57: putfield      #20                 // Field scheduler:Ljava/util/concurrent/ScheduledExecutorService;
      60: goto          69
      63: aload_0
      64: aload         4
      66: putfield      #20                 // Field scheduler:Ljava/util/concurrent/ScheduledExecutorService;
      69: return

  public synchronized void notify(java.lang.Object);
    Code:
       0: aload_0
       1: aload_1
       2: putfield      #4                  // Field rawAddresses:Ljava/lang/Object;
       5: invokestatic  #21                 // Method java/lang/System.currentTimeMillis:()J
       8: lstore_2
       9: aload_0
      10: lload_2
      11: putfield      #5                  // Field lastEventTime:J
      14: invokestatic  #21                 // Method java/lang/System.currentTimeMillis:()J
      17: aload_0
      18: getfield      #3                  // Field lastExecuteTime:J
      21: lsub
      22: aload_0
      23: getfield      #14                 // Field delayTime:J
      26: lsub
      27: lstore        4
      29: aload_0
      30: getfield      #10                 // Field shouldDelay:Ljava/util/concurrent/atomic/AtomicBoolean;
      33: invokevirtual #22                 // Method java/util/concurrent/atomic/AtomicBoolean.get:()Z
      36: ifeq          50
      39: lload         4
      41: lconst_0
      42: lcmp
      43: ifge          50
      46: iconst_1
      47: goto          51
      50: iconst_0
      51: istore        6
      53: iload         6
      55: ifeq          86
      58: aload_0
      59: getfield      #20                 // Field scheduler:Ljava/util/concurrent/ScheduledExecutorService;
      62: new           #23                 // class org/apache/dubbo/registry/RegistryNotifier$NotificationTask
      65: dup
      66: aload_0
      67: lload_2
      68: invokespecial #24                 // Method org/apache/dubbo/registry/RegistryNotifier$NotificationTask."<init>":(Lorg/apache/dubbo/registry/RegistryNotifier;J)V
      71: lload         4
      73: lneg
      74: getstatic     #25                 // Field java/util/concurrent/TimeUnit.MILLISECONDS:Ljava/util/concurrent/TimeUnit;
      77: invokeinterface #26,  5           // InterfaceMethod java/util/concurrent/ScheduledExecutorService.schedule:(Ljava/lang/Runnable;JLjava/util/concurrent/TimeUnit;)Ljava/util/concurrent/ScheduledFuture;
      82: pop
      83: goto          135
      86: aload_0
      87: getfield      #10                 // Field shouldDelay:Ljava/util/concurrent/atomic/AtomicBoolean;
      90: invokevirtual #22                 // Method java/util/concurrent/atomic/AtomicBoolean.get:()Z
      93: ifne          116
      96: aload_0
      97: getfield      #13                 // Field executeTime:Ljava/util/concurrent/atomic/AtomicInteger;
     100: invokevirtual #27                 // Method java/util/concurrent/atomic/AtomicInteger.incrementAndGet:()I
     103: bipush        10
     105: if_icmple     116
     108: aload_0
     109: getfield      #10                 // Field shouldDelay:Ljava/util/concurrent/atomic/AtomicBoolean;
     112: iconst_1
     113: invokevirtual #28                 // Method java/util/concurrent/atomic/AtomicBoolean.set:(Z)V
     116: aload_0
     117: getfield      #20                 // Field scheduler:Ljava/util/concurrent/ScheduledExecutorService;
     120: new           #23                 // class org/apache/dubbo/registry/RegistryNotifier$NotificationTask
     123: dup
     124: aload_0
     125: lload_2
     126: invokespecial #24                 // Method org/apache/dubbo/registry/RegistryNotifier$NotificationTask."<init>":(Lorg/apache/dubbo/registry/RegistryNotifier;J)V
     129: invokeinterface #29,  2           // InterfaceMethod java/util/concurrent/ScheduledExecutorService.submit:(Ljava/lang/Runnable;)Ljava/util/concurrent/Future;
     134: pop
     135: return

  public long getDelayTime();
    Code:
       0: aload_0
       1: getfield      #14                 // Field delayTime:J
       4: lreturn

  protected abstract void doNotify(java.lang.Object);

  static long access$000(org.apache.dubbo.registry.RegistryNotifier);
    Code:
       0: aload_0
       1: getfield      #5                  // Field lastEventTime:J
       4: lreturn

  static java.lang.Object access$100(org.apache.dubbo.registry.RegistryNotifier);
    Code:
       0: aload_0
       1: getfield      #4                  // Field rawAddresses:Ljava/lang/Object;
       4: areturn

  static long access$202(org.apache.dubbo.registry.RegistryNotifier, long);
    Code:
       0: aload_0
       1: lload_1
       2: dup2_x1
       3: putfield      #3                  // Field lastExecuteTime:J
       6: lreturn

  static java.lang.Object access$102(org.apache.dubbo.registry.RegistryNotifier, java.lang.Object);
    Code:
       0: aload_0
       1: aload_1
       2: dup_x1
       3: putfield      #4                  // Field rawAddresses:Ljava/lang/Object;
       6: areturn

  static org.apache.dubbo.common.logger.ErrorTypeAwareLogger access$300();
    Code:
       0: getstatic     #2                  // Field logger:Lorg/apache/dubbo/common/logger/ErrorTypeAwareLogger;
       3: areturn

  static {};
    Code:
       0: ldc           #30                 // class org/apache/dubbo/registry/RegistryNotifier
       2: invokestatic  #31                 // Method org/apache/dubbo/common/logger/LoggerFactory.getErrorTypeAwareLogger:(Ljava/lang/Class;)Lorg/apache/dubbo/common/logger/ErrorTypeAwareLogger;
       5: putstatic     #2                  // Field logger:Lorg/apache/dubbo/common/logger/ErrorTypeAwareLogger;
       8: return
}
