Compiled from "RegistryFactoryWrapper.java"
public class org.apache.dubbo.registry.RegistryFactoryWrapper implements org.apache.dubbo.registry.RegistryFactory {
  private org.apache.dubbo.registry.RegistryFactory registryFactory;

  public org.apache.dubbo.registry.RegistryFactoryWrapper(org.apache.dubbo.registry.RegistryFactory);
    Code:
       0: aload_0
       1: invokespecial #1                  // Method java/lang/Object."<init>":()V
       4: aload_0
       5: aload_1
       6: putfield      #2                  // Field registryFactory:Lorg/apache/dubbo/registry/RegistryFactory;
       9: return

  public org.apache.dubbo.registry.Registry getRegistry(org.apache.dubbo.common.URL);
    Code:
       0: new           #3                  // class org/apache/dubbo/registry/ListenerRegistryWrapper
       3: dup
       4: aload_0
       5: getfield      #2                  // Field registryFactory:Lorg/apache/dubbo/registry/RegistryFactory;
       8: aload_1
       9: invokeinterface #4,  2            // InterfaceMethod org/apache/dubbo/registry/RegistryFactory.getRegistry:(Lorg/apache/dubbo/common/URL;)Lorg/apache/dubbo/registry/Registry;
      14: aload_1
      15: invokevirtual #5                  // Method org/apache/dubbo/common/URL.getOrDefaultApplicationModel:()Lorg/apache/dubbo/rpc/model/ApplicationModel;
      18: ldc           #6                  // class org/apache/dubbo/registry/RegistryServiceListener
      20: invokevirtual #7                  // Method org/apache/dubbo/rpc/model/ApplicationModel.getExtensionLoader:(Ljava/lang/Class;)Lorg/apache/dubbo/common/extension/ExtensionLoader;
      23: aload_1
      24: ldc           #8                  // String registry.listeners
      26: invokevirtual #9                  // Method org/apache/dubbo/common/extension/ExtensionLoader.getActivateExtension:(Lorg/apache/dubbo/common/URL;Ljava/lang/String;)Ljava/util/List;
      29: invokestatic  #10                 // Method java/util/Collections.unmodifiableList:(Ljava/util/List;)Ljava/util/List;
      32: invokespecial #11                 // Method org/apache/dubbo/registry/ListenerRegistryWrapper."<init>":(Lorg/apache/dubbo/registry/Registry;Ljava/util/List;)V
      35: areturn
}
