Compiled from "DefaultGovernanceRuleRepositoryImpl.java"
public class org.apache.dubbo.rpc.cluster.governance.DefaultGovernanceRuleRepositoryImpl implements org.apache.dubbo.rpc.cluster.governance.GovernanceRuleRepository {
  private final org.apache.dubbo.rpc.model.ModuleModel moduleModel;

  public org.apache.dubbo.rpc.cluster.governance.DefaultGovernanceRuleRepositoryImpl(org.apache.dubbo.rpc.model.ModuleModel);
    Code:
       0: aload_0
       1: invokespecial #1                  // Method java/lang/Object."<init>":()V
       4: aload_0
       5: aload_1
       6: putfield      #2                  // Field moduleModel:Lorg/apache/dubbo/rpc/model/ModuleModel;
       9: return

  public void addListener(java.lang.String, java.lang.String, org.apache.dubbo.common.config.configcenter.ConfigurationListener);
    Code:
       0: aload_0
       1: invokespecial #3                  // Method getDynamicConfiguration:()Lorg/apache/dubbo/common/config/configcenter/DynamicConfiguration;
       4: astore        4
       6: aload         4
       8: ifnull        21
      11: aload         4
      13: aload_1
      14: aload_2
      15: aload_3
      16: invokeinterface #4,  4            // InterfaceMethod org/apache/dubbo/common/config/configcenter/DynamicConfiguration.addListener:(Ljava/lang/String;Ljava/lang/String;Lorg/apache/dubbo/common/config/configcenter/ConfigurationListener;)V
      21: return

  public void removeListener(java.lang.String, java.lang.String, org.apache.dubbo.common.config.configcenter.ConfigurationListener);
    Code:
       0: aload_0
       1: invokespecial #3                  // Method getDynamicConfiguration:()Lorg/apache/dubbo/common/config/configcenter/DynamicConfiguration;
       4: astore        4
       6: aload         4
       8: ifnull        21
      11: aload         4
      13: aload_1
      14: aload_2
      15: aload_3
      16: invokeinterface #5,  4            // InterfaceMethod org/apache/dubbo/common/config/configcenter/DynamicConfiguration.removeListener:(Ljava/lang/String;Ljava/lang/String;Lorg/apache/dubbo/common/config/configcenter/ConfigurationListener;)V
      21: return

  public java.lang.String getRule(java.lang.String, java.lang.String, long) throws java.lang.IllegalStateException;
    Code:
       0: aload_0
       1: invokespecial #3                  // Method getDynamicConfiguration:()Lorg/apache/dubbo/common/config/configcenter/DynamicConfiguration;
       4: astore        5
       6: aload         5
       8: ifnull        22
      11: aload         5
      13: aload_1
      14: aload_2
      15: lload_3
      16: invokeinterface #6,  5            // InterfaceMethod org/apache/dubbo/common/config/configcenter/DynamicConfiguration.getConfig:(Ljava/lang/String;Ljava/lang/String;J)Ljava/lang/String;
      21: areturn
      22: aconst_null
      23: areturn

  private org.apache.dubbo.common.config.configcenter.DynamicConfiguration getDynamicConfiguration();
    Code:
       0: aload_0
       1: getfield      #2                  // Field moduleModel:Lorg/apache/dubbo/rpc/model/ModuleModel;
       4: invokevirtual #7                  // Method org/apache/dubbo/rpc/model/ModuleModel.getModelEnvironment:()Lorg/apache/dubbo/common/config/ModuleEnvironment;
       7: invokevirtual #8                  // Method org/apache/dubbo/common/config/ModuleEnvironment.getDynamicConfiguration:()Ljava/util/Optional;
      10: aconst_null
      11: invokevirtual #9                  // Method java/util/Optional.orElse:(Ljava/lang/Object;)Ljava/lang/Object;
      14: checkcast     #10                 // class org/apache/dubbo/common/config/configcenter/DynamicConfiguration
      17: areturn
}
