Compiled from "GovernanceRuleRepository.java"
public interface org.apache.dubbo.rpc.cluster.governance.GovernanceRuleRepository {
  public static final java.lang.String DEFAULT_GROUP;

  public default void addListener(java.lang.String, org.apache.dubbo.common.config.configcenter.ConfigurationListener);
    Code:
       0: aload_0
       1: aload_1
       2: ldc           #2                  // String dubbo
       4: aload_2
       5: invokeinterface #3,  4            // InterfaceMethod addListener:(Ljava/lang/String;Ljava/lang/String;Lorg/apache/dubbo/common/config/configcenter/ConfigurationListener;)V
      10: return

  public default void removeListener(java.lang.String, org.apache.dubbo.common.config.configcenter.ConfigurationListener);
    Code:
       0: aload_0
       1: aload_1
       2: ldc           #2                  // String dubbo
       4: aload_2
       5: invokeinterface #4,  4            // InterfaceMethod removeListener:(Ljava/lang/String;Ljava/lang/String;Lorg/apache/dubbo/common/config/configcenter/ConfigurationListener;)V
      10: return

  public abstract void addListener(java.lang.String, java.lang.String, org.apache.dubbo.common.config.configcenter.ConfigurationListener);

  public abstract void removeListener(java.lang.String, java.lang.String, org.apache.dubbo.common.config.configcenter.ConfigurationListener);

  public default java.lang.String getRule(java.lang.String, java.lang.String);
    Code:
       0: aload_0
       1: aload_1
       2: aload_2
       3: ldc2_w        #5                  // long -1l
       6: invokeinterface #7,  5            // InterfaceMethod getRule:(Ljava/lang/String;Ljava/lang/String;J)Ljava/lang/String;
      11: areturn

  public abstract java.lang.String getRule(java.lang.String, java.lang.String, long) throws java.lang.IllegalStateException;
}
