Compiled from "HttpClientConfig.java"
public class org.apache.dubbo.remoting.http.config.HttpClientConfig {
  private int readTimeout;

  private int writeTimeout;

  private int connectTimeout;

  private int chunkLength;

  private int HTTP_CLIENT_CONNECTION_MANAGER_MAX_PER_ROUTE;

  private int HTTP_CLIENT_CONNECTION_MANAGER_MAX_TOTAL;

  private int HTTPCLIENT_KEEP_ALIVE_DURATION;

  private int HTTP_CLIENT_CONNECTION_MANAGER_CLOSE_WAIT_TIME_MS;

  private int HTTP_CLIENT_CONNECTION_MANAGER_CLOSE_IDLE_TIME_S;

  public org.apache.dubbo.remoting.http.config.HttpClientConfig();
    Code:
       0: aload_0
       1: invokespecial #1                  // Method java/lang/Object."<init>":()V
       4: aload_0
       5: sipush        6000
       8: putfield      #2                  // Field readTimeout:I
      11: aload_0
      12: sipush        6000
      15: putfield      #3                  // Field writeTimeout:I
      18: aload_0
      19: sipush        6000
      22: putfield      #4                  // Field connectTimeout:I
      25: aload_0
      26: sipush        8196
      29: putfield      #5                  // Field chunkLength:I
      32: aload_0
      33: bipush        20
      35: putfield      #6                  // Field HTTP_CLIENT_CONNECTION_MANAGER_MAX_PER_ROUTE:I
      38: aload_0
      39: bipush        20
      41: putfield      #7                  // Field HTTP_CLIENT_CONNECTION_MANAGER_MAX_TOTAL:I
      44: aload_0
      45: sipush        30000
      48: putfield      #8                  // Field HTTPCLIENT_KEEP_ALIVE_DURATION:I
      51: aload_0
      52: sipush        1000
      55: putfield      #9                  // Field HTTP_CLIENT_CONNECTION_MANAGER_CLOSE_WAIT_TIME_MS:I
      58: aload_0
      59: bipush        30
      61: putfield      #10                 // Field HTTP_CLIENT_CONNECTION_MANAGER_CLOSE_IDLE_TIME_S:I
      64: return

  public int getReadTimeout();
    Code:
       0: aload_0
       1: getfield      #2                  // Field readTimeout:I
       4: ireturn

  public void setReadTimeout(int);
    Code:
       0: aload_0
       1: iload_1
       2: putfield      #2                  // Field readTimeout:I
       5: return

  public int getWriteTimeout();
    Code:
       0: aload_0
       1: getfield      #3                  // Field writeTimeout:I
       4: ireturn

  public void setWriteTimeout(int);
    Code:
       0: aload_0
       1: iload_1
       2: putfield      #3                  // Field writeTimeout:I
       5: return

  public int getConnectTimeout();
    Code:
       0: aload_0
       1: getfield      #4                  // Field connectTimeout:I
       4: ireturn

  public void setConnectTimeout(int);
    Code:
       0: aload_0
       1: iload_1
       2: putfield      #4                  // Field connectTimeout:I
       5: return

  public int getChunkLength();
    Code:
       0: aload_0
       1: getfield      #5                  // Field chunkLength:I
       4: ireturn
}
