Compiled from "RegistryMetricsConstants.java"
public interface org.apache.dubbo.metrics.registry.RegistryMetricsConstants {
  public static final org.apache.dubbo.metrics.model.key.MetricsPlaceValue OP_TYPE_REGISTER;

  public static final org.apache.dubbo.metrics.model.key.MetricsPlaceValue OP_TYPE_SUBSCRIBE;

  public static final org.apache.dubbo.metrics.model.key.MetricsPlaceValue OP_TYPE_NOTIFY;

  public static final org.apache.dubbo.metrics.model.key.MetricsPlaceValue OP_TYPE_DIRECTORY;

  public static final org.apache.dubbo.metrics.model.key.MetricsPlaceValue OP_TYPE_REGISTER_SERVICE;

  public static final org.apache.dubbo.metrics.model.key.MetricsPlaceValue OP_TYPE_SUBSCRIBE_SERVICE;

  public static final java.util.List<org.apache.dubbo.metrics.model.key.MetricsKey> APP_LEVEL_KEYS;

  public static final java.util.List<org.apache.dubbo.metrics.model.key.MetricsKeyWrapper> SERVICE_LEVEL_KEYS;

  static {};
    Code:
       0: ldc           #1                  // String register
       2: getstatic     #2                  // Field org/apache/dubbo/metrics/model/key/MetricsLevel.APP:Lorg/apache/dubbo/metrics/model/key/MetricsLevel;
       5: invokestatic  #3                  // Method org/apache/dubbo/metrics/model/key/MetricsPlaceValue.of:(Ljava/lang/String;Lorg/apache/dubbo/metrics/model/key/MetricsLevel;)Lorg/apache/dubbo/metrics/model/key/MetricsPlaceValue;
       8: putstatic     #4                  // Field OP_TYPE_REGISTER:Lorg/apache/dubbo/metrics/model/key/MetricsPlaceValue;
      11: ldc           #5                  // String subscribe
      13: getstatic     #2                  // Field org/apache/dubbo/metrics/model/key/MetricsLevel.APP:Lorg/apache/dubbo/metrics/model/key/MetricsLevel;
      16: invokestatic  #3                  // Method org/apache/dubbo/metrics/model/key/MetricsPlaceValue.of:(Ljava/lang/String;Lorg/apache/dubbo/metrics/model/key/MetricsLevel;)Lorg/apache/dubbo/metrics/model/key/MetricsPlaceValue;
      19: putstatic     #6                  // Field OP_TYPE_SUBSCRIBE:Lorg/apache/dubbo/metrics/model/key/MetricsPlaceValue;
      22: ldc           #7                  // String notify
      24: getstatic     #2                  // Field org/apache/dubbo/metrics/model/key/MetricsLevel.APP:Lorg/apache/dubbo/metrics/model/key/MetricsLevel;
      27: invokestatic  #3                  // Method org/apache/dubbo/metrics/model/key/MetricsPlaceValue.of:(Ljava/lang/String;Lorg/apache/dubbo/metrics/model/key/MetricsLevel;)Lorg/apache/dubbo/metrics/model/key/MetricsPlaceValue;
      30: putstatic     #8                  // Field OP_TYPE_NOTIFY:Lorg/apache/dubbo/metrics/model/key/MetricsPlaceValue;
      33: ldc           #9                  // String directory
      35: getstatic     #2                  // Field org/apache/dubbo/metrics/model/key/MetricsLevel.APP:Lorg/apache/dubbo/metrics/model/key/MetricsLevel;
      38: invokestatic  #3                  // Method org/apache/dubbo/metrics/model/key/MetricsPlaceValue.of:(Ljava/lang/String;Lorg/apache/dubbo/metrics/model/key/MetricsLevel;)Lorg/apache/dubbo/metrics/model/key/MetricsPlaceValue;
      41: putstatic     #10                 // Field OP_TYPE_DIRECTORY:Lorg/apache/dubbo/metrics/model/key/MetricsPlaceValue;
      44: ldc           #11                 // String register.service
      46: getstatic     #12                 // Field org/apache/dubbo/metrics/model/key/MetricsLevel.SERVICE:Lorg/apache/dubbo/metrics/model/key/MetricsLevel;
      49: invokestatic  #3                  // Method org/apache/dubbo/metrics/model/key/MetricsPlaceValue.of:(Ljava/lang/String;Lorg/apache/dubbo/metrics/model/key/MetricsLevel;)Lorg/apache/dubbo/metrics/model/key/MetricsPlaceValue;
      52: putstatic     #13                 // Field OP_TYPE_REGISTER_SERVICE:Lorg/apache/dubbo/metrics/model/key/MetricsPlaceValue;
      55: ldc           #14                 // String subscribe.service
      57: getstatic     #12                 // Field org/apache/dubbo/metrics/model/key/MetricsLevel.SERVICE:Lorg/apache/dubbo/metrics/model/key/MetricsLevel;
      60: invokestatic  #3                  // Method org/apache/dubbo/metrics/model/key/MetricsPlaceValue.of:(Ljava/lang/String;Lorg/apache/dubbo/metrics/model/key/MetricsLevel;)Lorg/apache/dubbo/metrics/model/key/MetricsPlaceValue;
      63: putstatic     #15                 // Field OP_TYPE_SUBSCRIBE_SERVICE:Lorg/apache/dubbo/metrics/model/key/MetricsPlaceValue;
      66: bipush        7
      68: anewarray     #16                 // class org/apache/dubbo/metrics/model/key/MetricsKey
      71: dup
      72: iconst_0
      73: getstatic     #17                 // Field org/apache/dubbo/metrics/model/key/MetricsKey.REGISTER_METRIC_REQUESTS:Lorg/apache/dubbo/metrics/model/key/MetricsKey;
      76: aastore
      77: dup
      78: iconst_1
      79: getstatic     #18                 // Field org/apache/dubbo/metrics/model/key/MetricsKey.REGISTER_METRIC_REQUESTS_SUCCEED:Lorg/apache/dubbo/metrics/model/key/MetricsKey;
      82: aastore
      83: dup
      84: iconst_2
      85: getstatic     #19                 // Field org/apache/dubbo/metrics/model/key/MetricsKey.REGISTER_METRIC_REQUESTS_FAILED:Lorg/apache/dubbo/metrics/model/key/MetricsKey;
      88: aastore
      89: dup
      90: iconst_3
      91: getstatic     #20                 // Field org/apache/dubbo/metrics/model/key/MetricsKey.SUBSCRIBE_METRIC_NUM:Lorg/apache/dubbo/metrics/model/key/MetricsKey;
      94: aastore
      95: dup
      96: iconst_4
      97: getstatic     #21                 // Field org/apache/dubbo/metrics/model/key/MetricsKey.SUBSCRIBE_METRIC_NUM_SUCCEED:Lorg/apache/dubbo/metrics/model/key/MetricsKey;
     100: aastore
     101: dup
     102: iconst_5
     103: getstatic     #22                 // Field org/apache/dubbo/metrics/model/key/MetricsKey.SUBSCRIBE_METRIC_NUM_FAILED:Lorg/apache/dubbo/metrics/model/key/MetricsKey;
     106: aastore
     107: dup
     108: bipush        6
     110: getstatic     #23                 // Field org/apache/dubbo/metrics/model/key/MetricsKey.NOTIFY_METRIC_REQUESTS:Lorg/apache/dubbo/metrics/model/key/MetricsKey;
     113: aastore
     114: invokestatic  #24                 // Method java/util/Arrays.asList:([Ljava/lang/Object;)Ljava/util/List;
     117: putstatic     #25                 // Field APP_LEVEL_KEYS:Ljava/util/List;
     120: bipush        11
     122: anewarray     #26                 // class org/apache/dubbo/metrics/model/key/MetricsKeyWrapper
     125: dup
     126: iconst_0
     127: new           #26                 // class org/apache/dubbo/metrics/model/key/MetricsKeyWrapper
     130: dup
     131: getstatic     #27                 // Field org/apache/dubbo/metrics/model/key/MetricsKey.NOTIFY_METRIC_NUM_LAST:Lorg/apache/dubbo/metrics/model/key/MetricsKey;
     134: getstatic     #8                  // Field OP_TYPE_NOTIFY:Lorg/apache/dubbo/metrics/model/key/MetricsPlaceValue;
     137: invokespecial #28                 // Method org/apache/dubbo/metrics/model/key/MetricsKeyWrapper."<init>":(Lorg/apache/dubbo/metrics/model/key/MetricsKey;Lorg/apache/dubbo/metrics/model/key/MetricsPlaceValue;)V
     140: aastore
     141: dup
     142: iconst_1
     143: new           #26                 // class org/apache/dubbo/metrics/model/key/MetricsKeyWrapper
     146: dup
     147: getstatic     #29                 // Field org/apache/dubbo/metrics/model/key/MetricsKey.SERVICE_REGISTER_METRIC_REQUESTS:Lorg/apache/dubbo/metrics/model/key/MetricsKey;
     150: getstatic     #13                 // Field OP_TYPE_REGISTER_SERVICE:Lorg/apache/dubbo/metrics/model/key/MetricsPlaceValue;
     153: invokespecial #28                 // Method org/apache/dubbo/metrics/model/key/MetricsKeyWrapper."<init>":(Lorg/apache/dubbo/metrics/model/key/MetricsKey;Lorg/apache/dubbo/metrics/model/key/MetricsPlaceValue;)V
     156: aastore
     157: dup
     158: iconst_2
     159: new           #26                 // class org/apache/dubbo/metrics/model/key/MetricsKeyWrapper
     162: dup
     163: getstatic     #30                 // Field org/apache/dubbo/metrics/model/key/MetricsKey.SERVICE_REGISTER_METRIC_REQUESTS_SUCCEED:Lorg/apache/dubbo/metrics/model/key/MetricsKey;
     166: getstatic     #13                 // Field OP_TYPE_REGISTER_SERVICE:Lorg/apache/dubbo/metrics/model/key/MetricsPlaceValue;
     169: invokespecial #28                 // Method org/apache/dubbo/metrics/model/key/MetricsKeyWrapper."<init>":(Lorg/apache/dubbo/metrics/model/key/MetricsKey;Lorg/apache/dubbo/metrics/model/key/MetricsPlaceValue;)V
     172: aastore
     173: dup
     174: iconst_3
     175: new           #26                 // class org/apache/dubbo/metrics/model/key/MetricsKeyWrapper
     178: dup
     179: getstatic     #31                 // Field org/apache/dubbo/metrics/model/key/MetricsKey.SERVICE_REGISTER_METRIC_REQUESTS_FAILED:Lorg/apache/dubbo/metrics/model/key/MetricsKey;
     182: getstatic     #13                 // Field OP_TYPE_REGISTER_SERVICE:Lorg/apache/dubbo/metrics/model/key/MetricsPlaceValue;
     185: invokespecial #28                 // Method org/apache/dubbo/metrics/model/key/MetricsKeyWrapper."<init>":(Lorg/apache/dubbo/metrics/model/key/MetricsKey;Lorg/apache/dubbo/metrics/model/key/MetricsPlaceValue;)V
     188: aastore
     189: dup
     190: iconst_4
     191: new           #26                 // class org/apache/dubbo/metrics/model/key/MetricsKeyWrapper
     194: dup
     195: getstatic     #32                 // Field org/apache/dubbo/metrics/model/key/MetricsKey.SERVICE_SUBSCRIBE_METRIC_NUM:Lorg/apache/dubbo/metrics/model/key/MetricsKey;
     198: getstatic     #15                 // Field OP_TYPE_SUBSCRIBE_SERVICE:Lorg/apache/dubbo/metrics/model/key/MetricsPlaceValue;
     201: invokespecial #28                 // Method org/apache/dubbo/metrics/model/key/MetricsKeyWrapper."<init>":(Lorg/apache/dubbo/metrics/model/key/MetricsKey;Lorg/apache/dubbo/metrics/model/key/MetricsPlaceValue;)V
     204: aastore
     205: dup
     206: iconst_5
     207: new           #26                 // class org/apache/dubbo/metrics/model/key/MetricsKeyWrapper
     210: dup
     211: getstatic     #33                 // Field org/apache/dubbo/metrics/model/key/MetricsKey.SERVICE_SUBSCRIBE_METRIC_NUM_SUCCEED:Lorg/apache/dubbo/metrics/model/key/MetricsKey;
     214: getstatic     #15                 // Field OP_TYPE_SUBSCRIBE_SERVICE:Lorg/apache/dubbo/metrics/model/key/MetricsPlaceValue;
     217: invokespecial #28                 // Method org/apache/dubbo/metrics/model/key/MetricsKeyWrapper."<init>":(Lorg/apache/dubbo/metrics/model/key/MetricsKey;Lorg/apache/dubbo/metrics/model/key/MetricsPlaceValue;)V
     220: aastore
     221: dup
     222: bipush        6
     224: new           #26                 // class org/apache/dubbo/metrics/model/key/MetricsKeyWrapper
     227: dup
     228: getstatic     #34                 // Field org/apache/dubbo/metrics/model/key/MetricsKey.SERVICE_SUBSCRIBE_METRIC_NUM_FAILED:Lorg/apache/dubbo/metrics/model/key/MetricsKey;
     231: getstatic     #15                 // Field OP_TYPE_SUBSCRIBE_SERVICE:Lorg/apache/dubbo/metrics/model/key/MetricsPlaceValue;
     234: invokespecial #28                 // Method org/apache/dubbo/metrics/model/key/MetricsKeyWrapper."<init>":(Lorg/apache/dubbo/metrics/model/key/MetricsKey;Lorg/apache/dubbo/metrics/model/key/MetricsPlaceValue;)V
     237: aastore
     238: dup
     239: bipush        7
     241: new           #26                 // class org/apache/dubbo/metrics/model/key/MetricsKeyWrapper
     244: dup
     245: getstatic     #35                 // Field org/apache/dubbo/metrics/model/key/MetricsKey.DIRECTORY_METRIC_NUM_VALID:Lorg/apache/dubbo/metrics/model/key/MetricsKey;
     248: getstatic     #10                 // Field OP_TYPE_DIRECTORY:Lorg/apache/dubbo/metrics/model/key/MetricsPlaceValue;
     251: invokespecial #28                 // Method org/apache/dubbo/metrics/model/key/MetricsKeyWrapper."<init>":(Lorg/apache/dubbo/metrics/model/key/MetricsKey;Lorg/apache/dubbo/metrics/model/key/MetricsPlaceValue;)V
     254: aastore
     255: dup
     256: bipush        8
     258: new           #26                 // class org/apache/dubbo/metrics/model/key/MetricsKeyWrapper
     261: dup
     262: getstatic     #36                 // Field org/apache/dubbo/metrics/model/key/MetricsKey.DIRECTORY_METRIC_NUM_TO_RECONNECT:Lorg/apache/dubbo/metrics/model/key/MetricsKey;
     265: getstatic     #10                 // Field OP_TYPE_DIRECTORY:Lorg/apache/dubbo/metrics/model/key/MetricsPlaceValue;
     268: invokespecial #28                 // Method org/apache/dubbo/metrics/model/key/MetricsKeyWrapper."<init>":(Lorg/apache/dubbo/metrics/model/key/MetricsKey;Lorg/apache/dubbo/metrics/model/key/MetricsPlaceValue;)V
     271: aastore
     272: dup
     273: bipush        9
     275: new           #26                 // class org/apache/dubbo/metrics/model/key/MetricsKeyWrapper
     278: dup
     279: getstatic     #37                 // Field org/apache/dubbo/metrics/model/key/MetricsKey.DIRECTORY_METRIC_NUM_DISABLE:Lorg/apache/dubbo/metrics/model/key/MetricsKey;
     282: getstatic     #10                 // Field OP_TYPE_DIRECTORY:Lorg/apache/dubbo/metrics/model/key/MetricsPlaceValue;
     285: invokespecial #28                 // Method org/apache/dubbo/metrics/model/key/MetricsKeyWrapper."<init>":(Lorg/apache/dubbo/metrics/model/key/MetricsKey;Lorg/apache/dubbo/metrics/model/key/MetricsPlaceValue;)V
     288: aastore
     289: dup
     290: bipush        10
     292: new           #26                 // class org/apache/dubbo/metrics/model/key/MetricsKeyWrapper
     295: dup
     296: getstatic     #38                 // Field org/apache/dubbo/metrics/model/key/MetricsKey.DIRECTORY_METRIC_NUM_ALL:Lorg/apache/dubbo/metrics/model/key/MetricsKey;
     299: getstatic     #10                 // Field OP_TYPE_DIRECTORY:Lorg/apache/dubbo/metrics/model/key/MetricsPlaceValue;
     302: invokespecial #28                 // Method org/apache/dubbo/metrics/model/key/MetricsKeyWrapper."<init>":(Lorg/apache/dubbo/metrics/model/key/MetricsKey;Lorg/apache/dubbo/metrics/model/key/MetricsPlaceValue;)V
     305: aastore
     306: invokestatic  #24                 // Method java/util/Arrays.asList:([Ljava/lang/Object;)Ljava/util/List;
     309: putstatic     #39                 // Field SERVICE_LEVEL_KEYS:Ljava/util/List;
     312: return
}
