Compiled from "AbstractStream.java"
public abstract class org.apache.dubbo.rpc.protocol.tri.stream.AbstractStream implements org.apache.dubbo.rpc.protocol.tri.stream.Stream {
  protected java.util.concurrent.Executor executor;

  protected final org.apache.dubbo.rpc.model.FrameworkModel frameworkModel;

  private static final boolean HAS_PROTOBUF;

  public org.apache.dubbo.rpc.protocol.tri.stream.AbstractStream(java.util.concurrent.Executor, org.apache.dubbo.rpc.model.FrameworkModel);
    Code:
       0: aload_0
       1: invokespecial #1                  // Method java/lang/Object."<init>":()V
       4: aload_0
       5: new           #2                  // class org/apache/dubbo/common/threadpool/serial/SerializingExecutor
       8: dup
       9: aload_1
      10: invokespecial #3                  // Method org/apache/dubbo/common/threadpool/serial/SerializingExecutor."<init>":(Ljava/util/concurrent/Executor;)V
      13: putfield      #4                  // Field executor:Ljava/util/concurrent/Executor;
      16: aload_0
      17: aload_2
      18: putfield      #5                  // Field frameworkModel:Lorg/apache/dubbo/rpc/model/FrameworkModel;
      21: return

  public void setExecutor(java.util.concurrent.Executor);
    Code:
       0: aload_0
       1: new           #2                  // class org/apache/dubbo/common/threadpool/serial/SerializingExecutor
       4: dup
       5: aload_1
       6: invokespecial #3                  // Method org/apache/dubbo/common/threadpool/serial/SerializingExecutor."<init>":(Ljava/util/concurrent/Executor;)V
       9: putfield      #4                  // Field executor:Ljava/util/concurrent/Executor;
      12: return

  public static boolean getGrpcStatusDetailEnabled();
    Code:
       0: getstatic     #6                  // Field HAS_PROTOBUF:Z
       3: ireturn

  private static boolean hasProtobuf();
    Code:
       0: ldc           #7                  // String com.google.protobuf.Message
       2: invokestatic  #8                  // Method org/apache/dubbo/common/utils/ClassUtils.forName:(Ljava/lang/String;)Ljava/lang/Class;
       5: pop
       6: iconst_1
       7: ireturn
       8: astore_0
       9: iconst_0
      10: ireturn
    Exception table:
       from    to  target type
           0     7     8   Class java/lang/ClassNotFoundException

  static {};
    Code:
       0: invokestatic  #10                 // Method hasProtobuf:()Z
       3: putstatic     #6                  // Field HAS_PROTOBUF:Z
       6: return
}
