Compiled from "StreamUtils.java"
public class org.apache.dubbo.rpc.protocol.tri.stream.StreamUtils {
  protected static final org.apache.dubbo.common.logger.ErrorTypeAwareLogger LOGGER;

  private static final java.util.Base64$Decoder BASE64_DECODER;

  private static final java.util.Base64$Encoder BASE64_ENCODER;

  private static final int MAX_LRU_HEADER_MAP_SIZE;

  private static final java.util.Map<java.lang.String, java.lang.String> lruHeaderMap;

  public org.apache.dubbo.rpc.protocol.tri.stream.StreamUtils();
    Code:
       0: aload_0
       1: invokespecial #2                  // Method java/lang/Object."<init>":()V
       4: return

  public static java.lang.String encodeBase64ASCII(byte[]);
    Code:
       0: aload_0
       1: invokestatic  #3                  // Method encodeBase64:([B)[B
       4: astore_1
       5: new           #4                  // class java/lang/String
       8: dup
       9: aload_1
      10: getstatic     #5                  // Field java/nio/charset/StandardCharsets.US_ASCII:Ljava/nio/charset/Charset;
      13: invokespecial #6                  // Method java/lang/String."<init>":([BLjava/nio/charset/Charset;)V
      16: areturn

  public static byte[] encodeBase64(byte[]);
    Code:
       0: getstatic     #7                  // Field BASE64_ENCODER:Ljava/util/Base64$Encoder;
       3: aload_0
       4: invokevirtual #8                  // Method java/util/Base64$Encoder.encode:([B)[B
       7: areturn

  public static byte[] decodeASCIIByte(java.lang.CharSequence);
    Code:
       0: getstatic     #9                  // Field BASE64_DECODER:Ljava/util/Base64$Decoder;
       3: aload_0
       4: invokeinterface #10,  1           // InterfaceMethod java/lang/CharSequence.toString:()Ljava/lang/String;
       9: getstatic     #5                  // Field java/nio/charset/StandardCharsets.US_ASCII:Ljava/nio/charset/Charset;
      12: invokevirtual #11                 // Method java/lang/String.getBytes:(Ljava/nio/charset/Charset;)[B
      15: invokevirtual #12                 // Method java/util/Base64$Decoder.decode:([B)[B
      18: areturn

  public static java.util.Map<java.lang.String, java.lang.Object> toAttachments(java.util.Map<java.lang.String, java.lang.Object>);
    Code:
       0: aload_0
       1: ifnull        13
       4: aload_0
       5: invokeinterface #13,  1           // InterfaceMethod java/util/Map.isEmpty:()Z
      10: ifeq          17
      13: invokestatic  #14                 // Method java/util/Collections.emptyMap:()Ljava/util/Map;
      16: areturn
      17: new           #15                 // class java/util/HashMap
      20: dup
      21: aload_0
      22: invokeinterface #16,  1           // InterfaceMethod java/util/Map.size:()I
      27: invokespecial #17                 // Method java/util/HashMap."<init>":(I)V
      30: astore_1
      31: aload_0
      32: aload_1
      33: invokedynamic #18,  0             // InvokeDynamic #0:accept:(Ljava/util/Map;)Ljava/util/function/BiConsumer;
      38: invokeinterface #19,  2           // InterfaceMethod java/util/Map.forEach:(Ljava/util/function/BiConsumer;)V
      43: aload_1
      44: areturn

  public static void convertAttachment(io.netty.handler.codec.http2.DefaultHttp2Headers, java.util.Map<java.lang.String, java.lang.Object>, boolean);
    Code:
       0: aload_1
       1: ifnonnull     5
       4: return
       5: new           #15                 // class java/util/HashMap
       8: dup
       9: invokespecial #20                 // Method java/util/HashMap."<init>":()V
      12: astore_3
      13: aload_1
      14: invokeinterface #21,  1           // InterfaceMethod java/util/Map.entrySet:()Ljava/util/Set;
      19: invokeinterface #22,  1           // InterfaceMethod java/util/Set.iterator:()Ljava/util/Iterator;
      24: astore        4
      26: aload         4
      28: invokeinterface #23,  1           // InterfaceMethod java/util/Iterator.hasNext:()Z
      33: ifeq          187
      36: aload         4
      38: invokeinterface #24,  1           // InterfaceMethod java/util/Iterator.next:()Ljava/lang/Object;
      43: checkcast     #25                 // class java/util/Map$Entry
      46: astore        5
      48: getstatic     #26                 // Field lruHeaderMap:Ljava/util/Map;
      51: aload         5
      53: invokeinterface #27,  1           // InterfaceMethod java/util/Map$Entry.getKey:()Ljava/lang/Object;
      58: invokeinterface #28,  2           // InterfaceMethod java/util/Map.get:(Ljava/lang/Object;)Ljava/lang/Object;
      63: checkcast     #4                  // class java/lang/String
      66: astore        6
      68: aload         6
      70: ifnonnull     113
      73: aload         5
      75: invokeinterface #27,  1           // InterfaceMethod java/util/Map$Entry.getKey:()Ljava/lang/Object;
      80: checkcast     #4                  // class java/lang/String
      83: getstatic     #29                 // Field java/util/Locale.ROOT:Ljava/util/Locale;
      86: invokevirtual #30                 // Method java/lang/String.toLowerCase:(Ljava/util/Locale;)Ljava/lang/String;
      89: astore        7
      91: getstatic     #26                 // Field lruHeaderMap:Ljava/util/Map;
      94: aload         5
      96: invokeinterface #27,  1           // InterfaceMethod java/util/Map$Entry.getKey:()Ljava/lang/Object;
     101: aload         7
     103: invokeinterface #31,  3           // InterfaceMethod java/util/Map.put:(Ljava/lang/Object;Ljava/lang/Object;)Ljava/lang/Object;
     108: pop
     109: aload         7
     111: astore        6
     113: aload         6
     115: invokestatic  #32                 // Method org/apache/dubbo/rpc/protocol/tri/TripleHeaderEnum.containsExcludeAttachments:(Ljava/lang/String;)Z
     118: ifeq          124
     121: goto          26
     124: aload         5
     126: invokeinterface #33,  1           // InterfaceMethod java/util/Map$Entry.getValue:()Ljava/lang/Object;
     131: astore        7
     133: aload         7
     135: ifnonnull     141
     138: goto          26
     141: iload_2
     142: ifeq          176
     145: aload         6
     147: aload         5
     149: invokeinterface #27,  1           // InterfaceMethod java/util/Map$Entry.getKey:()Ljava/lang/Object;
     154: invokevirtual #34                 // Method java/lang/String.equals:(Ljava/lang/Object;)Z
     157: ifne          176
     160: aload_3
     161: aload         6
     163: aload         5
     165: invokeinterface #27,  1           // InterfaceMethod java/util/Map$Entry.getKey:()Ljava/lang/Object;
     170: invokeinterface #31,  3           // InterfaceMethod java/util/Map.put:(Ljava/lang/Object;Ljava/lang/Object;)Ljava/lang/Object;
     175: pop
     176: aload_0
     177: aload         6
     179: aload         7
     181: invokestatic  #35                 // Method convertSingleAttachment:(Lio/netty/handler/codec/http2/DefaultHttp2Headers;Ljava/lang/String;Ljava/lang/Object;)V
     184: goto          26
     187: aload_3
     188: invokeinterface #13,  1           // InterfaceMethod java/util/Map.isEmpty:()Z
     193: ifne          218
     196: aload_3
     197: invokestatic  #36                 // Method org/apache/dubbo/common/utils/JsonUtils.toJson:(Ljava/lang/Object;)Ljava/lang/String;
     200: astore        4
     202: aload_0
     203: getstatic     #37                 // Field org/apache/dubbo/rpc/protocol/tri/TripleHeaderEnum.TRI_HEADER_CONVERT:Lorg/apache/dubbo/rpc/protocol/tri/TripleHeaderEnum;
     206: invokevirtual #38                 // Method org/apache/dubbo/rpc/protocol/tri/TripleHeaderEnum.getHeader:()Ljava/lang/String;
     209: aload         4
     211: invokestatic  #39                 // Method org/apache/dubbo/rpc/TriRpcStatus.encodeMessage:(Ljava/lang/String;)Ljava/lang/String;
     214: invokevirtual #40                 // Method io/netty/handler/codec/http2/DefaultHttp2Headers.add:(Ljava/lang/Object;Ljava/lang/Object;)Lio/netty/handler/codec/Headers;
     217: pop
     218: return

  public static void convertAttachment(io.netty.handler.codec.http2.DefaultHttp2Headers, java.util.Map<java.lang.String, java.lang.Object>);
    Code:
       0: aload_0
       1: aload_1
       2: iconst_0
       3: invokestatic  #41                 // Method convertAttachment:(Lio/netty/handler/codec/http2/DefaultHttp2Headers;Ljava/util/Map;Z)V
       6: return

  private static void convertSingleAttachment(io.netty.handler.codec.http2.DefaultHttp2Headers, java.lang.String, java.lang.Object);
    Code:
       0: aload_2
       1: instanceof    #4                  // class java/lang/String
       4: ifne          21
       7: aload_2
       8: instanceof    #42                 // class java/lang/Number
      11: ifne          21
      14: aload_2
      15: instanceof    #43                 // class java/lang/Boolean
      18: ifeq          36
      21: aload_2
      22: invokevirtual #44                 // Method java/lang/Object.toString:()Ljava/lang/String;
      25: astore_3
      26: aload_0
      27: aload_1
      28: aload_3
      29: invokevirtual #45                 // Method io/netty/handler/codec/http2/DefaultHttp2Headers.set:(Ljava/lang/Object;Ljava/lang/Object;)Lio/netty/handler/codec/Headers;
      32: pop
      33: goto          130
      36: aload_2
      37: instanceof    #46                 // class "[B"
      40: ifeq          82
      43: aload_2
      44: checkcast     #46                 // class "[B"
      47: checkcast     #46                 // class "[B"
      50: invokestatic  #47                 // Method encodeBase64ASCII:([B)Ljava/lang/String;
      53: astore_3
      54: aload_0
      55: new           #48                 // class java/lang/StringBuilder
      58: dup
      59: invokespecial #49                 // Method java/lang/StringBuilder."<init>":()V
      62: aload_1
      63: invokevirtual #50                 // Method java/lang/StringBuilder.append:(Ljava/lang/String;)Ljava/lang/StringBuilder;
      66: ldc           #52                 // String -bin
      68: invokevirtual #50                 // Method java/lang/StringBuilder.append:(Ljava/lang/String;)Ljava/lang/StringBuilder;
      71: invokevirtual #53                 // Method java/lang/StringBuilder.toString:()Ljava/lang/String;
      74: aload_3
      75: invokevirtual #45                 // Method io/netty/handler/codec/http2/DefaultHttp2Headers.set:(Ljava/lang/Object;Ljava/lang/Object;)Lio/netty/handler/codec/Headers;
      78: pop
      79: goto          130
      82: getstatic     #54                 // Field LOGGER:Lorg/apache/dubbo/common/logger/ErrorTypeAwareLogger;
      85: ldc           #55                 // String 4-1
      87: ldc           #56                 // String
      89: ldc           #56                 // String
      91: new           #48                 // class java/lang/StringBuilder
      94: dup
      95: invokespecial #49                 // Method java/lang/StringBuilder."<init>":()V
      98: ldc           #57                 // String Unsupported attachment k:
     100: invokevirtual #50                 // Method java/lang/StringBuilder.append:(Ljava/lang/String;)Ljava/lang/StringBuilder;
     103: aload_1
     104: invokevirtual #50                 // Method java/lang/StringBuilder.append:(Ljava/lang/String;)Ljava/lang/StringBuilder;
     107: ldc           #58                 // String  class:
     109: invokevirtual #50                 // Method java/lang/StringBuilder.append:(Ljava/lang/String;)Ljava/lang/StringBuilder;
     112: aload_2
     113: invokevirtual #59                 // Method java/lang/Object.getClass:()Ljava/lang/Class;
     116: invokevirtual #60                 // Method java/lang/Class.getName:()Ljava/lang/String;
     119: invokevirtual #50                 // Method java/lang/StringBuilder.append:(Ljava/lang/String;)Ljava/lang/StringBuilder;
     122: invokevirtual #53                 // Method java/lang/StringBuilder.toString:()Ljava/lang/String;
     125: invokeinterface #61,  5           // InterfaceMethod org/apache/dubbo/common/logger/ErrorTypeAwareLogger.warn:(Ljava/lang/String;Ljava/lang/String;Ljava/lang/String;Ljava/lang/String;)V
     130: goto          177
     133: astore_3
     134: getstatic     #54                 // Field LOGGER:Lorg/apache/dubbo/common/logger/ErrorTypeAwareLogger;
     137: ldc           #55                 // String 4-1
     139: ldc           #56                 // String
     141: ldc           #56                 // String
     143: new           #48                 // class java/lang/StringBuilder
     146: dup
     147: invokespecial #49                 // Method java/lang/StringBuilder."<init>":()V
     150: ldc           #63                 // String Meet exception when convert single attachment key:
     152: invokevirtual #50                 // Method java/lang/StringBuilder.append:(Ljava/lang/String;)Ljava/lang/StringBuilder;
     155: aload_1
     156: invokevirtual #50                 // Method java/lang/StringBuilder.append:(Ljava/lang/String;)Ljava/lang/StringBuilder;
     159: ldc           #64                 // String  value=
     161: invokevirtual #50                 // Method java/lang/StringBuilder.append:(Ljava/lang/String;)Ljava/lang/StringBuilder;
     164: aload_2
     165: invokevirtual #65                 // Method java/lang/StringBuilder.append:(Ljava/lang/Object;)Ljava/lang/StringBuilder;
     168: invokevirtual #53                 // Method java/lang/StringBuilder.toString:()Ljava/lang/String;
     171: aload_3
     172: invokeinterface #66,  6           // InterfaceMethod org/apache/dubbo/common/logger/ErrorTypeAwareLogger.warn:(Ljava/lang/String;Ljava/lang/String;Ljava/lang/String;Ljava/lang/String;Ljava/lang/Throwable;)V
     177: return
    Exception table:
       from    to  target type
           0   130   133   Class java/lang/Throwable

  private static void lambda$toAttachments$0(java.util.Map, java.lang.String, java.lang.Object);
    Code:
       0: aload_1
       1: invokestatic  #32                 // Method org/apache/dubbo/rpc/protocol/tri/TripleHeaderEnum.containsExcludeAttachments:(Ljava/lang/String;)Z
       4: ifeq          8
       7: return
       8: aload_0
       9: aload_1
      10: aload_2
      11: invokeinterface #31,  3           // InterfaceMethod java/util/Map.put:(Ljava/lang/Object;Ljava/lang/Object;)Ljava/lang/Object;
      16: pop
      17: return

  static {};
    Code:
       0: ldc           #67                 // class org/apache/dubbo/rpc/protocol/tri/stream/StreamUtils
       2: invokestatic  #68                 // Method org/apache/dubbo/common/logger/LoggerFactory.getErrorTypeAwareLogger:(Ljava/lang/Class;)Lorg/apache/dubbo/common/logger/ErrorTypeAwareLogger;
       5: putstatic     #54                 // Field LOGGER:Lorg/apache/dubbo/common/logger/ErrorTypeAwareLogger;
       8: invokestatic  #69                 // Method java/util/Base64.getDecoder:()Ljava/util/Base64$Decoder;
      11: putstatic     #9                  // Field BASE64_DECODER:Ljava/util/Base64$Decoder;
      14: invokestatic  #70                 // Method java/util/Base64.getEncoder:()Ljava/util/Base64$Encoder;
      17: invokevirtual #71                 // Method java/util/Base64$Encoder.withoutPadding:()Ljava/util/Base64$Encoder;
      20: putstatic     #7                  // Field BASE64_ENCODER:Ljava/util/Base64$Encoder;
      23: new           #72                 // class org/apache/dubbo/common/utils/LRU2Cache
      26: dup
      27: sipush        10000
      30: invokespecial #73                 // Method org/apache/dubbo/common/utils/LRU2Cache."<init>":(I)V
      33: putstatic     #26                 // Field lruHeaderMap:Ljava/util/Map;
      36: return
}
