Compiled from "TripleStreamChannelFuture.java"
public class org.apache.dubbo.rpc.protocol.tri.stream.TripleStreamChannelFuture extends java.util.concurrent.CompletableFuture<io.netty.handler.codec.http2.Http2StreamChannel> {
  private final io.netty.channel.Channel parentChannel;

  private java.lang.Throwable cause;

  public org.apache.dubbo.rpc.protocol.tri.stream.TripleStreamChannelFuture(io.netty.channel.Channel);
    Code:
       0: aload_0
       1: invokespecial #1                  // Method java/util/concurrent/CompletableFuture."<init>":()V
       4: aload_1
       5: ldc           #2                  // String parentChannel cannot be null.
       7: invokestatic  #3                  // Method org/apache/dubbo/common/utils/Assert.notNull:(Ljava/lang/Object;Ljava/lang/String;)V
      10: aload_0
      11: aload_1
      12: putfield      #4                  // Field parentChannel:Lio/netty/channel/Channel;
      15: return

  public org.apache.dubbo.rpc.protocol.tri.stream.TripleStreamChannelFuture(io.netty.handler.codec.http2.Http2StreamChannel);
    Code:
       0: aload_0
       1: invokespecial #1                  // Method java/util/concurrent/CompletableFuture."<init>":()V
       4: aload_0
       5: aload_1
       6: invokevirtual #5                  // Method complete:(Ljava/lang/Object;)Z
       9: pop
      10: aload_0
      11: aload_1
      12: invokeinterface #6,  1            // InterfaceMethod io/netty/handler/codec/http2/Http2StreamChannel.parent:()Lio/netty/channel/Channel;
      17: putfield      #4                  // Field parentChannel:Lio/netty/channel/Channel;
      20: return

  public io.netty.channel.Channel getParentChannel();
    Code:
       0: aload_0
       1: getfield      #4                  // Field parentChannel:Lio/netty/channel/Channel;
       4: areturn

  public boolean completeExceptionally(java.lang.Throwable);
    Code:
       0: aload_0
       1: aload_1
       2: invokespecial #7                  // Method java/util/concurrent/CompletableFuture.completeExceptionally:(Ljava/lang/Throwable;)Z
       5: istore_2
       6: iload_2
       7: ifeq          15
      10: aload_0
      11: aload_1
      12: putfield      #8                  // Field cause:Ljava/lang/Throwable;
      15: iload_2
      16: ireturn

  public java.lang.Throwable cause();
    Code:
       0: aload_0
       1: getfield      #8                  // Field cause:Ljava/lang/Throwable;
       4: areturn

  public boolean isSuccess();
    Code:
       0: aload_0
       1: invokevirtual #9                  // Method isDone:()Z
       4: ifeq          18
       7: aload_0
       8: invokevirtual #10                 // Method cause:()Ljava/lang/Throwable;
      11: ifnonnull     18
      14: iconst_1
      15: goto          19
      18: iconst_0
      19: ireturn

  public io.netty.handler.codec.http2.Http2StreamChannel getNow();
    Code:
       0: aload_0
       1: aconst_null
       2: invokevirtual #11                 // Method getNow:(Ljava/lang/Object;)Ljava/lang/Object;
       5: checkcast     #12                 // class io/netty/handler/codec/http2/Http2StreamChannel
       8: areturn
}
