Compiled from "TripleClientStream.java"
class org.apache.dubbo.rpc.protocol.tri.stream.TripleClientStream$1 extends io.netty.channel.ChannelInboundHandlerAdapter {
  final org.apache.dubbo.rpc.protocol.tri.stream.TripleClientStream this$0;

  org.apache.dubbo.rpc.protocol.tri.stream.TripleClientStream$1(org.apache.dubbo.rpc.protocol.tri.stream.TripleClientStream);
    Code:
       0: aload_0
       1: aload_1
       2: putfield      #1                  // Field this$0:Lorg/apache/dubbo/rpc/protocol/tri/stream/TripleClientStream;
       5: aload_0
       6: invokespecial #2                  // Method io/netty/channel/ChannelInboundHandlerAdapter."<init>":()V
       9: return

  public void handlerAdded(io.netty.channel.ChannelHandlerContext) throws java.lang.Exception;
    Code:
       0: aload_1
       1: invokeinterface #3,  1            // InterfaceMethod io/netty/channel/ChannelHandlerContext.channel:()Lio/netty/channel/Channel;
       6: astore_2
       7: aload_2
       8: invokeinterface #4,  1            // InterfaceMethod io/netty/channel/Channel.pipeline:()Lio/netty/channel/ChannelPipeline;
      13: iconst_1
      14: anewarray     #5                  // class io/netty/channel/ChannelHandler
      17: dup
      18: iconst_0
      19: new           #6                  // class org/apache/dubbo/rpc/protocol/tri/transport/TripleCommandOutBoundHandler
      22: dup
      23: invokespecial #7                  // Method org/apache/dubbo/rpc/protocol/tri/transport/TripleCommandOutBoundHandler."<init>":()V
      26: aastore
      27: invokeinterface #8,  2            // InterfaceMethod io/netty/channel/ChannelPipeline.addLast:([Lio/netty/channel/ChannelHandler;)Lio/netty/channel/ChannelPipeline;
      32: pop
      33: aload_2
      34: invokeinterface #4,  1            // InterfaceMethod io/netty/channel/Channel.pipeline:()Lio/netty/channel/ChannelPipeline;
      39: iconst_1
      40: anewarray     #5                  // class io/netty/channel/ChannelHandler
      43: dup
      44: iconst_0
      45: new           #9                  // class org/apache/dubbo/rpc/protocol/tri/transport/TripleHttp2ClientResponseHandler
      48: dup
      49: aload_0
      50: getfield      #1                  // Field this$0:Lorg/apache/dubbo/rpc/protocol/tri/stream/TripleClientStream;
      53: invokevirtual #10                 // Method org/apache/dubbo/rpc/protocol/tri/stream/TripleClientStream.createTransportListener:()Lorg/apache/dubbo/rpc/protocol/tri/transport/H2TransportListener;
      56: invokespecial #11                 // Method org/apache/dubbo/rpc/protocol/tri/transport/TripleHttp2ClientResponseHandler."<init>":(Lorg/apache/dubbo/rpc/protocol/tri/transport/H2TransportListener;)V
      59: aastore
      60: invokeinterface #8,  2            // InterfaceMethod io/netty/channel/ChannelPipeline.addLast:([Lio/netty/channel/ChannelHandler;)Lio/netty/channel/ChannelPipeline;
      65: pop
      66: aload_2
      67: invokeinterface #12,  1           // InterfaceMethod io/netty/channel/Channel.closeFuture:()Lio/netty/channel/ChannelFuture;
      72: aload_0
      73: invokedynamic #13,  0             // InvokeDynamic #0:operationComplete:(Lorg/apache/dubbo/rpc/protocol/tri/stream/TripleClientStream$1;)Lio/netty/util/concurrent/GenericFutureListener;
      78: invokeinterface #14,  2           // InterfaceMethod io/netty/channel/ChannelFuture.addListener:(Lio/netty/util/concurrent/GenericFutureListener;)Lio/netty/channel/ChannelFuture;
      83: pop
      84: return

  private void lambda$handlerAdded$0(io.netty.util.concurrent.Future) throws java.lang.Exception;
    Code:
       0: aload_0
       1: getfield      #1                  // Field this$0:Lorg/apache/dubbo/rpc/protocol/tri/stream/TripleClientStream;
       4: aload_1
       5: invokeinterface #15,  1           // InterfaceMethod io/netty/util/concurrent/Future.cause:()Ljava/lang/Throwable;
      10: invokestatic  #16                 // Method org/apache/dubbo/rpc/protocol/tri/stream/TripleClientStream.access$000:(Lorg/apache/dubbo/rpc/protocol/tri/stream/TripleClientStream;Ljava/lang/Throwable;)V
      13: return
}
