Compiled from "TripleServerStream.java"
public class org.apache.dubbo.rpc.protocol.tri.stream.TripleServerStream$ServerTransportObserver extends org.apache.dubbo.rpc.protocol.tri.transport.AbstractH2TransportListener implements org.apache.dubbo.rpc.protocol.tri.transport.H2TransportListener {
  final org.apache.dubbo.rpc.protocol.tri.stream.TripleServerStream this$0;

  public org.apache.dubbo.rpc.protocol.tri.stream.TripleServerStream$ServerTransportObserver(org.apache.dubbo.rpc.protocol.tri.stream.TripleServerStream);
    Code:
       0: aload_0
       1: aload_1
       2: putfield      #1                  // Field this$0:Lorg/apache/dubbo/rpc/protocol/tri/stream/TripleServerStream;
       5: aload_0
       6: invokespecial #2                  // Method org/apache/dubbo/rpc/protocol/tri/transport/AbstractH2TransportListener."<init>":()V
       9: return

  private boolean supportContentType(java.lang.String);
    Code:
       0: aload_1
       1: ifnonnull     6
       4: iconst_0
       5: ireturn
       6: aload_1
       7: ldc           #4                  // String application/grpc
       9: invokevirtual #5                  // Method java/lang/String.startsWith:(Ljava/lang/String;)Z
      12: ireturn

  public void onHeader(io.netty.handler.codec.http2.Http2Headers, boolean);
    Code:
       0: aload_0
       1: getfield      #1                  // Field this$0:Lorg/apache/dubbo/rpc/protocol/tri/stream/TripleServerStream;
       4: getfield      #6                  // Field org/apache/dubbo/rpc/protocol/tri/stream/TripleServerStream.executor:Ljava/util/concurrent/Executor;
       7: aload_0
       8: aload_1
       9: iload_2
      10: invokedynamic #7,  0              // InvokeDynamic #0:run:(Lorg/apache/dubbo/rpc/protocol/tri/stream/TripleServerStream$ServerTransportObserver;Lio/netty/handler/codec/http2/Http2Headers;Z)Ljava/lang/Runnable;
      15: invokeinterface #8,  2            // InterfaceMethod java/util/concurrent/Executor.execute:(Ljava/lang/Runnable;)V
      20: return

  private void processHeader(io.netty.handler.codec.http2.Http2Headers, boolean);
    Code:
       0: getstatic     #9                  // Field io/netty/handler/codec/http/HttpMethod.POST:Lio/netty/handler/codec/http/HttpMethod;
       3: invokevirtual #10                 // Method io/netty/handler/codec/http/HttpMethod.asciiName:()Lio/netty/util/AsciiString;
       6: aload_1
       7: invokeinterface #11,  1           // InterfaceMethod io/netty/handler/codec/http2/Http2Headers.method:()Ljava/lang/CharSequence;
      12: invokevirtual #12                 // Method io/netty/util/AsciiString.contentEquals:(Ljava/lang/CharSequence;)Z
      15: ifne          56
      18: aload_0
      19: getfield      #1                  // Field this$0:Lorg/apache/dubbo/rpc/protocol/tri/stream/TripleServerStream;
      22: getstatic     #13                 // Field io/netty/handler/codec/http/HttpResponseStatus.METHOD_NOT_ALLOWED:Lio/netty/handler/codec/http/HttpResponseStatus;
      25: invokevirtual #14                 // Method io/netty/handler/codec/http/HttpResponseStatus.code:()I
      28: getstatic     #15                 // Field org/apache/dubbo/rpc/TriRpcStatus.INTERNAL:Lorg/apache/dubbo/rpc/TriRpcStatus;
      31: ldc           #16                 // String Method \'%s\' is not supported
      33: iconst_1
      34: anewarray     #17                 // class java/lang/Object
      37: dup
      38: iconst_0
      39: aload_1
      40: invokeinterface #11,  1           // InterfaceMethod io/netty/handler/codec/http2/Http2Headers.method:()Ljava/lang/CharSequence;
      45: aastore
      46: invokestatic  #18                 // Method java/lang/String.format:(Ljava/lang/String;[Ljava/lang/Object;)Ljava/lang/String;
      49: invokevirtual #19                 // Method org/apache/dubbo/rpc/TriRpcStatus.withDescription:(Ljava/lang/String;)Lorg/apache/dubbo/rpc/TriRpcStatus;
      52: invokestatic  #20                 // Method org/apache/dubbo/rpc/protocol/tri/stream/TripleServerStream.access$000:(Lorg/apache/dubbo/rpc/protocol/tri/stream/TripleServerStream;ILorg/apache/dubbo/rpc/TriRpcStatus;)V
      55: return
      56: aload_1
      57: invokeinterface #21,  1           // InterfaceMethod io/netty/handler/codec/http2/Http2Headers.path:()Ljava/lang/CharSequence;
      62: ifnonnull     93
      65: aload_0
      66: getfield      #1                  // Field this$0:Lorg/apache/dubbo/rpc/protocol/tri/stream/TripleServerStream;
      69: getstatic     #22                 // Field io/netty/handler/codec/http/HttpResponseStatus.NOT_FOUND:Lio/netty/handler/codec/http/HttpResponseStatus;
      72: invokevirtual #14                 // Method io/netty/handler/codec/http/HttpResponseStatus.code:()I
      75: getstatic     #23                 // Field org/apache/dubbo/rpc/TriRpcStatus$Code.UNIMPLEMENTED:Lorg/apache/dubbo/rpc/TriRpcStatus$Code;
      78: getfield      #24                 // Field org/apache/dubbo/rpc/TriRpcStatus$Code.code:I
      81: invokestatic  #25                 // Method org/apache/dubbo/rpc/TriRpcStatus.fromCode:(I)Lorg/apache/dubbo/rpc/TriRpcStatus;
      84: ldc           #26                 // String Expected path but is missing
      86: invokevirtual #19                 // Method org/apache/dubbo/rpc/TriRpcStatus.withDescription:(Ljava/lang/String;)Lorg/apache/dubbo/rpc/TriRpcStatus;
      89: invokestatic  #20                 // Method org/apache/dubbo/rpc/protocol/tri/stream/TripleServerStream.access$000:(Lorg/apache/dubbo/rpc/protocol/tri/stream/TripleServerStream;ILorg/apache/dubbo/rpc/TriRpcStatus;)V
      92: return
      93: aload_1
      94: invokeinterface #21,  1           // InterfaceMethod io/netty/handler/codec/http2/Http2Headers.path:()Ljava/lang/CharSequence;
      99: invokeinterface #27,  1           // InterfaceMethod java/lang/CharSequence.toString:()Ljava/lang/String;
     104: astore_3
     105: aload_3
     106: iconst_0
     107: invokevirtual #28                 // Method java/lang/String.charAt:(I)C
     110: bipush        47
     112: if_icmpeq     154
     115: aload_0
     116: getfield      #1                  // Field this$0:Lorg/apache/dubbo/rpc/protocol/tri/stream/TripleServerStream;
     119: getstatic     #22                 // Field io/netty/handler/codec/http/HttpResponseStatus.NOT_FOUND:Lio/netty/handler/codec/http/HttpResponseStatus;
     122: invokevirtual #14                 // Method io/netty/handler/codec/http/HttpResponseStatus.code:()I
     125: getstatic     #23                 // Field org/apache/dubbo/rpc/TriRpcStatus$Code.UNIMPLEMENTED:Lorg/apache/dubbo/rpc/TriRpcStatus$Code;
     128: getfield      #24                 // Field org/apache/dubbo/rpc/TriRpcStatus$Code.code:I
     131: invokestatic  #25                 // Method org/apache/dubbo/rpc/TriRpcStatus.fromCode:(I)Lorg/apache/dubbo/rpc/TriRpcStatus;
     134: ldc           #29                 // String Expected path to start with /: %s
     136: iconst_1
     137: anewarray     #17                 // class java/lang/Object
     140: dup
     141: iconst_0
     142: aload_3
     143: aastore
     144: invokestatic  #18                 // Method java/lang/String.format:(Ljava/lang/String;[Ljava/lang/Object;)Ljava/lang/String;
     147: invokevirtual #19                 // Method org/apache/dubbo/rpc/TriRpcStatus.withDescription:(Ljava/lang/String;)Lorg/apache/dubbo/rpc/TriRpcStatus;
     150: invokestatic  #20                 // Method org/apache/dubbo/rpc/protocol/tri/stream/TripleServerStream.access$000:(Lorg/apache/dubbo/rpc/protocol/tri/stream/TripleServerStream;ILorg/apache/dubbo/rpc/TriRpcStatus;)V
     153: return
     154: aload_1
     155: getstatic     #30                 // Field io/netty/handler/codec/http/HttpHeaderNames.CONTENT_TYPE:Lio/netty/util/AsciiString;
     158: invokeinterface #31,  2           // InterfaceMethod io/netty/handler/codec/http2/Http2Headers.get:(Ljava/lang/Object;)Ljava/lang/Object;
     163: checkcast     #32                 // class java/lang/CharSequence
     166: invokestatic  #33                 // Method io/netty/handler/codec/http/HttpUtil.getMimeType:(Ljava/lang/CharSequence;)Ljava/lang/CharSequence;
     169: astore        4
     171: aload         4
     173: ifnonnull     204
     176: aload_0
     177: getfield      #1                  // Field this$0:Lorg/apache/dubbo/rpc/protocol/tri/stream/TripleServerStream;
     180: getstatic     #34                 // Field io/netty/handler/codec/http/HttpResponseStatus.UNSUPPORTED_MEDIA_TYPE:Lio/netty/handler/codec/http/HttpResponseStatus;
     183: invokevirtual #14                 // Method io/netty/handler/codec/http/HttpResponseStatus.code:()I
     186: getstatic     #35                 // Field org/apache/dubbo/rpc/TriRpcStatus$Code.INTERNAL:Lorg/apache/dubbo/rpc/TriRpcStatus$Code;
     189: getfield      #24                 // Field org/apache/dubbo/rpc/TriRpcStatus$Code.code:I
     192: invokestatic  #25                 // Method org/apache/dubbo/rpc/TriRpcStatus.fromCode:(I)Lorg/apache/dubbo/rpc/TriRpcStatus;
     195: ldc           #36                 // String Content-Type is missing from the request
     197: invokevirtual #19                 // Method org/apache/dubbo/rpc/TriRpcStatus.withDescription:(Ljava/lang/String;)Lorg/apache/dubbo/rpc/TriRpcStatus;
     200: invokestatic  #20                 // Method org/apache/dubbo/rpc/protocol/tri/stream/TripleServerStream.access$000:(Lorg/apache/dubbo/rpc/protocol/tri/stream/TripleServerStream;ILorg/apache/dubbo/rpc/TriRpcStatus;)V
     203: return
     204: aload         4
     206: invokeinterface #27,  1           // InterfaceMethod java/lang/CharSequence.toString:()Ljava/lang/String;
     211: astore        5
     213: aload_0
     214: aload         5
     216: invokespecial #37                 // Method supportContentType:(Ljava/lang/String;)Z
     219: ifne          262
     222: aload_0
     223: getfield      #1                  // Field this$0:Lorg/apache/dubbo/rpc/protocol/tri/stream/TripleServerStream;
     226: getstatic     #34                 // Field io/netty/handler/codec/http/HttpResponseStatus.UNSUPPORTED_MEDIA_TYPE:Lio/netty/handler/codec/http/HttpResponseStatus;
     229: invokevirtual #14                 // Method io/netty/handler/codec/http/HttpResponseStatus.code:()I
     232: getstatic     #35                 // Field org/apache/dubbo/rpc/TriRpcStatus$Code.INTERNAL:Lorg/apache/dubbo/rpc/TriRpcStatus$Code;
     235: getfield      #24                 // Field org/apache/dubbo/rpc/TriRpcStatus$Code.code:I
     238: invokestatic  #25                 // Method org/apache/dubbo/rpc/TriRpcStatus.fromCode:(I)Lorg/apache/dubbo/rpc/TriRpcStatus;
     241: ldc           #38                 // String Content-Type \'%s\' is not supported
     243: iconst_1
     244: anewarray     #17                 // class java/lang/Object
     247: dup
     248: iconst_0
     249: aload         5
     251: aastore
     252: invokestatic  #18                 // Method java/lang/String.format:(Ljava/lang/String;[Ljava/lang/Object;)Ljava/lang/String;
     255: invokevirtual #19                 // Method org/apache/dubbo/rpc/TriRpcStatus.withDescription:(Ljava/lang/String;)Lorg/apache/dubbo/rpc/TriRpcStatus;
     258: invokestatic  #20                 // Method org/apache/dubbo/rpc/protocol/tri/stream/TripleServerStream.access$000:(Lorg/apache/dubbo/rpc/protocol/tri/stream/TripleServerStream;ILorg/apache/dubbo/rpc/TriRpcStatus;)V
     261: return
     262: aload_3
     263: ldc           #39                 // String /
     265: invokevirtual #40                 // Method java/lang/String.split:(Ljava/lang/String;)[Ljava/lang/String;
     268: astore        6
     270: aload         6
     272: arraylength
     273: iconst_3
     274: if_icmpeq     310
     277: aload_0
     278: getfield      #1                  // Field this$0:Lorg/apache/dubbo/rpc/protocol/tri/stream/TripleServerStream;
     281: getstatic     #41                 // Field org/apache/dubbo/rpc/TriRpcStatus.UNIMPLEMENTED:Lorg/apache/dubbo/rpc/TriRpcStatus;
     284: new           #42                 // class java/lang/StringBuilder
     287: dup
     288: invokespecial #43                 // Method java/lang/StringBuilder."<init>":()V
     291: ldc           #44                 // String Bad path format:
     293: invokevirtual #45                 // Method java/lang/StringBuilder.append:(Ljava/lang/String;)Ljava/lang/StringBuilder;
     296: aload_3
     297: invokevirtual #45                 // Method java/lang/StringBuilder.append:(Ljava/lang/String;)Ljava/lang/StringBuilder;
     300: invokevirtual #46                 // Method java/lang/StringBuilder.toString:()Ljava/lang/String;
     303: invokevirtual #19                 // Method org/apache/dubbo/rpc/TriRpcStatus.withDescription:(Ljava/lang/String;)Lorg/apache/dubbo/rpc/TriRpcStatus;
     306: invokestatic  #47                 // Method org/apache/dubbo/rpc/protocol/tri/stream/TripleServerStream.access$100:(Lorg/apache/dubbo/rpc/protocol/tri/stream/TripleServerStream;Lorg/apache/dubbo/rpc/TriRpcStatus;)V
     309: return
     310: aload         6
     312: iconst_1
     313: aaload
     314: astore        7
     316: aload         6
     318: iconst_2
     319: aaload
     320: astore        8
     322: aload_0
     323: getfield      #1                  // Field this$0:Lorg/apache/dubbo/rpc/protocol/tri/stream/TripleServerStream;
     326: aload_1
     327: aload         7
     329: invokestatic  #48                 // Method org/apache/dubbo/rpc/protocol/tri/stream/TripleServerStream.access$200:(Lorg/apache/dubbo/rpc/protocol/tri/stream/TripleServerStream;Lio/netty/handler/codec/http2/Http2Headers;Ljava/lang/String;)Lorg/apache/dubbo/rpc/Invoker;
     332: astore        9
     334: aload         9
     336: ifnonnull     373
     339: aload_0
     340: getfield      #1                  // Field this$0:Lorg/apache/dubbo/rpc/protocol/tri/stream/TripleServerStream;
     343: getstatic     #41                 // Field org/apache/dubbo/rpc/TriRpcStatus.UNIMPLEMENTED:Lorg/apache/dubbo/rpc/TriRpcStatus;
     346: new           #42                 // class java/lang/StringBuilder
     349: dup
     350: invokespecial #43                 // Method java/lang/StringBuilder."<init>":()V
     353: ldc           #49                 // String Service not found:
     355: invokevirtual #45                 // Method java/lang/StringBuilder.append:(Ljava/lang/String;)Ljava/lang/StringBuilder;
     358: aload         7
     360: invokevirtual #45                 // Method java/lang/StringBuilder.append:(Ljava/lang/String;)Ljava/lang/StringBuilder;
     363: invokevirtual #46                 // Method java/lang/StringBuilder.toString:()Ljava/lang/String;
     366: invokevirtual #19                 // Method org/apache/dubbo/rpc/TriRpcStatus.withDescription:(Ljava/lang/String;)Lorg/apache/dubbo/rpc/TriRpcStatus;
     369: invokestatic  #47                 // Method org/apache/dubbo/rpc/protocol/tri/stream/TripleServerStream.access$100:(Lorg/apache/dubbo/rpc/protocol/tri/stream/TripleServerStream;Lorg/apache/dubbo/rpc/TriRpcStatus;)V
     372: return
     373: iload_2
     374: ifeq          378
     377: return
     378: getstatic     #50                 // Field org/apache/dubbo/rpc/protocol/tri/compressor/DeCompressor.NONE:Lorg/apache/dubbo/rpc/protocol/tri/compressor/DeCompressor;
     381: astore        10
     383: aload_1
     384: getstatic     #51                 // Field org/apache/dubbo/rpc/protocol/tri/TripleHeaderEnum.GRPC_ENCODING:Lorg/apache/dubbo/rpc/protocol/tri/TripleHeaderEnum;
     387: invokevirtual #52                 // Method org/apache/dubbo/rpc/protocol/tri/TripleHeaderEnum.getHeader:()Ljava/lang/String;
     390: invokeinterface #31,  2           // InterfaceMethod io/netty/handler/codec/http2/Http2Headers.get:(Ljava/lang/Object;)Ljava/lang/Object;
     395: checkcast     #32                 // class java/lang/CharSequence
     398: astore        11
     400: aconst_null
     401: aload         11
     403: if_acmpeq     483
     406: aload         11
     408: invokeinterface #27,  1           // InterfaceMethod java/lang/CharSequence.toString:()Ljava/lang/String;
     413: astore        12
     415: ldc           #54                 // String identity
     417: aload         12
     419: invokevirtual #55                 // Method java/lang/String.equals:(Ljava/lang/Object;)Z
     422: ifne          483
     425: aload_0
     426: getfield      #1                  // Field this$0:Lorg/apache/dubbo/rpc/protocol/tri/stream/TripleServerStream;
     429: getfield      #56                 // Field org/apache/dubbo/rpc/protocol/tri/stream/TripleServerStream.frameworkModel:Lorg/apache/dubbo/rpc/model/FrameworkModel;
     432: aload         12
     434: invokestatic  #57                 // InterfaceMethod org/apache/dubbo/rpc/protocol/tri/compressor/DeCompressor.getCompressor:(Lorg/apache/dubbo/rpc/model/FrameworkModel;Ljava/lang/String;)Lorg/apache/dubbo/rpc/protocol/tri/compressor/DeCompressor;
     437: astore        13
     439: aconst_null
     440: aload         13
     442: if_acmpne     479
     445: aload_0
     446: getfield      #1                  // Field this$0:Lorg/apache/dubbo/rpc/protocol/tri/stream/TripleServerStream;
     449: getstatic     #23                 // Field org/apache/dubbo/rpc/TriRpcStatus$Code.UNIMPLEMENTED:Lorg/apache/dubbo/rpc/TriRpcStatus$Code;
     452: getfield      #24                 // Field org/apache/dubbo/rpc/TriRpcStatus$Code.code:I
     455: invokestatic  #25                 // Method org/apache/dubbo/rpc/TriRpcStatus.fromCode:(I)Lorg/apache/dubbo/rpc/TriRpcStatus;
     458: ldc           #58                 // String Grpc-encoding \'%s\' is not supported
     460: iconst_1
     461: anewarray     #17                 // class java/lang/Object
     464: dup
     465: iconst_0
     466: aload         12
     468: aastore
     469: invokestatic  #18                 // Method java/lang/String.format:(Ljava/lang/String;[Ljava/lang/Object;)Ljava/lang/String;
     472: invokevirtual #19                 // Method org/apache/dubbo/rpc/TriRpcStatus.withDescription:(Ljava/lang/String;)Lorg/apache/dubbo/rpc/TriRpcStatus;
     475: invokestatic  #47                 // Method org/apache/dubbo/rpc/protocol/tri/stream/TripleServerStream.access$100:(Lorg/apache/dubbo/rpc/protocol/tri/stream/TripleServerStream;Lorg/apache/dubbo/rpc/TriRpcStatus;)V
     478: return
     479: aload         13
     481: astore        10
     483: aload_0
     484: aload_1
     485: aload_1
     486: invokedynamic #59,  0             // InvokeDynamic #1:get:(Lio/netty/handler/codec/http2/Http2Headers;)Ljava/util/function/Supplier;
     491: invokevirtual #60                 // Method headersToMap:(Lio/netty/handler/codec/http2/Http2Headers;Ljava/util/function/Supplier;)Ljava/util/Map;
     494: astore        12
     496: aload_0
     497: getfield      #1                  // Field this$0:Lorg/apache/dubbo/rpc/protocol/tri/stream/TripleServerStream;
     500: invokestatic  #61                 // Method org/apache/dubbo/rpc/protocol/tri/stream/TripleServerStream.access$300:(Lorg/apache/dubbo/rpc/protocol/tri/stream/TripleServerStream;)Lorg/apache/dubbo/rpc/PathResolver;
     503: aload_3
     504: invokeinterface #62,  2           // InterfaceMethod org/apache/dubbo/rpc/PathResolver.hasNativeStub:(Ljava/lang/String;)Z
     509: istore        13
     511: iload         13
     513: ifeq          565
     516: aload_0
     517: getfield      #1                  // Field this$0:Lorg/apache/dubbo/rpc/protocol/tri/stream/TripleServerStream;
     520: new           #63                 // class org/apache/dubbo/rpc/protocol/tri/call/StubAbstractServerCall
     523: dup
     524: aload         9
     526: aload_0
     527: getfield      #1                  // Field this$0:Lorg/apache/dubbo/rpc/protocol/tri/stream/TripleServerStream;
     530: aload_0
     531: getfield      #1                  // Field this$0:Lorg/apache/dubbo/rpc/protocol/tri/stream/TripleServerStream;
     534: getfield      #56                 // Field org/apache/dubbo/rpc/protocol/tri/stream/TripleServerStream.frameworkModel:Lorg/apache/dubbo/rpc/model/FrameworkModel;
     537: aload_0
     538: getfield      #1                  // Field this$0:Lorg/apache/dubbo/rpc/protocol/tri/stream/TripleServerStream;
     541: invokestatic  #64                 // Method org/apache/dubbo/rpc/protocol/tri/stream/TripleServerStream.access$500:(Lorg/apache/dubbo/rpc/protocol/tri/stream/TripleServerStream;)Ljava/lang/String;
     544: aload         7
     546: aload         8
     548: aload_0
     549: getfield      #1                  // Field this$0:Lorg/apache/dubbo/rpc/protocol/tri/stream/TripleServerStream;
     552: getfield      #6                  // Field org/apache/dubbo/rpc/protocol/tri/stream/TripleServerStream.executor:Ljava/util/concurrent/Executor;
     555: invokespecial #65                 // Method org/apache/dubbo/rpc/protocol/tri/call/StubAbstractServerCall."<init>":(Lorg/apache/dubbo/rpc/Invoker;Lorg/apache/dubbo/rpc/protocol/tri/stream/ServerStream;Lorg/apache/dubbo/rpc/model/FrameworkModel;Ljava/lang/String;Ljava/lang/String;Ljava/lang/String;Ljava/util/concurrent/Executor;)V
     558: invokestatic  #66                 // Method org/apache/dubbo/rpc/protocol/tri/stream/TripleServerStream.access$402:(Lorg/apache/dubbo/rpc/protocol/tri/stream/TripleServerStream;Lorg/apache/dubbo/rpc/protocol/tri/stream/ServerStream$Listener;)Lorg/apache/dubbo/rpc/protocol/tri/stream/ServerStream$Listener;
     561: pop
     562: goto          618
     565: aload_0
     566: getfield      #1                  // Field this$0:Lorg/apache/dubbo/rpc/protocol/tri/stream/TripleServerStream;
     569: new           #67                 // class org/apache/dubbo/rpc/protocol/tri/call/ReflectionAbstractServerCall
     572: dup
     573: aload         9
     575: aload_0
     576: getfield      #1                  // Field this$0:Lorg/apache/dubbo/rpc/protocol/tri/stream/TripleServerStream;
     579: aload_0
     580: getfield      #1                  // Field this$0:Lorg/apache/dubbo/rpc/protocol/tri/stream/TripleServerStream;
     583: getfield      #56                 // Field org/apache/dubbo/rpc/protocol/tri/stream/TripleServerStream.frameworkModel:Lorg/apache/dubbo/rpc/model/FrameworkModel;
     586: aload_0
     587: getfield      #1                  // Field this$0:Lorg/apache/dubbo/rpc/protocol/tri/stream/TripleServerStream;
     590: invokestatic  #64                 // Method org/apache/dubbo/rpc/protocol/tri/stream/TripleServerStream.access$500:(Lorg/apache/dubbo/rpc/protocol/tri/stream/TripleServerStream;)Ljava/lang/String;
     593: aload         7
     595: aload         8
     597: aload_0
     598: getfield      #1                  // Field this$0:Lorg/apache/dubbo/rpc/protocol/tri/stream/TripleServerStream;
     601: invokestatic  #68                 // Method org/apache/dubbo/rpc/protocol/tri/stream/TripleServerStream.access$600:(Lorg/apache/dubbo/rpc/protocol/tri/stream/TripleServerStream;)Ljava/util/List;
     604: aload_0
     605: getfield      #1                  // Field this$0:Lorg/apache/dubbo/rpc/protocol/tri/stream/TripleServerStream;
     608: getfield      #6                  // Field org/apache/dubbo/rpc/protocol/tri/stream/TripleServerStream.executor:Ljava/util/concurrent/Executor;
     611: invokespecial #69                 // Method org/apache/dubbo/rpc/protocol/tri/call/ReflectionAbstractServerCall."<init>":(Lorg/apache/dubbo/rpc/Invoker;Lorg/apache/dubbo/rpc/protocol/tri/stream/ServerStream;Lorg/apache/dubbo/rpc/model/FrameworkModel;Ljava/lang/String;Ljava/lang/String;Ljava/lang/String;Ljava/util/List;Ljava/util/concurrent/Executor;)V
     614: invokestatic  #66                 // Method org/apache/dubbo/rpc/protocol/tri/stream/TripleServerStream.access$402:(Lorg/apache/dubbo/rpc/protocol/tri/stream/TripleServerStream;Lorg/apache/dubbo/rpc/protocol/tri/stream/ServerStream$Listener;)Lorg/apache/dubbo/rpc/protocol/tri/stream/ServerStream$Listener;
     617: pop
     618: aload_0
     619: getfield      #1                  // Field this$0:Lorg/apache/dubbo/rpc/protocol/tri/stream/TripleServerStream;
     622: new           #70                 // class org/apache/dubbo/rpc/protocol/tri/frame/TriDecoder
     625: dup
     626: aload         10
     628: new           #71                 // class org/apache/dubbo/rpc/protocol/tri/stream/TripleServerStream$ServerDecoderListener
     631: dup
     632: aload_0
     633: getfield      #1                  // Field this$0:Lorg/apache/dubbo/rpc/protocol/tri/stream/TripleServerStream;
     636: invokestatic  #72                 // Method org/apache/dubbo/rpc/protocol/tri/stream/TripleServerStream.access$400:(Lorg/apache/dubbo/rpc/protocol/tri/stream/TripleServerStream;)Lorg/apache/dubbo/rpc/protocol/tri/stream/ServerStream$Listener;
     639: invokespecial #73                 // Method org/apache/dubbo/rpc/protocol/tri/stream/TripleServerStream$ServerDecoderListener."<init>":(Lorg/apache/dubbo/rpc/protocol/tri/stream/ServerStream$Listener;)V
     642: invokespecial #74                 // Method org/apache/dubbo/rpc/protocol/tri/frame/TriDecoder."<init>":(Lorg/apache/dubbo/rpc/protocol/tri/compressor/DeCompressor;Lorg/apache/dubbo/rpc/protocol/tri/frame/TriDecoder$Listener;)V
     645: invokestatic  #75                 // Method org/apache/dubbo/rpc/protocol/tri/stream/TripleServerStream.access$702:(Lorg/apache/dubbo/rpc/protocol/tri/stream/TripleServerStream;Lorg/apache/dubbo/rpc/protocol/tri/frame/Deframer;)Lorg/apache/dubbo/rpc/protocol/tri/frame/Deframer;
     648: pop
     649: aload_0
     650: getfield      #1                  // Field this$0:Lorg/apache/dubbo/rpc/protocol/tri/stream/TripleServerStream;
     653: invokestatic  #72                 // Method org/apache/dubbo/rpc/protocol/tri/stream/TripleServerStream.access$400:(Lorg/apache/dubbo/rpc/protocol/tri/stream/TripleServerStream;)Lorg/apache/dubbo/rpc/protocol/tri/stream/ServerStream$Listener;
     656: aload         12
     658: invokeinterface #76,  2           // InterfaceMethod org/apache/dubbo/rpc/protocol/tri/stream/ServerStream$Listener.onHeader:(Ljava/util/Map;)V
     663: return

  public void onData(io.netty.buffer.ByteBuf, boolean);
    Code:
       0: aload_0
       1: getfield      #1                  // Field this$0:Lorg/apache/dubbo/rpc/protocol/tri/stream/TripleServerStream;
       4: getfield      #6                  // Field org/apache/dubbo/rpc/protocol/tri/stream/TripleServerStream.executor:Ljava/util/concurrent/Executor;
       7: aload_0
       8: aload_1
       9: iload_2
      10: invokedynamic #77,  0             // InvokeDynamic #2:run:(Lorg/apache/dubbo/rpc/protocol/tri/stream/TripleServerStream$ServerTransportObserver;Lio/netty/buffer/ByteBuf;Z)Ljava/lang/Runnable;
      15: invokeinterface #8,  2            // InterfaceMethod java/util/concurrent/Executor.execute:(Ljava/lang/Runnable;)V
      20: return

  private void doOnData(io.netty.buffer.ByteBuf, boolean);
    Code:
       0: aload_0
       1: getfield      #1                  // Field this$0:Lorg/apache/dubbo/rpc/protocol/tri/stream/TripleServerStream;
       4: invokestatic  #78                 // Method org/apache/dubbo/rpc/protocol/tri/stream/TripleServerStream.access$700:(Lorg/apache/dubbo/rpc/protocol/tri/stream/TripleServerStream;)Lorg/apache/dubbo/rpc/protocol/tri/frame/Deframer;
       7: ifnonnull     11
      10: return
      11: aload_0
      12: getfield      #1                  // Field this$0:Lorg/apache/dubbo/rpc/protocol/tri/stream/TripleServerStream;
      15: invokestatic  #78                 // Method org/apache/dubbo/rpc/protocol/tri/stream/TripleServerStream.access$700:(Lorg/apache/dubbo/rpc/protocol/tri/stream/TripleServerStream;)Lorg/apache/dubbo/rpc/protocol/tri/frame/Deframer;
      18: aload_1
      19: invokeinterface #79,  2           // InterfaceMethod org/apache/dubbo/rpc/protocol/tri/frame/Deframer.deframe:(Lio/netty/buffer/ByteBuf;)V
      24: iload_2
      25: ifeq          40
      28: aload_0
      29: getfield      #1                  // Field this$0:Lorg/apache/dubbo/rpc/protocol/tri/stream/TripleServerStream;
      32: invokestatic  #78                 // Method org/apache/dubbo/rpc/protocol/tri/stream/TripleServerStream.access$700:(Lorg/apache/dubbo/rpc/protocol/tri/stream/TripleServerStream;)Lorg/apache/dubbo/rpc/protocol/tri/frame/Deframer;
      35: invokeinterface #80,  1           // InterfaceMethod org/apache/dubbo/rpc/protocol/tri/frame/Deframer.close:()V
      40: return

  public void cancelByRemote(long);
    Code:
       0: aload_0
       1: getfield      #1                  // Field this$0:Lorg/apache/dubbo/rpc/protocol/tri/stream/TripleServerStream;
       4: iconst_1
       5: invokestatic  #81                 // Method org/apache/dubbo/rpc/protocol/tri/stream/TripleServerStream.access$802:(Lorg/apache/dubbo/rpc/protocol/tri/stream/TripleServerStream;Z)Z
       8: pop
       9: aload_0
      10: getfield      #1                  // Field this$0:Lorg/apache/dubbo/rpc/protocol/tri/stream/TripleServerStream;
      13: invokestatic  #82                 // Method org/apache/dubbo/rpc/protocol/tri/stream/TripleServerStream.access$900:(Lorg/apache/dubbo/rpc/protocol/tri/stream/TripleServerStream;)Z
      16: ifne          31
      19: aload_0
      20: getfield      #1                  // Field this$0:Lorg/apache/dubbo/rpc/protocol/tri/stream/TripleServerStream;
      23: lload_1
      24: invokestatic  #83                 // Method io/netty/handler/codec/http2/Http2Error.valueOf:(J)Lio/netty/handler/codec/http2/Http2Error;
      27: invokevirtual #84                 // Method org/apache/dubbo/rpc/protocol/tri/stream/TripleServerStream.reset:(Lio/netty/handler/codec/http2/Http2Error;)Lio/netty/channel/ChannelFuture;
      30: pop
      31: aload_0
      32: getfield      #1                  // Field this$0:Lorg/apache/dubbo/rpc/protocol/tri/stream/TripleServerStream;
      35: invokestatic  #72                 // Method org/apache/dubbo/rpc/protocol/tri/stream/TripleServerStream.access$400:(Lorg/apache/dubbo/rpc/protocol/tri/stream/TripleServerStream;)Lorg/apache/dubbo/rpc/protocol/tri/stream/ServerStream$Listener;
      38: ifnonnull     42
      41: return
      42: aload_0
      43: getfield      #1                  // Field this$0:Lorg/apache/dubbo/rpc/protocol/tri/stream/TripleServerStream;
      46: getfield      #6                  // Field org/apache/dubbo/rpc/protocol/tri/stream/TripleServerStream.executor:Ljava/util/concurrent/Executor;
      49: aload_0
      50: lload_1
      51: invokedynamic #85,  0             // InvokeDynamic #3:run:(Lorg/apache/dubbo/rpc/protocol/tri/stream/TripleServerStream$ServerTransportObserver;J)Ljava/lang/Runnable;
      56: invokeinterface #8,  2            // InterfaceMethod java/util/concurrent/Executor.execute:(Ljava/lang/Runnable;)V
      61: return

  private void lambda$cancelByRemote$3(long);
    Code:
       0: aload_0
       1: getfield      #1                  // Field this$0:Lorg/apache/dubbo/rpc/protocol/tri/stream/TripleServerStream;
       4: invokestatic  #72                 // Method org/apache/dubbo/rpc/protocol/tri/stream/TripleServerStream.access$400:(Lorg/apache/dubbo/rpc/protocol/tri/stream/TripleServerStream;)Lorg/apache/dubbo/rpc/protocol/tri/stream/ServerStream$Listener;
       7: getstatic     #86                 // Field org/apache/dubbo/rpc/TriRpcStatus.CANCELLED:Lorg/apache/dubbo/rpc/TriRpcStatus;
      10: new           #42                 // class java/lang/StringBuilder
      13: dup
      14: invokespecial #43                 // Method java/lang/StringBuilder."<init>":()V
      17: ldc           #87                 // String Canceled by client ,errorCode=
      19: invokevirtual #45                 // Method java/lang/StringBuilder.append:(Ljava/lang/String;)Ljava/lang/StringBuilder;
      22: lload_1
      23: invokevirtual #88                 // Method java/lang/StringBuilder.append:(J)Ljava/lang/StringBuilder;
      26: invokevirtual #46                 // Method java/lang/StringBuilder.toString:()Ljava/lang/String;
      29: invokevirtual #19                 // Method org/apache/dubbo/rpc/TriRpcStatus.withDescription:(Ljava/lang/String;)Lorg/apache/dubbo/rpc/TriRpcStatus;
      32: invokeinterface #89,  2           // InterfaceMethod org/apache/dubbo/rpc/protocol/tri/stream/ServerStream$Listener.onCancelByRemote:(Lorg/apache/dubbo/rpc/TriRpcStatus;)V
      37: return

  private void lambda$onData$2(io.netty.buffer.ByteBuf, boolean);
    Code:
       0: aload_0
       1: aload_1
       2: iload_2
       3: invokespecial #90                 // Method doOnData:(Lio/netty/buffer/ByteBuf;Z)V
       6: return

  private static java.lang.Object lambda$processHeader$1(io.netty.handler.codec.http2.Http2Headers);
    Code:
       0: aload_0
       1: getstatic     #91                 // Field org/apache/dubbo/rpc/protocol/tri/TripleHeaderEnum.TRI_HEADER_CONVERT:Lorg/apache/dubbo/rpc/protocol/tri/TripleHeaderEnum;
       4: invokevirtual #52                 // Method org/apache/dubbo/rpc/protocol/tri/TripleHeaderEnum.getHeader:()Ljava/lang/String;
       7: invokeinterface #31,  2           // InterfaceMethod io/netty/handler/codec/http2/Http2Headers.get:(Ljava/lang/Object;)Ljava/lang/Object;
      12: invokestatic  #92                 // Method java/util/Optional.ofNullable:(Ljava/lang/Object;)Ljava/util/Optional;
      15: invokedynamic #93,  0             // InvokeDynamic #4:apply:()Ljava/util/function/Function;
      20: invokevirtual #94                 // Method java/util/Optional.map:(Ljava/util/function/Function;)Ljava/util/Optional;
      23: aconst_null
      24: invokevirtual #95                 // Method java/util/Optional.orElse:(Ljava/lang/Object;)Ljava/lang/Object;
      27: areturn

  private void lambda$onHeader$0(io.netty.handler.codec.http2.Http2Headers, boolean);
    Code:
       0: aload_0
       1: aload_1
       2: iload_2
       3: invokespecial #96                 // Method processHeader:(Lio/netty/handler/codec/http2/Http2Headers;Z)V
       6: return
}
