Compiled from "TripleServerStream.java"
class org.apache.dubbo.rpc.protocol.tri.stream.TripleServerStream$ServerDecoderListener implements org.apache.dubbo.rpc.protocol.tri.frame.TriDecoder$Listener {
  private final org.apache.dubbo.rpc.protocol.tri.stream.ServerStream$Listener listener;

  public org.apache.dubbo.rpc.protocol.tri.stream.TripleServerStream$ServerDecoderListener(org.apache.dubbo.rpc.protocol.tri.stream.ServerStream$Listener);
    Code:
       0: aload_0
       1: invokespecial #1                  // Method java/lang/Object."<init>":()V
       4: aload_0
       5: aload_1
       6: putfield      #2                  // Field listener:Lorg/apache/dubbo/rpc/protocol/tri/stream/ServerStream$Listener;
       9: return

  public void onRawMessage(byte[]);
    Code:
       0: aload_0
       1: getfield      #2                  // Field listener:Lorg/apache/dubbo/rpc/protocol/tri/stream/ServerStream$Listener;
       4: aload_1
       5: iconst_0
       6: invokeinterface #3,  3            // InterfaceMethod org/apache/dubbo/rpc/protocol/tri/stream/ServerStream$Listener.onMessage:([BZ)V
      11: return

  public void close();
    Code:
       0: aload_0
       1: getfield      #2                  // Field listener:Lorg/apache/dubbo/rpc/protocol/tri/stream/ServerStream$Listener;
       4: invokeinterface #4,  1            // InterfaceMethod org/apache/dubbo/rpc/protocol/tri/stream/ServerStream$Listener.onComplete:()V
       9: return
}
