Compiled from "TripleClientStream.java"
class org.apache.dubbo.rpc.protocol.tri.stream.TripleClientStream$ClientTransportListener$1 implements org.apache.dubbo.rpc.protocol.tri.frame.TriDecoder$Listener {
  final org.apache.dubbo.rpc.protocol.tri.stream.TripleClientStream$ClientTransportListener this$1;

  org.apache.dubbo.rpc.protocol.tri.stream.TripleClientStream$ClientTransportListener$1(org.apache.dubbo.rpc.protocol.tri.stream.TripleClientStream$ClientTransportListener);
    Code:
       0: aload_0
       1: aload_1
       2: putfield      #1                  // Field this$1:Lorg/apache/dubbo/rpc/protocol/tri/stream/TripleClientStream$ClientTransportListener;
       5: aload_0
       6: invokespecial #2                  // Method java/lang/Object."<init>":()V
       9: return

  public void onRawMessage(byte[]);
    Code:
       0: aload_0
       1: getfield      #1                  // Field this$1:Lorg/apache/dubbo/rpc/protocol/tri/stream/TripleClientStream$ClientTransportListener;
       4: getfield      #3                  // Field org/apache/dubbo/rpc/protocol/tri/stream/TripleClientStream$ClientTransportListener.this$0:Lorg/apache/dubbo/rpc/protocol/tri/stream/TripleClientStream;
       7: getfield      #4                  // Field org/apache/dubbo/rpc/protocol/tri/stream/TripleClientStream.listener:Lorg/apache/dubbo/rpc/protocol/tri/stream/ClientStream$Listener;
      10: aload_1
      11: aload_0
      12: getfield      #1                  // Field this$1:Lorg/apache/dubbo/rpc/protocol/tri/stream/TripleClientStream$ClientTransportListener;
      15: getfield      #3                  // Field org/apache/dubbo/rpc/protocol/tri/stream/TripleClientStream$ClientTransportListener.this$0:Lorg/apache/dubbo/rpc/protocol/tri/stream/TripleClientStream;
      18: invokestatic  #5                  // Method org/apache/dubbo/rpc/protocol/tri/stream/TripleClientStream.access$400:(Lorg/apache/dubbo/rpc/protocol/tri/stream/TripleClientStream;)Z
      21: invokeinterface #6,  3            // InterfaceMethod org/apache/dubbo/rpc/protocol/tri/stream/ClientStream$Listener.onMessage:([BZ)V
      26: return

  public void close();
    Code:
       0: aload_0
       1: getfield      #1                  // Field this$1:Lorg/apache/dubbo/rpc/protocol/tri/stream/TripleClientStream$ClientTransportListener;
       4: aload_0
       5: getfield      #1                  // Field this$1:Lorg/apache/dubbo/rpc/protocol/tri/stream/TripleClientStream$ClientTransportListener;
       8: aload_0
       9: getfield      #1                  // Field this$1:Lorg/apache/dubbo/rpc/protocol/tri/stream/TripleClientStream$ClientTransportListener;
      12: invokestatic  #7                  // Method org/apache/dubbo/rpc/protocol/tri/stream/TripleClientStream$ClientTransportListener.access$500:(Lorg/apache/dubbo/rpc/protocol/tri/stream/TripleClientStream$ClientTransportListener;)Lio/netty/handler/codec/http2/Http2Headers;
      15: invokestatic  #8                  // Method org/apache/dubbo/rpc/protocol/tri/stream/TripleClientStream$ClientTransportListener.access$600:(Lorg/apache/dubbo/rpc/protocol/tri/stream/TripleClientStream$ClientTransportListener;Lio/netty/handler/codec/http2/Http2Headers;)Lorg/apache/dubbo/rpc/TriRpcStatus;
      18: aload_0
      19: getfield      #1                  // Field this$1:Lorg/apache/dubbo/rpc/protocol/tri/stream/TripleClientStream$ClientTransportListener;
      22: invokestatic  #7                  // Method org/apache/dubbo/rpc/protocol/tri/stream/TripleClientStream$ClientTransportListener.access$500:(Lorg/apache/dubbo/rpc/protocol/tri/stream/TripleClientStream$ClientTransportListener;)Lio/netty/handler/codec/http2/Http2Headers;
      25: aload_0
      26: getfield      #1                  // Field this$1:Lorg/apache/dubbo/rpc/protocol/tri/stream/TripleClientStream$ClientTransportListener;
      29: getfield      #3                  // Field org/apache/dubbo/rpc/protocol/tri/stream/TripleClientStream$ClientTransportListener.this$0:Lorg/apache/dubbo/rpc/protocol/tri/stream/TripleClientStream;
      32: invokestatic  #5                  // Method org/apache/dubbo/rpc/protocol/tri/stream/TripleClientStream.access$400:(Lorg/apache/dubbo/rpc/protocol/tri/stream/TripleClientStream;)Z
      35: invokevirtual #9                  // Method org/apache/dubbo/rpc/protocol/tri/stream/TripleClientStream$ClientTransportListener.finishProcess:(Lorg/apache/dubbo/rpc/TriRpcStatus;Lio/netty/handler/codec/http2/Http2Headers;Z)V
      38: return
}
