Compiled from "NacosMetadataReport.java"
class org.apache.dubbo.metadata.store.nacos.NacosMetadataReport$MappingDataListener implements org.apache.dubbo.common.config.configcenter.ConfigurationListener {
  private java.lang.String dataId;

  private java.lang.String groupId;

  private java.lang.String serviceKey;

  private java.util.Set<org.apache.dubbo.metadata.MappingListener> listeners;

  public org.apache.dubbo.metadata.store.nacos.NacosMetadataReport$MappingDataListener(java.lang.String, java.lang.String);
    Code:
       0: aload_0
       1: invokespecial #1                  // Method java/lang/Object."<init>":()V
       4: aload_0
       5: aload_1
       6: putfield      #2                  // Field serviceKey:Ljava/lang/String;
       9: aload_0
      10: aload_1
      11: putfield      #3                  // Field dataId:Ljava/lang/String;
      14: aload_0
      15: aload_2
      16: putfield      #4                  // Field groupId:Ljava/lang/String;
      19: aload_0
      20: new           #5                  // class java/util/HashSet
      23: dup
      24: invokespecial #6                  // Method java/util/HashSet."<init>":()V
      27: putfield      #7                  // Field listeners:Ljava/util/Set;
      30: return

  public void addListeners(org.apache.dubbo.metadata.MappingListener);
    Code:
       0: aload_0
       1: getfield      #7                  // Field listeners:Ljava/util/Set;
       4: aload_1
       5: invokeinterface #8,  2            // InterfaceMethod java/util/Set.add:(Ljava/lang/Object;)Z
      10: pop
      11: return

  public void removeListeners(org.apache.dubbo.metadata.MappingListener);
    Code:
       0: aload_0
       1: getfield      #7                  // Field listeners:Ljava/util/Set;
       4: aload_1
       5: invokeinterface #9,  2            // InterfaceMethod java/util/Set.remove:(Ljava/lang/Object;)Z
      10: pop
      11: return

  public boolean isEmpty();
    Code:
       0: aload_0
       1: getfield      #7                  // Field listeners:Ljava/util/Set;
       4: invokeinterface #10,  1           // InterfaceMethod java/util/Set.isEmpty:()Z
       9: ireturn

  public void process(org.apache.dubbo.common.config.configcenter.ConfigChangedEvent);
    Code:
       0: getstatic     #11                 // Field org/apache/dubbo/common/config/configcenter/ConfigChangeType.DELETED:Lorg/apache/dubbo/common/config/configcenter/ConfigChangeType;
       3: aload_1
       4: invokevirtual #12                 // Method org/apache/dubbo/common/config/configcenter/ConfigChangedEvent.getChangeType:()Lorg/apache/dubbo/common/config/configcenter/ConfigChangeType;
       7: if_acmpne     11
      10: return
      11: aload_0
      12: getfield      #3                  // Field dataId:Ljava/lang/String;
      15: aload_1
      16: invokevirtual #13                 // Method org/apache/dubbo/common/config/configcenter/ConfigChangedEvent.getKey:()Ljava/lang/String;
      19: invokevirtual #14                 // Method java/lang/String.equals:(Ljava/lang/Object;)Z
      22: ifeq          39
      25: aload_0
      26: getfield      #4                  // Field groupId:Ljava/lang/String;
      29: aload_1
      30: invokevirtual #15                 // Method org/apache/dubbo/common/config/configcenter/ConfigChangedEvent.getGroup:()Ljava/lang/String;
      33: invokevirtual #14                 // Method java/lang/String.equals:(Ljava/lang/Object;)Z
      36: ifne          40
      39: return
      40: aload_1
      41: invokevirtual #16                 // Method org/apache/dubbo/common/config/configcenter/ConfigChangedEvent.getContent:()Ljava/lang/String;
      44: invokestatic  #17                 // InterfaceMethod org/apache/dubbo/metadata/ServiceNameMapping.getAppNames:(Ljava/lang/String;)Ljava/util/Set;
      47: astore_2
      48: new           #18                 // class org/apache/dubbo/metadata/MappingChangedEvent
      51: dup
      52: aload_0
      53: getfield      #2                  // Field serviceKey:Ljava/lang/String;
      56: aload_2
      57: invokespecial #19                 // Method org/apache/dubbo/metadata/MappingChangedEvent."<init>":(Ljava/lang/String;Ljava/util/Set;)V
      60: astore_3
      61: aload_0
      62: getfield      #7                  // Field listeners:Ljava/util/Set;
      65: aload_3
      66: invokedynamic #20,  0             // InvokeDynamic #0:accept:(Lorg/apache/dubbo/metadata/MappingChangedEvent;)Ljava/util/function/Consumer;
      71: invokeinterface #21,  2           // InterfaceMethod java/util/Set.forEach:(Ljava/util/function/Consumer;)V
      76: return

  private static void lambda$process$0(org.apache.dubbo.metadata.MappingChangedEvent, org.apache.dubbo.metadata.MappingListener);
    Code:
       0: aload_1
       1: aload_0
       2: invokeinterface #22,  2           // InterfaceMethod org/apache/dubbo/metadata/MappingListener.onEvent:(Lorg/apache/dubbo/metadata/MappingChangedEvent;)V
       7: return
}
