Compiled from "CacheLoader.java"
class com.google.common.cache.CacheLoader$1 extends com.google.common.cache.CacheLoader<K, V> {
  final com.google.common.cache.CacheLoader val$loader;

  final java.util.concurrent.Executor val$executor;

  com.google.common.cache.CacheLoader$1(com.google.common.cache.CacheLoader, java.util.concurrent.Executor);
    Code:
       0: aload_0
       1: aload_1
       2: putfield      #1                  // Field val$loader:Lcom/google/common/cache/CacheLoader;
       5: aload_0
       6: aload_2
       7: putfield      #2                  // Field val$executor:Ljava/util/concurrent/Executor;
      10: aload_0
      11: invokespecial #3                  // Method com/google/common/cache/CacheLoader."<init>":()V
      14: return

  public V load(K) throws java.lang.Exception;
    Code:
       0: aload_0
       1: getfield      #1                  // Field val$loader:Lcom/google/common/cache/CacheLoader;
       4: aload_1
       5: invokevirtual #4                  // Method com/google/common/cache/CacheLoader.load:(Ljava/lang/Object;)Ljava/lang/Object;
       8: areturn

  public com.google.common.util.concurrent.ListenableFuture<V> reload(K, V);
    Code:
       0: aload_0
       1: getfield      #1                  // Field val$loader:Lcom/google/common/cache/CacheLoader;
       4: aload_1
       5: aload_2
       6: invokedynamic #5,  0              // InvokeDynamic #0:call:(Lcom/google/common/cache/CacheLoader;Ljava/lang/Object;Ljava/lang/Object;)Ljava/util/concurrent/Callable;
      11: invokestatic  #6                  // Method com/google/common/util/concurrent/ListenableFutureTask.create:(Ljava/util/concurrent/Callable;)Lcom/google/common/util/concurrent/ListenableFutureTask;
      14: astore_3
      15: aload_0
      16: getfield      #2                  // Field val$executor:Ljava/util/concurrent/Executor;
      19: aload_3
      20: invokeinterface #7,  2            // InterfaceMethod java/util/concurrent/Executor.execute:(Ljava/lang/Runnable;)V
      25: aload_3
      26: areturn

  public java.util.Map<K, V> loadAll(java.lang.Iterable<? extends K>) throws java.lang.Exception;
    Code:
       0: aload_0
       1: getfield      #1                  // Field val$loader:Lcom/google/common/cache/CacheLoader;
       4: aload_1
       5: invokevirtual #8                  // Method com/google/common/cache/CacheLoader.loadAll:(Ljava/lang/Iterable;)Ljava/util/Map;
       8: areturn

  private static java.lang.Object lambda$reload$0(com.google.common.cache.CacheLoader, java.lang.Object, java.lang.Object) throws java.lang.Exception;
    Code:
       0: aload_0
       1: aload_1
       2: aload_2
       3: invokevirtual #9                  // Method com/google/common/cache/CacheLoader.reload:(Ljava/lang/Object;Ljava/lang/Object;)Lcom/google/common/util/concurrent/ListenableFuture;
       6: invokeinterface #10,  1           // InterfaceMethod com/google/common/util/concurrent/ListenableFuture.get:()Ljava/lang/Object;
      11: areturn
}
