Compiled from "PDF417DetectorResult.java"
public final class com.google.zxing.pdf417.detector.PDF417DetectorResult {
  private final com.google.zxing.common.BitMatrix bits;

  private final java.util.List<com.google.zxing.ResultPoint[]> points;

  private final int rotation;

  public com.google.zxing.pdf417.detector.PDF417DetectorResult(com.google.zxing.common.BitMatrix, java.util.List<com.google.zxing.ResultPoint[]>, int);
    Code:
       0: aload_0
       1: invokespecial #1                  // Method java/lang/Object."<init>":()V
       4: aload_0
       5: aload_1
       6: putfield      #2                  // Field bits:Lcom/google/zxing/common/BitMatrix;
       9: aload_0
      10: aload_2
      11: putfield      #3                  // Field points:Ljava/util/List;
      14: aload_0
      15: iload_3
      16: putfield      #4                  // Field rotation:I
      19: return

  public com.google.zxing.pdf417.detector.PDF417DetectorResult(com.google.zxing.common.BitMatrix, java.util.List<com.google.zxing.ResultPoint[]>);
    Code:
       0: aload_0
       1: aload_1
       2: aload_2
       3: iconst_0
       4: invokespecial #5                  // Method "<init>":(Lcom/google/zxing/common/BitMatrix;Ljava/util/List;I)V
       7: return

  public com.google.zxing.common.BitMatrix getBits();
    Code:
       0: aload_0
       1: getfield      #2                  // Field bits:Lcom/google/zxing/common/BitMatrix;
       4: areturn

  public java.util.List<com.google.zxing.ResultPoint[]> getPoints();
    Code:
       0: aload_0
       1: getfield      #3                  // Field points:Ljava/util/List;
       4: areturn

  public int getRotation();
    Code:
       0: aload_0
       1: getfield      #4                  // Field rotation:I
       4: ireturn
}
