Compiled from "StaticDirectory.java"
public class org.apache.dubbo.rpc.cluster.directory.StaticDirectory<T> extends org.apache.dubbo.rpc.cluster.directory.AbstractDirectory<T> {
  private static final org.apache.dubbo.common.logger.ErrorTypeAwareLogger logger;

  public org.apache.dubbo.rpc.cluster.directory.StaticDirectory(java.util.List<org.apache.dubbo.rpc.Invoker<T>>);
    Code:
       0: aload_0
       1: aconst_null
       2: aload_1
       3: aconst_null
       4: invokespecial #2                  // Method "<init>":(Lorg/apache/dubbo/common/URL;Ljava/util/List;Lorg/apache/dubbo/rpc/cluster/RouterChain;)V
       7: return

  public org.apache.dubbo.rpc.cluster.directory.StaticDirectory(java.util.List<org.apache.dubbo.rpc.Invoker<T>>, org.apache.dubbo.rpc.cluster.RouterChain<T>);
    Code:
       0: aload_0
       1: aconst_null
       2: aload_1
       3: aload_2
       4: invokespecial #2                  // Method "<init>":(Lorg/apache/dubbo/common/URL;Ljava/util/List;Lorg/apache/dubbo/rpc/cluster/RouterChain;)V
       7: return

  public org.apache.dubbo.rpc.cluster.directory.StaticDirectory(org.apache.dubbo.common.URL, java.util.List<org.apache.dubbo.rpc.Invoker<T>>);
    Code:
       0: aload_0
       1: aload_1
       2: aload_2
       3: aconst_null
       4: invokespecial #2                  // Method "<init>":(Lorg/apache/dubbo/common/URL;Ljava/util/List;Lorg/apache/dubbo/rpc/cluster/RouterChain;)V
       7: return

  public org.apache.dubbo.rpc.cluster.directory.StaticDirectory(org.apache.dubbo.common.URL, java.util.List<org.apache.dubbo.rpc.Invoker<T>>, org.apache.dubbo.rpc.cluster.RouterChain<T>);
    Code:
       0: aload_0
       1: aload_1
       2: ifnonnull     30
       5: aload_2
       6: invokestatic  #3                  // Method org/apache/dubbo/common/utils/CollectionUtils.isNotEmpty:(Ljava/util/Collection;)Z
       9: ifeq          30
      12: aload_2
      13: iconst_0
      14: invokeinterface #4,  2            // InterfaceMethod java/util/List.get:(I)Ljava/lang/Object;
      19: checkcast     #5                  // class org/apache/dubbo/rpc/Invoker
      22: invokeinterface #6,  1            // InterfaceMethod org/apache/dubbo/rpc/Invoker.getUrl:()Lorg/apache/dubbo/common/URL;
      27: goto          31
      30: aload_1
      31: aload_3
      32: iconst_0
      33: invokespecial #7                  // Method org/apache/dubbo/rpc/cluster/directory/AbstractDirectory."<init>":(Lorg/apache/dubbo/common/URL;Lorg/apache/dubbo/rpc/cluster/RouterChain;Z)V
      36: aload_2
      37: invokestatic  #8                  // Method org/apache/dubbo/common/utils/CollectionUtils.isEmpty:(Ljava/util/Collection;)Z
      40: ifeq          53
      43: new           #9                  // class java/lang/IllegalArgumentException
      46: dup
      47: ldc           #10                 // String invokers == null
      49: invokespecial #11                 // Method java/lang/IllegalArgumentException."<init>":(Ljava/lang/String;)V
      52: athrow
      53: aload_0
      54: new           #12                 // class org/apache/dubbo/rpc/cluster/router/state/BitList
      57: dup
      58: aload_2
      59: invokespecial #13                 // Method org/apache/dubbo/rpc/cluster/router/state/BitList."<init>":(Ljava/util/List;)V
      62: invokevirtual #14                 // Method setInvokers:(Lorg/apache/dubbo/rpc/cluster/router/state/BitList;)V
      65: return

  public java.lang.Class<T> getInterface();
    Code:
       0: aload_0
       1: invokevirtual #15                 // Method getInvokers:()Lorg/apache/dubbo/rpc/cluster/router/state/BitList;
       4: iconst_0
       5: invokevirtual #16                 // Method org/apache/dubbo/rpc/cluster/router/state/BitList.get:(I)Ljava/lang/Object;
       8: checkcast     #5                  // class org/apache/dubbo/rpc/Invoker
      11: invokeinterface #17,  1           // InterfaceMethod org/apache/dubbo/rpc/Invoker.getInterface:()Ljava/lang/Class;
      16: areturn

  public java.util.List<org.apache.dubbo.rpc.Invoker<T>> getAllInvokers();
    Code:
       0: aload_0
       1: invokevirtual #15                 // Method getInvokers:()Lorg/apache/dubbo/rpc/cluster/router/state/BitList;
       4: areturn

  public boolean isAvailable();
    Code:
       0: aload_0
       1: invokevirtual #18                 // Method isDestroyed:()Z
       4: ifeq          9
       7: iconst_0
       8: ireturn
       9: aload_0
      10: invokevirtual #19                 // Method getValidInvokers:()Lorg/apache/dubbo/rpc/cluster/router/state/BitList;
      13: invokevirtual #20                 // Method org/apache/dubbo/rpc/cluster/router/state/BitList.iterator:()Ljava/util/Iterator;
      16: astore_1
      17: aload_1
      18: invokeinterface #21,  1           // InterfaceMethod java/util/Iterator.hasNext:()Z
      23: ifeq          55
      26: aload_1
      27: invokeinterface #22,  1           // InterfaceMethod java/util/Iterator.next:()Ljava/lang/Object;
      32: checkcast     #5                  // class org/apache/dubbo/rpc/Invoker
      35: astore_2
      36: aload_2
      37: invokeinterface #23,  1           // InterfaceMethod org/apache/dubbo/rpc/Invoker.isAvailable:()Z
      42: ifeq          47
      45: iconst_1
      46: ireturn
      47: aload_0
      48: aload_2
      49: invokevirtual #24                 // Method addInvalidateInvoker:(Lorg/apache/dubbo/rpc/Invoker;)V
      52: goto          17
      55: iconst_0
      56: ireturn

  public void destroy();
    Code:
       0: aload_0
       1: invokevirtual #18                 // Method isDestroyed:()Z
       4: ifeq          8
       7: return
       8: aload_0
       9: invokevirtual #15                 // Method getInvokers:()Lorg/apache/dubbo/rpc/cluster/router/state/BitList;
      12: invokevirtual #20                 // Method org/apache/dubbo/rpc/cluster/router/state/BitList.iterator:()Ljava/util/Iterator;
      15: astore_1
      16: aload_1
      17: invokeinterface #21,  1           // InterfaceMethod java/util/Iterator.hasNext:()Z
      22: ifeq          44
      25: aload_1
      26: invokeinterface #22,  1           // InterfaceMethod java/util/Iterator.next:()Ljava/lang/Object;
      31: checkcast     #5                  // class org/apache/dubbo/rpc/Invoker
      34: astore_2
      35: aload_2
      36: invokeinterface #25,  1           // InterfaceMethod org/apache/dubbo/rpc/Invoker.destroy:()V
      41: goto          16
      44: aload_0
      45: invokespecial #26                 // Method org/apache/dubbo/rpc/cluster/directory/AbstractDirectory.destroy:()V
      48: return

  public void buildRouterChain();
    Code:
       0: aload_0
       1: invokevirtual #27                 // Method getInterface:()Ljava/lang/Class;
       4: aload_0
       5: invokevirtual #28                 // Method getUrl:()Lorg/apache/dubbo/common/URL;
       8: invokestatic  #29                 // Method org/apache/dubbo/rpc/cluster/RouterChain.buildChain:(Ljava/lang/Class;Lorg/apache/dubbo/common/URL;)Lorg/apache/dubbo/rpc/cluster/RouterChain;
      11: astore_1
      12: aload_1
      13: aload_0
      14: invokevirtual #15                 // Method getInvokers:()Lorg/apache/dubbo/rpc/cluster/router/state/BitList;
      17: invokedynamic #30,  0             // InvokeDynamic #0:run:()Ljava/lang/Runnable;
      22: invokevirtual #31                 // Method org/apache/dubbo/rpc/cluster/RouterChain.setInvokers:(Lorg/apache/dubbo/rpc/cluster/router/state/BitList;Ljava/lang/Runnable;)V
      25: aload_0
      26: aload_1
      27: invokevirtual #32                 // Method setRouterChain:(Lorg/apache/dubbo/rpc/cluster/RouterChain;)V
      30: return

  public void notify(java.util.List<org.apache.dubbo.rpc.Invoker<T>>);
    Code:
       0: new           #12                 // class org/apache/dubbo/rpc/cluster/router/state/BitList
       3: dup
       4: aload_1
       5: invokespecial #13                 // Method org/apache/dubbo/rpc/cluster/router/state/BitList."<init>":(Ljava/util/List;)V
       8: astore_2
       9: aload_0
      10: getfield      #33                 // Field routerChain:Lorg/apache/dubbo/rpc/cluster/RouterChain;
      13: ifnull        34
      16: aload_0
      17: aload_2
      18: invokevirtual #34                 // Method org/apache/dubbo/rpc/cluster/router/state/BitList.clone:()Lorg/apache/dubbo/rpc/cluster/router/state/BitList;
      21: aload_0
      22: aload_2
      23: invokedynamic #35,  0             // InvokeDynamic #1:run:(Lorg/apache/dubbo/rpc/cluster/directory/StaticDirectory;Lorg/apache/dubbo/rpc/cluster/router/state/BitList;)Ljava/lang/Runnable;
      28: invokevirtual #36                 // Method refreshRouter:(Lorg/apache/dubbo/rpc/cluster/router/state/BitList;Ljava/lang/Runnable;)V
      31: goto          39
      34: aload_0
      35: aload_2
      36: invokevirtual #14                 // Method setInvokers:(Lorg/apache/dubbo/rpc/cluster/router/state/BitList;)V
      39: return

  protected java.util.List<org.apache.dubbo.rpc.Invoker<T>> doList(org.apache.dubbo.rpc.cluster.SingleRouterChain<T>, org.apache.dubbo.rpc.cluster.router.state.BitList<org.apache.dubbo.rpc.Invoker<T>>, org.apache.dubbo.rpc.Invocation) throws org.apache.dubbo.rpc.RpcException;
    Code:
       0: aload_1
       1: ifnull        87
       4: aload_1
       5: aload_0
       6: invokevirtual #37                 // Method getConsumerUrl:()Lorg/apache/dubbo/common/URL;
       9: aload_2
      10: aload_3
      11: invokevirtual #38                 // Method org/apache/dubbo/rpc/cluster/SingleRouterChain.route:(Lorg/apache/dubbo/common/URL;Lorg/apache/dubbo/rpc/cluster/router/state/BitList;Lorg/apache/dubbo/rpc/Invocation;)Ljava/util/List;
      14: astore        4
      16: aload         4
      18: ifnonnull     27
      21: invokestatic  #39                 // Method org/apache/dubbo/rpc/cluster/router/state/BitList.emptyList:()Lorg/apache/dubbo/rpc/cluster/router/state/BitList;
      24: goto          29
      27: aload         4
      29: areturn
      30: astore        4
      32: getstatic     #41                 // Field logger:Lorg/apache/dubbo/common/logger/ErrorTypeAwareLogger;
      35: ldc           #42                 // String 2-1
      37: ldc           #43                 // String Failed to execute router
      39: ldc           #44                 // String
      41: new           #45                 // class java/lang/StringBuilder
      44: dup
      45: invokespecial #46                 // Method java/lang/StringBuilder."<init>":()V
      48: ldc           #47                 // String Failed to execute router:
      50: invokevirtual #48                 // Method java/lang/StringBuilder.append:(Ljava/lang/String;)Ljava/lang/StringBuilder;
      53: aload_0
      54: invokevirtual #28                 // Method getUrl:()Lorg/apache/dubbo/common/URL;
      57: invokevirtual #49                 // Method java/lang/StringBuilder.append:(Ljava/lang/Object;)Ljava/lang/StringBuilder;
      60: ldc           #50                 // String , cause:
      62: invokevirtual #48                 // Method java/lang/StringBuilder.append:(Ljava/lang/String;)Ljava/lang/StringBuilder;
      65: aload         4
      67: invokevirtual #51                 // Method java/lang/Throwable.getMessage:()Ljava/lang/String;
      70: invokevirtual #48                 // Method java/lang/StringBuilder.append:(Ljava/lang/String;)Ljava/lang/StringBuilder;
      73: invokevirtual #52                 // Method java/lang/StringBuilder.toString:()Ljava/lang/String;
      76: aload         4
      78: invokeinterface #53,  6           // InterfaceMethod org/apache/dubbo/common/logger/ErrorTypeAwareLogger.error:(Ljava/lang/String;Ljava/lang/String;Ljava/lang/String;Ljava/lang/String;Ljava/lang/Throwable;)V
      83: invokestatic  #39                 // Method org/apache/dubbo/rpc/cluster/router/state/BitList.emptyList:()Lorg/apache/dubbo/rpc/cluster/router/state/BitList;
      86: areturn
      87: aload_2
      88: areturn
    Exception table:
       from    to  target type
           4    29    30   Class java/lang/Throwable

  private void lambda$notify$1(org.apache.dubbo.rpc.cluster.router.state.BitList);
    Code:
       0: aload_0
       1: aload_1
       2: invokevirtual #14                 // Method setInvokers:(Lorg/apache/dubbo/rpc/cluster/router/state/BitList;)V
       5: return

  private static void lambda$buildRouterChain$0();
    Code:
       0: return

  static {};
    Code:
       0: ldc           #54                 // class org/apache/dubbo/rpc/cluster/directory/StaticDirectory
       2: invokestatic  #55                 // Method org/apache/dubbo/common/logger/LoggerFactory.getErrorTypeAwareLogger:(Ljava/lang/Class;)Lorg/apache/dubbo/common/logger/ErrorTypeAwareLogger;
       5: putstatic     #41                 // Field logger:Lorg/apache/dubbo/common/logger/ErrorTypeAwareLogger;
       8: return
}
