Compiled from "GenericException.java"
public class org.apache.dubbo.rpc.service.GenericException extends java.lang.RuntimeException {
  private static final long serialVersionUID;

  private boolean useCause;

  private java.lang.String exceptionClass;

  private java.lang.String exceptionMessage;

  private final org.apache.dubbo.rpc.service.GenericException$GenericExceptionInfo genericExceptionInfo;

  public org.apache.dubbo.rpc.service.GenericException();
    Code:
       0: aload_0
       1: aconst_null
       2: aconst_null
       3: invokespecial #1                  // Method "<init>":(Ljava/lang/String;Ljava/lang/String;)V
       6: return

  public org.apache.dubbo.rpc.service.GenericException(java.lang.String, java.lang.String);
    Code:
       0: aload_0
       1: aload_2
       2: invokespecial #2                  // Method java/lang/RuntimeException."<init>":(Ljava/lang/String;)V
       5: aload_0
       6: iconst_0
       7: putfield      #3                  // Field useCause:Z
      10: aload_0
      11: aload_1
      12: putfield      #4                  // Field exceptionClass:Ljava/lang/String;
      15: aload_0
      16: aload_2
      17: putfield      #5                  // Field exceptionMessage:Ljava/lang/String;
      20: aload_0
      21: new           #6                  // class org/apache/dubbo/rpc/service/GenericException$GenericExceptionInfo
      24: dup
      25: aload_1
      26: aload_2
      27: aload_2
      28: aload_0
      29: invokevirtual #7                  // Method getStackTrace:()[Ljava/lang/StackTraceElement;
      32: invokespecial #8                  // Method org/apache/dubbo/rpc/service/GenericException$GenericExceptionInfo."<init>":(Ljava/lang/String;Ljava/lang/String;Ljava/lang/String;[Ljava/lang/StackTraceElement;)V
      35: putfield      #9                  // Field genericExceptionInfo:Lorg/apache/dubbo/rpc/service/GenericException$GenericExceptionInfo;
      38: return

  public org.apache.dubbo.rpc.service.GenericException(java.lang.Throwable);
    Code:
       0: aload_0
       1: aload_1
       2: invokestatic  #10                 // Method org/apache/dubbo/common/utils/StringUtils.toString:(Ljava/lang/Throwable;)Ljava/lang/String;
       5: invokespecial #2                  // Method java/lang/RuntimeException."<init>":(Ljava/lang/String;)V
       8: aload_0
       9: iconst_0
      10: putfield      #3                  // Field useCause:Z
      13: aload_0
      14: aload_1
      15: invokevirtual #11                 // Method java/lang/Object.getClass:()Ljava/lang/Class;
      18: invokevirtual #12                 // Method java/lang/Class.getName:()Ljava/lang/String;
      21: putfield      #4                  // Field exceptionClass:Ljava/lang/String;
      24: aload_0
      25: aload_1
      26: invokevirtual #13                 // Method java/lang/Throwable.getMessage:()Ljava/lang/String;
      29: putfield      #5                  // Field exceptionMessage:Ljava/lang/String;
      32: aload_0
      33: new           #6                  // class org/apache/dubbo/rpc/service/GenericException$GenericExceptionInfo
      36: dup
      37: aload_0
      38: getfield      #4                  // Field exceptionClass:Ljava/lang/String;
      41: aload_0
      42: getfield      #5                  // Field exceptionMessage:Ljava/lang/String;
      45: aload_0
      46: invokespecial #14                 // Method java/lang/RuntimeException.getMessage:()Ljava/lang/String;
      49: aload_0
      50: invokevirtual #7                  // Method getStackTrace:()[Ljava/lang/StackTraceElement;
      53: invokespecial #8                  // Method org/apache/dubbo/rpc/service/GenericException$GenericExceptionInfo."<init>":(Ljava/lang/String;Ljava/lang/String;Ljava/lang/String;[Ljava/lang/StackTraceElement;)V
      56: putfield      #9                  // Field genericExceptionInfo:Lorg/apache/dubbo/rpc/service/GenericException$GenericExceptionInfo;
      59: return

  protected org.apache.dubbo.rpc.service.GenericException(org.apache.dubbo.rpc.service.GenericException$GenericExceptionInfo);
    Code:
       0: aload_0
       1: aload_1
       2: invokevirtual #15                 // Method org/apache/dubbo/rpc/service/GenericException$GenericExceptionInfo.getMsg:()Ljava/lang/String;
       5: aconst_null
       6: iconst_1
       7: iconst_0
       8: invokespecial #16                 // Method java/lang/RuntimeException."<init>":(Ljava/lang/String;Ljava/lang/Throwable;ZZ)V
      11: aload_0
      12: aload_1
      13: invokevirtual #17                 // Method org/apache/dubbo/rpc/service/GenericException$GenericExceptionInfo.getStackTrace:()[Ljava/lang/StackTraceElement;
      16: invokevirtual #18                 // Method setStackTrace:([Ljava/lang/StackTraceElement;)V
      19: aload_0
      20: iconst_0
      21: putfield      #3                  // Field useCause:Z
      24: aload_0
      25: aload_1
      26: invokevirtual #19                 // Method org/apache/dubbo/rpc/service/GenericException$GenericExceptionInfo.getExClass:()Ljava/lang/String;
      29: putfield      #4                  // Field exceptionClass:Ljava/lang/String;
      32: aload_0
      33: aload_1
      34: invokevirtual #20                 // Method org/apache/dubbo/rpc/service/GenericException$GenericExceptionInfo.getExMsg:()Ljava/lang/String;
      37: putfield      #5                  // Field exceptionMessage:Ljava/lang/String;
      40: aload_0
      41: aload_1
      42: putfield      #9                  // Field genericExceptionInfo:Lorg/apache/dubbo/rpc/service/GenericException$GenericExceptionInfo;
      45: return

  public java.lang.String getExceptionClass();
    Code:
       0: aload_0
       1: getfield      #3                  // Field useCause:Z
       4: ifeq          18
       7: aload_0
       8: invokevirtual #21                 // Method getCause:()Ljava/lang/Throwable;
      11: checkcast     #22                 // class org/apache/dubbo/rpc/service/GenericException
      14: invokevirtual #23                 // Method getExceptionClass:()Ljava/lang/String;
      17: areturn
      18: aload_0
      19: getfield      #4                  // Field exceptionClass:Ljava/lang/String;
      22: areturn

  public void setExceptionClass(java.lang.String);
    Code:
       0: aload_0
       1: getfield      #3                  // Field useCause:Z
       4: ifeq          19
       7: aload_0
       8: invokevirtual #21                 // Method getCause:()Ljava/lang/Throwable;
      11: checkcast     #22                 // class org/apache/dubbo/rpc/service/GenericException
      14: aload_1
      15: invokevirtual #24                 // Method setExceptionClass:(Ljava/lang/String;)V
      18: return
      19: aload_0
      20: aload_1
      21: putfield      #4                  // Field exceptionClass:Ljava/lang/String;
      24: return

  public java.lang.String getExceptionMessage();
    Code:
       0: aload_0
       1: getfield      #3                  // Field useCause:Z
       4: ifeq          18
       7: aload_0
       8: invokevirtual #21                 // Method getCause:()Ljava/lang/Throwable;
      11: checkcast     #22                 // class org/apache/dubbo/rpc/service/GenericException
      14: invokevirtual #25                 // Method getExceptionMessage:()Ljava/lang/String;
      17: areturn
      18: aload_0
      19: getfield      #5                  // Field exceptionMessage:Ljava/lang/String;
      22: areturn

  public void setExceptionMessage(java.lang.String);
    Code:
       0: aload_0
       1: getfield      #3                  // Field useCause:Z
       4: ifeq          19
       7: aload_0
       8: invokevirtual #21                 // Method getCause:()Ljava/lang/Throwable;
      11: checkcast     #22                 // class org/apache/dubbo/rpc/service/GenericException
      14: aload_1
      15: invokevirtual #26                 // Method setExceptionMessage:(Ljava/lang/String;)V
      18: return
      19: aload_0
      20: aload_1
      21: putfield      #5                  // Field exceptionMessage:Ljava/lang/String;
      24: return

  public java.lang.StackTraceElement[] getStackTrace();
    Code:
       0: aload_0
       1: getfield      #3                  // Field useCause:Z
       4: ifeq          18
       7: aload_0
       8: invokevirtual #21                 // Method getCause:()Ljava/lang/Throwable;
      11: checkcast     #22                 // class org/apache/dubbo/rpc/service/GenericException
      14: invokevirtual #7                  // Method getStackTrace:()[Ljava/lang/StackTraceElement;
      17: areturn
      18: aload_0
      19: invokespecial #27                 // Method java/lang/RuntimeException.getStackTrace:()[Ljava/lang/StackTraceElement;
      22: areturn

  public java.lang.String getMessage();
    Code:
       0: aload_0
       1: getfield      #3                  // Field useCause:Z
       4: ifeq          15
       7: aload_0
       8: invokevirtual #21                 // Method getCause:()Ljava/lang/Throwable;
      11: invokevirtual #13                 // Method java/lang/Throwable.getMessage:()Ljava/lang/String;
      14: areturn
      15: aload_0
      16: getfield      #9                  // Field genericExceptionInfo:Lorg/apache/dubbo/rpc/service/GenericException$GenericExceptionInfo;
      19: invokestatic  #28                 // Method org/apache/dubbo/rpc/service/GenericException$GenericExceptionInfo.createNoStackTrace:(Lorg/apache/dubbo/rpc/service/GenericException$GenericExceptionInfo;)Lorg/apache/dubbo/rpc/service/GenericException$GenericExceptionInfo;
      22: invokestatic  #29                 // Method org/apache/dubbo/common/utils/JsonUtils.toJson:(Ljava/lang/Object;)Ljava/lang/String;
      25: areturn

  public java.lang.String getGenericException();
    Code:
       0: aload_0
       1: getfield      #3                  // Field useCause:Z
       4: ifeq          18
       7: aload_0
       8: invokevirtual #21                 // Method getCause:()Ljava/lang/Throwable;
      11: checkcast     #22                 // class org/apache/dubbo/rpc/service/GenericException
      14: invokevirtual #30                 // Method getGenericException:()Ljava/lang/String;
      17: areturn
      18: aload_0
      19: getfield      #9                  // Field genericExceptionInfo:Lorg/apache/dubbo/rpc/service/GenericException$GenericExceptionInfo;
      22: invokestatic  #29                 // Method org/apache/dubbo/common/utils/JsonUtils.toJson:(Ljava/lang/Object;)Ljava/lang/String;
      25: areturn

  public void setGenericException(java.lang.String);
    Code:
       0: aload_1
       1: ldc           #6                  // class org/apache/dubbo/rpc/service/GenericException$GenericExceptionInfo
       3: invokestatic  #31                 // Method org/apache/dubbo/common/utils/JsonUtils.toJavaObject:(Ljava/lang/String;Ljava/lang/reflect/Type;)Ljava/lang/Object;
       6: checkcast     #6                  // class org/apache/dubbo/rpc/service/GenericException$GenericExceptionInfo
       9: astore_2
      10: aload_2
      11: ifnonnull     15
      14: return
      15: aload_0
      16: iconst_1
      17: putfield      #3                  // Field useCause:Z
      20: aload_0
      21: new           #22                 // class org/apache/dubbo/rpc/service/GenericException
      24: dup
      25: aload_2
      26: invokespecial #32                 // Method "<init>":(Lorg/apache/dubbo/rpc/service/GenericException$GenericExceptionInfo;)V
      29: invokevirtual #33                 // Method initCause:(Ljava/lang/Throwable;)Ljava/lang/Throwable;
      32: pop
      33: return

  public java.lang.String getLocalizedMessage();
    Code:
       0: aload_0
       1: invokevirtual #34                 // Method getMessage:()Ljava/lang/String;
       4: areturn
}
