Compiled from "GenericException.java"
public class org.apache.dubbo.rpc.service.GenericException$GenericExceptionInfo implements java.io.Serializable {
  private java.lang.String exClass;

  private java.lang.String exMsg;

  private java.lang.String msg;

  private java.lang.StackTraceElement[] stackTrace;

  public org.apache.dubbo.rpc.service.GenericException$GenericExceptionInfo();
    Code:
       0: aload_0
       1: invokespecial #1                  // Method java/lang/Object."<init>":()V
       4: return

  public org.apache.dubbo.rpc.service.GenericException$GenericExceptionInfo(java.lang.String, java.lang.String, java.lang.String, java.lang.StackTraceElement[]);
    Code:
       0: aload_0
       1: invokespecial #1                  // Method java/lang/Object."<init>":()V
       4: aload_0
       5: aload_1
       6: putfield      #2                  // Field exClass:Ljava/lang/String;
       9: aload_0
      10: aload_2
      11: putfield      #3                  // Field exMsg:Ljava/lang/String;
      14: aload_0
      15: aload_3
      16: putfield      #4                  // Field msg:Ljava/lang/String;
      19: aload_0
      20: aload         4
      22: putfield      #5                  // Field stackTrace:[Ljava/lang/StackTraceElement;
      25: return

  public static org.apache.dubbo.rpc.service.GenericException$GenericExceptionInfo createNoStackTrace(org.apache.dubbo.rpc.service.GenericException$GenericExceptionInfo);
    Code:
       0: new           #6                  // class org/apache/dubbo/rpc/service/GenericException$GenericExceptionInfo
       3: dup
       4: aload_0
       5: invokevirtual #7                  // Method getExClass:()Ljava/lang/String;
       8: aload_0
       9: invokevirtual #8                  // Method getExMsg:()Ljava/lang/String;
      12: aload_0
      13: invokevirtual #9                  // Method getMsg:()Ljava/lang/String;
      16: aconst_null
      17: invokespecial #10                 // Method "<init>":(Ljava/lang/String;Ljava/lang/String;Ljava/lang/String;[Ljava/lang/StackTraceElement;)V
      20: areturn

  public java.lang.String getMsg();
    Code:
       0: aload_0
       1: getfield      #4                  // Field msg:Ljava/lang/String;
       4: areturn

  public java.lang.String getExClass();
    Code:
       0: aload_0
       1: getfield      #2                  // Field exClass:Ljava/lang/String;
       4: areturn

  public java.lang.String getExMsg();
    Code:
       0: aload_0
       1: getfield      #3                  // Field exMsg:Ljava/lang/String;
       4: areturn

  public void setExClass(java.lang.String);
    Code:
       0: aload_0
       1: aload_1
       2: putfield      #2                  // Field exClass:Ljava/lang/String;
       5: return

  public void setExMsg(java.lang.String);
    Code:
       0: aload_0
       1: aload_1
       2: putfield      #3                  // Field exMsg:Ljava/lang/String;
       5: return

  public void setMsg(java.lang.String);
    Code:
       0: aload_0
       1: aload_1
       2: putfield      #4                  // Field msg:Ljava/lang/String;
       5: return

  public java.lang.StackTraceElement[] getStackTrace();
    Code:
       0: aload_0
       1: getfield      #5                  // Field stackTrace:[Ljava/lang/StackTraceElement;
       4: areturn

  public void setStackTrace(java.lang.StackTraceElement[]);
    Code:
       0: aload_0
       1: aload_1
       2: putfield      #5                  // Field stackTrace:[Ljava/lang/StackTraceElement;
       5: return
}
