Compiled from "GenericService.java"
public interface org.apache.dubbo.rpc.service.GenericService {
  public abstract java.lang.Object $invoke(java.lang.String, java.lang.String[], java.lang.Object[]) throws org.apache.dubbo.rpc.service.GenericException;

  public default java.util.concurrent.CompletableFuture<java.lang.Object> $invokeAsync(java.lang.String, java.lang.String[], java.lang.Object[]) throws org.apache.dubbo.rpc.service.GenericException;
    Code:
       0: aload_0
       1: aload_1
       2: aload_2
       3: aload_3
       4: invokeinterface #1,  4            // InterfaceMethod $invoke:(Ljava/lang/String;[Ljava/lang/String;[Ljava/lang/Object;)Ljava/lang/Object;
       9: astore        4
      11: aload         4
      13: instanceof    #2                  // class java/util/concurrent/CompletableFuture
      16: ifeq          25
      19: aload         4
      21: checkcast     #2                  // class java/util/concurrent/CompletableFuture
      24: areturn
      25: aload         4
      27: invokestatic  #3                  // Method java/util/concurrent/CompletableFuture.completedFuture:(Ljava/lang/Object;)Ljava/util/concurrent/CompletableFuture;
      30: areturn
}
