Compiled from "ServiceDescriptorInternalCache.java"
public class org.apache.dubbo.rpc.service.ServiceDescriptorInternalCache {
  private static final org.apache.dubbo.rpc.model.ServiceDescriptor genericServiceDescriptor;

  private static final org.apache.dubbo.rpc.model.ServiceDescriptor echoServiceDescriptor;

  public org.apache.dubbo.rpc.service.ServiceDescriptorInternalCache();
    Code:
       0: aload_0
       1: invokespecial #1                  // Method java/lang/Object."<init>":()V
       4: return

  public static org.apache.dubbo.rpc.model.ServiceDescriptor genericService();
    Code:
       0: getstatic     #2                  // Field genericServiceDescriptor:Lorg/apache/dubbo/rpc/model/ServiceDescriptor;
       3: areturn

  public static org.apache.dubbo.rpc.model.ServiceDescriptor echoService();
    Code:
       0: getstatic     #3                  // Field echoServiceDescriptor:Lorg/apache/dubbo/rpc/model/ServiceDescriptor;
       3: areturn

  static {};
    Code:
       0: new           #4                  // class org/apache/dubbo/rpc/model/ReflectionServiceDescriptor
       3: dup
       4: ldc           #5                  // class org/apache/dubbo/rpc/service/GenericService
       6: invokespecial #6                  // Method org/apache/dubbo/rpc/model/ReflectionServiceDescriptor."<init>":(Ljava/lang/Class;)V
       9: putstatic     #2                  // Field genericServiceDescriptor:Lorg/apache/dubbo/rpc/model/ServiceDescriptor;
      12: new           #4                  // class org/apache/dubbo/rpc/model/ReflectionServiceDescriptor
      15: dup
      16: ldc           #7                  // class org/apache/dubbo/rpc/service/EchoService
      18: invokespecial #6                  // Method org/apache/dubbo/rpc/model/ReflectionServiceDescriptor."<init>":(Ljava/lang/Class;)V
      21: putstatic     #3                  // Field echoServiceDescriptor:Lorg/apache/dubbo/rpc/model/ServiceDescriptor;
      24: return
}
