Compiled from "DeltaEndpoint.java"
public class org.apache.dubbo.registry.xds.util.protocol.delta.DeltaEndpoint implements org.apache.dubbo.registry.xds.util.protocol.DeltaResource<org.apache.dubbo.registry.xds.util.protocol.message.EndpointResult> {
  private final java.util.Map<java.lang.String, java.util.Set<org.apache.dubbo.registry.xds.util.protocol.message.Endpoint>> data;

  public org.apache.dubbo.registry.xds.util.protocol.delta.DeltaEndpoint();
    Code:
       0: aload_0
       1: invokespecial #1                  // Method java/lang/Object."<init>":()V
       4: aload_0
       5: new           #2                  // class java/util/concurrent/ConcurrentHashMap
       8: dup
       9: invokespecial #3                  // Method java/util/concurrent/ConcurrentHashMap."<init>":()V
      12: putfield      #4                  // Field data:Ljava/util/Map;
      15: return

  public void addResource(java.lang.String, java.util.Set<org.apache.dubbo.registry.xds.util.protocol.message.Endpoint>);
    Code:
       0: aload_0
       1: getfield      #4                  // Field data:Ljava/util/Map;
       4: aload_1
       5: aload_2
       6: invokeinterface #5,  3            // InterfaceMethod java/util/Map.put:(Ljava/lang/Object;Ljava/lang/Object;)Ljava/lang/Object;
      11: pop
      12: return

  public void removeResource(java.util.Collection<java.lang.String>);
    Code:
       0: aload_1
       1: invokestatic  #6                  // Method org/apache/dubbo/common/utils/CollectionUtils.isNotEmpty:(Ljava/util/Collection;)Z
       4: ifeq          27
       7: aload_1
       8: aload_0
       9: getfield      #4                  // Field data:Ljava/util/Map;
      12: dup
      13: invokevirtual #7                  // Method java/lang/Object.getClass:()Ljava/lang/Class;
      16: pop
      17: invokedynamic #8,  0              // InvokeDynamic #0:accept:(Ljava/util/Map;)Ljava/util/function/Consumer;
      22: invokeinterface #9,  2            // InterfaceMethod java/util/Collection.forEach:(Ljava/util/function/Consumer;)V
      27: return

  public org.apache.dubbo.registry.xds.util.protocol.message.EndpointResult getResource();
    Code:
       0: aload_0
       1: getfield      #4                  // Field data:Ljava/util/Map;
       4: invokeinterface #10,  1           // InterfaceMethod java/util/Map.values:()Ljava/util/Collection;
       9: invokeinterface #11,  1           // InterfaceMethod java/util/Collection.stream:()Ljava/util/stream/Stream;
      14: invokedynamic #12,  0             // InvokeDynamic #1:apply:()Ljava/util/function/Function;
      19: invokeinterface #13,  2           // InterfaceMethod java/util/stream/Stream.flatMap:(Ljava/util/function/Function;)Ljava/util/stream/Stream;
      24: invokestatic  #14                 // Method java/util/stream/Collectors.toSet:()Ljava/util/stream/Collector;
      27: invokeinterface #15,  2           // InterfaceMethod java/util/stream/Stream.collect:(Ljava/util/stream/Collector;)Ljava/lang/Object;
      32: checkcast     #16                 // class java/util/Set
      35: astore_1
      36: new           #17                 // class org/apache/dubbo/registry/xds/util/protocol/message/EndpointResult
      39: dup
      40: aload_1
      41: invokespecial #18                 // Method org/apache/dubbo/registry/xds/util/protocol/message/EndpointResult."<init>":(Ljava/util/Set;)V
      44: areturn

  public java.lang.Object getResource();
    Code:
       0: aload_0
       1: invokevirtual #19                 // Method getResource:()Lorg/apache/dubbo/registry/xds/util/protocol/message/EndpointResult;
       4: areturn
}
