Compiled from "ArrayListSupplier.java"
public final class io.reactivex.rxjava3.internal.util.ArrayListSupplier extends java.lang.Enum<io.reactivex.rxjava3.internal.util.ArrayListSupplier> implements io.reactivex.rxjava3.functions.Supplier<java.util.List<java.lang.Object>>, io.reactivex.rxjava3.functions.Function<java.lang.Object, java.util.List<java.lang.Object>> {
  public static final io.reactivex.rxjava3.internal.util.ArrayListSupplier INSTANCE;

  private static final io.reactivex.rxjava3.internal.util.ArrayListSupplier[] $VALUES;

  public static io.reactivex.rxjava3.internal.util.ArrayListSupplier[] values();
    Code:
       0: getstatic     #1                  // Field $VALUES:[Lio/reactivex/rxjava3/internal/util/ArrayListSupplier;
       3: invokevirtual #2                  // Method "[Lio/reactivex/rxjava3/internal/util/ArrayListSupplier;".clone:()Ljava/lang/Object;
       6: checkcast     #3                  // class "[Lio/reactivex/rxjava3/internal/util/ArrayListSupplier;"
       9: areturn

  public static io.reactivex.rxjava3.internal.util.ArrayListSupplier valueOf(java.lang.String);
    Code:
       0: ldc           #4                  // class io/reactivex/rxjava3/internal/util/ArrayListSupplier
       2: aload_0
       3: invokestatic  #5                  // Method java/lang/Enum.valueOf:(Ljava/lang/Class;Ljava/lang/String;)Ljava/lang/Enum;
       6: checkcast     #4                  // class io/reactivex/rxjava3/internal/util/ArrayListSupplier
       9: areturn

  private io.reactivex.rxjava3.internal.util.ArrayListSupplier();
    Code:
       0: aload_0
       1: aload_1
       2: iload_2
       3: invokespecial #6                  // Method java/lang/Enum."<init>":(Ljava/lang/String;I)V
       6: return

  public static <T> io.reactivex.rxjava3.functions.Supplier<java.util.List<T>> asSupplier();
    Code:
       0: getstatic     #7                  // Field INSTANCE:Lio/reactivex/rxjava3/internal/util/ArrayListSupplier;
       3: areturn

  public static <T, O> io.reactivex.rxjava3.functions.Function<O, java.util.List<T>> asFunction();
    Code:
       0: getstatic     #7                  // Field INSTANCE:Lio/reactivex/rxjava3/internal/util/ArrayListSupplier;
       3: areturn

  public java.util.List<java.lang.Object> get();
    Code:
       0: new           #8                  // class java/util/ArrayList
       3: dup
       4: invokespecial #9                  // Method java/util/ArrayList."<init>":()V
       7: areturn

  public java.util.List<java.lang.Object> apply(java.lang.Object);
    Code:
       0: new           #8                  // class java/util/ArrayList
       3: dup
       4: invokespecial #9                  // Method java/util/ArrayList."<init>":()V
       7: areturn

  public java.lang.Object get() throws java.lang.Throwable;
    Code:
       0: aload_0
       1: invokevirtual #10                 // Method get:()Ljava/util/List;
       4: areturn

  public java.lang.Object apply(java.lang.Object) throws java.lang.Throwable;
    Code:
       0: aload_0
       1: aload_1
       2: invokevirtual #11                 // Method apply:(Ljava/lang/Object;)Ljava/util/List;
       5: areturn

  static {};
    Code:
       0: new           #4                  // class io/reactivex/rxjava3/internal/util/ArrayListSupplier
       3: dup
       4: ldc           #12                 // String INSTANCE
       6: iconst_0
       7: invokespecial #13                 // Method "<init>":(Ljava/lang/String;I)V
      10: putstatic     #7                  // Field INSTANCE:Lio/reactivex/rxjava3/internal/util/ArrayListSupplier;
      13: iconst_1
      14: anewarray     #4                  // class io/reactivex/rxjava3/internal/util/ArrayListSupplier
      17: dup
      18: iconst_0
      19: getstatic     #7                  // Field INSTANCE:Lio/reactivex/rxjava3/internal/util/ArrayListSupplier;
      22: aastore
      23: putstatic     #1                  // Field $VALUES:[Lio/reactivex/rxjava3/internal/util/ArrayListSupplier;
      26: return
}
