Compiled from "AtomicThrowable.java"
public final class io.reactivex.rxjava3.internal.util.AtomicThrowable extends java.util.concurrent.atomic.AtomicReference<java.lang.Throwable> {
  private static final long serialVersionUID;

  public io.reactivex.rxjava3.internal.util.AtomicThrowable();
    Code:
       0: aload_0
       1: invokespecial #1                  // Method java/util/concurrent/atomic/AtomicReference."<init>":()V
       4: return

  public boolean tryAddThrowable(java.lang.Throwable);
    Code:
       0: aload_0
       1: aload_1
       2: invokestatic  #2                  // Method io/reactivex/rxjava3/internal/util/ExceptionHelper.addThrowable:(Ljava/util/concurrent/atomic/AtomicReference;Ljava/lang/Throwable;)Z
       5: ireturn

  public boolean tryAddThrowableOrReport(java.lang.Throwable);
    Code:
       0: aload_0
       1: aload_1
       2: invokevirtual #3                  // Method tryAddThrowable:(Ljava/lang/Throwable;)Z
       5: ifeq          10
       8: iconst_1
       9: ireturn
      10: aload_1
      11: invokestatic  #4                  // Method io/reactivex/rxjava3/plugins/RxJavaPlugins.onError:(Ljava/lang/Throwable;)V
      14: iconst_0
      15: ireturn

  public java.lang.Throwable terminate();
    Code:
       0: aload_0
       1: invokestatic  #5                  // Method io/reactivex/rxjava3/internal/util/ExceptionHelper.terminate:(Ljava/util/concurrent/atomic/AtomicReference;)Ljava/lang/Throwable;
       4: areturn

  public boolean isTerminated();
    Code:
       0: aload_0
       1: invokevirtual #6                  // Method get:()Ljava/lang/Object;
       4: getstatic     #7                  // Field io/reactivex/rxjava3/internal/util/ExceptionHelper.TERMINATED:Ljava/lang/Throwable;
       7: if_acmpne     14
      10: iconst_1
      11: goto          15
      14: iconst_0
      15: ireturn

  public void tryTerminateAndReport();
    Code:
       0: aload_0
       1: invokevirtual #8                  // Method terminate:()Ljava/lang/Throwable;
       4: astore_1
       5: aload_1
       6: ifnull        20
       9: aload_1
      10: getstatic     #7                  // Field io/reactivex/rxjava3/internal/util/ExceptionHelper.TERMINATED:Ljava/lang/Throwable;
      13: if_acmpeq     20
      16: aload_1
      17: invokestatic  #4                  // Method io/reactivex/rxjava3/plugins/RxJavaPlugins.onError:(Ljava/lang/Throwable;)V
      20: return

  public void tryTerminateConsumer(org.reactivestreams.Subscriber<?>);
    Code:
       0: aload_0
       1: invokevirtual #8                  // Method terminate:()Ljava/lang/Throwable;
       4: astore_2
       5: aload_2
       6: ifnonnull     18
       9: aload_1
      10: invokeinterface #9,  1            // InterfaceMethod org/reactivestreams/Subscriber.onComplete:()V
      15: goto          32
      18: aload_2
      19: getstatic     #7                  // Field io/reactivex/rxjava3/internal/util/ExceptionHelper.TERMINATED:Ljava/lang/Throwable;
      22: if_acmpeq     32
      25: aload_1
      26: aload_2
      27: invokeinterface #10,  2           // InterfaceMethod org/reactivestreams/Subscriber.onError:(Ljava/lang/Throwable;)V
      32: return

  public void tryTerminateConsumer(io.reactivex.rxjava3.core.Observer<?>);
    Code:
       0: aload_0
       1: invokevirtual #8                  // Method terminate:()Ljava/lang/Throwable;
       4: astore_2
       5: aload_2
       6: ifnonnull     18
       9: aload_1
      10: invokeinterface #11,  1           // InterfaceMethod io/reactivex/rxjava3/core/Observer.onComplete:()V
      15: goto          32
      18: aload_2
      19: getstatic     #7                  // Field io/reactivex/rxjava3/internal/util/ExceptionHelper.TERMINATED:Ljava/lang/Throwable;
      22: if_acmpeq     32
      25: aload_1
      26: aload_2
      27: invokeinterface #12,  2           // InterfaceMethod io/reactivex/rxjava3/core/Observer.onError:(Ljava/lang/Throwable;)V
      32: return

  public void tryTerminateConsumer(io.reactivex.rxjava3.core.MaybeObserver<?>);
    Code:
       0: aload_0
       1: invokevirtual #8                  // Method terminate:()Ljava/lang/Throwable;
       4: astore_2
       5: aload_2
       6: ifnonnull     18
       9: aload_1
      10: invokeinterface #13,  1           // InterfaceMethod io/reactivex/rxjava3/core/MaybeObserver.onComplete:()V
      15: goto          32
      18: aload_2
      19: getstatic     #7                  // Field io/reactivex/rxjava3/internal/util/ExceptionHelper.TERMINATED:Ljava/lang/Throwable;
      22: if_acmpeq     32
      25: aload_1
      26: aload_2
      27: invokeinterface #14,  2           // InterfaceMethod io/reactivex/rxjava3/core/MaybeObserver.onError:(Ljava/lang/Throwable;)V
      32: return

  public void tryTerminateConsumer(io.reactivex.rxjava3.core.SingleObserver<?>);
    Code:
       0: aload_0
       1: invokevirtual #8                  // Method terminate:()Ljava/lang/Throwable;
       4: astore_2
       5: aload_2
       6: ifnull        23
       9: aload_2
      10: getstatic     #7                  // Field io/reactivex/rxjava3/internal/util/ExceptionHelper.TERMINATED:Ljava/lang/Throwable;
      13: if_acmpeq     23
      16: aload_1
      17: aload_2
      18: invokeinterface #15,  2           // InterfaceMethod io/reactivex/rxjava3/core/SingleObserver.onError:(Ljava/lang/Throwable;)V
      23: return

  public void tryTerminateConsumer(io.reactivex.rxjava3.core.CompletableObserver);
    Code:
       0: aload_0
       1: invokevirtual #8                  // Method terminate:()Ljava/lang/Throwable;
       4: astore_2
       5: aload_2
       6: ifnonnull     18
       9: aload_1
      10: invokeinterface #16,  1           // InterfaceMethod io/reactivex/rxjava3/core/CompletableObserver.onComplete:()V
      15: goto          32
      18: aload_2
      19: getstatic     #7                  // Field io/reactivex/rxjava3/internal/util/ExceptionHelper.TERMINATED:Ljava/lang/Throwable;
      22: if_acmpeq     32
      25: aload_1
      26: aload_2
      27: invokeinterface #17,  2           // InterfaceMethod io/reactivex/rxjava3/core/CompletableObserver.onError:(Ljava/lang/Throwable;)V
      32: return

  public void tryTerminateConsumer(io.reactivex.rxjava3.core.Emitter<?>);
    Code:
       0: aload_0
       1: invokevirtual #8                  // Method terminate:()Ljava/lang/Throwable;
       4: astore_2
       5: aload_2
       6: ifnonnull     18
       9: aload_1
      10: invokeinterface #18,  1           // InterfaceMethod io/reactivex/rxjava3/core/Emitter.onComplete:()V
      15: goto          32
      18: aload_2
      19: getstatic     #7                  // Field io/reactivex/rxjava3/internal/util/ExceptionHelper.TERMINATED:Ljava/lang/Throwable;
      22: if_acmpeq     32
      25: aload_1
      26: aload_2
      27: invokeinterface #19,  2           // InterfaceMethod io/reactivex/rxjava3/core/Emitter.onError:(Ljava/lang/Throwable;)V
      32: return
}
