Compiled from "BlockingIgnoringReceiver.java"
public final class io.reactivex.rxjava3.internal.util.BlockingIgnoringReceiver extends java.util.concurrent.CountDownLatch implements io.reactivex.rxjava3.functions.Consumer<java.lang.Throwable>, io.reactivex.rxjava3.functions.Action {
  public java.lang.Throwable error;

  public io.reactivex.rxjava3.internal.util.BlockingIgnoringReceiver();
    Code:
       0: aload_0
       1: iconst_1
       2: invokespecial #1                  // Method java/util/concurrent/CountDownLatch."<init>":(I)V
       5: return

  public void accept(java.lang.Throwable);
    Code:
       0: aload_0
       1: aload_1
       2: putfield      #2                  // Field error:Ljava/lang/Throwable;
       5: aload_0
       6: invokevirtual #3                  // Method countDown:()V
       9: return

  public void run();
    Code:
       0: aload_0
       1: invokevirtual #3                  // Method countDown:()V
       4: return

  public void accept(java.lang.Object) throws java.lang.Throwable;
    Code:
       0: aload_0
       1: aload_1
       2: checkcast     #4                  // class java/lang/Throwable
       5: invokevirtual #5                  // Method accept:(Ljava/lang/Throwable;)V
       8: return
}
