Compiled from "ConnectConsumer.java"
public final class io.reactivex.rxjava3.internal.util.ConnectConsumer implements io.reactivex.rxjava3.functions.Consumer<io.reactivex.rxjava3.disposables.Disposable> {
  public io.reactivex.rxjava3.disposables.Disposable disposable;

  public io.reactivex.rxjava3.internal.util.ConnectConsumer();
    Code:
       0: aload_0
       1: invokespecial #1                  // Method java/lang/Object."<init>":()V
       4: return

  public void accept(io.reactivex.rxjava3.disposables.Disposable);
    Code:
       0: aload_0
       1: aload_1
       2: putfield      #2                  // Field disposable:Lio/reactivex/rxjava3/disposables/Disposable;
       5: return

  public void accept(java.lang.Object) throws java.lang.Throwable;
    Code:
       0: aload_0
       1: aload_1
       2: checkcast     #3                  // class io/reactivex/rxjava3/disposables/Disposable
       5: invokevirtual #4                  // Method accept:(Lio/reactivex/rxjava3/disposables/Disposable;)V
       8: return
}
