Compiled from "EmptyComponent.java"
public final class io.reactivex.rxjava3.internal.util.EmptyComponent extends java.lang.Enum<io.reactivex.rxjava3.internal.util.EmptyComponent> implements io.reactivex.rxjava3.core.FlowableSubscriber<java.lang.Object>, io.reactivex.rxjava3.core.Observer<java.lang.Object>, io.reactivex.rxjava3.core.MaybeObserver<java.lang.Object>, io.reactivex.rxjava3.core.SingleObserver<java.lang.Object>, io.reactivex.rxjava3.core.CompletableObserver, org.reactivestreams.Subscription, io.reactivex.rxjava3.disposables.Disposable {
  public static final io.reactivex.rxjava3.internal.util.EmptyComponent INSTANCE;

  private static final io.reactivex.rxjava3.internal.util.EmptyComponent[] $VALUES;

  public static io.reactivex.rxjava3.internal.util.EmptyComponent[] values();
    Code:
       0: getstatic     #1                  // Field $VALUES:[Lio/reactivex/rxjava3/internal/util/EmptyComponent;
       3: invokevirtual #2                  // Method "[Lio/reactivex/rxjava3/internal/util/EmptyComponent;".clone:()Ljava/lang/Object;
       6: checkcast     #3                  // class "[Lio/reactivex/rxjava3/internal/util/EmptyComponent;"
       9: areturn

  public static io.reactivex.rxjava3.internal.util.EmptyComponent valueOf(java.lang.String);
    Code:
       0: ldc           #4                  // class io/reactivex/rxjava3/internal/util/EmptyComponent
       2: aload_0
       3: invokestatic  #5                  // Method java/lang/Enum.valueOf:(Ljava/lang/Class;Ljava/lang/String;)Ljava/lang/Enum;
       6: checkcast     #4                  // class io/reactivex/rxjava3/internal/util/EmptyComponent
       9: areturn

  private io.reactivex.rxjava3.internal.util.EmptyComponent();
    Code:
       0: aload_0
       1: aload_1
       2: iload_2
       3: invokespecial #6                  // Method java/lang/Enum."<init>":(Ljava/lang/String;I)V
       6: return

  public static <T> org.reactivestreams.Subscriber<T> asSubscriber();
    Code:
       0: getstatic     #7                  // Field INSTANCE:Lio/reactivex/rxjava3/internal/util/EmptyComponent;
       3: areturn

  public static <T> io.reactivex.rxjava3.core.Observer<T> asObserver();
    Code:
       0: getstatic     #7                  // Field INSTANCE:Lio/reactivex/rxjava3/internal/util/EmptyComponent;
       3: areturn

  public void dispose();
    Code:
       0: return

  public boolean isDisposed();
    Code:
       0: iconst_1
       1: ireturn

  public void request(long);
    Code:
       0: return

  public void cancel();
    Code:
       0: return

  public void onSubscribe(io.reactivex.rxjava3.disposables.Disposable);
    Code:
       0: aload_1
       1: invokeinterface #8,  1            // InterfaceMethod io/reactivex/rxjava3/disposables/Disposable.dispose:()V
       6: return

  public void onSubscribe(org.reactivestreams.Subscription);
    Code:
       0: aload_1
       1: invokeinterface #9,  1            // InterfaceMethod org/reactivestreams/Subscription.cancel:()V
       6: return

  public void onNext(java.lang.Object);
    Code:
       0: return

  public void onError(java.lang.Throwable);
    Code:
       0: aload_1
       1: invokestatic  #10                 // Method io/reactivex/rxjava3/plugins/RxJavaPlugins.onError:(Ljava/lang/Throwable;)V
       4: return

  public void onComplete();
    Code:
       0: return

  public void onSuccess(java.lang.Object);
    Code:
       0: return

  static {};
    Code:
       0: new           #4                  // class io/reactivex/rxjava3/internal/util/EmptyComponent
       3: dup
       4: ldc           #11                 // String INSTANCE
       6: iconst_0
       7: invokespecial #12                 // Method "<init>":(Ljava/lang/String;I)V
      10: putstatic     #7                  // Field INSTANCE:Lio/reactivex/rxjava3/internal/util/EmptyComponent;
      13: iconst_1
      14: anewarray     #4                  // class io/reactivex/rxjava3/internal/util/EmptyComponent
      17: dup
      18: iconst_0
      19: getstatic     #7                  // Field INSTANCE:Lio/reactivex/rxjava3/internal/util/EmptyComponent;
      22: aastore
      23: putstatic     #1                  // Field $VALUES:[Lio/reactivex/rxjava3/internal/util/EmptyComponent;
      26: return
}
