Compiled from "ErrorMode.java"
public final class io.reactivex.rxjava3.internal.util.ErrorMode extends java.lang.Enum<io.reactivex.rxjava3.internal.util.ErrorMode> {
  public static final io.reactivex.rxjava3.internal.util.ErrorMode IMMEDIATE;

  public static final io.reactivex.rxjava3.internal.util.ErrorMode BOUNDARY;

  public static final io.reactivex.rxjava3.internal.util.ErrorMode END;

  private static final io.reactivex.rxjava3.internal.util.ErrorMode[] $VALUES;

  public static io.reactivex.rxjava3.internal.util.ErrorMode[] values();
    Code:
       0: getstatic     #1                  // Field $VALUES:[Lio/reactivex/rxjava3/internal/util/ErrorMode;
       3: invokevirtual #2                  // Method "[Lio/reactivex/rxjava3/internal/util/ErrorMode;".clone:()Ljava/lang/Object;
       6: checkcast     #3                  // class "[Lio/reactivex/rxjava3/internal/util/ErrorMode;"
       9: areturn

  public static io.reactivex.rxjava3.internal.util.ErrorMode valueOf(java.lang.String);
    Code:
       0: ldc           #4                  // class io/reactivex/rxjava3/internal/util/ErrorMode
       2: aload_0
       3: invokestatic  #5                  // Method java/lang/Enum.valueOf:(Ljava/lang/Class;Ljava/lang/String;)Ljava/lang/Enum;
       6: checkcast     #4                  // class io/reactivex/rxjava3/internal/util/ErrorMode
       9: areturn

  private io.reactivex.rxjava3.internal.util.ErrorMode();
    Code:
       0: aload_0
       1: aload_1
       2: iload_2
       3: invokespecial #6                  // Method java/lang/Enum."<init>":(Ljava/lang/String;I)V
       6: return

  static {};
    Code:
       0: new           #4                  // class io/reactivex/rxjava3/internal/util/ErrorMode
       3: dup
       4: ldc           #7                  // String IMMEDIATE
       6: iconst_0
       7: invokespecial #8                  // Method "<init>":(Ljava/lang/String;I)V
      10: putstatic     #9                  // Field IMMEDIATE:Lio/reactivex/rxjava3/internal/util/ErrorMode;
      13: new           #4                  // class io/reactivex/rxjava3/internal/util/ErrorMode
      16: dup
      17: ldc           #10                 // String BOUNDARY
      19: iconst_1
      20: invokespecial #8                  // Method "<init>":(Ljava/lang/String;I)V
      23: putstatic     #11                 // Field BOUNDARY:Lio/reactivex/rxjava3/internal/util/ErrorMode;
      26: new           #4                  // class io/reactivex/rxjava3/internal/util/ErrorMode
      29: dup
      30: ldc           #12                 // String END
      32: iconst_2
      33: invokespecial #8                  // Method "<init>":(Ljava/lang/String;I)V
      36: putstatic     #13                 // Field END:Lio/reactivex/rxjava3/internal/util/ErrorMode;
      39: iconst_3
      40: anewarray     #4                  // class io/reactivex/rxjava3/internal/util/ErrorMode
      43: dup
      44: iconst_0
      45: getstatic     #9                  // Field IMMEDIATE:Lio/reactivex/rxjava3/internal/util/ErrorMode;
      48: aastore
      49: dup
      50: iconst_1
      51: getstatic     #11                 // Field BOUNDARY:Lio/reactivex/rxjava3/internal/util/ErrorMode;
      54: aastore
      55: dup
      56: iconst_2
      57: getstatic     #13                 // Field END:Lio/reactivex/rxjava3/internal/util/ErrorMode;
      60: aastore
      61: putstatic     #1                  // Field $VALUES:[Lio/reactivex/rxjava3/internal/util/ErrorMode;
      64: return
}
