Compiled from "HalfSerializer.java"
public final class io.reactivex.rxjava3.internal.util.HalfSerializer {
  private io.reactivex.rxjava3.internal.util.HalfSerializer();
    Code:
       0: aload_0
       1: invokespecial #1                  // Method java/lang/Object."<init>":()V
       4: new           #2                  // class java/lang/IllegalStateException
       7: dup
       8: ldc           #3                  // String No instances!
      10: invokespecial #4                  // Method java/lang/IllegalStateException."<init>":(Ljava/lang/String;)V
      13: athrow

  public static <T> boolean onNext(org.reactivestreams.Subscriber<? super T>, T, java.util.concurrent.atomic.AtomicInteger, io.reactivex.rxjava3.internal.util.AtomicThrowable);
    Code:
       0: aload_2
       1: invokevirtual #5                  // Method java/util/concurrent/atomic/AtomicInteger.get:()I
       4: ifne          37
       7: aload_2
       8: iconst_0
       9: iconst_1
      10: invokevirtual #6                  // Method java/util/concurrent/atomic/AtomicInteger.compareAndSet:(II)Z
      13: ifeq          37
      16: aload_0
      17: aload_1
      18: invokeinterface #7,  2            // InterfaceMethod org/reactivestreams/Subscriber.onNext:(Ljava/lang/Object;)V
      23: aload_2
      24: invokevirtual #8                  // Method java/util/concurrent/atomic/AtomicInteger.decrementAndGet:()I
      27: ifne          32
      30: iconst_1
      31: ireturn
      32: aload_3
      33: aload_0
      34: invokevirtual #9                  // Method io/reactivex/rxjava3/internal/util/AtomicThrowable.tryTerminateConsumer:(Lorg/reactivestreams/Subscriber;)V
      37: iconst_0
      38: ireturn

  public static void onError(org.reactivestreams.Subscriber<?>, java.lang.Throwable, java.util.concurrent.atomic.AtomicInteger, io.reactivex.rxjava3.internal.util.AtomicThrowable);
    Code:
       0: aload_3
       1: aload_1
       2: invokevirtual #10                 // Method io/reactivex/rxjava3/internal/util/AtomicThrowable.tryAddThrowableOrReport:(Ljava/lang/Throwable;)Z
       5: ifeq          20
       8: aload_2
       9: invokevirtual #11                 // Method java/util/concurrent/atomic/AtomicInteger.getAndIncrement:()I
      12: ifne          20
      15: aload_3
      16: aload_0
      17: invokevirtual #9                  // Method io/reactivex/rxjava3/internal/util/AtomicThrowable.tryTerminateConsumer:(Lorg/reactivestreams/Subscriber;)V
      20: return

  public static void onComplete(org.reactivestreams.Subscriber<?>, java.util.concurrent.atomic.AtomicInteger, io.reactivex.rxjava3.internal.util.AtomicThrowable);
    Code:
       0: aload_1
       1: invokevirtual #11                 // Method java/util/concurrent/atomic/AtomicInteger.getAndIncrement:()I
       4: ifne          12
       7: aload_2
       8: aload_0
       9: invokevirtual #9                  // Method io/reactivex/rxjava3/internal/util/AtomicThrowable.tryTerminateConsumer:(Lorg/reactivestreams/Subscriber;)V
      12: return

  public static <T> void onNext(io.reactivex.rxjava3.core.Observer<? super T>, T, java.util.concurrent.atomic.AtomicInteger, io.reactivex.rxjava3.internal.util.AtomicThrowable);
    Code:
       0: aload_2
       1: invokevirtual #5                  // Method java/util/concurrent/atomic/AtomicInteger.get:()I
       4: ifne          35
       7: aload_2
       8: iconst_0
       9: iconst_1
      10: invokevirtual #6                  // Method java/util/concurrent/atomic/AtomicInteger.compareAndSet:(II)Z
      13: ifeq          35
      16: aload_0
      17: aload_1
      18: invokeinterface #12,  2           // InterfaceMethod io/reactivex/rxjava3/core/Observer.onNext:(Ljava/lang/Object;)V
      23: aload_2
      24: invokevirtual #8                  // Method java/util/concurrent/atomic/AtomicInteger.decrementAndGet:()I
      27: ifeq          35
      30: aload_3
      31: aload_0
      32: invokevirtual #13                 // Method io/reactivex/rxjava3/internal/util/AtomicThrowable.tryTerminateConsumer:(Lio/reactivex/rxjava3/core/Observer;)V
      35: return

  public static void onError(io.reactivex.rxjava3.core.Observer<?>, java.lang.Throwable, java.util.concurrent.atomic.AtomicInteger, io.reactivex.rxjava3.internal.util.AtomicThrowable);
    Code:
       0: aload_3
       1: aload_1
       2: invokevirtual #10                 // Method io/reactivex/rxjava3/internal/util/AtomicThrowable.tryAddThrowableOrReport:(Ljava/lang/Throwable;)Z
       5: ifeq          20
       8: aload_2
       9: invokevirtual #11                 // Method java/util/concurrent/atomic/AtomicInteger.getAndIncrement:()I
      12: ifne          20
      15: aload_3
      16: aload_0
      17: invokevirtual #13                 // Method io/reactivex/rxjava3/internal/util/AtomicThrowable.tryTerminateConsumer:(Lio/reactivex/rxjava3/core/Observer;)V
      20: return

  public static void onComplete(io.reactivex.rxjava3.core.Observer<?>, java.util.concurrent.atomic.AtomicInteger, io.reactivex.rxjava3.internal.util.AtomicThrowable);
    Code:
       0: aload_1
       1: invokevirtual #11                 // Method java/util/concurrent/atomic/AtomicInteger.getAndIncrement:()I
       4: ifne          12
       7: aload_2
       8: aload_0
       9: invokevirtual #13                 // Method io/reactivex/rxjava3/internal/util/AtomicThrowable.tryTerminateConsumer:(Lio/reactivex/rxjava3/core/Observer;)V
      12: return
}
