Compiled from "HashMapSupplier.java"
public final class io.reactivex.rxjava3.internal.util.HashMapSupplier extends java.lang.Enum<io.reactivex.rxjava3.internal.util.HashMapSupplier> implements io.reactivex.rxjava3.functions.Supplier<java.util.Map<java.lang.Object, java.lang.Object>> {
  public static final io.reactivex.rxjava3.internal.util.HashMapSupplier INSTANCE;

  private static final io.reactivex.rxjava3.internal.util.HashMapSupplier[] $VALUES;

  public static io.reactivex.rxjava3.internal.util.HashMapSupplier[] values();
    Code:
       0: getstatic     #1                  // Field $VALUES:[Lio/reactivex/rxjava3/internal/util/HashMapSupplier;
       3: invokevirtual #2                  // Method "[Lio/reactivex/rxjava3/internal/util/HashMapSupplier;".clone:()Ljava/lang/Object;
       6: checkcast     #3                  // class "[Lio/reactivex/rxjava3/internal/util/HashMapSupplier;"
       9: areturn

  public static io.reactivex.rxjava3.internal.util.HashMapSupplier valueOf(java.lang.String);
    Code:
       0: ldc           #4                  // class io/reactivex/rxjava3/internal/util/HashMapSupplier
       2: aload_0
       3: invokestatic  #5                  // Method java/lang/Enum.valueOf:(Ljava/lang/Class;Ljava/lang/String;)Ljava/lang/Enum;
       6: checkcast     #4                  // class io/reactivex/rxjava3/internal/util/HashMapSupplier
       9: areturn

  private io.reactivex.rxjava3.internal.util.HashMapSupplier();
    Code:
       0: aload_0
       1: aload_1
       2: iload_2
       3: invokespecial #6                  // Method java/lang/Enum."<init>":(Ljava/lang/String;I)V
       6: return

  public static <K, V> io.reactivex.rxjava3.functions.Supplier<java.util.Map<K, V>> asSupplier();
    Code:
       0: getstatic     #7                  // Field INSTANCE:Lio/reactivex/rxjava3/internal/util/HashMapSupplier;
       3: areturn

  public java.util.Map<java.lang.Object, java.lang.Object> get();
    Code:
       0: new           #8                  // class java/util/HashMap
       3: dup
       4: invokespecial #9                  // Method java/util/HashMap."<init>":()V
       7: areturn

  public java.lang.Object get() throws java.lang.Throwable;
    Code:
       0: aload_0
       1: invokevirtual #10                 // Method get:()Ljava/util/Map;
       4: areturn

  static {};
    Code:
       0: new           #4                  // class io/reactivex/rxjava3/internal/util/HashMapSupplier
       3: dup
       4: ldc           #11                 // String INSTANCE
       6: iconst_0
       7: invokespecial #12                 // Method "<init>":(Ljava/lang/String;I)V
      10: putstatic     #7                  // Field INSTANCE:Lio/reactivex/rxjava3/internal/util/HashMapSupplier;
      13: iconst_1
      14: anewarray     #4                  // class io/reactivex/rxjava3/internal/util/HashMapSupplier
      17: dup
      18: iconst_0
      19: getstatic     #7                  // Field INSTANCE:Lio/reactivex/rxjava3/internal/util/HashMapSupplier;
      22: aastore
      23: putstatic     #1                  // Field $VALUES:[Lio/reactivex/rxjava3/internal/util/HashMapSupplier;
      26: return
}
