Compiled from "ListAddBiConsumer.java"
public final class io.reactivex.rxjava3.internal.util.ListAddBiConsumer extends java.lang.Enum<io.reactivex.rxjava3.internal.util.ListAddBiConsumer> implements io.reactivex.rxjava3.functions.BiFunction<java.util.List, java.lang.Object, java.util.List> {
  public static final io.reactivex.rxjava3.internal.util.ListAddBiConsumer INSTANCE;

  private static final io.reactivex.rxjava3.internal.util.ListAddBiConsumer[] $VALUES;

  public static io.reactivex.rxjava3.internal.util.ListAddBiConsumer[] values();
    Code:
       0: getstatic     #1                  // Field $VALUES:[Lio/reactivex/rxjava3/internal/util/ListAddBiConsumer;
       3: invokevirtual #2                  // Method "[Lio/reactivex/rxjava3/internal/util/ListAddBiConsumer;".clone:()Ljava/lang/Object;
       6: checkcast     #3                  // class "[Lio/reactivex/rxjava3/internal/util/ListAddBiConsumer;"
       9: areturn

  public static io.reactivex.rxjava3.internal.util.ListAddBiConsumer valueOf(java.lang.String);
    Code:
       0: ldc           #4                  // class io/reactivex/rxjava3/internal/util/ListAddBiConsumer
       2: aload_0
       3: invokestatic  #5                  // Method java/lang/Enum.valueOf:(Ljava/lang/Class;Ljava/lang/String;)Ljava/lang/Enum;
       6: checkcast     #4                  // class io/reactivex/rxjava3/internal/util/ListAddBiConsumer
       9: areturn

  private io.reactivex.rxjava3.internal.util.ListAddBiConsumer();
    Code:
       0: aload_0
       1: aload_1
       2: iload_2
       3: invokespecial #6                  // Method java/lang/Enum."<init>":(Ljava/lang/String;I)V
       6: return

  public static <T> io.reactivex.rxjava3.functions.BiFunction<java.util.List<T>, T, java.util.List<T>> instance();
    Code:
       0: getstatic     #7                  // Field INSTANCE:Lio/reactivex/rxjava3/internal/util/ListAddBiConsumer;
       3: areturn

  public java.util.List apply(java.util.List, java.lang.Object);
    Code:
       0: aload_1
       1: aload_2
       2: invokeinterface #8,  2            // InterfaceMethod java/util/List.add:(Ljava/lang/Object;)Z
       7: pop
       8: aload_1
       9: areturn

  public java.lang.Object apply(java.lang.Object, java.lang.Object) throws java.lang.Throwable;
    Code:
       0: aload_0
       1: aload_1
       2: checkcast     #9                  // class java/util/List
       5: aload_2
       6: invokevirtual #10                 // Method apply:(Ljava/util/List;Ljava/lang/Object;)Ljava/util/List;
       9: areturn

  static {};
    Code:
       0: new           #4                  // class io/reactivex/rxjava3/internal/util/ListAddBiConsumer
       3: dup
       4: ldc           #11                 // String INSTANCE
       6: iconst_0
       7: invokespecial #12                 // Method "<init>":(Ljava/lang/String;I)V
      10: putstatic     #7                  // Field INSTANCE:Lio/reactivex/rxjava3/internal/util/ListAddBiConsumer;
      13: iconst_1
      14: anewarray     #4                  // class io/reactivex/rxjava3/internal/util/ListAddBiConsumer
      17: dup
      18: iconst_0
      19: getstatic     #7                  // Field INSTANCE:Lio/reactivex/rxjava3/internal/util/ListAddBiConsumer;
      22: aastore
      23: putstatic     #1                  // Field $VALUES:[Lio/reactivex/rxjava3/internal/util/ListAddBiConsumer;
      26: return
}
