Compiled from "NotificationLite.java"
final class io.reactivex.rxjava3.internal.util.NotificationLite$ErrorNotification implements java.io.Serializable {
  private static final long serialVersionUID;

  final java.lang.Throwable e;

  io.reactivex.rxjava3.internal.util.NotificationLite$ErrorNotification(java.lang.Throwable);
    Code:
       0: aload_0
       1: invokespecial #1                  // Method java/lang/Object."<init>":()V
       4: aload_0
       5: aload_1
       6: putfield      #2                  // Field e:Ljava/lang/Throwable;
       9: return

  public java.lang.String toString();
    Code:
       0: new           #3                  // class java/lang/StringBuilder
       3: dup
       4: invokespecial #4                  // Method java/lang/StringBuilder."<init>":()V
       7: ldc           #5                  // String NotificationLite.Error[
       9: invokevirtual #6                  // Method java/lang/StringBuilder.append:(Ljava/lang/String;)Ljava/lang/StringBuilder;
      12: aload_0
      13: getfield      #2                  // Field e:Ljava/lang/Throwable;
      16: invokevirtual #7                  // Method java/lang/StringBuilder.append:(Ljava/lang/Object;)Ljava/lang/StringBuilder;
      19: ldc           #8                  // String ]
      21: invokevirtual #6                  // Method java/lang/StringBuilder.append:(Ljava/lang/String;)Ljava/lang/StringBuilder;
      24: invokevirtual #9                  // Method java/lang/StringBuilder.toString:()Ljava/lang/String;
      27: areturn

  public int hashCode();
    Code:
       0: aload_0
       1: getfield      #2                  // Field e:Ljava/lang/Throwable;
       4: invokevirtual #10                 // Method java/lang/Object.hashCode:()I
       7: ireturn

  public boolean equals(java.lang.Object);
    Code:
       0: aload_1
       1: instanceof    #11                 // class io/reactivex/rxjava3/internal/util/NotificationLite$ErrorNotification
       4: ifeq          24
       7: aload_1
       8: checkcast     #11                 // class io/reactivex/rxjava3/internal/util/NotificationLite$ErrorNotification
      11: astore_2
      12: aload_0
      13: getfield      #2                  // Field e:Ljava/lang/Throwable;
      16: aload_2
      17: getfield      #2                  // Field e:Ljava/lang/Throwable;
      20: invokestatic  #12                 // Method java/util/Objects.equals:(Ljava/lang/Object;Ljava/lang/Object;)Z
      23: ireturn
      24: iconst_0
      25: ireturn
}
