Compiled from "NotificationLite.java"
final class io.reactivex.rxjava3.internal.util.NotificationLite$SubscriptionNotification implements java.io.Serializable {
  private static final long serialVersionUID;

  final org.reactivestreams.Subscription upstream;

  io.reactivex.rxjava3.internal.util.NotificationLite$SubscriptionNotification(org.reactivestreams.Subscription);
    Code:
       0: aload_0
       1: invokespecial #1                  // Method java/lang/Object."<init>":()V
       4: aload_0
       5: aload_1
       6: putfield      #2                  // Field upstream:Lorg/reactivestreams/Subscription;
       9: return

  public java.lang.String toString();
    Code:
       0: new           #3                  // class java/lang/StringBuilder
       3: dup
       4: invokespecial #4                  // Method java/lang/StringBuilder."<init>":()V
       7: ldc           #5                  // String NotificationLite.Subscription[
       9: invokevirtual #6                  // Method java/lang/StringBuilder.append:(Ljava/lang/String;)Ljava/lang/StringBuilder;
      12: aload_0
      13: getfield      #2                  // Field upstream:Lorg/reactivestreams/Subscription;
      16: invokevirtual #7                  // Method java/lang/StringBuilder.append:(Ljava/lang/Object;)Ljava/lang/StringBuilder;
      19: ldc           #8                  // String ]
      21: invokevirtual #6                  // Method java/lang/StringBuilder.append:(Ljava/lang/String;)Ljava/lang/StringBuilder;
      24: invokevirtual #9                  // Method java/lang/StringBuilder.toString:()Ljava/lang/String;
      27: areturn
}
