Compiled from "NotificationLite.java"
public final class io.reactivex.rxjava3.internal.util.NotificationLite extends java.lang.Enum<io.reactivex.rxjava3.internal.util.NotificationLite> {
  public static final io.reactivex.rxjava3.internal.util.NotificationLite COMPLETE;

  private static final io.reactivex.rxjava3.internal.util.NotificationLite[] $VALUES;

  public static io.reactivex.rxjava3.internal.util.NotificationLite[] values();
    Code:
       0: getstatic     #1                  // Field $VALUES:[Lio/reactivex/rxjava3/internal/util/NotificationLite;
       3: invokevirtual #2                  // Method "[Lio/reactivex/rxjava3/internal/util/NotificationLite;".clone:()Ljava/lang/Object;
       6: checkcast     #3                  // class "[Lio/reactivex/rxjava3/internal/util/NotificationLite;"
       9: areturn

  public static io.reactivex.rxjava3.internal.util.NotificationLite valueOf(java.lang.String);
    Code:
       0: ldc           #4                  // class io/reactivex/rxjava3/internal/util/NotificationLite
       2: aload_0
       3: invokestatic  #5                  // Method java/lang/Enum.valueOf:(Ljava/lang/Class;Ljava/lang/String;)Ljava/lang/Enum;
       6: checkcast     #4                  // class io/reactivex/rxjava3/internal/util/NotificationLite
       9: areturn

  private io.reactivex.rxjava3.internal.util.NotificationLite();
    Code:
       0: aload_0
       1: aload_1
       2: iload_2
       3: invokespecial #6                  // Method java/lang/Enum."<init>":(Ljava/lang/String;I)V
       6: return

  public static <T> java.lang.Object next(T);
    Code:
       0: aload_0
       1: areturn

  public static java.lang.Object complete();
    Code:
       0: getstatic     #7                  // Field COMPLETE:Lio/reactivex/rxjava3/internal/util/NotificationLite;
       3: areturn

  public static java.lang.Object error(java.lang.Throwable);
    Code:
       0: new           #8                  // class io/reactivex/rxjava3/internal/util/NotificationLite$ErrorNotification
       3: dup
       4: aload_0
       5: invokespecial #9                  // Method io/reactivex/rxjava3/internal/util/NotificationLite$ErrorNotification."<init>":(Ljava/lang/Throwable;)V
       8: areturn

  public static java.lang.Object subscription(org.reactivestreams.Subscription);
    Code:
       0: new           #10                 // class io/reactivex/rxjava3/internal/util/NotificationLite$SubscriptionNotification
       3: dup
       4: aload_0
       5: invokespecial #11                 // Method io/reactivex/rxjava3/internal/util/NotificationLite$SubscriptionNotification."<init>":(Lorg/reactivestreams/Subscription;)V
       8: areturn

  public static java.lang.Object disposable(io.reactivex.rxjava3.disposables.Disposable);
    Code:
       0: new           #12                 // class io/reactivex/rxjava3/internal/util/NotificationLite$DisposableNotification
       3: dup
       4: aload_0
       5: invokespecial #13                 // Method io/reactivex/rxjava3/internal/util/NotificationLite$DisposableNotification."<init>":(Lio/reactivex/rxjava3/disposables/Disposable;)V
       8: areturn

  public static boolean isComplete(java.lang.Object);
    Code:
       0: aload_0
       1: getstatic     #7                  // Field COMPLETE:Lio/reactivex/rxjava3/internal/util/NotificationLite;
       4: if_acmpne     11
       7: iconst_1
       8: goto          12
      11: iconst_0
      12: ireturn

  public static boolean isError(java.lang.Object);
    Code:
       0: aload_0
       1: instanceof    #8                  // class io/reactivex/rxjava3/internal/util/NotificationLite$ErrorNotification
       4: ireturn

  public static boolean isSubscription(java.lang.Object);
    Code:
       0: aload_0
       1: instanceof    #10                 // class io/reactivex/rxjava3/internal/util/NotificationLite$SubscriptionNotification
       4: ireturn

  public static boolean isDisposable(java.lang.Object);
    Code:
       0: aload_0
       1: instanceof    #12                 // class io/reactivex/rxjava3/internal/util/NotificationLite$DisposableNotification
       4: ireturn

  public static <T> T getValue(java.lang.Object);
    Code:
       0: aload_0
       1: areturn

  public static java.lang.Throwable getError(java.lang.Object);
    Code:
       0: aload_0
       1: checkcast     #8                  // class io/reactivex/rxjava3/internal/util/NotificationLite$ErrorNotification
       4: getfield      #14                 // Field io/reactivex/rxjava3/internal/util/NotificationLite$ErrorNotification.e:Ljava/lang/Throwable;
       7: areturn

  public static org.reactivestreams.Subscription getSubscription(java.lang.Object);
    Code:
       0: aload_0
       1: checkcast     #10                 // class io/reactivex/rxjava3/internal/util/NotificationLite$SubscriptionNotification
       4: getfield      #15                 // Field io/reactivex/rxjava3/internal/util/NotificationLite$SubscriptionNotification.upstream:Lorg/reactivestreams/Subscription;
       7: areturn

  public static io.reactivex.rxjava3.disposables.Disposable getDisposable(java.lang.Object);
    Code:
       0: aload_0
       1: checkcast     #12                 // class io/reactivex/rxjava3/internal/util/NotificationLite$DisposableNotification
       4: getfield      #16                 // Field io/reactivex/rxjava3/internal/util/NotificationLite$DisposableNotification.upstream:Lio/reactivex/rxjava3/disposables/Disposable;
       7: areturn

  public static <T> boolean accept(java.lang.Object, org.reactivestreams.Subscriber<? super T>);
    Code:
       0: aload_0
       1: getstatic     #7                  // Field COMPLETE:Lio/reactivex/rxjava3/internal/util/NotificationLite;
       4: if_acmpne     15
       7: aload_1
       8: invokeinterface #17,  1           // InterfaceMethod org/reactivestreams/Subscriber.onComplete:()V
      13: iconst_1
      14: ireturn
      15: aload_0
      16: instanceof    #8                  // class io/reactivex/rxjava3/internal/util/NotificationLite$ErrorNotification
      19: ifeq          37
      22: aload_1
      23: aload_0
      24: checkcast     #8                  // class io/reactivex/rxjava3/internal/util/NotificationLite$ErrorNotification
      27: getfield      #14                 // Field io/reactivex/rxjava3/internal/util/NotificationLite$ErrorNotification.e:Ljava/lang/Throwable;
      30: invokeinterface #18,  2           // InterfaceMethod org/reactivestreams/Subscriber.onError:(Ljava/lang/Throwable;)V
      35: iconst_1
      36: ireturn
      37: aload_1
      38: aload_0
      39: invokeinterface #19,  2           // InterfaceMethod org/reactivestreams/Subscriber.onNext:(Ljava/lang/Object;)V
      44: iconst_0
      45: ireturn

  public static <T> boolean accept(java.lang.Object, io.reactivex.rxjava3.core.Observer<? super T>);
    Code:
       0: aload_0
       1: getstatic     #7                  // Field COMPLETE:Lio/reactivex/rxjava3/internal/util/NotificationLite;
       4: if_acmpne     15
       7: aload_1
       8: invokeinterface #20,  1           // InterfaceMethod io/reactivex/rxjava3/core/Observer.onComplete:()V
      13: iconst_1
      14: ireturn
      15: aload_0
      16: instanceof    #8                  // class io/reactivex/rxjava3/internal/util/NotificationLite$ErrorNotification
      19: ifeq          37
      22: aload_1
      23: aload_0
      24: checkcast     #8                  // class io/reactivex/rxjava3/internal/util/NotificationLite$ErrorNotification
      27: getfield      #14                 // Field io/reactivex/rxjava3/internal/util/NotificationLite$ErrorNotification.e:Ljava/lang/Throwable;
      30: invokeinterface #21,  2           // InterfaceMethod io/reactivex/rxjava3/core/Observer.onError:(Ljava/lang/Throwable;)V
      35: iconst_1
      36: ireturn
      37: aload_1
      38: aload_0
      39: invokeinterface #22,  2           // InterfaceMethod io/reactivex/rxjava3/core/Observer.onNext:(Ljava/lang/Object;)V
      44: iconst_0
      45: ireturn

  public static <T> boolean acceptFull(java.lang.Object, org.reactivestreams.Subscriber<? super T>);
    Code:
       0: aload_0
       1: getstatic     #7                  // Field COMPLETE:Lio/reactivex/rxjava3/internal/util/NotificationLite;
       4: if_acmpne     15
       7: aload_1
       8: invokeinterface #17,  1           // InterfaceMethod org/reactivestreams/Subscriber.onComplete:()V
      13: iconst_1
      14: ireturn
      15: aload_0
      16: instanceof    #8                  // class io/reactivex/rxjava3/internal/util/NotificationLite$ErrorNotification
      19: ifeq          37
      22: aload_1
      23: aload_0
      24: checkcast     #8                  // class io/reactivex/rxjava3/internal/util/NotificationLite$ErrorNotification
      27: getfield      #14                 // Field io/reactivex/rxjava3/internal/util/NotificationLite$ErrorNotification.e:Ljava/lang/Throwable;
      30: invokeinterface #18,  2           // InterfaceMethod org/reactivestreams/Subscriber.onError:(Ljava/lang/Throwable;)V
      35: iconst_1
      36: ireturn
      37: aload_0
      38: instanceof    #10                 // class io/reactivex/rxjava3/internal/util/NotificationLite$SubscriptionNotification
      41: ifeq          59
      44: aload_1
      45: aload_0
      46: checkcast     #10                 // class io/reactivex/rxjava3/internal/util/NotificationLite$SubscriptionNotification
      49: getfield      #15                 // Field io/reactivex/rxjava3/internal/util/NotificationLite$SubscriptionNotification.upstream:Lorg/reactivestreams/Subscription;
      52: invokeinterface #23,  2           // InterfaceMethod org/reactivestreams/Subscriber.onSubscribe:(Lorg/reactivestreams/Subscription;)V
      57: iconst_0
      58: ireturn
      59: aload_1
      60: aload_0
      61: invokeinterface #19,  2           // InterfaceMethod org/reactivestreams/Subscriber.onNext:(Ljava/lang/Object;)V
      66: iconst_0
      67: ireturn

  public static <T> boolean acceptFull(java.lang.Object, io.reactivex.rxjava3.core.Observer<? super T>);
    Code:
       0: aload_0
       1: getstatic     #7                  // Field COMPLETE:Lio/reactivex/rxjava3/internal/util/NotificationLite;
       4: if_acmpne     15
       7: aload_1
       8: invokeinterface #20,  1           // InterfaceMethod io/reactivex/rxjava3/core/Observer.onComplete:()V
      13: iconst_1
      14: ireturn
      15: aload_0
      16: instanceof    #8                  // class io/reactivex/rxjava3/internal/util/NotificationLite$ErrorNotification
      19: ifeq          37
      22: aload_1
      23: aload_0
      24: checkcast     #8                  // class io/reactivex/rxjava3/internal/util/NotificationLite$ErrorNotification
      27: getfield      #14                 // Field io/reactivex/rxjava3/internal/util/NotificationLite$ErrorNotification.e:Ljava/lang/Throwable;
      30: invokeinterface #21,  2           // InterfaceMethod io/reactivex/rxjava3/core/Observer.onError:(Ljava/lang/Throwable;)V
      35: iconst_1
      36: ireturn
      37: aload_0
      38: instanceof    #12                 // class io/reactivex/rxjava3/internal/util/NotificationLite$DisposableNotification
      41: ifeq          59
      44: aload_1
      45: aload_0
      46: checkcast     #12                 // class io/reactivex/rxjava3/internal/util/NotificationLite$DisposableNotification
      49: getfield      #16                 // Field io/reactivex/rxjava3/internal/util/NotificationLite$DisposableNotification.upstream:Lio/reactivex/rxjava3/disposables/Disposable;
      52: invokeinterface #24,  2           // InterfaceMethod io/reactivex/rxjava3/core/Observer.onSubscribe:(Lio/reactivex/rxjava3/disposables/Disposable;)V
      57: iconst_0
      58: ireturn
      59: aload_1
      60: aload_0
      61: invokeinterface #22,  2           // InterfaceMethod io/reactivex/rxjava3/core/Observer.onNext:(Ljava/lang/Object;)V
      66: iconst_0
      67: ireturn

  public java.lang.String toString();
    Code:
       0: ldc           #25                 // String NotificationLite.Complete
       2: areturn

  static {};
    Code:
       0: new           #4                  // class io/reactivex/rxjava3/internal/util/NotificationLite
       3: dup
       4: ldc           #26                 // String COMPLETE
       6: iconst_0
       7: invokespecial #27                 // Method "<init>":(Ljava/lang/String;I)V
      10: putstatic     #7                  // Field COMPLETE:Lio/reactivex/rxjava3/internal/util/NotificationLite;
      13: iconst_1
      14: anewarray     #4                  // class io/reactivex/rxjava3/internal/util/NotificationLite
      17: dup
      18: iconst_0
      19: getstatic     #7                  // Field COMPLETE:Lio/reactivex/rxjava3/internal/util/NotificationLite;
      22: aastore
      23: putstatic     #1                  // Field $VALUES:[Lio/reactivex/rxjava3/internal/util/NotificationLite;
      26: return
}
