Compiled from "Pow2.java"
public final class io.reactivex.rxjava3.internal.util.Pow2 {
  private io.reactivex.rxjava3.internal.util.Pow2();
    Code:
       0: aload_0
       1: invokespecial #1                  // Method java/lang/Object."<init>":()V
       4: new           #2                  // class java/lang/IllegalStateException
       7: dup
       8: ldc           #3                  // String No instances!
      10: invokespecial #4                  // Method java/lang/IllegalStateException."<init>":(Ljava/lang/String;)V
      13: athrow

  public static int roundToPowerOfTwo(int);
    Code:
       0: iconst_1
       1: bipush        32
       3: iload_0
       4: iconst_1
       5: isub
       6: invokestatic  #5                  // Method java/lang/Integer.numberOfLeadingZeros:(I)I
       9: isub
      10: ishl
      11: ireturn

  public static boolean isPowerOfTwo(int);
    Code:
       0: iload_0
       1: iload_0
       2: iconst_1
       3: isub
       4: iand
       5: ifne          12
       8: iconst_1
       9: goto          13
      12: iconst_0
      13: ireturn
}
