Compiled from "VolatileSizeArrayList.java"
public final class io.reactivex.rxjava3.internal.util.VolatileSizeArrayList<T> extends java.util.concurrent.atomic.AtomicInteger implements java.util.List<T>, java.util.RandomAccess {
  private static final long serialVersionUID;

  final java.util.ArrayList<T> list;

  public io.reactivex.rxjava3.internal.util.VolatileSizeArrayList();
    Code:
       0: aload_0
       1: invokespecial #1                  // Method java/util/concurrent/atomic/AtomicInteger."<init>":()V
       4: aload_0
       5: new           #2                  // class java/util/ArrayList
       8: dup
       9: invokespecial #3                  // Method java/util/ArrayList."<init>":()V
      12: putfield      #4                  // Field list:Ljava/util/ArrayList;
      15: return

  public io.reactivex.rxjava3.internal.util.VolatileSizeArrayList(int);
    Code:
       0: aload_0
       1: invokespecial #1                  // Method java/util/concurrent/atomic/AtomicInteger."<init>":()V
       4: aload_0
       5: new           #2                  // class java/util/ArrayList
       8: dup
       9: iload_1
      10: invokespecial #5                  // Method java/util/ArrayList."<init>":(I)V
      13: putfield      #4                  // Field list:Ljava/util/ArrayList;
      16: return

  public int size();
    Code:
       0: aload_0
       1: invokevirtual #6                  // Method get:()I
       4: ireturn

  public boolean isEmpty();
    Code:
       0: aload_0
       1: invokevirtual #6                  // Method get:()I
       4: ifne          11
       7: iconst_1
       8: goto          12
      11: iconst_0
      12: ireturn

  public boolean contains(java.lang.Object);
    Code:
       0: aload_0
       1: getfield      #4                  // Field list:Ljava/util/ArrayList;
       4: aload_1
       5: invokevirtual #7                  // Method java/util/ArrayList.contains:(Ljava/lang/Object;)Z
       8: ireturn

  public java.util.Iterator<T> iterator();
    Code:
       0: aload_0
       1: getfield      #4                  // Field list:Ljava/util/ArrayList;
       4: invokevirtual #8                  // Method java/util/ArrayList.iterator:()Ljava/util/Iterator;
       7: areturn

  public java.lang.Object[] toArray();
    Code:
       0: aload_0
       1: getfield      #4                  // Field list:Ljava/util/ArrayList;
       4: invokevirtual #9                  // Method java/util/ArrayList.toArray:()[Ljava/lang/Object;
       7: areturn

  public <E> E[] toArray(E[]);
    Code:
       0: aload_0
       1: getfield      #4                  // Field list:Ljava/util/ArrayList;
       4: aload_1
       5: invokevirtual #10                 // Method java/util/ArrayList.toArray:([Ljava/lang/Object;)[Ljava/lang/Object;
       8: areturn

  public boolean add(T);
    Code:
       0: aload_0
       1: getfield      #4                  // Field list:Ljava/util/ArrayList;
       4: aload_1
       5: invokevirtual #11                 // Method java/util/ArrayList.add:(Ljava/lang/Object;)Z
       8: istore_2
       9: aload_0
      10: aload_0
      11: getfield      #4                  // Field list:Ljava/util/ArrayList;
      14: invokevirtual #12                 // Method java/util/ArrayList.size:()I
      17: invokevirtual #13                 // Method lazySet:(I)V
      20: iload_2
      21: ireturn

  public boolean remove(java.lang.Object);
    Code:
       0: aload_0
       1: getfield      #4                  // Field list:Ljava/util/ArrayList;
       4: aload_1
       5: invokevirtual #14                 // Method java/util/ArrayList.remove:(Ljava/lang/Object;)Z
       8: istore_2
       9: aload_0
      10: aload_0
      11: getfield      #4                  // Field list:Ljava/util/ArrayList;
      14: invokevirtual #12                 // Method java/util/ArrayList.size:()I
      17: invokevirtual #13                 // Method lazySet:(I)V
      20: iload_2
      21: ireturn

  public boolean containsAll(java.util.Collection<?>);
    Code:
       0: aload_0
       1: getfield      #4                  // Field list:Ljava/util/ArrayList;
       4: aload_1
       5: invokevirtual #15                 // Method java/util/ArrayList.containsAll:(Ljava/util/Collection;)Z
       8: ireturn

  public boolean addAll(java.util.Collection<? extends T>);
    Code:
       0: aload_0
       1: getfield      #4                  // Field list:Ljava/util/ArrayList;
       4: aload_1
       5: invokevirtual #16                 // Method java/util/ArrayList.addAll:(Ljava/util/Collection;)Z
       8: istore_2
       9: aload_0
      10: aload_0
      11: getfield      #4                  // Field list:Ljava/util/ArrayList;
      14: invokevirtual #12                 // Method java/util/ArrayList.size:()I
      17: invokevirtual #13                 // Method lazySet:(I)V
      20: iload_2
      21: ireturn

  public boolean addAll(int, java.util.Collection<? extends T>);
    Code:
       0: aload_0
       1: getfield      #4                  // Field list:Ljava/util/ArrayList;
       4: iload_1
       5: aload_2
       6: invokevirtual #17                 // Method java/util/ArrayList.addAll:(ILjava/util/Collection;)Z
       9: istore_3
      10: aload_0
      11: aload_0
      12: getfield      #4                  // Field list:Ljava/util/ArrayList;
      15: invokevirtual #12                 // Method java/util/ArrayList.size:()I
      18: invokevirtual #13                 // Method lazySet:(I)V
      21: iload_3
      22: ireturn

  public boolean removeAll(java.util.Collection<?>);
    Code:
       0: aload_0
       1: getfield      #4                  // Field list:Ljava/util/ArrayList;
       4: aload_1
       5: invokevirtual #18                 // Method java/util/ArrayList.removeAll:(Ljava/util/Collection;)Z
       8: istore_2
       9: aload_0
      10: aload_0
      11: getfield      #4                  // Field list:Ljava/util/ArrayList;
      14: invokevirtual #12                 // Method java/util/ArrayList.size:()I
      17: invokevirtual #13                 // Method lazySet:(I)V
      20: iload_2
      21: ireturn

  public boolean retainAll(java.util.Collection<?>);
    Code:
       0: aload_0
       1: getfield      #4                  // Field list:Ljava/util/ArrayList;
       4: aload_1
       5: invokevirtual #19                 // Method java/util/ArrayList.retainAll:(Ljava/util/Collection;)Z
       8: istore_2
       9: aload_0
      10: aload_0
      11: getfield      #4                  // Field list:Ljava/util/ArrayList;
      14: invokevirtual #12                 // Method java/util/ArrayList.size:()I
      17: invokevirtual #13                 // Method lazySet:(I)V
      20: iload_2
      21: ireturn

  public void clear();
    Code:
       0: aload_0
       1: getfield      #4                  // Field list:Ljava/util/ArrayList;
       4: invokevirtual #20                 // Method java/util/ArrayList.clear:()V
       7: aload_0
       8: iconst_0
       9: invokevirtual #13                 // Method lazySet:(I)V
      12: return

  public T get(int);
    Code:
       0: aload_0
       1: getfield      #4                  // Field list:Ljava/util/ArrayList;
       4: iload_1
       5: invokevirtual #21                 // Method java/util/ArrayList.get:(I)Ljava/lang/Object;
       8: areturn

  public T set(int, T);
    Code:
       0: aload_0
       1: getfield      #4                  // Field list:Ljava/util/ArrayList;
       4: iload_1
       5: aload_2
       6: invokevirtual #22                 // Method java/util/ArrayList.set:(ILjava/lang/Object;)Ljava/lang/Object;
       9: areturn

  public void add(int, T);
    Code:
       0: aload_0
       1: getfield      #4                  // Field list:Ljava/util/ArrayList;
       4: iload_1
       5: aload_2
       6: invokevirtual #23                 // Method java/util/ArrayList.add:(ILjava/lang/Object;)V
       9: aload_0
      10: aload_0
      11: getfield      #4                  // Field list:Ljava/util/ArrayList;
      14: invokevirtual #12                 // Method java/util/ArrayList.size:()I
      17: invokevirtual #13                 // Method lazySet:(I)V
      20: return

  public T remove(int);
    Code:
       0: aload_0
       1: getfield      #4                  // Field list:Ljava/util/ArrayList;
       4: iload_1
       5: invokevirtual #24                 // Method java/util/ArrayList.remove:(I)Ljava/lang/Object;
       8: astore_2
       9: aload_0
      10: aload_0
      11: getfield      #4                  // Field list:Ljava/util/ArrayList;
      14: invokevirtual #12                 // Method java/util/ArrayList.size:()I
      17: invokevirtual #13                 // Method lazySet:(I)V
      20: aload_2
      21: areturn

  public int indexOf(java.lang.Object);
    Code:
       0: aload_0
       1: getfield      #4                  // Field list:Ljava/util/ArrayList;
       4: aload_1
       5: invokevirtual #25                 // Method java/util/ArrayList.indexOf:(Ljava/lang/Object;)I
       8: ireturn

  public int lastIndexOf(java.lang.Object);
    Code:
       0: aload_0
       1: getfield      #4                  // Field list:Ljava/util/ArrayList;
       4: aload_1
       5: invokevirtual #26                 // Method java/util/ArrayList.lastIndexOf:(Ljava/lang/Object;)I
       8: ireturn

  public java.util.ListIterator<T> listIterator();
    Code:
       0: aload_0
       1: getfield      #4                  // Field list:Ljava/util/ArrayList;
       4: invokevirtual #27                 // Method java/util/ArrayList.listIterator:()Ljava/util/ListIterator;
       7: areturn

  public java.util.ListIterator<T> listIterator(int);
    Code:
       0: aload_0
       1: getfield      #4                  // Field list:Ljava/util/ArrayList;
       4: iload_1
       5: invokevirtual #28                 // Method java/util/ArrayList.listIterator:(I)Ljava/util/ListIterator;
       8: areturn

  public java.util.List<T> subList(int, int);
    Code:
       0: aload_0
       1: getfield      #4                  // Field list:Ljava/util/ArrayList;
       4: iload_1
       5: iload_2
       6: invokevirtual #29                 // Method java/util/ArrayList.subList:(II)Ljava/util/List;
       9: areturn

  public boolean equals(java.lang.Object);
    Code:
       0: aload_1
       1: instanceof    #30                 // class io/reactivex/rxjava3/internal/util/VolatileSizeArrayList
       4: ifeq          22
       7: aload_0
       8: getfield      #4                  // Field list:Ljava/util/ArrayList;
      11: aload_1
      12: checkcast     #30                 // class io/reactivex/rxjava3/internal/util/VolatileSizeArrayList
      15: getfield      #4                  // Field list:Ljava/util/ArrayList;
      18: invokevirtual #31                 // Method java/util/ArrayList.equals:(Ljava/lang/Object;)Z
      21: ireturn
      22: aload_0
      23: getfield      #4                  // Field list:Ljava/util/ArrayList;
      26: aload_1
      27: invokevirtual #31                 // Method java/util/ArrayList.equals:(Ljava/lang/Object;)Z
      30: ireturn

  public int hashCode();
    Code:
       0: aload_0
       1: getfield      #4                  // Field list:Ljava/util/ArrayList;
       4: invokevirtual #32                 // Method java/util/ArrayList.hashCode:()I
       7: ireturn

  public java.lang.String toString();
    Code:
       0: aload_0
       1: getfield      #4                  // Field list:Ljava/util/ArrayList;
       4: invokevirtual #33                 // Method java/util/ArrayList.toString:()Ljava/lang/String;
       7: areturn
}
