Compiled from "ServerStatusChecker.java"
public class org.apache.dubbo.rpc.protocol.dubbo.status.ServerStatusChecker implements org.apache.dubbo.common.status.StatusChecker {
  public org.apache.dubbo.rpc.protocol.dubbo.status.ServerStatusChecker();
    Code:
       0: aload_0
       1: invokespecial #1                  // Method java/lang/Object."<init>":()V
       4: return

  public org.apache.dubbo.common.status.Status check();
    Code:
       0: invokestatic  #2                  // Method org/apache/dubbo/rpc/protocol/dubbo/DubboProtocol.getDubboProtocol:()Lorg/apache/dubbo/rpc/protocol/dubbo/DubboProtocol;
       3: invokevirtual #3                  // Method org/apache/dubbo/rpc/protocol/dubbo/DubboProtocol.getServers:()Ljava/util/List;
       6: astore_1
       7: aload_1
       8: ifnull        20
      11: aload_1
      12: invokeinterface #4,  1            // InterfaceMethod java/util/List.isEmpty:()Z
      17: ifeq          31
      20: new           #5                  // class org/apache/dubbo/common/status/Status
      23: dup
      24: getstatic     #6                  // Field org/apache/dubbo/common/status/Status$Level.UNKNOWN:Lorg/apache/dubbo/common/status/Status$Level;
      27: invokespecial #7                  // Method org/apache/dubbo/common/status/Status."<init>":(Lorg/apache/dubbo/common/status/Status$Level;)V
      30: areturn
      31: getstatic     #8                  // Field org/apache/dubbo/common/status/Status$Level.OK:Lorg/apache/dubbo/common/status/Status$Level;
      34: astore_2
      35: new           #9                  // class java/lang/StringBuilder
      38: dup
      39: invokespecial #10                 // Method java/lang/StringBuilder."<init>":()V
      42: astore_3
      43: aload_1
      44: invokeinterface #11,  1           // InterfaceMethod java/util/List.iterator:()Ljava/util/Iterator;
      49: astore        4
      51: aload         4
      53: invokeinterface #12,  1           // InterfaceMethod java/util/Iterator.hasNext:()Z
      58: ifeq          176
      61: aload         4
      63: invokeinterface #13,  1           // InterfaceMethod java/util/Iterator.next:()Ljava/lang/Object;
      68: checkcast     #14                 // class org/apache/dubbo/rpc/ProtocolServer
      71: astore        5
      73: aload         5
      75: invokeinterface #15,  1           // InterfaceMethod org/apache/dubbo/rpc/ProtocolServer.getRemotingServer:()Lorg/apache/dubbo/remoting/RemotingServer;
      80: astore        6
      82: aload         6
      84: invokeinterface #16,  1           // InterfaceMethod org/apache/dubbo/remoting/RemotingServer.isBound:()Z
      89: ifne          116
      92: getstatic     #17                 // Field org/apache/dubbo/common/status/Status$Level.ERROR:Lorg/apache/dubbo/common/status/Status$Level;
      95: astore_2
      96: aload_3
      97: iconst_0
      98: invokevirtual #18                 // Method java/lang/StringBuilder.setLength:(I)V
     101: aload_3
     102: aload         6
     104: invokeinterface #19,  1           // InterfaceMethod org/apache/dubbo/remoting/RemotingServer.getLocalAddress:()Ljava/net/InetSocketAddress;
     109: invokevirtual #20                 // Method java/lang/StringBuilder.append:(Ljava/lang/Object;)Ljava/lang/StringBuilder;
     112: pop
     113: goto          176
     116: aload_3
     117: invokevirtual #21                 // Method java/lang/StringBuilder.length:()I
     120: ifle          130
     123: aload_3
     124: bipush        44
     126: invokevirtual #22                 // Method java/lang/StringBuilder.append:(C)Ljava/lang/StringBuilder;
     129: pop
     130: aload_3
     131: aload         6
     133: invokeinterface #19,  1           // InterfaceMethod org/apache/dubbo/remoting/RemotingServer.getLocalAddress:()Ljava/net/InetSocketAddress;
     138: invokevirtual #20                 // Method java/lang/StringBuilder.append:(Ljava/lang/Object;)Ljava/lang/StringBuilder;
     141: pop
     142: aload_3
     143: ldc           #23                 // String (clients:
     145: invokevirtual #24                 // Method java/lang/StringBuilder.append:(Ljava/lang/String;)Ljava/lang/StringBuilder;
     148: pop
     149: aload_3
     150: aload         6
     152: invokeinterface #25,  1           // InterfaceMethod org/apache/dubbo/remoting/RemotingServer.getChannels:()Ljava/util/Collection;
     157: invokeinterface #26,  1           // InterfaceMethod java/util/Collection.size:()I
     162: invokevirtual #27                 // Method java/lang/StringBuilder.append:(I)Ljava/lang/StringBuilder;
     165: pop
     166: aload_3
     167: bipush        41
     169: invokevirtual #22                 // Method java/lang/StringBuilder.append:(C)Ljava/lang/StringBuilder;
     172: pop
     173: goto          51
     176: new           #5                  // class org/apache/dubbo/common/status/Status
     179: dup
     180: aload_2
     181: aload_3
     182: invokevirtual #28                 // Method java/lang/StringBuilder.toString:()Ljava/lang/String;
     185: invokespecial #29                 // Method org/apache/dubbo/common/status/Status."<init>":(Lorg/apache/dubbo/common/status/Status$Level;Ljava/lang/String;)V
     188: areturn
}
