Compiled from "QosDetector.java"
public class org.apache.dubbo.qos.pu.QosDetector implements org.apache.dubbo.remoting.api.ProtocolDetector {
  private final org.apache.dubbo.qos.pu.QosHTTP1Detector qosHTTP1Detector;

  private final org.apache.dubbo.qos.pu.TelnetDetector telnetDetector;

  private boolean QosEnableFlag;

  public void setQosEnableFlag(boolean);
    Code:
       0: aload_0
       1: iload_1
       2: putfield      #1                  // Field QosEnableFlag:Z
       5: return

  public org.apache.dubbo.qos.pu.QosDetector(org.apache.dubbo.rpc.model.FrameworkModel);
    Code:
       0: aload_0
       1: invokespecial #2                  // Method java/lang/Object."<init>":()V
       4: aload_0
       5: new           #3                  // class org/apache/dubbo/qos/pu/QosHTTP1Detector
       8: dup
       9: invokespecial #4                  // Method org/apache/dubbo/qos/pu/QosHTTP1Detector."<init>":()V
      12: putfield      #5                  // Field qosHTTP1Detector:Lorg/apache/dubbo/qos/pu/QosHTTP1Detector;
      15: aload_0
      16: iconst_1
      17: putfield      #1                  // Field QosEnableFlag:Z
      20: aload_0
      21: new           #6                  // class org/apache/dubbo/qos/pu/TelnetDetector
      24: dup
      25: aload_1
      26: invokespecial #7                  // Method org/apache/dubbo/qos/pu/TelnetDetector."<init>":(Lorg/apache/dubbo/rpc/model/FrameworkModel;)V
      29: putfield      #8                  // Field telnetDetector:Lorg/apache/dubbo/qos/pu/TelnetDetector;
      32: return

  public org.apache.dubbo.remoting.api.ProtocolDetector$Result detect(org.apache.dubbo.remoting.buffer.ChannelBuffer);
    Code:
       0: aload_0
       1: getfield      #1                  // Field QosEnableFlag:Z
       4: ifne          11
       7: getstatic     #9                  // Field org/apache/dubbo/remoting/api/ProtocolDetector$Result.UNRECOGNIZED:Lorg/apache/dubbo/remoting/api/ProtocolDetector$Result;
      10: areturn
      11: aload_0
      12: getfield      #5                  // Field qosHTTP1Detector:Lorg/apache/dubbo/qos/pu/QosHTTP1Detector;
      15: aload_1
      16: invokevirtual #10                 // Method org/apache/dubbo/qos/pu/QosHTTP1Detector.detect:(Lorg/apache/dubbo/remoting/buffer/ChannelBuffer;)Lorg/apache/dubbo/remoting/api/ProtocolDetector$Result;
      19: astore_2
      20: aload_2
      21: getstatic     #11                 // Field org/apache/dubbo/remoting/api/ProtocolDetector$Result.RECOGNIZED:Lorg/apache/dubbo/remoting/api/ProtocolDetector$Result;
      24: invokevirtual #12                 // Method org/apache/dubbo/remoting/api/ProtocolDetector$Result.equals:(Ljava/lang/Object;)Z
      27: ifeq          32
      30: aload_2
      31: areturn
      32: aload_0
      33: getfield      #8                  // Field telnetDetector:Lorg/apache/dubbo/qos/pu/TelnetDetector;
      36: aload_1
      37: invokevirtual #13                 // Method org/apache/dubbo/qos/pu/TelnetDetector.detect:(Lorg/apache/dubbo/remoting/buffer/ChannelBuffer;)Lorg/apache/dubbo/remoting/api/ProtocolDetector$Result;
      40: astore_3
      41: aload_3
      42: getstatic     #11                 // Field org/apache/dubbo/remoting/api/ProtocolDetector$Result.RECOGNIZED:Lorg/apache/dubbo/remoting/api/ProtocolDetector$Result;
      45: invokevirtual #12                 // Method org/apache/dubbo/remoting/api/ProtocolDetector$Result.equals:(Ljava/lang/Object;)Z
      48: ifeq          53
      51: aload_3
      52: areturn
      53: aload_2
      54: getstatic     #14                 // Field org/apache/dubbo/remoting/api/ProtocolDetector$Result.NEED_MORE_DATA:Lorg/apache/dubbo/remoting/api/ProtocolDetector$Result;
      57: invokevirtual #12                 // Method org/apache/dubbo/remoting/api/ProtocolDetector$Result.equals:(Ljava/lang/Object;)Z
      60: ifne          73
      63: aload_3
      64: getstatic     #14                 // Field org/apache/dubbo/remoting/api/ProtocolDetector$Result.NEED_MORE_DATA:Lorg/apache/dubbo/remoting/api/ProtocolDetector$Result;
      67: invokevirtual #12                 // Method org/apache/dubbo/remoting/api/ProtocolDetector$Result.equals:(Ljava/lang/Object;)Z
      70: ifeq          77
      73: getstatic     #14                 // Field org/apache/dubbo/remoting/api/ProtocolDetector$Result.NEED_MORE_DATA:Lorg/apache/dubbo/remoting/api/ProtocolDetector$Result;
      76: areturn
      77: getstatic     #9                  // Field org/apache/dubbo/remoting/api/ProtocolDetector$Result.UNRECOGNIZED:Lorg/apache/dubbo/remoting/api/ProtocolDetector$Result;
      80: areturn
}
