Compiled from "QosHTTP1Detector.java"
public class org.apache.dubbo.qos.pu.QosHTTP1Detector implements org.apache.dubbo.remoting.api.ProtocolDetector {
  public org.apache.dubbo.qos.pu.QosHTTP1Detector();
    Code:
       0: aload_0
       1: invokespecial #1                  // Method java/lang/Object."<init>":()V
       4: return

  private static boolean isHttp(int);
    Code:
       0: iload_0
       1: bipush        71
       3: if_icmpeq     12
       6: iload_0
       7: bipush        80
       9: if_icmpne     16
      12: iconst_1
      13: goto          17
      16: iconst_0
      17: ireturn

  public org.apache.dubbo.remoting.api.ProtocolDetector$Result detect(org.apache.dubbo.remoting.buffer.ChannelBuffer);
    Code:
       0: aload_1
       1: invokeinterface #2,  1            // InterfaceMethod org/apache/dubbo/remoting/buffer/ChannelBuffer.readableBytes:()I
       6: iconst_2
       7: if_icmpge     14
      10: getstatic     #3                  // Field org/apache/dubbo/remoting/api/ProtocolDetector$Result.NEED_MORE_DATA:Lorg/apache/dubbo/remoting/api/ProtocolDetector$Result;
      13: areturn
      14: aload_1
      15: aload_1
      16: invokeinterface #4,  1            // InterfaceMethod org/apache/dubbo/remoting/buffer/ChannelBuffer.readerIndex:()I
      21: invokeinterface #5,  2            // InterfaceMethod org/apache/dubbo/remoting/buffer/ChannelBuffer.getByte:(I)B
      26: istore_2
      27: iload_2
      28: invokestatic  #6                  // Method isHttp:(I)Z
      31: ifeq          57
      34: aload_1
      35: aload_1
      36: invokeinterface #4,  1            // InterfaceMethod org/apache/dubbo/remoting/buffer/ChannelBuffer.readerIndex:()I
      41: iconst_1
      42: iadd
      43: invokeinterface #5,  2            // InterfaceMethod org/apache/dubbo/remoting/buffer/ChannelBuffer.getByte:(I)B
      48: bipush        82
      50: if_icmpeq     57
      53: getstatic     #7                  // Field org/apache/dubbo/remoting/api/ProtocolDetector$Result.RECOGNIZED:Lorg/apache/dubbo/remoting/api/ProtocolDetector$Result;
      56: areturn
      57: getstatic     #8                  // Field org/apache/dubbo/remoting/api/ProtocolDetector$Result.UNRECOGNIZED:Lorg/apache/dubbo/remoting/api/ProtocolDetector$Result;
      60: areturn
}
