Compiled from "QosWireProtocol.java"
public class org.apache.dubbo.qos.pu.QosWireProtocol extends org.apache.dubbo.remoting.api.AbstractWireProtocol implements org.apache.dubbo.rpc.model.ScopeModelAware {
  public org.apache.dubbo.qos.pu.QosWireProtocol(org.apache.dubbo.rpc.model.FrameworkModel);
    Code:
       0: aload_0
       1: new           #1                  // class org/apache/dubbo/qos/pu/QosDetector
       4: dup
       5: aload_1
       6: invokespecial #2                  // Method org/apache/dubbo/qos/pu/QosDetector."<init>":(Lorg/apache/dubbo/rpc/model/FrameworkModel;)V
       9: invokespecial #3                  // Method org/apache/dubbo/remoting/api/AbstractWireProtocol."<init>":(Lorg/apache/dubbo/remoting/api/ProtocolDetector;)V
      12: return

  public void setQosEnable(boolean);
    Code:
       0: aload_0
       1: invokevirtual #4                  // Method detector:()Lorg/apache/dubbo/remoting/api/ProtocolDetector;
       4: checkcast     #1                  // class org/apache/dubbo/qos/pu/QosDetector
       7: iload_1
       8: invokevirtual #5                  // Method org/apache/dubbo/qos/pu/QosDetector.setQosEnableFlag:(Z)V
      11: return

  public void configServerProtocolHandler(org.apache.dubbo.common.URL, org.apache.dubbo.remoting.api.pu.ChannelOperator);
    Code:
       0: new           #6                  // class org/apache/dubbo/qos/server/handler/QosProcessHandler
       3: dup
       4: aload_1
       5: invokevirtual #7                  // Method org/apache/dubbo/common/URL.getOrDefaultFrameworkModel:()Lorg/apache/dubbo/rpc/model/FrameworkModel;
       8: invokestatic  #8                  // Method org/apache/dubbo/qos/api/QosConfiguration.builder:()Lorg/apache/dubbo/qos/api/QosConfiguration$Builder;
      11: getstatic     #9                  // Field org/apache/dubbo/qos/server/DubboLogo.DUBBO:Ljava/lang/String;
      14: invokevirtual #10                 // Method org/apache/dubbo/qos/api/QosConfiguration$Builder.welcome:(Ljava/lang/String;)Lorg/apache/dubbo/qos/api/QosConfiguration$Builder;
      17: iconst_0
      18: invokevirtual #11                 // Method org/apache/dubbo/qos/api/QosConfiguration$Builder.acceptForeignIp:(Z)Lorg/apache/dubbo/qos/api/QosConfiguration$Builder;
      21: ldc           #13                 // String
      23: invokevirtual #14                 // Method org/apache/dubbo/qos/api/QosConfiguration$Builder.acceptForeignIpWhitelist:(Ljava/lang/String;)Lorg/apache/dubbo/qos/api/QosConfiguration$Builder;
      26: getstatic     #15                 // Field org/apache/dubbo/qos/api/PermissionLevel.PUBLIC:Lorg/apache/dubbo/qos/api/PermissionLevel;
      29: invokevirtual #16                 // Method org/apache/dubbo/qos/api/PermissionLevel.name:()Ljava/lang/String;
      32: invokevirtual #17                 // Method org/apache/dubbo/qos/api/QosConfiguration$Builder.anonymousAccessPermissionLevel:(Ljava/lang/String;)Lorg/apache/dubbo/qos/api/QosConfiguration$Builder;
      35: invokevirtual #18                 // Method org/apache/dubbo/qos/api/QosConfiguration$Builder.build:()Lorg/apache/dubbo/qos/api/QosConfiguration;
      38: invokespecial #19                 // Method org/apache/dubbo/qos/server/handler/QosProcessHandler."<init>":(Lorg/apache/dubbo/rpc/model/FrameworkModel;Lorg/apache/dubbo/qos/api/QosConfiguration;)V
      41: astore_3
      42: new           #20                 // class java/util/ArrayList
      45: dup
      46: invokespecial #21                 // Method java/util/ArrayList."<init>":()V
      49: astore        4
      51: aload         4
      53: new           #22                 // class org/apache/dubbo/remoting/api/pu/ChannelHandlerPretender
      56: dup
      57: aload_3
      58: invokespecial #23                 // Method org/apache/dubbo/remoting/api/pu/ChannelHandlerPretender."<init>":(Ljava/lang/Object;)V
      61: invokeinterface #24,  2           // InterfaceMethod java/util/List.add:(Ljava/lang/Object;)Z
      66: pop
      67: aload_2
      68: aload         4
      70: invokeinterface #25,  2           // InterfaceMethod org/apache/dubbo/remoting/api/pu/ChannelOperator.configChannelHandler:(Ljava/util/List;)V
      75: return
}
