Compiled from "NotifyListener.java"
public class com.alibaba.dubbo.registry.NotifyListener$ReverseCompatibleNotifyListener implements org.apache.dubbo.registry.NotifyListener {
  private com.alibaba.dubbo.registry.NotifyListener listener;

  public com.alibaba.dubbo.registry.NotifyListener$ReverseCompatibleNotifyListener(com.alibaba.dubbo.registry.NotifyListener);
    Code:
       0: aload_0
       1: invokespecial #1                  // Method java/lang/Object."<init>":()V
       4: aload_0
       5: aload_1
       6: putfield      #2                  // Field listener:Lcom/alibaba/dubbo/registry/NotifyListener;
       9: return

  public void notify(java.util.List<org.apache.dubbo.common.URL>);
    Code:
       0: aload_0
       1: getfield      #2                  // Field listener:Lcom/alibaba/dubbo/registry/NotifyListener;
       4: ifnull        43
       7: aload_0
       8: getfield      #2                  // Field listener:Lcom/alibaba/dubbo/registry/NotifyListener;
      11: aload_1
      12: invokeinterface #3,  1            // InterfaceMethod java/util/List.stream:()Ljava/util/stream/Stream;
      17: invokedynamic #4,  0              // InvokeDynamic #0:apply:()Ljava/util/function/Function;
      22: invokeinterface #5,  2            // InterfaceMethod java/util/stream/Stream.map:(Ljava/util/function/Function;)Ljava/util/stream/Stream;
      27: invokestatic  #6                  // Method java/util/stream/Collectors.toList:()Ljava/util/stream/Collector;
      30: invokeinterface #7,  2            // InterfaceMethod java/util/stream/Stream.collect:(Ljava/util/stream/Collector;)Ljava/lang/Object;
      35: checkcast     #8                  // class java/util/List
      38: invokeinterface #9,  2            // InterfaceMethod com/alibaba/dubbo/registry/NotifyListener.notify:(Ljava/util/List;)V
      43: return

  private static com.alibaba.dubbo.common.URL lambda$notify$0(org.apache.dubbo.common.URL);
    Code:
       0: new           #10                 // class com/alibaba/dubbo/common/URL
       3: dup
       4: aload_0
       5: invokespecial #11                 // Method com/alibaba/dubbo/common/URL."<init>":(Lorg/apache/dubbo/common/URL;)V
       8: areturn
}
