Compiled from "Registry.java"
public interface com.alibaba.dubbo.registry.Registry extends org.apache.dubbo.registry.Registry {
  public abstract com.alibaba.dubbo.common.URL getUrl();

  public abstract void register(com.alibaba.dubbo.common.URL);

  public abstract void unregister(com.alibaba.dubbo.common.URL);

  public abstract void subscribe(com.alibaba.dubbo.common.URL, com.alibaba.dubbo.registry.NotifyListener);

  public abstract void unsubscribe(com.alibaba.dubbo.common.URL, com.alibaba.dubbo.registry.NotifyListener);

  public abstract java.util.List<com.alibaba.dubbo.common.URL> lookup(com.alibaba.dubbo.common.URL);

  public default void register(org.apache.dubbo.common.URL);
    Code:
       0: aload_0
       1: new           #1                  // class com/alibaba/dubbo/common/URL
       4: dup
       5: aload_1
       6: invokespecial #2                  // Method com/alibaba/dubbo/common/URL."<init>":(Lorg/apache/dubbo/common/URL;)V
       9: invokeinterface #3,  2            // InterfaceMethod register:(Lcom/alibaba/dubbo/common/URL;)V
      14: return

  public default void unregister(org.apache.dubbo.common.URL);
    Code:
       0: aload_0
       1: new           #1                  // class com/alibaba/dubbo/common/URL
       4: dup
       5: aload_1
       6: invokespecial #2                  // Method com/alibaba/dubbo/common/URL."<init>":(Lorg/apache/dubbo/common/URL;)V
       9: invokeinterface #4,  2            // InterfaceMethod unregister:(Lcom/alibaba/dubbo/common/URL;)V
      14: return

  public default void subscribe(org.apache.dubbo.common.URL, org.apache.dubbo.registry.NotifyListener);
    Code:
       0: aload_0
       1: new           #1                  // class com/alibaba/dubbo/common/URL
       4: dup
       5: aload_1
       6: invokespecial #2                  // Method com/alibaba/dubbo/common/URL."<init>":(Lorg/apache/dubbo/common/URL;)V
       9: new           #5                  // class com/alibaba/dubbo/registry/NotifyListener$CompatibleNotifyListener
      12: dup
      13: aload_2
      14: invokespecial #6                  // Method com/alibaba/dubbo/registry/NotifyListener$CompatibleNotifyListener."<init>":(Lorg/apache/dubbo/registry/NotifyListener;)V
      17: invokeinterface #7,  3            // InterfaceMethod subscribe:(Lcom/alibaba/dubbo/common/URL;Lcom/alibaba/dubbo/registry/NotifyListener;)V
      22: return

  public default void unsubscribe(org.apache.dubbo.common.URL, org.apache.dubbo.registry.NotifyListener);
    Code:
       0: aload_0
       1: new           #1                  // class com/alibaba/dubbo/common/URL
       4: dup
       5: aload_1
       6: invokespecial #2                  // Method com/alibaba/dubbo/common/URL."<init>":(Lorg/apache/dubbo/common/URL;)V
       9: new           #5                  // class com/alibaba/dubbo/registry/NotifyListener$CompatibleNotifyListener
      12: dup
      13: aload_2
      14: invokespecial #6                  // Method com/alibaba/dubbo/registry/NotifyListener$CompatibleNotifyListener."<init>":(Lorg/apache/dubbo/registry/NotifyListener;)V
      17: invokeinterface #8,  3            // InterfaceMethod unsubscribe:(Lcom/alibaba/dubbo/common/URL;Lcom/alibaba/dubbo/registry/NotifyListener;)V
      22: return

  public default java.util.List<org.apache.dubbo.common.URL> lookup(org.apache.dubbo.common.URL);
    Code:
       0: aload_0
       1: new           #1                  // class com/alibaba/dubbo/common/URL
       4: dup
       5: aload_1
       6: invokespecial #2                  // Method com/alibaba/dubbo/common/URL."<init>":(Lorg/apache/dubbo/common/URL;)V
       9: invokeinterface #9,  2            // InterfaceMethod lookup:(Lcom/alibaba/dubbo/common/URL;)Ljava/util/List;
      14: invokeinterface #10,  1           // InterfaceMethod java/util/List.stream:()Ljava/util/stream/Stream;
      19: invokedynamic #11,  0             // InvokeDynamic #0:apply:()Ljava/util/function/Function;
      24: invokeinterface #12,  2           // InterfaceMethod java/util/stream/Stream.map:(Ljava/util/function/Function;)Ljava/util/stream/Stream;
      29: invokestatic  #13                 // Method java/util/stream/Collectors.toList:()Ljava/util/stream/Collector;
      32: invokeinterface #14,  2           // InterfaceMethod java/util/stream/Stream.collect:(Ljava/util/stream/Collector;)Ljava/lang/Object;
      37: checkcast     #15                 // class java/util/List
      40: areturn

  public default org.apache.dubbo.common.URL getUrl();
    Code:
       0: aload_0
       1: invokeinterface #16,  1           // InterfaceMethod getUrl:()Lcom/alibaba/dubbo/common/URL;
       6: areturn

  private static org.apache.dubbo.common.URL lambda$lookup$0(com.alibaba.dubbo.common.URL);
    Code:
       0: aload_0
       1: invokevirtual #17                 // Method com/alibaba/dubbo/common/URL.getOriginalURL:()Lorg/apache/dubbo/common/URL;
       4: areturn
}
