Compiled from "RxJavaPlugins.java"
public final class io.reactivex.rxjava3.plugins.RxJavaPlugins {
  static volatile io.reactivex.rxjava3.functions.Consumer<? super java.lang.Throwable> errorHandler;

  static volatile io.reactivex.rxjava3.functions.Function<? super java.lang.Runnable, ? extends java.lang.Runnable> onScheduleHandler;

  static volatile io.reactivex.rxjava3.functions.Function<? super io.reactivex.rxjava3.functions.Supplier<io.reactivex.rxjava3.core.Scheduler>, ? extends io.reactivex.rxjava3.core.Scheduler> onInitComputationHandler;

  static volatile io.reactivex.rxjava3.functions.Function<? super io.reactivex.rxjava3.functions.Supplier<io.reactivex.rxjava3.core.Scheduler>, ? extends io.reactivex.rxjava3.core.Scheduler> onInitSingleHandler;

  static volatile io.reactivex.rxjava3.functions.Function<? super io.reactivex.rxjava3.functions.Supplier<io.reactivex.rxjava3.core.Scheduler>, ? extends io.reactivex.rxjava3.core.Scheduler> onInitIoHandler;

  static volatile io.reactivex.rxjava3.functions.Function<? super io.reactivex.rxjava3.functions.Supplier<io.reactivex.rxjava3.core.Scheduler>, ? extends io.reactivex.rxjava3.core.Scheduler> onInitNewThreadHandler;

  static volatile io.reactivex.rxjava3.functions.Function<? super io.reactivex.rxjava3.core.Scheduler, ? extends io.reactivex.rxjava3.core.Scheduler> onComputationHandler;

  static volatile io.reactivex.rxjava3.functions.Function<? super io.reactivex.rxjava3.core.Scheduler, ? extends io.reactivex.rxjava3.core.Scheduler> onSingleHandler;

  static volatile io.reactivex.rxjava3.functions.Function<? super io.reactivex.rxjava3.core.Scheduler, ? extends io.reactivex.rxjava3.core.Scheduler> onIoHandler;

  static volatile io.reactivex.rxjava3.functions.Function<? super io.reactivex.rxjava3.core.Scheduler, ? extends io.reactivex.rxjava3.core.Scheduler> onNewThreadHandler;

  static volatile io.reactivex.rxjava3.functions.Function<? super io.reactivex.rxjava3.core.Flowable, ? extends io.reactivex.rxjava3.core.Flowable> onFlowableAssembly;

  static volatile io.reactivex.rxjava3.functions.Function<? super io.reactivex.rxjava3.flowables.ConnectableFlowable, ? extends io.reactivex.rxjava3.flowables.ConnectableFlowable> onConnectableFlowableAssembly;

  static volatile io.reactivex.rxjava3.functions.Function<? super io.reactivex.rxjava3.core.Observable, ? extends io.reactivex.rxjava3.core.Observable> onObservableAssembly;

  static volatile io.reactivex.rxjava3.functions.Function<? super io.reactivex.rxjava3.observables.ConnectableObservable, ? extends io.reactivex.rxjava3.observables.ConnectableObservable> onConnectableObservableAssembly;

  static volatile io.reactivex.rxjava3.functions.Function<? super io.reactivex.rxjava3.core.Maybe, ? extends io.reactivex.rxjava3.core.Maybe> onMaybeAssembly;

  static volatile io.reactivex.rxjava3.functions.Function<? super io.reactivex.rxjava3.core.Single, ? extends io.reactivex.rxjava3.core.Single> onSingleAssembly;

  static volatile io.reactivex.rxjava3.functions.Function<? super io.reactivex.rxjava3.core.Completable, ? extends io.reactivex.rxjava3.core.Completable> onCompletableAssembly;

  static volatile io.reactivex.rxjava3.functions.Function<? super io.reactivex.rxjava3.parallel.ParallelFlowable, ? extends io.reactivex.rxjava3.parallel.ParallelFlowable> onParallelAssembly;

  static volatile io.reactivex.rxjava3.functions.BiFunction<? super io.reactivex.rxjava3.core.Flowable, ? super org.reactivestreams.Subscriber, ? extends org.reactivestreams.Subscriber> onFlowableSubscribe;

  static volatile io.reactivex.rxjava3.functions.BiFunction<? super io.reactivex.rxjava3.core.Maybe, ? super io.reactivex.rxjava3.core.MaybeObserver, ? extends io.reactivex.rxjava3.core.MaybeObserver> onMaybeSubscribe;

  static volatile io.reactivex.rxjava3.functions.BiFunction<? super io.reactivex.rxjava3.core.Observable, ? super io.reactivex.rxjava3.core.Observer, ? extends io.reactivex.rxjava3.core.Observer> onObservableSubscribe;

  static volatile io.reactivex.rxjava3.functions.BiFunction<? super io.reactivex.rxjava3.core.Single, ? super io.reactivex.rxjava3.core.SingleObserver, ? extends io.reactivex.rxjava3.core.SingleObserver> onSingleSubscribe;

  static volatile io.reactivex.rxjava3.functions.BiFunction<? super io.reactivex.rxjava3.core.Completable, ? super io.reactivex.rxjava3.core.CompletableObserver, ? extends io.reactivex.rxjava3.core.CompletableObserver> onCompletableSubscribe;

  static volatile io.reactivex.rxjava3.functions.BiFunction<? super io.reactivex.rxjava3.parallel.ParallelFlowable, ? super org.reactivestreams.Subscriber[], ? extends org.reactivestreams.Subscriber[]> onParallelSubscribe;

  static volatile io.reactivex.rxjava3.functions.BooleanSupplier onBeforeBlocking;

  static volatile boolean lockdown;

  static volatile boolean failNonBlockingScheduler;

  public static void lockdown();
    Code:
       0: iconst_1
       1: putstatic     #1                  // Field lockdown:Z
       4: return

  public static boolean isLockdown();
    Code:
       0: getstatic     #1                  // Field lockdown:Z
       3: ireturn

  public static void setFailOnNonBlockingScheduler(boolean);
    Code:
       0: getstatic     #1                  // Field lockdown:Z
       3: ifeq          16
       6: new           #2                  // class java/lang/IllegalStateException
       9: dup
      10: ldc           #3                  // String Plugins can\'t be changed anymore
      12: invokespecial #4                  // Method java/lang/IllegalStateException."<init>":(Ljava/lang/String;)V
      15: athrow
      16: iload_0
      17: putstatic     #5                  // Field failNonBlockingScheduler:Z
      20: return

  public static boolean isFailOnNonBlockingScheduler();
    Code:
       0: getstatic     #5                  // Field failNonBlockingScheduler:Z
       3: ireturn

  public static io.reactivex.rxjava3.functions.Function<? super io.reactivex.rxjava3.core.Scheduler, ? extends io.reactivex.rxjava3.core.Scheduler> getComputationSchedulerHandler();
    Code:
       0: getstatic     #6                  // Field onComputationHandler:Lio/reactivex/rxjava3/functions/Function;
       3: areturn

  public static io.reactivex.rxjava3.functions.Consumer<? super java.lang.Throwable> getErrorHandler();
    Code:
       0: getstatic     #7                  // Field errorHandler:Lio/reactivex/rxjava3/functions/Consumer;
       3: areturn

  public static io.reactivex.rxjava3.functions.Function<? super io.reactivex.rxjava3.functions.Supplier<io.reactivex.rxjava3.core.Scheduler>, ? extends io.reactivex.rxjava3.core.Scheduler> getInitComputationSchedulerHandler();
    Code:
       0: getstatic     #8                  // Field onInitComputationHandler:Lio/reactivex/rxjava3/functions/Function;
       3: areturn

  public static io.reactivex.rxjava3.functions.Function<? super io.reactivex.rxjava3.functions.Supplier<io.reactivex.rxjava3.core.Scheduler>, ? extends io.reactivex.rxjava3.core.Scheduler> getInitIoSchedulerHandler();
    Code:
       0: getstatic     #9                  // Field onInitIoHandler:Lio/reactivex/rxjava3/functions/Function;
       3: areturn

  public static io.reactivex.rxjava3.functions.Function<? super io.reactivex.rxjava3.functions.Supplier<io.reactivex.rxjava3.core.Scheduler>, ? extends io.reactivex.rxjava3.core.Scheduler> getInitNewThreadSchedulerHandler();
    Code:
       0: getstatic     #10                 // Field onInitNewThreadHandler:Lio/reactivex/rxjava3/functions/Function;
       3: areturn

  public static io.reactivex.rxjava3.functions.Function<? super io.reactivex.rxjava3.functions.Supplier<io.reactivex.rxjava3.core.Scheduler>, ? extends io.reactivex.rxjava3.core.Scheduler> getInitSingleSchedulerHandler();
    Code:
       0: getstatic     #11                 // Field onInitSingleHandler:Lio/reactivex/rxjava3/functions/Function;
       3: areturn

  public static io.reactivex.rxjava3.functions.Function<? super io.reactivex.rxjava3.core.Scheduler, ? extends io.reactivex.rxjava3.core.Scheduler> getIoSchedulerHandler();
    Code:
       0: getstatic     #12                 // Field onIoHandler:Lio/reactivex/rxjava3/functions/Function;
       3: areturn

  public static io.reactivex.rxjava3.functions.Function<? super io.reactivex.rxjava3.core.Scheduler, ? extends io.reactivex.rxjava3.core.Scheduler> getNewThreadSchedulerHandler();
    Code:
       0: getstatic     #13                 // Field onNewThreadHandler:Lio/reactivex/rxjava3/functions/Function;
       3: areturn

  public static io.reactivex.rxjava3.functions.Function<? super java.lang.Runnable, ? extends java.lang.Runnable> getScheduleHandler();
    Code:
       0: getstatic     #14                 // Field onScheduleHandler:Lio/reactivex/rxjava3/functions/Function;
       3: areturn

  public static io.reactivex.rxjava3.functions.Function<? super io.reactivex.rxjava3.core.Scheduler, ? extends io.reactivex.rxjava3.core.Scheduler> getSingleSchedulerHandler();
    Code:
       0: getstatic     #15                 // Field onSingleHandler:Lio/reactivex/rxjava3/functions/Function;
       3: areturn

  public static io.reactivex.rxjava3.core.Scheduler initComputationScheduler(io.reactivex.rxjava3.functions.Supplier<io.reactivex.rxjava3.core.Scheduler>);
    Code:
       0: aload_0
       1: ldc           #16                 // String Scheduler Supplier can\'t be null
       3: invokestatic  #17                 // Method java/util/Objects.requireNonNull:(Ljava/lang/Object;Ljava/lang/String;)Ljava/lang/Object;
       6: pop
       7: getstatic     #8                  // Field onInitComputationHandler:Lio/reactivex/rxjava3/functions/Function;
      10: astore_1
      11: aload_1
      12: ifnonnull     20
      15: aload_0
      16: invokestatic  #18                 // Method callRequireNonNull:(Lio/reactivex/rxjava3/functions/Supplier;)Lio/reactivex/rxjava3/core/Scheduler;
      19: areturn
      20: aload_1
      21: aload_0
      22: invokestatic  #19                 // Method applyRequireNonNull:(Lio/reactivex/rxjava3/functions/Function;Lio/reactivex/rxjava3/functions/Supplier;)Lio/reactivex/rxjava3/core/Scheduler;
      25: areturn

  public static io.reactivex.rxjava3.core.Scheduler initIoScheduler(io.reactivex.rxjava3.functions.Supplier<io.reactivex.rxjava3.core.Scheduler>);
    Code:
       0: aload_0
       1: ldc           #16                 // String Scheduler Supplier can\'t be null
       3: invokestatic  #17                 // Method java/util/Objects.requireNonNull:(Ljava/lang/Object;Ljava/lang/String;)Ljava/lang/Object;
       6: pop
       7: getstatic     #9                  // Field onInitIoHandler:Lio/reactivex/rxjava3/functions/Function;
      10: astore_1
      11: aload_1
      12: ifnonnull     20
      15: aload_0
      16: invokestatic  #18                 // Method callRequireNonNull:(Lio/reactivex/rxjava3/functions/Supplier;)Lio/reactivex/rxjava3/core/Scheduler;
      19: areturn
      20: aload_1
      21: aload_0
      22: invokestatic  #19                 // Method applyRequireNonNull:(Lio/reactivex/rxjava3/functions/Function;Lio/reactivex/rxjava3/functions/Supplier;)Lio/reactivex/rxjava3/core/Scheduler;
      25: areturn

  public static io.reactivex.rxjava3.core.Scheduler initNewThreadScheduler(io.reactivex.rxjava3.functions.Supplier<io.reactivex.rxjava3.core.Scheduler>);
    Code:
       0: aload_0
       1: ldc           #16                 // String Scheduler Supplier can\'t be null
       3: invokestatic  #17                 // Method java/util/Objects.requireNonNull:(Ljava/lang/Object;Ljava/lang/String;)Ljava/lang/Object;
       6: pop
       7: getstatic     #10                 // Field onInitNewThreadHandler:Lio/reactivex/rxjava3/functions/Function;
      10: astore_1
      11: aload_1
      12: ifnonnull     20
      15: aload_0
      16: invokestatic  #18                 // Method callRequireNonNull:(Lio/reactivex/rxjava3/functions/Supplier;)Lio/reactivex/rxjava3/core/Scheduler;
      19: areturn
      20: aload_1
      21: aload_0
      22: invokestatic  #19                 // Method applyRequireNonNull:(Lio/reactivex/rxjava3/functions/Function;Lio/reactivex/rxjava3/functions/Supplier;)Lio/reactivex/rxjava3/core/Scheduler;
      25: areturn

  public static io.reactivex.rxjava3.core.Scheduler initSingleScheduler(io.reactivex.rxjava3.functions.Supplier<io.reactivex.rxjava3.core.Scheduler>);
    Code:
       0: aload_0
       1: ldc           #16                 // String Scheduler Supplier can\'t be null
       3: invokestatic  #17                 // Method java/util/Objects.requireNonNull:(Ljava/lang/Object;Ljava/lang/String;)Ljava/lang/Object;
       6: pop
       7: getstatic     #11                 // Field onInitSingleHandler:Lio/reactivex/rxjava3/functions/Function;
      10: astore_1
      11: aload_1
      12: ifnonnull     20
      15: aload_0
      16: invokestatic  #18                 // Method callRequireNonNull:(Lio/reactivex/rxjava3/functions/Supplier;)Lio/reactivex/rxjava3/core/Scheduler;
      19: areturn
      20: aload_1
      21: aload_0
      22: invokestatic  #19                 // Method applyRequireNonNull:(Lio/reactivex/rxjava3/functions/Function;Lio/reactivex/rxjava3/functions/Supplier;)Lio/reactivex/rxjava3/core/Scheduler;
      25: areturn

  public static io.reactivex.rxjava3.core.Scheduler onComputationScheduler(io.reactivex.rxjava3.core.Scheduler);
    Code:
       0: getstatic     #6                  // Field onComputationHandler:Lio/reactivex/rxjava3/functions/Function;
       3: astore_1
       4: aload_1
       5: ifnonnull     10
       8: aload_0
       9: areturn
      10: aload_1
      11: aload_0
      12: invokestatic  #20                 // Method apply:(Lio/reactivex/rxjava3/functions/Function;Ljava/lang/Object;)Ljava/lang/Object;
      15: checkcast     #21                 // class io/reactivex/rxjava3/core/Scheduler
      18: areturn

  public static void onError(java.lang.Throwable);
    Code:
       0: getstatic     #7                  // Field errorHandler:Lio/reactivex/rxjava3/functions/Consumer;
       3: astore_1
       4: aload_0
       5: ifnonnull     17
       8: ldc           #22                 // String onError called with a null Throwable.
      10: invokestatic  #23                 // Method io/reactivex/rxjava3/internal/util/ExceptionHelper.createNullPointerException:(Ljava/lang/String;)Ljava/lang/NullPointerException;
      13: astore_0
      14: goto          33
      17: aload_0
      18: invokestatic  #24                 // Method isBug:(Ljava/lang/Throwable;)Z
      21: ifne          33
      24: new           #25                 // class io/reactivex/rxjava3/exceptions/UndeliverableException
      27: dup
      28: aload_0
      29: invokespecial #26                 // Method io/reactivex/rxjava3/exceptions/UndeliverableException."<init>":(Ljava/lang/Throwable;)V
      32: astore_0
      33: aload_1
      34: ifnull        54
      37: aload_1
      38: aload_0
      39: invokeinterface #27,  2           // InterfaceMethod io/reactivex/rxjava3/functions/Consumer.accept:(Ljava/lang/Object;)V
      44: return
      45: astore_2
      46: aload_2
      47: invokevirtual #29                 // Method java/lang/Throwable.printStackTrace:()V
      50: aload_2
      51: invokestatic  #30                 // Method uncaught:(Ljava/lang/Throwable;)V
      54: aload_0
      55: invokevirtual #29                 // Method java/lang/Throwable.printStackTrace:()V
      58: aload_0
      59: invokestatic  #30                 // Method uncaught:(Ljava/lang/Throwable;)V
      62: return
    Exception table:
       from    to  target type
          37    44    45   Class java/lang/Throwable

  static boolean isBug(java.lang.Throwable);
    Code:
       0: aload_0
       1: instanceof    #31                 // class io/reactivex/rxjava3/exceptions/OnErrorNotImplementedException
       4: ifeq          9
       7: iconst_1
       8: ireturn
       9: aload_0
      10: instanceof    #32                 // class io/reactivex/rxjava3/exceptions/MissingBackpressureException
      13: ifeq          18
      16: iconst_1
      17: ireturn
      18: aload_0
      19: instanceof    #33                 // class io/reactivex/rxjava3/exceptions/QueueOverflowException
      22: ifeq          27
      25: iconst_1
      26: ireturn
      27: aload_0
      28: instanceof    #2                  // class java/lang/IllegalStateException
      31: ifeq          36
      34: iconst_1
      35: ireturn
      36: aload_0
      37: instanceof    #34                 // class java/lang/NullPointerException
      40: ifeq          45
      43: iconst_1
      44: ireturn
      45: aload_0
      46: instanceof    #35                 // class java/lang/IllegalArgumentException
      49: ifeq          54
      52: iconst_1
      53: ireturn
      54: aload_0
      55: instanceof    #36                 // class io/reactivex/rxjava3/exceptions/CompositeException
      58: ifeq          63
      61: iconst_1
      62: ireturn
      63: iconst_0
      64: ireturn

  static void uncaught(java.lang.Throwable);
    Code:
       0: invokestatic  #37                 // Method java/lang/Thread.currentThread:()Ljava/lang/Thread;
       3: astore_1
       4: aload_1
       5: invokevirtual #38                 // Method java/lang/Thread.getUncaughtExceptionHandler:()Ljava/lang/Thread$UncaughtExceptionHandler;
       8: astore_2
       9: aload_2
      10: aload_1
      11: aload_0
      12: invokeinterface #39,  3           // InterfaceMethod java/lang/Thread$UncaughtExceptionHandler.uncaughtException:(Ljava/lang/Thread;Ljava/lang/Throwable;)V
      17: return

  public static io.reactivex.rxjava3.core.Scheduler onIoScheduler(io.reactivex.rxjava3.core.Scheduler);
    Code:
       0: getstatic     #12                 // Field onIoHandler:Lio/reactivex/rxjava3/functions/Function;
       3: astore_1
       4: aload_1
       5: ifnonnull     10
       8: aload_0
       9: areturn
      10: aload_1
      11: aload_0
      12: invokestatic  #20                 // Method apply:(Lio/reactivex/rxjava3/functions/Function;Ljava/lang/Object;)Ljava/lang/Object;
      15: checkcast     #40                 // class io/reactivex/rxjava3/core/Scheduler
      18: areturn

  public static io.reactivex.rxjava3.core.Scheduler onNewThreadScheduler(io.reactivex.rxjava3.core.Scheduler);
    Code:
       0: getstatic     #13                 // Field onNewThreadHandler:Lio/reactivex/rxjava3/functions/Function;
       3: astore_1
       4: aload_1
       5: ifnonnull     10
       8: aload_0
       9: areturn
      10: aload_1
      11: aload_0
      12: invokestatic  #20                 // Method apply:(Lio/reactivex/rxjava3/functions/Function;Ljava/lang/Object;)Ljava/lang/Object;
      15: checkcast     #41                 // class io/reactivex/rxjava3/core/Scheduler
      18: areturn

  public static java.lang.Runnable onSchedule(java.lang.Runnable);
    Code:
       0: aload_0
       1: ldc           #42                 // String run is null
       3: invokestatic  #17                 // Method java/util/Objects.requireNonNull:(Ljava/lang/Object;Ljava/lang/String;)Ljava/lang/Object;
       6: pop
       7: getstatic     #14                 // Field onScheduleHandler:Lio/reactivex/rxjava3/functions/Function;
      10: astore_1
      11: aload_1
      12: ifnonnull     17
      15: aload_0
      16: areturn
      17: aload_1
      18: aload_0
      19: invokestatic  #20                 // Method apply:(Lio/reactivex/rxjava3/functions/Function;Ljava/lang/Object;)Ljava/lang/Object;
      22: checkcast     #43                 // class java/lang/Runnable
      25: areturn

  public static io.reactivex.rxjava3.core.Scheduler onSingleScheduler(io.reactivex.rxjava3.core.Scheduler);
    Code:
       0: getstatic     #15                 // Field onSingleHandler:Lio/reactivex/rxjava3/functions/Function;
       3: astore_1
       4: aload_1
       5: ifnonnull     10
       8: aload_0
       9: areturn
      10: aload_1
      11: aload_0
      12: invokestatic  #20                 // Method apply:(Lio/reactivex/rxjava3/functions/Function;Ljava/lang/Object;)Ljava/lang/Object;
      15: checkcast     #44                 // class io/reactivex/rxjava3/core/Scheduler
      18: areturn

  public static void reset();
    Code:
       0: aconst_null
       1: invokestatic  #45                 // Method setErrorHandler:(Lio/reactivex/rxjava3/functions/Consumer;)V
       4: aconst_null
       5: invokestatic  #46                 // Method setScheduleHandler:(Lio/reactivex/rxjava3/functions/Function;)V
       8: aconst_null
       9: invokestatic  #47                 // Method setComputationSchedulerHandler:(Lio/reactivex/rxjava3/functions/Function;)V
      12: aconst_null
      13: invokestatic  #48                 // Method setInitComputationSchedulerHandler:(Lio/reactivex/rxjava3/functions/Function;)V
      16: aconst_null
      17: invokestatic  #49                 // Method setIoSchedulerHandler:(Lio/reactivex/rxjava3/functions/Function;)V
      20: aconst_null
      21: invokestatic  #50                 // Method setInitIoSchedulerHandler:(Lio/reactivex/rxjava3/functions/Function;)V
      24: aconst_null
      25: invokestatic  #51                 // Method setSingleSchedulerHandler:(Lio/reactivex/rxjava3/functions/Function;)V
      28: aconst_null
      29: invokestatic  #52                 // Method setInitSingleSchedulerHandler:(Lio/reactivex/rxjava3/functions/Function;)V
      32: aconst_null
      33: invokestatic  #53                 // Method setNewThreadSchedulerHandler:(Lio/reactivex/rxjava3/functions/Function;)V
      36: aconst_null
      37: invokestatic  #54                 // Method setInitNewThreadSchedulerHandler:(Lio/reactivex/rxjava3/functions/Function;)V
      40: aconst_null
      41: invokestatic  #55                 // Method setOnFlowableAssembly:(Lio/reactivex/rxjava3/functions/Function;)V
      44: aconst_null
      45: invokestatic  #56                 // Method setOnFlowableSubscribe:(Lio/reactivex/rxjava3/functions/BiFunction;)V
      48: aconst_null
      49: invokestatic  #57                 // Method setOnObservableAssembly:(Lio/reactivex/rxjava3/functions/Function;)V
      52: aconst_null
      53: invokestatic  #58                 // Method setOnObservableSubscribe:(Lio/reactivex/rxjava3/functions/BiFunction;)V
      56: aconst_null
      57: invokestatic  #59                 // Method setOnSingleAssembly:(Lio/reactivex/rxjava3/functions/Function;)V
      60: aconst_null
      61: invokestatic  #60                 // Method setOnSingleSubscribe:(Lio/reactivex/rxjava3/functions/BiFunction;)V
      64: aconst_null
      65: invokestatic  #61                 // Method setOnCompletableAssembly:(Lio/reactivex/rxjava3/functions/Function;)V
      68: aconst_null
      69: invokestatic  #62                 // Method setOnCompletableSubscribe:(Lio/reactivex/rxjava3/functions/BiFunction;)V
      72: aconst_null
      73: invokestatic  #63                 // Method setOnConnectableFlowableAssembly:(Lio/reactivex/rxjava3/functions/Function;)V
      76: aconst_null
      77: invokestatic  #64                 // Method setOnConnectableObservableAssembly:(Lio/reactivex/rxjava3/functions/Function;)V
      80: aconst_null
      81: invokestatic  #65                 // Method setOnMaybeAssembly:(Lio/reactivex/rxjava3/functions/Function;)V
      84: aconst_null
      85: invokestatic  #66                 // Method setOnMaybeSubscribe:(Lio/reactivex/rxjava3/functions/BiFunction;)V
      88: aconst_null
      89: invokestatic  #67                 // Method setOnParallelAssembly:(Lio/reactivex/rxjava3/functions/Function;)V
      92: aconst_null
      93: invokestatic  #68                 // Method setOnParallelSubscribe:(Lio/reactivex/rxjava3/functions/BiFunction;)V
      96: iconst_0
      97: invokestatic  #69                 // Method setFailOnNonBlockingScheduler:(Z)V
     100: aconst_null
     101: invokestatic  #70                 // Method setOnBeforeBlocking:(Lio/reactivex/rxjava3/functions/BooleanSupplier;)V
     104: return

  public static void setComputationSchedulerHandler(io.reactivex.rxjava3.functions.Function<? super io.reactivex.rxjava3.core.Scheduler, ? extends io.reactivex.rxjava3.core.Scheduler>);
    Code:
       0: getstatic     #1                  // Field lockdown:Z
       3: ifeq          16
       6: new           #2                  // class java/lang/IllegalStateException
       9: dup
      10: ldc           #3                  // String Plugins can\'t be changed anymore
      12: invokespecial #4                  // Method java/lang/IllegalStateException."<init>":(Ljava/lang/String;)V
      15: athrow
      16: aload_0
      17: putstatic     #6                  // Field onComputationHandler:Lio/reactivex/rxjava3/functions/Function;
      20: return

  public static void setErrorHandler(io.reactivex.rxjava3.functions.Consumer<? super java.lang.Throwable>);
    Code:
       0: getstatic     #1                  // Field lockdown:Z
       3: ifeq          16
       6: new           #2                  // class java/lang/IllegalStateException
       9: dup
      10: ldc           #3                  // String Plugins can\'t be changed anymore
      12: invokespecial #4                  // Method java/lang/IllegalStateException."<init>":(Ljava/lang/String;)V
      15: athrow
      16: aload_0
      17: putstatic     #7                  // Field errorHandler:Lio/reactivex/rxjava3/functions/Consumer;
      20: return

  public static void setInitComputationSchedulerHandler(io.reactivex.rxjava3.functions.Function<? super io.reactivex.rxjava3.functions.Supplier<io.reactivex.rxjava3.core.Scheduler>, ? extends io.reactivex.rxjava3.core.Scheduler>);
    Code:
       0: getstatic     #1                  // Field lockdown:Z
       3: ifeq          16
       6: new           #2                  // class java/lang/IllegalStateException
       9: dup
      10: ldc           #3                  // String Plugins can\'t be changed anymore
      12: invokespecial #4                  // Method java/lang/IllegalStateException."<init>":(Ljava/lang/String;)V
      15: athrow
      16: aload_0
      17: putstatic     #8                  // Field onInitComputationHandler:Lio/reactivex/rxjava3/functions/Function;
      20: return

  public static void setInitIoSchedulerHandler(io.reactivex.rxjava3.functions.Function<? super io.reactivex.rxjava3.functions.Supplier<io.reactivex.rxjava3.core.Scheduler>, ? extends io.reactivex.rxjava3.core.Scheduler>);
    Code:
       0: getstatic     #1                  // Field lockdown:Z
       3: ifeq          16
       6: new           #2                  // class java/lang/IllegalStateException
       9: dup
      10: ldc           #3                  // String Plugins can\'t be changed anymore
      12: invokespecial #4                  // Method java/lang/IllegalStateException."<init>":(Ljava/lang/String;)V
      15: athrow
      16: aload_0
      17: putstatic     #9                  // Field onInitIoHandler:Lio/reactivex/rxjava3/functions/Function;
      20: return

  public static void setInitNewThreadSchedulerHandler(io.reactivex.rxjava3.functions.Function<? super io.reactivex.rxjava3.functions.Supplier<io.reactivex.rxjava3.core.Scheduler>, ? extends io.reactivex.rxjava3.core.Scheduler>);
    Code:
       0: getstatic     #1                  // Field lockdown:Z
       3: ifeq          16
       6: new           #2                  // class java/lang/IllegalStateException
       9: dup
      10: ldc           #3                  // String Plugins can\'t be changed anymore
      12: invokespecial #4                  // Method java/lang/IllegalStateException."<init>":(Ljava/lang/String;)V
      15: athrow
      16: aload_0
      17: putstatic     #10                 // Field onInitNewThreadHandler:Lio/reactivex/rxjava3/functions/Function;
      20: return

  public static void setInitSingleSchedulerHandler(io.reactivex.rxjava3.functions.Function<? super io.reactivex.rxjava3.functions.Supplier<io.reactivex.rxjava3.core.Scheduler>, ? extends io.reactivex.rxjava3.core.Scheduler>);
    Code:
       0: getstatic     #1                  // Field lockdown:Z
       3: ifeq          16
       6: new           #2                  // class java/lang/IllegalStateException
       9: dup
      10: ldc           #3                  // String Plugins can\'t be changed anymore
      12: invokespecial #4                  // Method java/lang/IllegalStateException."<init>":(Ljava/lang/String;)V
      15: athrow
      16: aload_0
      17: putstatic     #11                 // Field onInitSingleHandler:Lio/reactivex/rxjava3/functions/Function;
      20: return

  public static void setIoSchedulerHandler(io.reactivex.rxjava3.functions.Function<? super io.reactivex.rxjava3.core.Scheduler, ? extends io.reactivex.rxjava3.core.Scheduler>);
    Code:
       0: getstatic     #1                  // Field lockdown:Z
       3: ifeq          16
       6: new           #2                  // class java/lang/IllegalStateException
       9: dup
      10: ldc           #3                  // String Plugins can\'t be changed anymore
      12: invokespecial #4                  // Method java/lang/IllegalStateException."<init>":(Ljava/lang/String;)V
      15: athrow
      16: aload_0
      17: putstatic     #12                 // Field onIoHandler:Lio/reactivex/rxjava3/functions/Function;
      20: return

  public static void setNewThreadSchedulerHandler(io.reactivex.rxjava3.functions.Function<? super io.reactivex.rxjava3.core.Scheduler, ? extends io.reactivex.rxjava3.core.Scheduler>);
    Code:
       0: getstatic     #1                  // Field lockdown:Z
       3: ifeq          16
       6: new           #2                  // class java/lang/IllegalStateException
       9: dup
      10: ldc           #3                  // String Plugins can\'t be changed anymore
      12: invokespecial #4                  // Method java/lang/IllegalStateException."<init>":(Ljava/lang/String;)V
      15: athrow
      16: aload_0
      17: putstatic     #13                 // Field onNewThreadHandler:Lio/reactivex/rxjava3/functions/Function;
      20: return

  public static void setScheduleHandler(io.reactivex.rxjava3.functions.Function<? super java.lang.Runnable, ? extends java.lang.Runnable>);
    Code:
       0: getstatic     #1                  // Field lockdown:Z
       3: ifeq          16
       6: new           #2                  // class java/lang/IllegalStateException
       9: dup
      10: ldc           #3                  // String Plugins can\'t be changed anymore
      12: invokespecial #4                  // Method java/lang/IllegalStateException."<init>":(Ljava/lang/String;)V
      15: athrow
      16: aload_0
      17: putstatic     #14                 // Field onScheduleHandler:Lio/reactivex/rxjava3/functions/Function;
      20: return

  public static void setSingleSchedulerHandler(io.reactivex.rxjava3.functions.Function<? super io.reactivex.rxjava3.core.Scheduler, ? extends io.reactivex.rxjava3.core.Scheduler>);
    Code:
       0: getstatic     #1                  // Field lockdown:Z
       3: ifeq          16
       6: new           #2                  // class java/lang/IllegalStateException
       9: dup
      10: ldc           #3                  // String Plugins can\'t be changed anymore
      12: invokespecial #4                  // Method java/lang/IllegalStateException."<init>":(Ljava/lang/String;)V
      15: athrow
      16: aload_0
      17: putstatic     #15                 // Field onSingleHandler:Lio/reactivex/rxjava3/functions/Function;
      20: return

  static void unlock();
    Code:
       0: iconst_0
       1: putstatic     #1                  // Field lockdown:Z
       4: return

  public static io.reactivex.rxjava3.functions.Function<? super io.reactivex.rxjava3.core.Completable, ? extends io.reactivex.rxjava3.core.Completable> getOnCompletableAssembly();
    Code:
       0: getstatic     #71                 // Field onCompletableAssembly:Lio/reactivex/rxjava3/functions/Function;
       3: areturn

  public static io.reactivex.rxjava3.functions.BiFunction<? super io.reactivex.rxjava3.core.Completable, ? super io.reactivex.rxjava3.core.CompletableObserver, ? extends io.reactivex.rxjava3.core.CompletableObserver> getOnCompletableSubscribe();
    Code:
       0: getstatic     #72                 // Field onCompletableSubscribe:Lio/reactivex/rxjava3/functions/BiFunction;
       3: areturn

  public static io.reactivex.rxjava3.functions.Function<? super io.reactivex.rxjava3.core.Flowable, ? extends io.reactivex.rxjava3.core.Flowable> getOnFlowableAssembly();
    Code:
       0: getstatic     #73                 // Field onFlowableAssembly:Lio/reactivex/rxjava3/functions/Function;
       3: areturn

  public static io.reactivex.rxjava3.functions.Function<? super io.reactivex.rxjava3.flowables.ConnectableFlowable, ? extends io.reactivex.rxjava3.flowables.ConnectableFlowable> getOnConnectableFlowableAssembly();
    Code:
       0: getstatic     #74                 // Field onConnectableFlowableAssembly:Lio/reactivex/rxjava3/functions/Function;
       3: areturn

  public static io.reactivex.rxjava3.functions.BiFunction<? super io.reactivex.rxjava3.core.Flowable, ? super org.reactivestreams.Subscriber, ? extends org.reactivestreams.Subscriber> getOnFlowableSubscribe();
    Code:
       0: getstatic     #75                 // Field onFlowableSubscribe:Lio/reactivex/rxjava3/functions/BiFunction;
       3: areturn

  public static io.reactivex.rxjava3.functions.BiFunction<? super io.reactivex.rxjava3.core.Maybe, ? super io.reactivex.rxjava3.core.MaybeObserver, ? extends io.reactivex.rxjava3.core.MaybeObserver> getOnMaybeSubscribe();
    Code:
       0: getstatic     #76                 // Field onMaybeSubscribe:Lio/reactivex/rxjava3/functions/BiFunction;
       3: areturn

  public static io.reactivex.rxjava3.functions.Function<? super io.reactivex.rxjava3.core.Maybe, ? extends io.reactivex.rxjava3.core.Maybe> getOnMaybeAssembly();
    Code:
       0: getstatic     #77                 // Field onMaybeAssembly:Lio/reactivex/rxjava3/functions/Function;
       3: areturn

  public static io.reactivex.rxjava3.functions.Function<? super io.reactivex.rxjava3.core.Single, ? extends io.reactivex.rxjava3.core.Single> getOnSingleAssembly();
    Code:
       0: getstatic     #78                 // Field onSingleAssembly:Lio/reactivex/rxjava3/functions/Function;
       3: areturn

  public static io.reactivex.rxjava3.functions.BiFunction<? super io.reactivex.rxjava3.core.Single, ? super io.reactivex.rxjava3.core.SingleObserver, ? extends io.reactivex.rxjava3.core.SingleObserver> getOnSingleSubscribe();
    Code:
       0: getstatic     #79                 // Field onSingleSubscribe:Lio/reactivex/rxjava3/functions/BiFunction;
       3: areturn

  public static io.reactivex.rxjava3.functions.Function<? super io.reactivex.rxjava3.core.Observable, ? extends io.reactivex.rxjava3.core.Observable> getOnObservableAssembly();
    Code:
       0: getstatic     #80                 // Field onObservableAssembly:Lio/reactivex/rxjava3/functions/Function;
       3: areturn

  public static io.reactivex.rxjava3.functions.Function<? super io.reactivex.rxjava3.observables.ConnectableObservable, ? extends io.reactivex.rxjava3.observables.ConnectableObservable> getOnConnectableObservableAssembly();
    Code:
       0: getstatic     #81                 // Field onConnectableObservableAssembly:Lio/reactivex/rxjava3/functions/Function;
       3: areturn

  public static io.reactivex.rxjava3.functions.BiFunction<? super io.reactivex.rxjava3.core.Observable, ? super io.reactivex.rxjava3.core.Observer, ? extends io.reactivex.rxjava3.core.Observer> getOnObservableSubscribe();
    Code:
       0: getstatic     #82                 // Field onObservableSubscribe:Lio/reactivex/rxjava3/functions/BiFunction;
       3: areturn

  public static void setOnCompletableAssembly(io.reactivex.rxjava3.functions.Function<? super io.reactivex.rxjava3.core.Completable, ? extends io.reactivex.rxjava3.core.Completable>);
    Code:
       0: getstatic     #1                  // Field lockdown:Z
       3: ifeq          16
       6: new           #2                  // class java/lang/IllegalStateException
       9: dup
      10: ldc           #3                  // String Plugins can\'t be changed anymore
      12: invokespecial #4                  // Method java/lang/IllegalStateException."<init>":(Ljava/lang/String;)V
      15: athrow
      16: aload_0
      17: putstatic     #71                 // Field onCompletableAssembly:Lio/reactivex/rxjava3/functions/Function;
      20: return

  public static void setOnCompletableSubscribe(io.reactivex.rxjava3.functions.BiFunction<? super io.reactivex.rxjava3.core.Completable, ? super io.reactivex.rxjava3.core.CompletableObserver, ? extends io.reactivex.rxjava3.core.CompletableObserver>);
    Code:
       0: getstatic     #1                  // Field lockdown:Z
       3: ifeq          16
       6: new           #2                  // class java/lang/IllegalStateException
       9: dup
      10: ldc           #3                  // String Plugins can\'t be changed anymore
      12: invokespecial #4                  // Method java/lang/IllegalStateException."<init>":(Ljava/lang/String;)V
      15: athrow
      16: aload_0
      17: putstatic     #72                 // Field onCompletableSubscribe:Lio/reactivex/rxjava3/functions/BiFunction;
      20: return

  public static void setOnFlowableAssembly(io.reactivex.rxjava3.functions.Function<? super io.reactivex.rxjava3.core.Flowable, ? extends io.reactivex.rxjava3.core.Flowable>);
    Code:
       0: getstatic     #1                  // Field lockdown:Z
       3: ifeq          16
       6: new           #2                  // class java/lang/IllegalStateException
       9: dup
      10: ldc           #3                  // String Plugins can\'t be changed anymore
      12: invokespecial #4                  // Method java/lang/IllegalStateException."<init>":(Ljava/lang/String;)V
      15: athrow
      16: aload_0
      17: putstatic     #73                 // Field onFlowableAssembly:Lio/reactivex/rxjava3/functions/Function;
      20: return

  public static void setOnMaybeAssembly(io.reactivex.rxjava3.functions.Function<? super io.reactivex.rxjava3.core.Maybe, ? extends io.reactivex.rxjava3.core.Maybe>);
    Code:
       0: getstatic     #1                  // Field lockdown:Z
       3: ifeq          16
       6: new           #2                  // class java/lang/IllegalStateException
       9: dup
      10: ldc           #3                  // String Plugins can\'t be changed anymore
      12: invokespecial #4                  // Method java/lang/IllegalStateException."<init>":(Ljava/lang/String;)V
      15: athrow
      16: aload_0
      17: putstatic     #77                 // Field onMaybeAssembly:Lio/reactivex/rxjava3/functions/Function;
      20: return

  public static void setOnConnectableFlowableAssembly(io.reactivex.rxjava3.functions.Function<? super io.reactivex.rxjava3.flowables.ConnectableFlowable, ? extends io.reactivex.rxjava3.flowables.ConnectableFlowable>);
    Code:
       0: getstatic     #1                  // Field lockdown:Z
       3: ifeq          16
       6: new           #2                  // class java/lang/IllegalStateException
       9: dup
      10: ldc           #3                  // String Plugins can\'t be changed anymore
      12: invokespecial #4                  // Method java/lang/IllegalStateException."<init>":(Ljava/lang/String;)V
      15: athrow
      16: aload_0
      17: putstatic     #74                 // Field onConnectableFlowableAssembly:Lio/reactivex/rxjava3/functions/Function;
      20: return

  public static void setOnFlowableSubscribe(io.reactivex.rxjava3.functions.BiFunction<? super io.reactivex.rxjava3.core.Flowable, ? super org.reactivestreams.Subscriber, ? extends org.reactivestreams.Subscriber>);
    Code:
       0: getstatic     #1                  // Field lockdown:Z
       3: ifeq          16
       6: new           #2                  // class java/lang/IllegalStateException
       9: dup
      10: ldc           #3                  // String Plugins can\'t be changed anymore
      12: invokespecial #4                  // Method java/lang/IllegalStateException."<init>":(Ljava/lang/String;)V
      15: athrow
      16: aload_0
      17: putstatic     #75                 // Field onFlowableSubscribe:Lio/reactivex/rxjava3/functions/BiFunction;
      20: return

  public static void setOnMaybeSubscribe(io.reactivex.rxjava3.functions.BiFunction<? super io.reactivex.rxjava3.core.Maybe, io.reactivex.rxjava3.core.MaybeObserver, ? extends io.reactivex.rxjava3.core.MaybeObserver>);
    Code:
       0: getstatic     #1                  // Field lockdown:Z
       3: ifeq          16
       6: new           #2                  // class java/lang/IllegalStateException
       9: dup
      10: ldc           #3                  // String Plugins can\'t be changed anymore
      12: invokespecial #4                  // Method java/lang/IllegalStateException."<init>":(Ljava/lang/String;)V
      15: athrow
      16: aload_0
      17: putstatic     #76                 // Field onMaybeSubscribe:Lio/reactivex/rxjava3/functions/BiFunction;
      20: return

  public static void setOnObservableAssembly(io.reactivex.rxjava3.functions.Function<? super io.reactivex.rxjava3.core.Observable, ? extends io.reactivex.rxjava3.core.Observable>);
    Code:
       0: getstatic     #1                  // Field lockdown:Z
       3: ifeq          16
       6: new           #2                  // class java/lang/IllegalStateException
       9: dup
      10: ldc           #3                  // String Plugins can\'t be changed anymore
      12: invokespecial #4                  // Method java/lang/IllegalStateException."<init>":(Ljava/lang/String;)V
      15: athrow
      16: aload_0
      17: putstatic     #80                 // Field onObservableAssembly:Lio/reactivex/rxjava3/functions/Function;
      20: return

  public static void setOnConnectableObservableAssembly(io.reactivex.rxjava3.functions.Function<? super io.reactivex.rxjava3.observables.ConnectableObservable, ? extends io.reactivex.rxjava3.observables.ConnectableObservable>);
    Code:
       0: getstatic     #1                  // Field lockdown:Z
       3: ifeq          16
       6: new           #2                  // class java/lang/IllegalStateException
       9: dup
      10: ldc           #3                  // String Plugins can\'t be changed anymore
      12: invokespecial #4                  // Method java/lang/IllegalStateException."<init>":(Ljava/lang/String;)V
      15: athrow
      16: aload_0
      17: putstatic     #81                 // Field onConnectableObservableAssembly:Lio/reactivex/rxjava3/functions/Function;
      20: return

  public static void setOnObservableSubscribe(io.reactivex.rxjava3.functions.BiFunction<? super io.reactivex.rxjava3.core.Observable, ? super io.reactivex.rxjava3.core.Observer, ? extends io.reactivex.rxjava3.core.Observer>);
    Code:
       0: getstatic     #1                  // Field lockdown:Z
       3: ifeq          16
       6: new           #2                  // class java/lang/IllegalStateException
       9: dup
      10: ldc           #3                  // String Plugins can\'t be changed anymore
      12: invokespecial #4                  // Method java/lang/IllegalStateException."<init>":(Ljava/lang/String;)V
      15: athrow
      16: aload_0
      17: putstatic     #82                 // Field onObservableSubscribe:Lio/reactivex/rxjava3/functions/BiFunction;
      20: return

  public static void setOnSingleAssembly(io.reactivex.rxjava3.functions.Function<? super io.reactivex.rxjava3.core.Single, ? extends io.reactivex.rxjava3.core.Single>);
    Code:
       0: getstatic     #1                  // Field lockdown:Z
       3: ifeq          16
       6: new           #2                  // class java/lang/IllegalStateException
       9: dup
      10: ldc           #3                  // String Plugins can\'t be changed anymore
      12: invokespecial #4                  // Method java/lang/IllegalStateException."<init>":(Ljava/lang/String;)V
      15: athrow
      16: aload_0
      17: putstatic     #78                 // Field onSingleAssembly:Lio/reactivex/rxjava3/functions/Function;
      20: return

  public static void setOnSingleSubscribe(io.reactivex.rxjava3.functions.BiFunction<? super io.reactivex.rxjava3.core.Single, ? super io.reactivex.rxjava3.core.SingleObserver, ? extends io.reactivex.rxjava3.core.SingleObserver>);
    Code:
       0: getstatic     #1                  // Field lockdown:Z
       3: ifeq          16
       6: new           #2                  // class java/lang/IllegalStateException
       9: dup
      10: ldc           #3                  // String Plugins can\'t be changed anymore
      12: invokespecial #4                  // Method java/lang/IllegalStateException."<init>":(Ljava/lang/String;)V
      15: athrow
      16: aload_0
      17: putstatic     #79                 // Field onSingleSubscribe:Lio/reactivex/rxjava3/functions/BiFunction;
      20: return

  public static <T> org.reactivestreams.Subscriber<? super T> onSubscribe(io.reactivex.rxjava3.core.Flowable<T>, org.reactivestreams.Subscriber<? super T>);
    Code:
       0: getstatic     #75                 // Field onFlowableSubscribe:Lio/reactivex/rxjava3/functions/BiFunction;
       3: astore_2
       4: aload_2
       5: ifnull        18
       8: aload_2
       9: aload_0
      10: aload_1
      11: invokestatic  #83                 // Method apply:(Lio/reactivex/rxjava3/functions/BiFunction;Ljava/lang/Object;Ljava/lang/Object;)Ljava/lang/Object;
      14: checkcast     #84                 // class org/reactivestreams/Subscriber
      17: areturn
      18: aload_1
      19: areturn

  public static <T> io.reactivex.rxjava3.core.Observer<? super T> onSubscribe(io.reactivex.rxjava3.core.Observable<T>, io.reactivex.rxjava3.core.Observer<? super T>);
    Code:
       0: getstatic     #82                 // Field onObservableSubscribe:Lio/reactivex/rxjava3/functions/BiFunction;
       3: astore_2
       4: aload_2
       5: ifnull        18
       8: aload_2
       9: aload_0
      10: aload_1
      11: invokestatic  #83                 // Method apply:(Lio/reactivex/rxjava3/functions/BiFunction;Ljava/lang/Object;Ljava/lang/Object;)Ljava/lang/Object;
      14: checkcast     #85                 // class io/reactivex/rxjava3/core/Observer
      17: areturn
      18: aload_1
      19: areturn

  public static <T> io.reactivex.rxjava3.core.SingleObserver<? super T> onSubscribe(io.reactivex.rxjava3.core.Single<T>, io.reactivex.rxjava3.core.SingleObserver<? super T>);
    Code:
       0: getstatic     #79                 // Field onSingleSubscribe:Lio/reactivex/rxjava3/functions/BiFunction;
       3: astore_2
       4: aload_2
       5: ifnull        18
       8: aload_2
       9: aload_0
      10: aload_1
      11: invokestatic  #83                 // Method apply:(Lio/reactivex/rxjava3/functions/BiFunction;Ljava/lang/Object;Ljava/lang/Object;)Ljava/lang/Object;
      14: checkcast     #86                 // class io/reactivex/rxjava3/core/SingleObserver
      17: areturn
      18: aload_1
      19: areturn

  public static io.reactivex.rxjava3.core.CompletableObserver onSubscribe(io.reactivex.rxjava3.core.Completable, io.reactivex.rxjava3.core.CompletableObserver);
    Code:
       0: getstatic     #72                 // Field onCompletableSubscribe:Lio/reactivex/rxjava3/functions/BiFunction;
       3: astore_2
       4: aload_2
       5: ifnull        18
       8: aload_2
       9: aload_0
      10: aload_1
      11: invokestatic  #83                 // Method apply:(Lio/reactivex/rxjava3/functions/BiFunction;Ljava/lang/Object;Ljava/lang/Object;)Ljava/lang/Object;
      14: checkcast     #87                 // class io/reactivex/rxjava3/core/CompletableObserver
      17: areturn
      18: aload_1
      19: areturn

  public static <T> io.reactivex.rxjava3.core.MaybeObserver<? super T> onSubscribe(io.reactivex.rxjava3.core.Maybe<T>, io.reactivex.rxjava3.core.MaybeObserver<? super T>);
    Code:
       0: getstatic     #76                 // Field onMaybeSubscribe:Lio/reactivex/rxjava3/functions/BiFunction;
       3: astore_2
       4: aload_2
       5: ifnull        18
       8: aload_2
       9: aload_0
      10: aload_1
      11: invokestatic  #83                 // Method apply:(Lio/reactivex/rxjava3/functions/BiFunction;Ljava/lang/Object;Ljava/lang/Object;)Ljava/lang/Object;
      14: checkcast     #88                 // class io/reactivex/rxjava3/core/MaybeObserver
      17: areturn
      18: aload_1
      19: areturn

  public static <T> org.reactivestreams.Subscriber<? super T>[] onSubscribe(io.reactivex.rxjava3.parallel.ParallelFlowable<T>, org.reactivestreams.Subscriber<? super T>[]);
    Code:
       0: getstatic     #89                 // Field onParallelSubscribe:Lio/reactivex/rxjava3/functions/BiFunction;
       3: astore_2
       4: aload_2
       5: ifnull        18
       8: aload_2
       9: aload_0
      10: aload_1
      11: invokestatic  #83                 // Method apply:(Lio/reactivex/rxjava3/functions/BiFunction;Ljava/lang/Object;Ljava/lang/Object;)Ljava/lang/Object;
      14: checkcast     #90                 // class "[Lorg/reactivestreams/Subscriber;"
      17: areturn
      18: aload_1
      19: areturn

  public static <T> io.reactivex.rxjava3.core.Maybe<T> onAssembly(io.reactivex.rxjava3.core.Maybe<T>);
    Code:
       0: getstatic     #77                 // Field onMaybeAssembly:Lio/reactivex/rxjava3/functions/Function;
       3: astore_1
       4: aload_1
       5: ifnull        17
       8: aload_1
       9: aload_0
      10: invokestatic  #20                 // Method apply:(Lio/reactivex/rxjava3/functions/Function;Ljava/lang/Object;)Ljava/lang/Object;
      13: checkcast     #91                 // class io/reactivex/rxjava3/core/Maybe
      16: areturn
      17: aload_0
      18: areturn

  public static <T> io.reactivex.rxjava3.core.Flowable<T> onAssembly(io.reactivex.rxjava3.core.Flowable<T>);
    Code:
       0: getstatic     #73                 // Field onFlowableAssembly:Lio/reactivex/rxjava3/functions/Function;
       3: astore_1
       4: aload_1
       5: ifnull        17
       8: aload_1
       9: aload_0
      10: invokestatic  #20                 // Method apply:(Lio/reactivex/rxjava3/functions/Function;Ljava/lang/Object;)Ljava/lang/Object;
      13: checkcast     #92                 // class io/reactivex/rxjava3/core/Flowable
      16: areturn
      17: aload_0
      18: areturn

  public static <T> io.reactivex.rxjava3.flowables.ConnectableFlowable<T> onAssembly(io.reactivex.rxjava3.flowables.ConnectableFlowable<T>);
    Code:
       0: getstatic     #74                 // Field onConnectableFlowableAssembly:Lio/reactivex/rxjava3/functions/Function;
       3: astore_1
       4: aload_1
       5: ifnull        17
       8: aload_1
       9: aload_0
      10: invokestatic  #20                 // Method apply:(Lio/reactivex/rxjava3/functions/Function;Ljava/lang/Object;)Ljava/lang/Object;
      13: checkcast     #93                 // class io/reactivex/rxjava3/flowables/ConnectableFlowable
      16: areturn
      17: aload_0
      18: areturn

  public static <T> io.reactivex.rxjava3.core.Observable<T> onAssembly(io.reactivex.rxjava3.core.Observable<T>);
    Code:
       0: getstatic     #80                 // Field onObservableAssembly:Lio/reactivex/rxjava3/functions/Function;
       3: astore_1
       4: aload_1
       5: ifnull        17
       8: aload_1
       9: aload_0
      10: invokestatic  #20                 // Method apply:(Lio/reactivex/rxjava3/functions/Function;Ljava/lang/Object;)Ljava/lang/Object;
      13: checkcast     #94                 // class io/reactivex/rxjava3/core/Observable
      16: areturn
      17: aload_0
      18: areturn

  public static <T> io.reactivex.rxjava3.observables.ConnectableObservable<T> onAssembly(io.reactivex.rxjava3.observables.ConnectableObservable<T>);
    Code:
       0: getstatic     #81                 // Field onConnectableObservableAssembly:Lio/reactivex/rxjava3/functions/Function;
       3: astore_1
       4: aload_1
       5: ifnull        17
       8: aload_1
       9: aload_0
      10: invokestatic  #20                 // Method apply:(Lio/reactivex/rxjava3/functions/Function;Ljava/lang/Object;)Ljava/lang/Object;
      13: checkcast     #95                 // class io/reactivex/rxjava3/observables/ConnectableObservable
      16: areturn
      17: aload_0
      18: areturn

  public static <T> io.reactivex.rxjava3.core.Single<T> onAssembly(io.reactivex.rxjava3.core.Single<T>);
    Code:
       0: getstatic     #78                 // Field onSingleAssembly:Lio/reactivex/rxjava3/functions/Function;
       3: astore_1
       4: aload_1
       5: ifnull        17
       8: aload_1
       9: aload_0
      10: invokestatic  #20                 // Method apply:(Lio/reactivex/rxjava3/functions/Function;Ljava/lang/Object;)Ljava/lang/Object;
      13: checkcast     #96                 // class io/reactivex/rxjava3/core/Single
      16: areturn
      17: aload_0
      18: areturn

  public static io.reactivex.rxjava3.core.Completable onAssembly(io.reactivex.rxjava3.core.Completable);
    Code:
       0: getstatic     #71                 // Field onCompletableAssembly:Lio/reactivex/rxjava3/functions/Function;
       3: astore_1
       4: aload_1
       5: ifnull        17
       8: aload_1
       9: aload_0
      10: invokestatic  #20                 // Method apply:(Lio/reactivex/rxjava3/functions/Function;Ljava/lang/Object;)Ljava/lang/Object;
      13: checkcast     #97                 // class io/reactivex/rxjava3/core/Completable
      16: areturn
      17: aload_0
      18: areturn

  public static void setOnParallelAssembly(io.reactivex.rxjava3.functions.Function<? super io.reactivex.rxjava3.parallel.ParallelFlowable, ? extends io.reactivex.rxjava3.parallel.ParallelFlowable>);
    Code:
       0: getstatic     #1                  // Field lockdown:Z
       3: ifeq          16
       6: new           #2                  // class java/lang/IllegalStateException
       9: dup
      10: ldc           #3                  // String Plugins can\'t be changed anymore
      12: invokespecial #4                  // Method java/lang/IllegalStateException."<init>":(Ljava/lang/String;)V
      15: athrow
      16: aload_0
      17: putstatic     #98                 // Field onParallelAssembly:Lio/reactivex/rxjava3/functions/Function;
      20: return

  public static io.reactivex.rxjava3.functions.Function<? super io.reactivex.rxjava3.parallel.ParallelFlowable, ? extends io.reactivex.rxjava3.parallel.ParallelFlowable> getOnParallelAssembly();
    Code:
       0: getstatic     #98                 // Field onParallelAssembly:Lio/reactivex/rxjava3/functions/Function;
       3: areturn

  public static void setOnParallelSubscribe(io.reactivex.rxjava3.functions.BiFunction<? super io.reactivex.rxjava3.parallel.ParallelFlowable, ? super org.reactivestreams.Subscriber[], ? extends org.reactivestreams.Subscriber[]>);
    Code:
       0: getstatic     #1                  // Field lockdown:Z
       3: ifeq          16
       6: new           #2                  // class java/lang/IllegalStateException
       9: dup
      10: ldc           #3                  // String Plugins can\'t be changed anymore
      12: invokespecial #4                  // Method java/lang/IllegalStateException."<init>":(Ljava/lang/String;)V
      15: athrow
      16: aload_0
      17: putstatic     #89                 // Field onParallelSubscribe:Lio/reactivex/rxjava3/functions/BiFunction;
      20: return

  public static io.reactivex.rxjava3.functions.BiFunction<? super io.reactivex.rxjava3.parallel.ParallelFlowable, ? super org.reactivestreams.Subscriber[], ? extends org.reactivestreams.Subscriber[]> getOnParallelSubscribe();
    Code:
       0: getstatic     #89                 // Field onParallelSubscribe:Lio/reactivex/rxjava3/functions/BiFunction;
       3: areturn

  public static <T> io.reactivex.rxjava3.parallel.ParallelFlowable<T> onAssembly(io.reactivex.rxjava3.parallel.ParallelFlowable<T>);
    Code:
       0: getstatic     #98                 // Field onParallelAssembly:Lio/reactivex/rxjava3/functions/Function;
       3: astore_1
       4: aload_1
       5: ifnull        17
       8: aload_1
       9: aload_0
      10: invokestatic  #20                 // Method apply:(Lio/reactivex/rxjava3/functions/Function;Ljava/lang/Object;)Ljava/lang/Object;
      13: checkcast     #99                 // class io/reactivex/rxjava3/parallel/ParallelFlowable
      16: areturn
      17: aload_0
      18: areturn

  public static boolean onBeforeBlocking();
    Code:
       0: getstatic     #100                // Field onBeforeBlocking:Lio/reactivex/rxjava3/functions/BooleanSupplier;
       3: astore_0
       4: aload_0
       5: ifnull        21
       8: aload_0
       9: invokeinterface #101,  1          // InterfaceMethod io/reactivex/rxjava3/functions/BooleanSupplier.getAsBoolean:()Z
      14: ireturn
      15: astore_1
      16: aload_1
      17: invokestatic  #102                // Method io/reactivex/rxjava3/internal/util/ExceptionHelper.wrapOrThrow:(Ljava/lang/Throwable;)Ljava/lang/RuntimeException;
      20: athrow
      21: iconst_0
      22: ireturn
    Exception table:
       from    to  target type
           8    14    15   Class java/lang/Throwable

  public static void setOnBeforeBlocking(io.reactivex.rxjava3.functions.BooleanSupplier);
    Code:
       0: getstatic     #1                  // Field lockdown:Z
       3: ifeq          16
       6: new           #2                  // class java/lang/IllegalStateException
       9: dup
      10: ldc           #3                  // String Plugins can\'t be changed anymore
      12: invokespecial #4                  // Method java/lang/IllegalStateException."<init>":(Ljava/lang/String;)V
      15: athrow
      16: aload_0
      17: putstatic     #100                // Field onBeforeBlocking:Lio/reactivex/rxjava3/functions/BooleanSupplier;
      20: return

  public static io.reactivex.rxjava3.functions.BooleanSupplier getOnBeforeBlocking();
    Code:
       0: getstatic     #100                // Field onBeforeBlocking:Lio/reactivex/rxjava3/functions/BooleanSupplier;
       3: areturn

  public static io.reactivex.rxjava3.core.Scheduler createComputationScheduler(java.util.concurrent.ThreadFactory);
    Code:
       0: new           #103                // class io/reactivex/rxjava3/internal/schedulers/ComputationScheduler
       3: dup
       4: aload_0
       5: ldc           #104                // String threadFactory is null
       7: invokestatic  #17                 // Method java/util/Objects.requireNonNull:(Ljava/lang/Object;Ljava/lang/String;)Ljava/lang/Object;
      10: checkcast     #105                // class java/util/concurrent/ThreadFactory
      13: invokespecial #106                // Method io/reactivex/rxjava3/internal/schedulers/ComputationScheduler."<init>":(Ljava/util/concurrent/ThreadFactory;)V
      16: areturn

  public static io.reactivex.rxjava3.core.Scheduler createIoScheduler(java.util.concurrent.ThreadFactory);
    Code:
       0: new           #107                // class io/reactivex/rxjava3/internal/schedulers/IoScheduler
       3: dup
       4: aload_0
       5: ldc           #104                // String threadFactory is null
       7: invokestatic  #17                 // Method java/util/Objects.requireNonNull:(Ljava/lang/Object;Ljava/lang/String;)Ljava/lang/Object;
      10: checkcast     #105                // class java/util/concurrent/ThreadFactory
      13: invokespecial #108                // Method io/reactivex/rxjava3/internal/schedulers/IoScheduler."<init>":(Ljava/util/concurrent/ThreadFactory;)V
      16: areturn

  public static io.reactivex.rxjava3.core.Scheduler createNewThreadScheduler(java.util.concurrent.ThreadFactory);
    Code:
       0: new           #109                // class io/reactivex/rxjava3/internal/schedulers/NewThreadScheduler
       3: dup
       4: aload_0
       5: ldc           #104                // String threadFactory is null
       7: invokestatic  #17                 // Method java/util/Objects.requireNonNull:(Ljava/lang/Object;Ljava/lang/String;)Ljava/lang/Object;
      10: checkcast     #105                // class java/util/concurrent/ThreadFactory
      13: invokespecial #110                // Method io/reactivex/rxjava3/internal/schedulers/NewThreadScheduler."<init>":(Ljava/util/concurrent/ThreadFactory;)V
      16: areturn

  public static io.reactivex.rxjava3.core.Scheduler createSingleScheduler(java.util.concurrent.ThreadFactory);
    Code:
       0: new           #111                // class io/reactivex/rxjava3/internal/schedulers/SingleScheduler
       3: dup
       4: aload_0
       5: ldc           #104                // String threadFactory is null
       7: invokestatic  #17                 // Method java/util/Objects.requireNonNull:(Ljava/lang/Object;Ljava/lang/String;)Ljava/lang/Object;
      10: checkcast     #105                // class java/util/concurrent/ThreadFactory
      13: invokespecial #112                // Method io/reactivex/rxjava3/internal/schedulers/SingleScheduler."<init>":(Ljava/util/concurrent/ThreadFactory;)V
      16: areturn

  public static io.reactivex.rxjava3.core.Scheduler createExecutorScheduler(java.util.concurrent.Executor, boolean, boolean);
    Code:
       0: new           #113                // class io/reactivex/rxjava3/internal/schedulers/ExecutorScheduler
       3: dup
       4: aload_0
       5: iload_1
       6: iload_2
       7: invokespecial #114                // Method io/reactivex/rxjava3/internal/schedulers/ExecutorScheduler."<init>":(Ljava/util/concurrent/Executor;ZZ)V
      10: areturn

  static <T, R> R apply(io.reactivex.rxjava3.functions.Function<T, R>, T);
    Code:
       0: aload_0
       1: aload_1
       2: invokeinterface #115,  2          // InterfaceMethod io/reactivex/rxjava3/functions/Function.apply:(Ljava/lang/Object;)Ljava/lang/Object;
       7: areturn
       8: astore_2
       9: aload_2
      10: invokestatic  #102                // Method io/reactivex/rxjava3/internal/util/ExceptionHelper.wrapOrThrow:(Ljava/lang/Throwable;)Ljava/lang/RuntimeException;
      13: athrow
    Exception table:
       from    to  target type
           0     7     8   Class java/lang/Throwable

  static <T, U, R> R apply(io.reactivex.rxjava3.functions.BiFunction<T, U, R>, T, U);
    Code:
       0: aload_0
       1: aload_1
       2: aload_2
       3: invokeinterface #116,  3          // InterfaceMethod io/reactivex/rxjava3/functions/BiFunction.apply:(Ljava/lang/Object;Ljava/lang/Object;)Ljava/lang/Object;
       8: areturn
       9: astore_3
      10: aload_3
      11: invokestatic  #102                // Method io/reactivex/rxjava3/internal/util/ExceptionHelper.wrapOrThrow:(Ljava/lang/Throwable;)Ljava/lang/RuntimeException;
      14: athrow
    Exception table:
       from    to  target type
           0     8     9   Class java/lang/Throwable

  static io.reactivex.rxjava3.core.Scheduler callRequireNonNull(io.reactivex.rxjava3.functions.Supplier<io.reactivex.rxjava3.core.Scheduler>);
    Code:
       0: aload_0
       1: invokeinterface #117,  1          // InterfaceMethod io/reactivex/rxjava3/functions/Supplier.get:()Ljava/lang/Object;
       6: ldc           #118                // String Scheduler Supplier result can\'t be null
       8: invokestatic  #17                 // Method java/util/Objects.requireNonNull:(Ljava/lang/Object;Ljava/lang/String;)Ljava/lang/Object;
      11: checkcast     #119                // class io/reactivex/rxjava3/core/Scheduler
      14: areturn
      15: astore_1
      16: aload_1
      17: invokestatic  #102                // Method io/reactivex/rxjava3/internal/util/ExceptionHelper.wrapOrThrow:(Ljava/lang/Throwable;)Ljava/lang/RuntimeException;
      20: athrow
    Exception table:
       from    to  target type
           0    14    15   Class java/lang/Throwable

  static io.reactivex.rxjava3.core.Scheduler applyRequireNonNull(io.reactivex.rxjava3.functions.Function<? super io.reactivex.rxjava3.functions.Supplier<io.reactivex.rxjava3.core.Scheduler>, ? extends io.reactivex.rxjava3.core.Scheduler>, io.reactivex.rxjava3.functions.Supplier<io.reactivex.rxjava3.core.Scheduler>);
    Code:
       0: aload_0
       1: aload_1
       2: invokestatic  #20                 // Method apply:(Lio/reactivex/rxjava3/functions/Function;Ljava/lang/Object;)Ljava/lang/Object;
       5: ldc           #118                // String Scheduler Supplier result can\'t be null
       7: invokestatic  #17                 // Method java/util/Objects.requireNonNull:(Ljava/lang/Object;Ljava/lang/String;)Ljava/lang/Object;
      10: checkcast     #120                // class io/reactivex/rxjava3/core/Scheduler
      13: areturn

  private io.reactivex.rxjava3.plugins.RxJavaPlugins();
    Code:
       0: aload_0
       1: invokespecial #121                // Method java/lang/Object."<init>":()V
       4: new           #2                  // class java/lang/IllegalStateException
       7: dup
       8: ldc           #122                // String No instances!
      10: invokespecial #4                  // Method java/lang/IllegalStateException."<init>":(Ljava/lang/String;)V
      13: athrow
}
