Compiled from "StringToNavigableSetConverter.java"
public class org.apache.dubbo.common.convert.multiple.StringToNavigableSetConverter extends org.apache.dubbo.common.convert.multiple.StringToIterableConverter<java.util.NavigableSet> {
  public org.apache.dubbo.common.convert.multiple.StringToNavigableSetConverter(org.apache.dubbo.rpc.model.FrameworkModel);
    Code:
       0: aload_0
       1: aload_1
       2: invokespecial #1                  // Method org/apache/dubbo/common/convert/multiple/StringToIterableConverter."<init>":(Lorg/apache/dubbo/rpc/model/FrameworkModel;)V
       5: return

  protected java.util.NavigableSet createMultiValue(int, java.lang.Class<?>);
    Code:
       0: new           #2                  // class java/util/TreeSet
       3: dup
       4: invokespecial #3                  // Method java/util/TreeSet."<init>":()V
       7: areturn

  protected java.lang.Iterable createMultiValue(int, java.lang.Class);
    Code:
       0: aload_0
       1: iload_1
       2: aload_2
       3: invokevirtual #4                  // Method createMultiValue:(ILjava/lang/Class;)Ljava/util/NavigableSet;
       6: areturn
}
