Compiled from "StringToIterableConverter.java"
public abstract class org.apache.dubbo.common.convert.multiple.StringToIterableConverter<T extends java.lang.Iterable> implements org.apache.dubbo.common.convert.multiple.StringToMultiValueConverter {
  private org.apache.dubbo.common.convert.ConverterUtil converterUtil;

  public org.apache.dubbo.common.convert.multiple.StringToIterableConverter(org.apache.dubbo.rpc.model.FrameworkModel);
    Code:
       0: aload_0
       1: invokespecial #1                  // Method java/lang/Object."<init>":()V
       4: aload_0
       5: aload_1
       6: invokevirtual #2                  // Method org/apache/dubbo/rpc/model/FrameworkModel.getBeanFactory:()Lorg/apache/dubbo/common/beans/factory/ScopeBeanFactory;
       9: ldc           #3                  // class org/apache/dubbo/common/convert/ConverterUtil
      11: invokevirtual #4                  // Method org/apache/dubbo/common/beans/factory/ScopeBeanFactory.getBean:(Ljava/lang/Class;)Ljava/lang/Object;
      14: checkcast     #3                  // class org/apache/dubbo/common/convert/ConverterUtil
      17: putfield      #5                  // Field converterUtil:Lorg/apache/dubbo/common/convert/ConverterUtil;
      20: return

  public boolean accept(java.lang.Class<java.lang.String>, java.lang.Class<?>);
    Code:
       0: aload_0
       1: invokevirtual #6                  // Method getSupportedType:()Ljava/lang/Class;
       4: aload_2
       5: invokestatic  #7                  // Method org/apache/dubbo/common/utils/ClassUtils.isAssignableFrom:(Ljava/lang/Class;Ljava/lang/Class;)Z
       8: ireturn

  public final java.lang.Object convert(java.lang.String[], int, java.lang.Class<?>, java.lang.Class<?>);
    Code:
       0: aload_0
       1: aload         4
       3: invokevirtual #8                  // Method getStringConverter:(Ljava/lang/Class;)Ljava/util/Optional;
       6: astore        5
       8: aload         5
      10: aload_0
      11: iload_2
      12: aload_3
      13: aload_1
      14: invokedynamic #9,  0              // InvokeDynamic #0:apply:(Lorg/apache/dubbo/common/convert/multiple/StringToIterableConverter;ILjava/lang/Class;[Ljava/lang/String;)Ljava/util/function/Function;
      19: invokevirtual #10                 // Method java/util/Optional.map:(Ljava/util/function/Function;)Ljava/util/Optional;
      22: aconst_null
      23: invokevirtual #11                 // Method java/util/Optional.orElse:(Ljava/lang/Object;)Ljava/lang/Object;
      26: areturn

  protected abstract T createMultiValue(int, java.lang.Class<?>);

  protected java.util.Optional<org.apache.dubbo.common.convert.StringConverter> getStringConverter(java.lang.Class<?>);
    Code:
       0: aload_0
       1: getfield      #5                  // Field converterUtil:Lorg/apache/dubbo/common/convert/ConverterUtil;
       4: ldc           #12                 // class java/lang/String
       6: aload_1
       7: invokevirtual #13                 // Method org/apache/dubbo/common/convert/ConverterUtil.getConverter:(Ljava/lang/Class;Ljava/lang/Class;)Lorg/apache/dubbo/common/convert/Converter;
      10: checkcast     #14                 // class org/apache/dubbo/common/convert/StringConverter
      13: astore_2
      14: aload_2
      15: invokestatic  #15                 // Method java/util/Optional.ofNullable:(Ljava/lang/Object;)Ljava/util/Optional;
      18: areturn

  protected final java.lang.Class<T> getSupportedType();
    Code:
       0: aload_0
       1: invokevirtual #16                 // Method java/lang/Object.getClass:()Ljava/lang/Class;
       4: ldc           #17                 // class org/apache/dubbo/common/convert/multiple/StringToIterableConverter
       6: iconst_0
       7: invokestatic  #18                 // InterfaceMethod org/apache/dubbo/common/utils/TypeUtils.findActualTypeArgument:(Ljava/lang/reflect/Type;Ljava/lang/Class;I)Ljava/lang/Class;
      10: areturn

  public final int getPriority();
    Code:
       0: aload_0
       1: invokevirtual #6                  // Method getSupportedType:()Ljava/lang/Class;
       4: iconst_1
       5: anewarray     #19                 // class java/util/function/Predicate
       8: dup
       9: iconst_0
      10: invokedynamic #20,  0             // InvokeDynamic #1:test:()Ljava/util/function/Predicate;
      15: aastore
      16: invokestatic  #21                 // Method org/apache/dubbo/common/utils/ClassUtils.getAllInterfaces:(Ljava/lang/Class;[Ljava/util/function/Predicate;)Ljava/util/Set;
      19: invokeinterface #22,  1           // InterfaceMethod java/util/Set.size:()I
      24: istore_1
      25: ldc           #24                 // int 2147483647
      27: iload_1
      28: isub
      29: ireturn

  private static boolean lambda$getPriority$1(java.lang.Class);
    Code:
       0: ldc           #25                 // class java/lang/Iterable
       2: aload_0
       3: invokestatic  #7                  // Method org/apache/dubbo/common/utils/ClassUtils.isAssignableFrom:(Ljava/lang/Class;Ljava/lang/Class;)Z
       6: ireturn

  private java.lang.Iterable lambda$convert$0(int, java.lang.Class, java.lang.String[], org.apache.dubbo.common.convert.StringConverter);
    Code:
       0: aload_0
       1: iload_1
       2: aload_2
       3: invokevirtual #26                 // Method createMultiValue:(ILjava/lang/Class;)Ljava/lang/Iterable;
       6: astore        5
       8: aload         5
      10: instanceof    #27                 // class java/util/Collection
      13: ifeq          68
      16: aload         5
      18: checkcast     #27                 // class java/util/Collection
      21: astore        6
      23: iconst_0
      24: istore        7
      26: iload         7
      28: iload_1
      29: if_icmpge     65
      32: aload_3
      33: iload         7
      35: aaload
      36: astore        8
      38: aload         4
      40: aload         8
      42: invokeinterface #28,  2           // InterfaceMethod org/apache/dubbo/common/convert/StringConverter.convert:(Ljava/lang/Object;)Ljava/lang/Object;
      47: astore        9
      49: aload         6
      51: aload         9
      53: invokeinterface #29,  2           // InterfaceMethod java/util/Collection.add:(Ljava/lang/Object;)Z
      58: pop
      59: iinc          7, 1
      62: goto          26
      65: aload         6
      67: areturn
      68: aload         5
      70: areturn
}
