Compiled from "StringToMultiValueConverter.java"
public interface org.apache.dubbo.common.convert.multiple.StringToMultiValueConverter extends org.apache.dubbo.common.convert.multiple.MultiValueConverter<java.lang.String> {
  public default java.lang.Object convert(java.lang.String, java.lang.Class<?>, java.lang.Class<?>);
    Code:
       0: aload_1
       1: invokestatic  #1                  // Method org/apache/dubbo/common/utils/StringUtils.isEmpty:(Ljava/lang/String;)Z
       4: ifeq          9
       7: aconst_null
       8: areturn
       9: aload_1
      10: bipush        44
      12: invokestatic  #2                  // Method org/apache/dubbo/common/utils/StringUtils.split:(Ljava/lang/String;C)[Ljava/lang/String;
      15: astore        4
      17: aload         4
      19: invokestatic  #3                  // Method org/apache/dubbo/common/utils/ArrayUtils.isEmpty:([Ljava/lang/Object;)Z
      22: ifeq          35
      25: iconst_1
      26: anewarray     #4                  // class java/lang/String
      29: dup
      30: iconst_0
      31: aload_1
      32: aastore
      33: astore        4
      35: aload         4
      37: arraylength
      38: istore        5
      40: aload_0
      41: aload         4
      43: iload         5
      45: aload_2
      46: aload_3
      47: invokeinterface #5,  5            // InterfaceMethod convert:([Ljava/lang/String;ILjava/lang/Class;Ljava/lang/Class;)Ljava/lang/Object;
      52: areturn

  public abstract java.lang.Object convert(java.lang.String[], int, java.lang.Class<?>, java.lang.Class<?>);

  public default java.lang.Object convert(java.lang.Object, java.lang.Class, java.lang.Class);
    Code:
       0: aload_0
       1: aload_1
       2: checkcast     #4                  // class java/lang/String
       5: aload_2
       6: aload_3
       7: invokeinterface #6,  4            // InterfaceMethod convert:(Ljava/lang/String;Ljava/lang/Class;Ljava/lang/Class;)Ljava/lang/Object;
      12: areturn
}
