Compiled from "StringToArrayConverter.java"
public class org.apache.dubbo.common.convert.multiple.StringToArrayConverter implements org.apache.dubbo.common.convert.multiple.StringToMultiValueConverter {
  private org.apache.dubbo.common.convert.ConverterUtil converterUtil;

  public org.apache.dubbo.common.convert.multiple.StringToArrayConverter(org.apache.dubbo.rpc.model.FrameworkModel);
    Code:
       0: aload_0
       1: invokespecial #1                  // Method java/lang/Object."<init>":()V
       4: aload_0
       5: aload_1
       6: invokevirtual #2                  // Method org/apache/dubbo/rpc/model/FrameworkModel.getBeanFactory:()Lorg/apache/dubbo/common/beans/factory/ScopeBeanFactory;
       9: ldc           #3                  // class org/apache/dubbo/common/convert/ConverterUtil
      11: invokevirtual #4                  // Method org/apache/dubbo/common/beans/factory/ScopeBeanFactory.getBean:(Ljava/lang/Class;)Ljava/lang/Object;
      14: checkcast     #3                  // class org/apache/dubbo/common/convert/ConverterUtil
      17: putfield      #5                  // Field converterUtil:Lorg/apache/dubbo/common/convert/ConverterUtil;
      20: return

  public boolean accept(java.lang.Class<java.lang.String>, java.lang.Class<?>);
    Code:
       0: aload_2
       1: ifnull        13
       4: aload_2
       5: invokevirtual #6                  // Method java/lang/Class.isArray:()Z
       8: ifeq          13
      11: iconst_1
      12: ireturn
      13: iconst_0
      14: ireturn

  public java.lang.Object convert(java.lang.String[], int, java.lang.Class<?>, java.lang.Class<?>);
    Code:
       0: aload_3
       1: invokevirtual #7                  // Method java/lang/Class.getComponentType:()Ljava/lang/Class;
       4: astore        5
       6: aload_0
       7: getfield      #5                  // Field converterUtil:Lorg/apache/dubbo/common/convert/ConverterUtil;
      10: ldc           #8                  // class java/lang/String
      12: aload         5
      14: invokevirtual #9                  // Method org/apache/dubbo/common/convert/ConverterUtil.getConverter:(Ljava/lang/Class;Ljava/lang/Class;)Lorg/apache/dubbo/common/convert/Converter;
      17: astore        6
      19: aload         5
      21: iload_2
      22: invokestatic  #10                 // Method java/lang/reflect/Array.newInstance:(Ljava/lang/Class;I)Ljava/lang/Object;
      25: astore        7
      27: iconst_0
      28: istore        8
      30: iload         8
      32: iload_2
      33: if_icmpge     60
      36: aload         7
      38: iload         8
      40: aload         6
      42: aload_1
      43: iload         8
      45: aaload
      46: invokeinterface #11,  2           // InterfaceMethod org/apache/dubbo/common/convert/Converter.convert:(Ljava/lang/Object;)Ljava/lang/Object;
      51: invokestatic  #12                 // Method java/lang/reflect/Array.set:(Ljava/lang/Object;ILjava/lang/Object;)V
      54: iinc          8, 1
      57: goto          30
      60: aload         7
      62: areturn

  public int getPriority();
    Code:
       0: ldc           #14                 // int 2147483647
       2: ireturn
}
