Compiled from "StringToBlockingDequeConverter.java"
public class org.apache.dubbo.common.convert.multiple.StringToBlockingDequeConverter extends org.apache.dubbo.common.convert.multiple.StringToIterableConverter<java.util.concurrent.BlockingDeque> {
  public org.apache.dubbo.common.convert.multiple.StringToBlockingDequeConverter(org.apache.dubbo.rpc.model.FrameworkModel);
    Code:
       0: aload_0
       1: aload_1
       2: invokespecial #1                  // Method org/apache/dubbo/common/convert/multiple/StringToIterableConverter."<init>":(Lorg/apache/dubbo/rpc/model/FrameworkModel;)V
       5: return

  protected java.util.concurrent.BlockingDeque createMultiValue(int, java.lang.Class<?>);
    Code:
       0: new           #2                  // class java/util/concurrent/LinkedBlockingDeque
       3: dup
       4: iload_1
       5: invokespecial #3                  // Method java/util/concurrent/LinkedBlockingDeque."<init>":(I)V
       8: areturn

  protected java.lang.Iterable createMultiValue(int, java.lang.Class);
    Code:
       0: aload_0
       1: iload_1
       2: aload_2
       3: invokevirtual #4                  // Method createMultiValue:(ILjava/lang/Class;)Ljava/util/concurrent/BlockingDeque;
       6: areturn
}
