Compiled from "AccessFlags.java"
class jadx.api.plugins.input.data.AccessFlags$1 {
  static final int[] $SwitchMap$jadx$api$plugins$input$data$AccessFlagsScope;

  static {};
    Code:
       0: invokestatic  #1                  // Method jadx/api/plugins/input/data/AccessFlagsScope.values:()[Ljadx/api/plugins/input/data/AccessFlagsScope;
       3: arraylength
       4: newarray       int
       6: putstatic     #2                  // Field $SwitchMap$jadx$api$plugins$input$data$AccessFlagsScope:[I
       9: getstatic     #2                  // Field $SwitchMap$jadx$api$plugins$input$data$AccessFlagsScope:[I
      12: getstatic     #3                  // Field jadx/api/plugins/input/data/AccessFlagsScope.METHOD:Ljadx/api/plugins/input/data/AccessFlagsScope;
      15: invokevirtual #4                  // Method jadx/api/plugins/input/data/AccessFlagsScope.ordinal:()I
      18: iconst_1
      19: iastore
      20: goto          24
      23: astore_0
      24: getstatic     #2                  // Field $SwitchMap$jadx$api$plugins$input$data$AccessFlagsScope:[I
      27: getstatic     #6                  // Field jadx/api/plugins/input/data/AccessFlagsScope.FIELD:Ljadx/api/plugins/input/data/AccessFlagsScope;
      30: invokevirtual #4                  // Method jadx/api/plugins/input/data/AccessFlagsScope.ordinal:()I
      33: iconst_2
      34: iastore
      35: goto          39
      38: astore_0
      39: getstatic     #2                  // Field $SwitchMap$jadx$api$plugins$input$data$AccessFlagsScope:[I
      42: getstatic     #7                  // Field jadx/api/plugins/input/data/AccessFlagsScope.CLASS:Ljadx/api/plugins/input/data/AccessFlagsScope;
      45: invokevirtual #4                  // Method jadx/api/plugins/input/data/AccessFlagsScope.ordinal:()I
      48: iconst_3
      49: iastore
      50: goto          54
      53: astore_0
      54: return
    Exception table:
       from    to  target type
           9    20    23   Class java/lang/NoSuchFieldError
          24    35    38   Class java/lang/NoSuchFieldError
          39    50    53   Class java/lang/NoSuchFieldError
}
