Compiled from "AccessFlagsScope.java"
public final class jadx.api.plugins.input.data.AccessFlagsScope extends java.lang.Enum<jadx.api.plugins.input.data.AccessFlagsScope> {
  public static final jadx.api.plugins.input.data.AccessFlagsScope CLASS;

  public static final jadx.api.plugins.input.data.AccessFlagsScope FIELD;

  public static final jadx.api.plugins.input.data.AccessFlagsScope METHOD;

  private static final jadx.api.plugins.input.data.AccessFlagsScope[] $VALUES;

  public static jadx.api.plugins.input.data.AccessFlagsScope[] values();
    Code:
       0: getstatic     #1                  // Field $VALUES:[Ljadx/api/plugins/input/data/AccessFlagsScope;
       3: invokevirtual #2                  // Method "[Ljadx/api/plugins/input/data/AccessFlagsScope;".clone:()Ljava/lang/Object;
       6: checkcast     #3                  // class "[Ljadx/api/plugins/input/data/AccessFlagsScope;"
       9: areturn

  public static jadx.api.plugins.input.data.AccessFlagsScope valueOf(java.lang.String);
    Code:
       0: ldc           #4                  // class jadx/api/plugins/input/data/AccessFlagsScope
       2: aload_0
       3: invokestatic  #5                  // Method java/lang/Enum.valueOf:(Ljava/lang/Class;Ljava/lang/String;)Ljava/lang/Enum;
       6: checkcast     #4                  // class jadx/api/plugins/input/data/AccessFlagsScope
       9: areturn

  private jadx.api.plugins.input.data.AccessFlagsScope();
    Code:
       0: aload_0
       1: aload_1
       2: iload_2
       3: invokespecial #6                  // Method java/lang/Enum."<init>":(Ljava/lang/String;I)V
       6: return

  static {};
    Code:
       0: new           #4                  // class jadx/api/plugins/input/data/AccessFlagsScope
       3: dup
       4: ldc           #7                  // String CLASS
       6: iconst_0
       7: invokespecial #8                  // Method "<init>":(Ljava/lang/String;I)V
      10: putstatic     #9                  // Field CLASS:Ljadx/api/plugins/input/data/AccessFlagsScope;
      13: new           #4                  // class jadx/api/plugins/input/data/AccessFlagsScope
      16: dup
      17: ldc           #10                 // String FIELD
      19: iconst_1
      20: invokespecial #8                  // Method "<init>":(Ljava/lang/String;I)V
      23: putstatic     #11                 // Field FIELD:Ljadx/api/plugins/input/data/AccessFlagsScope;
      26: new           #4                  // class jadx/api/plugins/input/data/AccessFlagsScope
      29: dup
      30: ldc           #12                 // String METHOD
      32: iconst_2
      33: invokespecial #8                  // Method "<init>":(Ljava/lang/String;I)V
      36: putstatic     #13                 // Field METHOD:Ljadx/api/plugins/input/data/AccessFlagsScope;
      39: iconst_3
      40: anewarray     #4                  // class jadx/api/plugins/input/data/AccessFlagsScope
      43: dup
      44: iconst_0
      45: getstatic     #9                  // Field CLASS:Ljadx/api/plugins/input/data/AccessFlagsScope;
      48: aastore
      49: dup
      50: iconst_1
      51: getstatic     #11                 // Field FIELD:Ljadx/api/plugins/input/data/AccessFlagsScope;
      54: aastore
      55: dup
      56: iconst_2
      57: getstatic     #13                 // Field METHOD:Ljadx/api/plugins/input/data/AccessFlagsScope;
      60: aastore
      61: putstatic     #1                  // Field $VALUES:[Ljadx/api/plugins/input/data/AccessFlagsScope;
      64: return
}
