Compiled from "AccessFlags.java"
public class jadx.api.plugins.input.data.AccessFlags {
  public static final int PUBLIC;

  public static final int PRIVATE;

  public static final int PROTECTED;

  public static final int STATIC;

  public static final int FINAL;

  public static final int SYNCHRONIZED;

  public static final int SUPER;

  public static final int VOLATILE;

  public static final int BRIDGE;

  public static final int TRANSIENT;

  public static final int VARARGS;

  public static final int NATIVE;

  public static final int INTERFACE;

  public static final int ABSTRACT;

  public static final int STRICT;

  public static final int SYNTHETIC;

  public static final int ANNOTATION;

  public static final int ENUM;

  public static final int MODULE;

  public static final int CONSTRUCTOR;

  public static final int DECLARED_SYNCHRONIZED;

  public jadx.api.plugins.input.data.AccessFlags();
    Code:
       0: aload_0
       1: invokespecial #1                  // Method java/lang/Object."<init>":()V
       4: return

  public static boolean hasFlag(int, int);
    Code:
       0: iload_0
       1: iload_1
       2: iand
       3: ifeq          10
       6: iconst_1
       7: goto          11
      10: iconst_0
      11: ireturn

  public static java.lang.String format(int, jadx.api.plugins.input.data.AccessFlagsScope);
    Code:
       0: new           #2                  // class java/lang/StringBuilder
       3: dup
       4: invokespecial #3                  // Method java/lang/StringBuilder."<init>":()V
       7: astore_2
       8: iload_0
       9: iconst_1
      10: invokestatic  #5                  // Method hasFlag:(II)Z
      13: ifeq          23
      16: aload_2
      17: ldc           #6                  // String public
      19: invokevirtual #7                  // Method java/lang/StringBuilder.append:(Ljava/lang/String;)Ljava/lang/StringBuilder;
      22: pop
      23: iload_0
      24: iconst_2
      25: invokestatic  #5                  // Method hasFlag:(II)Z
      28: ifeq          38
      31: aload_2
      32: ldc           #8                  // String private
      34: invokevirtual #7                  // Method java/lang/StringBuilder.append:(Ljava/lang/String;)Ljava/lang/StringBuilder;
      37: pop
      38: iload_0
      39: iconst_4
      40: invokestatic  #5                  // Method hasFlag:(II)Z
      43: ifeq          53
      46: aload_2
      47: ldc           #9                  // String protected
      49: invokevirtual #7                  // Method java/lang/StringBuilder.append:(Ljava/lang/String;)Ljava/lang/StringBuilder;
      52: pop
      53: iload_0
      54: bipush        8
      56: invokestatic  #5                  // Method hasFlag:(II)Z
      59: ifeq          69
      62: aload_2
      63: ldc           #10                 // String static
      65: invokevirtual #7                  // Method java/lang/StringBuilder.append:(Ljava/lang/String;)Ljava/lang/StringBuilder;
      68: pop
      69: iload_0
      70: bipush        16
      72: invokestatic  #5                  // Method hasFlag:(II)Z
      75: ifeq          85
      78: aload_2
      79: ldc           #11                 // String final
      81: invokevirtual #7                  // Method java/lang/StringBuilder.append:(Ljava/lang/String;)Ljava/lang/StringBuilder;
      84: pop
      85: iload_0
      86: sipush        1024
      89: invokestatic  #5                  // Method hasFlag:(II)Z
      92: ifeq          102
      95: aload_2
      96: ldc           #12                 // String abstract
      98: invokevirtual #7                  // Method java/lang/StringBuilder.append:(Ljava/lang/String;)Ljava/lang/StringBuilder;
     101: pop
     102: iload_0
     103: sipush        256
     106: invokestatic  #5                  // Method hasFlag:(II)Z
     109: ifeq          119
     112: aload_2
     113: ldc           #13                 // String native
     115: invokevirtual #7                  // Method java/lang/StringBuilder.append:(Ljava/lang/String;)Ljava/lang/StringBuilder;
     118: pop
     119: getstatic     #14                 // Field jadx/api/plugins/input/data/AccessFlags$1.$SwitchMap$jadx$api$plugins$input$data$AccessFlagsScope:[I
     122: aload_1
     123: invokevirtual #15                 // Method jadx/api/plugins/input/data/AccessFlagsScope.ordinal:()I
     126: iaload
     127: tableswitch   { // 1 to 3
                     1: 152
                     2: 204
                     3: 240
               default: 306
          }
     152: iload_0
     153: bipush        32
     155: invokestatic  #5                  // Method hasFlag:(II)Z
     158: ifeq          168
     161: aload_2
     162: ldc           #16                 // String synchronized
     164: invokevirtual #7                  // Method java/lang/StringBuilder.append:(Ljava/lang/String;)Ljava/lang/StringBuilder;
     167: pop
     168: iload_0
     169: bipush        64
     171: invokestatic  #5                  // Method hasFlag:(II)Z
     174: ifeq          184
     177: aload_2
     178: ldc           #17                 // String bridge
     180: invokevirtual #7                  // Method java/lang/StringBuilder.append:(Ljava/lang/String;)Ljava/lang/StringBuilder;
     183: pop
     184: iload_0
     185: sipush        128
     188: invokestatic  #5                  // Method hasFlag:(II)Z
     191: ifeq          306
     194: aload_2
     195: ldc           #18                 // String varargs
     197: invokevirtual #7                  // Method java/lang/StringBuilder.append:(Ljava/lang/String;)Ljava/lang/StringBuilder;
     200: pop
     201: goto          306
     204: iload_0
     205: bipush        64
     207: invokestatic  #5                  // Method hasFlag:(II)Z
     210: ifeq          220
     213: aload_2
     214: ldc           #19                 // String volatile
     216: invokevirtual #7                  // Method java/lang/StringBuilder.append:(Ljava/lang/String;)Ljava/lang/StringBuilder;
     219: pop
     220: iload_0
     221: sipush        128
     224: invokestatic  #5                  // Method hasFlag:(II)Z
     227: ifeq          306
     230: aload_2
     231: ldc           #20                 // String transient
     233: invokevirtual #7                  // Method java/lang/StringBuilder.append:(Ljava/lang/String;)Ljava/lang/StringBuilder;
     236: pop
     237: goto          306
     240: iload_0
     241: ldc           #21                 // int 32768
     243: invokestatic  #5                  // Method hasFlag:(II)Z
     246: ifeq          256
     249: aload_2
     250: ldc           #22                 // String module
     252: invokevirtual #7                  // Method java/lang/StringBuilder.append:(Ljava/lang/String;)Ljava/lang/StringBuilder;
     255: pop
     256: iload_0
     257: sipush        2048
     260: invokestatic  #5                  // Method hasFlag:(II)Z
     263: ifeq          273
     266: aload_2
     267: ldc           #23                 // String strict
     269: invokevirtual #7                  // Method java/lang/StringBuilder.append:(Ljava/lang/String;)Ljava/lang/StringBuilder;
     272: pop
     273: iload_0
     274: bipush        32
     276: invokestatic  #5                  // Method hasFlag:(II)Z
     279: ifeq          289
     282: aload_2
     283: ldc           #24                 // String super
     285: invokevirtual #7                  // Method java/lang/StringBuilder.append:(Ljava/lang/String;)Ljava/lang/StringBuilder;
     288: pop
     289: iload_0
     290: sipush        16384
     293: invokestatic  #5                  // Method hasFlag:(II)Z
     296: ifeq          306
     299: aload_2
     300: ldc           #25                 // String enum
     302: invokevirtual #7                  // Method java/lang/StringBuilder.append:(Ljava/lang/String;)Ljava/lang/StringBuilder;
     305: pop
     306: iload_0
     307: sipush        4096
     310: invokestatic  #5                  // Method hasFlag:(II)Z
     313: ifeq          323
     316: aload_2
     317: ldc           #26                 // String synthetic
     319: invokevirtual #7                  // Method java/lang/StringBuilder.append:(Ljava/lang/String;)Ljava/lang/StringBuilder;
     322: pop
     323: aload_2
     324: invokevirtual #27                 // Method java/lang/StringBuilder.toString:()Ljava/lang/String;
     327: areturn
}
