Compiled from "MethodHandleType.java"
public final class jadx.api.plugins.input.data.MethodHandleType extends java.lang.Enum<jadx.api.plugins.input.data.MethodHandleType> {
  public static final jadx.api.plugins.input.data.MethodHandleType STATIC_PUT;

  public static final jadx.api.plugins.input.data.MethodHandleType STATIC_GET;

  public static final jadx.api.plugins.input.data.MethodHandleType INSTANCE_PUT;

  public static final jadx.api.plugins.input.data.MethodHandleType INSTANCE_GET;

  public static final jadx.api.plugins.input.data.MethodHandleType INVOKE_STATIC;

  public static final jadx.api.plugins.input.data.MethodHandleType INVOKE_INSTANCE;

  public static final jadx.api.plugins.input.data.MethodHandleType INVOKE_DIRECT;

  public static final jadx.api.plugins.input.data.MethodHandleType INVOKE_CONSTRUCTOR;

  public static final jadx.api.plugins.input.data.MethodHandleType INVOKE_INTERFACE;

  private static final jadx.api.plugins.input.data.MethodHandleType[] $VALUES;

  public static jadx.api.plugins.input.data.MethodHandleType[] values();
    Code:
       0: getstatic     #1                  // Field $VALUES:[Ljadx/api/plugins/input/data/MethodHandleType;
       3: invokevirtual #2                  // Method "[Ljadx/api/plugins/input/data/MethodHandleType;".clone:()Ljava/lang/Object;
       6: checkcast     #3                  // class "[Ljadx/api/plugins/input/data/MethodHandleType;"
       9: areturn

  public static jadx.api.plugins.input.data.MethodHandleType valueOf(java.lang.String);
    Code:
       0: ldc           #4                  // class jadx/api/plugins/input/data/MethodHandleType
       2: aload_0
       3: invokestatic  #5                  // Method java/lang/Enum.valueOf:(Ljava/lang/Class;Ljava/lang/String;)Ljava/lang/Enum;
       6: checkcast     #4                  // class jadx/api/plugins/input/data/MethodHandleType
       9: areturn

  private jadx.api.plugins.input.data.MethodHandleType();
    Code:
       0: aload_0
       1: aload_1
       2: iload_2
       3: invokespecial #6                  // Method java/lang/Enum."<init>":(Ljava/lang/String;I)V
       6: return

  public boolean isField();
    Code:
       0: getstatic     #7                  // Field jadx/api/plugins/input/data/MethodHandleType$1.$SwitchMap$jadx$api$plugins$input$data$MethodHandleType:[I
       3: aload_0
       4: invokevirtual #8                  // Method ordinal:()I
       7: iaload
       8: tableswitch   { // 1 to 4
                     1: 40
                     2: 40
                     3: 40
                     4: 40
               default: 42
          }
      40: iconst_1
      41: ireturn
      42: iconst_0
      43: ireturn

  static {};
    Code:
       0: new           #4                  // class jadx/api/plugins/input/data/MethodHandleType
       3: dup
       4: ldc           #9                  // String STATIC_PUT
       6: iconst_0
       7: invokespecial #10                 // Method "<init>":(Ljava/lang/String;I)V
      10: putstatic     #11                 // Field STATIC_PUT:Ljadx/api/plugins/input/data/MethodHandleType;
      13: new           #4                  // class jadx/api/plugins/input/data/MethodHandleType
      16: dup
      17: ldc           #12                 // String STATIC_GET
      19: iconst_1
      20: invokespecial #10                 // Method "<init>":(Ljava/lang/String;I)V
      23: putstatic     #13                 // Field STATIC_GET:Ljadx/api/plugins/input/data/MethodHandleType;
      26: new           #4                  // class jadx/api/plugins/input/data/MethodHandleType
      29: dup
      30: ldc           #14                 // String INSTANCE_PUT
      32: iconst_2
      33: invokespecial #10                 // Method "<init>":(Ljava/lang/String;I)V
      36: putstatic     #15                 // Field INSTANCE_PUT:Ljadx/api/plugins/input/data/MethodHandleType;
      39: new           #4                  // class jadx/api/plugins/input/data/MethodHandleType
      42: dup
      43: ldc           #16                 // String INSTANCE_GET
      45: iconst_3
      46: invokespecial #10                 // Method "<init>":(Ljava/lang/String;I)V
      49: putstatic     #17                 // Field INSTANCE_GET:Ljadx/api/plugins/input/data/MethodHandleType;
      52: new           #4                  // class jadx/api/plugins/input/data/MethodHandleType
      55: dup
      56: ldc           #18                 // String INVOKE_STATIC
      58: iconst_4
      59: invokespecial #10                 // Method "<init>":(Ljava/lang/String;I)V
      62: putstatic     #19                 // Field INVOKE_STATIC:Ljadx/api/plugins/input/data/MethodHandleType;
      65: new           #4                  // class jadx/api/plugins/input/data/MethodHandleType
      68: dup
      69: ldc           #20                 // String INVOKE_INSTANCE
      71: iconst_5
      72: invokespecial #10                 // Method "<init>":(Ljava/lang/String;I)V
      75: putstatic     #21                 // Field INVOKE_INSTANCE:Ljadx/api/plugins/input/data/MethodHandleType;
      78: new           #4                  // class jadx/api/plugins/input/data/MethodHandleType
      81: dup
      82: ldc           #22                 // String INVOKE_DIRECT
      84: bipush        6
      86: invokespecial #10                 // Method "<init>":(Ljava/lang/String;I)V
      89: putstatic     #23                 // Field INVOKE_DIRECT:Ljadx/api/plugins/input/data/MethodHandleType;
      92: new           #4                  // class jadx/api/plugins/input/data/MethodHandleType
      95: dup
      96: ldc           #24                 // String INVOKE_CONSTRUCTOR
      98: bipush        7
     100: invokespecial #10                 // Method "<init>":(Ljava/lang/String;I)V
     103: putstatic     #25                 // Field INVOKE_CONSTRUCTOR:Ljadx/api/plugins/input/data/MethodHandleType;
     106: new           #4                  // class jadx/api/plugins/input/data/MethodHandleType
     109: dup
     110: ldc           #26                 // String INVOKE_INTERFACE
     112: bipush        8
     114: invokespecial #10                 // Method "<init>":(Ljava/lang/String;I)V
     117: putstatic     #27                 // Field INVOKE_INTERFACE:Ljadx/api/plugins/input/data/MethodHandleType;
     120: bipush        9
     122: anewarray     #4                  // class jadx/api/plugins/input/data/MethodHandleType
     125: dup
     126: iconst_0
     127: getstatic     #11                 // Field STATIC_PUT:Ljadx/api/plugins/input/data/MethodHandleType;
     130: aastore
     131: dup
     132: iconst_1
     133: getstatic     #13                 // Field STATIC_GET:Ljadx/api/plugins/input/data/MethodHandleType;
     136: aastore
     137: dup
     138: iconst_2
     139: getstatic     #15                 // Field INSTANCE_PUT:Ljadx/api/plugins/input/data/MethodHandleType;
     142: aastore
     143: dup
     144: iconst_3
     145: getstatic     #17                 // Field INSTANCE_GET:Ljadx/api/plugins/input/data/MethodHandleType;
     148: aastore
     149: dup
     150: iconst_4
     151: getstatic     #19                 // Field INVOKE_STATIC:Ljadx/api/plugins/input/data/MethodHandleType;
     154: aastore
     155: dup
     156: iconst_5
     157: getstatic     #21                 // Field INVOKE_INSTANCE:Ljadx/api/plugins/input/data/MethodHandleType;
     160: aastore
     161: dup
     162: bipush        6
     164: getstatic     #23                 // Field INVOKE_DIRECT:Ljadx/api/plugins/input/data/MethodHandleType;
     167: aastore
     168: dup
     169: bipush        7
     171: getstatic     #25                 // Field INVOKE_CONSTRUCTOR:Ljadx/api/plugins/input/data/MethodHandleType;
     174: aastore
     175: dup
     176: bipush        8
     178: getstatic     #27                 // Field INVOKE_INTERFACE:Ljadx/api/plugins/input/data/MethodHandleType;
     181: aastore
     182: putstatic     #1                  // Field $VALUES:[Ljadx/api/plugins/input/data/MethodHandleType;
     185: return
}
