Compiled from "Cluster.java"
public interface org.apache.dubbo.rpc.cluster.Cluster {
  public static final java.lang.String DEFAULT;

  public abstract <T> org.apache.dubbo.rpc.Invoker<T> join(org.apache.dubbo.rpc.cluster.Directory<T>, boolean) throws org.apache.dubbo.rpc.RpcException;

  public static org.apache.dubbo.rpc.cluster.Cluster getCluster(org.apache.dubbo.rpc.model.ScopeModel, java.lang.String);
    Code:
       0: aload_0
       1: aload_1
       2: iconst_1
       3: invokestatic  #1                  // InterfaceMethod getCluster:(Lorg/apache/dubbo/rpc/model/ScopeModel;Ljava/lang/String;Z)Lorg/apache/dubbo/rpc/cluster/Cluster;
       6: areturn

  public static org.apache.dubbo.rpc.cluster.Cluster getCluster(org.apache.dubbo.rpc.model.ScopeModel, java.lang.String, boolean);
    Code:
       0: aload_1
       1: invokestatic  #2                  // Method org/apache/dubbo/common/utils/StringUtils.isEmpty:(Ljava/lang/String;)Z
       4: ifeq          10
       7: ldc           #4                  // String failover
       9: astore_1
      10: aload_0
      11: invokestatic  #5                  // Method org/apache/dubbo/rpc/model/ScopeModelUtil.getApplicationModel:(Lorg/apache/dubbo/rpc/model/ScopeModel;)Lorg/apache/dubbo/rpc/model/ApplicationModel;
      14: ldc           #3                  // class org/apache/dubbo/rpc/cluster/Cluster
      16: invokevirtual #6                  // Method org/apache/dubbo/rpc/model/ApplicationModel.getExtensionLoader:(Ljava/lang/Class;)Lorg/apache/dubbo/common/extension/ExtensionLoader;
      19: aload_1
      20: iload_2
      21: invokevirtual #7                  // Method org/apache/dubbo/common/extension/ExtensionLoader.getExtension:(Ljava/lang/String;Z)Ljava/lang/Object;
      24: checkcast     #3                  // class org/apache/dubbo/rpc/cluster/Cluster
      27: areturn
}
