Compiled from "ClusterInvoker.java"
public interface org.apache.dubbo.rpc.cluster.ClusterInvoker<T> extends org.apache.dubbo.rpc.Invoker<T> {
  public abstract org.apache.dubbo.common.URL getRegistryUrl();

  public abstract org.apache.dubbo.rpc.cluster.Directory<T> getDirectory();

  public abstract boolean isDestroyed();

  public default boolean isServiceDiscovery();
    Code:
       0: aload_0
       1: invokeinterface #1,  1            // InterfaceMethod getDirectory:()Lorg/apache/dubbo/rpc/cluster/Directory;
       6: astore_1
       7: aload_1
       8: ifnonnull     13
      11: iconst_0
      12: ireturn
      13: aload_1
      14: invokeinterface #2,  1            // InterfaceMethod org/apache/dubbo/rpc/cluster/Directory.isServiceDiscovery:()Z
      19: ireturn

  public default boolean hasProxyInvokers();
    Code:
       0: aload_0
       1: invokeinterface #1,  1            // InterfaceMethod getDirectory:()Lorg/apache/dubbo/rpc/cluster/Directory;
       6: astore_1
       7: aload_1
       8: ifnonnull     13
      11: iconst_0
      12: ireturn
      13: aload_1
      14: invokeinterface #3,  1            // InterfaceMethod org/apache/dubbo/rpc/cluster/Directory.isEmpty:()Z
      19: ifne          26
      22: iconst_1
      23: goto          27
      26: iconst_0
      27: ireturn
}
