Compiled from "ClusterScopeModelInitializer.java"
public class org.apache.dubbo.rpc.cluster.ClusterScopeModelInitializer implements org.apache.dubbo.rpc.model.ScopeModelInitializer {
  public org.apache.dubbo.rpc.cluster.ClusterScopeModelInitializer();
    Code:
       0: aload_0
       1: invokespecial #1                  // Method java/lang/Object."<init>":()V
       4: return

  public void initializeFrameworkModel(org.apache.dubbo.rpc.model.FrameworkModel);
    Code:
       0: aload_1
       1: invokevirtual #2                  // Method org/apache/dubbo/rpc/model/FrameworkModel.getBeanFactory:()Lorg/apache/dubbo/common/beans/factory/ScopeBeanFactory;
       4: astore_2
       5: aload_2
       6: ldc           #3                  // class org/apache/dubbo/rpc/cluster/router/RouterSnapshotSwitcher
       8: invokevirtual #4                  // Method org/apache/dubbo/common/beans/factory/ScopeBeanFactory.registerBean:(Ljava/lang/Class;)Ljava/lang/Object;
      11: pop
      12: return

  public void initializeApplicationModel(org.apache.dubbo.rpc.model.ApplicationModel);
    Code:
       0: aload_1
       1: invokevirtual #5                  // Method org/apache/dubbo/rpc/model/ApplicationModel.getBeanFactory:()Lorg/apache/dubbo/common/beans/factory/ScopeBeanFactory;
       4: astore_2
       5: aload_2
       6: ldc           #6                  // class org/apache/dubbo/rpc/cluster/merger/MergerFactory
       8: invokevirtual #4                  // Method org/apache/dubbo/common/beans/factory/ScopeBeanFactory.registerBean:(Ljava/lang/Class;)Ljava/lang/Object;
      11: pop
      12: aload_2
      13: ldc           #7                  // class org/apache/dubbo/rpc/cluster/support/ClusterUtils
      15: invokevirtual #4                  // Method org/apache/dubbo/common/beans/factory/ScopeBeanFactory.registerBean:(Ljava/lang/Class;)Ljava/lang/Object;
      18: pop
      19: aload_2
      20: ldc           #8                  // class org/apache/dubbo/rpc/AdaptiveMetrics
      22: invokevirtual #4                  // Method org/apache/dubbo/common/beans/factory/ScopeBeanFactory.registerBean:(Ljava/lang/Class;)Ljava/lang/Object;
      25: pop
      26: return

  public void initializeModuleModel(org.apache.dubbo.rpc.model.ModuleModel);
    Code:
       0: aload_1
       1: invokevirtual #9                  // Method org/apache/dubbo/rpc/model/ModuleModel.getBeanFactory:()Lorg/apache/dubbo/common/beans/factory/ScopeBeanFactory;
       4: astore_2
       5: aload_2
       6: ldc           #10                 // class org/apache/dubbo/rpc/cluster/router/mesh/route/MeshRuleManager
       8: invokevirtual #4                  // Method org/apache/dubbo/common/beans/factory/ScopeBeanFactory.registerBean:(Ljava/lang/Class;)Ljava/lang/Object;
      11: pop
      12: return
}
