Compiled from "Configurator.java"
public interface org.apache.dubbo.rpc.cluster.Configurator extends java.lang.Comparable<org.apache.dubbo.rpc.cluster.Configurator> {
  public abstract org.apache.dubbo.common.URL getUrl();

  public abstract org.apache.dubbo.common.URL configure(org.apache.dubbo.common.URL);

  public static java.util.Optional<java.util.List<org.apache.dubbo.rpc.cluster.Configurator>> toConfigurators(java.util.List<org.apache.dubbo.common.URL>);
    Code:
       0: aload_0
       1: invokestatic  #4                  // Method org/apache/dubbo/common/utils/CollectionUtils.isEmpty:(Ljava/util/Collection;)Z
       4: ifeq          11
       7: invokestatic  #5                  // Method java/util/Optional.empty:()Ljava/util/Optional;
      10: areturn
      11: aload_0
      12: iconst_0
      13: invokeinterface #6,  2            // InterfaceMethod java/util/List.get:(I)Ljava/lang/Object;
      18: checkcast     #7                  // class org/apache/dubbo/common/URL
      21: invokevirtual #8                  // Method org/apache/dubbo/common/URL.getOrDefaultApplicationModel:()Lorg/apache/dubbo/rpc/model/ApplicationModel;
      24: ldc           #9                  // class org/apache/dubbo/rpc/cluster/ConfiguratorFactory
      26: invokevirtual #10                 // Method org/apache/dubbo/rpc/model/ApplicationModel.getExtensionLoader:(Ljava/lang/Class;)Lorg/apache/dubbo/common/extension/ExtensionLoader;
      29: invokevirtual #11                 // Method org/apache/dubbo/common/extension/ExtensionLoader.getAdaptiveExtension:()Ljava/lang/Object;
      32: checkcast     #9                  // class org/apache/dubbo/rpc/cluster/ConfiguratorFactory
      35: astore_1
      36: new           #12                 // class java/util/ArrayList
      39: dup
      40: aload_0
      41: invokeinterface #13,  1           // InterfaceMethod java/util/List.size:()I
      46: invokespecial #14                 // Method java/util/ArrayList."<init>":(I)V
      49: astore_2
      50: aload_0
      51: invokeinterface #15,  1           // InterfaceMethod java/util/List.iterator:()Ljava/util/Iterator;
      56: astore_3
      57: aload_3
      58: invokeinterface #16,  1           // InterfaceMethod java/util/Iterator.hasNext:()Z
      63: ifeq          152
      66: aload_3
      67: invokeinterface #17,  1           // InterfaceMethod java/util/Iterator.next:()Ljava/lang/Object;
      72: checkcast     #7                  // class org/apache/dubbo/common/URL
      75: astore        4
      77: ldc           #18                 // String empty
      79: aload         4
      81: invokevirtual #19                 // Method org/apache/dubbo/common/URL.getProtocol:()Ljava/lang/String;
      84: invokevirtual #20                 // Method java/lang/String.equals:(Ljava/lang/Object;)Z
      87: ifeq          99
      90: aload_2
      91: invokeinterface #21,  1           // InterfaceMethod java/util/List.clear:()V
      96: goto          152
      99: new           #22                 // class java/util/HashMap
     102: dup
     103: aload         4
     105: invokevirtual #23                 // Method org/apache/dubbo/common/URL.getParameters:()Ljava/util/Map;
     108: invokespecial #24                 // Method java/util/HashMap."<init>":(Ljava/util/Map;)V
     111: astore        5
     113: aload         5
     115: ldc           #25                 // String anyhost
     117: invokeinterface #26,  2           // InterfaceMethod java/util/Map.remove:(Ljava/lang/Object;)Ljava/lang/Object;
     122: pop
     123: aload         5
     125: invokestatic  #27                 // Method org/apache/dubbo/common/utils/CollectionUtils.isEmptyMap:(Ljava/util/Map;)Z
     128: ifeq          134
     131: goto          57
     134: aload_2
     135: aload_1
     136: aload         4
     138: invokeinterface #28,  2           // InterfaceMethod org/apache/dubbo/rpc/cluster/ConfiguratorFactory.getConfigurator:(Lorg/apache/dubbo/common/URL;)Lorg/apache/dubbo/rpc/cluster/Configurator;
     143: invokeinterface #29,  2           // InterfaceMethod java/util/List.add:(Ljava/lang/Object;)Z
     148: pop
     149: goto          57
     152: aload_2
     153: invokestatic  #30                 // Method java/util/Collections.sort:(Ljava/util/List;)V
     156: aload_2
     157: invokestatic  #31                 // Method java/util/Optional.of:(Ljava/lang/Object;)Ljava/util/Optional;
     160: areturn

  public default int compareTo(org.apache.dubbo.rpc.cluster.Configurator);
    Code:
       0: aload_1
       1: ifnonnull     6
       4: iconst_m1
       5: ireturn
       6: aload_0
       7: invokeinterface #32,  1           // InterfaceMethod getUrl:()Lorg/apache/dubbo/common/URL;
      12: invokevirtual #33                 // Method org/apache/dubbo/common/URL.getHost:()Ljava/lang/String;
      15: aload_1
      16: invokeinterface #32,  1           // InterfaceMethod getUrl:()Lorg/apache/dubbo/common/URL;
      21: invokevirtual #33                 // Method org/apache/dubbo/common/URL.getHost:()Ljava/lang/String;
      24: invokevirtual #34                 // Method java/lang/String.compareTo:(Ljava/lang/String;)I
      27: istore_2
      28: iload_2
      29: ifne          66
      32: aload_0
      33: invokeinterface #32,  1           // InterfaceMethod getUrl:()Lorg/apache/dubbo/common/URL;
      38: ldc           #35                 // String priority
      40: iconst_0
      41: invokevirtual #36                 // Method org/apache/dubbo/common/URL.getParameter:(Ljava/lang/String;I)I
      44: istore_3
      45: aload_1
      46: invokeinterface #32,  1           // InterfaceMethod getUrl:()Lorg/apache/dubbo/common/URL;
      51: ldc           #35                 // String priority
      53: iconst_0
      54: invokevirtual #36                 // Method org/apache/dubbo/common/URL.getParameter:(Ljava/lang/String;I)I
      57: istore        4
      59: iload_3
      60: iload         4
      62: invokestatic  #37                 // Method java/lang/Integer.compare:(II)I
      65: ireturn
      66: iload_2
      67: ireturn

  public default int compareTo(java.lang.Object);
    Code:
       0: aload_0
       1: aload_1
       2: checkcast     #38                 // class org/apache/dubbo/rpc/cluster/Configurator
       5: invokeinterface #39,  2           // InterfaceMethod compareTo:(Lorg/apache/dubbo/rpc/cluster/Configurator;)I
      10: ireturn
}
