Compiled from "Directory.java"
public interface org.apache.dubbo.rpc.cluster.Directory<T> extends org.apache.dubbo.common.Node {
  public abstract java.lang.Class<T> getInterface();

  public abstract java.util.List<org.apache.dubbo.rpc.Invoker<T>> list(org.apache.dubbo.rpc.Invocation) throws org.apache.dubbo.rpc.RpcException;

  public abstract java.util.List<org.apache.dubbo.rpc.Invoker<T>> getAllInvokers();

  public abstract org.apache.dubbo.common.URL getConsumerUrl();

  public abstract boolean isDestroyed();

  public default boolean isEmpty();
    Code:
       0: aload_0
       1: invokeinterface #1,  1            // InterfaceMethod getAllInvokers:()Ljava/util/List;
       6: invokestatic  #2                  // Method org/apache/dubbo/common/utils/CollectionUtils.isEmpty:(Ljava/util/Collection;)Z
       9: ireturn

  public default boolean isServiceDiscovery();
    Code:
       0: iconst_0
       1: ireturn

  public abstract void discordAddresses();

  public abstract org.apache.dubbo.rpc.cluster.RouterChain<T> getRouterChain();

  public abstract void addInvalidateInvoker(org.apache.dubbo.rpc.Invoker<T>);

  public abstract void addDisabledInvoker(org.apache.dubbo.rpc.Invoker<T>);

  public abstract void recoverDisabledInvoker(org.apache.dubbo.rpc.Invoker<T>);

  public default boolean isNotificationReceived();
    Code:
       0: iconst_0
       1: ireturn
}
