Compiled from "Router.java"
public interface org.apache.dubbo.rpc.cluster.Router extends java.lang.Comparable<org.apache.dubbo.rpc.cluster.Router> {
  public static final int DEFAULT_PRIORITY;

  public abstract org.apache.dubbo.common.URL getUrl();

  public default <T> java.util.List<org.apache.dubbo.rpc.Invoker<T>> route(java.util.List<org.apache.dubbo.rpc.Invoker<T>>, org.apache.dubbo.common.URL, org.apache.dubbo.rpc.Invocation) throws org.apache.dubbo.rpc.RpcException;
    Code:
       0: aconst_null
       1: areturn

  public default <T> org.apache.dubbo.rpc.cluster.router.RouterResult<org.apache.dubbo.rpc.Invoker<T>> route(java.util.List<org.apache.dubbo.rpc.Invoker<T>>, org.apache.dubbo.common.URL, org.apache.dubbo.rpc.Invocation, boolean) throws org.apache.dubbo.rpc.RpcException;
    Code:
       0: new           #2                  // class org/apache/dubbo/rpc/cluster/router/RouterResult
       3: dup
       4: aload_0
       5: aload_1
       6: aload_2
       7: aload_3
       8: invokeinterface #3,  4            // InterfaceMethod route:(Ljava/util/List;Lorg/apache/dubbo/common/URL;Lorg/apache/dubbo/rpc/Invocation;)Ljava/util/List;
      13: invokespecial #4                  // Method org/apache/dubbo/rpc/cluster/router/RouterResult."<init>":(Ljava/util/List;)V
      16: areturn

  public default <T> void notify(java.util.List<org.apache.dubbo.rpc.Invoker<T>>);
    Code:
       0: return

  public abstract boolean isRuntime();

  public abstract boolean isForce();

  public abstract int getPriority();

  public default void stop();
    Code:
       0: return

  public default int compareTo(org.apache.dubbo.rpc.cluster.Router);
    Code:
       0: aload_1
       1: ifnonnull     12
       4: new           #5                  // class java/lang/IllegalArgumentException
       7: dup
       8: invokespecial #6                  // Method java/lang/IllegalArgumentException."<init>":()V
      11: athrow
      12: aload_0
      13: invokeinterface #7,  1            // InterfaceMethod getPriority:()I
      18: aload_1
      19: invokeinterface #7,  1            // InterfaceMethod getPriority:()I
      24: invokestatic  #8                  // Method java/lang/Integer.compare:(II)I
      27: ireturn

  public default int compareTo(java.lang.Object);
    Code:
       0: aload_0
       1: aload_1
       2: checkcast     #9                  // class org/apache/dubbo/rpc/cluster/Router
       5: invokeinterface #10,  2           // InterfaceMethod compareTo:(Lorg/apache/dubbo/rpc/cluster/Router;)I
      10: ireturn
}
