Compiled from "CertDeployerListener.java"
public class org.apache.dubbo.security.cert.CertDeployerListener implements org.apache.dubbo.common.deploy.ApplicationDeployListener {
  private final org.apache.dubbo.security.cert.DubboCertManager dubboCertManager;

  public org.apache.dubbo.security.cert.CertDeployerListener(org.apache.dubbo.rpc.model.FrameworkModel);
    Code:
       0: aload_0
       1: invokespecial #1                  // Method java/lang/Object."<init>":()V
       4: aload_0
       5: aload_1
       6: invokevirtual #2                  // Method org/apache/dubbo/rpc/model/FrameworkModel.getBeanFactory:()Lorg/apache/dubbo/common/beans/factory/ScopeBeanFactory;
       9: ldc           #3                  // class org/apache/dubbo/security/cert/DubboCertManager
      11: invokevirtual #4                  // Method org/apache/dubbo/common/beans/factory/ScopeBeanFactory.getBean:(Ljava/lang/Class;)Ljava/lang/Object;
      14: checkcast     #3                  // class org/apache/dubbo/security/cert/DubboCertManager
      17: putfield      #5                  // Field dubboCertManager:Lorg/apache/dubbo/security/cert/DubboCertManager;
      20: return

  public void onInitialize(org.apache.dubbo.rpc.model.ApplicationModel);
    Code:
       0: return

  public void onStarting(org.apache.dubbo.rpc.model.ApplicationModel);
    Code:
       0: aload_1
       1: invokevirtual #6                  // Method org/apache/dubbo/rpc/model/ApplicationModel.getApplicationConfigManager:()Lorg/apache/dubbo/config/context/ConfigManager;
       4: invokevirtual #7                  // Method org/apache/dubbo/config/context/ConfigManager.getSsl:()Ljava/util/Optional;
       7: aload_0
       8: invokedynamic #8,  0              // InvokeDynamic #0:accept:(Lorg/apache/dubbo/security/cert/CertDeployerListener;)Ljava/util/function/Consumer;
      13: invokevirtual #9                  // Method java/util/Optional.ifPresent:(Ljava/util/function/Consumer;)V
      16: return

  public void onStarted(org.apache.dubbo.rpc.model.ApplicationModel);
    Code:
       0: return

  public void onStopping(org.apache.dubbo.rpc.model.ApplicationModel);
    Code:
       0: aload_0
       1: getfield      #5                  // Field dubboCertManager:Lorg/apache/dubbo/security/cert/DubboCertManager;
       4: ifnull        14
       7: aload_0
       8: getfield      #5                  // Field dubboCertManager:Lorg/apache/dubbo/security/cert/DubboCertManager;
      11: invokevirtual #10                 // Method org/apache/dubbo/security/cert/DubboCertManager.disConnect:()V
      14: return

  public void onStopped(org.apache.dubbo.rpc.model.ApplicationModel);
    Code:
       0: return

  public void onFailure(org.apache.dubbo.rpc.model.ApplicationModel, java.lang.Throwable);
    Code:
       0: aload_0
       1: getfield      #5                  // Field dubboCertManager:Lorg/apache/dubbo/security/cert/DubboCertManager;
       4: ifnull        14
       7: aload_0
       8: getfield      #5                  // Field dubboCertManager:Lorg/apache/dubbo/security/cert/DubboCertManager;
      11: invokevirtual #10                 // Method org/apache/dubbo/security/cert/DubboCertManager.disConnect:()V
      14: return

  public void onFailure(org.apache.dubbo.rpc.model.ScopeModel, java.lang.Throwable);
    Code:
       0: aload_0
       1: aload_1
       2: checkcast     #11                 // class org/apache/dubbo/rpc/model/ApplicationModel
       5: aload_2
       6: invokevirtual #12                 // Method onFailure:(Lorg/apache/dubbo/rpc/model/ApplicationModel;Ljava/lang/Throwable;)V
       9: return

  public void onStopped(org.apache.dubbo.rpc.model.ScopeModel);
    Code:
       0: aload_0
       1: aload_1
       2: checkcast     #11                 // class org/apache/dubbo/rpc/model/ApplicationModel
       5: invokevirtual #13                 // Method onStopped:(Lorg/apache/dubbo/rpc/model/ApplicationModel;)V
       8: return

  public void onStopping(org.apache.dubbo.rpc.model.ScopeModel);
    Code:
       0: aload_0
       1: aload_1
       2: checkcast     #11                 // class org/apache/dubbo/rpc/model/ApplicationModel
       5: invokevirtual #14                 // Method onStopping:(Lorg/apache/dubbo/rpc/model/ApplicationModel;)V
       8: return

  public void onStarted(org.apache.dubbo.rpc.model.ScopeModel);
    Code:
       0: aload_0
       1: aload_1
       2: checkcast     #11                 // class org/apache/dubbo/rpc/model/ApplicationModel
       5: invokevirtual #15                 // Method onStarted:(Lorg/apache/dubbo/rpc/model/ApplicationModel;)V
       8: return

  public void onStarting(org.apache.dubbo.rpc.model.ScopeModel);
    Code:
       0: aload_0
       1: aload_1
       2: checkcast     #11                 // class org/apache/dubbo/rpc/model/ApplicationModel
       5: invokevirtual #16                 // Method onStarting:(Lorg/apache/dubbo/rpc/model/ApplicationModel;)V
       8: return

  public void onInitialize(org.apache.dubbo.rpc.model.ScopeModel);
    Code:
       0: aload_0
       1: aload_1
       2: checkcast     #11                 // class org/apache/dubbo/rpc/model/ApplicationModel
       5: invokevirtual #17                 // Method onInitialize:(Lorg/apache/dubbo/rpc/model/ApplicationModel;)V
       8: return

  private void lambda$onStarting$0(org.apache.dubbo.config.SslConfig);
    Code:
       0: aload_1
       1: invokevirtual #18                 // Method org/apache/dubbo/config/SslConfig.getCaAddress:()Ljava/lang/String;
       4: invokestatic  #19                 // Method java/util/Objects.nonNull:(Ljava/lang/Object;)Z
       7: ifeq          49
      10: aload_0
      11: getfield      #5                  // Field dubboCertManager:Lorg/apache/dubbo/security/cert/DubboCertManager;
      14: ifnull        49
      17: new           #20                 // class org/apache/dubbo/security/cert/CertConfig
      20: dup
      21: aload_1
      22: invokevirtual #18                 // Method org/apache/dubbo/config/SslConfig.getCaAddress:()Ljava/lang/String;
      25: aload_1
      26: invokevirtual #21                 // Method org/apache/dubbo/config/SslConfig.getEnvType:()Ljava/lang/String;
      29: aload_1
      30: invokevirtual #22                 // Method org/apache/dubbo/config/SslConfig.getCaCertPath:()Ljava/lang/String;
      33: aload_1
      34: invokevirtual #23                 // Method org/apache/dubbo/config/SslConfig.getOidcTokenPath:()Ljava/lang/String;
      37: invokespecial #24                 // Method org/apache/dubbo/security/cert/CertConfig."<init>":(Ljava/lang/String;Ljava/lang/String;Ljava/lang/String;Ljava/lang/String;)V
      40: astore_2
      41: aload_0
      42: getfield      #5                  // Field dubboCertManager:Lorg/apache/dubbo/security/cert/DubboCertManager;
      45: aload_2
      46: invokevirtual #25                 // Method org/apache/dubbo/security/cert/DubboCertManager.connect:(Lorg/apache/dubbo/security/cert/CertConfig;)V
      49: return
}
