Compiled from "CertConfig.java"
public class org.apache.dubbo.security.cert.CertConfig {
  private final java.lang.String remoteAddress;

  private final java.lang.String envType;

  private final java.lang.String caCertPath;

  private final java.lang.String oidcTokenPath;

  private final int refreshInterval;

  public org.apache.dubbo.security.cert.CertConfig(java.lang.String, java.lang.String, java.lang.String, java.lang.String);
    Code:
       0: aload_0
       1: aload_1
       2: aload_2
       3: aload_3
       4: aload         4
       6: sipush        30000
       9: invokespecial #2                  // Method "<init>":(Ljava/lang/String;Ljava/lang/String;Ljava/lang/String;Ljava/lang/String;I)V
      12: return

  public org.apache.dubbo.security.cert.CertConfig(java.lang.String, java.lang.String, java.lang.String, java.lang.String, int);
    Code:
       0: aload_0
       1: invokespecial #3                  // Method java/lang/Object."<init>":()V
       4: aload_0
       5: aload_1
       6: putfield      #4                  // Field remoteAddress:Ljava/lang/String;
       9: aload_0
      10: aload_2
      11: putfield      #5                  // Field envType:Ljava/lang/String;
      14: aload_0
      15: aload_3
      16: putfield      #6                  // Field caCertPath:Ljava/lang/String;
      19: aload_0
      20: aload         4
      22: putfield      #7                  // Field oidcTokenPath:Ljava/lang/String;
      25: aload_0
      26: iload         5
      28: putfield      #8                  // Field refreshInterval:I
      31: return

  public java.lang.String getRemoteAddress();
    Code:
       0: aload_0
       1: getfield      #4                  // Field remoteAddress:Ljava/lang/String;
       4: areturn

  public java.lang.String getEnvType();
    Code:
       0: aload_0
       1: getfield      #5                  // Field envType:Ljava/lang/String;
       4: areturn

  public java.lang.String getCaCertPath();
    Code:
       0: aload_0
       1: getfield      #6                  // Field caCertPath:Ljava/lang/String;
       4: areturn

  public java.lang.String getOidcTokenPath();
    Code:
       0: aload_0
       1: getfield      #7                  // Field oidcTokenPath:Ljava/lang/String;
       4: areturn

  public int getRefreshInterval();
    Code:
       0: aload_0
       1: getfield      #8                  // Field refreshInterval:I
       4: ireturn

  public boolean equals(java.lang.Object);
    Code:
       0: aload_0
       1: aload_1
       2: if_acmpne     7
       5: iconst_1
       6: ireturn
       7: aload_1
       8: ifnull        22
      11: aload_0
      12: invokevirtual #9                  // Method java/lang/Object.getClass:()Ljava/lang/Class;
      15: aload_1
      16: invokevirtual #9                  // Method java/lang/Object.getClass:()Ljava/lang/Class;
      19: if_acmpeq     24
      22: iconst_0
      23: ireturn
      24: aload_1
      25: checkcast     #10                 // class org/apache/dubbo/security/cert/CertConfig
      28: astore_2
      29: aload_0
      30: getfield      #4                  // Field remoteAddress:Ljava/lang/String;
      33: aload_2
      34: getfield      #4                  // Field remoteAddress:Ljava/lang/String;
      37: invokestatic  #11                 // Method java/util/Objects.equals:(Ljava/lang/Object;Ljava/lang/Object;)Z
      40: ifeq          89
      43: aload_0
      44: getfield      #5                  // Field envType:Ljava/lang/String;
      47: aload_2
      48: getfield      #5                  // Field envType:Ljava/lang/String;
      51: invokestatic  #11                 // Method java/util/Objects.equals:(Ljava/lang/Object;Ljava/lang/Object;)Z
      54: ifeq          89
      57: aload_0
      58: getfield      #6                  // Field caCertPath:Ljava/lang/String;
      61: aload_2
      62: getfield      #6                  // Field caCertPath:Ljava/lang/String;
      65: invokestatic  #11                 // Method java/util/Objects.equals:(Ljava/lang/Object;Ljava/lang/Object;)Z
      68: ifeq          89
      71: aload_0
      72: getfield      #7                  // Field oidcTokenPath:Ljava/lang/String;
      75: aload_2
      76: getfield      #7                  // Field oidcTokenPath:Ljava/lang/String;
      79: invokestatic  #11                 // Method java/util/Objects.equals:(Ljava/lang/Object;Ljava/lang/Object;)Z
      82: ifeq          89
      85: iconst_1
      86: goto          90
      89: iconst_0
      90: ireturn

  public int hashCode();
    Code:
       0: iconst_4
       1: anewarray     #12                 // class java/lang/Object
       4: dup
       5: iconst_0
       6: aload_0
       7: getfield      #4                  // Field remoteAddress:Ljava/lang/String;
      10: aastore
      11: dup
      12: iconst_1
      13: aload_0
      14: getfield      #5                  // Field envType:Ljava/lang/String;
      17: aastore
      18: dup
      19: iconst_2
      20: aload_0
      21: getfield      #6                  // Field caCertPath:Ljava/lang/String;
      24: aastore
      25: dup
      26: iconst_3
      27: aload_0
      28: getfield      #7                  // Field oidcTokenPath:Ljava/lang/String;
      31: aastore
      32: invokestatic  #13                 // Method java/util/Objects.hash:([Ljava/lang/Object;)I
      35: ireturn
}
