Compiled from "DubboCertManager.java"
public class org.apache.dubbo.security.cert.DubboCertManager {
  private static final org.apache.dubbo.common.logger.ErrorTypeAwareLogger logger;

  private final org.apache.dubbo.rpc.model.FrameworkModel frameworkModel;

  protected volatile io.grpc.Channel channel;

  protected volatile org.apache.dubbo.security.cert.CertPair certPair;

  protected volatile org.apache.dubbo.security.cert.CertConfig certConfig;

  protected volatile java.util.concurrent.ScheduledFuture<?> refreshFuture;

  public org.apache.dubbo.security.cert.DubboCertManager(org.apache.dubbo.rpc.model.FrameworkModel);
    Code:
       0: aload_0
       1: invokespecial #2                  // Method java/lang/Object."<init>":()V
       4: aload_0
       5: aload_1
       6: putfield      #3                  // Field frameworkModel:Lorg/apache/dubbo/rpc/model/FrameworkModel;
       9: return

  public synchronized void connect(org.apache.dubbo.security.cert.CertConfig);
    Code:
       0: aload_0
       1: getfield      #4                  // Field channel:Lio/grpc/Channel;
       4: ifnull        24
       7: getstatic     #5                  // Field logger:Lorg/apache/dubbo/common/logger/ErrorTypeAwareLogger;
      10: ldc           #6                  // String 99-0
      12: ldc           #7                  // String
      14: ldc           #7                  // String
      16: ldc           #8                  // String Dubbo Cert Authority server is already connected.
      18: invokeinterface #9,  5            // InterfaceMethod org/apache/dubbo/common/logger/ErrorTypeAwareLogger.error:(Ljava/lang/String;Ljava/lang/String;Ljava/lang/String;Ljava/lang/String;)V
      23: return
      24: aload_1
      25: ifnonnull     29
      28: return
      29: aload_1
      30: invokevirtual #10                 // Method org/apache/dubbo/security/cert/CertConfig.getRemoteAddress:()Ljava/lang/String;
      33: invokestatic  #11                 // Method org/apache/dubbo/common/utils/StringUtils.isEmpty:(Ljava/lang/String;)Z
      36: ifeq          40
      39: return
      40: aload_1
      41: invokevirtual #12                 // Method org/apache/dubbo/security/cert/CertConfig.getEnvType:()Ljava/lang/String;
      44: invokestatic  #13                 // Method org/apache/dubbo/common/utils/StringUtils.isNotEmpty:(Ljava/lang/String;)Z
      47: ifeq          72
      50: ldc           #14                 // String Kubernetes
      52: aload_1
      53: invokevirtual #12                 // Method org/apache/dubbo/security/cert/CertConfig.getEnvType:()Ljava/lang/String;
      56: invokevirtual #15                 // Method java/lang/String.equalsIgnoreCase:(Ljava/lang/String;)Z
      59: ifne          72
      62: new           #16                 // class java/lang/IllegalArgumentException
      65: dup
      66: ldc           #17                 // String Only support Kubernetes env now.
      68: invokespecial #18                 // Method java/lang/IllegalArgumentException."<init>":(Ljava/lang/String;)V
      71: athrow
      72: aload_0
      73: aload_1
      74: invokevirtual #19                 // Method connect0:(Lorg/apache/dubbo/security/cert/CertConfig;)V
      77: aload_0
      78: aload_1
      79: putfield      #20                 // Field certConfig:Lorg/apache/dubbo/security/cert/CertConfig;
      82: aload_0
      83: invokevirtual #21                 // Method generateCert:()Lorg/apache/dubbo/security/cert/CertPair;
      86: pop
      87: aload_0
      88: invokevirtual #22                 // Method scheduleRefresh:()V
      91: return

  protected void scheduleRefresh();
    Code:
       0: aload_0
       1: getfield      #3                  // Field frameworkModel:Lorg/apache/dubbo/rpc/model/FrameworkModel;
       4: invokevirtual #23                 // Method org/apache/dubbo/rpc/model/FrameworkModel.getBeanFactory:()Lorg/apache/dubbo/common/beans/factory/ScopeBeanFactory;
       7: ldc           #24                 // class org/apache/dubbo/common/threadpool/manager/FrameworkExecutorRepository
       9: invokevirtual #25                 // Method org/apache/dubbo/common/beans/factory/ScopeBeanFactory.getBean:(Ljava/lang/Class;)Ljava/lang/Object;
      12: checkcast     #24                 // class org/apache/dubbo/common/threadpool/manager/FrameworkExecutorRepository
      15: astore_1
      16: aload_0
      17: aload_1
      18: invokevirtual #26                 // Method org/apache/dubbo/common/threadpool/manager/FrameworkExecutorRepository.getSharedScheduledExecutor:()Ljava/util/concurrent/ScheduledExecutorService;
      21: aload_0
      22: invokedynamic #27,  0             // InvokeDynamic #0:run:(Lorg/apache/dubbo/security/cert/DubboCertManager;)Ljava/lang/Runnable;
      27: aload_0
      28: getfield      #20                 // Field certConfig:Lorg/apache/dubbo/security/cert/CertConfig;
      31: invokevirtual #28                 // Method org/apache/dubbo/security/cert/CertConfig.getRefreshInterval:()I
      34: i2l
      35: aload_0
      36: getfield      #20                 // Field certConfig:Lorg/apache/dubbo/security/cert/CertConfig;
      39: invokevirtual #28                 // Method org/apache/dubbo/security/cert/CertConfig.getRefreshInterval:()I
      42: i2l
      43: getstatic     #29                 // Field java/util/concurrent/TimeUnit.MILLISECONDS:Ljava/util/concurrent/TimeUnit;
      46: invokeinterface #30,  7           // InterfaceMethod java/util/concurrent/ScheduledExecutorService.scheduleAtFixedRate:(Ljava/lang/Runnable;JJLjava/util/concurrent/TimeUnit;)Ljava/util/concurrent/ScheduledFuture;
      51: putfield      #31                 // Field refreshFuture:Ljava/util/concurrent/ScheduledFuture;
      54: return

  protected void connect0(org.apache.dubbo.security.cert.CertConfig);
    Code:
       0: aload_1
       1: invokevirtual #32                 // Method org/apache/dubbo/security/cert/CertConfig.getCaCertPath:()Ljava/lang/String;
       4: astore_2
       5: aload_1
       6: invokevirtual #10                 // Method org/apache/dubbo/security/cert/CertConfig.getRemoteAddress:()Ljava/lang/String;
       9: astore_3
      10: getstatic     #5                  // Field logger:Lorg/apache/dubbo/common/logger/ErrorTypeAwareLogger;
      13: new           #33                 // class java/lang/StringBuilder
      16: dup
      17: invokespecial #34                 // Method java/lang/StringBuilder."<init>":()V
      20: ldc           #35                 // String Try to connect to Dubbo Cert Authority server:
      22: invokevirtual #36                 // Method java/lang/StringBuilder.append:(Ljava/lang/String;)Ljava/lang/StringBuilder;
      25: aload_3
      26: invokevirtual #36                 // Method java/lang/StringBuilder.append:(Ljava/lang/String;)Ljava/lang/StringBuilder;
      29: ldc           #37                 // String , caCertPath:
      31: invokevirtual #36                 // Method java/lang/StringBuilder.append:(Ljava/lang/String;)Ljava/lang/StringBuilder;
      34: aload_3
      35: invokevirtual #36                 // Method java/lang/StringBuilder.append:(Ljava/lang/String;)Ljava/lang/StringBuilder;
      38: invokevirtual #38                 // Method java/lang/StringBuilder.toString:()Ljava/lang/String;
      41: invokeinterface #39,  2           // InterfaceMethod org/apache/dubbo/common/logger/ErrorTypeAwareLogger.info:(Ljava/lang/String;)V
      46: aload_2
      47: invokestatic  #13                 // Method org/apache/dubbo/common/utils/StringUtils.isNotEmpty:(Ljava/lang/String;)Z
      50: ifeq          87
      53: aload_0
      54: aload_3
      55: invokestatic  #40                 // Method io/grpc/netty/shaded/io/grpc/netty/NettyChannelBuilder.forTarget:(Ljava/lang/String;)Lio/grpc/netty/shaded/io/grpc/netty/NettyChannelBuilder;
      58: invokestatic  #41                 // Method io/grpc/netty/shaded/io/grpc/netty/GrpcSslContexts.forClient:()Lio/grpc/netty/shaded/io/netty/handler/ssl/SslContextBuilder;
      61: new           #42                 // class java/io/File
      64: dup
      65: aload_2
      66: invokespecial #43                 // Method java/io/File."<init>":(Ljava/lang/String;)V
      69: invokevirtual #44                 // Method io/grpc/netty/shaded/io/netty/handler/ssl/SslContextBuilder.trustManager:(Ljava/io/File;)Lio/grpc/netty/shaded/io/netty/handler/ssl/SslContextBuilder;
      72: invokevirtual #45                 // Method io/grpc/netty/shaded/io/netty/handler/ssl/SslContextBuilder.build:()Lio/grpc/netty/shaded/io/netty/handler/ssl/SslContext;
      75: invokevirtual #46                 // Method io/grpc/netty/shaded/io/grpc/netty/NettyChannelBuilder.sslContext:(Lio/grpc/netty/shaded/io/netty/handler/ssl/SslContext;)Lio/grpc/netty/shaded/io/grpc/netty/NettyChannelBuilder;
      78: invokevirtual #47                 // Method io/grpc/netty/shaded/io/grpc/netty/NettyChannelBuilder.build:()Lio/grpc/ManagedChannel;
      81: putfield      #4                  // Field channel:Lio/grpc/Channel;
      84: goto          129
      87: getstatic     #5                  // Field logger:Lorg/apache/dubbo/common/logger/ErrorTypeAwareLogger;
      90: ldc           #48                 // String 5-43
      92: ldc           #7                  // String
      94: ldc           #7                  // String
      96: ldc           #49                 // String No caCertPath is provided, will use insecure connection.
      98: invokeinterface #50,  5           // InterfaceMethod org/apache/dubbo/common/logger/ErrorTypeAwareLogger.warn:(Ljava/lang/String;Ljava/lang/String;Ljava/lang/String;Ljava/lang/String;)V
     103: aload_0
     104: aload_3
     105: invokestatic  #40                 // Method io/grpc/netty/shaded/io/grpc/netty/NettyChannelBuilder.forTarget:(Ljava/lang/String;)Lio/grpc/netty/shaded/io/grpc/netty/NettyChannelBuilder;
     108: invokestatic  #41                 // Method io/grpc/netty/shaded/io/grpc/netty/GrpcSslContexts.forClient:()Lio/grpc/netty/shaded/io/netty/handler/ssl/SslContextBuilder;
     111: getstatic     #51                 // Field io/grpc/netty/shaded/io/netty/handler/ssl/util/InsecureTrustManagerFactory.INSTANCE:Ljavax/net/ssl/TrustManagerFactory;
     114: invokevirtual #52                 // Method io/grpc/netty/shaded/io/netty/handler/ssl/SslContextBuilder.trustManager:(Ljavax/net/ssl/TrustManagerFactory;)Lio/grpc/netty/shaded/io/netty/handler/ssl/SslContextBuilder;
     117: invokevirtual #45                 // Method io/grpc/netty/shaded/io/netty/handler/ssl/SslContextBuilder.build:()Lio/grpc/netty/shaded/io/netty/handler/ssl/SslContext;
     120: invokevirtual #46                 // Method io/grpc/netty/shaded/io/grpc/netty/NettyChannelBuilder.sslContext:(Lio/grpc/netty/shaded/io/netty/handler/ssl/SslContext;)Lio/grpc/netty/shaded/io/grpc/netty/NettyChannelBuilder;
     123: invokevirtual #47                 // Method io/grpc/netty/shaded/io/grpc/netty/NettyChannelBuilder.build:()Lio/grpc/ManagedChannel;
     126: putfield      #4                  // Field channel:Lio/grpc/Channel;
     129: goto          162
     132: astore        4
     134: getstatic     #5                  // Field logger:Lorg/apache/dubbo/common/logger/ErrorTypeAwareLogger;
     137: ldc           #54                 // String 5-41
     139: ldc           #7                  // String
     141: ldc           #7                  // String
     143: ldc           #55                 // String Failed to load SSL cert file.
     145: aload         4
     147: invokeinterface #56,  6           // InterfaceMethod org/apache/dubbo/common/logger/ErrorTypeAwareLogger.error:(Ljava/lang/String;Ljava/lang/String;Ljava/lang/String;Ljava/lang/String;Ljava/lang/Throwable;)V
     152: new           #57                 // class java/lang/RuntimeException
     155: dup
     156: aload         4
     158: invokespecial #58                 // Method java/lang/RuntimeException."<init>":(Ljava/lang/Throwable;)V
     161: athrow
     162: return
    Exception table:
       from    to  target type
          46   129   132   Class java/lang/Exception

  public synchronized void disConnect();
    Code:
       0: aload_0
       1: getfield      #31                 // Field refreshFuture:Ljava/util/concurrent/ScheduledFuture;
       4: ifnull        23
       7: aload_0
       8: getfield      #31                 // Field refreshFuture:Ljava/util/concurrent/ScheduledFuture;
      11: iconst_1
      12: invokeinterface #59,  2           // InterfaceMethod java/util/concurrent/ScheduledFuture.cancel:(Z)Z
      17: pop
      18: aload_0
      19: aconst_null
      20: putfield      #31                 // Field refreshFuture:Ljava/util/concurrent/ScheduledFuture;
      23: aload_0
      24: getfield      #4                  // Field channel:Lio/grpc/Channel;
      27: ifnull        35
      30: aload_0
      31: aconst_null
      32: putfield      #4                  // Field channel:Lio/grpc/Channel;
      35: return

  public boolean isConnected();
    Code:
       0: aload_0
       1: getfield      #20                 // Field certConfig:Lorg/apache/dubbo/security/cert/CertConfig;
       4: ifnull        25
       7: aload_0
       8: getfield      #4                  // Field channel:Lio/grpc/Channel;
      11: ifnull        25
      14: aload_0
      15: getfield      #60                 // Field certPair:Lorg/apache/dubbo/security/cert/CertPair;
      18: ifnull        25
      21: iconst_1
      22: goto          26
      25: iconst_0
      26: ireturn

  protected org.apache.dubbo.security.cert.CertPair generateCert();
    Code:
       0: aload_0
       1: getfield      #60                 // Field certPair:Lorg/apache/dubbo/security/cert/CertPair;
       4: ifnull        22
       7: aload_0
       8: getfield      #60                 // Field certPair:Lorg/apache/dubbo/security/cert/CertPair;
      11: invokevirtual #61                 // Method org/apache/dubbo/security/cert/CertPair.isExpire:()Z
      14: ifne          22
      17: aload_0
      18: getfield      #60                 // Field certPair:Lorg/apache/dubbo/security/cert/CertPair;
      21: areturn
      22: aload_0
      23: dup
      24: astore_1
      25: monitorenter
      26: aload_0
      27: getfield      #60                 // Field certPair:Lorg/apache/dubbo/security/cert/CertPair;
      30: ifnull        43
      33: aload_0
      34: getfield      #60                 // Field certPair:Lorg/apache/dubbo/security/cert/CertPair;
      37: invokevirtual #61                 // Method org/apache/dubbo/security/cert/CertPair.isExpire:()Z
      40: ifeq          107
      43: getstatic     #5                  // Field logger:Lorg/apache/dubbo/common/logger/ErrorTypeAwareLogger;
      46: ldc           #62                 // String Try to generate cert from Dubbo Certificate Authority.
      48: invokeinterface #39,  2           // InterfaceMethod org/apache/dubbo/common/logger/ErrorTypeAwareLogger.info:(Ljava/lang/String;)V
      53: aload_0
      54: invokevirtual #63                 // Method refreshCert:()Lorg/apache/dubbo/security/cert/CertPair;
      57: astore_2
      58: aload_2
      59: ifnull        70
      62: aload_0
      63: aload_2
      64: putfield      #60                 // Field certPair:Lorg/apache/dubbo/security/cert/CertPair;
      67: goto          86
      70: getstatic     #5                  // Field logger:Lorg/apache/dubbo/common/logger/ErrorTypeAwareLogger;
      73: ldc           #64                 // String 5-42
      75: ldc           #7                  // String
      77: ldc           #7                  // String
      79: ldc           #65                 // String Generate Cert from Dubbo Certificate Authority failed.
      81: invokeinterface #9,  5            // InterfaceMethod org/apache/dubbo/common/logger/ErrorTypeAwareLogger.error:(Ljava/lang/String;Ljava/lang/String;Ljava/lang/String;Ljava/lang/String;)V
      86: goto          107
      89: astore_2
      90: getstatic     #5                  // Field logger:Lorg/apache/dubbo/common/logger/ErrorTypeAwareLogger;
      93: ldc           #66                 // String 1-26
      95: ldc           #7                  // String
      97: ldc           #7                  // String
      99: ldc           #67                 // String Generate Cert from Istio failed.
     101: aload_2
     102: invokeinterface #56,  6           // InterfaceMethod org/apache/dubbo/common/logger/ErrorTypeAwareLogger.error:(Ljava/lang/String;Ljava/lang/String;Ljava/lang/String;Ljava/lang/String;Ljava/lang/Throwable;)V
     107: aload_1
     108: monitorexit
     109: goto          117
     112: astore_3
     113: aload_1
     114: monitorexit
     115: aload_3
     116: athrow
     117: aload_0
     118: getfield      #60                 // Field certPair:Lorg/apache/dubbo/security/cert/CertPair;
     121: areturn
    Exception table:
       from    to  target type
          43    86    89   Class java/lang/Exception
          26   109   112   any
         112   115   112   any

  protected org.apache.dubbo.security.cert.CertPair refreshCert() throws java.io.IOException;
    Code:
       0: invokestatic  #68                 // Method signWithEcdsa:()Lorg/apache/dubbo/security/cert/DubboCertManager$KeyPair;
       3: astore_1
       4: aload_1
       5: ifnonnull     12
       8: invokestatic  #69                 // Method signWithRsa:()Lorg/apache/dubbo/security/cert/DubboCertManager$KeyPair;
      11: astore_1
      12: aload_1
      13: ifnonnull     34
      16: getstatic     #5                  // Field logger:Lorg/apache/dubbo/common/logger/ErrorTypeAwareLogger;
      19: ldc           #64                 // String 5-42
      21: ldc           #7                  // String
      23: ldc           #7                  // String
      25: ldc           #70                 // String Generate Key failed. Please check if your system support.
      27: invokeinterface #9,  5            // InterfaceMethod org/apache/dubbo/common/logger/ErrorTypeAwareLogger.error:(Ljava/lang/String;Ljava/lang/String;Ljava/lang/String;Ljava/lang/String;)V
      32: aconst_null
      33: areturn
      34: aload_0
      35: aload_1
      36: invokespecial #71                 // Method generateCsr:(Lorg/apache/dubbo/security/cert/DubboCertManager$KeyPair;)Ljava/lang/String;
      39: astore_2
      40: aload_0
      41: getfield      #4                  // Field channel:Lio/grpc/Channel;
      44: invokestatic  #72                 // Method org/apache/dubbo/auth/v1alpha1/DubboCertificateServiceGrpc.newBlockingStub:(Lio/grpc/Channel;)Lorg/apache/dubbo/auth/v1alpha1/DubboCertificateServiceGrpc$DubboCertificateServiceBlockingStub;
      47: astore_3
      48: aload_0
      49: aload_3
      50: invokespecial #73                 // Method setHeaderIfNeed:(Lorg/apache/dubbo/auth/v1alpha1/DubboCertificateServiceGrpc$DubboCertificateServiceBlockingStub;)Lorg/apache/dubbo/auth/v1alpha1/DubboCertificateServiceGrpc$DubboCertificateServiceBlockingStub;
      53: astore_3
      54: aload_0
      55: aload_1
      56: invokespecial #74                 // Method generatePrivatePemKey:(Lorg/apache/dubbo/security/cert/DubboCertManager$KeyPair;)Ljava/lang/String;
      59: astore        4
      61: aload_3
      62: aload_0
      63: aload_2
      64: invokespecial #75                 // Method generateRequest:(Ljava/lang/String;)Lorg/apache/dubbo/auth/v1alpha1/DubboCertificateRequest;
      67: invokevirtual #76                 // Method org/apache/dubbo/auth/v1alpha1/DubboCertificateServiceGrpc$DubboCertificateServiceBlockingStub.createCertificate:(Lorg/apache/dubbo/auth/v1alpha1/DubboCertificateRequest;)Lorg/apache/dubbo/auth/v1alpha1/DubboCertificateResponse;
      70: astore        5
      72: aload         5
      74: ifnull        85
      77: aload         5
      79: invokevirtual #77                 // Method org/apache/dubbo/auth/v1alpha1/DubboCertificateResponse.getSuccess:()Z
      82: ifne          134
      85: getstatic     #5                  // Field logger:Lorg/apache/dubbo/common/logger/ErrorTypeAwareLogger;
      88: ldc           #64                 // String 5-42
      90: ldc           #7                  // String
      92: ldc           #7                  // String
      94: new           #33                 // class java/lang/StringBuilder
      97: dup
      98: invokespecial #34                 // Method java/lang/StringBuilder."<init>":()V
     101: ldc           #78                 // String Failed to generate cert from Dubbo Certificate Authority. Message:
     103: invokevirtual #36                 // Method java/lang/StringBuilder.append:(Ljava/lang/String;)Ljava/lang/StringBuilder;
     106: aload         5
     108: ifnonnull     116
     111: ldc           #79                 // String null
     113: goto          121
     116: aload         5
     118: invokevirtual #80                 // Method org/apache/dubbo/auth/v1alpha1/DubboCertificateResponse.getMessage:()Ljava/lang/String;
     121: invokevirtual #36                 // Method java/lang/StringBuilder.append:(Ljava/lang/String;)Ljava/lang/StringBuilder;
     124: invokevirtual #38                 // Method java/lang/StringBuilder.toString:()Ljava/lang/String;
     127: invokeinterface #9,  5            // InterfaceMethod org/apache/dubbo/common/logger/ErrorTypeAwareLogger.error:(Ljava/lang/String;Ljava/lang/String;Ljava/lang/String;Ljava/lang/String;)V
     132: aconst_null
     133: areturn
     134: getstatic     #5                  // Field logger:Lorg/apache/dubbo/common/logger/ErrorTypeAwareLogger;
     137: new           #33                 // class java/lang/StringBuilder
     140: dup
     141: invokespecial #34                 // Method java/lang/StringBuilder."<init>":()V
     144: ldc           #81                 // String Successfully generate cert from Dubbo Certificate Authority. Cert expire time:
     146: invokevirtual #36                 // Method java/lang/StringBuilder.append:(Ljava/lang/String;)Ljava/lang/StringBuilder;
     149: aload         5
     151: invokevirtual #82                 // Method org/apache/dubbo/auth/v1alpha1/DubboCertificateResponse.getExpireTime:()J
     154: invokevirtual #83                 // Method java/lang/StringBuilder.append:(J)Ljava/lang/StringBuilder;
     157: invokevirtual #38                 // Method java/lang/StringBuilder.toString:()Ljava/lang/String;
     160: invokeinterface #39,  2           // InterfaceMethod org/apache/dubbo/common/logger/ErrorTypeAwareLogger.info:(Ljava/lang/String;)V
     165: new           #84                 // class org/apache/dubbo/security/cert/CertPair
     168: dup
     169: aload         4
     171: aload         5
     173: invokevirtual #85                 // Method org/apache/dubbo/auth/v1alpha1/DubboCertificateResponse.getCertPem:()Ljava/lang/String;
     176: ldc           #86                 // String \n
     178: aload         5
     180: invokevirtual #87                 // Method org/apache/dubbo/auth/v1alpha1/DubboCertificateResponse.getTrustCertsList:()Lcom/google/protobuf/ProtocolStringList;
     183: invokestatic  #88                 // Method java/lang/String.join:(Ljava/lang/CharSequence;Ljava/lang/Iterable;)Ljava/lang/String;
     186: aload         5
     188: invokevirtual #82                 // Method org/apache/dubbo/auth/v1alpha1/DubboCertificateResponse.getExpireTime:()J
     191: invokespecial #89                 // Method org/apache/dubbo/security/cert/CertPair."<init>":(Ljava/lang/String;Ljava/lang/String;Ljava/lang/String;J)V
     194: areturn

  private org.apache.dubbo.auth.v1alpha1.DubboCertificateServiceGrpc$DubboCertificateServiceBlockingStub setHeaderIfNeed(org.apache.dubbo.auth.v1alpha1.DubboCertificateServiceGrpc$DubboCertificateServiceBlockingStub) throws java.io.IOException;
    Code:
       0: aload_0
       1: getfield      #20                 // Field certConfig:Lorg/apache/dubbo/security/cert/CertConfig;
       4: invokevirtual #90                 // Method org/apache/dubbo/security/cert/CertConfig.getOidcTokenPath:()Ljava/lang/String;
       7: astore_2
       8: aload_2
       9: invokestatic  #13                 // Method org/apache/dubbo/common/utils/StringUtils.isNotEmpty:(Ljava/lang/String;)Z
      12: ifeq          146
      15: new           #91                 // class io/grpc/Metadata
      18: dup
      19: invokespecial #92                 // Method io/grpc/Metadata."<init>":()V
      22: astore_3
      23: ldc           #93                 // String authorization
      25: getstatic     #94                 // Field io/grpc/Metadata.ASCII_STRING_MARSHALLER:Lio/grpc/Metadata$AsciiMarshaller;
      28: invokestatic  #95                 // Method io/grpc/Metadata$Key.of:(Ljava/lang/String;Lio/grpc/Metadata$AsciiMarshaller;)Lio/grpc/Metadata$Key;
      31: astore        4
      33: aload_3
      34: aload         4
      36: new           #33                 // class java/lang/StringBuilder
      39: dup
      40: invokespecial #34                 // Method java/lang/StringBuilder."<init>":()V
      43: ldc           #96                 // String Bearer
      45: invokevirtual #36                 // Method java/lang/StringBuilder.append:(Ljava/lang/String;)Ljava/lang/StringBuilder;
      48: new           #97                 // class java/io/FileReader
      51: dup
      52: aload_2
      53: invokespecial #98                 // Method java/io/FileReader."<init>":(Ljava/lang/String;)V
      56: invokestatic  #99                 // Method org/apache/dubbo/common/utils/IOUtils.read:(Ljava/io/Reader;)Ljava/lang/String;
      59: ldc           #86                 // String \n
      61: ldc           #7                  // String
      63: invokevirtual #100                // Method java/lang/String.replace:(Ljava/lang/CharSequence;Ljava/lang/CharSequence;)Ljava/lang/String;
      66: ldc           #101                // String \t
      68: ldc           #7                  // String
      70: invokevirtual #100                // Method java/lang/String.replace:(Ljava/lang/CharSequence;Ljava/lang/CharSequence;)Ljava/lang/String;
      73: ldc           #102                // String \r
      75: ldc           #7                  // String
      77: invokevirtual #100                // Method java/lang/String.replace:(Ljava/lang/CharSequence;Ljava/lang/CharSequence;)Ljava/lang/String;
      80: invokevirtual #103                // Method java/lang/String.trim:()Ljava/lang/String;
      83: invokevirtual #36                 // Method java/lang/StringBuilder.append:(Ljava/lang/String;)Ljava/lang/StringBuilder;
      86: invokevirtual #38                 // Method java/lang/StringBuilder.toString:()Ljava/lang/String;
      89: invokevirtual #104                // Method io/grpc/Metadata.put:(Lio/grpc/Metadata$Key;Ljava/lang/Object;)V
      92: aload_1
      93: iconst_1
      94: anewarray     #105                // class io/grpc/ClientInterceptor
      97: dup
      98: iconst_0
      99: aload_3
     100: invokestatic  #106                // Method io/grpc/stub/MetadataUtils.newAttachHeadersInterceptor:(Lio/grpc/Metadata;)Lio/grpc/ClientInterceptor;
     103: aastore
     104: invokevirtual #107                // Method org/apache/dubbo/auth/v1alpha1/DubboCertificateServiceGrpc$DubboCertificateServiceBlockingStub.withInterceptors:([Lio/grpc/ClientInterceptor;)Lio/grpc/stub/AbstractStub;
     107: checkcast     #108                // class org/apache/dubbo/auth/v1alpha1/DubboCertificateServiceGrpc$DubboCertificateServiceBlockingStub
     110: astore_1
     111: getstatic     #5                  // Field logger:Lorg/apache/dubbo/common/logger/ErrorTypeAwareLogger;
     114: new           #33                 // class java/lang/StringBuilder
     117: dup
     118: invokespecial #34                 // Method java/lang/StringBuilder."<init>":()V
     121: ldc           #109                // String Use oidc token from
     123: invokevirtual #36                 // Method java/lang/StringBuilder.append:(Ljava/lang/String;)Ljava/lang/StringBuilder;
     126: aload_2
     127: invokevirtual #36                 // Method java/lang/StringBuilder.append:(Ljava/lang/String;)Ljava/lang/StringBuilder;
     130: ldc           #110                // String  to connect to Dubbo Certificate Authority.
     132: invokevirtual #36                 // Method java/lang/StringBuilder.append:(Ljava/lang/String;)Ljava/lang/StringBuilder;
     135: invokevirtual #38                 // Method java/lang/StringBuilder.toString:()Ljava/lang/String;
     138: invokeinterface #39,  2           // InterfaceMethod org/apache/dubbo/common/logger/ErrorTypeAwareLogger.info:(Ljava/lang/String;)V
     143: goto          162
     146: getstatic     #5                  // Field logger:Lorg/apache/dubbo/common/logger/ErrorTypeAwareLogger;
     149: ldc           #48                 // String 5-43
     151: ldc           #7                  // String
     153: ldc           #7                  // String
     155: ldc           #111                // String Use insecure connection to connect to Dubbo Certificate Authority. Reason: No oidc token is provided.
     157: invokeinterface #50,  5           // InterfaceMethod org/apache/dubbo/common/logger/ErrorTypeAwareLogger.warn:(Ljava/lang/String;Ljava/lang/String;Ljava/lang/String;Ljava/lang/String;)V
     162: aload_1
     163: areturn

  protected static org.apache.dubbo.security.cert.DubboCertManager$KeyPair signWithRsa();
    Code:
       0: aconst_null
       1: astore_0
       2: ldc           #112                // String RSA
       4: invokestatic  #113                // Method java/security/KeyPairGenerator.getInstance:(Ljava/lang/String;)Ljava/security/KeyPairGenerator;
       7: astore_1
       8: aload_1
       9: sipush        4096
      12: invokevirtual #114                // Method java/security/KeyPairGenerator.initialize:(I)V
      15: aload_1
      16: invokevirtual #115                // Method java/security/KeyPairGenerator.generateKeyPair:()Ljava/security/KeyPair;
      19: astore_2
      20: aload_2
      21: invokevirtual #116                // Method java/security/KeyPair.getPublic:()Ljava/security/PublicKey;
      24: astore_3
      25: aload_2
      26: invokevirtual #117                // Method java/security/KeyPair.getPrivate:()Ljava/security/PrivateKey;
      29: astore        4
      31: new           #118                // class org/bouncycastle/operator/jcajce/JcaContentSignerBuilder
      34: dup
      35: ldc           #119                // String SHA256WithRSA
      37: invokespecial #120                // Method org/bouncycastle/operator/jcajce/JcaContentSignerBuilder."<init>":(Ljava/lang/String;)V
      40: aload_2
      41: invokevirtual #117                // Method java/security/KeyPair.getPrivate:()Ljava/security/PrivateKey;
      44: invokevirtual #121                // Method org/bouncycastle/operator/jcajce/JcaContentSignerBuilder.build:(Ljava/security/PrivateKey;)Lorg/bouncycastle/operator/ContentSigner;
      47: astore        5
      49: new           #122                // class org/apache/dubbo/security/cert/DubboCertManager$KeyPair
      52: dup
      53: aload_3
      54: aload         4
      56: aload         5
      58: invokespecial #123                // Method org/apache/dubbo/security/cert/DubboCertManager$KeyPair."<init>":(Ljava/security/PublicKey;Ljava/security/PrivateKey;Lorg/bouncycastle/operator/ContentSigner;)V
      61: astore_0
      62: goto          83
      65: astore_1
      66: getstatic     #5                  // Field logger:Lorg/apache/dubbo/common/logger/ErrorTypeAwareLogger;
      69: ldc           #64                 // String 5-42
      71: ldc           #7                  // String
      73: ldc           #7                  // String
      75: ldc           #126                // String Generate Key with SHA256WithRSA algorithm failed. Please check if your system support.
      77: aload_1
      78: invokeinterface #56,  6           // InterfaceMethod org/apache/dubbo/common/logger/ErrorTypeAwareLogger.error:(Ljava/lang/String;Ljava/lang/String;Ljava/lang/String;Ljava/lang/String;Ljava/lang/Throwable;)V
      83: aload_0
      84: areturn
    Exception table:
       from    to  target type
           2    62    65   Class java/security/NoSuchAlgorithmException
           2    62    65   Class org/bouncycastle/operator/OperatorCreationException

  protected static org.apache.dubbo.security.cert.DubboCertManager$KeyPair signWithEcdsa();
    Code:
       0: aconst_null
       1: astore_0
       2: new           #127                // class java/security/spec/ECGenParameterSpec
       5: dup
       6: ldc           #128                // String secp256r1
       8: invokespecial #129                // Method java/security/spec/ECGenParameterSpec."<init>":(Ljava/lang/String;)V
      11: astore_1
      12: ldc           #130                // String EC
      14: invokestatic  #113                // Method java/security/KeyPairGenerator.getInstance:(Ljava/lang/String;)Ljava/security/KeyPairGenerator;
      17: astore_2
      18: aload_2
      19: aload_1
      20: new           #131                // class java/security/SecureRandom
      23: dup
      24: invokespecial #132                // Method java/security/SecureRandom."<init>":()V
      27: invokevirtual #133                // Method java/security/KeyPairGenerator.initialize:(Ljava/security/spec/AlgorithmParameterSpec;Ljava/security/SecureRandom;)V
      30: aload_2
      31: invokevirtual #115                // Method java/security/KeyPairGenerator.generateKeyPair:()Ljava/security/KeyPair;
      34: astore_3
      35: aload_3
      36: invokevirtual #116                // Method java/security/KeyPair.getPublic:()Ljava/security/PublicKey;
      39: astore        4
      41: aload_3
      42: invokevirtual #117                // Method java/security/KeyPair.getPrivate:()Ljava/security/PrivateKey;
      45: astore        5
      47: new           #118                // class org/bouncycastle/operator/jcajce/JcaContentSignerBuilder
      50: dup
      51: ldc           #134                // String SHA256withECDSA
      53: invokespecial #120                // Method org/bouncycastle/operator/jcajce/JcaContentSignerBuilder."<init>":(Ljava/lang/String;)V
      56: aload         5
      58: invokevirtual #121                // Method org/bouncycastle/operator/jcajce/JcaContentSignerBuilder.build:(Ljava/security/PrivateKey;)Lorg/bouncycastle/operator/ContentSigner;
      61: astore        6
      63: new           #122                // class org/apache/dubbo/security/cert/DubboCertManager$KeyPair
      66: dup
      67: aload         4
      69: aload         5
      71: aload         6
      73: invokespecial #123                // Method org/apache/dubbo/security/cert/DubboCertManager$KeyPair."<init>":(Ljava/security/PublicKey;Ljava/security/PrivateKey;Lorg/bouncycastle/operator/ContentSigner;)V
      76: astore_0
      77: goto          98
      80: astore_1
      81: getstatic     #5                  // Field logger:Lorg/apache/dubbo/common/logger/ErrorTypeAwareLogger;
      84: ldc           #64                 // String 5-42
      86: ldc           #7                  // String
      88: ldc           #7                  // String
      90: ldc           #136                // String Generate Key with secp256r1 algorithm failed. Please check if your system support. Will attempt to generate with RSA2048.
      92: aload_1
      93: invokeinterface #56,  6           // InterfaceMethod org/apache/dubbo/common/logger/ErrorTypeAwareLogger.error:(Ljava/lang/String;Ljava/lang/String;Ljava/lang/String;Ljava/lang/String;Ljava/lang/Throwable;)V
      98: aload_0
      99: areturn
    Exception table:
       from    to  target type
           2    77    80   Class java/security/NoSuchAlgorithmException
           2    77    80   Class java/security/InvalidAlgorithmParameterException
           2    77    80   Class org/bouncycastle/operator/OperatorCreationException

  private org.apache.dubbo.auth.v1alpha1.DubboCertificateRequest generateRequest(java.lang.String);
    Code:
       0: invokestatic  #137                // Method org/apache/dubbo/auth/v1alpha1/DubboCertificateRequest.newBuilder:()Lorg/apache/dubbo/auth/v1alpha1/DubboCertificateRequest$Builder;
       3: aload_1
       4: invokevirtual #138                // Method org/apache/dubbo/auth/v1alpha1/DubboCertificateRequest$Builder.setCsr:(Ljava/lang/String;)Lorg/apache/dubbo/auth/v1alpha1/DubboCertificateRequest$Builder;
       7: ldc           #139                // String CONNECTION
       9: invokevirtual #140                // Method org/apache/dubbo/auth/v1alpha1/DubboCertificateRequest$Builder.setType:(Ljava/lang/String;)Lorg/apache/dubbo/auth/v1alpha1/DubboCertificateRequest$Builder;
      12: invokevirtual #141                // Method org/apache/dubbo/auth/v1alpha1/DubboCertificateRequest$Builder.build:()Lorg/apache/dubbo/auth/v1alpha1/DubboCertificateRequest;
      15: areturn

  private java.lang.String generatePrivatePemKey(org.apache.dubbo.security.cert.DubboCertManager$KeyPair) throws java.io.IOException;
    Code:
       0: aload_0
       1: ldc           #142                // String RSA PRIVATE KEY
       3: aload_1
       4: invokevirtual #143                // Method org/apache/dubbo/security/cert/DubboCertManager$KeyPair.getPrivateKey:()Ljava/security/PrivateKey;
       7: invokeinterface #144,  1          // InterfaceMethod java/security/PrivateKey.getEncoded:()[B
      12: invokespecial #145                // Method generatePemKey:(Ljava/lang/String;[B)Ljava/lang/String;
      15: astore_2
      16: getstatic     #5                  // Field logger:Lorg/apache/dubbo/common/logger/ErrorTypeAwareLogger;
      19: invokeinterface #146,  1          // InterfaceMethod org/apache/dubbo/common/logger/ErrorTypeAwareLogger.isDebugEnabled:()Z
      24: ifeq          54
      27: getstatic     #5                  // Field logger:Lorg/apache/dubbo/common/logger/ErrorTypeAwareLogger;
      30: new           #33                 // class java/lang/StringBuilder
      33: dup
      34: invokespecial #34                 // Method java/lang/StringBuilder."<init>":()V
      37: ldc           #147                // String Generated Private Key. \n
      39: invokevirtual #36                 // Method java/lang/StringBuilder.append:(Ljava/lang/String;)Ljava/lang/StringBuilder;
      42: aload_2
      43: invokevirtual #36                 // Method java/lang/StringBuilder.append:(Ljava/lang/String;)Ljava/lang/StringBuilder;
      46: invokevirtual #38                 // Method java/lang/StringBuilder.toString:()Ljava/lang/String;
      49: invokeinterface #148,  2          // InterfaceMethod org/apache/dubbo/common/logger/ErrorTypeAwareLogger.debug:(Ljava/lang/String;)V
      54: aload_2
      55: areturn

  private java.lang.String generatePemKey(java.lang.String, byte[]) throws java.io.IOException;
    Code:
       0: new           #149                // class org/bouncycastle/util/io/pem/PemObject
       3: dup
       4: aload_1
       5: aload_2
       6: invokespecial #150                // Method org/bouncycastle/util/io/pem/PemObject."<init>":(Ljava/lang/String;[B)V
       9: astore_3
      10: new           #151                // class java/io/StringWriter
      13: dup
      14: invokespecial #152                // Method java/io/StringWriter."<init>":()V
      17: astore        4
      19: new           #153                // class org/bouncycastle/openssl/jcajce/JcaPEMWriter
      22: dup
      23: aload         4
      25: invokespecial #154                // Method org/bouncycastle/openssl/jcajce/JcaPEMWriter."<init>":(Ljava/io/Writer;)V
      28: astore        5
      30: aload         5
      32: aload_3
      33: invokevirtual #155                // Method org/bouncycastle/openssl/jcajce/JcaPEMWriter.writeObject:(Lorg/bouncycastle/util/io/pem/PemObjectGenerator;)V
      36: aload         5
      38: invokevirtual #156                // Method org/bouncycastle/openssl/jcajce/JcaPEMWriter.close:()V
      41: aload         4
      43: invokevirtual #157                // Method java/io/StringWriter.close:()V
      46: aload         4
      48: invokevirtual #158                // Method java/io/StringWriter.toString:()Ljava/lang/String;
      51: areturn

  private java.lang.String generateCsr(org.apache.dubbo.security.cert.DubboCertManager$KeyPair) throws java.io.IOException;
    Code:
       0: new           #159                // class org/bouncycastle/pkcs/jcajce/JcaPKCS10CertificationRequestBuilder
       3: dup
       4: new           #160                // class org/bouncycastle/asn1/x500/X500Name
       7: dup
       8: ldc           #161                // String O=cluster.domain
      10: invokespecial #162                // Method org/bouncycastle/asn1/x500/X500Name."<init>":(Ljava/lang/String;)V
      13: aload_1
      14: invokevirtual #163                // Method org/apache/dubbo/security/cert/DubboCertManager$KeyPair.getPublicKey:()Ljava/security/PublicKey;
      17: invokespecial #164                // Method org/bouncycastle/pkcs/jcajce/JcaPKCS10CertificationRequestBuilder."<init>":(Lorg/bouncycastle/asn1/x500/X500Name;Ljava/security/PublicKey;)V
      20: aload_1
      21: invokevirtual #165                // Method org/apache/dubbo/security/cert/DubboCertManager$KeyPair.getSigner:()Lorg/bouncycastle/operator/ContentSigner;
      24: invokevirtual #166                // Method org/bouncycastle/pkcs/jcajce/JcaPKCS10CertificationRequestBuilder.build:(Lorg/bouncycastle/operator/ContentSigner;)Lorg/bouncycastle/pkcs/PKCS10CertificationRequest;
      27: astore_2
      28: aload_0
      29: ldc           #167                // String CERTIFICATE REQUEST
      31: aload_2
      32: invokevirtual #168                // Method org/bouncycastle/pkcs/PKCS10CertificationRequest.getEncoded:()[B
      35: invokespecial #145                // Method generatePemKey:(Ljava/lang/String;[B)Ljava/lang/String;
      38: astore_3
      39: getstatic     #5                  // Field logger:Lorg/apache/dubbo/common/logger/ErrorTypeAwareLogger;
      42: invokeinterface #146,  1          // InterfaceMethod org/apache/dubbo/common/logger/ErrorTypeAwareLogger.isDebugEnabled:()Z
      47: ifeq          77
      50: getstatic     #5                  // Field logger:Lorg/apache/dubbo/common/logger/ErrorTypeAwareLogger;
      53: new           #33                 // class java/lang/StringBuilder
      56: dup
      57: invokespecial #34                 // Method java/lang/StringBuilder."<init>":()V
      60: ldc           #169                // String CSR Request to Dubbo Certificate Authorization. \n
      62: invokevirtual #36                 // Method java/lang/StringBuilder.append:(Ljava/lang/String;)Ljava/lang/StringBuilder;
      65: aload_3
      66: invokevirtual #36                 // Method java/lang/StringBuilder.append:(Ljava/lang/String;)Ljava/lang/StringBuilder;
      69: invokevirtual #38                 // Method java/lang/StringBuilder.toString:()Ljava/lang/String;
      72: invokeinterface #148,  2          // InterfaceMethod org/apache/dubbo/common/logger/ErrorTypeAwareLogger.debug:(Ljava/lang/String;)V
      77: aload_3
      78: areturn

  static {};
    Code:
       0: ldc           #170                // class org/apache/dubbo/security/cert/DubboCertManager
       2: invokestatic  #171                // Method org/apache/dubbo/common/logger/LoggerFactory.getErrorTypeAwareLogger:(Ljava/lang/Class;)Lorg/apache/dubbo/common/logger/ErrorTypeAwareLogger;
       5: putstatic     #5                  // Field logger:Lorg/apache/dubbo/common/logger/ErrorTypeAwareLogger;
       8: return
}
