Compiled from "DubboCertManager.java"
public class org.apache.dubbo.security.cert.DubboCertManager$KeyPair {
  private final java.security.PublicKey publicKey;

  private final java.security.PrivateKey privateKey;

  private final org.bouncycastle.operator.ContentSigner signer;

  public org.apache.dubbo.security.cert.DubboCertManager$KeyPair(java.security.PublicKey, java.security.PrivateKey, org.bouncycastle.operator.ContentSigner);
    Code:
       0: aload_0
       1: invokespecial #1                  // Method java/lang/Object."<init>":()V
       4: aload_0
       5: aload_1
       6: putfield      #2                  // Field publicKey:Ljava/security/PublicKey;
       9: aload_0
      10: aload_2
      11: putfield      #3                  // Field privateKey:Ljava/security/PrivateKey;
      14: aload_0
      15: aload_3
      16: putfield      #4                  // Field signer:Lorg/bouncycastle/operator/ContentSigner;
      19: return

  public java.security.PublicKey getPublicKey();
    Code:
       0: aload_0
       1: getfield      #2                  // Field publicKey:Ljava/security/PublicKey;
       4: areturn

  public java.security.PrivateKey getPrivateKey();
    Code:
       0: aload_0
       1: getfield      #3                  // Field privateKey:Ljava/security/PrivateKey;
       4: areturn

  public org.bouncycastle.operator.ContentSigner getSigner();
    Code:
       0: aload_0
       1: getfield      #4                  // Field signer:Lorg/bouncycastle/operator/ContentSigner;
       4: areturn
}
