Compiled from "DubboCertProvider.java"
public class org.apache.dubbo.security.cert.DubboCertProvider implements org.apache.dubbo.common.ssl.CertProvider {
  private final org.apache.dubbo.security.cert.DubboCertManager dubboCertManager;

  public org.apache.dubbo.security.cert.DubboCertProvider(org.apache.dubbo.rpc.model.FrameworkModel);
    Code:
       0: aload_0
       1: invokespecial #1                  // Method java/lang/Object."<init>":()V
       4: aload_0
       5: aload_1
       6: invokevirtual #2                  // Method org/apache/dubbo/rpc/model/FrameworkModel.getBeanFactory:()Lorg/apache/dubbo/common/beans/factory/ScopeBeanFactory;
       9: ldc           #3                  // class org/apache/dubbo/security/cert/DubboCertManager
      11: invokevirtual #4                  // Method org/apache/dubbo/common/beans/factory/ScopeBeanFactory.getBean:(Ljava/lang/Class;)Ljava/lang/Object;
      14: checkcast     #3                  // class org/apache/dubbo/security/cert/DubboCertManager
      17: putfield      #5                  // Field dubboCertManager:Lorg/apache/dubbo/security/cert/DubboCertManager;
      20: return

  public boolean isSupport(org.apache.dubbo.common.URL);
    Code:
       0: aload_0
       1: getfield      #5                  // Field dubboCertManager:Lorg/apache/dubbo/security/cert/DubboCertManager;
       4: ifnull        21
       7: aload_0
       8: getfield      #5                  // Field dubboCertManager:Lorg/apache/dubbo/security/cert/DubboCertManager;
      11: invokevirtual #6                  // Method org/apache/dubbo/security/cert/DubboCertManager.isConnected:()Z
      14: ifeq          21
      17: iconst_1
      18: goto          22
      21: iconst_0
      22: ireturn

  public org.apache.dubbo.common.ssl.ProviderCert getProviderConnectionConfig(org.apache.dubbo.common.URL);
    Code:
       0: aload_0
       1: getfield      #5                  // Field dubboCertManager:Lorg/apache/dubbo/security/cert/DubboCertManager;
       4: invokevirtual #7                  // Method org/apache/dubbo/security/cert/DubboCertManager.generateCert:()Lorg/apache/dubbo/security/cert/CertPair;
       7: astore_2
       8: aload_2
       9: ifnonnull     14
      12: aconst_null
      13: areturn
      14: new           #8                  // class org/apache/dubbo/common/ssl/ProviderCert
      17: dup
      18: aload_2
      19: invokevirtual #9                  // Method org/apache/dubbo/security/cert/CertPair.getCertificate:()Ljava/lang/String;
      22: getstatic     #10                 // Field java/nio/charset/StandardCharsets.UTF_8:Ljava/nio/charset/Charset;
      25: invokevirtual #11                 // Method java/lang/String.getBytes:(Ljava/nio/charset/Charset;)[B
      28: aload_2
      29: invokevirtual #12                 // Method org/apache/dubbo/security/cert/CertPair.getPrivateKey:()Ljava/lang/String;
      32: getstatic     #10                 // Field java/nio/charset/StandardCharsets.UTF_8:Ljava/nio/charset/Charset;
      35: invokevirtual #11                 // Method java/lang/String.getBytes:(Ljava/nio/charset/Charset;)[B
      38: aload_2
      39: invokevirtual #13                 // Method org/apache/dubbo/security/cert/CertPair.getTrustCerts:()Ljava/lang/String;
      42: getstatic     #10                 // Field java/nio/charset/StandardCharsets.UTF_8:Ljava/nio/charset/Charset;
      45: invokevirtual #11                 // Method java/lang/String.getBytes:(Ljava/nio/charset/Charset;)[B
      48: getstatic     #14                 // Field org/apache/dubbo/common/ssl/AuthPolicy.NONE:Lorg/apache/dubbo/common/ssl/AuthPolicy;
      51: invokespecial #15                 // Method org/apache/dubbo/common/ssl/ProviderCert."<init>":([B[B[BLorg/apache/dubbo/common/ssl/AuthPolicy;)V
      54: areturn

  public org.apache.dubbo.common.ssl.Cert getConsumerConnectionConfig(org.apache.dubbo.common.URL);
    Code:
       0: aload_0
       1: getfield      #5                  // Field dubboCertManager:Lorg/apache/dubbo/security/cert/DubboCertManager;
       4: invokevirtual #7                  // Method org/apache/dubbo/security/cert/DubboCertManager.generateCert:()Lorg/apache/dubbo/security/cert/CertPair;
       7: astore_2
       8: aload_2
       9: ifnonnull     14
      12: aconst_null
      13: areturn
      14: new           #16                 // class org/apache/dubbo/common/ssl/Cert
      17: dup
      18: aload_2
      19: invokevirtual #9                  // Method org/apache/dubbo/security/cert/CertPair.getCertificate:()Ljava/lang/String;
      22: getstatic     #10                 // Field java/nio/charset/StandardCharsets.UTF_8:Ljava/nio/charset/Charset;
      25: invokevirtual #11                 // Method java/lang/String.getBytes:(Ljava/nio/charset/Charset;)[B
      28: aload_2
      29: invokevirtual #12                 // Method org/apache/dubbo/security/cert/CertPair.getPrivateKey:()Ljava/lang/String;
      32: getstatic     #10                 // Field java/nio/charset/StandardCharsets.UTF_8:Ljava/nio/charset/Charset;
      35: invokevirtual #11                 // Method java/lang/String.getBytes:(Ljava/nio/charset/Charset;)[B
      38: aload_2
      39: invokevirtual #13                 // Method org/apache/dubbo/security/cert/CertPair.getTrustCerts:()Ljava/lang/String;
      42: getstatic     #10                 // Field java/nio/charset/StandardCharsets.UTF_8:Ljava/nio/charset/Charset;
      45: invokevirtual #11                 // Method java/lang/String.getBytes:(Ljava/nio/charset/Charset;)[B
      48: invokespecial #17                 // Method org/apache/dubbo/common/ssl/Cert."<init>":([B[B[B)V
      51: areturn
}
