Compiled from "DefaultExecutorRepository.java"
public class org.apache.dubbo.common.threadpool.manager.DefaultExecutorRepository implements org.apache.dubbo.common.threadpool.manager.ExecutorRepository,org.apache.dubbo.common.extension.ExtensionAccessorAware {
  private static final org.apache.dubbo.common.logger.ErrorTypeAwareLogger logger;

  private static final java.lang.String MAX_KEY;

  private volatile java.util.concurrent.ScheduledExecutorService serviceExportExecutor;

  private volatile java.util.concurrent.ExecutorService serviceReferExecutor;

  private final java.util.concurrent.ConcurrentMap<java.lang.String, java.util.concurrent.ConcurrentMap<java.lang.String, java.util.concurrent.ExecutorService>> data;

  private final java.lang.Object LOCK;

  private org.apache.dubbo.common.extension.ExtensionAccessor extensionAccessor;

  private final org.apache.dubbo.rpc.model.ApplicationModel applicationModel;

  private final org.apache.dubbo.common.threadpool.manager.FrameworkExecutorRepository frameworkExecutorRepository;

  private org.apache.dubbo.rpc.executor.ExecutorSupport executorSupport;

  private final org.apache.dubbo.common.store.DataStore dataStore;

  public org.apache.dubbo.common.threadpool.manager.DefaultExecutorRepository(org.apache.dubbo.rpc.model.ApplicationModel);
    Code:
       0: aload_0
       1: invokespecial #3                  // Method java/lang/Object."<init>":()V
       4: aload_0
       5: new           #4                  // class java/util/concurrent/ConcurrentHashMap
       8: dup
       9: invokespecial #5                  // Method java/util/concurrent/ConcurrentHashMap."<init>":()V
      12: putfield      #6                  // Field data:Ljava/util/concurrent/ConcurrentMap;
      15: aload_0
      16: new           #7                  // class java/lang/Object
      19: dup
      20: invokespecial #3                  // Method java/lang/Object."<init>":()V
      23: putfield      #8                  // Field LOCK:Ljava/lang/Object;
      26: aload_0
      27: aload_1
      28: putfield      #9                  // Field applicationModel:Lorg/apache/dubbo/rpc/model/ApplicationModel;
      31: aload_0
      32: aload_1
      33: invokevirtual #10                 // Method org/apache/dubbo/rpc/model/ApplicationModel.getFrameworkModel:()Lorg/apache/dubbo/rpc/model/FrameworkModel;
      36: invokevirtual #11                 // Method org/apache/dubbo/rpc/model/FrameworkModel.getBeanFactory:()Lorg/apache/dubbo/common/beans/factory/ScopeBeanFactory;
      39: ldc           #12                 // class org/apache/dubbo/common/threadpool/manager/FrameworkExecutorRepository
      41: invokevirtual #13                 // Method org/apache/dubbo/common/beans/factory/ScopeBeanFactory.getBean:(Ljava/lang/Class;)Ljava/lang/Object;
      44: checkcast     #12                 // class org/apache/dubbo/common/threadpool/manager/FrameworkExecutorRepository
      47: putfield      #14                 // Field frameworkExecutorRepository:Lorg/apache/dubbo/common/threadpool/manager/FrameworkExecutorRepository;
      50: aload_0
      51: aload_1
      52: ldc           #15                 // class org/apache/dubbo/common/store/DataStore
      54: invokevirtual #16                 // Method org/apache/dubbo/rpc/model/ApplicationModel.getExtensionLoader:(Ljava/lang/Class;)Lorg/apache/dubbo/common/extension/ExtensionLoader;
      57: invokevirtual #17                 // Method org/apache/dubbo/common/extension/ExtensionLoader.getDefaultExtension:()Ljava/lang/Object;
      60: checkcast     #15                 // class org/apache/dubbo/common/store/DataStore
      63: putfield      #18                 // Field dataStore:Lorg/apache/dubbo/common/store/DataStore;
      66: return

  public synchronized java.util.concurrent.ExecutorService createExecutorIfAbsent(org.apache.dubbo.common.URL);
    Code:
       0: aload_0
       1: aload_1
       2: invokespecial #19                 // Method getExecutorKey:(Lorg/apache/dubbo/common/URL;)Ljava/lang/String;
       5: astore_2
       6: aload_0
       7: getfield      #6                  // Field data:Ljava/util/concurrent/ConcurrentMap;
      10: aload_2
      11: invokedynamic #20,  0             // InvokeDynamic #0:apply:()Ljava/util/function/Function;
      16: invokestatic  #21                 // Method org/apache/dubbo/common/utils/ConcurrentHashMapUtils.computeIfAbsent:(Ljava/util/concurrent/ConcurrentMap;Ljava/lang/Object;Ljava/util/function/Function;)Ljava/lang/Object;
      19: checkcast     #22                 // class java/util/concurrent/ConcurrentMap
      22: astore_3
      23: aload_0
      24: aload_1
      25: invokespecial #23                 // Method getExecutorSecondKey:(Lorg/apache/dubbo/common/URL;)Ljava/lang/String;
      28: astore        4
      30: aload_0
      31: aload_1
      32: aload         4
      34: invokevirtual #24                 // Method setThreadNameIfAbsent:(Lorg/apache/dubbo/common/URL;Ljava/lang/String;)Lorg/apache/dubbo/common/URL;
      37: astore_1
      38: aload_1
      39: astore        5
      41: aload_3
      42: aload         4
      44: aload_0
      45: aload         5
      47: invokedynamic #25,  0             // InvokeDynamic #1:apply:(Lorg/apache/dubbo/common/threadpool/manager/DefaultExecutorRepository;Lorg/apache/dubbo/common/URL;)Ljava/util/function/Function;
      52: invokestatic  #21                 // Method org/apache/dubbo/common/utils/ConcurrentHashMapUtils.computeIfAbsent:(Ljava/util/concurrent/ConcurrentMap;Ljava/lang/Object;Ljava/util/function/Function;)Ljava/lang/Object;
      55: checkcast     #26                 // class java/util/concurrent/ExecutorService
      58: astore        6
      60: aload         6
      62: invokeinterface #27,  1           // InterfaceMethod java/util/concurrent/ExecutorService.isShutdown:()Z
      67: ifne          80
      70: aload         6
      72: invokeinterface #28,  1           // InterfaceMethod java/util/concurrent/ExecutorService.isTerminated:()Z
      77: ifeq          107
      80: aload_3
      81: aload         4
      83: invokeinterface #29,  2           // InterfaceMethod java/util/concurrent/ConcurrentMap.remove:(Ljava/lang/Object;)Ljava/lang/Object;
      88: pop
      89: aload_0
      90: aload_1
      91: invokevirtual #30                 // Method createExecutor:(Lorg/apache/dubbo/common/URL;)Ljava/util/concurrent/ExecutorService;
      94: astore        6
      96: aload_3
      97: aload         4
      99: aload         6
     101: invokeinterface #31,  3           // InterfaceMethod java/util/concurrent/ConcurrentMap.put:(Ljava/lang/Object;Ljava/lang/Object;)Ljava/lang/Object;
     106: pop
     107: aload_0
     108: getfield      #18                 // Field dataStore:Lorg/apache/dubbo/common/store/DataStore;
     111: aload_2
     112: aload         4
     114: aload         6
     116: invokeinterface #32,  4           // InterfaceMethod org/apache/dubbo/common/store/DataStore.put:(Ljava/lang/String;Ljava/lang/String;Ljava/lang/Object;)V
     121: aload         6
     123: areturn

  protected org.apache.dubbo.common.URL setThreadNameIfAbsent(org.apache.dubbo.common.URL, java.lang.String);
    Code:
       0: aload_1
       1: ldc           #33                 // String threadname
       3: invokevirtual #34                 // Method org/apache/dubbo/common/URL.getParameter:(Ljava/lang/String;)Ljava/lang/String;
       6: ifnonnull     54
       9: aload_1
      10: invokevirtual #35                 // Method org/apache/dubbo/common/URL.getProtocol:()Ljava/lang/String;
      13: astore_3
      14: aload_3
      15: invokestatic  #36                 // Method org/apache/dubbo/common/utils/StringUtils.isEmpty:(Ljava/lang/String;)Z
      18: ifeq          24
      21: ldc           #37                 // String dubbo
      23: astore_3
      24: aload_1
      25: ldc           #33                 // String threadname
      27: new           #38                 // class java/lang/StringBuilder
      30: dup
      31: invokespecial #39                 // Method java/lang/StringBuilder."<init>":()V
      34: aload_3
      35: invokevirtual #40                 // Method java/lang/StringBuilder.append:(Ljava/lang/String;)Ljava/lang/StringBuilder;
      38: ldc           #41                 // String -protocol-
      40: invokevirtual #40                 // Method java/lang/StringBuilder.append:(Ljava/lang/String;)Ljava/lang/StringBuilder;
      43: aload_2
      44: invokevirtual #40                 // Method java/lang/StringBuilder.append:(Ljava/lang/String;)Ljava/lang/StringBuilder;
      47: invokevirtual #42                 // Method java/lang/StringBuilder.toString:()Ljava/lang/String;
      50: invokevirtual #43                 // Method org/apache/dubbo/common/URL.putAttribute:(Ljava/lang/String;Ljava/lang/Object;)Lorg/apache/dubbo/common/URL;
      53: astore_1
      54: aload_1
      55: areturn

  private java.lang.String getExecutorSecondKey(org.apache.dubbo.common.URL);
    Code:
       0: ldc           #44                 // String consumer
       2: aload_1
       3: ldc           #45                 // String side
       5: invokevirtual #34                 // Method org/apache/dubbo/common/URL.getParameter:(Ljava/lang/String;)Ljava/lang/String;
       8: invokevirtual #46                 // Method java/lang/String.equalsIgnoreCase:(Ljava/lang/String;)Z
      11: ifeq          20
      14: aload_0
      15: aload_1
      16: invokespecial #47                 // Method getConsumerKey:(Lorg/apache/dubbo/common/URL;)Ljava/lang/String;
      19: areturn
      20: aload_0
      21: aload_1
      22: invokevirtual #48                 // Method getProviderKey:(Lorg/apache/dubbo/common/URL;)Ljava/lang/String;
      25: areturn

  private java.lang.String getExecutorSecondKey(org.apache.dubbo.rpc.model.ServiceModel, org.apache.dubbo.common.URL);
    Code:
       0: aload_1
       1: instanceof    #49                 // class org/apache/dubbo/rpc/model/ConsumerModel
       4: ifeq          13
       7: aload_0
       8: aload_1
       9: invokespecial #50                 // Method getConsumerKey:(Lorg/apache/dubbo/rpc/model/ServiceModel;)Ljava/lang/String;
      12: areturn
      13: aload_0
      14: aload_1
      15: checkcast     #51                 // class org/apache/dubbo/rpc/model/ProviderModel
      18: aload_2
      19: invokevirtual #52                 // Method getProviderKey:(Lorg/apache/dubbo/rpc/model/ProviderModel;Lorg/apache/dubbo/common/URL;)Ljava/lang/String;
      22: areturn

  private java.lang.String getConsumerKey(org.apache.dubbo.common.URL);
    Code:
       0: ldc           #54                 // int 2147483647
       2: invokestatic  #55                 // Method java/lang/String.valueOf:(I)Ljava/lang/String;
       5: areturn

  private java.lang.String getConsumerKey(org.apache.dubbo.rpc.model.ServiceModel);
    Code:
       0: getstatic     #56                 // Field MAX_KEY:Ljava/lang/String;
       3: areturn

  protected java.lang.String getProviderKey(org.apache.dubbo.common.URL);
    Code:
       0: aload_1
       1: invokevirtual #57                 // Method org/apache/dubbo/common/URL.getPort:()I
       4: invokestatic  #55                 // Method java/lang/String.valueOf:(I)Ljava/lang/String;
       7: areturn

  protected java.lang.String getProviderKey(org.apache.dubbo.rpc.model.ProviderModel, org.apache.dubbo.common.URL);
    Code:
       0: aload_2
       1: invokevirtual #57                 // Method org/apache/dubbo/common/URL.getPort:()I
       4: invokestatic  #55                 // Method java/lang/String.valueOf:(I)Ljava/lang/String;
       7: areturn

  private java.lang.String getExecutorKey(org.apache.dubbo.common.URL);
    Code:
       0: ldc           #44                 // String consumer
       2: aload_1
       3: ldc           #45                 // String side
       5: invokevirtual #34                 // Method org/apache/dubbo/common/URL.getParameter:(Ljava/lang/String;)Ljava/lang/String;
       8: invokevirtual #46                 // Method java/lang/String.equalsIgnoreCase:(Ljava/lang/String;)Z
      11: ifeq          17
      14: ldc           #58                 // String CONSUMER_SHARED_SERVICE_EXECUTOR
      16: areturn
      17: getstatic     #59                 // Field org/apache/dubbo/common/constants/CommonConstants.EXECUTOR_SERVICE_COMPONENT_KEY:Ljava/lang/String;
      20: areturn

  private java.lang.String getExecutorKey(org.apache.dubbo.rpc.model.ServiceModel);
    Code:
       0: aload_1
       1: instanceof    #51                 // class org/apache/dubbo/rpc/model/ProviderModel
       4: ifeq          11
       7: getstatic     #59                 // Field org/apache/dubbo/common/constants/CommonConstants.EXECUTOR_SERVICE_COMPONENT_KEY:Ljava/lang/String;
      10: areturn
      11: ldc           #58                 // String CONSUMER_SHARED_SERVICE_EXECUTOR
      13: areturn

  protected java.util.concurrent.ExecutorService createExecutor(org.apache.dubbo.common.URL);
    Code:
       0: aload_0
       1: getfield      #60                 // Field extensionAccessor:Lorg/apache/dubbo/common/extension/ExtensionAccessor;
       4: ldc           #61                 // class org/apache/dubbo/common/threadpool/ThreadPool
       6: invokeinterface #62,  2           // InterfaceMethod org/apache/dubbo/common/extension/ExtensionAccessor.getExtensionLoader:(Ljava/lang/Class;)Lorg/apache/dubbo/common/extension/ExtensionLoader;
      11: invokevirtual #63                 // Method org/apache/dubbo/common/extension/ExtensionLoader.getAdaptiveExtension:()Ljava/lang/Object;
      14: checkcast     #61                 // class org/apache/dubbo/common/threadpool/ThreadPool
      17: aload_1
      18: invokeinterface #64,  2           // InterfaceMethod org/apache/dubbo/common/threadpool/ThreadPool.getExecutor:(Lorg/apache/dubbo/common/URL;)Ljava/util/concurrent/Executor;
      23: checkcast     #26                 // class java/util/concurrent/ExecutorService
      26: areturn

  public java.util.concurrent.ExecutorService getExecutor(org.apache.dubbo.common.URL);
    Code:
       0: aload_0
       1: getfield      #6                  // Field data:Ljava/util/concurrent/ConcurrentMap;
       4: aload_0
       5: aload_1
       6: invokespecial #19                 // Method getExecutorKey:(Lorg/apache/dubbo/common/URL;)Ljava/lang/String;
       9: invokeinterface #65,  2           // InterfaceMethod java/util/concurrent/ConcurrentMap.get:(Ljava/lang/Object;)Ljava/lang/Object;
      14: checkcast     #66                 // class java/util/Map
      17: astore_2
      18: aload_2
      19: ifnonnull     40
      22: getstatic     #67                 // Field logger:Lorg/apache/dubbo/common/logger/ErrorTypeAwareLogger;
      25: ldc           #68                 // String 0-16
      27: ldc           #69                 // String
      29: ldc           #69                 // String
      31: ldc           #70                 // String No available executors, this is not expected, framework should call createExecutorIfAbsent firstbefore coming to here.
      33: invokeinterface #71,  5           // InterfaceMethod org/apache/dubbo/common/logger/ErrorTypeAwareLogger.warn:(Ljava/lang/String;Ljava/lang/String;Ljava/lang/String;Ljava/lang/String;)V
      38: aconst_null
      39: areturn
      40: aload_0
      41: aload_1
      42: invokespecial #23                 // Method getExecutorSecondKey:(Lorg/apache/dubbo/common/URL;)Ljava/lang/String;
      45: astore_3
      46: aload_2
      47: aload_3
      48: invokeinterface #72,  2           // InterfaceMethod java/util/Map.get:(Ljava/lang/Object;)Ljava/lang/Object;
      53: checkcast     #26                 // class java/util/concurrent/ExecutorService
      56: astore        4
      58: aload         4
      60: ifnull        126
      63: aload         4
      65: invokeinterface #27,  1           // InterfaceMethod java/util/concurrent/ExecutorService.isShutdown:()Z
      70: ifne          83
      73: aload         4
      75: invokeinterface #28,  1           // InterfaceMethod java/util/concurrent/ExecutorService.isTerminated:()Z
      80: ifeq          126
      83: aload_2
      84: aload_3
      85: invokeinterface #73,  2           // InterfaceMethod java/util/Map.remove:(Ljava/lang/Object;)Ljava/lang/Object;
      90: pop
      91: aconst_null
      92: astore        4
      94: getstatic     #67                 // Field logger:Lorg/apache/dubbo/common/logger/ErrorTypeAwareLogger;
      97: new           #38                 // class java/lang/StringBuilder
     100: dup
     101: invokespecial #39                 // Method java/lang/StringBuilder."<init>":()V
     104: ldc           #74                 // String Executor for
     106: invokevirtual #40                 // Method java/lang/StringBuilder.append:(Ljava/lang/String;)Ljava/lang/StringBuilder;
     109: aload_1
     110: invokevirtual #75                 // Method java/lang/StringBuilder.append:(Ljava/lang/Object;)Ljava/lang/StringBuilder;
     113: ldc           #76                 // String  is shutdown.
     115: invokevirtual #40                 // Method java/lang/StringBuilder.append:(Ljava/lang/String;)Ljava/lang/StringBuilder;
     118: invokevirtual #42                 // Method java/lang/StringBuilder.toString:()Ljava/lang/String;
     121: invokeinterface #77,  2           // InterfaceMethod org/apache/dubbo/common/logger/ErrorTypeAwareLogger.info:(Ljava/lang/String;)V
     126: aload         4
     128: ifnonnull     139
     131: aload_0
     132: getfield      #14                 // Field frameworkExecutorRepository:Lorg/apache/dubbo/common/threadpool/manager/FrameworkExecutorRepository;
     135: invokevirtual #78                 // Method org/apache/dubbo/common/threadpool/manager/FrameworkExecutorRepository.getSharedExecutor:()Ljava/util/concurrent/ExecutorService;
     138: areturn
     139: aload         4
     141: areturn

  public java.util.concurrent.ExecutorService getExecutor(org.apache.dubbo.rpc.model.ServiceModel, org.apache.dubbo.common.URL);
    Code:
       0: aload_0
       1: getfield      #6                  // Field data:Ljava/util/concurrent/ConcurrentMap;
       4: aload_0
       5: aload_1
       6: invokespecial #79                 // Method getExecutorKey:(Lorg/apache/dubbo/rpc/model/ServiceModel;)Ljava/lang/String;
       9: invokeinterface #65,  2           // InterfaceMethod java/util/concurrent/ConcurrentMap.get:(Ljava/lang/Object;)Ljava/lang/Object;
      14: checkcast     #66                 // class java/util/Map
      17: astore_3
      18: aload_3
      19: ifnonnull     40
      22: getstatic     #67                 // Field logger:Lorg/apache/dubbo/common/logger/ErrorTypeAwareLogger;
      25: ldc           #68                 // String 0-16
      27: ldc           #69                 // String
      29: ldc           #69                 // String
      31: ldc           #70                 // String No available executors, this is not expected, framework should call createExecutorIfAbsent firstbefore coming to here.
      33: invokeinterface #71,  5           // InterfaceMethod org/apache/dubbo/common/logger/ErrorTypeAwareLogger.warn:(Ljava/lang/String;Ljava/lang/String;Ljava/lang/String;Ljava/lang/String;)V
      38: aconst_null
      39: areturn
      40: aload_0
      41: aload_1
      42: aload_2
      43: invokespecial #80                 // Method getExecutorSecondKey:(Lorg/apache/dubbo/rpc/model/ServiceModel;Lorg/apache/dubbo/common/URL;)Ljava/lang/String;
      46: astore        4
      48: aload_3
      49: aload         4
      51: invokeinterface #72,  2           // InterfaceMethod java/util/Map.get:(Ljava/lang/Object;)Ljava/lang/Object;
      56: checkcast     #26                 // class java/util/concurrent/ExecutorService
      59: astore        5
      61: aload         5
      63: ifnull        130
      66: aload         5
      68: invokeinterface #27,  1           // InterfaceMethod java/util/concurrent/ExecutorService.isShutdown:()Z
      73: ifne          86
      76: aload         5
      78: invokeinterface #28,  1           // InterfaceMethod java/util/concurrent/ExecutorService.isTerminated:()Z
      83: ifeq          130
      86: aload_3
      87: aload         4
      89: invokeinterface #73,  2           // InterfaceMethod java/util/Map.remove:(Ljava/lang/Object;)Ljava/lang/Object;
      94: pop
      95: aconst_null
      96: astore        5
      98: getstatic     #67                 // Field logger:Lorg/apache/dubbo/common/logger/ErrorTypeAwareLogger;
     101: new           #38                 // class java/lang/StringBuilder
     104: dup
     105: invokespecial #39                 // Method java/lang/StringBuilder."<init>":()V
     108: ldc           #74                 // String Executor for
     110: invokevirtual #40                 // Method java/lang/StringBuilder.append:(Ljava/lang/String;)Ljava/lang/StringBuilder;
     113: aload_2
     114: invokevirtual #75                 // Method java/lang/StringBuilder.append:(Ljava/lang/Object;)Ljava/lang/StringBuilder;
     117: ldc           #76                 // String  is shutdown.
     119: invokevirtual #40                 // Method java/lang/StringBuilder.append:(Ljava/lang/String;)Ljava/lang/StringBuilder;
     122: invokevirtual #42                 // Method java/lang/StringBuilder.toString:()Ljava/lang/String;
     125: invokeinterface #77,  2           // InterfaceMethod org/apache/dubbo/common/logger/ErrorTypeAwareLogger.info:(Ljava/lang/String;)V
     130: aload         5
     132: ifnonnull     143
     135: aload_0
     136: getfield      #14                 // Field frameworkExecutorRepository:Lorg/apache/dubbo/common/threadpool/manager/FrameworkExecutorRepository;
     139: invokevirtual #78                 // Method org/apache/dubbo/common/threadpool/manager/FrameworkExecutorRepository.getSharedExecutor:()Ljava/util/concurrent/ExecutorService;
     142: areturn
     143: aload         5
     145: areturn

  public void updateThreadpool(org.apache.dubbo.common.URL, java.util.concurrent.ExecutorService);
    Code:
       0: aload_1
       1: ldc           #81                 // String threads
       3: invokevirtual #82                 // Method org/apache/dubbo/common/URL.hasParameter:(Ljava/lang/String;)Z
       6: ifeq          118
       9: aload_2
      10: instanceof    #83                 // class java/util/concurrent/ThreadPoolExecutor
      13: ifeq          118
      16: aload_2
      17: invokeinterface #27,  1           // InterfaceMethod java/util/concurrent/ExecutorService.isShutdown:()Z
      22: ifne          118
      25: aload_2
      26: checkcast     #83                 // class java/util/concurrent/ThreadPoolExecutor
      29: astore_3
      30: aload_1
      31: ldc           #81                 // String threads
      33: iconst_0
      34: invokevirtual #84                 // Method org/apache/dubbo/common/URL.getParameter:(Ljava/lang/String;I)I
      37: istore        4
      39: aload_3
      40: invokevirtual #85                 // Method java/util/concurrent/ThreadPoolExecutor.getMaximumPoolSize:()I
      43: istore        5
      45: aload_3
      46: invokevirtual #86                 // Method java/util/concurrent/ThreadPoolExecutor.getCorePoolSize:()I
      49: istore        6
      51: iload         4
      53: ifle          118
      56: iload         4
      58: iload         5
      60: if_icmpne     70
      63: iload         4
      65: iload         6
      67: if_icmpeq     118
      70: iload         4
      72: iload         6
      74: if_icmpge     99
      77: aload_3
      78: iload         4
      80: invokevirtual #87                 // Method java/util/concurrent/ThreadPoolExecutor.setCorePoolSize:(I)V
      83: iload         6
      85: iload         5
      87: if_icmpne     118
      90: aload_3
      91: iload         4
      93: invokevirtual #88                 // Method java/util/concurrent/ThreadPoolExecutor.setMaximumPoolSize:(I)V
      96: goto          118
      99: aload_3
     100: iload         4
     102: invokevirtual #88                 // Method java/util/concurrent/ThreadPoolExecutor.setMaximumPoolSize:(I)V
     105: iload         6
     107: iload         5
     109: if_icmpne     118
     112: aload_3
     113: iload         4
     115: invokevirtual #87                 // Method java/util/concurrent/ThreadPoolExecutor.setCorePoolSize:(I)V
     118: goto          141
     121: astore_3
     122: getstatic     #67                 // Field logger:Lorg/apache/dubbo/common/logger/ErrorTypeAwareLogger;
     125: ldc           #90                 // String 0-18
     127: ldc           #69                 // String
     129: ldc           #69                 // String
     131: aload_3
     132: invokevirtual #91                 // Method java/lang/Throwable.getMessage:()Ljava/lang/String;
     135: aload_3
     136: invokeinterface #92,  6           // InterfaceMethod org/apache/dubbo/common/logger/ErrorTypeAwareLogger.error:(Ljava/lang/String;Ljava/lang/String;Ljava/lang/String;Ljava/lang/String;Ljava/lang/Throwable;)V
     141: return
    Exception table:
       from    to  target type
           0   118   121   Class java/lang/Throwable

  public java.util.concurrent.ScheduledExecutorService getServiceExportExecutor();
    Code:
       0: aload_0
       1: getfield      #8                  // Field LOCK:Ljava/lang/Object;
       4: dup
       5: astore_1
       6: monitorenter
       7: aload_0
       8: getfield      #93                 // Field serviceExportExecutor:Ljava/util/concurrent/ScheduledExecutorService;
      11: ifnonnull     84
      14: aload_0
      15: invokespecial #94                 // Method getExportThreadNum:()Ljava/lang/Integer;
      18: invokevirtual #95                 // Method java/lang/Integer.intValue:()I
      21: istore_2
      22: aload_0
      23: getfield      #9                  // Field applicationModel:Lorg/apache/dubbo/rpc/model/ApplicationModel;
      26: invokevirtual #96                 // Method org/apache/dubbo/rpc/model/ApplicationModel.tryGetApplicationName:()Ljava/lang/String;
      29: astore_3
      30: aload_3
      31: invokestatic  #36                 // Method org/apache/dubbo/common/utils/StringUtils.isEmpty:(Ljava/lang/String;)Z
      34: ifeq          42
      37: ldc           #97                 // String app
      39: goto          43
      42: aload_3
      43: astore_3
      44: aload_0
      45: iload_2
      46: new           #98                 // class org/apache/dubbo/common/utils/NamedThreadFactory
      49: dup
      50: new           #38                 // class java/lang/StringBuilder
      53: dup
      54: invokespecial #39                 // Method java/lang/StringBuilder."<init>":()V
      57: ldc           #99                 // String Dubbo-
      59: invokevirtual #40                 // Method java/lang/StringBuilder.append:(Ljava/lang/String;)Ljava/lang/StringBuilder;
      62: aload_3
      63: invokevirtual #40                 // Method java/lang/StringBuilder.append:(Ljava/lang/String;)Ljava/lang/StringBuilder;
      66: ldc           #100                // String -service-export
      68: invokevirtual #40                 // Method java/lang/StringBuilder.append:(Ljava/lang/String;)Ljava/lang/StringBuilder;
      71: invokevirtual #42                 // Method java/lang/StringBuilder.toString:()Ljava/lang/String;
      74: iconst_1
      75: invokespecial #101                // Method org/apache/dubbo/common/utils/NamedThreadFactory."<init>":(Ljava/lang/String;Z)V
      78: invokestatic  #102                // Method java/util/concurrent/Executors.newScheduledThreadPool:(ILjava/util/concurrent/ThreadFactory;)Ljava/util/concurrent/ScheduledExecutorService;
      81: putfield      #93                 // Field serviceExportExecutor:Ljava/util/concurrent/ScheduledExecutorService;
      84: aload_1
      85: monitorexit
      86: goto          96
      89: astore        4
      91: aload_1
      92: monitorexit
      93: aload         4
      95: athrow
      96: aload_0
      97: getfield      #93                 // Field serviceExportExecutor:Ljava/util/concurrent/ScheduledExecutorService;
     100: areturn
    Exception table:
       from    to  target type
           7    86    89   any
          89    93    89   any

  public void shutdownServiceExportExecutor();
    Code:
       0: aload_0
       1: getfield      #8                  // Field LOCK:Ljava/lang/Object;
       4: dup
       5: astore_1
       6: monitorenter
       7: aload_0
       8: getfield      #93                 // Field serviceExportExecutor:Ljava/util/concurrent/ScheduledExecutorService;
      11: ifnull        58
      14: aload_0
      15: getfield      #93                 // Field serviceExportExecutor:Ljava/util/concurrent/ScheduledExecutorService;
      18: invokeinterface #103,  1          // InterfaceMethod java/util/concurrent/ScheduledExecutorService.isShutdown:()Z
      23: ifne          58
      26: aload_0
      27: getfield      #93                 // Field serviceExportExecutor:Ljava/util/concurrent/ScheduledExecutorService;
      30: invokeinterface #104,  1          // InterfaceMethod java/util/concurrent/ScheduledExecutorService.shutdown:()V
      35: goto          58
      38: astore_2
      39: getstatic     #67                 // Field logger:Lorg/apache/dubbo/common/logger/ErrorTypeAwareLogger;
      42: ldc           #105                // String 0-17
      44: ldc           #69                 // String
      46: ldc           #69                 // String
      48: aload_2
      49: invokevirtual #91                 // Method java/lang/Throwable.getMessage:()Ljava/lang/String;
      52: aload_2
      53: invokeinterface #106,  6          // InterfaceMethod org/apache/dubbo/common/logger/ErrorTypeAwareLogger.warn:(Ljava/lang/String;Ljava/lang/String;Ljava/lang/String;Ljava/lang/String;Ljava/lang/Throwable;)V
      58: aload_0
      59: aconst_null
      60: putfield      #93                 // Field serviceExportExecutor:Ljava/util/concurrent/ScheduledExecutorService;
      63: aload_1
      64: monitorexit
      65: goto          73
      68: astore_3
      69: aload_1
      70: monitorexit
      71: aload_3
      72: athrow
      73: return
    Exception table:
       from    to  target type
          26    35    38   Class java/lang/Throwable
           7    65    68   any
          68    71    68   any

  public java.util.concurrent.ExecutorService getServiceReferExecutor();
    Code:
       0: aload_0
       1: getfield      #8                  // Field LOCK:Ljava/lang/Object;
       4: dup
       5: astore_1
       6: monitorenter
       7: aload_0
       8: getfield      #107                // Field serviceReferExecutor:Ljava/util/concurrent/ExecutorService;
      11: ifnonnull     84
      14: aload_0
      15: invokespecial #108                // Method getReferThreadNum:()Ljava/lang/Integer;
      18: invokevirtual #95                 // Method java/lang/Integer.intValue:()I
      21: istore_2
      22: aload_0
      23: getfield      #9                  // Field applicationModel:Lorg/apache/dubbo/rpc/model/ApplicationModel;
      26: invokevirtual #96                 // Method org/apache/dubbo/rpc/model/ApplicationModel.tryGetApplicationName:()Ljava/lang/String;
      29: astore_3
      30: aload_3
      31: invokestatic  #36                 // Method org/apache/dubbo/common/utils/StringUtils.isEmpty:(Ljava/lang/String;)Z
      34: ifeq          42
      37: ldc           #97                 // String app
      39: goto          43
      42: aload_3
      43: astore_3
      44: aload_0
      45: iload_2
      46: new           #98                 // class org/apache/dubbo/common/utils/NamedThreadFactory
      49: dup
      50: new           #38                 // class java/lang/StringBuilder
      53: dup
      54: invokespecial #39                 // Method java/lang/StringBuilder."<init>":()V
      57: ldc           #99                 // String Dubbo-
      59: invokevirtual #40                 // Method java/lang/StringBuilder.append:(Ljava/lang/String;)Ljava/lang/StringBuilder;
      62: aload_3
      63: invokevirtual #40                 // Method java/lang/StringBuilder.append:(Ljava/lang/String;)Ljava/lang/StringBuilder;
      66: ldc           #109                // String -service-refer
      68: invokevirtual #40                 // Method java/lang/StringBuilder.append:(Ljava/lang/String;)Ljava/lang/StringBuilder;
      71: invokevirtual #42                 // Method java/lang/StringBuilder.toString:()Ljava/lang/String;
      74: iconst_1
      75: invokespecial #101                // Method org/apache/dubbo/common/utils/NamedThreadFactory."<init>":(Ljava/lang/String;Z)V
      78: invokestatic  #110                // Method java/util/concurrent/Executors.newFixedThreadPool:(ILjava/util/concurrent/ThreadFactory;)Ljava/util/concurrent/ExecutorService;
      81: putfield      #107                // Field serviceReferExecutor:Ljava/util/concurrent/ExecutorService;
      84: aload_1
      85: monitorexit
      86: goto          96
      89: astore        4
      91: aload_1
      92: monitorexit
      93: aload         4
      95: athrow
      96: aload_0
      97: getfield      #107                // Field serviceReferExecutor:Ljava/util/concurrent/ExecutorService;
     100: areturn
    Exception table:
       from    to  target type
           7    86    89   any
          89    93    89   any

  public void shutdownServiceReferExecutor();
    Code:
       0: aload_0
       1: getfield      #8                  // Field LOCK:Ljava/lang/Object;
       4: dup
       5: astore_1
       6: monitorenter
       7: aload_0
       8: getfield      #107                // Field serviceReferExecutor:Ljava/util/concurrent/ExecutorService;
      11: ifnull        58
      14: aload_0
      15: getfield      #107                // Field serviceReferExecutor:Ljava/util/concurrent/ExecutorService;
      18: invokeinterface #27,  1           // InterfaceMethod java/util/concurrent/ExecutorService.isShutdown:()Z
      23: ifne          58
      26: aload_0
      27: getfield      #107                // Field serviceReferExecutor:Ljava/util/concurrent/ExecutorService;
      30: invokeinterface #111,  1          // InterfaceMethod java/util/concurrent/ExecutorService.shutdown:()V
      35: goto          58
      38: astore_2
      39: getstatic     #67                 // Field logger:Lorg/apache/dubbo/common/logger/ErrorTypeAwareLogger;
      42: ldc           #105                // String 0-17
      44: ldc           #69                 // String
      46: ldc           #69                 // String
      48: aload_2
      49: invokevirtual #91                 // Method java/lang/Throwable.getMessage:()Ljava/lang/String;
      52: aload_2
      53: invokeinterface #106,  6          // InterfaceMethod org/apache/dubbo/common/logger/ErrorTypeAwareLogger.warn:(Ljava/lang/String;Ljava/lang/String;Ljava/lang/String;Ljava/lang/String;Ljava/lang/Throwable;)V
      58: aload_0
      59: aconst_null
      60: putfield      #107                // Field serviceReferExecutor:Ljava/util/concurrent/ExecutorService;
      63: aload_1
      64: monitorexit
      65: goto          73
      68: astore_3
      69: aload_1
      70: monitorexit
      71: aload_3
      72: athrow
      73: return
    Exception table:
       from    to  target type
          26    35    38   Class java/lang/Throwable
           7    65    68   any
          68    71    68   any

  private java.lang.Integer getExportThreadNum();
    Code:
       0: aconst_null
       1: astore_1
       2: aload_0
       3: getfield      #9                  // Field applicationModel:Lorg/apache/dubbo/rpc/model/ApplicationModel;
       6: invokestatic  #112                // Method org/apache/dubbo/rpc/model/ApplicationModel.ofNullable:(Lorg/apache/dubbo/rpc/model/ApplicationModel;)Lorg/apache/dubbo/rpc/model/ApplicationModel;
       9: astore_2
      10: aload_2
      11: invokevirtual #113                // Method org/apache/dubbo/rpc/model/ApplicationModel.getPubModuleModels:()Ljava/util/List;
      14: invokeinterface #114,  1          // InterfaceMethod java/util/List.iterator:()Ljava/util/Iterator;
      19: astore_3
      20: aload_3
      21: invokeinterface #115,  1          // InterfaceMethod java/util/Iterator.hasNext:()Z
      26: ifeq          57
      29: aload_3
      30: invokeinterface #116,  1          // InterfaceMethod java/util/Iterator.next:()Ljava/lang/Object;
      35: checkcast     #117                // class org/apache/dubbo/rpc/model/ModuleModel
      38: astore        4
      40: aload_0
      41: aload         4
      43: invokespecial #118                // Method getExportThreadNum:(Lorg/apache/dubbo/rpc/model/ModuleModel;)Ljava/lang/Integer;
      46: astore_1
      47: aload_1
      48: ifnull        54
      51: goto          57
      54: goto          20
      57: aload_1
      58: ifnonnull     77
      61: getstatic     #67                 // Field logger:Lorg/apache/dubbo/common/logger/ErrorTypeAwareLogger;
      64: ldc           #119                // String Cannot get config `export-thread-num` from module config, using default: 10
      66: invokeinterface #77,  2           // InterfaceMethod org/apache/dubbo/common/logger/ErrorTypeAwareLogger.info:(Ljava/lang/String;)V
      71: bipush        10
      73: invokestatic  #120                // Method java/lang/Integer.valueOf:(I)Ljava/lang/Integer;
      76: areturn
      77: aload_1
      78: areturn

  private java.lang.Integer getExportThreadNum(org.apache.dubbo.rpc.model.ModuleModel);
    Code:
       0: aload_1
       1: invokevirtual #121                // Method org/apache/dubbo/rpc/model/ModuleModel.getConfigManager:()Lorg/apache/dubbo/config/context/ModuleConfigManager;
       4: invokevirtual #122                // Method org/apache/dubbo/config/context/ModuleConfigManager.getModule:()Ljava/util/Optional;
       7: aconst_null
       8: invokevirtual #123                // Method java/util/Optional.orElse:(Ljava/lang/Object;)Ljava/lang/Object;
      11: checkcast     #124                // class org/apache/dubbo/config/ModuleConfig
      14: astore_2
      15: aload_2
      16: ifnonnull     21
      19: aconst_null
      20: areturn
      21: aload_2
      22: invokevirtual #125                // Method org/apache/dubbo/config/ModuleConfig.getExportThreadNum:()Ljava/lang/Integer;
      25: astore_3
      26: aload_3
      27: ifnonnull     75
      30: aload_1
      31: invokevirtual #121                // Method org/apache/dubbo/rpc/model/ModuleModel.getConfigManager:()Lorg/apache/dubbo/config/context/ModuleConfigManager;
      34: invokevirtual #126                // Method org/apache/dubbo/config/context/ModuleConfigManager.getProviders:()Ljava/util/Collection;
      37: invokeinterface #127,  1          // InterfaceMethod java/util/Collection.stream:()Ljava/util/stream/Stream;
      42: invokedynamic #128,  0            // InvokeDynamic #2:apply:()Ljava/util/function/Function;
      47: invokeinterface #129,  2          // InterfaceMethod java/util/stream/Stream.map:(Ljava/util/function/Function;)Ljava/util/stream/Stream;
      52: invokedynamic #130,  0            // InvokeDynamic #3:test:()Ljava/util/function/Predicate;
      57: invokeinterface #131,  2          // InterfaceMethod java/util/stream/Stream.filter:(Ljava/util/function/Predicate;)Ljava/util/stream/Stream;
      62: invokeinterface #132,  1          // InterfaceMethod java/util/stream/Stream.findAny:()Ljava/util/Optional;
      67: aconst_null
      68: invokevirtual #123                // Method java/util/Optional.orElse:(Ljava/lang/Object;)Ljava/lang/Object;
      71: checkcast     #53                 // class java/lang/Integer
      74: astore_3
      75: aload_3
      76: areturn

  private java.lang.Integer getReferThreadNum();
    Code:
       0: aconst_null
       1: astore_1
       2: aload_0
       3: getfield      #9                  // Field applicationModel:Lorg/apache/dubbo/rpc/model/ApplicationModel;
       6: invokestatic  #112                // Method org/apache/dubbo/rpc/model/ApplicationModel.ofNullable:(Lorg/apache/dubbo/rpc/model/ApplicationModel;)Lorg/apache/dubbo/rpc/model/ApplicationModel;
       9: astore_2
      10: aload_2
      11: invokevirtual #113                // Method org/apache/dubbo/rpc/model/ApplicationModel.getPubModuleModels:()Ljava/util/List;
      14: invokeinterface #114,  1          // InterfaceMethod java/util/List.iterator:()Ljava/util/Iterator;
      19: astore_3
      20: aload_3
      21: invokeinterface #115,  1          // InterfaceMethod java/util/Iterator.hasNext:()Z
      26: ifeq          57
      29: aload_3
      30: invokeinterface #116,  1          // InterfaceMethod java/util/Iterator.next:()Ljava/lang/Object;
      35: checkcast     #117                // class org/apache/dubbo/rpc/model/ModuleModel
      38: astore        4
      40: aload_0
      41: aload         4
      43: invokespecial #133                // Method getReferThreadNum:(Lorg/apache/dubbo/rpc/model/ModuleModel;)Ljava/lang/Integer;
      46: astore_1
      47: aload_1
      48: ifnull        54
      51: goto          57
      54: goto          20
      57: aload_1
      58: ifnonnull     77
      61: getstatic     #67                 // Field logger:Lorg/apache/dubbo/common/logger/ErrorTypeAwareLogger;
      64: ldc           #134                // String Cannot get config `refer-thread-num` from module config, using default: 10
      66: invokeinterface #77,  2           // InterfaceMethod org/apache/dubbo/common/logger/ErrorTypeAwareLogger.info:(Ljava/lang/String;)V
      71: bipush        10
      73: invokestatic  #120                // Method java/lang/Integer.valueOf:(I)Ljava/lang/Integer;
      76: areturn
      77: aload_1
      78: areturn

  private java.lang.Integer getReferThreadNum(org.apache.dubbo.rpc.model.ModuleModel);
    Code:
       0: aload_1
       1: invokevirtual #121                // Method org/apache/dubbo/rpc/model/ModuleModel.getConfigManager:()Lorg/apache/dubbo/config/context/ModuleConfigManager;
       4: invokevirtual #122                // Method org/apache/dubbo/config/context/ModuleConfigManager.getModule:()Ljava/util/Optional;
       7: aconst_null
       8: invokevirtual #123                // Method java/util/Optional.orElse:(Ljava/lang/Object;)Ljava/lang/Object;
      11: checkcast     #124                // class org/apache/dubbo/config/ModuleConfig
      14: astore_2
      15: aload_2
      16: ifnonnull     21
      19: aconst_null
      20: areturn
      21: aload_2
      22: invokevirtual #135                // Method org/apache/dubbo/config/ModuleConfig.getReferThreadNum:()Ljava/lang/Integer;
      25: astore_3
      26: aload_3
      27: ifnonnull     75
      30: aload_1
      31: invokevirtual #121                // Method org/apache/dubbo/rpc/model/ModuleModel.getConfigManager:()Lorg/apache/dubbo/config/context/ModuleConfigManager;
      34: invokevirtual #136                // Method org/apache/dubbo/config/context/ModuleConfigManager.getConsumers:()Ljava/util/Collection;
      37: invokeinterface #127,  1          // InterfaceMethod java/util/Collection.stream:()Ljava/util/stream/Stream;
      42: invokedynamic #137,  0            // InvokeDynamic #4:apply:()Ljava/util/function/Function;
      47: invokeinterface #129,  2          // InterfaceMethod java/util/stream/Stream.map:(Ljava/util/function/Function;)Ljava/util/stream/Stream;
      52: invokedynamic #138,  0            // InvokeDynamic #5:test:()Ljava/util/function/Predicate;
      57: invokeinterface #131,  2          // InterfaceMethod java/util/stream/Stream.filter:(Ljava/util/function/Predicate;)Ljava/util/stream/Stream;
      62: invokeinterface #132,  1          // InterfaceMethod java/util/stream/Stream.findAny:()Ljava/util/Optional;
      67: aconst_null
      68: invokevirtual #123                // Method java/util/Optional.orElse:(Ljava/lang/Object;)Ljava/lang/Object;
      71: checkcast     #53                 // class java/lang/Integer
      74: astore_3
      75: aload_3
      76: areturn

  public void destroyAll();
    Code:
       0: getstatic     #67                 // Field logger:Lorg/apache/dubbo/common/logger/ErrorTypeAwareLogger;
       3: ldc           #139                // String destroying application executor repository ..
       5: invokeinterface #77,  2           // InterfaceMethod org/apache/dubbo/common/logger/ErrorTypeAwareLogger.info:(Ljava/lang/String;)V
      10: aload_0
      11: invokevirtual #140                // Method shutdownServiceExportExecutor:()V
      14: aload_0
      15: invokevirtual #141                // Method shutdownServiceReferExecutor:()V
      18: aload_0
      19: getfield      #6                  // Field data:Ljava/util/concurrent/ConcurrentMap;
      22: invokeinterface #142,  1          // InterfaceMethod java/util/concurrent/ConcurrentMap.values:()Ljava/util/Collection;
      27: invokedynamic #143,  0            // InvokeDynamic #6:accept:()Ljava/util/function/Consumer;
      32: invokeinterface #144,  2          // InterfaceMethod java/util/Collection.forEach:(Ljava/util/function/Consumer;)V
      37: aload_0
      38: getfield      #6                  // Field data:Ljava/util/concurrent/ConcurrentMap;
      41: invokeinterface #145,  1          // InterfaceMethod java/util/concurrent/ConcurrentMap.clear:()V
      46: return

  private void shutdownExecutorService(java.util.concurrent.ExecutorService, java.lang.String);
    Code:
       0: aload_1
       1: invokeinterface #146,  1          // InterfaceMethod java/util/concurrent/ExecutorService.shutdownNow:()Ljava/util/List;
       6: pop
       7: goto          74
      10: astore_3
      11: new           #38                 // class java/lang/StringBuilder
      14: dup
      15: invokespecial #39                 // Method java/lang/StringBuilder."<init>":()V
      18: ldc           #148                // String shutdown executor service [
      20: invokevirtual #40                 // Method java/lang/StringBuilder.append:(Ljava/lang/String;)Ljava/lang/StringBuilder;
      23: aload_2
      24: invokevirtual #40                 // Method java/lang/StringBuilder.append:(Ljava/lang/String;)Ljava/lang/StringBuilder;
      27: ldc           #149                // String ] failed:
      29: invokevirtual #40                 // Method java/lang/StringBuilder.append:(Ljava/lang/String;)Ljava/lang/StringBuilder;
      32: invokevirtual #42                 // Method java/lang/StringBuilder.toString:()Ljava/lang/String;
      35: astore        4
      37: getstatic     #67                 // Field logger:Lorg/apache/dubbo/common/logger/ErrorTypeAwareLogger;
      40: ldc           #105                // String 0-17
      42: ldc           #69                 // String
      44: ldc           #69                 // String
      46: new           #38                 // class java/lang/StringBuilder
      49: dup
      50: invokespecial #39                 // Method java/lang/StringBuilder."<init>":()V
      53: aload         4
      55: invokevirtual #40                 // Method java/lang/StringBuilder.append:(Ljava/lang/String;)Ljava/lang/StringBuilder;
      58: aload_3
      59: invokevirtual #150                // Method java/lang/Exception.getMessage:()Ljava/lang/String;
      62: invokevirtual #40                 // Method java/lang/StringBuilder.append:(Ljava/lang/String;)Ljava/lang/StringBuilder;
      65: invokevirtual #42                 // Method java/lang/StringBuilder.toString:()Ljava/lang/String;
      68: aload_3
      69: invokeinterface #106,  6          // InterfaceMethod org/apache/dubbo/common/logger/ErrorTypeAwareLogger.warn:(Ljava/lang/String;Ljava/lang/String;Ljava/lang/String;Ljava/lang/String;Ljava/lang/Throwable;)V
      74: return
    Exception table:
       from    to  target type
           0     7    10   Class java/lang/Exception

  public void setExtensionAccessor(org.apache.dubbo.common.extension.ExtensionAccessor);
    Code:
       0: aload_0
       1: aload_1
       2: putfield      #60                 // Field extensionAccessor:Lorg/apache/dubbo/common/extension/ExtensionAccessor;
       5: return

  public java.util.concurrent.ScheduledExecutorService nextScheduledExecutor();
    Code:
       0: aload_0
       1: getfield      #14                 // Field frameworkExecutorRepository:Lorg/apache/dubbo/common/threadpool/manager/FrameworkExecutorRepository;
       4: invokevirtual #151                // Method org/apache/dubbo/common/threadpool/manager/FrameworkExecutorRepository.nextScheduledExecutor:()Ljava/util/concurrent/ScheduledExecutorService;
       7: areturn

  public java.util.concurrent.ExecutorService nextExecutorExecutor();
    Code:
       0: aload_0
       1: getfield      #14                 // Field frameworkExecutorRepository:Lorg/apache/dubbo/common/threadpool/manager/FrameworkExecutorRepository;
       4: invokevirtual #152                // Method org/apache/dubbo/common/threadpool/manager/FrameworkExecutorRepository.nextExecutorExecutor:()Ljava/util/concurrent/ExecutorService;
       7: areturn

  public java.util.concurrent.ScheduledExecutorService getServiceDiscoveryAddressNotificationExecutor();
    Code:
       0: aload_0
       1: getfield      #14                 // Field frameworkExecutorRepository:Lorg/apache/dubbo/common/threadpool/manager/FrameworkExecutorRepository;
       4: invokevirtual #153                // Method org/apache/dubbo/common/threadpool/manager/FrameworkExecutorRepository.getServiceDiscoveryAddressNotificationExecutor:()Ljava/util/concurrent/ScheduledExecutorService;
       7: areturn

  public java.util.concurrent.ScheduledExecutorService getMetadataRetryExecutor();
    Code:
       0: aload_0
       1: getfield      #14                 // Field frameworkExecutorRepository:Lorg/apache/dubbo/common/threadpool/manager/FrameworkExecutorRepository;
       4: invokevirtual #154                // Method org/apache/dubbo/common/threadpool/manager/FrameworkExecutorRepository.getMetadataRetryExecutor:()Ljava/util/concurrent/ScheduledExecutorService;
       7: areturn

  public java.util.concurrent.ScheduledExecutorService getRegistryNotificationExecutor();
    Code:
       0: aload_0
       1: getfield      #14                 // Field frameworkExecutorRepository:Lorg/apache/dubbo/common/threadpool/manager/FrameworkExecutorRepository;
       4: invokevirtual #155                // Method org/apache/dubbo/common/threadpool/manager/FrameworkExecutorRepository.getRegistryNotificationExecutor:()Ljava/util/concurrent/ScheduledExecutorService;
       7: areturn

  public java.util.concurrent.ExecutorService getSharedExecutor();
    Code:
       0: aload_0
       1: getfield      #14                 // Field frameworkExecutorRepository:Lorg/apache/dubbo/common/threadpool/manager/FrameworkExecutorRepository;
       4: invokevirtual #78                 // Method org/apache/dubbo/common/threadpool/manager/FrameworkExecutorRepository.getSharedExecutor:()Ljava/util/concurrent/ExecutorService;
       7: areturn

  public java.util.concurrent.ScheduledExecutorService getSharedScheduledExecutor();
    Code:
       0: aload_0
       1: getfield      #14                 // Field frameworkExecutorRepository:Lorg/apache/dubbo/common/threadpool/manager/FrameworkExecutorRepository;
       4: invokevirtual #156                // Method org/apache/dubbo/common/threadpool/manager/FrameworkExecutorRepository.getSharedScheduledExecutor:()Ljava/util/concurrent/ScheduledExecutorService;
       7: areturn

  public java.util.concurrent.ExecutorService getPoolRouterExecutor();
    Code:
       0: aload_0
       1: getfield      #14                 // Field frameworkExecutorRepository:Lorg/apache/dubbo/common/threadpool/manager/FrameworkExecutorRepository;
       4: invokevirtual #157                // Method org/apache/dubbo/common/threadpool/manager/FrameworkExecutorRepository.getPoolRouterExecutor:()Ljava/util/concurrent/ExecutorService;
       7: areturn

  public java.util.concurrent.ScheduledExecutorService getConnectivityScheduledExecutor();
    Code:
       0: aload_0
       1: getfield      #14                 // Field frameworkExecutorRepository:Lorg/apache/dubbo/common/threadpool/manager/FrameworkExecutorRepository;
       4: invokevirtual #158                // Method org/apache/dubbo/common/threadpool/manager/FrameworkExecutorRepository.getConnectivityScheduledExecutor:()Ljava/util/concurrent/ScheduledExecutorService;
       7: areturn

  public java.util.concurrent.ScheduledExecutorService getCacheRefreshingScheduledExecutor();
    Code:
       0: aload_0
       1: getfield      #14                 // Field frameworkExecutorRepository:Lorg/apache/dubbo/common/threadpool/manager/FrameworkExecutorRepository;
       4: invokevirtual #159                // Method org/apache/dubbo/common/threadpool/manager/FrameworkExecutorRepository.getCacheRefreshingScheduledExecutor:()Ljava/util/concurrent/ScheduledExecutorService;
       7: areturn

  public java.util.concurrent.ExecutorService getMappingRefreshingExecutor();
    Code:
       0: aload_0
       1: getfield      #14                 // Field frameworkExecutorRepository:Lorg/apache/dubbo/common/threadpool/manager/FrameworkExecutorRepository;
       4: invokevirtual #160                // Method org/apache/dubbo/common/threadpool/manager/FrameworkExecutorRepository.getMappingRefreshingExecutor:()Ljava/util/concurrent/ExecutorService;
       7: areturn

  public org.apache.dubbo.rpc.executor.ExecutorSupport getExecutorSupport(org.apache.dubbo.common.URL);
    Code:
       0: aload_0
       1: getfield      #161                // Field executorSupport:Lorg/apache/dubbo/rpc/executor/ExecutorSupport;
       4: ifnonnull     19
       7: aload_0
       8: new           #162                // class org/apache/dubbo/rpc/executor/DefaultExecutorSupport
      11: dup
      12: aload_1
      13: invokespecial #163                // Method org/apache/dubbo/rpc/executor/DefaultExecutorSupport."<init>":(Lorg/apache/dubbo/common/URL;)V
      16: putfield      #161                // Field executorSupport:Lorg/apache/dubbo/rpc/executor/ExecutorSupport;
      19: aload_0
      20: getfield      #161                // Field executorSupport:Lorg/apache/dubbo/rpc/executor/ExecutorSupport;
      23: areturn

  private static void lambda$destroyAll$5(java.util.concurrent.ConcurrentMap);
    Code:
       0: aload_0
       1: ifnull        20
       4: aload_0
       5: invokeinterface #142,  1          // InterfaceMethod java/util/concurrent/ConcurrentMap.values:()Ljava/util/Collection;
      10: invokedynamic #164,  0            // InvokeDynamic #7:accept:()Ljava/util/function/Consumer;
      15: invokeinterface #144,  2          // InterfaceMethod java/util/Collection.forEach:(Ljava/util/function/Consumer;)V
      20: return

  private static void lambda$null$4(java.util.concurrent.ExecutorService);
    Code:
       0: aload_0
       1: ifnull        42
       4: aload_0
       5: invokeinterface #27,  1           // InterfaceMethod java/util/concurrent/ExecutorService.isShutdown:()Z
      10: ifne          42
      13: aload_0
      14: bipush        100
      16: invokestatic  #165                // Method org/apache/dubbo/common/utils/ExecutorUtil.shutdownNow:(Ljava/util/concurrent/Executor;I)V
      19: goto          42
      22: astore_1
      23: getstatic     #67                 // Field logger:Lorg/apache/dubbo/common/logger/ErrorTypeAwareLogger;
      26: ldc           #105                // String 0-17
      28: ldc           #69                 // String
      30: ldc           #69                 // String
      32: aload_1
      33: invokevirtual #91                 // Method java/lang/Throwable.getMessage:()Ljava/lang/String;
      36: aload_1
      37: invokeinterface #106,  6          // InterfaceMethod org/apache/dubbo/common/logger/ErrorTypeAwareLogger.warn:(Ljava/lang/String;Ljava/lang/String;Ljava/lang/String;Ljava/lang/String;Ljava/lang/Throwable;)V
      42: return
    Exception table:
       from    to  target type
          13    19    22   Class java/lang/Throwable

  private static boolean lambda$getReferThreadNum$3(java.lang.Integer);
    Code:
       0: aload_0
       1: ifnull        15
       4: aload_0
       5: invokevirtual #95                 // Method java/lang/Integer.intValue:()I
       8: ifle          15
      11: iconst_1
      12: goto          16
      15: iconst_0
      16: ireturn

  private static boolean lambda$getExportThreadNum$2(java.lang.Integer);
    Code:
       0: aload_0
       1: ifnull        15
       4: aload_0
       5: invokevirtual #95                 // Method java/lang/Integer.intValue:()I
       8: ifle          15
      11: iconst_1
      12: goto          16
      15: iconst_0
      16: ireturn

  private java.util.concurrent.ExecutorService lambda$createExecutorIfAbsent$1(org.apache.dubbo.common.URL, java.lang.String);
    Code:
       0: aload_0
       1: aload_1
       2: invokevirtual #30                 // Method createExecutor:(Lorg/apache/dubbo/common/URL;)Ljava/util/concurrent/ExecutorService;
       5: areturn

  private static java.util.concurrent.ConcurrentMap lambda$createExecutorIfAbsent$0(java.lang.String);
    Code:
       0: new           #4                  // class java/util/concurrent/ConcurrentHashMap
       3: dup
       4: invokespecial #5                  // Method java/util/concurrent/ConcurrentHashMap."<init>":()V
       7: areturn

  static {};
    Code:
       0: ldc           #166                // class org/apache/dubbo/common/threadpool/manager/DefaultExecutorRepository
       2: invokestatic  #167                // Method org/apache/dubbo/common/logger/LoggerFactory.getErrorTypeAwareLogger:(Ljava/lang/Class;)Lorg/apache/dubbo/common/logger/ErrorTypeAwareLogger;
       5: putstatic     #67                 // Field logger:Lorg/apache/dubbo/common/logger/ErrorTypeAwareLogger;
       8: ldc           #54                 // int 2147483647
      10: invokestatic  #55                 // Method java/lang/String.valueOf:(I)Ljava/lang/String;
      13: putstatic     #56                 // Field MAX_KEY:Ljava/lang/String;
      16: return
}
