Compiled from "IsolationExecutorRepository.java"
public class org.apache.dubbo.common.threadpool.manager.IsolationExecutorRepository extends org.apache.dubbo.common.threadpool.manager.DefaultExecutorRepository {
  public org.apache.dubbo.common.threadpool.manager.IsolationExecutorRepository(org.apache.dubbo.rpc.model.ApplicationModel);
    Code:
       0: aload_0
       1: aload_1
       2: invokespecial #2                  // Method org/apache/dubbo/common/threadpool/manager/DefaultExecutorRepository."<init>":(Lorg/apache/dubbo/rpc/model/ApplicationModel;)V
       5: return

  protected org.apache.dubbo.common.URL setThreadNameIfAbsent(org.apache.dubbo.common.URL, java.lang.String);
    Code:
       0: aload_1
       1: ldc           #3                  // String threadname
       3: invokevirtual #4                  // Method org/apache/dubbo/common/URL.getParameter:(Ljava/lang/String;)Ljava/lang/String;
       6: ifnonnull     35
       9: aload_1
      10: ldc           #3                  // String threadname
      12: new           #5                  // class java/lang/StringBuilder
      15: dup
      16: invokespecial #6                  // Method java/lang/StringBuilder."<init>":()V
      19: ldc           #7                  // String isolation-
      21: invokevirtual #8                  // Method java/lang/StringBuilder.append:(Ljava/lang/String;)Ljava/lang/StringBuilder;
      24: aload_2
      25: invokevirtual #8                  // Method java/lang/StringBuilder.append:(Ljava/lang/String;)Ljava/lang/StringBuilder;
      28: invokevirtual #9                  // Method java/lang/StringBuilder.toString:()Ljava/lang/String;
      31: invokevirtual #10                 // Method org/apache/dubbo/common/URL.putAttribute:(Ljava/lang/String;Ljava/lang/Object;)Lorg/apache/dubbo/common/URL;
      34: astore_1
      35: aload_1
      36: areturn

  protected java.lang.String getProviderKey(org.apache.dubbo.common.URL);
    Code:
       0: aload_1
       1: invokevirtual #11                 // Method org/apache/dubbo/common/URL.getAttributes:()Ljava/util/Map;
       4: ldc           #12                 // String service-executor
       6: invokeinterface #13,  2           // InterfaceMethod java/util/Map.containsKey:(Ljava/lang/Object;)Z
      11: ifeq          19
      14: aload_1
      15: invokevirtual #14                 // Method org/apache/dubbo/common/URL.getServiceKey:()Ljava/lang/String;
      18: areturn
      19: aload_0
      20: aload_1
      21: invokespecial #15                 // Method org/apache/dubbo/common/threadpool/manager/DefaultExecutorRepository.getProviderKey:(Lorg/apache/dubbo/common/URL;)Ljava/lang/String;
      24: areturn

  protected java.lang.String getProviderKey(org.apache.dubbo.rpc.model.ProviderModel, org.apache.dubbo.common.URL);
    Code:
       0: aload_2
       1: invokevirtual #11                 // Method org/apache/dubbo/common/URL.getAttributes:()Ljava/util/Map;
       4: ldc           #12                 // String service-executor
       6: invokeinterface #13,  2           // InterfaceMethod java/util/Map.containsKey:(Ljava/lang/Object;)Z
      11: ifeq          19
      14: aload_1
      15: invokevirtual #16                 // Method org/apache/dubbo/rpc/model/ProviderModel.getServiceKey:()Ljava/lang/String;
      18: areturn
      19: aload_0
      20: aload_2
      21: invokespecial #15                 // Method org/apache/dubbo/common/threadpool/manager/DefaultExecutorRepository.getProviderKey:(Lorg/apache/dubbo/common/URL;)Ljava/lang/String;
      24: areturn

  protected java.util.concurrent.ExecutorService createExecutor(org.apache.dubbo.common.URL);
    Code:
       0: aload_1
       1: invokevirtual #11                 // Method org/apache/dubbo/common/URL.getAttributes:()Ljava/util/Map;
       4: ldc           #12                 // String service-executor
       6: invokeinterface #17,  2           // InterfaceMethod java/util/Map.get:(Ljava/lang/Object;)Ljava/lang/Object;
      11: astore_2
      12: aload_2
      13: instanceof    #18                 // class java/util/concurrent/ExecutorService
      16: ifeq          24
      19: aload_2
      20: checkcast     #18                 // class java/util/concurrent/ExecutorService
      23: areturn
      24: aload_0
      25: aload_1
      26: invokespecial #19                 // Method org/apache/dubbo/common/threadpool/manager/DefaultExecutorRepository.createExecutor:(Lorg/apache/dubbo/common/URL;)Ljava/util/concurrent/ExecutorService;
      29: areturn

  public org.apache.dubbo.rpc.executor.ExecutorSupport getExecutorSupport(org.apache.dubbo.common.URL);
    Code:
       0: aload_1
       1: invokestatic  #20                 // InterfaceMethod org/apache/dubbo/rpc/executor/IsolationExecutorSupportFactory.getIsolationExecutorSupport:(Lorg/apache/dubbo/common/URL;)Lorg/apache/dubbo/rpc/executor/ExecutorSupport;
       4: areturn
}
