Compiled from "MeshRuleCache.java"
public class org.apache.dubbo.rpc.cluster.router.mesh.route.MeshRuleCache<T> {
  private final java.util.List<java.lang.String> appList;

  private final java.util.Map<java.lang.String, org.apache.dubbo.rpc.cluster.router.mesh.rule.VsDestinationGroup> appToVDGroup;

  private final java.util.Map<java.lang.String, java.util.Map<java.lang.String, org.apache.dubbo.rpc.cluster.router.state.BitList<org.apache.dubbo.rpc.Invoker<T>>>> totalSubsetMap;

  private final org.apache.dubbo.rpc.cluster.router.state.BitList<org.apache.dubbo.rpc.Invoker<T>> unmatchedInvokers;

  private org.apache.dubbo.rpc.cluster.router.mesh.route.MeshRuleCache(java.util.List<java.lang.String>, java.util.Map<java.lang.String, org.apache.dubbo.rpc.cluster.router.mesh.rule.VsDestinationGroup>, java.util.Map<java.lang.String, java.util.Map<java.lang.String, org.apache.dubbo.rpc.cluster.router.state.BitList<org.apache.dubbo.rpc.Invoker<T>>>>, org.apache.dubbo.rpc.cluster.router.state.BitList<org.apache.dubbo.rpc.Invoker<T>>);
    Code:
       0: aload_0
       1: invokespecial #2                  // Method java/lang/Object."<init>":()V
       4: aload_0
       5: aload_1
       6: putfield      #3                  // Field appList:Ljava/util/List;
       9: aload_0
      10: aload_2
      11: putfield      #4                  // Field appToVDGroup:Ljava/util/Map;
      14: aload_0
      15: aload_3
      16: putfield      #5                  // Field totalSubsetMap:Ljava/util/Map;
      19: aload_0
      20: aload         4
      22: putfield      #6                  // Field unmatchedInvokers:Lorg/apache/dubbo/rpc/cluster/router/state/BitList;
      25: return

  public java.util.List<java.lang.String> getAppList();
    Code:
       0: aload_0
       1: getfield      #3                  // Field appList:Ljava/util/List;
       4: areturn

  public java.util.Map<java.lang.String, org.apache.dubbo.rpc.cluster.router.mesh.rule.VsDestinationGroup> getAppToVDGroup();
    Code:
       0: aload_0
       1: getfield      #4                  // Field appToVDGroup:Ljava/util/Map;
       4: areturn

  public java.util.Map<java.lang.String, java.util.Map<java.lang.String, org.apache.dubbo.rpc.cluster.router.state.BitList<org.apache.dubbo.rpc.Invoker<T>>>> getTotalSubsetMap();
    Code:
       0: aload_0
       1: getfield      #5                  // Field totalSubsetMap:Ljava/util/Map;
       4: areturn

  public org.apache.dubbo.rpc.cluster.router.state.BitList<org.apache.dubbo.rpc.Invoker<T>> getUnmatchedInvokers();
    Code:
       0: aload_0
       1: getfield      #6                  // Field unmatchedInvokers:Lorg/apache/dubbo/rpc/cluster/router/state/BitList;
       4: areturn

  public org.apache.dubbo.rpc.cluster.router.mesh.rule.VsDestinationGroup getVsDestinationGroup(java.lang.String);
    Code:
       0: aload_0
       1: getfield      #4                  // Field appToVDGroup:Ljava/util/Map;
       4: aload_1
       5: invokeinterface #7,  2            // InterfaceMethod java/util/Map.get:(Ljava/lang/Object;)Ljava/lang/Object;
      10: checkcast     #8                  // class org/apache/dubbo/rpc/cluster/router/mesh/rule/VsDestinationGroup
      13: areturn

  public org.apache.dubbo.rpc.cluster.router.state.BitList<org.apache.dubbo.rpc.Invoker<T>> getSubsetInvokers(java.lang.String, java.lang.String);
    Code:
       0: aload_0
       1: getfield      #5                  // Field totalSubsetMap:Ljava/util/Map;
       4: aload_1
       5: invokeinterface #7,  2            // InterfaceMethod java/util/Map.get:(Ljava/lang/Object;)Ljava/lang/Object;
      10: checkcast     #9                  // class java/util/Map
      13: astore_3
      14: aload_3
      15: invokestatic  #10                 // Method org/apache/dubbo/common/utils/CollectionUtils.isNotEmptyMap:(Ljava/util/Map;)Z
      18: ifeq          44
      21: aload_3
      22: aload_2
      23: invokeinterface #7,  2            // InterfaceMethod java/util/Map.get:(Ljava/lang/Object;)Ljava/lang/Object;
      28: checkcast     #11                 // class org/apache/dubbo/rpc/cluster/router/state/BitList
      31: astore        4
      33: aload         4
      35: invokestatic  #12                 // Method org/apache/dubbo/common/utils/CollectionUtils.isNotEmpty:(Ljava/util/Collection;)Z
      38: ifeq          44
      41: aload         4
      43: areturn
      44: invokestatic  #13                 // Method org/apache/dubbo/rpc/cluster/router/state/BitList.emptyList:()Lorg/apache/dubbo/rpc/cluster/router/state/BitList;
      47: areturn

  public boolean containsRule();
    Code:
       0: aload_0
       1: getfield      #5                  // Field totalSubsetMap:Ljava/util/Map;
       4: invokeinterface #14,  1           // InterfaceMethod java/util/Map.isEmpty:()Z
       9: ifne          16
      12: iconst_1
      13: goto          17
      16: iconst_0
      17: ireturn

  public static <T> org.apache.dubbo.rpc.cluster.router.mesh.route.MeshRuleCache<T> build(java.lang.String, org.apache.dubbo.rpc.cluster.router.state.BitList<org.apache.dubbo.rpc.Invoker<T>>, java.util.Map<java.lang.String, org.apache.dubbo.rpc.cluster.router.mesh.rule.VsDestinationGroup>);
    Code:
       0: aload_2
       1: invokestatic  #10                 // Method org/apache/dubbo/common/utils/CollectionUtils.isNotEmptyMap:(Ljava/util/Map;)Z
       4: ifeq          341
       7: new           #11                 // class org/apache/dubbo/rpc/cluster/router/state/BitList
      10: dup
      11: aload_1
      12: invokevirtual #15                 // Method org/apache/dubbo/rpc/cluster/router/state/BitList.getOriginList:()Ljava/util/List;
      15: iconst_1
      16: invokespecial #16                 // Method org/apache/dubbo/rpc/cluster/router/state/BitList."<init>":(Ljava/util/List;Z)V
      19: astore_3
      20: new           #17                 // class java/util/HashMap
      23: dup
      24: invokespecial #18                 // Method java/util/HashMap."<init>":()V
      27: astore        4
      29: aload_1
      30: invokevirtual #19                 // Method org/apache/dubbo/rpc/cluster/router/state/BitList.iterator:()Ljava/util/Iterator;
      33: astore        5
      35: aload         5
      37: invokeinterface #20,  1           // InterfaceMethod java/util/Iterator.hasNext:()Z
      42: ifeq          310
      45: aload         5
      47: invokeinterface #21,  1           // InterfaceMethod java/util/Iterator.next:()Ljava/lang/Object;
      52: checkcast     #22                 // class org/apache/dubbo/rpc/Invoker
      55: astore        6
      57: aload         6
      59: invokeinterface #23,  1           // InterfaceMethod org/apache/dubbo/rpc/Invoker.getUrl:()Lorg/apache/dubbo/common/URL;
      64: invokevirtual #24                 // Method org/apache/dubbo/common/URL.getRemoteApplication:()Ljava/lang/String;
      67: astore        7
      69: aload         7
      71: invokestatic  #25                 // Method org/apache/dubbo/common/utils/StringUtils.isEmpty:(Ljava/lang/String;)Z
      74: ifne          87
      77: ldc           #26                 // String unknown
      79: aload         7
      81: invokevirtual #27                 // Method java/lang/String.equals:(Ljava/lang/Object;)Z
      84: ifeq          97
      87: aload_3
      88: aload         6
      90: invokevirtual #28                 // Method org/apache/dubbo/rpc/cluster/router/state/BitList.add:(Ljava/lang/Object;)Z
      93: pop
      94: goto          35
      97: aload_2
      98: aload         7
     100: invokeinterface #7,  2            // InterfaceMethod java/util/Map.get:(Ljava/lang/Object;)Ljava/lang/Object;
     105: checkcast     #8                  // class org/apache/dubbo/rpc/cluster/router/mesh/rule/VsDestinationGroup
     108: astore        8
     110: aload         8
     112: ifnonnull     125
     115: aload_3
     116: aload         6
     118: invokevirtual #28                 // Method org/apache/dubbo/rpc/cluster/router/state/BitList.add:(Ljava/lang/Object;)Z
     121: pop
     122: goto          35
     125: aload         4
     127: aload         7
     129: invokedynamic #29,  0             // InvokeDynamic #0:apply:()Ljava/util/function/Function;
     134: invokeinterface #30,  3           // InterfaceMethod java/util/Map.computeIfAbsent:(Ljava/lang/Object;Ljava/util/function/Function;)Ljava/lang/Object;
     139: checkcast     #9                  // class java/util/Map
     142: astore        9
     144: iconst_0
     145: istore        10
     147: aload         8
     149: invokevirtual #31                 // Method org/apache/dubbo/rpc/cluster/router/mesh/rule/VsDestinationGroup.getDestinationRuleList:()Ljava/util/List;
     152: invokeinterface #32,  1           // InterfaceMethod java/util/List.iterator:()Ljava/util/Iterator;
     157: astore        11
     159: aload         11
     161: invokeinterface #20,  1           // InterfaceMethod java/util/Iterator.hasNext:()Z
     166: ifeq          295
     169: aload         11
     171: invokeinterface #21,  1           // InterfaceMethod java/util/Iterator.next:()Ljava/lang/Object;
     176: checkcast     #33                 // class org/apache/dubbo/rpc/cluster/router/mesh/rule/destination/DestinationRule
     179: astore        12
     181: aload         12
     183: invokevirtual #34                 // Method org/apache/dubbo/rpc/cluster/router/mesh/rule/destination/DestinationRule.getSpec:()Lorg/apache/dubbo/rpc/cluster/router/mesh/rule/destination/DestinationRuleSpec;
     186: astore        13
     188: aload         13
     190: invokevirtual #35                 // Method org/apache/dubbo/rpc/cluster/router/mesh/rule/destination/DestinationRuleSpec.getSubsets:()Ljava/util/List;
     193: astore        14
     195: aload         14
     197: invokeinterface #32,  1           // InterfaceMethod java/util/List.iterator:()Ljava/util/Iterator;
     202: astore        15
     204: aload         15
     206: invokeinterface #20,  1           // InterfaceMethod java/util/Iterator.hasNext:()Z
     211: ifeq          292
     214: aload         15
     216: invokeinterface #21,  1           // InterfaceMethod java/util/Iterator.next:()Ljava/lang/Object;
     221: checkcast     #36                 // class org/apache/dubbo/rpc/cluster/router/mesh/rule/destination/Subset
     224: astore        16
     226: aload         16
     228: invokevirtual #37                 // Method org/apache/dubbo/rpc/cluster/router/mesh/rule/destination/Subset.getName:()Ljava/lang/String;
     231: astore        17
     233: aload         9
     235: aload         17
     237: aload_1
     238: invokedynamic #38,  0             // InvokeDynamic #1:apply:(Lorg/apache/dubbo/rpc/cluster/router/state/BitList;)Ljava/util/function/Function;
     243: invokeinterface #30,  3           // InterfaceMethod java/util/Map.computeIfAbsent:(Ljava/lang/Object;Ljava/util/function/Function;)Ljava/lang/Object;
     248: checkcast     #39                 // class java/util/List
     251: astore        18
     253: aload         16
     255: invokevirtual #40                 // Method org/apache/dubbo/rpc/cluster/router/mesh/rule/destination/Subset.getLabels:()Ljava/util/Map;
     258: astore        19
     260: aload         6
     262: invokeinterface #23,  1           // InterfaceMethod org/apache/dubbo/rpc/Invoker.getUrl:()Lorg/apache/dubbo/common/URL;
     267: aload_0
     268: aload         19
     270: invokestatic  #41                 // Method isLabelMatch:(Lorg/apache/dubbo/common/URL;Ljava/lang/String;Ljava/util/Map;)Z
     273: ifeq          289
     276: aload         18
     278: aload         6
     280: invokeinterface #42,  2           // InterfaceMethod java/util/List.add:(Ljava/lang/Object;)Z
     285: pop
     286: iconst_1
     287: istore        10
     289: goto          204
     292: goto          159
     295: iload         10
     297: ifne          307
     300: aload_3
     301: aload         6
     303: invokevirtual #28                 // Method org/apache/dubbo/rpc/cluster/router/state/BitList.add:(Ljava/lang/Object;)Z
     306: pop
     307: goto          35
     310: new           #43                 // class org/apache/dubbo/rpc/cluster/router/mesh/route/MeshRuleCache
     313: dup
     314: new           #44                 // class java/util/LinkedList
     317: dup
     318: aload_2
     319: invokeinterface #45,  1           // InterfaceMethod java/util/Map.keySet:()Ljava/util/Set;
     324: invokespecial #46                 // Method java/util/LinkedList."<init>":(Ljava/util/Collection;)V
     327: aload_2
     328: invokestatic  #47                 // Method java/util/Collections.unmodifiableMap:(Ljava/util/Map;)Ljava/util/Map;
     331: aload         4
     333: invokestatic  #47                 // Method java/util/Collections.unmodifiableMap:(Ljava/util/Map;)Ljava/util/Map;
     336: aload_3
     337: invokespecial #48                 // Method "<init>":(Ljava/util/List;Ljava/util/Map;Ljava/util/Map;Lorg/apache/dubbo/rpc/cluster/router/state/BitList;)V
     340: areturn
     341: new           #43                 // class org/apache/dubbo/rpc/cluster/router/mesh/route/MeshRuleCache
     344: dup
     345: invokestatic  #49                 // Method java/util/Collections.emptyList:()Ljava/util/List;
     348: invokestatic  #50                 // Method java/util/Collections.emptyMap:()Ljava/util/Map;
     351: invokestatic  #50                 // Method java/util/Collections.emptyMap:()Ljava/util/Map;
     354: aload_1
     355: invokespecial #48                 // Method "<init>":(Ljava/util/List;Ljava/util/Map;Ljava/util/Map;Lorg/apache/dubbo/rpc/cluster/router/state/BitList;)V
     358: areturn

  public static <T> org.apache.dubbo.rpc.cluster.router.mesh.route.MeshRuleCache<T> emptyCache();
    Code:
       0: new           #43                 // class org/apache/dubbo/rpc/cluster/router/mesh/route/MeshRuleCache
       3: dup
       4: invokestatic  #49                 // Method java/util/Collections.emptyList:()Ljava/util/List;
       7: invokestatic  #50                 // Method java/util/Collections.emptyMap:()Ljava/util/Map;
      10: invokestatic  #50                 // Method java/util/Collections.emptyMap:()Ljava/util/Map;
      13: invokestatic  #13                 // Method org/apache/dubbo/rpc/cluster/router/state/BitList.emptyList:()Lorg/apache/dubbo/rpc/cluster/router/state/BitList;
      16: invokespecial #48                 // Method "<init>":(Ljava/util/List;Ljava/util/Map;Ljava/util/Map;Lorg/apache/dubbo/rpc/cluster/router/state/BitList;)V
      19: areturn

  protected static boolean isLabelMatch(org.apache.dubbo.common.URL, java.lang.String, java.util.Map<java.lang.String, java.lang.String>);
    Code:
       0: aload_2
       1: ifnull        13
       4: aload_2
       5: invokeinterface #51,  1           // InterfaceMethod java/util/Map.size:()I
      10: ifne          15
      13: iconst_1
      14: ireturn
      15: aload_2
      16: invokeinterface #52,  1           // InterfaceMethod java/util/Map.entrySet:()Ljava/util/Set;
      21: invokeinterface #53,  1           // InterfaceMethod java/util/Set.iterator:()Ljava/util/Iterator;
      26: astore_3
      27: aload_3
      28: invokeinterface #20,  1           // InterfaceMethod java/util/Iterator.hasNext:()Z
      33: ifeq          95
      36: aload_3
      37: invokeinterface #21,  1           // InterfaceMethod java/util/Iterator.next:()Ljava/lang/Object;
      42: checkcast     #54                 // class java/util/Map$Entry
      45: astore        4
      47: aload         4
      49: invokeinterface #55,  1           // InterfaceMethod java/util/Map$Entry.getKey:()Ljava/lang/Object;
      54: checkcast     #56                 // class java/lang/String
      57: astore        5
      59: aload         4
      61: invokeinterface #57,  1           // InterfaceMethod java/util/Map$Entry.getValue:()Ljava/lang/Object;
      66: checkcast     #56                 // class java/lang/String
      69: astore        6
      71: aload_0
      72: aload_1
      73: aload         5
      75: invokevirtual #58                 // Method org/apache/dubbo/common/URL.getOriginalServiceParameter:(Ljava/lang/String;Ljava/lang/String;)Ljava/lang/String;
      78: astore        7
      80: aload         6
      82: aload         7
      84: invokevirtual #27                 // Method java/lang/String.equals:(Ljava/lang/Object;)Z
      87: ifne          92
      90: iconst_0
      91: ireturn
      92: goto          27
      95: iconst_1
      96: ireturn

  public boolean equals(java.lang.Object);
    Code:
       0: aload_0
       1: aload_1
       2: if_acmpne     7
       5: iconst_1
       6: ireturn
       7: aload_1
       8: ifnull        22
      11: aload_0
      12: invokevirtual #59                 // Method java/lang/Object.getClass:()Ljava/lang/Class;
      15: aload_1
      16: invokevirtual #59                 // Method java/lang/Object.getClass:()Ljava/lang/Class;
      19: if_acmpeq     24
      22: iconst_0
      23: ireturn
      24: aload_1
      25: checkcast     #43                 // class org/apache/dubbo/rpc/cluster/router/mesh/route/MeshRuleCache
      28: astore_2
      29: aload_0
      30: getfield      #3                  // Field appList:Ljava/util/List;
      33: aload_2
      34: getfield      #3                  // Field appList:Ljava/util/List;
      37: invokestatic  #60                 // Method java/util/Objects.equals:(Ljava/lang/Object;Ljava/lang/Object;)Z
      40: ifeq          89
      43: aload_0
      44: getfield      #4                  // Field appToVDGroup:Ljava/util/Map;
      47: aload_2
      48: getfield      #4                  // Field appToVDGroup:Ljava/util/Map;
      51: invokestatic  #60                 // Method java/util/Objects.equals:(Ljava/lang/Object;Ljava/lang/Object;)Z
      54: ifeq          89
      57: aload_0
      58: getfield      #5                  // Field totalSubsetMap:Ljava/util/Map;
      61: aload_2
      62: getfield      #5                  // Field totalSubsetMap:Ljava/util/Map;
      65: invokestatic  #60                 // Method java/util/Objects.equals:(Ljava/lang/Object;Ljava/lang/Object;)Z
      68: ifeq          89
      71: aload_0
      72: getfield      #6                  // Field unmatchedInvokers:Lorg/apache/dubbo/rpc/cluster/router/state/BitList;
      75: aload_2
      76: getfield      #6                  // Field unmatchedInvokers:Lorg/apache/dubbo/rpc/cluster/router/state/BitList;
      79: invokestatic  #60                 // Method java/util/Objects.equals:(Ljava/lang/Object;Ljava/lang/Object;)Z
      82: ifeq          89
      85: iconst_1
      86: goto          90
      89: iconst_0
      90: ireturn

  public int hashCode();
    Code:
       0: iconst_4
       1: anewarray     #61                 // class java/lang/Object
       4: dup
       5: iconst_0
       6: aload_0
       7: getfield      #3                  // Field appList:Ljava/util/List;
      10: aastore
      11: dup
      12: iconst_1
      13: aload_0
      14: getfield      #4                  // Field appToVDGroup:Ljava/util/Map;
      17: aastore
      18: dup
      19: iconst_2
      20: aload_0
      21: getfield      #5                  // Field totalSubsetMap:Ljava/util/Map;
      24: aastore
      25: dup
      26: iconst_3
      27: aload_0
      28: getfield      #6                  // Field unmatchedInvokers:Lorg/apache/dubbo/rpc/cluster/router/state/BitList;
      31: aastore
      32: invokestatic  #62                 // Method java/util/Objects.hash:([Ljava/lang/Object;)I
      35: ireturn

  private static org.apache.dubbo.rpc.cluster.router.state.BitList lambda$build$1(org.apache.dubbo.rpc.cluster.router.state.BitList, java.lang.String);
    Code:
       0: new           #11                 // class org/apache/dubbo/rpc/cluster/router/state/BitList
       3: dup
       4: aload_0
       5: invokevirtual #15                 // Method org/apache/dubbo/rpc/cluster/router/state/BitList.getOriginList:()Ljava/util/List;
       8: iconst_1
       9: invokespecial #16                 // Method org/apache/dubbo/rpc/cluster/router/state/BitList."<init>":(Ljava/util/List;Z)V
      12: areturn

  private static java.util.Map lambda$build$0(java.lang.String);
    Code:
       0: new           #17                 // class java/util/HashMap
       3: dup
       4: invokespecial #18                 // Method java/util/HashMap."<init>":()V
       7: areturn
}
