Compiled from "MeshAppRuleListener.java"
public class org.apache.dubbo.rpc.cluster.router.mesh.route.MeshAppRuleListener implements org.apache.dubbo.common.config.configcenter.ConfigurationListener {
  private static final org.apache.dubbo.common.logger.ErrorTypeAwareLogger logger;

  private final org.apache.dubbo.rpc.cluster.router.mesh.util.MeshRuleDispatcher meshRuleDispatcher;

  private final java.lang.String appName;

  private volatile java.util.Map<java.lang.String, java.util.List<java.util.Map<java.lang.String, java.lang.Object>>> ruleMapHolder;

  public org.apache.dubbo.rpc.cluster.router.mesh.route.MeshAppRuleListener(java.lang.String);
    Code:
       0: aload_0
       1: invokespecial #3                  // Method java/lang/Object."<init>":()V
       4: aload_0
       5: aload_1
       6: putfield      #4                  // Field appName:Ljava/lang/String;
       9: aload_0
      10: new           #5                  // class org/apache/dubbo/rpc/cluster/router/mesh/util/MeshRuleDispatcher
      13: dup
      14: aload_1
      15: invokespecial #6                  // Method org/apache/dubbo/rpc/cluster/router/mesh/util/MeshRuleDispatcher."<init>":(Ljava/lang/String;)V
      18: putfield      #7                  // Field meshRuleDispatcher:Lorg/apache/dubbo/rpc/cluster/router/mesh/util/MeshRuleDispatcher;
      21: return

  public void receiveConfigInfo(java.lang.String);
    Code:
       0: getstatic     #8                  // Field logger:Lorg/apache/dubbo/common/logger/ErrorTypeAwareLogger;
       3: invokeinterface #9,  1            // InterfaceMethod org/apache/dubbo/common/logger/ErrorTypeAwareLogger.isDebugEnabled:()Z
       8: ifeq          39
      11: getstatic     #8                  // Field logger:Lorg/apache/dubbo/common/logger/ErrorTypeAwareLogger;
      14: ldc           #10                 // String [MeshAppRule] Received rule for app [{0}]: {1}.
      16: iconst_2
      17: anewarray     #11                 // class java/lang/Object
      20: dup
      21: iconst_0
      22: aload_0
      23: getfield      #4                  // Field appName:Ljava/lang/String;
      26: aastore
      27: dup
      28: iconst_1
      29: aload_1
      30: aastore
      31: invokestatic  #12                 // Method java/text/MessageFormat.format:(Ljava/lang/String;[Ljava/lang/Object;)Ljava/lang/String;
      34: invokeinterface #13,  2           // InterfaceMethod org/apache/dubbo/common/logger/ErrorTypeAwareLogger.debug:(Ljava/lang/String;)V
      39: new           #14                 // class java/util/HashMap
      42: dup
      43: invokespecial #15                 // Method java/util/HashMap."<init>":()V
      46: astore_2
      47: new           #16                 // class org/yaml/snakeyaml/representer/Representer
      50: dup
      51: new           #17                 // class org/yaml/snakeyaml/DumperOptions
      54: dup
      55: invokespecial #18                 // Method org/yaml/snakeyaml/DumperOptions."<init>":()V
      58: invokespecial #19                 // Method org/yaml/snakeyaml/representer/Representer."<init>":(Lorg/yaml/snakeyaml/DumperOptions;)V
      61: astore_3
      62: aload_3
      63: invokevirtual #20                 // Method org/yaml/snakeyaml/representer/Representer.getPropertyUtils:()Lorg/yaml/snakeyaml/introspector/PropertyUtils;
      66: iconst_1
      67: invokevirtual #21                 // Method org/yaml/snakeyaml/introspector/PropertyUtils.setSkipMissingProperties:(Z)V
      70: new           #22                 // class org/yaml/snakeyaml/Yaml
      73: dup
      74: new           #23                 // class org/yaml/snakeyaml/constructor/SafeConstructor
      77: dup
      78: new           #24                 // class org/yaml/snakeyaml/LoaderOptions
      81: dup
      82: invokespecial #25                 // Method org/yaml/snakeyaml/LoaderOptions."<init>":()V
      85: invokespecial #26                 // Method org/yaml/snakeyaml/constructor/SafeConstructor."<init>":(Lorg/yaml/snakeyaml/LoaderOptions;)V
      88: aload_3
      89: invokespecial #27                 // Method org/yaml/snakeyaml/Yaml."<init>":(Lorg/yaml/snakeyaml/constructor/BaseConstructor;Lorg/yaml/snakeyaml/representer/Representer;)V
      92: astore        4
      94: aload         4
      96: aload_1
      97: invokevirtual #28                 // Method org/yaml/snakeyaml/Yaml.loadAll:(Ljava/lang/String;)Ljava/lang/Iterable;
     100: astore        5
     102: aload         5
     104: invokeinterface #29,  1           // InterfaceMethod java/lang/Iterable.iterator:()Ljava/util/Iterator;
     109: astore        6
     111: aload         6
     113: invokeinterface #30,  1           // InterfaceMethod java/util/Iterator.hasNext:()Z
     118: ifeq          281
     121: aload         6
     123: invokeinterface #31,  1           // InterfaceMethod java/util/Iterator.next:()Ljava/lang/Object;
     128: astore        7
     130: aload         7
     132: instanceof    #32                 // class java/util/Map
     135: ifeq          233
     138: aload         7
     140: checkcast     #32                 // class java/util/Map
     143: astore        8
     145: aload_0
     146: aload         8
     148: invokespecial #33                 // Method computeRuleType:(Ljava/util/Map;)Ljava/lang/String;
     151: astore        9
     153: aload         9
     155: ifnull        185
     158: aload_2
     159: aload         9
     161: invokedynamic #34,  0             // InvokeDynamic #0:apply:()Ljava/util/function/Function;
     166: invokeinterface #35,  3           // InterfaceMethod java/util/Map.computeIfAbsent:(Ljava/lang/Object;Ljava/util/function/Function;)Ljava/lang/Object;
     171: checkcast     #36                 // class java/util/List
     174: aload         8
     176: invokeinterface #37,  2           // InterfaceMethod java/util/List.add:(Ljava/lang/Object;)Z
     181: pop
     182: goto          230
     185: getstatic     #8                  // Field logger:Lorg/apache/dubbo/common/logger/ErrorTypeAwareLogger;
     188: ldc           #38                 // String 2-13
     190: ldc           #39                 // String receive mesh app route rule is invalid
     192: ldc           #40                 // String
     194: new           #41                 // class java/lang/StringBuilder
     197: dup
     198: invokespecial #42                 // Method java/lang/StringBuilder."<init>":()V
     201: ldc           #43                 // String Unable to get rule type from raw rule. Probably the metadata.name is absent. App Name:
     203: invokevirtual #44                 // Method java/lang/StringBuilder.append:(Ljava/lang/String;)Ljava/lang/StringBuilder;
     206: aload_0
     207: getfield      #4                  // Field appName:Ljava/lang/String;
     210: invokevirtual #44                 // Method java/lang/StringBuilder.append:(Ljava/lang/String;)Ljava/lang/StringBuilder;
     213: ldc           #45                 // String  RawRule:
     215: invokevirtual #44                 // Method java/lang/StringBuilder.append:(Ljava/lang/String;)Ljava/lang/StringBuilder;
     218: aload_1
     219: invokevirtual #44                 // Method java/lang/StringBuilder.append:(Ljava/lang/String;)Ljava/lang/StringBuilder;
     222: invokevirtual #46                 // Method java/lang/StringBuilder.toString:()Ljava/lang/String;
     225: invokeinterface #47,  5           // InterfaceMethod org/apache/dubbo/common/logger/ErrorTypeAwareLogger.error:(Ljava/lang/String;Ljava/lang/String;Ljava/lang/String;Ljava/lang/String;)V
     230: goto          278
     233: getstatic     #8                  // Field logger:Lorg/apache/dubbo/common/logger/ErrorTypeAwareLogger;
     236: ldc           #38                 // String 2-13
     238: ldc           #39                 // String receive mesh app route rule is invalid
     240: ldc           #40                 // String
     242: new           #41                 // class java/lang/StringBuilder
     245: dup
     246: invokespecial #42                 // Method java/lang/StringBuilder."<init>":()V
     249: ldc           #48                 // String Rule format is unacceptable. App Name:
     251: invokevirtual #44                 // Method java/lang/StringBuilder.append:(Ljava/lang/String;)Ljava/lang/StringBuilder;
     254: aload_0
     255: getfield      #4                  // Field appName:Ljava/lang/String;
     258: invokevirtual #44                 // Method java/lang/StringBuilder.append:(Ljava/lang/String;)Ljava/lang/StringBuilder;
     261: ldc           #45                 // String  RawRule:
     263: invokevirtual #44                 // Method java/lang/StringBuilder.append:(Ljava/lang/String;)Ljava/lang/StringBuilder;
     266: aload_1
     267: invokevirtual #44                 // Method java/lang/StringBuilder.append:(Ljava/lang/String;)Ljava/lang/StringBuilder;
     270: invokevirtual #46                 // Method java/lang/StringBuilder.toString:()Ljava/lang/String;
     273: invokeinterface #47,  5           // InterfaceMethod org/apache/dubbo/common/logger/ErrorTypeAwareLogger.error:(Ljava/lang/String;Ljava/lang/String;Ljava/lang/String;Ljava/lang/String;)V
     278: goto          111
     281: aload_0
     282: aload_2
     283: putfield      #49                 // Field ruleMapHolder:Ljava/util/Map;
     286: goto          324
     289: astore_2
     290: getstatic     #8                  // Field logger:Lorg/apache/dubbo/common/logger/ErrorTypeAwareLogger;
     293: ldc           #38                 // String 2-13
     295: ldc           #51                 // String failed to receive mesh app route rule
     297: ldc           #40                 // String
     299: new           #41                 // class java/lang/StringBuilder
     302: dup
     303: invokespecial #42                 // Method java/lang/StringBuilder."<init>":()V
     306: ldc           #52                 // String [MeshAppRule] parse failed:
     308: invokevirtual #44                 // Method java/lang/StringBuilder.append:(Ljava/lang/String;)Ljava/lang/StringBuilder;
     311: aload_1
     312: invokevirtual #44                 // Method java/lang/StringBuilder.append:(Ljava/lang/String;)Ljava/lang/StringBuilder;
     315: invokevirtual #46                 // Method java/lang/StringBuilder.toString:()Ljava/lang/String;
     318: aload_2
     319: invokeinterface #53,  6           // InterfaceMethod org/apache/dubbo/common/logger/ErrorTypeAwareLogger.error:(Ljava/lang/String;Ljava/lang/String;Ljava/lang/String;Ljava/lang/String;Ljava/lang/Throwable;)V
     324: aload_0
     325: getfield      #49                 // Field ruleMapHolder:Ljava/util/Map;
     328: ifnull        342
     331: aload_0
     332: getfield      #7                  // Field meshRuleDispatcher:Lorg/apache/dubbo/rpc/cluster/router/mesh/util/MeshRuleDispatcher;
     335: aload_0
     336: getfield      #49                 // Field ruleMapHolder:Ljava/util/Map;
     339: invokevirtual #54                 // Method org/apache/dubbo/rpc/cluster/router/mesh/util/MeshRuleDispatcher.post:(Ljava/util/Map;)V
     342: return
    Exception table:
       from    to  target type
          39   286   289   Class java/lang/Exception

  private java.lang.String computeRuleType(java.util.Map<java.lang.String, java.lang.Object>);
    Code:
       0: aload_1
       1: ldc           #55                 // String metadata
       3: invokeinterface #56,  2           // InterfaceMethod java/util/Map.get:(Ljava/lang/Object;)Ljava/lang/Object;
       8: astore_2
       9: aload_2
      10: instanceof    #32                 // class java/util/Map
      13: ifeq          72
      16: aload_2
      17: checkcast     #32                 // class java/util/Map
      20: invokestatic  #57                 // Method org/apache/dubbo/common/utils/CollectionUtils.isNotEmptyMap:(Ljava/util/Map;)Z
      23: ifeq          72
      26: aload_2
      27: checkcast     #32                 // class java/util/Map
      30: astore_3
      31: aload_3
      32: ldc           #58                 // String name
      34: invokeinterface #56,  2           // InterfaceMethod java/util/Map.get:(Ljava/lang/Object;)Ljava/lang/Object;
      39: checkcast     #59                 // class java/lang/String
      42: astore        4
      44: aload         4
      46: ldc           #60                 // String .
      48: invokevirtual #61                 // Method java/lang/String.contains:(Ljava/lang/CharSequence;)Z
      51: ifne          57
      54: ldc           #62                 // String standard
      56: areturn
      57: aload         4
      59: aload         4
      61: ldc           #60                 // String .
      63: invokevirtual #63                 // Method java/lang/String.indexOf:(Ljava/lang/String;)I
      66: iconst_1
      67: iadd
      68: invokevirtual #64                 // Method java/lang/String.substring:(I)Ljava/lang/String;
      71: areturn
      72: aconst_null
      73: areturn

  public <T> void register(org.apache.dubbo.rpc.cluster.router.mesh.util.MeshRuleListener);
    Code:
       0: aload_0
       1: getfield      #49                 // Field ruleMapHolder:Ljava/util/Map;
       4: ifnull        41
       7: aload_0
       8: getfield      #49                 // Field ruleMapHolder:Ljava/util/Map;
      11: aload_1
      12: invokeinterface #65,  1           // InterfaceMethod org/apache/dubbo/rpc/cluster/router/mesh/util/MeshRuleListener.ruleSuffix:()Ljava/lang/String;
      17: invokeinterface #56,  2           // InterfaceMethod java/util/Map.get:(Ljava/lang/Object;)Ljava/lang/Object;
      22: checkcast     #36                 // class java/util/List
      25: astore_2
      26: aload_2
      27: ifnull        41
      30: aload_1
      31: aload_0
      32: getfield      #4                  // Field appName:Ljava/lang/String;
      35: aload_2
      36: invokeinterface #66,  3           // InterfaceMethod org/apache/dubbo/rpc/cluster/router/mesh/util/MeshRuleListener.onRuleChange:(Ljava/lang/String;Ljava/util/List;)V
      41: aload_0
      42: getfield      #7                  // Field meshRuleDispatcher:Lorg/apache/dubbo/rpc/cluster/router/mesh/util/MeshRuleDispatcher;
      45: aload_1
      46: invokevirtual #67                 // Method org/apache/dubbo/rpc/cluster/router/mesh/util/MeshRuleDispatcher.register:(Lorg/apache/dubbo/rpc/cluster/router/mesh/util/MeshRuleListener;)V
      49: return

  public <T> void unregister(org.apache.dubbo.rpc.cluster.router.mesh.util.MeshRuleListener);
    Code:
       0: aload_0
       1: getfield      #7                  // Field meshRuleDispatcher:Lorg/apache/dubbo/rpc/cluster/router/mesh/util/MeshRuleDispatcher;
       4: aload_1
       5: invokevirtual #68                 // Method org/apache/dubbo/rpc/cluster/router/mesh/util/MeshRuleDispatcher.unregister:(Lorg/apache/dubbo/rpc/cluster/router/mesh/util/MeshRuleListener;)V
       8: return

  public void process(org.apache.dubbo.common.config.configcenter.ConfigChangedEvent);
    Code:
       0: aload_1
       1: invokevirtual #69                 // Method org/apache/dubbo/common/config/configcenter/ConfigChangedEvent.getChangeType:()Lorg/apache/dubbo/common/config/configcenter/ConfigChangeType;
       4: getstatic     #70                 // Field org/apache/dubbo/common/config/configcenter/ConfigChangeType.DELETED:Lorg/apache/dubbo/common/config/configcenter/ConfigChangeType;
       7: if_acmpne     17
      10: aload_0
      11: ldc           #40                 // String
      13: invokevirtual #71                 // Method receiveConfigInfo:(Ljava/lang/String;)V
      16: return
      17: aload_0
      18: aload_1
      19: invokevirtual #72                 // Method org/apache/dubbo/common/config/configcenter/ConfigChangedEvent.getContent:()Ljava/lang/String;
      22: invokevirtual #71                 // Method receiveConfigInfo:(Ljava/lang/String;)V
      25: return

  public boolean isEmpty();
    Code:
       0: aload_0
       1: getfield      #7                  // Field meshRuleDispatcher:Lorg/apache/dubbo/rpc/cluster/router/mesh/util/MeshRuleDispatcher;
       4: invokevirtual #73                 // Method org/apache/dubbo/rpc/cluster/router/mesh/util/MeshRuleDispatcher.isEmpty:()Z
       7: ireturn

  public org.apache.dubbo.rpc.cluster.router.mesh.util.MeshRuleDispatcher getMeshRuleDispatcher();
    Code:
       0: aload_0
       1: getfield      #7                  // Field meshRuleDispatcher:Lorg/apache/dubbo/rpc/cluster/router/mesh/util/MeshRuleDispatcher;
       4: areturn

  private static java.util.List lambda$receiveConfigInfo$0(java.lang.String);
    Code:
       0: new           #74                 // class java/util/LinkedList
       3: dup
       4: invokespecial #75                 // Method java/util/LinkedList."<init>":()V
       7: areturn

  static {};
    Code:
       0: ldc           #76                 // class org/apache/dubbo/rpc/cluster/router/mesh/route/MeshAppRuleListener
       2: invokestatic  #77                 // Method org/apache/dubbo/common/logger/LoggerFactory.getErrorTypeAwareLogger:(Ljava/lang/Class;)Lorg/apache/dubbo/common/logger/ErrorTypeAwareLogger;
       5: putstatic     #8                  // Field logger:Lorg/apache/dubbo/common/logger/ErrorTypeAwareLogger;
       8: return
}
