Compiled from "StandardMeshRuleRouterFactory.java"
public class org.apache.dubbo.rpc.cluster.router.mesh.route.StandardMeshRuleRouterFactory implements org.apache.dubbo.rpc.cluster.router.state.StateRouterFactory {
  public org.apache.dubbo.rpc.cluster.router.mesh.route.StandardMeshRuleRouterFactory();
    Code:
       0: aload_0
       1: invokespecial #1                  // Method java/lang/Object."<init>":()V
       4: return

  public <T> org.apache.dubbo.rpc.cluster.router.state.StateRouter<T> getRouter(java.lang.Class<T>, org.apache.dubbo.common.URL);
    Code:
       0: new           #2                  // class org/apache/dubbo/rpc/cluster/router/mesh/route/StandardMeshRuleRouter
       3: dup
       4: aload_2
       5: invokespecial #3                  // Method org/apache/dubbo/rpc/cluster/router/mesh/route/StandardMeshRuleRouter."<init>":(Lorg/apache/dubbo/common/URL;)V
       8: areturn
}
