Compiled from "DataMatrixWriter.java"
public final class com.google.zxing.datamatrix.DataMatrixWriter implements com.google.zxing.Writer {
  public com.google.zxing.datamatrix.DataMatrixWriter();
    Code:
       0: aload_0
       1: invokespecial #1                  // Method java/lang/Object."<init>":()V
       4: return

  public com.google.zxing.common.BitMatrix encode(java.lang.String, com.google.zxing.BarcodeFormat, int, int);
    Code:
       0: aload_0
       1: aload_1
       2: aload_2
       3: iload_3
       4: iload         4
       6: aconst_null
       7: invokevirtual #2                  // Method encode:(Ljava/lang/String;Lcom/google/zxing/BarcodeFormat;IILjava/util/Map;)Lcom/google/zxing/common/BitMatrix;
      10: areturn

  public com.google.zxing.common.BitMatrix encode(java.lang.String, com.google.zxing.BarcodeFormat, int, int, java.util.Map<com.google.zxing.EncodeHintType, ?>);
    Code:
       0: aload_1
       1: invokevirtual #3                  // Method java/lang/String.isEmpty:()Z
       4: ifeq          17
       7: new           #4                  // class java/lang/IllegalArgumentException
      10: dup
      11: ldc           #5                  // String Found empty contents
      13: invokespecial #6                  // Method java/lang/IllegalArgumentException."<init>":(Ljava/lang/String;)V
      16: athrow
      17: aload_2
      18: getstatic     #7                  // Field com/google/zxing/BarcodeFormat.DATA_MATRIX:Lcom/google/zxing/BarcodeFormat;
      21: if_acmpeq     51
      24: new           #4                  // class java/lang/IllegalArgumentException
      27: dup
      28: new           #8                  // class java/lang/StringBuilder
      31: dup
      32: invokespecial #9                  // Method java/lang/StringBuilder."<init>":()V
      35: ldc           #10                 // String Can only encode DATA_MATRIX, but got
      37: invokevirtual #11                 // Method java/lang/StringBuilder.append:(Ljava/lang/String;)Ljava/lang/StringBuilder;
      40: aload_2
      41: invokevirtual #12                 // Method java/lang/StringBuilder.append:(Ljava/lang/Object;)Ljava/lang/StringBuilder;
      44: invokevirtual #13                 // Method java/lang/StringBuilder.toString:()Ljava/lang/String;
      47: invokespecial #6                  // Method java/lang/IllegalArgumentException."<init>":(Ljava/lang/String;)V
      50: athrow
      51: iload_3
      52: iflt          60
      55: iload         4
      57: ifge          97
      60: new           #4                  // class java/lang/IllegalArgumentException
      63: dup
      64: new           #8                  // class java/lang/StringBuilder
      67: dup
      68: invokespecial #9                  // Method java/lang/StringBuilder."<init>":()V
      71: ldc           #14                 // String Requested dimensions can\'t be negative:
      73: invokevirtual #11                 // Method java/lang/StringBuilder.append:(Ljava/lang/String;)Ljava/lang/StringBuilder;
      76: iload_3
      77: invokevirtual #15                 // Method java/lang/StringBuilder.append:(I)Ljava/lang/StringBuilder;
      80: bipush        120
      82: invokevirtual #16                 // Method java/lang/StringBuilder.append:(C)Ljava/lang/StringBuilder;
      85: iload         4
      87: invokevirtual #15                 // Method java/lang/StringBuilder.append:(I)Ljava/lang/StringBuilder;
      90: invokevirtual #13                 // Method java/lang/StringBuilder.toString:()Ljava/lang/String;
      93: invokespecial #6                  // Method java/lang/IllegalArgumentException."<init>":(Ljava/lang/String;)V
      96: athrow
      97: getstatic     #17                 // Field com/google/zxing/datamatrix/encoder/SymbolShapeHint.FORCE_NONE:Lcom/google/zxing/datamatrix/encoder/SymbolShapeHint;
     100: astore        6
     102: aconst_null
     103: astore        7
     105: aconst_null
     106: astore        8
     108: aload         5
     110: ifnull        185
     113: aload         5
     115: getstatic     #18                 // Field com/google/zxing/EncodeHintType.DATA_MATRIX_SHAPE:Lcom/google/zxing/EncodeHintType;
     118: invokeinterface #19,  2           // InterfaceMethod java/util/Map.get:(Ljava/lang/Object;)Ljava/lang/Object;
     123: checkcast     #20                 // class com/google/zxing/datamatrix/encoder/SymbolShapeHint
     126: astore        9
     128: aload         9
     130: ifnull        137
     133: aload         9
     135: astore        6
     137: aload         5
     139: getstatic     #21                 // Field com/google/zxing/EncodeHintType.MIN_SIZE:Lcom/google/zxing/EncodeHintType;
     142: invokeinterface #19,  2           // InterfaceMethod java/util/Map.get:(Ljava/lang/Object;)Ljava/lang/Object;
     147: checkcast     #22                 // class com/google/zxing/Dimension
     150: astore        10
     152: aload         10
     154: ifnull        161
     157: aload         10
     159: astore        7
     161: aload         5
     163: getstatic     #23                 // Field com/google/zxing/EncodeHintType.MAX_SIZE:Lcom/google/zxing/EncodeHintType;
     166: invokeinterface #19,  2           // InterfaceMethod java/util/Map.get:(Ljava/lang/Object;)Ljava/lang/Object;
     171: checkcast     #22                 // class com/google/zxing/Dimension
     174: astore        11
     176: aload         11
     178: ifnull        185
     181: aload         11
     183: astore        8
     185: aload         5
     187: ifnull        226
     190: aload         5
     192: getstatic     #24                 // Field com/google/zxing/EncodeHintType.DATA_MATRIX_COMPACT:Lcom/google/zxing/EncodeHintType;
     195: invokeinterface #25,  2           // InterfaceMethod java/util/Map.containsKey:(Ljava/lang/Object;)Z
     200: ifeq          226
     203: aload         5
     205: getstatic     #24                 // Field com/google/zxing/EncodeHintType.DATA_MATRIX_COMPACT:Lcom/google/zxing/EncodeHintType;
     208: invokeinterface #19,  2           // InterfaceMethod java/util/Map.get:(Ljava/lang/Object;)Ljava/lang/Object;
     213: invokevirtual #26                 // Method java/lang/Object.toString:()Ljava/lang/String;
     216: invokestatic  #27                 // Method java/lang/Boolean.parseBoolean:(Ljava/lang/String;)Z
     219: ifeq          226
     222: iconst_1
     223: goto          227
     226: iconst_0
     227: istore        10
     229: iload         10
     231: ifeq          335
     234: aload         5
     236: getstatic     #28                 // Field com/google/zxing/EncodeHintType.GS1_FORMAT:Lcom/google/zxing/EncodeHintType;
     239: invokeinterface #25,  2           // InterfaceMethod java/util/Map.containsKey:(Ljava/lang/Object;)Z
     244: ifeq          270
     247: aload         5
     249: getstatic     #28                 // Field com/google/zxing/EncodeHintType.GS1_FORMAT:Lcom/google/zxing/EncodeHintType;
     252: invokeinterface #19,  2           // InterfaceMethod java/util/Map.get:(Ljava/lang/Object;)Ljava/lang/Object;
     257: invokevirtual #26                 // Method java/lang/Object.toString:()Ljava/lang/String;
     260: invokestatic  #27                 // Method java/lang/Boolean.parseBoolean:(Ljava/lang/String;)Z
     263: ifeq          270
     266: iconst_1
     267: goto          271
     270: iconst_0
     271: istore        11
     273: aconst_null
     274: astore        12
     276: aload         5
     278: getstatic     #29                 // Field com/google/zxing/EncodeHintType.CHARACTER_SET:Lcom/google/zxing/EncodeHintType;
     281: invokeinterface #25,  2           // InterfaceMethod java/util/Map.containsKey:(Ljava/lang/Object;)Z
     286: istore        13
     288: iload         13
     290: ifeq          311
     293: aload         5
     295: getstatic     #29                 // Field com/google/zxing/EncodeHintType.CHARACTER_SET:Lcom/google/zxing/EncodeHintType;
     298: invokeinterface #19,  2           // InterfaceMethod java/util/Map.get:(Ljava/lang/Object;)Ljava/lang/Object;
     303: invokevirtual #26                 // Method java/lang/Object.toString:()Ljava/lang/String;
     306: invokestatic  #30                 // Method java/nio/charset/Charset.forName:(Ljava/lang/String;)Ljava/nio/charset/Charset;
     309: astore        12
     311: aload_1
     312: aload         12
     314: iload         11
     316: ifeq          324
     319: bipush        29
     321: goto          325
     324: iconst_m1
     325: aload         6
     327: invokestatic  #31                 // Method com/google/zxing/datamatrix/encoder/MinimalEncoder.encodeHighLevel:(Ljava/lang/String;Ljava/nio/charset/Charset;ILcom/google/zxing/datamatrix/encoder/SymbolShapeHint;)Ljava/lang/String;
     330: astore        9
     332: goto          393
     335: aload         5
     337: ifnull        376
     340: aload         5
     342: getstatic     #32                 // Field com/google/zxing/EncodeHintType.FORCE_C40:Lcom/google/zxing/EncodeHintType;
     345: invokeinterface #25,  2           // InterfaceMethod java/util/Map.containsKey:(Ljava/lang/Object;)Z
     350: ifeq          376
     353: aload         5
     355: getstatic     #32                 // Field com/google/zxing/EncodeHintType.FORCE_C40:Lcom/google/zxing/EncodeHintType;
     358: invokeinterface #19,  2           // InterfaceMethod java/util/Map.get:(Ljava/lang/Object;)Ljava/lang/Object;
     363: invokevirtual #26                 // Method java/lang/Object.toString:()Ljava/lang/String;
     366: invokestatic  #27                 // Method java/lang/Boolean.parseBoolean:(Ljava/lang/String;)Z
     369: ifeq          376
     372: iconst_1
     373: goto          377
     376: iconst_0
     377: istore        11
     379: aload_1
     380: aload         6
     382: aload         7
     384: aload         8
     386: iload         11
     388: invokestatic  #33                 // Method com/google/zxing/datamatrix/encoder/HighLevelEncoder.encodeHighLevel:(Ljava/lang/String;Lcom/google/zxing/datamatrix/encoder/SymbolShapeHint;Lcom/google/zxing/Dimension;Lcom/google/zxing/Dimension;Z)Ljava/lang/String;
     391: astore        9
     393: aload         9
     395: invokevirtual #34                 // Method java/lang/String.length:()I
     398: aload         6
     400: aload         7
     402: aload         8
     404: iconst_1
     405: invokestatic  #35                 // Method com/google/zxing/datamatrix/encoder/SymbolInfo.lookup:(ILcom/google/zxing/datamatrix/encoder/SymbolShapeHint;Lcom/google/zxing/Dimension;Lcom/google/zxing/Dimension;Z)Lcom/google/zxing/datamatrix/encoder/SymbolInfo;
     408: astore        11
     410: aload         9
     412: aload         11
     414: invokestatic  #36                 // Method com/google/zxing/datamatrix/encoder/ErrorCorrection.encodeECC200:(Ljava/lang/String;Lcom/google/zxing/datamatrix/encoder/SymbolInfo;)Ljava/lang/String;
     417: astore        12
     419: new           #37                 // class com/google/zxing/datamatrix/encoder/DefaultPlacement
     422: dup
     423: aload         12
     425: aload         11
     427: invokevirtual #38                 // Method com/google/zxing/datamatrix/encoder/SymbolInfo.getSymbolDataWidth:()I
     430: aload         11
     432: invokevirtual #39                 // Method com/google/zxing/datamatrix/encoder/SymbolInfo.getSymbolDataHeight:()I
     435: invokespecial #40                 // Method com/google/zxing/datamatrix/encoder/DefaultPlacement."<init>":(Ljava/lang/CharSequence;II)V
     438: astore        13
     440: aload         13
     442: invokevirtual #41                 // Method com/google/zxing/datamatrix/encoder/DefaultPlacement.place:()V
     445: aload         13
     447: aload         11
     449: iload_3
     450: iload         4
     452: invokestatic  #42                 // Method encodeLowLevel:(Lcom/google/zxing/datamatrix/encoder/DefaultPlacement;Lcom/google/zxing/datamatrix/encoder/SymbolInfo;II)Lcom/google/zxing/common/BitMatrix;
     455: areturn

  private static com.google.zxing.common.BitMatrix encodeLowLevel(com.google.zxing.datamatrix.encoder.DefaultPlacement, com.google.zxing.datamatrix.encoder.SymbolInfo, int, int);
    Code:
       0: aload_1
       1: invokevirtual #38                 // Method com/google/zxing/datamatrix/encoder/SymbolInfo.getSymbolDataWidth:()I
       4: istore        4
       6: aload_1
       7: invokevirtual #39                 // Method com/google/zxing/datamatrix/encoder/SymbolInfo.getSymbolDataHeight:()I
      10: istore        5
      12: new           #43                 // class com/google/zxing/qrcode/encoder/ByteMatrix
      15: dup
      16: aload_1
      17: invokevirtual #44                 // Method com/google/zxing/datamatrix/encoder/SymbolInfo.getSymbolWidth:()I
      20: aload_1
      21: invokevirtual #45                 // Method com/google/zxing/datamatrix/encoder/SymbolInfo.getSymbolHeight:()I
      24: invokespecial #46                 // Method com/google/zxing/qrcode/encoder/ByteMatrix."<init>":(II)V
      27: astore        6
      29: iconst_0
      30: istore        7
      32: iconst_0
      33: istore        8
      35: iload         8
      37: iload         5
      39: if_icmpge     264
      42: iload         8
      44: aload_1
      45: getfield      #47                 // Field com/google/zxing/datamatrix/encoder/SymbolInfo.matrixHeight:I
      48: irem
      49: ifne          100
      52: iconst_0
      53: istore        9
      55: iconst_0
      56: istore        10
      58: iload         10
      60: aload_1
      61: invokevirtual #44                 // Method com/google/zxing/datamatrix/encoder/SymbolInfo.getSymbolWidth:()I
      64: if_icmpge     97
      67: aload         6
      69: iload         9
      71: iload         7
      73: iload         10
      75: iconst_2
      76: irem
      77: ifne          84
      80: iconst_1
      81: goto          85
      84: iconst_0
      85: invokevirtual #48                 // Method com/google/zxing/qrcode/encoder/ByteMatrix.set:(IIZ)V
      88: iinc          9, 1
      91: iinc          10, 1
      94: goto          58
      97: iinc          7, 1
     100: iconst_0
     101: istore        9
     103: iconst_0
     104: istore        10
     106: iload         10
     108: iload         4
     110: if_icmpge     202
     113: iload         10
     115: aload_1
     116: getfield      #49                 // Field com/google/zxing/datamatrix/encoder/SymbolInfo.matrixWidth:I
     119: irem
     120: ifne          136
     123: aload         6
     125: iload         9
     127: iload         7
     129: iconst_1
     130: invokevirtual #48                 // Method com/google/zxing/qrcode/encoder/ByteMatrix.set:(IIZ)V
     133: iinc          9, 1
     136: aload         6
     138: iload         9
     140: iload         7
     142: aload_0
     143: iload         10
     145: iload         8
     147: invokevirtual #50                 // Method com/google/zxing/datamatrix/encoder/DefaultPlacement.getBit:(II)Z
     150: invokevirtual #48                 // Method com/google/zxing/qrcode/encoder/ByteMatrix.set:(IIZ)V
     153: iinc          9, 1
     156: iload         10
     158: aload_1
     159: getfield      #49                 // Field com/google/zxing/datamatrix/encoder/SymbolInfo.matrixWidth:I
     162: irem
     163: aload_1
     164: getfield      #49                 // Field com/google/zxing/datamatrix/encoder/SymbolInfo.matrixWidth:I
     167: iconst_1
     168: isub
     169: if_icmpne     196
     172: aload         6
     174: iload         9
     176: iload         7
     178: iload         8
     180: iconst_2
     181: irem
     182: ifne          189
     185: iconst_1
     186: goto          190
     189: iconst_0
     190: invokevirtual #48                 // Method com/google/zxing/qrcode/encoder/ByteMatrix.set:(IIZ)V
     193: iinc          9, 1
     196: iinc          10, 1
     199: goto          106
     202: iinc          7, 1
     205: iload         8
     207: aload_1
     208: getfield      #47                 // Field com/google/zxing/datamatrix/encoder/SymbolInfo.matrixHeight:I
     211: irem
     212: aload_1
     213: getfield      #47                 // Field com/google/zxing/datamatrix/encoder/SymbolInfo.matrixHeight:I
     216: iconst_1
     217: isub
     218: if_icmpne     258
     221: iconst_0
     222: istore        9
     224: iconst_0
     225: istore        10
     227: iload         10
     229: aload_1
     230: invokevirtual #44                 // Method com/google/zxing/datamatrix/encoder/SymbolInfo.getSymbolWidth:()I
     233: if_icmpge     255
     236: aload         6
     238: iload         9
     240: iload         7
     242: iconst_1
     243: invokevirtual #48                 // Method com/google/zxing/qrcode/encoder/ByteMatrix.set:(IIZ)V
     246: iinc          9, 1
     249: iinc          10, 1
     252: goto          227
     255: iinc          7, 1
     258: iinc          8, 1
     261: goto          35
     264: aload         6
     266: iload_2
     267: iload_3
     268: invokestatic  #51                 // Method convertByteMatrixToBitMatrix:(Lcom/google/zxing/qrcode/encoder/ByteMatrix;II)Lcom/google/zxing/common/BitMatrix;
     271: areturn

  private static com.google.zxing.common.BitMatrix convertByteMatrixToBitMatrix(com.google.zxing.qrcode.encoder.ByteMatrix, int, int);
    Code:
       0: aload_0
       1: invokevirtual #52                 // Method com/google/zxing/qrcode/encoder/ByteMatrix.getWidth:()I
       4: istore_3
       5: aload_0
       6: invokevirtual #53                 // Method com/google/zxing/qrcode/encoder/ByteMatrix.getHeight:()I
       9: istore        4
      11: iload_1
      12: iload_3
      13: invokestatic  #54                 // Method java/lang/Math.max:(II)I
      16: istore        5
      18: iload_2
      19: iload         4
      21: invokestatic  #54                 // Method java/lang/Math.max:(II)I
      24: istore        6
      26: iload         5
      28: iload_3
      29: idiv
      30: iload         6
      32: iload         4
      34: idiv
      35: invokestatic  #55                 // Method java/lang/Math.min:(II)I
      38: istore        7
      40: iload         5
      42: iload_3
      43: iload         7
      45: imul
      46: isub
      47: iconst_2
      48: idiv
      49: istore        8
      51: iload         6
      53: iload         4
      55: iload         7
      57: imul
      58: isub
      59: iconst_2
      60: idiv
      61: istore        9
      63: iload_2
      64: iload         4
      66: if_icmplt     74
      69: iload_1
      70: iload_3
      71: if_icmpge     95
      74: iconst_0
      75: istore        8
      77: iconst_0
      78: istore        9
      80: new           #56                 // class com/google/zxing/common/BitMatrix
      83: dup
      84: iload_3
      85: iload         4
      87: invokespecial #57                 // Method com/google/zxing/common/BitMatrix."<init>":(II)V
      90: astore        10
      92: goto          106
      95: new           #56                 // class com/google/zxing/common/BitMatrix
      98: dup
      99: iload_1
     100: iload_2
     101: invokespecial #57                 // Method com/google/zxing/common/BitMatrix."<init>":(II)V
     104: astore        10
     106: aload         10
     108: invokevirtual #58                 // Method com/google/zxing/common/BitMatrix.clear:()V
     111: iconst_0
     112: istore        11
     114: iload         9
     116: istore        12
     118: iload         11
     120: iload         4
     122: if_icmpge     189
     125: iconst_0
     126: istore        13
     128: iload         8
     130: istore        14
     132: iload         13
     134: iload_3
     135: if_icmpge     176
     138: aload_0
     139: iload         13
     141: iload         11
     143: invokevirtual #59                 // Method com/google/zxing/qrcode/encoder/ByteMatrix.get:(II)B
     146: iconst_1
     147: if_icmpne     163
     150: aload         10
     152: iload         14
     154: iload         12
     156: iload         7
     158: iload         7
     160: invokevirtual #60                 // Method com/google/zxing/common/BitMatrix.setRegion:(IIII)V
     163: iinc          13, 1
     166: iload         14
     168: iload         7
     170: iadd
     171: istore        14
     173: goto          132
     176: iinc          11, 1
     179: iload         12
     181: iload         7
     183: iadd
     184: istore        12
     186: goto          118
     189: aload         10
     191: areturn
}
