Compiled from "StatItem.java"
class org.apache.dubbo.rpc.filter.tps.StatItem {
  private final java.lang.String name;

  private final java.util.concurrent.atomic.AtomicLong lastResetTime;

  private final long interval;

  private final java.util.concurrent.atomic.AtomicInteger token;

  private final int rate;

  org.apache.dubbo.rpc.filter.tps.StatItem(java.lang.String, int, long);
    Code:
       0: aload_0
       1: invokespecial #1                  // Method java/lang/Object."<init>":()V
       4: aload_0
       5: aload_1
       6: putfield      #2                  // Field name:Ljava/lang/String;
       9: aload_0
      10: iload_2
      11: putfield      #3                  // Field rate:I
      14: aload_0
      15: lload_3
      16: putfield      #4                  // Field interval:J
      19: aload_0
      20: new           #5                  // class java/util/concurrent/atomic/AtomicLong
      23: dup
      24: invokestatic  #6                  // Method java/lang/System.currentTimeMillis:()J
      27: invokespecial #7                  // Method java/util/concurrent/atomic/AtomicLong."<init>":(J)V
      30: putfield      #8                  // Field lastResetTime:Ljava/util/concurrent/atomic/AtomicLong;
      33: aload_0
      34: new           #9                  // class java/util/concurrent/atomic/AtomicInteger
      37: dup
      38: iload_2
      39: invokespecial #10                 // Method java/util/concurrent/atomic/AtomicInteger."<init>":(I)V
      42: putfield      #11                 // Field token:Ljava/util/concurrent/atomic/AtomicInteger;
      45: return

  public boolean isAllowable();
    Code:
       0: invokestatic  #6                  // Method java/lang/System.currentTimeMillis:()J
       3: lstore_1
       4: lload_1
       5: aload_0
       6: getfield      #8                  // Field lastResetTime:Ljava/util/concurrent/atomic/AtomicLong;
       9: invokevirtual #12                 // Method java/util/concurrent/atomic/AtomicLong.get:()J
      12: aload_0
      13: getfield      #4                  // Field interval:J
      16: ladd
      17: lcmp
      18: ifle          40
      21: aload_0
      22: getfield      #11                 // Field token:Ljava/util/concurrent/atomic/AtomicInteger;
      25: aload_0
      26: getfield      #3                  // Field rate:I
      29: invokevirtual #13                 // Method java/util/concurrent/atomic/AtomicInteger.set:(I)V
      32: aload_0
      33: getfield      #8                  // Field lastResetTime:Ljava/util/concurrent/atomic/AtomicLong;
      36: lload_1
      37: invokevirtual #14                 // Method java/util/concurrent/atomic/AtomicLong.set:(J)V
      40: aload_0
      41: getfield      #11                 // Field token:Ljava/util/concurrent/atomic/AtomicInteger;
      44: invokevirtual #15                 // Method java/util/concurrent/atomic/AtomicInteger.decrementAndGet:()I
      47: iflt          54
      50: iconst_1
      51: goto          55
      54: iconst_0
      55: ireturn

  public long getInterval();
    Code:
       0: aload_0
       1: getfield      #4                  // Field interval:J
       4: lreturn

  public int getRate();
    Code:
       0: aload_0
       1: getfield      #3                  // Field rate:I
       4: ireturn

  long getLastResetTime();
    Code:
       0: aload_0
       1: getfield      #8                  // Field lastResetTime:Ljava/util/concurrent/atomic/AtomicLong;
       4: invokevirtual #12                 // Method java/util/concurrent/atomic/AtomicLong.get:()J
       7: lreturn

  int getToken();
    Code:
       0: aload_0
       1: getfield      #11                 // Field token:Ljava/util/concurrent/atomic/AtomicInteger;
       4: invokevirtual #16                 // Method java/util/concurrent/atomic/AtomicInteger.get:()I
       7: ireturn

  public java.lang.String toString();
    Code:
       0: new           #17                 // class java/lang/StringBuilder
       3: dup
       4: invokespecial #18                 // Method java/lang/StringBuilder."<init>":()V
       7: ldc           #19                 // String StatItem [name=
       9: invokevirtual #20                 // Method java/lang/StringBuilder.append:(Ljava/lang/String;)Ljava/lang/StringBuilder;
      12: aload_0
      13: getfield      #2                  // Field name:Ljava/lang/String;
      16: invokevirtual #20                 // Method java/lang/StringBuilder.append:(Ljava/lang/String;)Ljava/lang/StringBuilder;
      19: ldc           #21                 // String , rate =
      21: invokevirtual #20                 // Method java/lang/StringBuilder.append:(Ljava/lang/String;)Ljava/lang/StringBuilder;
      24: aload_0
      25: getfield      #3                  // Field rate:I
      28: invokevirtual #22                 // Method java/lang/StringBuilder.append:(I)Ljava/lang/StringBuilder;
      31: ldc           #23                 // String , interval =
      33: invokevirtual #20                 // Method java/lang/StringBuilder.append:(Ljava/lang/String;)Ljava/lang/StringBuilder;
      36: aload_0
      37: getfield      #4                  // Field interval:J
      40: invokevirtual #24                 // Method java/lang/StringBuilder.append:(J)Ljava/lang/StringBuilder;
      43: bipush        93
      45: invokevirtual #25                 // Method java/lang/StringBuilder.append:(C)Ljava/lang/StringBuilder;
      48: invokevirtual #26                 // Method java/lang/StringBuilder.toString:()Ljava/lang/String;
      51: areturn
}
