Compiled from "ApplicationMetric.java"
public class org.apache.dubbo.metrics.model.ApplicationMetric implements org.apache.dubbo.metrics.model.Metric {
  private final org.apache.dubbo.rpc.model.ApplicationModel applicationModel;

  private static final java.lang.String version;

  private static final java.lang.String commitId;

  public org.apache.dubbo.metrics.model.ApplicationMetric(org.apache.dubbo.rpc.model.ApplicationModel);
    Code:
       0: aload_0
       1: invokespecial #2                  // Method java/lang/Object."<init>":()V
       4: aload_0
       5: aload_1
       6: putfield      #3                  // Field applicationModel:Lorg/apache/dubbo/rpc/model/ApplicationModel;
       9: return

  public org.apache.dubbo.rpc.model.ApplicationModel getApplicationModel();
    Code:
       0: aload_0
       1: getfield      #3                  // Field applicationModel:Lorg/apache/dubbo/rpc/model/ApplicationModel;
       4: areturn

  public java.lang.String getApplicationName();
    Code:
       0: aload_0
       1: invokevirtual #4                  // Method getApplicationModel:()Lorg/apache/dubbo/rpc/model/ApplicationModel;
       4: invokevirtual #5                  // Method org/apache/dubbo/rpc/model/ApplicationModel.getApplicationName:()Ljava/lang/String;
       7: areturn

  public java.lang.String getData();
    Code:
       0: getstatic     #6                  // Field version:Ljava/lang/String;
       3: areturn

  public java.util.Map<java.lang.String, java.lang.String> getTags();
    Code:
       0: new           #7                  // class java/util/HashMap
       3: dup
       4: invokespecial #8                  // Method java/util/HashMap."<init>":()V
       7: astore_1
       8: aload_1
       9: ldc           #9                  // String ip
      11: invokestatic  #10                 // Method org/apache/dubbo/common/utils/NetUtils.getLocalHost:()Ljava/lang/String;
      14: invokeinterface #11,  3           // InterfaceMethod java/util/Map.put:(Ljava/lang/Object;Ljava/lang/Object;)Ljava/lang/Object;
      19: pop
      20: aload_1
      21: ldc           #12                 // String hostname
      23: invokestatic  #13                 // Method org/apache/dubbo/common/utils/NetUtils.getLocalHostName:()Ljava/lang/String;
      26: invokeinterface #11,  3           // InterfaceMethod java/util/Map.put:(Ljava/lang/Object;Ljava/lang/Object;)Ljava/lang/Object;
      31: pop
      32: aload_1
      33: ldc           #14                 // String application.name
      35: aload_0
      36: invokevirtual #15                 // Method getApplicationName:()Ljava/lang/String;
      39: invokeinterface #11,  3           // InterfaceMethod java/util/Map.put:(Ljava/lang/Object;Ljava/lang/Object;)Ljava/lang/Object;
      44: pop
      45: aload_1
      46: ldc           #16                 // String application.version
      48: getstatic     #6                  // Field version:Ljava/lang/String;
      51: invokeinterface #11,  3           // InterfaceMethod java/util/Map.put:(Ljava/lang/Object;Ljava/lang/Object;)Ljava/lang/Object;
      56: pop
      57: aload_1
      58: getstatic     #17                 // Field org/apache/dubbo/metrics/model/key/MetricsKey.METADATA_GIT_COMMITID_METRIC:Lorg/apache/dubbo/metrics/model/key/MetricsKey;
      61: invokevirtual #18                 // Method org/apache/dubbo/metrics/model/key/MetricsKey.getName:()Ljava/lang/String;
      64: getstatic     #19                 // Field commitId:Ljava/lang/String;
      67: invokeinterface #11,  3           // InterfaceMethod java/util/Map.put:(Ljava/lang/Object;Ljava/lang/Object;)Ljava/lang/Object;
      72: pop
      73: aload_1
      74: areturn

  static {};
    Code:
       0: invokestatic  #20                 // Method org/apache/dubbo/common/Version.getVersion:()Ljava/lang/String;
       3: putstatic     #6                  // Field version:Ljava/lang/String;
       6: invokestatic  #21                 // Method org/apache/dubbo/common/Version.getLastCommitId:()Ljava/lang/String;
       9: putstatic     #19                 // Field commitId:Ljava/lang/String;
      12: return
}
