Compiled from "MethodMetric.java"
public class org.apache.dubbo.metrics.model.MethodMetric extends org.apache.dubbo.metrics.model.ServiceKeyMetric {
  private java.lang.String side;

  private final java.lang.String methodName;

  private java.lang.String group;

  private java.lang.String version;

  private final org.apache.dubbo.metrics.model.sample.MetricSample$Type sampleType;

  public org.apache.dubbo.metrics.model.MethodMetric(org.apache.dubbo.rpc.model.ApplicationModel, org.apache.dubbo.rpc.Invocation);
    Code:
       0: aload_0
       1: aload_1
       2: aload_2
       3: invokestatic  #3                  // Method org/apache/dubbo/metrics/model/MetricsSupport.getInterfaceName:(Lorg/apache/dubbo/rpc/Invocation;)Ljava/lang/String;
       6: invokespecial #4                  // Method org/apache/dubbo/metrics/model/ServiceKeyMetric."<init>":(Lorg/apache/dubbo/rpc/model/ApplicationModel;Ljava/lang/String;)V
       9: aload_0
      10: aload_2
      11: invokestatic  #5                  // Method org/apache/dubbo/metrics/model/MetricsSupport.getMethodName:(Lorg/apache/dubbo/rpc/Invocation;)Ljava/lang/String;
      14: putfield      #6                  // Field methodName:Ljava/lang/String;
      17: aload_0
      18: aload_2
      19: invokestatic  #7                  // Method org/apache/dubbo/metrics/model/MetricsSupport.getSide:(Lorg/apache/dubbo/rpc/Invocation;)Ljava/lang/String;
      22: putfield      #8                  // Field side:Ljava/lang/String;
      25: aload_0
      26: aload_2
      27: invokestatic  #9                  // Method org/apache/dubbo/metrics/model/MetricsSupport.getGroup:(Lorg/apache/dubbo/rpc/Invocation;)Ljava/lang/String;
      30: putfield      #10                 // Field group:Ljava/lang/String;
      33: aload_0
      34: aload_2
      35: invokestatic  #11                 // Method org/apache/dubbo/metrics/model/MetricsSupport.getVersion:(Lorg/apache/dubbo/rpc/Invocation;)Ljava/lang/String;
      38: putfield      #12                 // Field version:Ljava/lang/String;
      41: aload_0
      42: aload_2
      43: ldc           #13                 // String metric_filter_invocation_counter
      45: invokeinterface #14,  2           // InterfaceMethod org/apache/dubbo/rpc/Invocation.get:(Ljava/lang/Object;)Ljava/lang/Object;
      50: checkcast     #15                 // class org/apache/dubbo/metrics/model/sample/MetricSample$Type
      53: putfield      #16                 // Field sampleType:Lorg/apache/dubbo/metrics/model/sample/MetricSample$Type;
      56: return

  public org.apache.dubbo.metrics.model.sample.MetricSample$Type getSampleType();
    Code:
       0: aload_0
       1: getfield      #16                 // Field sampleType:Lorg/apache/dubbo/metrics/model/sample/MetricSample$Type;
       4: areturn

  public java.lang.String getGroup();
    Code:
       0: aload_0
       1: getfield      #10                 // Field group:Ljava/lang/String;
       4: areturn

  public void setGroup(java.lang.String);
    Code:
       0: aload_0
       1: aload_1
       2: putfield      #10                 // Field group:Ljava/lang/String;
       5: return

  public java.lang.String getVersion();
    Code:
       0: aload_0
       1: getfield      #12                 // Field version:Ljava/lang/String;
       4: areturn

  public void setVersion(java.lang.String);
    Code:
       0: aload_0
       1: aload_1
       2: putfield      #12                 // Field version:Ljava/lang/String;
       5: return

  public java.util.Map<java.lang.String, java.lang.String> getTags();
    Code:
       0: aload_0
       1: invokevirtual #17                 // Method getApplicationModel:()Lorg/apache/dubbo/rpc/model/ApplicationModel;
       4: aload_0
       5: invokevirtual #18                 // Method getInterfaceName:()Ljava/lang/String;
       8: aload_0
       9: getfield      #6                  // Field methodName:Ljava/lang/String;
      12: invokestatic  #19                 // Method org/apache/dubbo/metrics/model/MetricsSupport.methodTags:(Lorg/apache/dubbo/rpc/model/ApplicationModel;Ljava/lang/String;Ljava/lang/String;)Ljava/util/Map;
      15: astore_1
      16: aload_1
      17: ldc           #20                 // String group
      19: aload_0
      20: getfield      #10                 // Field group:Ljava/lang/String;
      23: invokeinterface #21,  3           // InterfaceMethod java/util/Map.put:(Ljava/lang/Object;Ljava/lang/Object;)Ljava/lang/Object;
      28: pop
      29: aload_1
      30: ldc           #22                 // String version
      32: aload_0
      33: getfield      #12                 // Field version:Ljava/lang/String;
      36: invokeinterface #21,  3           // InterfaceMethod java/util/Map.put:(Ljava/lang/Object;Ljava/lang/Object;)Ljava/lang/Object;
      41: pop
      42: aload_1
      43: areturn

  public java.lang.String getMethodName();
    Code:
       0: aload_0
       1: getfield      #6                  // Field methodName:Ljava/lang/String;
       4: areturn

  public java.lang.String getSide();
    Code:
       0: aload_0
       1: getfield      #8                  // Field side:Ljava/lang/String;
       4: areturn

  public void setSide(java.lang.String);
    Code:
       0: aload_0
       1: aload_1
       2: putfield      #8                  // Field side:Ljava/lang/String;
       5: return

  public java.lang.String toString();
    Code:
       0: new           #23                 // class java/lang/StringBuilder
       3: dup
       4: invokespecial #24                 // Method java/lang/StringBuilder."<init>":()V
       7: ldc           #25                 // String MethodMetric{applicationName=\'
       9: invokevirtual #26                 // Method java/lang/StringBuilder.append:(Ljava/lang/String;)Ljava/lang/StringBuilder;
      12: aload_0
      13: invokevirtual #27                 // Method getApplicationName:()Ljava/lang/String;
      16: invokevirtual #26                 // Method java/lang/StringBuilder.append:(Ljava/lang/String;)Ljava/lang/StringBuilder;
      19: bipush        39
      21: invokevirtual #28                 // Method java/lang/StringBuilder.append:(C)Ljava/lang/StringBuilder;
      24: ldc           #29                 // String , side=\'
      26: invokevirtual #26                 // Method java/lang/StringBuilder.append:(Ljava/lang/String;)Ljava/lang/StringBuilder;
      29: aload_0
      30: getfield      #8                  // Field side:Ljava/lang/String;
      33: invokevirtual #26                 // Method java/lang/StringBuilder.append:(Ljava/lang/String;)Ljava/lang/StringBuilder;
      36: bipush        39
      38: invokevirtual #28                 // Method java/lang/StringBuilder.append:(C)Ljava/lang/StringBuilder;
      41: ldc           #30                 // String , interfaceName=\'
      43: invokevirtual #26                 // Method java/lang/StringBuilder.append:(Ljava/lang/String;)Ljava/lang/StringBuilder;
      46: aload_0
      47: invokevirtual #18                 // Method getInterfaceName:()Ljava/lang/String;
      50: invokevirtual #26                 // Method java/lang/StringBuilder.append:(Ljava/lang/String;)Ljava/lang/StringBuilder;
      53: bipush        39
      55: invokevirtual #28                 // Method java/lang/StringBuilder.append:(C)Ljava/lang/StringBuilder;
      58: ldc           #31                 // String , methodName=\'
      60: invokevirtual #26                 // Method java/lang/StringBuilder.append:(Ljava/lang/String;)Ljava/lang/StringBuilder;
      63: aload_0
      64: getfield      #6                  // Field methodName:Ljava/lang/String;
      67: invokevirtual #26                 // Method java/lang/StringBuilder.append:(Ljava/lang/String;)Ljava/lang/StringBuilder;
      70: bipush        39
      72: invokevirtual #28                 // Method java/lang/StringBuilder.append:(C)Ljava/lang/StringBuilder;
      75: ldc           #32                 // String , group=\'
      77: invokevirtual #26                 // Method java/lang/StringBuilder.append:(Ljava/lang/String;)Ljava/lang/StringBuilder;
      80: aload_0
      81: getfield      #10                 // Field group:Ljava/lang/String;
      84: invokevirtual #26                 // Method java/lang/StringBuilder.append:(Ljava/lang/String;)Ljava/lang/StringBuilder;
      87: bipush        39
      89: invokevirtual #28                 // Method java/lang/StringBuilder.append:(C)Ljava/lang/StringBuilder;
      92: ldc           #33                 // String , version=\'
      94: invokevirtual #26                 // Method java/lang/StringBuilder.append:(Ljava/lang/String;)Ljava/lang/StringBuilder;
      97: aload_0
      98: getfield      #12                 // Field version:Ljava/lang/String;
     101: invokevirtual #26                 // Method java/lang/StringBuilder.append:(Ljava/lang/String;)Ljava/lang/StringBuilder;
     104: bipush        39
     106: invokevirtual #28                 // Method java/lang/StringBuilder.append:(C)Ljava/lang/StringBuilder;
     109: bipush        125
     111: invokevirtual #28                 // Method java/lang/StringBuilder.append:(C)Ljava/lang/StringBuilder;
     114: invokevirtual #34                 // Method java/lang/StringBuilder.toString:()Ljava/lang/String;
     117: areturn

  public boolean equals(java.lang.Object);
    Code:
       0: aload_0
       1: aload_1
       2: if_acmpne     7
       5: iconst_1
       6: ireturn
       7: aload_1
       8: ifnull        22
      11: aload_0
      12: invokevirtual #35                 // Method java/lang/Object.getClass:()Ljava/lang/Class;
      15: aload_1
      16: invokevirtual #35                 // Method java/lang/Object.getClass:()Ljava/lang/Class;
      19: if_acmpeq     24
      22: iconst_0
      23: ireturn
      24: aload_1
      25: checkcast     #36                 // class org/apache/dubbo/metrics/model/MethodMetric
      28: astore_2
      29: aload_0
      30: invokevirtual #27                 // Method getApplicationName:()Ljava/lang/String;
      33: aload_2
      34: invokevirtual #27                 // Method getApplicationName:()Ljava/lang/String;
      37: invokestatic  #37                 // Method java/util/Objects.equals:(Ljava/lang/Object;Ljava/lang/Object;)Z
      40: ifeq          117
      43: aload_0
      44: getfield      #8                  // Field side:Ljava/lang/String;
      47: aload_2
      48: getfield      #8                  // Field side:Ljava/lang/String;
      51: invokestatic  #37                 // Method java/util/Objects.equals:(Ljava/lang/Object;Ljava/lang/Object;)Z
      54: ifeq          117
      57: aload_0
      58: invokevirtual #18                 // Method getInterfaceName:()Ljava/lang/String;
      61: aload_2
      62: invokevirtual #18                 // Method getInterfaceName:()Ljava/lang/String;
      65: invokestatic  #37                 // Method java/util/Objects.equals:(Ljava/lang/Object;Ljava/lang/Object;)Z
      68: ifeq          117
      71: aload_0
      72: getfield      #6                  // Field methodName:Ljava/lang/String;
      75: aload_2
      76: getfield      #6                  // Field methodName:Ljava/lang/String;
      79: invokestatic  #37                 // Method java/util/Objects.equals:(Ljava/lang/Object;Ljava/lang/Object;)Z
      82: ifeq          117
      85: aload_0
      86: getfield      #10                 // Field group:Ljava/lang/String;
      89: aload_2
      90: getfield      #10                 // Field group:Ljava/lang/String;
      93: invokestatic  #37                 // Method java/util/Objects.equals:(Ljava/lang/Object;Ljava/lang/Object;)Z
      96: ifeq          117
      99: aload_0
     100: getfield      #12                 // Field version:Ljava/lang/String;
     103: aload_2
     104: getfield      #12                 // Field version:Ljava/lang/String;
     107: invokestatic  #37                 // Method java/util/Objects.equals:(Ljava/lang/Object;Ljava/lang/Object;)Z
     110: ifeq          117
     113: iconst_1
     114: goto          118
     117: iconst_0
     118: ireturn

  public int hashCode();
    Code:
       0: bipush        6
       2: anewarray     #38                 // class java/lang/Object
       5: dup
       6: iconst_0
       7: aload_0
       8: invokevirtual #27                 // Method getApplicationName:()Ljava/lang/String;
      11: aastore
      12: dup
      13: iconst_1
      14: aload_0
      15: getfield      #8                  // Field side:Ljava/lang/String;
      18: aastore
      19: dup
      20: iconst_2
      21: aload_0
      22: invokevirtual #18                 // Method getInterfaceName:()Ljava/lang/String;
      25: aastore
      26: dup
      27: iconst_3
      28: aload_0
      29: getfield      #6                  // Field methodName:Ljava/lang/String;
      32: aastore
      33: dup
      34: iconst_4
      35: aload_0
      36: getfield      #10                 // Field group:Ljava/lang/String;
      39: aastore
      40: dup
      41: iconst_5
      42: aload_0
      43: getfield      #12                 // Field version:Ljava/lang/String;
      46: aastore
      47: invokestatic  #39                 // Method java/util/Objects.hash:([Ljava/lang/Object;)I
      50: ireturn
}
