Compiled from "MetricsCategory.java"
public final class org.apache.dubbo.metrics.model.MetricsCategory extends java.lang.Enum<org.apache.dubbo.metrics.model.MetricsCategory> {
  public static final org.apache.dubbo.metrics.model.MetricsCategory RT;

  public static final org.apache.dubbo.metrics.model.MetricsCategory QPS;

  public static final org.apache.dubbo.metrics.model.MetricsCategory REQUESTS;

  public static final org.apache.dubbo.metrics.model.MetricsCategory APPLICATION;

  public static final org.apache.dubbo.metrics.model.MetricsCategory CONFIGCENTER;

  public static final org.apache.dubbo.metrics.model.MetricsCategory REGISTRY;

  public static final org.apache.dubbo.metrics.model.MetricsCategory METADATA;

  public static final org.apache.dubbo.metrics.model.MetricsCategory THREAD_POOL;

  private static final org.apache.dubbo.metrics.model.MetricsCategory[] $VALUES;

  public static org.apache.dubbo.metrics.model.MetricsCategory[] values();
    Code:
       0: getstatic     #1                  // Field $VALUES:[Lorg/apache/dubbo/metrics/model/MetricsCategory;
       3: invokevirtual #2                  // Method "[Lorg/apache/dubbo/metrics/model/MetricsCategory;".clone:()Ljava/lang/Object;
       6: checkcast     #3                  // class "[Lorg/apache/dubbo/metrics/model/MetricsCategory;"
       9: areturn

  public static org.apache.dubbo.metrics.model.MetricsCategory valueOf(java.lang.String);
    Code:
       0: ldc           #4                  // class org/apache/dubbo/metrics/model/MetricsCategory
       2: aload_0
       3: invokestatic  #5                  // Method java/lang/Enum.valueOf:(Ljava/lang/Class;Ljava/lang/String;)Ljava/lang/Enum;
       6: checkcast     #4                  // class org/apache/dubbo/metrics/model/MetricsCategory
       9: areturn

  private org.apache.dubbo.metrics.model.MetricsCategory();
    Code:
       0: aload_0
       1: aload_1
       2: iload_2
       3: invokespecial #6                  // Method java/lang/Enum."<init>":(Ljava/lang/String;I)V
       6: return

  static {};
    Code:
       0: new           #4                  // class org/apache/dubbo/metrics/model/MetricsCategory
       3: dup
       4: ldc           #7                  // String RT
       6: iconst_0
       7: invokespecial #8                  // Method "<init>":(Ljava/lang/String;I)V
      10: putstatic     #9                  // Field RT:Lorg/apache/dubbo/metrics/model/MetricsCategory;
      13: new           #4                  // class org/apache/dubbo/metrics/model/MetricsCategory
      16: dup
      17: ldc           #10                 // String QPS
      19: iconst_1
      20: invokespecial #8                  // Method "<init>":(Ljava/lang/String;I)V
      23: putstatic     #11                 // Field QPS:Lorg/apache/dubbo/metrics/model/MetricsCategory;
      26: new           #4                  // class org/apache/dubbo/metrics/model/MetricsCategory
      29: dup
      30: ldc           #12                 // String REQUESTS
      32: iconst_2
      33: invokespecial #8                  // Method "<init>":(Ljava/lang/String;I)V
      36: putstatic     #13                 // Field REQUESTS:Lorg/apache/dubbo/metrics/model/MetricsCategory;
      39: new           #4                  // class org/apache/dubbo/metrics/model/MetricsCategory
      42: dup
      43: ldc           #14                 // String APPLICATION
      45: iconst_3
      46: invokespecial #8                  // Method "<init>":(Ljava/lang/String;I)V
      49: putstatic     #15                 // Field APPLICATION:Lorg/apache/dubbo/metrics/model/MetricsCategory;
      52: new           #4                  // class org/apache/dubbo/metrics/model/MetricsCategory
      55: dup
      56: ldc           #16                 // String CONFIGCENTER
      58: iconst_4
      59: invokespecial #8                  // Method "<init>":(Ljava/lang/String;I)V
      62: putstatic     #17                 // Field CONFIGCENTER:Lorg/apache/dubbo/metrics/model/MetricsCategory;
      65: new           #4                  // class org/apache/dubbo/metrics/model/MetricsCategory
      68: dup
      69: ldc           #18                 // String REGISTRY
      71: iconst_5
      72: invokespecial #8                  // Method "<init>":(Ljava/lang/String;I)V
      75: putstatic     #19                 // Field REGISTRY:Lorg/apache/dubbo/metrics/model/MetricsCategory;
      78: new           #4                  // class org/apache/dubbo/metrics/model/MetricsCategory
      81: dup
      82: ldc           #20                 // String METADATA
      84: bipush        6
      86: invokespecial #8                  // Method "<init>":(Ljava/lang/String;I)V
      89: putstatic     #21                 // Field METADATA:Lorg/apache/dubbo/metrics/model/MetricsCategory;
      92: new           #4                  // class org/apache/dubbo/metrics/model/MetricsCategory
      95: dup
      96: ldc           #22                 // String THREAD_POOL
      98: bipush        7
     100: invokespecial #8                  // Method "<init>":(Ljava/lang/String;I)V
     103: putstatic     #23                 // Field THREAD_POOL:Lorg/apache/dubbo/metrics/model/MetricsCategory;
     106: bipush        8
     108: anewarray     #4                  // class org/apache/dubbo/metrics/model/MetricsCategory
     111: dup
     112: iconst_0
     113: getstatic     #9                  // Field RT:Lorg/apache/dubbo/metrics/model/MetricsCategory;
     116: aastore
     117: dup
     118: iconst_1
     119: getstatic     #11                 // Field QPS:Lorg/apache/dubbo/metrics/model/MetricsCategory;
     122: aastore
     123: dup
     124: iconst_2
     125: getstatic     #13                 // Field REQUESTS:Lorg/apache/dubbo/metrics/model/MetricsCategory;
     128: aastore
     129: dup
     130: iconst_3
     131: getstatic     #15                 // Field APPLICATION:Lorg/apache/dubbo/metrics/model/MetricsCategory;
     134: aastore
     135: dup
     136: iconst_4
     137: getstatic     #17                 // Field CONFIGCENTER:Lorg/apache/dubbo/metrics/model/MetricsCategory;
     140: aastore
     141: dup
     142: iconst_5
     143: getstatic     #19                 // Field REGISTRY:Lorg/apache/dubbo/metrics/model/MetricsCategory;
     146: aastore
     147: dup
     148: bipush        6
     150: getstatic     #21                 // Field METADATA:Lorg/apache/dubbo/metrics/model/MetricsCategory;
     153: aastore
     154: dup
     155: bipush        7
     157: getstatic     #23                 // Field THREAD_POOL:Lorg/apache/dubbo/metrics/model/MetricsCategory;
     160: aastore
     161: putstatic     #1                  // Field $VALUES:[Lorg/apache/dubbo/metrics/model/MetricsCategory;
     164: return
}
