Compiled from "ServiceKeyMetric.java"
public class org.apache.dubbo.metrics.model.ServiceKeyMetric extends org.apache.dubbo.metrics.model.ApplicationMetric {
  private final java.lang.String interfaceName;

  public org.apache.dubbo.metrics.model.ServiceKeyMetric(org.apache.dubbo.rpc.model.ApplicationModel, java.lang.String);
    Code:
       0: aload_0
       1: aload_1
       2: invokespecial #1                  // Method org/apache/dubbo/metrics/model/ApplicationMetric."<init>":(Lorg/apache/dubbo/rpc/model/ApplicationModel;)V
       5: aload_0
       6: aload_2
       7: putfield      #2                  // Field interfaceName:Ljava/lang/String;
      10: return

  public java.util.Map<java.lang.String, java.lang.String> getTags();
    Code:
       0: aload_0
       1: invokevirtual #3                  // Method getApplicationModel:()Lorg/apache/dubbo/rpc/model/ApplicationModel;
       4: aload_0
       5: getfield      #2                  // Field interfaceName:Ljava/lang/String;
       8: invokestatic  #4                  // Method org/apache/dubbo/metrics/model/MetricsSupport.serviceTags:(Lorg/apache/dubbo/rpc/model/ApplicationModel;Ljava/lang/String;)Ljava/util/Map;
      11: areturn

  public java.lang.String getInterfaceName();
    Code:
       0: aload_0
       1: getfield      #2                  // Field interfaceName:Ljava/lang/String;
       4: areturn

  public boolean equals(java.lang.Object);
    Code:
       0: aload_0
       1: aload_1
       2: if_acmpne     7
       5: iconst_1
       6: ireturn
       7: aload_1
       8: ifnull        22
      11: aload_0
      12: invokevirtual #5                  // Method java/lang/Object.getClass:()Ljava/lang/Class;
      15: aload_1
      16: invokevirtual #5                  // Method java/lang/Object.getClass:()Ljava/lang/Class;
      19: if_acmpeq     24
      22: iconst_0
      23: ireturn
      24: aload_1
      25: checkcast     #6                  // class org/apache/dubbo/metrics/model/ServiceKeyMetric
      28: astore_2
      29: aload_0
      30: invokevirtual #7                  // Method getApplicationName:()Ljava/lang/String;
      33: aload_2
      34: invokevirtual #7                  // Method getApplicationName:()Ljava/lang/String;
      37: invokevirtual #8                  // Method java/lang/String.equals:(Ljava/lang/Object;)Z
      40: ifne          45
      43: iconst_0
      44: ireturn
      45: aload_0
      46: getfield      #2                  // Field interfaceName:Ljava/lang/String;
      49: aload_2
      50: getfield      #2                  // Field interfaceName:Ljava/lang/String;
      53: invokevirtual #8                  // Method java/lang/String.equals:(Ljava/lang/Object;)Z
      56: ireturn

  public int hashCode();
    Code:
       0: aload_0
       1: invokevirtual #7                  // Method getApplicationName:()Ljava/lang/String;
       4: invokevirtual #9                  // Method java/lang/String.hashCode:()I
       7: istore_1
       8: bipush        31
      10: iload_1
      11: imul
      12: aload_0
      13: getfield      #2                  // Field interfaceName:Ljava/lang/String;
      16: invokevirtual #9                  // Method java/lang/String.hashCode:()I
      19: iadd
      20: istore_1
      21: iload_1
      22: ireturn

  public java.lang.String toString();
    Code:
       0: new           #10                 // class java/lang/StringBuilder
       3: dup
       4: invokespecial #11                 // Method java/lang/StringBuilder."<init>":()V
       7: ldc           #12                 // String ServiceKeyMetric{applicationName=\'
       9: invokevirtual #13                 // Method java/lang/StringBuilder.append:(Ljava/lang/String;)Ljava/lang/StringBuilder;
      12: aload_0
      13: invokevirtual #7                  // Method getApplicationName:()Ljava/lang/String;
      16: invokevirtual #13                 // Method java/lang/StringBuilder.append:(Ljava/lang/String;)Ljava/lang/StringBuilder;
      19: bipush        39
      21: invokevirtual #14                 // Method java/lang/StringBuilder.append:(C)Ljava/lang/StringBuilder;
      24: ldc           #15                 // String , serviceKey=\'
      26: invokevirtual #13                 // Method java/lang/StringBuilder.append:(Ljava/lang/String;)Ljava/lang/StringBuilder;
      29: aload_0
      30: getfield      #2                  // Field interfaceName:Ljava/lang/String;
      33: invokevirtual #13                 // Method java/lang/StringBuilder.append:(Ljava/lang/String;)Ljava/lang/StringBuilder;
      36: bipush        39
      38: invokevirtual #14                 // Method java/lang/StringBuilder.append:(C)Ljava/lang/StringBuilder;
      41: bipush        125
      43: invokevirtual #14                 // Method java/lang/StringBuilder.append:(C)Ljava/lang/StringBuilder;
      46: invokevirtual #16                 // Method java/lang/StringBuilder.toString:()Ljava/lang/String;
      49: areturn
}
