Compiled from "TimePair.java"
public class org.apache.dubbo.metrics.model.TimePair {
  private final long begin;

  private long end;

  private static final org.apache.dubbo.metrics.model.TimePair empty;

  public org.apache.dubbo.metrics.model.TimePair(long);
    Code:
       0: aload_0
       1: invokespecial #1                  // Method java/lang/Object."<init>":()V
       4: aload_0
       5: lload_1
       6: putfield      #2                  // Field begin:J
       9: return

  public static org.apache.dubbo.metrics.model.TimePair start();
    Code:
       0: new           #3                  // class org/apache/dubbo/metrics/model/TimePair
       3: dup
       4: invokestatic  #4                  // Method java/lang/System.currentTimeMillis:()J
       7: invokespecial #5                  // Method "<init>":(J)V
      10: areturn

  public void end();
    Code:
       0: aload_0
       1: invokestatic  #4                  // Method java/lang/System.currentTimeMillis:()J
       4: putfield      #6                  // Field end:J
       7: return

  public long calc();
    Code:
       0: aload_0
       1: getfield      #6                  // Field end:J
       4: aload_0
       5: getfield      #2                  // Field begin:J
       8: lsub
       9: lreturn

  public static org.apache.dubbo.metrics.model.TimePair empty();
    Code:
       0: getstatic     #7                  // Field empty:Lorg/apache/dubbo/metrics/model/TimePair;
       3: areturn

  static {};
    Code:
       0: new           #3                  // class org/apache/dubbo/metrics/model/TimePair
       3: dup
       4: lconst_0
       5: invokespecial #5                  // Method "<init>":(J)V
       8: putstatic     #7                  // Field empty:Lorg/apache/dubbo/metrics/model/TimePair;
      11: return
}
