Compiled from "BaseServiceMetadataIdentifier.java"
public class org.apache.dubbo.metadata.report.identifier.BaseServiceMetadataIdentifier {
  protected java.lang.String serviceInterface;

  protected java.lang.String version;

  protected java.lang.String group;

  protected java.lang.String side;

  public org.apache.dubbo.metadata.report.identifier.BaseServiceMetadataIdentifier();
    Code:
       0: aload_0
       1: invokespecial #3                  // Method java/lang/Object."<init>":()V
       4: return

  protected java.lang.String getUniqueKey(org.apache.dubbo.metadata.report.identifier.KeyTypeEnum, java.lang.String...);
    Code:
       0: aload_1
       1: getstatic     #4                  // Field org/apache/dubbo/metadata/report/identifier/KeyTypeEnum.PATH:Lorg/apache/dubbo/metadata/report/identifier/KeyTypeEnum;
       4: if_acmpne     13
       7: aload_0
       8: aload_2
       9: invokespecial #5                  // Method getFilePathKey:([Ljava/lang/String;)Ljava/lang/String;
      12: areturn
      13: aload_0
      14: aload_2
      15: invokevirtual #6                  // Method getIdentifierKey:([Ljava/lang/String;)Ljava/lang/String;
      18: areturn

  protected java.lang.String getIdentifierKey(java.lang.String...);
    Code:
       0: getstatic     #7                  // Field org/apache/dubbo/metadata/report/identifier/KeyTypeEnum.UNIQUE_KEY:Lorg/apache/dubbo/metadata/report/identifier/KeyTypeEnum;
       3: aload_0
       4: getfield      #8                  // Field serviceInterface:Ljava/lang/String;
       7: iconst_3
       8: anewarray     #9                  // class java/lang/String
      11: dup
      12: iconst_0
      13: aload_0
      14: getfield      #10                 // Field version:Ljava/lang/String;
      17: aastore
      18: dup
      19: iconst_1
      20: aload_0
      21: getfield      #11                 // Field group:Ljava/lang/String;
      24: aastore
      25: dup
      26: iconst_2
      27: aload_0
      28: getfield      #12                 // Field side:Ljava/lang/String;
      31: aastore
      32: invokevirtual #13                 // Method org/apache/dubbo/metadata/report/identifier/KeyTypeEnum.build:(Ljava/lang/String;[Ljava/lang/String;)Ljava/lang/String;
      35: astore_2
      36: getstatic     #7                  // Field org/apache/dubbo/metadata/report/identifier/KeyTypeEnum.UNIQUE_KEY:Lorg/apache/dubbo/metadata/report/identifier/KeyTypeEnum;
      39: aload_2
      40: aload_1
      41: invokevirtual #13                 // Method org/apache/dubbo/metadata/report/identifier/KeyTypeEnum.build:(Ljava/lang/String;[Ljava/lang/String;)Ljava/lang/String;
      44: areturn

  private java.lang.String getFilePathKey(java.lang.String...);
    Code:
       0: aload_0
       1: ldc           #14                 // String metadata
       3: aload_1
       4: invokespecial #15                 // Method getFilePathKey:(Ljava/lang/String;[Ljava/lang/String;)Ljava/lang/String;
       7: areturn

  private java.lang.String getFilePathKey(java.lang.String, java.lang.String...);
    Code:
       0: getstatic     #4                  // Field org/apache/dubbo/metadata/report/identifier/KeyTypeEnum.PATH:Lorg/apache/dubbo/metadata/report/identifier/KeyTypeEnum;
       3: aload_1
       4: iconst_4
       5: anewarray     #9                  // class java/lang/String
       8: dup
       9: iconst_0
      10: aload_0
      11: invokespecial #16                 // Method toServicePath:()Ljava/lang/String;
      14: aastore
      15: dup
      16: iconst_1
      17: aload_0
      18: getfield      #10                 // Field version:Ljava/lang/String;
      21: aastore
      22: dup
      23: iconst_2
      24: aload_0
      25: getfield      #11                 // Field group:Ljava/lang/String;
      28: aastore
      29: dup
      30: iconst_3
      31: aload_0
      32: getfield      #12                 // Field side:Ljava/lang/String;
      35: aastore
      36: invokevirtual #13                 // Method org/apache/dubbo/metadata/report/identifier/KeyTypeEnum.build:(Ljava/lang/String;[Ljava/lang/String;)Ljava/lang/String;
      39: astore_3
      40: getstatic     #4                  // Field org/apache/dubbo/metadata/report/identifier/KeyTypeEnum.PATH:Lorg/apache/dubbo/metadata/report/identifier/KeyTypeEnum;
      43: aload_3
      44: aload_2
      45: invokevirtual #13                 // Method org/apache/dubbo/metadata/report/identifier/KeyTypeEnum.build:(Ljava/lang/String;[Ljava/lang/String;)Ljava/lang/String;
      48: areturn

  private java.lang.String toServicePath();
    Code:
       0: ldc           #17                 // String *
       2: aload_0
       3: getfield      #8                  // Field serviceInterface:Ljava/lang/String;
       6: invokevirtual #18                 // Method java/lang/String.equals:(Ljava/lang/Object;)Z
       9: ifeq          15
      12: ldc           #19                 // String
      14: areturn
      15: aload_0
      16: getfield      #8                  // Field serviceInterface:Ljava/lang/String;
      19: invokestatic  #20                 // Method org/apache/dubbo/common/URL.encode:(Ljava/lang/String;)Ljava/lang/String;
      22: areturn
}
