Compiled from "BaseApplicationMetadataIdentifier.java"
public class org.apache.dubbo.metadata.report.identifier.BaseApplicationMetadataIdentifier {
  protected java.lang.String application;

  public org.apache.dubbo.metadata.report.identifier.BaseApplicationMetadataIdentifier();
    Code:
       0: aload_0
       1: invokespecial #2                  // Method java/lang/Object."<init>":()V
       4: return

  protected java.lang.String getUniqueKey(org.apache.dubbo.metadata.report.identifier.KeyTypeEnum, java.lang.String...);
    Code:
       0: aload_1
       1: getstatic     #3                  // Field org/apache/dubbo/metadata/report/identifier/KeyTypeEnum.PATH:Lorg/apache/dubbo/metadata/report/identifier/KeyTypeEnum;
       4: if_acmpne     13
       7: aload_0
       8: aload_2
       9: invokespecial #4                  // Method getFilePathKey:([Ljava/lang/String;)Ljava/lang/String;
      12: areturn
      13: aload_0
      14: aload_2
      15: invokevirtual #5                  // Method getIdentifierKey:([Ljava/lang/String;)Ljava/lang/String;
      18: areturn

  protected java.lang.String getIdentifierKey(java.lang.String...);
    Code:
       0: getstatic     #6                  // Field org/apache/dubbo/metadata/report/identifier/KeyTypeEnum.UNIQUE_KEY:Lorg/apache/dubbo/metadata/report/identifier/KeyTypeEnum;
       3: aload_0
       4: getfield      #7                  // Field application:Ljava/lang/String;
       7: aload_1
       8: invokevirtual #8                  // Method org/apache/dubbo/metadata/report/identifier/KeyTypeEnum.build:(Ljava/lang/String;[Ljava/lang/String;)Ljava/lang/String;
      11: areturn

  private java.lang.String getFilePathKey(java.lang.String...);
    Code:
       0: aload_0
       1: ldc           #9                  // String metadata
       3: aload_1
       4: invokespecial #10                 // Method getFilePathKey:(Ljava/lang/String;[Ljava/lang/String;)Ljava/lang/String;
       7: areturn

  private java.lang.String getFilePathKey(java.lang.String, java.lang.String...);
    Code:
       0: getstatic     #3                  // Field org/apache/dubbo/metadata/report/identifier/KeyTypeEnum.PATH:Lorg/apache/dubbo/metadata/report/identifier/KeyTypeEnum;
       3: aload_1
       4: iconst_1
       5: anewarray     #11                 // class java/lang/String
       8: dup
       9: iconst_0
      10: aload_0
      11: getfield      #7                  // Field application:Ljava/lang/String;
      14: aastore
      15: invokevirtual #8                  // Method org/apache/dubbo/metadata/report/identifier/KeyTypeEnum.build:(Ljava/lang/String;[Ljava/lang/String;)Ljava/lang/String;
      18: astore_3
      19: getstatic     #3                  // Field org/apache/dubbo/metadata/report/identifier/KeyTypeEnum.PATH:Lorg/apache/dubbo/metadata/report/identifier/KeyTypeEnum;
      22: aload_3
      23: aload_2
      24: invokevirtual #8                  // Method org/apache/dubbo/metadata/report/identifier/KeyTypeEnum.build:(Ljava/lang/String;[Ljava/lang/String;)Ljava/lang/String;
      27: areturn
}
