Compiled from "KeyTypeEnum.java"
public abstract class org.apache.dubbo.metadata.report.identifier.KeyTypeEnum extends java.lang.Enum<org.apache.dubbo.metadata.report.identifier.KeyTypeEnum> {
  public static final org.apache.dubbo.metadata.report.identifier.KeyTypeEnum PATH;

  public static final org.apache.dubbo.metadata.report.identifier.KeyTypeEnum UNIQUE_KEY;

  final java.lang.String separator;

  private static final org.apache.dubbo.metadata.report.identifier.KeyTypeEnum[] $VALUES;

  public static org.apache.dubbo.metadata.report.identifier.KeyTypeEnum[] values();
    Code:
       0: getstatic     #4                  // Field $VALUES:[Lorg/apache/dubbo/metadata/report/identifier/KeyTypeEnum;
       3: invokevirtual #5                  // Method "[Lorg/apache/dubbo/metadata/report/identifier/KeyTypeEnum;".clone:()Ljava/lang/Object;
       6: checkcast     #6                  // class "[Lorg/apache/dubbo/metadata/report/identifier/KeyTypeEnum;"
       9: areturn

  public static org.apache.dubbo.metadata.report.identifier.KeyTypeEnum valueOf(java.lang.String);
    Code:
       0: ldc           #7                  // class org/apache/dubbo/metadata/report/identifier/KeyTypeEnum
       2: aload_0
       3: invokestatic  #8                  // Method java/lang/Enum.valueOf:(Ljava/lang/Class;Ljava/lang/String;)Ljava/lang/Enum;
       6: checkcast     #7                  // class org/apache/dubbo/metadata/report/identifier/KeyTypeEnum
       9: areturn

  private org.apache.dubbo.metadata.report.identifier.KeyTypeEnum(java.lang.String);
    Code:
       0: aload_0
       1: aload_1
       2: iload_2
       3: invokespecial #9                  // Method java/lang/Enum."<init>":(Ljava/lang/String;I)V
       6: aload_0
       7: aload_3
       8: putfield      #10                 // Field separator:Ljava/lang/String;
      11: return

  public abstract java.lang.String build(java.lang.String, java.lang.String...);

  org.apache.dubbo.metadata.report.identifier.KeyTypeEnum(java.lang.String, int, java.lang.String, org.apache.dubbo.metadata.report.identifier.KeyTypeEnum$1);
    Code:
       0: aload_0
       1: aload_1
       2: iload_2
       3: aload_3
       4: invokespecial #3                  // Method "<init>":(Ljava/lang/String;ILjava/lang/String;)V
       7: return

  static {};
    Code:
       0: new           #11                 // class org/apache/dubbo/metadata/report/identifier/KeyTypeEnum$1
       3: dup
       4: ldc           #12                 // String PATH
       6: iconst_0
       7: ldc           #13                 // String /
       9: invokespecial #14                 // Method org/apache/dubbo/metadata/report/identifier/KeyTypeEnum$1."<init>":(Ljava/lang/String;ILjava/lang/String;)V
      12: putstatic     #15                 // Field PATH:Lorg/apache/dubbo/metadata/report/identifier/KeyTypeEnum;
      15: new           #16                 // class org/apache/dubbo/metadata/report/identifier/KeyTypeEnum$2
      18: dup
      19: ldc           #17                 // String UNIQUE_KEY
      21: iconst_1
      22: ldc           #18                 // String :
      24: invokespecial #19                 // Method org/apache/dubbo/metadata/report/identifier/KeyTypeEnum$2."<init>":(Ljava/lang/String;ILjava/lang/String;)V
      27: putstatic     #20                 // Field UNIQUE_KEY:Lorg/apache/dubbo/metadata/report/identifier/KeyTypeEnum;
      30: iconst_2
      31: anewarray     #7                  // class org/apache/dubbo/metadata/report/identifier/KeyTypeEnum
      34: dup
      35: iconst_0
      36: getstatic     #15                 // Field PATH:Lorg/apache/dubbo/metadata/report/identifier/KeyTypeEnum;
      39: aastore
      40: dup
      41: iconst_1
      42: getstatic     #20                 // Field UNIQUE_KEY:Lorg/apache/dubbo/metadata/report/identifier/KeyTypeEnum;
      45: aastore
      46: putstatic     #4                  // Field $VALUES:[Lorg/apache/dubbo/metadata/report/identifier/KeyTypeEnum;
      49: return
}
