Compiled from "KeyTypeEnum.java"
final class org.apache.dubbo.metadata.report.identifier.KeyTypeEnum$2 extends org.apache.dubbo.metadata.report.identifier.KeyTypeEnum {
  org.apache.dubbo.metadata.report.identifier.KeyTypeEnum$2(java.lang.String, int, java.lang.String);
    Code:
       0: aload_0
       1: aload_1
       2: iload_2
       3: aload_3
       4: aconst_null
       5: invokespecial #2                  // Method org/apache/dubbo/metadata/report/identifier/KeyTypeEnum."<init>":(Ljava/lang/String;ILjava/lang/String;Lorg/apache/dubbo/metadata/report/identifier/KeyTypeEnum$1;)V
       8: return

  public java.lang.String build(java.lang.String, java.lang.String...);
    Code:
       0: new           #3                  // class java/lang/StringBuilder
       3: dup
       4: aload_1
       5: invokespecial #4                  // Method java/lang/StringBuilder."<init>":(Ljava/lang/String;)V
       8: astore_3
       9: aload_2
      10: astore        4
      12: aload         4
      14: arraylength
      15: istore        5
      17: iconst_0
      18: istore        6
      20: iload         6
      22: iload         5
      24: if_icmpge     67
      27: aload         4
      29: iload         6
      31: aaload
      32: astore        7
      34: aload_3
      35: aload_0
      36: getfield      #5                  // Field separator:Ljava/lang/String;
      39: invokevirtual #6                  // Method java/lang/StringBuilder.append:(Ljava/lang/String;)Ljava/lang/StringBuilder;
      42: aload         7
      44: invokestatic  #7                  // Method org/apache/dubbo/common/utils/StringUtils.isBlank:(Ljava/lang/CharSequence;)Z
      47: ifeq          55
      50: ldc           #8                  // String
      52: goto          57
      55: aload         7
      57: invokevirtual #6                  // Method java/lang/StringBuilder.append:(Ljava/lang/String;)Ljava/lang/StringBuilder;
      60: pop
      61: iinc          6, 1
      64: goto          20
      67: aload_3
      68: invokevirtual #9                  // Method java/lang/StringBuilder.toString:()Ljava/lang/String;
      71: areturn
}
