Compiled from "KeyTypeEnum.java"
final class org.apache.dubbo.metadata.report.identifier.KeyTypeEnum$1 extends org.apache.dubbo.metadata.report.identifier.KeyTypeEnum {
  org.apache.dubbo.metadata.report.identifier.KeyTypeEnum$1(java.lang.String, int, java.lang.String);
    Code:
       0: aload_0
       1: aload_1
       2: iload_2
       3: aload_3
       4: aconst_null
       5: invokespecial #1                  // Method org/apache/dubbo/metadata/report/identifier/KeyTypeEnum."<init>":(Ljava/lang/String;ILjava/lang/String;Lorg/apache/dubbo/metadata/report/identifier/KeyTypeEnum$1;)V
       8: return

  public java.lang.String build(java.lang.String, java.lang.String...);
    Code:
       0: aload_1
       1: aload_2
       2: invokestatic  #2                  // InterfaceMethod org/apache/dubbo/common/utils/PathUtils.buildPath:(Ljava/lang/String;[Ljava/lang/String;)Ljava/lang/String;
       5: areturn
}
