Compiled from "MetadataIdentifier.java"
public class org.apache.dubbo.metadata.report.identifier.MetadataIdentifier extends org.apache.dubbo.metadata.report.identifier.BaseServiceMetadataIdentifier implements org.apache.dubbo.metadata.report.identifier.BaseMetadataIdentifier {
  private java.lang.String application;

  public org.apache.dubbo.metadata.report.identifier.MetadataIdentifier();
    Code:
       0: aload_0
       1: invokespecial #1                  // Method org/apache/dubbo/metadata/report/identifier/BaseServiceMetadataIdentifier."<init>":()V
       4: return

  public org.apache.dubbo.metadata.report.identifier.MetadataIdentifier(java.lang.String, java.lang.String, java.lang.String, java.lang.String, java.lang.String);
    Code:
       0: aload_0
       1: invokespecial #1                  // Method org/apache/dubbo/metadata/report/identifier/BaseServiceMetadataIdentifier."<init>":()V
       4: aload_0
       5: aload_1
       6: putfield      #2                  // Field serviceInterface:Ljava/lang/String;
       9: aload_0
      10: aload_2
      11: putfield      #3                  // Field version:Ljava/lang/String;
      14: aload_0
      15: aload_3
      16: putfield      #4                  // Field group:Ljava/lang/String;
      19: aload_0
      20: aload         4
      22: putfield      #5                  // Field side:Ljava/lang/String;
      25: aload_0
      26: aload         5
      28: putfield      #6                  // Field application:Ljava/lang/String;
      31: return

  public org.apache.dubbo.metadata.report.identifier.MetadataIdentifier(org.apache.dubbo.common.URL);
    Code:
       0: aload_0
       1: invokespecial #1                  // Method org/apache/dubbo/metadata/report/identifier/BaseServiceMetadataIdentifier."<init>":()V
       4: aload_0
       5: aload_1
       6: invokevirtual #7                  // Method org/apache/dubbo/common/URL.getServiceInterface:()Ljava/lang/String;
       9: putfield      #2                  // Field serviceInterface:Ljava/lang/String;
      12: aload_0
      13: aload_1
      14: invokevirtual #8                  // Method org/apache/dubbo/common/URL.getVersion:()Ljava/lang/String;
      17: putfield      #3                  // Field version:Ljava/lang/String;
      20: aload_0
      21: aload_1
      22: invokevirtual #9                  // Method org/apache/dubbo/common/URL.getGroup:()Ljava/lang/String;
      25: putfield      #4                  // Field group:Ljava/lang/String;
      28: aload_0
      29: aload_1
      30: invokevirtual #10                 // Method org/apache/dubbo/common/URL.getSide:()Ljava/lang/String;
      33: putfield      #5                  // Field side:Ljava/lang/String;
      36: aload_0
      37: aload_1
      38: invokevirtual #11                 // Method org/apache/dubbo/common/URL.getApplication:()Ljava/lang/String;
      41: invokevirtual #12                 // Method setApplication:(Ljava/lang/String;)V
      44: return

  public java.lang.String getUniqueKey(org.apache.dubbo.metadata.report.identifier.KeyTypeEnum);
    Code:
       0: aload_0
       1: aload_1
       2: iconst_1
       3: anewarray     #13                 // class java/lang/String
       6: dup
       7: iconst_0
       8: aload_0
       9: getfield      #6                  // Field application:Ljava/lang/String;
      12: aastore
      13: invokespecial #14                 // Method org/apache/dubbo/metadata/report/identifier/BaseServiceMetadataIdentifier.getUniqueKey:(Lorg/apache/dubbo/metadata/report/identifier/KeyTypeEnum;[Ljava/lang/String;)Ljava/lang/String;
      16: areturn

  public java.lang.String getIdentifierKey();
    Code:
       0: aload_0
       1: iconst_1
       2: anewarray     #13                 // class java/lang/String
       5: dup
       6: iconst_0
       7: aload_0
       8: getfield      #6                  // Field application:Ljava/lang/String;
      11: aastore
      12: invokespecial #15                 // Method org/apache/dubbo/metadata/report/identifier/BaseServiceMetadataIdentifier.getIdentifierKey:([Ljava/lang/String;)Ljava/lang/String;
      15: areturn

  public java.lang.String getServiceInterface();
    Code:
       0: aload_0
       1: getfield      #2                  // Field serviceInterface:Ljava/lang/String;
       4: areturn

  public void setServiceInterface(java.lang.String);
    Code:
       0: aload_0
       1: aload_1
       2: putfield      #2                  // Field serviceInterface:Ljava/lang/String;
       5: return

  public java.lang.String getVersion();
    Code:
       0: aload_0
       1: getfield      #3                  // Field version:Ljava/lang/String;
       4: areturn

  public void setVersion(java.lang.String);
    Code:
       0: aload_0
       1: aload_1
       2: putfield      #3                  // Field version:Ljava/lang/String;
       5: return

  public java.lang.String getGroup();
    Code:
       0: aload_0
       1: getfield      #4                  // Field group:Ljava/lang/String;
       4: areturn

  public void setGroup(java.lang.String);
    Code:
       0: aload_0
       1: aload_1
       2: putfield      #4                  // Field group:Ljava/lang/String;
       5: return

  public java.lang.String getSide();
    Code:
       0: aload_0
       1: getfield      #5                  // Field side:Ljava/lang/String;
       4: areturn

  public void setSide(java.lang.String);
    Code:
       0: aload_0
       1: aload_1
       2: putfield      #5                  // Field side:Ljava/lang/String;
       5: return

  public java.lang.String getApplication();
    Code:
       0: aload_0
       1: getfield      #6                  // Field application:Ljava/lang/String;
       4: areturn

  public void setApplication(java.lang.String);
    Code:
       0: aload_0
       1: aload_1
       2: putfield      #6                  // Field application:Ljava/lang/String;
       5: return
}
