Compiled from "ServiceMetadataIdentifier.java"
public class org.apache.dubbo.metadata.report.identifier.ServiceMetadataIdentifier extends org.apache.dubbo.metadata.report.identifier.BaseServiceMetadataIdentifier implements org.apache.dubbo.metadata.report.identifier.BaseMetadataIdentifier {
  private java.lang.String revision;

  private java.lang.String protocol;

  public org.apache.dubbo.metadata.report.identifier.ServiceMetadataIdentifier();
    Code:
       0: aload_0
       1: invokespecial #2                  // Method org/apache/dubbo/metadata/report/identifier/BaseServiceMetadataIdentifier."<init>":()V
       4: return

  public org.apache.dubbo.metadata.report.identifier.ServiceMetadataIdentifier(java.lang.String, java.lang.String, java.lang.String, java.lang.String, java.lang.String, java.lang.String);
    Code:
       0: aload_0
       1: invokespecial #2                  // Method org/apache/dubbo/metadata/report/identifier/BaseServiceMetadataIdentifier."<init>":()V
       4: aload_0
       5: aload_1
       6: putfield      #3                  // Field serviceInterface:Ljava/lang/String;
       9: aload_0
      10: aload_2
      11: putfield      #4                  // Field version:Ljava/lang/String;
      14: aload_0
      15: aload_3
      16: putfield      #5                  // Field group:Ljava/lang/String;
      19: aload_0
      20: aload         4
      22: putfield      #6                  // Field side:Ljava/lang/String;
      25: aload_0
      26: aload         5
      28: putfield      #7                  // Field revision:Ljava/lang/String;
      31: aload_0
      32: aload         6
      34: putfield      #8                  // Field protocol:Ljava/lang/String;
      37: return

  public org.apache.dubbo.metadata.report.identifier.ServiceMetadataIdentifier(org.apache.dubbo.common.URL);
    Code:
       0: aload_0
       1: invokespecial #2                  // Method org/apache/dubbo/metadata/report/identifier/BaseServiceMetadataIdentifier."<init>":()V
       4: aload_0
       5: aload_1
       6: invokevirtual #9                  // Method org/apache/dubbo/common/URL.getServiceInterface:()Ljava/lang/String;
       9: putfield      #3                  // Field serviceInterface:Ljava/lang/String;
      12: aload_0
      13: aload_1
      14: invokevirtual #10                 // Method org/apache/dubbo/common/URL.getVersion:()Ljava/lang/String;
      17: putfield      #4                  // Field version:Ljava/lang/String;
      20: aload_0
      21: aload_1
      22: invokevirtual #11                 // Method org/apache/dubbo/common/URL.getGroup:()Ljava/lang/String;
      25: putfield      #5                  // Field group:Ljava/lang/String;
      28: aload_0
      29: aload_1
      30: invokevirtual #12                 // Method org/apache/dubbo/common/URL.getSide:()Ljava/lang/String;
      33: putfield      #6                  // Field side:Ljava/lang/String;
      36: aload_0
      37: aload_1
      38: invokevirtual #13                 // Method org/apache/dubbo/common/URL.getProtocol:()Ljava/lang/String;
      41: putfield      #8                  // Field protocol:Ljava/lang/String;
      44: return

  public java.lang.String getUniqueKey(org.apache.dubbo.metadata.report.identifier.KeyTypeEnum);
    Code:
       0: aload_0
       1: aload_1
       2: iconst_2
       3: anewarray     #14                 // class java/lang/String
       6: dup
       7: iconst_0
       8: aload_0
       9: getfield      #8                  // Field protocol:Ljava/lang/String;
      12: aastore
      13: dup
      14: iconst_1
      15: new           #15                 // class java/lang/StringBuilder
      18: dup
      19: invokespecial #16                 // Method java/lang/StringBuilder."<init>":()V
      22: ldc           #17                 // String revision
      24: invokevirtual #18                 // Method java/lang/StringBuilder.append:(Ljava/lang/String;)Ljava/lang/StringBuilder;
      27: aload_0
      28: getfield      #7                  // Field revision:Ljava/lang/String;
      31: invokevirtual #18                 // Method java/lang/StringBuilder.append:(Ljava/lang/String;)Ljava/lang/StringBuilder;
      34: invokevirtual #19                 // Method java/lang/StringBuilder.toString:()Ljava/lang/String;
      37: aastore
      38: invokespecial #20                 // Method org/apache/dubbo/metadata/report/identifier/BaseServiceMetadataIdentifier.getUniqueKey:(Lorg/apache/dubbo/metadata/report/identifier/KeyTypeEnum;[Ljava/lang/String;)Ljava/lang/String;
      41: areturn

  public java.lang.String getIdentifierKey();
    Code:
       0: aload_0
       1: iconst_2
       2: anewarray     #14                 // class java/lang/String
       5: dup
       6: iconst_0
       7: aload_0
       8: getfield      #8                  // Field protocol:Ljava/lang/String;
      11: aastore
      12: dup
      13: iconst_1
      14: new           #15                 // class java/lang/StringBuilder
      17: dup
      18: invokespecial #16                 // Method java/lang/StringBuilder."<init>":()V
      21: ldc           #17                 // String revision
      23: invokevirtual #18                 // Method java/lang/StringBuilder.append:(Ljava/lang/String;)Ljava/lang/StringBuilder;
      26: aload_0
      27: getfield      #7                  // Field revision:Ljava/lang/String;
      30: invokevirtual #18                 // Method java/lang/StringBuilder.append:(Ljava/lang/String;)Ljava/lang/StringBuilder;
      33: invokevirtual #19                 // Method java/lang/StringBuilder.toString:()Ljava/lang/String;
      36: aastore
      37: invokespecial #21                 // Method org/apache/dubbo/metadata/report/identifier/BaseServiceMetadataIdentifier.getIdentifierKey:([Ljava/lang/String;)Ljava/lang/String;
      40: areturn

  public void setRevision(java.lang.String);
    Code:
       0: aload_0
       1: aload_1
       2: putfield      #7                  // Field revision:Ljava/lang/String;
       5: return

  public void setProtocol(java.lang.String);
    Code:
       0: aload_0
       1: aload_1
       2: putfield      #8                  // Field protocol:Ljava/lang/String;
       5: return

  public java.lang.String toString();
    Code:
       0: new           #15                 // class java/lang/StringBuilder
       3: dup
       4: invokespecial #16                 // Method java/lang/StringBuilder."<init>":()V
       7: ldc           #22                 // String ServiceMetadataIdentifier{revision=\'
       9: invokevirtual #18                 // Method java/lang/StringBuilder.append:(Ljava/lang/String;)Ljava/lang/StringBuilder;
      12: aload_0
      13: getfield      #7                  // Field revision:Ljava/lang/String;
      16: invokevirtual #18                 // Method java/lang/StringBuilder.append:(Ljava/lang/String;)Ljava/lang/StringBuilder;
      19: bipush        39
      21: invokevirtual #23                 // Method java/lang/StringBuilder.append:(C)Ljava/lang/StringBuilder;
      24: ldc           #24                 // String , protocol=\'
      26: invokevirtual #18                 // Method java/lang/StringBuilder.append:(Ljava/lang/String;)Ljava/lang/StringBuilder;
      29: aload_0
      30: getfield      #8                  // Field protocol:Ljava/lang/String;
      33: invokevirtual #18                 // Method java/lang/StringBuilder.append:(Ljava/lang/String;)Ljava/lang/StringBuilder;
      36: bipush        39
      38: invokevirtual #23                 // Method java/lang/StringBuilder.append:(C)Ljava/lang/StringBuilder;
      41: ldc           #25                 // String , serviceInterface=\'
      43: invokevirtual #18                 // Method java/lang/StringBuilder.append:(Ljava/lang/String;)Ljava/lang/StringBuilder;
      46: aload_0
      47: getfield      #3                  // Field serviceInterface:Ljava/lang/String;
      50: invokevirtual #18                 // Method java/lang/StringBuilder.append:(Ljava/lang/String;)Ljava/lang/StringBuilder;
      53: bipush        39
      55: invokevirtual #23                 // Method java/lang/StringBuilder.append:(C)Ljava/lang/StringBuilder;
      58: ldc           #26                 // String , version=\'
      60: invokevirtual #18                 // Method java/lang/StringBuilder.append:(Ljava/lang/String;)Ljava/lang/StringBuilder;
      63: aload_0
      64: getfield      #4                  // Field version:Ljava/lang/String;
      67: invokevirtual #18                 // Method java/lang/StringBuilder.append:(Ljava/lang/String;)Ljava/lang/StringBuilder;
      70: bipush        39
      72: invokevirtual #23                 // Method java/lang/StringBuilder.append:(C)Ljava/lang/StringBuilder;
      75: ldc           #27                 // String , group=\'
      77: invokevirtual #18                 // Method java/lang/StringBuilder.append:(Ljava/lang/String;)Ljava/lang/StringBuilder;
      80: aload_0
      81: getfield      #5                  // Field group:Ljava/lang/String;
      84: invokevirtual #18                 // Method java/lang/StringBuilder.append:(Ljava/lang/String;)Ljava/lang/StringBuilder;
      87: bipush        39
      89: invokevirtual #23                 // Method java/lang/StringBuilder.append:(C)Ljava/lang/StringBuilder;
      92: ldc           #28                 // String , side=\'
      94: invokevirtual #18                 // Method java/lang/StringBuilder.append:(Ljava/lang/String;)Ljava/lang/StringBuilder;
      97: aload_0
      98: getfield      #6                  // Field side:Ljava/lang/String;
     101: invokevirtual #18                 // Method java/lang/StringBuilder.append:(Ljava/lang/String;)Ljava/lang/StringBuilder;
     104: bipush        39
     106: invokevirtual #23                 // Method java/lang/StringBuilder.append:(C)Ljava/lang/StringBuilder;
     109: ldc           #29                 // String }
     111: invokevirtual #18                 // Method java/lang/StringBuilder.append:(Ljava/lang/String;)Ljava/lang/StringBuilder;
     114: aload_0
     115: invokespecial #30                 // Method java/lang/Object.toString:()Ljava/lang/String;
     118: invokevirtual #18                 // Method java/lang/StringBuilder.append:(Ljava/lang/String;)Ljava/lang/StringBuilder;
     121: invokevirtual #19                 // Method java/lang/StringBuilder.toString:()Ljava/lang/String;
     124: areturn
}
