Compiled from "SubscriberMetadataIdentifier.java"
public class org.apache.dubbo.metadata.report.identifier.SubscriberMetadataIdentifier extends org.apache.dubbo.metadata.report.identifier.BaseApplicationMetadataIdentifier implements org.apache.dubbo.metadata.report.identifier.BaseMetadataIdentifier {
  private java.lang.String revision;

  public org.apache.dubbo.metadata.report.identifier.SubscriberMetadataIdentifier();
    Code:
       0: aload_0
       1: invokespecial #2                  // Method org/apache/dubbo/metadata/report/identifier/BaseApplicationMetadataIdentifier."<init>":()V
       4: return

  public org.apache.dubbo.metadata.report.identifier.SubscriberMetadataIdentifier(java.lang.String, java.lang.String);
    Code:
       0: aload_0
       1: invokespecial #2                  // Method org/apache/dubbo/metadata/report/identifier/BaseApplicationMetadataIdentifier."<init>":()V
       4: aload_0
       5: aload_1
       6: putfield      #3                  // Field application:Ljava/lang/String;
       9: aload_0
      10: aload_2
      11: putfield      #4                  // Field revision:Ljava/lang/String;
      14: return

  public org.apache.dubbo.metadata.report.identifier.SubscriberMetadataIdentifier(org.apache.dubbo.common.URL);
    Code:
       0: aload_0
       1: invokespecial #2                  // Method org/apache/dubbo/metadata/report/identifier/BaseApplicationMetadataIdentifier."<init>":()V
       4: aload_0
       5: aload_1
       6: ldc           #5                  // String
       8: invokevirtual #6                  // Method org/apache/dubbo/common/URL.getApplication:(Ljava/lang/String;)Ljava/lang/String;
      11: putfield      #3                  // Field application:Ljava/lang/String;
      14: aload_0
      15: aload_1
      16: ldc           #7                  // String revision
      18: ldc           #5                  // String
      20: invokevirtual #8                  // Method org/apache/dubbo/common/URL.getParameter:(Ljava/lang/String;Ljava/lang/String;)Ljava/lang/String;
      23: putfield      #4                  // Field revision:Ljava/lang/String;
      26: return

  public java.lang.String getUniqueKey(org.apache.dubbo.metadata.report.identifier.KeyTypeEnum);
    Code:
       0: aload_0
       1: aload_1
       2: iconst_1
       3: anewarray     #9                  // class java/lang/String
       6: dup
       7: iconst_0
       8: aload_0
       9: getfield      #4                  // Field revision:Ljava/lang/String;
      12: aastore
      13: invokespecial #10                 // Method org/apache/dubbo/metadata/report/identifier/BaseApplicationMetadataIdentifier.getUniqueKey:(Lorg/apache/dubbo/metadata/report/identifier/KeyTypeEnum;[Ljava/lang/String;)Ljava/lang/String;
      16: areturn

  public java.lang.String getIdentifierKey();
    Code:
       0: aload_0
       1: iconst_1
       2: anewarray     #9                  // class java/lang/String
       5: dup
       6: iconst_0
       7: aload_0
       8: getfield      #4                  // Field revision:Ljava/lang/String;
      11: aastore
      12: invokespecial #11                 // Method org/apache/dubbo/metadata/report/identifier/BaseApplicationMetadataIdentifier.getIdentifierKey:([Ljava/lang/String;)Ljava/lang/String;
      15: areturn

  public java.lang.String getApplication();
    Code:
       0: aload_0
       1: getfield      #3                  // Field application:Ljava/lang/String;
       4: areturn

  public void setApplication(java.lang.String);
    Code:
       0: aload_0
       1: aload_1
       2: putfield      #3                  // Field application:Ljava/lang/String;
       5: return

  public java.lang.String getRevision();
    Code:
       0: aload_0
       1: getfield      #4                  // Field revision:Ljava/lang/String;
       4: areturn

  public void setRevision(java.lang.String);
    Code:
       0: aload_0
       1: aload_1
       2: putfield      #4                  // Field revision:Ljava/lang/String;
       5: return
}
