Compiled from "ParamMatch.java"
public class org.apache.dubbo.rpc.cluster.router.tag.model.ParamMatch {
  private java.lang.String key;

  private org.apache.dubbo.rpc.cluster.router.mesh.rule.virtualservice.match.StringMatch value;

  public org.apache.dubbo.rpc.cluster.router.tag.model.ParamMatch();
    Code:
       0: aload_0
       1: invokespecial #1                  // Method java/lang/Object."<init>":()V
       4: return

  public java.lang.String getKey();
    Code:
       0: aload_0
       1: getfield      #2                  // Field key:Ljava/lang/String;
       4: areturn

  public void setKey(java.lang.String);
    Code:
       0: aload_0
       1: aload_1
       2: putfield      #2                  // Field key:Ljava/lang/String;
       5: return

  public org.apache.dubbo.rpc.cluster.router.mesh.rule.virtualservice.match.StringMatch getValue();
    Code:
       0: aload_0
       1: getfield      #3                  // Field value:Lorg/apache/dubbo/rpc/cluster/router/mesh/rule/virtualservice/match/StringMatch;
       4: areturn

  public void setValue(org.apache.dubbo.rpc.cluster.router.mesh.rule.virtualservice.match.StringMatch);
    Code:
       0: aload_0
       1: aload_1
       2: putfield      #3                  // Field value:Lorg/apache/dubbo/rpc/cluster/router/mesh/rule/virtualservice/match/StringMatch;
       5: return

  public boolean isMatch(java.lang.String);
    Code:
       0: aload_0
       1: invokevirtual #4                  // Method getValue:()Lorg/apache/dubbo/rpc/cluster/router/mesh/rule/virtualservice/match/StringMatch;
       4: ifnull        20
       7: aload_1
       8: ifnull        20
      11: aload_0
      12: invokevirtual #4                  // Method getValue:()Lorg/apache/dubbo/rpc/cluster/router/mesh/rule/virtualservice/match/StringMatch;
      15: aload_1
      16: invokevirtual #5                  // Method org/apache/dubbo/rpc/cluster/router/mesh/rule/virtualservice/match/StringMatch.isMatch:(Ljava/lang/String;)Z
      19: ireturn
      20: iconst_0
      21: ireturn
}
