Compiled from "AppStateRouterFactory.java"
public class org.apache.dubbo.rpc.cluster.router.condition.config.AppStateRouterFactory implements org.apache.dubbo.rpc.cluster.router.state.StateRouterFactory {
  public static final java.lang.String NAME;

  private volatile org.apache.dubbo.rpc.cluster.router.state.StateRouter router;

  public org.apache.dubbo.rpc.cluster.router.condition.config.AppStateRouterFactory();
    Code:
       0: aload_0
       1: invokespecial #1                  // Method java/lang/Object."<init>":()V
       4: return

  public <T> org.apache.dubbo.rpc.cluster.router.state.StateRouter<T> getRouter(java.lang.Class<T>, org.apache.dubbo.common.URL);
    Code:
       0: aload_0
       1: getfield      #2                  // Field router:Lorg/apache/dubbo/rpc/cluster/router/state/StateRouter;
       4: ifnull        12
       7: aload_0
       8: getfield      #2                  // Field router:Lorg/apache/dubbo/rpc/cluster/router/state/StateRouter;
      11: areturn
      12: aload_0
      13: dup
      14: astore_3
      15: monitorenter
      16: aload_0
      17: getfield      #2                  // Field router:Lorg/apache/dubbo/rpc/cluster/router/state/StateRouter;
      20: ifnonnull     32
      23: aload_0
      24: aload_0
      25: aload_2
      26: invokespecial #3                  // Method createRouter:(Lorg/apache/dubbo/common/URL;)Lorg/apache/dubbo/rpc/cluster/router/state/StateRouter;
      29: putfield      #2                  // Field router:Lorg/apache/dubbo/rpc/cluster/router/state/StateRouter;
      32: aload_3
      33: monitorexit
      34: goto          44
      37: astore        4
      39: aload_3
      40: monitorexit
      41: aload         4
      43: athrow
      44: aload_0
      45: getfield      #2                  // Field router:Lorg/apache/dubbo/rpc/cluster/router/state/StateRouter;
      48: areturn
    Exception table:
       from    to  target type
          16    34    37   any
          37    41    37   any

  private <T> org.apache.dubbo.rpc.cluster.router.state.StateRouter<T> createRouter(org.apache.dubbo.common.URL);
    Code:
       0: new           #4                  // class org/apache/dubbo/rpc/cluster/router/condition/config/AppStateRouter
       3: dup
       4: aload_1
       5: invokespecial #5                  // Method org/apache/dubbo/rpc/cluster/router/condition/config/AppStateRouter."<init>":(Lorg/apache/dubbo/common/URL;)V
       8: areturn
}
