Compiled from "ProviderAppStateRouter.java"
public class org.apache.dubbo.rpc.cluster.router.condition.config.ProviderAppStateRouter<T> extends org.apache.dubbo.rpc.cluster.router.condition.config.ListenableStateRouter<T> {
  private static final org.apache.dubbo.common.logger.ErrorTypeAwareLogger logger;

  public static final java.lang.String NAME;

  private java.lang.String application;

  private final java.lang.String currentApplication;

  public org.apache.dubbo.rpc.cluster.router.condition.config.ProviderAppStateRouter(org.apache.dubbo.common.URL);
    Code:
       0: aload_0
       1: aload_1
       2: aload_1
       3: invokevirtual #2                  // Method org/apache/dubbo/common/URL.getApplication:()Ljava/lang/String;
       6: invokespecial #3                  // Method org/apache/dubbo/rpc/cluster/router/condition/config/ListenableStateRouter."<init>":(Lorg/apache/dubbo/common/URL;Ljava/lang/String;)V
       9: aload_0
      10: aload_1
      11: invokevirtual #2                  // Method org/apache/dubbo/common/URL.getApplication:()Ljava/lang/String;
      14: putfield      #4                  // Field currentApplication:Ljava/lang/String;
      17: return

  public void notify(org.apache.dubbo.rpc.cluster.router.state.BitList<org.apache.dubbo.rpc.Invoker<T>>);
    Code:
       0: aload_1
       1: invokestatic  #5                  // Method org/apache/dubbo/common/utils/CollectionUtils.isEmpty:(Ljava/util/Collection;)Z
       4: ifeq          8
       7: return
       8: aload_1
       9: iconst_0
      10: invokevirtual #6                  // Method org/apache/dubbo/rpc/cluster/router/state/BitList.get:(I)Ljava/lang/Object;
      13: checkcast     #7                  // class org/apache/dubbo/rpc/Invoker
      16: astore_2
      17: aload_2
      18: invokeinterface #8,  1            // InterfaceMethod org/apache/dubbo/rpc/Invoker.getUrl:()Lorg/apache/dubbo/common/URL;
      23: astore_3
      24: aload_3
      25: invokevirtual #9                  // Method org/apache/dubbo/common/URL.getRemoteApplication:()Ljava/lang/String;
      28: astore        4
      30: aload         4
      32: invokestatic  #10                 // Method org/apache/dubbo/common/utils/StringUtils.isEmpty:(Ljava/lang/String;)Z
      35: ifne          50
      38: aload         4
      40: aload_0
      41: getfield      #4                  // Field currentApplication:Ljava/lang/String;
      44: invokevirtual #11                 // Method java/lang/String.equals:(Ljava/lang/Object;)Z
      47: ifeq          67
      50: getstatic     #12                 // Field logger:Lorg/apache/dubbo/common/logger/ErrorTypeAwareLogger;
      53: ldc           #13                 // String 2-12
      55: ldc           #14                 // String condition router get providerApplication is empty, will not subscribe to provider app rules.
      57: ldc           #15                 // String
      59: ldc           #15                 // String
      61: invokeinterface #16,  5           // InterfaceMethod org/apache/dubbo/common/logger/ErrorTypeAwareLogger.warn:(Ljava/lang/String;Ljava/lang/String;Ljava/lang/String;Ljava/lang/String;)V
      66: return
      67: aload_0
      68: dup
      69: astore        5
      71: monitorenter
      72: aload         4
      74: aload_0
      75: getfield      #17                 // Field application:Ljava/lang/String;
      78: invokevirtual #11                 // Method java/lang/String.equals:(Ljava/lang/Object;)Z
      81: ifne          206
      84: aload_0
      85: getfield      #17                 // Field application:Ljava/lang/String;
      88: invokestatic  #18                 // Method org/apache/dubbo/common/utils/StringUtils.isNotEmpty:(Ljava/lang/String;)Z
      91: ifeq          126
      94: aload_0
      95: invokevirtual #19                 // Method getRuleRepository:()Lorg/apache/dubbo/rpc/cluster/governance/GovernanceRuleRepository;
      98: new           #20                 // class java/lang/StringBuilder
     101: dup
     102: invokespecial #21                 // Method java/lang/StringBuilder."<init>":()V
     105: aload_0
     106: getfield      #17                 // Field application:Ljava/lang/String;
     109: invokevirtual #22                 // Method java/lang/StringBuilder.append:(Ljava/lang/String;)Ljava/lang/StringBuilder;
     112: ldc           #24                 // String .condition-router
     114: invokevirtual #22                 // Method java/lang/StringBuilder.append:(Ljava/lang/String;)Ljava/lang/StringBuilder;
     117: invokevirtual #25                 // Method java/lang/StringBuilder.toString:()Ljava/lang/String;
     120: aload_0
     121: invokeinterface #26,  3           // InterfaceMethod org/apache/dubbo/rpc/cluster/governance/GovernanceRuleRepository.removeListener:(Ljava/lang/String;Lorg/apache/dubbo/common/config/configcenter/ConfigurationListener;)V
     126: new           #20                 // class java/lang/StringBuilder
     129: dup
     130: invokespecial #21                 // Method java/lang/StringBuilder."<init>":()V
     133: aload         4
     135: invokevirtual #22                 // Method java/lang/StringBuilder.append:(Ljava/lang/String;)Ljava/lang/StringBuilder;
     138: ldc           #24                 // String .condition-router
     140: invokevirtual #22                 // Method java/lang/StringBuilder.append:(Ljava/lang/String;)Ljava/lang/StringBuilder;
     143: invokevirtual #25                 // Method java/lang/StringBuilder.toString:()Ljava/lang/String;
     146: astore        6
     148: aload_0
     149: invokevirtual #19                 // Method getRuleRepository:()Lorg/apache/dubbo/rpc/cluster/governance/GovernanceRuleRepository;
     152: aload         6
     154: aload_0
     155: invokeinterface #27,  3           // InterfaceMethod org/apache/dubbo/rpc/cluster/governance/GovernanceRuleRepository.addListener:(Ljava/lang/String;Lorg/apache/dubbo/common/config/configcenter/ConfigurationListener;)V
     160: aload_0
     161: aload         4
     163: putfield      #17                 // Field application:Ljava/lang/String;
     166: aload_0
     167: invokevirtual #19                 // Method getRuleRepository:()Lorg/apache/dubbo/rpc/cluster/governance/GovernanceRuleRepository;
     170: aload         6
     172: ldc           #29                 // String dubbo
     174: invokeinterface #30,  3           // InterfaceMethod org/apache/dubbo/rpc/cluster/governance/GovernanceRuleRepository.getRule:(Ljava/lang/String;Ljava/lang/String;)Ljava/lang/String;
     179: astore        7
     181: aload         7
     183: invokestatic  #18                 // Method org/apache/dubbo/common/utils/StringUtils.isNotEmpty:(Ljava/lang/String;)Z
     186: ifeq          206
     189: aload_0
     190: new           #31                 // class org/apache/dubbo/common/config/configcenter/ConfigChangedEvent
     193: dup
     194: aload         6
     196: ldc           #29                 // String dubbo
     198: aload         7
     200: invokespecial #32                 // Method org/apache/dubbo/common/config/configcenter/ConfigChangedEvent."<init>":(Ljava/lang/String;Ljava/lang/String;Ljava/lang/String;)V
     203: invokevirtual #33                 // Method process:(Lorg/apache/dubbo/common/config/configcenter/ConfigChangedEvent;)V
     206: aload         5
     208: monitorexit
     209: goto          220
     212: astore        8
     214: aload         5
     216: monitorexit
     217: aload         8
     219: athrow
     220: return
    Exception table:
       from    to  target type
          72   209   212   any
         212   217   212   any

  static {};
    Code:
       0: ldc           #23                 // class org/apache/dubbo/rpc/cluster/router/condition/config/ListenableStateRouter
       2: invokestatic  #34                 // Method org/apache/dubbo/common/logger/LoggerFactory.getErrorTypeAwareLogger:(Ljava/lang/Class;)Lorg/apache/dubbo/common/logger/ErrorTypeAwareLogger;
       5: putstatic     #12                 // Field logger:Lorg/apache/dubbo/common/logger/ErrorTypeAwareLogger;
       8: return
}
