Compiled from "ProviderAppStateRouterFactory.java"
public class org.apache.dubbo.rpc.cluster.router.condition.config.ProviderAppStateRouterFactory extends org.apache.dubbo.rpc.cluster.router.state.CacheableStateRouterFactory {
  public static final java.lang.String NAME;

  public org.apache.dubbo.rpc.cluster.router.condition.config.ProviderAppStateRouterFactory();
    Code:
       0: aload_0
       1: invokespecial #1                  // Method org/apache/dubbo/rpc/cluster/router/state/CacheableStateRouterFactory."<init>":()V
       4: return

  protected <T> org.apache.dubbo.rpc.cluster.router.state.StateRouter<T> createRouter(java.lang.Class<T>, org.apache.dubbo.common.URL);
    Code:
       0: new           #2                  // class org/apache/dubbo/rpc/cluster/router/condition/config/ProviderAppStateRouter
       3: dup
       4: aload_2
       5: invokespecial #3                  // Method org/apache/dubbo/rpc/cluster/router/condition/config/ProviderAppStateRouter."<init>":(Lorg/apache/dubbo/common/URL;)V
       8: areturn
}
