Compiled from "AbstractChannelBuffer.java"
public abstract class org.apache.dubbo.remoting.buffer.AbstractChannelBuffer implements org.apache.dubbo.remoting.buffer.ChannelBuffer {
  private int readerIndex;

  private int writerIndex;

  private int markedReaderIndex;

  private int markedWriterIndex;

  public org.apache.dubbo.remoting.buffer.AbstractChannelBuffer();
    Code:
       0: aload_0
       1: invokespecial #1                  // Method java/lang/Object."<init>":()V
       4: return

  public int readerIndex();
    Code:
       0: aload_0
       1: getfield      #2                  // Field readerIndex:I
       4: ireturn

  public void readerIndex(int);
    Code:
       0: iload_1
       1: iflt          12
       4: iload_1
       5: aload_0
       6: getfield      #3                  // Field writerIndex:I
       9: if_icmple     20
      12: new           #4                  // class java/lang/IndexOutOfBoundsException
      15: dup
      16: invokespecial #5                  // Method java/lang/IndexOutOfBoundsException."<init>":()V
      19: athrow
      20: aload_0
      21: iload_1
      22: putfield      #2                  // Field readerIndex:I
      25: return

  public int writerIndex();
    Code:
       0: aload_0
       1: getfield      #3                  // Field writerIndex:I
       4: ireturn

  public void writerIndex(int);
    Code:
       0: iload_1
       1: aload_0
       2: getfield      #2                  // Field readerIndex:I
       5: if_icmplt     16
       8: iload_1
       9: aload_0
      10: invokevirtual #6                  // Method capacity:()I
      13: if_icmple     24
      16: new           #4                  // class java/lang/IndexOutOfBoundsException
      19: dup
      20: invokespecial #5                  // Method java/lang/IndexOutOfBoundsException."<init>":()V
      23: athrow
      24: aload_0
      25: iload_1
      26: putfield      #3                  // Field writerIndex:I
      29: return

  public void setIndex(int, int);
    Code:
       0: iload_1
       1: iflt          17
       4: iload_1
       5: iload_2
       6: if_icmpgt     17
       9: iload_2
      10: aload_0
      11: invokevirtual #6                  // Method capacity:()I
      14: if_icmple     25
      17: new           #4                  // class java/lang/IndexOutOfBoundsException
      20: dup
      21: invokespecial #5                  // Method java/lang/IndexOutOfBoundsException."<init>":()V
      24: athrow
      25: aload_0
      26: iload_1
      27: putfield      #2                  // Field readerIndex:I
      30: aload_0
      31: iload_2
      32: putfield      #3                  // Field writerIndex:I
      35: return

  public void clear();
    Code:
       0: aload_0
       1: aload_0
       2: iconst_0
       3: dup_x1
       4: putfield      #3                  // Field writerIndex:I
       7: putfield      #2                  // Field readerIndex:I
      10: return

  public boolean readable();
    Code:
       0: aload_0
       1: invokevirtual #7                  // Method readableBytes:()I
       4: ifle          11
       7: iconst_1
       8: goto          12
      11: iconst_0
      12: ireturn

  public boolean writable();
    Code:
       0: aload_0
       1: invokevirtual #8                  // Method writableBytes:()I
       4: ifle          11
       7: iconst_1
       8: goto          12
      11: iconst_0
      12: ireturn

  public int readableBytes();
    Code:
       0: aload_0
       1: getfield      #3                  // Field writerIndex:I
       4: aload_0
       5: getfield      #2                  // Field readerIndex:I
       8: isub
       9: ireturn

  public int writableBytes();
    Code:
       0: aload_0
       1: invokevirtual #6                  // Method capacity:()I
       4: aload_0
       5: getfield      #3                  // Field writerIndex:I
       8: isub
       9: ireturn

  public void markReaderIndex();
    Code:
       0: aload_0
       1: aload_0
       2: getfield      #2                  // Field readerIndex:I
       5: putfield      #9                  // Field markedReaderIndex:I
       8: return

  public void resetReaderIndex();
    Code:
       0: aload_0
       1: aload_0
       2: getfield      #9                  // Field markedReaderIndex:I
       5: invokevirtual #10                 // Method readerIndex:(I)V
       8: return

  public void markWriterIndex();
    Code:
       0: aload_0
       1: aload_0
       2: getfield      #3                  // Field writerIndex:I
       5: putfield      #11                 // Field markedWriterIndex:I
       8: return

  public void resetWriterIndex();
    Code:
       0: aload_0
       1: aload_0
       2: getfield      #11                 // Field markedWriterIndex:I
       5: putfield      #3                  // Field writerIndex:I
       8: return

  public void discardReadBytes();
    Code:
       0: aload_0
       1: getfield      #2                  // Field readerIndex:I
       4: ifne          8
       7: return
       8: aload_0
       9: iconst_0
      10: aload_0
      11: aload_0
      12: getfield      #2                  // Field readerIndex:I
      15: aload_0
      16: getfield      #3                  // Field writerIndex:I
      19: aload_0
      20: getfield      #2                  // Field readerIndex:I
      23: isub
      24: invokevirtual #12                 // Method setBytes:(ILorg/apache/dubbo/remoting/buffer/ChannelBuffer;II)V
      27: aload_0
      28: dup
      29: getfield      #3                  // Field writerIndex:I
      32: aload_0
      33: getfield      #2                  // Field readerIndex:I
      36: isub
      37: putfield      #3                  // Field writerIndex:I
      40: aload_0
      41: aload_0
      42: getfield      #9                  // Field markedReaderIndex:I
      45: aload_0
      46: getfield      #2                  // Field readerIndex:I
      49: isub
      50: iconst_0
      51: invokestatic  #13                 // Method java/lang/Math.max:(II)I
      54: putfield      #9                  // Field markedReaderIndex:I
      57: aload_0
      58: aload_0
      59: getfield      #11                 // Field markedWriterIndex:I
      62: aload_0
      63: getfield      #2                  // Field readerIndex:I
      66: isub
      67: iconst_0
      68: invokestatic  #13                 // Method java/lang/Math.max:(II)I
      71: putfield      #11                 // Field markedWriterIndex:I
      74: aload_0
      75: iconst_0
      76: putfield      #2                  // Field readerIndex:I
      79: return

  public void ensureWritableBytes(int);
    Code:
       0: iload_1
       1: aload_0
       2: invokevirtual #8                  // Method writableBytes:()I
       5: if_icmple     16
       8: new           #4                  // class java/lang/IndexOutOfBoundsException
      11: dup
      12: invokespecial #5                  // Method java/lang/IndexOutOfBoundsException."<init>":()V
      15: athrow
      16: return

  public void getBytes(int, byte[]);
    Code:
       0: aload_0
       1: iload_1
       2: aload_2
       3: iconst_0
       4: aload_2
       5: arraylength
       6: invokevirtual #14                 // Method getBytes:(I[BII)V
       9: return

  public void getBytes(int, org.apache.dubbo.remoting.buffer.ChannelBuffer);
    Code:
       0: aload_0
       1: iload_1
       2: aload_2
       3: aload_2
       4: invokeinterface #15,  1           // InterfaceMethod org/apache/dubbo/remoting/buffer/ChannelBuffer.writableBytes:()I
       9: invokevirtual #16                 // Method getBytes:(ILorg/apache/dubbo/remoting/buffer/ChannelBuffer;I)V
      12: return

  public void getBytes(int, org.apache.dubbo.remoting.buffer.ChannelBuffer, int);
    Code:
       0: iload_3
       1: aload_2
       2: invokeinterface #15,  1           // InterfaceMethod org/apache/dubbo/remoting/buffer/ChannelBuffer.writableBytes:()I
       7: if_icmple     18
      10: new           #4                  // class java/lang/IndexOutOfBoundsException
      13: dup
      14: invokespecial #5                  // Method java/lang/IndexOutOfBoundsException."<init>":()V
      17: athrow
      18: aload_0
      19: iload_1
      20: aload_2
      21: aload_2
      22: invokeinterface #17,  1           // InterfaceMethod org/apache/dubbo/remoting/buffer/ChannelBuffer.writerIndex:()I
      27: iload_3
      28: invokevirtual #18                 // Method getBytes:(ILorg/apache/dubbo/remoting/buffer/ChannelBuffer;II)V
      31: aload_2
      32: aload_2
      33: invokeinterface #17,  1           // InterfaceMethod org/apache/dubbo/remoting/buffer/ChannelBuffer.writerIndex:()I
      38: iload_3
      39: iadd
      40: invokeinterface #19,  2           // InterfaceMethod org/apache/dubbo/remoting/buffer/ChannelBuffer.writerIndex:(I)V
      45: return

  public void setBytes(int, byte[]);
    Code:
       0: aload_0
       1: iload_1
       2: aload_2
       3: iconst_0
       4: aload_2
       5: arraylength
       6: invokevirtual #20                 // Method setBytes:(I[BII)V
       9: return

  public void setBytes(int, org.apache.dubbo.remoting.buffer.ChannelBuffer);
    Code:
       0: aload_0
       1: iload_1
       2: aload_2
       3: aload_2
       4: invokeinterface #21,  1           // InterfaceMethod org/apache/dubbo/remoting/buffer/ChannelBuffer.readableBytes:()I
       9: invokevirtual #22                 // Method setBytes:(ILorg/apache/dubbo/remoting/buffer/ChannelBuffer;I)V
      12: return

  public void setBytes(int, org.apache.dubbo.remoting.buffer.ChannelBuffer, int);
    Code:
       0: iload_3
       1: aload_2
       2: invokeinterface #21,  1           // InterfaceMethod org/apache/dubbo/remoting/buffer/ChannelBuffer.readableBytes:()I
       7: if_icmple     18
      10: new           #4                  // class java/lang/IndexOutOfBoundsException
      13: dup
      14: invokespecial #5                  // Method java/lang/IndexOutOfBoundsException."<init>":()V
      17: athrow
      18: aload_0
      19: iload_1
      20: aload_2
      21: aload_2
      22: invokeinterface #23,  1           // InterfaceMethod org/apache/dubbo/remoting/buffer/ChannelBuffer.readerIndex:()I
      27: iload_3
      28: invokevirtual #12                 // Method setBytes:(ILorg/apache/dubbo/remoting/buffer/ChannelBuffer;II)V
      31: aload_2
      32: aload_2
      33: invokeinterface #23,  1           // InterfaceMethod org/apache/dubbo/remoting/buffer/ChannelBuffer.readerIndex:()I
      38: iload_3
      39: iadd
      40: invokeinterface #24,  2           // InterfaceMethod org/apache/dubbo/remoting/buffer/ChannelBuffer.readerIndex:(I)V
      45: return

  public byte readByte();
    Code:
       0: aload_0
       1: getfield      #2                  // Field readerIndex:I
       4: aload_0
       5: getfield      #3                  // Field writerIndex:I
       8: if_icmpne     19
      11: new           #4                  // class java/lang/IndexOutOfBoundsException
      14: dup
      15: invokespecial #5                  // Method java/lang/IndexOutOfBoundsException."<init>":()V
      18: athrow
      19: aload_0
      20: aload_0
      21: dup
      22: getfield      #2                  // Field readerIndex:I
      25: dup_x1
      26: iconst_1
      27: iadd
      28: putfield      #2                  // Field readerIndex:I
      31: invokevirtual #25                 // Method getByte:(I)B
      34: ireturn

  public org.apache.dubbo.remoting.buffer.ChannelBuffer readBytes(int);
    Code:
       0: aload_0
       1: iload_1
       2: invokevirtual #26                 // Method checkReadableBytes:(I)V
       5: iload_1
       6: ifne          13
       9: getstatic     #27                 // Field org/apache/dubbo/remoting/buffer/ChannelBuffers.EMPTY_BUFFER:Lorg/apache/dubbo/remoting/buffer/ChannelBuffer;
      12: areturn
      13: aload_0
      14: invokevirtual #28                 // Method factory:()Lorg/apache/dubbo/remoting/buffer/ChannelBufferFactory;
      17: iload_1
      18: invokeinterface #29,  2           // InterfaceMethod org/apache/dubbo/remoting/buffer/ChannelBufferFactory.getBuffer:(I)Lorg/apache/dubbo/remoting/buffer/ChannelBuffer;
      23: astore_2
      24: aload_2
      25: aload_0
      26: aload_0
      27: getfield      #2                  // Field readerIndex:I
      30: iload_1
      31: invokeinterface #30,  4           // InterfaceMethod org/apache/dubbo/remoting/buffer/ChannelBuffer.writeBytes:(Lorg/apache/dubbo/remoting/buffer/ChannelBuffer;II)V
      36: aload_0
      37: dup
      38: getfield      #2                  // Field readerIndex:I
      41: iload_1
      42: iadd
      43: putfield      #2                  // Field readerIndex:I
      46: aload_2
      47: areturn

  public void readBytes(byte[], int, int);
    Code:
       0: aload_0
       1: iload_3
       2: invokevirtual #26                 // Method checkReadableBytes:(I)V
       5: aload_0
       6: aload_0
       7: getfield      #2                  // Field readerIndex:I
      10: aload_1
      11: iload_2
      12: iload_3
      13: invokevirtual #14                 // Method getBytes:(I[BII)V
      16: aload_0
      17: dup
      18: getfield      #2                  // Field readerIndex:I
      21: iload_3
      22: iadd
      23: putfield      #2                  // Field readerIndex:I
      26: return

  public void readBytes(byte[]);
    Code:
       0: aload_0
       1: aload_1
       2: iconst_0
       3: aload_1
       4: arraylength
       5: invokevirtual #31                 // Method readBytes:([BII)V
       8: return

  public void readBytes(org.apache.dubbo.remoting.buffer.ChannelBuffer);
    Code:
       0: aload_0
       1: aload_1
       2: aload_1
       3: invokeinterface #15,  1           // InterfaceMethod org/apache/dubbo/remoting/buffer/ChannelBuffer.writableBytes:()I
       8: invokevirtual #32                 // Method readBytes:(Lorg/apache/dubbo/remoting/buffer/ChannelBuffer;I)V
      11: return

  public void readBytes(org.apache.dubbo.remoting.buffer.ChannelBuffer, int);
    Code:
       0: iload_2
       1: aload_1
       2: invokeinterface #15,  1           // InterfaceMethod org/apache/dubbo/remoting/buffer/ChannelBuffer.writableBytes:()I
       7: if_icmple     18
      10: new           #4                  // class java/lang/IndexOutOfBoundsException
      13: dup
      14: invokespecial #5                  // Method java/lang/IndexOutOfBoundsException."<init>":()V
      17: athrow
      18: aload_0
      19: aload_1
      20: aload_1
      21: invokeinterface #17,  1           // InterfaceMethod org/apache/dubbo/remoting/buffer/ChannelBuffer.writerIndex:()I
      26: iload_2
      27: invokevirtual #33                 // Method readBytes:(Lorg/apache/dubbo/remoting/buffer/ChannelBuffer;II)V
      30: aload_1
      31: aload_1
      32: invokeinterface #17,  1           // InterfaceMethod org/apache/dubbo/remoting/buffer/ChannelBuffer.writerIndex:()I
      37: iload_2
      38: iadd
      39: invokeinterface #19,  2           // InterfaceMethod org/apache/dubbo/remoting/buffer/ChannelBuffer.writerIndex:(I)V
      44: return

  public void readBytes(org.apache.dubbo.remoting.buffer.ChannelBuffer, int, int);
    Code:
       0: aload_0
       1: iload_3
       2: invokevirtual #26                 // Method checkReadableBytes:(I)V
       5: aload_0
       6: aload_0
       7: getfield      #2                  // Field readerIndex:I
      10: aload_1
      11: iload_2
      12: iload_3
      13: invokevirtual #18                 // Method getBytes:(ILorg/apache/dubbo/remoting/buffer/ChannelBuffer;II)V
      16: aload_0
      17: dup
      18: getfield      #2                  // Field readerIndex:I
      21: iload_3
      22: iadd
      23: putfield      #2                  // Field readerIndex:I
      26: return

  public void readBytes(java.nio.ByteBuffer);
    Code:
       0: aload_1
       1: invokevirtual #34                 // Method java/nio/ByteBuffer.remaining:()I
       4: istore_2
       5: aload_0
       6: iload_2
       7: invokevirtual #26                 // Method checkReadableBytes:(I)V
      10: aload_0
      11: aload_0
      12: getfield      #2                  // Field readerIndex:I
      15: aload_1
      16: invokevirtual #35                 // Method getBytes:(ILjava/nio/ByteBuffer;)V
      19: aload_0
      20: dup
      21: getfield      #2                  // Field readerIndex:I
      24: iload_2
      25: iadd
      26: putfield      #2                  // Field readerIndex:I
      29: return

  public void readBytes(java.io.OutputStream, int) throws java.io.IOException;
    Code:
       0: aload_0
       1: iload_2
       2: invokevirtual #26                 // Method checkReadableBytes:(I)V
       5: aload_0
       6: aload_0
       7: getfield      #2                  // Field readerIndex:I
      10: aload_1
      11: iload_2
      12: invokevirtual #36                 // Method getBytes:(ILjava/io/OutputStream;I)V
      15: aload_0
      16: dup
      17: getfield      #2                  // Field readerIndex:I
      20: iload_2
      21: iadd
      22: putfield      #2                  // Field readerIndex:I
      25: return

  public void skipBytes(int);
    Code:
       0: aload_0
       1: getfield      #2                  // Field readerIndex:I
       4: iload_1
       5: iadd
       6: istore_2
       7: iload_2
       8: aload_0
       9: getfield      #3                  // Field writerIndex:I
      12: if_icmple     23
      15: new           #4                  // class java/lang/IndexOutOfBoundsException
      18: dup
      19: invokespecial #5                  // Method java/lang/IndexOutOfBoundsException."<init>":()V
      22: athrow
      23: aload_0
      24: iload_2
      25: putfield      #2                  // Field readerIndex:I
      28: return

  public void writeByte(int);
    Code:
       0: aload_0
       1: aload_0
       2: dup
       3: getfield      #3                  // Field writerIndex:I
       6: dup_x1
       7: iconst_1
       8: iadd
       9: putfield      #3                  // Field writerIndex:I
      12: iload_1
      13: invokevirtual #37                 // Method setByte:(II)V
      16: return

  public void writeBytes(byte[], int, int);
    Code:
       0: aload_0
       1: aload_0
       2: getfield      #3                  // Field writerIndex:I
       5: aload_1
       6: iload_2
       7: iload_3
       8: invokevirtual #20                 // Method setBytes:(I[BII)V
      11: aload_0
      12: dup
      13: getfield      #3                  // Field writerIndex:I
      16: iload_3
      17: iadd
      18: putfield      #3                  // Field writerIndex:I
      21: return

  public void writeBytes(byte[]);
    Code:
       0: aload_0
       1: aload_1
       2: iconst_0
       3: aload_1
       4: arraylength
       5: invokevirtual #38                 // Method writeBytes:([BII)V
       8: return

  public void writeBytes(org.apache.dubbo.remoting.buffer.ChannelBuffer);
    Code:
       0: aload_0
       1: aload_1
       2: aload_1
       3: invokeinterface #21,  1           // InterfaceMethod org/apache/dubbo/remoting/buffer/ChannelBuffer.readableBytes:()I
       8: invokevirtual #39                 // Method writeBytes:(Lorg/apache/dubbo/remoting/buffer/ChannelBuffer;I)V
      11: return

  public void writeBytes(org.apache.dubbo.remoting.buffer.ChannelBuffer, int);
    Code:
       0: iload_2
       1: aload_1
       2: invokeinterface #21,  1           // InterfaceMethod org/apache/dubbo/remoting/buffer/ChannelBuffer.readableBytes:()I
       7: if_icmple     18
      10: new           #4                  // class java/lang/IndexOutOfBoundsException
      13: dup
      14: invokespecial #5                  // Method java/lang/IndexOutOfBoundsException."<init>":()V
      17: athrow
      18: aload_0
      19: aload_1
      20: aload_1
      21: invokeinterface #23,  1           // InterfaceMethod org/apache/dubbo/remoting/buffer/ChannelBuffer.readerIndex:()I
      26: iload_2
      27: invokevirtual #40                 // Method writeBytes:(Lorg/apache/dubbo/remoting/buffer/ChannelBuffer;II)V
      30: aload_1
      31: aload_1
      32: invokeinterface #23,  1           // InterfaceMethod org/apache/dubbo/remoting/buffer/ChannelBuffer.readerIndex:()I
      37: iload_2
      38: iadd
      39: invokeinterface #24,  2           // InterfaceMethod org/apache/dubbo/remoting/buffer/ChannelBuffer.readerIndex:(I)V
      44: return

  public void writeBytes(org.apache.dubbo.remoting.buffer.ChannelBuffer, int, int);
    Code:
       0: aload_0
       1: aload_0
       2: getfield      #3                  // Field writerIndex:I
       5: aload_1
       6: iload_2
       7: iload_3
       8: invokevirtual #12                 // Method setBytes:(ILorg/apache/dubbo/remoting/buffer/ChannelBuffer;II)V
      11: aload_0
      12: dup
      13: getfield      #3                  // Field writerIndex:I
      16: iload_3
      17: iadd
      18: putfield      #3                  // Field writerIndex:I
      21: return

  public void writeBytes(java.nio.ByteBuffer);
    Code:
       0: aload_1
       1: invokevirtual #34                 // Method java/nio/ByteBuffer.remaining:()I
       4: istore_2
       5: aload_0
       6: aload_0
       7: getfield      #3                  // Field writerIndex:I
      10: aload_1
      11: invokevirtual #41                 // Method setBytes:(ILjava/nio/ByteBuffer;)V
      14: aload_0
      15: dup
      16: getfield      #3                  // Field writerIndex:I
      19: iload_2
      20: iadd
      21: putfield      #3                  // Field writerIndex:I
      24: return

  public int writeBytes(java.io.InputStream, int) throws java.io.IOException;
    Code:
       0: aload_0
       1: aload_0
       2: getfield      #3                  // Field writerIndex:I
       5: aload_1
       6: iload_2
       7: invokevirtual #42                 // Method setBytes:(ILjava/io/InputStream;I)I
      10: istore_3
      11: iload_3
      12: ifle          25
      15: aload_0
      16: dup
      17: getfield      #3                  // Field writerIndex:I
      20: iload_3
      21: iadd
      22: putfield      #3                  // Field writerIndex:I
      25: iload_3
      26: ireturn

  public org.apache.dubbo.remoting.buffer.ChannelBuffer copy();
    Code:
       0: aload_0
       1: aload_0
       2: getfield      #2                  // Field readerIndex:I
       5: aload_0
       6: invokevirtual #7                  // Method readableBytes:()I
       9: invokevirtual #43                 // Method copy:(II)Lorg/apache/dubbo/remoting/buffer/ChannelBuffer;
      12: areturn

  public java.nio.ByteBuffer toByteBuffer();
    Code:
       0: aload_0
       1: aload_0
       2: getfield      #2                  // Field readerIndex:I
       5: aload_0
       6: invokevirtual #7                  // Method readableBytes:()I
       9: invokevirtual #44                 // Method toByteBuffer:(II)Ljava/nio/ByteBuffer;
      12: areturn

  public boolean equals(java.lang.Object);
    Code:
       0: aload_1
       1: instanceof    #45                 // class org/apache/dubbo/remoting/buffer/ChannelBuffer
       4: ifeq          22
       7: aload_0
       8: aload_1
       9: checkcast     #45                 // class org/apache/dubbo/remoting/buffer/ChannelBuffer
      12: invokestatic  #46                 // Method org/apache/dubbo/remoting/buffer/ChannelBuffers.equals:(Lorg/apache/dubbo/remoting/buffer/ChannelBuffer;Lorg/apache/dubbo/remoting/buffer/ChannelBuffer;)Z
      15: ifeq          22
      18: iconst_1
      19: goto          23
      22: iconst_0
      23: ireturn

  public int hashCode();
    Code:
       0: aload_0
       1: invokestatic  #47                 // Method org/apache/dubbo/remoting/buffer/ChannelBuffers.hasCode:(Lorg/apache/dubbo/remoting/buffer/ChannelBuffer;)I
       4: ireturn

  public int compareTo(org.apache.dubbo.remoting.buffer.ChannelBuffer);
    Code:
       0: aload_0
       1: aload_1
       2: invokestatic  #48                 // Method org/apache/dubbo/remoting/buffer/ChannelBuffers.compare:(Lorg/apache/dubbo/remoting/buffer/ChannelBuffer;Lorg/apache/dubbo/remoting/buffer/ChannelBuffer;)I
       5: ireturn

  public java.lang.String toString();
    Code:
       0: new           #49                 // class java/lang/StringBuilder
       3: dup
       4: invokespecial #50                 // Method java/lang/StringBuilder."<init>":()V
       7: aload_0
       8: invokevirtual #51                 // Method java/lang/Object.getClass:()Ljava/lang/Class;
      11: invokevirtual #52                 // Method java/lang/Class.getSimpleName:()Ljava/lang/String;
      14: invokevirtual #53                 // Method java/lang/StringBuilder.append:(Ljava/lang/String;)Ljava/lang/StringBuilder;
      17: bipush        40
      19: invokevirtual #54                 // Method java/lang/StringBuilder.append:(C)Ljava/lang/StringBuilder;
      22: ldc           #55                 // String ridx=
      24: invokevirtual #53                 // Method java/lang/StringBuilder.append:(Ljava/lang/String;)Ljava/lang/StringBuilder;
      27: aload_0
      28: getfield      #2                  // Field readerIndex:I
      31: invokevirtual #56                 // Method java/lang/StringBuilder.append:(I)Ljava/lang/StringBuilder;
      34: ldc           #57                 // String , widx=
      36: invokevirtual #53                 // Method java/lang/StringBuilder.append:(Ljava/lang/String;)Ljava/lang/StringBuilder;
      39: aload_0
      40: getfield      #3                  // Field writerIndex:I
      43: invokevirtual #56                 // Method java/lang/StringBuilder.append:(I)Ljava/lang/StringBuilder;
      46: ldc           #58                 // String , cap=
      48: invokevirtual #53                 // Method java/lang/StringBuilder.append:(Ljava/lang/String;)Ljava/lang/StringBuilder;
      51: aload_0
      52: invokevirtual #6                  // Method capacity:()I
      55: invokevirtual #56                 // Method java/lang/StringBuilder.append:(I)Ljava/lang/StringBuilder;
      58: bipush        41
      60: invokevirtual #54                 // Method java/lang/StringBuilder.append:(C)Ljava/lang/StringBuilder;
      63: invokevirtual #59                 // Method java/lang/StringBuilder.toString:()Ljava/lang/String;
      66: areturn

  protected void checkReadableBytes(int);
    Code:
       0: aload_0
       1: invokevirtual #7                  // Method readableBytes:()I
       4: iload_1
       5: if_icmpge     16
       8: new           #4                  // class java/lang/IndexOutOfBoundsException
      11: dup
      12: invokespecial #5                  // Method java/lang/IndexOutOfBoundsException."<init>":()V
      15: athrow
      16: return

  public int compareTo(java.lang.Object);
    Code:
       0: aload_0
       1: aload_1
       2: checkcast     #45                 // class org/apache/dubbo/remoting/buffer/ChannelBuffer
       5: invokevirtual #60                 // Method compareTo:(Lorg/apache/dubbo/remoting/buffer/ChannelBuffer;)I
       8: ireturn
}
