Compiled from "ChannelBufferOutputStream.java"
public class org.apache.dubbo.remoting.buffer.ChannelBufferOutputStream extends java.io.OutputStream {
  private final org.apache.dubbo.remoting.buffer.ChannelBuffer buffer;

  private final int startIndex;

  public org.apache.dubbo.remoting.buffer.ChannelBufferOutputStream(org.apache.dubbo.remoting.buffer.ChannelBuffer);
    Code:
       0: aload_0
       1: invokespecial #1                  // Method java/io/OutputStream."<init>":()V
       4: aload_1
       5: ifnonnull     18
       8: new           #2                  // class java/lang/NullPointerException
      11: dup
      12: ldc           #3                  // String buffer
      14: invokespecial #4                  // Method java/lang/NullPointerException."<init>":(Ljava/lang/String;)V
      17: athrow
      18: aload_0
      19: aload_1
      20: putfield      #5                  // Field buffer:Lorg/apache/dubbo/remoting/buffer/ChannelBuffer;
      23: aload_0
      24: aload_1
      25: invokeinterface #6,  1            // InterfaceMethod org/apache/dubbo/remoting/buffer/ChannelBuffer.writerIndex:()I
      30: putfield      #7                  // Field startIndex:I
      33: return

  public int writtenBytes();
    Code:
       0: aload_0
       1: getfield      #5                  // Field buffer:Lorg/apache/dubbo/remoting/buffer/ChannelBuffer;
       4: invokeinterface #6,  1            // InterfaceMethod org/apache/dubbo/remoting/buffer/ChannelBuffer.writerIndex:()I
       9: aload_0
      10: getfield      #7                  // Field startIndex:I
      13: isub
      14: ireturn

  public void write(byte[], int, int) throws java.io.IOException;
    Code:
       0: iload_3
       1: ifne          5
       4: return
       5: aload_0
       6: getfield      #5                  // Field buffer:Lorg/apache/dubbo/remoting/buffer/ChannelBuffer;
       9: aload_1
      10: iload_2
      11: iload_3
      12: invokeinterface #8,  4            // InterfaceMethod org/apache/dubbo/remoting/buffer/ChannelBuffer.writeBytes:([BII)V
      17: return

  public void write(byte[]) throws java.io.IOException;
    Code:
       0: aload_0
       1: getfield      #5                  // Field buffer:Lorg/apache/dubbo/remoting/buffer/ChannelBuffer;
       4: aload_1
       5: invokeinterface #9,  2            // InterfaceMethod org/apache/dubbo/remoting/buffer/ChannelBuffer.writeBytes:([B)V
      10: return

  public void write(int) throws java.io.IOException;
    Code:
       0: aload_0
       1: getfield      #5                  // Field buffer:Lorg/apache/dubbo/remoting/buffer/ChannelBuffer;
       4: iload_1
       5: i2b
       6: invokeinterface #10,  2           // InterfaceMethod org/apache/dubbo/remoting/buffer/ChannelBuffer.writeByte:(I)V
      11: return

  public org.apache.dubbo.remoting.buffer.ChannelBuffer buffer();
    Code:
       0: aload_0
       1: getfield      #5                  // Field buffer:Lorg/apache/dubbo/remoting/buffer/ChannelBuffer;
       4: areturn
}
