Compiled from "ChannelBuffers.java"
public final class org.apache.dubbo.remoting.buffer.ChannelBuffers {
  public static final org.apache.dubbo.remoting.buffer.ChannelBuffer EMPTY_BUFFER;

  public static final int DEFAULT_CAPACITY;

  private org.apache.dubbo.remoting.buffer.ChannelBuffers();
    Code:
       0: aload_0
       1: invokespecial #1                  // Method java/lang/Object."<init>":()V
       4: return

  public static org.apache.dubbo.remoting.buffer.ChannelBuffer dynamicBuffer();
    Code:
       0: sipush        256
       3: invokestatic  #3                  // Method dynamicBuffer:(I)Lorg/apache/dubbo/remoting/buffer/ChannelBuffer;
       6: areturn

  public static org.apache.dubbo.remoting.buffer.ChannelBuffer dynamicBuffer(int);
    Code:
       0: new           #4                  // class org/apache/dubbo/remoting/buffer/DynamicChannelBuffer
       3: dup
       4: iload_0
       5: invokespecial #5                  // Method org/apache/dubbo/remoting/buffer/DynamicChannelBuffer."<init>":(I)V
       8: areturn

  public static org.apache.dubbo.remoting.buffer.ChannelBuffer dynamicBuffer(int, org.apache.dubbo.remoting.buffer.ChannelBufferFactory);
    Code:
       0: new           #4                  // class org/apache/dubbo/remoting/buffer/DynamicChannelBuffer
       3: dup
       4: iload_0
       5: aload_1
       6: invokespecial #6                  // Method org/apache/dubbo/remoting/buffer/DynamicChannelBuffer."<init>":(ILorg/apache/dubbo/remoting/buffer/ChannelBufferFactory;)V
       9: areturn

  public static org.apache.dubbo.remoting.buffer.ChannelBuffer buffer(int);
    Code:
       0: iload_0
       1: ifge          14
       4: new           #7                  // class java/lang/IllegalArgumentException
       7: dup
       8: ldc           #8                  // String capacity can not be negative
      10: invokespecial #9                  // Method java/lang/IllegalArgumentException."<init>":(Ljava/lang/String;)V
      13: athrow
      14: iload_0
      15: ifne          22
      18: getstatic     #10                 // Field EMPTY_BUFFER:Lorg/apache/dubbo/remoting/buffer/ChannelBuffer;
      21: areturn
      22: new           #11                 // class org/apache/dubbo/remoting/buffer/HeapChannelBuffer
      25: dup
      26: iload_0
      27: invokespecial #12                 // Method org/apache/dubbo/remoting/buffer/HeapChannelBuffer."<init>":(I)V
      30: areturn

  public static org.apache.dubbo.remoting.buffer.ChannelBuffer wrappedBuffer(byte[], int, int);
    Code:
       0: aload_0
       1: ifnonnull     14
       4: new           #13                 // class java/lang/NullPointerException
       7: dup
       8: ldc           #14                 // String array == null
      10: invokespecial #15                 // Method java/lang/NullPointerException."<init>":(Ljava/lang/String;)V
      13: athrow
      14: iload_2
      15: newarray       byte
      17: astore_3
      18: aload_0
      19: iload_1
      20: aload_3
      21: iconst_0
      22: iload_2
      23: invokestatic  #16                 // Method java/lang/System.arraycopy:(Ljava/lang/Object;ILjava/lang/Object;II)V
      26: aload_3
      27: invokestatic  #17                 // Method wrappedBuffer:([B)Lorg/apache/dubbo/remoting/buffer/ChannelBuffer;
      30: areturn

  public static org.apache.dubbo.remoting.buffer.ChannelBuffer wrappedBuffer(byte[]);
    Code:
       0: aload_0
       1: ifnonnull     14
       4: new           #13                 // class java/lang/NullPointerException
       7: dup
       8: ldc           #14                 // String array == null
      10: invokespecial #15                 // Method java/lang/NullPointerException."<init>":(Ljava/lang/String;)V
      13: athrow
      14: aload_0
      15: arraylength
      16: ifne          23
      19: getstatic     #10                 // Field EMPTY_BUFFER:Lorg/apache/dubbo/remoting/buffer/ChannelBuffer;
      22: areturn
      23: new           #11                 // class org/apache/dubbo/remoting/buffer/HeapChannelBuffer
      26: dup
      27: aload_0
      28: invokespecial #18                 // Method org/apache/dubbo/remoting/buffer/HeapChannelBuffer."<init>":([B)V
      31: areturn

  public static org.apache.dubbo.remoting.buffer.ChannelBuffer wrappedBuffer(java.nio.ByteBuffer);
    Code:
       0: aload_0
       1: invokevirtual #19                 // Method java/nio/ByteBuffer.hasRemaining:()Z
       4: ifne          11
       7: getstatic     #10                 // Field EMPTY_BUFFER:Lorg/apache/dubbo/remoting/buffer/ChannelBuffer;
      10: areturn
      11: aload_0
      12: invokevirtual #20                 // Method java/nio/ByteBuffer.hasArray:()Z
      15: ifeq          39
      18: aload_0
      19: invokevirtual #21                 // Method java/nio/ByteBuffer.array:()[B
      22: aload_0
      23: invokevirtual #22                 // Method java/nio/ByteBuffer.arrayOffset:()I
      26: aload_0
      27: invokevirtual #23                 // Method java/nio/ByteBuffer.position:()I
      30: iadd
      31: aload_0
      32: invokevirtual #24                 // Method java/nio/ByteBuffer.remaining:()I
      35: invokestatic  #25                 // Method wrappedBuffer:([BII)Lorg/apache/dubbo/remoting/buffer/ChannelBuffer;
      38: areturn
      39: new           #26                 // class org/apache/dubbo/remoting/buffer/ByteBufferBackedChannelBuffer
      42: dup
      43: aload_0
      44: invokespecial #27                 // Method org/apache/dubbo/remoting/buffer/ByteBufferBackedChannelBuffer."<init>":(Ljava/nio/ByteBuffer;)V
      47: areturn

  public static org.apache.dubbo.remoting.buffer.ChannelBuffer directBuffer(int);
    Code:
       0: iload_0
       1: ifne          8
       4: getstatic     #10                 // Field EMPTY_BUFFER:Lorg/apache/dubbo/remoting/buffer/ChannelBuffer;
       7: areturn
       8: new           #26                 // class org/apache/dubbo/remoting/buffer/ByteBufferBackedChannelBuffer
      11: dup
      12: iload_0
      13: invokestatic  #28                 // Method java/nio/ByteBuffer.allocateDirect:(I)Ljava/nio/ByteBuffer;
      16: invokespecial #27                 // Method org/apache/dubbo/remoting/buffer/ByteBufferBackedChannelBuffer."<init>":(Ljava/nio/ByteBuffer;)V
      19: astore_1
      20: aload_1
      21: invokeinterface #29,  1           // InterfaceMethod org/apache/dubbo/remoting/buffer/ChannelBuffer.clear:()V
      26: aload_1
      27: areturn

  public static boolean equals(org.apache.dubbo.remoting.buffer.ChannelBuffer, org.apache.dubbo.remoting.buffer.ChannelBuffer);
    Code:
       0: aload_0
       1: invokeinterface #30,  1           // InterfaceMethod org/apache/dubbo/remoting/buffer/ChannelBuffer.readableBytes:()I
       6: istore_2
       7: iload_2
       8: aload_1
       9: invokeinterface #30,  1           // InterfaceMethod org/apache/dubbo/remoting/buffer/ChannelBuffer.readableBytes:()I
      14: if_icmpeq     19
      17: iconst_0
      18: ireturn
      19: iload_2
      20: bipush        7
      22: iand
      23: istore_3
      24: aload_0
      25: invokeinterface #31,  1           // InterfaceMethod org/apache/dubbo/remoting/buffer/ChannelBuffer.readerIndex:()I
      30: istore        4
      32: aload_1
      33: invokeinterface #31,  1           // InterfaceMethod org/apache/dubbo/remoting/buffer/ChannelBuffer.readerIndex:()I
      38: istore        5
      40: iload_3
      41: istore        6
      43: iload         6
      45: ifle          81
      48: aload_0
      49: iload         4
      51: invokeinterface #32,  2           // InterfaceMethod org/apache/dubbo/remoting/buffer/ChannelBuffer.getByte:(I)B
      56: aload_1
      57: iload         5
      59: invokeinterface #32,  2           // InterfaceMethod org/apache/dubbo/remoting/buffer/ChannelBuffer.getByte:(I)B
      64: if_icmpeq     69
      67: iconst_0
      68: ireturn
      69: iinc          4, 1
      72: iinc          5, 1
      75: iinc          6, -1
      78: goto          43
      81: iconst_1
      82: ireturn

  public static boolean prefixEquals(org.apache.dubbo.remoting.buffer.ChannelBuffer, org.apache.dubbo.remoting.buffer.ChannelBuffer, int);
    Code:
       0: aload_0
       1: invokeinterface #30,  1           // InterfaceMethod org/apache/dubbo/remoting/buffer/ChannelBuffer.readableBytes:()I
       6: istore_3
       7: aload_1
       8: invokeinterface #30,  1           // InterfaceMethod org/apache/dubbo/remoting/buffer/ChannelBuffer.readableBytes:()I
      13: istore        4
      15: iload_3
      16: iload_2
      17: if_icmplt     26
      20: iload         4
      22: iload_2
      23: if_icmpge     28
      26: iconst_0
      27: ireturn
      28: aload_0
      29: invokeinterface #31,  1           // InterfaceMethod org/apache/dubbo/remoting/buffer/ChannelBuffer.readerIndex:()I
      34: istore        5
      36: aload_1
      37: invokeinterface #31,  1           // InterfaceMethod org/apache/dubbo/remoting/buffer/ChannelBuffer.readerIndex:()I
      42: istore        6
      44: iload_2
      45: istore        7
      47: iload         7
      49: ifle          85
      52: aload_0
      53: iload         5
      55: invokeinterface #32,  2           // InterfaceMethod org/apache/dubbo/remoting/buffer/ChannelBuffer.getByte:(I)B
      60: aload_1
      61: iload         6
      63: invokeinterface #32,  2           // InterfaceMethod org/apache/dubbo/remoting/buffer/ChannelBuffer.getByte:(I)B
      68: if_icmpeq     73
      71: iconst_0
      72: ireturn
      73: iinc          5, 1
      76: iinc          6, 1
      79: iinc          7, -1
      82: goto          47
      85: iconst_1
      86: ireturn

  public static int hasCode(org.apache.dubbo.remoting.buffer.ChannelBuffer);
    Code:
       0: aload_0
       1: invokeinterface #30,  1           // InterfaceMethod org/apache/dubbo/remoting/buffer/ChannelBuffer.readableBytes:()I
       6: istore_1
       7: iload_1
       8: bipush        7
      10: iand
      11: istore_2
      12: iconst_1
      13: istore_3
      14: aload_0
      15: invokeinterface #31,  1           // InterfaceMethod org/apache/dubbo/remoting/buffer/ChannelBuffer.readerIndex:()I
      20: istore        4
      22: iload_2
      23: istore        5
      25: iload         5
      27: ifle          53
      30: bipush        31
      32: iload_3
      33: imul
      34: aload_0
      35: iload         4
      37: iinc          4, 1
      40: invokeinterface #32,  2           // InterfaceMethod org/apache/dubbo/remoting/buffer/ChannelBuffer.getByte:(I)B
      45: iadd
      46: istore_3
      47: iinc          5, -1
      50: goto          25
      53: iload_3
      54: ifne          59
      57: iconst_1
      58: istore_3
      59: iload_3
      60: ireturn

  public static int compare(org.apache.dubbo.remoting.buffer.ChannelBuffer, org.apache.dubbo.remoting.buffer.ChannelBuffer);
    Code:
       0: aload_0
       1: invokeinterface #30,  1           // InterfaceMethod org/apache/dubbo/remoting/buffer/ChannelBuffer.readableBytes:()I
       6: istore_2
       7: aload_1
       8: invokeinterface #30,  1           // InterfaceMethod org/apache/dubbo/remoting/buffer/ChannelBuffer.readableBytes:()I
      13: istore_3
      14: iload_2
      15: iload_3
      16: invokestatic  #33                 // Method java/lang/Math.min:(II)I
      19: istore        4
      21: aload_0
      22: invokeinterface #31,  1           // InterfaceMethod org/apache/dubbo/remoting/buffer/ChannelBuffer.readerIndex:()I
      27: istore        5
      29: aload_1
      30: invokeinterface #31,  1           // InterfaceMethod org/apache/dubbo/remoting/buffer/ChannelBuffer.readerIndex:()I
      35: istore        6
      37: iload         4
      39: istore        7
      41: iload         7
      43: ifle          96
      46: aload_0
      47: iload         5
      49: invokeinterface #32,  2           // InterfaceMethod org/apache/dubbo/remoting/buffer/ChannelBuffer.getByte:(I)B
      54: istore        8
      56: aload_1
      57: iload         6
      59: invokeinterface #32,  2           // InterfaceMethod org/apache/dubbo/remoting/buffer/ChannelBuffer.getByte:(I)B
      64: istore        9
      66: iload         8
      68: iload         9
      70: if_icmple     75
      73: iconst_1
      74: ireturn
      75: iload         8
      77: iload         9
      79: if_icmpge     84
      82: iconst_m1
      83: ireturn
      84: iinc          5, 1
      87: iinc          6, 1
      90: iinc          7, -1
      93: goto          41
      96: iload_2
      97: iload_3
      98: isub
      99: ireturn

  static {};
    Code:
       0: new           #11                 // class org/apache/dubbo/remoting/buffer/HeapChannelBuffer
       3: dup
       4: iconst_0
       5: invokespecial #12                 // Method org/apache/dubbo/remoting/buffer/HeapChannelBuffer."<init>":(I)V
       8: putstatic     #10                 // Field EMPTY_BUFFER:Lorg/apache/dubbo/remoting/buffer/ChannelBuffer;
      11: return
}
