Compiled from "ChannelBufferInputStream.java"
public class org.apache.dubbo.remoting.buffer.ChannelBufferInputStream extends java.io.InputStream {
  private final org.apache.dubbo.remoting.buffer.ChannelBuffer buffer;

  private final int startIndex;

  private final int endIndex;

  public org.apache.dubbo.remoting.buffer.ChannelBufferInputStream(org.apache.dubbo.remoting.buffer.ChannelBuffer);
    Code:
       0: aload_0
       1: aload_1
       2: aload_1
       3: invokeinterface #1,  1            // InterfaceMethod org/apache/dubbo/remoting/buffer/ChannelBuffer.readableBytes:()I
       8: invokespecial #2                  // Method "<init>":(Lorg/apache/dubbo/remoting/buffer/ChannelBuffer;I)V
      11: return

  public org.apache.dubbo.remoting.buffer.ChannelBufferInputStream(org.apache.dubbo.remoting.buffer.ChannelBuffer, int);
    Code:
       0: aload_0
       1: invokespecial #3                  // Method java/io/InputStream."<init>":()V
       4: aload_1
       5: ifnonnull     18
       8: new           #4                  // class java/lang/NullPointerException
      11: dup
      12: ldc           #5                  // String buffer
      14: invokespecial #6                  // Method java/lang/NullPointerException."<init>":(Ljava/lang/String;)V
      17: athrow
      18: iload_2
      19: ifge          49
      22: new           #7                  // class java/lang/IllegalArgumentException
      25: dup
      26: new           #8                  // class java/lang/StringBuilder
      29: dup
      30: invokespecial #9                  // Method java/lang/StringBuilder."<init>":()V
      33: ldc           #10                 // String length:
      35: invokevirtual #11                 // Method java/lang/StringBuilder.append:(Ljava/lang/String;)Ljava/lang/StringBuilder;
      38: iload_2
      39: invokevirtual #12                 // Method java/lang/StringBuilder.append:(I)Ljava/lang/StringBuilder;
      42: invokevirtual #13                 // Method java/lang/StringBuilder.toString:()Ljava/lang/String;
      45: invokespecial #14                 // Method java/lang/IllegalArgumentException."<init>":(Ljava/lang/String;)V
      48: athrow
      49: iload_2
      50: aload_1
      51: invokeinterface #1,  1            // InterfaceMethod org/apache/dubbo/remoting/buffer/ChannelBuffer.readableBytes:()I
      56: if_icmple     67
      59: new           #15                 // class java/lang/IndexOutOfBoundsException
      62: dup
      63: invokespecial #16                 // Method java/lang/IndexOutOfBoundsException."<init>":()V
      66: athrow
      67: aload_0
      68: aload_1
      69: putfield      #17                 // Field buffer:Lorg/apache/dubbo/remoting/buffer/ChannelBuffer;
      72: aload_0
      73: aload_1
      74: invokeinterface #18,  1           // InterfaceMethod org/apache/dubbo/remoting/buffer/ChannelBuffer.readerIndex:()I
      79: putfield      #19                 // Field startIndex:I
      82: aload_0
      83: aload_0
      84: getfield      #19                 // Field startIndex:I
      87: iload_2
      88: iadd
      89: putfield      #20                 // Field endIndex:I
      92: aload_1
      93: invokeinterface #21,  1           // InterfaceMethod org/apache/dubbo/remoting/buffer/ChannelBuffer.markReaderIndex:()V
      98: return

  public int readBytes();
    Code:
       0: aload_0
       1: getfield      #17                 // Field buffer:Lorg/apache/dubbo/remoting/buffer/ChannelBuffer;
       4: invokeinterface #18,  1           // InterfaceMethod org/apache/dubbo/remoting/buffer/ChannelBuffer.readerIndex:()I
       9: aload_0
      10: getfield      #19                 // Field startIndex:I
      13: isub
      14: ireturn

  public int available() throws java.io.IOException;
    Code:
       0: aload_0
       1: getfield      #20                 // Field endIndex:I
       4: aload_0
       5: getfield      #17                 // Field buffer:Lorg/apache/dubbo/remoting/buffer/ChannelBuffer;
       8: invokeinterface #18,  1           // InterfaceMethod org/apache/dubbo/remoting/buffer/ChannelBuffer.readerIndex:()I
      13: isub
      14: ireturn

  public synchronized void mark(int);
    Code:
       0: aload_0
       1: getfield      #17                 // Field buffer:Lorg/apache/dubbo/remoting/buffer/ChannelBuffer;
       4: invokeinterface #21,  1           // InterfaceMethod org/apache/dubbo/remoting/buffer/ChannelBuffer.markReaderIndex:()V
       9: return

  public boolean markSupported();
    Code:
       0: iconst_1
       1: ireturn

  public int read() throws java.io.IOException;
    Code:
       0: aload_0
       1: getfield      #17                 // Field buffer:Lorg/apache/dubbo/remoting/buffer/ChannelBuffer;
       4: invokeinterface #22,  1           // InterfaceMethod org/apache/dubbo/remoting/buffer/ChannelBuffer.readable:()Z
       9: ifne          14
      12: iconst_m1
      13: ireturn
      14: aload_0
      15: getfield      #17                 // Field buffer:Lorg/apache/dubbo/remoting/buffer/ChannelBuffer;
      18: invokeinterface #23,  1           // InterfaceMethod org/apache/dubbo/remoting/buffer/ChannelBuffer.readByte:()B
      23: sipush        255
      26: iand
      27: ireturn

  public int read(byte[], int, int) throws java.io.IOException;
    Code:
       0: aload_0
       1: invokevirtual #24                 // Method available:()I
       4: istore        4
       6: iload         4
       8: ifne          13
      11: iconst_m1
      12: ireturn
      13: iload         4
      15: iload_3
      16: invokestatic  #25                 // Method java/lang/Math.min:(II)I
      19: istore_3
      20: aload_0
      21: getfield      #17                 // Field buffer:Lorg/apache/dubbo/remoting/buffer/ChannelBuffer;
      24: aload_1
      25: iload_2
      26: iload_3
      27: invokeinterface #26,  4           // InterfaceMethod org/apache/dubbo/remoting/buffer/ChannelBuffer.readBytes:([BII)V
      32: iload_3
      33: ireturn

  public synchronized void reset() throws java.io.IOException;
    Code:
       0: aload_0
       1: getfield      #17                 // Field buffer:Lorg/apache/dubbo/remoting/buffer/ChannelBuffer;
       4: invokeinterface #27,  1           // InterfaceMethod org/apache/dubbo/remoting/buffer/ChannelBuffer.resetReaderIndex:()V
       9: return

  public long skip(long) throws java.io.IOException;
    Code:
       0: lload_1
       1: ldc2_w        #29                 // long 2147483647l
       4: lcmp
       5: ifle          16
       8: aload_0
       9: ldc           #31                 // int 2147483647
      11: invokespecial #32                 // Method skipBytes:(I)I
      14: i2l
      15: lreturn
      16: aload_0
      17: lload_1
      18: l2i
      19: invokespecial #32                 // Method skipBytes:(I)I
      22: i2l
      23: lreturn

  private int skipBytes(int) throws java.io.IOException;
    Code:
       0: aload_0
       1: invokevirtual #24                 // Method available:()I
       4: iload_1
       5: invokestatic  #25                 // Method java/lang/Math.min:(II)I
       8: istore_2
       9: aload_0
      10: getfield      #17                 // Field buffer:Lorg/apache/dubbo/remoting/buffer/ChannelBuffer;
      13: iload_2
      14: invokeinterface #33,  2           // InterfaceMethod org/apache/dubbo/remoting/buffer/ChannelBuffer.skipBytes:(I)V
      19: iload_2
      20: ireturn
}
