Compiled from "DirectChannelBufferFactory.java"
public class org.apache.dubbo.remoting.buffer.DirectChannelBufferFactory implements org.apache.dubbo.remoting.buffer.ChannelBufferFactory {
  private static final org.apache.dubbo.remoting.buffer.DirectChannelBufferFactory INSTANCE;

  public org.apache.dubbo.remoting.buffer.DirectChannelBufferFactory();
    Code:
       0: aload_0
       1: invokespecial #1                  // Method java/lang/Object."<init>":()V
       4: return

  public static org.apache.dubbo.remoting.buffer.ChannelBufferFactory getInstance();
    Code:
       0: getstatic     #2                  // Field INSTANCE:Lorg/apache/dubbo/remoting/buffer/DirectChannelBufferFactory;
       3: areturn

  public org.apache.dubbo.remoting.buffer.ChannelBuffer getBuffer(int);
    Code:
       0: iload_1
       1: ifge          31
       4: new           #3                  // class java/lang/IllegalArgumentException
       7: dup
       8: new           #4                  // class java/lang/StringBuilder
      11: dup
      12: invokespecial #5                  // Method java/lang/StringBuilder."<init>":()V
      15: ldc           #6                  // String capacity:
      17: invokevirtual #7                  // Method java/lang/StringBuilder.append:(Ljava/lang/String;)Ljava/lang/StringBuilder;
      20: iload_1
      21: invokevirtual #8                  // Method java/lang/StringBuilder.append:(I)Ljava/lang/StringBuilder;
      24: invokevirtual #9                  // Method java/lang/StringBuilder.toString:()Ljava/lang/String;
      27: invokespecial #10                 // Method java/lang/IllegalArgumentException."<init>":(Ljava/lang/String;)V
      30: athrow
      31: iload_1
      32: ifne          39
      35: getstatic     #11                 // Field org/apache/dubbo/remoting/buffer/ChannelBuffers.EMPTY_BUFFER:Lorg/apache/dubbo/remoting/buffer/ChannelBuffer;
      38: areturn
      39: iload_1
      40: invokestatic  #12                 // Method org/apache/dubbo/remoting/buffer/ChannelBuffers.directBuffer:(I)Lorg/apache/dubbo/remoting/buffer/ChannelBuffer;
      43: areturn

  public org.apache.dubbo.remoting.buffer.ChannelBuffer getBuffer(byte[], int, int);
    Code:
       0: aload_1
       1: ifnonnull     14
       4: new           #13                 // class java/lang/NullPointerException
       7: dup
       8: ldc           #14                 // String array
      10: invokespecial #15                 // Method java/lang/NullPointerException."<init>":(Ljava/lang/String;)V
      13: athrow
      14: iload_2
      15: ifge          45
      18: new           #16                 // class java/lang/IndexOutOfBoundsException
      21: dup
      22: new           #4                  // class java/lang/StringBuilder
      25: dup
      26: invokespecial #5                  // Method java/lang/StringBuilder."<init>":()V
      29: ldc           #17                 // String offset:
      31: invokevirtual #7                  // Method java/lang/StringBuilder.append:(Ljava/lang/String;)Ljava/lang/StringBuilder;
      34: iload_2
      35: invokevirtual #8                  // Method java/lang/StringBuilder.append:(I)Ljava/lang/StringBuilder;
      38: invokevirtual #9                  // Method java/lang/StringBuilder.toString:()Ljava/lang/String;
      41: invokespecial #18                 // Method java/lang/IndexOutOfBoundsException."<init>":(Ljava/lang/String;)V
      44: athrow
      45: iload_3
      46: ifne          53
      49: getstatic     #11                 // Field org/apache/dubbo/remoting/buffer/ChannelBuffers.EMPTY_BUFFER:Lorg/apache/dubbo/remoting/buffer/ChannelBuffer;
      52: areturn
      53: iload_2
      54: iload_3
      55: iadd
      56: aload_1
      57: arraylength
      58: if_icmple     88
      61: new           #16                 // class java/lang/IndexOutOfBoundsException
      64: dup
      65: new           #4                  // class java/lang/StringBuilder
      68: dup
      69: invokespecial #5                  // Method java/lang/StringBuilder."<init>":()V
      72: ldc           #19                 // String length:
      74: invokevirtual #7                  // Method java/lang/StringBuilder.append:(Ljava/lang/String;)Ljava/lang/StringBuilder;
      77: iload_3
      78: invokevirtual #8                  // Method java/lang/StringBuilder.append:(I)Ljava/lang/StringBuilder;
      81: invokevirtual #9                  // Method java/lang/StringBuilder.toString:()Ljava/lang/String;
      84: invokespecial #18                 // Method java/lang/IndexOutOfBoundsException."<init>":(Ljava/lang/String;)V
      87: athrow
      88: aload_0
      89: iload_3
      90: invokevirtual #20                 // Method getBuffer:(I)Lorg/apache/dubbo/remoting/buffer/ChannelBuffer;
      93: astore        4
      95: aload         4
      97: aload_1
      98: iload_2
      99: iload_3
     100: invokeinterface #21,  4           // InterfaceMethod org/apache/dubbo/remoting/buffer/ChannelBuffer.writeBytes:([BII)V
     105: aload         4
     107: areturn

  public org.apache.dubbo.remoting.buffer.ChannelBuffer getBuffer(java.nio.ByteBuffer);
    Code:
       0: aload_1
       1: invokevirtual #22                 // Method java/nio/ByteBuffer.isReadOnly:()Z
       4: ifne          19
       7: aload_1
       8: invokevirtual #23                 // Method java/nio/ByteBuffer.isDirect:()Z
      11: ifeq          19
      14: aload_1
      15: invokestatic  #24                 // Method org/apache/dubbo/remoting/buffer/ChannelBuffers.wrappedBuffer:(Ljava/nio/ByteBuffer;)Lorg/apache/dubbo/remoting/buffer/ChannelBuffer;
      18: areturn
      19: aload_0
      20: aload_1
      21: invokevirtual #25                 // Method java/nio/ByteBuffer.remaining:()I
      24: invokevirtual #20                 // Method getBuffer:(I)Lorg/apache/dubbo/remoting/buffer/ChannelBuffer;
      27: astore_2
      28: aload_1
      29: invokevirtual #26                 // Method java/nio/ByteBuffer.position:()I
      32: istore_3
      33: aload_2
      34: aload_1
      35: invokeinterface #27,  2           // InterfaceMethod org/apache/dubbo/remoting/buffer/ChannelBuffer.writeBytes:(Ljava/nio/ByteBuffer;)V
      40: aload_1
      41: iload_3
      42: invokevirtual #28                 // Method java/nio/ByteBuffer.position:(I)Ljava/nio/Buffer;
      45: pop
      46: aload_2
      47: areturn

  static {};
    Code:
       0: new           #29                 // class org/apache/dubbo/remoting/buffer/DirectChannelBufferFactory
       3: dup
       4: invokespecial #30                 // Method "<init>":()V
       7: putstatic     #2                  // Field INSTANCE:Lorg/apache/dubbo/remoting/buffer/DirectChannelBufferFactory;
      10: return
}
