Compiled from "DynamicChannelBuffer.java"
public class org.apache.dubbo.remoting.buffer.DynamicChannelBuffer extends org.apache.dubbo.remoting.buffer.AbstractChannelBuffer {
  private final org.apache.dubbo.remoting.buffer.ChannelBufferFactory factory;

  private org.apache.dubbo.remoting.buffer.ChannelBuffer buffer;

  public org.apache.dubbo.remoting.buffer.DynamicChannelBuffer(int);
    Code:
       0: aload_0
       1: iload_1
       2: invokestatic  #1                  // Method org/apache/dubbo/remoting/buffer/HeapChannelBufferFactory.getInstance:()Lorg/apache/dubbo/remoting/buffer/ChannelBufferFactory;
       5: invokespecial #2                  // Method "<init>":(ILorg/apache/dubbo/remoting/buffer/ChannelBufferFactory;)V
       8: return

  public org.apache.dubbo.remoting.buffer.DynamicChannelBuffer(int, org.apache.dubbo.remoting.buffer.ChannelBufferFactory);
    Code:
       0: aload_0
       1: invokespecial #3                  // Method org/apache/dubbo/remoting/buffer/AbstractChannelBuffer."<init>":()V
       4: iload_1
       5: ifge          35
       8: new           #4                  // class java/lang/IllegalArgumentException
      11: dup
      12: new           #5                  // class java/lang/StringBuilder
      15: dup
      16: invokespecial #6                  // Method java/lang/StringBuilder."<init>":()V
      19: ldc           #7                  // String estimatedLength:
      21: invokevirtual #8                  // Method java/lang/StringBuilder.append:(Ljava/lang/String;)Ljava/lang/StringBuilder;
      24: iload_1
      25: invokevirtual #9                  // Method java/lang/StringBuilder.append:(I)Ljava/lang/StringBuilder;
      28: invokevirtual #10                 // Method java/lang/StringBuilder.toString:()Ljava/lang/String;
      31: invokespecial #11                 // Method java/lang/IllegalArgumentException."<init>":(Ljava/lang/String;)V
      34: athrow
      35: aload_2
      36: ifnonnull     49
      39: new           #12                 // class java/lang/NullPointerException
      42: dup
      43: ldc           #13                 // String factory
      45: invokespecial #14                 // Method java/lang/NullPointerException."<init>":(Ljava/lang/String;)V
      48: athrow
      49: aload_0
      50: aload_2
      51: putfield      #15                 // Field factory:Lorg/apache/dubbo/remoting/buffer/ChannelBufferFactory;
      54: aload_0
      55: aload_2
      56: iload_1
      57: invokeinterface #16,  2           // InterfaceMethod org/apache/dubbo/remoting/buffer/ChannelBufferFactory.getBuffer:(I)Lorg/apache/dubbo/remoting/buffer/ChannelBuffer;
      62: putfield      #17                 // Field buffer:Lorg/apache/dubbo/remoting/buffer/ChannelBuffer;
      65: return

  public void ensureWritableBytes(int);
    Code:
       0: iload_1
       1: aload_0
       2: invokevirtual #18                 // Method writableBytes:()I
       5: if_icmpgt     9
       8: return
       9: aload_0
      10: invokevirtual #19                 // Method capacity:()I
      13: ifne          20
      16: iconst_1
      17: goto          24
      20: aload_0
      21: invokevirtual #19                 // Method capacity:()I
      24: istore_2
      25: aload_0
      26: invokevirtual #20                 // Method writerIndex:()I
      29: iload_1
      30: iadd
      31: istore_3
      32: iload_2
      33: iload_3
      34: if_icmpge     44
      37: iload_2
      38: iconst_1
      39: ishl
      40: istore_2
      41: goto          32
      44: aload_0
      45: invokevirtual #21                 // Method factory:()Lorg/apache/dubbo/remoting/buffer/ChannelBufferFactory;
      48: iload_2
      49: invokeinterface #16,  2           // InterfaceMethod org/apache/dubbo/remoting/buffer/ChannelBufferFactory.getBuffer:(I)Lorg/apache/dubbo/remoting/buffer/ChannelBuffer;
      54: astore        4
      56: aload         4
      58: aload_0
      59: getfield      #17                 // Field buffer:Lorg/apache/dubbo/remoting/buffer/ChannelBuffer;
      62: iconst_0
      63: aload_0
      64: invokevirtual #20                 // Method writerIndex:()I
      67: invokeinterface #22,  4           // InterfaceMethod org/apache/dubbo/remoting/buffer/ChannelBuffer.writeBytes:(Lorg/apache/dubbo/remoting/buffer/ChannelBuffer;II)V
      72: aload_0
      73: aload         4
      75: putfield      #17                 // Field buffer:Lorg/apache/dubbo/remoting/buffer/ChannelBuffer;
      78: return

  public int capacity();
    Code:
       0: aload_0
       1: getfield      #17                 // Field buffer:Lorg/apache/dubbo/remoting/buffer/ChannelBuffer;
       4: invokeinterface #23,  1           // InterfaceMethod org/apache/dubbo/remoting/buffer/ChannelBuffer.capacity:()I
       9: ireturn

  public org.apache.dubbo.remoting.buffer.ChannelBuffer copy(int, int);
    Code:
       0: new           #24                 // class org/apache/dubbo/remoting/buffer/DynamicChannelBuffer
       3: dup
       4: iload_2
       5: bipush        64
       7: invokestatic  #25                 // Method java/lang/Math.max:(II)I
      10: aload_0
      11: invokevirtual #21                 // Method factory:()Lorg/apache/dubbo/remoting/buffer/ChannelBufferFactory;
      14: invokespecial #2                  // Method "<init>":(ILorg/apache/dubbo/remoting/buffer/ChannelBufferFactory;)V
      17: astore_3
      18: aload_3
      19: aload_0
      20: getfield      #17                 // Field buffer:Lorg/apache/dubbo/remoting/buffer/ChannelBuffer;
      23: iload_1
      24: iload_2
      25: invokeinterface #26,  3           // InterfaceMethod org/apache/dubbo/remoting/buffer/ChannelBuffer.copy:(II)Lorg/apache/dubbo/remoting/buffer/ChannelBuffer;
      30: putfield      #17                 // Field buffer:Lorg/apache/dubbo/remoting/buffer/ChannelBuffer;
      33: aload_3
      34: iconst_0
      35: iload_2
      36: invokevirtual #27                 // Method setIndex:(II)V
      39: aload_3
      40: areturn

  public org.apache.dubbo.remoting.buffer.ChannelBufferFactory factory();
    Code:
       0: aload_0
       1: getfield      #15                 // Field factory:Lorg/apache/dubbo/remoting/buffer/ChannelBufferFactory;
       4: areturn

  public byte getByte(int);
    Code:
       0: aload_0
       1: getfield      #17                 // Field buffer:Lorg/apache/dubbo/remoting/buffer/ChannelBuffer;
       4: iload_1
       5: invokeinterface #28,  2           // InterfaceMethod org/apache/dubbo/remoting/buffer/ChannelBuffer.getByte:(I)B
      10: ireturn

  public void getBytes(int, byte[], int, int);
    Code:
       0: aload_0
       1: getfield      #17                 // Field buffer:Lorg/apache/dubbo/remoting/buffer/ChannelBuffer;
       4: iload_1
       5: aload_2
       6: iload_3
       7: iload         4
       9: invokeinterface #29,  5           // InterfaceMethod org/apache/dubbo/remoting/buffer/ChannelBuffer.getBytes:(I[BII)V
      14: return

  public void getBytes(int, java.nio.ByteBuffer);
    Code:
       0: aload_0
       1: getfield      #17                 // Field buffer:Lorg/apache/dubbo/remoting/buffer/ChannelBuffer;
       4: iload_1
       5: aload_2
       6: invokeinterface #30,  3           // InterfaceMethod org/apache/dubbo/remoting/buffer/ChannelBuffer.getBytes:(ILjava/nio/ByteBuffer;)V
      11: return

  public void getBytes(int, org.apache.dubbo.remoting.buffer.ChannelBuffer, int, int);
    Code:
       0: aload_0
       1: getfield      #17                 // Field buffer:Lorg/apache/dubbo/remoting/buffer/ChannelBuffer;
       4: iload_1
       5: aload_2
       6: iload_3
       7: iload         4
       9: invokeinterface #31,  5           // InterfaceMethod org/apache/dubbo/remoting/buffer/ChannelBuffer.getBytes:(ILorg/apache/dubbo/remoting/buffer/ChannelBuffer;II)V
      14: return

  public void getBytes(int, java.io.OutputStream, int) throws java.io.IOException;
    Code:
       0: aload_0
       1: getfield      #17                 // Field buffer:Lorg/apache/dubbo/remoting/buffer/ChannelBuffer;
       4: iload_1
       5: aload_2
       6: iload_3
       7: invokeinterface #32,  4           // InterfaceMethod org/apache/dubbo/remoting/buffer/ChannelBuffer.getBytes:(ILjava/io/OutputStream;I)V
      12: return

  public boolean isDirect();
    Code:
       0: aload_0
       1: getfield      #17                 // Field buffer:Lorg/apache/dubbo/remoting/buffer/ChannelBuffer;
       4: invokeinterface #33,  1           // InterfaceMethod org/apache/dubbo/remoting/buffer/ChannelBuffer.isDirect:()Z
       9: ireturn

  public void setByte(int, int);
    Code:
       0: aload_0
       1: getfield      #17                 // Field buffer:Lorg/apache/dubbo/remoting/buffer/ChannelBuffer;
       4: iload_1
       5: iload_2
       6: invokeinterface #34,  3           // InterfaceMethod org/apache/dubbo/remoting/buffer/ChannelBuffer.setByte:(II)V
      11: return

  public void setBytes(int, byte[], int, int);
    Code:
       0: aload_0
       1: getfield      #17                 // Field buffer:Lorg/apache/dubbo/remoting/buffer/ChannelBuffer;
       4: iload_1
       5: aload_2
       6: iload_3
       7: iload         4
       9: invokeinterface #35,  5           // InterfaceMethod org/apache/dubbo/remoting/buffer/ChannelBuffer.setBytes:(I[BII)V
      14: return

  public void setBytes(int, java.nio.ByteBuffer);
    Code:
       0: aload_0
       1: getfield      #17                 // Field buffer:Lorg/apache/dubbo/remoting/buffer/ChannelBuffer;
       4: iload_1
       5: aload_2
       6: invokeinterface #36,  3           // InterfaceMethod org/apache/dubbo/remoting/buffer/ChannelBuffer.setBytes:(ILjava/nio/ByteBuffer;)V
      11: return

  public void setBytes(int, org.apache.dubbo.remoting.buffer.ChannelBuffer, int, int);
    Code:
       0: aload_0
       1: getfield      #17                 // Field buffer:Lorg/apache/dubbo/remoting/buffer/ChannelBuffer;
       4: iload_1
       5: aload_2
       6: iload_3
       7: iload         4
       9: invokeinterface #37,  5           // InterfaceMethod org/apache/dubbo/remoting/buffer/ChannelBuffer.setBytes:(ILorg/apache/dubbo/remoting/buffer/ChannelBuffer;II)V
      14: return

  public int setBytes(int, java.io.InputStream, int) throws java.io.IOException;
    Code:
       0: aload_0
       1: getfield      #17                 // Field buffer:Lorg/apache/dubbo/remoting/buffer/ChannelBuffer;
       4: iload_1
       5: aload_2
       6: iload_3
       7: invokeinterface #38,  4           // InterfaceMethod org/apache/dubbo/remoting/buffer/ChannelBuffer.setBytes:(ILjava/io/InputStream;I)I
      12: ireturn

  public java.nio.ByteBuffer toByteBuffer(int, int);
    Code:
       0: aload_0
       1: getfield      #17                 // Field buffer:Lorg/apache/dubbo/remoting/buffer/ChannelBuffer;
       4: iload_1
       5: iload_2
       6: invokeinterface #39,  3           // InterfaceMethod org/apache/dubbo/remoting/buffer/ChannelBuffer.toByteBuffer:(II)Ljava/nio/ByteBuffer;
      11: areturn

  public void writeByte(int);
    Code:
       0: aload_0
       1: iconst_1
       2: invokevirtual #40                 // Method ensureWritableBytes:(I)V
       5: aload_0
       6: iload_1
       7: invokespecial #41                 // Method org/apache/dubbo/remoting/buffer/AbstractChannelBuffer.writeByte:(I)V
      10: return

  public void writeBytes(byte[], int, int);
    Code:
       0: aload_0
       1: iload_3
       2: invokevirtual #40                 // Method ensureWritableBytes:(I)V
       5: aload_0
       6: aload_1
       7: iload_2
       8: iload_3
       9: invokespecial #42                 // Method org/apache/dubbo/remoting/buffer/AbstractChannelBuffer.writeBytes:([BII)V
      12: return

  public void writeBytes(org.apache.dubbo.remoting.buffer.ChannelBuffer, int, int);
    Code:
       0: aload_0
       1: iload_3
       2: invokevirtual #40                 // Method ensureWritableBytes:(I)V
       5: aload_0
       6: aload_1
       7: iload_2
       8: iload_3
       9: invokespecial #43                 // Method org/apache/dubbo/remoting/buffer/AbstractChannelBuffer.writeBytes:(Lorg/apache/dubbo/remoting/buffer/ChannelBuffer;II)V
      12: return

  public void writeBytes(java.nio.ByteBuffer);
    Code:
       0: aload_0
       1: aload_1
       2: invokevirtual #44                 // Method java/nio/ByteBuffer.remaining:()I
       5: invokevirtual #40                 // Method ensureWritableBytes:(I)V
       8: aload_0
       9: aload_1
      10: invokespecial #45                 // Method org/apache/dubbo/remoting/buffer/AbstractChannelBuffer.writeBytes:(Ljava/nio/ByteBuffer;)V
      13: return

  public int writeBytes(java.io.InputStream, int) throws java.io.IOException;
    Code:
       0: aload_0
       1: iload_2
       2: invokevirtual #40                 // Method ensureWritableBytes:(I)V
       5: aload_0
       6: aload_1
       7: iload_2
       8: invokespecial #46                 // Method org/apache/dubbo/remoting/buffer/AbstractChannelBuffer.writeBytes:(Ljava/io/InputStream;I)I
      11: ireturn

  public byte[] array();
    Code:
       0: aload_0
       1: getfield      #17                 // Field buffer:Lorg/apache/dubbo/remoting/buffer/ChannelBuffer;
       4: invokeinterface #47,  1           // InterfaceMethod org/apache/dubbo/remoting/buffer/ChannelBuffer.array:()[B
       9: areturn

  public boolean hasArray();
    Code:
       0: aload_0
       1: getfield      #17                 // Field buffer:Lorg/apache/dubbo/remoting/buffer/ChannelBuffer;
       4: invokeinterface #48,  1           // InterfaceMethod org/apache/dubbo/remoting/buffer/ChannelBuffer.hasArray:()Z
       9: ireturn

  public int arrayOffset();
    Code:
       0: aload_0
       1: getfield      #17                 // Field buffer:Lorg/apache/dubbo/remoting/buffer/ChannelBuffer;
       4: invokeinterface #49,  1           // InterfaceMethod org/apache/dubbo/remoting/buffer/ChannelBuffer.arrayOffset:()I
       9: ireturn

  public void release();
    Code:
       0: aload_0
       1: getfield      #17                 // Field buffer:Lorg/apache/dubbo/remoting/buffer/ChannelBuffer;
       4: invokeinterface #50,  1           // InterfaceMethod org/apache/dubbo/remoting/buffer/ChannelBuffer.release:()V
       9: return
}
