Compiled from "HeapChannelBufferFactory.java"
public class org.apache.dubbo.remoting.buffer.HeapChannelBufferFactory implements org.apache.dubbo.remoting.buffer.ChannelBufferFactory {
  private static final org.apache.dubbo.remoting.buffer.HeapChannelBufferFactory INSTANCE;

  public org.apache.dubbo.remoting.buffer.HeapChannelBufferFactory();
    Code:
       0: aload_0
       1: invokespecial #1                  // Method java/lang/Object."<init>":()V
       4: return

  public static org.apache.dubbo.remoting.buffer.ChannelBufferFactory getInstance();
    Code:
       0: getstatic     #2                  // Field INSTANCE:Lorg/apache/dubbo/remoting/buffer/HeapChannelBufferFactory;
       3: areturn

  public org.apache.dubbo.remoting.buffer.ChannelBuffer getBuffer(int);
    Code:
       0: iload_1
       1: invokestatic  #3                  // Method org/apache/dubbo/remoting/buffer/ChannelBuffers.buffer:(I)Lorg/apache/dubbo/remoting/buffer/ChannelBuffer;
       4: areturn

  public org.apache.dubbo.remoting.buffer.ChannelBuffer getBuffer(byte[], int, int);
    Code:
       0: aload_1
       1: iload_2
       2: iload_3
       3: invokestatic  #4                  // Method org/apache/dubbo/remoting/buffer/ChannelBuffers.wrappedBuffer:([BII)Lorg/apache/dubbo/remoting/buffer/ChannelBuffer;
       6: areturn

  public org.apache.dubbo.remoting.buffer.ChannelBuffer getBuffer(java.nio.ByteBuffer);
    Code:
       0: aload_1
       1: invokevirtual #5                  // Method java/nio/ByteBuffer.hasArray:()Z
       4: ifeq          12
       7: aload_1
       8: invokestatic  #6                  // Method org/apache/dubbo/remoting/buffer/ChannelBuffers.wrappedBuffer:(Ljava/nio/ByteBuffer;)Lorg/apache/dubbo/remoting/buffer/ChannelBuffer;
      11: areturn
      12: aload_0
      13: aload_1
      14: invokevirtual #7                  // Method java/nio/ByteBuffer.remaining:()I
      17: invokevirtual #8                  // Method getBuffer:(I)Lorg/apache/dubbo/remoting/buffer/ChannelBuffer;
      20: astore_2
      21: aload_1
      22: invokevirtual #9                  // Method java/nio/ByteBuffer.position:()I
      25: istore_3
      26: aload_2
      27: aload_1
      28: invokeinterface #10,  2           // InterfaceMethod org/apache/dubbo/remoting/buffer/ChannelBuffer.writeBytes:(Ljava/nio/ByteBuffer;)V
      33: aload_1
      34: iload_3
      35: invokevirtual #11                 // Method java/nio/ByteBuffer.position:(I)Ljava/nio/Buffer;
      38: pop
      39: aload_2
      40: areturn

  static {};
    Code:
       0: new           #12                 // class org/apache/dubbo/remoting/buffer/HeapChannelBufferFactory
       3: dup
       4: invokespecial #13                 // Method "<init>":()V
       7: putstatic     #2                  // Field INSTANCE:Lorg/apache/dubbo/remoting/buffer/HeapChannelBufferFactory;
      10: return
}
