Compiled from "LoggingApplicationListener.java"
class org.springframework.boot.context.logging.LoggingApplicationListener$Lifecycle implements org.springframework.context.SmartLifecycle {
  private volatile boolean running;

  final org.springframework.boot.context.logging.LoggingApplicationListener this$0;

  private org.springframework.boot.context.logging.LoggingApplicationListener$Lifecycle(org.springframework.boot.context.logging.LoggingApplicationListener);
    Code:
       0: aload_0
       1: aload_1
       2: putfield      #1                  // Field this$0:Lorg/springframework/boot/context/logging/LoggingApplicationListener;
       5: aload_0
       6: invokespecial #7                  // Method java/lang/Object."<init>":()V
       9: return

  public void start();
    Code:
       0: aload_0
       1: iconst_1
       2: putfield      #13                 // Field running:Z
       5: return

  public void stop();
    Code:
       0: aload_0
       1: iconst_0
       2: putfield      #13                 // Field running:Z
       5: aload_0
       6: getfield      #1                  // Field this$0:Lorg/springframework/boot/context/logging/LoggingApplicationListener;
       9: invokevirtual #17                 // Method org/springframework/boot/context/logging/LoggingApplicationListener.cleanupLoggingSystem:()V
      12: return

  public boolean isRunning();
    Code:
       0: aload_0
       1: getfield      #13                 // Field running:Z
       4: ireturn

  public int getPhase();
    Code:
       0: ldc           #24                 // int -2147483647
       2: ireturn
}
