Compiled from "ServiceInstancesChangedListener.java"
public class org.apache.dubbo.registry.client.event.listener.ServiceInstancesChangedListener$AddressRefreshRetryTask implements java.lang.Runnable {
  private final org.apache.dubbo.registry.client.event.RetryServiceInstancesChangedEvent retryEvent;

  private final java.util.concurrent.Semaphore retryPermission;

  final org.apache.dubbo.registry.client.event.listener.ServiceInstancesChangedListener this$0;

  public org.apache.dubbo.registry.client.event.listener.ServiceInstancesChangedListener$AddressRefreshRetryTask(org.apache.dubbo.registry.client.event.listener.ServiceInstancesChangedListener, java.util.concurrent.Semaphore, java.lang.String);
    Code:
       0: aload_0
       1: aload_1
       2: putfield      #1                  // Field this$0:Lorg/apache/dubbo/registry/client/event/listener/ServiceInstancesChangedListener;
       5: aload_0
       6: invokespecial #2                  // Method java/lang/Object."<init>":()V
       9: aload_0
      10: new           #3                  // class org/apache/dubbo/registry/client/event/RetryServiceInstancesChangedEvent
      13: dup
      14: aload_3
      15: invokespecial #4                  // Method org/apache/dubbo/registry/client/event/RetryServiceInstancesChangedEvent."<init>":(Ljava/lang/String;)V
      18: putfield      #5                  // Field retryEvent:Lorg/apache/dubbo/registry/client/event/RetryServiceInstancesChangedEvent;
      21: aload_0
      22: aload_2
      23: putfield      #6                  // Field retryPermission:Ljava/util/concurrent/Semaphore;
      26: return

  public void run();
    Code:
       0: aload_0
       1: getfield      #6                  // Field retryPermission:Ljava/util/concurrent/Semaphore;
       4: invokevirtual #7                  // Method java/util/concurrent/Semaphore.release:()V
       7: aload_0
       8: getfield      #1                  // Field this$0:Lorg/apache/dubbo/registry/client/event/listener/ServiceInstancesChangedListener;
      11: aload_0
      12: getfield      #5                  // Field retryEvent:Lorg/apache/dubbo/registry/client/event/RetryServiceInstancesChangedEvent;
      15: invokevirtual #8                  // Method org/apache/dubbo/registry/client/event/listener/ServiceInstancesChangedListener.onEvent:(Lorg/apache/dubbo/registry/client/event/ServiceInstancesChangedEvent;)V
      18: return
}
