Compiled from "ServiceInstancesChangedListener.java"
public class org.apache.dubbo.registry.client.event.listener.ServiceInstancesChangedListener {
  private static final org.apache.dubbo.common.logger.ErrorTypeAwareLogger logger;

  protected final java.util.Set<java.lang.String> serviceNames;

  protected final org.apache.dubbo.registry.client.ServiceDiscovery serviceDiscovery;

  protected java.util.Map<java.lang.String, java.util.Set<org.apache.dubbo.registry.client.event.listener.ServiceInstancesChangedListener$NotifyListenerWithKey>> listeners;

  protected java.util.concurrent.atomic.AtomicBoolean destroyed;

  protected java.util.Map<java.lang.String, java.util.List<org.apache.dubbo.registry.client.ServiceInstance>> allInstances;

  protected java.util.Map<java.lang.String, java.util.List<org.apache.dubbo.registry.client.event.listener.ServiceInstancesChangedListener$ProtocolServiceKeyWithUrls>> serviceUrls;

  private volatile long lastRefreshTime;

  private final java.util.concurrent.Semaphore retryPermission;

  private volatile java.util.concurrent.ScheduledFuture<?> retryFuture;

  private final java.util.concurrent.ScheduledExecutorService scheduler;

  private volatile boolean hasEmptyMetadata;

  private final java.util.Set<org.apache.dubbo.registry.client.metadata.ServiceInstanceNotificationCustomizer> serviceInstanceNotificationCustomizers;

  private final org.apache.dubbo.rpc.model.ApplicationModel applicationModel;

  public org.apache.dubbo.registry.client.event.listener.ServiceInstancesChangedListener(java.util.Set<java.lang.String>, org.apache.dubbo.registry.client.ServiceDiscovery);
    Code:
       0: aload_0
       1: invokespecial #5                  // Method java/lang/Object."<init>":()V
       4: aload_0
       5: new           #6                  // class java/util/concurrent/atomic/AtomicBoolean
       8: dup
       9: iconst_0
      10: invokespecial #7                  // Method java/util/concurrent/atomic/AtomicBoolean."<init>":(Z)V
      13: putfield      #8                  // Field destroyed:Ljava/util/concurrent/atomic/AtomicBoolean;
      16: aload_0
      17: aload_1
      18: putfield      #9                  // Field serviceNames:Ljava/util/Set;
      21: aload_0
      22: aload_2
      23: putfield      #10                 // Field serviceDiscovery:Lorg/apache/dubbo/registry/client/ServiceDiscovery;
      26: aload_0
      27: new           #11                 // class java/util/concurrent/ConcurrentHashMap
      30: dup
      31: invokespecial #12                 // Method java/util/concurrent/ConcurrentHashMap."<init>":()V
      34: putfield      #13                 // Field listeners:Ljava/util/Map;
      37: aload_0
      38: new           #14                 // class java/util/HashMap
      41: dup
      42: invokespecial #15                 // Method java/util/HashMap."<init>":()V
      45: putfield      #16                 // Field allInstances:Ljava/util/Map;
      48: aload_0
      49: new           #14                 // class java/util/HashMap
      52: dup
      53: invokespecial #15                 // Method java/util/HashMap."<init>":()V
      56: putfield      #17                 // Field serviceUrls:Ljava/util/Map;
      59: aload_0
      60: new           #18                 // class java/util/concurrent/Semaphore
      63: dup
      64: iconst_1
      65: invokespecial #19                 // Method java/util/concurrent/Semaphore."<init>":(I)V
      68: putfield      #20                 // Field retryPermission:Ljava/util/concurrent/Semaphore;
      71: aload_2
      72: ifnull        84
      75: aload_2
      76: invokeinterface #21,  1           // InterfaceMethod org/apache/dubbo/registry/client/ServiceDiscovery.getUrl:()Lorg/apache/dubbo/common/URL;
      81: ifnonnull     88
      84: aconst_null
      85: goto          97
      88: aload_2
      89: invokeinterface #21,  1           // InterfaceMethod org/apache/dubbo/registry/client/ServiceDiscovery.getUrl:()Lorg/apache/dubbo/common/URL;
      94: invokevirtual #22                 // Method org/apache/dubbo/common/URL.getScopeModel:()Lorg/apache/dubbo/rpc/model/ScopeModel;
      97: invokestatic  #23                 // Method org/apache/dubbo/rpc/model/ScopeModelUtil.getApplicationModel:(Lorg/apache/dubbo/rpc/model/ScopeModel;)Lorg/apache/dubbo/rpc/model/ApplicationModel;
     100: astore_3
     101: aload_0
     102: aload_3
     103: invokevirtual #24                 // Method org/apache/dubbo/rpc/model/ApplicationModel.getBeanFactory:()Lorg/apache/dubbo/common/beans/factory/ScopeBeanFactory;
     106: ldc           #25                 // class org/apache/dubbo/common/threadpool/manager/FrameworkExecutorRepository
     108: invokevirtual #26                 // Method org/apache/dubbo/common/beans/factory/ScopeBeanFactory.getBean:(Ljava/lang/Class;)Ljava/lang/Object;
     111: checkcast     #25                 // class org/apache/dubbo/common/threadpool/manager/FrameworkExecutorRepository
     114: invokevirtual #27                 // Method org/apache/dubbo/common/threadpool/manager/FrameworkExecutorRepository.getMetadataRetryExecutor:()Ljava/util/concurrent/ScheduledExecutorService;
     117: putfield      #28                 // Field scheduler:Ljava/util/concurrent/ScheduledExecutorService;
     120: aload_0
     121: aload_3
     122: ldc           #29                 // class org/apache/dubbo/registry/client/metadata/ServiceInstanceNotificationCustomizer
     124: invokevirtual #30                 // Method org/apache/dubbo/rpc/model/ApplicationModel.getExtensionLoader:(Ljava/lang/Class;)Lorg/apache/dubbo/common/extension/ExtensionLoader;
     127: invokevirtual #31                 // Method org/apache/dubbo/common/extension/ExtensionLoader.getSupportedExtensionInstances:()Ljava/util/Set;
     130: putfield      #32                 // Field serviceInstanceNotificationCustomizers:Ljava/util/Set;
     133: aload_0
     134: aload_3
     135: putfield      #33                 // Field applicationModel:Lorg/apache/dubbo/rpc/model/ApplicationModel;
     138: return

  public void onEvent(org.apache.dubbo.registry.client.event.ServiceInstancesChangedEvent);
    Code:
       0: aload_0
       1: getfield      #8                  // Field destroyed:Ljava/util/concurrent/atomic/AtomicBoolean;
       4: invokevirtual #34                 // Method java/util/concurrent/atomic/AtomicBoolean.get:()Z
       7: ifne          26
      10: aload_0
      11: aload_1
      12: invokespecial #35                 // Method accept:(Lorg/apache/dubbo/registry/client/event/ServiceInstancesChangedEvent;)Z
      15: ifeq          26
      18: aload_0
      19: aload_1
      20: invokevirtual #36                 // Method isRetryAndExpired:(Lorg/apache/dubbo/registry/client/event/ServiceInstancesChangedEvent;)Z
      23: ifeq          27
      26: return
      27: aload_0
      28: aload_1
      29: invokespecial #37                 // Method doOnEvent:(Lorg/apache/dubbo/registry/client/event/ServiceInstancesChangedEvent;)V
      32: return

  private synchronized void doOnEvent(org.apache.dubbo.registry.client.event.ServiceInstancesChangedEvent);
    Code:
       0: aload_0
       1: getfield      #8                  // Field destroyed:Ljava/util/concurrent/atomic/AtomicBoolean;
       4: invokevirtual #34                 // Method java/util/concurrent/atomic/AtomicBoolean.get:()Z
       7: ifne          26
      10: aload_0
      11: aload_1
      12: invokespecial #35                 // Method accept:(Lorg/apache/dubbo/registry/client/event/ServiceInstancesChangedEvent;)Z
      15: ifeq          26
      18: aload_0
      19: aload_1
      20: invokevirtual #36                 // Method isRetryAndExpired:(Lorg/apache/dubbo/registry/client/event/ServiceInstancesChangedEvent;)Z
      23: ifeq          27
      26: return
      27: aload_0
      28: aload_1
      29: invokespecial #38                 // Method refreshInstance:(Lorg/apache/dubbo/registry/client/event/ServiceInstancesChangedEvent;)V
      32: getstatic     #39                 // Field logger:Lorg/apache/dubbo/common/logger/ErrorTypeAwareLogger;
      35: invokeinterface #40,  1           // InterfaceMethod org/apache/dubbo/common/logger/ErrorTypeAwareLogger.isDebugEnabled:()Z
      40: ifeq          58
      43: getstatic     #39                 // Field logger:Lorg/apache/dubbo/common/logger/ErrorTypeAwareLogger;
      46: aload_1
      47: invokevirtual #41                 // Method org/apache/dubbo/registry/client/event/ServiceInstancesChangedEvent.getServiceInstances:()Ljava/util/List;
      50: invokevirtual #42                 // Method java/lang/Object.toString:()Ljava/lang/String;
      53: invokeinterface #43,  2           // InterfaceMethod org/apache/dubbo/common/logger/ErrorTypeAwareLogger.debug:(Ljava/lang/String;)V
      58: new           #14                 // class java/util/HashMap
      61: dup
      62: invokespecial #15                 // Method java/util/HashMap."<init>":()V
      65: astore_2
      66: new           #14                 // class java/util/HashMap
      69: dup
      70: invokespecial #15                 // Method java/util/HashMap."<init>":()V
      73: astore_3
      74: aload_0
      75: getfield      #16                 // Field allInstances:Ljava/util/Map;
      78: invokeinterface #44,  1           // InterfaceMethod java/util/Map.entrySet:()Ljava/util/Set;
      83: invokeinterface #45,  1           // InterfaceMethod java/util/Set.iterator:()Ljava/util/Iterator;
      88: astore        4
      90: aload         4
      92: invokeinterface #46,  1           // InterfaceMethod java/util/Iterator.hasNext:()Z
      97: ifeq          258
     100: aload         4
     102: invokeinterface #47,  1           // InterfaceMethod java/util/Iterator.next:()Ljava/lang/Object;
     107: checkcast     #48                 // class java/util/Map$Entry
     110: astore        5
     112: aload         5
     114: invokeinterface #49,  1           // InterfaceMethod java/util/Map$Entry.getValue:()Ljava/lang/Object;
     119: checkcast     #50                 // class java/util/List
     122: astore        6
     124: aload         6
     126: invokeinterface #51,  1           // InterfaceMethod java/util/List.iterator:()Ljava/util/Iterator;
     131: astore        7
     133: aload         7
     135: invokeinterface #46,  1           // InterfaceMethod java/util/Iterator.hasNext:()Z
     140: ifeq          255
     143: aload         7
     145: invokeinterface #47,  1           // InterfaceMethod java/util/Iterator.next:()Ljava/lang/Object;
     150: checkcast     #52                 // class org/apache/dubbo/registry/client/ServiceInstance
     153: astore        8
     155: aload         8
     157: invokestatic  #53                 // Method org/apache/dubbo/registry/client/metadata/ServiceInstanceMetadataUtils.getExportedServicesRevision:(Lorg/apache/dubbo/registry/client/ServiceInstance;)Ljava/lang/String;
     160: astore        9
     162: aload         9
     164: ifnull        177
     167: ldc           #54                 // String 0
     169: aload         9
     171: invokevirtual #55                 // Method java/lang/String.equals:(Ljava/lang/Object;)Z
     174: ifeq          224
     177: getstatic     #39                 // Field logger:Lorg/apache/dubbo/common/logger/ErrorTypeAwareLogger;
     180: invokeinterface #40,  1           // InterfaceMethod org/apache/dubbo/common/logger/ErrorTypeAwareLogger.isDebugEnabled:()Z
     185: ifeq          133
     188: getstatic     #39                 // Field logger:Lorg/apache/dubbo/common/logger/ErrorTypeAwareLogger;
     191: new           #56                 // class java/lang/StringBuilder
     194: dup
     195: invokespecial #57                 // Method java/lang/StringBuilder."<init>":()V
     198: ldc           #58                 // String Find instance without valid service metadata:
     200: invokevirtual #59                 // Method java/lang/StringBuilder.append:(Ljava/lang/String;)Ljava/lang/StringBuilder;
     203: aload         8
     205: invokeinterface #60,  1           // InterfaceMethod org/apache/dubbo/registry/client/ServiceInstance.getAddress:()Ljava/lang/String;
     210: invokevirtual #59                 // Method java/lang/StringBuilder.append:(Ljava/lang/String;)Ljava/lang/StringBuilder;
     213: invokevirtual #61                 // Method java/lang/StringBuilder.toString:()Ljava/lang/String;
     216: invokeinterface #43,  2           // InterfaceMethod org/apache/dubbo/common/logger/ErrorTypeAwareLogger.debug:(Ljava/lang/String;)V
     221: goto          133
     224: aload_2
     225: aload         9
     227: invokedynamic #62,  0             // InvokeDynamic #0:apply:()Ljava/util/function/Function;
     232: invokeinterface #63,  3           // InterfaceMethod java/util/Map.computeIfAbsent:(Ljava/lang/Object;Ljava/util/function/Function;)Ljava/lang/Object;
     237: checkcast     #50                 // class java/util/List
     240: astore        10
     242: aload         10
     244: aload         8
     246: invokeinterface #64,  2           // InterfaceMethod java/util/List.add:(Ljava/lang/Object;)Z
     251: pop
     252: goto          133
     255: goto          90
     258: aload_2
     259: invokeinterface #44,  1           // InterfaceMethod java/util/Map.entrySet:()Ljava/util/Set;
     264: invokeinterface #45,  1           // InterfaceMethod java/util/Set.iterator:()Ljava/util/Iterator;
     269: astore        4
     271: aload         4
     273: invokeinterface #46,  1           // InterfaceMethod java/util/Iterator.hasNext:()Z
     278: ifeq          465
     281: aload         4
     283: invokeinterface #47,  1           // InterfaceMethod java/util/Iterator.next:()Ljava/lang/Object;
     288: checkcast     #48                 // class java/util/Map$Entry
     291: astore        5
     293: aload         5
     295: invokeinterface #65,  1           // InterfaceMethod java/util/Map$Entry.getKey:()Ljava/lang/Object;
     300: checkcast     #66                 // class java/lang/String
     303: astore        6
     305: aload         5
     307: invokeinterface #49,  1           // InterfaceMethod java/util/Map$Entry.getValue:()Ljava/lang/Object;
     312: checkcast     #50                 // class java/util/List
     315: astore        7
     317: aload         7
     319: invokeinterface #67,  1           // InterfaceMethod java/util/List.stream:()Ljava/util/stream/Stream;
     324: invokedynamic #68,  0             // InvokeDynamic #1:apply:()Ljava/util/function/Function;
     329: invokeinterface #69,  2           // InterfaceMethod java/util/stream/Stream.map:(Ljava/util/function/Function;)Ljava/util/stream/Stream;
     334: invokedynamic #70,  0             // InvokeDynamic #2:test:()Ljava/util/function/Predicate;
     339: invokeinterface #71,  2           // InterfaceMethod java/util/stream/Stream.filter:(Ljava/util/function/Predicate;)Ljava/util/stream/Stream;
     344: aload         6
     346: invokedynamic #72,  0             // InvokeDynamic #3:test:(Ljava/lang/String;)Ljava/util/function/Predicate;
     351: invokeinterface #71,  2           // InterfaceMethod java/util/stream/Stream.filter:(Ljava/util/function/Predicate;)Ljava/util/stream/Stream;
     356: invokeinterface #73,  1           // InterfaceMethod java/util/stream/Stream.findFirst:()Ljava/util/Optional;
     361: aload_0
     362: aload         6
     364: aload         7
     366: invokedynamic #74,  0             // InvokeDynamic #4:get:(Lorg/apache/dubbo/registry/client/event/listener/ServiceInstancesChangedListener;Ljava/lang/String;Ljava/util/List;)Ljava/util/function/Supplier;
     371: invokevirtual #75                 // Method java/util/Optional.orElseGet:(Ljava/util/function/Supplier;)Ljava/lang/Object;
     374: checkcast     #76                 // class org/apache/dubbo/metadata/MetadataInfo
     377: astore        8
     379: aload_0
     380: aload         6
     382: aload         8
     384: aload_3
     385: invokevirtual #77                 // Method parseMetadata:(Ljava/lang/String;Lorg/apache/dubbo/metadata/MetadataInfo;Ljava/util/Map;)Ljava/util/Map;
     388: pop
     389: aload         7
     391: invokeinterface #51,  1           // InterfaceMethod java/util/List.iterator:()Ljava/util/Iterator;
     396: astore        9
     398: aload         9
     400: invokeinterface #46,  1           // InterfaceMethod java/util/Iterator.hasNext:()Z
     405: ifeq          462
     408: aload         9
     410: invokeinterface #47,  1           // InterfaceMethod java/util/Iterator.next:()Ljava/lang/Object;
     415: checkcast     #52                 // class org/apache/dubbo/registry/client/ServiceInstance
     418: astore        10
     420: aload         10
     422: invokeinterface #78,  1           // InterfaceMethod org/apache/dubbo/registry/client/ServiceInstance.getServiceMetadata:()Lorg/apache/dubbo/metadata/MetadataInfo;
     427: astore        11
     429: aload         11
     431: ifnull        450
     434: aload         11
     436: invokevirtual #79                 // Method org/apache/dubbo/metadata/MetadataInfo.getRevision:()Ljava/lang/String;
     439: aload         8
     441: invokevirtual #79                 // Method org/apache/dubbo/metadata/MetadataInfo.getRevision:()Ljava/lang/String;
     444: invokestatic  #80                 // Method java/util/Objects.equals:(Ljava/lang/Object;Ljava/lang/Object;)Z
     447: ifne          459
     450: aload         10
     452: aload         8
     454: invokeinterface #81,  2           // InterfaceMethod org/apache/dubbo/registry/client/ServiceInstance.setServiceMetadata:(Lorg/apache/dubbo/metadata/MetadataInfo;)V
     459: goto          398
     462: goto          271
     465: aload_0
     466: aload_2
     467: invokevirtual #82                 // Method hasEmptyMetadata:(Ljava/util/Map;)I
     470: istore        4
     472: iload         4
     474: ifeq          622
     477: aload_0
     478: iconst_1
     479: putfield      #83                 // Field hasEmptyMetadata:Z
     482: aload_0
     483: getfield      #20                 // Field retryPermission:Ljava/util/concurrent/Semaphore;
     486: invokevirtual #84                 // Method java/util/concurrent/Semaphore.tryAcquire:()Z
     489: ifeq          594
     492: aload_0
     493: getfield      #85                 // Field retryFuture:Ljava/util/concurrent/ScheduledFuture;
     496: ifnull        522
     499: aload_0
     500: getfield      #85                 // Field retryFuture:Ljava/util/concurrent/ScheduledFuture;
     503: invokeinterface #86,  1           // InterfaceMethod java/util/concurrent/ScheduledFuture.isDone:()Z
     508: ifne          522
     511: aload_0
     512: getfield      #85                 // Field retryFuture:Ljava/util/concurrent/ScheduledFuture;
     515: iconst_1
     516: invokeinterface #87,  2           // InterfaceMethod java/util/concurrent/ScheduledFuture.cancel:(Z)Z
     521: pop
     522: aload_0
     523: aload_0
     524: getfield      #28                 // Field scheduler:Ljava/util/concurrent/ScheduledExecutorService;
     527: new           #88                 // class org/apache/dubbo/registry/client/event/listener/ServiceInstancesChangedListener$AddressRefreshRetryTask
     530: dup
     531: aload_0
     532: aload_0
     533: getfield      #20                 // Field retryPermission:Ljava/util/concurrent/Semaphore;
     536: aload_1
     537: invokevirtual #89                 // Method org/apache/dubbo/registry/client/event/ServiceInstancesChangedEvent.getServiceName:()Ljava/lang/String;
     540: invokespecial #90                 // Method org/apache/dubbo/registry/client/event/listener/ServiceInstancesChangedListener$AddressRefreshRetryTask."<init>":(Lorg/apache/dubbo/registry/client/event/listener/ServiceInstancesChangedListener;Ljava/util/concurrent/Semaphore;Ljava/lang/String;)V
     543: ldc2_w        #91                 // long 10000l
     546: getstatic     #93                 // Field java/util/concurrent/TimeUnit.MILLISECONDS:Ljava/util/concurrent/TimeUnit;
     549: invokeinterface #94,  5           // InterfaceMethod java/util/concurrent/ScheduledExecutorService.schedule:(Ljava/lang/Runnable;JLjava/util/concurrent/TimeUnit;)Ljava/util/concurrent/ScheduledFuture;
     554: putfield      #85                 // Field retryFuture:Ljava/util/concurrent/ScheduledFuture;
     557: goto          578
     560: astore        5
     562: getstatic     #39                 // Field logger:Lorg/apache/dubbo/common/logger/ErrorTypeAwareLogger;
     565: ldc           #96                 // String 99-0
     567: ldc           #97                 // String unknown error in registry module
     569: ldc           #98                 // String
     571: ldc           #99                 // String Error submitting async retry task.
     573: invokeinterface #100,  5          // InterfaceMethod org/apache/dubbo/common/logger/ErrorTypeAwareLogger.error:(Ljava/lang/String;Ljava/lang/String;Ljava/lang/String;Ljava/lang/String;)V
     578: getstatic     #39                 // Field logger:Lorg/apache/dubbo/common/logger/ErrorTypeAwareLogger;
     581: ldc           #96                 // String 99-0
     583: ldc           #97                 // String unknown error in registry module
     585: ldc           #98                 // String
     587: ldc           #101                // String Address refresh try task submitted
     589: invokeinterface #102,  5          // InterfaceMethod org/apache/dubbo/common/logger/ErrorTypeAwareLogger.warn:(Ljava/lang/String;Ljava/lang/String;Ljava/lang/String;Ljava/lang/String;)V
     594: iload         4
     596: aload_2
     597: invokeinterface #103,  1          // InterfaceMethod java/util/Map.size:()I
     602: if_icmpne     622
     605: getstatic     #39                 // Field logger:Lorg/apache/dubbo/common/logger/ErrorTypeAwareLogger;
     608: ldc           #104                // String 1-17
     610: ldc           #105                // String metadata Server failure
     612: ldc           #98                 // String
     614: ldc           #106                // String Address refresh failed because of Metadata Server failure, wait for retry or new address refresh event.
     616: invokeinterface #100,  5          // InterfaceMethod org/apache/dubbo/common/logger/ErrorTypeAwareLogger.error:(Ljava/lang/String;Ljava/lang/String;Ljava/lang/String;Ljava/lang/String;)V
     621: return
     622: aload_0
     623: iconst_0
     624: putfield      #83                 // Field hasEmptyMetadata:Z
     627: new           #14                 // class java/util/HashMap
     630: dup
     631: invokespecial #15                 // Method java/util/HashMap."<init>":()V
     634: astore        5
     636: new           #14                 // class java/util/HashMap
     639: dup
     640: invokespecial #15                 // Method java/util/HashMap."<init>":()V
     643: astore        6
     645: aload_3
     646: invokeinterface #44,  1           // InterfaceMethod java/util/Map.entrySet:()Ljava/util/Set;
     651: invokeinterface #45,  1           // InterfaceMethod java/util/Set.iterator:()Ljava/util/Iterator;
     656: astore        7
     658: aload         7
     660: invokeinterface #46,  1           // InterfaceMethod java/util/Iterator.hasNext:()Z
     665: ifeq          848
     668: aload         7
     670: invokeinterface #47,  1           // InterfaceMethod java/util/Iterator.next:()Ljava/lang/Object;
     675: checkcast     #48                 // class java/util/Map$Entry
     678: astore        8
     680: aload         8
     682: invokeinterface #65,  1           // InterfaceMethod java/util/Map$Entry.getKey:()Ljava/lang/Object;
     687: checkcast     #107                // class org/apache/dubbo/metadata/MetadataInfo$ServiceInfo
     690: astore        9
     692: aload         8
     694: invokeinterface #49,  1           // InterfaceMethod java/util/Map$Entry.getValue:()Ljava/lang/Object;
     699: checkcast     #108                // class java/util/Set
     702: astore        10
     704: aload         5
     706: aload         9
     708: invokevirtual #109                // Method org/apache/dubbo/metadata/MetadataInfo$ServiceInfo.getProtocol:()Ljava/lang/String;
     711: invokedynamic #110,  0            // InvokeDynamic #5:apply:()Ljava/util/function/Function;
     716: invokeinterface #63,  3           // InterfaceMethod java/util/Map.computeIfAbsent:(Ljava/lang/Object;Ljava/util/function/Function;)Ljava/lang/Object;
     721: checkcast     #111                // class java/util/Map
     724: astore        11
     726: aload         11
     728: aload         9
     730: invokevirtual #112                // Method org/apache/dubbo/metadata/MetadataInfo$ServiceInfo.getPort:()I
     733: invokestatic  #113                // Method java/lang/Integer.valueOf:(I)Ljava/lang/Integer;
     736: invokedynamic #114,  0            // InvokeDynamic #6:apply:()Ljava/util/function/Function;
     741: invokeinterface #63,  3           // InterfaceMethod java/util/Map.computeIfAbsent:(Ljava/lang/Object;Ljava/util/function/Function;)Ljava/lang/Object;
     746: checkcast     #111                // class java/util/Map
     749: astore        12
     751: aload         12
     753: aload         10
     755: invokeinterface #115,  2          // InterfaceMethod java/util/Map.get:(Ljava/lang/Object;)Ljava/lang/Object;
     760: astore        13
     762: aload         13
     764: ifnonnull     798
     767: aload_0
     768: aload_2
     769: aload         10
     771: aload         9
     773: invokevirtual #109                // Method org/apache/dubbo/metadata/MetadataInfo$ServiceInfo.getProtocol:()Ljava/lang/String;
     776: aload         9
     778: invokevirtual #112                // Method org/apache/dubbo/metadata/MetadataInfo$ServiceInfo.getPort:()I
     781: invokevirtual #116                // Method getServiceUrlsCache:(Ljava/util/Map;Ljava/util/Set;Ljava/lang/String;I)Ljava/lang/Object;
     784: astore        13
     786: aload         12
     788: aload         10
     790: aload         13
     792: invokeinterface #117,  3          // InterfaceMethod java/util/Map.put:(Ljava/lang/Object;Ljava/lang/Object;)Ljava/lang/Object;
     797: pop
     798: aload         6
     800: aload         9
     802: invokevirtual #118                // Method org/apache/dubbo/metadata/MetadataInfo$ServiceInfo.getPath:()Ljava/lang/String;
     805: invokedynamic #119,  0            // InvokeDynamic #7:apply:()Ljava/util/function/Function;
     810: invokeinterface #63,  3           // InterfaceMethod java/util/Map.computeIfAbsent:(Ljava/lang/Object;Ljava/util/function/Function;)Ljava/lang/Object;
     815: checkcast     #50                 // class java/util/List
     818: astore        14
     820: aload         14
     822: new           #120                // class org/apache/dubbo/registry/client/event/listener/ServiceInstancesChangedListener$ProtocolServiceKeyWithUrls
     825: dup
     826: aload         9
     828: invokevirtual #121                // Method org/apache/dubbo/metadata/MetadataInfo$ServiceInfo.getProtocolServiceKey:()Lorg/apache/dubbo/common/ProtocolServiceKey;
     831: aload         13
     833: checkcast     #50                 // class java/util/List
     836: invokespecial #122                // Method org/apache/dubbo/registry/client/event/listener/ServiceInstancesChangedListener$ProtocolServiceKeyWithUrls."<init>":(Lorg/apache/dubbo/common/ProtocolServiceKey;Ljava/util/List;)V
     839: invokeinterface #64,  2           // InterfaceMethod java/util/List.add:(Ljava/lang/Object;)Z
     844: pop
     845: goto          658
     848: aload_0
     849: aload         6
     851: putfield      #17                 // Field serviceUrls:Ljava/util/Map;
     854: aload_0
     855: invokevirtual #123                // Method notifyAddressChanged:()V
     858: return
    Exception table:
       from    to  target type
         522   557   560   Class java/lang/Exception

  public synchronized void addListenerAndNotify(org.apache.dubbo.common.URL, org.apache.dubbo.registry.NotifyListener);
    Code:
       0: aload_0
       1: getfield      #8                  // Field destroyed:Ljava/util/concurrent/atomic/AtomicBoolean;
       4: invokevirtual #34                 // Method java/util/concurrent/atomic/AtomicBoolean.get:()Z
       7: ifeq          11
      10: return
      11: aload_0
      12: getfield      #13                 // Field listeners:Ljava/util/Map;
      15: aload_1
      16: invokevirtual #124                // Method org/apache/dubbo/common/URL.getServiceKey:()Ljava/lang/String;
      19: invokedynamic #125,  0            // InvokeDynamic #8:apply:()Ljava/util/function/Function;
      24: invokeinterface #63,  3           // InterfaceMethod java/util/Map.computeIfAbsent:(Ljava/lang/Object;Ljava/util/function/Function;)Ljava/lang/Object;
      29: checkcast     #108                // class java/util/Set
      32: astore_3
      33: aload_2
      34: invokeinterface #126,  1          // InterfaceMethod org/apache/dubbo/registry/NotifyListener.getConsumerUrl:()Lorg/apache/dubbo/common/URL;
      39: ldc           #127                // String protocol
      41: aload_1
      42: invokevirtual #128                // Method org/apache/dubbo/common/URL.getProtocol:()Ljava/lang/String;
      45: invokevirtual #129                // Method org/apache/dubbo/common/URL.getParameter:(Ljava/lang/String;Ljava/lang/String;)Ljava/lang/String;
      48: astore        4
      50: new           #130                // class org/apache/dubbo/common/ProtocolServiceKey
      53: dup
      54: aload_1
      55: invokevirtual #131                // Method org/apache/dubbo/common/URL.getServiceInterface:()Ljava/lang/String;
      58: aload_1
      59: invokevirtual #132                // Method org/apache/dubbo/common/URL.getVersion:()Ljava/lang/String;
      62: aload_1
      63: invokevirtual #133                // Method org/apache/dubbo/common/URL.getGroup:()Ljava/lang/String;
      66: ldc           #134                // String consumer
      68: aload         4
      70: invokevirtual #55                 // Method java/lang/String.equals:(Ljava/lang/Object;)Z
      73: ifne          81
      76: aload         4
      78: goto          82
      81: aconst_null
      82: invokespecial #135                // Method org/apache/dubbo/common/ProtocolServiceKey."<init>":(Ljava/lang/String;Ljava/lang/String;Ljava/lang/String;Ljava/lang/String;)V
      85: astore        5
      87: new           #136                // class org/apache/dubbo/registry/client/event/listener/ServiceInstancesChangedListener$NotifyListenerWithKey
      90: dup
      91: aload         5
      93: aload_2
      94: invokespecial #137                // Method org/apache/dubbo/registry/client/event/listener/ServiceInstancesChangedListener$NotifyListenerWithKey."<init>":(Lorg/apache/dubbo/common/ProtocolServiceKey;Lorg/apache/dubbo/registry/NotifyListener;)V
      97: astore        6
      99: aload_3
     100: aload         6
     102: invokeinterface #138,  2          // InterfaceMethod java/util/Set.add:(Ljava/lang/Object;)Z
     107: pop
     108: aload_0
     109: aload         5
     111: aload_2
     112: invokeinterface #126,  1          // InterfaceMethod org/apache/dubbo/registry/NotifyListener.getConsumerUrl:()Lorg/apache/dubbo/common/URL;
     117: invokevirtual #139                // Method getAddresses:(Lorg/apache/dubbo/common/ProtocolServiceKey;Lorg/apache/dubbo/common/URL;)Ljava/util/List;
     120: astore        7
     122: aload         7
     124: invokestatic  #140                // Method org/apache/dubbo/common/utils/CollectionUtils.isNotEmpty:(Ljava/util/Collection;)Z
     127: ifeq          177
     130: getstatic     #39                 // Field logger:Lorg/apache/dubbo/common/logger/ErrorTypeAwareLogger;
     133: ldc           #141                // String Notify serviceKey: %s, listener: %s with %s urls on subscription
     135: iconst_3
     136: anewarray     #142                // class java/lang/Object
     139: dup
     140: iconst_0
     141: aload         5
     143: aastore
     144: dup
     145: iconst_1
     146: aload_2
     147: aastore
     148: dup
     149: iconst_2
     150: aload         7
     152: invokeinterface #143,  1          // InterfaceMethod java/util/List.size:()I
     157: invokestatic  #113                // Method java/lang/Integer.valueOf:(I)Ljava/lang/Integer;
     160: aastore
     161: invokestatic  #144                // Method java/lang/String.format:(Ljava/lang/String;[Ljava/lang/Object;)Ljava/lang/String;
     164: invokeinterface #145,  2          // InterfaceMethod org/apache/dubbo/common/logger/ErrorTypeAwareLogger.info:(Ljava/lang/String;)V
     169: aload_2
     170: aload         7
     172: invokeinterface #146,  2          // InterfaceMethod org/apache/dubbo/registry/NotifyListener.notify:(Ljava/util/List;)V
     177: return

  public synchronized void removeListener(java.lang.String, org.apache.dubbo.registry.NotifyListener);
    Code:
       0: aload_0
       1: getfield      #8                  // Field destroyed:Ljava/util/concurrent/atomic/AtomicBoolean;
       4: invokevirtual #34                 // Method java/util/concurrent/atomic/AtomicBoolean.get:()Z
       7: ifeq          11
      10: return
      11: aload_0
      12: getfield      #13                 // Field listeners:Ljava/util/Map;
      15: aload_1
      16: invokeinterface #115,  2          // InterfaceMethod java/util/Map.get:(Ljava/lang/Object;)Ljava/lang/Object;
      21: checkcast     #108                // class java/util/Set
      24: astore_3
      25: aload_3
      26: ifnull        62
      29: aload_3
      30: aload_2
      31: invokedynamic #147,  0            // InvokeDynamic #9:test:(Lorg/apache/dubbo/registry/NotifyListener;)Ljava/util/function/Predicate;
      36: invokeinterface #148,  2          // InterfaceMethod java/util/Set.removeIf:(Ljava/util/function/Predicate;)Z
      41: pop
      42: aload_3
      43: invokeinterface #149,  1          // InterfaceMethod java/util/Set.size:()I
      48: ifne          62
      51: aload_0
      52: getfield      #13                 // Field listeners:Ljava/util/Map;
      55: aload_1
      56: invokeinterface #150,  2          // InterfaceMethod java/util/Map.remove:(Ljava/lang/Object;)Ljava/lang/Object;
      61: pop
      62: return

  public boolean hasListeners();
    Code:
       0: aload_0
       1: getfield      #13                 // Field listeners:Ljava/util/Map;
       4: invokestatic  #151                // Method org/apache/dubbo/common/utils/CollectionUtils.isNotEmptyMap:(Ljava/util/Map;)Z
       7: ireturn

  public final java.util.Set<java.lang.String> getServiceNames();
    Code:
       0: aload_0
       1: getfield      #9                  // Field serviceNames:Ljava/util/Set;
       4: areturn

  public java.util.Map<java.lang.String, java.util.List<org.apache.dubbo.registry.client.ServiceInstance>> getAllInstances();
    Code:
       0: aload_0
       1: getfield      #16                 // Field allInstances:Ljava/util/Map;
       4: areturn

  private boolean accept(org.apache.dubbo.registry.client.event.ServiceInstancesChangedEvent);
    Code:
       0: aload_0
       1: getfield      #9                  // Field serviceNames:Ljava/util/Set;
       4: aload_1
       5: invokevirtual #89                 // Method org/apache/dubbo/registry/client/event/ServiceInstancesChangedEvent.getServiceName:()Ljava/lang/String;
       8: invokeinterface #152,  2          // InterfaceMethod java/util/Set.contains:(Ljava/lang/Object;)Z
      13: ireturn

  protected boolean isRetryAndExpired(org.apache.dubbo.registry.client.event.ServiceInstancesChangedEvent);
    Code:
       0: aload_1
       1: instanceof    #153                // class org/apache/dubbo/registry/client/event/RetryServiceInstancesChangedEvent
       4: ifeq          133
       7: aload_1
       8: checkcast     #153                // class org/apache/dubbo/registry/client/event/RetryServiceInstancesChangedEvent
      11: astore_2
      12: getstatic     #39                 // Field logger:Lorg/apache/dubbo/common/logger/ErrorTypeAwareLogger;
      15: ldc           #96                 // String 99-0
      17: ldc           #97                 // String unknown error in registry module
      19: ldc           #98                 // String
      21: new           #56                 // class java/lang/StringBuilder
      24: dup
      25: invokespecial #57                 // Method java/lang/StringBuilder."<init>":()V
      28: ldc           #154                // String Received address refresh retry event,
      30: invokevirtual #59                 // Method java/lang/StringBuilder.append:(Ljava/lang/String;)Ljava/lang/StringBuilder;
      33: aload_2
      34: invokevirtual #155                // Method org/apache/dubbo/registry/client/event/RetryServiceInstancesChangedEvent.getFailureRecordTime:()J
      37: invokevirtual #156                // Method java/lang/StringBuilder.append:(J)Ljava/lang/StringBuilder;
      40: invokevirtual #61                 // Method java/lang/StringBuilder.toString:()Ljava/lang/String;
      43: invokeinterface #102,  5          // InterfaceMethod org/apache/dubbo/common/logger/ErrorTypeAwareLogger.warn:(Ljava/lang/String;Ljava/lang/String;Ljava/lang/String;Ljava/lang/String;)V
      48: aload_2
      49: invokevirtual #155                // Method org/apache/dubbo/registry/client/event/RetryServiceInstancesChangedEvent.getFailureRecordTime:()J
      52: aload_0
      53: getfield      #157                // Field lastRefreshTime:J
      56: lcmp
      57: ifge          117
      60: aload_0
      61: getfield      #83                 // Field hasEmptyMetadata:Z
      64: ifne          117
      67: getstatic     #39                 // Field logger:Lorg/apache/dubbo/common/logger/ErrorTypeAwareLogger;
      70: ldc           #96                 // String 99-0
      72: ldc           #97                 // String unknown error in registry module
      74: ldc           #98                 // String
      76: new           #56                 // class java/lang/StringBuilder
      79: dup
      80: invokespecial #57                 // Method java/lang/StringBuilder."<init>":()V
      83: ldc           #158                // String Ignore retry event, event time:
      85: invokevirtual #59                 // Method java/lang/StringBuilder.append:(Ljava/lang/String;)Ljava/lang/StringBuilder;
      88: aload_2
      89: invokevirtual #155                // Method org/apache/dubbo/registry/client/event/RetryServiceInstancesChangedEvent.getFailureRecordTime:()J
      92: invokevirtual #156                // Method java/lang/StringBuilder.append:(J)Ljava/lang/StringBuilder;
      95: ldc           #159                // String , last refresh time:
      97: invokevirtual #59                 // Method java/lang/StringBuilder.append:(Ljava/lang/String;)Ljava/lang/StringBuilder;
     100: aload_0
     101: getfield      #157                // Field lastRefreshTime:J
     104: invokevirtual #156                // Method java/lang/StringBuilder.append:(J)Ljava/lang/StringBuilder;
     107: invokevirtual #61                 // Method java/lang/StringBuilder.toString:()Ljava/lang/String;
     110: invokeinterface #102,  5          // InterfaceMethod org/apache/dubbo/common/logger/ErrorTypeAwareLogger.warn:(Ljava/lang/String;Ljava/lang/String;Ljava/lang/String;Ljava/lang/String;)V
     115: iconst_1
     116: ireturn
     117: getstatic     #39                 // Field logger:Lorg/apache/dubbo/common/logger/ErrorTypeAwareLogger;
     120: ldc           #96                 // String 99-0
     122: ldc           #97                 // String unknown error in registry module
     124: ldc           #98                 // String
     126: ldc           #160                // String Retrying address notification...
     128: invokeinterface #102,  5          // InterfaceMethod org/apache/dubbo/common/logger/ErrorTypeAwareLogger.warn:(Ljava/lang/String;Ljava/lang/String;Ljava/lang/String;Ljava/lang/String;)V
     133: iconst_0
     134: ireturn

  private void refreshInstance(org.apache.dubbo.registry.client.event.ServiceInstancesChangedEvent);
    Code:
       0: aload_1
       1: instanceof    #153                // class org/apache/dubbo/registry/client/event/RetryServiceInstancesChangedEvent
       4: ifeq          8
       7: return
       8: aload_1
       9: invokevirtual #89                 // Method org/apache/dubbo/registry/client/event/ServiceInstancesChangedEvent.getServiceName:()Ljava/lang/String;
      12: astore_2
      13: aload_1
      14: invokevirtual #41                 // Method org/apache/dubbo/registry/client/event/ServiceInstancesChangedEvent.getServiceInstances:()Ljava/util/List;
      17: astore_3
      18: getstatic     #39                 // Field logger:Lorg/apache/dubbo/common/logger/ErrorTypeAwareLogger;
      21: new           #56                 // class java/lang/StringBuilder
      24: dup
      25: invokespecial #57                 // Method java/lang/StringBuilder."<init>":()V
      28: ldc           #161                // String Received instance notification, serviceName:
      30: invokevirtual #59                 // Method java/lang/StringBuilder.append:(Ljava/lang/String;)Ljava/lang/StringBuilder;
      33: aload_2
      34: invokevirtual #59                 // Method java/lang/StringBuilder.append:(Ljava/lang/String;)Ljava/lang/StringBuilder;
      37: ldc           #162                // String , instances:
      39: invokevirtual #59                 // Method java/lang/StringBuilder.append:(Ljava/lang/String;)Ljava/lang/StringBuilder;
      42: aload_3
      43: invokeinterface #143,  1          // InterfaceMethod java/util/List.size:()I
      48: invokevirtual #163                // Method java/lang/StringBuilder.append:(I)Ljava/lang/StringBuilder;
      51: invokevirtual #61                 // Method java/lang/StringBuilder.toString:()Ljava/lang/String;
      54: invokeinterface #145,  2          // InterfaceMethod org/apache/dubbo/common/logger/ErrorTypeAwareLogger.info:(Ljava/lang/String;)V
      59: aload_0
      60: getfield      #32                 // Field serviceInstanceNotificationCustomizers:Ljava/util/Set;
      63: invokeinterface #45,  1           // InterfaceMethod java/util/Set.iterator:()Ljava/util/Iterator;
      68: astore        4
      70: aload         4
      72: invokeinterface #46,  1           // InterfaceMethod java/util/Iterator.hasNext:()Z
      77: ifeq          103
      80: aload         4
      82: invokeinterface #47,  1           // InterfaceMethod java/util/Iterator.next:()Ljava/lang/Object;
      87: checkcast     #29                 // class org/apache/dubbo/registry/client/metadata/ServiceInstanceNotificationCustomizer
      90: astore        5
      92: aload         5
      94: aload_3
      95: invokeinterface #164,  2          // InterfaceMethod org/apache/dubbo/registry/client/metadata/ServiceInstanceNotificationCustomizer.customize:(Ljava/util/List;)V
     100: goto          70
     103: aload_0
     104: getfield      #16                 // Field allInstances:Ljava/util/Map;
     107: aload_2
     108: aload_3
     109: invokeinterface #117,  3          // InterfaceMethod java/util/Map.put:(Ljava/lang/Object;Ljava/lang/Object;)Ljava/lang/Object;
     114: pop
     115: aload_0
     116: invokestatic  #165                // Method java/lang/System.currentTimeMillis:()J
     119: putfield      #157                // Field lastRefreshTime:J
     122: return

  protected int hasEmptyMetadata(java.util.Map<java.lang.String, java.util.List<org.apache.dubbo.registry.client.ServiceInstance>>);
    Code:
       0: aload_1
       1: ifnonnull     6
       4: iconst_0
       5: ireturn
       6: new           #56                 // class java/lang/StringBuilder
       9: dup
      10: invokespecial #57                 // Method java/lang/StringBuilder."<init>":()V
      13: astore_2
      14: iconst_0
      15: istore_3
      16: aload_1
      17: invokeinterface #44,  1           // InterfaceMethod java/util/Map.entrySet:()Ljava/util/Set;
      22: invokeinterface #45,  1           // InterfaceMethod java/util/Set.iterator:()Ljava/util/Iterator;
      27: astore        4
      29: aload         4
      31: invokeinterface #46,  1           // InterfaceMethod java/util/Iterator.hasNext:()Z
      36: ifeq          116
      39: aload         4
      41: invokeinterface #47,  1           // InterfaceMethod java/util/Iterator.next:()Ljava/lang/Object;
      46: checkcast     #48                 // class java/util/Map$Entry
      49: astore        5
      51: aload         5
      53: invokeinterface #49,  1           // InterfaceMethod java/util/Map$Entry.getValue:()Ljava/lang/Object;
      58: checkcast     #50                 // class java/util/List
      61: iconst_0
      62: invokeinterface #166,  2          // InterfaceMethod java/util/List.get:(I)Ljava/lang/Object;
      67: checkcast     #167                // class org/apache/dubbo/registry/client/DefaultServiceInstance
      70: astore        6
      72: aload         6
      74: ifnull        88
      77: aload         6
      79: invokevirtual #168                // Method org/apache/dubbo/registry/client/DefaultServiceInstance.getServiceMetadata:()Lorg/apache/dubbo/metadata/MetadataInfo;
      82: getstatic     #169                // Field org/apache/dubbo/metadata/MetadataInfo.EMPTY:Lorg/apache/dubbo/metadata/MetadataInfo;
      85: if_acmpne     91
      88: iinc          3, 1
      91: aload_2
      92: aload         5
      94: invokeinterface #65,  1           // InterfaceMethod java/util/Map$Entry.getKey:()Ljava/lang/Object;
      99: checkcast     #66                 // class java/lang/String
     102: invokevirtual #59                 // Method java/lang/StringBuilder.append:(Ljava/lang/String;)Ljava/lang/StringBuilder;
     105: pop
     106: aload_2
     107: bipush        32
     109: invokevirtual #170                // Method java/lang/StringBuilder.append:(C)Ljava/lang/StringBuilder;
     112: pop
     113: goto          29
     116: iload_3
     117: ifle          180
     120: aload_2
     121: iconst_0
     122: new           #56                 // class java/lang/StringBuilder
     125: dup
     126: invokespecial #57                 // Method java/lang/StringBuilder."<init>":()V
     129: iload_3
     130: invokevirtual #163                // Method java/lang/StringBuilder.append:(I)Ljava/lang/StringBuilder;
     133: ldc           #171                // String /
     135: invokevirtual #59                 // Method java/lang/StringBuilder.append:(Ljava/lang/String;)Ljava/lang/StringBuilder;
     138: aload_1
     139: invokeinterface #103,  1          // InterfaceMethod java/util/Map.size:()I
     144: invokevirtual #163                // Method java/lang/StringBuilder.append:(I)Ljava/lang/StringBuilder;
     147: ldc           #172                // String  revisions failed to get metadata from remote:
     149: invokevirtual #59                 // Method java/lang/StringBuilder.append:(Ljava/lang/String;)Ljava/lang/StringBuilder;
     152: invokevirtual #61                 // Method java/lang/StringBuilder.toString:()Ljava/lang/String;
     155: invokevirtual #173                // Method java/lang/StringBuilder.insert:(ILjava/lang/String;)Ljava/lang/StringBuilder;
     158: pop
     159: getstatic     #39                 // Field logger:Lorg/apache/dubbo/common/logger/ErrorTypeAwareLogger;
     162: ldc           #96                 // String 99-0
     164: ldc           #97                 // String unknown error in registry module
     166: ldc           #98                 // String
     168: aload_2
     169: invokevirtual #61                 // Method java/lang/StringBuilder.toString:()Ljava/lang/String;
     172: invokeinterface #100,  5          // InterfaceMethod org/apache/dubbo/common/logger/ErrorTypeAwareLogger.error:(Ljava/lang/String;Ljava/lang/String;Ljava/lang/String;Ljava/lang/String;)V
     177: goto          222
     180: aload_2
     181: iconst_0
     182: new           #56                 // class java/lang/StringBuilder
     185: dup
     186: invokespecial #57                 // Method java/lang/StringBuilder."<init>":()V
     189: aload_1
     190: invokeinterface #103,  1          // InterfaceMethod java/util/Map.size:()I
     195: invokevirtual #163                // Method java/lang/StringBuilder.append:(I)Ljava/lang/StringBuilder;
     198: ldc           #174                // String  unique working revisions:
     200: invokevirtual #59                 // Method java/lang/StringBuilder.append:(Ljava/lang/String;)Ljava/lang/StringBuilder;
     203: invokevirtual #61                 // Method java/lang/StringBuilder.toString:()Ljava/lang/String;
     206: invokevirtual #173                // Method java/lang/StringBuilder.insert:(ILjava/lang/String;)Ljava/lang/StringBuilder;
     209: pop
     210: getstatic     #39                 // Field logger:Lorg/apache/dubbo/common/logger/ErrorTypeAwareLogger;
     213: aload_2
     214: invokevirtual #61                 // Method java/lang/StringBuilder.toString:()Ljava/lang/String;
     217: invokeinterface #145,  2          // InterfaceMethod org/apache/dubbo/common/logger/ErrorTypeAwareLogger.info:(Ljava/lang/String;)V
     222: iload_3
     223: ireturn

  protected java.util.Map<org.apache.dubbo.metadata.MetadataInfo$ServiceInfo, java.util.Set<java.lang.String>> parseMetadata(java.lang.String, org.apache.dubbo.metadata.MetadataInfo, java.util.Map<org.apache.dubbo.metadata.MetadataInfo$ServiceInfo, java.util.Set<java.lang.String>>);
    Code:
       0: aload_2
       1: invokevirtual #175                // Method org/apache/dubbo/metadata/MetadataInfo.getServices:()Ljava/util/Map;
       4: astore        4
       6: aload         4
       8: invokeinterface #44,  1           // InterfaceMethod java/util/Map.entrySet:()Ljava/util/Set;
      13: invokeinterface #45,  1           // InterfaceMethod java/util/Set.iterator:()Ljava/util/Iterator;
      18: astore        5
      20: aload         5
      22: invokeinterface #46,  1           // InterfaceMethod java/util/Iterator.hasNext:()Z
      27: ifeq          77
      30: aload         5
      32: invokeinterface #47,  1           // InterfaceMethod java/util/Iterator.next:()Ljava/lang/Object;
      37: checkcast     #48                 // class java/util/Map$Entry
      40: astore        6
      42: aload_3
      43: aload         6
      45: invokeinterface #49,  1           // InterfaceMethod java/util/Map$Entry.getValue:()Ljava/lang/Object;
      50: invokedynamic #176,  0            // InvokeDynamic #10:apply:()Ljava/util/function/Function;
      55: invokeinterface #63,  3           // InterfaceMethod java/util/Map.computeIfAbsent:(Ljava/lang/Object;Ljava/util/function/Function;)Ljava/lang/Object;
      60: checkcast     #108                // class java/util/Set
      63: astore        7
      65: aload         7
      67: aload_1
      68: invokeinterface #138,  2          // InterfaceMethod java/util/Set.add:(Ljava/lang/Object;)Z
      73: pop
      74: goto          20
      77: aload_3
      78: areturn

  protected java.lang.Object getServiceUrlsCache(java.util.Map<java.lang.String, java.util.List<org.apache.dubbo.registry.client.ServiceInstance>>, java.util.Set<java.lang.String>, java.lang.String, int);
    Code:
       0: new           #177                // class java/util/ArrayList
       3: dup
       4: invokespecial #178                // Method java/util/ArrayList."<init>":()V
       7: astore        5
       9: aload_2
      10: invokeinterface #45,  1           // InterfaceMethod java/util/Set.iterator:()Ljava/util/Iterator;
      15: astore        6
      17: aload         6
      19: invokeinterface #46,  1           // InterfaceMethod java/util/Iterator.hasNext:()Z
      24: ifeq          257
      27: aload         6
      29: invokeinterface #47,  1           // InterfaceMethod java/util/Iterator.next:()Ljava/lang/Object;
      34: checkcast     #66                 // class java/lang/String
      37: astore        7
      39: aload_1
      40: aload         7
      42: invokeinterface #115,  2          // InterfaceMethod java/util/Map.get:(Ljava/lang/Object;)Ljava/lang/Object;
      47: checkcast     #50                 // class java/util/List
      50: invokeinterface #51,  1           // InterfaceMethod java/util/List.iterator:()Ljava/util/Iterator;
      55: astore        8
      57: aload         8
      59: invokeinterface #46,  1           // InterfaceMethod java/util/Iterator.hasNext:()Z
      64: ifeq          254
      67: aload         8
      69: invokeinterface #47,  1           // InterfaceMethod java/util/Iterator.next:()Ljava/lang/Object;
      74: checkcast     #52                 // class org/apache/dubbo/registry/client/ServiceInstance
      77: astore        9
      79: iload         4
      81: ifle          160
      84: aload         9
      86: invokeinterface #179,  1          // InterfaceMethod org/apache/dubbo/registry/client/ServiceInstance.getPort:()I
      91: iload         4
      93: if_icmpne     125
      96: aload         5
      98: aload         9
     100: aload_3
     101: invokeinterface #180,  2          // InterfaceMethod org/apache/dubbo/registry/client/ServiceInstance.toURL:(Ljava/lang/String;)Lorg/apache/dubbo/registry/client/InstanceAddressURL;
     106: aload         9
     108: invokeinterface #181,  1          // InterfaceMethod org/apache/dubbo/registry/client/ServiceInstance.getApplicationModel:()Lorg/apache/dubbo/rpc/model/ApplicationModel;
     113: invokevirtual #182                // Method org/apache/dubbo/registry/client/InstanceAddressURL.setScopeModel:(Lorg/apache/dubbo/rpc/model/ScopeModel;)Lorg/apache/dubbo/common/URL;
     116: invokeinterface #64,  2           // InterfaceMethod java/util/List.add:(Ljava/lang/Object;)Z
     121: pop
     122: goto          57
     125: aload         5
     127: aload         9
     129: checkcast     #167                // class org/apache/dubbo/registry/client/DefaultServiceInstance
     132: iload         4
     134: invokevirtual #183                // Method org/apache/dubbo/registry/client/DefaultServiceInstance.copyFrom:(I)Lorg/apache/dubbo/registry/client/DefaultServiceInstance;
     137: aload_3
     138: invokevirtual #184                // Method org/apache/dubbo/registry/client/DefaultServiceInstance.toURL:(Ljava/lang/String;)Lorg/apache/dubbo/registry/client/InstanceAddressURL;
     141: aload         9
     143: invokeinterface #181,  1          // InterfaceMethod org/apache/dubbo/registry/client/ServiceInstance.getApplicationModel:()Lorg/apache/dubbo/rpc/model/ApplicationModel;
     148: invokevirtual #182                // Method org/apache/dubbo/registry/client/InstanceAddressURL.setScopeModel:(Lorg/apache/dubbo/rpc/model/ScopeModel;)Lorg/apache/dubbo/common/URL;
     151: invokeinterface #64,  2           // InterfaceMethod java/util/List.add:(Ljava/lang/Object;)Z
     156: pop
     157: goto          57
     160: aload         9
     162: invokestatic  #185                // Method org/apache/dubbo/registry/client/metadata/ServiceInstanceMetadataUtils.hasEndpoints:(Lorg/apache/dubbo/registry/client/ServiceInstance;)Z
     165: ifeq          225
     168: aload         9
     170: aload_3
     171: invokestatic  #186                // Method org/apache/dubbo/registry/client/metadata/ServiceInstanceMetadataUtils.getEndpoint:(Lorg/apache/dubbo/registry/client/ServiceInstance;Ljava/lang/String;)Lorg/apache/dubbo/registry/client/DefaultServiceInstance$Endpoint;
     174: astore        10
     176: aload         10
     178: ifnull        225
     181: aload         10
     183: invokevirtual #187                // Method org/apache/dubbo/registry/client/DefaultServiceInstance$Endpoint.getPort:()I
     186: aload         9
     188: invokeinterface #179,  1          // InterfaceMethod org/apache/dubbo/registry/client/ServiceInstance.getPort:()I
     193: if_icmpeq     225
     196: aload         5
     198: aload         9
     200: checkcast     #167                // class org/apache/dubbo/registry/client/DefaultServiceInstance
     203: aload         10
     205: invokevirtual #188                // Method org/apache/dubbo/registry/client/DefaultServiceInstance.copyFrom:(Lorg/apache/dubbo/registry/client/DefaultServiceInstance$Endpoint;)Lorg/apache/dubbo/registry/client/DefaultServiceInstance;
     208: aload         10
     210: invokevirtual #189                // Method org/apache/dubbo/registry/client/DefaultServiceInstance$Endpoint.getProtocol:()Ljava/lang/String;
     213: invokevirtual #184                // Method org/apache/dubbo/registry/client/DefaultServiceInstance.toURL:(Ljava/lang/String;)Lorg/apache/dubbo/registry/client/InstanceAddressURL;
     216: invokeinterface #64,  2           // InterfaceMethod java/util/List.add:(Ljava/lang/Object;)Z
     221: pop
     222: goto          57
     225: aload         5
     227: aload         9
     229: aload_3
     230: invokeinterface #180,  2          // InterfaceMethod org/apache/dubbo/registry/client/ServiceInstance.toURL:(Ljava/lang/String;)Lorg/apache/dubbo/registry/client/InstanceAddressURL;
     235: aload         9
     237: invokeinterface #181,  1          // InterfaceMethod org/apache/dubbo/registry/client/ServiceInstance.getApplicationModel:()Lorg/apache/dubbo/rpc/model/ApplicationModel;
     242: invokevirtual #182                // Method org/apache/dubbo/registry/client/InstanceAddressURL.setScopeModel:(Lorg/apache/dubbo/rpc/model/ScopeModel;)Lorg/apache/dubbo/common/URL;
     245: invokeinterface #64,  2           // InterfaceMethod java/util/List.add:(Ljava/lang/Object;)Z
     250: pop
     251: goto          57
     254: goto          17
     257: aload         5
     259: areturn

  protected java.util.List<org.apache.dubbo.common.URL> getAddresses(org.apache.dubbo.common.ProtocolServiceKey, org.apache.dubbo.common.URL);
    Code:
       0: aload_0
       1: getfield      #17                 // Field serviceUrls:Ljava/util/Map;
       4: aload_1
       5: invokevirtual #190                // Method org/apache/dubbo/common/ProtocolServiceKey.getInterfaceName:()Ljava/lang/String;
       8: invokeinterface #115,  2          // InterfaceMethod java/util/Map.get:(Ljava/lang/Object;)Ljava/lang/Object;
      13: checkcast     #50                 // class java/util/List
      16: astore_3
      17: new           #177                // class java/util/ArrayList
      20: dup
      21: invokespecial #178                // Method java/util/ArrayList."<init>":()V
      24: astore        4
      26: aload_3
      27: ifnull        88
      30: aload_3
      31: invokeinterface #51,  1           // InterfaceMethod java/util/List.iterator:()Ljava/util/Iterator;
      36: astore        5
      38: aload         5
      40: invokeinterface #46,  1           // InterfaceMethod java/util/Iterator.hasNext:()Z
      45: ifeq          88
      48: aload         5
      50: invokeinterface #47,  1           // InterfaceMethod java/util/Iterator.next:()Ljava/lang/Object;
      55: checkcast     #120                // class org/apache/dubbo/registry/client/event/listener/ServiceInstancesChangedListener$ProtocolServiceKeyWithUrls
      58: astore        6
      60: aload_1
      61: aload         6
      63: invokevirtual #191                // Method org/apache/dubbo/registry/client/event/listener/ServiceInstancesChangedListener$ProtocolServiceKeyWithUrls.getProtocolServiceKey:()Lorg/apache/dubbo/common/ProtocolServiceKey;
      66: invokestatic  #192                // Method org/apache/dubbo/common/ProtocolServiceKey$Matcher.isMatch:(Lorg/apache/dubbo/common/ProtocolServiceKey;Lorg/apache/dubbo/common/ProtocolServiceKey;)Z
      69: ifeq          85
      72: aload         4
      74: aload         6
      76: invokevirtual #193                // Method org/apache/dubbo/registry/client/event/listener/ServiceInstancesChangedListener$ProtocolServiceKeyWithUrls.getUrls:()Ljava/util/List;
      79: invokeinterface #194,  2          // InterfaceMethod java/util/List.addAll:(Ljava/util/Collection;)Z
      84: pop
      85: goto          38
      88: aload_0
      89: getfield      #17                 // Field serviceUrls:Ljava/util/Map;
      92: ldc           #195                // String *
      94: invokeinterface #196,  2          // InterfaceMethod java/util/Map.containsKey:(Ljava/lang/Object;)Z
      99: ifeq          161
     102: aload_0
     103: getfield      #17                 // Field serviceUrls:Ljava/util/Map;
     106: ldc           #195                // String *
     108: invokeinterface #115,  2          // InterfaceMethod java/util/Map.get:(Ljava/lang/Object;)Ljava/lang/Object;
     113: checkcast     #50                 // class java/util/List
     116: invokeinterface #51,  1           // InterfaceMethod java/util/List.iterator:()Ljava/util/Iterator;
     121: astore        5
     123: aload         5
     125: invokeinterface #46,  1           // InterfaceMethod java/util/Iterator.hasNext:()Z
     130: ifeq          161
     133: aload         5
     135: invokeinterface #47,  1           // InterfaceMethod java/util/Iterator.next:()Ljava/lang/Object;
     140: checkcast     #120                // class org/apache/dubbo/registry/client/event/listener/ServiceInstancesChangedListener$ProtocolServiceKeyWithUrls
     143: astore        6
     145: aload         4
     147: aload         6
     149: invokevirtual #193                // Method org/apache/dubbo/registry/client/event/listener/ServiceInstancesChangedListener$ProtocolServiceKeyWithUrls.getUrls:()Ljava/util/List;
     152: invokeinterface #194,  2          // InterfaceMethod java/util/List.addAll:(Ljava/util/Collection;)Z
     157: pop
     158: goto          123
     161: aload         4
     163: areturn

  protected void notifyAddressChanged();
    Code:
       0: aload_0
       1: getfield      #33                 // Field applicationModel:Lorg/apache/dubbo/rpc/model/ApplicationModel;
       4: invokestatic  #197                // Method org/apache/dubbo/metrics/registry/event/RegistryEvent.toNotifyEvent:(Lorg/apache/dubbo/rpc/model/ApplicationModel;)Lorg/apache/dubbo/metrics/registry/event/RegistryEvent;
       7: aload_0
       8: invokedynamic #198,  0            // InvokeDynamic #11:get:(Lorg/apache/dubbo/registry/client/event/listener/ServiceInstancesChangedListener;)Ljava/util/function/Supplier;
      13: invokestatic  #199                // Method org/apache/dubbo/metrics/event/MetricsEventBus.post:(Lorg/apache/dubbo/metrics/event/MetricsEvent;Ljava/util/function/Supplier;)Ljava/lang/Object;
      16: pop
      17: return

  protected java.util.List<org.apache.dubbo.common.URL> toUrlsWithEmpty(java.util.List<org.apache.dubbo.common.URL>);
    Code:
       0: aload_0
       1: getfield      #10                 // Field serviceDiscovery:Lorg/apache/dubbo/registry/client/ServiceDiscovery;
       4: invokeinterface #21,  1           // InterfaceMethod org/apache/dubbo/registry/client/ServiceDiscovery.getUrl:()Lorg/apache/dubbo/common/URL;
       9: ldc           #200                // String enable-empty-protection
      11: iconst_0
      12: invokevirtual #201                // Method org/apache/dubbo/common/URL.getParameter:(Ljava/lang/String;Z)Z
      15: istore_2
      16: iload_2
      17: ifne          35
      20: aload_1
      21: ifnonnull     35
      24: new           #177                // class java/util/ArrayList
      27: dup
      28: invokespecial #178                // Method java/util/ArrayList."<init>":()V
      31: astore_1
      32: goto          47
      35: iload_2
      36: ifeq          47
      39: aload_1
      40: ifnonnull     47
      43: invokestatic  #202                // Method java/util/Collections.emptyList:()Ljava/util/List;
      46: astore_1
      47: aload_1
      48: invokestatic  #203                // Method org/apache/dubbo/common/utils/CollectionUtils.isEmpty:(Ljava/util/Collection;)Z
      51: ifeq          87
      54: iload_2
      55: ifne          87
      58: aload_0
      59: getfield      #10                 // Field serviceDiscovery:Lorg/apache/dubbo/registry/client/ServiceDiscovery;
      62: invokeinterface #21,  1           // InterfaceMethod org/apache/dubbo/registry/client/ServiceDiscovery.getUrl:()Lorg/apache/dubbo/common/URL;
      67: invokestatic  #204                // Method org/apache/dubbo/common/URLBuilder.from:(Lorg/apache/dubbo/common/URL;)Lorg/apache/dubbo/common/URLBuilder;
      70: ldc           #205                // String empty
      72: invokevirtual #206                // Method org/apache/dubbo/common/URLBuilder.setProtocol:(Ljava/lang/String;)Lorg/apache/dubbo/common/URLBuilder;
      75: invokevirtual #207                // Method org/apache/dubbo/common/URLBuilder.build:()Lorg/apache/dubbo/common/url/component/ServiceConfigURL;
      78: astore_3
      79: aload_1
      80: aload_3
      81: invokeinterface #64,  2           // InterfaceMethod java/util/List.add:(Ljava/lang/Object;)Z
      86: pop
      87: aload_1
      88: areturn

  public void destroy();
    Code:
       0: aload_0
       1: getfield      #8                  // Field destroyed:Ljava/util/concurrent/atomic/AtomicBoolean;
       4: iconst_0
       5: iconst_1
       6: invokevirtual #208                // Method java/util/concurrent/atomic/AtomicBoolean.compareAndSet:(ZZ)Z
       9: ifeq          123
      12: getstatic     #39                 // Field logger:Lorg/apache/dubbo/common/logger/ErrorTypeAwareLogger;
      15: new           #56                 // class java/lang/StringBuilder
      18: dup
      19: invokespecial #57                 // Method java/lang/StringBuilder."<init>":()V
      22: ldc           #209                // String Destroying instance listener of
      24: invokevirtual #59                 // Method java/lang/StringBuilder.append:(Ljava/lang/String;)Ljava/lang/StringBuilder;
      27: aload_0
      28: invokevirtual #210                // Method getServiceNames:()Ljava/util/Set;
      31: invokevirtual #211                // Method java/lang/StringBuilder.append:(Ljava/lang/Object;)Ljava/lang/StringBuilder;
      34: invokevirtual #61                 // Method java/lang/StringBuilder.toString:()Ljava/lang/String;
      37: invokeinterface #145,  2          // InterfaceMethod org/apache/dubbo/common/logger/ErrorTypeAwareLogger.info:(Ljava/lang/String;)V
      42: aload_0
      43: getfield      #10                 // Field serviceDiscovery:Lorg/apache/dubbo/registry/client/ServiceDiscovery;
      46: aload_0
      47: invokeinterface #212,  2          // InterfaceMethod org/apache/dubbo/registry/client/ServiceDiscovery.removeServiceInstancesChangedListener:(Lorg/apache/dubbo/registry/client/event/listener/ServiceInstancesChangedListener;)V
      52: aload_0
      53: dup
      54: astore_1
      55: monitorenter
      56: aload_0
      57: getfield      #16                 // Field allInstances:Ljava/util/Map;
      60: invokeinterface #213,  1          // InterfaceMethod java/util/Map.clear:()V
      65: aload_0
      66: getfield      #17                 // Field serviceUrls:Ljava/util/Map;
      69: invokeinterface #213,  1          // InterfaceMethod java/util/Map.clear:()V
      74: aload_0
      75: getfield      #13                 // Field listeners:Ljava/util/Map;
      78: invokeinterface #213,  1          // InterfaceMethod java/util/Map.clear:()V
      83: aload_0
      84: getfield      #85                 // Field retryFuture:Ljava/util/concurrent/ScheduledFuture;
      87: ifnull        113
      90: aload_0
      91: getfield      #85                 // Field retryFuture:Ljava/util/concurrent/ScheduledFuture;
      94: invokeinterface #86,  1           // InterfaceMethod java/util/concurrent/ScheduledFuture.isDone:()Z
      99: ifne          113
     102: aload_0
     103: getfield      #85                 // Field retryFuture:Ljava/util/concurrent/ScheduledFuture;
     106: iconst_1
     107: invokeinterface #87,  2           // InterfaceMethod java/util/concurrent/ScheduledFuture.cancel:(Z)Z
     112: pop
     113: aload_1
     114: monitorexit
     115: goto          123
     118: astore_2
     119: aload_1
     120: monitorexit
     121: aload_2
     122: athrow
     123: return
    Exception table:
       from    to  target type
          56   115   118   any
         118   121   118   any

  public boolean isDestroyed();
    Code:
       0: aload_0
       1: getfield      #8                  // Field destroyed:Ljava/util/concurrent/atomic/AtomicBoolean;
       4: invokevirtual #34                 // Method java/util/concurrent/atomic/AtomicBoolean.get:()Z
       7: ireturn

  public boolean equals(java.lang.Object);
    Code:
       0: aload_0
       1: aload_1
       2: if_acmpne     7
       5: iconst_1
       6: ireturn
       7: aload_1
       8: instanceof    #214                // class org/apache/dubbo/registry/client/event/listener/ServiceInstancesChangedListener
      11: ifne          16
      14: iconst_0
      15: ireturn
      16: aload_1
      17: checkcast     #214                // class org/apache/dubbo/registry/client/event/listener/ServiceInstancesChangedListener
      20: astore_2
      21: aload_0
      22: invokevirtual #210                // Method getServiceNames:()Ljava/util/Set;
      25: aload_2
      26: invokevirtual #210                // Method getServiceNames:()Ljava/util/Set;
      29: invokestatic  #80                 // Method java/util/Objects.equals:(Ljava/lang/Object;Ljava/lang/Object;)Z
      32: ifeq          53
      35: aload_0
      36: getfield      #13                 // Field listeners:Ljava/util/Map;
      39: aload_2
      40: getfield      #13                 // Field listeners:Ljava/util/Map;
      43: invokestatic  #80                 // Method java/util/Objects.equals:(Ljava/lang/Object;Ljava/lang/Object;)Z
      46: ifeq          53
      49: iconst_1
      50: goto          54
      53: iconst_0
      54: ireturn

  public int hashCode();
    Code:
       0: iconst_3
       1: anewarray     #142                // class java/lang/Object
       4: dup
       5: iconst_0
       6: aload_0
       7: invokevirtual #215                // Method java/lang/Object.getClass:()Ljava/lang/Class;
      10: aastore
      11: dup
      12: iconst_1
      13: aload_0
      14: invokevirtual #210                // Method getServiceNames:()Ljava/util/Set;
      17: aastore
      18: dup
      19: iconst_2
      20: aload_0
      21: getfield      #13                 // Field listeners:Ljava/util/Map;
      24: aastore
      25: invokestatic  #216                // Method java/util/Objects.hash:([Ljava/lang/Object;)I
      28: ireturn

  private java.util.Map lambda$notifyAddressChanged$10();
    Code:
       0: new           #14                 // class java/util/HashMap
       3: dup
       4: invokespecial #15                 // Method java/util/HashMap."<init>":()V
       7: astore_1
       8: aload_0
       9: getfield      #13                 // Field listeners:Ljava/util/Map;
      12: aload_0
      13: aload_1
      14: invokedynamic #217,  0            // InvokeDynamic #12:accept:(Lorg/apache/dubbo/registry/client/event/listener/ServiceInstancesChangedListener;Ljava/util/Map;)Ljava/util/function/BiConsumer;
      19: invokeinterface #218,  2          // InterfaceMethod java/util/Map.forEach:(Ljava/util/function/BiConsumer;)V
      24: aload_1
      25: areturn

  private void lambda$null$9(java.util.Map, java.lang.String, java.util.Set);
    Code:
       0: aload_3
       1: invokeinterface #45,  1           // InterfaceMethod java/util/Set.iterator:()Ljava/util/Iterator;
       6: astore        4
       8: aload         4
      10: invokeinterface #46,  1           // InterfaceMethod java/util/Iterator.hasNext:()Z
      15: ifeq          135
      18: aload         4
      20: invokeinterface #47,  1           // InterfaceMethod java/util/Iterator.next:()Ljava/lang/Object;
      25: checkcast     #136                // class org/apache/dubbo/registry/client/event/listener/ServiceInstancesChangedListener$NotifyListenerWithKey
      28: astore        5
      30: aload         5
      32: invokevirtual #219                // Method org/apache/dubbo/registry/client/event/listener/ServiceInstancesChangedListener$NotifyListenerWithKey.getNotifyListener:()Lorg/apache/dubbo/registry/NotifyListener;
      35: astore        6
      37: aload_0
      38: aload_0
      39: aload         5
      41: invokevirtual #220                // Method org/apache/dubbo/registry/client/event/listener/ServiceInstancesChangedListener$NotifyListenerWithKey.getProtocolServiceKey:()Lorg/apache/dubbo/common/ProtocolServiceKey;
      44: aload         6
      46: invokeinterface #126,  1          // InterfaceMethod org/apache/dubbo/registry/NotifyListener.getConsumerUrl:()Lorg/apache/dubbo/common/URL;
      51: invokevirtual #139                // Method getAddresses:(Lorg/apache/dubbo/common/ProtocolServiceKey;Lorg/apache/dubbo/common/URL;)Ljava/util/List;
      54: invokevirtual #221                // Method toUrlsWithEmpty:(Ljava/util/List;)Ljava/util/List;
      57: astore        7
      59: getstatic     #39                 // Field logger:Lorg/apache/dubbo/common/logger/ErrorTypeAwareLogger;
      62: new           #56                 // class java/lang/StringBuilder
      65: dup
      66: invokespecial #57                 // Method java/lang/StringBuilder."<init>":()V
      69: ldc           #222                // String Notify service
      71: invokevirtual #59                 // Method java/lang/StringBuilder.append:(Ljava/lang/String;)Ljava/lang/StringBuilder;
      74: aload         5
      76: invokevirtual #220                // Method org/apache/dubbo/registry/client/event/listener/ServiceInstancesChangedListener$NotifyListenerWithKey.getProtocolServiceKey:()Lorg/apache/dubbo/common/ProtocolServiceKey;
      79: invokevirtual #211                // Method java/lang/StringBuilder.append:(Ljava/lang/Object;)Ljava/lang/StringBuilder;
      82: ldc           #223                // String  with urls
      84: invokevirtual #59                 // Method java/lang/StringBuilder.append:(Ljava/lang/String;)Ljava/lang/StringBuilder;
      87: aload         7
      89: invokeinterface #143,  1          // InterfaceMethod java/util/List.size:()I
      94: invokevirtual #163                // Method java/lang/StringBuilder.append:(I)Ljava/lang/StringBuilder;
      97: invokevirtual #61                 // Method java/lang/StringBuilder.toString:()Ljava/lang/String;
     100: invokeinterface #145,  2          // InterfaceMethod org/apache/dubbo/common/logger/ErrorTypeAwareLogger.info:(Ljava/lang/String;)V
     105: aload         6
     107: aload         7
     109: invokeinterface #146,  2          // InterfaceMethod org/apache/dubbo/registry/NotifyListener.notify:(Ljava/util/List;)V
     114: aload_1
     115: aload_2
     116: aload         7
     118: invokeinterface #143,  1          // InterfaceMethod java/util/List.size:()I
     123: invokestatic  #113                // Method java/lang/Integer.valueOf:(I)Ljava/lang/Integer;
     126: invokeinterface #117,  3          // InterfaceMethod java/util/Map.put:(Ljava/lang/Object;Ljava/lang/Object;)Ljava/lang/Object;
     131: pop
     132: goto          8
     135: return

  private static java.util.Set lambda$parseMetadata$8(org.apache.dubbo.metadata.MetadataInfo$ServiceInfo);
    Code:
       0: new           #224                // class java/util/TreeSet
       3: dup
       4: invokespecial #225                // Method java/util/TreeSet."<init>":()V
       7: areturn

  private static boolean lambda$removeListener$7(org.apache.dubbo.registry.NotifyListener, org.apache.dubbo.registry.client.event.listener.ServiceInstancesChangedListener$NotifyListenerWithKey);
    Code:
       0: aload_1
       1: invokevirtual #219                // Method org/apache/dubbo/registry/client/event/listener/ServiceInstancesChangedListener$NotifyListenerWithKey.getNotifyListener:()Lorg/apache/dubbo/registry/NotifyListener;
       4: aload_0
       5: invokevirtual #226                // Method java/lang/Object.equals:(Ljava/lang/Object;)Z
       8: ireturn

  private static java.util.Set lambda$addListenerAndNotify$6(java.lang.String);
    Code:
       0: new           #227                // class org/apache/dubbo/common/utils/ConcurrentHashSet
       3: dup
       4: invokespecial #228                // Method org/apache/dubbo/common/utils/ConcurrentHashSet."<init>":()V
       7: areturn

  private static java.util.List lambda$doOnEvent$5(java.lang.String);
    Code:
       0: new           #229                // class java/util/LinkedList
       3: dup
       4: invokespecial #230                // Method java/util/LinkedList."<init>":()V
       7: areturn

  private static java.util.Map lambda$doOnEvent$4(java.lang.Integer);
    Code:
       0: new           #14                 // class java/util/HashMap
       3: dup
       4: invokespecial #15                 // Method java/util/HashMap."<init>":()V
       7: areturn

  private static java.util.Map lambda$doOnEvent$3(java.lang.String);
    Code:
       0: new           #14                 // class java/util/HashMap
       3: dup
       4: invokespecial #15                 // Method java/util/HashMap."<init>":()V
       7: areturn

  private org.apache.dubbo.metadata.MetadataInfo lambda$doOnEvent$2(java.lang.String, java.util.List);
    Code:
       0: aload_0
       1: getfield      #10                 // Field serviceDiscovery:Lorg/apache/dubbo/registry/client/ServiceDiscovery;
       4: aload_1
       5: aload_2
       6: invokeinterface #231,  3          // InterfaceMethod org/apache/dubbo/registry/client/ServiceDiscovery.getRemoteMetadata:(Ljava/lang/String;Ljava/util/List;)Lorg/apache/dubbo/metadata/MetadataInfo;
      11: areturn

  private static boolean lambda$doOnEvent$1(java.lang.String, org.apache.dubbo.metadata.MetadataInfo);
    Code:
       0: aload_0
       1: aload_1
       2: invokevirtual #79                 // Method org/apache/dubbo/metadata/MetadataInfo.getRevision:()Ljava/lang/String;
       5: invokevirtual #55                 // Method java/lang/String.equals:(Ljava/lang/Object;)Z
       8: ireturn

  private static java.util.List lambda$doOnEvent$0(java.lang.String);
    Code:
       0: new           #229                // class java/util/LinkedList
       3: dup
       4: invokespecial #230                // Method java/util/LinkedList."<init>":()V
       7: areturn

  static {};
    Code:
       0: ldc           #214                // class org/apache/dubbo/registry/client/event/listener/ServiceInstancesChangedListener
       2: invokestatic  #232                // Method org/apache/dubbo/common/logger/LoggerFactory.getErrorTypeAwareLogger:(Ljava/lang/Class;)Lorg/apache/dubbo/common/logger/ErrorTypeAwareLogger;
       5: putstatic     #39                 // Field logger:Lorg/apache/dubbo/common/logger/ErrorTypeAwareLogger;
       8: return
}
