Compiled from "ServiceInstancesChangedListener.java"
public class org.apache.dubbo.registry.client.event.listener.ServiceInstancesChangedListener$ProtocolServiceKeyWithUrls {
  private final org.apache.dubbo.common.ProtocolServiceKey protocolServiceKey;

  private final java.util.List<org.apache.dubbo.common.URL> urls;

  public org.apache.dubbo.registry.client.event.listener.ServiceInstancesChangedListener$ProtocolServiceKeyWithUrls(org.apache.dubbo.common.ProtocolServiceKey, java.util.List<org.apache.dubbo.common.URL>);
    Code:
       0: aload_0
       1: invokespecial #1                  // Method java/lang/Object."<init>":()V
       4: aload_0
       5: aload_1
       6: putfield      #2                  // Field protocolServiceKey:Lorg/apache/dubbo/common/ProtocolServiceKey;
       9: aload_0
      10: aload_2
      11: putfield      #3                  // Field urls:Ljava/util/List;
      14: return

  public org.apache.dubbo.common.ProtocolServiceKey getProtocolServiceKey();
    Code:
       0: aload_0
       1: getfield      #2                  // Field protocolServiceKey:Lorg/apache/dubbo/common/ProtocolServiceKey;
       4: areturn

  public java.util.List<org.apache.dubbo.common.URL> getUrls();
    Code:
       0: aload_0
       1: getfield      #3                  // Field urls:Ljava/util/List;
       4: areturn
}
