Compiled from "CommandHelper.java"
public class org.apache.dubbo.qos.command.util.CommandHelper {
  private final org.apache.dubbo.rpc.model.FrameworkModel frameworkModel;

  public org.apache.dubbo.qos.command.util.CommandHelper(org.apache.dubbo.rpc.model.FrameworkModel);
    Code:
       0: aload_0
       1: invokespecial #1                  // Method java/lang/Object."<init>":()V
       4: aload_0
       5: aload_1
       6: putfield      #2                  // Field frameworkModel:Lorg/apache/dubbo/rpc/model/FrameworkModel;
       9: return

  public boolean hasCommand(java.lang.String);
    Code:
       0: aload_0
       1: getfield      #2                  // Field frameworkModel:Lorg/apache/dubbo/rpc/model/FrameworkModel;
       4: ldc           #3                  // class org/apache/dubbo/qos/api/BaseCommand
       6: invokevirtual #4                  // Method org/apache/dubbo/rpc/model/FrameworkModel.getExtensionLoader:(Ljava/lang/Class;)Lorg/apache/dubbo/common/extension/ExtensionLoader;
       9: aload_1
      10: invokevirtual #5                  // Method org/apache/dubbo/common/extension/ExtensionLoader.getExtension:(Ljava/lang/String;)Ljava/lang/Object;
      13: checkcast     #3                  // class org/apache/dubbo/qos/api/BaseCommand
      16: astore_2
      17: goto          23
      20: astore_3
      21: iconst_0
      22: ireturn
      23: aload_2
      24: ifnull        31
      27: iconst_1
      28: goto          32
      31: iconst_0
      32: ireturn
    Exception table:
       from    to  target type
           0    17    20   Class java/lang/Throwable

  public java.util.List<java.lang.Class<?>> getAllCommandClass();
    Code:
       0: aload_0
       1: getfield      #2                  // Field frameworkModel:Lorg/apache/dubbo/rpc/model/FrameworkModel;
       4: ldc           #3                  // class org/apache/dubbo/qos/api/BaseCommand
       6: invokevirtual #4                  // Method org/apache/dubbo/rpc/model/FrameworkModel.getExtensionLoader:(Ljava/lang/Class;)Lorg/apache/dubbo/common/extension/ExtensionLoader;
       9: invokevirtual #7                  // Method org/apache/dubbo/common/extension/ExtensionLoader.getSupportedExtensions:()Ljava/util/Set;
      12: astore_1
      13: new           #8                  // class java/util/ArrayList
      16: dup
      17: invokespecial #9                  // Method java/util/ArrayList."<init>":()V
      20: astore_2
      21: aload_1
      22: invokeinterface #10,  1           // InterfaceMethod java/util/Set.iterator:()Ljava/util/Iterator;
      27: astore_3
      28: aload_3
      29: invokeinterface #11,  1           // InterfaceMethod java/util/Iterator.hasNext:()Z
      34: ifeq          82
      37: aload_3
      38: invokeinterface #12,  1           // InterfaceMethod java/util/Iterator.next:()Ljava/lang/Object;
      43: checkcast     #13                 // class java/lang/String
      46: astore        4
      48: aload_0
      49: getfield      #2                  // Field frameworkModel:Lorg/apache/dubbo/rpc/model/FrameworkModel;
      52: ldc           #3                  // class org/apache/dubbo/qos/api/BaseCommand
      54: invokevirtual #4                  // Method org/apache/dubbo/rpc/model/FrameworkModel.getExtensionLoader:(Ljava/lang/Class;)Lorg/apache/dubbo/common/extension/ExtensionLoader;
      57: aload         4
      59: invokevirtual #5                  // Method org/apache/dubbo/common/extension/ExtensionLoader.getExtension:(Ljava/lang/String;)Ljava/lang/Object;
      62: checkcast     #3                  // class org/apache/dubbo/qos/api/BaseCommand
      65: astore        5
      67: aload_2
      68: aload         5
      70: invokevirtual #14                 // Method java/lang/Object.getClass:()Ljava/lang/Class;
      73: invokeinterface #15,  2           // InterfaceMethod java/util/List.add:(Ljava/lang/Object;)Z
      78: pop
      79: goto          28
      82: aload_2
      83: areturn

  public java.lang.Class<?> getCommandClass(java.lang.String);
    Code:
       0: aload_0
       1: aload_1
       2: invokevirtual #16                 // Method hasCommand:(Ljava/lang/String;)Z
       5: ifeq          28
       8: aload_0
       9: getfield      #2                  // Field frameworkModel:Lorg/apache/dubbo/rpc/model/FrameworkModel;
      12: ldc           #3                  // class org/apache/dubbo/qos/api/BaseCommand
      14: invokevirtual #4                  // Method org/apache/dubbo/rpc/model/FrameworkModel.getExtensionLoader:(Ljava/lang/Class;)Lorg/apache/dubbo/common/extension/ExtensionLoader;
      17: aload_1
      18: invokevirtual #5                  // Method org/apache/dubbo/common/extension/ExtensionLoader.getExtension:(Ljava/lang/String;)Ljava/lang/Object;
      21: checkcast     #3                  // class org/apache/dubbo/qos/api/BaseCommand
      24: invokevirtual #14                 // Method java/lang/Object.getClass:()Ljava/lang/Class;
      27: areturn
      28: aconst_null
      29: areturn
}
