Compiled from "SerializeCheckUtils.java"
public class org.apache.dubbo.qos.command.util.SerializeCheckUtils implements org.apache.dubbo.common.utils.AllowClassNotifyListener {
  private final org.apache.dubbo.common.utils.SerializeSecurityManager manager;

  private volatile java.util.Set<java.lang.String> allowedList;

  private volatile java.util.Set<java.lang.String> disAllowedList;

  private volatile org.apache.dubbo.common.utils.SerializeCheckStatus status;

  private volatile boolean checkSerializable;

  public org.apache.dubbo.qos.command.util.SerializeCheckUtils(org.apache.dubbo.rpc.model.FrameworkModel);
    Code:
       0: aload_0
       1: invokespecial #1                  // Method java/lang/Object."<init>":()V
       4: aload_0
       5: invokestatic  #2                  // Method java/util/Collections.emptySet:()Ljava/util/Set;
       8: putfield      #3                  // Field allowedList:Ljava/util/Set;
      11: aload_0
      12: invokestatic  #2                  // Method java/util/Collections.emptySet:()Ljava/util/Set;
      15: putfield      #4                  // Field disAllowedList:Ljava/util/Set;
      18: aload_0
      19: getstatic     #5                  // Field org/apache/dubbo/common/utils/AllowClassNotifyListener.DEFAULT_STATUS:Lorg/apache/dubbo/common/utils/SerializeCheckStatus;
      22: putfield      #6                  // Field status:Lorg/apache/dubbo/common/utils/SerializeCheckStatus;
      25: aload_0
      26: iconst_1
      27: putfield      #7                  // Field checkSerializable:Z
      30: aload_0
      31: aload_1
      32: invokevirtual #8                  // Method org/apache/dubbo/rpc/model/FrameworkModel.getBeanFactory:()Lorg/apache/dubbo/common/beans/factory/ScopeBeanFactory;
      35: ldc           #9                  // class org/apache/dubbo/common/utils/SerializeSecurityManager
      37: invokevirtual #10                 // Method org/apache/dubbo/common/beans/factory/ScopeBeanFactory.getOrRegisterBean:(Ljava/lang/Class;)Ljava/lang/Object;
      40: checkcast     #9                  // class org/apache/dubbo/common/utils/SerializeSecurityManager
      43: putfield      #11                 // Field manager:Lorg/apache/dubbo/common/utils/SerializeSecurityManager;
      46: aload_0
      47: getfield      #11                 // Field manager:Lorg/apache/dubbo/common/utils/SerializeSecurityManager;
      50: aload_0
      51: invokevirtual #12                 // Method org/apache/dubbo/common/utils/SerializeSecurityManager.registerListener:(Lorg/apache/dubbo/common/utils/AllowClassNotifyListener;)V
      54: return

  public void notifyPrefix(java.util.Set<java.lang.String>, java.util.Set<java.lang.String>);
    Code:
       0: aload_0
       1: aload_1
       2: putfield      #3                  // Field allowedList:Ljava/util/Set;
       5: aload_0
       6: aload_2
       7: putfield      #4                  // Field disAllowedList:Ljava/util/Set;
      10: return

  public void notifyCheckStatus(org.apache.dubbo.common.utils.SerializeCheckStatus);
    Code:
       0: aload_0
       1: aload_1
       2: putfield      #6                  // Field status:Lorg/apache/dubbo/common/utils/SerializeCheckStatus;
       5: return

  public void notifyCheckSerializable(boolean);
    Code:
       0: aload_0
       1: iload_1
       2: putfield      #7                  // Field checkSerializable:Z
       5: return

  public java.util.Set<java.lang.String> getAllowedList();
    Code:
       0: aload_0
       1: getfield      #3                  // Field allowedList:Ljava/util/Set;
       4: areturn

  public java.util.Set<java.lang.String> getDisAllowedList();
    Code:
       0: aload_0
       1: getfield      #4                  // Field disAllowedList:Ljava/util/Set;
       4: areturn

  public org.apache.dubbo.common.utils.SerializeCheckStatus getStatus();
    Code:
       0: aload_0
       1: getfield      #6                  // Field status:Lorg/apache/dubbo/common/utils/SerializeCheckStatus;
       4: areturn

  public boolean isCheckSerializable();
    Code:
       0: aload_0
       1: getfield      #7                  // Field checkSerializable:Z
       4: ireturn

  public java.util.Set<java.lang.String> getWarnedClasses();
    Code:
       0: aload_0
       1: getfield      #11                 // Field manager:Lorg/apache/dubbo/common/utils/SerializeSecurityManager;
       4: invokevirtual #13                 // Method org/apache/dubbo/common/utils/SerializeSecurityManager.getWarnedClasses:()Ljava/util/Set;
       7: areturn
}
