Compiled from "ServiceCheckUtils.java"
public class org.apache.dubbo.qos.command.util.ServiceCheckUtils {
  public org.apache.dubbo.qos.command.util.ServiceCheckUtils();
    Code:
       0: aload_0
       1: invokespecial #1                  // Method java/lang/Object."<init>":()V
       4: return

  public static java.lang.String getRegisterStatus(org.apache.dubbo.rpc.model.ProviderModel);
    Code:
       0: new           #2                  // class java/util/LinkedList
       3: dup
       4: invokespecial #3                  // Method java/util/LinkedList."<init>":()V
       7: astore_1
       8: aload_0
       9: invokevirtual #4                  // Method org/apache/dubbo/rpc/model/ProviderModel.getStatedUrl:()Ljava/util/List;
      12: invokeinterface #5,  1            // InterfaceMethod java/util/List.iterator:()Ljava/util/Iterator;
      17: astore_2
      18: aload_2
      19: invokeinterface #6,  1            // InterfaceMethod java/util/Iterator.hasNext:()Z
      24: ifeq          144
      27: aload_2
      28: invokeinterface #7,  1            // InterfaceMethod java/util/Iterator.next:()Ljava/lang/Object;
      33: checkcast     #8                  // class org/apache/dubbo/rpc/model/ProviderModel$RegisterStatedURL
      36: astore_3
      37: aload_3
      38: invokevirtual #9                  // Method org/apache/dubbo/rpc/model/ProviderModel$RegisterStatedURL.getRegistryUrl:()Lorg/apache/dubbo/common/URL;
      41: astore        4
      43: aload         4
      45: invokestatic  #10                 // Method org/apache/dubbo/common/utils/UrlUtils.isServiceDiscoveryURL:(Lorg/apache/dubbo/common/URL;)Z
      48: istore        5
      50: iload         5
      52: ifeq          65
      55: aload         4
      57: ldc           #12                 // String registry
      59: invokevirtual #13                 // Method org/apache/dubbo/common/URL.getParameter:(Ljava/lang/String;)Ljava/lang/String;
      62: goto          70
      65: aload         4
      67: invokevirtual #14                 // Method org/apache/dubbo/common/URL.getProtocol:()Ljava/lang/String;
      70: astore        6
      72: aload_1
      73: new           #15                 // class java/lang/StringBuilder
      76: dup
      77: invokespecial #16                 // Method java/lang/StringBuilder."<init>":()V
      80: aload         6
      82: invokevirtual #17                 // Method java/lang/StringBuilder.append:(Ljava/lang/String;)Ljava/lang/StringBuilder;
      85: ldc           #18                 // String -
      87: invokevirtual #17                 // Method java/lang/StringBuilder.append:(Ljava/lang/String;)Ljava/lang/StringBuilder;
      90: iload         5
      92: ifeq          100
      95: ldc           #19                 // String A
      97: goto          102
     100: ldc           #20                 // String I
     102: invokevirtual #17                 // Method java/lang/StringBuilder.append:(Ljava/lang/String;)Ljava/lang/StringBuilder;
     105: ldc           #21                 // String (
     107: invokevirtual #17                 // Method java/lang/StringBuilder.append:(Ljava/lang/String;)Ljava/lang/StringBuilder;
     110: aload_3
     111: invokevirtual #22                 // Method org/apache/dubbo/rpc/model/ProviderModel$RegisterStatedURL.isRegistered:()Z
     114: ifeq          122
     117: ldc           #23                 // String Y
     119: goto          124
     122: ldc           #24                 // String N
     124: invokevirtual #17                 // Method java/lang/StringBuilder.append:(Ljava/lang/String;)Ljava/lang/StringBuilder;
     127: ldc           #25                 // String )
     129: invokevirtual #17                 // Method java/lang/StringBuilder.append:(Ljava/lang/String;)Ljava/lang/StringBuilder;
     132: invokevirtual #26                 // Method java/lang/StringBuilder.toString:()Ljava/lang/String;
     135: invokeinterface #27,  2           // InterfaceMethod java/util/List.add:(Ljava/lang/Object;)Z
     140: pop
     141: goto          18
     144: ldc           #28                 // String /
     146: aload_1
     147: iconst_0
     148: anewarray     #29                 // class java/lang/String
     151: invokeinterface #30,  2           // InterfaceMethod java/util/List.toArray:([Ljava/lang/Object;)[Ljava/lang/Object;
     156: checkcast     #31                 // class "[Ljava/lang/CharSequence;"
     159: invokestatic  #32                 // Method java/lang/String.join:(Ljava/lang/CharSequence;[Ljava/lang/CharSequence;)Ljava/lang/String;
     162: areturn

  public static java.lang.String getConsumerAddressNum(org.apache.dubbo.rpc.model.ConsumerModel);
    Code:
       0: iconst_0
       1: istore_1
       2: aload_0
       3: invokevirtual #33                 // Method org/apache/dubbo/rpc/model/ConsumerModel.getServiceMetadata:()Lorg/apache/dubbo/rpc/model/ServiceMetadata;
       6: ldc           #35                 // String currentClusterInvoker
       8: invokevirtual #36                 // Method org/apache/dubbo/rpc/model/ServiceMetadata.getAttribute:(Ljava/lang/String;)Ljava/lang/Object;
      11: astore_2
      12: new           #2                  // class java/util/LinkedList
      15: dup
      16: invokespecial #3                  // Method java/util/LinkedList."<init>":()V
      19: astore        4
      21: aload_2
      22: instanceof    #37                 // class java/util/Map
      25: ifeq          377
      28: aload_2
      29: checkcast     #37                 // class java/util/Map
      32: astore_3
      33: aload_3
      34: invokeinterface #38,  1           // InterfaceMethod java/util/Map.entrySet:()Ljava/util/Set;
      39: invokeinterface #39,  1           // InterfaceMethod java/util/Set.iterator:()Ljava/util/Iterator;
      44: astore        5
      46: aload         5
      48: invokeinterface #6,  1            // InterfaceMethod java/util/Iterator.hasNext:()Z
      53: ifeq          377
      56: aload         5
      58: invokeinterface #7,  1            // InterfaceMethod java/util/Iterator.next:()Ljava/lang/Object;
      63: checkcast     #40                 // class java/util/Map$Entry
      66: astore        6
      68: aload         6
      70: invokeinterface #41,  1           // InterfaceMethod java/util/Map$Entry.getKey:()Ljava/lang/Object;
      75: checkcast     #42                 // class org/apache/dubbo/registry/Registry
      78: invokeinterface #43,  1           // InterfaceMethod org/apache/dubbo/registry/Registry.getUrl:()Lorg/apache/dubbo/common/URL;
      83: astore        7
      85: aload         7
      87: invokestatic  #10                 // Method org/apache/dubbo/common/utils/UrlUtils.isServiceDiscoveryURL:(Lorg/apache/dubbo/common/URL;)Z
      90: istore        8
      92: iload         8
      94: ifeq          107
      97: aload         7
      99: ldc           #12                 // String registry
     101: invokevirtual #13                 // Method org/apache/dubbo/common/URL.getParameter:(Ljava/lang/String;)Ljava/lang/String;
     104: goto          112
     107: aload         7
     109: invokevirtual #14                 // Method org/apache/dubbo/common/URL.getProtocol:()Ljava/lang/String;
     112: astore        9
     114: aload         6
     116: invokeinterface #44,  1           // InterfaceMethod java/util/Map$Entry.getValue:()Ljava/lang/Object;
     121: checkcast     #45                 // class org/apache/dubbo/registry/client/migration/MigrationInvoker
     124: astore        10
     126: aload         10
     128: invokevirtual #46                 // Method org/apache/dubbo/registry/client/migration/MigrationInvoker.getMigrationStep:()Lorg/apache/dubbo/registry/client/migration/model/MigrationStep;
     131: astore        11
     133: aload         10
     135: invokevirtual #47                 // Method org/apache/dubbo/registry/client/migration/MigrationInvoker.getInvoker:()Lorg/apache/dubbo/rpc/cluster/ClusterInvoker;
     138: invokestatic  #48                 // Method java/util/Optional.ofNullable:(Ljava/lang/Object;)Ljava/util/Optional;
     141: invokedynamic #49,  0             // InvokeDynamic #0:apply:()Ljava/util/function/Function;
     146: invokevirtual #50                 // Method java/util/Optional.map:(Ljava/util/function/Function;)Ljava/util/Optional;
     149: invokedynamic #51,  0             // InvokeDynamic #1:apply:()Ljava/util/function/Function;
     154: invokevirtual #50                 // Method java/util/Optional.map:(Ljava/util/function/Function;)Ljava/util/Optional;
     157: invokedynamic #52,  0             // InvokeDynamic #2:apply:()Ljava/util/function/Function;
     162: invokevirtual #50                 // Method java/util/Optional.map:(Ljava/util/function/Function;)Ljava/util/Optional;
     165: invokedynamic #53,  0             // InvokeDynamic #3:apply:()Ljava/util/function/Function;
     170: invokevirtual #50                 // Method java/util/Optional.map:(Ljava/util/function/Function;)Ljava/util/Optional;
     173: ldc           #18                 // String -
     175: invokevirtual #54                 // Method java/util/Optional.orElse:(Ljava/lang/Object;)Ljava/lang/Object;
     178: checkcast     #29                 // class java/lang/String
     181: astore        12
     183: aload         10
     185: invokevirtual #55                 // Method org/apache/dubbo/registry/client/migration/MigrationInvoker.getServiceDiscoveryInvoker:()Lorg/apache/dubbo/rpc/cluster/ClusterInvoker;
     188: invokestatic  #48                 // Method java/util/Optional.ofNullable:(Ljava/lang/Object;)Ljava/util/Optional;
     191: invokedynamic #49,  0             // InvokeDynamic #0:apply:()Ljava/util/function/Function;
     196: invokevirtual #50                 // Method java/util/Optional.map:(Ljava/util/function/Function;)Ljava/util/Optional;
     199: invokedynamic #51,  0             // InvokeDynamic #1:apply:()Ljava/util/function/Function;
     204: invokevirtual #50                 // Method java/util/Optional.map:(Ljava/util/function/Function;)Ljava/util/Optional;
     207: invokedynamic #52,  0             // InvokeDynamic #2:apply:()Ljava/util/function/Function;
     212: invokevirtual #50                 // Method java/util/Optional.map:(Ljava/util/function/Function;)Ljava/util/Optional;
     215: invokedynamic #53,  0             // InvokeDynamic #3:apply:()Ljava/util/function/Function;
     220: invokevirtual #50                 // Method java/util/Optional.map:(Ljava/util/function/Function;)Ljava/util/Optional;
     223: ldc           #18                 // String -
     225: invokevirtual #54                 // Method java/util/Optional.orElse:(Ljava/lang/Object;)Ljava/lang/Object;
     228: checkcast     #29                 // class java/lang/String
     231: astore        13
     233: getstatic     #56                 // Field org/apache/dubbo/qos/command/util/ServiceCheckUtils$1.$SwitchMap$org$apache$dubbo$registry$client$migration$model$MigrationStep:[I
     236: aload         11
     238: invokevirtual #57                 // Method org/apache/dubbo/registry/client/migration/model/MigrationStep.ordinal:()I
     241: iaload
     242: lookupswitch  { // 2
                     1: 268
                     2: 307
               default: 318
          }
     268: ldc           #58                 // String AF
     270: astore        14
     272: new           #15                 // class java/lang/StringBuilder
     275: dup
     276: invokespecial #16                 // Method java/lang/StringBuilder."<init>":()V
     279: ldc           #59                 // String I-
     281: invokevirtual #17                 // Method java/lang/StringBuilder.append:(Ljava/lang/String;)Ljava/lang/StringBuilder;
     284: aload         12
     286: invokevirtual #17                 // Method java/lang/StringBuilder.append:(Ljava/lang/String;)Ljava/lang/StringBuilder;
     289: ldc           #60                 // String ,A-
     291: invokevirtual #17                 // Method java/lang/StringBuilder.append:(Ljava/lang/String;)Ljava/lang/StringBuilder;
     294: aload         13
     296: invokevirtual #17                 // Method java/lang/StringBuilder.append:(Ljava/lang/String;)Ljava/lang/StringBuilder;
     299: invokevirtual #26                 // Method java/lang/StringBuilder.toString:()Ljava/lang/String;
     302: astore        15
     304: goto          326
     307: ldc           #20                 // String I
     309: astore        14
     311: aload         12
     313: astore        15
     315: goto          326
     318: ldc           #19                 // String A
     320: astore        14
     322: aload         13
     324: astore        15
     326: aload         4
     328: new           #15                 // class java/lang/StringBuilder
     331: dup
     332: invokespecial #16                 // Method java/lang/StringBuilder."<init>":()V
     335: aload         9
     337: invokevirtual #17                 // Method java/lang/StringBuilder.append:(Ljava/lang/String;)Ljava/lang/StringBuilder;
     340: ldc           #18                 // String -
     342: invokevirtual #17                 // Method java/lang/StringBuilder.append:(Ljava/lang/String;)Ljava/lang/StringBuilder;
     345: aload         14
     347: invokevirtual #17                 // Method java/lang/StringBuilder.append:(Ljava/lang/String;)Ljava/lang/StringBuilder;
     350: ldc           #21                 // String (
     352: invokevirtual #17                 // Method java/lang/StringBuilder.append:(Ljava/lang/String;)Ljava/lang/StringBuilder;
     355: aload         15
     357: invokevirtual #17                 // Method java/lang/StringBuilder.append:(Ljava/lang/String;)Ljava/lang/StringBuilder;
     360: ldc           #25                 // String )
     362: invokevirtual #17                 // Method java/lang/StringBuilder.append:(Ljava/lang/String;)Ljava/lang/StringBuilder;
     365: invokevirtual #26                 // Method java/lang/StringBuilder.toString:()Ljava/lang/String;
     368: invokeinterface #27,  2           // InterfaceMethod java/util/List.add:(Ljava/lang/Object;)Z
     373: pop
     374: goto          46
     377: ldc           #28                 // String /
     379: aload         4
     381: iconst_0
     382: anewarray     #29                 // class java/lang/String
     385: invokeinterface #30,  2           // InterfaceMethod java/util/List.toArray:([Ljava/lang/Object;)[Ljava/lang/Object;
     390: checkcast     #31                 // class "[Ljava/lang/CharSequence;"
     393: invokestatic  #32                 // Method java/lang/String.join:(Ljava/lang/CharSequence;[Ljava/lang/CharSequence;)Ljava/lang/String;
     396: areturn
}
