Compiled from "ApplicationConversionService.java"
public class org.springframework.boot.convert.ApplicationConversionService extends org.springframework.format.support.FormattingConversionService {
  private static volatile org.springframework.boot.convert.ApplicationConversionService sharedInstance;

  private final boolean unmodifiable;

  public org.springframework.boot.convert.ApplicationConversionService();
    Code:
       0: aload_0
       1: aconst_null
       2: invokespecial #1                  // Method "<init>":(Lorg/springframework/util/StringValueResolver;)V
       5: return

  public org.springframework.boot.convert.ApplicationConversionService(org.springframework.util.StringValueResolver);
    Code:
       0: aload_0
       1: aload_1
       2: iconst_0
       3: invokespecial #7                  // Method "<init>":(Lorg/springframework/util/StringValueResolver;Z)V
       6: return

  private org.springframework.boot.convert.ApplicationConversionService(org.springframework.util.StringValueResolver, boolean);
    Code:
       0: aload_0
       1: invokespecial #10                 // Method org/springframework/format/support/FormattingConversionService."<init>":()V
       4: aload_1
       5: ifnull        13
       8: aload_0
       9: aload_1
      10: invokevirtual #15                 // Method setEmbeddedValueResolver:(Lorg/springframework/util/StringValueResolver;)V
      13: aload_0
      14: invokestatic  #18                 // Method configure:(Lorg/springframework/format/FormatterRegistry;)V
      17: aload_0
      18: iload_2
      19: putfield      #22                 // Field unmodifiable:Z
      22: return

  public void addPrinter(org.springframework.format.Printer<?>);
    Code:
       0: aload_0
       1: invokevirtual #26                 // Method assertModifiable:()V
       4: aload_0
       5: aload_1
       6: invokespecial #29                 // Method org/springframework/format/support/FormattingConversionService.addPrinter:(Lorg/springframework/format/Printer;)V
       9: return

  public void addParser(org.springframework.format.Parser<?>);
    Code:
       0: aload_0
       1: invokevirtual #26                 // Method assertModifiable:()V
       4: aload_0
       5: aload_1
       6: invokespecial #33                 // Method org/springframework/format/support/FormattingConversionService.addParser:(Lorg/springframework/format/Parser;)V
       9: return

  public void addFormatter(org.springframework.format.Formatter<?>);
    Code:
       0: aload_0
       1: invokevirtual #26                 // Method assertModifiable:()V
       4: aload_0
       5: aload_1
       6: invokespecial #37                 // Method org/springframework/format/support/FormattingConversionService.addFormatter:(Lorg/springframework/format/Formatter;)V
       9: return

  public void addFormatterForFieldType(java.lang.Class<?>, org.springframework.format.Formatter<?>);
    Code:
       0: aload_0
       1: invokevirtual #26                 // Method assertModifiable:()V
       4: aload_0
       5: aload_1
       6: aload_2
       7: invokespecial #41                 // Method org/springframework/format/support/FormattingConversionService.addFormatterForFieldType:(Ljava/lang/Class;Lorg/springframework/format/Formatter;)V
      10: return

  public void addConverter(org.springframework.core.convert.converter.Converter<?, ?>);
    Code:
       0: aload_0
       1: invokevirtual #26                 // Method assertModifiable:()V
       4: aload_0
       5: aload_1
       6: invokespecial #45                 // Method org/springframework/format/support/FormattingConversionService.addConverter:(Lorg/springframework/core/convert/converter/Converter;)V
       9: return

  public void addFormatterForFieldType(java.lang.Class<?>, org.springframework.format.Printer<?>, org.springframework.format.Parser<?>);
    Code:
       0: aload_0
       1: invokevirtual #26                 // Method assertModifiable:()V
       4: aload_0
       5: aload_1
       6: aload_2
       7: aload_3
       8: invokespecial #49                 // Method org/springframework/format/support/FormattingConversionService.addFormatterForFieldType:(Ljava/lang/Class;Lorg/springframework/format/Printer;Lorg/springframework/format/Parser;)V
      11: return

  public void addFormatterForFieldAnnotation(org.springframework.format.AnnotationFormatterFactory<? extends java.lang.annotation.Annotation>);
    Code:
       0: aload_0
       1: invokevirtual #26                 // Method assertModifiable:()V
       4: aload_0
       5: aload_1
       6: invokespecial #52                 // Method org/springframework/format/support/FormattingConversionService.addFormatterForFieldAnnotation:(Lorg/springframework/format/AnnotationFormatterFactory;)V
       9: return

  public <S, T> void addConverter(java.lang.Class<S>, java.lang.Class<T>, org.springframework.core.convert.converter.Converter<? super S, ? extends T>);
    Code:
       0: aload_0
       1: invokevirtual #26                 // Method assertModifiable:()V
       4: aload_0
       5: aload_1
       6: aload_2
       7: aload_3
       8: invokespecial #56                 // Method org/springframework/format/support/FormattingConversionService.addConverter:(Ljava/lang/Class;Ljava/lang/Class;Lorg/springframework/core/convert/converter/Converter;)V
      11: return

  public void addConverter(org.springframework.core.convert.converter.GenericConverter);
    Code:
       0: aload_0
       1: invokevirtual #26                 // Method assertModifiable:()V
       4: aload_0
       5: aload_1
       6: invokespecial #59                 // Method org/springframework/format/support/FormattingConversionService.addConverter:(Lorg/springframework/core/convert/converter/GenericConverter;)V
       9: return

  public void addConverterFactory(org.springframework.core.convert.converter.ConverterFactory<?, ?>);
    Code:
       0: aload_0
       1: invokevirtual #26                 // Method assertModifiable:()V
       4: aload_0
       5: aload_1
       6: invokespecial #62                 // Method org/springframework/format/support/FormattingConversionService.addConverterFactory:(Lorg/springframework/core/convert/converter/ConverterFactory;)V
       9: return

  public void removeConvertible(java.lang.Class<?>, java.lang.Class<?>);
    Code:
       0: aload_0
       1: invokevirtual #26                 // Method assertModifiable:()V
       4: aload_0
       5: aload_1
       6: aload_2
       7: invokespecial #66                 // Method org/springframework/format/support/FormattingConversionService.removeConvertible:(Ljava/lang/Class;Ljava/lang/Class;)V
      10: return

  private void assertModifiable();
    Code:
       0: aload_0
       1: getfield      #22                 // Field unmodifiable:Z
       4: ifeq          17
       7: new           #70                 // class java/lang/UnsupportedOperationException
      10: dup
      11: ldc           #72                 // String This ApplicationConversionService cannot be modified
      13: invokespecial #74                 // Method java/lang/UnsupportedOperationException."<init>":(Ljava/lang/String;)V
      16: athrow
      17: return

  public boolean isConvertViaObjectSourceType(org.springframework.core.convert.TypeDescriptor, org.springframework.core.convert.TypeDescriptor);
    Code:
       0: aload_0
       1: aload_1
       2: aload_2
       3: invokevirtual #77                 // Method getConverter:(Lorg/springframework/core/convert/TypeDescriptor;Lorg/springframework/core/convert/TypeDescriptor;)Lorg/springframework/core/convert/converter/GenericConverter;
       6: astore_3
       7: aload_3
       8: ifnull        20
      11: aload_3
      12: invokeinterface #81,  1           // InterfaceMethod org/springframework/core/convert/converter/GenericConverter.getConvertibleTypes:()Ljava/util/Set;
      17: goto          21
      20: aconst_null
      21: astore        4
      23: aload         4
      25: ifnull        77
      28: aload         4
      30: invokeinterface #87,  1           // InterfaceMethod java/util/Set.iterator:()Ljava/util/Iterator;
      35: astore        5
      37: aload         5
      39: invokeinterface #93,  1           // InterfaceMethod java/util/Iterator.hasNext:()Z
      44: ifeq          77
      47: aload         5
      49: invokeinterface #99,  1           // InterfaceMethod java/util/Iterator.next:()Ljava/lang/Object;
      54: checkcast     #103                // class org/springframework/core/convert/converter/GenericConverter$ConvertiblePair
      57: astore        6
      59: ldc           #105                // class java/lang/Object
      61: aload         6
      63: invokevirtual #107                // Method org/springframework/core/convert/converter/GenericConverter$ConvertiblePair.getSourceType:()Ljava/lang/Class;
      66: invokevirtual #111                // Method java/lang/Object.equals:(Ljava/lang/Object;)Z
      69: ifeq          74
      72: iconst_1
      73: ireturn
      74: goto          37
      77: iconst_0
      78: ireturn

  public static org.springframework.core.convert.ConversionService getSharedInstance();
    Code:
       0: getstatic     #115                // Field sharedInstance:Lorg/springframework/boot/convert/ApplicationConversionService;
       3: astore_0
       4: aload_0
       5: ifnonnull     45
       8: ldc           #2                  // class org/springframework/boot/convert/ApplicationConversionService
      10: dup
      11: astore_1
      12: monitorenter
      13: getstatic     #115                // Field sharedInstance:Lorg/springframework/boot/convert/ApplicationConversionService;
      16: astore_0
      17: aload_0
      18: ifnonnull     35
      21: new           #2                  // class org/springframework/boot/convert/ApplicationConversionService
      24: dup
      25: aconst_null
      26: iconst_1
      27: invokespecial #7                  // Method "<init>":(Lorg/springframework/util/StringValueResolver;Z)V
      30: astore_0
      31: aload_0
      32: putstatic     #115                // Field sharedInstance:Lorg/springframework/boot/convert/ApplicationConversionService;
      35: aload_1
      36: monitorexit
      37: goto          45
      40: astore_2
      41: aload_1
      42: monitorexit
      43: aload_2
      44: athrow
      45: aload_0
      46: areturn
    Exception table:
       from    to  target type
          13    37    40   any
          40    43    40   any

  public static void configure(org.springframework.format.FormatterRegistry);
    Code:
       0: aload_0
       1: invokestatic  #119                // Method org/springframework/core/convert/support/DefaultConversionService.addDefaultConverters:(Lorg/springframework/core/convert/converter/ConverterRegistry;)V
       4: aload_0
       5: invokestatic  #125                // Method org/springframework/format/support/DefaultFormattingConversionService.addDefaultFormatters:(Lorg/springframework/format/FormatterRegistry;)V
       8: aload_0
       9: invokestatic  #130                // Method addApplicationFormatters:(Lorg/springframework/format/FormatterRegistry;)V
      12: aload_0
      13: invokestatic  #133                // Method addApplicationConverters:(Lorg/springframework/core/convert/converter/ConverterRegistry;)V
      16: return

  public static void addApplicationConverters(org.springframework.core.convert.converter.ConverterRegistry);
    Code:
       0: aload_0
       1: invokestatic  #136                // Method addDelimitedStringConverters:(Lorg/springframework/core/convert/converter/ConverterRegistry;)V
       4: aload_0
       5: new           #139                // class org/springframework/boot/convert/StringToDurationConverter
       8: dup
       9: invokespecial #141                // Method org/springframework/boot/convert/StringToDurationConverter."<init>":()V
      12: invokeinterface #142,  2          // InterfaceMethod org/springframework/core/convert/converter/ConverterRegistry.addConverter:(Lorg/springframework/core/convert/converter/GenericConverter;)V
      17: aload_0
      18: new           #145                // class org/springframework/boot/convert/DurationToStringConverter
      21: dup
      22: invokespecial #147                // Method org/springframework/boot/convert/DurationToStringConverter."<init>":()V
      25: invokeinterface #142,  2          // InterfaceMethod org/springframework/core/convert/converter/ConverterRegistry.addConverter:(Lorg/springframework/core/convert/converter/GenericConverter;)V
      30: aload_0
      31: new           #148                // class org/springframework/boot/convert/NumberToDurationConverter
      34: dup
      35: invokespecial #150                // Method org/springframework/boot/convert/NumberToDurationConverter."<init>":()V
      38: invokeinterface #142,  2          // InterfaceMethod org/springframework/core/convert/converter/ConverterRegistry.addConverter:(Lorg/springframework/core/convert/converter/GenericConverter;)V
      43: aload_0
      44: new           #151                // class org/springframework/boot/convert/DurationToNumberConverter
      47: dup
      48: invokespecial #153                // Method org/springframework/boot/convert/DurationToNumberConverter."<init>":()V
      51: invokeinterface #142,  2          // InterfaceMethod org/springframework/core/convert/converter/ConverterRegistry.addConverter:(Lorg/springframework/core/convert/converter/GenericConverter;)V
      56: aload_0
      57: new           #154                // class org/springframework/boot/convert/StringToPeriodConverter
      60: dup
      61: invokespecial #156                // Method org/springframework/boot/convert/StringToPeriodConverter."<init>":()V
      64: invokeinterface #142,  2          // InterfaceMethod org/springframework/core/convert/converter/ConverterRegistry.addConverter:(Lorg/springframework/core/convert/converter/GenericConverter;)V
      69: aload_0
      70: new           #157                // class org/springframework/boot/convert/PeriodToStringConverter
      73: dup
      74: invokespecial #159                // Method org/springframework/boot/convert/PeriodToStringConverter."<init>":()V
      77: invokeinterface #142,  2          // InterfaceMethod org/springframework/core/convert/converter/ConverterRegistry.addConverter:(Lorg/springframework/core/convert/converter/GenericConverter;)V
      82: aload_0
      83: new           #160                // class org/springframework/boot/convert/NumberToPeriodConverter
      86: dup
      87: invokespecial #162                // Method org/springframework/boot/convert/NumberToPeriodConverter."<init>":()V
      90: invokeinterface #142,  2          // InterfaceMethod org/springframework/core/convert/converter/ConverterRegistry.addConverter:(Lorg/springframework/core/convert/converter/GenericConverter;)V
      95: aload_0
      96: new           #163                // class org/springframework/boot/convert/StringToDataSizeConverter
      99: dup
     100: invokespecial #165                // Method org/springframework/boot/convert/StringToDataSizeConverter."<init>":()V
     103: invokeinterface #142,  2          // InterfaceMethod org/springframework/core/convert/converter/ConverterRegistry.addConverter:(Lorg/springframework/core/convert/converter/GenericConverter;)V
     108: aload_0
     109: new           #166                // class org/springframework/boot/convert/NumberToDataSizeConverter
     112: dup
     113: invokespecial #168                // Method org/springframework/boot/convert/NumberToDataSizeConverter."<init>":()V
     116: invokeinterface #142,  2          // InterfaceMethod org/springframework/core/convert/converter/ConverterRegistry.addConverter:(Lorg/springframework/core/convert/converter/GenericConverter;)V
     121: aload_0
     122: new           #169                // class org/springframework/boot/convert/StringToFileConverter
     125: dup
     126: invokespecial #171                // Method org/springframework/boot/convert/StringToFileConverter."<init>":()V
     129: invokeinterface #172,  2          // InterfaceMethod org/springframework/core/convert/converter/ConverterRegistry.addConverter:(Lorg/springframework/core/convert/converter/Converter;)V
     134: aload_0
     135: new           #173                // class org/springframework/boot/convert/InputStreamSourceToByteArrayConverter
     138: dup
     139: invokespecial #175                // Method org/springframework/boot/convert/InputStreamSourceToByteArrayConverter."<init>":()V
     142: invokeinterface #172,  2          // InterfaceMethod org/springframework/core/convert/converter/ConverterRegistry.addConverter:(Lorg/springframework/core/convert/converter/Converter;)V
     147: aload_0
     148: new           #176                // class org/springframework/boot/convert/LenientStringToEnumConverterFactory
     151: dup
     152: invokespecial #178                // Method org/springframework/boot/convert/LenientStringToEnumConverterFactory."<init>":()V
     155: invokeinterface #179,  2          // InterfaceMethod org/springframework/core/convert/converter/ConverterRegistry.addConverterFactory:(Lorg/springframework/core/convert/converter/ConverterFactory;)V
     160: aload_0
     161: new           #180                // class org/springframework/boot/convert/LenientBooleanToEnumConverterFactory
     164: dup
     165: invokespecial #182                // Method org/springframework/boot/convert/LenientBooleanToEnumConverterFactory."<init>":()V
     168: invokeinterface #179,  2          // InterfaceMethod org/springframework/core/convert/converter/ConverterRegistry.addConverterFactory:(Lorg/springframework/core/convert/converter/ConverterFactory;)V
     173: aload_0
     174: instanceof    #183                // class org/springframework/core/convert/ConversionService
     177: ifeq          190
     180: aload_0
     181: checkcast     #183                // class org/springframework/core/convert/ConversionService
     184: astore_1
     185: aload_0
     186: aload_1
     187: invokestatic  #185                // Method addApplicationConverters:(Lorg/springframework/core/convert/converter/ConverterRegistry;Lorg/springframework/core/convert/ConversionService;)V
     190: return

  private static void addApplicationConverters(org.springframework.core.convert.converter.ConverterRegistry, org.springframework.core.convert.ConversionService);
    Code:
       0: aload_0
       1: new           #188                // class org/springframework/boot/convert/CharSequenceToObjectConverter
       4: dup
       5: aload_1
       6: invokespecial #190                // Method org/springframework/boot/convert/CharSequenceToObjectConverter."<init>":(Lorg/springframework/core/convert/ConversionService;)V
       9: invokeinterface #142,  2          // InterfaceMethod org/springframework/core/convert/converter/ConverterRegistry.addConverter:(Lorg/springframework/core/convert/converter/GenericConverter;)V
      14: return

  public static void addDelimitedStringConverters(org.springframework.core.convert.converter.ConverterRegistry);
    Code:
       0: aload_0
       1: checkcast     #183                // class org/springframework/core/convert/ConversionService
       4: astore_1
       5: aload_0
       6: new           #193                // class org/springframework/boot/convert/ArrayToDelimitedStringConverter
       9: dup
      10: aload_1
      11: invokespecial #195                // Method org/springframework/boot/convert/ArrayToDelimitedStringConverter."<init>":(Lorg/springframework/core/convert/ConversionService;)V
      14: invokeinterface #142,  2          // InterfaceMethod org/springframework/core/convert/converter/ConverterRegistry.addConverter:(Lorg/springframework/core/convert/converter/GenericConverter;)V
      19: aload_0
      20: new           #196                // class org/springframework/boot/convert/CollectionToDelimitedStringConverter
      23: dup
      24: aload_1
      25: invokespecial #198                // Method org/springframework/boot/convert/CollectionToDelimitedStringConverter."<init>":(Lorg/springframework/core/convert/ConversionService;)V
      28: invokeinterface #142,  2          // InterfaceMethod org/springframework/core/convert/converter/ConverterRegistry.addConverter:(Lorg/springframework/core/convert/converter/GenericConverter;)V
      33: aload_0
      34: new           #199                // class org/springframework/boot/convert/DelimitedStringToArrayConverter
      37: dup
      38: aload_1
      39: invokespecial #201                // Method org/springframework/boot/convert/DelimitedStringToArrayConverter."<init>":(Lorg/springframework/core/convert/ConversionService;)V
      42: invokeinterface #142,  2          // InterfaceMethod org/springframework/core/convert/converter/ConverterRegistry.addConverter:(Lorg/springframework/core/convert/converter/GenericConverter;)V
      47: aload_0
      48: new           #202                // class org/springframework/boot/convert/DelimitedStringToCollectionConverter
      51: dup
      52: aload_1
      53: invokespecial #204                // Method org/springframework/boot/convert/DelimitedStringToCollectionConverter."<init>":(Lorg/springframework/core/convert/ConversionService;)V
      56: invokeinterface #142,  2          // InterfaceMethod org/springframework/core/convert/converter/ConverterRegistry.addConverter:(Lorg/springframework/core/convert/converter/GenericConverter;)V
      61: return

  public static void addApplicationFormatters(org.springframework.format.FormatterRegistry);
    Code:
       0: aload_0
       1: new           #205                // class org/springframework/boot/convert/CharArrayFormatter
       4: dup
       5: invokespecial #207                // Method org/springframework/boot/convert/CharArrayFormatter."<init>":()V
       8: invokeinterface #208,  2          // InterfaceMethod org/springframework/format/FormatterRegistry.addFormatter:(Lorg/springframework/format/Formatter;)V
      13: aload_0
      14: new           #211                // class org/springframework/boot/convert/InetAddressFormatter
      17: dup
      18: invokespecial #213                // Method org/springframework/boot/convert/InetAddressFormatter."<init>":()V
      21: invokeinterface #208,  2          // InterfaceMethod org/springframework/format/FormatterRegistry.addFormatter:(Lorg/springframework/format/Formatter;)V
      26: aload_0
      27: new           #214                // class org/springframework/boot/convert/IsoOffsetFormatter
      30: dup
      31: invokespecial #216                // Method org/springframework/boot/convert/IsoOffsetFormatter."<init>":()V
      34: invokeinterface #208,  2          // InterfaceMethod org/springframework/format/FormatterRegistry.addFormatter:(Lorg/springframework/format/Formatter;)V
      39: return

  public static void addBeans(org.springframework.format.FormatterRegistry, org.springframework.beans.factory.ListableBeanFactory);
    Code:
       0: new           #217                // class java/util/LinkedHashSet
       3: dup
       4: invokespecial #219                // Method java/util/LinkedHashSet."<init>":()V
       7: astore_2
       8: aload_2
       9: aload_1
      10: ldc           #82                 // class org/springframework/core/convert/converter/GenericConverter
      12: invokeinterface #220,  2          // InterfaceMethod org/springframework/beans/factory/ListableBeanFactory.getBeansOfType:(Ljava/lang/Class;)Ljava/util/Map;
      17: invokeinterface #226,  1          // InterfaceMethod java/util/Map.values:()Ljava/util/Collection;
      22: invokeinterface #232,  2          // InterfaceMethod java/util/Set.addAll:(Ljava/util/Collection;)Z
      27: pop
      28: aload_2
      29: aload_1
      30: ldc           #236                // class org/springframework/core/convert/converter/Converter
      32: invokeinterface #220,  2          // InterfaceMethod org/springframework/beans/factory/ListableBeanFactory.getBeansOfType:(Ljava/lang/Class;)Ljava/util/Map;
      37: invokeinterface #226,  1          // InterfaceMethod java/util/Map.values:()Ljava/util/Collection;
      42: invokeinterface #232,  2          // InterfaceMethod java/util/Set.addAll:(Ljava/util/Collection;)Z
      47: pop
      48: aload_2
      49: aload_1
      50: ldc           #238                // class org/springframework/format/Printer
      52: invokeinterface #220,  2          // InterfaceMethod org/springframework/beans/factory/ListableBeanFactory.getBeansOfType:(Ljava/lang/Class;)Ljava/util/Map;
      57: invokeinterface #226,  1          // InterfaceMethod java/util/Map.values:()Ljava/util/Collection;
      62: invokeinterface #232,  2          // InterfaceMethod java/util/Set.addAll:(Ljava/util/Collection;)Z
      67: pop
      68: aload_2
      69: aload_1
      70: ldc           #240                // class org/springframework/format/Parser
      72: invokeinterface #220,  2          // InterfaceMethod org/springframework/beans/factory/ListableBeanFactory.getBeansOfType:(Ljava/lang/Class;)Ljava/util/Map;
      77: invokeinterface #226,  1          // InterfaceMethod java/util/Map.values:()Ljava/util/Collection;
      82: invokeinterface #232,  2          // InterfaceMethod java/util/Set.addAll:(Ljava/util/Collection;)Z
      87: pop
      88: aload_2
      89: invokeinterface #87,  1           // InterfaceMethod java/util/Set.iterator:()Ljava/util/Iterator;
      94: astore_3
      95: aload_3
      96: invokeinterface #93,  1           // InterfaceMethod java/util/Iterator.hasNext:()Z
     101: ifeq          222
     104: aload_3
     105: invokeinterface #99,  1           // InterfaceMethod java/util/Iterator.next:()Ljava/lang/Object;
     110: astore        4
     112: aload         4
     114: instanceof    #82                 // class org/springframework/core/convert/converter/GenericConverter
     117: ifeq          134
     120: aload_0
     121: aload         4
     123: checkcast     #82                 // class org/springframework/core/convert/converter/GenericConverter
     126: invokeinterface #242,  2          // InterfaceMethod org/springframework/format/FormatterRegistry.addConverter:(Lorg/springframework/core/convert/converter/GenericConverter;)V
     131: goto          219
     134: aload         4
     136: instanceof    #236                // class org/springframework/core/convert/converter/Converter
     139: ifeq          156
     142: aload_0
     143: aload         4
     145: checkcast     #236                // class org/springframework/core/convert/converter/Converter
     148: invokeinterface #243,  2          // InterfaceMethod org/springframework/format/FormatterRegistry.addConverter:(Lorg/springframework/core/convert/converter/Converter;)V
     153: goto          219
     156: aload         4
     158: instanceof    #244                // class org/springframework/format/Formatter
     161: ifeq          178
     164: aload_0
     165: aload         4
     167: checkcast     #244                // class org/springframework/format/Formatter
     170: invokeinterface #208,  2          // InterfaceMethod org/springframework/format/FormatterRegistry.addFormatter:(Lorg/springframework/format/Formatter;)V
     175: goto          219
     178: aload         4
     180: instanceof    #238                // class org/springframework/format/Printer
     183: ifeq          200
     186: aload_0
     187: aload         4
     189: checkcast     #238                // class org/springframework/format/Printer
     192: invokeinterface #246,  2          // InterfaceMethod org/springframework/format/FormatterRegistry.addPrinter:(Lorg/springframework/format/Printer;)V
     197: goto          219
     200: aload         4
     202: instanceof    #240                // class org/springframework/format/Parser
     205: ifeq          219
     208: aload_0
     209: aload         4
     211: checkcast     #240                // class org/springframework/format/Parser
     214: invokeinterface #247,  2          // InterfaceMethod org/springframework/format/FormatterRegistry.addParser:(Lorg/springframework/format/Parser;)V
     219: goto          95
     222: return
}
