Compiled from "ArrayToDelimitedStringConverter.java"
final class org.springframework.boot.convert.ArrayToDelimitedStringConverter implements org.springframework.core.convert.converter.ConditionalGenericConverter {
  private final org.springframework.boot.convert.CollectionToDelimitedStringConverter delegate;

  org.springframework.boot.convert.ArrayToDelimitedStringConverter(org.springframework.core.convert.ConversionService);
    Code:
       0: aload_0
       1: invokespecial #1                  // Method java/lang/Object."<init>":()V
       4: aload_0
       5: new           #7                  // class org/springframework/boot/convert/CollectionToDelimitedStringConverter
       8: dup
       9: aload_1
      10: invokespecial #9                  // Method org/springframework/boot/convert/CollectionToDelimitedStringConverter."<init>":(Lorg/springframework/core/convert/ConversionService;)V
      13: putfield      #12                 // Field delegate:Lorg/springframework/boot/convert/CollectionToDelimitedStringConverter;
      16: return

  public java.util.Set<org.springframework.core.convert.converter.GenericConverter$ConvertiblePair> getConvertibleTypes();
    Code:
       0: new           #18                 // class org/springframework/core/convert/converter/GenericConverter$ConvertiblePair
       3: dup
       4: ldc           #20                 // class "[Ljava/lang/Object;"
       6: ldc           #22                 // class java/lang/String
       8: invokespecial #24                 // Method org/springframework/core/convert/converter/GenericConverter$ConvertiblePair."<init>":(Ljava/lang/Class;Ljava/lang/Class;)V
      11: invokestatic  #27                 // Method java/util/Collections.singleton:(Ljava/lang/Object;)Ljava/util/Set;
      14: areturn

  public boolean matches(org.springframework.core.convert.TypeDescriptor, org.springframework.core.convert.TypeDescriptor);
    Code:
       0: aload_0
       1: getfield      #12                 // Field delegate:Lorg/springframework/boot/convert/CollectionToDelimitedStringConverter;
       4: aload_1
       5: aload_2
       6: invokevirtual #33                 // Method org/springframework/boot/convert/CollectionToDelimitedStringConverter.matches:(Lorg/springframework/core/convert/TypeDescriptor;Lorg/springframework/core/convert/TypeDescriptor;)Z
       9: ireturn

  public java.lang.Object convert(java.lang.Object, org.springframework.core.convert.TypeDescriptor, org.springframework.core.convert.TypeDescriptor);
    Code:
       0: aload_1
       1: invokestatic  #37                 // Method org/springframework/util/ObjectUtils.toObjectArray:(Ljava/lang/Object;)[Ljava/lang/Object;
       4: invokestatic  #43                 // Method java/util/Arrays.asList:([Ljava/lang/Object;)Ljava/util/List;
       7: astore        4
       9: aload_0
      10: getfield      #12                 // Field delegate:Lorg/springframework/boot/convert/CollectionToDelimitedStringConverter;
      13: aload         4
      15: aload_2
      16: aload_3
      17: invokevirtual #49                 // Method org/springframework/boot/convert/CollectionToDelimitedStringConverter.convert:(Ljava/lang/Object;Lorg/springframework/core/convert/TypeDescriptor;Lorg/springframework/core/convert/TypeDescriptor;)Ljava/lang/Object;
      20: areturn
}
