Compiled from "CharSequenceToObjectConverter.java"
class org.springframework.boot.convert.CharSequenceToObjectConverter implements org.springframework.core.convert.converter.ConditionalGenericConverter {
  private static final org.springframework.core.convert.TypeDescriptor STRING;

  private static final org.springframework.core.convert.TypeDescriptor BYTE_ARRAY;

  private static final java.util.Set<org.springframework.core.convert.converter.GenericConverter$ConvertiblePair> TYPES;

  private final java.lang.ThreadLocal<java.lang.Boolean> disable;

  private final org.springframework.core.convert.ConversionService conversionService;

  org.springframework.boot.convert.CharSequenceToObjectConverter(org.springframework.core.convert.ConversionService);
    Code:
       0: aload_0
       1: invokespecial #1                  // Method java/lang/Object."<init>":()V
       4: aload_0
       5: new           #7                  // class java/lang/ThreadLocal
       8: dup
       9: invokespecial #9                  // Method java/lang/ThreadLocal."<init>":()V
      12: putfield      #10                 // Field disable:Ljava/lang/ThreadLocal;
      15: aload_0
      16: aload_1
      17: putfield      #16                 // Field conversionService:Lorg/springframework/core/convert/ConversionService;
      20: return

  public java.util.Set<org.springframework.core.convert.converter.GenericConverter$ConvertiblePair> getConvertibleTypes();
    Code:
       0: getstatic     #20                 // Field TYPES:Ljava/util/Set;
       3: areturn

  public boolean matches(org.springframework.core.convert.TypeDescriptor, org.springframework.core.convert.TypeDescriptor);
    Code:
       0: aload_1
       1: invokevirtual #24                 // Method org/springframework/core/convert/TypeDescriptor.getType:()Ljava/lang/Class;
       4: ldc           #30                 // class java/lang/String
       6: if_acmpeq     22
       9: aload_0
      10: getfield      #10                 // Field disable:Ljava/lang/ThreadLocal;
      13: invokevirtual #32                 // Method java/lang/ThreadLocal.get:()Ljava/lang/Object;
      16: getstatic     #36                 // Field java/lang/Boolean.TRUE:Ljava/lang/Boolean;
      19: if_acmpne     24
      22: iconst_0
      23: ireturn
      24: aload_0
      25: getfield      #10                 // Field disable:Ljava/lang/ThreadLocal;
      28: getstatic     #36                 // Field java/lang/Boolean.TRUE:Ljava/lang/Boolean;
      31: invokevirtual #42                 // Method java/lang/ThreadLocal.set:(Ljava/lang/Object;)V
      34: aload_0
      35: getfield      #16                 // Field conversionService:Lorg/springframework/core/convert/ConversionService;
      38: aload_1
      39: aload_2
      40: invokeinterface #46,  3           // InterfaceMethod org/springframework/core/convert/ConversionService.canConvert:(Lorg/springframework/core/convert/TypeDescriptor;Lorg/springframework/core/convert/TypeDescriptor;)Z
      45: istore_3
      46: iload_3
      47: ifeq          72
      50: aload_0
      51: aload_1
      52: aload_2
      53: invokevirtual #52                 // Method isStringConversionBetter:(Lorg/springframework/core/convert/TypeDescriptor;Lorg/springframework/core/convert/TypeDescriptor;)Z
      56: ifne          72
      59: iconst_0
      60: istore        4
      62: aload_0
      63: getfield      #10                 // Field disable:Ljava/lang/ThreadLocal;
      66: invokevirtual #55                 // Method java/lang/ThreadLocal.remove:()V
      69: iload         4
      71: ireturn
      72: aload_0
      73: getfield      #16                 // Field conversionService:Lorg/springframework/core/convert/ConversionService;
      76: getstatic     #58                 // Field STRING:Lorg/springframework/core/convert/TypeDescriptor;
      79: aload_2
      80: invokeinterface #46,  3           // InterfaceMethod org/springframework/core/convert/ConversionService.canConvert:(Lorg/springframework/core/convert/TypeDescriptor;Lorg/springframework/core/convert/TypeDescriptor;)Z
      85: istore        4
      87: aload_0
      88: getfield      #10                 // Field disable:Ljava/lang/ThreadLocal;
      91: invokevirtual #55                 // Method java/lang/ThreadLocal.remove:()V
      94: iload         4
      96: ireturn
      97: astore        5
      99: aload_0
     100: getfield      #10                 // Field disable:Ljava/lang/ThreadLocal;
     103: invokevirtual #55                 // Method java/lang/ThreadLocal.remove:()V
     106: aload         5
     108: athrow
    Exception table:
       from    to  target type
          34    62    97   any
          72    87    97   any
          97    99    97   any

  private boolean isStringConversionBetter(org.springframework.core.convert.TypeDescriptor, org.springframework.core.convert.TypeDescriptor);
    Code:
       0: aload_0
       1: getfield      #16                 // Field conversionService:Lorg/springframework/core/convert/ConversionService;
       4: astore        4
       6: aload         4
       8: instanceof    #62                 // class org/springframework/boot/convert/ApplicationConversionService
      11: ifeq          31
      14: aload         4
      16: checkcast     #62                 // class org/springframework/boot/convert/ApplicationConversionService
      19: astore_3
      20: aload_3
      21: aload_1
      22: aload_2
      23: invokevirtual #64                 // Method org/springframework/boot/convert/ApplicationConversionService.isConvertViaObjectSourceType:(Lorg/springframework/core/convert/TypeDescriptor;Lorg/springframework/core/convert/TypeDescriptor;)Z
      26: ifeq          31
      29: iconst_1
      30: ireturn
      31: aload_2
      32: invokevirtual #67                 // Method org/springframework/core/convert/TypeDescriptor.isArray:()Z
      35: ifne          45
      38: aload_2
      39: invokevirtual #71                 // Method org/springframework/core/convert/TypeDescriptor.isCollection:()Z
      42: ifeq          57
      45: aload_2
      46: getstatic     #74                 // Field BYTE_ARRAY:Lorg/springframework/core/convert/TypeDescriptor;
      49: invokevirtual #77                 // Method org/springframework/core/convert/TypeDescriptor.equals:(Ljava/lang/Object;)Z
      52: ifne          57
      55: iconst_1
      56: ireturn
      57: iconst_0
      58: ireturn

  public java.lang.Object convert(java.lang.Object, org.springframework.core.convert.TypeDescriptor, org.springframework.core.convert.TypeDescriptor);
    Code:
       0: aload_0
       1: getfield      #16                 // Field conversionService:Lorg/springframework/core/convert/ConversionService;
       4: aload_1
       5: invokevirtual #81                 // Method java/lang/Object.toString:()Ljava/lang/String;
       8: getstatic     #58                 // Field STRING:Lorg/springframework/core/convert/TypeDescriptor;
      11: aload_3
      12: invokeinterface #85,  4           // InterfaceMethod org/springframework/core/convert/ConversionService.convert:(Ljava/lang/Object;Lorg/springframework/core/convert/TypeDescriptor;Lorg/springframework/core/convert/TypeDescriptor;)Ljava/lang/Object;
      17: areturn

  static {};
    Code:
       0: ldc           #30                 // class java/lang/String
       2: invokestatic  #89                 // Method org/springframework/core/convert/TypeDescriptor.valueOf:(Ljava/lang/Class;)Lorg/springframework/core/convert/TypeDescriptor;
       5: putstatic     #58                 // Field STRING:Lorg/springframework/core/convert/TypeDescriptor;
       8: ldc           #93                 // class "[B"
      10: invokestatic  #89                 // Method org/springframework/core/convert/TypeDescriptor.valueOf:(Ljava/lang/Class;)Lorg/springframework/core/convert/TypeDescriptor;
      13: putstatic     #74                 // Field BYTE_ARRAY:Lorg/springframework/core/convert/TypeDescriptor;
      16: new           #95                 // class org/springframework/core/convert/converter/GenericConverter$ConvertiblePair
      19: dup
      20: ldc           #97                 // class java/lang/CharSequence
      22: ldc           #2                  // class java/lang/Object
      24: invokespecial #99                 // Method org/springframework/core/convert/converter/GenericConverter$ConvertiblePair."<init>":(Ljava/lang/Class;Ljava/lang/Class;)V
      27: invokestatic  #102                // Method java/util/Collections.singleton:(Ljava/lang/Object;)Ljava/util/Set;
      30: putstatic     #20                 // Field TYPES:Ljava/util/Set;
      33: return
}
