Compiled from "DelimitedStringToCollectionConverter.java"
final class org.springframework.boot.convert.DelimitedStringToCollectionConverter implements org.springframework.core.convert.converter.ConditionalGenericConverter {
  private final org.springframework.core.convert.ConversionService conversionService;

  org.springframework.boot.convert.DelimitedStringToCollectionConverter(org.springframework.core.convert.ConversionService);
    Code:
       0: aload_0
       1: invokespecial #1                  // Method java/lang/Object."<init>":()V
       4: aload_1
       5: ldc           #7                  // String ConversionService must not be null
       7: invokestatic  #9                  // Method org/springframework/util/Assert.notNull:(Ljava/lang/Object;Ljava/lang/String;)V
      10: aload_0
      11: aload_1
      12: putfield      #15                 // Field conversionService:Lorg/springframework/core/convert/ConversionService;
      15: return

  public java.util.Set<org.springframework.core.convert.converter.GenericConverter$ConvertiblePair> getConvertibleTypes();
    Code:
       0: new           #21                 // class org/springframework/core/convert/converter/GenericConverter$ConvertiblePair
       3: dup
       4: ldc           #23                 // class java/lang/String
       6: ldc           #25                 // class java/util/Collection
       8: invokespecial #27                 // Method org/springframework/core/convert/converter/GenericConverter$ConvertiblePair."<init>":(Ljava/lang/Class;Ljava/lang/Class;)V
      11: invokestatic  #30                 // Method java/util/Collections.singleton:(Ljava/lang/Object;)Ljava/util/Set;
      14: areturn

  public boolean matches(org.springframework.core.convert.TypeDescriptor, org.springframework.core.convert.TypeDescriptor);
    Code:
       0: aload_2
       1: invokevirtual #36                 // Method org/springframework/core/convert/TypeDescriptor.getElementTypeDescriptor:()Lorg/springframework/core/convert/TypeDescriptor;
       4: ifnull        24
       7: aload_0
       8: getfield      #15                 // Field conversionService:Lorg/springframework/core/convert/ConversionService;
      11: aload_1
      12: aload_2
      13: invokevirtual #36                 // Method org/springframework/core/convert/TypeDescriptor.getElementTypeDescriptor:()Lorg/springframework/core/convert/TypeDescriptor;
      16: invokeinterface #42,  3           // InterfaceMethod org/springframework/core/convert/ConversionService.canConvert:(Lorg/springframework/core/convert/TypeDescriptor;Lorg/springframework/core/convert/TypeDescriptor;)Z
      21: ifeq          28
      24: iconst_1
      25: goto          29
      28: iconst_0
      29: ireturn

  public java.lang.Object convert(java.lang.Object, org.springframework.core.convert.TypeDescriptor, org.springframework.core.convert.TypeDescriptor);
    Code:
       0: aload_1
       1: ifnonnull     6
       4: aconst_null
       5: areturn
       6: aload_0
       7: aload_1
       8: checkcast     #23                 // class java/lang/String
      11: aload_2
      12: aload_3
      13: invokevirtual #48                 // Method convert:(Ljava/lang/String;Lorg/springframework/core/convert/TypeDescriptor;Lorg/springframework/core/convert/TypeDescriptor;)Ljava/lang/Object;
      16: areturn

  private java.lang.Object convert(java.lang.String, org.springframework.core.convert.TypeDescriptor, org.springframework.core.convert.TypeDescriptor);
    Code:
       0: aload_3
       1: ldc           #52                 // class org/springframework/boot/convert/Delimiter
       3: invokevirtual #54                 // Method org/springframework/core/convert/TypeDescriptor.getAnnotation:(Ljava/lang/Class;)Ljava/lang/annotation/Annotation;
       6: checkcast     #52                 // class org/springframework/boot/convert/Delimiter
       9: astore        4
      11: aload_0
      12: aload_1
      13: aload         4
      15: ifnull        28
      18: aload         4
      20: invokeinterface #58,  1           // InterfaceMethod org/springframework/boot/convert/Delimiter.value:()Ljava/lang/String;
      25: goto          30
      28: ldc           #62                 // String ,
      30: invokevirtual #64                 // Method getElements:(Ljava/lang/String;Ljava/lang/String;)[Ljava/lang/String;
      33: astore        5
      35: aload_3
      36: invokevirtual #36                 // Method org/springframework/core/convert/TypeDescriptor.getElementTypeDescriptor:()Lorg/springframework/core/convert/TypeDescriptor;
      39: astore        6
      41: aload_0
      42: aload_3
      43: aload         6
      45: aload         5
      47: arraylength
      48: invokevirtual #68                 // Method createCollection:(Lorg/springframework/core/convert/TypeDescriptor;Lorg/springframework/core/convert/TypeDescriptor;I)Ljava/util/Collection;
      51: astore        7
      53: aload         5
      55: invokestatic  #72                 // Method java/util/Arrays.stream:([Ljava/lang/Object;)Ljava/util/stream/Stream;
      58: invokedynamic #78,  0             // InvokeDynamic #0:apply:()Ljava/util/function/Function;
      63: invokeinterface #82,  2           // InterfaceMethod java/util/stream/Stream.map:(Ljava/util/function/Function;)Ljava/util/stream/Stream;
      68: astore        8
      70: aload         6
      72: ifnull        93
      75: aload         8
      77: aload_0
      78: aload_2
      79: aload         6
      81: invokedynamic #88,  0             // InvokeDynamic #1:apply:(Lorg/springframework/boot/convert/DelimitedStringToCollectionConverter;Lorg/springframework/core/convert/TypeDescriptor;Lorg/springframework/core/convert/TypeDescriptor;)Ljava/util/function/Function;
      86: invokeinterface #82,  2           // InterfaceMethod java/util/stream/Stream.map:(Ljava/util/function/Function;)Ljava/util/stream/Stream;
      91: astore        8
      93: aload         8
      95: aload         7
      97: dup
      98: invokestatic  #91                 // Method java/util/Objects.requireNonNull:(Ljava/lang/Object;)Ljava/lang/Object;
     101: pop
     102: invokedynamic #97,  0             // InvokeDynamic #2:accept:(Ljava/util/Collection;)Ljava/util/function/Consumer;
     107: invokeinterface #101,  2          // InterfaceMethod java/util/stream/Stream.forEach:(Ljava/util/function/Consumer;)V
     112: aload         7
     114: areturn

  private java.util.Collection<java.lang.Object> createCollection(org.springframework.core.convert.TypeDescriptor, org.springframework.core.convert.TypeDescriptor, int);
    Code:
       0: aload_1
       1: invokevirtual #105                // Method org/springframework/core/convert/TypeDescriptor.getType:()Ljava/lang/Class;
       4: aload_2
       5: ifnull        15
       8: aload_2
       9: invokevirtual #105                // Method org/springframework/core/convert/TypeDescriptor.getType:()Ljava/lang/Class;
      12: goto          16
      15: aconst_null
      16: iload_3
      17: invokestatic  #109                // Method org/springframework/core/CollectionFactory.createCollection:(Ljava/lang/Class;Ljava/lang/Class;I)Ljava/util/Collection;
      20: areturn

  private java.lang.String[] getElements(java.lang.String, java.lang.String);
    Code:
       0: aload_1
       1: ldc           #114                // String
       3: aload_2
       4: invokevirtual #116                // Method java/lang/String.equals:(Ljava/lang/Object;)Z
       7: ifeq          14
      10: aconst_null
      11: goto          15
      14: aload_2
      15: invokestatic  #120                // Method org/springframework/util/StringUtils.delimitedListToStringArray:(Ljava/lang/String;Ljava/lang/String;)[Ljava/lang/String;
      18: areturn

  private java.lang.Object lambda$convert$0(org.springframework.core.convert.TypeDescriptor, org.springframework.core.convert.TypeDescriptor, java.lang.Object);
    Code:
       0: aload_0
       1: getfield      #15                 // Field conversionService:Lorg/springframework/core/convert/ConversionService;
       4: aload_3
       5: aload_1
       6: aload_2
       7: invokeinterface #125,  4          // InterfaceMethod org/springframework/core/convert/ConversionService.convert:(Ljava/lang/Object;Lorg/springframework/core/convert/TypeDescriptor;Lorg/springframework/core/convert/TypeDescriptor;)Ljava/lang/Object;
      12: areturn
}
