Compiled from "DurationStyle.java"
final class org.springframework.boot.convert.DurationStyle$1 extends org.springframework.boot.convert.DurationStyle {
  private org.springframework.boot.convert.DurationStyle$1(java.lang.String, int, java.lang.String);
    Code:
       0: aload_0
       1: aload_1
       2: iload_2
       3: aload_3
       4: invokespecial #1                  // Method org/springframework/boot/convert/DurationStyle."<init>":(Ljava/lang/String;ILjava/lang/String;)V
       7: return

  public java.time.Duration parse(java.lang.String, java.time.temporal.ChronoUnit);
    Code:
       0: aload_0
       1: aload_1
       2: invokevirtual #7                  // Method matcher:(Ljava/lang/String;)Ljava/util/regex/Matcher;
       5: astore_3
       6: aload_3
       7: invokevirtual #13                 // Method java/util/regex/Matcher.matches:()Z
      10: ldc           #19                 // String Does not match simple duration pattern
      12: invokestatic  #21                 // Method org/springframework/util/Assert.state:(ZLjava/lang/String;)V
      15: aload_3
      16: iconst_2
      17: invokevirtual #27                 // Method java/util/regex/Matcher.group:(I)Ljava/lang/String;
      20: astore        4
      22: aload         4
      24: invokestatic  #31                 // Method org/springframework/util/StringUtils.hasLength:(Ljava/lang/String;)Z
      27: ifeq          38
      30: aload         4
      32: invokestatic  #37                 // Method org/springframework/boot/convert/DurationStyle$Unit.fromSuffix:(Ljava/lang/String;)Lorg/springframework/boot/convert/DurationStyle$Unit;
      35: goto          42
      38: aload_2
      39: invokestatic  #43                 // Method org/springframework/boot/convert/DurationStyle$Unit.fromChronoUnit:(Ljava/time/temporal/ChronoUnit;)Lorg/springframework/boot/convert/DurationStyle$Unit;
      42: aload_3
      43: iconst_1
      44: invokevirtual #27                 // Method java/util/regex/Matcher.group:(I)Ljava/lang/String;
      47: invokevirtual #47                 // Method org/springframework/boot/convert/DurationStyle$Unit.parse:(Ljava/lang/String;)Ljava/time/Duration;
      50: areturn
      51: astore_3
      52: new           #53                 // class java/lang/IllegalArgumentException
      55: dup
      56: aload_1
      57: invokedynamic #55,  0             // InvokeDynamic #0:makeConcatWithConstants:(Ljava/lang/String;)Ljava/lang/String;
      62: aload_3
      63: invokespecial #59                 // Method java/lang/IllegalArgumentException."<init>":(Ljava/lang/String;Ljava/lang/Throwable;)V
      66: athrow
    Exception table:
       from    to  target type
           0    50    51   Class java/lang/Exception

  public java.lang.String print(java.time.Duration, java.time.temporal.ChronoUnit);
    Code:
       0: aload_2
       1: invokestatic  #43                 // Method org/springframework/boot/convert/DurationStyle$Unit.fromChronoUnit:(Ljava/time/temporal/ChronoUnit;)Lorg/springframework/boot/convert/DurationStyle$Unit;
       4: aload_1
       5: invokevirtual #62                 // Method org/springframework/boot/convert/DurationStyle$Unit.print:(Ljava/time/Duration;)Ljava/lang/String;
       8: areturn
}
