Compiled from "LenientObjectToEnumConverterFactory.java"
abstract class org.springframework.boot.convert.LenientObjectToEnumConverterFactory<T> implements org.springframework.core.convert.converter.ConverterFactory<T, java.lang.Enum<?>> {
  private static final java.util.Map<java.lang.String, java.util.List<java.lang.String>> ALIASES;

  org.springframework.boot.convert.LenientObjectToEnumConverterFactory();
    Code:
       0: aload_0
       1: invokespecial #1                  // Method java/lang/Object."<init>":()V
       4: return

  public <E extends java.lang.Enum<?>> org.springframework.core.convert.converter.Converter<T, E> getConverter(java.lang.Class<E>);
    Code:
       0: aload_1
       1: astore_2
       2: aload_2
       3: ifnull        21
       6: aload_2
       7: invokevirtual #7                  // Method java/lang/Class.isEnum:()Z
      10: ifne          21
      13: aload_2
      14: invokevirtual #13                 // Method java/lang/Class.getSuperclass:()Ljava/lang/Class;
      17: astore_2
      18: goto          2
      21: aload_2
      22: aload_1
      23: invokedynamic #17,  0             // InvokeDynamic #0:get:(Ljava/lang/Class;)Ljava/util/function/Supplier;
      28: invokestatic  #21                 // Method org/springframework/util/Assert.notNull:(Ljava/lang/Object;Ljava/util/function/Supplier;)V
      31: new           #27                 // class org/springframework/boot/convert/LenientObjectToEnumConverterFactory$LenientToEnumConverter
      34: dup
      35: aload_0
      36: aload_2
      37: invokespecial #29                 // Method org/springframework/boot/convert/LenientObjectToEnumConverterFactory$LenientToEnumConverter."<init>":(Lorg/springframework/boot/convert/LenientObjectToEnumConverterFactory;Ljava/lang/Class;)V
      40: areturn

  private static java.lang.String lambda$getConverter$0(java.lang.Class);
    Code:
       0: aload_0
       1: invokevirtual #32                 // Method java/lang/Class.getName:()Ljava/lang/String;
       4: invokedynamic #36,  0             // InvokeDynamic #1:makeConcatWithConstants:(Ljava/lang/String;)Ljava/lang/String;
       9: areturn

  static {};
    Code:
       0: new           #40                 // class org/springframework/util/LinkedMultiValueMap
       3: dup
       4: invokespecial #42                 // Method org/springframework/util/LinkedMultiValueMap."<init>":()V
       7: astore_0
       8: aload_0
       9: ldc           #43                 // String true
      11: ldc           #45                 // String on
      13: invokeinterface #47,  3           // InterfaceMethod org/springframework/util/MultiValueMap.add:(Ljava/lang/Object;Ljava/lang/Object;)V
      18: aload_0
      19: ldc           #53                 // String false
      21: ldc           #55                 // String off
      23: invokeinterface #47,  3           // InterfaceMethod org/springframework/util/MultiValueMap.add:(Ljava/lang/Object;Ljava/lang/Object;)V
      28: aload_0
      29: invokestatic  #57                 // Method java/util/Collections.unmodifiableMap:(Ljava/util/Map;)Ljava/util/Map;
      32: putstatic     #63                 // Field ALIASES:Ljava/util/Map;
      35: return
}
