Compiled from "PeriodStyle.java"
final class org.springframework.boot.convert.PeriodStyle$Unit extends java.lang.Enum<org.springframework.boot.convert.PeriodStyle$Unit> {
  public static final org.springframework.boot.convert.PeriodStyle$Unit DAYS;

  public static final org.springframework.boot.convert.PeriodStyle$Unit WEEKS;

  public static final org.springframework.boot.convert.PeriodStyle$Unit MONTHS;

  public static final org.springframework.boot.convert.PeriodStyle$Unit YEARS;

  private final java.time.temporal.ChronoUnit chronoUnit;

  private final java.lang.String suffix;

  private final java.util.function.Function<java.time.Period, java.lang.Integer> intValue;

  private final java.util.function.Function<java.lang.Integer, java.time.Period> factory;

  private static final org.springframework.boot.convert.PeriodStyle$Unit[] $VALUES;

  public static org.springframework.boot.convert.PeriodStyle$Unit[] values();
    Code:
       0: getstatic     #16                 // Field $VALUES:[Lorg/springframework/boot/convert/PeriodStyle$Unit;
       3: invokevirtual #20                 // Method "[Lorg/springframework/boot/convert/PeriodStyle$Unit;".clone:()Ljava/lang/Object;
       6: checkcast     #21                 // class "[Lorg/springframework/boot/convert/PeriodStyle$Unit;"
       9: areturn

  public static org.springframework.boot.convert.PeriodStyle$Unit valueOf(java.lang.String);
    Code:
       0: ldc           #1                  // class org/springframework/boot/convert/PeriodStyle$Unit
       2: aload_0
       3: invokestatic  #25                 // Method java/lang/Enum.valueOf:(Ljava/lang/Class;Ljava/lang/String;)Ljava/lang/Enum;
       6: checkcast     #1                  // class org/springframework/boot/convert/PeriodStyle$Unit
       9: areturn

  private org.springframework.boot.convert.PeriodStyle$Unit(java.time.temporal.ChronoUnit, java.lang.String, java.util.function.Function<java.time.Period, java.lang.Integer>, java.util.function.Function<java.lang.Integer, java.time.Period>);
    Code:
       0: aload_0
       1: aload_1
       2: iload_2
       3: invokespecial #31                 // Method java/lang/Enum."<init>":(Ljava/lang/String;I)V
       6: aload_0
       7: aload_3
       8: putfield      #35                 // Field chronoUnit:Ljava/time/temporal/ChronoUnit;
      11: aload_0
      12: aload         4
      14: putfield      #39                 // Field suffix:Ljava/lang/String;
      17: aload_0
      18: aload         5
      20: putfield      #43                 // Field intValue:Ljava/util/function/Function;
      23: aload_0
      24: aload         6
      26: putfield      #47                 // Field factory:Ljava/util/function/Function;
      29: return

  private java.time.Period parse(java.lang.String);
    Code:
       0: aload_0
       1: getfield      #47                 // Field factory:Ljava/util/function/Function;
       4: aload_1
       5: invokestatic  #50                 // Method java/lang/Integer.parseInt:(Ljava/lang/String;)I
       8: invokestatic  #56                 // Method java/lang/Integer.valueOf:(I)Ljava/lang/Integer;
      11: invokeinterface #59,  2           // InterfaceMethod java/util/function/Function.apply:(Ljava/lang/Object;)Ljava/lang/Object;
      16: checkcast     #65                 // class java/time/Period
      19: areturn

  private java.lang.String print(java.time.Period);
    Code:
       0: aload_0
       1: aload_1
       2: invokevirtual #67                 // Method intValue:(Ljava/time/Period;)I
       5: aload_0
       6: getfield      #39                 // Field suffix:Ljava/lang/String;
       9: invokedynamic #70,  0             // InvokeDynamic #0:makeConcatWithConstants:(ILjava/lang/String;)Ljava/lang/String;
      14: areturn

  private boolean isZero(java.time.Period);
    Code:
       0: aload_0
       1: aload_1
       2: invokevirtual #67                 // Method intValue:(Ljava/time/Period;)I
       5: ifne          12
       8: iconst_1
       9: goto          13
      12: iconst_0
      13: ireturn

  private int intValue(java.time.Period);
    Code:
       0: aload_0
       1: getfield      #43                 // Field intValue:Ljava/util/function/Function;
       4: aload_0
       5: invokedynamic #74,  0             // InvokeDynamic #1:get:(Lorg/springframework/boot/convert/PeriodStyle$Unit;)Ljava/util/function/Supplier;
      10: invokestatic  #78                 // Method org/springframework/util/Assert.notNull:(Ljava/lang/Object;Ljava/util/function/Supplier;)V
      13: aload_0
      14: getfield      #43                 // Field intValue:Ljava/util/function/Function;
      17: aload_1
      18: invokeinterface #59,  2           // InterfaceMethod java/util/function/Function.apply:(Ljava/lang/Object;)Ljava/lang/Object;
      23: checkcast     #51                 // class java/lang/Integer
      26: invokevirtual #84                 // Method java/lang/Integer.intValue:()I
      29: ireturn

  private static org.springframework.boot.convert.PeriodStyle$Unit fromChronoUnit(java.time.temporal.ChronoUnit);
    Code:
       0: aload_0
       1: ifnonnull     8
       4: getstatic     #3                  // Field DAYS:Lorg/springframework/boot/convert/PeriodStyle$Unit;
       7: areturn
       8: invokestatic  #87                 // Method values:()[Lorg/springframework/boot/convert/PeriodStyle$Unit;
      11: astore_1
      12: aload_1
      13: arraylength
      14: istore_2
      15: iconst_0
      16: istore_3
      17: iload_3
      18: iload_2
      19: if_icmpge     45
      22: aload_1
      23: iload_3
      24: aaload
      25: astore        4
      27: aload         4
      29: getfield      #35                 // Field chronoUnit:Ljava/time/temporal/ChronoUnit;
      32: aload_0
      33: if_acmpne     39
      36: aload         4
      38: areturn
      39: iinc          3, 1
      42: goto          17
      45: new           #91                 // class java/lang/IllegalArgumentException
      48: dup
      49: aload_0
      50: invokedynamic #93,  0             // InvokeDynamic #2:makeConcatWithConstants:(Ljava/time/temporal/ChronoUnit;)Ljava/lang/String;
      55: invokespecial #96                 // Method java/lang/IllegalArgumentException."<init>":(Ljava/lang/String;)V
      58: athrow

  private java.lang.String lambda$intValue$0();
    Code:
       0: aload_0
       1: invokevirtual #99                 // Method name:()Ljava/lang/String;
       4: invokedynamic #103,  0            // InvokeDynamic #3:makeConcatWithConstants:(Ljava/lang/String;)Ljava/lang/String;
       9: areturn

  private static org.springframework.boot.convert.PeriodStyle$Unit[] $values();
    Code:
       0: iconst_4
       1: anewarray     #1                  // class org/springframework/boot/convert/PeriodStyle$Unit
       4: dup
       5: iconst_0
       6: getstatic     #3                  // Field DAYS:Lorg/springframework/boot/convert/PeriodStyle$Unit;
       9: aastore
      10: dup
      11: iconst_1
      12: getstatic     #7                  // Field WEEKS:Lorg/springframework/boot/convert/PeriodStyle$Unit;
      15: aastore
      16: dup
      17: iconst_2
      18: getstatic     #10                 // Field MONTHS:Lorg/springframework/boot/convert/PeriodStyle$Unit;
      21: aastore
      22: dup
      23: iconst_3
      24: getstatic     #13                 // Field YEARS:Lorg/springframework/boot/convert/PeriodStyle$Unit;
      27: aastore
      28: areturn

  static {};
    Code:
       0: new           #1                  // class org/springframework/boot/convert/PeriodStyle$Unit
       3: dup
       4: ldc           #106                // String DAYS
       6: iconst_0
       7: getstatic     #107                // Field java/time/temporal/ChronoUnit.DAYS:Ljava/time/temporal/ChronoUnit;
      10: ldc           #111                // String d
      12: invokedynamic #113,  0            // InvokeDynamic #4:apply:()Ljava/util/function/Function;
      17: invokedynamic #116,  0            // InvokeDynamic #5:apply:()Ljava/util/function/Function;
      22: invokespecial #117                // Method "<init>":(Ljava/lang/String;ILjava/time/temporal/ChronoUnit;Ljava/lang/String;Ljava/util/function/Function;Ljava/util/function/Function;)V
      25: putstatic     #3                  // Field DAYS:Lorg/springframework/boot/convert/PeriodStyle$Unit;
      28: new           #1                  // class org/springframework/boot/convert/PeriodStyle$Unit
      31: dup
      32: ldc           #120                // String WEEKS
      34: iconst_1
      35: getstatic     #121                // Field java/time/temporal/ChronoUnit.WEEKS:Ljava/time/temporal/ChronoUnit;
      38: ldc           #123                // String w
      40: aconst_null
      41: invokedynamic #125,  0            // InvokeDynamic #6:apply:()Ljava/util/function/Function;
      46: invokespecial #117                // Method "<init>":(Ljava/lang/String;ILjava/time/temporal/ChronoUnit;Ljava/lang/String;Ljava/util/function/Function;Ljava/util/function/Function;)V
      49: putstatic     #7                  // Field WEEKS:Lorg/springframework/boot/convert/PeriodStyle$Unit;
      52: new           #1                  // class org/springframework/boot/convert/PeriodStyle$Unit
      55: dup
      56: ldc           #126                // String MONTHS
      58: iconst_2
      59: getstatic     #127                // Field java/time/temporal/ChronoUnit.MONTHS:Ljava/time/temporal/ChronoUnit;
      62: ldc           #129                // String m
      64: invokedynamic #131,  0            // InvokeDynamic #7:apply:()Ljava/util/function/Function;
      69: invokedynamic #132,  0            // InvokeDynamic #8:apply:()Ljava/util/function/Function;
      74: invokespecial #117                // Method "<init>":(Ljava/lang/String;ILjava/time/temporal/ChronoUnit;Ljava/lang/String;Ljava/util/function/Function;Ljava/util/function/Function;)V
      77: putstatic     #10                 // Field MONTHS:Lorg/springframework/boot/convert/PeriodStyle$Unit;
      80: new           #1                  // class org/springframework/boot/convert/PeriodStyle$Unit
      83: dup
      84: ldc           #133                // String YEARS
      86: iconst_3
      87: getstatic     #134                // Field java/time/temporal/ChronoUnit.YEARS:Ljava/time/temporal/ChronoUnit;
      90: ldc           #136                // String y
      92: invokedynamic #138,  0            // InvokeDynamic #9:apply:()Ljava/util/function/Function;
      97: invokedynamic #139,  0            // InvokeDynamic #10:apply:()Ljava/util/function/Function;
     102: invokespecial #117                // Method "<init>":(Ljava/lang/String;ILjava/time/temporal/ChronoUnit;Ljava/lang/String;Ljava/util/function/Function;Ljava/util/function/Function;)V
     105: putstatic     #13                 // Field YEARS:Lorg/springframework/boot/convert/PeriodStyle$Unit;
     108: invokestatic  #140                // Method $values:()[Lorg/springframework/boot/convert/PeriodStyle$Unit;
     111: putstatic     #16                 // Field $VALUES:[Lorg/springframework/boot/convert/PeriodStyle$Unit;
     114: return
}
