Compiled from "PeriodStyle.java"
final class org.springframework.boot.convert.PeriodStyle$1 extends org.springframework.boot.convert.PeriodStyle {
  private org.springframework.boot.convert.PeriodStyle$1(java.lang.String, int, java.lang.String, int);
    Code:
       0: aload_0
       1: aload_1
       2: iload_2
       3: aload_3
       4: iload         4
       6: invokespecial #1                  // Method org/springframework/boot/convert/PeriodStyle."<init>":(Ljava/lang/String;ILjava/lang/String;I)V
       9: return

  public java.time.Period parse(java.lang.String, java.time.temporal.ChronoUnit);
    Code:
       0: getstatic     #7                  // Field org/springframework/boot/convert/PeriodStyle.NUMERIC:Ljava/util/regex/Pattern;
       3: aload_1
       4: invokevirtual #11                 // Method java/util/regex/Pattern.matcher:(Ljava/lang/CharSequence;)Ljava/util/regex/Matcher;
       7: invokevirtual #17                 // Method java/util/regex/Matcher.matches:()Z
      10: ifeq          22
      13: aload_2
      14: invokestatic  #23                 // Method org/springframework/boot/convert/PeriodStyle$Unit.fromChronoUnit:(Ljava/time/temporal/ChronoUnit;)Lorg/springframework/boot/convert/PeriodStyle$Unit;
      17: aload_1
      18: invokevirtual #29                 // Method org/springframework/boot/convert/PeriodStyle$Unit.parse:(Ljava/lang/String;)Ljava/time/Period;
      21: areturn
      22: aload_0
      23: aload_1
      24: invokevirtual #33                 // Method matcher:(Ljava/lang/String;)Ljava/util/regex/Matcher;
      27: astore_3
      28: aload_3
      29: invokevirtual #17                 // Method java/util/regex/Matcher.matches:()Z
      32: ldc           #38                 // String Does not match simple period pattern
      34: invokestatic  #40                 // Method org/springframework/util/Assert.state:(ZLjava/lang/String;)V
      37: aload_0
      38: aload_3
      39: invokevirtual #46                 // Method hasAtLeastOneGroupValue:(Ljava/util/regex/Matcher;)Z
      42: aload_1
      43: invokedynamic #50,  0             // InvokeDynamic #0:get:(Ljava/lang/String;)Ljava/util/function/Supplier;
      48: invokestatic  #54                 // Method org/springframework/util/Assert.isTrue:(ZLjava/util/function/Supplier;)V
      51: aload_0
      52: aload_3
      53: iconst_1
      54: invokevirtual #58                 // Method parseInt:(Ljava/util/regex/Matcher;I)I
      57: istore        4
      59: aload_0
      60: aload_3
      61: iconst_2
      62: invokevirtual #58                 // Method parseInt:(Ljava/util/regex/Matcher;I)I
      65: istore        5
      67: aload_0
      68: aload_3
      69: iconst_3
      70: invokevirtual #58                 // Method parseInt:(Ljava/util/regex/Matcher;I)I
      73: istore        6
      75: aload_0
      76: aload_3
      77: iconst_4
      78: invokevirtual #58                 // Method parseInt:(Ljava/util/regex/Matcher;I)I
      81: istore        7
      83: iload         4
      85: iload         5
      87: iload         6
      89: bipush        7
      91: invokestatic  #62                 // Method java/lang/Math.multiplyExact:(II)I
      94: iload         7
      96: invokestatic  #68                 // Method java/lang/Math.addExact:(II)I
      99: invokestatic  #71                 // Method java/time/Period.of:(III)Ljava/time/Period;
     102: areturn
     103: astore_3
     104: new           #79                 // class java/lang/IllegalArgumentException
     107: dup
     108: aload_1
     109: invokedynamic #81,  0             // InvokeDynamic #1:makeConcatWithConstants:(Ljava/lang/String;)Ljava/lang/String;
     114: aload_3
     115: invokespecial #85                 // Method java/lang/IllegalArgumentException."<init>":(Ljava/lang/String;Ljava/lang/Throwable;)V
     118: athrow
    Exception table:
       from    to  target type
           0    21   103   Class java/lang/Exception
          22   102   103   Class java/lang/Exception

  boolean hasAtLeastOneGroupValue(java.util.regex.Matcher);
    Code:
       0: iconst_0
       1: istore_2
       2: iload_2
       3: aload_1
       4: invokevirtual #88                 // Method java/util/regex/Matcher.groupCount:()I
       7: if_icmpge     28
      10: aload_1
      11: iload_2
      12: iconst_1
      13: iadd
      14: invokevirtual #92                 // Method java/util/regex/Matcher.group:(I)Ljava/lang/String;
      17: ifnull        22
      20: iconst_1
      21: ireturn
      22: iinc          2, 1
      25: goto          2
      28: iconst_0
      29: ireturn

  private int parseInt(java.util.regex.Matcher, int);
    Code:
       0: aload_1
       1: iload_2
       2: invokevirtual #92                 // Method java/util/regex/Matcher.group:(I)Ljava/lang/String;
       5: astore_3
       6: aload_3
       7: ifnull        17
      10: aload_3
      11: invokestatic  #96                 // Method java/lang/Integer.parseInt:(Ljava/lang/String;)I
      14: goto          18
      17: iconst_0
      18: ireturn

  protected boolean matches(java.lang.String);
    Code:
       0: getstatic     #7                  // Field org/springframework/boot/convert/PeriodStyle.NUMERIC:Ljava/util/regex/Pattern;
       3: aload_1
       4: invokevirtual #11                 // Method java/util/regex/Pattern.matcher:(Ljava/lang/CharSequence;)Ljava/util/regex/Matcher;
       7: invokevirtual #17                 // Method java/util/regex/Matcher.matches:()Z
      10: ifne          24
      13: aload_0
      14: aload_1
      15: invokevirtual #33                 // Method matcher:(Ljava/lang/String;)Ljava/util/regex/Matcher;
      18: invokevirtual #17                 // Method java/util/regex/Matcher.matches:()Z
      21: ifeq          28
      24: iconst_1
      25: goto          29
      28: iconst_0
      29: ireturn

  public java.lang.String print(java.time.Period, java.time.temporal.ChronoUnit);
    Code:
       0: aload_1
       1: invokevirtual #101                // Method java/time/Period.isZero:()Z
       4: ifeq          16
       7: aload_2
       8: invokestatic  #23                 // Method org/springframework/boot/convert/PeriodStyle$Unit.fromChronoUnit:(Ljava/time/temporal/ChronoUnit;)Lorg/springframework/boot/convert/PeriodStyle$Unit;
      11: aload_1
      12: invokevirtual #104                // Method org/springframework/boot/convert/PeriodStyle$Unit.print:(Ljava/time/Period;)Ljava/lang/String;
      15: areturn
      16: new           #108                // class java/lang/StringBuilder
      19: dup
      20: invokespecial #110                // Method java/lang/StringBuilder."<init>":()V
      23: astore_3
      24: aload_0
      25: aload_3
      26: aload_1
      27: getstatic     #113                // Field org/springframework/boot/convert/PeriodStyle$Unit.YEARS:Lorg/springframework/boot/convert/PeriodStyle$Unit;
      30: invokevirtual #117                // Method append:(Ljava/lang/StringBuilder;Ljava/time/Period;Lorg/springframework/boot/convert/PeriodStyle$Unit;)V
      33: aload_0
      34: aload_3
      35: aload_1
      36: getstatic     #121                // Field org/springframework/boot/convert/PeriodStyle$Unit.MONTHS:Lorg/springframework/boot/convert/PeriodStyle$Unit;
      39: invokevirtual #117                // Method append:(Ljava/lang/StringBuilder;Ljava/time/Period;Lorg/springframework/boot/convert/PeriodStyle$Unit;)V
      42: aload_0
      43: aload_3
      44: aload_1
      45: getstatic     #124                // Field org/springframework/boot/convert/PeriodStyle$Unit.DAYS:Lorg/springframework/boot/convert/PeriodStyle$Unit;
      48: invokevirtual #117                // Method append:(Ljava/lang/StringBuilder;Ljava/time/Period;Lorg/springframework/boot/convert/PeriodStyle$Unit;)V
      51: aload_3
      52: invokevirtual #127                // Method java/lang/StringBuilder.toString:()Ljava/lang/String;
      55: areturn

  private void append(java.lang.StringBuilder, java.time.Period, org.springframework.boot.convert.PeriodStyle$Unit);
    Code:
       0: aload_3
       1: aload_2
       2: invokevirtual #131                // Method org/springframework/boot/convert/PeriodStyle$Unit.isZero:(Ljava/time/Period;)Z
       5: ifne          18
       8: aload_1
       9: aload_3
      10: aload_2
      11: invokevirtual #104                // Method org/springframework/boot/convert/PeriodStyle$Unit.print:(Ljava/time/Period;)Ljava/lang/String;
      14: invokevirtual #134                // Method java/lang/StringBuilder.append:(Ljava/lang/String;)Ljava/lang/StringBuilder;
      17: pop
      18: return

  private static java.lang.String lambda$parse$0(java.lang.String);
    Code:
       0: aload_0
       1: invokedynamic #81,  0             // InvokeDynamic #1:makeConcatWithConstants:(Ljava/lang/String;)Ljava/lang/String;
       6: areturn
}
