Compiled from "PeriodStyle.java"
final class org.springframework.boot.convert.PeriodStyle$2 extends org.springframework.boot.convert.PeriodStyle {
  private org.springframework.boot.convert.PeriodStyle$2(java.lang.String, int, java.lang.String, int);
    Code:
       0: aload_0
       1: aload_1
       2: iload_2
       3: aload_3
       4: iload         4
       6: invokespecial #1                  // Method org/springframework/boot/convert/PeriodStyle."<init>":(Ljava/lang/String;ILjava/lang/String;I)V
       9: return

  public java.time.Period parse(java.lang.String, java.time.temporal.ChronoUnit);
    Code:
       0: aload_1
       1: invokestatic  #7                  // Method java/time/Period.parse:(Ljava/lang/CharSequence;)Ljava/time/Period;
       4: areturn
       5: astore_3
       6: new           #15                 // class java/lang/IllegalArgumentException
       9: dup
      10: aload_1
      11: invokedynamic #17,  0             // InvokeDynamic #0:makeConcatWithConstants:(Ljava/lang/String;)Ljava/lang/String;
      16: aload_3
      17: invokespecial #21                 // Method java/lang/IllegalArgumentException."<init>":(Ljava/lang/String;Ljava/lang/Throwable;)V
      20: athrow
    Exception table:
       from    to  target type
           0     4     5   Class java/lang/Exception

  public java.lang.String print(java.time.Period, java.time.temporal.ChronoUnit);
    Code:
       0: aload_1
       1: invokevirtual #24                 // Method java/time/Period.toString:()Ljava/lang/String;
       4: areturn
}
