Compiled from "StringToDataSizeConverter.java"
final class org.springframework.boot.convert.StringToDataSizeConverter implements org.springframework.core.convert.converter.GenericConverter {
  org.springframework.boot.convert.StringToDataSizeConverter();
    Code:
       0: aload_0
       1: invokespecial #1                  // Method java/lang/Object."<init>":()V
       4: return

  public java.util.Set<org.springframework.core.convert.converter.GenericConverter$ConvertiblePair> getConvertibleTypes();
    Code:
       0: new           #7                  // class org/springframework/core/convert/converter/GenericConverter$ConvertiblePair
       3: dup
       4: ldc           #9                  // class java/lang/String
       6: ldc           #11                 // class org/springframework/util/unit/DataSize
       8: invokespecial #13                 // Method org/springframework/core/convert/converter/GenericConverter$ConvertiblePair."<init>":(Ljava/lang/Class;Ljava/lang/Class;)V
      11: invokestatic  #16                 // Method java/util/Collections.singleton:(Ljava/lang/Object;)Ljava/util/Set;
      14: areturn

  public java.lang.Object convert(java.lang.Object, org.springframework.core.convert.TypeDescriptor, org.springframework.core.convert.TypeDescriptor);
    Code:
       0: aload_1
       1: invokestatic  #22                 // Method org/springframework/util/ObjectUtils.isEmpty:(Ljava/lang/Object;)Z
       4: ifeq          9
       7: aconst_null
       8: areturn
       9: aload_0
      10: aload_1
      11: invokevirtual #28                 // Method java/lang/Object.toString:()Ljava/lang/String;
      14: aload_0
      15: aload_3
      16: invokevirtual #32                 // Method getDataUnit:(Lorg/springframework/core/convert/TypeDescriptor;)Lorg/springframework/util/unit/DataUnit;
      19: invokevirtual #38                 // Method convert:(Ljava/lang/String;Lorg/springframework/util/unit/DataUnit;)Lorg/springframework/util/unit/DataSize;
      22: areturn

  private org.springframework.util.unit.DataUnit getDataUnit(org.springframework.core.convert.TypeDescriptor);
    Code:
       0: aload_1
       1: ldc           #42                 // class org/springframework/boot/convert/DataSizeUnit
       3: invokevirtual #44                 // Method org/springframework/core/convert/TypeDescriptor.getAnnotation:(Ljava/lang/Class;)Ljava/lang/annotation/Annotation;
       6: checkcast     #42                 // class org/springframework/boot/convert/DataSizeUnit
       9: astore_2
      10: aload_2
      11: ifnull        23
      14: aload_2
      15: invokeinterface #50,  1           // InterfaceMethod org/springframework/boot/convert/DataSizeUnit.value:()Lorg/springframework/util/unit/DataUnit;
      20: goto          24
      23: aconst_null
      24: areturn

  private org.springframework.util.unit.DataSize convert(java.lang.String, org.springframework.util.unit.DataUnit);
    Code:
       0: aload_1
       1: aload_2
       2: invokestatic  #54                 // Method org/springframework/util/unit/DataSize.parse:(Ljava/lang/CharSequence;Lorg/springframework/util/unit/DataUnit;)Lorg/springframework/util/unit/DataSize;
       5: areturn
}
