Compiled from "StringToDurationConverter.java"
final class org.springframework.boot.convert.StringToDurationConverter implements org.springframework.core.convert.converter.GenericConverter {
  org.springframework.boot.convert.StringToDurationConverter();
    Code:
       0: aload_0
       1: invokespecial #1                  // Method java/lang/Object."<init>":()V
       4: return

  public java.util.Set<org.springframework.core.convert.converter.GenericConverter$ConvertiblePair> getConvertibleTypes();
    Code:
       0: new           #7                  // class org/springframework/core/convert/converter/GenericConverter$ConvertiblePair
       3: dup
       4: ldc           #9                  // class java/lang/String
       6: ldc           #11                 // class java/time/Duration
       8: invokespecial #13                 // Method org/springframework/core/convert/converter/GenericConverter$ConvertiblePair."<init>":(Ljava/lang/Class;Ljava/lang/Class;)V
      11: invokestatic  #16                 // Method java/util/Collections.singleton:(Ljava/lang/Object;)Ljava/util/Set;
      14: areturn

  public java.lang.Object convert(java.lang.Object, org.springframework.core.convert.TypeDescriptor, org.springframework.core.convert.TypeDescriptor);
    Code:
       0: aload_1
       1: invokestatic  #22                 // Method org/springframework/util/ObjectUtils.isEmpty:(Ljava/lang/Object;)Z
       4: ifeq          9
       7: aconst_null
       8: areturn
       9: aload_0
      10: aload_1
      11: invokevirtual #28                 // Method java/lang/Object.toString:()Ljava/lang/String;
      14: aload_0
      15: aload_3
      16: invokevirtual #32                 // Method getStyle:(Lorg/springframework/core/convert/TypeDescriptor;)Lorg/springframework/boot/convert/DurationStyle;
      19: aload_0
      20: aload_3
      21: invokevirtual #38                 // Method getDurationUnit:(Lorg/springframework/core/convert/TypeDescriptor;)Ljava/time/temporal/ChronoUnit;
      24: invokevirtual #42                 // Method convert:(Ljava/lang/String;Lorg/springframework/boot/convert/DurationStyle;Ljava/time/temporal/ChronoUnit;)Ljava/time/Duration;
      27: areturn

  private org.springframework.boot.convert.DurationStyle getStyle(org.springframework.core.convert.TypeDescriptor);
    Code:
       0: aload_1
       1: ldc           #46                 // class org/springframework/boot/convert/DurationFormat
       3: invokevirtual #48                 // Method org/springframework/core/convert/TypeDescriptor.getAnnotation:(Ljava/lang/Class;)Ljava/lang/annotation/Annotation;
       6: checkcast     #46                 // class org/springframework/boot/convert/DurationFormat
       9: astore_2
      10: aload_2
      11: ifnull        23
      14: aload_2
      15: invokeinterface #54,  1           // InterfaceMethod org/springframework/boot/convert/DurationFormat.value:()Lorg/springframework/boot/convert/DurationStyle;
      20: goto          24
      23: aconst_null
      24: areturn

  private java.time.temporal.ChronoUnit getDurationUnit(org.springframework.core.convert.TypeDescriptor);
    Code:
       0: aload_1
       1: ldc           #58                 // class org/springframework/boot/convert/DurationUnit
       3: invokevirtual #48                 // Method org/springframework/core/convert/TypeDescriptor.getAnnotation:(Ljava/lang/Class;)Ljava/lang/annotation/Annotation;
       6: checkcast     #58                 // class org/springframework/boot/convert/DurationUnit
       9: astore_2
      10: aload_2
      11: ifnull        23
      14: aload_2
      15: invokeinterface #60,  1           // InterfaceMethod org/springframework/boot/convert/DurationUnit.value:()Ljava/time/temporal/ChronoUnit;
      20: goto          24
      23: aconst_null
      24: areturn

  private java.time.Duration convert(java.lang.String, org.springframework.boot.convert.DurationStyle, java.time.temporal.ChronoUnit);
    Code:
       0: aload_2
       1: ifnull        8
       4: aload_2
       5: goto          12
       8: aload_1
       9: invokestatic  #63                 // Method org/springframework/boot/convert/DurationStyle.detect:(Ljava/lang/String;)Lorg/springframework/boot/convert/DurationStyle;
      12: astore_2
      13: aload_2
      14: aload_1
      15: aload_3
      16: invokevirtual #69                 // Method org/springframework/boot/convert/DurationStyle.parse:(Ljava/lang/String;Ljava/time/temporal/ChronoUnit;)Ljava/time/Duration;
      19: areturn
}
