Compiled from "Serialization.java"
public interface com.alibaba.dubbo.common.serialize.Serialization extends org.apache.dubbo.common.serialize.Serialization {
  public abstract com.alibaba.dubbo.common.serialize.ObjectOutput serialize(com.alibaba.dubbo.common.URL, java.io.OutputStream) throws java.io.IOException;

  public abstract com.alibaba.dubbo.common.serialize.ObjectInput deserialize(com.alibaba.dubbo.common.URL, java.io.InputStream) throws java.io.IOException;

  public default org.apache.dubbo.common.serialize.ObjectOutput serialize(org.apache.dubbo.common.URL, java.io.OutputStream) throws java.io.IOException;
    Code:
       0: aload_0
       1: new           #1                  // class com/alibaba/dubbo/common/URL
       4: dup
       5: aload_1
       6: invokespecial #2                  // Method com/alibaba/dubbo/common/URL."<init>":(Lorg/apache/dubbo/common/URL;)V
       9: aload_2
      10: invokeinterface #3,  3            // InterfaceMethod serialize:(Lcom/alibaba/dubbo/common/URL;Ljava/io/OutputStream;)Lcom/alibaba/dubbo/common/serialize/ObjectOutput;
      15: areturn

  public default org.apache.dubbo.common.serialize.ObjectInput deserialize(org.apache.dubbo.common.URL, java.io.InputStream) throws java.io.IOException;
    Code:
       0: aload_0
       1: new           #1                  // class com/alibaba/dubbo/common/URL
       4: dup
       5: aload_1
       6: invokespecial #2                  // Method com/alibaba/dubbo/common/URL."<init>":(Lorg/apache/dubbo/common/URL;)V
       9: aload_2
      10: invokeinterface #4,  3            // InterfaceMethod deserialize:(Lcom/alibaba/dubbo/common/URL;Ljava/io/InputStream;)Lcom/alibaba/dubbo/common/serialize/ObjectInput;
      15: areturn
}
