Compiled from "AbstractWireProtocol.java"
public abstract class org.apache.dubbo.remoting.api.AbstractWireProtocol implements org.apache.dubbo.remoting.api.WireProtocol {
  private final org.apache.dubbo.remoting.api.ProtocolDetector detector;

  public org.apache.dubbo.remoting.api.AbstractWireProtocol(org.apache.dubbo.remoting.api.ProtocolDetector);
    Code:
       0: aload_0
       1: invokespecial #1                  // Method java/lang/Object."<init>":()V
       4: aload_0
       5: aload_1
       6: putfield      #2                  // Field detector:Lorg/apache/dubbo/remoting/api/ProtocolDetector;
       9: return

  public org.apache.dubbo.remoting.api.ProtocolDetector detector();
    Code:
       0: aload_0
       1: getfield      #2                  // Field detector:Lorg/apache/dubbo/remoting/api/ProtocolDetector;
       4: areturn

  public void configClientPipeline(org.apache.dubbo.common.URL, org.apache.dubbo.remoting.api.pu.ChannelOperator, org.apache.dubbo.remoting.api.ssl.ContextOperator);
    Code:
       0: return

  public void close();
    Code:
       0: return
}
