Compiled from "JCache.java"
public class org.apache.dubbo.cache.support.jcache.JCache implements org.apache.dubbo.cache.Cache {
  private final javax.cache.Cache<java.lang.Object, java.lang.Object> store;

  public org.apache.dubbo.cache.support.jcache.JCache(org.apache.dubbo.common.URL);
    Code:
       0: aload_0
       1: invokespecial #2                  // Method java/lang/Object."<init>":()V
       4: aload_1
       5: ldc           #3                  // String method
       7: ldc           #4                  // String
       9: invokevirtual #5                  // Method org/apache/dubbo/common/URL.getParameter:(Ljava/lang/String;Ljava/lang/String;)Ljava/lang/String;
      12: astore_2
      13: new           #6                  // class java/lang/StringBuilder
      16: dup
      17: invokespecial #7                  // Method java/lang/StringBuilder."<init>":()V
      20: aload_1
      21: invokevirtual #8                  // Method org/apache/dubbo/common/URL.getAddress:()Ljava/lang/String;
      24: invokevirtual #9                  // Method java/lang/StringBuilder.append:(Ljava/lang/String;)Ljava/lang/StringBuilder;
      27: ldc           #10                 // String .
      29: invokevirtual #9                  // Method java/lang/StringBuilder.append:(Ljava/lang/String;)Ljava/lang/StringBuilder;
      32: aload_1
      33: invokevirtual #11                 // Method org/apache/dubbo/common/URL.getServiceKey:()Ljava/lang/String;
      36: invokevirtual #9                  // Method java/lang/StringBuilder.append:(Ljava/lang/String;)Ljava/lang/StringBuilder;
      39: ldc           #10                 // String .
      41: invokevirtual #9                  // Method java/lang/StringBuilder.append:(Ljava/lang/String;)Ljava/lang/StringBuilder;
      44: aload_2
      45: invokevirtual #9                  // Method java/lang/StringBuilder.append:(Ljava/lang/String;)Ljava/lang/StringBuilder;
      48: invokevirtual #12                 // Method java/lang/StringBuilder.toString:()Ljava/lang/String;
      51: astore_3
      52: aload_1
      53: ldc           #13                 // String jcache
      55: invokevirtual #14                 // Method org/apache/dubbo/common/URL.getParameter:(Ljava/lang/String;)Ljava/lang/String;
      58: astore        4
      60: aload         4
      62: invokestatic  #15                 // Method org/apache/dubbo/common/utils/StringUtils.isEmpty:(Ljava/lang/String;)Z
      65: ifeq          74
      68: invokestatic  #16                 // Method javax/cache/Caching.getCachingProvider:()Ljavax/cache/spi/CachingProvider;
      71: goto          79
      74: aload         4
      76: invokestatic  #17                 // Method javax/cache/Caching.getCachingProvider:(Ljava/lang/String;)Ljavax/cache/spi/CachingProvider;
      79: astore        5
      81: aload         5
      83: invokeinterface #18,  1           // InterfaceMethod javax/cache/spi/CachingProvider.getCacheManager:()Ljavax/cache/CacheManager;
      88: astore        6
      90: aload         6
      92: aload_3
      93: invokeinterface #19,  2           // InterfaceMethod javax/cache/CacheManager.getCache:(Ljava/lang/String;)Ljavax/cache/Cache;
      98: astore        7
     100: aload         7
     102: ifnonnull     186
     105: new           #20                 // class javax/cache/configuration/MutableConfiguration
     108: dup
     109: invokespecial #21                 // Method javax/cache/configuration/MutableConfiguration."<init>":()V
     112: ldc           #22                 // class java/lang/Object
     114: ldc           #22                 // class java/lang/Object
     116: invokevirtual #23                 // Method javax/cache/configuration/MutableConfiguration.setTypes:(Ljava/lang/Class;Ljava/lang/Class;)Ljavax/cache/configuration/MutableConfiguration;
     119: new           #24                 // class javax/cache/expiry/Duration
     122: dup
     123: getstatic     #25                 // Field java/util/concurrent/TimeUnit.MILLISECONDS:Ljava/util/concurrent/TimeUnit;
     126: aload_1
     127: aload_2
     128: ldc           #26                 // String cache.write.expire
     130: ldc           #27                 // int 60000
     132: invokevirtual #28                 // Method org/apache/dubbo/common/URL.getMethodParameter:(Ljava/lang/String;Ljava/lang/String;I)I
     135: i2l
     136: invokespecial #29                 // Method javax/cache/expiry/Duration."<init>":(Ljava/util/concurrent/TimeUnit;J)V
     139: invokestatic  #30                 // Method javax/cache/expiry/CreatedExpiryPolicy.factoryOf:(Ljavax/cache/expiry/Duration;)Ljavax/cache/configuration/Factory;
     142: invokevirtual #31                 // Method javax/cache/configuration/MutableConfiguration.setExpiryPolicyFactory:(Ljavax/cache/configuration/Factory;)Ljavax/cache/configuration/MutableConfiguration;
     145: iconst_0
     146: invokevirtual #32                 // Method javax/cache/configuration/MutableConfiguration.setStoreByValue:(Z)Ljavax/cache/configuration/MutableConfiguration;
     149: iconst_1
     150: invokevirtual #33                 // Method javax/cache/configuration/MutableConfiguration.setManagementEnabled:(Z)Ljavax/cache/configuration/MutableConfiguration;
     153: iconst_1
     154: invokevirtual #34                 // Method javax/cache/configuration/MutableConfiguration.setStatisticsEnabled:(Z)Ljavax/cache/configuration/MutableConfiguration;
     157: astore        8
     159: aload         6
     161: aload_3
     162: aload         8
     164: invokeinterface #35,  3           // InterfaceMethod javax/cache/CacheManager.createCache:(Ljava/lang/String;Ljavax/cache/configuration/Configuration;)Ljavax/cache/Cache;
     169: astore        7
     171: goto          186
     174: astore        8
     176: aload         6
     178: aload_3
     179: invokeinterface #19,  2           // InterfaceMethod javax/cache/CacheManager.getCache:(Ljava/lang/String;)Ljavax/cache/Cache;
     184: astore        7
     186: aload_0
     187: aload         7
     189: putfield      #37                 // Field store:Ljavax/cache/Cache;
     192: return
    Exception table:
       from    to  target type
         105   171   174   Class javax/cache/CacheException

  public void put(java.lang.Object, java.lang.Object);
    Code:
       0: aload_0
       1: getfield      #37                 // Field store:Ljavax/cache/Cache;
       4: aload_1
       5: aload_2
       6: invokeinterface #38,  3           // InterfaceMethod javax/cache/Cache.put:(Ljava/lang/Object;Ljava/lang/Object;)V
      11: return

  public java.lang.Object get(java.lang.Object);
    Code:
       0: aload_0
       1: getfield      #37                 // Field store:Ljavax/cache/Cache;
       4: aload_1
       5: invokeinterface #39,  2           // InterfaceMethod javax/cache/Cache.get:(Ljava/lang/Object;)Ljava/lang/Object;
      10: areturn
}
