Compiled from "AbstractMonitorFactory.java"
public abstract class org.apache.dubbo.monitor.support.AbstractMonitorFactory implements org.apache.dubbo.monitor.MonitorFactory {
  private static final org.apache.dubbo.common.logger.ErrorTypeAwareLogger logger;

  private static final java.util.concurrent.locks.ReentrantLock LOCK;

  private static final java.util.Map<java.lang.String, org.apache.dubbo.monitor.Monitor> MONITORS;

  private static final java.util.Map<java.lang.String, java.util.concurrent.Future<org.apache.dubbo.monitor.Monitor>> FUTURES;

  private static final java.util.concurrent.ExecutorService EXECUTOR;

  public org.apache.dubbo.monitor.support.AbstractMonitorFactory();
    Code:
       0: aload_0
       1: invokespecial #3                  // Method java/lang/Object."<init>":()V
       4: return

  public static java.util.Collection<org.apache.dubbo.monitor.Monitor> getMonitors();
    Code:
       0: getstatic     #4                  // Field MONITORS:Ljava/util/Map;
       3: invokeinterface #5,  1            // InterfaceMethod java/util/Map.values:()Ljava/util/Collection;
       8: invokestatic  #6                  // Method java/util/Collections.unmodifiableCollection:(Ljava/util/Collection;)Ljava/util/Collection;
      11: areturn

  public org.apache.dubbo.monitor.Monitor getMonitor(org.apache.dubbo.common.URL);
    Code:
       0: aload_1
       1: ldc           #7                  // class org/apache/dubbo/monitor/MonitorService
       3: invokevirtual #8                  // Method java/lang/Class.getName:()Ljava/lang/String;
       6: invokevirtual #9                  // Method org/apache/dubbo/common/URL.setPath:(Ljava/lang/String;)Lorg/apache/dubbo/common/URL;
       9: ldc           #10                 // String interface
      11: ldc           #7                  // class org/apache/dubbo/monitor/MonitorService
      13: invokevirtual #8                  // Method java/lang/Class.getName:()Ljava/lang/String;
      16: invokevirtual #11                 // Method org/apache/dubbo/common/URL.addParameter:(Ljava/lang/String;Ljava/lang/String;)Lorg/apache/dubbo/common/URL;
      19: astore_1
      20: aload_1
      21: invokevirtual #12                 // Method org/apache/dubbo/common/URL.toServiceStringWithoutResolving:()Ljava/lang/String;
      24: astore_2
      25: getstatic     #4                  // Field MONITORS:Ljava/util/Map;
      28: aload_2
      29: invokeinterface #13,  2           // InterfaceMethod java/util/Map.get:(Ljava/lang/Object;)Ljava/lang/Object;
      34: checkcast     #14                 // class org/apache/dubbo/monitor/Monitor
      37: astore_3
      38: getstatic     #15                 // Field FUTURES:Ljava/util/Map;
      41: aload_2
      42: invokeinterface #13,  2           // InterfaceMethod java/util/Map.get:(Ljava/lang/Object;)Ljava/lang/Object;
      47: checkcast     #16                 // class java/util/concurrent/Future
      50: astore        4
      52: aload_3
      53: ifnonnull     61
      56: aload         4
      58: ifnull        63
      61: aload_3
      62: areturn
      63: getstatic     #17                 // Field LOCK:Ljava/util/concurrent/locks/ReentrantLock;
      66: invokevirtual #18                 // Method java/util/concurrent/locks/ReentrantLock.lock:()V
      69: getstatic     #4                  // Field MONITORS:Ljava/util/Map;
      72: aload_2
      73: invokeinterface #13,  2           // InterfaceMethod java/util/Map.get:(Ljava/lang/Object;)Ljava/lang/Object;
      78: checkcast     #14                 // class org/apache/dubbo/monitor/Monitor
      81: astore_3
      82: getstatic     #15                 // Field FUTURES:Ljava/util/Map;
      85: aload_2
      86: invokeinterface #13,  2           // InterfaceMethod java/util/Map.get:(Ljava/lang/Object;)Ljava/lang/Object;
      91: checkcast     #16                 // class java/util/concurrent/Future
      94: astore        4
      96: aload_3
      97: ifnonnull     105
     100: aload         4
     102: ifnull        117
     105: aload_3
     106: astore        5
     108: getstatic     #17                 // Field LOCK:Ljava/util/concurrent/locks/ReentrantLock;
     111: invokevirtual #19                 // Method java/util/concurrent/locks/ReentrantLock.unlock:()V
     114: aload         5
     116: areturn
     117: aload_1
     118: astore        5
     120: getstatic     #20                 // Field EXECUTOR:Ljava/util/concurrent/ExecutorService;
     123: aload_0
     124: aload         5
     126: aload_2
     127: invokedynamic #21,  0             // InvokeDynamic #0:call:(Lorg/apache/dubbo/monitor/support/AbstractMonitorFactory;Lorg/apache/dubbo/common/URL;Ljava/lang/String;)Ljava/util/concurrent/Callable;
     132: invokeinterface #22,  2           // InterfaceMethod java/util/concurrent/ExecutorService.submit:(Ljava/util/concurrent/Callable;)Ljava/util/concurrent/Future;
     137: astore        4
     139: getstatic     #15                 // Field FUTURES:Ljava/util/Map;
     142: aload_2
     143: aload         4
     145: invokeinterface #23,  3           // InterfaceMethod java/util/Map.put:(Ljava/lang/Object;Ljava/lang/Object;)Ljava/lang/Object;
     150: pop
     151: aconst_null
     152: astore        6
     154: getstatic     #17                 // Field LOCK:Ljava/util/concurrent/locks/ReentrantLock;
     157: invokevirtual #19                 // Method java/util/concurrent/locks/ReentrantLock.unlock:()V
     160: aload         6
     162: areturn
     163: astore        7
     165: getstatic     #17                 // Field LOCK:Ljava/util/concurrent/locks/ReentrantLock;
     168: invokevirtual #19                 // Method java/util/concurrent/locks/ReentrantLock.unlock:()V
     171: aload         7
     173: athrow
    Exception table:
       from    to  target type
          69   108   163   any
         117   154   163   any
         163   165   163   any

  protected abstract org.apache.dubbo.monitor.Monitor createMonitor(org.apache.dubbo.common.URL);

  private org.apache.dubbo.monitor.Monitor lambda$getMonitor$0(org.apache.dubbo.common.URL, java.lang.String) throws java.lang.Exception;
    Code:
       0: aload_0
       1: aload_1
       2: invokevirtual #24                 // Method createMonitor:(Lorg/apache/dubbo/common/URL;)Lorg/apache/dubbo/monitor/Monitor;
       5: astore_3
       6: getstatic     #4                  // Field MONITORS:Ljava/util/Map;
       9: aload_2
      10: aload_3
      11: invokeinterface #23,  3           // InterfaceMethod java/util/Map.put:(Ljava/lang/Object;Ljava/lang/Object;)Ljava/lang/Object;
      16: pop
      17: getstatic     #15                 // Field FUTURES:Ljava/util/Map;
      20: aload_2
      21: invokeinterface #25,  2           // InterfaceMethod java/util/Map.remove:(Ljava/lang/Object;)Ljava/lang/Object;
      26: pop
      27: aload_3
      28: areturn
      29: astore_3
      30: getstatic     #27                 // Field logger:Lorg/apache/dubbo/common/logger/ErrorTypeAwareLogger;
      33: ldc           #28                 // String 0-14
      35: ldc           #29                 // String
      37: ldc           #29                 // String
      39: new           #30                 // class java/lang/StringBuilder
      42: dup
      43: invokespecial #31                 // Method java/lang/StringBuilder."<init>":()V
      46: ldc           #32                 // String Create monitor failed, monitor data will not be collected until you fix this problem. monitorUrl:
      48: invokevirtual #33                 // Method java/lang/StringBuilder.append:(Ljava/lang/String;)Ljava/lang/StringBuilder;
      51: aload_1
      52: invokevirtual #34                 // Method java/lang/StringBuilder.append:(Ljava/lang/Object;)Ljava/lang/StringBuilder;
      55: invokevirtual #35                 // Method java/lang/StringBuilder.toString:()Ljava/lang/String;
      58: aload_3
      59: invokeinterface #36,  6           // InterfaceMethod org/apache/dubbo/common/logger/ErrorTypeAwareLogger.warn:(Ljava/lang/String;Ljava/lang/String;Ljava/lang/String;Ljava/lang/String;Ljava/lang/Throwable;)V
      64: aconst_null
      65: areturn
    Exception table:
       from    to  target type
           0    28    29   Class java/lang/Throwable

  static {};
    Code:
       0: ldc           #37                 // class org/apache/dubbo/monitor/support/AbstractMonitorFactory
       2: invokestatic  #38                 // Method org/apache/dubbo/common/logger/LoggerFactory.getErrorTypeAwareLogger:(Ljava/lang/Class;)Lorg/apache/dubbo/common/logger/ErrorTypeAwareLogger;
       5: putstatic     #27                 // Field logger:Lorg/apache/dubbo/common/logger/ErrorTypeAwareLogger;
       8: new           #39                 // class java/util/concurrent/locks/ReentrantLock
      11: dup
      12: invokespecial #40                 // Method java/util/concurrent/locks/ReentrantLock."<init>":()V
      15: putstatic     #17                 // Field LOCK:Ljava/util/concurrent/locks/ReentrantLock;
      18: new           #41                 // class java/util/concurrent/ConcurrentHashMap
      21: dup
      22: invokespecial #42                 // Method java/util/concurrent/ConcurrentHashMap."<init>":()V
      25: putstatic     #4                  // Field MONITORS:Ljava/util/Map;
      28: new           #41                 // class java/util/concurrent/ConcurrentHashMap
      31: dup
      32: invokespecial #42                 // Method java/util/concurrent/ConcurrentHashMap."<init>":()V
      35: putstatic     #15                 // Field FUTURES:Ljava/util/Map;
      38: new           #43                 // class java/util/concurrent/ThreadPoolExecutor
      41: dup
      42: iconst_0
      43: bipush        10
      45: ldc2_w        #44                 // long 60l
      48: getstatic     #46                 // Field java/util/concurrent/TimeUnit.SECONDS:Ljava/util/concurrent/TimeUnit;
      51: new           #47                 // class java/util/concurrent/SynchronousQueue
      54: dup
      55: invokespecial #48                 // Method java/util/concurrent/SynchronousQueue."<init>":()V
      58: new           #49                 // class org/apache/dubbo/common/utils/NamedThreadFactory
      61: dup
      62: ldc           #50                 // String DubboMonitorCreator
      64: iconst_1
      65: invokespecial #51                 // Method org/apache/dubbo/common/utils/NamedThreadFactory."<init>":(Ljava/lang/String;Z)V
      68: invokespecial #52                 // Method java/util/concurrent/ThreadPoolExecutor."<init>":(IIJLjava/util/concurrent/TimeUnit;Ljava/util/concurrent/BlockingQueue;Ljava/util/concurrent/ThreadFactory;)V
      71: putstatic     #20                 // Field EXECUTOR:Ljava/util/concurrent/ExecutorService;
      74: return
}
