Compiled from "MonitorFilter.java"
public class org.apache.dubbo.monitor.support.MonitorFilter implements org.apache.dubbo.rpc.Filter,org.apache.dubbo.rpc.BaseFilter$Listener {
  private static final org.apache.dubbo.common.logger.ErrorTypeAwareLogger logger;

  private static final java.lang.String MONITOR_FILTER_START_TIME;

  private static final java.lang.String MONITOR_REMOTE_HOST_STORE;

  private final java.util.concurrent.ConcurrentMap<java.lang.String, java.util.concurrent.atomic.AtomicInteger> concurrents;

  private org.apache.dubbo.monitor.MonitorFactory monitorFactory;

  public org.apache.dubbo.monitor.support.MonitorFilter();
    Code:
       0: aload_0
       1: invokespecial #5                  // Method java/lang/Object."<init>":()V
       4: aload_0
       5: new           #6                  // class java/util/concurrent/ConcurrentHashMap
       8: dup
       9: invokespecial #7                  // Method java/util/concurrent/ConcurrentHashMap."<init>":()V
      12: putfield      #8                  // Field concurrents:Ljava/util/concurrent/ConcurrentMap;
      15: return

  public void setMonitorFactory(org.apache.dubbo.monitor.MonitorFactory);
    Code:
       0: aload_0
       1: aload_1
       2: putfield      #9                  // Field monitorFactory:Lorg/apache/dubbo/monitor/MonitorFactory;
       5: return

  public org.apache.dubbo.rpc.Result invoke(org.apache.dubbo.rpc.Invoker<?>, org.apache.dubbo.rpc.Invocation) throws org.apache.dubbo.rpc.RpcException;
    Code:
       0: aload_1
       1: invokeinterface #10,  1           // InterfaceMethod org/apache/dubbo/rpc/Invoker.getUrl:()Lorg/apache/dubbo/common/URL;
       6: ldc           #11                 // String monitor
       8: invokevirtual #12                 // Method org/apache/dubbo/common/URL.hasAttribute:(Ljava/lang/String;)Z
      11: ifeq          54
      14: aload_2
      15: ldc           #14                 // String monitor_filter_start_time
      17: invokestatic  #15                 // Method java/lang/System.currentTimeMillis:()J
      20: invokestatic  #16                 // Method java/lang/Long.valueOf:(J)Ljava/lang/Long;
      23: invokeinterface #17,  3           // InterfaceMethod org/apache/dubbo/rpc/Invocation.put:(Ljava/lang/Object;Ljava/lang/Object;)Ljava/lang/Object;
      28: pop
      29: aload_2
      30: ldc           #18                 // String monitor_remote_host_store
      32: invokestatic  #19                 // Method org/apache/dubbo/rpc/RpcContext.getServiceContext:()Lorg/apache/dubbo/rpc/RpcServiceContext;
      35: invokevirtual #20                 // Method org/apache/dubbo/rpc/RpcServiceContext.getRemoteHost:()Ljava/lang/String;
      38: invokeinterface #17,  3           // InterfaceMethod org/apache/dubbo/rpc/Invocation.put:(Ljava/lang/Object;Ljava/lang/Object;)Ljava/lang/Object;
      43: pop
      44: aload_0
      45: aload_1
      46: aload_2
      47: invokespecial #21                 // Method getConcurrent:(Lorg/apache/dubbo/rpc/Invoker;Lorg/apache/dubbo/rpc/Invocation;)Ljava/util/concurrent/atomic/AtomicInteger;
      50: invokevirtual #22                 // Method java/util/concurrent/atomic/AtomicInteger.incrementAndGet:()I
      53: pop
      54: aload_1
      55: invokeinterface #10,  1           // InterfaceMethod org/apache/dubbo/rpc/Invoker.getUrl:()Lorg/apache/dubbo/common/URL;
      60: invokevirtual #23                 // Method org/apache/dubbo/common/URL.getServiceModel:()Lorg/apache/dubbo/rpc/model/ServiceModel;
      63: astore_3
      64: aload_3
      65: instanceof    #24                 // class org/apache/dubbo/rpc/model/ProviderModel
      68: ifeq          78
      71: aload_3
      72: checkcast     #24                 // class org/apache/dubbo/rpc/model/ProviderModel
      75: invokevirtual #25                 // Method org/apache/dubbo/rpc/model/ProviderModel.updateLastInvokeTime:()V
      78: aload_1
      79: aload_2
      80: invokeinterface #26,  2           // InterfaceMethod org/apache/dubbo/rpc/Invoker.invoke:(Lorg/apache/dubbo/rpc/Invocation;)Lorg/apache/dubbo/rpc/Result;
      85: areturn

  private java.util.concurrent.atomic.AtomicInteger getConcurrent(org.apache.dubbo.rpc.Invoker<?>, org.apache.dubbo.rpc.Invocation);
    Code:
       0: new           #27                 // class java/lang/StringBuilder
       3: dup
       4: invokespecial #28                 // Method java/lang/StringBuilder."<init>":()V
       7: aload_1
       8: invokeinterface #29,  1           // InterfaceMethod org/apache/dubbo/rpc/Invoker.getInterface:()Ljava/lang/Class;
      13: invokevirtual #30                 // Method java/lang/Class.getName:()Ljava/lang/String;
      16: invokevirtual #31                 // Method java/lang/StringBuilder.append:(Ljava/lang/String;)Ljava/lang/StringBuilder;
      19: ldc           #32                 // String .
      21: invokevirtual #31                 // Method java/lang/StringBuilder.append:(Ljava/lang/String;)Ljava/lang/StringBuilder;
      24: aload_2
      25: invokeinterface #33,  1           // InterfaceMethod org/apache/dubbo/rpc/Invocation.getMethodName:()Ljava/lang/String;
      30: invokevirtual #31                 // Method java/lang/StringBuilder.append:(Ljava/lang/String;)Ljava/lang/StringBuilder;
      33: invokevirtual #34                 // Method java/lang/StringBuilder.toString:()Ljava/lang/String;
      36: astore_3
      37: aload_0
      38: getfield      #8                  // Field concurrents:Ljava/util/concurrent/ConcurrentMap;
      41: aload_3
      42: invokedynamic #35,  0             // InvokeDynamic #0:apply:()Ljava/util/function/Function;
      47: invokestatic  #36                 // Method org/apache/dubbo/common/utils/ConcurrentHashMapUtils.computeIfAbsent:(Ljava/util/concurrent/ConcurrentMap;Ljava/lang/Object;Ljava/util/function/Function;)Ljava/lang/Object;
      50: checkcast     #37                 // class java/util/concurrent/atomic/AtomicInteger
      53: areturn

  public void onResponse(org.apache.dubbo.rpc.Result, org.apache.dubbo.rpc.Invoker<?>, org.apache.dubbo.rpc.Invocation);
    Code:
       0: aload_2
       1: invokeinterface #10,  1           // InterfaceMethod org/apache/dubbo/rpc/Invoker.getUrl:()Lorg/apache/dubbo/common/URL;
       6: ldc           #11                 // String monitor
       8: invokevirtual #12                 // Method org/apache/dubbo/common/URL.hasAttribute:(Ljava/lang/String;)Z
      11: ifeq          66
      14: aload_3
      15: ldc           #14                 // String monitor_filter_start_time
      17: invokeinterface #38,  2           // InterfaceMethod org/apache/dubbo/rpc/Invocation.get:(Ljava/lang/Object;)Ljava/lang/Object;
      22: checkcast     #39                 // class java/lang/Long
      25: astore        4
      27: aload         4
      29: ifnull        56
      32: aload_0
      33: aload_2
      34: aload_3
      35: aload_1
      36: aload_3
      37: ldc           #18                 // String monitor_remote_host_store
      39: invokeinterface #38,  2           // InterfaceMethod org/apache/dubbo/rpc/Invocation.get:(Ljava/lang/Object;)Ljava/lang/Object;
      44: checkcast     #40                 // class java/lang/String
      47: aload         4
      49: invokevirtual #41                 // Method java/lang/Long.longValue:()J
      52: iconst_0
      53: invokespecial #42                 // Method collect:(Lorg/apache/dubbo/rpc/Invoker;Lorg/apache/dubbo/rpc/Invocation;Lorg/apache/dubbo/rpc/Result;Ljava/lang/String;JZ)V
      56: aload_0
      57: aload_2
      58: aload_3
      59: invokespecial #21                 // Method getConcurrent:(Lorg/apache/dubbo/rpc/Invoker;Lorg/apache/dubbo/rpc/Invocation;)Ljava/util/concurrent/atomic/AtomicInteger;
      62: invokevirtual #43                 // Method java/util/concurrent/atomic/AtomicInteger.decrementAndGet:()I
      65: pop
      66: return

  public void onError(java.lang.Throwable, org.apache.dubbo.rpc.Invoker<?>, org.apache.dubbo.rpc.Invocation);
    Code:
       0: aload_2
       1: invokeinterface #10,  1           // InterfaceMethod org/apache/dubbo/rpc/Invoker.getUrl:()Lorg/apache/dubbo/common/URL;
       6: ldc           #11                 // String monitor
       8: invokevirtual #12                 // Method org/apache/dubbo/common/URL.hasAttribute:(Ljava/lang/String;)Z
      11: ifeq          66
      14: aload_3
      15: ldc           #14                 // String monitor_filter_start_time
      17: invokeinterface #38,  2           // InterfaceMethod org/apache/dubbo/rpc/Invocation.get:(Ljava/lang/Object;)Ljava/lang/Object;
      22: checkcast     #39                 // class java/lang/Long
      25: astore        4
      27: aload         4
      29: ifnull        56
      32: aload_0
      33: aload_2
      34: aload_3
      35: aconst_null
      36: aload_3
      37: ldc           #18                 // String monitor_remote_host_store
      39: invokeinterface #38,  2           // InterfaceMethod org/apache/dubbo/rpc/Invocation.get:(Ljava/lang/Object;)Ljava/lang/Object;
      44: checkcast     #40                 // class java/lang/String
      47: aload         4
      49: invokevirtual #41                 // Method java/lang/Long.longValue:()J
      52: iconst_1
      53: invokespecial #42                 // Method collect:(Lorg/apache/dubbo/rpc/Invoker;Lorg/apache/dubbo/rpc/Invocation;Lorg/apache/dubbo/rpc/Result;Ljava/lang/String;JZ)V
      56: aload_0
      57: aload_2
      58: aload_3
      59: invokespecial #21                 // Method getConcurrent:(Lorg/apache/dubbo/rpc/Invoker;Lorg/apache/dubbo/rpc/Invocation;)Ljava/util/concurrent/atomic/AtomicInteger;
      62: invokevirtual #43                 // Method java/util/concurrent/atomic/AtomicInteger.decrementAndGet:()I
      65: pop
      66: return

  private void collect(org.apache.dubbo.rpc.Invoker<?>, org.apache.dubbo.rpc.Invocation, org.apache.dubbo.rpc.Result, java.lang.String, long, boolean);
    Code:
       0: aload_1
       1: invokeinterface #10,  1           // InterfaceMethod org/apache/dubbo/rpc/Invoker.getUrl:()Lorg/apache/dubbo/common/URL;
       6: ldc           #11                 // String monitor
       8: invokevirtual #44                 // Method org/apache/dubbo/common/URL.getAttribute:(Ljava/lang/String;)Ljava/lang/Object;
      11: astore        8
      13: aload         8
      15: instanceof    #45                 // class org/apache/dubbo/common/URL
      18: ifeq          70
      21: aload_0
      22: getfield      #9                  // Field monitorFactory:Lorg/apache/dubbo/monitor/MonitorFactory;
      25: aload         8
      27: checkcast     #45                 // class org/apache/dubbo/common/URL
      30: invokeinterface #46,  2           // InterfaceMethod org/apache/dubbo/monitor/MonitorFactory.getMonitor:(Lorg/apache/dubbo/common/URL;)Lorg/apache/dubbo/monitor/Monitor;
      35: astore        9
      37: aload         9
      39: ifnonnull     43
      42: return
      43: aload_0
      44: aload_1
      45: aload_2
      46: aload_3
      47: aload         4
      49: lload         5
      51: iload         7
      53: invokespecial #47                 // Method createStatisticsUrl:(Lorg/apache/dubbo/rpc/Invoker;Lorg/apache/dubbo/rpc/Invocation;Lorg/apache/dubbo/rpc/Result;Ljava/lang/String;JZ)Lorg/apache/dubbo/common/URL;
      56: astore        10
      58: aload         9
      60: aload         10
      62: invokevirtual #48                 // Method org/apache/dubbo/common/URL.toSerializableURL:()Lorg/apache/dubbo/common/URL;
      65: invokeinterface #49,  2           // InterfaceMethod org/apache/dubbo/monitor/Monitor.collect:(Lorg/apache/dubbo/common/URL;)V
      70: goto          128
      73: astore        8
      75: getstatic     #51                 // Field logger:Lorg/apache/dubbo/common/logger/ErrorTypeAwareLogger;
      78: ldc           #52                 // String 0-14
      80: ldc           #53                 // String
      82: ldc           #53                 // String
      84: new           #27                 // class java/lang/StringBuilder
      87: dup
      88: invokespecial #28                 // Method java/lang/StringBuilder."<init>":()V
      91: ldc           #54                 // String Failed to monitor count service
      93: invokevirtual #31                 // Method java/lang/StringBuilder.append:(Ljava/lang/String;)Ljava/lang/StringBuilder;
      96: aload_1
      97: invokeinterface #10,  1           // InterfaceMethod org/apache/dubbo/rpc/Invoker.getUrl:()Lorg/apache/dubbo/common/URL;
     102: invokevirtual #55                 // Method java/lang/StringBuilder.append:(Ljava/lang/Object;)Ljava/lang/StringBuilder;
     105: ldc           #56                 // String , cause:
     107: invokevirtual #31                 // Method java/lang/StringBuilder.append:(Ljava/lang/String;)Ljava/lang/StringBuilder;
     110: aload         8
     112: invokevirtual #57                 // Method java/lang/Throwable.getMessage:()Ljava/lang/String;
     115: invokevirtual #31                 // Method java/lang/StringBuilder.append:(Ljava/lang/String;)Ljava/lang/StringBuilder;
     118: invokevirtual #34                 // Method java/lang/StringBuilder.toString:()Ljava/lang/String;
     121: aload         8
     123: invokeinterface #58,  6           // InterfaceMethod org/apache/dubbo/common/logger/ErrorTypeAwareLogger.warn:(Ljava/lang/String;Ljava/lang/String;Ljava/lang/String;Ljava/lang/String;Ljava/lang/Throwable;)V
     128: return
    Exception table:
       from    to  target type
           0    42    73   Class java/lang/Throwable
          43    70    73   Class java/lang/Throwable

  private org.apache.dubbo.common.URL createStatisticsUrl(org.apache.dubbo.rpc.Invoker<?>, org.apache.dubbo.rpc.Invocation, org.apache.dubbo.rpc.Result, java.lang.String, long, boolean);
    Code:
       0: invokestatic  #15                 // Method java/lang/System.currentTimeMillis:()J
       3: lload         5
       5: lsub
       6: lstore        8
       8: aload_0
       9: aload_1
      10: aload_2
      11: invokespecial #21                 // Method getConcurrent:(Lorg/apache/dubbo/rpc/Invoker;Lorg/apache/dubbo/rpc/Invocation;)Ljava/util/concurrent/atomic/AtomicInteger;
      14: invokevirtual #59                 // Method java/util/concurrent/atomic/AtomicInteger.get:()I
      17: istore        10
      19: aload_1
      20: invokeinterface #10,  1           // InterfaceMethod org/apache/dubbo/rpc/Invoker.getUrl:()Lorg/apache/dubbo/common/URL;
      25: invokevirtual #60                 // Method org/apache/dubbo/common/URL.getApplication:()Ljava/lang/String;
      28: astore        11
      30: aload_1
      31: invokeinterface #29,  1           // InterfaceMethod org/apache/dubbo/rpc/Invoker.getInterface:()Ljava/lang/Class;
      36: invokevirtual #30                 // Method java/lang/Class.getName:()Ljava/lang/String;
      39: astore        12
      41: aload_2
      42: invokestatic  #61                 // Method org/apache/dubbo/rpc/support/RpcUtils.getMethodName:(Lorg/apache/dubbo/rpc/Invocation;)Ljava/lang/String;
      45: astore        13
      47: aload_1
      48: invokeinterface #10,  1           // InterfaceMethod org/apache/dubbo/rpc/Invoker.getUrl:()Lorg/apache/dubbo/common/URL;
      53: invokevirtual #62                 // Method org/apache/dubbo/common/URL.getGroup:()Ljava/lang/String;
      56: astore        14
      58: aload_1
      59: invokeinterface #10,  1           // InterfaceMethod org/apache/dubbo/rpc/Invoker.getUrl:()Lorg/apache/dubbo/common/URL;
      64: invokevirtual #63                 // Method org/apache/dubbo/common/URL.getVersion:()Ljava/lang/String;
      67: astore        15
      69: ldc           #64                 // String consumer
      71: aload_1
      72: invokeinterface #10,  1           // InterfaceMethod org/apache/dubbo/rpc/Invoker.getUrl:()Lorg/apache/dubbo/common/URL;
      77: invokevirtual #65                 // Method org/apache/dubbo/common/URL.getSide:()Ljava/lang/String;
      80: invokevirtual #66                 // Method java/lang/String.equals:(Ljava/lang/Object;)Z
      83: ifeq          107
      86: iconst_0
      87: istore        16
      89: ldc           #67                 // String provider
      91: astore        17
      93: aload_1
      94: invokeinterface #10,  1           // InterfaceMethod org/apache/dubbo/rpc/Invoker.getUrl:()Lorg/apache/dubbo/common/URL;
      99: invokevirtual #68                 // Method org/apache/dubbo/common/URL.getAddress:()Ljava/lang/String;
     102: astore        18
     104: goto          126
     107: aload_1
     108: invokeinterface #10,  1           // InterfaceMethod org/apache/dubbo/rpc/Invoker.getUrl:()Lorg/apache/dubbo/common/URL;
     113: invokevirtual #69                 // Method org/apache/dubbo/common/URL.getPort:()I
     116: istore        16
     118: ldc           #64                 // String consumer
     120: astore        17
     122: aload         4
     124: astore        18
     126: ldc           #53                 // String
     128: astore        19
     130: ldc           #53                 // String
     132: astore        20
     134: aload_2
     135: ldc           #70                 // String input
     137: invokeinterface #71,  2           // InterfaceMethod org/apache/dubbo/rpc/Invocation.getAttachment:(Ljava/lang/String;)Ljava/lang/String;
     142: ifnull        155
     145: aload_2
     146: ldc           #70                 // String input
     148: invokeinterface #71,  2           // InterfaceMethod org/apache/dubbo/rpc/Invocation.getAttachment:(Ljava/lang/String;)Ljava/lang/String;
     153: astore        19
     155: aload_3
     156: ifnull        180
     159: aload_3
     160: ldc           #72                 // String output
     162: invokeinterface #73,  2           // InterfaceMethod org/apache/dubbo/rpc/Result.getAttachment:(Ljava/lang/String;)Ljava/lang/String;
     167: ifnull        180
     170: aload_3
     171: ldc           #72                 // String output
     173: invokeinterface #73,  2           // InterfaceMethod org/apache/dubbo/rpc/Result.getAttachment:(Ljava/lang/String;)Ljava/lang/String;
     178: astore        20
     180: new           #74                 // class org/apache/dubbo/common/url/component/ServiceConfigURL
     183: dup
     184: ldc           #75                 // String count
     186: invokestatic  #76                 // Method org/apache/dubbo/common/utils/NetUtils.getLocalHost:()Ljava/lang/String;
     189: iload         16
     191: new           #27                 // class java/lang/StringBuilder
     194: dup
     195: invokespecial #28                 // Method java/lang/StringBuilder."<init>":()V
     198: aload         12
     200: invokevirtual #31                 // Method java/lang/StringBuilder.append:(Ljava/lang/String;)Ljava/lang/StringBuilder;
     203: ldc           #77                 // String /
     205: invokevirtual #31                 // Method java/lang/StringBuilder.append:(Ljava/lang/String;)Ljava/lang/StringBuilder;
     208: aload         13
     210: invokevirtual #31                 // Method java/lang/StringBuilder.append:(Ljava/lang/String;)Ljava/lang/StringBuilder;
     213: invokevirtual #34                 // Method java/lang/StringBuilder.toString:()Ljava/lang/String;
     216: bipush        22
     218: anewarray     #40                 // class java/lang/String
     221: dup
     222: iconst_0
     223: ldc           #78                 // String application
     225: aastore
     226: dup
     227: iconst_1
     228: aload         11
     230: aastore
     231: dup
     232: iconst_2
     233: ldc           #79                 // String interface
     235: aastore
     236: dup
     237: iconst_3
     238: aload         12
     240: aastore
     241: dup
     242: iconst_4
     243: ldc           #80                 // String method
     245: aastore
     246: dup
     247: iconst_5
     248: aload         13
     250: aastore
     251: dup
     252: bipush        6
     254: aload         17
     256: aastore
     257: dup
     258: bipush        7
     260: aload         18
     262: aastore
     263: dup
     264: bipush        8
     266: iload         7
     268: ifeq          276
     271: ldc           #81                 // String failure
     273: goto          278
     276: ldc           #82                 // String success
     278: aastore
     279: dup
     280: bipush        9
     282: ldc           #83                 // String 1
     284: aastore
     285: dup
     286: bipush        10
     288: ldc           #84                 // String elapsed
     290: aastore
     291: dup
     292: bipush        11
     294: lload         8
     296: invokestatic  #85                 // Method java/lang/String.valueOf:(J)Ljava/lang/String;
     299: aastore
     300: dup
     301: bipush        12
     303: ldc           #86                 // String concurrent
     305: aastore
     306: dup
     307: bipush        13
     309: iload         10
     311: invokestatic  #87                 // Method java/lang/String.valueOf:(I)Ljava/lang/String;
     314: aastore
     315: dup
     316: bipush        14
     318: ldc           #70                 // String input
     320: aastore
     321: dup
     322: bipush        15
     324: aload         19
     326: aastore
     327: dup
     328: bipush        16
     330: ldc           #72                 // String output
     332: aastore
     333: dup
     334: bipush        17
     336: aload         20
     338: aastore
     339: dup
     340: bipush        18
     342: ldc           #88                 // String group
     344: aastore
     345: dup
     346: bipush        19
     348: aload         14
     350: aastore
     351: dup
     352: bipush        20
     354: ldc           #89                 // String version
     356: aastore
     357: dup
     358: bipush        21
     360: aload         15
     362: aastore
     363: invokespecial #90                 // Method org/apache/dubbo/common/url/component/ServiceConfigURL."<init>":(Ljava/lang/String;Ljava/lang/String;ILjava/lang/String;[Ljava/lang/String;)V
     366: areturn

  private static java.util.concurrent.atomic.AtomicInteger lambda$getConcurrent$0(java.lang.String);
    Code:
       0: new           #37                 // class java/util/concurrent/atomic/AtomicInteger
       3: dup
       4: invokespecial #91                 // Method java/util/concurrent/atomic/AtomicInteger."<init>":()V
       7: areturn

  static {};
    Code:
       0: ldc           #13                 // class org/apache/dubbo/monitor/support/MonitorFilter
       2: invokestatic  #92                 // Method org/apache/dubbo/common/logger/LoggerFactory.getErrorTypeAwareLogger:(Ljava/lang/Class;)Lorg/apache/dubbo/common/logger/ErrorTypeAwareLogger;
       5: putstatic     #51                 // Field logger:Lorg/apache/dubbo/common/logger/ErrorTypeAwareLogger;
       8: return
}
