Compiled from "ClientTripleReactorSubscriber.java"
public class org.apache.dubbo.reactive.ClientTripleReactorSubscriber<T> extends org.apache.dubbo.reactive.AbstractTripleReactorSubscriber<T> {
  public org.apache.dubbo.reactive.ClientTripleReactorSubscriber();
    Code:
       0: aload_0
       1: invokespecial #1                  // Method org/apache/dubbo/reactive/AbstractTripleReactorSubscriber."<init>":()V
       4: return

  public void cancel();
    Code:
       0: aload_0
       1: invokevirtual #2                  // Method isCanceled:()Z
       4: ifne          30
       7: aload_0
       8: invokespecial #3                  // Method org/apache/dubbo/reactive/AbstractTripleReactorSubscriber.cancel:()V
      11: aload_0
      12: getfield      #4                  // Field downstream:Lorg/apache/dubbo/rpc/protocol/tri/observer/CallStreamObserver;
      15: checkcast     #5                  // class org/apache/dubbo/rpc/protocol/tri/observer/ClientCallToObserverAdapter
      18: new           #6                  // class java/lang/Exception
      21: dup
      22: ldc           #7                  // String Cancelled
      24: invokespecial #8                  // Method java/lang/Exception."<init>":(Ljava/lang/String;)V
      27: invokevirtual #9                  // Method org/apache/dubbo/rpc/protocol/tri/observer/ClientCallToObserverAdapter.cancel:(Ljava/lang/Throwable;)V
      30: return
}
