Compiled from "ClientTripleReactorPublisher.java"
public class org.apache.dubbo.reactive.ClientTripleReactorPublisher<T> extends org.apache.dubbo.reactive.AbstractTripleReactorPublisher<T> {
  public org.apache.dubbo.reactive.ClientTripleReactorPublisher();
    Code:
       0: aload_0
       1: invokespecial #1                  // Method org/apache/dubbo/reactive/AbstractTripleReactorPublisher."<init>":()V
       4: return

  public org.apache.dubbo.reactive.ClientTripleReactorPublisher(java.util.function.Consumer<org.apache.dubbo.rpc.protocol.tri.observer.CallStreamObserver<?>>, java.lang.Runnable);
    Code:
       0: aload_0
       1: aload_1
       2: aload_2
       3: invokespecial #2                  // Method org/apache/dubbo/reactive/AbstractTripleReactorPublisher."<init>":(Ljava/util/function/Consumer;Ljava/lang/Runnable;)V
       6: return

  public void beforeStart(org.apache.dubbo.rpc.protocol.tri.observer.ClientCallToObserverAdapter<T>);
    Code:
       0: aload_0
       1: aload_1
       2: invokespecial #3                  // Method org/apache/dubbo/reactive/AbstractTripleReactorPublisher.onSubscribe:(Lorg/apache/dubbo/rpc/protocol/tri/observer/CallStreamObserver;)V
       5: return
}
