Compiled from "ServerTripleReactorSubscriber.java"
public class org.apache.dubbo.reactive.ServerTripleReactorSubscriber<T> extends org.apache.dubbo.reactive.AbstractTripleReactorSubscriber<T> {
  public org.apache.dubbo.reactive.ServerTripleReactorSubscriber();
    Code:
       0: aload_0
       1: invokespecial #1                  // Method org/apache/dubbo/reactive/AbstractTripleReactorSubscriber."<init>":()V
       4: return

  public void subscribe(org.apache.dubbo.rpc.protocol.tri.observer.CallStreamObserver<T>);
    Code:
       0: aload_0
       1: aload_1
       2: invokespecial #2                  // Method org/apache/dubbo/reactive/AbstractTripleReactorSubscriber.subscribe:(Lorg/apache/dubbo/rpc/protocol/tri/observer/CallStreamObserver;)V
       5: aload_1
       6: instanceof    #3                  // class org/apache/dubbo/rpc/protocol/tri/CancelableStreamObserver
       9: ifeq          55
      12: aload_1
      13: checkcast     #3                  // class org/apache/dubbo/rpc/protocol/tri/CancelableStreamObserver
      16: astore_2
      17: aload_2
      18: invokevirtual #4                  // Method org/apache/dubbo/rpc/protocol/tri/CancelableStreamObserver.getCancellationContext:()Lorg/apache/dubbo/rpc/CancellationContext;
      21: ifnonnull     40
      24: new           #5                  // class org/apache/dubbo/rpc/CancellationContext
      27: dup
      28: invokespecial #6                  // Method org/apache/dubbo/rpc/CancellationContext."<init>":()V
      31: astore_3
      32: aload_2
      33: aload_3
      34: invokevirtual #7                  // Method org/apache/dubbo/rpc/protocol/tri/CancelableStreamObserver.setCancellationContext:(Lorg/apache/dubbo/rpc/CancellationContext;)V
      37: goto          45
      40: aload_2
      41: invokevirtual #4                  // Method org/apache/dubbo/rpc/protocol/tri/CancelableStreamObserver.getCancellationContext:()Lorg/apache/dubbo/rpc/CancellationContext;
      44: astore_3
      45: aload_3
      46: aload_0
      47: invokedynamic #8,  0              // InvokeDynamic #0:cancelled:(Lorg/apache/dubbo/reactive/ServerTripleReactorSubscriber;)Lorg/apache/dubbo/rpc/CancellationListener;
      52: invokevirtual #9                  // Method org/apache/dubbo/rpc/CancellationContext.addListener:(Lorg/apache/dubbo/rpc/CancellationListener;)V
      55: return

  private void lambda$subscribe$0(org.apache.dubbo.rpc.RpcServiceContext);
    Code:
       0: aload_0
       1: invokespecial #10                 // Method org/apache/dubbo/reactive/AbstractTripleReactorSubscriber.cancel:()V
       4: return
}
