Compiled from "AsyncMethodInfo.java"
public class org.apache.dubbo.rpc.model.AsyncMethodInfo {
  private java.lang.Object oninvokeInstance;

  private java.lang.reflect.Method oninvokeMethod;

  private java.lang.Object onreturnInstance;

  private java.lang.reflect.Method onreturnMethod;

  private java.lang.Object onthrowInstance;

  private java.lang.reflect.Method onthrowMethod;

  public org.apache.dubbo.rpc.model.AsyncMethodInfo();
    Code:
       0: aload_0
       1: invokespecial #1                  // Method java/lang/Object."<init>":()V
       4: return

  public java.lang.Object getOninvokeInstance();
    Code:
       0: aload_0
       1: getfield      #2                  // Field oninvokeInstance:Ljava/lang/Object;
       4: areturn

  public void setOninvokeInstance(java.lang.Object);
    Code:
       0: aload_0
       1: aload_1
       2: putfield      #2                  // Field oninvokeInstance:Ljava/lang/Object;
       5: return

  public java.lang.reflect.Method getOninvokeMethod();
    Code:
       0: aload_0
       1: getfield      #3                  // Field oninvokeMethod:Ljava/lang/reflect/Method;
       4: areturn

  public void setOninvokeMethod(java.lang.reflect.Method);
    Code:
       0: aload_0
       1: aload_1
       2: putfield      #3                  // Field oninvokeMethod:Ljava/lang/reflect/Method;
       5: return

  public java.lang.Object getOnreturnInstance();
    Code:
       0: aload_0
       1: getfield      #4                  // Field onreturnInstance:Ljava/lang/Object;
       4: areturn

  public void setOnreturnInstance(java.lang.Object);
    Code:
       0: aload_0
       1: aload_1
       2: putfield      #4                  // Field onreturnInstance:Ljava/lang/Object;
       5: return

  public java.lang.reflect.Method getOnreturnMethod();
    Code:
       0: aload_0
       1: getfield      #5                  // Field onreturnMethod:Ljava/lang/reflect/Method;
       4: areturn

  public void setOnreturnMethod(java.lang.reflect.Method);
    Code:
       0: aload_0
       1: aload_1
       2: putfield      #5                  // Field onreturnMethod:Ljava/lang/reflect/Method;
       5: return

  public java.lang.Object getOnthrowInstance();
    Code:
       0: aload_0
       1: getfield      #6                  // Field onthrowInstance:Ljava/lang/Object;
       4: areturn

  public void setOnthrowInstance(java.lang.Object);
    Code:
       0: aload_0
       1: aload_1
       2: putfield      #6                  // Field onthrowInstance:Ljava/lang/Object;
       5: return

  public java.lang.reflect.Method getOnthrowMethod();
    Code:
       0: aload_0
       1: getfield      #7                  // Field onthrowMethod:Ljava/lang/reflect/Method;
       4: areturn

  public void setOnthrowMethod(java.lang.reflect.Method);
    Code:
       0: aload_0
       1: aload_1
       2: putfield      #7                  // Field onthrowMethod:Ljava/lang/reflect/Method;
       5: return
}
