Compiled from "ConsumerMethodModel.java"
public class org.apache.dubbo.rpc.model.ConsumerMethodModel {
  private final java.lang.reflect.Method method;

  private final java.lang.String[] parameterTypes;

  private final java.lang.Class<?>[] parameterClasses;

  private final java.lang.Class<?> returnClass;

  private final java.lang.String methodName;

  private final boolean generic;

  private final java.util.concurrent.ConcurrentMap<java.lang.String, java.lang.Object> attributeMap;

  public org.apache.dubbo.rpc.model.ConsumerMethodModel(java.lang.reflect.Method);
    Code:
       0: aload_0
       1: invokespecial #2                  // Method java/lang/Object."<init>":()V
       4: aload_0
       5: new           #3                  // class java/util/concurrent/ConcurrentHashMap
       8: dup
       9: invokespecial #4                  // Method java/util/concurrent/ConcurrentHashMap."<init>":()V
      12: putfield      #5                  // Field attributeMap:Ljava/util/concurrent/ConcurrentMap;
      15: aload_0
      16: aload_1
      17: putfield      #6                  // Field method:Ljava/lang/reflect/Method;
      20: aload_0
      21: aload_1
      22: invokevirtual #7                  // Method java/lang/reflect/Method.getParameterTypes:()[Ljava/lang/Class;
      25: putfield      #8                  // Field parameterClasses:[Ljava/lang/Class;
      28: aload_0
      29: aload_1
      30: invokevirtual #9                  // Method java/lang/reflect/Method.getReturnType:()Ljava/lang/Class;
      33: putfield      #10                 // Field returnClass:Ljava/lang/Class;
      36: aload_0
      37: aload_0
      38: aload_0
      39: getfield      #8                  // Field parameterClasses:[Ljava/lang/Class;
      42: invokespecial #11                 // Method createParamSignature:([Ljava/lang/Class;)[Ljava/lang/String;
      45: putfield      #12                 // Field parameterTypes:[Ljava/lang/String;
      48: aload_0
      49: aload_1
      50: invokevirtual #13                 // Method java/lang/reflect/Method.getName:()Ljava/lang/String;
      53: putfield      #14                 // Field methodName:Ljava/lang/String;
      56: aload_0
      57: aload_0
      58: getfield      #14                 // Field methodName:Ljava/lang/String;
      61: ldc           #15                 // String $invoke
      63: invokevirtual #16                 // Method java/lang/String.equals:(Ljava/lang/Object;)Z
      66: ifeq          89
      69: aload_0
      70: getfield      #12                 // Field parameterTypes:[Ljava/lang/String;
      73: ifnull        89
      76: aload_0
      77: getfield      #12                 // Field parameterTypes:[Ljava/lang/String;
      80: arraylength
      81: iconst_3
      82: if_icmpne     89
      85: iconst_1
      86: goto          90
      89: iconst_0
      90: putfield      #17                 // Field generic:Z
      93: return

  public java.lang.reflect.Method getMethod();
    Code:
       0: aload_0
       1: getfield      #6                  // Field method:Ljava/lang/reflect/Method;
       4: areturn

  public void addAttribute(java.lang.String, java.lang.Object);
    Code:
       0: aload_0
       1: getfield      #5                  // Field attributeMap:Ljava/util/concurrent/ConcurrentMap;
       4: aload_1
       5: aload_2
       6: invokeinterface #18,  3           // InterfaceMethod java/util/concurrent/ConcurrentMap.put:(Ljava/lang/Object;Ljava/lang/Object;)Ljava/lang/Object;
      11: pop
      12: return

  public java.lang.Object getAttribute(java.lang.String);
    Code:
       0: aload_0
       1: getfield      #5                  // Field attributeMap:Ljava/util/concurrent/ConcurrentMap;
       4: aload_1
       5: invokeinterface #19,  2           // InterfaceMethod java/util/concurrent/ConcurrentMap.get:(Ljava/lang/Object;)Ljava/lang/Object;
      10: areturn

  public java.lang.Class<?> getReturnClass();
    Code:
       0: aload_0
       1: getfield      #10                 // Field returnClass:Ljava/lang/Class;
       4: areturn

  public java.lang.String getMethodName();
    Code:
       0: aload_0
       1: getfield      #14                 // Field methodName:Ljava/lang/String;
       4: areturn

  public java.lang.String[] getParameterTypes();
    Code:
       0: aload_0
       1: getfield      #12                 // Field parameterTypes:[Ljava/lang/String;
       4: areturn

  private java.lang.String[] createParamSignature(java.lang.Class<?>[]);
    Code:
       0: aload_1
       1: ifnull        9
       4: aload_1
       5: arraylength
       6: ifne          14
       9: iconst_0
      10: anewarray     #20                 // class java/lang/String
      13: areturn
      14: aload_1
      15: arraylength
      16: anewarray     #20                 // class java/lang/String
      19: astore_2
      20: iconst_0
      21: istore_3
      22: iload_3
      23: aload_1
      24: arraylength
      25: if_icmpge     43
      28: aload_2
      29: iload_3
      30: aload_1
      31: iload_3
      32: aaload
      33: invokevirtual #21                 // Method java/lang/Class.getName:()Ljava/lang/String;
      36: aastore
      37: iinc          3, 1
      40: goto          22
      43: aload_2
      44: areturn

  public boolean isGeneric();
    Code:
       0: aload_0
       1: getfield      #17                 // Field generic:Z
       4: ireturn

  public java.lang.Class<?>[] getParameterClasses();
    Code:
       0: aload_0
       1: getfield      #8                  // Field parameterClasses:[Ljava/lang/Class;
       4: areturn
}
