Compiled from "ConsumerModel.java"
public class org.apache.dubbo.rpc.model.ConsumerModel extends org.apache.dubbo.rpc.model.ServiceModel {
  private final java.util.Set<java.lang.String> apps;

  private final java.util.Map<java.lang.String, org.apache.dubbo.rpc.model.AsyncMethodInfo> methodConfigs;

  private java.util.Map<java.lang.reflect.Method, org.apache.dubbo.rpc.model.ConsumerMethodModel> methodModels;

  public org.apache.dubbo.rpc.model.ConsumerModel(java.lang.String, java.lang.Object, org.apache.dubbo.rpc.model.ServiceDescriptor, java.util.Map<java.lang.String, org.apache.dubbo.rpc.model.AsyncMethodInfo>, java.lang.ClassLoader);
    Code:
       0: aload_0
       1: aload_2
       2: aload_1
       3: aload_3
       4: aconst_null
       5: aload         5
       7: invokespecial #1                  // Method org/apache/dubbo/rpc/model/ServiceModel."<init>":(Ljava/lang/Object;Ljava/lang/String;Lorg/apache/dubbo/rpc/model/ServiceDescriptor;Lorg/apache/dubbo/rpc/model/ModuleModel;Ljava/lang/ClassLoader;)V
      10: aload_0
      11: new           #2                  // class java/util/TreeSet
      14: dup
      15: invokespecial #3                  // Method java/util/TreeSet."<init>":()V
      18: putfield      #4                  // Field apps:Ljava/util/Set;
      21: aload_0
      22: new           #5                  // class java/util/HashMap
      25: dup
      26: invokespecial #6                  // Method java/util/HashMap."<init>":()V
      29: putfield      #7                  // Field methodModels:Ljava/util/Map;
      32: aload_1
      33: ldc           #8                  // String Service name can\'t be null or blank
      35: invokestatic  #9                  // Method org/apache/dubbo/common/utils/Assert.notEmptyString:(Ljava/lang/String;Ljava/lang/String;)V
      38: aload_0
      39: aload         4
      41: ifnonnull     54
      44: new           #5                  // class java/util/HashMap
      47: dup
      48: invokespecial #6                  // Method java/util/HashMap."<init>":()V
      51: goto          56
      54: aload         4
      56: putfield      #10                 // Field methodConfigs:Ljava/util/Map;
      59: return

  public org.apache.dubbo.rpc.model.ConsumerModel(java.lang.String, java.lang.Object, org.apache.dubbo.rpc.model.ServiceDescriptor, org.apache.dubbo.rpc.model.ServiceMetadata, java.util.Map<java.lang.String, org.apache.dubbo.rpc.model.AsyncMethodInfo>, java.lang.ClassLoader);
    Code:
       0: aload_0
       1: aload_2
       2: aload_1
       3: aload_3
       4: aconst_null
       5: aload         4
       7: aload         6
       9: invokespecial #11                 // Method org/apache/dubbo/rpc/model/ServiceModel."<init>":(Ljava/lang/Object;Ljava/lang/String;Lorg/apache/dubbo/rpc/model/ServiceDescriptor;Lorg/apache/dubbo/rpc/model/ModuleModel;Lorg/apache/dubbo/rpc/model/ServiceMetadata;Ljava/lang/ClassLoader;)V
      12: aload_0
      13: new           #2                  // class java/util/TreeSet
      16: dup
      17: invokespecial #3                  // Method java/util/TreeSet."<init>":()V
      20: putfield      #4                  // Field apps:Ljava/util/Set;
      23: aload_0
      24: new           #5                  // class java/util/HashMap
      27: dup
      28: invokespecial #6                  // Method java/util/HashMap."<init>":()V
      31: putfield      #7                  // Field methodModels:Ljava/util/Map;
      34: aload_1
      35: ldc           #8                  // String Service name can\'t be null or blank
      37: invokestatic  #9                  // Method org/apache/dubbo/common/utils/Assert.notEmptyString:(Ljava/lang/String;Ljava/lang/String;)V
      40: aload_0
      41: aload         5
      43: ifnonnull     56
      46: new           #5                  // class java/util/HashMap
      49: dup
      50: invokespecial #6                  // Method java/util/HashMap."<init>":()V
      53: goto          58
      56: aload         5
      58: putfield      #10                 // Field methodConfigs:Ljava/util/Map;
      61: return

  public org.apache.dubbo.rpc.model.ConsumerModel(java.lang.String, java.lang.Object, org.apache.dubbo.rpc.model.ServiceDescriptor, org.apache.dubbo.rpc.model.ModuleModel, org.apache.dubbo.rpc.model.ServiceMetadata, java.util.Map<java.lang.String, org.apache.dubbo.rpc.model.AsyncMethodInfo>, java.lang.ClassLoader);
    Code:
       0: aload_0
       1: aload_2
       2: aload_1
       3: aload_3
       4: aload         4
       6: aload         5
       8: aload         7
      10: invokespecial #11                 // Method org/apache/dubbo/rpc/model/ServiceModel."<init>":(Ljava/lang/Object;Ljava/lang/String;Lorg/apache/dubbo/rpc/model/ServiceDescriptor;Lorg/apache/dubbo/rpc/model/ModuleModel;Lorg/apache/dubbo/rpc/model/ServiceMetadata;Ljava/lang/ClassLoader;)V
      13: aload_0
      14: new           #2                  // class java/util/TreeSet
      17: dup
      18: invokespecial #3                  // Method java/util/TreeSet."<init>":()V
      21: putfield      #4                  // Field apps:Ljava/util/Set;
      24: aload_0
      25: new           #5                  // class java/util/HashMap
      28: dup
      29: invokespecial #6                  // Method java/util/HashMap."<init>":()V
      32: putfield      #7                  // Field methodModels:Ljava/util/Map;
      35: aload_1
      36: ldc           #8                  // String Service name can\'t be null or blank
      38: invokestatic  #9                  // Method org/apache/dubbo/common/utils/Assert.notEmptyString:(Ljava/lang/String;Ljava/lang/String;)V
      41: aload_0
      42: aload         6
      44: ifnonnull     57
      47: new           #5                  // class java/util/HashMap
      50: dup
      51: invokespecial #6                  // Method java/util/HashMap."<init>":()V
      54: goto          59
      57: aload         6
      59: putfield      #10                 // Field methodConfigs:Ljava/util/Map;
      62: return

  public org.apache.dubbo.rpc.model.AsyncMethodInfo getMethodConfig(java.lang.String);
    Code:
       0: aload_0
       1: getfield      #10                 // Field methodConfigs:Ljava/util/Map;
       4: aload_1
       5: invokeinterface #12,  2           // InterfaceMethod java/util/Map.get:(Ljava/lang/Object;)Ljava/lang/Object;
      10: checkcast     #13                 // class org/apache/dubbo/rpc/model/AsyncMethodInfo
      13: areturn

  public java.util.Set<java.lang.String> getApps();
    Code:
       0: aload_0
       1: getfield      #4                  // Field apps:Ljava/util/Set;
       4: areturn

  public org.apache.dubbo.rpc.model.AsyncMethodInfo getAsyncInfo(java.lang.String);
    Code:
       0: aload_0
       1: getfield      #10                 // Field methodConfigs:Ljava/util/Map;
       4: aload_1
       5: invokeinterface #12,  2           // InterfaceMethod java/util/Map.get:(Ljava/lang/Object;)Ljava/lang/Object;
      10: checkcast     #13                 // class org/apache/dubbo/rpc/model/AsyncMethodInfo
      13: areturn

  public void initMethodModels();
    Code:
       0: aload_0
       1: invokevirtual #14                 // Method getProxyObject:()Ljava/lang/Object;
       4: ifnonnull     36
       7: aload_0
       8: invokevirtual #15                 // Method getServiceInterfaceClass:()Ljava/lang/Class;
      11: astore_2
      12: aload_2
      13: ifnull        28
      16: iconst_1
      17: anewarray     #16                 // class java/lang/Class
      20: dup
      21: iconst_0
      22: aload_2
      23: aastore
      24: astore_1
      25: goto          33
      28: iconst_0
      29: anewarray     #16                 // class java/lang/Class
      32: astore_1
      33: goto          47
      36: aload_0
      37: invokevirtual #14                 // Method getProxyObject:()Ljava/lang/Object;
      40: invokevirtual #17                 // Method java/lang/Object.getClass:()Ljava/lang/Class;
      43: invokevirtual #18                 // Method java/lang/Class.getInterfaces:()[Ljava/lang/Class;
      46: astore_1
      47: aload_1
      48: astore_2
      49: aload_2
      50: arraylength
      51: istore_3
      52: iconst_0
      53: istore        4
      55: iload         4
      57: iload_3
      58: if_icmpge     129
      61: aload_2
      62: iload         4
      64: aaload
      65: astore        5
      67: aload         5
      69: invokevirtual #19                 // Method java/lang/Class.getMethods:()[Ljava/lang/reflect/Method;
      72: astore        6
      74: aload         6
      76: arraylength
      77: istore        7
      79: iconst_0
      80: istore        8
      82: iload         8
      84: iload         7
      86: if_icmpge     123
      89: aload         6
      91: iload         8
      93: aaload
      94: astore        9
      96: aload_0
      97: getfield      #7                  // Field methodModels:Ljava/util/Map;
     100: aload         9
     102: new           #20                 // class org/apache/dubbo/rpc/model/ConsumerMethodModel
     105: dup
     106: aload         9
     108: invokespecial #21                 // Method org/apache/dubbo/rpc/model/ConsumerMethodModel."<init>":(Ljava/lang/reflect/Method;)V
     111: invokeinterface #22,  3           // InterfaceMethod java/util/Map.put:(Ljava/lang/Object;Ljava/lang/Object;)Ljava/lang/Object;
     116: pop
     117: iinc          8, 1
     120: goto          82
     123: iinc          4, 1
     126: goto          55
     129: return

  public org.apache.dubbo.rpc.model.ConsumerMethodModel getMethodModel(java.lang.reflect.Method);
    Code:
       0: aload_0
       1: getfield      #7                  // Field methodModels:Ljava/util/Map;
       4: aload_1
       5: invokeinterface #12,  2           // InterfaceMethod java/util/Map.get:(Ljava/lang/Object;)Ljava/lang/Object;
      10: checkcast     #20                 // class org/apache/dubbo/rpc/model/ConsumerMethodModel
      13: areturn

  public org.apache.dubbo.rpc.model.ConsumerMethodModel getMethodModel(java.lang.String);
    Code:
       0: aload_0
       1: getfield      #7                  // Field methodModels:Ljava/util/Map;
       4: invokeinterface #23,  1           // InterfaceMethod java/util/Map.entrySet:()Ljava/util/Set;
       9: invokeinterface #24,  1           // InterfaceMethod java/util/Set.stream:()Ljava/util/stream/Stream;
      14: aload_1
      15: invokedynamic #25,  0             // InvokeDynamic #0:test:(Ljava/lang/String;)Ljava/util/function/Predicate;
      20: invokeinterface #26,  2           // InterfaceMethod java/util/stream/Stream.filter:(Ljava/util/function/Predicate;)Ljava/util/stream/Stream;
      25: invokeinterface #27,  1           // InterfaceMethod java/util/stream/Stream.findFirst:()Ljava/util/Optional;
      30: astore_2
      31: aload_2
      32: invokedynamic #28,  0             // InvokeDynamic #1:apply:()Ljava/util/function/Function;
      37: invokevirtual #29                 // Method java/util/Optional.map:(Ljava/util/function/Function;)Ljava/util/Optional;
      40: aconst_null
      41: invokevirtual #30                 // Method java/util/Optional.orElse:(Ljava/lang/Object;)Ljava/lang/Object;
      44: checkcast     #20                 // class org/apache/dubbo/rpc/model/ConsumerMethodModel
      47: areturn

  public org.apache.dubbo.rpc.model.ConsumerMethodModel getMethodModel(java.lang.String, java.lang.String[]);
    Code:
       0: aload_0
       1: getfield      #7                  // Field methodModels:Ljava/util/Map;
       4: invokeinterface #23,  1           // InterfaceMethod java/util/Map.entrySet:()Ljava/util/Set;
       9: invokeinterface #24,  1           // InterfaceMethod java/util/Set.stream:()Ljava/util/stream/Stream;
      14: aload_1
      15: invokedynamic #31,  0             // InvokeDynamic #2:test:(Ljava/lang/String;)Ljava/util/function/Predicate;
      20: invokeinterface #26,  2           // InterfaceMethod java/util/stream/Stream.filter:(Ljava/util/function/Predicate;)Ljava/util/stream/Stream;
      25: invokedynamic #28,  0             // InvokeDynamic #1:apply:()Ljava/util/function/Function;
      30: invokeinterface #32,  2           // InterfaceMethod java/util/stream/Stream.map:(Ljava/util/function/Function;)Ljava/util/stream/Stream;
      35: aload_2
      36: invokedynamic #33,  0             // InvokeDynamic #3:test:([Ljava/lang/String;)Ljava/util/function/Predicate;
      41: invokeinterface #26,  2           // InterfaceMethod java/util/stream/Stream.filter:(Ljava/util/function/Predicate;)Ljava/util/stream/Stream;
      46: invokeinterface #27,  1           // InterfaceMethod java/util/stream/Stream.findFirst:()Ljava/util/Optional;
      51: astore_3
      52: aload_3
      53: aconst_null
      54: invokevirtual #30                 // Method java/util/Optional.orElse:(Ljava/lang/Object;)Ljava/lang/Object;
      57: checkcast     #20                 // class org/apache/dubbo/rpc/model/ConsumerMethodModel
      60: areturn

  public java.util.List<org.apache.dubbo.rpc.model.ConsumerMethodModel> getAllMethodModels();
    Code:
       0: new           #34                 // class java/util/ArrayList
       3: dup
       4: aload_0
       5: getfield      #7                  // Field methodModels:Ljava/util/Map;
       8: invokeinterface #35,  1           // InterfaceMethod java/util/Map.values:()Ljava/util/Collection;
      13: invokespecial #36                 // Method java/util/ArrayList."<init>":(Ljava/util/Collection;)V
      16: areturn

  public boolean equals(java.lang.Object);
    Code:
       0: aload_0
       1: aload_1
       2: if_acmpne     7
       5: iconst_1
       6: ireturn
       7: aload_1
       8: ifnull        22
      11: aload_0
      12: invokevirtual #17                 // Method java/lang/Object.getClass:()Ljava/lang/Class;
      15: aload_1
      16: invokevirtual #17                 // Method java/lang/Object.getClass:()Ljava/lang/Class;
      19: if_acmpeq     24
      22: iconst_0
      23: ireturn
      24: aload_0
      25: aload_1
      26: invokespecial #37                 // Method org/apache/dubbo/rpc/model/ServiceModel.equals:(Ljava/lang/Object;)Z
      29: ifne          34
      32: iconst_0
      33: ireturn
      34: aload_1
      35: checkcast     #38                 // class org/apache/dubbo/rpc/model/ConsumerModel
      38: astore_2
      39: aload_0
      40: getfield      #4                  // Field apps:Ljava/util/Set;
      43: aload_2
      44: getfield      #4                  // Field apps:Ljava/util/Set;
      47: invokestatic  #39                 // Method java/util/Objects.equals:(Ljava/lang/Object;Ljava/lang/Object;)Z
      50: ifeq          85
      53: aload_0
      54: getfield      #10                 // Field methodConfigs:Ljava/util/Map;
      57: aload_2
      58: getfield      #10                 // Field methodConfigs:Ljava/util/Map;
      61: invokestatic  #39                 // Method java/util/Objects.equals:(Ljava/lang/Object;Ljava/lang/Object;)Z
      64: ifeq          85
      67: aload_0
      68: getfield      #7                  // Field methodModels:Ljava/util/Map;
      71: aload_2
      72: getfield      #7                  // Field methodModels:Ljava/util/Map;
      75: invokestatic  #39                 // Method java/util/Objects.equals:(Ljava/lang/Object;Ljava/lang/Object;)Z
      78: ifeq          85
      81: iconst_1
      82: goto          86
      85: iconst_0
      86: ireturn

  public int hashCode();
    Code:
       0: iconst_4
       1: anewarray     #40                 // class java/lang/Object
       4: dup
       5: iconst_0
       6: aload_0
       7: invokespecial #41                 // Method org/apache/dubbo/rpc/model/ServiceModel.hashCode:()I
      10: invokestatic  #42                 // Method java/lang/Integer.valueOf:(I)Ljava/lang/Integer;
      13: aastore
      14: dup
      15: iconst_1
      16: aload_0
      17: getfield      #4                  // Field apps:Ljava/util/Set;
      20: aastore
      21: dup
      22: iconst_2
      23: aload_0
      24: getfield      #10                 // Field methodConfigs:Ljava/util/Map;
      27: aastore
      28: dup
      29: iconst_3
      30: aload_0
      31: getfield      #7                  // Field methodModels:Ljava/util/Map;
      34: aastore
      35: invokestatic  #43                 // Method java/util/Objects.hash:([Ljava/lang/Object;)I
      38: ireturn

  private static boolean lambda$getMethodModel$2(java.lang.String[], org.apache.dubbo.rpc.model.ConsumerMethodModel);
    Code:
       0: aload_0
       1: aload_1
       2: invokevirtual #44                 // Method org/apache/dubbo/rpc/model/ConsumerMethodModel.getParameterTypes:()[Ljava/lang/String;
       5: invokestatic  #45                 // Method java/util/Arrays.equals:([Ljava/lang/Object;[Ljava/lang/Object;)Z
       8: ireturn

  private static boolean lambda$getMethodModel$1(java.lang.String, java.util.Map$Entry);
    Code:
       0: aload_1
       1: invokeinterface #46,  1           // InterfaceMethod java/util/Map$Entry.getKey:()Ljava/lang/Object;
       6: checkcast     #47                 // class java/lang/reflect/Method
       9: invokevirtual #48                 // Method java/lang/reflect/Method.getName:()Ljava/lang/String;
      12: aload_0
      13: invokevirtual #49                 // Method java/lang/String.equals:(Ljava/lang/Object;)Z
      16: ireturn

  private static boolean lambda$getMethodModel$0(java.lang.String, java.util.Map$Entry);
    Code:
       0: aload_1
       1: invokeinterface #46,  1           // InterfaceMethod java/util/Map$Entry.getKey:()Ljava/lang/Object;
       6: checkcast     #47                 // class java/lang/reflect/Method
       9: invokevirtual #48                 // Method java/lang/reflect/Method.getName:()Ljava/lang/String;
      12: aload_0
      13: invokevirtual #49                 // Method java/lang/String.equals:(Ljava/lang/Object;)Z
      16: ireturn
}
