Compiled from "FrameworkModel.java"
public class org.apache.dubbo.rpc.model.FrameworkModel extends org.apache.dubbo.rpc.model.ScopeModel {
  protected static final org.apache.dubbo.common.logger.Logger LOGGER;

  public static final java.lang.String NAME;

  private static final java.util.concurrent.atomic.AtomicLong index;

  private static final java.lang.Object globalLock;

  private static volatile org.apache.dubbo.rpc.model.FrameworkModel defaultInstance;

  private static final java.util.List<org.apache.dubbo.rpc.model.FrameworkModel> allInstances;

  private final java.util.concurrent.atomic.AtomicLong appIndex;

  private volatile org.apache.dubbo.rpc.model.ApplicationModel defaultAppModel;

  private final java.util.List<org.apache.dubbo.rpc.model.ApplicationModel> applicationModels;

  private final java.util.List<org.apache.dubbo.rpc.model.ApplicationModel> pubApplicationModels;

  private final org.apache.dubbo.rpc.model.FrameworkServiceRepository serviceRepository;

  private final org.apache.dubbo.rpc.model.ApplicationModel internalApplicationModel;

  private final java.util.concurrent.locks.ReentrantLock destroyLock;

  public org.apache.dubbo.rpc.model.FrameworkModel();
    Code:
       0: aload_0
       1: aconst_null
       2: getstatic     #1                  // Field org/apache/dubbo/common/extension/ExtensionScope.FRAMEWORK:Lorg/apache/dubbo/common/extension/ExtensionScope;
       5: iconst_0
       6: invokespecial #2                  // Method org/apache/dubbo/rpc/model/ScopeModel."<init>":(Lorg/apache/dubbo/rpc/model/ScopeModel;Lorg/apache/dubbo/common/extension/ExtensionScope;Z)V
       9: aload_0
      10: new           #3                  // class java/util/concurrent/atomic/AtomicLong
      13: dup
      14: lconst_0
      15: invokespecial #4                  // Method java/util/concurrent/atomic/AtomicLong."<init>":(J)V
      18: putfield      #5                  // Field appIndex:Ljava/util/concurrent/atomic/AtomicLong;
      21: aload_0
      22: new           #6                  // class java/util/concurrent/CopyOnWriteArrayList
      25: dup
      26: invokespecial #7                  // Method java/util/concurrent/CopyOnWriteArrayList."<init>":()V
      29: putfield      #8                  // Field applicationModels:Ljava/util/List;
      32: aload_0
      33: new           #6                  // class java/util/concurrent/CopyOnWriteArrayList
      36: dup
      37: invokespecial #7                  // Method java/util/concurrent/CopyOnWriteArrayList."<init>":()V
      40: putfield      #9                  // Field pubApplicationModels:Ljava/util/List;
      43: aload_0
      44: new           #10                 // class java/util/concurrent/locks/ReentrantLock
      47: dup
      48: invokespecial #11                 // Method java/util/concurrent/locks/ReentrantLock."<init>":()V
      51: putfield      #12                 // Field destroyLock:Ljava/util/concurrent/locks/ReentrantLock;
      54: getstatic     #13                 // Field globalLock:Ljava/lang/Object;
      57: dup
      58: astore_1
      59: monitorenter
      60: aload_0
      61: getfield      #14                 // Field instLock:Ljava/lang/Object;
      64: dup
      65: astore_2
      66: monitorenter
      67: aload_0
      68: getstatic     #15                 // Field index:Ljava/util/concurrent/atomic/AtomicLong;
      71: invokevirtual #16                 // Method java/util/concurrent/atomic/AtomicLong.getAndIncrement:()J
      74: invokestatic  #17                 // Method java/lang/String.valueOf:(J)Ljava/lang/String;
      77: invokevirtual #18                 // Method setInternalId:(Ljava/lang/String;)V
      80: getstatic     #19                 // Field allInstances:Ljava/util/List;
      83: aload_0
      84: invokeinterface #20,  2           // InterfaceMethod java/util/List.add:(Ljava/lang/Object;)Z
      89: pop
      90: getstatic     #21                 // Field LOGGER:Lorg/apache/dubbo/common/logger/Logger;
      93: invokeinterface #22,  1           // InterfaceMethod org/apache/dubbo/common/logger/Logger.isInfoEnabled:()Z
      98: ifeq          131
     101: getstatic     #21                 // Field LOGGER:Lorg/apache/dubbo/common/logger/Logger;
     104: new           #23                 // class java/lang/StringBuilder
     107: dup
     108: invokespecial #24                 // Method java/lang/StringBuilder."<init>":()V
     111: aload_0
     112: invokevirtual #25                 // Method getDesc:()Ljava/lang/String;
     115: invokevirtual #26                 // Method java/lang/StringBuilder.append:(Ljava/lang/String;)Ljava/lang/StringBuilder;
     118: ldc           #27                 // String  is created
     120: invokevirtual #26                 // Method java/lang/StringBuilder.append:(Ljava/lang/String;)Ljava/lang/StringBuilder;
     123: invokevirtual #28                 // Method java/lang/StringBuilder.toString:()Ljava/lang/String;
     126: invokeinterface #29,  2           // InterfaceMethod org/apache/dubbo/common/logger/Logger.info:(Ljava/lang/String;)V
     131: aload_0
     132: invokevirtual #30                 // Method initialize:()V
     135: aload_0
     136: invokestatic  #31                 // Method org/apache/dubbo/metadata/definition/TypeDefinitionBuilder.initBuilders:(Lorg/apache/dubbo/rpc/model/FrameworkModel;)V
     139: aload_0
     140: new           #32                 // class org/apache/dubbo/rpc/model/FrameworkServiceRepository
     143: dup
     144: aload_0
     145: invokespecial #33                 // Method org/apache/dubbo/rpc/model/FrameworkServiceRepository."<init>":(Lorg/apache/dubbo/rpc/model/FrameworkModel;)V
     148: putfield      #34                 // Field serviceRepository:Lorg/apache/dubbo/rpc/model/FrameworkServiceRepository;
     151: aload_0
     152: ldc           #35                 // class org/apache/dubbo/rpc/model/ScopeModelInitializer
     154: invokevirtual #36                 // Method getExtensionLoader:(Ljava/lang/Class;)Lorg/apache/dubbo/common/extension/ExtensionLoader;
     157: astore_3
     158: aload_3
     159: invokevirtual #37                 // Method org/apache/dubbo/common/extension/ExtensionLoader.getSupportedExtensionInstances:()Ljava/util/Set;
     162: astore        4
     164: aload         4
     166: invokeinterface #38,  1           // InterfaceMethod java/util/Set.iterator:()Ljava/util/Iterator;
     171: astore        5
     173: aload         5
     175: invokeinterface #39,  1           // InterfaceMethod java/util/Iterator.hasNext:()Z
     180: ifeq          206
     183: aload         5
     185: invokeinterface #40,  1           // InterfaceMethod java/util/Iterator.next:()Ljava/lang/Object;
     190: checkcast     #35                 // class org/apache/dubbo/rpc/model/ScopeModelInitializer
     193: astore        6
     195: aload         6
     197: aload_0
     198: invokeinterface #41,  2           // InterfaceMethod org/apache/dubbo/rpc/model/ScopeModelInitializer.initializeFrameworkModel:(Lorg/apache/dubbo/rpc/model/FrameworkModel;)V
     203: goto          173
     206: aload_0
     207: new           #42                 // class org/apache/dubbo/rpc/model/ApplicationModel
     210: dup
     211: aload_0
     212: iconst_1
     213: invokespecial #43                 // Method org/apache/dubbo/rpc/model/ApplicationModel."<init>":(Lorg/apache/dubbo/rpc/model/FrameworkModel;Z)V
     216: putfield      #44                 // Field internalApplicationModel:Lorg/apache/dubbo/rpc/model/ApplicationModel;
     219: aload_0
     220: getfield      #44                 // Field internalApplicationModel:Lorg/apache/dubbo/rpc/model/ApplicationModel;
     223: invokevirtual #45                 // Method org/apache/dubbo/rpc/model/ApplicationModel.getApplicationConfigManager:()Lorg/apache/dubbo/config/context/ConfigManager;
     226: new           #46                 // class org/apache/dubbo/config/ApplicationConfig
     229: dup
     230: aload_0
     231: getfield      #44                 // Field internalApplicationModel:Lorg/apache/dubbo/rpc/model/ApplicationModel;
     234: ldc           #48                 // String DUBBO_INTERNAL_APPLICATION
     236: invokespecial #49                 // Method org/apache/dubbo/config/ApplicationConfig."<init>":(Lorg/apache/dubbo/rpc/model/ApplicationModel;Ljava/lang/String;)V
     239: invokevirtual #50                 // Method org/apache/dubbo/config/context/ConfigManager.setApplication:(Lorg/apache/dubbo/config/ApplicationConfig;)V
     242: aload_0
     243: getfield      #44                 // Field internalApplicationModel:Lorg/apache/dubbo/rpc/model/ApplicationModel;
     246: ldc           #48                 // String DUBBO_INTERNAL_APPLICATION
     248: invokevirtual #51                 // Method org/apache/dubbo/rpc/model/ApplicationModel.setModelName:(Ljava/lang/String;)V
     251: aload_2
     252: monitorexit
     253: goto          263
     256: astore        7
     258: aload_2
     259: monitorexit
     260: aload         7
     262: athrow
     263: aload_1
     264: monitorexit
     265: goto          275
     268: astore        8
     270: aload_1
     271: monitorexit
     272: aload         8
     274: athrow
     275: return
    Exception table:
       from    to  target type
          67   253   256   any
         256   260   256   any
          60   265   268   any
         268   272   268   any

  protected void onDestroy();
    Code:
       0: aload_0
       1: getfield      #14                 // Field instLock:Ljava/lang/Object;
       4: dup
       5: astore_1
       6: monitorenter
       7: getstatic     #52                 // Field defaultInstance:Lorg/apache/dubbo/rpc/model/FrameworkModel;
      10: aload_0
      11: if_acmpne     55
      14: getstatic     #21                 // Field LOGGER:Lorg/apache/dubbo/common/logger/Logger;
      17: invokeinterface #22,  1           // InterfaceMethod org/apache/dubbo/common/logger/Logger.isInfoEnabled:()Z
      22: ifeq          55
      25: getstatic     #21                 // Field LOGGER:Lorg/apache/dubbo/common/logger/Logger;
      28: new           #23                 // class java/lang/StringBuilder
      31: dup
      32: invokespecial #24                 // Method java/lang/StringBuilder."<init>":()V
      35: ldc           #53                 // String Destroying default framework model:
      37: invokevirtual #26                 // Method java/lang/StringBuilder.append:(Ljava/lang/String;)Ljava/lang/StringBuilder;
      40: aload_0
      41: invokevirtual #25                 // Method getDesc:()Ljava/lang/String;
      44: invokevirtual #26                 // Method java/lang/StringBuilder.append:(Ljava/lang/String;)Ljava/lang/StringBuilder;
      47: invokevirtual #28                 // Method java/lang/StringBuilder.toString:()Ljava/lang/String;
      50: invokeinterface #29,  2           // InterfaceMethod org/apache/dubbo/common/logger/Logger.info:(Ljava/lang/String;)V
      55: getstatic     #21                 // Field LOGGER:Lorg/apache/dubbo/common/logger/Logger;
      58: invokeinterface #22,  1           // InterfaceMethod org/apache/dubbo/common/logger/Logger.isInfoEnabled:()Z
      63: ifeq          96
      66: getstatic     #21                 // Field LOGGER:Lorg/apache/dubbo/common/logger/Logger;
      69: new           #23                 // class java/lang/StringBuilder
      72: dup
      73: invokespecial #24                 // Method java/lang/StringBuilder."<init>":()V
      76: aload_0
      77: invokevirtual #25                 // Method getDesc:()Ljava/lang/String;
      80: invokevirtual #26                 // Method java/lang/StringBuilder.append:(Ljava/lang/String;)Ljava/lang/StringBuilder;
      83: ldc           #54                 // String  is destroying ...
      85: invokevirtual #26                 // Method java/lang/StringBuilder.append:(Ljava/lang/String;)Ljava/lang/StringBuilder;
      88: invokevirtual #28                 // Method java/lang/StringBuilder.toString:()Ljava/lang/String;
      91: invokeinterface #29,  2           // InterfaceMethod org/apache/dubbo/common/logger/Logger.info:(Ljava/lang/String;)V
      96: new           #55                 // class java/util/ArrayList
      99: dup
     100: aload_0
     101: getfield      #8                  // Field applicationModels:Ljava/util/List;
     104: invokespecial #56                 // Method java/util/ArrayList."<init>":(Ljava/util/Collection;)V
     107: invokevirtual #57                 // Method java/util/ArrayList.iterator:()Ljava/util/Iterator;
     110: astore_2
     111: aload_2
     112: invokeinterface #39,  1           // InterfaceMethod java/util/Iterator.hasNext:()Z
     117: ifeq          137
     120: aload_2
     121: invokeinterface #40,  1           // InterfaceMethod java/util/Iterator.next:()Ljava/lang/Object;
     126: checkcast     #42                 // class org/apache/dubbo/rpc/model/ApplicationModel
     129: astore_3
     130: aload_3
     131: invokevirtual #58                 // Method org/apache/dubbo/rpc/model/ApplicationModel.destroy:()V
     134: goto          111
     137: aload_0
     138: invokespecial #59                 // Method checkApplicationDestroy:()V
     141: aload_0
     142: invokevirtual #60                 // Method notifyDestroy:()V
     145: getstatic     #21                 // Field LOGGER:Lorg/apache/dubbo/common/logger/Logger;
     148: invokeinterface #22,  1           // InterfaceMethod org/apache/dubbo/common/logger/Logger.isInfoEnabled:()Z
     153: ifeq          186
     156: getstatic     #21                 // Field LOGGER:Lorg/apache/dubbo/common/logger/Logger;
     159: new           #23                 // class java/lang/StringBuilder
     162: dup
     163: invokespecial #24                 // Method java/lang/StringBuilder."<init>":()V
     166: aload_0
     167: invokevirtual #25                 // Method getDesc:()Ljava/lang/String;
     170: invokevirtual #26                 // Method java/lang/StringBuilder.append:(Ljava/lang/String;)Ljava/lang/StringBuilder;
     173: ldc           #61                 // String  is destroyed
     175: invokevirtual #26                 // Method java/lang/StringBuilder.append:(Ljava/lang/String;)Ljava/lang/StringBuilder;
     178: invokevirtual #28                 // Method java/lang/StringBuilder.toString:()Ljava/lang/String;
     181: invokeinterface #29,  2           // InterfaceMethod org/apache/dubbo/common/logger/Logger.info:(Ljava/lang/String;)V
     186: getstatic     #13                 // Field globalLock:Ljava/lang/Object;
     189: dup
     190: astore_2
     191: monitorenter
     192: getstatic     #19                 // Field allInstances:Ljava/util/List;
     195: aload_0
     196: invokeinterface #62,  2           // InterfaceMethod java/util/List.remove:(Ljava/lang/Object;)Z
     201: pop
     202: invokestatic  #63                 // Method resetDefaultFrameworkModel:()V
     205: aload_2
     206: monitorexit
     207: goto          217
     210: astore        4
     212: aload_2
     213: monitorexit
     214: aload         4
     216: athrow
     217: aload_0
     218: invokespecial #64                 // Method destroyGlobalResources:()V
     221: aload_1
     222: monitorexit
     223: goto          233
     226: astore        5
     228: aload_1
     229: monitorexit
     230: aload         5
     232: athrow
     233: return
    Exception table:
       from    to  target type
         192   207   210   any
         210   214   210   any
           7   223   226   any
         226   230   226   any

  private void checkApplicationDestroy();
    Code:
       0: aload_0
       1: getfield      #14                 // Field instLock:Ljava/lang/Object;
       4: dup
       5: astore_1
       6: monitorenter
       7: aload_0
       8: getfield      #8                  // Field applicationModels:Ljava/util/List;
      11: invokeinterface #65,  1           // InterfaceMethod java/util/List.size:()I
      16: ifle          91
      19: aload_0
      20: getfield      #8                  // Field applicationModels:Ljava/util/List;
      23: invokeinterface #66,  1           // InterfaceMethod java/util/List.stream:()Ljava/util/stream/Stream;
      28: invokedynamic #67,  0             // InvokeDynamic #0:apply:()Ljava/util/function/Function;
      33: invokeinterface #68,  2           // InterfaceMethod java/util/stream/Stream.map:(Ljava/util/function/Function;)Ljava/util/stream/Stream;
      38: invokestatic  #69                 // Method java/util/stream/Collectors.toList:()Ljava/util/stream/Collector;
      41: invokeinterface #70,  2           // InterfaceMethod java/util/stream/Stream.collect:(Ljava/util/stream/Collector;)Ljava/lang/Object;
      46: checkcast     #71                 // class java/util/List
      49: astore_2
      50: new           #72                 // class java/lang/IllegalStateException
      53: dup
      54: new           #23                 // class java/lang/StringBuilder
      57: dup
      58: invokespecial #24                 // Method java/lang/StringBuilder."<init>":()V
      61: ldc           #73                 // String Not all application models are completely destroyed, remaining
      63: invokevirtual #26                 // Method java/lang/StringBuilder.append:(Ljava/lang/String;)Ljava/lang/StringBuilder;
      66: aload_2
      67: invokeinterface #65,  1           // InterfaceMethod java/util/List.size:()I
      72: invokevirtual #74                 // Method java/lang/StringBuilder.append:(I)Ljava/lang/StringBuilder;
      75: ldc           #75                 // String  application models may be created during destruction:
      77: invokevirtual #26                 // Method java/lang/StringBuilder.append:(Ljava/lang/String;)Ljava/lang/StringBuilder;
      80: aload_2
      81: invokevirtual #76                 // Method java/lang/StringBuilder.append:(Ljava/lang/Object;)Ljava/lang/StringBuilder;
      84: invokevirtual #28                 // Method java/lang/StringBuilder.toString:()Ljava/lang/String;
      87: invokespecial #77                 // Method java/lang/IllegalStateException."<init>":(Ljava/lang/String;)V
      90: athrow
      91: aload_1
      92: monitorexit
      93: goto          101
      96: astore_3
      97: aload_1
      98: monitorexit
      99: aload_3
     100: athrow
     101: return
    Exception table:
       from    to  target type
           7    93    96   any
          96    99    96   any

  private void destroyGlobalResources();
    Code:
       0: getstatic     #13                 // Field globalLock:Ljava/lang/Object;
       3: dup
       4: astore_1
       5: monitorenter
       6: getstatic     #19                 // Field allInstances:Ljava/util/List;
       9: invokeinterface #78,  1           // InterfaceMethod java/util/List.isEmpty:()Z
      14: ifeq          23
      17: invokestatic  #79                 // Method org/apache/dubbo/common/resource/GlobalResourcesRepository.getInstance:()Lorg/apache/dubbo/common/resource/GlobalResourcesRepository;
      20: invokevirtual #80                 // Method org/apache/dubbo/common/resource/GlobalResourcesRepository.destroy:()V
      23: aload_1
      24: monitorexit
      25: goto          33
      28: astore_2
      29: aload_1
      30: monitorexit
      31: aload_2
      32: athrow
      33: return
    Exception table:
       from    to  target type
           6    25    28   any
          28    31    28   any

  public static org.apache.dubbo.rpc.model.FrameworkModel defaultModel();
    Code:
       0: getstatic     #52                 // Field defaultInstance:Lorg/apache/dubbo/rpc/model/FrameworkModel;
       3: astore_0
       4: aload_0
       5: ifnonnull     47
       8: getstatic     #13                 // Field globalLock:Ljava/lang/Object;
      11: dup
      12: astore_1
      13: monitorenter
      14: invokestatic  #63                 // Method resetDefaultFrameworkModel:()V
      17: getstatic     #52                 // Field defaultInstance:Lorg/apache/dubbo/rpc/model/FrameworkModel;
      20: ifnonnull     33
      23: new           #81                 // class org/apache/dubbo/rpc/model/FrameworkModel
      26: dup
      27: invokespecial #82                 // Method "<init>":()V
      30: putstatic     #52                 // Field defaultInstance:Lorg/apache/dubbo/rpc/model/FrameworkModel;
      33: getstatic     #52                 // Field defaultInstance:Lorg/apache/dubbo/rpc/model/FrameworkModel;
      36: astore_0
      37: aload_1
      38: monitorexit
      39: goto          47
      42: astore_2
      43: aload_1
      44: monitorexit
      45: aload_2
      46: athrow
      47: aload_0
      48: ldc           #83                 // String Default FrameworkModel is null
      50: invokestatic  #84                 // Method org/apache/dubbo/common/utils/Assert.notNull:(Ljava/lang/Object;Ljava/lang/String;)V
      53: aload_0
      54: areturn
    Exception table:
       from    to  target type
          14    39    42   any
          42    45    42   any

  public static java.util.List<org.apache.dubbo.rpc.model.FrameworkModel> getAllInstances();
    Code:
       0: getstatic     #13                 // Field globalLock:Ljava/lang/Object;
       3: dup
       4: astore_0
       5: monitorenter
       6: new           #55                 // class java/util/ArrayList
       9: dup
      10: getstatic     #19                 // Field allInstances:Ljava/util/List;
      13: invokespecial #56                 // Method java/util/ArrayList."<init>":(Ljava/util/Collection;)V
      16: invokestatic  #85                 // Method java/util/Collections.unmodifiableList:(Ljava/util/List;)Ljava/util/List;
      19: aload_0
      20: monitorexit
      21: areturn
      22: astore_1
      23: aload_0
      24: monitorexit
      25: aload_1
      26: athrow
    Exception table:
       from    to  target type
           6    21    22   any
          22    25    22   any

  public static void destroyAll();
    Code:
       0: getstatic     #13                 // Field globalLock:Ljava/lang/Object;
       3: dup
       4: astore_0
       5: monitorenter
       6: new           #55                 // class java/util/ArrayList
       9: dup
      10: getstatic     #19                 // Field allInstances:Ljava/util/List;
      13: invokespecial #56                 // Method java/util/ArrayList."<init>":(Ljava/util/Collection;)V
      16: invokevirtual #57                 // Method java/util/ArrayList.iterator:()Ljava/util/Iterator;
      19: astore_1
      20: aload_1
      21: invokeinterface #39,  1           // InterfaceMethod java/util/Iterator.hasNext:()Z
      26: ifeq          46
      29: aload_1
      30: invokeinterface #40,  1           // InterfaceMethod java/util/Iterator.next:()Ljava/lang/Object;
      35: checkcast     #81                 // class org/apache/dubbo/rpc/model/FrameworkModel
      38: astore_2
      39: aload_2
      40: invokevirtual #86                 // Method destroy:()V
      43: goto          20
      46: aload_0
      47: monitorexit
      48: goto          56
      51: astore_3
      52: aload_0
      53: monitorexit
      54: aload_3
      55: athrow
      56: return
    Exception table:
       from    to  target type
           6    48    51   any
          51    54    51   any

  public org.apache.dubbo.rpc.model.ApplicationModel newApplication();
    Code:
       0: aload_0
       1: getfield      #14                 // Field instLock:Ljava/lang/Object;
       4: dup
       5: astore_1
       6: monitorenter
       7: new           #42                 // class org/apache/dubbo/rpc/model/ApplicationModel
      10: dup
      11: aload_0
      12: invokespecial #87                 // Method org/apache/dubbo/rpc/model/ApplicationModel."<init>":(Lorg/apache/dubbo/rpc/model/FrameworkModel;)V
      15: aload_1
      16: monitorexit
      17: areturn
      18: astore_2
      19: aload_1
      20: monitorexit
      21: aload_2
      22: athrow
    Exception table:
       from    to  target type
           7    17    18   any
          18    21    18   any

  public org.apache.dubbo.rpc.model.ApplicationModel defaultApplication();
    Code:
       0: aload_0
       1: getfield      #88                 // Field defaultAppModel:Lorg/apache/dubbo/rpc/model/ApplicationModel;
       4: astore_1
       5: aload_1
       6: ifnonnull     63
       9: aload_0
      10: invokespecial #89                 // Method checkDestroyed:()V
      13: aload_0
      14: invokespecial #90                 // Method resetDefaultAppModel:()V
      17: aload_0
      18: getfield      #88                 // Field defaultAppModel:Lorg/apache/dubbo/rpc/model/ApplicationModel;
      21: dup
      22: astore_1
      23: ifnonnull     63
      26: aload_0
      27: getfield      #14                 // Field instLock:Ljava/lang/Object;
      30: dup
      31: astore_2
      32: monitorenter
      33: aload_0
      34: getfield      #88                 // Field defaultAppModel:Lorg/apache/dubbo/rpc/model/ApplicationModel;
      37: ifnonnull     48
      40: aload_0
      41: aload_0
      42: invokevirtual #91                 // Method newApplication:()Lorg/apache/dubbo/rpc/model/ApplicationModel;
      45: putfield      #88                 // Field defaultAppModel:Lorg/apache/dubbo/rpc/model/ApplicationModel;
      48: aload_0
      49: getfield      #88                 // Field defaultAppModel:Lorg/apache/dubbo/rpc/model/ApplicationModel;
      52: astore_1
      53: aload_2
      54: monitorexit
      55: goto          63
      58: astore_3
      59: aload_2
      60: monitorexit
      61: aload_3
      62: athrow
      63: aload_1
      64: ldc           #92                 // String Default ApplicationModel is null
      66: invokestatic  #84                 // Method org/apache/dubbo/common/utils/Assert.notNull:(Ljava/lang/Object;Ljava/lang/String;)V
      69: aload_1
      70: areturn
    Exception table:
       from    to  target type
          33    55    58   any
          58    61    58   any

  org.apache.dubbo.rpc.model.ApplicationModel getDefaultAppModel();
    Code:
       0: aload_0
       1: getfield      #88                 // Field defaultAppModel:Lorg/apache/dubbo/rpc/model/ApplicationModel;
       4: areturn

  void addApplication(org.apache.dubbo.rpc.model.ApplicationModel);
    Code:
       0: aload_0
       1: invokespecial #89                 // Method checkDestroyed:()V
       4: aload_0
       5: getfield      #14                 // Field instLock:Ljava/lang/Object;
       8: dup
       9: astore_2
      10: monitorenter
      11: aload_0
      12: getfield      #8                  // Field applicationModels:Ljava/util/List;
      15: aload_1
      16: invokeinterface #93,  2           // InterfaceMethod java/util/List.contains:(Ljava/lang/Object;)Z
      21: ifne          72
      24: aload_1
      25: aload_0
      26: aload_0
      27: invokevirtual #94                 // Method getInternalId:()Ljava/lang/String;
      30: aload_0
      31: getfield      #5                  // Field appIndex:Ljava/util/concurrent/atomic/AtomicLong;
      34: invokevirtual #16                 // Method java/util/concurrent/atomic/AtomicLong.getAndIncrement:()J
      37: invokevirtual #95                 // Method buildInternalId:(Ljava/lang/String;J)Ljava/lang/String;
      40: invokevirtual #96                 // Method org/apache/dubbo/rpc/model/ApplicationModel.setInternalId:(Ljava/lang/String;)V
      43: aload_0
      44: getfield      #8                  // Field applicationModels:Ljava/util/List;
      47: aload_1
      48: invokeinterface #20,  2           // InterfaceMethod java/util/List.add:(Ljava/lang/Object;)Z
      53: pop
      54: aload_1
      55: invokevirtual #97                 // Method org/apache/dubbo/rpc/model/ApplicationModel.isInternal:()Z
      58: ifne          72
      61: aload_0
      62: getfield      #9                  // Field pubApplicationModels:Ljava/util/List;
      65: aload_1
      66: invokeinterface #20,  2           // InterfaceMethod java/util/List.add:(Ljava/lang/Object;)Z
      71: pop
      72: aload_2
      73: monitorexit
      74: goto          82
      77: astore_3
      78: aload_2
      79: monitorexit
      80: aload_3
      81: athrow
      82: return
    Exception table:
       from    to  target type
          11    74    77   any
          77    80    77   any

  void removeApplication(org.apache.dubbo.rpc.model.ApplicationModel);
    Code:
       0: aload_0
       1: getfield      #14                 // Field instLock:Ljava/lang/Object;
       4: dup
       5: astore_2
       6: monitorenter
       7: aload_0
       8: getfield      #8                  // Field applicationModels:Ljava/util/List;
      11: aload_1
      12: invokeinterface #62,  2           // InterfaceMethod java/util/List.remove:(Ljava/lang/Object;)Z
      17: pop
      18: aload_1
      19: invokevirtual #97                 // Method org/apache/dubbo/rpc/model/ApplicationModel.isInternal:()Z
      22: ifne          36
      25: aload_0
      26: getfield      #9                  // Field pubApplicationModels:Ljava/util/List;
      29: aload_1
      30: invokeinterface #62,  2           // InterfaceMethod java/util/List.remove:(Ljava/lang/Object;)Z
      35: pop
      36: aload_0
      37: invokespecial #90                 // Method resetDefaultAppModel:()V
      40: aload_2
      41: monitorexit
      42: goto          50
      45: astore_3
      46: aload_2
      47: monitorexit
      48: aload_3
      49: athrow
      50: return
    Exception table:
       from    to  target type
           7    42    45   any
          45    48    45   any

  void tryDestroyProtocols();
    Code:
       0: aload_0
       1: getfield      #14                 // Field instLock:Ljava/lang/Object;
       4: dup
       5: astore_1
       6: monitorenter
       7: aload_0
       8: getfield      #9                  // Field pubApplicationModels:Ljava/util/List;
      11: invokeinterface #65,  1           // InterfaceMethod java/util/List.size:()I
      16: ifne          23
      19: aload_0
      20: invokevirtual #98                 // Method notifyProtocolDestroy:()V
      23: aload_1
      24: monitorexit
      25: goto          33
      28: astore_2
      29: aload_1
      30: monitorexit
      31: aload_2
      32: athrow
      33: return
    Exception table:
       from    to  target type
           7    25    28   any
          28    31    28   any

  void tryDestroy();
    Code:
       0: aload_0
       1: getfield      #14                 // Field instLock:Ljava/lang/Object;
       4: dup
       5: astore_1
       6: monitorenter
       7: aload_0
       8: getfield      #9                  // Field pubApplicationModels:Ljava/util/List;
      11: invokeinterface #65,  1           // InterfaceMethod java/util/List.size:()I
      16: ifne          23
      19: aload_0
      20: invokevirtual #86                 // Method destroy:()V
      23: aload_1
      24: monitorexit
      25: goto          33
      28: astore_2
      29: aload_1
      30: monitorexit
      31: aload_2
      32: athrow
      33: return
    Exception table:
       from    to  target type
           7    25    28   any
          28    31    28   any

  private void checkDestroyed();
    Code:
       0: aload_0
       1: invokevirtual #99                 // Method isDestroyed:()Z
       4: ifeq          17
       7: new           #72                 // class java/lang/IllegalStateException
      10: dup
      11: ldc           #100                // String FrameworkModel is destroyed
      13: invokespecial #77                 // Method java/lang/IllegalStateException."<init>":(Ljava/lang/String;)V
      16: athrow
      17: return

  private void resetDefaultAppModel();
    Code:
       0: aload_0
       1: getfield      #14                 // Field instLock:Ljava/lang/Object;
       4: dup
       5: astore_1
       6: monitorenter
       7: aload_0
       8: getfield      #88                 // Field defaultAppModel:Lorg/apache/dubbo/rpc/model/ApplicationModel;
      11: ifnull        27
      14: aload_0
      15: getfield      #88                 // Field defaultAppModel:Lorg/apache/dubbo/rpc/model/ApplicationModel;
      18: invokevirtual #101                // Method org/apache/dubbo/rpc/model/ApplicationModel.isDestroyed:()Z
      21: ifne          27
      24: aload_1
      25: monitorexit
      26: return
      27: aload_0
      28: getfield      #88                 // Field defaultAppModel:Lorg/apache/dubbo/rpc/model/ApplicationModel;
      31: astore_2
      32: aload_0
      33: getfield      #9                  // Field pubApplicationModels:Ljava/util/List;
      36: invokeinterface #65,  1           // InterfaceMethod java/util/List.size:()I
      41: ifle          64
      44: aload_0
      45: aload_0
      46: getfield      #9                  // Field pubApplicationModels:Ljava/util/List;
      49: iconst_0
      50: invokeinterface #102,  2          // InterfaceMethod java/util/List.get:(I)Ljava/lang/Object;
      55: checkcast     #42                 // class org/apache/dubbo/rpc/model/ApplicationModel
      58: putfield      #88                 // Field defaultAppModel:Lorg/apache/dubbo/rpc/model/ApplicationModel;
      61: goto          69
      64: aload_0
      65: aconst_null
      66: putfield      #88                 // Field defaultAppModel:Lorg/apache/dubbo/rpc/model/ApplicationModel;
      69: getstatic     #52                 // Field defaultInstance:Lorg/apache/dubbo/rpc/model/FrameworkModel;
      72: aload_0
      73: if_acmpne     140
      76: aload_2
      77: aload_0
      78: getfield      #88                 // Field defaultAppModel:Lorg/apache/dubbo/rpc/model/ApplicationModel;
      81: if_acmpeq     140
      84: getstatic     #21                 // Field LOGGER:Lorg/apache/dubbo/common/logger/Logger;
      87: invokeinterface #22,  1           // InterfaceMethod org/apache/dubbo/common/logger/Logger.isInfoEnabled:()Z
      92: ifeq          140
      95: getstatic     #21                 // Field LOGGER:Lorg/apache/dubbo/common/logger/Logger;
      98: new           #23                 // class java/lang/StringBuilder
     101: dup
     102: invokespecial #24                 // Method java/lang/StringBuilder."<init>":()V
     105: ldc           #103                // String Reset global default application from
     107: invokevirtual #26                 // Method java/lang/StringBuilder.append:(Ljava/lang/String;)Ljava/lang/StringBuilder;
     110: aload_2
     111: invokestatic  #104                // Method safeGetModelDesc:(Lorg/apache/dubbo/rpc/model/ScopeModel;)Ljava/lang/String;
     114: invokevirtual #26                 // Method java/lang/StringBuilder.append:(Ljava/lang/String;)Ljava/lang/StringBuilder;
     117: ldc           #105                // String  to
     119: invokevirtual #26                 // Method java/lang/StringBuilder.append:(Ljava/lang/String;)Ljava/lang/StringBuilder;
     122: aload_0
     123: getfield      #88                 // Field defaultAppModel:Lorg/apache/dubbo/rpc/model/ApplicationModel;
     126: invokestatic  #104                // Method safeGetModelDesc:(Lorg/apache/dubbo/rpc/model/ScopeModel;)Ljava/lang/String;
     129: invokevirtual #26                 // Method java/lang/StringBuilder.append:(Ljava/lang/String;)Ljava/lang/StringBuilder;
     132: invokevirtual #28                 // Method java/lang/StringBuilder.toString:()Ljava/lang/String;
     135: invokeinterface #29,  2           // InterfaceMethod org/apache/dubbo/common/logger/Logger.info:(Ljava/lang/String;)V
     140: aload_1
     141: monitorexit
     142: goto          150
     145: astore_3
     146: aload_1
     147: monitorexit
     148: aload_3
     149: athrow
     150: return
    Exception table:
       from    to  target type
           7    26   145   any
          27   142   145   any
         145   148   145   any

  private static void resetDefaultFrameworkModel();
    Code:
       0: getstatic     #13                 // Field globalLock:Ljava/lang/Object;
       3: dup
       4: astore_0
       5: monitorenter
       6: getstatic     #52                 // Field defaultInstance:Lorg/apache/dubbo/rpc/model/FrameworkModel;
       9: ifnull        24
      12: getstatic     #52                 // Field defaultInstance:Lorg/apache/dubbo/rpc/model/FrameworkModel;
      15: invokevirtual #99                 // Method isDestroyed:()Z
      18: ifne          24
      21: aload_0
      22: monitorexit
      23: return
      24: getstatic     #52                 // Field defaultInstance:Lorg/apache/dubbo/rpc/model/FrameworkModel;
      27: astore_1
      28: getstatic     #19                 // Field allInstances:Ljava/util/List;
      31: invokeinterface #65,  1           // InterfaceMethod java/util/List.size:()I
      36: ifle          57
      39: getstatic     #19                 // Field allInstances:Ljava/util/List;
      42: iconst_0
      43: invokeinterface #102,  2          // InterfaceMethod java/util/List.get:(I)Ljava/lang/Object;
      48: checkcast     #81                 // class org/apache/dubbo/rpc/model/FrameworkModel
      51: putstatic     #52                 // Field defaultInstance:Lorg/apache/dubbo/rpc/model/FrameworkModel;
      54: goto          61
      57: aconst_null
      58: putstatic     #52                 // Field defaultInstance:Lorg/apache/dubbo/rpc/model/FrameworkModel;
      61: aload_1
      62: getstatic     #52                 // Field defaultInstance:Lorg/apache/dubbo/rpc/model/FrameworkModel;
      65: if_acmpeq     123
      68: getstatic     #21                 // Field LOGGER:Lorg/apache/dubbo/common/logger/Logger;
      71: invokeinterface #22,  1           // InterfaceMethod org/apache/dubbo/common/logger/Logger.isInfoEnabled:()Z
      76: ifeq          123
      79: getstatic     #21                 // Field LOGGER:Lorg/apache/dubbo/common/logger/Logger;
      82: new           #23                 // class java/lang/StringBuilder
      85: dup
      86: invokespecial #24                 // Method java/lang/StringBuilder."<init>":()V
      89: ldc           #106                // String Reset global default framework from
      91: invokevirtual #26                 // Method java/lang/StringBuilder.append:(Ljava/lang/String;)Ljava/lang/StringBuilder;
      94: aload_1
      95: invokestatic  #104                // Method safeGetModelDesc:(Lorg/apache/dubbo/rpc/model/ScopeModel;)Ljava/lang/String;
      98: invokevirtual #26                 // Method java/lang/StringBuilder.append:(Ljava/lang/String;)Ljava/lang/StringBuilder;
     101: ldc           #105                // String  to
     103: invokevirtual #26                 // Method java/lang/StringBuilder.append:(Ljava/lang/String;)Ljava/lang/StringBuilder;
     106: getstatic     #52                 // Field defaultInstance:Lorg/apache/dubbo/rpc/model/FrameworkModel;
     109: invokestatic  #104                // Method safeGetModelDesc:(Lorg/apache/dubbo/rpc/model/ScopeModel;)Ljava/lang/String;
     112: invokevirtual #26                 // Method java/lang/StringBuilder.append:(Ljava/lang/String;)Ljava/lang/StringBuilder;
     115: invokevirtual #28                 // Method java/lang/StringBuilder.toString:()Ljava/lang/String;
     118: invokeinterface #29,  2           // InterfaceMethod org/apache/dubbo/common/logger/Logger.info:(Ljava/lang/String;)V
     123: aload_0
     124: monitorexit
     125: goto          133
     128: astore_2
     129: aload_0
     130: monitorexit
     131: aload_2
     132: athrow
     133: return
    Exception table:
       from    to  target type
           6    23   128   any
          24   125   128   any
         128   131   128   any

  private static java.lang.String safeGetModelDesc(org.apache.dubbo.rpc.model.ScopeModel);
    Code:
       0: aload_0
       1: ifnull        11
       4: aload_0
       5: invokevirtual #107                // Method org/apache/dubbo/rpc/model/ScopeModel.getDesc:()Ljava/lang/String;
       8: goto          12
      11: aconst_null
      12: areturn

  public java.util.List<org.apache.dubbo.rpc.model.ApplicationModel> getApplicationModels();
    Code:
       0: getstatic     #13                 // Field globalLock:Ljava/lang/Object;
       3: dup
       4: astore_1
       5: monitorenter
       6: aload_0
       7: getfield      #9                  // Field pubApplicationModels:Ljava/util/List;
      10: invokestatic  #85                 // Method java/util/Collections.unmodifiableList:(Ljava/util/List;)Ljava/util/List;
      13: aload_1
      14: monitorexit
      15: areturn
      16: astore_2
      17: aload_1
      18: monitorexit
      19: aload_2
      20: athrow
    Exception table:
       from    to  target type
           6    15    16   any
          16    19    16   any

  public java.util.List<org.apache.dubbo.rpc.model.ApplicationModel> getAllApplicationModels();
    Code:
       0: getstatic     #13                 // Field globalLock:Ljava/lang/Object;
       3: dup
       4: astore_1
       5: monitorenter
       6: aload_0
       7: getfield      #8                  // Field applicationModels:Ljava/util/List;
      10: invokestatic  #85                 // Method java/util/Collections.unmodifiableList:(Ljava/util/List;)Ljava/util/List;
      13: aload_1
      14: monitorexit
      15: areturn
      16: astore_2
      17: aload_1
      18: monitorexit
      19: aload_2
      20: athrow
    Exception table:
       from    to  target type
           6    15    16   any
          16    19    16   any

  public org.apache.dubbo.rpc.model.ApplicationModel getInternalApplicationModel();
    Code:
       0: aload_0
       1: getfield      #44                 // Field internalApplicationModel:Lorg/apache/dubbo/rpc/model/ApplicationModel;
       4: areturn

  public org.apache.dubbo.rpc.model.FrameworkServiceRepository getServiceRepository();
    Code:
       0: aload_0
       1: getfield      #34                 // Field serviceRepository:Lorg/apache/dubbo/rpc/model/FrameworkServiceRepository;
       4: areturn

  protected java.util.concurrent.locks.Lock acquireDestroyLock();
    Code:
       0: aload_0
       1: getfield      #12                 // Field destroyLock:Ljava/util/concurrent/locks/ReentrantLock;
       4: areturn

  public org.apache.dubbo.common.config.Environment getModelEnvironment();
    Code:
       0: new           #108                // class java/lang/UnsupportedOperationException
       3: dup
       4: ldc           #109                // String Environment is inaccessible for FrameworkModel
       6: invokespecial #110                // Method java/lang/UnsupportedOperationException."<init>":(Ljava/lang/String;)V
       9: athrow

  protected boolean checkIfClassLoaderCanRemoved(java.lang.ClassLoader);
    Code:
       0: aload_0
       1: aload_1
       2: invokespecial #111                // Method org/apache/dubbo/rpc/model/ScopeModel.checkIfClassLoaderCanRemoved:(Ljava/lang/ClassLoader;)Z
       5: ifeq          35
       8: aload_0
       9: getfield      #8                  // Field applicationModels:Ljava/util/List;
      12: invokeinterface #66,  1           // InterfaceMethod java/util/List.stream:()Ljava/util/stream/Stream;
      17: aload_1
      18: invokedynamic #112,  0            // InvokeDynamic #1:test:(Ljava/lang/ClassLoader;)Ljava/util/function/Predicate;
      23: invokeinterface #113,  2          // InterfaceMethod java/util/stream/Stream.noneMatch:(Ljava/util/function/Predicate;)Z
      28: ifeq          35
      31: iconst_1
      32: goto          36
      35: iconst_0
      36: ireturn

  private static boolean lambda$checkIfClassLoaderCanRemoved$0(java.lang.ClassLoader, org.apache.dubbo.rpc.model.ApplicationModel);
    Code:
       0: aload_1
       1: aload_0
       2: invokevirtual #114                // Method org/apache/dubbo/rpc/model/ApplicationModel.containsClassLoader:(Ljava/lang/ClassLoader;)Z
       5: ireturn

  static {};
    Code:
       0: ldc           #81                 // class org/apache/dubbo/rpc/model/FrameworkModel
       2: invokestatic  #115                // Method org/apache/dubbo/common/logger/LoggerFactory.getLogger:(Ljava/lang/Class;)Lorg/apache/dubbo/common/logger/Logger;
       5: putstatic     #21                 // Field LOGGER:Lorg/apache/dubbo/common/logger/Logger;
       8: new           #3                  // class java/util/concurrent/atomic/AtomicLong
      11: dup
      12: lconst_1
      13: invokespecial #4                  // Method java/util/concurrent/atomic/AtomicLong."<init>":(J)V
      16: putstatic     #15                 // Field index:Ljava/util/concurrent/atomic/AtomicLong;
      19: new           #116                // class java/lang/Object
      22: dup
      23: invokespecial #117                // Method java/lang/Object."<init>":()V
      26: putstatic     #13                 // Field globalLock:Ljava/lang/Object;
      29: new           #6                  // class java/util/concurrent/CopyOnWriteArrayList
      32: dup
      33: invokespecial #7                  // Method java/util/concurrent/CopyOnWriteArrayList."<init>":()V
      36: putstatic     #19                 // Field allInstances:Ljava/util/List;
      39: return
}
