Compiled from "MethodDescriptor.java"
public final class org.apache.dubbo.rpc.model.MethodDescriptor$RpcType extends java.lang.Enum<org.apache.dubbo.rpc.model.MethodDescriptor$RpcType> {
  public static final org.apache.dubbo.rpc.model.MethodDescriptor$RpcType UNARY;

  public static final org.apache.dubbo.rpc.model.MethodDescriptor$RpcType CLIENT_STREAM;

  public static final org.apache.dubbo.rpc.model.MethodDescriptor$RpcType SERVER_STREAM;

  public static final org.apache.dubbo.rpc.model.MethodDescriptor$RpcType BI_STREAM;

  private static final org.apache.dubbo.rpc.model.MethodDescriptor$RpcType[] $VALUES;

  public static org.apache.dubbo.rpc.model.MethodDescriptor$RpcType[] values();
    Code:
       0: getstatic     #1                  // Field $VALUES:[Lorg/apache/dubbo/rpc/model/MethodDescriptor$RpcType;
       3: invokevirtual #2                  // Method "[Lorg/apache/dubbo/rpc/model/MethodDescriptor$RpcType;".clone:()Ljava/lang/Object;
       6: checkcast     #3                  // class "[Lorg/apache/dubbo/rpc/model/MethodDescriptor$RpcType;"
       9: areturn

  public static org.apache.dubbo.rpc.model.MethodDescriptor$RpcType valueOf(java.lang.String);
    Code:
       0: ldc           #4                  // class org/apache/dubbo/rpc/model/MethodDescriptor$RpcType
       2: aload_0
       3: invokestatic  #5                  // Method java/lang/Enum.valueOf:(Ljava/lang/Class;Ljava/lang/String;)Ljava/lang/Enum;
       6: checkcast     #4                  // class org/apache/dubbo/rpc/model/MethodDescriptor$RpcType
       9: areturn

  private org.apache.dubbo.rpc.model.MethodDescriptor$RpcType();
    Code:
       0: aload_0
       1: aload_1
       2: iload_2
       3: invokespecial #6                  // Method java/lang/Enum."<init>":(Ljava/lang/String;I)V
       6: return

  static {};
    Code:
       0: new           #4                  // class org/apache/dubbo/rpc/model/MethodDescriptor$RpcType
       3: dup
       4: ldc           #7                  // String UNARY
       6: iconst_0
       7: invokespecial #8                  // Method "<init>":(Ljava/lang/String;I)V
      10: putstatic     #9                  // Field UNARY:Lorg/apache/dubbo/rpc/model/MethodDescriptor$RpcType;
      13: new           #4                  // class org/apache/dubbo/rpc/model/MethodDescriptor$RpcType
      16: dup
      17: ldc           #10                 // String CLIENT_STREAM
      19: iconst_1
      20: invokespecial #8                  // Method "<init>":(Ljava/lang/String;I)V
      23: putstatic     #11                 // Field CLIENT_STREAM:Lorg/apache/dubbo/rpc/model/MethodDescriptor$RpcType;
      26: new           #4                  // class org/apache/dubbo/rpc/model/MethodDescriptor$RpcType
      29: dup
      30: ldc           #12                 // String SERVER_STREAM
      32: iconst_2
      33: invokespecial #8                  // Method "<init>":(Ljava/lang/String;I)V
      36: putstatic     #13                 // Field SERVER_STREAM:Lorg/apache/dubbo/rpc/model/MethodDescriptor$RpcType;
      39: new           #4                  // class org/apache/dubbo/rpc/model/MethodDescriptor$RpcType
      42: dup
      43: ldc           #14                 // String BI_STREAM
      45: iconst_3
      46: invokespecial #8                  // Method "<init>":(Ljava/lang/String;I)V
      49: putstatic     #15                 // Field BI_STREAM:Lorg/apache/dubbo/rpc/model/MethodDescriptor$RpcType;
      52: iconst_4
      53: anewarray     #4                  // class org/apache/dubbo/rpc/model/MethodDescriptor$RpcType
      56: dup
      57: iconst_0
      58: getstatic     #9                  // Field UNARY:Lorg/apache/dubbo/rpc/model/MethodDescriptor$RpcType;
      61: aastore
      62: dup
      63: iconst_1
      64: getstatic     #11                 // Field CLIENT_STREAM:Lorg/apache/dubbo/rpc/model/MethodDescriptor$RpcType;
      67: aastore
      68: dup
      69: iconst_2
      70: getstatic     #13                 // Field SERVER_STREAM:Lorg/apache/dubbo/rpc/model/MethodDescriptor$RpcType;
      73: aastore
      74: dup
      75: iconst_3
      76: getstatic     #15                 // Field BI_STREAM:Lorg/apache/dubbo/rpc/model/MethodDescriptor$RpcType;
      79: aastore
      80: putstatic     #1                  // Field $VALUES:[Lorg/apache/dubbo/rpc/model/MethodDescriptor$RpcType;
      83: return
}
