Compiled from "PackableMethod.java"
public interface org.apache.dubbo.rpc.model.PackableMethod {
  public default java.lang.Object parseRequest(byte[]) throws java.lang.Exception;
    Code:
       0: aload_0
       1: invokeinterface #1,  1            // InterfaceMethod getRequestUnpack:()Lorg/apache/dubbo/rpc/model/UnPack;
       6: aload_1
       7: invokeinterface #2,  2            // InterfaceMethod org/apache/dubbo/rpc/model/UnPack.unpack:([B)Ljava/lang/Object;
      12: areturn

  public default java.lang.Object parseResponse(byte[]) throws java.lang.Exception;
    Code:
       0: aload_0
       1: aload_1
       2: iconst_0
       3: invokeinterface #3,  3            // InterfaceMethod parseResponse:([BZ)Ljava/lang/Object;
       8: areturn

  public default java.lang.Object parseResponse(byte[], boolean) throws java.lang.Exception;
    Code:
       0: aload_0
       1: invokeinterface #4,  1            // InterfaceMethod getResponseUnpack:()Lorg/apache/dubbo/rpc/model/UnPack;
       6: astore_3
       7: aload_3
       8: instanceof    #5                  // class org/apache/dubbo/rpc/model/WrapperUnPack
      11: ifeq          26
      14: aload_3
      15: checkcast     #5                  // class org/apache/dubbo/rpc/model/WrapperUnPack
      18: aload_1
      19: iload_2
      20: invokeinterface #6,  3            // InterfaceMethod org/apache/dubbo/rpc/model/WrapperUnPack.unpack:([BZ)Ljava/lang/Object;
      25: areturn
      26: aload_3
      27: aload_1
      28: invokeinterface #2,  2            // InterfaceMethod org/apache/dubbo/rpc/model/UnPack.unpack:([B)Ljava/lang/Object;
      33: areturn

  public default byte[] packRequest(java.lang.Object) throws java.lang.Exception;
    Code:
       0: aload_0
       1: invokeinterface #7,  1            // InterfaceMethod getRequestPack:()Lorg/apache/dubbo/rpc/model/Pack;
       6: aload_1
       7: invokeinterface #8,  2            // InterfaceMethod org/apache/dubbo/rpc/model/Pack.pack:(Ljava/lang/Object;)[B
      12: areturn

  public default byte[] packResponse(java.lang.Object) throws java.lang.Exception;
    Code:
       0: aload_0
       1: invokeinterface #9,  1            // InterfaceMethod getResponsePack:()Lorg/apache/dubbo/rpc/model/Pack;
       6: aload_1
       7: invokeinterface #8,  2            // InterfaceMethod org/apache/dubbo/rpc/model/Pack.pack:(Ljava/lang/Object;)[B
      12: areturn

  public default boolean needWrapper();
    Code:
       0: iconst_0
       1: ireturn

  public abstract org.apache.dubbo.rpc.model.Pack getRequestPack();

  public abstract org.apache.dubbo.rpc.model.Pack getResponsePack();

  public abstract org.apache.dubbo.rpc.model.UnPack getResponseUnpack();

  public abstract org.apache.dubbo.rpc.model.UnPack getRequestUnpack();
}
