Compiled from "ProviderModel.java"
public class org.apache.dubbo.rpc.model.ProviderModel$RegisterStatedURL {
  private volatile org.apache.dubbo.common.URL registryUrl;

  private volatile org.apache.dubbo.common.URL providerUrl;

  private volatile boolean registered;

  public org.apache.dubbo.rpc.model.ProviderModel$RegisterStatedURL(org.apache.dubbo.common.URL, org.apache.dubbo.common.URL, boolean);
    Code:
       0: aload_0
       1: invokespecial #1                  // Method java/lang/Object."<init>":()V
       4: aload_0
       5: aload_1
       6: putfield      #2                  // Field providerUrl:Lorg/apache/dubbo/common/URL;
       9: aload_0
      10: iload_3
      11: putfield      #3                  // Field registered:Z
      14: aload_0
      15: aload_2
      16: putfield      #4                  // Field registryUrl:Lorg/apache/dubbo/common/URL;
      19: return

  public org.apache.dubbo.common.URL getProviderUrl();
    Code:
       0: aload_0
       1: getfield      #2                  // Field providerUrl:Lorg/apache/dubbo/common/URL;
       4: areturn

  public void setProviderUrl(org.apache.dubbo.common.URL);
    Code:
       0: aload_0
       1: aload_1
       2: putfield      #2                  // Field providerUrl:Lorg/apache/dubbo/common/URL;
       5: return

  public boolean isRegistered();
    Code:
       0: aload_0
       1: getfield      #3                  // Field registered:Z
       4: ireturn

  public void setRegistered(boolean);
    Code:
       0: aload_0
       1: iload_1
       2: putfield      #3                  // Field registered:Z
       5: return

  public org.apache.dubbo.common.URL getRegistryUrl();
    Code:
       0: aload_0
       1: getfield      #4                  // Field registryUrl:Lorg/apache/dubbo/common/URL;
       4: areturn

  public void setRegistryUrl(org.apache.dubbo.common.URL);
    Code:
       0: aload_0
       1: aload_1
       2: putfield      #4                  // Field registryUrl:Lorg/apache/dubbo/common/URL;
       5: return
}
