Compiled from "ProviderMethodModel.java"
public class org.apache.dubbo.rpc.model.ProviderMethodModel {
  private final java.lang.reflect.Method method;

  private final java.lang.String methodName;

  private final java.lang.Class<?>[] parameterClasses;

  private final java.lang.String[] methodArgTypes;

  private final java.lang.reflect.Type[] genericParameterTypes;

  private final java.util.concurrent.ConcurrentMap<java.lang.String, java.lang.Object> attributeMap;

  public org.apache.dubbo.rpc.model.ProviderMethodModel(java.lang.reflect.Method);
    Code:
       0: aload_0
       1: invokespecial #1                  // Method java/lang/Object."<init>":()V
       4: aload_0
       5: new           #2                  // class java/util/concurrent/ConcurrentHashMap
       8: dup
       9: invokespecial #3                  // Method java/util/concurrent/ConcurrentHashMap."<init>":()V
      12: putfield      #4                  // Field attributeMap:Ljava/util/concurrent/ConcurrentMap;
      15: aload_0
      16: aload_1
      17: putfield      #5                  // Field method:Ljava/lang/reflect/Method;
      20: aload_0
      21: aload_1
      22: invokevirtual #6                  // Method java/lang/reflect/Method.getName:()Ljava/lang/String;
      25: putfield      #7                  // Field methodName:Ljava/lang/String;
      28: aload_0
      29: aload_1
      30: invokevirtual #8                  // Method java/lang/reflect/Method.getParameterTypes:()[Ljava/lang/Class;
      33: putfield      #9                  // Field parameterClasses:[Ljava/lang/Class;
      36: aload_0
      37: aload_1
      38: invokestatic  #10                 // Method getArgTypes:(Ljava/lang/reflect/Method;)[Ljava/lang/String;
      41: putfield      #11                 // Field methodArgTypes:[Ljava/lang/String;
      44: aload_0
      45: aload_1
      46: invokevirtual #12                 // Method java/lang/reflect/Method.getGenericParameterTypes:()[Ljava/lang/reflect/Type;
      49: putfield      #13                 // Field genericParameterTypes:[Ljava/lang/reflect/Type;
      52: return

  public java.lang.reflect.Method getMethod();
    Code:
       0: aload_0
       1: getfield      #5                  // Field method:Ljava/lang/reflect/Method;
       4: areturn

  public java.lang.String getMethodName();
    Code:
       0: aload_0
       1: getfield      #7                  // Field methodName:Ljava/lang/String;
       4: areturn

  public java.lang.String[] getMethodArgTypes();
    Code:
       0: aload_0
       1: getfield      #11                 // Field methodArgTypes:[Ljava/lang/String;
       4: areturn

  public java.util.concurrent.ConcurrentMap<java.lang.String, java.lang.Object> getAttributeMap();
    Code:
       0: aload_0
       1: getfield      #4                  // Field attributeMap:Ljava/util/concurrent/ConcurrentMap;
       4: areturn

  private static java.lang.String[] getArgTypes(java.lang.reflect.Method);
    Code:
       0: iconst_0
       1: anewarray     #14                 // class java/lang/String
       4: astore_1
       5: aload_0
       6: invokevirtual #8                  // Method java/lang/reflect/Method.getParameterTypes:()[Ljava/lang/Class;
       9: astore_2
      10: aload_2
      11: arraylength
      12: ifle          65
      15: aload_2
      16: arraylength
      17: anewarray     #14                 // class java/lang/String
      20: astore_1
      21: iconst_0
      22: istore_3
      23: aload_2
      24: astore        4
      26: aload         4
      28: arraylength
      29: istore        5
      31: iconst_0
      32: istore        6
      34: iload         6
      36: iload         5
      38: if_icmpge     65
      41: aload         4
      43: iload         6
      45: aaload
      46: astore        7
      48: aload_1
      49: iload_3
      50: iinc          3, 1
      53: aload         7
      55: invokevirtual #15                 // Method java/lang/Class.getName:()Ljava/lang/String;
      58: aastore
      59: iinc          6, 1
      62: goto          34
      65: aload_1
      66: areturn

  public java.lang.Class<?>[] getParameterClasses();
    Code:
       0: aload_0
       1: getfield      #9                  // Field parameterClasses:[Ljava/lang/Class;
       4: areturn

  public java.lang.reflect.Type[] getGenericParameterTypes();
    Code:
       0: aload_0
       1: getfield      #13                 // Field genericParameterTypes:[Ljava/lang/reflect/Type;
       4: areturn
}
