Compiled from "ProviderModel.java"
public class org.apache.dubbo.rpc.model.ProviderModel extends org.apache.dubbo.rpc.model.ServiceModel {
  private final java.util.List<org.apache.dubbo.rpc.model.ProviderModel$RegisterStatedURL> urls;

  private final java.util.Map<java.lang.String, java.util.List<org.apache.dubbo.rpc.model.ProviderMethodModel>> methods;

  private java.util.List<org.apache.dubbo.common.URL> serviceUrls;

  private volatile long lastInvokeTime;

  public org.apache.dubbo.rpc.model.ProviderModel(java.lang.String, java.lang.Object, org.apache.dubbo.rpc.model.ServiceDescriptor, java.lang.ClassLoader);
    Code:
       0: aload_0
       1: aload_2
       2: aload_1
       3: aload_3
       4: aconst_null
       5: aload         4
       7: invokespecial #1                  // Method org/apache/dubbo/rpc/model/ServiceModel."<init>":(Ljava/lang/Object;Ljava/lang/String;Lorg/apache/dubbo/rpc/model/ServiceDescriptor;Lorg/apache/dubbo/rpc/model/ModuleModel;Ljava/lang/ClassLoader;)V
      10: aload_0
      11: new           #2                  // class java/util/HashMap
      14: dup
      15: invokespecial #3                  // Method java/util/HashMap."<init>":()V
      18: putfield      #4                  // Field methods:Ljava/util/Map;
      21: aload_0
      22: new           #5                  // class java/util/ArrayList
      25: dup
      26: invokespecial #6                  // Method java/util/ArrayList."<init>":()V
      29: putfield      #7                  // Field serviceUrls:Ljava/util/List;
      32: aload_0
      33: lconst_0
      34: putfield      #8                  // Field lastInvokeTime:J
      37: aconst_null
      38: aload_2
      39: if_acmpne     74
      42: new           #9                  // class java/lang/IllegalArgumentException
      45: dup
      46: new           #10                 // class java/lang/StringBuilder
      49: dup
      50: invokespecial #11                 // Method java/lang/StringBuilder."<init>":()V
      53: ldc           #12                 // String Service[
      55: invokevirtual #13                 // Method java/lang/StringBuilder.append:(Ljava/lang/String;)Ljava/lang/StringBuilder;
      58: aload_1
      59: invokevirtual #13                 // Method java/lang/StringBuilder.append:(Ljava/lang/String;)Ljava/lang/StringBuilder;
      62: ldc           #14                 // String ]Target is NULL.
      64: invokevirtual #13                 // Method java/lang/StringBuilder.append:(Ljava/lang/String;)Ljava/lang/StringBuilder;
      67: invokevirtual #15                 // Method java/lang/StringBuilder.toString:()Ljava/lang/String;
      70: invokespecial #16                 // Method java/lang/IllegalArgumentException."<init>":(Ljava/lang/String;)V
      73: athrow
      74: aload_0
      75: new           #17                 // class java/util/concurrent/CopyOnWriteArrayList
      78: dup
      79: invokespecial #18                 // Method java/util/concurrent/CopyOnWriteArrayList."<init>":()V
      82: putfield      #19                 // Field urls:Ljava/util/List;
      85: return

  public org.apache.dubbo.rpc.model.ProviderModel(java.lang.String, java.lang.Object, org.apache.dubbo.rpc.model.ServiceDescriptor, org.apache.dubbo.rpc.model.ServiceMetadata, java.lang.ClassLoader);
    Code:
       0: aload_0
       1: aload_2
       2: aload_1
       3: aload_3
       4: aconst_null
       5: aload         4
       7: aload         5
       9: invokespecial #20                 // Method org/apache/dubbo/rpc/model/ServiceModel."<init>":(Ljava/lang/Object;Ljava/lang/String;Lorg/apache/dubbo/rpc/model/ServiceDescriptor;Lorg/apache/dubbo/rpc/model/ModuleModel;Lorg/apache/dubbo/rpc/model/ServiceMetadata;Ljava/lang/ClassLoader;)V
      12: aload_0
      13: new           #2                  // class java/util/HashMap
      16: dup
      17: invokespecial #3                  // Method java/util/HashMap."<init>":()V
      20: putfield      #4                  // Field methods:Ljava/util/Map;
      23: aload_0
      24: new           #5                  // class java/util/ArrayList
      27: dup
      28: invokespecial #6                  // Method java/util/ArrayList."<init>":()V
      31: putfield      #7                  // Field serviceUrls:Ljava/util/List;
      34: aload_0
      35: lconst_0
      36: putfield      #8                  // Field lastInvokeTime:J
      39: aconst_null
      40: aload_2
      41: if_acmpne     76
      44: new           #9                  // class java/lang/IllegalArgumentException
      47: dup
      48: new           #10                 // class java/lang/StringBuilder
      51: dup
      52: invokespecial #11                 // Method java/lang/StringBuilder."<init>":()V
      55: ldc           #12                 // String Service[
      57: invokevirtual #13                 // Method java/lang/StringBuilder.append:(Ljava/lang/String;)Ljava/lang/StringBuilder;
      60: aload_1
      61: invokevirtual #13                 // Method java/lang/StringBuilder.append:(Ljava/lang/String;)Ljava/lang/StringBuilder;
      64: ldc           #14                 // String ]Target is NULL.
      66: invokevirtual #13                 // Method java/lang/StringBuilder.append:(Ljava/lang/String;)Ljava/lang/StringBuilder;
      69: invokevirtual #15                 // Method java/lang/StringBuilder.toString:()Ljava/lang/String;
      72: invokespecial #16                 // Method java/lang/IllegalArgumentException."<init>":(Ljava/lang/String;)V
      75: athrow
      76: aload_0
      77: aload_3
      78: invokeinterface #21,  1           // InterfaceMethod org/apache/dubbo/rpc/model/ServiceDescriptor.getServiceInterfaceClass:()Ljava/lang/Class;
      83: invokespecial #22                 // Method initMethod:(Ljava/lang/Class;)V
      86: aload_0
      87: new           #5                  // class java/util/ArrayList
      90: dup
      91: iconst_1
      92: invokespecial #23                 // Method java/util/ArrayList."<init>":(I)V
      95: putfield      #19                 // Field urls:Ljava/util/List;
      98: return

  public org.apache.dubbo.rpc.model.ProviderModel(java.lang.String, java.lang.Object, org.apache.dubbo.rpc.model.ServiceDescriptor, org.apache.dubbo.rpc.model.ModuleModel, org.apache.dubbo.rpc.model.ServiceMetadata, java.lang.ClassLoader);
    Code:
       0: aload_0
       1: aload_2
       2: aload_1
       3: aload_3
       4: aload         4
       6: aload         5
       8: aload         6
      10: invokespecial #20                 // Method org/apache/dubbo/rpc/model/ServiceModel."<init>":(Ljava/lang/Object;Ljava/lang/String;Lorg/apache/dubbo/rpc/model/ServiceDescriptor;Lorg/apache/dubbo/rpc/model/ModuleModel;Lorg/apache/dubbo/rpc/model/ServiceMetadata;Ljava/lang/ClassLoader;)V
      13: aload_0
      14: new           #2                  // class java/util/HashMap
      17: dup
      18: invokespecial #3                  // Method java/util/HashMap."<init>":()V
      21: putfield      #4                  // Field methods:Ljava/util/Map;
      24: aload_0
      25: new           #5                  // class java/util/ArrayList
      28: dup
      29: invokespecial #6                  // Method java/util/ArrayList."<init>":()V
      32: putfield      #7                  // Field serviceUrls:Ljava/util/List;
      35: aload_0
      36: lconst_0
      37: putfield      #8                  // Field lastInvokeTime:J
      40: aconst_null
      41: aload_2
      42: if_acmpne     77
      45: new           #9                  // class java/lang/IllegalArgumentException
      48: dup
      49: new           #10                 // class java/lang/StringBuilder
      52: dup
      53: invokespecial #11                 // Method java/lang/StringBuilder."<init>":()V
      56: ldc           #12                 // String Service[
      58: invokevirtual #13                 // Method java/lang/StringBuilder.append:(Ljava/lang/String;)Ljava/lang/StringBuilder;
      61: aload_1
      62: invokevirtual #13                 // Method java/lang/StringBuilder.append:(Ljava/lang/String;)Ljava/lang/StringBuilder;
      65: ldc           #14                 // String ]Target is NULL.
      67: invokevirtual #13                 // Method java/lang/StringBuilder.append:(Ljava/lang/String;)Ljava/lang/StringBuilder;
      70: invokevirtual #15                 // Method java/lang/StringBuilder.toString:()Ljava/lang/String;
      73: invokespecial #16                 // Method java/lang/IllegalArgumentException."<init>":(Ljava/lang/String;)V
      76: athrow
      77: aload_0
      78: aload_3
      79: invokeinterface #21,  1           // InterfaceMethod org/apache/dubbo/rpc/model/ServiceDescriptor.getServiceInterfaceClass:()Ljava/lang/Class;
      84: invokespecial #22                 // Method initMethod:(Ljava/lang/Class;)V
      87: aload_0
      88: new           #5                  // class java/util/ArrayList
      91: dup
      92: iconst_1
      93: invokespecial #23                 // Method java/util/ArrayList."<init>":(I)V
      96: putfield      #19                 // Field urls:Ljava/util/List;
      99: return

  public java.lang.Object getServiceInstance();
    Code:
       0: aload_0
       1: invokevirtual #24                 // Method getProxyObject:()Ljava/lang/Object;
       4: areturn

  public java.util.List<org.apache.dubbo.rpc.model.ProviderModel$RegisterStatedURL> getStatedUrl();
    Code:
       0: aload_0
       1: getfield      #19                 // Field urls:Ljava/util/List;
       4: areturn

  public void addStatedUrl(org.apache.dubbo.rpc.model.ProviderModel$RegisterStatedURL);
    Code:
       0: aload_0
       1: getfield      #19                 // Field urls:Ljava/util/List;
       4: aload_1
       5: invokeinterface #25,  2           // InterfaceMethod java/util/List.add:(Ljava/lang/Object;)Z
      10: pop
      11: return

  public java.util.List<org.apache.dubbo.rpc.model.ProviderMethodModel> getAllMethodModels();
    Code:
       0: new           #5                  // class java/util/ArrayList
       3: dup
       4: invokespecial #6                  // Method java/util/ArrayList."<init>":()V
       7: astore_1
       8: aload_0
       9: getfield      #4                  // Field methods:Ljava/util/Map;
      12: invokeinterface #26,  1           // InterfaceMethod java/util/Map.values:()Ljava/util/Collection;
      17: invokeinterface #27,  1           // InterfaceMethod java/util/Collection.iterator:()Ljava/util/Iterator;
      22: astore_2
      23: aload_2
      24: invokeinterface #28,  1           // InterfaceMethod java/util/Iterator.hasNext:()Z
      29: ifeq          53
      32: aload_2
      33: invokeinterface #29,  1           // InterfaceMethod java/util/Iterator.next:()Ljava/lang/Object;
      38: checkcast     #30                 // class java/util/List
      41: astore_3
      42: aload_1
      43: aload_3
      44: invokeinterface #31,  2           // InterfaceMethod java/util/List.addAll:(Ljava/util/Collection;)Z
      49: pop
      50: goto          23
      53: aload_1
      54: areturn

  public org.apache.dubbo.rpc.model.ProviderMethodModel getMethodModel(java.lang.String, java.lang.String[]);
    Code:
       0: aload_0
       1: getfield      #4                  // Field methods:Ljava/util/Map;
       4: aload_1
       5: invokeinterface #32,  2           // InterfaceMethod java/util/Map.get:(Ljava/lang/Object;)Ljava/lang/Object;
      10: checkcast     #30                 // class java/util/List
      13: astore_3
      14: aload_3
      15: ifnull        66
      18: aload_3
      19: invokeinterface #33,  1           // InterfaceMethod java/util/List.iterator:()Ljava/util/Iterator;
      24: astore        4
      26: aload         4
      28: invokeinterface #28,  1           // InterfaceMethod java/util/Iterator.hasNext:()Z
      33: ifeq          66
      36: aload         4
      38: invokeinterface #29,  1           // InterfaceMethod java/util/Iterator.next:()Ljava/lang/Object;
      43: checkcast     #34                 // class org/apache/dubbo/rpc/model/ProviderMethodModel
      46: astore        5
      48: aload_2
      49: aload         5
      51: invokevirtual #35                 // Method org/apache/dubbo/rpc/model/ProviderMethodModel.getMethodArgTypes:()[Ljava/lang/String;
      54: invokestatic  #36                 // Method java/util/Arrays.equals:([Ljava/lang/Object;[Ljava/lang/Object;)Z
      57: ifeq          63
      60: aload         5
      62: areturn
      63: goto          26
      66: aconst_null
      67: areturn

  public java.util.List<org.apache.dubbo.rpc.model.ProviderMethodModel> getMethodModelList(java.lang.String);
    Code:
       0: aload_0
       1: getfield      #4                  // Field methods:Ljava/util/Map;
       4: aload_1
       5: invokeinterface #32,  2           // InterfaceMethod java/util/Map.get:(Ljava/lang/Object;)Ljava/lang/Object;
      10: checkcast     #30                 // class java/util/List
      13: astore_2
      14: aload_2
      15: ifnonnull     24
      18: invokestatic  #37                 // Method java/util/Collections.emptyList:()Ljava/util/List;
      21: goto          25
      24: aload_2
      25: areturn

  private void initMethod(java.lang.Class<?>);
    Code:
       0: aload_1
       1: invokevirtual #38                 // Method java/lang/Class.getMethods:()[Ljava/lang/reflect/Method;
       4: astore_2
       5: aload_2
       6: astore_3
       7: aload_3
       8: arraylength
       9: istore        4
      11: iconst_0
      12: istore        5
      14: iload         5
      16: iload         4
      18: if_icmpge     80
      21: aload_3
      22: iload         5
      24: aaload
      25: astore        6
      27: aload         6
      29: iconst_1
      30: invokevirtual #39                 // Method java/lang/reflect/Method.setAccessible:(Z)V
      33: aload_0
      34: getfield      #4                  // Field methods:Ljava/util/Map;
      37: aload         6
      39: invokevirtual #40                 // Method java/lang/reflect/Method.getName:()Ljava/lang/String;
      42: invokedynamic #41,  0             // InvokeDynamic #0:apply:()Ljava/util/function/Function;
      47: invokeinterface #42,  3           // InterfaceMethod java/util/Map.computeIfAbsent:(Ljava/lang/Object;Ljava/util/function/Function;)Ljava/lang/Object;
      52: checkcast     #30                 // class java/util/List
      55: astore        7
      57: aload         7
      59: new           #34                 // class org/apache/dubbo/rpc/model/ProviderMethodModel
      62: dup
      63: aload         6
      65: invokespecial #43                 // Method org/apache/dubbo/rpc/model/ProviderMethodModel."<init>":(Ljava/lang/reflect/Method;)V
      68: invokeinterface #25,  2           // InterfaceMethod java/util/List.add:(Ljava/lang/Object;)Z
      73: pop
      74: iinc          5, 1
      77: goto          14
      80: return

  public java.util.List<org.apache.dubbo.common.URL> getServiceUrls();
    Code:
       0: aload_0
       1: getfield      #7                  // Field serviceUrls:Ljava/util/List;
       4: areturn

  public void setServiceUrls(java.util.List<org.apache.dubbo.common.URL>);
    Code:
       0: aload_0
       1: aload_1
       2: putfield      #7                  // Field serviceUrls:Ljava/util/List;
       5: return

  public long getLastInvokeTime();
    Code:
       0: aload_0
       1: getfield      #8                  // Field lastInvokeTime:J
       4: lreturn

  public void updateLastInvokeTime();
    Code:
       0: aload_0
       1: invokestatic  #44                 // Method java/lang/System.currentTimeMillis:()J
       4: putfield      #8                  // Field lastInvokeTime:J
       7: return

  public boolean equals(java.lang.Object);
    Code:
       0: aload_0
       1: aload_1
       2: if_acmpne     7
       5: iconst_1
       6: ireturn
       7: aload_1
       8: ifnull        22
      11: aload_0
      12: invokevirtual #45                 // Method java/lang/Object.getClass:()Ljava/lang/Class;
      15: aload_1
      16: invokevirtual #45                 // Method java/lang/Object.getClass:()Ljava/lang/Class;
      19: if_acmpeq     24
      22: iconst_0
      23: ireturn
      24: aload_0
      25: aload_1
      26: invokespecial #46                 // Method org/apache/dubbo/rpc/model/ServiceModel.equals:(Ljava/lang/Object;)Z
      29: ifne          34
      32: iconst_0
      33: ireturn
      34: aload_1
      35: checkcast     #47                 // class org/apache/dubbo/rpc/model/ProviderModel
      38: astore_2
      39: aload_0
      40: getfield      #19                 // Field urls:Ljava/util/List;
      43: aload_2
      44: getfield      #19                 // Field urls:Ljava/util/List;
      47: invokestatic  #48                 // Method java/util/Objects.equals:(Ljava/lang/Object;Ljava/lang/Object;)Z
      50: ifeq          71
      53: aload_0
      54: getfield      #4                  // Field methods:Ljava/util/Map;
      57: aload_2
      58: getfield      #4                  // Field methods:Ljava/util/Map;
      61: invokestatic  #48                 // Method java/util/Objects.equals:(Ljava/lang/Object;Ljava/lang/Object;)Z
      64: ifeq          71
      67: iconst_1
      68: goto          72
      71: iconst_0
      72: ireturn

  public int hashCode();
    Code:
       0: iconst_3
       1: anewarray     #49                 // class java/lang/Object
       4: dup
       5: iconst_0
       6: aload_0
       7: invokespecial #50                 // Method org/apache/dubbo/rpc/model/ServiceModel.hashCode:()I
      10: invokestatic  #51                 // Method java/lang/Integer.valueOf:(I)Ljava/lang/Integer;
      13: aastore
      14: dup
      15: iconst_1
      16: aload_0
      17: getfield      #19                 // Field urls:Ljava/util/List;
      20: aastore
      21: dup
      22: iconst_2
      23: aload_0
      24: getfield      #4                  // Field methods:Ljava/util/Map;
      27: aastore
      28: invokestatic  #52                 // Method java/util/Objects.hash:([Ljava/lang/Object;)I
      31: ireturn

  private static java.util.List lambda$initMethod$0(java.lang.String);
    Code:
       0: new           #5                  // class java/util/ArrayList
       3: dup
       4: invokespecial #6                  // Method java/util/ArrayList."<init>":()V
       7: areturn
}
