Compiled from "ReflectionMethodDescriptor.java"
public class org.apache.dubbo.rpc.model.ReflectionMethodDescriptor implements org.apache.dubbo.rpc.model.MethodDescriptor {
  private static final org.apache.dubbo.common.logger.ErrorTypeAwareLogger logger;

  private final java.util.concurrent.ConcurrentMap<java.lang.String, java.lang.Object> attributeMap;

  public final java.lang.String methodName;

  private final java.lang.String[] compatibleParamSignatures;

  private final java.lang.Class<?>[] parameterClasses;

  private final java.lang.Class<?> returnClass;

  private final java.lang.reflect.Type[] returnTypes;

  private final java.lang.String paramDesc;

  private final java.lang.reflect.Method method;

  private final boolean generic;

  private final org.apache.dubbo.rpc.model.MethodDescriptor$RpcType rpcType;

  public org.apache.dubbo.rpc.model.ReflectionMethodDescriptor(java.lang.reflect.Method);
    Code:
       0: aload_0
       1: invokespecial #3                  // Method java/lang/Object."<init>":()V
       4: aload_0
       5: new           #4                  // class java/util/concurrent/ConcurrentHashMap
       8: dup
       9: invokespecial #5                  // Method java/util/concurrent/ConcurrentHashMap."<init>":()V
      12: putfield      #6                  // Field attributeMap:Ljava/util/concurrent/ConcurrentMap;
      15: aload_0
      16: aload_1
      17: putfield      #7                  // Field method:Ljava/lang/reflect/Method;
      20: aload_0
      21: aload_1
      22: invokevirtual #8                  // Method java/lang/reflect/Method.getName:()Ljava/lang/String;
      25: putfield      #9                  // Field methodName:Ljava/lang/String;
      28: aload_0
      29: aload_1
      30: invokevirtual #10                 // Method java/lang/reflect/Method.getParameterTypes:()[Ljava/lang/Class;
      33: putfield      #11                 // Field parameterClasses:[Ljava/lang/Class;
      36: aload_0
      37: aload_1
      38: invokevirtual #12                 // Method java/lang/reflect/Method.getReturnType:()Ljava/lang/Class;
      41: putfield      #13                 // Field returnClass:Ljava/lang/Class;
      44: aload_1
      45: invokestatic  #14                 // Method org/apache/dubbo/common/utils/ReflectUtils.getReturnTypes:(Ljava/lang/reflect/Method;)[Ljava/lang/reflect/Type;
      48: astore_2
      49: goto          124
      52: astore_3
      53: getstatic     #16                 // Field logger:Lorg/apache/dubbo/common/logger/ErrorTypeAwareLogger;
      56: ldc           #17                 // String 0-8
      58: ldc           #18                 // String
      60: ldc           #18                 // String
      62: new           #19                 // class java/lang/StringBuilder
      65: dup
      66: invokespecial #20                 // Method java/lang/StringBuilder."<init>":()V
      69: ldc           #21                 // String fail to get return types. Method name:
      71: invokevirtual #22                 // Method java/lang/StringBuilder.append:(Ljava/lang/String;)Ljava/lang/StringBuilder;
      74: aload_0
      75: getfield      #9                  // Field methodName:Ljava/lang/String;
      78: invokevirtual #22                 // Method java/lang/StringBuilder.append:(Ljava/lang/String;)Ljava/lang/StringBuilder;
      81: ldc           #23                 // String  Declaring class:
      83: invokevirtual #22                 // Method java/lang/StringBuilder.append:(Ljava/lang/String;)Ljava/lang/StringBuilder;
      86: aload_1
      87: invokevirtual #24                 // Method java/lang/reflect/Method.getDeclaringClass:()Ljava/lang/Class;
      90: invokevirtual #25                 // Method java/lang/Class.getName:()Ljava/lang/String;
      93: invokevirtual #22                 // Method java/lang/StringBuilder.append:(Ljava/lang/String;)Ljava/lang/StringBuilder;
      96: invokevirtual #26                 // Method java/lang/StringBuilder.toString:()Ljava/lang/String;
      99: aload_3
     100: invokeinterface #27,  6           // InterfaceMethod org/apache/dubbo/common/logger/ErrorTypeAwareLogger.error:(Ljava/lang/String;Ljava/lang/String;Ljava/lang/String;Ljava/lang/String;Ljava/lang/Throwable;)V
     105: iconst_2
     106: anewarray     #28                 // class java/lang/reflect/Type
     109: dup
     110: iconst_0
     111: aload_0
     112: getfield      #13                 // Field returnClass:Ljava/lang/Class;
     115: aastore
     116: dup
     117: iconst_1
     118: aload_0
     119: getfield      #13                 // Field returnClass:Ljava/lang/Class;
     122: aastore
     123: astore_2
     124: aload_0
     125: aload_2
     126: putfield      #29                 // Field returnTypes:[Ljava/lang/reflect/Type;
     129: aload_0
     130: aload_0
     131: getfield      #11                 // Field parameterClasses:[Ljava/lang/Class;
     134: invokestatic  #30                 // Method org/apache/dubbo/common/utils/ReflectUtils.getDesc:([Ljava/lang/Class;)Ljava/lang/String;
     137: putfield      #31                 // Field paramDesc:Ljava/lang/String;
     140: aload_0
     141: aload_0
     142: getfield      #11                 // Field parameterClasses:[Ljava/lang/Class;
     145: invokestatic  #32                 // InterfaceMethod java/util/stream/Stream.of:([Ljava/lang/Object;)Ljava/util/stream/Stream;
     148: invokedynamic #33,  0             // InvokeDynamic #0:apply:()Ljava/util/function/Function;
     153: invokeinterface #34,  2           // InterfaceMethod java/util/stream/Stream.map:(Ljava/util/function/Function;)Ljava/util/stream/Stream;
     158: invokedynamic #35,  0             // InvokeDynamic #1:apply:()Ljava/util/function/IntFunction;
     163: invokeinterface #36,  2           // InterfaceMethod java/util/stream/Stream.toArray:(Ljava/util/function/IntFunction;)[Ljava/lang/Object;
     168: checkcast     #37                 // class "[Ljava/lang/String;"
     171: putfield      #38                 // Field compatibleParamSignatures:[Ljava/lang/String;
     174: aload_0
     175: aload_0
     176: getfield      #9                  // Field methodName:Ljava/lang/String;
     179: ldc           #39                 // String $invoke
     181: invokevirtual #40                 // Method java/lang/String.equals:(Ljava/lang/Object;)Z
     184: ifne          199
     187: aload_0
     188: getfield      #9                  // Field methodName:Ljava/lang/String;
     191: ldc           #41                 // String $invokeAsync
     193: invokevirtual #40                 // Method java/lang/String.equals:(Ljava/lang/Object;)Z
     196: ifeq          212
     199: aload_0
     200: getfield      #11                 // Field parameterClasses:[Ljava/lang/Class;
     203: arraylength
     204: iconst_3
     205: if_icmpne     212
     208: iconst_1
     209: goto          213
     212: iconst_0
     213: putfield      #42                 // Field generic:Z
     216: aload_0
     217: aload_0
     218: invokespecial #43                 // Method determineRpcType:()Lorg/apache/dubbo/rpc/model/MethodDescriptor$RpcType;
     221: putfield      #44                 // Field rpcType:Lorg/apache/dubbo/rpc/model/MethodDescriptor$RpcType;
     224: return
    Exception table:
       from    to  target type
          44    49    52   Class java/lang/Throwable

  private org.apache.dubbo.rpc.model.MethodDescriptor$RpcType determineRpcType();
    Code:
       0: aload_0
       1: getfield      #42                 // Field generic:Z
       4: ifeq          11
       7: getstatic     #45                 // Field org/apache/dubbo/rpc/model/MethodDescriptor$RpcType.UNARY:Lorg/apache/dubbo/rpc/model/MethodDescriptor$RpcType;
      10: areturn
      11: aload_0
      12: getfield      #11                 // Field parameterClasses:[Ljava/lang/Class;
      15: arraylength
      16: iconst_2
      17: if_icmple     24
      20: getstatic     #45                 // Field org/apache/dubbo/rpc/model/MethodDescriptor$RpcType.UNARY:Lorg/apache/dubbo/rpc/model/MethodDescriptor$RpcType;
      23: areturn
      24: aload_0
      25: getfield      #11                 // Field parameterClasses:[Ljava/lang/Class;
      28: arraylength
      29: iconst_1
      30: if_icmpne     61
      33: aload_0
      34: aload_0
      35: getfield      #11                 // Field parameterClasses:[Ljava/lang/Class;
      38: iconst_0
      39: aaload
      40: invokespecial #46                 // Method isStreamType:(Ljava/lang/Class;)Z
      43: ifeq          61
      46: aload_0
      47: aload_0
      48: getfield      #13                 // Field returnClass:Ljava/lang/Class;
      51: invokespecial #46                 // Method isStreamType:(Ljava/lang/Class;)Z
      54: ifeq          61
      57: getstatic     #47                 // Field org/apache/dubbo/rpc/model/MethodDescriptor$RpcType.BI_STREAM:Lorg/apache/dubbo/rpc/model/MethodDescriptor$RpcType;
      60: areturn
      61: aload_0
      62: getfield      #11                 // Field parameterClasses:[Ljava/lang/Class;
      65: arraylength
      66: iconst_2
      67: if_icmpne     119
      70: aload_0
      71: aload_0
      72: getfield      #11                 // Field parameterClasses:[Ljava/lang/Class;
      75: iconst_0
      76: aaload
      77: invokespecial #46                 // Method isStreamType:(Ljava/lang/Class;)Z
      80: ifne          119
      83: aload_0
      84: aload_0
      85: getfield      #11                 // Field parameterClasses:[Ljava/lang/Class;
      88: iconst_1
      89: aaload
      90: invokespecial #46                 // Method isStreamType:(Ljava/lang/Class;)Z
      93: ifeq          119
      96: aload_0
      97: getfield      #13                 // Field returnClass:Ljava/lang/Class;
     100: invokevirtual #25                 // Method java/lang/Class.getName:()Ljava/lang/String;
     103: getstatic     #48                 // Field java/lang/Void.TYPE:Ljava/lang/Class;
     106: invokevirtual #25                 // Method java/lang/Class.getName:()Ljava/lang/String;
     109: invokevirtual #40                 // Method java/lang/String.equals:(Ljava/lang/Object;)Z
     112: ifeq          119
     115: getstatic     #49                 // Field org/apache/dubbo/rpc/model/MethodDescriptor$RpcType.SERVER_STREAM:Lorg/apache/dubbo/rpc/model/MethodDescriptor$RpcType;
     118: areturn
     119: aload_0
     120: getfield      #11                 // Field parameterClasses:[Ljava/lang/Class;
     123: invokestatic  #50                 // Method java/util/Arrays.stream:([Ljava/lang/Object;)Ljava/util/stream/Stream;
     126: aload_0
     127: invokedynamic #51,  0             // InvokeDynamic #2:test:(Lorg/apache/dubbo/rpc/model/ReflectionMethodDescriptor;)Ljava/util/function/Predicate;
     132: invokeinterface #52,  2           // InterfaceMethod java/util/stream/Stream.anyMatch:(Ljava/util/function/Predicate;)Z
     137: ifne          151
     140: aload_0
     141: aload_0
     142: getfield      #13                 // Field returnClass:Ljava/lang/Class;
     145: invokespecial #46                 // Method isStreamType:(Ljava/lang/Class;)Z
     148: ifeq          198
     151: new           #53                 // class java/lang/IllegalStateException
     154: dup
     155: new           #19                 // class java/lang/StringBuilder
     158: dup
     159: invokespecial #20                 // Method java/lang/StringBuilder."<init>":()V
     162: ldc           #54                 // String Bad stream method signature. method(
     164: invokevirtual #22                 // Method java/lang/StringBuilder.append:(Ljava/lang/String;)Ljava/lang/StringBuilder;
     167: aload_0
     168: getfield      #9                  // Field methodName:Ljava/lang/String;
     171: invokevirtual #22                 // Method java/lang/StringBuilder.append:(Ljava/lang/String;)Ljava/lang/StringBuilder;
     174: ldc           #55                 // String :
     176: invokevirtual #22                 // Method java/lang/StringBuilder.append:(Ljava/lang/String;)Ljava/lang/StringBuilder;
     179: aload_0
     180: getfield      #31                 // Field paramDesc:Ljava/lang/String;
     183: invokevirtual #22                 // Method java/lang/StringBuilder.append:(Ljava/lang/String;)Ljava/lang/StringBuilder;
     186: ldc           #56                 // String )
     188: invokevirtual #22                 // Method java/lang/StringBuilder.append:(Ljava/lang/String;)Ljava/lang/StringBuilder;
     191: invokevirtual #26                 // Method java/lang/StringBuilder.toString:()Ljava/lang/String;
     194: invokespecial #57                 // Method java/lang/IllegalStateException."<init>":(Ljava/lang/String;)V
     197: athrow
     198: getstatic     #45                 // Field org/apache/dubbo/rpc/model/MethodDescriptor$RpcType.UNARY:Lorg/apache/dubbo/rpc/model/MethodDescriptor$RpcType;
     201: areturn

  private boolean isStreamType(java.lang.Class<?>);
    Code:
       0: ldc           #58                 // class org/apache/dubbo/common/stream/StreamObserver
       2: aload_1
       3: invokevirtual #59                 // Method java/lang/Class.isAssignableFrom:(Ljava/lang/Class;)Z
       6: ireturn

  public java.lang.String getMethodName();
    Code:
       0: aload_0
       1: getfield      #9                  // Field methodName:Ljava/lang/String;
       4: areturn

  public java.lang.reflect.Method getMethod();
    Code:
       0: aload_0
       1: getfield      #7                  // Field method:Ljava/lang/reflect/Method;
       4: areturn

  public java.lang.String[] getCompatibleParamSignatures();
    Code:
       0: aload_0
       1: getfield      #38                 // Field compatibleParamSignatures:[Ljava/lang/String;
       4: areturn

  public java.lang.Class<?>[] getParameterClasses();
    Code:
       0: aload_0
       1: getfield      #11                 // Field parameterClasses:[Ljava/lang/Class;
       4: areturn

  public java.lang.String getParamDesc();
    Code:
       0: aload_0
       1: getfield      #31                 // Field paramDesc:Ljava/lang/String;
       4: areturn

  public java.lang.Class<?> getReturnClass();
    Code:
       0: aload_0
       1: getfield      #13                 // Field returnClass:Ljava/lang/Class;
       4: areturn

  public java.lang.reflect.Type[] getReturnTypes();
    Code:
       0: aload_0
       1: getfield      #29                 // Field returnTypes:[Ljava/lang/reflect/Type;
       4: areturn

  public org.apache.dubbo.rpc.model.MethodDescriptor$RpcType getRpcType();
    Code:
       0: aload_0
       1: getfield      #44                 // Field rpcType:Lorg/apache/dubbo/rpc/model/MethodDescriptor$RpcType;
       4: areturn

  public boolean isGeneric();
    Code:
       0: aload_0
       1: getfield      #42                 // Field generic:Z
       4: ireturn

  public void addAttribute(java.lang.String, java.lang.Object);
    Code:
       0: aload_0
       1: getfield      #6                  // Field attributeMap:Ljava/util/concurrent/ConcurrentMap;
       4: aload_1
       5: aload_2
       6: invokeinterface #60,  3           // InterfaceMethod java/util/concurrent/ConcurrentMap.put:(Ljava/lang/Object;Ljava/lang/Object;)Ljava/lang/Object;
      11: pop
      12: return

  public java.lang.Object getAttribute(java.lang.String);
    Code:
       0: aload_0
       1: getfield      #6                  // Field attributeMap:Ljava/util/concurrent/ConcurrentMap;
       4: aload_1
       5: invokeinterface #61,  2           // InterfaceMethod java/util/concurrent/ConcurrentMap.get:(Ljava/lang/Object;)Ljava/lang/Object;
      10: areturn

  public boolean equals(java.lang.Object);
    Code:
       0: aload_0
       1: aload_1
       2: if_acmpne     7
       5: iconst_1
       6: ireturn
       7: aload_1
       8: ifnull        22
      11: aload_0
      12: invokevirtual #62                 // Method java/lang/Object.getClass:()Ljava/lang/Class;
      15: aload_1
      16: invokevirtual #62                 // Method java/lang/Object.getClass:()Ljava/lang/Class;
      19: if_acmpeq     24
      22: iconst_0
      23: ireturn
      24: aload_1
      25: checkcast     #63                 // class org/apache/dubbo/rpc/model/ReflectionMethodDescriptor
      28: astore_2
      29: aload_0
      30: getfield      #42                 // Field generic:Z
      33: aload_2
      34: getfield      #42                 // Field generic:Z
      37: if_icmpne     156
      40: aload_0
      41: getfield      #7                  // Field method:Ljava/lang/reflect/Method;
      44: aload_2
      45: getfield      #7                  // Field method:Ljava/lang/reflect/Method;
      48: invokestatic  #64                 // Method java/util/Objects.equals:(Ljava/lang/Object;Ljava/lang/Object;)Z
      51: ifeq          156
      54: aload_0
      55: getfield      #31                 // Field paramDesc:Ljava/lang/String;
      58: aload_2
      59: getfield      #31                 // Field paramDesc:Ljava/lang/String;
      62: invokestatic  #64                 // Method java/util/Objects.equals:(Ljava/lang/Object;Ljava/lang/Object;)Z
      65: ifeq          156
      68: aload_0
      69: getfield      #38                 // Field compatibleParamSignatures:[Ljava/lang/String;
      72: aload_2
      73: getfield      #38                 // Field compatibleParamSignatures:[Ljava/lang/String;
      76: invokestatic  #65                 // Method java/util/Arrays.equals:([Ljava/lang/Object;[Ljava/lang/Object;)Z
      79: ifeq          156
      82: aload_0
      83: getfield      #11                 // Field parameterClasses:[Ljava/lang/Class;
      86: aload_2
      87: getfield      #11                 // Field parameterClasses:[Ljava/lang/Class;
      90: invokestatic  #65                 // Method java/util/Arrays.equals:([Ljava/lang/Object;[Ljava/lang/Object;)Z
      93: ifeq          156
      96: aload_0
      97: getfield      #13                 // Field returnClass:Ljava/lang/Class;
     100: aload_2
     101: getfield      #13                 // Field returnClass:Ljava/lang/Class;
     104: invokestatic  #64                 // Method java/util/Objects.equals:(Ljava/lang/Object;Ljava/lang/Object;)Z
     107: ifeq          156
     110: aload_0
     111: getfield      #29                 // Field returnTypes:[Ljava/lang/reflect/Type;
     114: aload_2
     115: getfield      #29                 // Field returnTypes:[Ljava/lang/reflect/Type;
     118: invokestatic  #65                 // Method java/util/Arrays.equals:([Ljava/lang/Object;[Ljava/lang/Object;)Z
     121: ifeq          156
     124: aload_0
     125: getfield      #9                  // Field methodName:Ljava/lang/String;
     128: aload_2
     129: getfield      #9                  // Field methodName:Ljava/lang/String;
     132: invokestatic  #64                 // Method java/util/Objects.equals:(Ljava/lang/Object;Ljava/lang/Object;)Z
     135: ifeq          156
     138: aload_0
     139: getfield      #6                  // Field attributeMap:Ljava/util/concurrent/ConcurrentMap;
     142: aload_2
     143: getfield      #6                  // Field attributeMap:Ljava/util/concurrent/ConcurrentMap;
     146: invokestatic  #64                 // Method java/util/Objects.equals:(Ljava/lang/Object;Ljava/lang/Object;)Z
     149: ifeq          156
     152: iconst_1
     153: goto          157
     156: iconst_0
     157: ireturn

  public int hashCode();
    Code:
       0: bipush        6
       2: anewarray     #66                 // class java/lang/Object
       5: dup
       6: iconst_0
       7: aload_0
       8: getfield      #7                  // Field method:Ljava/lang/reflect/Method;
      11: aastore
      12: dup
      13: iconst_1
      14: aload_0
      15: getfield      #31                 // Field paramDesc:Ljava/lang/String;
      18: aastore
      19: dup
      20: iconst_2
      21: aload_0
      22: getfield      #13                 // Field returnClass:Ljava/lang/Class;
      25: aastore
      26: dup
      27: iconst_3
      28: aload_0
      29: getfield      #9                  // Field methodName:Ljava/lang/String;
      32: aastore
      33: dup
      34: iconst_4
      35: aload_0
      36: getfield      #42                 // Field generic:Z
      39: invokestatic  #67                 // Method java/lang/Boolean.valueOf:(Z)Ljava/lang/Boolean;
      42: aastore
      43: dup
      44: iconst_5
      45: aload_0
      46: getfield      #6                  // Field attributeMap:Ljava/util/concurrent/ConcurrentMap;
      49: aastore
      50: invokestatic  #68                 // Method java/util/Objects.hash:([Ljava/lang/Object;)I
      53: istore_1
      54: bipush        31
      56: iload_1
      57: imul
      58: aload_0
      59: getfield      #38                 // Field compatibleParamSignatures:[Ljava/lang/String;
      62: invokestatic  #69                 // Method java/util/Arrays.hashCode:([Ljava/lang/Object;)I
      65: iadd
      66: istore_1
      67: bipush        31
      69: iload_1
      70: imul
      71: aload_0
      72: getfield      #11                 // Field parameterClasses:[Ljava/lang/Class;
      75: invokestatic  #69                 // Method java/util/Arrays.hashCode:([Ljava/lang/Object;)I
      78: iadd
      79: istore_1
      80: bipush        31
      82: iload_1
      83: imul
      84: aload_0
      85: getfield      #29                 // Field returnTypes:[Ljava/lang/reflect/Type;
      88: invokestatic  #69                 // Method java/util/Arrays.hashCode:([Ljava/lang/Object;)I
      91: iadd
      92: istore_1
      93: iload_1
      94: ireturn

  private static java.lang.String[] lambda$new$0(int);
    Code:
       0: iload_0
       1: anewarray     #70                 // class java/lang/String
       4: areturn

  static {};
    Code:
       0: ldc           #63                 // class org/apache/dubbo/rpc/model/ReflectionMethodDescriptor
       2: invokestatic  #71                 // Method org/apache/dubbo/common/logger/LoggerFactory.getErrorTypeAwareLogger:(Ljava/lang/Class;)Lorg/apache/dubbo/common/logger/ErrorTypeAwareLogger;
       5: putstatic     #16                 // Field logger:Lorg/apache/dubbo/common/logger/ErrorTypeAwareLogger;
       8: return
}
