Compiled from "ScopeModelAccessor.java"
public interface org.apache.dubbo.rpc.model.ScopeModelAccessor {
  public abstract org.apache.dubbo.rpc.model.ScopeModel getScopeModel();

  public default org.apache.dubbo.rpc.model.FrameworkModel getFrameworkModel();
    Code:
       0: aload_0
       1: invokeinterface #1,  1            // InterfaceMethod getScopeModel:()Lorg/apache/dubbo/rpc/model/ScopeModel;
       6: invokestatic  #2                  // Method org/apache/dubbo/rpc/model/ScopeModelUtil.getFrameworkModel:(Lorg/apache/dubbo/rpc/model/ScopeModel;)Lorg/apache/dubbo/rpc/model/FrameworkModel;
       9: areturn

  public default org.apache.dubbo.rpc.model.ApplicationModel getApplicationModel();
    Code:
       0: aload_0
       1: invokeinterface #1,  1            // InterfaceMethod getScopeModel:()Lorg/apache/dubbo/rpc/model/ScopeModel;
       6: invokestatic  #3                  // Method org/apache/dubbo/rpc/model/ScopeModelUtil.getApplicationModel:(Lorg/apache/dubbo/rpc/model/ScopeModel;)Lorg/apache/dubbo/rpc/model/ApplicationModel;
       9: areturn

  public default org.apache.dubbo.rpc.model.ModuleModel getModuleModel();
    Code:
       0: aload_0
       1: invokeinterface #1,  1            // InterfaceMethod getScopeModel:()Lorg/apache/dubbo/rpc/model/ScopeModel;
       6: invokestatic  #4                  // Method org/apache/dubbo/rpc/model/ScopeModelUtil.getModuleModel:(Lorg/apache/dubbo/rpc/model/ScopeModel;)Lorg/apache/dubbo/rpc/model/ModuleModel;
       9: areturn
}
