Compiled from "ScopeModelAwareExtensionProcessor.java"
public class org.apache.dubbo.rpc.model.ScopeModelAwareExtensionProcessor implements org.apache.dubbo.common.extension.ExtensionPostProcessor,org.apache.dubbo.rpc.model.ScopeModelAccessor {
  private org.apache.dubbo.rpc.model.ScopeModel scopeModel;

  private org.apache.dubbo.rpc.model.FrameworkModel frameworkModel;

  private org.apache.dubbo.rpc.model.ApplicationModel applicationModel;

  private org.apache.dubbo.rpc.model.ModuleModel moduleModel;

  public org.apache.dubbo.rpc.model.ScopeModelAwareExtensionProcessor(org.apache.dubbo.rpc.model.ScopeModel);
    Code:
       0: aload_0
       1: invokespecial #1                  // Method java/lang/Object."<init>":()V
       4: aload_0
       5: aload_1
       6: putfield      #2                  // Field scopeModel:Lorg/apache/dubbo/rpc/model/ScopeModel;
       9: aload_0
      10: invokespecial #3                  // Method initialize:()V
      13: return

  private void initialize();
    Code:
       0: aload_0
       1: getfield      #2                  // Field scopeModel:Lorg/apache/dubbo/rpc/model/ScopeModel;
       4: instanceof    #4                  // class org/apache/dubbo/rpc/model/FrameworkModel
       7: ifeq          24
      10: aload_0
      11: aload_0
      12: getfield      #2                  // Field scopeModel:Lorg/apache/dubbo/rpc/model/ScopeModel;
      15: checkcast     #4                  // class org/apache/dubbo/rpc/model/FrameworkModel
      18: putfield      #5                  // Field frameworkModel:Lorg/apache/dubbo/rpc/model/FrameworkModel;
      21: goto          102
      24: aload_0
      25: getfield      #2                  // Field scopeModel:Lorg/apache/dubbo/rpc/model/ScopeModel;
      28: instanceof    #6                  // class org/apache/dubbo/rpc/model/ApplicationModel
      31: ifeq          59
      34: aload_0
      35: aload_0
      36: getfield      #2                  // Field scopeModel:Lorg/apache/dubbo/rpc/model/ScopeModel;
      39: checkcast     #6                  // class org/apache/dubbo/rpc/model/ApplicationModel
      42: putfield      #7                  // Field applicationModel:Lorg/apache/dubbo/rpc/model/ApplicationModel;
      45: aload_0
      46: aload_0
      47: getfield      #7                  // Field applicationModel:Lorg/apache/dubbo/rpc/model/ApplicationModel;
      50: invokevirtual #8                  // Method org/apache/dubbo/rpc/model/ApplicationModel.getFrameworkModel:()Lorg/apache/dubbo/rpc/model/FrameworkModel;
      53: putfield      #5                  // Field frameworkModel:Lorg/apache/dubbo/rpc/model/FrameworkModel;
      56: goto          102
      59: aload_0
      60: getfield      #2                  // Field scopeModel:Lorg/apache/dubbo/rpc/model/ScopeModel;
      63: instanceof    #9                  // class org/apache/dubbo/rpc/model/ModuleModel
      66: ifeq          102
      69: aload_0
      70: aload_0
      71: getfield      #2                  // Field scopeModel:Lorg/apache/dubbo/rpc/model/ScopeModel;
      74: checkcast     #9                  // class org/apache/dubbo/rpc/model/ModuleModel
      77: putfield      #10                 // Field moduleModel:Lorg/apache/dubbo/rpc/model/ModuleModel;
      80: aload_0
      81: aload_0
      82: getfield      #10                 // Field moduleModel:Lorg/apache/dubbo/rpc/model/ModuleModel;
      85: invokevirtual #11                 // Method org/apache/dubbo/rpc/model/ModuleModel.getApplicationModel:()Lorg/apache/dubbo/rpc/model/ApplicationModel;
      88: putfield      #7                  // Field applicationModel:Lorg/apache/dubbo/rpc/model/ApplicationModel;
      91: aload_0
      92: aload_0
      93: getfield      #7                  // Field applicationModel:Lorg/apache/dubbo/rpc/model/ApplicationModel;
      96: invokevirtual #8                  // Method org/apache/dubbo/rpc/model/ApplicationModel.getFrameworkModel:()Lorg/apache/dubbo/rpc/model/FrameworkModel;
      99: putfield      #5                  // Field frameworkModel:Lorg/apache/dubbo/rpc/model/FrameworkModel;
     102: return

  public java.lang.Object postProcessAfterInitialization(java.lang.Object, java.lang.String) throws java.lang.Exception;
    Code:
       0: aload_1
       1: instanceof    #12                 // class org/apache/dubbo/rpc/model/ScopeModelAware
       4: ifeq          73
       7: aload_1
       8: checkcast     #12                 // class org/apache/dubbo/rpc/model/ScopeModelAware
      11: astore_3
      12: aload_3
      13: aload_0
      14: getfield      #2                  // Field scopeModel:Lorg/apache/dubbo/rpc/model/ScopeModel;
      17: invokeinterface #13,  2           // InterfaceMethod org/apache/dubbo/rpc/model/ScopeModelAware.setScopeModel:(Lorg/apache/dubbo/rpc/model/ScopeModel;)V
      22: aload_0
      23: getfield      #10                 // Field moduleModel:Lorg/apache/dubbo/rpc/model/ModuleModel;
      26: ifnull        39
      29: aload_3
      30: aload_0
      31: getfield      #10                 // Field moduleModel:Lorg/apache/dubbo/rpc/model/ModuleModel;
      34: invokeinterface #14,  2           // InterfaceMethod org/apache/dubbo/rpc/model/ScopeModelAware.setModuleModel:(Lorg/apache/dubbo/rpc/model/ModuleModel;)V
      39: aload_0
      40: getfield      #7                  // Field applicationModel:Lorg/apache/dubbo/rpc/model/ApplicationModel;
      43: ifnull        56
      46: aload_3
      47: aload_0
      48: getfield      #7                  // Field applicationModel:Lorg/apache/dubbo/rpc/model/ApplicationModel;
      51: invokeinterface #15,  2           // InterfaceMethod org/apache/dubbo/rpc/model/ScopeModelAware.setApplicationModel:(Lorg/apache/dubbo/rpc/model/ApplicationModel;)V
      56: aload_0
      57: getfield      #5                  // Field frameworkModel:Lorg/apache/dubbo/rpc/model/FrameworkModel;
      60: ifnull        73
      63: aload_3
      64: aload_0
      65: getfield      #5                  // Field frameworkModel:Lorg/apache/dubbo/rpc/model/FrameworkModel;
      68: invokeinterface #16,  2           // InterfaceMethod org/apache/dubbo/rpc/model/ScopeModelAware.setFrameworkModel:(Lorg/apache/dubbo/rpc/model/FrameworkModel;)V
      73: aload_1
      74: areturn

  public org.apache.dubbo.rpc.model.ScopeModel getScopeModel();
    Code:
       0: aload_0
       1: getfield      #2                  // Field scopeModel:Lorg/apache/dubbo/rpc/model/ScopeModel;
       4: areturn

  public org.apache.dubbo.rpc.model.FrameworkModel getFrameworkModel();
    Code:
       0: aload_0
       1: getfield      #5                  // Field frameworkModel:Lorg/apache/dubbo/rpc/model/FrameworkModel;
       4: areturn

  public org.apache.dubbo.rpc.model.ApplicationModel getApplicationModel();
    Code:
       0: aload_0
       1: getfield      #7                  // Field applicationModel:Lorg/apache/dubbo/rpc/model/ApplicationModel;
       4: areturn

  public org.apache.dubbo.rpc.model.ModuleModel getModuleModel();
    Code:
       0: aload_0
       1: getfield      #10                 // Field moduleModel:Lorg/apache/dubbo/rpc/model/ModuleModel;
       4: areturn
}
