Compiled from "ScopeModel.java"
public abstract class org.apache.dubbo.rpc.model.ScopeModel implements org.apache.dubbo.common.extension.ExtensionAccessor {
  protected static final org.apache.dubbo.common.logger.ErrorTypeAwareLogger LOGGER;

  private java.lang.String internalId;

  private java.lang.String modelName;

  private java.lang.String desc;

  private final java.util.Set<java.lang.ClassLoader> classLoaders;

  private final org.apache.dubbo.rpc.model.ScopeModel parent;

  private final org.apache.dubbo.common.extension.ExtensionScope scope;

  private volatile org.apache.dubbo.common.extension.ExtensionDirector extensionDirector;

  private volatile org.apache.dubbo.common.beans.factory.ScopeBeanFactory beanFactory;

  private final java.util.List<org.apache.dubbo.rpc.model.ScopeModelDestroyListener> destroyListeners;

  private final java.util.List<org.apache.dubbo.rpc.model.ScopeClassLoaderListener> classLoaderListeners;

  private final java.util.Map<java.lang.String, java.lang.Object> attributes;

  private final java.util.concurrent.atomic.AtomicBoolean destroyed;

  private final boolean internalScope;

  protected final java.lang.Object instLock;

  protected org.apache.dubbo.rpc.model.ScopeModel(org.apache.dubbo.rpc.model.ScopeModel, org.apache.dubbo.common.extension.ExtensionScope, boolean);
    Code:
       0: aload_0
       1: invokespecial #2                  // Method java/lang/Object."<init>":()V
       4: aload_0
       5: new           #3                  // class org/apache/dubbo/common/utils/ConcurrentHashSet
       8: dup
       9: invokespecial #4                  // Method org/apache/dubbo/common/utils/ConcurrentHashSet."<init>":()V
      12: putfield      #5                  // Field classLoaders:Ljava/util/Set;
      15: aload_0
      16: new           #6                  // class java/util/concurrent/CopyOnWriteArrayList
      19: dup
      20: invokespecial #7                  // Method java/util/concurrent/CopyOnWriteArrayList."<init>":()V
      23: putfield      #8                  // Field destroyListeners:Ljava/util/List;
      26: aload_0
      27: new           #6                  // class java/util/concurrent/CopyOnWriteArrayList
      30: dup
      31: invokespecial #7                  // Method java/util/concurrent/CopyOnWriteArrayList."<init>":()V
      34: putfield      #9                  // Field classLoaderListeners:Ljava/util/List;
      37: aload_0
      38: new           #10                 // class java/util/concurrent/ConcurrentHashMap
      41: dup
      42: invokespecial #11                 // Method java/util/concurrent/ConcurrentHashMap."<init>":()V
      45: putfield      #12                 // Field attributes:Ljava/util/Map;
      48: aload_0
      49: new           #13                 // class java/util/concurrent/atomic/AtomicBoolean
      52: dup
      53: iconst_0
      54: invokespecial #14                 // Method java/util/concurrent/atomic/AtomicBoolean."<init>":(Z)V
      57: putfield      #15                 // Field destroyed:Ljava/util/concurrent/atomic/AtomicBoolean;
      60: aload_0
      61: new           #16                 // class java/lang/Object
      64: dup
      65: invokespecial #2                  // Method java/lang/Object."<init>":()V
      68: putfield      #17                 // Field instLock:Ljava/lang/Object;
      71: aload_0
      72: aload_1
      73: putfield      #18                 // Field parent:Lorg/apache/dubbo/rpc/model/ScopeModel;
      76: aload_0
      77: aload_2
      78: putfield      #19                 // Field scope:Lorg/apache/dubbo/common/extension/ExtensionScope;
      81: aload_0
      82: iload_3
      83: putfield      #20                 // Field internalScope:Z
      86: return

  protected void initialize();
    Code:
       0: aload_0
       1: getfield      #17                 // Field instLock:Ljava/lang/Object;
       4: dup
       5: astore_1
       6: monitorenter
       7: aload_0
       8: new           #21                 // class org/apache/dubbo/common/extension/ExtensionDirector
      11: dup
      12: aload_0
      13: getfield      #18                 // Field parent:Lorg/apache/dubbo/rpc/model/ScopeModel;
      16: ifnull        29
      19: aload_0
      20: getfield      #18                 // Field parent:Lorg/apache/dubbo/rpc/model/ScopeModel;
      23: invokevirtual #22                 // Method getExtensionDirector:()Lorg/apache/dubbo/common/extension/ExtensionDirector;
      26: goto          30
      29: aconst_null
      30: aload_0
      31: getfield      #19                 // Field scope:Lorg/apache/dubbo/common/extension/ExtensionScope;
      34: aload_0
      35: invokespecial #23                 // Method org/apache/dubbo/common/extension/ExtensionDirector."<init>":(Lorg/apache/dubbo/common/extension/ExtensionDirector;Lorg/apache/dubbo/common/extension/ExtensionScope;Lorg/apache/dubbo/rpc/model/ScopeModel;)V
      38: putfield      #24                 // Field extensionDirector:Lorg/apache/dubbo/common/extension/ExtensionDirector;
      41: aload_0
      42: getfield      #24                 // Field extensionDirector:Lorg/apache/dubbo/common/extension/ExtensionDirector;
      45: new           #25                 // class org/apache/dubbo/rpc/model/ScopeModelAwareExtensionProcessor
      48: dup
      49: aload_0
      50: invokespecial #26                 // Method org/apache/dubbo/rpc/model/ScopeModelAwareExtensionProcessor."<init>":(Lorg/apache/dubbo/rpc/model/ScopeModel;)V
      53: invokevirtual #27                 // Method org/apache/dubbo/common/extension/ExtensionDirector.addExtensionPostProcessor:(Lorg/apache/dubbo/common/extension/ExtensionPostProcessor;)V
      56: aload_0
      57: new           #28                 // class org/apache/dubbo/common/beans/factory/ScopeBeanFactory
      60: dup
      61: aload_0
      62: getfield      #18                 // Field parent:Lorg/apache/dubbo/rpc/model/ScopeModel;
      65: ifnull        78
      68: aload_0
      69: getfield      #18                 // Field parent:Lorg/apache/dubbo/rpc/model/ScopeModel;
      72: invokevirtual #29                 // Method getBeanFactory:()Lorg/apache/dubbo/common/beans/factory/ScopeBeanFactory;
      75: goto          79
      78: aconst_null
      79: aload_0
      80: getfield      #24                 // Field extensionDirector:Lorg/apache/dubbo/common/extension/ExtensionDirector;
      83: invokespecial #30                 // Method org/apache/dubbo/common/beans/factory/ScopeBeanFactory."<init>":(Lorg/apache/dubbo/common/beans/factory/ScopeBeanFactory;Lorg/apache/dubbo/common/extension/ExtensionAccessor;)V
      86: putfield      #31                 // Field beanFactory:Lorg/apache/dubbo/common/beans/factory/ScopeBeanFactory;
      89: ldc           #32                 // class org/apache/dubbo/rpc/model/ScopeModel
      91: invokevirtual #33                 // Method java/lang/Class.getClassLoader:()Ljava/lang/ClassLoader;
      94: astore_2
      95: aload_2
      96: ifnull        104
      99: aload_0
     100: aload_2
     101: invokevirtual #34                 // Method addClassLoader:(Ljava/lang/ClassLoader;)V
     104: aload_1
     105: monitorexit
     106: goto          114
     109: astore_3
     110: aload_1
     111: monitorexit
     112: aload_3
     113: athrow
     114: return
    Exception table:
       from    to  target type
           7   106   109   any
         109   112   109   any

  protected abstract java.util.concurrent.locks.Lock acquireDestroyLock();

  public void destroy();
    Code:
       0: aload_0
       1: invokevirtual #35                 // Method acquireDestroyLock:()Ljava/util/concurrent/locks/Lock;
       4: astore_1
       5: aload_1
       6: invokeinterface #36,  1           // InterfaceMethod java/util/concurrent/locks/Lock.lock:()V
      11: aload_0
      12: getfield      #15                 // Field destroyed:Ljava/util/concurrent/atomic/AtomicBoolean;
      15: iconst_0
      16: iconst_1
      17: invokevirtual #37                 // Method java/util/concurrent/atomic/AtomicBoolean.compareAndSet:(ZZ)Z
      20: ifeq          122
      23: aload_0
      24: invokevirtual #38                 // Method onDestroy:()V
      27: new           #39                 // class java/util/HashSet
      30: dup
      31: aload_0
      32: getfield      #5                  // Field classLoaders:Ljava/util/Set;
      35: invokespecial #40                 // Method java/util/HashSet."<init>":(Ljava/util/Collection;)V
      38: astore_2
      39: aload_2
      40: invokevirtual #41                 // Method java/util/HashSet.iterator:()Ljava/util/Iterator;
      43: astore_3
      44: aload_3
      45: invokeinterface #42,  1           // InterfaceMethod java/util/Iterator.hasNext:()Z
      50: ifeq          73
      53: aload_3
      54: invokeinterface #43,  1           // InterfaceMethod java/util/Iterator.next:()Ljava/lang/Object;
      59: checkcast     #44                 // class java/lang/ClassLoader
      62: astore        4
      64: aload_0
      65: aload         4
      67: invokevirtual #45                 // Method removeClassLoader:(Ljava/lang/ClassLoader;)V
      70: goto          44
      73: aload_0
      74: getfield      #31                 // Field beanFactory:Lorg/apache/dubbo/common/beans/factory/ScopeBeanFactory;
      77: ifnull        87
      80: aload_0
      81: getfield      #31                 // Field beanFactory:Lorg/apache/dubbo/common/beans/factory/ScopeBeanFactory;
      84: invokevirtual #46                 // Method org/apache/dubbo/common/beans/factory/ScopeBeanFactory.destroy:()V
      87: aload_0
      88: getfield      #24                 // Field extensionDirector:Lorg/apache/dubbo/common/extension/ExtensionDirector;
      91: ifnull        101
      94: aload_0
      95: getfield      #24                 // Field extensionDirector:Lorg/apache/dubbo/common/extension/ExtensionDirector;
      98: invokevirtual #47                 // Method org/apache/dubbo/common/extension/ExtensionDirector.destroy:()V
     101: goto          122
     104: astore_2
     105: getstatic     #49                 // Field LOGGER:Lorg/apache/dubbo/common/logger/ErrorTypeAwareLogger;
     108: ldc           #50                 // String 5-13
     110: ldc           #51                 // String
     112: ldc           #51                 // String
     114: ldc           #52                 // String Error happened when destroying ScopeModel.
     116: aload_2
     117: invokeinterface #53,  6           // InterfaceMethod org/apache/dubbo/common/logger/ErrorTypeAwareLogger.error:(Ljava/lang/String;Ljava/lang/String;Ljava/lang/String;Ljava/lang/String;Ljava/lang/Throwable;)V
     122: aload_1
     123: invokeinterface #54,  1           // InterfaceMethod java/util/concurrent/locks/Lock.unlock:()V
     128: goto          142
     131: astore        5
     133: aload_1
     134: invokeinterface #54,  1           // InterfaceMethod java/util/concurrent/locks/Lock.unlock:()V
     139: aload         5
     141: athrow
     142: return
    Exception table:
       from    to  target type
          23   101   104   Class java/lang/Throwable
           5   122   131   any
         131   133   131   any

  public boolean isDestroyed();
    Code:
       0: aload_0
       1: getfield      #15                 // Field destroyed:Ljava/util/concurrent/atomic/AtomicBoolean;
       4: invokevirtual #55                 // Method java/util/concurrent/atomic/AtomicBoolean.get:()Z
       7: ireturn

  protected void notifyDestroy();
    Code:
       0: aload_0
       1: getfield      #8                  // Field destroyListeners:Ljava/util/List;
       4: invokeinterface #56,  1           // InterfaceMethod java/util/List.iterator:()Ljava/util/Iterator;
       9: astore_1
      10: aload_1
      11: invokeinterface #42,  1           // InterfaceMethod java/util/Iterator.hasNext:()Z
      16: ifeq          39
      19: aload_1
      20: invokeinterface #43,  1           // InterfaceMethod java/util/Iterator.next:()Ljava/lang/Object;
      25: checkcast     #57                 // class org/apache/dubbo/rpc/model/ScopeModelDestroyListener
      28: astore_2
      29: aload_2
      30: aload_0
      31: invokeinterface #58,  2           // InterfaceMethod org/apache/dubbo/rpc/model/ScopeModelDestroyListener.onDestroy:(Lorg/apache/dubbo/rpc/model/ScopeModel;)V
      36: goto          10
      39: return

  protected void notifyProtocolDestroy();
    Code:
       0: aload_0
       1: getfield      #8                  // Field destroyListeners:Ljava/util/List;
       4: invokeinterface #56,  1           // InterfaceMethod java/util/List.iterator:()Ljava/util/Iterator;
       9: astore_1
      10: aload_1
      11: invokeinterface #42,  1           // InterfaceMethod java/util/Iterator.hasNext:()Z
      16: ifeq          48
      19: aload_1
      20: invokeinterface #43,  1           // InterfaceMethod java/util/Iterator.next:()Ljava/lang/Object;
      25: checkcast     #57                 // class org/apache/dubbo/rpc/model/ScopeModelDestroyListener
      28: astore_2
      29: aload_2
      30: invokeinterface #59,  1           // InterfaceMethod org/apache/dubbo/rpc/model/ScopeModelDestroyListener.isProtocol:()Z
      35: ifeq          45
      38: aload_2
      39: aload_0
      40: invokeinterface #58,  2           // InterfaceMethod org/apache/dubbo/rpc/model/ScopeModelDestroyListener.onDestroy:(Lorg/apache/dubbo/rpc/model/ScopeModel;)V
      45: goto          10
      48: return

  protected void notifyClassLoaderAdd(java.lang.ClassLoader);
    Code:
       0: aload_0
       1: getfield      #9                  // Field classLoaderListeners:Ljava/util/List;
       4: invokeinterface #56,  1           // InterfaceMethod java/util/List.iterator:()Ljava/util/Iterator;
       9: astore_2
      10: aload_2
      11: invokeinterface #42,  1           // InterfaceMethod java/util/Iterator.hasNext:()Z
      16: ifeq          40
      19: aload_2
      20: invokeinterface #43,  1           // InterfaceMethod java/util/Iterator.next:()Ljava/lang/Object;
      25: checkcast     #60                 // class org/apache/dubbo/rpc/model/ScopeClassLoaderListener
      28: astore_3
      29: aload_3
      30: aload_0
      31: aload_1
      32: invokeinterface #61,  3           // InterfaceMethod org/apache/dubbo/rpc/model/ScopeClassLoaderListener.onAddClassLoader:(Lorg/apache/dubbo/rpc/model/ScopeModel;Ljava/lang/ClassLoader;)V
      37: goto          10
      40: return

  protected void notifyClassLoaderDestroy(java.lang.ClassLoader);
    Code:
       0: aload_0
       1: getfield      #9                  // Field classLoaderListeners:Ljava/util/List;
       4: invokeinterface #56,  1           // InterfaceMethod java/util/List.iterator:()Ljava/util/Iterator;
       9: astore_2
      10: aload_2
      11: invokeinterface #42,  1           // InterfaceMethod java/util/Iterator.hasNext:()Z
      16: ifeq          40
      19: aload_2
      20: invokeinterface #43,  1           // InterfaceMethod java/util/Iterator.next:()Ljava/lang/Object;
      25: checkcast     #60                 // class org/apache/dubbo/rpc/model/ScopeClassLoaderListener
      28: astore_3
      29: aload_3
      30: aload_0
      31: aload_1
      32: invokeinterface #62,  3           // InterfaceMethod org/apache/dubbo/rpc/model/ScopeClassLoaderListener.onRemoveClassLoader:(Lorg/apache/dubbo/rpc/model/ScopeModel;Ljava/lang/ClassLoader;)V
      37: goto          10
      40: return

  protected abstract void onDestroy();

  public final void addDestroyListener(org.apache.dubbo.rpc.model.ScopeModelDestroyListener);
    Code:
       0: aload_0
       1: getfield      #8                  // Field destroyListeners:Ljava/util/List;
       4: aload_1
       5: invokeinterface #63,  2           // InterfaceMethod java/util/List.add:(Ljava/lang/Object;)Z
      10: pop
      11: return

  public final void addClassLoaderListener(org.apache.dubbo.rpc.model.ScopeClassLoaderListener);
    Code:
       0: aload_0
       1: getfield      #9                  // Field classLoaderListeners:Ljava/util/List;
       4: aload_1
       5: invokeinterface #63,  2           // InterfaceMethod java/util/List.add:(Ljava/lang/Object;)Z
      10: pop
      11: return

  public java.util.Map<java.lang.String, java.lang.Object> getAttributes();
    Code:
       0: aload_0
       1: getfield      #12                 // Field attributes:Ljava/util/Map;
       4: areturn

  public <T> T getAttribute(java.lang.String, java.lang.Class<T>);
    Code:
       0: aload_0
       1: getfield      #12                 // Field attributes:Ljava/util/Map;
       4: aload_1
       5: invokeinterface #64,  2           // InterfaceMethod java/util/Map.get:(Ljava/lang/Object;)Ljava/lang/Object;
      10: areturn

  public java.lang.Object getAttribute(java.lang.String);
    Code:
       0: aload_0
       1: getfield      #12                 // Field attributes:Ljava/util/Map;
       4: aload_1
       5: invokeinterface #64,  2           // InterfaceMethod java/util/Map.get:(Ljava/lang/Object;)Ljava/lang/Object;
      10: areturn

  public void setAttribute(java.lang.String, java.lang.Object);
    Code:
       0: aload_0
       1: getfield      #12                 // Field attributes:Ljava/util/Map;
       4: aload_1
       5: aload_2
       6: invokeinterface #65,  3           // InterfaceMethod java/util/Map.put:(Ljava/lang/Object;Ljava/lang/Object;)Ljava/lang/Object;
      11: pop
      12: return

  public org.apache.dubbo.common.extension.ExtensionDirector getExtensionDirector();
    Code:
       0: aload_0
       1: getfield      #24                 // Field extensionDirector:Lorg/apache/dubbo/common/extension/ExtensionDirector;
       4: areturn

  public org.apache.dubbo.common.beans.factory.ScopeBeanFactory getBeanFactory();
    Code:
       0: aload_0
       1: getfield      #31                 // Field beanFactory:Lorg/apache/dubbo/common/beans/factory/ScopeBeanFactory;
       4: areturn

  public org.apache.dubbo.rpc.model.ScopeModel getParent();
    Code:
       0: aload_0
       1: getfield      #18                 // Field parent:Lorg/apache/dubbo/rpc/model/ScopeModel;
       4: areturn

  public org.apache.dubbo.common.extension.ExtensionScope getScope();
    Code:
       0: aload_0
       1: getfield      #19                 // Field scope:Lorg/apache/dubbo/common/extension/ExtensionScope;
       4: areturn

  public void addClassLoader(java.lang.ClassLoader);
    Code:
       0: aload_0
       1: getfield      #17                 // Field instLock:Ljava/lang/Object;
       4: dup
       5: astore_2
       6: monitorenter
       7: aload_0
       8: getfield      #5                  // Field classLoaders:Ljava/util/Set;
      11: aload_1
      12: invokeinterface #66,  2           // InterfaceMethod java/util/Set.add:(Ljava/lang/Object;)Z
      17: pop
      18: aload_0
      19: getfield      #18                 // Field parent:Lorg/apache/dubbo/rpc/model/ScopeModel;
      22: ifnull        33
      25: aload_0
      26: getfield      #18                 // Field parent:Lorg/apache/dubbo/rpc/model/ScopeModel;
      29: aload_1
      30: invokevirtual #34                 // Method addClassLoader:(Ljava/lang/ClassLoader;)V
      33: aload_0
      34: getfield      #24                 // Field extensionDirector:Lorg/apache/dubbo/common/extension/ExtensionDirector;
      37: invokevirtual #67                 // Method org/apache/dubbo/common/extension/ExtensionDirector.removeAllCachedLoader:()V
      40: aload_0
      41: aload_1
      42: invokevirtual #68                 // Method notifyClassLoaderAdd:(Ljava/lang/ClassLoader;)V
      45: aload_2
      46: monitorexit
      47: goto          55
      50: astore_3
      51: aload_2
      52: monitorexit
      53: aload_3
      54: athrow
      55: return
    Exception table:
       from    to  target type
           7    47    50   any
          50    53    50   any

  public void removeClassLoader(java.lang.ClassLoader);
    Code:
       0: aload_0
       1: getfield      #17                 // Field instLock:Ljava/lang/Object;
       4: dup
       5: astore_2
       6: monitorenter
       7: aload_0
       8: aload_1
       9: invokevirtual #69                 // Method checkIfClassLoaderCanRemoved:(Ljava/lang/ClassLoader;)Z
      12: ifeq          53
      15: aload_0
      16: getfield      #5                  // Field classLoaders:Ljava/util/Set;
      19: aload_1
      20: invokeinterface #70,  2           // InterfaceMethod java/util/Set.remove:(Ljava/lang/Object;)Z
      25: pop
      26: aload_0
      27: getfield      #18                 // Field parent:Lorg/apache/dubbo/rpc/model/ScopeModel;
      30: ifnull        41
      33: aload_0
      34: getfield      #18                 // Field parent:Lorg/apache/dubbo/rpc/model/ScopeModel;
      37: aload_1
      38: invokevirtual #45                 // Method removeClassLoader:(Ljava/lang/ClassLoader;)V
      41: aload_0
      42: getfield      #24                 // Field extensionDirector:Lorg/apache/dubbo/common/extension/ExtensionDirector;
      45: invokevirtual #67                 // Method org/apache/dubbo/common/extension/ExtensionDirector.removeAllCachedLoader:()V
      48: aload_0
      49: aload_1
      50: invokevirtual #71                 // Method notifyClassLoaderDestroy:(Ljava/lang/ClassLoader;)V
      53: aload_2
      54: monitorexit
      55: goto          63
      58: astore_3
      59: aload_2
      60: monitorexit
      61: aload_3
      62: athrow
      63: return
    Exception table:
       from    to  target type
           7    55    58   any
          58    61    58   any

  protected boolean checkIfClassLoaderCanRemoved(java.lang.ClassLoader);
    Code:
       0: aload_1
       1: ifnull        20
       4: aload_1
       5: ldc           #32                 // class org/apache/dubbo/rpc/model/ScopeModel
       7: invokevirtual #33                 // Method java/lang/Class.getClassLoader:()Ljava/lang/ClassLoader;
      10: invokevirtual #72                 // Method java/lang/Object.equals:(Ljava/lang/Object;)Z
      13: ifne          20
      16: iconst_1
      17: goto          21
      20: iconst_0
      21: ireturn

  public java.util.Set<java.lang.ClassLoader> getClassLoaders();
    Code:
       0: aload_0
       1: getfield      #5                  // Field classLoaders:Ljava/util/Set;
       4: invokestatic  #73                 // Method java/util/Collections.unmodifiableSet:(Ljava/util/Set;)Ljava/util/Set;
       7: areturn

  public abstract org.apache.dubbo.common.config.Environment getModelEnvironment();

  public java.lang.String getInternalId();
    Code:
       0: aload_0
       1: getfield      #74                 // Field internalId:Ljava/lang/String;
       4: areturn

  void setInternalId(java.lang.String);
    Code:
       0: aload_0
       1: aload_1
       2: putfield      #74                 // Field internalId:Ljava/lang/String;
       5: return

  protected java.lang.String buildInternalId(java.lang.String, long);
    Code:
       0: aload_1
       1: invokestatic  #75                 // Method org/apache/dubbo/common/utils/StringUtils.hasText:(Ljava/lang/CharSequence;)Z
       4: ifeq          31
       7: new           #76                 // class java/lang/StringBuilder
      10: dup
      11: invokespecial #77                 // Method java/lang/StringBuilder."<init>":()V
      14: aload_1
      15: invokevirtual #78                 // Method java/lang/StringBuilder.append:(Ljava/lang/String;)Ljava/lang/StringBuilder;
      18: ldc           #79                 // String .
      20: invokevirtual #78                 // Method java/lang/StringBuilder.append:(Ljava/lang/String;)Ljava/lang/StringBuilder;
      23: lload_2
      24: invokevirtual #80                 // Method java/lang/StringBuilder.append:(J)Ljava/lang/StringBuilder;
      27: invokevirtual #81                 // Method java/lang/StringBuilder.toString:()Ljava/lang/String;
      30: areturn
      31: new           #76                 // class java/lang/StringBuilder
      34: dup
      35: invokespecial #77                 // Method java/lang/StringBuilder."<init>":()V
      38: ldc           #51                 // String
      40: invokevirtual #78                 // Method java/lang/StringBuilder.append:(Ljava/lang/String;)Ljava/lang/StringBuilder;
      43: lload_2
      44: invokevirtual #80                 // Method java/lang/StringBuilder.append:(J)Ljava/lang/StringBuilder;
      47: invokevirtual #81                 // Method java/lang/StringBuilder.toString:()Ljava/lang/String;
      50: areturn

  public java.lang.String getModelName();
    Code:
       0: aload_0
       1: getfield      #82                 // Field modelName:Ljava/lang/String;
       4: areturn

  public void setModelName(java.lang.String);
    Code:
       0: aload_0
       1: aload_1
       2: putfield      #82                 // Field modelName:Ljava/lang/String;
       5: aload_0
       6: aload_0
       7: invokespecial #83                 // Method buildDesc:()Ljava/lang/String;
      10: putfield      #84                 // Field desc:Ljava/lang/String;
      13: return

  public boolean isInternal();
    Code:
       0: aload_0
       1: getfield      #20                 // Field internalScope:Z
       4: ireturn

  public java.lang.String getDesc();
    Code:
       0: aload_0
       1: getfield      #84                 // Field desc:Ljava/lang/String;
       4: ifnonnull     15
       7: aload_0
       8: aload_0
       9: invokespecial #83                 // Method buildDesc:()Ljava/lang/String;
      12: putfield      #84                 // Field desc:Ljava/lang/String;
      15: aload_0
      16: getfield      #84                 // Field desc:Ljava/lang/String;
      19: areturn

  private java.lang.String buildDesc();
    Code:
       0: aload_0
       1: invokevirtual #85                 // Method java/lang/Object.getClass:()Ljava/lang/Class;
       4: invokevirtual #86                 // Method java/lang/Class.getSimpleName:()Ljava/lang/String;
       7: ldc           #87                 // String Model
       9: ldc           #51                 // String
      11: invokevirtual #88                 // Method java/lang/String.replace:(Ljava/lang/CharSequence;Ljava/lang/CharSequence;)Ljava/lang/String;
      14: astore_1
      15: new           #76                 // class java/lang/StringBuilder
      18: dup
      19: invokespecial #77                 // Method java/lang/StringBuilder."<init>":()V
      22: ldc           #89                 // String Dubbo
      24: invokevirtual #78                 // Method java/lang/StringBuilder.append:(Ljava/lang/String;)Ljava/lang/StringBuilder;
      27: aload_1
      28: invokevirtual #78                 // Method java/lang/StringBuilder.append:(Ljava/lang/String;)Ljava/lang/StringBuilder;
      31: ldc           #90                 // String [
      33: invokevirtual #78                 // Method java/lang/StringBuilder.append:(Ljava/lang/String;)Ljava/lang/StringBuilder;
      36: aload_0
      37: invokevirtual #91                 // Method getInternalId:()Ljava/lang/String;
      40: invokevirtual #78                 // Method java/lang/StringBuilder.append:(Ljava/lang/String;)Ljava/lang/StringBuilder;
      43: ldc           #92                 // String ]
      45: invokevirtual #78                 // Method java/lang/StringBuilder.append:(Ljava/lang/String;)Ljava/lang/StringBuilder;
      48: invokevirtual #81                 // Method java/lang/StringBuilder.toString:()Ljava/lang/String;
      51: astore_2
      52: aload_0
      53: invokespecial #93                 // Method getModelNamePath:()Ljava/lang/String;
      56: astore_3
      57: aload_3
      58: invokestatic  #75                 // Method org/apache/dubbo/common/utils/StringUtils.hasText:(Ljava/lang/CharSequence;)Z
      61: ifeq          93
      64: new           #76                 // class java/lang/StringBuilder
      67: dup
      68: invokespecial #77                 // Method java/lang/StringBuilder."<init>":()V
      71: aload_2
      72: invokevirtual #78                 // Method java/lang/StringBuilder.append:(Ljava/lang/String;)Ljava/lang/StringBuilder;
      75: ldc           #94                 // String (
      77: invokevirtual #78                 // Method java/lang/StringBuilder.append:(Ljava/lang/String;)Ljava/lang/StringBuilder;
      80: aload_3
      81: invokevirtual #78                 // Method java/lang/StringBuilder.append:(Ljava/lang/String;)Ljava/lang/StringBuilder;
      84: ldc           #95                 // String )
      86: invokevirtual #78                 // Method java/lang/StringBuilder.append:(Ljava/lang/String;)Ljava/lang/StringBuilder;
      89: invokevirtual #81                 // Method java/lang/StringBuilder.toString:()Ljava/lang/String;
      92: astore_2
      93: aload_2
      94: areturn

  private java.lang.String getModelNamePath();
    Code:
       0: aload_0
       1: instanceof    #96                 // class org/apache/dubbo/rpc/model/ApplicationModel
       4: ifeq          15
       7: aload_0
       8: checkcast     #96                 // class org/apache/dubbo/rpc/model/ApplicationModel
      11: invokestatic  #97                 // Method safeGetAppName:(Lorg/apache/dubbo/rpc/model/ApplicationModel;)Ljava/lang/String;
      14: areturn
      15: aload_0
      16: instanceof    #98                 // class org/apache/dubbo/rpc/model/ModuleModel
      19: ifeq          67
      22: aload_0
      23: invokevirtual #99                 // Method getModelName:()Ljava/lang/String;
      26: astore_1
      27: aload_1
      28: invokestatic  #75                 // Method org/apache/dubbo/common/utils/StringUtils.hasText:(Ljava/lang/CharSequence;)Z
      31: ifeq          67
      34: new           #76                 // class java/lang/StringBuilder
      37: dup
      38: invokespecial #77                 // Method java/lang/StringBuilder."<init>":()V
      41: aload_0
      42: checkcast     #98                 // class org/apache/dubbo/rpc/model/ModuleModel
      45: invokevirtual #100                // Method org/apache/dubbo/rpc/model/ModuleModel.getApplicationModel:()Lorg/apache/dubbo/rpc/model/ApplicationModel;
      48: invokestatic  #97                 // Method safeGetAppName:(Lorg/apache/dubbo/rpc/model/ApplicationModel;)Ljava/lang/String;
      51: invokevirtual #78                 // Method java/lang/StringBuilder.append:(Ljava/lang/String;)Ljava/lang/StringBuilder;
      54: ldc           #101                // String /
      56: invokevirtual #78                 // Method java/lang/StringBuilder.append:(Ljava/lang/String;)Ljava/lang/StringBuilder;
      59: aload_1
      60: invokevirtual #78                 // Method java/lang/StringBuilder.append:(Ljava/lang/String;)Ljava/lang/StringBuilder;
      63: invokevirtual #81                 // Method java/lang/StringBuilder.toString:()Ljava/lang/String;
      66: areturn
      67: aconst_null
      68: areturn

  private static java.lang.String safeGetAppName(org.apache.dubbo.rpc.model.ApplicationModel);
    Code:
       0: aload_0
       1: invokevirtual #102                // Method org/apache/dubbo/rpc/model/ApplicationModel.getModelName:()Ljava/lang/String;
       4: astore_1
       5: aload_1
       6: invokestatic  #103                // Method org/apache/dubbo/common/utils/StringUtils.isBlank:(Ljava/lang/CharSequence;)Z
       9: ifeq          15
      12: ldc           #104                // String unknown
      14: astore_1
      15: aload_1
      16: areturn

  public java.lang.String toString();
    Code:
       0: aload_0
       1: invokevirtual #105                // Method getDesc:()Ljava/lang/String;
       4: areturn

  static {};
    Code:
       0: ldc           #32                 // class org/apache/dubbo/rpc/model/ScopeModel
       2: invokestatic  #106                // Method org/apache/dubbo/common/logger/LoggerFactory.getErrorTypeAwareLogger:(Ljava/lang/Class;)Lorg/apache/dubbo/common/logger/ErrorTypeAwareLogger;
       5: putstatic     #49                 // Field LOGGER:Lorg/apache/dubbo/common/logger/ErrorTypeAwareLogger;
       8: return
}
