Compiled from "ScopeModelUtil.java"
public class org.apache.dubbo.rpc.model.ScopeModelUtil {
  public org.apache.dubbo.rpc.model.ScopeModelUtil();
    Code:
       0: aload_0
       1: invokespecial #1                  // Method java/lang/Object."<init>":()V
       4: return

  public static <T> org.apache.dubbo.rpc.model.ScopeModel getOrDefault(org.apache.dubbo.rpc.model.ScopeModel, java.lang.Class<T>);
    Code:
       0: aload_0
       1: ifnull        6
       4: aload_0
       5: areturn
       6: aload_1
       7: invokestatic  #2                  // Method getDefaultScopeModel:(Ljava/lang/Class;)Lorg/apache/dubbo/rpc/model/ScopeModel;
      10: areturn

  private static <T> org.apache.dubbo.rpc.model.ScopeModel getDefaultScopeModel(java.lang.Class<T>);
    Code:
       0: aload_0
       1: ldc           #3                  // class org/apache/dubbo/common/extension/SPI
       3: invokevirtual #4                  // Method java/lang/Class.getAnnotation:(Ljava/lang/Class;)Ljava/lang/annotation/Annotation;
       6: checkcast     #3                  // class org/apache/dubbo/common/extension/SPI
       9: astore_1
      10: aload_1
      11: ifnonnull     44
      14: new           #5                  // class java/lang/IllegalArgumentException
      17: dup
      18: new           #6                  // class java/lang/StringBuilder
      21: dup
      22: invokespecial #7                  // Method java/lang/StringBuilder."<init>":()V
      25: ldc           #8                  // String SPI annotation not found for class:
      27: invokevirtual #9                  // Method java/lang/StringBuilder.append:(Ljava/lang/String;)Ljava/lang/StringBuilder;
      30: aload_0
      31: invokevirtual #10                 // Method java/lang/Class.getName:()Ljava/lang/String;
      34: invokevirtual #9                  // Method java/lang/StringBuilder.append:(Ljava/lang/String;)Ljava/lang/StringBuilder;
      37: invokevirtual #11                 // Method java/lang/StringBuilder.toString:()Ljava/lang/String;
      40: invokespecial #12                 // Method java/lang/IllegalArgumentException."<init>":(Ljava/lang/String;)V
      43: athrow
      44: getstatic     #13                 // Field org/apache/dubbo/rpc/model/ScopeModelUtil$1.$SwitchMap$org$apache$dubbo$common$extension$ExtensionScope:[I
      47: aload_1
      48: invokeinterface #14,  1           // InterfaceMethod org/apache/dubbo/common/extension/SPI.scope:()Lorg/apache/dubbo/common/extension/ExtensionScope;
      53: invokevirtual #15                 // Method org/apache/dubbo/common/extension/ExtensionScope.ordinal:()I
      56: iaload
      57: tableswitch   { // 1 to 3
                     1: 84
                     2: 88
                     3: 92
               default: 99
          }
      84: invokestatic  #16                 // Method org/apache/dubbo/rpc/model/FrameworkModel.defaultModel:()Lorg/apache/dubbo/rpc/model/FrameworkModel;
      87: areturn
      88: invokestatic  #17                 // Method org/apache/dubbo/rpc/model/ApplicationModel.defaultModel:()Lorg/apache/dubbo/rpc/model/ApplicationModel;
      91: areturn
      92: invokestatic  #17                 // Method org/apache/dubbo/rpc/model/ApplicationModel.defaultModel:()Lorg/apache/dubbo/rpc/model/ApplicationModel;
      95: invokevirtual #18                 // Method org/apache/dubbo/rpc/model/ApplicationModel.getDefaultModule:()Lorg/apache/dubbo/rpc/model/ModuleModel;
      98: areturn
      99: new           #19                 // class java/lang/IllegalStateException
     102: dup
     103: new           #6                  // class java/lang/StringBuilder
     106: dup
     107: invokespecial #7                  // Method java/lang/StringBuilder."<init>":()V
     110: ldc           #20                 // String Unable to get default scope model for type:
     112: invokevirtual #9                  // Method java/lang/StringBuilder.append:(Ljava/lang/String;)Ljava/lang/StringBuilder;
     115: aload_0
     116: invokevirtual #10                 // Method java/lang/Class.getName:()Ljava/lang/String;
     119: invokevirtual #9                  // Method java/lang/StringBuilder.append:(Ljava/lang/String;)Ljava/lang/StringBuilder;
     122: invokevirtual #11                 // Method java/lang/StringBuilder.toString:()Ljava/lang/String;
     125: invokespecial #21                 // Method java/lang/IllegalStateException."<init>":(Ljava/lang/String;)V
     128: athrow

  public static org.apache.dubbo.rpc.model.ModuleModel getModuleModel(org.apache.dubbo.rpc.model.ScopeModel);
    Code:
       0: aload_0
       1: ifnonnull     11
       4: invokestatic  #17                 // Method org/apache/dubbo/rpc/model/ApplicationModel.defaultModel:()Lorg/apache/dubbo/rpc/model/ApplicationModel;
       7: invokevirtual #18                 // Method org/apache/dubbo/rpc/model/ApplicationModel.getDefaultModule:()Lorg/apache/dubbo/rpc/model/ModuleModel;
      10: areturn
      11: aload_0
      12: instanceof    #22                 // class org/apache/dubbo/rpc/model/ModuleModel
      15: ifeq          23
      18: aload_0
      19: checkcast     #22                 // class org/apache/dubbo/rpc/model/ModuleModel
      22: areturn
      23: new           #5                  // class java/lang/IllegalArgumentException
      26: dup
      27: new           #6                  // class java/lang/StringBuilder
      30: dup
      31: invokespecial #7                  // Method java/lang/StringBuilder."<init>":()V
      34: ldc           #23                 // String Unable to get ModuleModel from
      36: invokevirtual #9                  // Method java/lang/StringBuilder.append:(Ljava/lang/String;)Ljava/lang/StringBuilder;
      39: aload_0
      40: invokevirtual #24                 // Method java/lang/StringBuilder.append:(Ljava/lang/Object;)Ljava/lang/StringBuilder;
      43: invokevirtual #11                 // Method java/lang/StringBuilder.toString:()Ljava/lang/String;
      46: invokespecial #12                 // Method java/lang/IllegalArgumentException."<init>":(Ljava/lang/String;)V
      49: athrow

  public static org.apache.dubbo.rpc.model.ApplicationModel getApplicationModel(org.apache.dubbo.rpc.model.ScopeModel);
    Code:
       0: aload_0
       1: invokestatic  #25                 // Method getOrDefaultApplicationModel:(Lorg/apache/dubbo/rpc/model/ScopeModel;)Lorg/apache/dubbo/rpc/model/ApplicationModel;
       4: areturn

  public static org.apache.dubbo.rpc.model.ApplicationModel getOrDefaultApplicationModel(org.apache.dubbo.rpc.model.ScopeModel);
    Code:
       0: aload_0
       1: ifnonnull     8
       4: invokestatic  #17                 // Method org/apache/dubbo/rpc/model/ApplicationModel.defaultModel:()Lorg/apache/dubbo/rpc/model/ApplicationModel;
       7: areturn
       8: aload_0
       9: invokestatic  #26                 // Method getOrNullApplicationModel:(Lorg/apache/dubbo/rpc/model/ScopeModel;)Lorg/apache/dubbo/rpc/model/ApplicationModel;
      12: areturn

  public static org.apache.dubbo.rpc.model.ApplicationModel getOrNullApplicationModel(org.apache.dubbo.rpc.model.ScopeModel);
    Code:
       0: aload_0
       1: ifnonnull     6
       4: aconst_null
       5: areturn
       6: aload_0
       7: instanceof    #27                 // class org/apache/dubbo/rpc/model/ApplicationModel
      10: ifeq          18
      13: aload_0
      14: checkcast     #27                 // class org/apache/dubbo/rpc/model/ApplicationModel
      17: areturn
      18: aload_0
      19: instanceof    #22                 // class org/apache/dubbo/rpc/model/ModuleModel
      22: ifeq          35
      25: aload_0
      26: checkcast     #22                 // class org/apache/dubbo/rpc/model/ModuleModel
      29: astore_1
      30: aload_1
      31: invokevirtual #28                 // Method org/apache/dubbo/rpc/model/ModuleModel.getApplicationModel:()Lorg/apache/dubbo/rpc/model/ApplicationModel;
      34: areturn
      35: new           #5                  // class java/lang/IllegalArgumentException
      38: dup
      39: new           #6                  // class java/lang/StringBuilder
      42: dup
      43: invokespecial #7                  // Method java/lang/StringBuilder."<init>":()V
      46: ldc           #29                 // String Unable to get ApplicationModel from
      48: invokevirtual #9                  // Method java/lang/StringBuilder.append:(Ljava/lang/String;)Ljava/lang/StringBuilder;
      51: aload_0
      52: invokevirtual #24                 // Method java/lang/StringBuilder.append:(Ljava/lang/Object;)Ljava/lang/StringBuilder;
      55: invokevirtual #11                 // Method java/lang/StringBuilder.toString:()Ljava/lang/String;
      58: invokespecial #12                 // Method java/lang/IllegalArgumentException."<init>":(Ljava/lang/String;)V
      61: athrow

  public static org.apache.dubbo.rpc.model.FrameworkModel getFrameworkModel(org.apache.dubbo.rpc.model.ScopeModel);
    Code:
       0: aload_0
       1: ifnonnull     8
       4: invokestatic  #16                 // Method org/apache/dubbo/rpc/model/FrameworkModel.defaultModel:()Lorg/apache/dubbo/rpc/model/FrameworkModel;
       7: areturn
       8: aload_0
       9: instanceof    #27                 // class org/apache/dubbo/rpc/model/ApplicationModel
      12: ifeq          23
      15: aload_0
      16: checkcast     #27                 // class org/apache/dubbo/rpc/model/ApplicationModel
      19: invokevirtual #30                 // Method org/apache/dubbo/rpc/model/ApplicationModel.getFrameworkModel:()Lorg/apache/dubbo/rpc/model/FrameworkModel;
      22: areturn
      23: aload_0
      24: instanceof    #22                 // class org/apache/dubbo/rpc/model/ModuleModel
      27: ifeq          43
      30: aload_0
      31: checkcast     #22                 // class org/apache/dubbo/rpc/model/ModuleModel
      34: astore_1
      35: aload_1
      36: invokevirtual #28                 // Method org/apache/dubbo/rpc/model/ModuleModel.getApplicationModel:()Lorg/apache/dubbo/rpc/model/ApplicationModel;
      39: invokevirtual #30                 // Method org/apache/dubbo/rpc/model/ApplicationModel.getFrameworkModel:()Lorg/apache/dubbo/rpc/model/FrameworkModel;
      42: areturn
      43: aload_0
      44: instanceof    #31                 // class org/apache/dubbo/rpc/model/FrameworkModel
      47: ifeq          55
      50: aload_0
      51: checkcast     #31                 // class org/apache/dubbo/rpc/model/FrameworkModel
      54: areturn
      55: new           #5                  // class java/lang/IllegalArgumentException
      58: dup
      59: new           #6                  // class java/lang/StringBuilder
      62: dup
      63: invokespecial #7                  // Method java/lang/StringBuilder."<init>":()V
      66: ldc           #32                 // String Unable to get FrameworkModel from
      68: invokevirtual #9                  // Method java/lang/StringBuilder.append:(Ljava/lang/String;)Ljava/lang/StringBuilder;
      71: aload_0
      72: invokevirtual #24                 // Method java/lang/StringBuilder.append:(Ljava/lang/Object;)Ljava/lang/StringBuilder;
      75: invokevirtual #11                 // Method java/lang/StringBuilder.toString:()Ljava/lang/String;
      78: invokespecial #12                 // Method java/lang/IllegalArgumentException."<init>":(Ljava/lang/String;)V
      81: athrow

  public static <T> org.apache.dubbo.common.extension.ExtensionLoader<T> getExtensionLoader(java.lang.Class<T>, org.apache.dubbo.rpc.model.ScopeModel);
    Code:
       0: aload_1
       1: ifnull        10
       4: aload_1
       5: aload_0
       6: invokevirtual #33                 // Method org/apache/dubbo/rpc/model/ScopeModel.getExtensionLoader:(Ljava/lang/Class;)Lorg/apache/dubbo/common/extension/ExtensionLoader;
       9: areturn
      10: aload_0
      11: ldc           #3                  // class org/apache/dubbo/common/extension/SPI
      13: invokevirtual #4                  // Method java/lang/Class.getAnnotation:(Ljava/lang/Class;)Ljava/lang/annotation/Annotation;
      16: checkcast     #3                  // class org/apache/dubbo/common/extension/SPI
      19: astore_2
      20: aload_2
      21: ifnonnull     54
      24: new           #5                  // class java/lang/IllegalArgumentException
      27: dup
      28: new           #6                  // class java/lang/StringBuilder
      31: dup
      32: invokespecial #7                  // Method java/lang/StringBuilder."<init>":()V
      35: ldc           #8                  // String SPI annotation not found for class:
      37: invokevirtual #9                  // Method java/lang/StringBuilder.append:(Ljava/lang/String;)Ljava/lang/StringBuilder;
      40: aload_0
      41: invokevirtual #10                 // Method java/lang/Class.getName:()Ljava/lang/String;
      44: invokevirtual #9                  // Method java/lang/StringBuilder.append:(Ljava/lang/String;)Ljava/lang/StringBuilder;
      47: invokevirtual #11                 // Method java/lang/StringBuilder.toString:()Ljava/lang/String;
      50: invokespecial #12                 // Method java/lang/IllegalArgumentException."<init>":(Ljava/lang/String;)V
      53: athrow
      54: getstatic     #13                 // Field org/apache/dubbo/rpc/model/ScopeModelUtil$1.$SwitchMap$org$apache$dubbo$common$extension$ExtensionScope:[I
      57: aload_2
      58: invokeinterface #14,  1           // InterfaceMethod org/apache/dubbo/common/extension/SPI.scope:()Lorg/apache/dubbo/common/extension/ExtensionScope;
      63: invokevirtual #15                 // Method org/apache/dubbo/common/extension/ExtensionScope.ordinal:()I
      66: iaload
      67: tableswitch   { // 1 to 3
                     1: 92
                     2: 100
                     3: 108
               default: 119
          }
      92: invokestatic  #16                 // Method org/apache/dubbo/rpc/model/FrameworkModel.defaultModel:()Lorg/apache/dubbo/rpc/model/FrameworkModel;
      95: aload_0
      96: invokevirtual #34                 // Method org/apache/dubbo/rpc/model/FrameworkModel.getExtensionLoader:(Ljava/lang/Class;)Lorg/apache/dubbo/common/extension/ExtensionLoader;
      99: areturn
     100: invokestatic  #17                 // Method org/apache/dubbo/rpc/model/ApplicationModel.defaultModel:()Lorg/apache/dubbo/rpc/model/ApplicationModel;
     103: aload_0
     104: invokevirtual #35                 // Method org/apache/dubbo/rpc/model/ApplicationModel.getExtensionLoader:(Ljava/lang/Class;)Lorg/apache/dubbo/common/extension/ExtensionLoader;
     107: areturn
     108: invokestatic  #17                 // Method org/apache/dubbo/rpc/model/ApplicationModel.defaultModel:()Lorg/apache/dubbo/rpc/model/ApplicationModel;
     111: invokevirtual #18                 // Method org/apache/dubbo/rpc/model/ApplicationModel.getDefaultModule:()Lorg/apache/dubbo/rpc/model/ModuleModel;
     114: aload_0
     115: invokevirtual #36                 // Method org/apache/dubbo/rpc/model/ModuleModel.getExtensionLoader:(Ljava/lang/Class;)Lorg/apache/dubbo/common/extension/ExtensionLoader;
     118: areturn
     119: new           #5                  // class java/lang/IllegalArgumentException
     122: dup
     123: new           #6                  // class java/lang/StringBuilder
     126: dup
     127: invokespecial #7                  // Method java/lang/StringBuilder."<init>":()V
     130: ldc           #37                 // String Unable to get ExtensionLoader for type:
     132: invokevirtual #9                  // Method java/lang/StringBuilder.append:(Ljava/lang/String;)Ljava/lang/StringBuilder;
     135: aload_0
     136: invokevirtual #10                 // Method java/lang/Class.getName:()Ljava/lang/String;
     139: invokevirtual #9                  // Method java/lang/StringBuilder.append:(Ljava/lang/String;)Ljava/lang/StringBuilder;
     142: invokevirtual #11                 // Method java/lang/StringBuilder.toString:()Ljava/lang/String;
     145: invokespecial #12                 // Method java/lang/IllegalArgumentException."<init>":(Ljava/lang/String;)V
     148: athrow
}
