Compiled from "ServiceRepository.java"
public class org.apache.dubbo.rpc.model.ServiceRepository {
  public static final java.lang.String NAME;

  private final java.util.concurrent.atomic.AtomicBoolean initialized;

  private final org.apache.dubbo.rpc.model.ApplicationModel applicationModel;

  public org.apache.dubbo.rpc.model.ServiceRepository(org.apache.dubbo.rpc.model.ApplicationModel);
    Code:
       0: aload_0
       1: invokespecial #1                  // Method java/lang/Object."<init>":()V
       4: aload_0
       5: new           #2                  // class java/util/concurrent/atomic/AtomicBoolean
       8: dup
       9: iconst_0
      10: invokespecial #3                  // Method java/util/concurrent/atomic/AtomicBoolean."<init>":(Z)V
      13: putfield      #4                  // Field initialized:Ljava/util/concurrent/atomic/AtomicBoolean;
      16: aload_0
      17: aload_1
      18: putfield      #5                  // Field applicationModel:Lorg/apache/dubbo/rpc/model/ApplicationModel;
      21: aload_0
      22: invokespecial #6                  // Method initialize:()V
      25: return

  private void initialize();
    Code:
       0: aload_0
       1: getfield      #4                  // Field initialized:Ljava/util/concurrent/atomic/AtomicBoolean;
       4: iconst_0
       5: iconst_1
       6: invokevirtual #7                  // Method java/util/concurrent/atomic/AtomicBoolean.compareAndSet:(ZZ)Z
       9: ifeq          81
      12: aload_0
      13: getfield      #5                  // Field applicationModel:Lorg/apache/dubbo/rpc/model/ApplicationModel;
      16: ldc           #8                  // class org/apache/dubbo/rpc/model/BuiltinServiceDetector
      18: invokevirtual #9                  // Method org/apache/dubbo/rpc/model/ApplicationModel.getExtensionLoader:(Ljava/lang/Class;)Lorg/apache/dubbo/common/extension/ExtensionLoader;
      21: invokevirtual #10                 // Method org/apache/dubbo/common/extension/ExtensionLoader.getSupportedExtensionInstances:()Ljava/util/Set;
      24: astore_1
      25: aload_1
      26: invokestatic  #11                 // Method org/apache/dubbo/common/utils/CollectionUtils.isNotEmpty:(Ljava/util/Collection;)Z
      29: ifeq          81
      32: aload_1
      33: invokeinterface #12,  1           // InterfaceMethod java/util/Set.iterator:()Ljava/util/Iterator;
      38: astore_2
      39: aload_2
      40: invokeinterface #13,  1           // InterfaceMethod java/util/Iterator.hasNext:()Z
      45: ifeq          81
      48: aload_2
      49: invokeinterface #14,  1           // InterfaceMethod java/util/Iterator.next:()Ljava/lang/Object;
      54: checkcast     #8                  // class org/apache/dubbo/rpc/model/BuiltinServiceDetector
      57: astore_3
      58: aload_0
      59: getfield      #5                  // Field applicationModel:Lorg/apache/dubbo/rpc/model/ApplicationModel;
      62: invokevirtual #15                 // Method org/apache/dubbo/rpc/model/ApplicationModel.getInternalModule:()Lorg/apache/dubbo/rpc/model/ModuleModel;
      65: invokevirtual #16                 // Method org/apache/dubbo/rpc/model/ModuleModel.getServiceRepository:()Lorg/apache/dubbo/rpc/model/ModuleServiceRepository;
      68: aload_3
      69: invokeinterface #17,  1           // InterfaceMethod org/apache/dubbo/rpc/model/BuiltinServiceDetector.getService:()Ljava/lang/Class;
      74: invokevirtual #18                 // Method org/apache/dubbo/rpc/model/ModuleServiceRepository.registerService:(Ljava/lang/Class;)Lorg/apache/dubbo/rpc/model/ServiceDescriptor;
      77: pop
      78: goto          39
      81: return

  public void destroy();
    Code:
       0: return

  public java.util.Collection<org.apache.dubbo.rpc.model.ConsumerModel> allConsumerModels();
    Code:
       0: new           #19                 // class java/util/ArrayList
       3: dup
       4: invokespecial #20                 // Method java/util/ArrayList."<init>":()V
       7: astore_1
       8: aload_0
       9: getfield      #5                  // Field applicationModel:Lorg/apache/dubbo/rpc/model/ApplicationModel;
      12: invokevirtual #21                 // Method org/apache/dubbo/rpc/model/ApplicationModel.getModuleModels:()Ljava/util/List;
      15: invokeinterface #22,  1           // InterfaceMethod java/util/List.iterator:()Ljava/util/Iterator;
      20: astore_2
      21: aload_2
      22: invokeinterface #13,  1           // InterfaceMethod java/util/Iterator.hasNext:()Z
      27: ifeq          57
      30: aload_2
      31: invokeinterface #14,  1           // InterfaceMethod java/util/Iterator.next:()Ljava/lang/Object;
      36: checkcast     #23                 // class org/apache/dubbo/rpc/model/ModuleModel
      39: astore_3
      40: aload_1
      41: aload_3
      42: invokevirtual #16                 // Method org/apache/dubbo/rpc/model/ModuleModel.getServiceRepository:()Lorg/apache/dubbo/rpc/model/ModuleServiceRepository;
      45: invokevirtual #24                 // Method org/apache/dubbo/rpc/model/ModuleServiceRepository.getReferredServices:()Ljava/util/List;
      48: invokeinterface #25,  2           // InterfaceMethod java/util/List.addAll:(Ljava/util/Collection;)Z
      53: pop
      54: goto          21
      57: aload_1
      58: areturn

  public java.util.Collection<org.apache.dubbo.rpc.model.ProviderModel> allProviderModels();
    Code:
       0: new           #19                 // class java/util/ArrayList
       3: dup
       4: invokespecial #20                 // Method java/util/ArrayList."<init>":()V
       7: astore_1
       8: aload_0
       9: getfield      #5                  // Field applicationModel:Lorg/apache/dubbo/rpc/model/ApplicationModel;
      12: invokevirtual #21                 // Method org/apache/dubbo/rpc/model/ApplicationModel.getModuleModels:()Ljava/util/List;
      15: invokeinterface #22,  1           // InterfaceMethod java/util/List.iterator:()Ljava/util/Iterator;
      20: astore_2
      21: aload_2
      22: invokeinterface #13,  1           // InterfaceMethod java/util/Iterator.hasNext:()Z
      27: ifeq          57
      30: aload_2
      31: invokeinterface #14,  1           // InterfaceMethod java/util/Iterator.next:()Ljava/lang/Object;
      36: checkcast     #23                 // class org/apache/dubbo/rpc/model/ModuleModel
      39: astore_3
      40: aload_1
      41: aload_3
      42: invokevirtual #16                 // Method org/apache/dubbo/rpc/model/ModuleModel.getServiceRepository:()Lorg/apache/dubbo/rpc/model/ModuleServiceRepository;
      45: invokevirtual #26                 // Method org/apache/dubbo/rpc/model/ModuleServiceRepository.getExportedServices:()Ljava/util/List;
      48: invokeinterface #25,  2           // InterfaceMethod java/util/List.addAll:(Ljava/util/Collection;)Z
      53: pop
      54: goto          21
      57: aload_1
      58: areturn
}
