Compiled from "ServiceModel.java"
public class org.apache.dubbo.rpc.model.ServiceModel {
  private java.lang.String serviceKey;

  private java.lang.Object proxyObject;

  private java.lang.Runnable destroyRunner;

  private java.lang.ClassLoader classLoader;

  private final java.lang.ClassLoader interfaceClassLoader;

  private final org.apache.dubbo.rpc.model.ModuleModel moduleModel;

  private final org.apache.dubbo.rpc.model.ServiceDescriptor serviceModel;

  private org.apache.dubbo.config.AbstractInterfaceConfig config;

  private final org.apache.dubbo.rpc.model.ServiceMetadata serviceMetadata;

  public org.apache.dubbo.rpc.model.ServiceModel(java.lang.Object, java.lang.String, org.apache.dubbo.rpc.model.ServiceDescriptor, org.apache.dubbo.rpc.model.ModuleModel, java.lang.ClassLoader);
    Code:
       0: aload_0
       1: aload_1
       2: aload_2
       3: aload_3
       4: aload         4
       6: aconst_null
       7: aload         5
       9: invokespecial #1                  // Method "<init>":(Ljava/lang/Object;Ljava/lang/String;Lorg/apache/dubbo/rpc/model/ServiceDescriptor;Lorg/apache/dubbo/rpc/model/ModuleModel;Lorg/apache/dubbo/rpc/model/ServiceMetadata;Ljava/lang/ClassLoader;)V
      12: return

  public org.apache.dubbo.rpc.model.ServiceModel(java.lang.Object, java.lang.String, org.apache.dubbo.rpc.model.ServiceDescriptor, org.apache.dubbo.rpc.model.ModuleModel, org.apache.dubbo.rpc.model.ServiceMetadata, java.lang.ClassLoader);
    Code:
       0: aload_0
       1: invokespecial #2                  // Method java/lang/Object."<init>":()V
       4: aload_0
       5: aload_1
       6: putfield      #3                  // Field proxyObject:Ljava/lang/Object;
       9: aload_0
      10: aload_2
      11: putfield      #4                  // Field serviceKey:Ljava/lang/String;
      14: aload_0
      15: aload_3
      16: putfield      #5                  // Field serviceModel:Lorg/apache/dubbo/rpc/model/ServiceDescriptor;
      19: aload_0
      20: aload         4
      22: invokestatic  #6                  // Method org/apache/dubbo/rpc/model/ScopeModelUtil.getModuleModel:(Lorg/apache/dubbo/rpc/model/ScopeModel;)Lorg/apache/dubbo/rpc/model/ModuleModel;
      25: putfield      #7                  // Field moduleModel:Lorg/apache/dubbo/rpc/model/ModuleModel;
      28: aload_0
      29: aload         5
      31: putfield      #8                  // Field serviceMetadata:Lorg/apache/dubbo/rpc/model/ServiceMetadata;
      34: aload_0
      35: aload         6
      37: putfield      #9                  // Field interfaceClassLoader:Ljava/lang/ClassLoader;
      40: aload         5
      42: ifnull        51
      45: aload         5
      47: aload_0
      48: invokevirtual #10                 // Method org/apache/dubbo/rpc/model/ServiceMetadata.setServiceModel:(Lorg/apache/dubbo/rpc/model/ServiceModel;)V
      51: aload         6
      53: ifnull        62
      56: aload_0
      57: aload         6
      59: putfield      #11                 // Field classLoader:Ljava/lang/ClassLoader;
      62: aload_0
      63: getfield      #11                 // Field classLoader:Ljava/lang/ClassLoader;
      66: ifnonnull     79
      69: aload_0
      70: invokestatic  #12                 // Method java/lang/Thread.currentThread:()Ljava/lang/Thread;
      73: invokevirtual #13                 // Method java/lang/Thread.getContextClassLoader:()Ljava/lang/ClassLoader;
      76: putfield      #11                 // Field classLoader:Ljava/lang/ClassLoader;
      79: return

  public org.apache.dubbo.config.AbstractInterfaceConfig getConfig();
    Code:
       0: aload_0
       1: getfield      #14                 // Field config:Lorg/apache/dubbo/config/AbstractInterfaceConfig;
       4: areturn

  public void setConfig(org.apache.dubbo.config.AbstractInterfaceConfig);
    Code:
       0: aload_0
       1: aload_1
       2: putfield      #14                 // Field config:Lorg/apache/dubbo/config/AbstractInterfaceConfig;
       5: return

  public org.apache.dubbo.config.ReferenceConfigBase<?> getReferenceConfig();
    Code:
       0: aload_0
       1: getfield      #14                 // Field config:Lorg/apache/dubbo/config/AbstractInterfaceConfig;
       4: ifnonnull     9
       7: aconst_null
       8: areturn
       9: aload_0
      10: getfield      #14                 // Field config:Lorg/apache/dubbo/config/AbstractInterfaceConfig;
      13: instanceof    #15                 // class org/apache/dubbo/config/ReferenceConfigBase
      16: ifeq          27
      19: aload_0
      20: getfield      #14                 // Field config:Lorg/apache/dubbo/config/AbstractInterfaceConfig;
      23: checkcast     #15                 // class org/apache/dubbo/config/ReferenceConfigBase
      26: areturn
      27: new           #16                 // class java/lang/IllegalArgumentException
      30: dup
      31: ldc           #17                 // String Current ServiceModel is not a ConsumerModel
      33: invokespecial #18                 // Method java/lang/IllegalArgumentException."<init>":(Ljava/lang/String;)V
      36: athrow

  public org.apache.dubbo.config.ServiceConfigBase<?> getServiceConfig();
    Code:
       0: aload_0
       1: getfield      #14                 // Field config:Lorg/apache/dubbo/config/AbstractInterfaceConfig;
       4: ifnonnull     9
       7: aconst_null
       8: areturn
       9: aload_0
      10: getfield      #14                 // Field config:Lorg/apache/dubbo/config/AbstractInterfaceConfig;
      13: instanceof    #19                 // class org/apache/dubbo/config/ServiceConfigBase
      16: ifeq          27
      19: aload_0
      20: getfield      #14                 // Field config:Lorg/apache/dubbo/config/AbstractInterfaceConfig;
      23: checkcast     #19                 // class org/apache/dubbo/config/ServiceConfigBase
      26: areturn
      27: new           #16                 // class java/lang/IllegalArgumentException
      30: dup
      31: ldc           #20                 // String Current ServiceModel is not a ProviderModel
      33: invokespecial #18                 // Method java/lang/IllegalArgumentException."<init>":(Ljava/lang/String;)V
      36: athrow

  public java.lang.String getServiceKey();
    Code:
       0: aload_0
       1: getfield      #4                  // Field serviceKey:Ljava/lang/String;
       4: areturn

  public void setProxyObject(java.lang.Object);
    Code:
       0: aload_0
       1: aload_1
       2: putfield      #3                  // Field proxyObject:Ljava/lang/Object;
       5: return

  public java.lang.Object getProxyObject();
    Code:
       0: aload_0
       1: getfield      #3                  // Field proxyObject:Ljava/lang/Object;
       4: areturn

  public org.apache.dubbo.rpc.model.ServiceDescriptor getServiceModel();
    Code:
       0: aload_0
       1: getfield      #5                  // Field serviceModel:Lorg/apache/dubbo/rpc/model/ServiceDescriptor;
       4: areturn

  public void setClassLoader(java.lang.ClassLoader);
    Code:
       0: aload_0
       1: aload_1
       2: putfield      #11                 // Field classLoader:Ljava/lang/ClassLoader;
       5: return

  public java.lang.ClassLoader getClassLoader();
    Code:
       0: aload_0
       1: getfield      #11                 // Field classLoader:Ljava/lang/ClassLoader;
       4: areturn

  public java.util.Set<org.apache.dubbo.rpc.model.MethodDescriptor> getAllMethods();
    Code:
       0: aload_0
       1: getfield      #5                  // Field serviceModel:Lorg/apache/dubbo/rpc/model/ServiceDescriptor;
       4: invokeinterface #21,  1           // InterfaceMethod org/apache/dubbo/rpc/model/ServiceDescriptor.getAllMethods:()Ljava/util/Set;
       9: areturn

  public java.lang.Class<?> getServiceInterfaceClass();
    Code:
       0: aload_0
       1: getfield      #5                  // Field serviceModel:Lorg/apache/dubbo/rpc/model/ServiceDescriptor;
       4: invokeinterface #22,  1           // InterfaceMethod org/apache/dubbo/rpc/model/ServiceDescriptor.getServiceInterfaceClass:()Ljava/lang/Class;
       9: areturn

  public void setServiceKey(java.lang.String);
    Code:
       0: aload_0
       1: aload_1
       2: putfield      #4                  // Field serviceKey:Ljava/lang/String;
       5: aload_0
       6: getfield      #8                  // Field serviceMetadata:Lorg/apache/dubbo/rpc/model/ServiceMetadata;
       9: ifnull        31
      12: aload_0
      13: getfield      #8                  // Field serviceMetadata:Lorg/apache/dubbo/rpc/model/ServiceMetadata;
      16: aload_1
      17: invokevirtual #23                 // Method org/apache/dubbo/rpc/model/ServiceMetadata.setServiceKey:(Ljava/lang/String;)V
      20: aload_0
      21: getfield      #8                  // Field serviceMetadata:Lorg/apache/dubbo/rpc/model/ServiceMetadata;
      24: aload_1
      25: invokestatic  #24                 // Method org/apache/dubbo/common/BaseServiceMetadata.groupFromServiceKey:(Ljava/lang/String;)Ljava/lang/String;
      28: invokevirtual #25                 // Method org/apache/dubbo/rpc/model/ServiceMetadata.setGroup:(Ljava/lang/String;)V
      31: return

  public java.lang.String getServiceName();
    Code:
       0: aload_0
       1: getfield      #8                  // Field serviceMetadata:Lorg/apache/dubbo/rpc/model/ServiceMetadata;
       4: invokevirtual #26                 // Method org/apache/dubbo/rpc/model/ServiceMetadata.getServiceKey:()Ljava/lang/String;
       7: areturn

  public org.apache.dubbo.rpc.model.ServiceMetadata getServiceMetadata();
    Code:
       0: aload_0
       1: getfield      #8                  // Field serviceMetadata:Lorg/apache/dubbo/rpc/model/ServiceMetadata;
       4: areturn

  public org.apache.dubbo.rpc.model.ModuleModel getModuleModel();
    Code:
       0: aload_0
       1: getfield      #7                  // Field moduleModel:Lorg/apache/dubbo/rpc/model/ModuleModel;
       4: areturn

  public java.lang.Runnable getDestroyRunner();
    Code:
       0: aload_0
       1: getfield      #27                 // Field destroyRunner:Ljava/lang/Runnable;
       4: areturn

  public void setDestroyRunner(java.lang.Runnable);
    Code:
       0: aload_0
       1: aload_1
       2: putfield      #27                 // Field destroyRunner:Ljava/lang/Runnable;
       5: return

  public java.lang.ClassLoader getInterfaceClassLoader();
    Code:
       0: aload_0
       1: getfield      #9                  // Field interfaceClassLoader:Ljava/lang/ClassLoader;
       4: areturn

  public boolean equals(java.lang.Object);
    Code:
       0: aload_0
       1: aload_1
       2: if_acmpne     7
       5: iconst_1
       6: ireturn
       7: aload_1
       8: ifnull        22
      11: aload_0
      12: invokevirtual #28                 // Method java/lang/Object.getClass:()Ljava/lang/Class;
      15: aload_1
      16: invokevirtual #28                 // Method java/lang/Object.getClass:()Ljava/lang/Class;
      19: if_acmpeq     24
      22: iconst_0
      23: ireturn
      24: aload_1
      25: checkcast     #29                 // class org/apache/dubbo/rpc/model/ServiceModel
      28: astore_2
      29: aload_0
      30: getfield      #4                  // Field serviceKey:Ljava/lang/String;
      33: aload_2
      34: getfield      #4                  // Field serviceKey:Ljava/lang/String;
      37: invokestatic  #30                 // Method java/util/Objects.equals:(Ljava/lang/Object;Ljava/lang/Object;)Z
      40: ifeq          145
      43: aload_0
      44: getfield      #3                  // Field proxyObject:Ljava/lang/Object;
      47: aload_2
      48: getfield      #3                  // Field proxyObject:Ljava/lang/Object;
      51: invokestatic  #30                 // Method java/util/Objects.equals:(Ljava/lang/Object;Ljava/lang/Object;)Z
      54: ifeq          145
      57: aload_0
      58: getfield      #27                 // Field destroyRunner:Ljava/lang/Runnable;
      61: aload_2
      62: getfield      #27                 // Field destroyRunner:Ljava/lang/Runnable;
      65: invokestatic  #30                 // Method java/util/Objects.equals:(Ljava/lang/Object;Ljava/lang/Object;)Z
      68: ifeq          145
      71: aload_0
      72: getfield      #11                 // Field classLoader:Ljava/lang/ClassLoader;
      75: aload_2
      76: getfield      #11                 // Field classLoader:Ljava/lang/ClassLoader;
      79: invokestatic  #30                 // Method java/util/Objects.equals:(Ljava/lang/Object;Ljava/lang/Object;)Z
      82: ifeq          145
      85: aload_0
      86: getfield      #9                  // Field interfaceClassLoader:Ljava/lang/ClassLoader;
      89: aload_2
      90: getfield      #9                  // Field interfaceClassLoader:Ljava/lang/ClassLoader;
      93: invokestatic  #30                 // Method java/util/Objects.equals:(Ljava/lang/Object;Ljava/lang/Object;)Z
      96: ifeq          145
      99: aload_0
     100: getfield      #7                  // Field moduleModel:Lorg/apache/dubbo/rpc/model/ModuleModel;
     103: aload_2
     104: getfield      #7                  // Field moduleModel:Lorg/apache/dubbo/rpc/model/ModuleModel;
     107: invokestatic  #30                 // Method java/util/Objects.equals:(Ljava/lang/Object;Ljava/lang/Object;)Z
     110: ifeq          145
     113: aload_0
     114: getfield      #5                  // Field serviceModel:Lorg/apache/dubbo/rpc/model/ServiceDescriptor;
     117: aload_2
     118: getfield      #5                  // Field serviceModel:Lorg/apache/dubbo/rpc/model/ServiceDescriptor;
     121: invokestatic  #30                 // Method java/util/Objects.equals:(Ljava/lang/Object;Ljava/lang/Object;)Z
     124: ifeq          145
     127: aload_0
     128: getfield      #8                  // Field serviceMetadata:Lorg/apache/dubbo/rpc/model/ServiceMetadata;
     131: aload_2
     132: getfield      #8                  // Field serviceMetadata:Lorg/apache/dubbo/rpc/model/ServiceMetadata;
     135: invokestatic  #30                 // Method java/util/Objects.equals:(Ljava/lang/Object;Ljava/lang/Object;)Z
     138: ifeq          145
     141: iconst_1
     142: goto          146
     145: iconst_0
     146: ireturn

  public int hashCode();
    Code:
       0: bipush        8
       2: anewarray     #31                 // class java/lang/Object
       5: dup
       6: iconst_0
       7: aload_0
       8: getfield      #4                  // Field serviceKey:Ljava/lang/String;
      11: aastore
      12: dup
      13: iconst_1
      14: aload_0
      15: getfield      #3                  // Field proxyObject:Ljava/lang/Object;
      18: aastore
      19: dup
      20: iconst_2
      21: aload_0
      22: getfield      #27                 // Field destroyRunner:Ljava/lang/Runnable;
      25: aastore
      26: dup
      27: iconst_3
      28: aload_0
      29: getfield      #11                 // Field classLoader:Ljava/lang/ClassLoader;
      32: aastore
      33: dup
      34: iconst_4
      35: aload_0
      36: getfield      #9                  // Field interfaceClassLoader:Ljava/lang/ClassLoader;
      39: aastore
      40: dup
      41: iconst_5
      42: aload_0
      43: getfield      #7                  // Field moduleModel:Lorg/apache/dubbo/rpc/model/ModuleModel;
      46: aastore
      47: dup
      48: bipush        6
      50: aload_0
      51: getfield      #5                  // Field serviceModel:Lorg/apache/dubbo/rpc/model/ServiceDescriptor;
      54: aastore
      55: dup
      56: bipush        7
      58: aload_0
      59: getfield      #8                  // Field serviceMetadata:Lorg/apache/dubbo/rpc/model/ServiceMetadata;
      62: aastore
      63: invokestatic  #32                 // Method java/util/Objects.hash:([Ljava/lang/Object;)I
      66: ireturn
}
