Compiled from "ServiceMetadata.java"
public class org.apache.dubbo.rpc.model.ServiceMetadata extends org.apache.dubbo.common.BaseServiceMetadata {
  private java.lang.String defaultGroup;

  private java.lang.Class<?> serviceType;

  private java.lang.Object target;

  private final java.util.Map<java.lang.String, java.lang.Object> attachments;

  private final java.util.Map<java.lang.String, java.lang.Object> attributeMap;

  public org.apache.dubbo.rpc.model.ServiceMetadata(java.lang.String, java.lang.String, java.lang.String, java.lang.Class<?>);
    Code:
       0: aload_0
       1: invokespecial #1                  // Method org/apache/dubbo/common/BaseServiceMetadata."<init>":()V
       4: aload_0
       5: new           #2                  // class java/util/concurrent/ConcurrentHashMap
       8: dup
       9: invokespecial #3                  // Method java/util/concurrent/ConcurrentHashMap."<init>":()V
      12: putfield      #4                  // Field attachments:Ljava/util/Map;
      15: aload_0
      16: new           #2                  // class java/util/concurrent/ConcurrentHashMap
      19: dup
      20: invokespecial #3                  // Method java/util/concurrent/ConcurrentHashMap."<init>":()V
      23: putfield      #5                  // Field attributeMap:Ljava/util/Map;
      26: aload_0
      27: aload_1
      28: putfield      #6                  // Field serviceInterfaceName:Ljava/lang/String;
      31: aload_0
      32: aload_2
      33: putfield      #7                  // Field defaultGroup:Ljava/lang/String;
      36: aload_0
      37: aload_2
      38: putfield      #8                  // Field group:Ljava/lang/String;
      41: aload_0
      42: aload_3
      43: putfield      #9                  // Field version:Ljava/lang/String;
      46: aload_0
      47: aload_1
      48: aload_2
      49: aload_3
      50: invokestatic  #10                 // Method buildServiceKey:(Ljava/lang/String;Ljava/lang/String;Ljava/lang/String;)Ljava/lang/String;
      53: putfield      #11                 // Field serviceKey:Ljava/lang/String;
      56: aload_0
      57: aload         4
      59: putfield      #12                 // Field serviceType:Ljava/lang/Class;
      62: return

  public org.apache.dubbo.rpc.model.ServiceMetadata();
    Code:
       0: aload_0
       1: invokespecial #1                  // Method org/apache/dubbo/common/BaseServiceMetadata."<init>":()V
       4: aload_0
       5: new           #2                  // class java/util/concurrent/ConcurrentHashMap
       8: dup
       9: invokespecial #3                  // Method java/util/concurrent/ConcurrentHashMap."<init>":()V
      12: putfield      #4                  // Field attachments:Ljava/util/Map;
      15: aload_0
      16: new           #2                  // class java/util/concurrent/ConcurrentHashMap
      19: dup
      20: invokespecial #3                  // Method java/util/concurrent/ConcurrentHashMap."<init>":()V
      23: putfield      #5                  // Field attributeMap:Ljava/util/Map;
      26: return

  public java.lang.String getServiceKey();
    Code:
       0: aload_0
       1: getfield      #11                 // Field serviceKey:Ljava/lang/String;
       4: areturn

  public java.util.Map<java.lang.String, java.lang.Object> getAttachments();
    Code:
       0: aload_0
       1: getfield      #4                  // Field attachments:Ljava/util/Map;
       4: areturn

  public java.util.Map<java.lang.String, java.lang.Object> getAttributeMap();
    Code:
       0: aload_0
       1: getfield      #5                  // Field attributeMap:Ljava/util/Map;
       4: areturn

  public java.lang.Object getAttribute(java.lang.String);
    Code:
       0: aload_0
       1: getfield      #5                  // Field attributeMap:Ljava/util/Map;
       4: aload_1
       5: invokeinterface #13,  2           // InterfaceMethod java/util/Map.get:(Ljava/lang/Object;)Ljava/lang/Object;
      10: areturn

  public void addAttribute(java.lang.String, java.lang.Object);
    Code:
       0: aload_0
       1: getfield      #5                  // Field attributeMap:Ljava/util/Map;
       4: aload_1
       5: aload_2
       6: invokeinterface #14,  3           // InterfaceMethod java/util/Map.put:(Ljava/lang/Object;Ljava/lang/Object;)Ljava/lang/Object;
      11: pop
      12: return

  public void addAttachment(java.lang.String, java.lang.Object);
    Code:
       0: aload_0
       1: getfield      #4                  // Field attachments:Ljava/util/Map;
       4: aload_1
       5: aload_2
       6: invokeinterface #14,  3           // InterfaceMethod java/util/Map.put:(Ljava/lang/Object;Ljava/lang/Object;)Ljava/lang/Object;
      11: pop
      12: return

  public java.lang.Class<?> getServiceType();
    Code:
       0: aload_0
       1: getfield      #12                 // Field serviceType:Ljava/lang/Class;
       4: areturn

  public java.lang.String getDefaultGroup();
    Code:
       0: aload_0
       1: getfield      #7                  // Field defaultGroup:Ljava/lang/String;
       4: areturn

  public void setDefaultGroup(java.lang.String);
    Code:
       0: aload_0
       1: aload_1
       2: putfield      #7                  // Field defaultGroup:Ljava/lang/String;
       5: return

  public void setServiceType(java.lang.Class<?>);
    Code:
       0: aload_0
       1: aload_1
       2: putfield      #12                 // Field serviceType:Ljava/lang/Class;
       5: return

  public java.lang.Object getTarget();
    Code:
       0: aload_0
       1: getfield      #15                 // Field target:Ljava/lang/Object;
       4: areturn

  public void setTarget(java.lang.Object);
    Code:
       0: aload_0
       1: aload_1
       2: putfield      #15                 // Field target:Ljava/lang/Object;
       5: return
}
