Compiled from "GlobalResourcesRepository.java"
public class org.apache.dubbo.common.resource.GlobalResourcesRepository {
  private static final org.apache.dubbo.common.logger.ErrorTypeAwareLogger logger;

  private static volatile org.apache.dubbo.common.resource.GlobalResourcesRepository instance;

  private volatile java.util.concurrent.ExecutorService executorService;

  private final java.util.List<org.apache.dubbo.common.resource.Disposable> oneoffDisposables;

  private static final java.util.List<org.apache.dubbo.common.resource.Disposable> globalReusedDisposables;

  private org.apache.dubbo.common.resource.GlobalResourcesRepository();
    Code:
       0: aload_0
       1: invokespecial #2                  // Method java/lang/Object."<init>":()V
       4: aload_0
       5: new           #3                  // class java/util/concurrent/CopyOnWriteArrayList
       8: dup
       9: invokespecial #4                  // Method java/util/concurrent/CopyOnWriteArrayList."<init>":()V
      12: putfield      #5                  // Field oneoffDisposables:Ljava/util/List;
      15: return

  public static org.apache.dubbo.common.resource.GlobalResourcesRepository getInstance();
    Code:
       0: getstatic     #6                  // Field instance:Lorg/apache/dubbo/common/resource/GlobalResourcesRepository;
       3: ifnonnull     37
       6: ldc           #7                  // class org/apache/dubbo/common/resource/GlobalResourcesRepository
       8: dup
       9: astore_0
      10: monitorenter
      11: getstatic     #6                  // Field instance:Lorg/apache/dubbo/common/resource/GlobalResourcesRepository;
      14: ifnonnull     27
      17: new           #7                  // class org/apache/dubbo/common/resource/GlobalResourcesRepository
      20: dup
      21: invokespecial #8                  // Method "<init>":()V
      24: putstatic     #6                  // Field instance:Lorg/apache/dubbo/common/resource/GlobalResourcesRepository;
      27: aload_0
      28: monitorexit
      29: goto          37
      32: astore_1
      33: aload_0
      34: monitorexit
      35: aload_1
      36: athrow
      37: getstatic     #6                  // Field instance:Lorg/apache/dubbo/common/resource/GlobalResourcesRepository;
      40: areturn
    Exception table:
       from    to  target type
          11    29    32   any
          32    35    32   any

  public static void registerGlobalDisposable(org.apache.dubbo.common.resource.Disposable);
    Code:
       0: getstatic     #9                  // Field globalReusedDisposables:Ljava/util/List;
       3: aload_0
       4: invokeinterface #10,  2           // InterfaceMethod java/util/List.contains:(Ljava/lang/Object;)Z
       9: ifne          49
      12: ldc           #7                  // class org/apache/dubbo/common/resource/GlobalResourcesRepository
      14: dup
      15: astore_1
      16: monitorenter
      17: getstatic     #9                  // Field globalReusedDisposables:Ljava/util/List;
      20: aload_0
      21: invokeinterface #10,  2           // InterfaceMethod java/util/List.contains:(Ljava/lang/Object;)Z
      26: ifne          39
      29: getstatic     #9                  // Field globalReusedDisposables:Ljava/util/List;
      32: aload_0
      33: invokeinterface #11,  2           // InterfaceMethod java/util/List.add:(Ljava/lang/Object;)Z
      38: pop
      39: aload_1
      40: monitorexit
      41: goto          49
      44: astore_2
      45: aload_1
      46: monitorexit
      47: aload_2
      48: athrow
      49: return
    Exception table:
       from    to  target type
          17    41    44   any
          44    47    44   any

  public void removeGlobalDisposable(org.apache.dubbo.common.resource.Disposable);
    Code:
       0: getstatic     #9                  // Field globalReusedDisposables:Ljava/util/List;
       3: aload_1
       4: invokeinterface #10,  2           // InterfaceMethod java/util/List.contains:(Ljava/lang/Object;)Z
       9: ifeq          51
      12: ldc           #7                  // class org/apache/dubbo/common/resource/GlobalResourcesRepository
      14: dup
      15: astore_2
      16: monitorenter
      17: getstatic     #9                  // Field globalReusedDisposables:Ljava/util/List;
      20: aload_1
      21: invokeinterface #10,  2           // InterfaceMethod java/util/List.contains:(Ljava/lang/Object;)Z
      26: ifeq          41
      29: aload_0
      30: pop
      31: getstatic     #9                  // Field globalReusedDisposables:Ljava/util/List;
      34: aload_1
      35: invokeinterface #12,  2           // InterfaceMethod java/util/List.remove:(Ljava/lang/Object;)Z
      40: pop
      41: aload_2
      42: monitorexit
      43: goto          51
      46: astore_3
      47: aload_2
      48: monitorexit
      49: aload_3
      50: athrow
      51: return
    Exception table:
       from    to  target type
          17    43    46   any
          46    49    46   any

  public static java.util.concurrent.ExecutorService getGlobalExecutorService();
    Code:
       0: invokestatic  #13                 // Method getInstance:()Lorg/apache/dubbo/common/resource/GlobalResourcesRepository;
       3: invokevirtual #14                 // Method getExecutorService:()Ljava/util/concurrent/ExecutorService;
       6: areturn

  public java.util.concurrent.ExecutorService getExecutorService();
    Code:
       0: aload_0
       1: getfield      #15                 // Field executorService:Ljava/util/concurrent/ExecutorService;
       4: ifnull        19
       7: aload_0
       8: getfield      #15                 // Field executorService:Ljava/util/concurrent/ExecutorService;
      11: invokeinterface #16,  1           // InterfaceMethod java/util/concurrent/ExecutorService.isShutdown:()Z
      16: ifeq          90
      19: aload_0
      20: dup
      21: astore_1
      22: monitorenter
      23: aload_0
      24: getfield      #15                 // Field executorService:Ljava/util/concurrent/ExecutorService;
      27: ifnull        42
      30: aload_0
      31: getfield      #15                 // Field executorService:Ljava/util/concurrent/ExecutorService;
      34: invokeinterface #16,  1           // InterfaceMethod java/util/concurrent/ExecutorService.isShutdown:()Z
      39: ifeq          80
      42: getstatic     #17                 // Field logger:Lorg/apache/dubbo/common/logger/ErrorTypeAwareLogger;
      45: invokeinterface #18,  1           // InterfaceMethod org/apache/dubbo/common/logger/ErrorTypeAwareLogger.isInfoEnabled:()Z
      50: ifeq          63
      53: getstatic     #17                 // Field logger:Lorg/apache/dubbo/common/logger/ErrorTypeAwareLogger;
      56: ldc           #19                 // String Creating global shared handler ...
      58: invokeinterface #20,  2           // InterfaceMethod org/apache/dubbo/common/logger/ErrorTypeAwareLogger.info:(Ljava/lang/String;)V
      63: aload_0
      64: new           #21                 // class org/apache/dubbo/common/utils/NamedThreadFactory
      67: dup
      68: ldc           #22                 // String Dubbo-global-shared-handler
      70: iconst_1
      71: invokespecial #23                 // Method org/apache/dubbo/common/utils/NamedThreadFactory."<init>":(Ljava/lang/String;Z)V
      74: invokestatic  #24                 // Method java/util/concurrent/Executors.newCachedThreadPool:(Ljava/util/concurrent/ThreadFactory;)Ljava/util/concurrent/ExecutorService;
      77: putfield      #15                 // Field executorService:Ljava/util/concurrent/ExecutorService;
      80: aload_1
      81: monitorexit
      82: goto          90
      85: astore_2
      86: aload_1
      87: monitorexit
      88: aload_2
      89: athrow
      90: aload_0
      91: getfield      #15                 // Field executorService:Ljava/util/concurrent/ExecutorService;
      94: areturn
    Exception table:
       from    to  target type
          23    82    85   any
          85    88    85   any

  public synchronized void destroy();
    Code:
       0: getstatic     #17                 // Field logger:Lorg/apache/dubbo/common/logger/ErrorTypeAwareLogger;
       3: invokeinterface #18,  1           // InterfaceMethod org/apache/dubbo/common/logger/ErrorTypeAwareLogger.isInfoEnabled:()Z
       8: ifeq          21
      11: getstatic     #17                 // Field logger:Lorg/apache/dubbo/common/logger/ErrorTypeAwareLogger;
      14: ldc           #25                 // String Destroying global resources ...
      16: invokeinterface #20,  2           // InterfaceMethod org/apache/dubbo/common/logger/ErrorTypeAwareLogger.info:(Ljava/lang/String;)V
      21: aload_0
      22: getfield      #15                 // Field executorService:Ljava/util/concurrent/ExecutorService;
      25: ifnull        43
      28: aload_0
      29: getfield      #15                 // Field executorService:Ljava/util/concurrent/ExecutorService;
      32: invokeinterface #26,  1           // InterfaceMethod java/util/concurrent/ExecutorService.shutdownNow:()Ljava/util/List;
      37: pop
      38: aload_0
      39: aconst_null
      40: putfield      #15                 // Field executorService:Ljava/util/concurrent/ExecutorService;
      43: new           #27                 // class java/util/ArrayList
      46: dup
      47: aload_0
      48: getfield      #5                  // Field oneoffDisposables:Ljava/util/List;
      51: invokespecial #28                 // Method java/util/ArrayList."<init>":(Ljava/util/Collection;)V
      54: invokevirtual #29                 // Method java/util/ArrayList.iterator:()Ljava/util/Iterator;
      57: astore_1
      58: aload_1
      59: invokeinterface #30,  1           // InterfaceMethod java/util/Iterator.hasNext:()Z
      64: ifeq          127
      67: aload_1
      68: invokeinterface #31,  1           // InterfaceMethod java/util/Iterator.next:()Ljava/lang/Object;
      73: checkcast     #32                 // class org/apache/dubbo/common/resource/Disposable
      76: astore_2
      77: aload_2
      78: invokeinterface #33,  1           // InterfaceMethod org/apache/dubbo/common/resource/Disposable.destroy:()V
      83: goto          124
      86: astore_3
      87: getstatic     #17                 // Field logger:Lorg/apache/dubbo/common/logger/ErrorTypeAwareLogger;
      90: ldc           #35                 // String 0-12
      92: ldc           #36                 // String
      94: ldc           #36                 // String
      96: new           #37                 // class java/lang/StringBuilder
      99: dup
     100: invokespecial #38                 // Method java/lang/StringBuilder."<init>":()V
     103: ldc           #39                 // String destroy resources failed:
     105: invokevirtual #40                 // Method java/lang/StringBuilder.append:(Ljava/lang/String;)Ljava/lang/StringBuilder;
     108: aload_3
     109: invokevirtual #41                 // Method java/lang/Exception.getMessage:()Ljava/lang/String;
     112: invokevirtual #40                 // Method java/lang/StringBuilder.append:(Ljava/lang/String;)Ljava/lang/StringBuilder;
     115: invokevirtual #42                 // Method java/lang/StringBuilder.toString:()Ljava/lang/String;
     118: aload_3
     119: invokeinterface #43,  6           // InterfaceMethod org/apache/dubbo/common/logger/ErrorTypeAwareLogger.warn:(Ljava/lang/String;Ljava/lang/String;Ljava/lang/String;Ljava/lang/String;Ljava/lang/Throwable;)V
     124: goto          58
     127: aload_0
     128: getfield      #5                  // Field oneoffDisposables:Ljava/util/List;
     131: invokeinterface #44,  1           // InterfaceMethod java/util/List.clear:()V
     136: new           #27                 // class java/util/ArrayList
     139: dup
     140: getstatic     #9                  // Field globalReusedDisposables:Ljava/util/List;
     143: invokespecial #28                 // Method java/util/ArrayList."<init>":(Ljava/util/Collection;)V
     146: invokevirtual #29                 // Method java/util/ArrayList.iterator:()Ljava/util/Iterator;
     149: astore_1
     150: aload_1
     151: invokeinterface #30,  1           // InterfaceMethod java/util/Iterator.hasNext:()Z
     156: ifeq          219
     159: aload_1
     160: invokeinterface #31,  1           // InterfaceMethod java/util/Iterator.next:()Ljava/lang/Object;
     165: checkcast     #32                 // class org/apache/dubbo/common/resource/Disposable
     168: astore_2
     169: aload_2
     170: invokeinterface #33,  1           // InterfaceMethod org/apache/dubbo/common/resource/Disposable.destroy:()V
     175: goto          216
     178: astore_3
     179: getstatic     #17                 // Field logger:Lorg/apache/dubbo/common/logger/ErrorTypeAwareLogger;
     182: ldc           #35                 // String 0-12
     184: ldc           #36                 // String
     186: ldc           #36                 // String
     188: new           #37                 // class java/lang/StringBuilder
     191: dup
     192: invokespecial #38                 // Method java/lang/StringBuilder."<init>":()V
     195: ldc           #39                 // String destroy resources failed:
     197: invokevirtual #40                 // Method java/lang/StringBuilder.append:(Ljava/lang/String;)Ljava/lang/StringBuilder;
     200: aload_3
     201: invokevirtual #41                 // Method java/lang/Exception.getMessage:()Ljava/lang/String;
     204: invokevirtual #40                 // Method java/lang/StringBuilder.append:(Ljava/lang/String;)Ljava/lang/StringBuilder;
     207: invokevirtual #42                 // Method java/lang/StringBuilder.toString:()Ljava/lang/String;
     210: aload_3
     211: invokeinterface #43,  6           // InterfaceMethod org/apache/dubbo/common/logger/ErrorTypeAwareLogger.warn:(Ljava/lang/String;Ljava/lang/String;Ljava/lang/String;Ljava/lang/String;Ljava/lang/Throwable;)V
     216: goto          150
     219: getstatic     #17                 // Field logger:Lorg/apache/dubbo/common/logger/ErrorTypeAwareLogger;
     222: invokeinterface #18,  1           // InterfaceMethod org/apache/dubbo/common/logger/ErrorTypeAwareLogger.isInfoEnabled:()Z
     227: ifeq          240
     230: getstatic     #17                 // Field logger:Lorg/apache/dubbo/common/logger/ErrorTypeAwareLogger;
     233: ldc           #45                 // String Dubbo is completely destroyed
     235: invokeinterface #20,  2           // InterfaceMethod org/apache/dubbo/common/logger/ErrorTypeAwareLogger.info:(Ljava/lang/String;)V
     240: return
    Exception table:
       from    to  target type
          77    83    86   Class java/lang/Exception
         169   175   178   Class java/lang/Exception

  public void registerDisposable(org.apache.dubbo.common.resource.Disposable);
    Code:
       0: aload_0
       1: getfield      #5                  // Field oneoffDisposables:Ljava/util/List;
       4: aload_1
       5: invokeinterface #10,  2           // InterfaceMethod java/util/List.contains:(Ljava/lang/Object;)Z
      10: ifne          51
      13: aload_0
      14: dup
      15: astore_2
      16: monitorenter
      17: aload_0
      18: getfield      #5                  // Field oneoffDisposables:Ljava/util/List;
      21: aload_1
      22: invokeinterface #10,  2           // InterfaceMethod java/util/List.contains:(Ljava/lang/Object;)Z
      27: ifne          41
      30: aload_0
      31: getfield      #5                  // Field oneoffDisposables:Ljava/util/List;
      34: aload_1
      35: invokeinterface #11,  2           // InterfaceMethod java/util/List.add:(Ljava/lang/Object;)Z
      40: pop
      41: aload_2
      42: monitorexit
      43: goto          51
      46: astore_3
      47: aload_2
      48: monitorexit
      49: aload_3
      50: athrow
      51: return
    Exception table:
       from    to  target type
          17    43    46   any
          46    49    46   any

  public void removeDisposable(org.apache.dubbo.common.resource.Disposable);
    Code:
       0: aload_0
       1: getfield      #5                  // Field oneoffDisposables:Ljava/util/List;
       4: aload_1
       5: invokeinterface #10,  2           // InterfaceMethod java/util/List.contains:(Ljava/lang/Object;)Z
      10: ifeq          51
      13: aload_0
      14: dup
      15: astore_2
      16: monitorenter
      17: aload_0
      18: getfield      #5                  // Field oneoffDisposables:Ljava/util/List;
      21: aload_1
      22: invokeinterface #10,  2           // InterfaceMethod java/util/List.contains:(Ljava/lang/Object;)Z
      27: ifeq          41
      30: aload_0
      31: getfield      #5                  // Field oneoffDisposables:Ljava/util/List;
      34: aload_1
      35: invokeinterface #12,  2           // InterfaceMethod java/util/List.remove:(Ljava/lang/Object;)Z
      40: pop
      41: aload_2
      42: monitorexit
      43: goto          51
      46: astore_3
      47: aload_2
      48: monitorexit
      49: aload_3
      50: athrow
      51: return
    Exception table:
       from    to  target type
          17    43    46   any
          46    49    46   any

  public static java.util.List<org.apache.dubbo.common.resource.Disposable> getGlobalReusedDisposables();
    Code:
       0: getstatic     #9                  // Field globalReusedDisposables:Ljava/util/List;
       3: areturn

  public java.util.List<org.apache.dubbo.common.resource.Disposable> getOneoffDisposables();
    Code:
       0: aload_0
       1: getfield      #5                  // Field oneoffDisposables:Ljava/util/List;
       4: areturn

  static {};
    Code:
       0: ldc           #7                  // class org/apache/dubbo/common/resource/GlobalResourcesRepository
       2: invokestatic  #46                 // Method org/apache/dubbo/common/logger/LoggerFactory.getErrorTypeAwareLogger:(Ljava/lang/Class;)Lorg/apache/dubbo/common/logger/ErrorTypeAwareLogger;
       5: putstatic     #17                 // Field logger:Lorg/apache/dubbo/common/logger/ErrorTypeAwareLogger;
       8: new           #3                  // class java/util/concurrent/CopyOnWriteArrayList
      11: dup
      12: invokespecial #4                  // Method java/util/concurrent/CopyOnWriteArrayList."<init>":()V
      15: putstatic     #9                  // Field globalReusedDisposables:Ljava/util/List;
      18: return
}
