Compiled from "GlobalResourceInitializer.java"
public class org.apache.dubbo.common.resource.GlobalResourceInitializer<T> extends org.apache.dubbo.common.concurrent.CallableSafeInitializer<T> {
  private java.util.function.Consumer<T> disposeAction;

  private org.apache.dubbo.common.resource.Disposable disposable;

  public org.apache.dubbo.common.resource.GlobalResourceInitializer(java.util.concurrent.Callable<T>);
    Code:
       0: aload_0
       1: aload_1
       2: invokespecial #1                  // Method org/apache/dubbo/common/concurrent/CallableSafeInitializer."<init>":(Ljava/util/concurrent/Callable;)V
       5: return

  public org.apache.dubbo.common.resource.GlobalResourceInitializer(java.util.concurrent.Callable<T>, java.util.function.Consumer<T>);
    Code:
       0: aload_0
       1: aload_1
       2: invokespecial #1                  // Method org/apache/dubbo/common/concurrent/CallableSafeInitializer."<init>":(Ljava/util/concurrent/Callable;)V
       5: aload_0
       6: aload_2
       7: putfield      #2                  // Field disposeAction:Ljava/util/function/Consumer;
      10: return

  public org.apache.dubbo.common.resource.GlobalResourceInitializer(java.util.concurrent.Callable<T>, org.apache.dubbo.common.resource.Disposable);
    Code:
       0: aload_0
       1: aload_1
       2: invokespecial #1                  // Method org/apache/dubbo/common/concurrent/CallableSafeInitializer."<init>":(Ljava/util/concurrent/Callable;)V
       5: aload_0
       6: aload_2
       7: putfield      #3                  // Field disposable:Lorg/apache/dubbo/common/resource/Disposable;
      10: return

  protected T initialize();
    Code:
       0: aload_0
       1: invokespecial #4                  // Method org/apache/dubbo/common/concurrent/CallableSafeInitializer.initialize:()Ljava/lang/Object;
       4: astore_1
       5: aload_0
       6: getfield      #3                  // Field disposable:Lorg/apache/dubbo/common/resource/Disposable;
       9: ifnull        25
      12: invokestatic  #5                  // Method org/apache/dubbo/common/resource/GlobalResourcesRepository.getInstance:()Lorg/apache/dubbo/common/resource/GlobalResourcesRepository;
      15: aload_0
      16: getfield      #3                  // Field disposable:Lorg/apache/dubbo/common/resource/Disposable;
      19: invokevirtual #6                  // Method org/apache/dubbo/common/resource/GlobalResourcesRepository.registerDisposable:(Lorg/apache/dubbo/common/resource/Disposable;)V
      22: goto          37
      25: invokestatic  #5                  // Method org/apache/dubbo/common/resource/GlobalResourcesRepository.getInstance:()Lorg/apache/dubbo/common/resource/GlobalResourcesRepository;
      28: aload_0
      29: invokedynamic #7,  0              // InvokeDynamic #0:destroy:(Lorg/apache/dubbo/common/resource/GlobalResourceInitializer;)Lorg/apache/dubbo/common/resource/Disposable;
      34: invokevirtual #6                  // Method org/apache/dubbo/common/resource/GlobalResourcesRepository.registerDisposable:(Lorg/apache/dubbo/common/resource/Disposable;)V
      37: aload_1
      38: areturn

  private void lambda$initialize$0();
    Code:
       0: aload_0
       1: aload_0
       2: getfield      #2                  // Field disposeAction:Ljava/util/function/Consumer;
       5: invokevirtual #8                  // Method remove:(Ljava/util/function/Consumer;)Ljava/lang/Object;
       8: pop
       9: return
}
