Compiled from "AbstractDoCoMoResultParser.java"
abstract class com.google.zxing.client.result.AbstractDoCoMoResultParser extends com.google.zxing.client.result.ResultParser {
  com.google.zxing.client.result.AbstractDoCoMoResultParser();
    Code:
       0: aload_0
       1: invokespecial #1                  // Method com/google/zxing/client/result/ResultParser."<init>":()V
       4: return

  static java.lang.String[] matchDoCoMoPrefixedField(java.lang.String, java.lang.String);
    Code:
       0: aload_0
       1: aload_1
       2: bipush        59
       4: iconst_1
       5: invokestatic  #2                  // Method matchPrefixedField:(Ljava/lang/String;Ljava/lang/String;CZ)[Ljava/lang/String;
       8: areturn

  static java.lang.String matchSingleDoCoMoPrefixedField(java.lang.String, java.lang.String, boolean);
    Code:
       0: aload_0
       1: aload_1
       2: bipush        59
       4: iload_2
       5: invokestatic  #3                  // Method matchSinglePrefixedField:(Ljava/lang/String;Ljava/lang/String;CZ)Ljava/lang/String;
       8: areturn
}
