Compiled from "AddressBookParsedResult.java"
public final class com.google.zxing.client.result.AddressBookParsedResult extends com.google.zxing.client.result.ParsedResult {
  private final java.lang.String[] names;

  private final java.lang.String[] nicknames;

  private final java.lang.String pronunciation;

  private final java.lang.String[] phoneNumbers;

  private final java.lang.String[] phoneTypes;

  private final java.lang.String[] emails;

  private final java.lang.String[] emailTypes;

  private final java.lang.String instantMessenger;

  private final java.lang.String note;

  private final java.lang.String[] addresses;

  private final java.lang.String[] addressTypes;

  private final java.lang.String org;

  private final java.lang.String birthday;

  private final java.lang.String title;

  private final java.lang.String[] urls;

  private final java.lang.String[] geo;

  public com.google.zxing.client.result.AddressBookParsedResult(java.lang.String[], java.lang.String[], java.lang.String[], java.lang.String[], java.lang.String[], java.lang.String[], java.lang.String[]);
    Code:
       0: aload_0
       1: aload_1
       2: aconst_null
       3: aconst_null
       4: aload_2
       5: aload_3
       6: aload         4
       8: aload         5
      10: aconst_null
      11: aconst_null
      12: aload         6
      14: aload         7
      16: aconst_null
      17: aconst_null
      18: aconst_null
      19: aconst_null
      20: aconst_null
      21: invokespecial #1                  // Method "<init>":([Ljava/lang/String;[Ljava/lang/String;Ljava/lang/String;[Ljava/lang/String;[Ljava/lang/String;[Ljava/lang/String;[Ljava/lang/String;Ljava/lang/String;Ljava/lang/String;[Ljava/lang/String;[Ljava/lang/String;Ljava/lang/String;Ljava/lang/String;Ljava/lang/String;[Ljava/lang/String;[Ljava/lang/String;)V
      24: return

  public com.google.zxing.client.result.AddressBookParsedResult(java.lang.String[], java.lang.String[], java.lang.String, java.lang.String[], java.lang.String[], java.lang.String[], java.lang.String[], java.lang.String, java.lang.String, java.lang.String[], java.lang.String[], java.lang.String, java.lang.String, java.lang.String, java.lang.String[], java.lang.String[]);
    Code:
       0: aload_0
       1: getstatic     #2                  // Field com/google/zxing/client/result/ParsedResultType.ADDRESSBOOK:Lcom/google/zxing/client/result/ParsedResultType;
       4: invokespecial #3                  // Method com/google/zxing/client/result/ParsedResult."<init>":(Lcom/google/zxing/client/result/ParsedResultType;)V
       7: aload         4
       9: ifnull        36
      12: aload         5
      14: ifnull        36
      17: aload         4
      19: arraylength
      20: aload         5
      22: arraylength
      23: if_icmpeq     36
      26: new           #4                  // class java/lang/IllegalArgumentException
      29: dup
      30: ldc           #5                  // String Phone numbers and types lengths differ
      32: invokespecial #6                  // Method java/lang/IllegalArgumentException."<init>":(Ljava/lang/String;)V
      35: athrow
      36: aload         6
      38: ifnull        65
      41: aload         7
      43: ifnull        65
      46: aload         6
      48: arraylength
      49: aload         7
      51: arraylength
      52: if_icmpeq     65
      55: new           #4                  // class java/lang/IllegalArgumentException
      58: dup
      59: ldc           #7                  // String Emails and types lengths differ
      61: invokespecial #6                  // Method java/lang/IllegalArgumentException."<init>":(Ljava/lang/String;)V
      64: athrow
      65: aload         10
      67: ifnull        94
      70: aload         11
      72: ifnull        94
      75: aload         10
      77: arraylength
      78: aload         11
      80: arraylength
      81: if_icmpeq     94
      84: new           #4                  // class java/lang/IllegalArgumentException
      87: dup
      88: ldc           #8                  // String Addresses and types lengths differ
      90: invokespecial #6                  // Method java/lang/IllegalArgumentException."<init>":(Ljava/lang/String;)V
      93: athrow
      94: aload_0
      95: aload_1
      96: putfield      #9                  // Field names:[Ljava/lang/String;
      99: aload_0
     100: aload_2
     101: putfield      #10                 // Field nicknames:[Ljava/lang/String;
     104: aload_0
     105: aload_3
     106: putfield      #11                 // Field pronunciation:Ljava/lang/String;
     109: aload_0
     110: aload         4
     112: putfield      #12                 // Field phoneNumbers:[Ljava/lang/String;
     115: aload_0
     116: aload         5
     118: putfield      #13                 // Field phoneTypes:[Ljava/lang/String;
     121: aload_0
     122: aload         6
     124: putfield      #14                 // Field emails:[Ljava/lang/String;
     127: aload_0
     128: aload         7
     130: putfield      #15                 // Field emailTypes:[Ljava/lang/String;
     133: aload_0
     134: aload         8
     136: putfield      #16                 // Field instantMessenger:Ljava/lang/String;
     139: aload_0
     140: aload         9
     142: putfield      #17                 // Field note:Ljava/lang/String;
     145: aload_0
     146: aload         10
     148: putfield      #18                 // Field addresses:[Ljava/lang/String;
     151: aload_0
     152: aload         11
     154: putfield      #19                 // Field addressTypes:[Ljava/lang/String;
     157: aload_0
     158: aload         12
     160: putfield      #20                 // Field org:Ljava/lang/String;
     163: aload_0
     164: aload         13
     166: putfield      #21                 // Field birthday:Ljava/lang/String;
     169: aload_0
     170: aload         14
     172: putfield      #22                 // Field title:Ljava/lang/String;
     175: aload_0
     176: aload         15
     178: putfield      #23                 // Field urls:[Ljava/lang/String;
     181: aload_0
     182: aload         16
     184: putfield      #24                 // Field geo:[Ljava/lang/String;
     187: return

  public java.lang.String[] getNames();
    Code:
       0: aload_0
       1: getfield      #9                  // Field names:[Ljava/lang/String;
       4: areturn

  public java.lang.String[] getNicknames();
    Code:
       0: aload_0
       1: getfield      #10                 // Field nicknames:[Ljava/lang/String;
       4: areturn

  public java.lang.String getPronunciation();
    Code:
       0: aload_0
       1: getfield      #11                 // Field pronunciation:Ljava/lang/String;
       4: areturn

  public java.lang.String[] getPhoneNumbers();
    Code:
       0: aload_0
       1: getfield      #12                 // Field phoneNumbers:[Ljava/lang/String;
       4: areturn

  public java.lang.String[] getPhoneTypes();
    Code:
       0: aload_0
       1: getfield      #13                 // Field phoneTypes:[Ljava/lang/String;
       4: areturn

  public java.lang.String[] getEmails();
    Code:
       0: aload_0
       1: getfield      #14                 // Field emails:[Ljava/lang/String;
       4: areturn

  public java.lang.String[] getEmailTypes();
    Code:
       0: aload_0
       1: getfield      #15                 // Field emailTypes:[Ljava/lang/String;
       4: areturn

  public java.lang.String getInstantMessenger();
    Code:
       0: aload_0
       1: getfield      #16                 // Field instantMessenger:Ljava/lang/String;
       4: areturn

  public java.lang.String getNote();
    Code:
       0: aload_0
       1: getfield      #17                 // Field note:Ljava/lang/String;
       4: areturn

  public java.lang.String[] getAddresses();
    Code:
       0: aload_0
       1: getfield      #18                 // Field addresses:[Ljava/lang/String;
       4: areturn

  public java.lang.String[] getAddressTypes();
    Code:
       0: aload_0
       1: getfield      #19                 // Field addressTypes:[Ljava/lang/String;
       4: areturn

  public java.lang.String getTitle();
    Code:
       0: aload_0
       1: getfield      #22                 // Field title:Ljava/lang/String;
       4: areturn

  public java.lang.String getOrg();
    Code:
       0: aload_0
       1: getfield      #20                 // Field org:Ljava/lang/String;
       4: areturn

  public java.lang.String[] getURLs();
    Code:
       0: aload_0
       1: getfield      #23                 // Field urls:[Ljava/lang/String;
       4: areturn

  public java.lang.String getBirthday();
    Code:
       0: aload_0
       1: getfield      #21                 // Field birthday:Ljava/lang/String;
       4: areturn

  public java.lang.String[] getGeo();
    Code:
       0: aload_0
       1: getfield      #24                 // Field geo:[Ljava/lang/String;
       4: areturn

  public java.lang.String getDisplayResult();
    Code:
       0: new           #25                 // class java/lang/StringBuilder
       3: dup
       4: bipush        100
       6: invokespecial #26                 // Method java/lang/StringBuilder."<init>":(I)V
       9: astore_1
      10: aload_0
      11: getfield      #9                  // Field names:[Ljava/lang/String;
      14: aload_1
      15: invokestatic  #27                 // Method maybeAppend:([Ljava/lang/String;Ljava/lang/StringBuilder;)V
      18: aload_0
      19: getfield      #10                 // Field nicknames:[Ljava/lang/String;
      22: aload_1
      23: invokestatic  #27                 // Method maybeAppend:([Ljava/lang/String;Ljava/lang/StringBuilder;)V
      26: aload_0
      27: getfield      #11                 // Field pronunciation:Ljava/lang/String;
      30: aload_1
      31: invokestatic  #28                 // Method maybeAppend:(Ljava/lang/String;Ljava/lang/StringBuilder;)V
      34: aload_0
      35: getfield      #22                 // Field title:Ljava/lang/String;
      38: aload_1
      39: invokestatic  #28                 // Method maybeAppend:(Ljava/lang/String;Ljava/lang/StringBuilder;)V
      42: aload_0
      43: getfield      #20                 // Field org:Ljava/lang/String;
      46: aload_1
      47: invokestatic  #28                 // Method maybeAppend:(Ljava/lang/String;Ljava/lang/StringBuilder;)V
      50: aload_0
      51: getfield      #18                 // Field addresses:[Ljava/lang/String;
      54: aload_1
      55: invokestatic  #27                 // Method maybeAppend:([Ljava/lang/String;Ljava/lang/StringBuilder;)V
      58: aload_0
      59: getfield      #12                 // Field phoneNumbers:[Ljava/lang/String;
      62: aload_1
      63: invokestatic  #27                 // Method maybeAppend:([Ljava/lang/String;Ljava/lang/StringBuilder;)V
      66: aload_0
      67: getfield      #14                 // Field emails:[Ljava/lang/String;
      70: aload_1
      71: invokestatic  #27                 // Method maybeAppend:([Ljava/lang/String;Ljava/lang/StringBuilder;)V
      74: aload_0
      75: getfield      #16                 // Field instantMessenger:Ljava/lang/String;
      78: aload_1
      79: invokestatic  #28                 // Method maybeAppend:(Ljava/lang/String;Ljava/lang/StringBuilder;)V
      82: aload_0
      83: getfield      #23                 // Field urls:[Ljava/lang/String;
      86: aload_1
      87: invokestatic  #27                 // Method maybeAppend:([Ljava/lang/String;Ljava/lang/StringBuilder;)V
      90: aload_0
      91: getfield      #21                 // Field birthday:Ljava/lang/String;
      94: aload_1
      95: invokestatic  #28                 // Method maybeAppend:(Ljava/lang/String;Ljava/lang/StringBuilder;)V
      98: aload_0
      99: getfield      #24                 // Field geo:[Ljava/lang/String;
     102: aload_1
     103: invokestatic  #27                 // Method maybeAppend:([Ljava/lang/String;Ljava/lang/StringBuilder;)V
     106: aload_0
     107: getfield      #17                 // Field note:Ljava/lang/String;
     110: aload_1
     111: invokestatic  #28                 // Method maybeAppend:(Ljava/lang/String;Ljava/lang/StringBuilder;)V
     114: aload_1
     115: invokevirtual #29                 // Method java/lang/StringBuilder.toString:()Ljava/lang/String;
     118: areturn
}
