Compiled from "AddressBookDoCoMoResultParser.java"
public final class com.google.zxing.client.result.AddressBookDoCoMoResultParser extends com.google.zxing.client.result.AbstractDoCoMoResultParser {
  public com.google.zxing.client.result.AddressBookDoCoMoResultParser();
    Code:
       0: aload_0
       1: invokespecial #1                  // Method com/google/zxing/client/result/AbstractDoCoMoResultParser."<init>":()V
       4: return

  public com.google.zxing.client.result.AddressBookParsedResult parse(com.google.zxing.Result);
    Code:
       0: aload_1
       1: invokestatic  #2                  // Method getMassagedText:(Lcom/google/zxing/Result;)Ljava/lang/String;
       4: astore_2
       5: aload_2
       6: ldc           #3                  // String MECARD:
       8: invokevirtual #4                  // Method java/lang/String.startsWith:(Ljava/lang/String;)Z
      11: ifne          16
      14: aconst_null
      15: areturn
      16: ldc           #5                  // String N:
      18: aload_2
      19: invokestatic  #6                  // Method matchDoCoMoPrefixedField:(Ljava/lang/String;Ljava/lang/String;)[Ljava/lang/String;
      22: astore_3
      23: aload_3
      24: ifnonnull     29
      27: aconst_null
      28: areturn
      29: aload_3
      30: iconst_0
      31: aaload
      32: invokestatic  #7                  // Method parseName:(Ljava/lang/String;)Ljava/lang/String;
      35: astore        4
      37: ldc           #8                  // String SOUND:
      39: aload_2
      40: iconst_1
      41: invokestatic  #9                  // Method matchSingleDoCoMoPrefixedField:(Ljava/lang/String;Ljava/lang/String;Z)Ljava/lang/String;
      44: astore        5
      46: ldc           #10                 // String TEL:
      48: aload_2
      49: invokestatic  #6                  // Method matchDoCoMoPrefixedField:(Ljava/lang/String;Ljava/lang/String;)[Ljava/lang/String;
      52: astore        6
      54: ldc           #11                 // String EMAIL:
      56: aload_2
      57: invokestatic  #6                  // Method matchDoCoMoPrefixedField:(Ljava/lang/String;Ljava/lang/String;)[Ljava/lang/String;
      60: astore        7
      62: ldc           #12                 // String NOTE:
      64: aload_2
      65: iconst_0
      66: invokestatic  #9                  // Method matchSingleDoCoMoPrefixedField:(Ljava/lang/String;Ljava/lang/String;Z)Ljava/lang/String;
      69: astore        8
      71: ldc           #13                 // String ADR:
      73: aload_2
      74: invokestatic  #6                  // Method matchDoCoMoPrefixedField:(Ljava/lang/String;Ljava/lang/String;)[Ljava/lang/String;
      77: astore        9
      79: ldc           #14                 // String BDAY:
      81: aload_2
      82: iconst_1
      83: invokestatic  #9                  // Method matchSingleDoCoMoPrefixedField:(Ljava/lang/String;Ljava/lang/String;Z)Ljava/lang/String;
      86: astore        10
      88: aload         10
      90: bipush        8
      92: invokestatic  #15                 // Method isStringOfDigits:(Ljava/lang/CharSequence;I)Z
      95: ifne          101
      98: aconst_null
      99: astore        10
     101: ldc           #16                 // String URL:
     103: aload_2
     104: invokestatic  #6                  // Method matchDoCoMoPrefixedField:(Ljava/lang/String;Ljava/lang/String;)[Ljava/lang/String;
     107: astore        11
     109: ldc           #17                 // String ORG:
     111: aload_2
     112: iconst_1
     113: invokestatic  #9                  // Method matchSingleDoCoMoPrefixedField:(Ljava/lang/String;Ljava/lang/String;Z)Ljava/lang/String;
     116: astore        12
     118: new           #18                 // class com/google/zxing/client/result/AddressBookParsedResult
     121: dup
     122: aload         4
     124: invokestatic  #19                 // Method maybeWrap:(Ljava/lang/String;)[Ljava/lang/String;
     127: aconst_null
     128: aload         5
     130: aload         6
     132: aconst_null
     133: aload         7
     135: aconst_null
     136: aconst_null
     137: aload         8
     139: aload         9
     141: aconst_null
     142: aload         12
     144: aload         10
     146: aconst_null
     147: aload         11
     149: aconst_null
     150: invokespecial #20                 // Method com/google/zxing/client/result/AddressBookParsedResult."<init>":([Ljava/lang/String;[Ljava/lang/String;Ljava/lang/String;[Ljava/lang/String;[Ljava/lang/String;[Ljava/lang/String;[Ljava/lang/String;Ljava/lang/String;Ljava/lang/String;[Ljava/lang/String;[Ljava/lang/String;Ljava/lang/String;Ljava/lang/String;Ljava/lang/String;[Ljava/lang/String;[Ljava/lang/String;)V
     153: areturn

  private static java.lang.String parseName(java.lang.String);
    Code:
       0: aload_0
       1: bipush        44
       3: invokevirtual #21                 // Method java/lang/String.indexOf:(I)I
       6: istore_1
       7: iload_1
       8: iflt          46
      11: new           #22                 // class java/lang/StringBuilder
      14: dup
      15: invokespecial #23                 // Method java/lang/StringBuilder."<init>":()V
      18: aload_0
      19: iload_1
      20: iconst_1
      21: iadd
      22: invokevirtual #24                 // Method java/lang/String.substring:(I)Ljava/lang/String;
      25: invokevirtual #25                 // Method java/lang/StringBuilder.append:(Ljava/lang/String;)Ljava/lang/StringBuilder;
      28: bipush        32
      30: invokevirtual #26                 // Method java/lang/StringBuilder.append:(C)Ljava/lang/StringBuilder;
      33: aload_0
      34: iconst_0
      35: iload_1
      36: invokevirtual #27                 // Method java/lang/String.substring:(II)Ljava/lang/String;
      39: invokevirtual #25                 // Method java/lang/StringBuilder.append:(Ljava/lang/String;)Ljava/lang/StringBuilder;
      42: invokevirtual #28                 // Method java/lang/StringBuilder.toString:()Ljava/lang/String;
      45: areturn
      46: aload_0
      47: areturn

  public com.google.zxing.client.result.ParsedResult parse(com.google.zxing.Result);
    Code:
       0: aload_0
       1: aload_1
       2: invokevirtual #29                 // Method parse:(Lcom/google/zxing/Result;)Lcom/google/zxing/client/result/AddressBookParsedResult;
       5: areturn
}
