Compiled from "BookmarkDoCoMoResultParser.java"
public final class com.google.zxing.client.result.BookmarkDoCoMoResultParser extends com.google.zxing.client.result.AbstractDoCoMoResultParser {
  public com.google.zxing.client.result.BookmarkDoCoMoResultParser();
    Code:
       0: aload_0
       1: invokespecial #1                  // Method com/google/zxing/client/result/AbstractDoCoMoResultParser."<init>":()V
       4: return

  public com.google.zxing.client.result.URIParsedResult parse(com.google.zxing.Result);
    Code:
       0: aload_1
       1: invokevirtual #2                  // Method com/google/zxing/Result.getText:()Ljava/lang/String;
       4: astore_2
       5: aload_2
       6: ldc           #3                  // String MEBKM:
       8: invokevirtual #4                  // Method java/lang/String.startsWith:(Ljava/lang/String;)Z
      11: ifne          16
      14: aconst_null
      15: areturn
      16: ldc           #5                  // String TITLE:
      18: aload_2
      19: iconst_1
      20: invokestatic  #6                  // Method matchSingleDoCoMoPrefixedField:(Ljava/lang/String;Ljava/lang/String;Z)Ljava/lang/String;
      23: astore_3
      24: ldc           #7                  // String URL:
      26: aload_2
      27: invokestatic  #8                  // Method matchDoCoMoPrefixedField:(Ljava/lang/String;Ljava/lang/String;)[Ljava/lang/String;
      30: astore        4
      32: aload         4
      34: ifnonnull     39
      37: aconst_null
      38: areturn
      39: aload         4
      41: iconst_0
      42: aaload
      43: astore        5
      45: aload         5
      47: invokestatic  #9                  // Method com/google/zxing/client/result/URIResultParser.isBasicallyValidURI:(Ljava/lang/String;)Z
      50: ifeq          66
      53: new           #10                 // class com/google/zxing/client/result/URIParsedResult
      56: dup
      57: aload         5
      59: aload_3
      60: invokespecial #11                 // Method com/google/zxing/client/result/URIParsedResult."<init>":(Ljava/lang/String;Ljava/lang/String;)V
      63: goto          67
      66: aconst_null
      67: areturn

  public com.google.zxing.client.result.ParsedResult parse(com.google.zxing.Result);
    Code:
       0: aload_0
       1: aload_1
       2: invokevirtual #12                 // Method parse:(Lcom/google/zxing/Result;)Lcom/google/zxing/client/result/URIParsedResult;
       5: areturn
}
