Compiled from "EmailDoCoMoResultParser.java"
public final class com.google.zxing.client.result.EmailDoCoMoResultParser extends com.google.zxing.client.result.AbstractDoCoMoResultParser {
  private static final java.util.regex.Pattern ATEXT_ALPHANUMERIC;

  public com.google.zxing.client.result.EmailDoCoMoResultParser();
    Code:
       0: aload_0
       1: invokespecial #1                  // Method com/google/zxing/client/result/AbstractDoCoMoResultParser."<init>":()V
       4: return

  public com.google.zxing.client.result.EmailAddressParsedResult parse(com.google.zxing.Result);
    Code:
       0: aload_1
       1: invokestatic  #2                  // Method getMassagedText:(Lcom/google/zxing/Result;)Ljava/lang/String;
       4: astore_2
       5: aload_2
       6: ldc           #3                  // String MATMSG:
       8: invokevirtual #4                  // Method java/lang/String.startsWith:(Ljava/lang/String;)Z
      11: ifne          16
      14: aconst_null
      15: areturn
      16: ldc           #5                  // String TO:
      18: aload_2
      19: invokestatic  #6                  // Method matchDoCoMoPrefixedField:(Ljava/lang/String;Ljava/lang/String;)[Ljava/lang/String;
      22: astore_3
      23: aload_3
      24: ifnonnull     29
      27: aconst_null
      28: areturn
      29: aload_3
      30: astore        4
      32: aload         4
      34: arraylength
      35: istore        5
      37: iconst_0
      38: istore        6
      40: iload         6
      42: iload         5
      44: if_icmpge     70
      47: aload         4
      49: iload         6
      51: aaload
      52: astore        7
      54: aload         7
      56: invokestatic  #7                  // Method isBasicallyValidEmailAddress:(Ljava/lang/String;)Z
      59: ifne          64
      62: aconst_null
      63: areturn
      64: iinc          6, 1
      67: goto          40
      70: ldc           #8                  // String SUB:
      72: aload_2
      73: iconst_0
      74: invokestatic  #9                  // Method matchSingleDoCoMoPrefixedField:(Ljava/lang/String;Ljava/lang/String;Z)Ljava/lang/String;
      77: astore        4
      79: ldc           #10                 // String BODY:
      81: aload_2
      82: iconst_0
      83: invokestatic  #9                  // Method matchSingleDoCoMoPrefixedField:(Ljava/lang/String;Ljava/lang/String;Z)Ljava/lang/String;
      86: astore        5
      88: new           #11                 // class com/google/zxing/client/result/EmailAddressParsedResult
      91: dup
      92: aload_3
      93: aconst_null
      94: aconst_null
      95: aload         4
      97: aload         5
      99: invokespecial #12                 // Method com/google/zxing/client/result/EmailAddressParsedResult."<init>":([Ljava/lang/String;[Ljava/lang/String;[Ljava/lang/String;Ljava/lang/String;Ljava/lang/String;)V
     102: areturn

  static boolean isBasicallyValidEmailAddress(java.lang.String);
    Code:
       0: aload_0
       1: ifnull        30
       4: getstatic     #13                 // Field ATEXT_ALPHANUMERIC:Ljava/util/regex/Pattern;
       7: aload_0
       8: invokevirtual #14                 // Method java/util/regex/Pattern.matcher:(Ljava/lang/CharSequence;)Ljava/util/regex/Matcher;
      11: invokevirtual #15                 // Method java/util/regex/Matcher.matches:()Z
      14: ifeq          30
      17: aload_0
      18: bipush        64
      20: invokevirtual #16                 // Method java/lang/String.indexOf:(I)I
      23: iflt          30
      26: iconst_1
      27: goto          31
      30: iconst_0
      31: ireturn

  public com.google.zxing.client.result.ParsedResult parse(com.google.zxing.Result);
    Code:
       0: aload_0
       1: aload_1
       2: invokevirtual #17                 // Method parse:(Lcom/google/zxing/Result;)Lcom/google/zxing/client/result/EmailAddressParsedResult;
       5: areturn

  static {};
    Code:
       0: ldc           #18                 // String [a-zA-Z0-9@.!#$%&\'*+\\-/=?^_`{|}~]+
       2: invokestatic  #19                 // Method java/util/regex/Pattern.compile:(Ljava/lang/String;)Ljava/util/regex/Pattern;
       5: putstatic     #13                 // Field ATEXT_ALPHANUMERIC:Ljava/util/regex/Pattern;
       8: return
}
