Compiled from "EmailAddressParsedResult.java"
public final class com.google.zxing.client.result.EmailAddressParsedResult extends com.google.zxing.client.result.ParsedResult {
  private final java.lang.String[] tos;

  private final java.lang.String[] ccs;

  private final java.lang.String[] bccs;

  private final java.lang.String subject;

  private final java.lang.String body;

  com.google.zxing.client.result.EmailAddressParsedResult(java.lang.String);
    Code:
       0: aload_0
       1: iconst_1
       2: anewarray     #1                  // class java/lang/String
       5: dup
       6: iconst_0
       7: aload_1
       8: aastore
       9: aconst_null
      10: aconst_null
      11: aconst_null
      12: aconst_null
      13: invokespecial #2                  // Method "<init>":([Ljava/lang/String;[Ljava/lang/String;[Ljava/lang/String;Ljava/lang/String;Ljava/lang/String;)V
      16: return

  com.google.zxing.client.result.EmailAddressParsedResult(java.lang.String[], java.lang.String[], java.lang.String[], java.lang.String, java.lang.String);
    Code:
       0: aload_0
       1: getstatic     #3                  // Field com/google/zxing/client/result/ParsedResultType.EMAIL_ADDRESS:Lcom/google/zxing/client/result/ParsedResultType;
       4: invokespecial #4                  // Method com/google/zxing/client/result/ParsedResult."<init>":(Lcom/google/zxing/client/result/ParsedResultType;)V
       7: aload_0
       8: aload_1
       9: putfield      #5                  // Field tos:[Ljava/lang/String;
      12: aload_0
      13: aload_2
      14: putfield      #6                  // Field ccs:[Ljava/lang/String;
      17: aload_0
      18: aload_3
      19: putfield      #7                  // Field bccs:[Ljava/lang/String;
      22: aload_0
      23: aload         4
      25: putfield      #8                  // Field subject:Ljava/lang/String;
      28: aload_0
      29: aload         5
      31: putfield      #9                  // Field body:Ljava/lang/String;
      34: return

  public java.lang.String getEmailAddress();
    Code:
       0: aload_0
       1: getfield      #5                  // Field tos:[Ljava/lang/String;
       4: ifnull        15
       7: aload_0
       8: getfield      #5                  // Field tos:[Ljava/lang/String;
      11: arraylength
      12: ifne          19
      15: aconst_null
      16: goto          25
      19: aload_0
      20: getfield      #5                  // Field tos:[Ljava/lang/String;
      23: iconst_0
      24: aaload
      25: areturn

  public java.lang.String[] getTos();
    Code:
       0: aload_0
       1: getfield      #5                  // Field tos:[Ljava/lang/String;
       4: areturn

  public java.lang.String[] getCCs();
    Code:
       0: aload_0
       1: getfield      #6                  // Field ccs:[Ljava/lang/String;
       4: areturn

  public java.lang.String[] getBCCs();
    Code:
       0: aload_0
       1: getfield      #7                  // Field bccs:[Ljava/lang/String;
       4: areturn

  public java.lang.String getSubject();
    Code:
       0: aload_0
       1: getfield      #8                  // Field subject:Ljava/lang/String;
       4: areturn

  public java.lang.String getBody();
    Code:
       0: aload_0
       1: getfield      #9                  // Field body:Ljava/lang/String;
       4: areturn

  public java.lang.String getMailtoURI();
    Code:
       0: ldc           #10                 // String mailto:
       2: areturn

  public java.lang.String getDisplayResult();
    Code:
       0: new           #11                 // class java/lang/StringBuilder
       3: dup
       4: bipush        30
       6: invokespecial #12                 // Method java/lang/StringBuilder."<init>":(I)V
       9: astore_1
      10: aload_0
      11: getfield      #5                  // Field tos:[Ljava/lang/String;
      14: aload_1
      15: invokestatic  #13                 // Method maybeAppend:([Ljava/lang/String;Ljava/lang/StringBuilder;)V
      18: aload_0
      19: getfield      #6                  // Field ccs:[Ljava/lang/String;
      22: aload_1
      23: invokestatic  #13                 // Method maybeAppend:([Ljava/lang/String;Ljava/lang/StringBuilder;)V
      26: aload_0
      27: getfield      #7                  // Field bccs:[Ljava/lang/String;
      30: aload_1
      31: invokestatic  #13                 // Method maybeAppend:([Ljava/lang/String;Ljava/lang/StringBuilder;)V
      34: aload_0
      35: getfield      #8                  // Field subject:Ljava/lang/String;
      38: aload_1
      39: invokestatic  #14                 // Method maybeAppend:(Ljava/lang/String;Ljava/lang/StringBuilder;)V
      42: aload_0
      43: getfield      #9                  // Field body:Ljava/lang/String;
      46: aload_1
      47: invokestatic  #14                 // Method maybeAppend:(Ljava/lang/String;Ljava/lang/StringBuilder;)V
      50: aload_1
      51: invokevirtual #15                 // Method java/lang/StringBuilder.toString:()Ljava/lang/String;
      54: areturn
}
