Compiled from "ExpandedProductParsedResult.java"
public final class com.google.zxing.client.result.ExpandedProductParsedResult extends com.google.zxing.client.result.ParsedResult {
  public static final java.lang.String KILOGRAM;

  public static final java.lang.String POUND;

  private final java.lang.String rawText;

  private final java.lang.String productID;

  private final java.lang.String sscc;

  private final java.lang.String lotNumber;

  private final java.lang.String productionDate;

  private final java.lang.String packagingDate;

  private final java.lang.String bestBeforeDate;

  private final java.lang.String expirationDate;

  private final java.lang.String weight;

  private final java.lang.String weightType;

  private final java.lang.String weightIncrement;

  private final java.lang.String price;

  private final java.lang.String priceIncrement;

  private final java.lang.String priceCurrency;

  private final java.util.Map<java.lang.String, java.lang.String> uncommonAIs;

  public com.google.zxing.client.result.ExpandedProductParsedResult(java.lang.String, java.lang.String, java.lang.String, java.lang.String, java.lang.String, java.lang.String, java.lang.String, java.lang.String, java.lang.String, java.lang.String, java.lang.String, java.lang.String, java.lang.String, java.lang.String, java.util.Map<java.lang.String, java.lang.String>);
    Code:
       0: aload_0
       1: getstatic     #1                  // Field com/google/zxing/client/result/ParsedResultType.PRODUCT:Lcom/google/zxing/client/result/ParsedResultType;
       4: invokespecial #2                  // Method com/google/zxing/client/result/ParsedResult."<init>":(Lcom/google/zxing/client/result/ParsedResultType;)V
       7: aload_0
       8: aload_1
       9: putfield      #3                  // Field rawText:Ljava/lang/String;
      12: aload_0
      13: aload_2
      14: putfield      #4                  // Field productID:Ljava/lang/String;
      17: aload_0
      18: aload_3
      19: putfield      #5                  // Field sscc:Ljava/lang/String;
      22: aload_0
      23: aload         4
      25: putfield      #6                  // Field lotNumber:Ljava/lang/String;
      28: aload_0
      29: aload         5
      31: putfield      #7                  // Field productionDate:Ljava/lang/String;
      34: aload_0
      35: aload         6
      37: putfield      #8                  // Field packagingDate:Ljava/lang/String;
      40: aload_0
      41: aload         7
      43: putfield      #9                  // Field bestBeforeDate:Ljava/lang/String;
      46: aload_0
      47: aload         8
      49: putfield      #10                 // Field expirationDate:Ljava/lang/String;
      52: aload_0
      53: aload         9
      55: putfield      #11                 // Field weight:Ljava/lang/String;
      58: aload_0
      59: aload         10
      61: putfield      #12                 // Field weightType:Ljava/lang/String;
      64: aload_0
      65: aload         11
      67: putfield      #13                 // Field weightIncrement:Ljava/lang/String;
      70: aload_0
      71: aload         12
      73: putfield      #14                 // Field price:Ljava/lang/String;
      76: aload_0
      77: aload         13
      79: putfield      #15                 // Field priceIncrement:Ljava/lang/String;
      82: aload_0
      83: aload         14
      85: putfield      #16                 // Field priceCurrency:Ljava/lang/String;
      88: aload_0
      89: aload         15
      91: putfield      #17                 // Field uncommonAIs:Ljava/util/Map;
      94: return

  public boolean equals(java.lang.Object);
    Code:
       0: aload_1
       1: instanceof    #18                 // class com/google/zxing/client/result/ExpandedProductParsedResult
       4: ifne          9
       7: iconst_0
       8: ireturn
       9: aload_1
      10: checkcast     #18                 // class com/google/zxing/client/result/ExpandedProductParsedResult
      13: astore_2
      14: aload_0
      15: getfield      #4                  // Field productID:Ljava/lang/String;
      18: aload_2
      19: getfield      #4                  // Field productID:Ljava/lang/String;
      22: invokestatic  #19                 // Method java/util/Objects.equals:(Ljava/lang/Object;Ljava/lang/Object;)Z
      25: ifeq          200
      28: aload_0
      29: getfield      #5                  // Field sscc:Ljava/lang/String;
      32: aload_2
      33: getfield      #5                  // Field sscc:Ljava/lang/String;
      36: invokestatic  #19                 // Method java/util/Objects.equals:(Ljava/lang/Object;Ljava/lang/Object;)Z
      39: ifeq          200
      42: aload_0
      43: getfield      #6                  // Field lotNumber:Ljava/lang/String;
      46: aload_2
      47: getfield      #6                  // Field lotNumber:Ljava/lang/String;
      50: invokestatic  #19                 // Method java/util/Objects.equals:(Ljava/lang/Object;Ljava/lang/Object;)Z
      53: ifeq          200
      56: aload_0
      57: getfield      #7                  // Field productionDate:Ljava/lang/String;
      60: aload_2
      61: getfield      #7                  // Field productionDate:Ljava/lang/String;
      64: invokestatic  #19                 // Method java/util/Objects.equals:(Ljava/lang/Object;Ljava/lang/Object;)Z
      67: ifeq          200
      70: aload_0
      71: getfield      #9                  // Field bestBeforeDate:Ljava/lang/String;
      74: aload_2
      75: getfield      #9                  // Field bestBeforeDate:Ljava/lang/String;
      78: invokestatic  #19                 // Method java/util/Objects.equals:(Ljava/lang/Object;Ljava/lang/Object;)Z
      81: ifeq          200
      84: aload_0
      85: getfield      #10                 // Field expirationDate:Ljava/lang/String;
      88: aload_2
      89: getfield      #10                 // Field expirationDate:Ljava/lang/String;
      92: invokestatic  #19                 // Method java/util/Objects.equals:(Ljava/lang/Object;Ljava/lang/Object;)Z
      95: ifeq          200
      98: aload_0
      99: getfield      #11                 // Field weight:Ljava/lang/String;
     102: aload_2
     103: getfield      #11                 // Field weight:Ljava/lang/String;
     106: invokestatic  #19                 // Method java/util/Objects.equals:(Ljava/lang/Object;Ljava/lang/Object;)Z
     109: ifeq          200
     112: aload_0
     113: getfield      #12                 // Field weightType:Ljava/lang/String;
     116: aload_2
     117: getfield      #12                 // Field weightType:Ljava/lang/String;
     120: invokestatic  #19                 // Method java/util/Objects.equals:(Ljava/lang/Object;Ljava/lang/Object;)Z
     123: ifeq          200
     126: aload_0
     127: getfield      #13                 // Field weightIncrement:Ljava/lang/String;
     130: aload_2
     131: getfield      #13                 // Field weightIncrement:Ljava/lang/String;
     134: invokestatic  #19                 // Method java/util/Objects.equals:(Ljava/lang/Object;Ljava/lang/Object;)Z
     137: ifeq          200
     140: aload_0
     141: getfield      #14                 // Field price:Ljava/lang/String;
     144: aload_2
     145: getfield      #14                 // Field price:Ljava/lang/String;
     148: invokestatic  #19                 // Method java/util/Objects.equals:(Ljava/lang/Object;Ljava/lang/Object;)Z
     151: ifeq          200
     154: aload_0
     155: getfield      #15                 // Field priceIncrement:Ljava/lang/String;
     158: aload_2
     159: getfield      #15                 // Field priceIncrement:Ljava/lang/String;
     162: invokestatic  #19                 // Method java/util/Objects.equals:(Ljava/lang/Object;Ljava/lang/Object;)Z
     165: ifeq          200
     168: aload_0
     169: getfield      #16                 // Field priceCurrency:Ljava/lang/String;
     172: aload_2
     173: getfield      #16                 // Field priceCurrency:Ljava/lang/String;
     176: invokestatic  #19                 // Method java/util/Objects.equals:(Ljava/lang/Object;Ljava/lang/Object;)Z
     179: ifeq          200
     182: aload_0
     183: getfield      #17                 // Field uncommonAIs:Ljava/util/Map;
     186: aload_2
     187: getfield      #17                 // Field uncommonAIs:Ljava/util/Map;
     190: invokestatic  #19                 // Method java/util/Objects.equals:(Ljava/lang/Object;Ljava/lang/Object;)Z
     193: ifeq          200
     196: iconst_1
     197: goto          201
     200: iconst_0
     201: ireturn

  public int hashCode();
    Code:
       0: aload_0
       1: getfield      #4                  // Field productID:Ljava/lang/String;
       4: invokestatic  #20                 // Method java/util/Objects.hashCode:(Ljava/lang/Object;)I
       7: istore_1
       8: iload_1
       9: aload_0
      10: getfield      #5                  // Field sscc:Ljava/lang/String;
      13: invokestatic  #20                 // Method java/util/Objects.hashCode:(Ljava/lang/Object;)I
      16: ixor
      17: istore_1
      18: iload_1
      19: aload_0
      20: getfield      #6                  // Field lotNumber:Ljava/lang/String;
      23: invokestatic  #20                 // Method java/util/Objects.hashCode:(Ljava/lang/Object;)I
      26: ixor
      27: istore_1
      28: iload_1
      29: aload_0
      30: getfield      #7                  // Field productionDate:Ljava/lang/String;
      33: invokestatic  #20                 // Method java/util/Objects.hashCode:(Ljava/lang/Object;)I
      36: ixor
      37: istore_1
      38: iload_1
      39: aload_0
      40: getfield      #9                  // Field bestBeforeDate:Ljava/lang/String;
      43: invokestatic  #20                 // Method java/util/Objects.hashCode:(Ljava/lang/Object;)I
      46: ixor
      47: istore_1
      48: iload_1
      49: aload_0
      50: getfield      #10                 // Field expirationDate:Ljava/lang/String;
      53: invokestatic  #20                 // Method java/util/Objects.hashCode:(Ljava/lang/Object;)I
      56: ixor
      57: istore_1
      58: iload_1
      59: aload_0
      60: getfield      #11                 // Field weight:Ljava/lang/String;
      63: invokestatic  #20                 // Method java/util/Objects.hashCode:(Ljava/lang/Object;)I
      66: ixor
      67: istore_1
      68: iload_1
      69: aload_0
      70: getfield      #12                 // Field weightType:Ljava/lang/String;
      73: invokestatic  #20                 // Method java/util/Objects.hashCode:(Ljava/lang/Object;)I
      76: ixor
      77: istore_1
      78: iload_1
      79: aload_0
      80: getfield      #13                 // Field weightIncrement:Ljava/lang/String;
      83: invokestatic  #20                 // Method java/util/Objects.hashCode:(Ljava/lang/Object;)I
      86: ixor
      87: istore_1
      88: iload_1
      89: aload_0
      90: getfield      #14                 // Field price:Ljava/lang/String;
      93: invokestatic  #20                 // Method java/util/Objects.hashCode:(Ljava/lang/Object;)I
      96: ixor
      97: istore_1
      98: iload_1
      99: aload_0
     100: getfield      #15                 // Field priceIncrement:Ljava/lang/String;
     103: invokestatic  #20                 // Method java/util/Objects.hashCode:(Ljava/lang/Object;)I
     106: ixor
     107: istore_1
     108: iload_1
     109: aload_0
     110: getfield      #16                 // Field priceCurrency:Ljava/lang/String;
     113: invokestatic  #20                 // Method java/util/Objects.hashCode:(Ljava/lang/Object;)I
     116: ixor
     117: istore_1
     118: iload_1
     119: aload_0
     120: getfield      #17                 // Field uncommonAIs:Ljava/util/Map;
     123: invokestatic  #20                 // Method java/util/Objects.hashCode:(Ljava/lang/Object;)I
     126: ixor
     127: istore_1
     128: iload_1
     129: ireturn

  public java.lang.String getRawText();
    Code:
       0: aload_0
       1: getfield      #3                  // Field rawText:Ljava/lang/String;
       4: areturn

  public java.lang.String getProductID();
    Code:
       0: aload_0
       1: getfield      #4                  // Field productID:Ljava/lang/String;
       4: areturn

  public java.lang.String getSscc();
    Code:
       0: aload_0
       1: getfield      #5                  // Field sscc:Ljava/lang/String;
       4: areturn

  public java.lang.String getLotNumber();
    Code:
       0: aload_0
       1: getfield      #6                  // Field lotNumber:Ljava/lang/String;
       4: areturn

  public java.lang.String getProductionDate();
    Code:
       0: aload_0
       1: getfield      #7                  // Field productionDate:Ljava/lang/String;
       4: areturn

  public java.lang.String getPackagingDate();
    Code:
       0: aload_0
       1: getfield      #8                  // Field packagingDate:Ljava/lang/String;
       4: areturn

  public java.lang.String getBestBeforeDate();
    Code:
       0: aload_0
       1: getfield      #9                  // Field bestBeforeDate:Ljava/lang/String;
       4: areturn

  public java.lang.String getExpirationDate();
    Code:
       0: aload_0
       1: getfield      #10                 // Field expirationDate:Ljava/lang/String;
       4: areturn

  public java.lang.String getWeight();
    Code:
       0: aload_0
       1: getfield      #11                 // Field weight:Ljava/lang/String;
       4: areturn

  public java.lang.String getWeightType();
    Code:
       0: aload_0
       1: getfield      #12                 // Field weightType:Ljava/lang/String;
       4: areturn

  public java.lang.String getWeightIncrement();
    Code:
       0: aload_0
       1: getfield      #13                 // Field weightIncrement:Ljava/lang/String;
       4: areturn

  public java.lang.String getPrice();
    Code:
       0: aload_0
       1: getfield      #14                 // Field price:Ljava/lang/String;
       4: areturn

  public java.lang.String getPriceIncrement();
    Code:
       0: aload_0
       1: getfield      #15                 // Field priceIncrement:Ljava/lang/String;
       4: areturn

  public java.lang.String getPriceCurrency();
    Code:
       0: aload_0
       1: getfield      #16                 // Field priceCurrency:Ljava/lang/String;
       4: areturn

  public java.util.Map<java.lang.String, java.lang.String> getUncommonAIs();
    Code:
       0: aload_0
       1: getfield      #17                 // Field uncommonAIs:Ljava/util/Map;
       4: areturn

  public java.lang.String getDisplayResult();
    Code:
       0: aload_0
       1: getfield      #3                  // Field rawText:Ljava/lang/String;
       4: invokestatic  #21                 // Method java/lang/String.valueOf:(Ljava/lang/Object;)Ljava/lang/String;
       7: areturn
}
