Compiled from "GeoParsedResult.java"
public final class com.google.zxing.client.result.GeoParsedResult extends com.google.zxing.client.result.ParsedResult {
  private final double latitude;

  private final double longitude;

  private final double altitude;

  private final java.lang.String query;

  com.google.zxing.client.result.GeoParsedResult(double, double, double, java.lang.String);
    Code:
       0: aload_0
       1: getstatic     #1                  // Field com/google/zxing/client/result/ParsedResultType.GEO:Lcom/google/zxing/client/result/ParsedResultType;
       4: invokespecial #2                  // Method com/google/zxing/client/result/ParsedResult."<init>":(Lcom/google/zxing/client/result/ParsedResultType;)V
       7: aload_0
       8: dload_1
       9: putfield      #3                  // Field latitude:D
      12: aload_0
      13: dload_3
      14: putfield      #4                  // Field longitude:D
      17: aload_0
      18: dload         5
      20: putfield      #5                  // Field altitude:D
      23: aload_0
      24: aload         7
      26: putfield      #6                  // Field query:Ljava/lang/String;
      29: return

  public java.lang.String getGeoURI();
    Code:
       0: new           #7                  // class java/lang/StringBuilder
       3: dup
       4: invokespecial #8                  // Method java/lang/StringBuilder."<init>":()V
       7: astore_1
       8: aload_1
       9: ldc           #9                  // String geo:
      11: invokevirtual #10                 // Method java/lang/StringBuilder.append:(Ljava/lang/String;)Ljava/lang/StringBuilder;
      14: pop
      15: aload_1
      16: aload_0
      17: getfield      #3                  // Field latitude:D
      20: invokevirtual #11                 // Method java/lang/StringBuilder.append:(D)Ljava/lang/StringBuilder;
      23: pop
      24: aload_1
      25: bipush        44
      27: invokevirtual #12                 // Method java/lang/StringBuilder.append:(C)Ljava/lang/StringBuilder;
      30: pop
      31: aload_1
      32: aload_0
      33: getfield      #4                  // Field longitude:D
      36: invokevirtual #11                 // Method java/lang/StringBuilder.append:(D)Ljava/lang/StringBuilder;
      39: pop
      40: aload_0
      41: getfield      #5                  // Field altitude:D
      44: dconst_0
      45: dcmpl
      46: ifle          65
      49: aload_1
      50: bipush        44
      52: invokevirtual #12                 // Method java/lang/StringBuilder.append:(C)Ljava/lang/StringBuilder;
      55: pop
      56: aload_1
      57: aload_0
      58: getfield      #5                  // Field altitude:D
      61: invokevirtual #11                 // Method java/lang/StringBuilder.append:(D)Ljava/lang/StringBuilder;
      64: pop
      65: aload_0
      66: getfield      #6                  // Field query:Ljava/lang/String;
      69: ifnull        88
      72: aload_1
      73: bipush        63
      75: invokevirtual #12                 // Method java/lang/StringBuilder.append:(C)Ljava/lang/StringBuilder;
      78: pop
      79: aload_1
      80: aload_0
      81: getfield      #6                  // Field query:Ljava/lang/String;
      84: invokevirtual #10                 // Method java/lang/StringBuilder.append:(Ljava/lang/String;)Ljava/lang/StringBuilder;
      87: pop
      88: aload_1
      89: invokevirtual #13                 // Method java/lang/StringBuilder.toString:()Ljava/lang/String;
      92: areturn

  public double getLatitude();
    Code:
       0: aload_0
       1: getfield      #3                  // Field latitude:D
       4: dreturn

  public double getLongitude();
    Code:
       0: aload_0
       1: getfield      #4                  // Field longitude:D
       4: dreturn

  public double getAltitude();
    Code:
       0: aload_0
       1: getfield      #5                  // Field altitude:D
       4: dreturn

  public java.lang.String getQuery();
    Code:
       0: aload_0
       1: getfield      #6                  // Field query:Ljava/lang/String;
       4: areturn

  public java.lang.String getDisplayResult();
    Code:
       0: new           #7                  // class java/lang/StringBuilder
       3: dup
       4: bipush        20
       6: invokespecial #14                 // Method java/lang/StringBuilder."<init>":(I)V
       9: astore_1
      10: aload_1
      11: aload_0
      12: getfield      #3                  // Field latitude:D
      15: invokevirtual #11                 // Method java/lang/StringBuilder.append:(D)Ljava/lang/StringBuilder;
      18: pop
      19: aload_1
      20: ldc           #15                 // String ,
      22: invokevirtual #10                 // Method java/lang/StringBuilder.append:(Ljava/lang/String;)Ljava/lang/StringBuilder;
      25: pop
      26: aload_1
      27: aload_0
      28: getfield      #4                  // Field longitude:D
      31: invokevirtual #11                 // Method java/lang/StringBuilder.append:(D)Ljava/lang/StringBuilder;
      34: pop
      35: aload_0
      36: getfield      #5                  // Field altitude:D
      39: dconst_0
      40: dcmpl
      41: ifle          67
      44: aload_1
      45: ldc           #15                 // String ,
      47: invokevirtual #10                 // Method java/lang/StringBuilder.append:(Ljava/lang/String;)Ljava/lang/StringBuilder;
      50: pop
      51: aload_1
      52: aload_0
      53: getfield      #5                  // Field altitude:D
      56: invokevirtual #11                 // Method java/lang/StringBuilder.append:(D)Ljava/lang/StringBuilder;
      59: pop
      60: aload_1
      61: bipush        109
      63: invokevirtual #12                 // Method java/lang/StringBuilder.append:(C)Ljava/lang/StringBuilder;
      66: pop
      67: aload_0
      68: getfield      #6                  // Field query:Ljava/lang/String;
      71: ifnull        97
      74: aload_1
      75: ldc           #16                 // String  (
      77: invokevirtual #10                 // Method java/lang/StringBuilder.append:(Ljava/lang/String;)Ljava/lang/StringBuilder;
      80: pop
      81: aload_1
      82: aload_0
      83: getfield      #6                  // Field query:Ljava/lang/String;
      86: invokevirtual #10                 // Method java/lang/StringBuilder.append:(Ljava/lang/String;)Ljava/lang/StringBuilder;
      89: pop
      90: aload_1
      91: bipush        41
      93: invokevirtual #12                 // Method java/lang/StringBuilder.append:(C)Ljava/lang/StringBuilder;
      96: pop
      97: aload_1
      98: invokevirtual #13                 // Method java/lang/StringBuilder.toString:()Ljava/lang/String;
     101: areturn
}
