Compiled from "ISBNParsedResult.java"
public final class com.google.zxing.client.result.ISBNParsedResult extends com.google.zxing.client.result.ParsedResult {
  private final java.lang.String isbn;

  com.google.zxing.client.result.ISBNParsedResult(java.lang.String);
    Code:
       0: aload_0
       1: getstatic     #1                  // Field com/google/zxing/client/result/ParsedResultType.ISBN:Lcom/google/zxing/client/result/ParsedResultType;
       4: invokespecial #2                  // Method com/google/zxing/client/result/ParsedResult."<init>":(Lcom/google/zxing/client/result/ParsedResultType;)V
       7: aload_0
       8: aload_1
       9: putfield      #3                  // Field isbn:Ljava/lang/String;
      12: return

  public java.lang.String getISBN();
    Code:
       0: aload_0
       1: getfield      #3                  // Field isbn:Ljava/lang/String;
       4: areturn

  public java.lang.String getDisplayResult();
    Code:
       0: aload_0
       1: getfield      #3                  // Field isbn:Ljava/lang/String;
       4: areturn
}
