Compiled from "ParsedResult.java"
public abstract class com.google.zxing.client.result.ParsedResult {
  private final com.google.zxing.client.result.ParsedResultType type;

  protected com.google.zxing.client.result.ParsedResult(com.google.zxing.client.result.ParsedResultType);
    Code:
       0: aload_0
       1: invokespecial #1                  // Method java/lang/Object."<init>":()V
       4: aload_0
       5: aload_1
       6: putfield      #2                  // Field type:Lcom/google/zxing/client/result/ParsedResultType;
       9: return

  public final com.google.zxing.client.result.ParsedResultType getType();
    Code:
       0: aload_0
       1: getfield      #2                  // Field type:Lcom/google/zxing/client/result/ParsedResultType;
       4: areturn

  public abstract java.lang.String getDisplayResult();

  public final java.lang.String toString();
    Code:
       0: aload_0
       1: invokevirtual #3                  // Method getDisplayResult:()Ljava/lang/String;
       4: areturn

  public static void maybeAppend(java.lang.String, java.lang.StringBuilder);
    Code:
       0: aload_0
       1: ifnull        31
       4: aload_0
       5: invokevirtual #4                  // Method java/lang/String.isEmpty:()Z
       8: ifne          31
      11: aload_1
      12: invokevirtual #5                  // Method java/lang/StringBuilder.length:()I
      15: ifle          25
      18: aload_1
      19: bipush        10
      21: invokevirtual #6                  // Method java/lang/StringBuilder.append:(C)Ljava/lang/StringBuilder;
      24: pop
      25: aload_1
      26: aload_0
      27: invokevirtual #7                  // Method java/lang/StringBuilder.append:(Ljava/lang/String;)Ljava/lang/StringBuilder;
      30: pop
      31: return

  public static void maybeAppend(java.lang.String[], java.lang.StringBuilder);
    Code:
       0: aload_0
       1: ifnull        36
       4: aload_0
       5: astore_2
       6: aload_2
       7: arraylength
       8: istore_3
       9: iconst_0
      10: istore        4
      12: iload         4
      14: iload_3
      15: if_icmpge     36
      18: aload_2
      19: iload         4
      21: aaload
      22: astore        5
      24: aload         5
      26: aload_1
      27: invokestatic  #8                  // Method maybeAppend:(Ljava/lang/String;Ljava/lang/StringBuilder;)V
      30: iinc          4, 1
      33: goto          12
      36: return
}
