Compiled from "ProductResultParser.java"
public final class com.google.zxing.client.result.ProductResultParser extends com.google.zxing.client.result.ResultParser {
  public com.google.zxing.client.result.ProductResultParser();
    Code:
       0: aload_0
       1: invokespecial #1                  // Method com/google/zxing/client/result/ResultParser."<init>":()V
       4: return

  public com.google.zxing.client.result.ProductParsedResult parse(com.google.zxing.Result);
    Code:
       0: aload_1
       1: invokevirtual #2                  // Method com/google/zxing/Result.getBarcodeFormat:()Lcom/google/zxing/BarcodeFormat;
       4: astore_2
       5: aload_2
       6: getstatic     #3                  // Field com/google/zxing/BarcodeFormat.UPC_A:Lcom/google/zxing/BarcodeFormat;
       9: if_acmpeq     35
      12: aload_2
      13: getstatic     #4                  // Field com/google/zxing/BarcodeFormat.UPC_E:Lcom/google/zxing/BarcodeFormat;
      16: if_acmpeq     35
      19: aload_2
      20: getstatic     #5                  // Field com/google/zxing/BarcodeFormat.EAN_8:Lcom/google/zxing/BarcodeFormat;
      23: if_acmpeq     35
      26: aload_2
      27: getstatic     #6                  // Field com/google/zxing/BarcodeFormat.EAN_13:Lcom/google/zxing/BarcodeFormat;
      30: if_acmpeq     35
      33: aconst_null
      34: areturn
      35: aload_1
      36: invokestatic  #7                  // Method getMassagedText:(Lcom/google/zxing/Result;)Ljava/lang/String;
      39: astore_3
      40: aload_3
      41: aload_3
      42: invokevirtual #8                  // Method java/lang/String.length:()I
      45: invokestatic  #9                  // Method isStringOfDigits:(Ljava/lang/CharSequence;I)Z
      48: ifne          53
      51: aconst_null
      52: areturn
      53: aload_2
      54: getstatic     #4                  // Field com/google/zxing/BarcodeFormat.UPC_E:Lcom/google/zxing/BarcodeFormat;
      57: if_acmpne     78
      60: aload_3
      61: invokevirtual #8                  // Method java/lang/String.length:()I
      64: bipush        8
      66: if_icmpne     78
      69: aload_3
      70: invokestatic  #10                 // Method com/google/zxing/oned/UPCEReader.convertUPCEtoUPCA:(Ljava/lang/String;)Ljava/lang/String;
      73: astore        4
      75: goto          81
      78: aload_3
      79: astore        4
      81: new           #11                 // class com/google/zxing/client/result/ProductParsedResult
      84: dup
      85: aload_3
      86: aload         4
      88: invokespecial #12                 // Method com/google/zxing/client/result/ProductParsedResult."<init>":(Ljava/lang/String;Ljava/lang/String;)V
      91: areturn

  public com.google.zxing.client.result.ParsedResult parse(com.google.zxing.Result);
    Code:
       0: aload_0
       1: aload_1
       2: invokevirtual #13                 // Method parse:(Lcom/google/zxing/Result;)Lcom/google/zxing/client/result/ProductParsedResult;
       5: areturn
}
