Compiled from "ProductParsedResult.java"
public final class com.google.zxing.client.result.ProductParsedResult extends com.google.zxing.client.result.ParsedResult {
  private final java.lang.String productID;

  private final java.lang.String normalizedProductID;

  com.google.zxing.client.result.ProductParsedResult(java.lang.String);
    Code:
       0: aload_0
       1: aload_1
       2: aload_1
       3: invokespecial #1                  // Method "<init>":(Ljava/lang/String;Ljava/lang/String;)V
       6: return

  com.google.zxing.client.result.ProductParsedResult(java.lang.String, java.lang.String);
    Code:
       0: aload_0
       1: getstatic     #2                  // Field com/google/zxing/client/result/ParsedResultType.PRODUCT:Lcom/google/zxing/client/result/ParsedResultType;
       4: invokespecial #3                  // Method com/google/zxing/client/result/ParsedResult."<init>":(Lcom/google/zxing/client/result/ParsedResultType;)V
       7: aload_0
       8: aload_1
       9: putfield      #4                  // Field productID:Ljava/lang/String;
      12: aload_0
      13: aload_2
      14: putfield      #5                  // Field normalizedProductID:Ljava/lang/String;
      17: return

  public java.lang.String getProductID();
    Code:
       0: aload_0
       1: getfield      #4                  // Field productID:Ljava/lang/String;
       4: areturn

  public java.lang.String getNormalizedProductID();
    Code:
       0: aload_0
       1: getfield      #5                  // Field normalizedProductID:Ljava/lang/String;
       4: areturn

  public java.lang.String getDisplayResult();
    Code:
       0: aload_0
       1: getfield      #4                  // Field productID:Ljava/lang/String;
       4: areturn
}
