Compiled from "TelParsedResult.java"
public final class com.google.zxing.client.result.TelParsedResult extends com.google.zxing.client.result.ParsedResult {
  private final java.lang.String number;

  private final java.lang.String telURI;

  private final java.lang.String title;

  public com.google.zxing.client.result.TelParsedResult(java.lang.String, java.lang.String, java.lang.String);
    Code:
       0: aload_0
       1: getstatic     #1                  // Field com/google/zxing/client/result/ParsedResultType.TEL:Lcom/google/zxing/client/result/ParsedResultType;
       4: invokespecial #2                  // Method com/google/zxing/client/result/ParsedResult."<init>":(Lcom/google/zxing/client/result/ParsedResultType;)V
       7: aload_0
       8: aload_1
       9: putfield      #3                  // Field number:Ljava/lang/String;
      12: aload_0
      13: aload_2
      14: putfield      #4                  // Field telURI:Ljava/lang/String;
      17: aload_0
      18: aload_3
      19: putfield      #5                  // Field title:Ljava/lang/String;
      22: return

  public java.lang.String getNumber();
    Code:
       0: aload_0
       1: getfield      #3                  // Field number:Ljava/lang/String;
       4: areturn

  public java.lang.String getTelURI();
    Code:
       0: aload_0
       1: getfield      #4                  // Field telURI:Ljava/lang/String;
       4: areturn

  public java.lang.String getTitle();
    Code:
       0: aload_0
       1: getfield      #5                  // Field title:Ljava/lang/String;
       4: areturn

  public java.lang.String getDisplayResult();
    Code:
       0: new           #6                  // class java/lang/StringBuilder
       3: dup
       4: bipush        20
       6: invokespecial #7                  // Method java/lang/StringBuilder."<init>":(I)V
       9: astore_1
      10: aload_0
      11: getfield      #3                  // Field number:Ljava/lang/String;
      14: aload_1
      15: invokestatic  #8                  // Method maybeAppend:(Ljava/lang/String;Ljava/lang/StringBuilder;)V
      18: aload_0
      19: getfield      #5                  // Field title:Ljava/lang/String;
      22: aload_1
      23: invokestatic  #8                  // Method maybeAppend:(Ljava/lang/String;Ljava/lang/StringBuilder;)V
      26: aload_1
      27: invokevirtual #9                  // Method java/lang/StringBuilder.toString:()Ljava/lang/String;
      30: areturn
}
