Compiled from "TelResultParser.java"
public final class com.google.zxing.client.result.TelResultParser extends com.google.zxing.client.result.ResultParser {
  public com.google.zxing.client.result.TelResultParser();
    Code:
       0: aload_0
       1: invokespecial #1                  // Method com/google/zxing/client/result/ResultParser."<init>":()V
       4: return

  public com.google.zxing.client.result.TelParsedResult parse(com.google.zxing.Result);
    Code:
       0: aload_1
       1: invokestatic  #2                  // Method getMassagedText:(Lcom/google/zxing/Result;)Ljava/lang/String;
       4: astore_2
       5: aload_2
       6: ldc           #3                  // String tel:
       8: invokevirtual #4                  // Method java/lang/String.startsWith:(Ljava/lang/String;)Z
      11: ifne          25
      14: aload_2
      15: ldc           #5                  // String TEL:
      17: invokevirtual #4                  // Method java/lang/String.startsWith:(Ljava/lang/String;)Z
      20: ifne          25
      23: aconst_null
      24: areturn
      25: aload_2
      26: ldc           #5                  // String TEL:
      28: invokevirtual #4                  // Method java/lang/String.startsWith:(Ljava/lang/String;)Z
      31: ifeq          60
      34: new           #6                  // class java/lang/StringBuilder
      37: dup
      38: invokespecial #7                  // Method java/lang/StringBuilder."<init>":()V
      41: ldc           #3                  // String tel:
      43: invokevirtual #8                  // Method java/lang/StringBuilder.append:(Ljava/lang/String;)Ljava/lang/StringBuilder;
      46: aload_2
      47: iconst_4
      48: invokevirtual #9                  // Method java/lang/String.substring:(I)Ljava/lang/String;
      51: invokevirtual #8                  // Method java/lang/StringBuilder.append:(Ljava/lang/String;)Ljava/lang/StringBuilder;
      54: invokevirtual #10                 // Method java/lang/StringBuilder.toString:()Ljava/lang/String;
      57: goto          61
      60: aload_2
      61: astore_3
      62: aload_2
      63: bipush        63
      65: iconst_4
      66: invokevirtual #11                 // Method java/lang/String.indexOf:(II)I
      69: istore        4
      71: iload         4
      73: ifge          84
      76: aload_2
      77: iconst_4
      78: invokevirtual #9                  // Method java/lang/String.substring:(I)Ljava/lang/String;
      81: goto          91
      84: aload_2
      85: iconst_4
      86: iload         4
      88: invokevirtual #12                 // Method java/lang/String.substring:(II)Ljava/lang/String;
      91: astore        5
      93: new           #13                 // class com/google/zxing/client/result/TelParsedResult
      96: dup
      97: aload         5
      99: aload_3
     100: aconst_null
     101: invokespecial #14                 // Method com/google/zxing/client/result/TelParsedResult."<init>":(Ljava/lang/String;Ljava/lang/String;Ljava/lang/String;)V
     104: areturn

  public com.google.zxing.client.result.ParsedResult parse(com.google.zxing.Result);
    Code:
       0: aload_0
       1: aload_1
       2: invokevirtual #15                 // Method parse:(Lcom/google/zxing/Result;)Lcom/google/zxing/client/result/TelParsedResult;
       5: areturn
}
