Compiled from "TextParsedResult.java"
public final class com.google.zxing.client.result.TextParsedResult extends com.google.zxing.client.result.ParsedResult {
  private final java.lang.String text;

  private final java.lang.String language;

  public com.google.zxing.client.result.TextParsedResult(java.lang.String, java.lang.String);
    Code:
       0: aload_0
       1: getstatic     #1                  // Field com/google/zxing/client/result/ParsedResultType.TEXT:Lcom/google/zxing/client/result/ParsedResultType;
       4: invokespecial #2                  // Method com/google/zxing/client/result/ParsedResult."<init>":(Lcom/google/zxing/client/result/ParsedResultType;)V
       7: aload_0
       8: aload_1
       9: putfield      #3                  // Field text:Ljava/lang/String;
      12: aload_0
      13: aload_2
      14: putfield      #4                  // Field language:Ljava/lang/String;
      17: return

  public java.lang.String getText();
    Code:
       0: aload_0
       1: getfield      #3                  // Field text:Ljava/lang/String;
       4: areturn

  public java.lang.String getLanguage();
    Code:
       0: aload_0
       1: getfield      #4                  // Field language:Ljava/lang/String;
       4: areturn

  public java.lang.String getDisplayResult();
    Code:
       0: aload_0
       1: getfield      #3                  // Field text:Ljava/lang/String;
       4: areturn
}
