Compiled from "URIParsedResult.java"
public final class com.google.zxing.client.result.URIParsedResult extends com.google.zxing.client.result.ParsedResult {
  private final java.lang.String uri;

  private final java.lang.String title;

  public com.google.zxing.client.result.URIParsedResult(java.lang.String, java.lang.String);
    Code:
       0: aload_0
       1: getstatic     #1                  // Field com/google/zxing/client/result/ParsedResultType.URI:Lcom/google/zxing/client/result/ParsedResultType;
       4: invokespecial #2                  // Method com/google/zxing/client/result/ParsedResult."<init>":(Lcom/google/zxing/client/result/ParsedResultType;)V
       7: aload_0
       8: aload_1
       9: invokestatic  #3                  // Method massageURI:(Ljava/lang/String;)Ljava/lang/String;
      12: putfield      #4                  // Field uri:Ljava/lang/String;
      15: aload_0
      16: aload_2
      17: putfield      #5                  // Field title:Ljava/lang/String;
      20: return

  public java.lang.String getURI();
    Code:
       0: aload_0
       1: getfield      #4                  // Field uri:Ljava/lang/String;
       4: areturn

  public java.lang.String getTitle();
    Code:
       0: aload_0
       1: getfield      #5                  // Field title:Ljava/lang/String;
       4: areturn

  public boolean isPossiblyMaliciousURI();
    Code:
       0: aload_0
       1: getfield      #4                  // Field uri:Ljava/lang/String;
       4: invokestatic  #6                  // Method com/google/zxing/client/result/URIResultParser.isPossiblyMaliciousURI:(Ljava/lang/String;)Z
       7: ireturn

  public java.lang.String getDisplayResult();
    Code:
       0: new           #7                  // class java/lang/StringBuilder
       3: dup
       4: bipush        30
       6: invokespecial #8                  // Method java/lang/StringBuilder."<init>":(I)V
       9: astore_1
      10: aload_0
      11: getfield      #5                  // Field title:Ljava/lang/String;
      14: aload_1
      15: invokestatic  #9                  // Method maybeAppend:(Ljava/lang/String;Ljava/lang/StringBuilder;)V
      18: aload_0
      19: getfield      #4                  // Field uri:Ljava/lang/String;
      22: aload_1
      23: invokestatic  #9                  // Method maybeAppend:(Ljava/lang/String;Ljava/lang/StringBuilder;)V
      26: aload_1
      27: invokevirtual #10                 // Method java/lang/StringBuilder.toString:()Ljava/lang/String;
      30: areturn

  private static java.lang.String massageURI(java.lang.String);
    Code:
       0: aload_0
       1: invokevirtual #11                 // Method java/lang/String.trim:()Ljava/lang/String;
       4: astore_0
       5: aload_0
       6: bipush        58
       8: invokevirtual #12                 // Method java/lang/String.indexOf:(I)I
      11: istore_1
      12: iload_1
      13: iflt          24
      16: aload_0
      17: iload_1
      18: invokestatic  #13                 // Method isColonFollowedByPortNumber:(Ljava/lang/String;I)Z
      21: ifeq          44
      24: new           #7                  // class java/lang/StringBuilder
      27: dup
      28: invokespecial #14                 // Method java/lang/StringBuilder."<init>":()V
      31: ldc           #15                 // String http://
      33: invokevirtual #16                 // Method java/lang/StringBuilder.append:(Ljava/lang/String;)Ljava/lang/StringBuilder;
      36: aload_0
      37: invokevirtual #16                 // Method java/lang/StringBuilder.append:(Ljava/lang/String;)Ljava/lang/StringBuilder;
      40: invokevirtual #10                 // Method java/lang/StringBuilder.toString:()Ljava/lang/String;
      43: astore_0
      44: aload_0
      45: areturn

  private static boolean isColonFollowedByPortNumber(java.lang.String, int);
    Code:
       0: iload_1
       1: iconst_1
       2: iadd
       3: istore_2
       4: aload_0
       5: bipush        47
       7: iload_2
       8: invokevirtual #17                 // Method java/lang/String.indexOf:(II)I
      11: istore_3
      12: iload_3
      13: ifge          21
      16: aload_0
      17: invokevirtual #18                 // Method java/lang/String.length:()I
      20: istore_3
      21: aload_0
      22: iload_2
      23: iload_3
      24: iload_2
      25: isub
      26: invokestatic  #19                 // Method com/google/zxing/client/result/ResultParser.isSubstringOfDigits:(Ljava/lang/CharSequence;II)Z
      29: ireturn
}
