Compiled from "URIResultParser.java"
public final class com.google.zxing.client.result.URIResultParser extends com.google.zxing.client.result.ResultParser {
  private static final java.util.regex.Pattern ALLOWED_URI_CHARS_PATTERN;

  private static final java.util.regex.Pattern USER_IN_HOST;

  private static final java.util.regex.Pattern URL_WITH_PROTOCOL_PATTERN;

  private static final java.util.regex.Pattern URL_WITHOUT_PROTOCOL_PATTERN;

  public com.google.zxing.client.result.URIResultParser();
    Code:
       0: aload_0
       1: invokespecial #1                  // Method com/google/zxing/client/result/ResultParser."<init>":()V
       4: return

  public com.google.zxing.client.result.URIParsedResult parse(com.google.zxing.Result);
    Code:
       0: aload_1
       1: invokestatic  #2                  // Method getMassagedText:(Lcom/google/zxing/Result;)Ljava/lang/String;
       4: astore_2
       5: aload_2
       6: ldc           #3                  // String URL:
       8: invokevirtual #4                  // Method java/lang/String.startsWith:(Ljava/lang/String;)Z
      11: ifne          23
      14: aload_2
      15: ldc           #5                  // String URI:
      17: invokevirtual #4                  // Method java/lang/String.startsWith:(Ljava/lang/String;)Z
      20: ifeq          40
      23: new           #6                  // class com/google/zxing/client/result/URIParsedResult
      26: dup
      27: aload_2
      28: iconst_4
      29: invokevirtual #7                  // Method java/lang/String.substring:(I)Ljava/lang/String;
      32: invokevirtual #8                  // Method java/lang/String.trim:()Ljava/lang/String;
      35: aconst_null
      36: invokespecial #9                  // Method com/google/zxing/client/result/URIParsedResult."<init>":(Ljava/lang/String;Ljava/lang/String;)V
      39: areturn
      40: aload_2
      41: invokevirtual #8                  // Method java/lang/String.trim:()Ljava/lang/String;
      44: astore_2
      45: aload_2
      46: invokestatic  #10                 // Method isBasicallyValidURI:(Ljava/lang/String;)Z
      49: ifeq          59
      52: aload_2
      53: invokestatic  #11                 // Method isPossiblyMaliciousURI:(Ljava/lang/String;)Z
      56: ifeq          61
      59: aconst_null
      60: areturn
      61: new           #6                  // class com/google/zxing/client/result/URIParsedResult
      64: dup
      65: aload_2
      66: aconst_null
      67: invokespecial #9                  // Method com/google/zxing/client/result/URIParsedResult."<init>":(Ljava/lang/String;Ljava/lang/String;)V
      70: areturn

  static boolean isPossiblyMaliciousURI(java.lang.String);
    Code:
       0: getstatic     #12                 // Field ALLOWED_URI_CHARS_PATTERN:Ljava/util/regex/Pattern;
       3: aload_0
       4: invokevirtual #13                 // Method java/util/regex/Pattern.matcher:(Ljava/lang/CharSequence;)Ljava/util/regex/Matcher;
       7: invokevirtual #14                 // Method java/util/regex/Matcher.matches:()Z
      10: ifeq          26
      13: getstatic     #15                 // Field USER_IN_HOST:Ljava/util/regex/Pattern;
      16: aload_0
      17: invokevirtual #13                 // Method java/util/regex/Pattern.matcher:(Ljava/lang/CharSequence;)Ljava/util/regex/Matcher;
      20: invokevirtual #16                 // Method java/util/regex/Matcher.find:()Z
      23: ifeq          30
      26: iconst_1
      27: goto          31
      30: iconst_0
      31: ireturn

  static boolean isBasicallyValidURI(java.lang.String);
    Code:
       0: aload_0
       1: ldc           #17                 // String
       3: invokevirtual #18                 // Method java/lang/String.contains:(Ljava/lang/CharSequence;)Z
       6: ifeq          11
       9: iconst_0
      10: ireturn
      11: getstatic     #19                 // Field URL_WITH_PROTOCOL_PATTERN:Ljava/util/regex/Pattern;
      14: aload_0
      15: invokevirtual #13                 // Method java/util/regex/Pattern.matcher:(Ljava/lang/CharSequence;)Ljava/util/regex/Matcher;
      18: astore_1
      19: aload_1
      20: invokevirtual #16                 // Method java/util/regex/Matcher.find:()Z
      23: ifeq          35
      26: aload_1
      27: invokevirtual #20                 // Method java/util/regex/Matcher.start:()I
      30: ifne          35
      33: iconst_1
      34: ireturn
      35: getstatic     #21                 // Field URL_WITHOUT_PROTOCOL_PATTERN:Ljava/util/regex/Pattern;
      38: aload_0
      39: invokevirtual #13                 // Method java/util/regex/Pattern.matcher:(Ljava/lang/CharSequence;)Ljava/util/regex/Matcher;
      42: astore_1
      43: aload_1
      44: invokevirtual #16                 // Method java/util/regex/Matcher.find:()Z
      47: ifeq          61
      50: aload_1
      51: invokevirtual #20                 // Method java/util/regex/Matcher.start:()I
      54: ifne          61
      57: iconst_1
      58: goto          62
      61: iconst_0
      62: ireturn

  public com.google.zxing.client.result.ParsedResult parse(com.google.zxing.Result);
    Code:
       0: aload_0
       1: aload_1
       2: invokevirtual #22                 // Method parse:(Lcom/google/zxing/Result;)Lcom/google/zxing/client/result/URIParsedResult;
       5: areturn

  static {};
    Code:
       0: ldc           #23                 // String [-._~:/?#\\[\\]@!$&\'()*+,;=%A-Za-z0-9]+
       2: invokestatic  #24                 // Method java/util/regex/Pattern.compile:(Ljava/lang/String;)Ljava/util/regex/Pattern;
       5: putstatic     #12                 // Field ALLOWED_URI_CHARS_PATTERN:Ljava/util/regex/Pattern;
       8: ldc           #25                 // String :/*([^/@]+)@[^/]+
      10: invokestatic  #24                 // Method java/util/regex/Pattern.compile:(Ljava/lang/String;)Ljava/util/regex/Pattern;
      13: putstatic     #15                 // Field USER_IN_HOST:Ljava/util/regex/Pattern;
      16: ldc           #26                 // String [a-zA-Z][a-zA-Z0-9+-.]+:
      18: invokestatic  #24                 // Method java/util/regex/Pattern.compile:(Ljava/lang/String;)Ljava/util/regex/Pattern;
      21: putstatic     #19                 // Field URL_WITH_PROTOCOL_PATTERN:Ljava/util/regex/Pattern;
      24: ldc           #27                 // String ([a-zA-Z0-9\\-]+\\.){1,6}[a-zA-Z]{2,}(:\\d{1,5})?(/|\\?|$)
      26: invokestatic  #24                 // Method java/util/regex/Pattern.compile:(Ljava/lang/String;)Ljava/util/regex/Pattern;
      29: putstatic     #21                 // Field URL_WITHOUT_PROTOCOL_PATTERN:Ljava/util/regex/Pattern;
      32: return
}
