Compiled from "VCardResultParser.java"
public final class com.google.zxing.client.result.VCardResultParser extends com.google.zxing.client.result.ResultParser {
  private static final java.util.regex.Pattern BEGIN_VCARD;

  private static final java.util.regex.Pattern VCARD_LIKE_DATE;

  private static final java.util.regex.Pattern CR_LF_SPACE_TAB;

  private static final java.util.regex.Pattern NEWLINE_ESCAPE;

  private static final java.util.regex.Pattern VCARD_ESCAPES;

  private static final java.util.regex.Pattern EQUALS;

  private static final java.util.regex.Pattern SEMICOLON;

  private static final java.util.regex.Pattern UNESCAPED_SEMICOLONS;

  private static final java.util.regex.Pattern COMMA;

  private static final java.util.regex.Pattern SEMICOLON_OR_COMMA;

  public com.google.zxing.client.result.VCardResultParser();
    Code:
       0: aload_0
       1: invokespecial #1                  // Method com/google/zxing/client/result/ResultParser."<init>":()V
       4: return

  public com.google.zxing.client.result.AddressBookParsedResult parse(com.google.zxing.Result);
    Code:
       0: aload_1
       1: invokestatic  #2                  // Method getMassagedText:(Lcom/google/zxing/Result;)Ljava/lang/String;
       4: astore_2
       5: getstatic     #3                  // Field BEGIN_VCARD:Ljava/util/regex/Pattern;
       8: aload_2
       9: invokevirtual #4                  // Method java/util/regex/Pattern.matcher:(Ljava/lang/CharSequence;)Ljava/util/regex/Matcher;
      12: astore_3
      13: aload_3
      14: invokevirtual #5                  // Method java/util/regex/Matcher.find:()Z
      17: ifeq          27
      20: aload_3
      21: invokevirtual #6                  // Method java/util/regex/Matcher.start:()I
      24: ifeq          29
      27: aconst_null
      28: areturn
      29: ldc           #7                  // String FN
      31: aload_2
      32: iconst_1
      33: iconst_0
      34: invokestatic  #8                  // Method matchVCardPrefixedField:(Ljava/lang/CharSequence;Ljava/lang/String;ZZ)Ljava/util/List;
      37: astore        4
      39: aload         4
      41: ifnonnull     59
      44: ldc           #9                  // String N
      46: aload_2
      47: iconst_1
      48: iconst_0
      49: invokestatic  #8                  // Method matchVCardPrefixedField:(Ljava/lang/CharSequence;Ljava/lang/String;ZZ)Ljava/util/List;
      52: astore        4
      54: aload         4
      56: invokestatic  #10                 // Method formatNames:(Ljava/lang/Iterable;)V
      59: ldc           #11                 // String NICKNAME
      61: aload_2
      62: iconst_1
      63: iconst_0
      64: invokestatic  #12                 // Method matchSingleVCardPrefixedField:(Ljava/lang/CharSequence;Ljava/lang/String;ZZ)Ljava/util/List;
      67: astore        5
      69: aload         5
      71: ifnonnull     78
      74: aconst_null
      75: goto          95
      78: getstatic     #13                 // Field COMMA:Ljava/util/regex/Pattern;
      81: aload         5
      83: iconst_0
      84: invokeinterface #14,  2           // InterfaceMethod java/util/List.get:(I)Ljava/lang/Object;
      89: checkcast     #15                 // class java/lang/CharSequence
      92: invokevirtual #16                 // Method java/util/regex/Pattern.split:(Ljava/lang/CharSequence;)[Ljava/lang/String;
      95: astore        6
      97: ldc           #17                 // String TEL
      99: aload_2
     100: iconst_1
     101: iconst_0
     102: invokestatic  #8                  // Method matchVCardPrefixedField:(Ljava/lang/CharSequence;Ljava/lang/String;ZZ)Ljava/util/List;
     105: astore        7
     107: ldc           #18                 // String EMAIL
     109: aload_2
     110: iconst_1
     111: iconst_0
     112: invokestatic  #8                  // Method matchVCardPrefixedField:(Ljava/lang/CharSequence;Ljava/lang/String;ZZ)Ljava/util/List;
     115: astore        8
     117: ldc           #19                 // String NOTE
     119: aload_2
     120: iconst_0
     121: iconst_0
     122: invokestatic  #12                 // Method matchSingleVCardPrefixedField:(Ljava/lang/CharSequence;Ljava/lang/String;ZZ)Ljava/util/List;
     125: astore        9
     127: ldc           #20                 // String ADR
     129: aload_2
     130: iconst_1
     131: iconst_1
     132: invokestatic  #8                  // Method matchVCardPrefixedField:(Ljava/lang/CharSequence;Ljava/lang/String;ZZ)Ljava/util/List;
     135: astore        10
     137: ldc           #21                 // String ORG
     139: aload_2
     140: iconst_1
     141: iconst_1
     142: invokestatic  #12                 // Method matchSingleVCardPrefixedField:(Ljava/lang/CharSequence;Ljava/lang/String;ZZ)Ljava/util/List;
     145: astore        11
     147: ldc           #22                 // String BDAY
     149: aload_2
     150: iconst_1
     151: iconst_0
     152: invokestatic  #12                 // Method matchSingleVCardPrefixedField:(Ljava/lang/CharSequence;Ljava/lang/String;ZZ)Ljava/util/List;
     155: astore        12
     157: aload         12
     159: ifnull        182
     162: aload         12
     164: iconst_0
     165: invokeinterface #14,  2           // InterfaceMethod java/util/List.get:(I)Ljava/lang/Object;
     170: checkcast     #15                 // class java/lang/CharSequence
     173: invokestatic  #23                 // Method isLikeVCardDate:(Ljava/lang/CharSequence;)Z
     176: ifne          182
     179: aconst_null
     180: astore        12
     182: ldc           #24                 // String TITLE
     184: aload_2
     185: iconst_1
     186: iconst_0
     187: invokestatic  #12                 // Method matchSingleVCardPrefixedField:(Ljava/lang/CharSequence;Ljava/lang/String;ZZ)Ljava/util/List;
     190: astore        13
     192: ldc           #25                 // String URL
     194: aload_2
     195: iconst_1
     196: iconst_0
     197: invokestatic  #8                  // Method matchVCardPrefixedField:(Ljava/lang/CharSequence;Ljava/lang/String;ZZ)Ljava/util/List;
     200: astore        14
     202: ldc           #26                 // String IMPP
     204: aload_2
     205: iconst_1
     206: iconst_0
     207: invokestatic  #12                 // Method matchSingleVCardPrefixedField:(Ljava/lang/CharSequence;Ljava/lang/String;ZZ)Ljava/util/List;
     210: astore        15
     212: ldc           #27                 // String GEO
     214: aload_2
     215: iconst_1
     216: iconst_0
     217: invokestatic  #12                 // Method matchSingleVCardPrefixedField:(Ljava/lang/CharSequence;Ljava/lang/String;ZZ)Ljava/util/List;
     220: astore        16
     222: aload         16
     224: ifnonnull     231
     227: aconst_null
     228: goto          248
     231: getstatic     #28                 // Field SEMICOLON_OR_COMMA:Ljava/util/regex/Pattern;
     234: aload         16
     236: iconst_0
     237: invokeinterface #14,  2           // InterfaceMethod java/util/List.get:(I)Ljava/lang/Object;
     242: checkcast     #15                 // class java/lang/CharSequence
     245: invokevirtual #16                 // Method java/util/regex/Pattern.split:(Ljava/lang/CharSequence;)[Ljava/lang/String;
     248: astore        17
     250: aload         17
     252: ifnull        265
     255: aload         17
     257: arraylength
     258: iconst_2
     259: if_icmpeq     265
     262: aconst_null
     263: astore        17
     265: new           #29                 // class com/google/zxing/client/result/AddressBookParsedResult
     268: dup
     269: aload         4
     271: invokestatic  #30                 // Method toPrimaryValues:(Ljava/util/Collection;)[Ljava/lang/String;
     274: aload         6
     276: aconst_null
     277: aload         7
     279: invokestatic  #30                 // Method toPrimaryValues:(Ljava/util/Collection;)[Ljava/lang/String;
     282: aload         7
     284: invokestatic  #31                 // Method toTypes:(Ljava/util/Collection;)[Ljava/lang/String;
     287: aload         8
     289: invokestatic  #30                 // Method toPrimaryValues:(Ljava/util/Collection;)[Ljava/lang/String;
     292: aload         8
     294: invokestatic  #31                 // Method toTypes:(Ljava/util/Collection;)[Ljava/lang/String;
     297: aload         15
     299: invokestatic  #32                 // Method toPrimaryValue:(Ljava/util/List;)Ljava/lang/String;
     302: aload         9
     304: invokestatic  #32                 // Method toPrimaryValue:(Ljava/util/List;)Ljava/lang/String;
     307: aload         10
     309: invokestatic  #30                 // Method toPrimaryValues:(Ljava/util/Collection;)[Ljava/lang/String;
     312: aload         10
     314: invokestatic  #31                 // Method toTypes:(Ljava/util/Collection;)[Ljava/lang/String;
     317: aload         11
     319: invokestatic  #32                 // Method toPrimaryValue:(Ljava/util/List;)Ljava/lang/String;
     322: aload         12
     324: invokestatic  #32                 // Method toPrimaryValue:(Ljava/util/List;)Ljava/lang/String;
     327: aload         13
     329: invokestatic  #32                 // Method toPrimaryValue:(Ljava/util/List;)Ljava/lang/String;
     332: aload         14
     334: invokestatic  #30                 // Method toPrimaryValues:(Ljava/util/Collection;)[Ljava/lang/String;
     337: aload         17
     339: invokespecial #33                 // Method com/google/zxing/client/result/AddressBookParsedResult."<init>":([Ljava/lang/String;[Ljava/lang/String;Ljava/lang/String;[Ljava/lang/String;[Ljava/lang/String;[Ljava/lang/String;[Ljava/lang/String;Ljava/lang/String;Ljava/lang/String;[Ljava/lang/String;[Ljava/lang/String;Ljava/lang/String;Ljava/lang/String;Ljava/lang/String;[Ljava/lang/String;[Ljava/lang/String;)V
     342: areturn

  static java.util.List<java.util.List<java.lang.String>> matchVCardPrefixedField(java.lang.CharSequence, java.lang.String, boolean, boolean);
    Code:
       0: aconst_null
       1: astore        4
       3: iconst_0
       4: istore        5
       6: aload_1
       7: invokevirtual #34                 // Method java/lang/String.length:()I
      10: istore        6
      12: iload         5
      14: iload         6
      16: if_icmpge     645
      19: new           #35                 // class java/lang/StringBuilder
      22: dup
      23: invokespecial #36                 // Method java/lang/StringBuilder."<init>":()V
      26: ldc           #37                 // String (?:^|\n)
      28: invokevirtual #38                 // Method java/lang/StringBuilder.append:(Ljava/lang/String;)Ljava/lang/StringBuilder;
      31: aload_0
      32: invokevirtual #39                 // Method java/lang/StringBuilder.append:(Ljava/lang/Object;)Ljava/lang/StringBuilder;
      35: ldc           #40                 // String (?:;([^:]*))?:
      37: invokevirtual #38                 // Method java/lang/StringBuilder.append:(Ljava/lang/String;)Ljava/lang/StringBuilder;
      40: invokevirtual #41                 // Method java/lang/StringBuilder.toString:()Ljava/lang/String;
      43: iconst_2
      44: invokestatic  #43                 // Method java/util/regex/Pattern.compile:(Ljava/lang/String;I)Ljava/util/regex/Pattern;
      47: aload_1
      48: invokevirtual #4                  // Method java/util/regex/Pattern.matcher:(Ljava/lang/CharSequence;)Ljava/util/regex/Matcher;
      51: astore        7
      53: iload         5
      55: ifle          61
      58: iinc          5, -1
      61: aload         7
      63: iload         5
      65: invokevirtual #44                 // Method java/util/regex/Matcher.find:(I)Z
      68: ifne          74
      71: goto          645
      74: aload         7
      76: iconst_0
      77: invokevirtual #45                 // Method java/util/regex/Matcher.end:(I)I
      80: istore        5
      82: aload         7
      84: iconst_1
      85: invokevirtual #46                 // Method java/util/regex/Matcher.group:(I)Ljava/lang/String;
      88: astore        8
      90: aconst_null
      91: astore        9
      93: iconst_0
      94: istore        10
      96: aconst_null
      97: astore        11
      99: aconst_null
     100: astore        12
     102: aload         8
     104: ifnull        257
     107: getstatic     #47                 // Field SEMICOLON:Ljava/util/regex/Pattern;
     110: aload         8
     112: invokevirtual #16                 // Method java/util/regex/Pattern.split:(Ljava/lang/CharSequence;)[Ljava/lang/String;
     115: astore        13
     117: aload         13
     119: arraylength
     120: istore        14
     122: iconst_0
     123: istore        15
     125: iload         15
     127: iload         14
     129: if_icmpge     257
     132: aload         13
     134: iload         15
     136: aaload
     137: astore        16
     139: aload         9
     141: ifnonnull     154
     144: new           #48                 // class java/util/ArrayList
     147: dup
     148: iconst_1
     149: invokespecial #49                 // Method java/util/ArrayList."<init>":(I)V
     152: astore        9
     154: aload         9
     156: aload         16
     158: invokeinterface #50,  2           // InterfaceMethod java/util/List.add:(Ljava/lang/Object;)Z
     163: pop
     164: getstatic     #51                 // Field EQUALS:Ljava/util/regex/Pattern;
     167: aload         16
     169: iconst_2
     170: invokevirtual #52                 // Method java/util/regex/Pattern.split:(Ljava/lang/CharSequence;I)[Ljava/lang/String;
     173: astore        17
     175: aload         17
     177: arraylength
     178: iconst_1
     179: if_icmple     251
     182: aload         17
     184: iconst_0
     185: aaload
     186: astore        18
     188: aload         17
     190: iconst_1
     191: aaload
     192: astore        19
     194: ldc           #53                 // String ENCODING
     196: aload         18
     198: invokevirtual #54                 // Method java/lang/String.equalsIgnoreCase:(Ljava/lang/String;)Z
     201: ifeq          220
     204: ldc           #55                 // String QUOTED-PRINTABLE
     206: aload         19
     208: invokevirtual #54                 // Method java/lang/String.equalsIgnoreCase:(Ljava/lang/String;)Z
     211: ifeq          220
     214: iconst_1
     215: istore        10
     217: goto          251
     220: ldc           #56                 // String CHARSET
     222: aload         18
     224: invokevirtual #54                 // Method java/lang/String.equalsIgnoreCase:(Ljava/lang/String;)Z
     227: ifeq          237
     230: aload         19
     232: astore        11
     234: goto          251
     237: ldc           #57                 // String VALUE
     239: aload         18
     241: invokevirtual #54                 // Method java/lang/String.equalsIgnoreCase:(Ljava/lang/String;)Z
     244: ifeq          251
     247: aload         19
     249: astore        12
     251: iinc          15, 1
     254: goto          125
     257: iload         5
     259: istore        13
     261: aload_1
     262: bipush        10
     264: iload         5
     266: invokevirtual #58                 // Method java/lang/String.indexOf:(II)I
     269: dup
     270: istore        5
     272: iflt          367
     275: iload         5
     277: aload_1
     278: invokevirtual #34                 // Method java/lang/String.length:()I
     281: iconst_1
     282: isub
     283: if_icmpge     318
     286: aload_1
     287: iload         5
     289: iconst_1
     290: iadd
     291: invokevirtual #59                 // Method java/lang/String.charAt:(I)C
     294: bipush        32
     296: if_icmpeq     312
     299: aload_1
     300: iload         5
     302: iconst_1
     303: iadd
     304: invokevirtual #59                 // Method java/lang/String.charAt:(I)C
     307: bipush        9
     309: if_icmpne     318
     312: iinc          5, 2
     315: goto          261
     318: iload         10
     320: ifeq          367
     323: iload         5
     325: iconst_1
     326: if_icmplt     342
     329: aload_1
     330: iload         5
     332: iconst_1
     333: isub
     334: invokevirtual #59                 // Method java/lang/String.charAt:(I)C
     337: bipush        61
     339: if_icmpeq     361
     342: iload         5
     344: iconst_2
     345: if_icmplt     367
     348: aload_1
     349: iload         5
     351: iconst_2
     352: isub
     353: invokevirtual #59                 // Method java/lang/String.charAt:(I)C
     356: bipush        61
     358: if_icmpne     367
     361: iinc          5, 1
     364: goto          261
     367: iload         5
     369: ifge          379
     372: iload         6
     374: istore        5
     376: goto          642
     379: iload         5
     381: iload         13
     383: if_icmple     639
     386: aload         4
     388: ifnonnull     401
     391: new           #48                 // class java/util/ArrayList
     394: dup
     395: iconst_1
     396: invokespecial #49                 // Method java/util/ArrayList."<init>":(I)V
     399: astore        4
     401: iload         5
     403: iconst_1
     404: if_icmplt     423
     407: aload_1
     408: iload         5
     410: iconst_1
     411: isub
     412: invokevirtual #59                 // Method java/lang/String.charAt:(I)C
     415: bipush        13
     417: if_icmpne     423
     420: iinc          5, -1
     423: aload_1
     424: iload         13
     426: iload         5
     428: invokevirtual #60                 // Method java/lang/String.substring:(II)Ljava/lang/String;
     431: astore        14
     433: iload_2
     434: ifeq          444
     437: aload         14
     439: invokevirtual #61                 // Method java/lang/String.trim:()Ljava/lang/String;
     442: astore        14
     444: iload         10
     446: ifeq          483
     449: aload         14
     451: aload         11
     453: invokestatic  #62                 // Method decodeQuotedPrintable:(Ljava/lang/CharSequence;Ljava/lang/String;)Ljava/lang/String;
     456: astore        14
     458: iload_3
     459: ifeq          550
     462: getstatic     #63                 // Field UNESCAPED_SEMICOLONS:Ljava/util/regex/Pattern;
     465: aload         14
     467: invokevirtual #4                  // Method java/util/regex/Pattern.matcher:(Ljava/lang/CharSequence;)Ljava/util/regex/Matcher;
     470: ldc           #64                 // String \n
     472: invokevirtual #65                 // Method java/util/regex/Matcher.replaceAll:(Ljava/lang/String;)Ljava/lang/String;
     475: invokevirtual #61                 // Method java/lang/String.trim:()Ljava/lang/String;
     478: astore        14
     480: goto          550
     483: iload_3
     484: ifeq          505
     487: getstatic     #63                 // Field UNESCAPED_SEMICOLONS:Ljava/util/regex/Pattern;
     490: aload         14
     492: invokevirtual #4                  // Method java/util/regex/Pattern.matcher:(Ljava/lang/CharSequence;)Ljava/util/regex/Matcher;
     495: ldc           #64                 // String \n
     497: invokevirtual #65                 // Method java/util/regex/Matcher.replaceAll:(Ljava/lang/String;)Ljava/lang/String;
     500: invokevirtual #61                 // Method java/lang/String.trim:()Ljava/lang/String;
     503: astore        14
     505: getstatic     #66                 // Field CR_LF_SPACE_TAB:Ljava/util/regex/Pattern;
     508: aload         14
     510: invokevirtual #4                  // Method java/util/regex/Pattern.matcher:(Ljava/lang/CharSequence;)Ljava/util/regex/Matcher;
     513: ldc           #67                 // String
     515: invokevirtual #65                 // Method java/util/regex/Matcher.replaceAll:(Ljava/lang/String;)Ljava/lang/String;
     518: astore        14
     520: getstatic     #68                 // Field NEWLINE_ESCAPE:Ljava/util/regex/Pattern;
     523: aload         14
     525: invokevirtual #4                  // Method java/util/regex/Pattern.matcher:(Ljava/lang/CharSequence;)Ljava/util/regex/Matcher;
     528: ldc           #64                 // String \n
     530: invokevirtual #65                 // Method java/util/regex/Matcher.replaceAll:(Ljava/lang/String;)Ljava/lang/String;
     533: astore        14
     535: getstatic     #69                 // Field VCARD_ESCAPES:Ljava/util/regex/Pattern;
     538: aload         14
     540: invokevirtual #4                  // Method java/util/regex/Pattern.matcher:(Ljava/lang/CharSequence;)Ljava/util/regex/Matcher;
     543: ldc           #70                 // String $1
     545: invokevirtual #65                 // Method java/util/regex/Matcher.replaceAll:(Ljava/lang/String;)Ljava/lang/String;
     548: astore        14
     550: ldc           #71                 // String uri
     552: aload         12
     554: invokevirtual #72                 // Method java/lang/String.equals:(Ljava/lang/Object;)Z
     557: ifeq          575
     560: aload         14
     562: invokestatic  #73                 // Method java/net/URI.create:(Ljava/lang/String;)Ljava/net/URI;
     565: invokevirtual #74                 // Method java/net/URI.getSchemeSpecificPart:()Ljava/lang/String;
     568: astore        14
     570: goto          575
     573: astore        15
     575: aload         9
     577: ifnonnull     613
     580: new           #48                 // class java/util/ArrayList
     583: dup
     584: iconst_1
     585: invokespecial #49                 // Method java/util/ArrayList."<init>":(I)V
     588: astore        15
     590: aload         15
     592: aload         14
     594: invokeinterface #50,  2           // InterfaceMethod java/util/List.add:(Ljava/lang/Object;)Z
     599: pop
     600: aload         4
     602: aload         15
     604: invokeinterface #50,  2           // InterfaceMethod java/util/List.add:(Ljava/lang/Object;)Z
     609: pop
     610: goto          633
     613: aload         9
     615: iconst_0
     616: aload         14
     618: invokeinterface #76,  3           // InterfaceMethod java/util/List.add:(ILjava/lang/Object;)V
     623: aload         4
     625: aload         9
     627: invokeinterface #50,  2           // InterfaceMethod java/util/List.add:(Ljava/lang/Object;)Z
     632: pop
     633: iinc          5, 1
     636: goto          642
     639: iinc          5, 1
     642: goto          12
     645: aload         4
     647: areturn
    Exception table:
       from    to  target type
         560   570   573   Class java/lang/IllegalArgumentException

  private static java.lang.String decodeQuotedPrintable(java.lang.CharSequence, java.lang.String);
    Code:
       0: aload_0
       1: invokeinterface #77,  1           // InterfaceMethod java/lang/CharSequence.length:()I
       6: istore_2
       7: new           #35                 // class java/lang/StringBuilder
      10: dup
      11: iload_2
      12: invokespecial #78                 // Method java/lang/StringBuilder."<init>":(I)V
      15: astore_3
      16: new           #79                 // class java/io/ByteArrayOutputStream
      19: dup
      20: invokespecial #80                 // Method java/io/ByteArrayOutputStream."<init>":()V
      23: astore        4
      25: iconst_0
      26: istore        5
      28: iload         5
      30: iload_2
      31: if_icmpge     191
      34: aload_0
      35: iload         5
      37: invokeinterface #81,  2           // InterfaceMethod java/lang/CharSequence.charAt:(I)C
      42: istore        6
      44: iload         6
      46: lookupswitch  { // 3
                    10: 80
                    13: 80
                    61: 83
               default: 171
          }
      80: goto          185
      83: iload         5
      85: iload_2
      86: iconst_2
      87: isub
      88: if_icmpge     185
      91: aload_0
      92: iload         5
      94: iconst_1
      95: iadd
      96: invokeinterface #81,  2           // InterfaceMethod java/lang/CharSequence.charAt:(I)C
     101: istore        7
     103: iload         7
     105: bipush        13
     107: if_icmpeq     168
     110: iload         7
     112: bipush        10
     114: if_icmpeq     168
     117: aload_0
     118: iload         5
     120: iconst_2
     121: iadd
     122: invokeinterface #81,  2           // InterfaceMethod java/lang/CharSequence.charAt:(I)C
     127: istore        8
     129: iload         7
     131: invokestatic  #82                 // Method parseHexDigit:(C)I
     134: istore        9
     136: iload         8
     138: invokestatic  #82                 // Method parseHexDigit:(C)I
     141: istore        10
     143: iload         9
     145: iflt          165
     148: iload         10
     150: iflt          165
     153: aload         4
     155: iload         9
     157: iconst_4
     158: ishl
     159: iload         10
     161: iadd
     162: invokevirtual #83                 // Method java/io/ByteArrayOutputStream.write:(I)V
     165: iinc          5, 2
     168: goto          185
     171: aload         4
     173: aload_1
     174: aload_3
     175: invokestatic  #84                 // Method maybeAppendFragment:(Ljava/io/ByteArrayOutputStream;Ljava/lang/String;Ljava/lang/StringBuilder;)V
     178: aload_3
     179: iload         6
     181: invokevirtual #85                 // Method java/lang/StringBuilder.append:(C)Ljava/lang/StringBuilder;
     184: pop
     185: iinc          5, 1
     188: goto          28
     191: aload         4
     193: aload_1
     194: aload_3
     195: invokestatic  #84                 // Method maybeAppendFragment:(Ljava/io/ByteArrayOutputStream;Ljava/lang/String;Ljava/lang/StringBuilder;)V
     198: aload_3
     199: invokevirtual #41                 // Method java/lang/StringBuilder.toString:()Ljava/lang/String;
     202: areturn

  private static void maybeAppendFragment(java.io.ByteArrayOutputStream, java.lang.String, java.lang.StringBuilder);
    Code:
       0: aload_0
       1: invokevirtual #86                 // Method java/io/ByteArrayOutputStream.size:()I
       4: ifle          72
       7: aload_0
       8: invokevirtual #87                 // Method java/io/ByteArrayOutputStream.toByteArray:()[B
      11: astore_3
      12: aload_1
      13: ifnonnull     32
      16: new           #88                 // class java/lang/String
      19: dup
      20: aload_3
      21: getstatic     #89                 // Field java/nio/charset/StandardCharsets.UTF_8:Ljava/nio/charset/Charset;
      24: invokespecial #90                 // Method java/lang/String."<init>":([BLjava/nio/charset/Charset;)V
      27: astore        4
      29: goto          61
      32: new           #88                 // class java/lang/String
      35: dup
      36: aload_3
      37: aload_1
      38: invokespecial #91                 // Method java/lang/String."<init>":([BLjava/lang/String;)V
      41: astore        4
      43: goto          61
      46: astore        5
      48: new           #88                 // class java/lang/String
      51: dup
      52: aload_3
      53: getstatic     #89                 // Field java/nio/charset/StandardCharsets.UTF_8:Ljava/nio/charset/Charset;
      56: invokespecial #90                 // Method java/lang/String."<init>":([BLjava/nio/charset/Charset;)V
      59: astore        4
      61: aload_0
      62: invokevirtual #93                 // Method java/io/ByteArrayOutputStream.reset:()V
      65: aload_2
      66: aload         4
      68: invokevirtual #38                 // Method java/lang/StringBuilder.append:(Ljava/lang/String;)Ljava/lang/StringBuilder;
      71: pop
      72: return
    Exception table:
       from    to  target type
          32    43    46   Class java/io/UnsupportedEncodingException

  static java.util.List<java.lang.String> matchSingleVCardPrefixedField(java.lang.CharSequence, java.lang.String, boolean, boolean);
    Code:
       0: aload_0
       1: aload_1
       2: iload_2
       3: iload_3
       4: invokestatic  #8                  // Method matchVCardPrefixedField:(Ljava/lang/CharSequence;Ljava/lang/String;ZZ)Ljava/util/List;
       7: astore        4
       9: aload         4
      11: ifnull        24
      14: aload         4
      16: invokeinterface #94,  1           // InterfaceMethod java/util/List.isEmpty:()Z
      21: ifeq          28
      24: aconst_null
      25: goto          39
      28: aload         4
      30: iconst_0
      31: invokeinterface #14,  2           // InterfaceMethod java/util/List.get:(I)Ljava/lang/Object;
      36: checkcast     #95                 // class java/util/List
      39: areturn

  private static java.lang.String toPrimaryValue(java.util.List<java.lang.String>);
    Code:
       0: aload_0
       1: ifnull        13
       4: aload_0
       5: invokeinterface #94,  1           // InterfaceMethod java/util/List.isEmpty:()Z
      10: ifeq          17
      13: aconst_null
      14: goto          27
      17: aload_0
      18: iconst_0
      19: invokeinterface #14,  2           // InterfaceMethod java/util/List.get:(I)Ljava/lang/Object;
      24: checkcast     #88                 // class java/lang/String
      27: areturn

  private static java.lang.String[] toPrimaryValues(java.util.Collection<java.util.List<java.lang.String>>);
    Code:
       0: aload_0
       1: ifnull        13
       4: aload_0
       5: invokeinterface #96,  1           // InterfaceMethod java/util/Collection.isEmpty:()Z
      10: ifeq          15
      13: aconst_null
      14: areturn
      15: new           #48                 // class java/util/ArrayList
      18: dup
      19: aload_0
      20: invokeinterface #97,  1           // InterfaceMethod java/util/Collection.size:()I
      25: invokespecial #49                 // Method java/util/ArrayList."<init>":(I)V
      28: astore_1
      29: aload_0
      30: invokeinterface #98,  1           // InterfaceMethod java/util/Collection.iterator:()Ljava/util/Iterator;
      35: astore_2
      36: aload_2
      37: invokeinterface #99,  1           // InterfaceMethod java/util/Iterator.hasNext:()Z
      42: ifeq          92
      45: aload_2
      46: invokeinterface #100,  1          // InterfaceMethod java/util/Iterator.next:()Ljava/lang/Object;
      51: checkcast     #95                 // class java/util/List
      54: astore_3
      55: aload_3
      56: iconst_0
      57: invokeinterface #14,  2           // InterfaceMethod java/util/List.get:(I)Ljava/lang/Object;
      62: checkcast     #88                 // class java/lang/String
      65: astore        4
      67: aload         4
      69: ifnull        89
      72: aload         4
      74: invokevirtual #101                // Method java/lang/String.isEmpty:()Z
      77: ifne          89
      80: aload_1
      81: aload         4
      83: invokeinterface #50,  2           // InterfaceMethod java/util/List.add:(Ljava/lang/Object;)Z
      88: pop
      89: goto          36
      92: aload_1
      93: getstatic     #102                // Field EMPTY_STR_ARRAY:[Ljava/lang/String;
      96: invokeinterface #103,  2          // InterfaceMethod java/util/List.toArray:([Ljava/lang/Object;)[Ljava/lang/Object;
     101: checkcast     #104                // class "[Ljava/lang/String;"
     104: areturn

  private static java.lang.String[] toTypes(java.util.Collection<java.util.List<java.lang.String>>);
    Code:
       0: aload_0
       1: ifnull        13
       4: aload_0
       5: invokeinterface #96,  1           // InterfaceMethod java/util/Collection.isEmpty:()Z
      10: ifeq          15
      13: aconst_null
      14: areturn
      15: new           #48                 // class java/util/ArrayList
      18: dup
      19: aload_0
      20: invokeinterface #97,  1           // InterfaceMethod java/util/Collection.size:()I
      25: invokespecial #49                 // Method java/util/ArrayList."<init>":(I)V
      28: astore_1
      29: aload_0
      30: invokeinterface #98,  1           // InterfaceMethod java/util/Collection.iterator:()Ljava/util/Iterator;
      35: astore_2
      36: aload_2
      37: invokeinterface #99,  1           // InterfaceMethod java/util/Iterator.hasNext:()Z
      42: ifeq          179
      45: aload_2
      46: invokeinterface #100,  1          // InterfaceMethod java/util/Iterator.next:()Ljava/lang/Object;
      51: checkcast     #95                 // class java/util/List
      54: astore_3
      55: aload_3
      56: iconst_0
      57: invokeinterface #14,  2           // InterfaceMethod java/util/List.get:(I)Ljava/lang/Object;
      62: checkcast     #88                 // class java/lang/String
      65: astore        4
      67: aload         4
      69: ifnull        176
      72: aload         4
      74: invokevirtual #101                // Method java/lang/String.isEmpty:()Z
      77: ifne          176
      80: aconst_null
      81: astore        5
      83: iconst_1
      84: istore        6
      86: iload         6
      88: aload_3
      89: invokeinterface #105,  1          // InterfaceMethod java/util/List.size:()I
      94: if_icmpge     167
      97: aload_3
      98: iload         6
     100: invokeinterface #14,  2           // InterfaceMethod java/util/List.get:(I)Ljava/lang/Object;
     105: checkcast     #88                 // class java/lang/String
     108: astore        7
     110: aload         7
     112: bipush        61
     114: invokevirtual #106                // Method java/lang/String.indexOf:(I)I
     117: istore        8
     119: iload         8
     121: ifge          131
     124: aload         7
     126: astore        5
     128: goto          167
     131: ldc           #107                // String TYPE
     133: aload         7
     135: iconst_0
     136: iload         8
     138: invokevirtual #60                 // Method java/lang/String.substring:(II)Ljava/lang/String;
     141: invokevirtual #54                 // Method java/lang/String.equalsIgnoreCase:(Ljava/lang/String;)Z
     144: ifeq          161
     147: aload         7
     149: iload         8
     151: iconst_1
     152: iadd
     153: invokevirtual #108                // Method java/lang/String.substring:(I)Ljava/lang/String;
     156: astore        5
     158: goto          167
     161: iinc          6, 1
     164: goto          86
     167: aload_1
     168: aload         5
     170: invokeinterface #50,  2           // InterfaceMethod java/util/List.add:(Ljava/lang/Object;)Z
     175: pop
     176: goto          36
     179: aload_1
     180: getstatic     #102                // Field EMPTY_STR_ARRAY:[Ljava/lang/String;
     183: invokeinterface #103,  2          // InterfaceMethod java/util/List.toArray:([Ljava/lang/Object;)[Ljava/lang/Object;
     188: checkcast     #104                // class "[Ljava/lang/String;"
     191: areturn

  private static boolean isLikeVCardDate(java.lang.CharSequence);
    Code:
       0: aload_0
       1: ifnull        17
       4: getstatic     #109                // Field VCARD_LIKE_DATE:Ljava/util/regex/Pattern;
       7: aload_0
       8: invokevirtual #4                  // Method java/util/regex/Pattern.matcher:(Ljava/lang/CharSequence;)Ljava/util/regex/Matcher;
      11: invokevirtual #110                // Method java/util/regex/Matcher.matches:()Z
      14: ifeq          21
      17: iconst_1
      18: goto          22
      21: iconst_0
      22: ireturn

  private static void formatNames(java.lang.Iterable<java.util.List<java.lang.String>>);
    Code:
       0: aload_0
       1: ifnull        183
       4: aload_0
       5: invokeinterface #111,  1          // InterfaceMethod java/lang/Iterable.iterator:()Ljava/util/Iterator;
      10: astore_1
      11: aload_1
      12: invokeinterface #99,  1           // InterfaceMethod java/util/Iterator.hasNext:()Z
      17: ifeq          183
      20: aload_1
      21: invokeinterface #100,  1          // InterfaceMethod java/util/Iterator.next:()Ljava/lang/Object;
      26: checkcast     #95                 // class java/util/List
      29: astore_2
      30: aload_2
      31: iconst_0
      32: invokeinterface #14,  2           // InterfaceMethod java/util/List.get:(I)Ljava/lang/Object;
      37: checkcast     #88                 // class java/lang/String
      40: astore_3
      41: iconst_5
      42: anewarray     #88                 // class java/lang/String
      45: astore        4
      47: iconst_0
      48: istore        5
      50: iconst_0
      51: istore        7
      53: iload         7
      55: aload         4
      57: arraylength
      58: iconst_1
      59: isub
      60: if_icmpge     102
      63: aload_3
      64: bipush        59
      66: iload         5
      68: invokevirtual #58                 // Method java/lang/String.indexOf:(II)I
      71: dup
      72: istore        6
      74: iflt          102
      77: aload         4
      79: iload         7
      81: aload_3
      82: iload         5
      84: iload         6
      86: invokevirtual #60                 // Method java/lang/String.substring:(II)Ljava/lang/String;
      89: aastore
      90: iinc          7, 1
      93: iload         6
      95: iconst_1
      96: iadd
      97: istore        5
      99: goto          53
     102: aload         4
     104: iload         7
     106: aload_3
     107: iload         5
     109: invokevirtual #108                // Method java/lang/String.substring:(I)Ljava/lang/String;
     112: aastore
     113: new           #35                 // class java/lang/StringBuilder
     116: dup
     117: bipush        100
     119: invokespecial #78                 // Method java/lang/StringBuilder."<init>":(I)V
     122: astore        8
     124: aload         4
     126: iconst_3
     127: aload         8
     129: invokestatic  #112                // Method maybeAppendComponent:([Ljava/lang/String;ILjava/lang/StringBuilder;)V
     132: aload         4
     134: iconst_1
     135: aload         8
     137: invokestatic  #112                // Method maybeAppendComponent:([Ljava/lang/String;ILjava/lang/StringBuilder;)V
     140: aload         4
     142: iconst_2
     143: aload         8
     145: invokestatic  #112                // Method maybeAppendComponent:([Ljava/lang/String;ILjava/lang/StringBuilder;)V
     148: aload         4
     150: iconst_0
     151: aload         8
     153: invokestatic  #112                // Method maybeAppendComponent:([Ljava/lang/String;ILjava/lang/StringBuilder;)V
     156: aload         4
     158: iconst_4
     159: aload         8
     161: invokestatic  #112                // Method maybeAppendComponent:([Ljava/lang/String;ILjava/lang/StringBuilder;)V
     164: aload_2
     165: iconst_0
     166: aload         8
     168: invokevirtual #41                 // Method java/lang/StringBuilder.toString:()Ljava/lang/String;
     171: invokevirtual #61                 // Method java/lang/String.trim:()Ljava/lang/String;
     174: invokeinterface #113,  3          // InterfaceMethod java/util/List.set:(ILjava/lang/Object;)Ljava/lang/Object;
     179: pop
     180: goto          11
     183: return

  private static void maybeAppendComponent(java.lang.String[], int, java.lang.StringBuilder);
    Code:
       0: aload_0
       1: iload_1
       2: aaload
       3: ifnull        37
       6: aload_0
       7: iload_1
       8: aaload
       9: invokevirtual #101                // Method java/lang/String.isEmpty:()Z
      12: ifne          37
      15: aload_2
      16: invokevirtual #114                // Method java/lang/StringBuilder.length:()I
      19: ifle          29
      22: aload_2
      23: bipush        32
      25: invokevirtual #85                 // Method java/lang/StringBuilder.append:(C)Ljava/lang/StringBuilder;
      28: pop
      29: aload_2
      30: aload_0
      31: iload_1
      32: aaload
      33: invokevirtual #38                 // Method java/lang/StringBuilder.append:(Ljava/lang/String;)Ljava/lang/StringBuilder;
      36: pop
      37: return

  public com.google.zxing.client.result.ParsedResult parse(com.google.zxing.Result);
    Code:
       0: aload_0
       1: aload_1
       2: invokevirtual #115                // Method parse:(Lcom/google/zxing/Result;)Lcom/google/zxing/client/result/AddressBookParsedResult;
       5: areturn

  static {};
    Code:
       0: ldc           #116                // String BEGIN:VCARD
       2: iconst_2
       3: invokestatic  #43                 // Method java/util/regex/Pattern.compile:(Ljava/lang/String;I)Ljava/util/regex/Pattern;
       6: putstatic     #3                  // Field BEGIN_VCARD:Ljava/util/regex/Pattern;
       9: ldc           #117                // String \\d{4}-?\\d{2}-?\\d{2}
      11: invokestatic  #118                // Method java/util/regex/Pattern.compile:(Ljava/lang/String;)Ljava/util/regex/Pattern;
      14: putstatic     #109                // Field VCARD_LIKE_DATE:Ljava/util/regex/Pattern;
      17: ldc           #119                // String \r\n[ \t]
      19: invokestatic  #118                // Method java/util/regex/Pattern.compile:(Ljava/lang/String;)Ljava/util/regex/Pattern;
      22: putstatic     #66                 // Field CR_LF_SPACE_TAB:Ljava/util/regex/Pattern;
      25: ldc           #120                // String \\\\[nN]
      27: invokestatic  #118                // Method java/util/regex/Pattern.compile:(Ljava/lang/String;)Ljava/util/regex/Pattern;
      30: putstatic     #68                 // Field NEWLINE_ESCAPE:Ljava/util/regex/Pattern;
      33: ldc           #121                // String \\\\([,;\\\\])
      35: invokestatic  #118                // Method java/util/regex/Pattern.compile:(Ljava/lang/String;)Ljava/util/regex/Pattern;
      38: putstatic     #69                 // Field VCARD_ESCAPES:Ljava/util/regex/Pattern;
      41: ldc           #122                // String =
      43: invokestatic  #118                // Method java/util/regex/Pattern.compile:(Ljava/lang/String;)Ljava/util/regex/Pattern;
      46: putstatic     #51                 // Field EQUALS:Ljava/util/regex/Pattern;
      49: ldc           #123                // String ;
      51: invokestatic  #118                // Method java/util/regex/Pattern.compile:(Ljava/lang/String;)Ljava/util/regex/Pattern;
      54: putstatic     #47                 // Field SEMICOLON:Ljava/util/regex/Pattern;
      57: ldc           #124                // String (?<!\\\\);+
      59: invokestatic  #118                // Method java/util/regex/Pattern.compile:(Ljava/lang/String;)Ljava/util/regex/Pattern;
      62: putstatic     #63                 // Field UNESCAPED_SEMICOLONS:Ljava/util/regex/Pattern;
      65: ldc           #125                // String ,
      67: invokestatic  #118                // Method java/util/regex/Pattern.compile:(Ljava/lang/String;)Ljava/util/regex/Pattern;
      70: putstatic     #13                 // Field COMMA:Ljava/util/regex/Pattern;
      73: ldc           #126                // String [;,]
      75: invokestatic  #118                // Method java/util/regex/Pattern.compile:(Ljava/lang/String;)Ljava/util/regex/Pattern;
      78: putstatic     #28                 // Field SEMICOLON_OR_COMMA:Ljava/util/regex/Pattern;
      81: return
}
