Compiled from "VINParsedResult.java"
public final class com.google.zxing.client.result.VINParsedResult extends com.google.zxing.client.result.ParsedResult {
  private final java.lang.String vin;

  private final java.lang.String worldManufacturerID;

  private final java.lang.String vehicleDescriptorSection;

  private final java.lang.String vehicleIdentifierSection;

  private final java.lang.String countryCode;

  private final java.lang.String vehicleAttributes;

  private final int modelYear;

  private final char plantCode;

  private final java.lang.String sequentialNumber;

  public com.google.zxing.client.result.VINParsedResult(java.lang.String, java.lang.String, java.lang.String, java.lang.String, java.lang.String, java.lang.String, int, char, java.lang.String);
    Code:
       0: aload_0
       1: getstatic     #1                  // Field com/google/zxing/client/result/ParsedResultType.VIN:Lcom/google/zxing/client/result/ParsedResultType;
       4: invokespecial #2                  // Method com/google/zxing/client/result/ParsedResult."<init>":(Lcom/google/zxing/client/result/ParsedResultType;)V
       7: aload_0
       8: aload_1
       9: putfield      #3                  // Field vin:Ljava/lang/String;
      12: aload_0
      13: aload_2
      14: putfield      #4                  // Field worldManufacturerID:Ljava/lang/String;
      17: aload_0
      18: aload_3
      19: putfield      #5                  // Field vehicleDescriptorSection:Ljava/lang/String;
      22: aload_0
      23: aload         4
      25: putfield      #6                  // Field vehicleIdentifierSection:Ljava/lang/String;
      28: aload_0
      29: aload         5
      31: putfield      #7                  // Field countryCode:Ljava/lang/String;
      34: aload_0
      35: aload         6
      37: putfield      #8                  // Field vehicleAttributes:Ljava/lang/String;
      40: aload_0
      41: iload         7
      43: putfield      #9                  // Field modelYear:I
      46: aload_0
      47: iload         8
      49: putfield      #10                 // Field plantCode:C
      52: aload_0
      53: aload         9
      55: putfield      #11                 // Field sequentialNumber:Ljava/lang/String;
      58: return

  public java.lang.String getVIN();
    Code:
       0: aload_0
       1: getfield      #3                  // Field vin:Ljava/lang/String;
       4: areturn

  public java.lang.String getWorldManufacturerID();
    Code:
       0: aload_0
       1: getfield      #4                  // Field worldManufacturerID:Ljava/lang/String;
       4: areturn

  public java.lang.String getVehicleDescriptorSection();
    Code:
       0: aload_0
       1: getfield      #5                  // Field vehicleDescriptorSection:Ljava/lang/String;
       4: areturn

  public java.lang.String getVehicleIdentifierSection();
    Code:
       0: aload_0
       1: getfield      #6                  // Field vehicleIdentifierSection:Ljava/lang/String;
       4: areturn

  public java.lang.String getCountryCode();
    Code:
       0: aload_0
       1: getfield      #7                  // Field countryCode:Ljava/lang/String;
       4: areturn

  public java.lang.String getVehicleAttributes();
    Code:
       0: aload_0
       1: getfield      #8                  // Field vehicleAttributes:Ljava/lang/String;
       4: areturn

  public int getModelYear();
    Code:
       0: aload_0
       1: getfield      #9                  // Field modelYear:I
       4: ireturn

  public char getPlantCode();
    Code:
       0: aload_0
       1: getfield      #10                 // Field plantCode:C
       4: ireturn

  public java.lang.String getSequentialNumber();
    Code:
       0: aload_0
       1: getfield      #11                 // Field sequentialNumber:Ljava/lang/String;
       4: areturn

  public java.lang.String getDisplayResult();
    Code:
       0: new           #12                 // class java/lang/StringBuilder
       3: dup
       4: bipush        50
       6: invokespecial #13                 // Method java/lang/StringBuilder."<init>":(I)V
       9: astore_1
      10: aload_1
      11: aload_0
      12: getfield      #4                  // Field worldManufacturerID:Ljava/lang/String;
      15: invokevirtual #14                 // Method java/lang/StringBuilder.append:(Ljava/lang/String;)Ljava/lang/StringBuilder;
      18: bipush        32
      20: invokevirtual #15                 // Method java/lang/StringBuilder.append:(C)Ljava/lang/StringBuilder;
      23: pop
      24: aload_1
      25: aload_0
      26: getfield      #5                  // Field vehicleDescriptorSection:Ljava/lang/String;
      29: invokevirtual #14                 // Method java/lang/StringBuilder.append:(Ljava/lang/String;)Ljava/lang/StringBuilder;
      32: bipush        32
      34: invokevirtual #15                 // Method java/lang/StringBuilder.append:(C)Ljava/lang/StringBuilder;
      37: pop
      38: aload_1
      39: aload_0
      40: getfield      #6                  // Field vehicleIdentifierSection:Ljava/lang/String;
      43: invokevirtual #14                 // Method java/lang/StringBuilder.append:(Ljava/lang/String;)Ljava/lang/StringBuilder;
      46: bipush        10
      48: invokevirtual #15                 // Method java/lang/StringBuilder.append:(C)Ljava/lang/StringBuilder;
      51: pop
      52: aload_0
      53: getfield      #7                  // Field countryCode:Ljava/lang/String;
      56: ifnull        73
      59: aload_1
      60: aload_0
      61: getfield      #7                  // Field countryCode:Ljava/lang/String;
      64: invokevirtual #14                 // Method java/lang/StringBuilder.append:(Ljava/lang/String;)Ljava/lang/StringBuilder;
      67: bipush        32
      69: invokevirtual #15                 // Method java/lang/StringBuilder.append:(C)Ljava/lang/StringBuilder;
      72: pop
      73: aload_1
      74: aload_0
      75: getfield      #9                  // Field modelYear:I
      78: invokevirtual #16                 // Method java/lang/StringBuilder.append:(I)Ljava/lang/StringBuilder;
      81: bipush        32
      83: invokevirtual #15                 // Method java/lang/StringBuilder.append:(C)Ljava/lang/StringBuilder;
      86: pop
      87: aload_1
      88: aload_0
      89: getfield      #10                 // Field plantCode:C
      92: invokevirtual #15                 // Method java/lang/StringBuilder.append:(C)Ljava/lang/StringBuilder;
      95: bipush        32
      97: invokevirtual #15                 // Method java/lang/StringBuilder.append:(C)Ljava/lang/StringBuilder;
     100: pop
     101: aload_1
     102: aload_0
     103: getfield      #11                 // Field sequentialNumber:Ljava/lang/String;
     106: invokevirtual #14                 // Method java/lang/StringBuilder.append:(Ljava/lang/String;)Ljava/lang/StringBuilder;
     109: bipush        10
     111: invokevirtual #15                 // Method java/lang/StringBuilder.append:(C)Ljava/lang/StringBuilder;
     114: pop
     115: aload_1
     116: invokevirtual #17                 // Method java/lang/StringBuilder.toString:()Ljava/lang/String;
     119: areturn
}
