Compiled from "WifiParsedResult.java"
public final class com.google.zxing.client.result.WifiParsedResult extends com.google.zxing.client.result.ParsedResult {
  private final java.lang.String ssid;

  private final java.lang.String networkEncryption;

  private final java.lang.String password;

  private final boolean hidden;

  private final java.lang.String identity;

  private final java.lang.String anonymousIdentity;

  private final java.lang.String eapMethod;

  private final java.lang.String phase2Method;

  public com.google.zxing.client.result.WifiParsedResult(java.lang.String, java.lang.String, java.lang.String);
    Code:
       0: aload_0
       1: aload_1
       2: aload_2
       3: aload_3
       4: iconst_0
       5: invokespecial #1                  // Method "<init>":(Ljava/lang/String;Ljava/lang/String;Ljava/lang/String;Z)V
       8: return

  public com.google.zxing.client.result.WifiParsedResult(java.lang.String, java.lang.String, java.lang.String, boolean);
    Code:
       0: aload_0
       1: aload_1
       2: aload_2
       3: aload_3
       4: iload         4
       6: aconst_null
       7: aconst_null
       8: aconst_null
       9: aconst_null
      10: invokespecial #2                  // Method "<init>":(Ljava/lang/String;Ljava/lang/String;Ljava/lang/String;ZLjava/lang/String;Ljava/lang/String;Ljava/lang/String;Ljava/lang/String;)V
      13: return

  public com.google.zxing.client.result.WifiParsedResult(java.lang.String, java.lang.String, java.lang.String, boolean, java.lang.String, java.lang.String, java.lang.String, java.lang.String);
    Code:
       0: aload_0
       1: getstatic     #3                  // Field com/google/zxing/client/result/ParsedResultType.WIFI:Lcom/google/zxing/client/result/ParsedResultType;
       4: invokespecial #4                  // Method com/google/zxing/client/result/ParsedResult."<init>":(Lcom/google/zxing/client/result/ParsedResultType;)V
       7: aload_0
       8: aload_2
       9: putfield      #5                  // Field ssid:Ljava/lang/String;
      12: aload_0
      13: aload_1
      14: putfield      #6                  // Field networkEncryption:Ljava/lang/String;
      17: aload_0
      18: aload_3
      19: putfield      #7                  // Field password:Ljava/lang/String;
      22: aload_0
      23: iload         4
      25: putfield      #8                  // Field hidden:Z
      28: aload_0
      29: aload         5
      31: putfield      #9                  // Field identity:Ljava/lang/String;
      34: aload_0
      35: aload         6
      37: putfield      #10                 // Field anonymousIdentity:Ljava/lang/String;
      40: aload_0
      41: aload         7
      43: putfield      #11                 // Field eapMethod:Ljava/lang/String;
      46: aload_0
      47: aload         8
      49: putfield      #12                 // Field phase2Method:Ljava/lang/String;
      52: return

  public java.lang.String getSsid();
    Code:
       0: aload_0
       1: getfield      #5                  // Field ssid:Ljava/lang/String;
       4: areturn

  public java.lang.String getNetworkEncryption();
    Code:
       0: aload_0
       1: getfield      #6                  // Field networkEncryption:Ljava/lang/String;
       4: areturn

  public java.lang.String getPassword();
    Code:
       0: aload_0
       1: getfield      #7                  // Field password:Ljava/lang/String;
       4: areturn

  public boolean isHidden();
    Code:
       0: aload_0
       1: getfield      #8                  // Field hidden:Z
       4: ireturn

  public java.lang.String getIdentity();
    Code:
       0: aload_0
       1: getfield      #9                  // Field identity:Ljava/lang/String;
       4: areturn

  public java.lang.String getAnonymousIdentity();
    Code:
       0: aload_0
       1: getfield      #10                 // Field anonymousIdentity:Ljava/lang/String;
       4: areturn

  public java.lang.String getEapMethod();
    Code:
       0: aload_0
       1: getfield      #11                 // Field eapMethod:Ljava/lang/String;
       4: areturn

  public java.lang.String getPhase2Method();
    Code:
       0: aload_0
       1: getfield      #12                 // Field phase2Method:Ljava/lang/String;
       4: areturn

  public java.lang.String getDisplayResult();
    Code:
       0: new           #13                 // class java/lang/StringBuilder
       3: dup
       4: bipush        80
       6: invokespecial #14                 // Method java/lang/StringBuilder."<init>":(I)V
       9: astore_1
      10: aload_0
      11: getfield      #5                  // Field ssid:Ljava/lang/String;
      14: aload_1
      15: invokestatic  #15                 // Method maybeAppend:(Ljava/lang/String;Ljava/lang/StringBuilder;)V
      18: aload_0
      19: getfield      #6                  // Field networkEncryption:Ljava/lang/String;
      22: aload_1
      23: invokestatic  #15                 // Method maybeAppend:(Ljava/lang/String;Ljava/lang/StringBuilder;)V
      26: aload_0
      27: getfield      #7                  // Field password:Ljava/lang/String;
      30: aload_1
      31: invokestatic  #15                 // Method maybeAppend:(Ljava/lang/String;Ljava/lang/StringBuilder;)V
      34: aload_0
      35: getfield      #8                  // Field hidden:Z
      38: invokestatic  #16                 // Method java/lang/Boolean.toString:(Z)Ljava/lang/String;
      41: aload_1
      42: invokestatic  #15                 // Method maybeAppend:(Ljava/lang/String;Ljava/lang/StringBuilder;)V
      45: aload_1
      46: invokevirtual #17                 // Method java/lang/StringBuilder.toString:()Ljava/lang/String;
      49: areturn
}
