Compiled from "AbortPolicy.java"
public class org.apache.dubbo.common.concurrent.AbortPolicy<E> implements org.apache.dubbo.common.concurrent.Rejector<E> {
  public org.apache.dubbo.common.concurrent.AbortPolicy();
    Code:
       0: aload_0
       1: invokespecial #1                  // Method java/lang/Object."<init>":()V
       4: return

  public void reject(E, java.util.Queue<E>);
    Code:
       0: new           #2                  // class org/apache/dubbo/common/concurrent/RejectException
       3: dup
       4: ldc           #3                  // String no more memory can be used !
       6: invokespecial #4                  // Method org/apache/dubbo/common/concurrent/RejectException."<init>":(Ljava/lang/String;)V
       9: athrow
}
