Compiled from "DiscardOldestPolicy.java"
public class org.apache.dubbo.common.concurrent.DiscardOldestPolicy<E> implements org.apache.dubbo.common.concurrent.Rejector<E> {
  public org.apache.dubbo.common.concurrent.DiscardOldestPolicy();
    Code:
       0: aload_0
       1: invokespecial #1                  // Method java/lang/Object."<init>":()V
       4: return

  public void reject(E, java.util.Queue<E>);
    Code:
       0: aload_2
       1: invokeinterface #2,  1            // InterfaceMethod java/util/Queue.poll:()Ljava/lang/Object;
       6: pop
       7: aload_2
       8: aload_1
       9: invokeinterface #3,  2            // InterfaceMethod java/util/Queue.offer:(Ljava/lang/Object;)Z
      14: pop
      15: return
}
