Compiled from "DynamicParamTable.java"
public final class org.apache.dubbo.common.url.component.param.DynamicParamTable {
  private static int[] KEYS;

  private static java.lang.String[] ORIGIN_KEYS;

  private static org.apache.dubbo.common.url.component.param.ParamValue[] VALUES;

  private static final java.util.Map<java.lang.String, java.lang.Integer> KEY2INDEX;

  private org.apache.dubbo.common.url.component.param.DynamicParamTable();
    Code:
       0: aload_0
       1: invokespecial #1                  // Method java/lang/Object."<init>":()V
       4: new           #2                  // class java/lang/IllegalStateException
       7: dup
       8: invokespecial #3                  // Method java/lang/IllegalStateException."<init>":()V
      11: athrow

  public static int getKeyIndex(boolean, java.lang.String);
    Code:
       0: iload_0
       1: ifne          6
       4: iconst_m1
       5: ireturn
       6: aload_1
       7: invokestatic  #4                  // Method java/lang/System.identityHashCode:(Ljava/lang/Object;)I
      10: istore_2
      11: getstatic     #5                  // Field KEYS:[I
      14: iload_2
      15: invokestatic  #6                  // Method java/util/Arrays.binarySearch:([II)I
      18: istore_3
      19: iload_3
      20: iflt          25
      23: iload_3
      24: ireturn
      25: getstatic     #7                  // Field KEY2INDEX:Ljava/util/Map;
      28: aload_1
      29: invokeinterface #8,  2            // InterfaceMethod java/util/Map.get:(Ljava/lang/Object;)Ljava/lang/Object;
      34: checkcast     #9                  // class java/lang/Integer
      37: astore        4
      39: aload         4
      41: ifnonnull     48
      44: iconst_m1
      45: goto          53
      48: aload         4
      50: invokevirtual #10                 // Method java/lang/Integer.intValue:()I
      53: ireturn

  public static int getValueIndex(java.lang.String, java.lang.String);
    Code:
       0: iconst_1
       1: aload_0
       2: invokestatic  #11                 // Method getKeyIndex:(ZLjava/lang/String;)I
       5: istore_2
       6: iload_2
       7: ifge          37
      10: new           #12                 // class java/lang/IllegalArgumentException
      13: dup
      14: new           #13                 // class java/lang/StringBuilder
      17: dup
      18: invokespecial #14                 // Method java/lang/StringBuilder."<init>":()V
      21: ldc           #15                 // String Cannot found key in url param:
      23: invokevirtual #16                 // Method java/lang/StringBuilder.append:(Ljava/lang/String;)Ljava/lang/StringBuilder;
      26: aload_0
      27: invokevirtual #16                 // Method java/lang/StringBuilder.append:(Ljava/lang/String;)Ljava/lang/StringBuilder;
      30: invokevirtual #17                 // Method java/lang/StringBuilder.toString:()Ljava/lang/String;
      33: invokespecial #18                 // Method java/lang/IllegalArgumentException."<init>":(Ljava/lang/String;)V
      36: athrow
      37: getstatic     #19                 // Field VALUES:[Lorg/apache/dubbo/common/url/component/param/ParamValue;
      40: iload_2
      41: aaload
      42: astore_3
      43: aload_3
      44: aload_1
      45: invokeinterface #20,  2           // InterfaceMethod org/apache/dubbo/common/url/component/param/ParamValue.getIndex:(Ljava/lang/String;)I
      50: ireturn

  public static java.lang.String getKey(int);
    Code:
       0: getstatic     #21                 // Field ORIGIN_KEYS:[Ljava/lang/String;
       3: iload_0
       4: aaload
       5: areturn

  public static java.lang.String getValue(int, int);
    Code:
       0: getstatic     #19                 // Field VALUES:[Lorg/apache/dubbo/common/url/component/param/ParamValue;
       3: iload_0
       4: aaload
       5: iload_1
       6: invokeinterface #22,  2           // InterfaceMethod org/apache/dubbo/common/url/component/param/ParamValue.getN:(I)Ljava/lang/String;
      11: areturn

  private static void init();
    Code:
       0: new           #23                 // class java/util/LinkedList
       3: dup
       4: invokespecial #24                 // Method java/util/LinkedList."<init>":()V
       7: astore_0
       8: new           #23                 // class java/util/LinkedList
      11: dup
      12: invokespecial #24                 // Method java/util/LinkedList."<init>":()V
      15: astore_1
      16: new           #25                 // class java/util/HashMap
      19: dup
      20: bipush        64
      22: invokespecial #26                 // Method java/util/HashMap."<init>":(I)V
      25: astore_2
      26: aload_0
      27: ldc           #27                 // String
      29: invokeinterface #28,  2           // InterfaceMethod java/util/List.add:(Ljava/lang/Object;)Z
      34: pop
      35: aload_1
      36: new           #29                 // class org/apache/dubbo/common/url/component/param/DynamicValues
      39: dup
      40: aconst_null
      41: invokespecial #30                 // Method org/apache/dubbo/common/url/component/param/DynamicValues."<init>":(Ljava/lang/String;)V
      44: invokeinterface #28,  2           // InterfaceMethod java/util/List.add:(Ljava/lang/Object;)Z
      49: pop
      50: invokestatic  #31                 // Method org/apache/dubbo/rpc/model/FrameworkModel.defaultModel:()Lorg/apache/dubbo/rpc/model/FrameworkModel;
      53: ldc           #32                 // class org/apache/dubbo/common/url/component/param/DynamicParamSource
      55: invokevirtual #33                 // Method org/apache/dubbo/rpc/model/FrameworkModel.getExtensionLoader:(Ljava/lang/Class;)Lorg/apache/dubbo/common/extension/ExtensionLoader;
      58: invokevirtual #34                 // Method org/apache/dubbo/common/extension/ExtensionLoader.getSupportedExtensionInstances:()Ljava/util/Set;
      61: aload_0
      62: aload_1
      63: invokedynamic #35,  0             // InvokeDynamic #0:accept:(Ljava/util/List;Ljava/util/List;)Ljava/util/function/Consumer;
      68: invokeinterface #36,  2           // InterfaceMethod java/util/Set.forEach:(Ljava/util/function/Consumer;)V
      73: new           #37                 // class java/util/TreeMap
      76: dup
      77: invokedynamic #38,  0             // InvokeDynamic #1:applyAsInt:()Ljava/util/function/ToIntFunction;
      82: invokestatic  #39                 // InterfaceMethod java/util/Comparator.comparingInt:(Ljava/util/function/ToIntFunction;)Ljava/util/Comparator;
      85: invokespecial #40                 // Method java/util/TreeMap."<init>":(Ljava/util/Comparator;)V
      88: astore_3
      89: iconst_0
      90: istore        4
      92: iload         4
      94: aload_0
      95: invokeinterface #41,  1           // InterfaceMethod java/util/List.size:()I
     100: if_icmpge     130
     103: aload_3
     104: aload_0
     105: iload         4
     107: invokeinterface #42,  2           // InterfaceMethod java/util/List.get:(I)Ljava/lang/Object;
     112: aload_1
     113: iload         4
     115: invokeinterface #42,  2           // InterfaceMethod java/util/List.get:(I)Ljava/lang/Object;
     120: invokevirtual #43                 // Method java/util/TreeMap.put:(Ljava/lang/Object;Ljava/lang/Object;)Ljava/lang/Object;
     123: pop
     124: iinc          4, 1
     127: goto          92
     130: aload_3
     131: invokevirtual #44                 // Method java/util/TreeMap.keySet:()Ljava/util/Set;
     134: invokeinterface #45,  1           // InterfaceMethod java/util/Set.stream:()Ljava/util/stream/Stream;
     139: invokedynamic #46,  0             // InvokeDynamic #2:apply:()Ljava/util/function/Function;
     144: invokeinterface #47,  2           // InterfaceMethod java/util/stream/Stream.map:(Ljava/util/function/Function;)Ljava/util/stream/Stream;
     149: invokedynamic #48,  0             // InvokeDynamic #3:applyAsInt:()Ljava/util/function/ToIntFunction;
     154: invokeinterface #49,  2           // InterfaceMethod java/util/stream/Stream.mapToInt:(Ljava/util/function/ToIntFunction;)Ljava/util/stream/IntStream;
     159: invokeinterface #50,  1           // InterfaceMethod java/util/stream/IntStream.toArray:()[I
     164: putstatic     #5                  // Field KEYS:[I
     167: aload_3
     168: invokevirtual #44                 // Method java/util/TreeMap.keySet:()Ljava/util/Set;
     171: iconst_0
     172: anewarray     #51                 // class java/lang/String
     175: invokeinterface #52,  2           // InterfaceMethod java/util/Set.toArray:([Ljava/lang/Object;)[Ljava/lang/Object;
     180: checkcast     #53                 // class "[Ljava/lang/String;"
     183: putstatic     #21                 // Field ORIGIN_KEYS:[Ljava/lang/String;
     186: aload_3
     187: invokevirtual #54                 // Method java/util/TreeMap.values:()Ljava/util/Collection;
     190: iconst_0
     191: anewarray     #55                 // class org/apache/dubbo/common/url/component/param/ParamValue
     194: invokeinterface #56,  2           // InterfaceMethod java/util/Collection.toArray:([Ljava/lang/Object;)[Ljava/lang/Object;
     199: checkcast     #57                 // class "[Lorg/apache/dubbo/common/url/component/param/ParamValue;"
     202: putstatic     #19                 // Field VALUES:[Lorg/apache/dubbo/common/url/component/param/ParamValue;
     205: iconst_0
     206: istore        4
     208: iload         4
     210: getstatic     #21                 // Field ORIGIN_KEYS:[Ljava/lang/String;
     213: arraylength
     214: if_icmpge     241
     217: aload_2
     218: getstatic     #21                 // Field ORIGIN_KEYS:[Ljava/lang/String;
     221: iload         4
     223: aaload
     224: iload         4
     226: invokestatic  #58                 // Method java/lang/Integer.valueOf:(I)Ljava/lang/Integer;
     229: invokeinterface #59,  3           // InterfaceMethod java/util/Map.put:(Ljava/lang/Object;Ljava/lang/Object;)Ljava/lang/Object;
     234: pop
     235: iinc          4, 1
     238: goto          208
     241: getstatic     #7                  // Field KEY2INDEX:Ljava/util/Map;
     244: aload_2
     245: invokeinterface #60,  2           // InterfaceMethod java/util/Map.putAll:(Ljava/util/Map;)V
     250: return

  private static int lambda$init$1(java.lang.Integer);
    Code:
       0: aload_0
       1: invokevirtual #10                 // Method java/lang/Integer.intValue:()I
       4: ireturn

  private static void lambda$init$0(java.util.List, java.util.List, org.apache.dubbo.common.url.component.param.DynamicParamSource);
    Code:
       0: aload_2
       1: aload_0
       2: aload_1
       3: invokeinterface #61,  3           // InterfaceMethod org/apache/dubbo/common/url/component/param/DynamicParamSource.init:(Ljava/util/List;Ljava/util/List;)V
       8: return

  static {};
    Code:
       0: new           #25                 // class java/util/HashMap
       3: dup
       4: bipush        64
       6: invokespecial #26                 // Method java/util/HashMap."<init>":(I)V
       9: putstatic     #7                  // Field KEY2INDEX:Ljava/util/Map;
      12: invokestatic  #62                 // Method init:()V
      15: return
}
