Compiled from "FixedParamValue.java"
public class org.apache.dubbo.common.url.component.param.FixedParamValue implements org.apache.dubbo.common.url.component.param.ParamValue {
  private final java.lang.String[] values;

  private final java.util.Map<java.lang.String, java.lang.Integer> val2Index;

  public org.apache.dubbo.common.url.component.param.FixedParamValue(java.lang.String...);
    Code:
       0: aload_0
       1: invokespecial #1                  // Method java/lang/Object."<init>":()V
       4: aload_1
       5: arraylength
       6: ifne          19
       9: new           #2                  // class java/lang/IllegalArgumentException
      12: dup
      13: ldc           #3                  // String the array size of values should be larger than 0
      15: invokespecial #4                  // Method java/lang/IllegalArgumentException."<init>":(Ljava/lang/String;)V
      18: athrow
      19: aload_0
      20: aload_1
      21: putfield      #5                  // Field values:[Ljava/lang/String;
      24: new           #6                  // class java/util/HashMap
      27: dup
      28: aload_1
      29: arraylength
      30: invokespecial #7                  // Method java/util/HashMap."<init>":(I)V
      33: astore_2
      34: iconst_0
      35: istore_3
      36: iload_3
      37: aload_1
      38: arraylength
      39: if_icmpge     74
      42: aload_1
      43: iload_3
      44: aaload
      45: ifnull        68
      48: aload_2
      49: aload_1
      50: iload_3
      51: aaload
      52: getstatic     #8                  // Field java/util/Locale.ROOT:Ljava/util/Locale;
      55: invokevirtual #9                  // Method java/lang/String.toLowerCase:(Ljava/util/Locale;)Ljava/lang/String;
      58: iload_3
      59: invokestatic  #10                 // Method java/lang/Integer.valueOf:(I)Ljava/lang/Integer;
      62: invokeinterface #11,  3           // InterfaceMethod java/util/Map.put:(Ljava/lang/Object;Ljava/lang/Object;)Ljava/lang/Object;
      67: pop
      68: iinc          3, 1
      71: goto          36
      74: aload_0
      75: aload_2
      76: invokestatic  #12                 // Method java/util/Collections.unmodifiableMap:(Ljava/util/Map;)Ljava/util/Map;
      79: putfield      #13                 // Field val2Index:Ljava/util/Map;
      82: return

  public java.lang.String getN(int);
    Code:
       0: aload_0
       1: getfield      #5                  // Field values:[Ljava/lang/String;
       4: iload_1
       5: aaload
       6: areturn

  public int getIndex(java.lang.String);
    Code:
       0: aload_0
       1: getfield      #13                 // Field val2Index:Ljava/util/Map;
       4: aload_1
       5: getstatic     #8                  // Field java/util/Locale.ROOT:Ljava/util/Locale;
       8: invokevirtual #9                  // Method java/lang/String.toLowerCase:(Ljava/util/Locale;)Ljava/lang/String;
      11: invokeinterface #14,  2           // InterfaceMethod java/util/Map.get:(Ljava/lang/Object;)Ljava/lang/Object;
      16: checkcast     #15                 // class java/lang/Integer
      19: astore_2
      20: aload_2
      21: ifnonnull     66
      24: new           #2                  // class java/lang/IllegalArgumentException
      27: dup
      28: new           #16                 // class java/lang/StringBuilder
      31: dup
      32: invokespecial #17                 // Method java/lang/StringBuilder."<init>":()V
      35: ldc           #18                 // String unrecognized value
      37: invokevirtual #19                 // Method java/lang/StringBuilder.append:(Ljava/lang/String;)Ljava/lang/StringBuilder;
      40: aload_1
      41: invokevirtual #19                 // Method java/lang/StringBuilder.append:(Ljava/lang/String;)Ljava/lang/StringBuilder;
      44: ldc           #20                 // String  , please check if value is illegal. Permitted values:
      46: invokevirtual #19                 // Method java/lang/StringBuilder.append:(Ljava/lang/String;)Ljava/lang/StringBuilder;
      49: aload_0
      50: getfield      #5                  // Field values:[Ljava/lang/String;
      53: invokestatic  #21                 // Method java/util/Arrays.asList:([Ljava/lang/Object;)Ljava/util/List;
      56: invokevirtual #22                 // Method java/lang/StringBuilder.append:(Ljava/lang/Object;)Ljava/lang/StringBuilder;
      59: invokevirtual #23                 // Method java/lang/StringBuilder.toString:()Ljava/lang/String;
      62: invokespecial #4                  // Method java/lang/IllegalArgumentException."<init>":(Ljava/lang/String;)V
      65: athrow
      66: aload_2
      67: invokevirtual #24                 // Method java/lang/Integer.intValue:()I
      70: ireturn
}
