Compiled from "IgnoredParam.java"
public class org.apache.dubbo.common.url.component.param.IgnoredParam {
  private static final java.util.HashSet<java.lang.String> IGNORED;

  public org.apache.dubbo.common.url.component.param.IgnoredParam();
    Code:
       0: aload_0
       1: invokespecial #1                  // Method java/lang/Object."<init>":()V
       4: return

  static boolean ignore(java.lang.String);
    Code:
       0: getstatic     #2                  // Field IGNORED:Ljava/util/HashSet;
       3: aload_0
       4: invokevirtual #3                  // Method java/util/HashSet.contains:(Ljava/lang/Object;)Z
       7: ireturn

  static {};
    Code:
       0: new           #4                  // class java/util/HashSet
       3: dup
       4: invokespecial #5                  // Method java/util/HashSet."<init>":()V
       7: putstatic     #2                  // Field IGNORED:Ljava/util/HashSet;
      10: getstatic     #2                  // Field IGNORED:Ljava/util/HashSet;
      13: ldc           #6                  // String timestamp
      15: invokevirtual #7                  // Method java/util/HashSet.add:(Ljava/lang/Object;)Z
      18: pop
      19: return
}
