Compiled from "OKHttpRestClient.java"
class org.apache.dubbo.remoting.http.restclient.OKHttpRestClient$1 implements okhttp3.Callback {
  final java.util.concurrent.CompletableFuture val$future;

  final org.apache.dubbo.remoting.http.restclient.OKHttpRestClient this$0;

  org.apache.dubbo.remoting.http.restclient.OKHttpRestClient$1(org.apache.dubbo.remoting.http.restclient.OKHttpRestClient, java.util.concurrent.CompletableFuture);
    Code:
       0: aload_0
       1: aload_1
       2: putfield      #1                  // Field this$0:Lorg/apache/dubbo/remoting/http/restclient/OKHttpRestClient;
       5: aload_0
       6: aload_2
       7: putfield      #2                  // Field val$future:Ljava/util/concurrent/CompletableFuture;
      10: aload_0
      11: invokespecial #3                  // Method java/lang/Object."<init>":()V
      14: return

  public void onFailure(okhttp3.Call, java.io.IOException);
    Code:
       0: aload_0
       1: getfield      #2                  // Field val$future:Ljava/util/concurrent/CompletableFuture;
       4: aload_2
       5: invokevirtual #4                  // Method java/util/concurrent/CompletableFuture.completeExceptionally:(Ljava/lang/Throwable;)Z
       8: pop
       9: return

  public void onResponse(okhttp3.Call, okhttp3.Response) throws java.io.IOException;
    Code:
       0: aload_0
       1: getfield      #2                  // Field val$future:Ljava/util/concurrent/CompletableFuture;
       4: new           #5                  // class org/apache/dubbo/remoting/http/restclient/OKHttpRestClient$1$1
       7: dup
       8: aload_0
       9: aload_2
      10: invokespecial #6                  // Method org/apache/dubbo/remoting/http/restclient/OKHttpRestClient$1$1."<init>":(Lorg/apache/dubbo/remoting/http/restclient/OKHttpRestClient$1;Lokhttp3/Response;)V
      13: invokevirtual #7                  // Method java/util/concurrent/CompletableFuture.complete:(Ljava/lang/Object;)Z
      16: pop
      17: return
}
