Compiled from "OKHttpRestClient.java"
class org.apache.dubbo.remoting.http.restclient.OKHttpRestClient$1$1 implements org.apache.dubbo.remoting.http.RestResult {
  final okhttp3.Response val$response;

  final org.apache.dubbo.remoting.http.restclient.OKHttpRestClient$1 this$1;

  org.apache.dubbo.remoting.http.restclient.OKHttpRestClient$1$1(org.apache.dubbo.remoting.http.restclient.OKHttpRestClient$1, okhttp3.Response);
    Code:
       0: aload_0
       1: aload_1
       2: putfield      #1                  // Field this$1:Lorg/apache/dubbo/remoting/http/restclient/OKHttpRestClient$1;
       5: aload_0
       6: aload_2
       7: putfield      #2                  // Field val$response:Lokhttp3/Response;
      10: aload_0
      11: invokespecial #3                  // Method java/lang/Object."<init>":()V
      14: return

  public java.lang.String getContentType();
    Code:
       0: aload_0
       1: getfield      #2                  // Field val$response:Lokhttp3/Response;
       4: ldc           #4                  // String Content-Type
       6: invokevirtual #5                  // Method okhttp3/Response.header:(Ljava/lang/String;)Ljava/lang/String;
       9: areturn

  public byte[] getBody() throws java.io.IOException;
    Code:
       0: aload_0
       1: getfield      #2                  // Field val$response:Lokhttp3/Response;
       4: invokevirtual #6                  // Method okhttp3/Response.body:()Lokhttp3/ResponseBody;
       7: astore_1
       8: aload_1
       9: ifnonnull     16
      12: aconst_null
      13: goto          20
      16: aload_1
      17: invokevirtual #7                  // Method okhttp3/ResponseBody.bytes:()[B
      20: areturn

  public java.util.Map<java.lang.String, java.util.List<java.lang.String>> headers();
    Code:
       0: aload_0
       1: getfield      #2                  // Field val$response:Lokhttp3/Response;
       4: invokevirtual #8                  // Method okhttp3/Response.headers:()Lokhttp3/Headers;
       7: invokevirtual #9                  // Method okhttp3/Headers.toMultimap:()Ljava/util/Map;
      10: areturn

  public byte[] getErrorResponse() throws java.io.IOException;
    Code:
       0: aload_0
       1: invokevirtual #10                 // Method getBody:()[B
       4: areturn

  public int getResponseCode() throws java.io.IOException;
    Code:
       0: aload_0
       1: getfield      #2                  // Field val$response:Lokhttp3/Response;
       4: invokevirtual #11                 // Method okhttp3/Response.code:()I
       7: ireturn

  public java.lang.String getMessage() throws java.io.IOException;
    Code:
       0: aload_0
       1: aload_0
       2: getfield      #2                  // Field val$response:Lokhttp3/Response;
       5: invokevirtual #12                 // Method okhttp3/Response.message:()Ljava/lang/String;
       8: new           #13                 // class java/lang/String
      11: dup
      12: aload_0
      13: invokevirtual #10                 // Method getBody:()[B
      16: invokespecial #14                 // Method java/lang/String."<init>":([B)V
      19: invokevirtual #15                 // Method appendErrorMessage:(Ljava/lang/String;Ljava/lang/String;)Ljava/lang/String;
      22: areturn
}
