Compiled from "OKHttpRestClient.java"
public class org.apache.dubbo.remoting.http.restclient.OKHttpRestClient implements org.apache.dubbo.remoting.http.RestClient {
  private final okhttp3.OkHttpClient okHttpClient;

  private final org.apache.dubbo.remoting.http.config.HttpClientConfig httpClientConfig;

  public org.apache.dubbo.remoting.http.restclient.OKHttpRestClient(org.apache.dubbo.remoting.http.config.HttpClientConfig);
    Code:
       0: aload_0
       1: invokespecial #1                  // Method java/lang/Object."<init>":()V
       4: aload_0
       5: aload_0
       6: aload_1
       7: invokevirtual #2                  // Method createHttpClient:(Lorg/apache/dubbo/remoting/http/config/HttpClientConfig;)Lokhttp3/OkHttpClient;
      10: putfield      #3                  // Field okHttpClient:Lokhttp3/OkHttpClient;
      13: aload_0
      14: aload_1
      15: putfield      #4                  // Field httpClientConfig:Lorg/apache/dubbo/remoting/http/config/HttpClientConfig;
      18: return

  public java.util.concurrent.CompletableFuture<org.apache.dubbo.remoting.http.RestResult> send(org.apache.dubbo.remoting.http.RequestTemplate);
    Code:
       0: new           #5                  // class okhttp3/Request$Builder
       3: dup
       4: invokespecial #6                  // Method okhttp3/Request$Builder."<init>":()V
       7: astore_2
       8: aload_2
       9: aload_1
      10: invokevirtual #7                  // Method org/apache/dubbo/remoting/http/RequestTemplate.getURL:()Ljava/lang/String;
      13: invokevirtual #8                  // Method okhttp3/Request$Builder.url:(Ljava/lang/String;)Lokhttp3/Request$Builder;
      16: pop
      17: aload_1
      18: invokevirtual #9                  // Method org/apache/dubbo/remoting/http/RequestTemplate.getAllHeaders:()Ljava/util/Map;
      21: astore_3
      22: iconst_0
      23: istore        4
      25: aconst_null
      26: astore        5
      28: aload_1
      29: invokevirtual #10                 // Method org/apache/dubbo/remoting/http/RequestTemplate.getHttpMethod:()Ljava/lang/String;
      32: invokestatic  #11                 // Method okhttp3/internal/http/HttpMethod.permitsRequestBody:(Ljava/lang/String;)Z
      35: ifeq          51
      38: aconst_null
      39: aload_1
      40: invokevirtual #12                 // Method org/apache/dubbo/remoting/http/RequestTemplate.getSerializedBody:()[B
      43: invokestatic  #13                 // Method okhttp3/RequestBody.create:(Lokhttp3/MediaType;[B)Lokhttp3/RequestBody;
      46: astore        5
      48: iconst_1
      49: istore        4
      51: aload_3
      52: invokeinterface #14,  1           // InterfaceMethod java/util/Map.keySet:()Ljava/util/Set;
      57: invokeinterface #15,  1           // InterfaceMethod java/util/Set.iterator:()Ljava/util/Iterator;
      62: astore        6
      64: aload         6
      66: invokeinterface #16,  1           // InterfaceMethod java/util/Iterator.hasNext:()Z
      71: ifeq          163
      74: aload         6
      76: invokeinterface #17,  1           // InterfaceMethod java/util/Iterator.next:()Ljava/lang/Object;
      81: checkcast     #18                 // class java/lang/String
      84: astore        7
      86: aload_3
      87: aload         7
      89: invokeinterface #19,  2           // InterfaceMethod java/util/Map.get:(Ljava/lang/Object;)Ljava/lang/Object;
      94: checkcast     #20                 // class java/util/Collection
      97: astore        8
      99: iload         4
     101: ifne          117
     104: ldc           #21                 // String Content-Length
     106: aload         7
     108: invokevirtual #22                 // Method java/lang/String.equals:(Ljava/lang/Object;)Z
     111: ifeq          117
     114: goto          64
     117: aload         8
     119: invokeinterface #23,  1           // InterfaceMethod java/util/Collection.iterator:()Ljava/util/Iterator;
     124: astore        9
     126: aload         9
     128: invokeinterface #16,  1           // InterfaceMethod java/util/Iterator.hasNext:()Z
     133: ifeq          160
     136: aload         9
     138: invokeinterface #17,  1           // InterfaceMethod java/util/Iterator.next:()Ljava/lang/Object;
     143: checkcast     #18                 // class java/lang/String
     146: astore        10
     148: aload_2
     149: aload         7
     151: aload         10
     153: invokevirtual #24                 // Method okhttp3/Request$Builder.addHeader:(Ljava/lang/String;Ljava/lang/String;)Lokhttp3/Request$Builder;
     156: pop
     157: goto          126
     160: goto          64
     163: aload_2
     164: aload_1
     165: invokevirtual #10                 // Method org/apache/dubbo/remoting/http/RequestTemplate.getHttpMethod:()Ljava/lang/String;
     168: aload         5
     170: invokevirtual #25                 // Method okhttp3/Request$Builder.method:(Ljava/lang/String;Lokhttp3/RequestBody;)Lokhttp3/Request$Builder;
     173: pop
     174: new           #26                 // class java/util/concurrent/CompletableFuture
     177: dup
     178: invokespecial #27                 // Method java/util/concurrent/CompletableFuture."<init>":()V
     181: astore        6
     183: aload_0
     184: getfield      #3                  // Field okHttpClient:Lokhttp3/OkHttpClient;
     187: aload_2
     188: invokevirtual #28                 // Method okhttp3/Request$Builder.build:()Lokhttp3/Request;
     191: invokevirtual #29                 // Method okhttp3/OkHttpClient.newCall:(Lokhttp3/Request;)Lokhttp3/Call;
     194: new           #30                 // class org/apache/dubbo/remoting/http/restclient/OKHttpRestClient$1
     197: dup
     198: aload_0
     199: aload         6
     201: invokespecial #31                 // Method org/apache/dubbo/remoting/http/restclient/OKHttpRestClient$1."<init>":(Lorg/apache/dubbo/remoting/http/restclient/OKHttpRestClient;Ljava/util/concurrent/CompletableFuture;)V
     204: invokeinterface #32,  2           // InterfaceMethod okhttp3/Call.enqueue:(Lokhttp3/Callback;)V
     209: aload         6
     211: areturn

  public void close();
    Code:
       0: aload_0
       1: getfield      #3                  // Field okHttpClient:Lokhttp3/OkHttpClient;
       4: invokevirtual #33                 // Method okhttp3/OkHttpClient.connectionPool:()Lokhttp3/ConnectionPool;
       7: invokevirtual #34                 // Method okhttp3/ConnectionPool.evictAll:()V
      10: return

  public void close(int);
    Code:
       0: return

  public boolean isClosed();
    Code:
       0: aload_0
       1: getfield      #3                  // Field okHttpClient:Lokhttp3/OkHttpClient;
       4: invokevirtual #35                 // Method okhttp3/OkHttpClient.retryOnConnectionFailure:()Z
       7: ireturn

  public okhttp3.OkHttpClient createHttpClient(org.apache.dubbo.remoting.http.config.HttpClientConfig);
    Code:
       0: new           #36                 // class okhttp3/OkHttpClient$Builder
       3: dup
       4: invokespecial #37                 // Method okhttp3/OkHttpClient$Builder."<init>":()V
       7: aload_1
       8: invokevirtual #38                 // Method org/apache/dubbo/remoting/http/config/HttpClientConfig.getReadTimeout:()I
      11: i2l
      12: getstatic     #39                 // Field java/util/concurrent/TimeUnit.SECONDS:Ljava/util/concurrent/TimeUnit;
      15: invokevirtual #40                 // Method okhttp3/OkHttpClient$Builder.readTimeout:(JLjava/util/concurrent/TimeUnit;)Lokhttp3/OkHttpClient$Builder;
      18: aload_1
      19: invokevirtual #41                 // Method org/apache/dubbo/remoting/http/config/HttpClientConfig.getWriteTimeout:()I
      22: i2l
      23: getstatic     #39                 // Field java/util/concurrent/TimeUnit.SECONDS:Ljava/util/concurrent/TimeUnit;
      26: invokevirtual #42                 // Method okhttp3/OkHttpClient$Builder.writeTimeout:(JLjava/util/concurrent/TimeUnit;)Lokhttp3/OkHttpClient$Builder;
      29: aload_1
      30: invokevirtual #43                 // Method org/apache/dubbo/remoting/http/config/HttpClientConfig.getConnectTimeout:()I
      33: i2l
      34: getstatic     #39                 // Field java/util/concurrent/TimeUnit.SECONDS:Ljava/util/concurrent/TimeUnit;
      37: invokevirtual #44                 // Method okhttp3/OkHttpClient$Builder.connectTimeout:(JLjava/util/concurrent/TimeUnit;)Lokhttp3/OkHttpClient$Builder;
      40: invokevirtual #45                 // Method okhttp3/OkHttpClient$Builder.build:()Lokhttp3/OkHttpClient;
      43: astore_2
      44: aload_2
      45: areturn
}
