Compiled from "URLConnectionRestClient.java"
class org.apache.dubbo.remoting.http.restclient.URLConnectionRestClient$1 implements org.apache.dubbo.remoting.http.RestResult {
  final java.net.HttpURLConnection val$connection;

  final org.apache.dubbo.remoting.http.restclient.URLConnectionRestClient this$0;

  org.apache.dubbo.remoting.http.restclient.URLConnectionRestClient$1(org.apache.dubbo.remoting.http.restclient.URLConnectionRestClient, java.net.HttpURLConnection);
    Code:
       0: aload_0
       1: aload_1
       2: putfield      #1                  // Field this$0:Lorg/apache/dubbo/remoting/http/restclient/URLConnectionRestClient;
       5: aload_0
       6: aload_2
       7: putfield      #2                  // Field val$connection:Ljava/net/HttpURLConnection;
      10: aload_0
      11: invokespecial #3                  // Method java/lang/Object."<init>":()V
      14: return

  public java.lang.String getContentType();
    Code:
       0: aload_0
       1: getfield      #2                  // Field val$connection:Ljava/net/HttpURLConnection;
       4: invokevirtual #4                  // Method java/net/HttpURLConnection.getContentType:()Ljava/lang/String;
       7: areturn

  public byte[] getBody() throws java.io.IOException;
    Code:
       0: aload_0
       1: getfield      #2                  // Field val$connection:Ljava/net/HttpURLConnection;
       4: invokevirtual #5                  // Method java/net/HttpURLConnection.getInputStream:()Ljava/io/InputStream;
       7: invokestatic  #6                  // Method org/apache/commons/io/IOUtils.toByteArray:(Ljava/io/InputStream;)[B
      10: areturn

  public java.util.Map<java.lang.String, java.util.List<java.lang.String>> headers();
    Code:
       0: aload_0
       1: getfield      #2                  // Field val$connection:Ljava/net/HttpURLConnection;
       4: invokevirtual #7                  // Method java/net/HttpURLConnection.getHeaderFields:()Ljava/util/Map;
       7: areturn

  public byte[] getErrorResponse() throws java.io.IOException;
    Code:
       0: aload_0
       1: getfield      #2                  // Field val$connection:Ljava/net/HttpURLConnection;
       4: invokevirtual #8                  // Method java/net/HttpURLConnection.getErrorStream:()Ljava/io/InputStream;
       7: invokestatic  #6                  // Method org/apache/commons/io/IOUtils.toByteArray:(Ljava/io/InputStream;)[B
      10: areturn

  public int getResponseCode() throws java.io.IOException;
    Code:
       0: aload_0
       1: getfield      #2                  // Field val$connection:Ljava/net/HttpURLConnection;
       4: invokevirtual #9                  // Method java/net/HttpURLConnection.getResponseCode:()I
       7: ireturn

  public java.lang.String getMessage() throws java.io.IOException;
    Code:
       0: aload_0
       1: aload_0
       2: getfield      #2                  // Field val$connection:Ljava/net/HttpURLConnection;
       5: invokevirtual #10                 // Method java/net/HttpURLConnection.getResponseMessage:()Ljava/lang/String;
       8: new           #11                 // class java/lang/String
      11: dup
      12: aload_0
      13: invokevirtual #12                 // Method getErrorResponse:()[B
      16: invokespecial #13                 // Method java/lang/String."<init>":([B)V
      19: invokevirtual #14                 // Method appendErrorMessage:(Ljava/lang/String;Ljava/lang/String;)Ljava/lang/String;
      22: areturn
}
