Compiled from "URLConnectionRestClient.java"
public class org.apache.dubbo.remoting.http.restclient.URLConnectionRestClient implements org.apache.dubbo.remoting.http.RestClient {
  private final org.apache.dubbo.remoting.http.config.HttpClientConfig clientConfig;

  public org.apache.dubbo.remoting.http.restclient.URLConnectionRestClient(org.apache.dubbo.remoting.http.config.HttpClientConfig);
    Code:
       0: aload_0
       1: invokespecial #1                  // Method java/lang/Object."<init>":()V
       4: aload_0
       5: aload_1
       6: putfield      #2                  // Field clientConfig:Lorg/apache/dubbo/remoting/http/config/HttpClientConfig;
       9: return

  public java.util.concurrent.CompletableFuture<org.apache.dubbo.remoting.http.RestResult> send(org.apache.dubbo.remoting.http.RequestTemplate);
    Code:
       0: new           #3                  // class java/util/concurrent/CompletableFuture
       3: dup
       4: invokespecial #4                  // Method java/util/concurrent/CompletableFuture."<init>":()V
       7: astore_2
       8: new           #5                  // class java/net/URL
      11: dup
      12: aload_1
      13: invokevirtual #6                  // Method org/apache/dubbo/remoting/http/RequestTemplate.getURL:()Ljava/lang/String;
      16: invokespecial #7                  // Method java/net/URL."<init>":(Ljava/lang/String;)V
      19: invokevirtual #8                  // Method java/net/URL.openConnection:()Ljava/net/URLConnection;
      22: checkcast     #9                  // class java/net/HttpURLConnection
      25: astore_3
      26: aload_3
      27: aload_0
      28: getfield      #2                  // Field clientConfig:Lorg/apache/dubbo/remoting/http/config/HttpClientConfig;
      31: invokevirtual #10                 // Method org/apache/dubbo/remoting/http/config/HttpClientConfig.getConnectTimeout:()I
      34: invokevirtual #11                 // Method java/net/HttpURLConnection.setConnectTimeout:(I)V
      37: aload_3
      38: aload_0
      39: getfield      #2                  // Field clientConfig:Lorg/apache/dubbo/remoting/http/config/HttpClientConfig;
      42: invokevirtual #12                 // Method org/apache/dubbo/remoting/http/config/HttpClientConfig.getReadTimeout:()I
      45: invokevirtual #13                 // Method java/net/HttpURLConnection.setReadTimeout:(I)V
      48: aload_3
      49: aload_1
      50: invokevirtual #14                 // Method org/apache/dubbo/remoting/http/RequestTemplate.getHttpMethod:()Ljava/lang/String;
      53: invokevirtual #15                 // Method java/net/HttpURLConnection.setRequestMethod:(Ljava/lang/String;)V
      56: aload_0
      57: aload_3
      58: aload_1
      59: invokevirtual #14                 // Method org/apache/dubbo/remoting/http/RequestTemplate.getHttpMethod:()Ljava/lang/String;
      62: invokespecial #16                 // Method prepareConnection:(Ljava/net/HttpURLConnection;Ljava/lang/String;)V
      65: aload_1
      66: invokevirtual #17                 // Method org/apache/dubbo/remoting/http/RequestTemplate.getAllHeaders:()Ljava/util/Map;
      69: invokeinterface #18,  1           // InterfaceMethod java/util/Map.keySet:()Ljava/util/Set;
      74: invokeinterface #19,  1           // InterfaceMethod java/util/Set.iterator:()Ljava/util/Iterator;
      79: astore        4
      81: aload         4
      83: invokeinterface #20,  1           // InterfaceMethod java/util/Iterator.hasNext:()Z
      88: ifeq          152
      91: aload         4
      93: invokeinterface #21,  1           // InterfaceMethod java/util/Iterator.next:()Ljava/lang/Object;
      98: checkcast     #22                 // class java/lang/String
     101: astore        5
     103: aload_1
     104: aload         5
     106: invokevirtual #23                 // Method org/apache/dubbo/remoting/http/RequestTemplate.getHeaders:(Ljava/lang/String;)Ljava/util/Collection;
     109: invokeinterface #24,  1           // InterfaceMethod java/util/Collection.iterator:()Ljava/util/Iterator;
     114: astore        6
     116: aload         6
     118: invokeinterface #20,  1           // InterfaceMethod java/util/Iterator.hasNext:()Z
     123: ifeq          149
     126: aload         6
     128: invokeinterface #21,  1           // InterfaceMethod java/util/Iterator.next:()Ljava/lang/Object;
     133: checkcast     #22                 // class java/lang/String
     136: astore        7
     138: aload_3
     139: aload         5
     141: aload         7
     143: invokevirtual #25                 // Method java/net/HttpURLConnection.addRequestProperty:(Ljava/lang/String;Ljava/lang/String;)V
     146: goto          116
     149: goto          81
     152: aload_1
     153: invokevirtual #26                 // Method org/apache/dubbo/remoting/http/RequestTemplate.isGzipEncodedRequest:()Z
     156: istore        4
     158: aload_1
     159: invokevirtual #27                 // Method org/apache/dubbo/remoting/http/RequestTemplate.isDeflateEncodedRequest:()Z
     162: istore        5
     164: aload_1
     165: invokevirtual #28                 // Method org/apache/dubbo/remoting/http/RequestTemplate.isBodyEmpty:()Z
     168: ifeq          183
     171: aload_2
     172: aload_0
     173: aload_3
     174: invokespecial #29                 // Method getRestResultFromConnection:(Ljava/net/HttpURLConnection;)Lorg/apache/dubbo/remoting/http/RestResult;
     177: invokevirtual #30                 // Method java/util/concurrent/CompletableFuture.complete:(Ljava/lang/Object;)Z
     180: pop
     181: aload_2
     182: areturn
     183: aload_1
     184: invokevirtual #31                 // Method org/apache/dubbo/remoting/http/RequestTemplate.getContentLength:()Ljava/lang/Integer;
     187: astore        6
     189: aload         6
     191: ifnull        206
     194: aload_3
     195: aload         6
     197: invokevirtual #32                 // Method java/lang/Integer.intValue:()I
     200: invokevirtual #33                 // Method java/net/HttpURLConnection.setFixedLengthStreamingMode:(I)V
     203: goto          217
     206: aload_3
     207: aload_0
     208: getfield      #2                  // Field clientConfig:Lorg/apache/dubbo/remoting/http/config/HttpClientConfig;
     211: invokevirtual #34                 // Method org/apache/dubbo/remoting/http/config/HttpClientConfig.getChunkLength:()I
     214: invokevirtual #35                 // Method java/net/HttpURLConnection.setChunkedStreamingMode:(I)V
     217: aload_3
     218: invokevirtual #36                 // Method java/net/HttpURLConnection.getOutputStream:()Ljava/io/OutputStream;
     221: astore        7
     223: iload         4
     225: ifeq          242
     228: new           #37                 // class java/util/zip/GZIPOutputStream
     231: dup
     232: aload         7
     234: invokespecial #38                 // Method java/util/zip/GZIPOutputStream."<init>":(Ljava/io/OutputStream;)V
     237: astore        7
     239: goto          258
     242: iload         5
     244: ifeq          258
     247: new           #39                 // class java/util/zip/DeflaterOutputStream
     250: dup
     251: aload         7
     253: invokespecial #40                 // Method java/util/zip/DeflaterOutputStream."<init>":(Ljava/io/OutputStream;)V
     256: astore        7
     258: aload         7
     260: aload_1
     261: invokevirtual #41                 // Method org/apache/dubbo/remoting/http/RequestTemplate.getSerializedBody:()[B
     264: invokevirtual #42                 // Method java/io/OutputStream.write:([B)V
     267: aload         7
     269: invokevirtual #43                 // Method java/io/OutputStream.close:()V
     272: goto          295
     275: astore        8
     277: goto          295
     280: astore        9
     282: aload         7
     284: invokevirtual #43                 // Method java/io/OutputStream.close:()V
     287: goto          292
     290: astore        10
     292: aload         9
     294: athrow
     295: aload_2
     296: aload_0
     297: aload_3
     298: invokespecial #29                 // Method getRestResultFromConnection:(Ljava/net/HttpURLConnection;)Lorg/apache/dubbo/remoting/http/RestResult;
     301: invokevirtual #30                 // Method java/util/concurrent/CompletableFuture.complete:(Ljava/lang/Object;)Z
     304: pop
     305: goto          315
     308: astore_3
     309: aload_2
     310: aload_3
     311: invokevirtual #46                 // Method java/util/concurrent/CompletableFuture.completeExceptionally:(Ljava/lang/Throwable;)Z
     314: pop
     315: aload_2
     316: areturn
    Exception table:
       from    to  target type
         267   272   275   Class java/io/IOException
         258   267   280   any
         282   287   290   Class java/io/IOException
         280   282   280   any
           8   182   308   Class java/lang/Exception
         183   305   308   Class java/lang/Exception

  public void close();
    Code:
       0: return

  public void close(int);
    Code:
       0: return

  public boolean isClosed();
    Code:
       0: iconst_1
       1: ireturn

  private org.apache.dubbo.remoting.http.RestResult getRestResultFromConnection(java.net.HttpURLConnection);
    Code:
       0: new           #47                 // class org/apache/dubbo/remoting/http/restclient/URLConnectionRestClient$1
       3: dup
       4: aload_0
       5: aload_1
       6: invokespecial #48                 // Method org/apache/dubbo/remoting/http/restclient/URLConnectionRestClient$1."<init>":(Lorg/apache/dubbo/remoting/http/restclient/URLConnectionRestClient;Ljava/net/HttpURLConnection;)V
       9: areturn

  private void prepareConnection(java.net.HttpURLConnection, java.lang.String) throws java.io.IOException;
    Code:
       0: aload_1
       1: iconst_1
       2: invokevirtual #49                 // Method java/net/HttpURLConnection.setDoInput:(Z)V
       5: ldc           #50                 // String GET
       7: aload_2
       8: invokevirtual #51                 // Method java/lang/String.equals:(Ljava/lang/Object;)Z
      11: ifeq          22
      14: aload_1
      15: iconst_1
      16: invokevirtual #52                 // Method java/net/HttpURLConnection.setInstanceFollowRedirects:(Z)V
      19: goto          27
      22: aload_1
      23: iconst_0
      24: invokevirtual #52                 // Method java/net/HttpURLConnection.setInstanceFollowRedirects:(Z)V
      27: ldc           #53                 // String POST
      29: aload_2
      30: invokevirtual #51                 // Method java/lang/String.equals:(Ljava/lang/Object;)Z
      33: ifne          63
      36: ldc           #54                 // String PUT
      38: aload_2
      39: invokevirtual #51                 // Method java/lang/String.equals:(Ljava/lang/Object;)Z
      42: ifne          63
      45: ldc           #55                 // String PATCH
      47: aload_2
      48: invokevirtual #51                 // Method java/lang/String.equals:(Ljava/lang/Object;)Z
      51: ifne          63
      54: ldc           #56                 // String DELETE
      56: aload_2
      57: invokevirtual #51                 // Method java/lang/String.equals:(Ljava/lang/Object;)Z
      60: ifeq          71
      63: aload_1
      64: iconst_1
      65: invokevirtual #57                 // Method java/net/HttpURLConnection.setDoOutput:(Z)V
      68: goto          76
      71: aload_1
      72: iconst_0
      73: invokevirtual #57                 // Method java/net/HttpURLConnection.setDoOutput:(Z)V
      76: aload_1
      77: aload_2
      78: invokevirtual #15                 // Method java/net/HttpURLConnection.setRequestMethod:(Ljava/lang/String;)V
      81: return
}
