Compiled from "AbstractConditionMatcher.java"
public abstract class org.apache.dubbo.rpc.cluster.router.condition.matcher.AbstractConditionMatcher implements org.apache.dubbo.rpc.cluster.router.condition.matcher.ConditionMatcher {
  public static final org.apache.dubbo.common.logger.ErrorTypeAwareLogger logger;

  public static final java.lang.String DOES_NOT_FOUND_VALUE;

  final java.util.Set<java.lang.String> matches;

  final java.util.Set<java.lang.String> mismatches;

  private final org.apache.dubbo.rpc.model.ModuleModel model;

  private final java.util.List<org.apache.dubbo.rpc.cluster.router.condition.matcher.pattern.ValuePattern> valueMatchers;

  protected final java.lang.String key;

  public org.apache.dubbo.rpc.cluster.router.condition.matcher.AbstractConditionMatcher(java.lang.String, org.apache.dubbo.rpc.model.ModuleModel);
    Code:
       0: aload_0
       1: invokespecial #3                  // Method java/lang/Object."<init>":()V
       4: aload_0
       5: new           #4                  // class java/util/HashSet
       8: dup
       9: invokespecial #5                  // Method java/util/HashSet."<init>":()V
      12: putfield      #6                  // Field matches:Ljava/util/Set;
      15: aload_0
      16: new           #4                  // class java/util/HashSet
      19: dup
      20: invokespecial #5                  // Method java/util/HashSet."<init>":()V
      23: putfield      #7                  // Field mismatches:Ljava/util/Set;
      26: aload_0
      27: aload_1
      28: putfield      #8                  // Field key:Ljava/lang/String;
      31: aload_0
      32: aload_2
      33: putfield      #9                  // Field model:Lorg/apache/dubbo/rpc/model/ModuleModel;
      36: aload_0
      37: aload_2
      38: ldc           #10                 // class org/apache/dubbo/rpc/cluster/router/condition/matcher/pattern/ValuePattern
      40: invokevirtual #11                 // Method org/apache/dubbo/rpc/model/ModuleModel.getExtensionLoader:(Ljava/lang/Class;)Lorg/apache/dubbo/common/extension/ExtensionLoader;
      43: invokevirtual #12                 // Method org/apache/dubbo/common/extension/ExtensionLoader.getActivateExtensions:()Ljava/util/List;
      46: putfield      #13                 // Field valueMatchers:Ljava/util/List;
      49: return

  public static java.lang.String getSampleValueFromUrl(java.lang.String, java.util.Map<java.lang.String, java.lang.String>, org.apache.dubbo.common.URL, org.apache.dubbo.rpc.Invocation);
    Code:
       0: aload_3
       1: ifnull        33
       4: ldc           #14                 // String method
       6: aload_0
       7: invokevirtual #15                 // Method java/lang/String.equals:(Ljava/lang/Object;)Z
      10: ifne          22
      13: ldc           #16                 // String methods
      15: aload_0
      16: invokevirtual #15                 // Method java/lang/String.equals:(Ljava/lang/Object;)Z
      19: ifeq          33
      22: aload_3
      23: invokeinterface #17,  1           // InterfaceMethod org/apache/dubbo/rpc/Invocation.getMethodName:()Ljava/lang/String;
      28: astore        4
      30: goto          45
      33: aload_1
      34: aload_0
      35: invokeinterface #18,  2           // InterfaceMethod java/util/Map.get:(Ljava/lang/Object;)Ljava/lang/Object;
      40: checkcast     #19                 // class java/lang/String
      43: astore        4
      45: aload         4
      47: areturn

  public boolean isMatch(java.util.Map<java.lang.String, java.lang.String>, org.apache.dubbo.common.URL, org.apache.dubbo.rpc.Invocation, boolean);
    Code:
       0: aload_0
       1: aload_1
       2: aload_2
       3: aload_3
       4: invokevirtual #20                 // Method getValue:(Ljava/util/Map;Lorg/apache/dubbo/common/URL;Lorg/apache/dubbo/rpc/Invocation;)Ljava/lang/String;
       7: astore        5
       9: aload         5
      11: ifnonnull     16
      14: iconst_0
      15: ireturn
      16: aload_0
      17: getfield      #6                  // Field matches:Ljava/util/Set;
      20: invokeinterface #21,  1           // InterfaceMethod java/util/Set.isEmpty:()Z
      25: ifne          95
      28: aload_0
      29: getfield      #7                  // Field mismatches:Ljava/util/Set;
      32: invokeinterface #21,  1           // InterfaceMethod java/util/Set.isEmpty:()Z
      37: ifeq          95
      40: aload_0
      41: getfield      #6                  // Field matches:Ljava/util/Set;
      44: invokeinterface #22,  1           // InterfaceMethod java/util/Set.iterator:()Ljava/util/Iterator;
      49: astore        6
      51: aload         6
      53: invokeinterface #23,  1           // InterfaceMethod java/util/Iterator.hasNext:()Z
      58: ifeq          93
      61: aload         6
      63: invokeinterface #24,  1           // InterfaceMethod java/util/Iterator.next:()Ljava/lang/Object;
      68: checkcast     #19                 // class java/lang/String
      71: astore        7
      73: aload_0
      74: aload         7
      76: aload         5
      78: aload_2
      79: aload_3
      80: iload         4
      82: invokevirtual #25                 // Method doPatternMatch:(Ljava/lang/String;Ljava/lang/String;Lorg/apache/dubbo/common/URL;Lorg/apache/dubbo/rpc/Invocation;Z)Z
      85: ifeq          90
      88: iconst_1
      89: ireturn
      90: goto          51
      93: iconst_0
      94: ireturn
      95: aload_0
      96: getfield      #7                  // Field mismatches:Ljava/util/Set;
      99: invokeinterface #21,  1           // InterfaceMethod java/util/Set.isEmpty:()Z
     104: ifne          174
     107: aload_0
     108: getfield      #6                  // Field matches:Ljava/util/Set;
     111: invokeinterface #21,  1           // InterfaceMethod java/util/Set.isEmpty:()Z
     116: ifeq          174
     119: aload_0
     120: getfield      #7                  // Field mismatches:Ljava/util/Set;
     123: invokeinterface #22,  1           // InterfaceMethod java/util/Set.iterator:()Ljava/util/Iterator;
     128: astore        6
     130: aload         6
     132: invokeinterface #23,  1           // InterfaceMethod java/util/Iterator.hasNext:()Z
     137: ifeq          172
     140: aload         6
     142: invokeinterface #24,  1           // InterfaceMethod java/util/Iterator.next:()Ljava/lang/Object;
     147: checkcast     #19                 // class java/lang/String
     150: astore        7
     152: aload_0
     153: aload         7
     155: aload         5
     157: aload_2
     158: aload_3
     159: iload         4
     161: invokevirtual #25                 // Method doPatternMatch:(Ljava/lang/String;Ljava/lang/String;Lorg/apache/dubbo/common/URL;Lorg/apache/dubbo/rpc/Invocation;Z)Z
     164: ifeq          169
     167: iconst_0
     168: ireturn
     169: goto          130
     172: iconst_1
     173: ireturn
     174: aload_0
     175: getfield      #6                  // Field matches:Ljava/util/Set;
     178: invokeinterface #21,  1           // InterfaceMethod java/util/Set.isEmpty:()Z
     183: ifne          306
     186: aload_0
     187: getfield      #7                  // Field mismatches:Ljava/util/Set;
     190: invokeinterface #21,  1           // InterfaceMethod java/util/Set.isEmpty:()Z
     195: ifne          306
     198: aload_0
     199: getfield      #7                  // Field mismatches:Ljava/util/Set;
     202: invokeinterface #22,  1           // InterfaceMethod java/util/Set.iterator:()Ljava/util/Iterator;
     207: astore        6
     209: aload         6
     211: invokeinterface #23,  1           // InterfaceMethod java/util/Iterator.hasNext:()Z
     216: ifeq          251
     219: aload         6
     221: invokeinterface #24,  1           // InterfaceMethod java/util/Iterator.next:()Ljava/lang/Object;
     226: checkcast     #19                 // class java/lang/String
     229: astore        7
     231: aload_0
     232: aload         7
     234: aload         5
     236: aload_2
     237: aload_3
     238: iload         4
     240: invokevirtual #25                 // Method doPatternMatch:(Ljava/lang/String;Ljava/lang/String;Lorg/apache/dubbo/common/URL;Lorg/apache/dubbo/rpc/Invocation;Z)Z
     243: ifeq          248
     246: iconst_0
     247: ireturn
     248: goto          209
     251: aload_0
     252: getfield      #6                  // Field matches:Ljava/util/Set;
     255: invokeinterface #22,  1           // InterfaceMethod java/util/Set.iterator:()Ljava/util/Iterator;
     260: astore        6
     262: aload         6
     264: invokeinterface #23,  1           // InterfaceMethod java/util/Iterator.hasNext:()Z
     269: ifeq          304
     272: aload         6
     274: invokeinterface #24,  1           // InterfaceMethod java/util/Iterator.next:()Ljava/lang/Object;
     279: checkcast     #19                 // class java/lang/String
     282: astore        7
     284: aload_0
     285: aload         7
     287: aload         5
     289: aload_2
     290: aload_3
     291: iload         4
     293: invokevirtual #25                 // Method doPatternMatch:(Ljava/lang/String;Ljava/lang/String;Lorg/apache/dubbo/common/URL;Lorg/apache/dubbo/rpc/Invocation;Z)Z
     296: ifeq          301
     299: iconst_1
     300: ireturn
     301: goto          262
     304: iconst_0
     305: ireturn
     306: iconst_0
     307: ireturn

  public java.util.Set<java.lang.String> getMatches();
    Code:
       0: aload_0
       1: getfield      #6                  // Field matches:Ljava/util/Set;
       4: areturn

  public java.util.Set<java.lang.String> getMismatches();
    Code:
       0: aload_0
       1: getfield      #7                  // Field mismatches:Ljava/util/Set;
       4: areturn

  protected boolean doPatternMatch(java.lang.String, java.lang.String, org.apache.dubbo.common.URL, org.apache.dubbo.rpc.Invocation, boolean);
    Code:
       0: aload_0
       1: getfield      #13                 // Field valueMatchers:Ljava/util/List;
       4: invokeinterface #26,  1           // InterfaceMethod java/util/List.iterator:()Ljava/util/Iterator;
       9: astore        6
      11: aload         6
      13: invokeinterface #23,  1           // InterfaceMethod java/util/Iterator.hasNext:()Z
      18: ifeq          62
      21: aload         6
      23: invokeinterface #24,  1           // InterfaceMethod java/util/Iterator.next:()Ljava/lang/Object;
      28: checkcast     #10                 // class org/apache/dubbo/rpc/cluster/router/condition/matcher/pattern/ValuePattern
      31: astore        7
      33: aload         7
      35: aload_1
      36: invokeinterface #27,  2           // InterfaceMethod org/apache/dubbo/rpc/cluster/router/condition/matcher/pattern/ValuePattern.shouldMatch:(Ljava/lang/String;)Z
      41: ifeq          59
      44: aload         7
      46: aload_1
      47: aload_2
      48: aload_3
      49: aload         4
      51: iload         5
      53: invokeinterface #28,  6           // InterfaceMethod org/apache/dubbo/rpc/cluster/router/condition/matcher/pattern/ValuePattern.match:(Ljava/lang/String;Ljava/lang/String;Lorg/apache/dubbo/common/URL;Lorg/apache/dubbo/rpc/Invocation;Z)Z
      58: ireturn
      59: goto          11
      62: getstatic     #29                 // Field logger:Lorg/apache/dubbo/common/logger/ErrorTypeAwareLogger;
      65: ldc           #30                 // String 2-7
      67: ldc           #31                 // String Executing condition rule value match expression error.
      69: new           #32                 // class java/lang/StringBuilder
      72: dup
      73: invokespecial #33                 // Method java/lang/StringBuilder."<init>":()V
      76: ldc           #34                 // String pattern is
      78: invokevirtual #35                 // Method java/lang/StringBuilder.append:(Ljava/lang/String;)Ljava/lang/StringBuilder;
      81: aload_1
      82: invokevirtual #35                 // Method java/lang/StringBuilder.append:(Ljava/lang/String;)Ljava/lang/StringBuilder;
      85: ldc           #36                 // String , value is
      87: invokevirtual #35                 // Method java/lang/StringBuilder.append:(Ljava/lang/String;)Ljava/lang/StringBuilder;
      90: aload_2
      91: invokevirtual #35                 // Method java/lang/StringBuilder.append:(Ljava/lang/String;)Ljava/lang/StringBuilder;
      94: ldc           #37                 // String , condition type
      96: invokevirtual #35                 // Method java/lang/StringBuilder.append:(Ljava/lang/String;)Ljava/lang/StringBuilder;
      99: iload         5
     101: ifeq          109
     104: ldc           #38                 // String when
     106: goto          111
     109: ldc           #39                 // String then
     111: invokevirtual #35                 // Method java/lang/StringBuilder.append:(Ljava/lang/String;)Ljava/lang/StringBuilder;
     114: invokevirtual #40                 // Method java/lang/StringBuilder.toString:()Ljava/lang/String;
     117: ldc           #41                 // String There should at least has one ValueMatcher instance that applies to all patterns, will force to use wildcard matcher now.
     119: invokeinterface #42,  5           // InterfaceMethod org/apache/dubbo/common/logger/ErrorTypeAwareLogger.error:(Ljava/lang/String;Ljava/lang/String;Ljava/lang/String;Ljava/lang/String;)V
     124: aload_0
     125: getfield      #9                  // Field model:Lorg/apache/dubbo/rpc/model/ModuleModel;
     128: ldc           #10                 // class org/apache/dubbo/rpc/cluster/router/condition/matcher/pattern/ValuePattern
     130: invokevirtual #11                 // Method org/apache/dubbo/rpc/model/ModuleModel.getExtensionLoader:(Ljava/lang/Class;)Lorg/apache/dubbo/common/extension/ExtensionLoader;
     133: ldc           #43                 // String wildcard
     135: invokevirtual #44                 // Method org/apache/dubbo/common/extension/ExtensionLoader.getExtension:(Ljava/lang/String;)Ljava/lang/Object;
     138: checkcast     #10                 // class org/apache/dubbo/rpc/cluster/router/condition/matcher/pattern/ValuePattern
     141: astore        6
     143: aload         6
     145: aload_1
     146: aload_2
     147: aload_3
     148: aload         4
     150: iload         5
     152: invokeinterface #28,  6           // InterfaceMethod org/apache/dubbo/rpc/cluster/router/condition/matcher/pattern/ValuePattern.match:(Ljava/lang/String;Ljava/lang/String;Lorg/apache/dubbo/common/URL;Lorg/apache/dubbo/rpc/Invocation;Z)Z
     157: ireturn

  protected abstract java.lang.String getValue(java.util.Map<java.lang.String, java.lang.String>, org.apache.dubbo.common.URL, org.apache.dubbo.rpc.Invocation);

  static {};
    Code:
       0: ldc           #45                 // class org/apache/dubbo/rpc/cluster/router/condition/matcher/AbstractConditionMatcher
       2: invokestatic  #46                 // Method org/apache/dubbo/common/logger/LoggerFactory.getErrorTypeAwareLogger:(Ljava/lang/Class;)Lorg/apache/dubbo/common/logger/ErrorTypeAwareLogger;
       5: putstatic     #29                 // Field logger:Lorg/apache/dubbo/common/logger/ErrorTypeAwareLogger;
       8: return
}
