Compiled from "FileSystemDynamicConfiguration.java"
final class org.apache.dubbo.common.config.configcenter.file.FileSystemDynamicConfiguration$1 extends java.util.HashMap<java.lang.String, org.apache.dubbo.common.config.configcenter.ConfigChangeType> {
  org.apache.dubbo.common.config.configcenter.file.FileSystemDynamicConfiguration$1();
    Code:
       0: aload_0
       1: invokespecial #1                  // Method java/util/HashMap."<init>":()V
       4: aload_0
       5: getstatic     #2                  // Field java/nio/file/StandardWatchEventKinds.ENTRY_CREATE:Ljava/nio/file/WatchEvent$Kind;
       8: invokeinterface #3,  1            // InterfaceMethod java/nio/file/WatchEvent$Kind.name:()Ljava/lang/String;
      13: getstatic     #4                  // Field org/apache/dubbo/common/config/configcenter/ConfigChangeType.ADDED:Lorg/apache/dubbo/common/config/configcenter/ConfigChangeType;
      16: invokevirtual #5                  // Method put:(Ljava/lang/Object;Ljava/lang/Object;)Ljava/lang/Object;
      19: pop
      20: aload_0
      21: getstatic     #6                  // Field java/nio/file/StandardWatchEventKinds.ENTRY_DELETE:Ljava/nio/file/WatchEvent$Kind;
      24: invokeinterface #3,  1            // InterfaceMethod java/nio/file/WatchEvent$Kind.name:()Ljava/lang/String;
      29: getstatic     #7                  // Field org/apache/dubbo/common/config/configcenter/ConfigChangeType.DELETED:Lorg/apache/dubbo/common/config/configcenter/ConfigChangeType;
      32: invokevirtual #5                  // Method put:(Ljava/lang/Object;Ljava/lang/Object;)Ljava/lang/Object;
      35: pop
      36: aload_0
      37: getstatic     #8                  // Field java/nio/file/StandardWatchEventKinds.ENTRY_MODIFY:Ljava/nio/file/WatchEvent$Kind;
      40: invokeinterface #3,  1            // InterfaceMethod java/nio/file/WatchEvent$Kind.name:()Ljava/lang/String;
      45: getstatic     #9                  // Field org/apache/dubbo/common/config/configcenter/ConfigChangeType.MODIFIED:Lorg/apache/dubbo/common/config/configcenter/ConfigChangeType;
      48: invokevirtual #5                  // Method put:(Ljava/lang/Object;Ljava/lang/Object;)Ljava/lang/Object;
      51: pop
      52: return
}
