Compiled from "FileSystemDynamicConfigurationFactory.java"
public class org.apache.dubbo.common.config.configcenter.file.FileSystemDynamicConfigurationFactory extends org.apache.dubbo.common.config.configcenter.AbstractDynamicConfigurationFactory {
  public org.apache.dubbo.common.config.configcenter.file.FileSystemDynamicConfigurationFactory();
    Code:
       0: aload_0
       1: invokespecial #1                  // Method org/apache/dubbo/common/config/configcenter/AbstractDynamicConfigurationFactory."<init>":()V
       4: return

  protected org.apache.dubbo.common.config.configcenter.DynamicConfiguration createDynamicConfiguration(org.apache.dubbo.common.URL);
    Code:
       0: new           #2                  // class org/apache/dubbo/common/config/configcenter/file/FileSystemDynamicConfiguration
       3: dup
       4: aload_1
       5: invokespecial #3                  // Method org/apache/dubbo/common/config/configcenter/file/FileSystemDynamicConfiguration."<init>":(Lorg/apache/dubbo/common/URL;)V
       8: areturn
}
