Compiled from "FileSystemDynamicConfiguration.java"
public class org.apache.dubbo.common.config.configcenter.file.FileSystemDynamicConfiguration extends org.apache.dubbo.common.config.configcenter.TreePathDynamicConfiguration {
  public static final java.lang.String CONFIG_CENTER_DIR_PARAM_NAME;

  public static final java.lang.String CONFIG_CENTER_ENCODING_PARAM_NAME;

  public static final java.lang.String DEFAULT_CONFIG_CENTER_DIR_PATH;

  public static final int DEFAULT_THREAD_POOL_SIZE;

  public static final java.lang.String DEFAULT_CONFIG_CENTER_ENCODING;

  private static final java.nio.file.WatchEvent$Kind[] INTEREST_PATH_KINDS;

  private static final java.lang.String POLLING_WATCH_SERVICE_CLASS_NAME;

  private static final int THREAD_POOL_SIZE;

  private static final org.apache.dubbo.common.logger.ErrorTypeAwareLogger logger;

  private static final java.util.Map<java.lang.String, org.apache.dubbo.common.config.configcenter.ConfigChangeType> CONFIG_CHANGE_TYPES_MAP;

  private static final java.util.Optional<java.nio.file.WatchService> watchService;

  private static final boolean BASED_POOLING_WATCH_SERVICE;

  private static final java.nio.file.WatchEvent$Modifier[] MODIFIERS;

  private static final java.lang.Integer DELAY;

  private static final java.util.concurrent.ThreadPoolExecutor WATCH_EVENTS_LOOP_THREAD_POOL;

  private final java.io.File rootDirectory;

  private final java.lang.String encoding;

  private final java.util.Set<java.io.File> processingDirectories;

  private final java.util.Map<java.io.File, java.util.List<org.apache.dubbo.common.config.configcenter.ConfigurationListener>> listenersRepository;

  private org.apache.dubbo.rpc.model.ScopeModel scopeModel;

  private java.util.concurrent.atomic.AtomicBoolean hasRegisteredShutdownHook;

  public org.apache.dubbo.common.config.configcenter.file.FileSystemDynamicConfiguration();
    Code:
       0: aload_0
       1: new           #3                  // class java/io/File
       4: dup
       5: getstatic     #4                  // Field DEFAULT_CONFIG_CENTER_DIR_PATH:Ljava/lang/String;
       8: invokespecial #5                  // Method java/io/File."<init>":(Ljava/lang/String;)V
      11: invokespecial #6                  // Method "<init>":(Ljava/io/File;)V
      14: return

  public org.apache.dubbo.common.config.configcenter.file.FileSystemDynamicConfiguration(java.io.File);
    Code:
       0: aload_0
       1: aload_1
       2: ldc           #8                  // String UTF-8
       4: invokespecial #9                  // Method "<init>":(Ljava/io/File;Ljava/lang/String;)V
       7: return

  public org.apache.dubbo.common.config.configcenter.file.FileSystemDynamicConfiguration(java.io.File, java.lang.String);
    Code:
       0: aload_0
       1: aload_1
       2: aload_2
       3: ldc           #10                 // String dubbo.config-center.workers
       5: invokespecial #11                 // Method "<init>":(Ljava/io/File;Ljava/lang/String;Ljava/lang/String;)V
       8: return

  public org.apache.dubbo.common.config.configcenter.file.FileSystemDynamicConfiguration(java.io.File, java.lang.String, java.lang.String);
    Code:
       0: aload_0
       1: aload_1
       2: aload_2
       3: aload_3
       4: iconst_1
       5: invokespecial #12                 // Method "<init>":(Ljava/io/File;Ljava/lang/String;Ljava/lang/String;I)V
       8: return

  public org.apache.dubbo.common.config.configcenter.file.FileSystemDynamicConfiguration(java.io.File, java.lang.String, java.lang.String, int);
    Code:
       0: aload_0
       1: aload_1
       2: aload_2
       3: aload_3
       4: iload         4
       6: getstatic     #13                 // Field DEFAULT_THREAD_POOL_KEEP_ALIVE_TIME:J
       9: invokespecial #14                 // Method "<init>":(Ljava/io/File;Ljava/lang/String;Ljava/lang/String;IJ)V
      12: return

  public org.apache.dubbo.common.config.configcenter.file.FileSystemDynamicConfiguration(java.io.File, java.lang.String, java.lang.String, int, long);
    Code:
       0: aload_0
       1: aload_1
       2: invokevirtual #15                 // Method java/io/File.getAbsolutePath:()Ljava/lang/String;
       5: aload_3
       6: iload         4
       8: lload         5
      10: ldc           #17                 // String dubbo
      12: ldc2_w        #18                 // long -1l
      15: invokespecial #20                 // Method org/apache/dubbo/common/config/configcenter/TreePathDynamicConfiguration."<init>":(Ljava/lang/String;Ljava/lang/String;IJLjava/lang/String;J)V
      18: aload_0
      19: new           #21                 // class java/util/concurrent/atomic/AtomicBoolean
      22: dup
      23: invokespecial #22                 // Method java/util/concurrent/atomic/AtomicBoolean."<init>":()V
      26: putfield      #23                 // Field hasRegisteredShutdownHook:Ljava/util/concurrent/atomic/AtomicBoolean;
      29: aload_0
      30: aload_1
      31: putfield      #24                 // Field rootDirectory:Ljava/io/File;
      34: aload_0
      35: aload_2
      36: putfield      #25                 // Field encoding:Ljava/lang/String;
      39: aload_0
      40: aload_0
      41: invokespecial #26                 // Method initProcessingDirectories:()Ljava/util/Set;
      44: putfield      #27                 // Field processingDirectories:Ljava/util/Set;
      47: aload_0
      48: new           #28                 // class java/util/HashMap
      51: dup
      52: invokespecial #29                 // Method java/util/HashMap."<init>":()V
      55: putfield      #30                 // Field listenersRepository:Ljava/util/Map;
      58: aload_0
      59: invokespecial #31                 // Method registerDubboShutdownHook:()V
      62: return

  public org.apache.dubbo.common.config.configcenter.file.FileSystemDynamicConfiguration(java.io.File, java.lang.String, java.lang.String, int, long, org.apache.dubbo.rpc.model.ScopeModel);
    Code:
       0: aload_0
       1: aload_1
       2: invokevirtual #15                 // Method java/io/File.getAbsolutePath:()Ljava/lang/String;
       5: aload_3
       6: iload         4
       8: lload         5
      10: ldc           #17                 // String dubbo
      12: ldc2_w        #18                 // long -1l
      15: invokespecial #20                 // Method org/apache/dubbo/common/config/configcenter/TreePathDynamicConfiguration."<init>":(Ljava/lang/String;Ljava/lang/String;IJLjava/lang/String;J)V
      18: aload_0
      19: new           #21                 // class java/util/concurrent/atomic/AtomicBoolean
      22: dup
      23: invokespecial #22                 // Method java/util/concurrent/atomic/AtomicBoolean."<init>":()V
      26: putfield      #23                 // Field hasRegisteredShutdownHook:Ljava/util/concurrent/atomic/AtomicBoolean;
      29: aload_0
      30: aload_1
      31: putfield      #24                 // Field rootDirectory:Ljava/io/File;
      34: aload_0
      35: aload_2
      36: putfield      #25                 // Field encoding:Ljava/lang/String;
      39: aload_0
      40: aload_0
      41: invokespecial #26                 // Method initProcessingDirectories:()Ljava/util/Set;
      44: putfield      #27                 // Field processingDirectories:Ljava/util/Set;
      47: aload_0
      48: new           #28                 // class java/util/HashMap
      51: dup
      52: invokespecial #29                 // Method java/util/HashMap."<init>":()V
      55: putfield      #30                 // Field listenersRepository:Ljava/util/Map;
      58: aload_0
      59: aload         7
      61: putfield      #32                 // Field scopeModel:Lorg/apache/dubbo/rpc/model/ScopeModel;
      64: aload_0
      65: invokespecial #31                 // Method registerDubboShutdownHook:()V
      68: return

  public org.apache.dubbo.common.config.configcenter.file.FileSystemDynamicConfiguration(org.apache.dubbo.common.URL);
    Code:
       0: aload_0
       1: aload_1
       2: invokestatic  #33                 // Method initDirectory:(Lorg/apache/dubbo/common/URL;)Ljava/io/File;
       5: aload_1
       6: invokestatic  #34                 // Method getEncoding:(Lorg/apache/dubbo/common/URL;)Ljava/lang/String;
       9: aload_1
      10: invokestatic  #35                 // Method getThreadPoolPrefixName:(Lorg/apache/dubbo/common/URL;)Ljava/lang/String;
      13: aload_1
      14: invokestatic  #36                 // Method getThreadPoolSize:(Lorg/apache/dubbo/common/URL;)I
      17: aload_1
      18: invokestatic  #37                 // Method getThreadPoolKeepAliveTime:(Lorg/apache/dubbo/common/URL;)J
      21: aload_1
      22: invokevirtual #38                 // Method org/apache/dubbo/common/URL.getScopeModel:()Lorg/apache/dubbo/rpc/model/ScopeModel;
      25: invokespecial #39                 // Method "<init>":(Ljava/io/File;Ljava/lang/String;Ljava/lang/String;IJLorg/apache/dubbo/rpc/model/ScopeModel;)V
      28: return

  private java.util.Set<java.io.File> initProcessingDirectories();
    Code:
       0: invokestatic  #40                 // Method isBasedPoolingWatchService:()Z
       3: ifeq          16
       6: new           #41                 // class java/util/LinkedHashSet
       9: dup
      10: invokespecial #42                 // Method java/util/LinkedHashSet."<init>":()V
      13: goto          19
      16: invokestatic  #43                 // Method java/util/Collections.emptySet:()Ljava/util/Set;
      19: areturn

  public java.io.File configFile(java.lang.String, java.lang.String);
    Code:
       0: new           #3                  // class java/io/File
       3: dup
       4: aload_0
       5: aload_2
       6: aload_1
       7: invokevirtual #44                 // Method buildPathKey:(Ljava/lang/String;Ljava/lang/String;)Ljava/lang/String;
      10: invokespecial #5                  // Method java/io/File."<init>":(Ljava/lang/String;)V
      13: areturn

  private void doInListener(java.lang.String, java.util.function.BiConsumer<java.io.File, java.util.List<org.apache.dubbo.common.config.configcenter.ConfigurationListener>>);
    Code:
       0: getstatic     #45                 // Field watchService:Ljava/util/Optional;
       3: aload_0
       4: aload_1
       5: aload_2
       6: invokedynamic #46,  0             // InvokeDynamic #0:accept:(Lorg/apache/dubbo/common/config/configcenter/file/FileSystemDynamicConfiguration;Ljava/lang/String;Ljava/util/function/BiConsumer;)Ljava/util/function/Consumer;
      11: invokevirtual #47                 // Method java/util/Optional.ifPresent:(Ljava/util/function/Consumer;)V
      14: return

  private void registerDubboShutdownHook();
    Code:
       0: aload_0
       1: getfield      #23                 // Field hasRegisteredShutdownHook:Ljava/util/concurrent/atomic/AtomicBoolean;
       4: iconst_0
       5: iconst_1
       6: invokevirtual #48                 // Method java/util/concurrent/atomic/AtomicBoolean.compareAndSet:(ZZ)Z
       9: ifne          13
      12: return
      13: aload_0
      14: getfield      #32                 // Field scopeModel:Lorg/apache/dubbo/rpc/model/ScopeModel;
      17: invokestatic  #49                 // Method org/apache/dubbo/rpc/model/ScopeModelUtil.getApplicationModel:(Lorg/apache/dubbo/rpc/model/ScopeModel;)Lorg/apache/dubbo/rpc/model/ApplicationModel;
      20: invokevirtual #50                 // Method org/apache/dubbo/rpc/model/ApplicationModel.getBeanFactory:()Lorg/apache/dubbo/common/beans/factory/ScopeBeanFactory;
      23: ldc           #51                 // class org/apache/dubbo/common/lang/ShutdownHookCallbacks
      25: invokevirtual #52                 // Method org/apache/dubbo/common/beans/factory/ScopeBeanFactory.getBean:(Ljava/lang/Class;)Ljava/lang/Object;
      28: checkcast     #51                 // class org/apache/dubbo/common/lang/ShutdownHookCallbacks
      31: astore_1
      32: aload_1
      33: invokedynamic #53,  0             // InvokeDynamic #1:callback:()Lorg/apache/dubbo/common/lang/ShutdownHookCallback;
      38: invokevirtual #54                 // Method org/apache/dubbo/common/lang/ShutdownHookCallbacks.addCallback:(Lorg/apache/dubbo/common/lang/ShutdownHookCallback;)Lorg/apache/dubbo/common/lang/ShutdownHookCallbacks;
      41: pop
      42: return

  private static boolean isProcessingWatchEvents();
    Code:
       0: invokestatic  #55                 // Method getWatchEventsLoopThreadPool:()Ljava/util/concurrent/ThreadPoolExecutor;
       3: invokevirtual #56                 // Method java/util/concurrent/ThreadPoolExecutor.getActiveCount:()I
       6: ifle          13
       9: iconst_1
      10: goto          14
      13: iconst_0
      14: ireturn

  private void processWatchEvents(java.nio.file.WatchService);
    Code:
       0: invokestatic  #55                 // Method getWatchEventsLoopThreadPool:()Ljava/util/concurrent/ThreadPoolExecutor;
       3: aload_0
       4: aload_1
       5: invokedynamic #57,  0             // InvokeDynamic #2:run:(Lorg/apache/dubbo/common/config/configcenter/file/FileSystemDynamicConfiguration;Ljava/nio/file/WatchService;)Ljava/lang/Runnable;
      10: invokevirtual #58                 // Method java/util/concurrent/ThreadPoolExecutor.execute:(Ljava/lang/Runnable;)V
      13: return

  private void signalConfigDirectory(java.io.File);
    Code:
       0: invokestatic  #40                 // Method isBasedPoolingWatchService:()Z
       3: ifeq          51
       6: aload_0
       7: aload_1
       8: invokespecial #59                 // Method removeProcessingDirectory:(Ljava/io/File;)V
      11: aload_0
      12: aload_1
      13: invokespecial #60                 // Method notifyProcessingDirectory:(Ljava/io/File;)V
      16: getstatic     #61                 // Field logger:Lorg/apache/dubbo/common/logger/ErrorTypeAwareLogger;
      19: invokeinterface #62,  1           // InterfaceMethod org/apache/dubbo/common/logger/ErrorTypeAwareLogger.isDebugEnabled:()Z
      24: ifeq          51
      27: getstatic     #61                 // Field logger:Lorg/apache/dubbo/common/logger/ErrorTypeAwareLogger;
      30: ldc           #63                 // String The config rootDirectory[%s] is signalled...
      32: iconst_1
      33: anewarray     #64                 // class java/lang/Object
      36: dup
      37: iconst_0
      38: aload_1
      39: invokevirtual #65                 // Method java/io/File.getName:()Ljava/lang/String;
      42: aastore
      43: invokestatic  #66                 // Method java/lang/String.format:(Ljava/lang/String;[Ljava/lang/Object;)Ljava/lang/String;
      46: invokeinterface #67,  2           // InterfaceMethod org/apache/dubbo/common/logger/ErrorTypeAwareLogger.debug:(Ljava/lang/String;)V
      51: return

  private void removeProcessingDirectory(java.io.File);
    Code:
       0: aload_0
       1: getfield      #27                 // Field processingDirectories:Ljava/util/Set;
       4: aload_1
       5: invokeinterface #68,  2           // InterfaceMethod java/util/Set.remove:(Ljava/lang/Object;)Z
      10: pop
      11: return

  private void notifyProcessingDirectory(java.io.File);
    Code:
       0: aload_1
       1: invokevirtual #69                 // Method java/lang/Object.notifyAll:()V
       4: return

  private java.util.List<org.apache.dubbo.common.config.configcenter.ConfigurationListener> getListeners(java.io.File);
    Code:
       0: aload_0
       1: getfield      #30                 // Field listenersRepository:Ljava/util/Map;
       4: aload_1
       5: invokedynamic #70,  0             // InvokeDynamic #3:apply:()Ljava/util/function/Function;
      10: invokeinterface #71,  3           // InterfaceMethod java/util/Map.computeIfAbsent:(Ljava/lang/Object;Ljava/util/function/Function;)Ljava/lang/Object;
      15: checkcast     #72                 // class java/util/List
      18: areturn

  private void fireConfigChangeEvent(java.io.File, java.io.File, org.apache.dubbo.common.config.configcenter.ConfigChangeType);
    Code:
       0: aload_2
       1: invokevirtual #65                 // Method java/io/File.getName:()Ljava/lang/String;
       4: astore        4
       6: aload_0
       7: aload_2
       8: invokevirtual #73                 // Method getConfig:(Ljava/io/File;)Ljava/lang/String;
      11: astore        5
      13: aload_0
      14: aload_2
      15: invokespecial #74                 // Method getListeners:(Ljava/io/File;)Ljava/util/List;
      18: aload         4
      20: aload_1
      21: aload         5
      23: aload_3
      24: invokedynamic #75,  0             // InvokeDynamic #4:accept:(Ljava/lang/String;Ljava/io/File;Ljava/lang/String;Lorg/apache/dubbo/common/config/configcenter/ConfigChangeType;)Ljava/util/function/Consumer;
      29: invokeinterface #76,  2           // InterfaceMethod java/util/List.forEach:(Ljava/util/function/Consumer;)V
      34: return

  private boolean canRead(java.io.File);
    Code:
       0: aload_1
       1: invokevirtual #77                 // Method java/io/File.exists:()Z
       4: ifeq          18
       7: aload_1
       8: invokevirtual #78                 // Method java/io/File.canRead:()Z
      11: ifeq          18
      14: iconst_1
      15: goto          19
      18: iconst_0
      19: ireturn

  public java.lang.Object getInternalProperty(java.lang.String);
    Code:
       0: aconst_null
       1: areturn

  protected boolean doPublishConfig(java.lang.String, java.lang.String) throws java.lang.Exception;
    Code:
       0: aload_0
       1: aload_1
       2: aload_0
       3: aload_2
       4: invokedynamic #79,  0             // InvokeDynamic #5:apply:(Lorg/apache/dubbo/common/config/configcenter/file/FileSystemDynamicConfiguration;Ljava/lang/String;)Lorg/apache/dubbo/common/function/ThrowableFunction;
       9: invokevirtual #80                 // Method delay:(Ljava/lang/String;Lorg/apache/dubbo/common/function/ThrowableFunction;)Ljava/lang/Object;
      12: checkcast     #81                 // class java/lang/Boolean
      15: invokevirtual #82                 // Method java/lang/Boolean.booleanValue:()Z
      18: ireturn

  protected java.lang.String doGetConfig(java.lang.String) throws java.lang.Exception;
    Code:
       0: new           #3                  // class java/io/File
       3: dup
       4: aload_1
       5: invokespecial #5                  // Method java/io/File."<init>":(Ljava/lang/String;)V
       8: astore_2
       9: aload_0
      10: aload_2
      11: invokevirtual #73                 // Method getConfig:(Ljava/io/File;)Ljava/lang/String;
      14: areturn

  protected boolean doRemoveConfig(java.lang.String) throws java.lang.Exception;
    Code:
       0: aload_0
       1: aload_1
       2: aload_0
       3: invokedynamic #83,  0             // InvokeDynamic #6:apply:(Lorg/apache/dubbo/common/config/configcenter/file/FileSystemDynamicConfiguration;)Lorg/apache/dubbo/common/function/ThrowableFunction;
       8: invokevirtual #80                 // Method delay:(Ljava/lang/String;Lorg/apache/dubbo/common/function/ThrowableFunction;)Ljava/lang/Object;
      11: pop
      12: iconst_1
      13: ireturn

  protected java.util.Collection<java.lang.String> doGetConfigKeys(java.lang.String);
    Code:
       0: new           #3                  // class java/io/File
       3: dup
       4: aload_1
       5: invokespecial #5                  // Method java/io/File."<init>":(Ljava/lang/String;)V
       8: invokedynamic #84,  0             // InvokeDynamic #7:accept:()Ljava/io/FileFilter;
      13: invokevirtual #85                 // Method java/io/File.listFiles:(Ljava/io/FileFilter;)[Ljava/io/File;
      16: astore_2
      17: aload_2
      18: ifnonnull     29
      21: new           #86                 // class java/util/TreeSet
      24: dup
      25: invokespecial #87                 // Method java/util/TreeSet."<init>":()V
      28: areturn
      29: aload_2
      30: invokestatic  #88                 // InterfaceMethod java/util/stream/Stream.of:([Ljava/lang/Object;)Ljava/util/stream/Stream;
      33: invokedynamic #89,  0             // InvokeDynamic #8:apply:()Ljava/util/function/Function;
      38: invokeinterface #90,  2           // InterfaceMethod java/util/stream/Stream.map:(Ljava/util/function/Function;)Ljava/util/stream/Stream;
      43: invokestatic  #91                 // Method java/util/stream/Collectors.toList:()Ljava/util/stream/Collector;
      46: invokeinterface #92,  2           // InterfaceMethod java/util/stream/Stream.collect:(Ljava/util/stream/Collector;)Ljava/lang/Object;
      51: checkcast     #93                 // class java/util/Collection
      54: areturn

  protected void doAddListener(java.lang.String, org.apache.dubbo.common.config.configcenter.ConfigurationListener, java.lang.String, java.lang.String);
    Code:
       0: aload_0
       1: aload_1
       2: aload_2
       3: invokedynamic #94,  0             // InvokeDynamic #9:accept:(Lorg/apache/dubbo/common/config/configcenter/ConfigurationListener;)Ljava/util/function/BiConsumer;
       8: invokespecial #95                 // Method doInListener:(Ljava/lang/String;Ljava/util/function/BiConsumer;)V
      11: return

  protected void doRemoveListener(java.lang.String, org.apache.dubbo.common.config.configcenter.ConfigurationListener);
    Code:
       0: aload_0
       1: aload_1
       2: aload_2
       3: invokedynamic #96,  0             // InvokeDynamic #10:accept:(Lorg/apache/dubbo/common/config/configcenter/ConfigurationListener;)Ljava/util/function/BiConsumer;
       8: invokespecial #95                 // Method doInListener:(Ljava/lang/String;Ljava/util/function/BiConsumer;)V
      11: return

  protected <V> V delay(java.lang.String, org.apache.dubbo.common.function.ThrowableFunction<java.io.File, V>);
    Code:
       0: new           #3                  // class java/io/File
       3: dup
       4: aload_1
       5: invokespecial #5                  // Method java/io/File."<init>":(Ljava/lang/String;)V
       8: astore_3
       9: invokestatic  #40                 // Method isBasedPoolingWatchService:()Z
      12: ifeq          38
      15: aload_3
      16: invokevirtual #97                 // Method java/io/File.getParentFile:()Ljava/io/File;
      19: astore        4
      21: aload_0
      22: aload         4
      24: aload_0
      25: aload_3
      26: aload         4
      28: aload_1
      29: invokedynamic #98,  0             // InvokeDynamic #11:call:(Lorg/apache/dubbo/common/config/configcenter/file/FileSystemDynamicConfiguration;Ljava/io/File;Ljava/io/File;Ljava/lang/String;)Ljava/util/concurrent/Callable;
      34: invokespecial #99                 // Method executeMutually:(Ljava/lang/Object;Ljava/util/concurrent/Callable;)Ljava/lang/Object;
      37: pop
      38: aconst_null
      39: astore        4
      41: aload_2
      42: aload_3
      43: invokeinterface #100,  2          // InterfaceMethod org/apache/dubbo/common/function/ThrowableFunction.apply:(Ljava/lang/Object;)Ljava/lang/Object;
      48: astore        4
      50: goto          87
      53: astore        5
      55: getstatic     #61                 // Field logger:Lorg/apache/dubbo/common/logger/ErrorTypeAwareLogger;
      58: invokeinterface #102,  1          // InterfaceMethod org/apache/dubbo/common/logger/ErrorTypeAwareLogger.isErrorEnabled:()Z
      63: ifeq          87
      66: getstatic     #61                 // Field logger:Lorg/apache/dubbo/common/logger/ErrorTypeAwareLogger;
      69: ldc           #103                // String 5-37
      71: ldc           #104                // String
      73: ldc           #104                // String
      75: aload         5
      77: invokevirtual #105                // Method java/lang/Throwable.getMessage:()Ljava/lang/String;
      80: aload         5
      82: invokeinterface #106,  6          // InterfaceMethod org/apache/dubbo/common/logger/ErrorTypeAwareLogger.error:(Ljava/lang/String;Ljava/lang/String;Ljava/lang/String;Ljava/lang/String;Ljava/lang/Throwable;)V
      87: aload         4
      89: areturn
    Exception table:
       from    to  target type
          41    50    53   Class java/lang/Throwable

  private boolean hasListeners(java.io.File);
    Code:
       0: aload_0
       1: aload_1
       2: invokespecial #74                 // Method getListeners:(Ljava/io/File;)Ljava/util/List;
       5: invokeinterface #107,  1          // InterfaceMethod java/util/List.size:()I
      10: ifle          17
      13: iconst_1
      14: goto          18
      17: iconst_0
      18: ireturn

  private boolean isProcessing(java.io.File);
    Code:
       0: aload_0
       1: getfield      #27                 // Field processingDirectories:Ljava/util/Set;
       4: aload_1
       5: invokeinterface #108,  2          // InterfaceMethod java/util/Set.contains:(Ljava/lang/Object;)Z
      10: ireturn

  private void addProcessing(java.io.File);
    Code:
       0: aload_0
       1: getfield      #27                 // Field processingDirectories:Ljava/util/Set;
       4: aload_1
       5: invokeinterface #109,  2          // InterfaceMethod java/util/Set.add:(Ljava/lang/Object;)Z
      10: pop
      11: return

  public java.util.Set<java.lang.String> getConfigGroups();
    Code:
       0: aload_0
       1: invokevirtual #110                // Method getRootDirectory:()Ljava/io/File;
       4: invokevirtual #111                // Method java/io/File.listFiles:()[Ljava/io/File;
       7: invokestatic  #88                 // InterfaceMethod java/util/stream/Stream.of:([Ljava/lang/Object;)Ljava/util/stream/Stream;
      10: invokedynamic #112,  0            // InvokeDynamic #12:test:()Ljava/util/function/Predicate;
      15: invokeinterface #113,  2          // InterfaceMethod java/util/stream/Stream.filter:(Ljava/util/function/Predicate;)Ljava/util/stream/Stream;
      20: invokedynamic #89,  0             // InvokeDynamic #8:apply:()Ljava/util/function/Function;
      25: invokeinterface #90,  2           // InterfaceMethod java/util/stream/Stream.map:(Ljava/util/function/Function;)Ljava/util/stream/Stream;
      30: invokestatic  #114                // Method java/util/stream/Collectors.toSet:()Ljava/util/stream/Collector;
      33: invokeinterface #92,  2           // InterfaceMethod java/util/stream/Stream.collect:(Ljava/util/stream/Collector;)Ljava/lang/Object;
      38: checkcast     #115                // class java/util/Set
      41: areturn

  protected java.lang.String getConfig(java.io.File);
    Code:
       0: aload_1
       1: aload_0
       2: aload_1
       3: invokedynamic #116,  0            // InvokeDynamic #13:apply:(Lorg/apache/dubbo/common/config/configcenter/file/FileSystemDynamicConfiguration;Ljava/io/File;)Lorg/apache/dubbo/common/function/ThrowableFunction;
       8: invokestatic  #117                // InterfaceMethod org/apache/dubbo/common/function/ThrowableFunction.execute:(Ljava/lang/Object;Lorg/apache/dubbo/common/function/ThrowableFunction;)Ljava/lang/Object;
      11: checkcast     #118                // class java/lang/String
      14: areturn

  protected void doClose() throws java.lang.Exception;
    Code:
       0: return

  public java.io.File getRootDirectory();
    Code:
       0: aload_0
       1: getfield      #24                 // Field rootDirectory:Ljava/io/File;
       4: areturn

  public java.lang.String getEncoding();
    Code:
       0: aload_0
       1: getfield      #25                 // Field encoding:Ljava/lang/String;
       4: areturn

  protected java.lang.Integer getDelay();
    Code:
       0: getstatic     #119                // Field DELAY:Ljava/lang/Integer;
       3: areturn

  protected static boolean isBasedPoolingWatchService();
    Code:
       0: getstatic     #120                // Field BASED_POOLING_WATCH_SERVICE:Z
       3: ireturn

  protected static java.util.concurrent.ThreadPoolExecutor getWatchEventsLoopThreadPool();
    Code:
       0: getstatic     #121                // Field WATCH_EVENTS_LOOP_THREAD_POOL:Ljava/util/concurrent/ThreadPoolExecutor;
       3: areturn

  protected java.util.concurrent.ThreadPoolExecutor getWorkersThreadPool();
    Code:
       0: aload_0
       1: invokespecial #122                // Method org/apache/dubbo/common/config/configcenter/TreePathDynamicConfiguration.getWorkersThreadPool:()Ljava/util/concurrent/ThreadPoolExecutor;
       4: areturn

  private <V> V executeMutually(java.lang.Object, java.util.concurrent.Callable<V>);
    Code:
       0: aconst_null
       1: astore_3
       2: aload_1
       3: dup
       4: astore        4
       6: monitorenter
       7: aload_2
       8: invokeinterface #123,  1          // InterfaceMethod java/util/concurrent/Callable.call:()Ljava/lang/Object;
      13: astore_3
      14: goto          51
      17: astore        5
      19: getstatic     #61                 // Field logger:Lorg/apache/dubbo/common/logger/ErrorTypeAwareLogger;
      22: invokeinterface #102,  1          // InterfaceMethod org/apache/dubbo/common/logger/ErrorTypeAwareLogger.isErrorEnabled:()Z
      27: ifeq          51
      30: getstatic     #61                 // Field logger:Lorg/apache/dubbo/common/logger/ErrorTypeAwareLogger;
      33: ldc           #103                // String 5-37
      35: ldc           #104                // String
      37: ldc           #104                // String
      39: aload         5
      41: invokevirtual #125                // Method java/lang/Exception.getMessage:()Ljava/lang/String;
      44: aload         5
      46: invokeinterface #106,  6          // InterfaceMethod org/apache/dubbo/common/logger/ErrorTypeAwareLogger.error:(Ljava/lang/String;Ljava/lang/String;Ljava/lang/String;Ljava/lang/String;Ljava/lang/Throwable;)V
      51: aload         4
      53: monitorexit
      54: goto          65
      57: astore        6
      59: aload         4
      61: monitorexit
      62: aload         6
      64: athrow
      65: aload_3
      66: areturn
    Exception table:
       from    to  target type
           7    14    17   Class java/lang/Exception
           7    54    57   any
          57    62    57   any

  private static <T> T[] of(T...);
    Code:
       0: aload_0
       1: areturn

  private static java.lang.Integer initDelay(java.nio.file.WatchEvent$Modifier[]);
    Code:
       0: invokestatic  #40                 // Method isBasedPoolingWatchService:()Z
       3: ifeq          11
       6: iconst_2
       7: invokestatic  #126                // Method java/lang/Integer.valueOf:(I)Ljava/lang/Integer;
      10: areturn
      11: aconst_null
      12: areturn

  private static java.nio.file.WatchEvent$Modifier[] initWatchEventModifiers();
    Code:
       0: iconst_0
       1: anewarray     #127                // class java/nio/file/WatchEvent$Modifier
       4: invokestatic  #128                // Method of:([Ljava/lang/Object;)[Ljava/lang/Object;
       7: checkcast     #129                // class "[Ljava/nio/file/WatchEvent$Modifier;"
      10: areturn

  private static boolean detectPoolingBasedWatchService(java.util.Optional<java.nio.file.WatchService>);
    Code:
       0: aload_0
       1: invokedynamic #130,  0            // InvokeDynamic #14:apply:()Ljava/util/function/Function;
       6: invokevirtual #131                // Method java/util/Optional.map:(Ljava/util/function/Function;)Ljava/util/Optional;
       9: invokedynamic #132,  0            // InvokeDynamic #15:apply:()Ljava/util/function/Function;
      14: invokevirtual #131                // Method java/util/Optional.map:(Ljava/util/function/Function;)Ljava/util/Optional;
      17: aconst_null
      18: invokevirtual #133                // Method java/util/Optional.orElse:(Ljava/lang/Object;)Ljava/lang/Object;
      21: checkcast     #118                // class java/lang/String
      24: astore_1
      25: ldc           #134                // String sun.nio.fs.PollingWatchService
      27: aload_1
      28: invokevirtual #135                // Method java/lang/String.equals:(Ljava/lang/Object;)Z
      31: ireturn

  private static java.util.Optional<java.nio.file.WatchService> newWatchService();
    Code:
       0: aconst_null
       1: astore_0
       2: invokestatic  #136                // Method java/nio/file/FileSystems.getDefault:()Ljava/nio/file/FileSystem;
       5: astore_1
       6: aload_1
       7: invokevirtual #137                // Method java/nio/file/FileSystem.newWatchService:()Ljava/nio/file/WatchService;
      10: invokestatic  #138                // Method java/util/Optional.of:(Ljava/lang/Object;)Ljava/util/Optional;
      13: astore_0
      14: goto          52
      17: astore_2
      18: getstatic     #61                 // Field logger:Lorg/apache/dubbo/common/logger/ErrorTypeAwareLogger;
      21: invokeinterface #102,  1          // InterfaceMethod org/apache/dubbo/common/logger/ErrorTypeAwareLogger.isErrorEnabled:()Z
      26: ifeq          48
      29: getstatic     #61                 // Field logger:Lorg/apache/dubbo/common/logger/ErrorTypeAwareLogger;
      32: ldc           #103                // String 5-37
      34: ldc           #104                // String
      36: ldc           #104                // String
      38: aload_2
      39: invokevirtual #140                // Method java/io/IOException.getMessage:()Ljava/lang/String;
      42: aload_2
      43: invokeinterface #106,  6          // InterfaceMethod org/apache/dubbo/common/logger/ErrorTypeAwareLogger.error:(Ljava/lang/String;Ljava/lang/String;Ljava/lang/String;Ljava/lang/String;Ljava/lang/Throwable;)V
      48: invokestatic  #141                // Method java/util/Optional.empty:()Ljava/util/Optional;
      51: astore_0
      52: aload_0
      53: areturn
    Exception table:
       from    to  target type
           6    14    17   Class java/io/IOException

  protected static java.io.File initDirectory(org.apache.dubbo.common.URL);
    Code:
       0: aload_0
       1: ldc           #142                // String dubbo.config-center.dir
       3: aload_0
       4: ifnonnull     11
       7: aconst_null
       8: goto          15
      11: aload_0
      12: invokevirtual #143                // Method org/apache/dubbo/common/URL.getPath:()Ljava/lang/String;
      15: invokestatic  #144                // Method getParameter:(Lorg/apache/dubbo/common/URL;Ljava/lang/String;Ljava/lang/String;)Ljava/lang/String;
      18: astore_1
      19: aconst_null
      20: astore_2
      21: aload_1
      22: invokestatic  #145                // Method org/apache/dubbo/common/utils/StringUtils.isBlank:(Ljava/lang/CharSequence;)Z
      25: ifne          55
      28: new           #3                  // class java/io/File
      31: dup
      32: new           #146                // class java/lang/StringBuilder
      35: dup
      36: invokespecial #147                // Method java/lang/StringBuilder."<init>":()V
      39: ldc           #148                // String /
      41: invokevirtual #149                // Method java/lang/StringBuilder.append:(Ljava/lang/String;)Ljava/lang/StringBuilder;
      44: aload_1
      45: invokevirtual #149                // Method java/lang/StringBuilder.append:(Ljava/lang/String;)Ljava/lang/StringBuilder;
      48: invokevirtual #150                // Method java/lang/StringBuilder.toString:()Ljava/lang/String;
      51: invokespecial #5                  // Method java/io/File."<init>":(Ljava/lang/String;)V
      54: astore_2
      55: aload_1
      56: ifnull        66
      59: aload_2
      60: invokevirtual #77                 // Method java/io/File.exists:()Z
      63: ifne          77
      66: new           #3                  // class java/io/File
      69: dup
      70: getstatic     #4                  // Field DEFAULT_CONFIG_CENTER_DIR_PATH:Ljava/lang/String;
      73: invokespecial #5                  // Method java/io/File."<init>":(Ljava/lang/String;)V
      76: astore_2
      77: aload_2
      78: invokevirtual #77                 // Method java/io/File.exists:()Z
      81: ifne          115
      84: aload_2
      85: invokevirtual #151                // Method java/io/File.mkdirs:()Z
      88: ifne          115
      91: new           #152                // class java/lang/IllegalStateException
      94: dup
      95: ldc           #153                // String Dubbo config center rootDirectory[%s] can\'t be created!
      97: iconst_1
      98: anewarray     #64                 // class java/lang/Object
     101: dup
     102: iconst_0
     103: aload_2
     104: invokevirtual #15                 // Method java/io/File.getAbsolutePath:()Ljava/lang/String;
     107: aastore
     108: invokestatic  #66                 // Method java/lang/String.format:(Ljava/lang/String;[Ljava/lang/Object;)Ljava/lang/String;
     111: invokespecial #154                // Method java/lang/IllegalStateException."<init>":(Ljava/lang/String;)V
     114: athrow
     115: aload_2
     116: areturn

  protected static java.lang.String getEncoding(org.apache.dubbo.common.URL);
    Code:
       0: aload_0
       1: ldc           #155                // String dubbo.config-center.encoding
       3: ldc           #8                  // String UTF-8
       5: invokestatic  #144                // Method getParameter:(Lorg/apache/dubbo/common/URL;Ljava/lang/String;Ljava/lang/String;)Ljava/lang/String;
       8: areturn

  private static java.util.concurrent.ThreadPoolExecutor newWatchEventsLoopThreadPool();
    Code:
       0: new           #156                // class java/util/concurrent/ThreadPoolExecutor
       3: dup
       4: iconst_1
       5: iconst_1
       6: lconst_0
       7: getstatic     #157                // Field java/util/concurrent/TimeUnit.MILLISECONDS:Ljava/util/concurrent/TimeUnit;
      10: new           #158                // class java/util/concurrent/SynchronousQueue
      13: dup
      14: invokespecial #159                // Method java/util/concurrent/SynchronousQueue."<init>":()V
      17: new           #160                // class org/apache/dubbo/common/utils/NamedThreadFactory
      20: dup
      21: ldc           #161                // String dubbo-config-center-watch-events-loop
      23: iconst_1
      24: invokespecial #162                // Method org/apache/dubbo/common/utils/NamedThreadFactory."<init>":(Ljava/lang/String;Z)V
      27: invokespecial #163                // Method java/util/concurrent/ThreadPoolExecutor."<init>":(IIJLjava/util/concurrent/TimeUnit;Ljava/util/concurrent/BlockingQueue;Ljava/util/concurrent/ThreadFactory;)V
      30: areturn

  private java.lang.String lambda$getConfig$14(java.io.File, java.io.File) throws java.lang.Throwable;
    Code:
       0: aload_0
       1: aload_1
       2: invokespecial #164                // Method canRead:(Ljava/io/File;)Z
       5: ifeq          19
       8: aload_1
       9: aload_0
      10: invokevirtual #165                // Method getEncoding:()Ljava/lang/String;
      13: invokestatic  #166                // Method org/apache/commons/io/FileUtils.readFileToString:(Ljava/io/File;Ljava/lang/String;)Ljava/lang/String;
      16: goto          20
      19: aconst_null
      20: areturn

  private java.lang.Object lambda$delay$13(java.io.File, java.io.File, java.lang.String) throws java.lang.Exception;
    Code:
       0: aload_0
       1: aload_1
       2: invokespecial #167                // Method hasListeners:(Ljava/io/File;)Z
       5: ifeq          87
       8: aload_0
       9: aload_2
      10: invokespecial #168                // Method isProcessing:(Ljava/io/File;)Z
      13: ifeq          87
      16: aload_0
      17: invokevirtual #169                // Method getDelay:()Ljava/lang/Integer;
      20: astore        4
      22: aload         4
      24: ifnull        87
      27: getstatic     #170                // Field java/util/concurrent/TimeUnit.SECONDS:Ljava/util/concurrent/TimeUnit;
      30: aload         4
      32: invokevirtual #171                // Method java/lang/Integer.intValue:()I
      35: i2l
      36: invokevirtual #172                // Method java/util/concurrent/TimeUnit.toMillis:(J)J
      39: lstore        5
      41: getstatic     #61                 // Field logger:Lorg/apache/dubbo/common/logger/ErrorTypeAwareLogger;
      44: invokeinterface #62,  1           // InterfaceMethod org/apache/dubbo/common/logger/ErrorTypeAwareLogger.isDebugEnabled:()Z
      49: ifeq          81
      52: getstatic     #61                 // Field logger:Lorg/apache/dubbo/common/logger/ErrorTypeAwareLogger;
      55: ldc           #173                // String The config[path : %s] is about to delay in %d ms.
      57: iconst_2
      58: anewarray     #64                 // class java/lang/Object
      61: dup
      62: iconst_0
      63: aload_3
      64: aastore
      65: dup
      66: iconst_1
      67: lload         5
      69: invokestatic  #174                // Method java/lang/Long.valueOf:(J)Ljava/lang/Long;
      72: aastore
      73: invokestatic  #66                 // Method java/lang/String.format:(Ljava/lang/String;[Ljava/lang/Object;)Ljava/lang/String;
      76: invokeinterface #67,  2           // InterfaceMethod org/apache/dubbo/common/logger/ErrorTypeAwareLogger.debug:(Ljava/lang/String;)V
      81: aload_2
      82: lload         5
      84: invokevirtual #175                // Method java/lang/Object.wait:(J)V
      87: aload_0
      88: aload_2
      89: invokespecial #176                // Method addProcessing:(Ljava/io/File;)V
      92: aconst_null
      93: areturn

  private static void lambda$doRemoveListener$12(org.apache.dubbo.common.config.configcenter.ConfigurationListener, java.io.File, java.util.List);
    Code:
       0: aload_2
       1: aload_0
       2: invokeinterface #177,  2          // InterfaceMethod java/util/List.remove:(Ljava/lang/Object;)Z
       7: pop
       8: return

  private static void lambda$doAddListener$11(org.apache.dubbo.common.config.configcenter.ConfigurationListener, java.io.File, java.util.List);
    Code:
       0: aload_2
       1: invokeinterface #178,  1          // InterfaceMethod java/util/List.isEmpty:()Z
       6: ifeq          18
       9: aload_1
      10: invokedynamic #179,  0            // InvokeDynamic #16:accept:()Lorg/apache/dubbo/common/function/ThrowableConsumer;
      15: invokestatic  #180                // InterfaceMethod org/apache/dubbo/common/function/ThrowableConsumer.execute:(Ljava/lang/Object;Lorg/apache/dubbo/common/function/ThrowableConsumer;)V
      18: aload_2
      19: aload_0
      20: invokeinterface #181,  2          // InterfaceMethod java/util/List.add:(Ljava/lang/Object;)Z
      25: pop
      26: return

  private static void lambda$null$10(java.io.File) throws java.lang.Throwable;
    Code:
       0: aload_0
       1: invokestatic  #182                // Method org/apache/commons/io/FileUtils.forceMkdirParent:(Ljava/io/File;)V
       4: aload_0
       5: invokevirtual #97                 // Method java/io/File.getParentFile:()Ljava/io/File;
       8: astore_1
       9: aload_1
      10: ifnull        38
      13: aload_1
      14: invokevirtual #183                // Method java/io/File.toPath:()Ljava/nio/file/Path;
      17: getstatic     #45                 // Field watchService:Ljava/util/Optional;
      20: invokevirtual #184                // Method java/util/Optional.get:()Ljava/lang/Object;
      23: checkcast     #185                // class java/nio/file/WatchService
      26: getstatic     #186                // Field INTEREST_PATH_KINDS:[Ljava/nio/file/WatchEvent$Kind;
      29: getstatic     #187                // Field MODIFIERS:[Ljava/nio/file/WatchEvent$Modifier;
      32: invokeinterface #188,  4          // InterfaceMethod java/nio/file/Path.register:(Ljava/nio/file/WatchService;[Ljava/nio/file/WatchEvent$Kind;[Ljava/nio/file/WatchEvent$Modifier;)Ljava/nio/file/WatchKey;
      37: pop
      38: return

  private java.lang.String lambda$doRemoveConfig$9(java.io.File) throws java.lang.Throwable;
    Code:
       0: aload_0
       1: aload_1
       2: invokevirtual #73                 // Method getConfig:(Ljava/io/File;)Ljava/lang/String;
       5: astore_2
       6: aload_1
       7: invokestatic  #189                // Method org/apache/commons/io/FileUtils.deleteQuietly:(Ljava/io/File;)Z
      10: pop
      11: aload_2
      12: areturn

  private java.lang.Boolean lambda$doPublishConfig$8(java.lang.String, java.io.File) throws java.lang.Throwable;
    Code:
       0: aload_2
       1: aload_1
       2: aload_0
       3: invokevirtual #165                // Method getEncoding:()Ljava/lang/String;
       6: invokestatic  #190                // Method org/apache/commons/io/FileUtils.write:(Ljava/io/File;Ljava/lang/CharSequence;Ljava/lang/String;)V
       9: iconst_1
      10: invokestatic  #191                // Method java/lang/Boolean.valueOf:(Z)Ljava/lang/Boolean;
      13: areturn

  private static void lambda$fireConfigChangeEvent$7(java.lang.String, java.io.File, java.lang.String, org.apache.dubbo.common.config.configcenter.ConfigChangeType, org.apache.dubbo.common.config.configcenter.ConfigurationListener);
    Code:
       0: aload         4
       2: new           #192                // class org/apache/dubbo/common/config/configcenter/ConfigChangedEvent
       5: dup
       6: aload_0
       7: aload_1
       8: invokevirtual #65                 // Method java/io/File.getName:()Ljava/lang/String;
      11: aload_2
      12: aload_3
      13: invokespecial #193                // Method org/apache/dubbo/common/config/configcenter/ConfigChangedEvent."<init>":(Ljava/lang/String;Ljava/lang/String;Ljava/lang/String;Lorg/apache/dubbo/common/config/configcenter/ConfigChangeType;)V
      16: invokeinterface #194,  2          // InterfaceMethod org/apache/dubbo/common/config/configcenter/ConfigurationListener.process:(Lorg/apache/dubbo/common/config/configcenter/ConfigChangedEvent;)V
      21: goto          58
      24: astore        5
      26: getstatic     #61                 // Field logger:Lorg/apache/dubbo/common/logger/ErrorTypeAwareLogger;
      29: invokeinterface #102,  1          // InterfaceMethod org/apache/dubbo/common/logger/ErrorTypeAwareLogger.isErrorEnabled:()Z
      34: ifeq          58
      37: getstatic     #61                 // Field logger:Lorg/apache/dubbo/common/logger/ErrorTypeAwareLogger;
      40: ldc           #103                // String 5-37
      42: ldc           #104                // String
      44: ldc           #104                // String
      46: aload         5
      48: invokevirtual #105                // Method java/lang/Throwable.getMessage:()Ljava/lang/String;
      51: aload         5
      53: invokeinterface #106,  6          // InterfaceMethod org/apache/dubbo/common/logger/ErrorTypeAwareLogger.error:(Ljava/lang/String;Ljava/lang/String;Ljava/lang/String;Ljava/lang/String;Ljava/lang/Throwable;)V
      58: return
    Exception table:
       from    to  target type
           0    21    24   Class java/lang/Throwable

  private static java.util.List lambda$getListeners$6(java.io.File);
    Code:
       0: new           #195                // class java/util/LinkedList
       3: dup
       4: invokespecial #196                // Method java/util/LinkedList."<init>":()V
       7: areturn

  private void lambda$processWatchEvents$5(java.nio.file.WatchService);
    Code:
       0: aconst_null
       1: astore_2
       2: aload_1
       3: invokeinterface #197,  1          // InterfaceMethod java/nio/file/WatchService.take:()Ljava/nio/file/WatchKey;
       8: astore_2
       9: aload_2
      10: invokeinterface #198,  1          // InterfaceMethod java/nio/file/WatchKey.isValid:()Z
      15: ifne          32
      18: aload_2
      19: ifnull        0
      22: aload_2
      23: invokeinterface #199,  1          // InterfaceMethod java/nio/file/WatchKey.reset:()Z
      28: pop
      29: goto          0
      32: aload_2
      33: invokeinterface #200,  1          // InterfaceMethod java/nio/file/WatchKey.pollEvents:()Ljava/util/List;
      38: invokeinterface #201,  1          // InterfaceMethod java/util/List.iterator:()Ljava/util/Iterator;
      43: astore_3
      44: aload_3
      45: invokeinterface #202,  1          // InterfaceMethod java/util/Iterator.hasNext:()Z
      50: ifeq          166
      53: aload_3
      54: invokeinterface #203,  1          // InterfaceMethod java/util/Iterator.next:()Ljava/lang/Object;
      59: checkcast     #204                // class java/nio/file/WatchEvent
      62: astore        4
      64: aload         4
      66: invokeinterface #205,  1          // InterfaceMethod java/nio/file/WatchEvent.kind:()Ljava/nio/file/WatchEvent$Kind;
      71: astore        5
      73: getstatic     #206                // Field CONFIG_CHANGE_TYPES_MAP:Ljava/util/Map;
      76: aload         5
      78: invokeinterface #207,  1          // InterfaceMethod java/nio/file/WatchEvent$Kind.name:()Ljava/lang/String;
      83: invokeinterface #208,  2          // InterfaceMethod java/util/Map.get:(Ljava/lang/Object;)Ljava/lang/Object;
      88: checkcast     #209                // class org/apache/dubbo/common/config/configcenter/ConfigChangeType
      91: astore        6
      93: aload         6
      95: ifnonnull     101
      98: goto          44
     101: aload_2
     102: invokeinterface #210,  1          // InterfaceMethod java/nio/file/WatchKey.watchable:()Ljava/nio/file/Watchable;
     107: checkcast     #211                // class java/nio/file/Path
     110: astore        7
     112: aload         4
     114: invokeinterface #212,  1          // InterfaceMethod java/nio/file/WatchEvent.context:()Ljava/lang/Object;
     119: checkcast     #211                // class java/nio/file/Path
     122: astore        8
     124: aload         7
     126: aload         8
     128: invokeinterface #213,  2          // InterfaceMethod java/nio/file/Path.resolve:(Ljava/nio/file/Path;)Ljava/nio/file/Path;
     133: astore        9
     135: aload         7
     137: invokeinterface #214,  1          // InterfaceMethod java/nio/file/Path.toFile:()Ljava/io/File;
     142: astore        10
     144: aload_0
     145: aload         10
     147: aload_0
     148: aload         10
     150: aload         9
     152: aload         6
     154: invokedynamic #215,  0            // InvokeDynamic #17:call:(Lorg/apache/dubbo/common/config/configcenter/file/FileSystemDynamicConfiguration;Ljava/io/File;Ljava/nio/file/Path;Lorg/apache/dubbo/common/config/configcenter/ConfigChangeType;)Ljava/util/concurrent/Callable;
     159: invokespecial #99                 // Method executeMutually:(Ljava/lang/Object;Ljava/util/concurrent/Callable;)Ljava/lang/Object;
     162: pop
     163: goto          44
     166: aload_2
     167: ifnull        209
     170: aload_2
     171: invokeinterface #199,  1          // InterfaceMethod java/nio/file/WatchKey.reset:()Z
     176: pop
     177: goto          209
     180: astore_3
     181: aload_2
     182: ifnull        192
     185: aload_2
     186: invokeinterface #199,  1          // InterfaceMethod java/nio/file/WatchKey.reset:()Z
     191: pop
     192: return
     193: astore        11
     195: aload_2
     196: ifnull        206
     199: aload_2
     200: invokeinterface #199,  1          // InterfaceMethod java/nio/file/WatchKey.reset:()Z
     205: pop
     206: aload         11
     208: athrow
     209: goto          0
    Exception table:
       from    to  target type
           2    18   180   Class java/lang/Exception
          32   166   180   Class java/lang/Exception
           2    18   193   any
          32   166   193   any
         193   195   193   any

  private java.lang.Object lambda$null$4(java.io.File, java.nio.file.Path, org.apache.dubbo.common.config.configcenter.ConfigChangeType) throws java.lang.Exception;
    Code:
       0: aload_0
       1: aload_1
       2: aload_2
       3: invokeinterface #214,  1          // InterfaceMethod java/nio/file/Path.toFile:()Ljava/io/File;
       8: aload_3
       9: invokespecial #216                // Method fireConfigChangeEvent:(Ljava/io/File;Ljava/io/File;Lorg/apache/dubbo/common/config/configcenter/ConfigChangeType;)V
      12: aload_0
      13: aload_1
      14: invokespecial #217                // Method signalConfigDirectory:(Ljava/io/File;)V
      17: aconst_null
      18: areturn

  private static void lambda$registerDubboShutdownHook$3() throws java.lang.Throwable;
    Code:
       0: getstatic     #45                 // Field watchService:Ljava/util/Optional;
       3: invokedynamic #218,  0            // InvokeDynamic #18:accept:()Ljava/util/function/Consumer;
       8: invokevirtual #47                 // Method java/util/Optional.ifPresent:(Ljava/util/function/Consumer;)V
      11: invokestatic  #55                 // Method getWatchEventsLoopThreadPool:()Ljava/util/concurrent/ThreadPoolExecutor;
      14: invokevirtual #219                // Method java/util/concurrent/ThreadPoolExecutor.shutdown:()V
      17: return

  private static void lambda$null$2(java.nio.file.WatchService);
    Code:
       0: aload_0
       1: invokeinterface #220,  1          // InterfaceMethod java/nio/file/WatchService.close:()V
       6: goto          19
       9: astore_1
      10: new           #221                // class java/lang/RuntimeException
      13: dup
      14: aload_1
      15: invokespecial #222                // Method java/lang/RuntimeException."<init>":(Ljava/lang/Throwable;)V
      18: athrow
      19: return
    Exception table:
       from    to  target type
           0     6     9   Class java/io/IOException

  private void lambda$doInListener$1(java.lang.String, java.util.function.BiConsumer, java.nio.file.WatchService);
    Code:
       0: new           #3                  // class java/io/File
       3: dup
       4: aload_1
       5: invokespecial #5                  // Method java/io/File."<init>":(Ljava/lang/String;)V
       8: astore        4
      10: aload_0
      11: aload         4
      13: invokevirtual #97                 // Method java/io/File.getParentFile:()Ljava/io/File;
      16: aload_0
      17: aload_3
      18: aload         4
      20: aload_2
      21: invokedynamic #223,  0            // InvokeDynamic #19:call:(Lorg/apache/dubbo/common/config/configcenter/file/FileSystemDynamicConfiguration;Ljava/nio/file/WatchService;Ljava/io/File;Ljava/util/function/BiConsumer;)Ljava/util/concurrent/Callable;
      26: invokespecial #99                 // Method executeMutually:(Ljava/lang/Object;Ljava/util/concurrent/Callable;)Ljava/lang/Object;
      29: pop
      30: return

  private java.lang.Object lambda$null$0(java.nio.file.WatchService, java.io.File, java.util.function.BiConsumer) throws java.lang.Exception;
    Code:
       0: invokestatic  #224                // Method isProcessingWatchEvents:()Z
       3: ifne          11
       6: aload_0
       7: aload_1
       8: invokespecial #225                // Method processWatchEvents:(Ljava/nio/file/WatchService;)V
      11: aload_0
      12: aload_2
      13: invokespecial #74                 // Method getListeners:(Ljava/io/File;)Ljava/util/List;
      16: astore        4
      18: aload_3
      19: aload_2
      20: aload         4
      22: invokeinterface #226,  3          // InterfaceMethod java/util/function/BiConsumer.accept:(Ljava/lang/Object;Ljava/lang/Object;)V
      27: aconst_null
      28: areturn

  static {};
    Code:
       0: new           #146                // class java/lang/StringBuilder
       3: dup
       4: invokespecial #147                // Method java/lang/StringBuilder."<init>":()V
       7: ldc           #227                // String user.home
       9: invokestatic  #228                // Method java/lang/System.getProperty:(Ljava/lang/String;)Ljava/lang/String;
      12: invokevirtual #149                // Method java/lang/StringBuilder.append:(Ljava/lang/String;)Ljava/lang/StringBuilder;
      15: getstatic     #229                // Field java/io/File.separator:Ljava/lang/String;
      18: invokevirtual #149                // Method java/lang/StringBuilder.append:(Ljava/lang/String;)Ljava/lang/StringBuilder;
      21: ldc           #230                // String .dubbo
      23: invokevirtual #149                // Method java/lang/StringBuilder.append:(Ljava/lang/String;)Ljava/lang/StringBuilder;
      26: getstatic     #229                // Field java/io/File.separator:Ljava/lang/String;
      29: invokevirtual #149                // Method java/lang/StringBuilder.append:(Ljava/lang/String;)Ljava/lang/StringBuilder;
      32: ldc           #231                // String config-center
      34: invokevirtual #149                // Method java/lang/StringBuilder.append:(Ljava/lang/String;)Ljava/lang/StringBuilder;
      37: invokevirtual #150                // Method java/lang/StringBuilder.toString:()Ljava/lang/String;
      40: putstatic     #4                  // Field DEFAULT_CONFIG_CENTER_DIR_PATH:Ljava/lang/String;
      43: iconst_3
      44: anewarray     #232                // class java/nio/file/WatchEvent$Kind
      47: dup
      48: iconst_0
      49: getstatic     #233                // Field java/nio/file/StandardWatchEventKinds.ENTRY_CREATE:Ljava/nio/file/WatchEvent$Kind;
      52: aastore
      53: dup
      54: iconst_1
      55: getstatic     #234                // Field java/nio/file/StandardWatchEventKinds.ENTRY_DELETE:Ljava/nio/file/WatchEvent$Kind;
      58: aastore
      59: dup
      60: iconst_2
      61: getstatic     #235                // Field java/nio/file/StandardWatchEventKinds.ENTRY_MODIFY:Ljava/nio/file/WatchEvent$Kind;
      64: aastore
      65: invokestatic  #128                // Method of:([Ljava/lang/Object;)[Ljava/lang/Object;
      68: checkcast     #236                // class "[Ljava/nio/file/WatchEvent$Kind;"
      71: putstatic     #186                // Field INTEREST_PATH_KINDS:[Ljava/nio/file/WatchEvent$Kind;
      74: ldc           #7                  // class org/apache/dubbo/common/config/configcenter/file/FileSystemDynamicConfiguration
      76: invokestatic  #237                // Method org/apache/dubbo/common/logger/LoggerFactory.getErrorTypeAwareLogger:(Ljava/lang/Class;)Lorg/apache/dubbo/common/logger/ErrorTypeAwareLogger;
      79: putstatic     #61                 // Field logger:Lorg/apache/dubbo/common/logger/ErrorTypeAwareLogger;
      82: new           #238                // class org/apache/dubbo/common/config/configcenter/file/FileSystemDynamicConfiguration$1
      85: dup
      86: invokespecial #239                // Method org/apache/dubbo/common/config/configcenter/file/FileSystemDynamicConfiguration$1."<init>":()V
      89: invokestatic  #240                // Method java/util/Collections.unmodifiableMap:(Ljava/util/Map;)Ljava/util/Map;
      92: putstatic     #206                // Field CONFIG_CHANGE_TYPES_MAP:Ljava/util/Map;
      95: invokestatic  #241                // Method newWatchService:()Ljava/util/Optional;
      98: putstatic     #45                 // Field watchService:Ljava/util/Optional;
     101: getstatic     #45                 // Field watchService:Ljava/util/Optional;
     104: invokestatic  #242                // Method detectPoolingBasedWatchService:(Ljava/util/Optional;)Z
     107: putstatic     #120                // Field BASED_POOLING_WATCH_SERVICE:Z
     110: invokestatic  #243                // Method initWatchEventModifiers:()[Ljava/nio/file/WatchEvent$Modifier;
     113: putstatic     #187                // Field MODIFIERS:[Ljava/nio/file/WatchEvent$Modifier;
     116: getstatic     #187                // Field MODIFIERS:[Ljava/nio/file/WatchEvent$Modifier;
     119: invokestatic  #244                // Method initDelay:([Ljava/nio/file/WatchEvent$Modifier;)Ljava/lang/Integer;
     122: putstatic     #119                // Field DELAY:Ljava/lang/Integer;
     125: invokestatic  #245                // Method newWatchEventsLoopThreadPool:()Ljava/util/concurrent/ThreadPoolExecutor;
     128: putstatic     #121                // Field WATCH_EVENTS_LOOP_THREAD_POOL:Ljava/util/concurrent/ThreadPoolExecutor;
     131: return
}
