Compiled from "AbstractConfiguratorListener.java"
public abstract class org.apache.dubbo.registry.integration.AbstractConfiguratorListener implements org.apache.dubbo.common.config.configcenter.ConfigurationListener {
  private static final org.apache.dubbo.common.logger.ErrorTypeAwareLogger logger;

  protected java.util.List<org.apache.dubbo.rpc.cluster.Configurator> configurators;

  protected org.apache.dubbo.rpc.cluster.governance.GovernanceRuleRepository ruleRepository;

  protected java.util.Set<java.lang.String> securityKey;

  protected org.apache.dubbo.rpc.model.ModuleModel moduleModel;

  public org.apache.dubbo.registry.integration.AbstractConfiguratorListener(org.apache.dubbo.rpc.model.ModuleModel);
    Code:
       0: aload_0
       1: invokespecial #4                  // Method java/lang/Object."<init>":()V
       4: aload_0
       5: invokestatic  #5                  // Method java/util/Collections.emptyList:()Ljava/util/List;
       8: putfield      #6                  // Field configurators:Ljava/util/List;
      11: aload_0
      12: new           #7                  // class java/util/HashSet
      15: dup
      16: invokespecial #8                  // Method java/util/HashSet."<init>":()V
      19: putfield      #9                  // Field securityKey:Ljava/util/Set;
      22: aload_0
      23: aload_1
      24: putfield      #10                 // Field moduleModel:Lorg/apache/dubbo/rpc/model/ModuleModel;
      27: aload_0
      28: aload_1
      29: ldc           #11                 // class org/apache/dubbo/rpc/cluster/governance/GovernanceRuleRepository
      31: invokevirtual #12                 // Method org/apache/dubbo/rpc/model/ModuleModel.getExtensionLoader:(Ljava/lang/Class;)Lorg/apache/dubbo/common/extension/ExtensionLoader;
      34: invokevirtual #13                 // Method org/apache/dubbo/common/extension/ExtensionLoader.getDefaultExtension:()Ljava/lang/Object;
      37: checkcast     #11                 // class org/apache/dubbo/rpc/cluster/governance/GovernanceRuleRepository
      40: putfield      #14                 // Field ruleRepository:Lorg/apache/dubbo/rpc/cluster/governance/GovernanceRuleRepository;
      43: aload_0
      44: invokespecial #15                 // Method initSecurityKey:()V
      47: return

  private void initSecurityKey();
    Code:
       0: aload_0
       1: getfield      #9                  // Field securityKey:Ljava/util/Set;
       4: ldc           #16                 // String accesslog.fixed.path
       6: invokeinterface #17,  2           // InterfaceMethod java/util/Set.add:(Ljava/lang/Object;)Z
      11: pop
      12: aload_0
      13: getfield      #9                  // Field securityKey:Ljava/util/Set;
      16: ldc           #18                 // String router
      18: invokeinterface #17,  2           // InterfaceMethod java/util/Set.add:(Ljava/lang/Object;)Z
      23: pop
      24: aload_0
      25: getfield      #9                  // Field securityKey:Ljava/util/Set;
      28: ldc           #19                 // String rule
      30: invokeinterface #17,  2           // InterfaceMethod java/util/Set.add:(Ljava/lang/Object;)Z
      35: pop
      36: aload_0
      37: getfield      #9                  // Field securityKey:Ljava/util/Set;
      40: ldc           #20                 // String runtime
      42: invokeinterface #17,  2           // InterfaceMethod java/util/Set.add:(Ljava/lang/Object;)Z
      47: pop
      48: aload_0
      49: getfield      #9                  // Field securityKey:Ljava/util/Set;
      52: ldc           #21                 // String type
      54: invokeinterface #17,  2           // InterfaceMethod java/util/Set.add:(Ljava/lang/Object;)Z
      59: pop
      60: return

  protected final void initWith(java.lang.String);
    Code:
       0: aload_0
       1: getfield      #14                 // Field ruleRepository:Lorg/apache/dubbo/rpc/cluster/governance/GovernanceRuleRepository;
       4: aload_1
       5: aload_0
       6: invokeinterface #22,  3           // InterfaceMethod org/apache/dubbo/rpc/cluster/governance/GovernanceRuleRepository.addListener:(Ljava/lang/String;Lorg/apache/dubbo/common/config/configcenter/ConfigurationListener;)V
      11: aload_0
      12: getfield      #14                 // Field ruleRepository:Lorg/apache/dubbo/rpc/cluster/governance/GovernanceRuleRepository;
      15: aload_1
      16: ldc           #24                 // String dubbo
      18: invokeinterface #25,  3           // InterfaceMethod org/apache/dubbo/rpc/cluster/governance/GovernanceRuleRepository.getRule:(Ljava/lang/String;Ljava/lang/String;)Ljava/lang/String;
      23: astore_2
      24: aload_2
      25: invokestatic  #26                 // Method org/apache/dubbo/common/utils/StringUtils.isEmpty:(Ljava/lang/String;)Z
      28: ifne          37
      31: aload_0
      32: aload_2
      33: invokespecial #27                 // Method genConfiguratorsFromRawRule:(Ljava/lang/String;)Z
      36: pop
      37: return

  protected final void stopListen(java.lang.String);
    Code:
       0: aload_0
       1: getfield      #14                 // Field ruleRepository:Lorg/apache/dubbo/rpc/cluster/governance/GovernanceRuleRepository;
       4: aload_1
       5: aload_0
       6: invokeinterface #28,  3           // InterfaceMethod org/apache/dubbo/rpc/cluster/governance/GovernanceRuleRepository.removeListener:(Ljava/lang/String;Lorg/apache/dubbo/common/config/configcenter/ConfigurationListener;)V
      11: return

  public void process(org.apache.dubbo.common.config.configcenter.ConfigChangedEvent);
    Code:
       0: getstatic     #29                 // Field logger:Lorg/apache/dubbo/common/logger/ErrorTypeAwareLogger;
       3: invokeinterface #30,  1           // InterfaceMethod org/apache/dubbo/common/logger/ErrorTypeAwareLogger.isInfoEnabled:()Z
       8: ifeq          53
      11: getstatic     #29                 // Field logger:Lorg/apache/dubbo/common/logger/ErrorTypeAwareLogger;
      14: new           #31                 // class java/lang/StringBuilder
      17: dup
      18: invokespecial #32                 // Method java/lang/StringBuilder."<init>":()V
      21: ldc           #33                 // String Notification of overriding rule, change type is:
      23: invokevirtual #34                 // Method java/lang/StringBuilder.append:(Ljava/lang/String;)Ljava/lang/StringBuilder;
      26: aload_1
      27: invokevirtual #35                 // Method org/apache/dubbo/common/config/configcenter/ConfigChangedEvent.getChangeType:()Lorg/apache/dubbo/common/config/configcenter/ConfigChangeType;
      30: invokevirtual #36                 // Method java/lang/StringBuilder.append:(Ljava/lang/Object;)Ljava/lang/StringBuilder;
      33: ldc           #37                 // String , raw config content is:\n
      35: invokevirtual #34                 // Method java/lang/StringBuilder.append:(Ljava/lang/String;)Ljava/lang/StringBuilder;
      38: aload_1
      39: invokevirtual #38                 // Method org/apache/dubbo/common/config/configcenter/ConfigChangedEvent.getContent:()Ljava/lang/String;
      42: invokevirtual #34                 // Method java/lang/StringBuilder.append:(Ljava/lang/String;)Ljava/lang/StringBuilder;
      45: invokevirtual #39                 // Method java/lang/StringBuilder.toString:()Ljava/lang/String;
      48: invokeinterface #40,  2           // InterfaceMethod org/apache/dubbo/common/logger/ErrorTypeAwareLogger.info:(Ljava/lang/String;)V
      53: aload_1
      54: invokevirtual #35                 // Method org/apache/dubbo/common/config/configcenter/ConfigChangedEvent.getChangeType:()Lorg/apache/dubbo/common/config/configcenter/ConfigChangeType;
      57: getstatic     #41                 // Field org/apache/dubbo/common/config/configcenter/ConfigChangeType.DELETED:Lorg/apache/dubbo/common/config/configcenter/ConfigChangeType;
      60: invokevirtual #42                 // Method org/apache/dubbo/common/config/configcenter/ConfigChangeType.equals:(Ljava/lang/Object;)Z
      63: ifeq          78
      66: aload_0
      67: getfield      #6                  // Field configurators:Ljava/util/List;
      70: invokeinterface #43,  1           // InterfaceMethod java/util/List.clear:()V
      75: goto          90
      78: aload_0
      79: aload_1
      80: invokevirtual #38                 // Method org/apache/dubbo/common/config/configcenter/ConfigChangedEvent.getContent:()Ljava/lang/String;
      83: invokespecial #27                 // Method genConfiguratorsFromRawRule:(Ljava/lang/String;)Z
      86: ifne          90
      89: return
      90: aload_0
      91: invokevirtual #44                 // Method notifyOverrides:()V
      94: return

  private boolean genConfiguratorsFromRawRule(java.lang.String);
    Code:
       0: aload_1
       1: invokestatic  #45                 // Method org/apache/dubbo/rpc/cluster/configurator/parser/ConfigParser.parseConfigurators:(Ljava/lang/String;)Ljava/util/List;
       4: astore_2
       5: goto          56
       8: astore_3
       9: getstatic     #29                 // Field logger:Lorg/apache/dubbo/common/logger/ErrorTypeAwareLogger;
      12: ldc           #47                 // String 1-14
      14: ldc           #48                 // String
      16: ldc           #48                 // String
      18: new           #31                 // class java/lang/StringBuilder
      21: dup
      22: invokespecial #32                 // Method java/lang/StringBuilder."<init>":()V
      25: ldc           #49                 // String Failed to parse raw dynamic config and it will not take effect, the raw config is:
      27: invokevirtual #34                 // Method java/lang/StringBuilder.append:(Ljava/lang/String;)Ljava/lang/StringBuilder;
      30: aload_1
      31: invokevirtual #34                 // Method java/lang/StringBuilder.append:(Ljava/lang/String;)Ljava/lang/StringBuilder;
      34: ldc           #50                 // String , cause:
      36: invokevirtual #34                 // Method java/lang/StringBuilder.append:(Ljava/lang/String;)Ljava/lang/StringBuilder;
      39: aload_3
      40: invokevirtual #51                 // Method java/lang/Exception.getMessage:()Ljava/lang/String;
      43: invokevirtual #34                 // Method java/lang/StringBuilder.append:(Ljava/lang/String;)Ljava/lang/StringBuilder;
      46: invokevirtual #39                 // Method java/lang/StringBuilder.toString:()Ljava/lang/String;
      49: invokeinterface #52,  5           // InterfaceMethod org/apache/dubbo/common/logger/ErrorTypeAwareLogger.warn:(Ljava/lang/String;Ljava/lang/String;Ljava/lang/String;Ljava/lang/String;)V
      54: iconst_0
      55: ireturn
      56: aload_2
      57: invokeinterface #53,  1           // InterfaceMethod java/util/List.stream:()Ljava/util/stream/Stream;
      62: aload_0
      63: invokedynamic #54,  0             // InvokeDynamic #0:apply:(Lorg/apache/dubbo/registry/integration/AbstractConfiguratorListener;)Ljava/util/function/Function;
      68: invokeinterface #55,  2           // InterfaceMethod java/util/stream/Stream.map:(Ljava/util/function/Function;)Ljava/util/stream/Stream;
      73: aload_0
      74: invokedynamic #56,  0             // InvokeDynamic #1:apply:(Lorg/apache/dubbo/registry/integration/AbstractConfiguratorListener;)Ljava/util/function/Function;
      79: invokeinterface #55,  2           // InterfaceMethod java/util/stream/Stream.map:(Ljava/util/function/Function;)Ljava/util/stream/Stream;
      84: invokestatic  #57                 // Method java/util/stream/Collectors.toList:()Ljava/util/stream/Collector;
      87: invokeinterface #58,  2           // InterfaceMethod java/util/stream/Stream.collect:(Ljava/util/stream/Collector;)Ljava/lang/Object;
      92: checkcast     #59                 // class java/util/List
      95: astore_3
      96: aload_0
      97: aload_3
      98: invokestatic  #60                 // InterfaceMethod org/apache/dubbo/rpc/cluster/Configurator.toConfigurators:(Ljava/util/List;)Ljava/util/Optional;
     101: aload_0
     102: getfield      #6                  // Field configurators:Ljava/util/List;
     105: invokevirtual #61                 // Method java/util/Optional.orElse:(Ljava/lang/Object;)Ljava/lang/Object;
     108: checkcast     #59                 // class java/util/List
     111: putfield      #6                  // Field configurators:Ljava/util/List;
     114: iconst_1
     115: ireturn
    Exception table:
       from    to  target type
           0     5     8   Class java/lang/Exception

  protected abstract void notifyOverrides();

  public java.util.List<org.apache.dubbo.rpc.cluster.Configurator> getConfigurators();
    Code:
       0: aload_0
       1: getfield      #6                  // Field configurators:Ljava/util/List;
       4: areturn

  public void setConfigurators(java.util.List<org.apache.dubbo.rpc.cluster.Configurator>);
    Code:
       0: aload_0
       1: aload_1
       2: putfield      #6                  // Field configurators:Ljava/util/List;
       5: return

  private org.apache.dubbo.common.URL lambda$genConfiguratorsFromRawRule$1(org.apache.dubbo.common.URL);
    Code:
       0: aload_1
       1: aload_0
       2: getfield      #10                 // Field moduleModel:Lorg/apache/dubbo/rpc/model/ModuleModel;
       5: invokevirtual #62                 // Method org/apache/dubbo/common/URL.setScopeModel:(Lorg/apache/dubbo/rpc/model/ScopeModel;)Lorg/apache/dubbo/common/URL;
       8: areturn

  private org.apache.dubbo.common.URL lambda$genConfiguratorsFromRawRule$0(org.apache.dubbo.common.URL);
    Code:
       0: aload_1
       1: aload_0
       2: getfield      #9                  // Field securityKey:Ljava/util/Set;
       5: invokevirtual #63                 // Method org/apache/dubbo/common/URL.removeParameters:(Ljava/util/Collection;)Lorg/apache/dubbo/common/URL;
       8: areturn

  static {};
    Code:
       0: ldc           #64                 // class org/apache/dubbo/registry/integration/AbstractConfiguratorListener
       2: invokestatic  #65                 // Method org/apache/dubbo/common/logger/LoggerFactory.getErrorTypeAwareLogger:(Ljava/lang/Class;)Lorg/apache/dubbo/common/logger/ErrorTypeAwareLogger;
       5: putstatic     #29                 // Field logger:Lorg/apache/dubbo/common/logger/ErrorTypeAwareLogger;
       8: return
}
