Compiled from "InterfaceCompatibleRegistryProtocol.java"
public class org.apache.dubbo.registry.integration.InterfaceCompatibleRegistryProtocol extends org.apache.dubbo.registry.integration.RegistryProtocol {
  public org.apache.dubbo.registry.integration.InterfaceCompatibleRegistryProtocol();
    Code:
       0: aload_0
       1: invokespecial #3                  // Method org/apache/dubbo/registry/integration/RegistryProtocol."<init>":()V
       4: return

  protected org.apache.dubbo.common.URL getRegistryUrl(org.apache.dubbo.rpc.Invoker<?>);
    Code:
       0: aload_1
       1: invokeinterface #4,  1            // InterfaceMethod org/apache/dubbo/rpc/Invoker.getUrl:()Lorg/apache/dubbo/common/URL;
       6: astore_2
       7: ldc           #5                  // String registry
       9: aload_2
      10: invokevirtual #6                  // Method org/apache/dubbo/common/URL.getProtocol:()Ljava/lang/String;
      13: invokevirtual #7                  // Method java/lang/String.equals:(Ljava/lang/Object;)Z
      16: ifeq          39
      19: aload_2
      20: ldc           #5                  // String registry
      22: ldc           #8                  // String dubbo
      24: invokevirtual #9                  // Method org/apache/dubbo/common/URL.getParameter:(Ljava/lang/String;Ljava/lang/String;)Ljava/lang/String;
      27: astore_3
      28: aload_2
      29: aload_3
      30: invokevirtual #10                 // Method org/apache/dubbo/common/URL.setProtocol:(Ljava/lang/String;)Lorg/apache/dubbo/common/URL;
      33: ldc           #5                  // String registry
      35: invokevirtual #11                 // Method org/apache/dubbo/common/URL.removeParameter:(Ljava/lang/String;)Lorg/apache/dubbo/common/URL;
      38: astore_2
      39: aload_2
      40: areturn

  protected org.apache.dubbo.common.URL getRegistryUrl(org.apache.dubbo.common.URL);
    Code:
       0: aload_1
       1: invokestatic  #12                 // Method org/apache/dubbo/common/URLBuilder.from:(Lorg/apache/dubbo/common/URL;)Lorg/apache/dubbo/common/URLBuilder;
       4: aload_1
       5: ldc           #5                  // String registry
       7: ldc           #8                  // String dubbo
       9: invokevirtual #9                  // Method org/apache/dubbo/common/URL.getParameter:(Ljava/lang/String;Ljava/lang/String;)Ljava/lang/String;
      12: invokevirtual #13                 // Method org/apache/dubbo/common/URLBuilder.setProtocol:(Ljava/lang/String;)Lorg/apache/dubbo/common/URLBuilder;
      15: ldc           #5                  // String registry
      17: invokevirtual #14                 // Method org/apache/dubbo/common/URLBuilder.removeParameter:(Ljava/lang/String;)Lorg/apache/dubbo/common/URLBuilder;
      20: invokevirtual #15                 // Method org/apache/dubbo/common/URLBuilder.build:()Lorg/apache/dubbo/common/url/component/ServiceConfigURL;
      23: areturn

  public <T> org.apache.dubbo.rpc.cluster.ClusterInvoker<T> getInvoker(org.apache.dubbo.rpc.cluster.Cluster, org.apache.dubbo.registry.Registry, java.lang.Class<T>, org.apache.dubbo.common.URL);
    Code:
       0: new           #16                 // class org/apache/dubbo/registry/integration/RegistryDirectory
       3: dup
       4: aload_3
       5: aload         4
       7: invokespecial #17                 // Method org/apache/dubbo/registry/integration/RegistryDirectory."<init>":(Ljava/lang/Class;Lorg/apache/dubbo/common/URL;)V
      10: astore        5
      12: aload_0
      13: aload         5
      15: aload_1
      16: aload_2
      17: aload_3
      18: invokevirtual #18                 // Method doCreateInvoker:(Lorg/apache/dubbo/registry/integration/DynamicDirectory;Lorg/apache/dubbo/rpc/cluster/Cluster;Lorg/apache/dubbo/registry/Registry;Ljava/lang/Class;)Lorg/apache/dubbo/rpc/cluster/ClusterInvoker;
      21: areturn

  public <T> org.apache.dubbo.rpc.cluster.ClusterInvoker<T> getServiceDiscoveryInvoker(org.apache.dubbo.rpc.cluster.Cluster, org.apache.dubbo.registry.Registry, java.lang.Class<T>, org.apache.dubbo.common.URL);
    Code:
       0: aload_0
       1: aload_0
       2: aload         4
       4: invokespecial #19                 // Method org/apache/dubbo/registry/integration/RegistryProtocol.getRegistryUrl:(Lorg/apache/dubbo/common/URL;)Lorg/apache/dubbo/common/URL;
       7: invokevirtual #20                 // Method getRegistry:(Lorg/apache/dubbo/common/URL;)Lorg/apache/dubbo/registry/Registry;
      10: astore_2
      11: new           #21                 // class org/apache/dubbo/registry/client/ServiceDiscoveryRegistryDirectory
      14: dup
      15: aload_3
      16: aload         4
      18: invokespecial #22                 // Method org/apache/dubbo/registry/client/ServiceDiscoveryRegistryDirectory."<init>":(Ljava/lang/Class;Lorg/apache/dubbo/common/URL;)V
      21: astore        5
      23: aload_0
      24: aload         5
      26: aload_1
      27: aload_2
      28: aload_3
      29: invokevirtual #18                 // Method doCreateInvoker:(Lorg/apache/dubbo/registry/integration/DynamicDirectory;Lorg/apache/dubbo/rpc/cluster/Cluster;Lorg/apache/dubbo/registry/Registry;Ljava/lang/Class;)Lorg/apache/dubbo/rpc/cluster/ClusterInvoker;
      32: areturn

  protected <T> org.apache.dubbo.rpc.cluster.ClusterInvoker<T> getMigrationInvoker(org.apache.dubbo.registry.integration.RegistryProtocol, org.apache.dubbo.rpc.cluster.Cluster, org.apache.dubbo.registry.Registry, java.lang.Class<T>, org.apache.dubbo.common.URL, org.apache.dubbo.common.URL);
    Code:
       0: new           #23                 // class org/apache/dubbo/registry/client/migration/MigrationInvoker
       3: dup
       4: aload_1
       5: aload_2
       6: aload_3
       7: aload         4
       9: aload         5
      11: aload         6
      13: invokespecial #24                 // Method org/apache/dubbo/registry/client/migration/MigrationInvoker."<init>":(Lorg/apache/dubbo/registry/integration/RegistryProtocol;Lorg/apache/dubbo/rpc/cluster/Cluster;Lorg/apache/dubbo/registry/Registry;Ljava/lang/Class;Lorg/apache/dubbo/common/URL;Lorg/apache/dubbo/common/URL;)V
      16: areturn
}
