Compiled from "RegistryProtocol.java"
public class org.apache.dubbo.registry.integration.RegistryProtocol$InvokerDelegate<T> extends org.apache.dubbo.rpc.protocol.InvokerWrapper<T> {
  public org.apache.dubbo.registry.integration.RegistryProtocol$InvokerDelegate(org.apache.dubbo.rpc.Invoker<T>, org.apache.dubbo.common.URL);
    Code:
       0: aload_0
       1: aload_1
       2: aload_2
       3: invokespecial #1                  // Method org/apache/dubbo/rpc/protocol/InvokerWrapper."<init>":(Lorg/apache/dubbo/rpc/Invoker;Lorg/apache/dubbo/common/URL;)V
       6: return

  public org.apache.dubbo.rpc.Invoker<T> getInvoker();
    Code:
       0: aload_0
       1: getfield      #2                  // Field invoker:Lorg/apache/dubbo/rpc/Invoker;
       4: instanceof    #3                  // class org/apache/dubbo/registry/integration/RegistryProtocol$InvokerDelegate
       7: ifeq          21
      10: aload_0
      11: getfield      #2                  // Field invoker:Lorg/apache/dubbo/rpc/Invoker;
      14: checkcast     #3                  // class org/apache/dubbo/registry/integration/RegistryProtocol$InvokerDelegate
      17: invokevirtual #4                  // Method getInvoker:()Lorg/apache/dubbo/rpc/Invoker;
      20: areturn
      21: aload_0
      22: getfield      #2                  // Field invoker:Lorg/apache/dubbo/rpc/Invoker;
      25: areturn
}
