Compiled from "RegistryDirectory.java"
public class org.apache.dubbo.registry.integration.RegistryDirectory<T> extends org.apache.dubbo.registry.integration.DynamicDirectory<T> {
  private static final org.apache.dubbo.common.logger.ErrorTypeAwareLogger logger;

  private final org.apache.dubbo.registry.integration.RegistryDirectory$ConsumerConfigurationListener consumerConfigurationListener;

  private org.apache.dubbo.registry.integration.RegistryDirectory$ReferenceConfigurationListener referenceConfigurationListener;

  protected volatile java.util.Map<org.apache.dubbo.common.URL, org.apache.dubbo.rpc.Invoker<T>> urlInvokerMap;

  protected volatile java.util.Set<org.apache.dubbo.common.URL> cachedInvokerUrls;

  private final org.apache.dubbo.rpc.model.ModuleModel moduleModel;

  public org.apache.dubbo.registry.integration.RegistryDirectory(java.lang.Class<T>, org.apache.dubbo.common.URL);
    Code:
       0: aload_0
       1: aload_1
       2: aload_2
       3: invokespecial #7                  // Method org/apache/dubbo/registry/integration/DynamicDirectory."<init>":(Ljava/lang/Class;Lorg/apache/dubbo/common/URL;)V
       6: aload_0
       7: aload_2
       8: invokevirtual #8                  // Method org/apache/dubbo/common/URL.getScopeModel:()Lorg/apache/dubbo/rpc/model/ScopeModel;
      11: invokestatic  #9                  // Method org/apache/dubbo/rpc/model/ScopeModelUtil.getModuleModel:(Lorg/apache/dubbo/rpc/model/ScopeModel;)Lorg/apache/dubbo/rpc/model/ModuleModel;
      14: putfield      #10                 // Field moduleModel:Lorg/apache/dubbo/rpc/model/ModuleModel;
      17: aload_0
      18: aload_0
      19: aload_0
      20: getfield      #10                 // Field moduleModel:Lorg/apache/dubbo/rpc/model/ModuleModel;
      23: invokespecial #11                 // Method getConsumerConfigurationListener:(Lorg/apache/dubbo/rpc/model/ModuleModel;)Lorg/apache/dubbo/registry/integration/RegistryDirectory$ConsumerConfigurationListener;
      26: putfield      #12                 // Field consumerConfigurationListener:Lorg/apache/dubbo/registry/integration/RegistryDirectory$ConsumerConfigurationListener;
      29: return

  public void subscribe(org.apache.dubbo.common.URL);
    Code:
       0: aload_1
       1: invokevirtual #13                 // Method org/apache/dubbo/common/URL.getApplicationModel:()Lorg/apache/dubbo/rpc/model/ApplicationModel;
       4: astore_2
       5: aload_2
       6: invokestatic  #14                 // Method org/apache/dubbo/metrics/registry/event/RegistryEvent.toSubscribeEvent:(Lorg/apache/dubbo/rpc/model/ApplicationModel;)Lorg/apache/dubbo/metrics/registry/event/RegistryEvent;
       9: aload_0
      10: aload_1
      11: invokedynamic #15,  0             // InvokeDynamic #0:get:(Lorg/apache/dubbo/registry/integration/RegistryDirectory;Lorg/apache/dubbo/common/URL;)Ljava/util/function/Supplier;
      16: invokestatic  #16                 // Method org/apache/dubbo/metrics/event/MetricsEventBus.post:(Lorg/apache/dubbo/metrics/event/MetricsEvent;Ljava/util/function/Supplier;)Ljava/lang/Object;
      19: pop
      20: aload_0
      21: getfield      #10                 // Field moduleModel:Lorg/apache/dubbo/rpc/model/ModuleModel;
      24: invokevirtual #17                 // Method org/apache/dubbo/rpc/model/ModuleModel.getModelEnvironment:()Lorg/apache/dubbo/common/config/ModuleEnvironment;
      27: invokevirtual #18                 // Method org/apache/dubbo/common/config/ModuleEnvironment.getConfiguration:()Lorg/apache/dubbo/common/config/CompositeConfiguration;
      30: ldc           #19                 // class java/lang/Boolean
      32: ldc           #20                 // String enable-configuration-listen
      34: iconst_1
      35: invokestatic  #21                 // Method java/lang/Boolean.valueOf:(Z)Ljava/lang/Boolean;
      38: invokevirtual #22                 // Method org/apache/dubbo/common/config/CompositeConfiguration.convert:(Ljava/lang/Class;Ljava/lang/String;Ljava/lang/Object;)Ljava/lang/Object;
      41: checkcast     #19                 // class java/lang/Boolean
      44: invokevirtual #23                 // Method java/lang/Boolean.booleanValue:()Z
      47: ifeq          75
      50: aload_0
      51: getfield      #12                 // Field consumerConfigurationListener:Lorg/apache/dubbo/registry/integration/RegistryDirectory$ConsumerConfigurationListener;
      54: aload_0
      55: invokevirtual #24                 // Method org/apache/dubbo/registry/integration/RegistryDirectory$ConsumerConfigurationListener.addNotifyListener:(Lorg/apache/dubbo/registry/integration/RegistryDirectory;)V
      58: aload_0
      59: new           #25                 // class org/apache/dubbo/registry/integration/RegistryDirectory$ReferenceConfigurationListener
      62: dup
      63: aload_0
      64: getfield      #10                 // Field moduleModel:Lorg/apache/dubbo/rpc/model/ModuleModel;
      67: aload_0
      68: aload_1
      69: invokespecial #26                 // Method org/apache/dubbo/registry/integration/RegistryDirectory$ReferenceConfigurationListener."<init>":(Lorg/apache/dubbo/rpc/model/ModuleModel;Lorg/apache/dubbo/registry/integration/RegistryDirectory;Lorg/apache/dubbo/common/URL;)V
      72: putfield      #27                 // Field referenceConfigurationListener:Lorg/apache/dubbo/registry/integration/RegistryDirectory$ReferenceConfigurationListener;
      75: return

  private org.apache.dubbo.registry.integration.RegistryDirectory$ConsumerConfigurationListener getConsumerConfigurationListener(org.apache.dubbo.rpc.model.ModuleModel);
    Code:
       0: aload_1
       1: invokevirtual #28                 // Method org/apache/dubbo/rpc/model/ModuleModel.getBeanFactory:()Lorg/apache/dubbo/common/beans/factory/ScopeBeanFactory;
       4: ldc           #29                 // class org/apache/dubbo/registry/integration/RegistryDirectory$ConsumerConfigurationListener
       6: aload_1
       7: invokedynamic #30,  0             // InvokeDynamic #1:apply:(Lorg/apache/dubbo/rpc/model/ModuleModel;)Ljava/util/function/Function;
      12: invokevirtual #31                 // Method org/apache/dubbo/common/beans/factory/ScopeBeanFactory.getOrRegisterBean:(Ljava/lang/Class;Ljava/util/function/Function;)Ljava/lang/Object;
      15: checkcast     #29                 // class org/apache/dubbo/registry/integration/RegistryDirectory$ConsumerConfigurationListener
      18: areturn

  public void unSubscribe(org.apache.dubbo.common.URL);
    Code:
       0: aload_0
       1: aload_1
       2: invokespecial #32                 // Method org/apache/dubbo/registry/integration/DynamicDirectory.unSubscribe:(Lorg/apache/dubbo/common/URL;)V
       5: aload_0
       6: getfield      #10                 // Field moduleModel:Lorg/apache/dubbo/rpc/model/ModuleModel;
       9: invokevirtual #17                 // Method org/apache/dubbo/rpc/model/ModuleModel.getModelEnvironment:()Lorg/apache/dubbo/common/config/ModuleEnvironment;
      12: invokevirtual #18                 // Method org/apache/dubbo/common/config/ModuleEnvironment.getConfiguration:()Lorg/apache/dubbo/common/config/CompositeConfiguration;
      15: ldc           #19                 // class java/lang/Boolean
      17: ldc           #20                 // String enable-configuration-listen
      19: iconst_1
      20: invokestatic  #21                 // Method java/lang/Boolean.valueOf:(Z)Ljava/lang/Boolean;
      23: invokevirtual #22                 // Method org/apache/dubbo/common/config/CompositeConfiguration.convert:(Ljava/lang/Class;Ljava/lang/String;Ljava/lang/Object;)Ljava/lang/Object;
      26: checkcast     #19                 // class java/lang/Boolean
      29: invokevirtual #23                 // Method java/lang/Boolean.booleanValue:()Z
      32: ifeq          57
      35: aload_0
      36: getfield      #12                 // Field consumerConfigurationListener:Lorg/apache/dubbo/registry/integration/RegistryDirectory$ConsumerConfigurationListener;
      39: aload_0
      40: invokevirtual #33                 // Method org/apache/dubbo/registry/integration/RegistryDirectory$ConsumerConfigurationListener.removeNotifyListener:(Lorg/apache/dubbo/registry/integration/RegistryDirectory;)V
      43: aload_0
      44: getfield      #27                 // Field referenceConfigurationListener:Lorg/apache/dubbo/registry/integration/RegistryDirectory$ReferenceConfigurationListener;
      47: ifnull        57
      50: aload_0
      51: getfield      #27                 // Field referenceConfigurationListener:Lorg/apache/dubbo/registry/integration/RegistryDirectory$ReferenceConfigurationListener;
      54: invokevirtual #34                 // Method org/apache/dubbo/registry/integration/RegistryDirectory$ReferenceConfigurationListener.stop:()V
      57: return

  public void destroy();
    Code:
       0: aload_0
       1: invokespecial #35                 // Method org/apache/dubbo/registry/integration/DynamicDirectory.destroy:()V
       4: aload_0
       5: getfield      #10                 // Field moduleModel:Lorg/apache/dubbo/rpc/model/ModuleModel;
       8: invokevirtual #17                 // Method org/apache/dubbo/rpc/model/ModuleModel.getModelEnvironment:()Lorg/apache/dubbo/common/config/ModuleEnvironment;
      11: invokevirtual #18                 // Method org/apache/dubbo/common/config/ModuleEnvironment.getConfiguration:()Lorg/apache/dubbo/common/config/CompositeConfiguration;
      14: ldc           #19                 // class java/lang/Boolean
      16: ldc           #20                 // String enable-configuration-listen
      18: iconst_1
      19: invokestatic  #21                 // Method java/lang/Boolean.valueOf:(Z)Ljava/lang/Boolean;
      22: invokevirtual #22                 // Method org/apache/dubbo/common/config/CompositeConfiguration.convert:(Ljava/lang/Class;Ljava/lang/String;Ljava/lang/Object;)Ljava/lang/Object;
      25: checkcast     #19                 // class java/lang/Boolean
      28: invokevirtual #23                 // Method java/lang/Boolean.booleanValue:()Z
      31: ifeq          56
      34: aload_0
      35: getfield      #12                 // Field consumerConfigurationListener:Lorg/apache/dubbo/registry/integration/RegistryDirectory$ConsumerConfigurationListener;
      38: aload_0
      39: invokevirtual #33                 // Method org/apache/dubbo/registry/integration/RegistryDirectory$ConsumerConfigurationListener.removeNotifyListener:(Lorg/apache/dubbo/registry/integration/RegistryDirectory;)V
      42: aload_0
      43: getfield      #27                 // Field referenceConfigurationListener:Lorg/apache/dubbo/registry/integration/RegistryDirectory$ReferenceConfigurationListener;
      46: ifnull        56
      49: aload_0
      50: getfield      #27                 // Field referenceConfigurationListener:Lorg/apache/dubbo/registry/integration/RegistryDirectory$ReferenceConfigurationListener;
      53: invokevirtual #34                 // Method org/apache/dubbo/registry/integration/RegistryDirectory$ReferenceConfigurationListener.stop:()V
      56: return

  public synchronized void notify(java.util.List<org.apache.dubbo.common.URL>);
    Code:
       0: aload_0
       1: invokevirtual #36                 // Method isDestroyed:()Z
       4: ifeq          8
       7: return
       8: aload_1
       9: invokeinterface #37,  1           // InterfaceMethod java/util/List.stream:()Ljava/util/stream/Stream;
      14: invokedynamic #38,  0             // InvokeDynamic #2:test:()Ljava/util/function/Predicate;
      19: invokeinterface #39,  2           // InterfaceMethod java/util/stream/Stream.filter:(Ljava/util/function/Predicate;)Ljava/util/stream/Stream;
      24: aload_0
      25: invokedynamic #40,  0             // InvokeDynamic #3:test:(Lorg/apache/dubbo/registry/integration/RegistryDirectory;)Ljava/util/function/Predicate;
      30: invokeinterface #39,  2           // InterfaceMethod java/util/stream/Stream.filter:(Ljava/util/function/Predicate;)Ljava/util/stream/Stream;
      35: aload_0
      36: invokedynamic #41,  0             // InvokeDynamic #4:test:(Lorg/apache/dubbo/registry/integration/RegistryDirectory;)Ljava/util/function/Predicate;
      41: invokeinterface #39,  2           // InterfaceMethod java/util/stream/Stream.filter:(Ljava/util/function/Predicate;)Ljava/util/stream/Stream;
      46: aload_0
      47: invokedynamic #42,  0             // InvokeDynamic #5:apply:(Lorg/apache/dubbo/registry/integration/RegistryDirectory;)Ljava/util/function/Function;
      52: invokestatic  #43                 // Method java/util/stream/Collectors.groupingBy:(Ljava/util/function/Function;)Ljava/util/stream/Collector;
      55: invokeinterface #44,  2           // InterfaceMethod java/util/stream/Stream.collect:(Ljava/util/stream/Collector;)Ljava/lang/Object;
      60: checkcast     #45                 // class java/util/Map
      63: astore_2
      64: aload_0
      65: getfield      #10                 // Field moduleModel:Lorg/apache/dubbo/rpc/model/ModuleModel;
      68: invokevirtual #17                 // Method org/apache/dubbo/rpc/model/ModuleModel.getModelEnvironment:()Lorg/apache/dubbo/common/config/ModuleEnvironment;
      71: invokevirtual #18                 // Method org/apache/dubbo/common/config/ModuleEnvironment.getConfiguration:()Lorg/apache/dubbo/common/config/CompositeConfiguration;
      74: ldc           #19                 // class java/lang/Boolean
      76: ldc           #46                 // String enable-26x-configuration-listen
      78: iconst_1
      79: invokestatic  #21                 // Method java/lang/Boolean.valueOf:(Z)Ljava/lang/Boolean;
      82: invokevirtual #22                 // Method org/apache/dubbo/common/config/CompositeConfiguration.convert:(Ljava/lang/Class;Ljava/lang/String;Ljava/lang/Object;)Ljava/lang/Object;
      85: checkcast     #19                 // class java/lang/Boolean
      88: invokevirtual #23                 // Method java/lang/Boolean.booleanValue:()Z
      91: ifeq          158
      94: aload_2
      95: ldc           #47                 // String configurators
      97: invokestatic  #48                 // Method java/util/Collections.emptyList:()Ljava/util/List;
     100: invokeinterface #49,  3           // InterfaceMethod java/util/Map.getOrDefault:(Ljava/lang/Object;Ljava/lang/Object;)Ljava/lang/Object;
     105: checkcast     #50                 // class java/util/List
     108: astore_3
     109: aload_0
     110: aload_3
     111: invokestatic  #51                 // InterfaceMethod org/apache/dubbo/rpc/cluster/Configurator.toConfigurators:(Ljava/util/List;)Ljava/util/Optional;
     114: aload_0
     115: getfield      #52                 // Field configurators:Ljava/util/List;
     118: invokevirtual #53                 // Method java/util/Optional.orElse:(Ljava/lang/Object;)Ljava/lang/Object;
     121: checkcast     #50                 // class java/util/List
     124: putfield      #52                 // Field configurators:Ljava/util/List;
     127: aload_2
     128: ldc           #54                 // String routers
     130: invokestatic  #48                 // Method java/util/Collections.emptyList:()Ljava/util/List;
     133: invokeinterface #49,  3           // InterfaceMethod java/util/Map.getOrDefault:(Ljava/lang/Object;Ljava/lang/Object;)Ljava/lang/Object;
     138: checkcast     #50                 // class java/util/List
     141: astore        4
     143: aload_0
     144: aload         4
     146: invokespecial #55                 // Method toRouters:(Ljava/util/List;)Ljava/util/Optional;
     149: aload_0
     150: invokedynamic #56,  0             // InvokeDynamic #6:accept:(Lorg/apache/dubbo/registry/integration/RegistryDirectory;)Ljava/util/function/Consumer;
     155: invokevirtual #57                 // Method java/util/Optional.ifPresent:(Ljava/util/function/Consumer;)V
     158: aload_2
     159: ldc           #58                 // String providers
     161: invokestatic  #48                 // Method java/util/Collections.emptyList:()Ljava/util/List;
     164: invokeinterface #49,  3           // InterfaceMethod java/util/Map.getOrDefault:(Ljava/lang/Object;Ljava/lang/Object;)Ljava/lang/Object;
     169: checkcast     #50                 // class java/util/List
     172: astore_3
     173: aload_0
     174: invokevirtual #59                 // Method getUrl:()Lorg/apache/dubbo/common/URL;
     177: invokevirtual #60                 // Method org/apache/dubbo/common/URL.getOrDefaultModuleModel:()Lorg/apache/dubbo/rpc/model/ModuleModel;
     180: ldc           #61                 // class org/apache/dubbo/registry/AddressListener
     182: invokevirtual #62                 // Method org/apache/dubbo/rpc/model/ModuleModel.getExtensionLoader:(Ljava/lang/Class;)Lorg/apache/dubbo/common/extension/ExtensionLoader;
     185: astore        4
     187: aload         4
     189: aload_0
     190: invokevirtual #59                 // Method getUrl:()Lorg/apache/dubbo/common/URL;
     193: aconst_null
     194: checkcast     #63                 // class "[Ljava/lang/String;"
     197: invokevirtual #64                 // Method org/apache/dubbo/common/extension/ExtensionLoader.getActivateExtension:(Lorg/apache/dubbo/common/URL;[Ljava/lang/String;)Ljava/util/List;
     200: astore        5
     202: aload         5
     204: ifnull        265
     207: aload         5
     209: invokeinterface #65,  1           // InterfaceMethod java/util/List.isEmpty:()Z
     214: ifne          265
     217: aload         5
     219: invokeinterface #66,  1           // InterfaceMethod java/util/List.iterator:()Ljava/util/Iterator;
     224: astore        6
     226: aload         6
     228: invokeinterface #67,  1           // InterfaceMethod java/util/Iterator.hasNext:()Z
     233: ifeq          265
     236: aload         6
     238: invokeinterface #68,  1           // InterfaceMethod java/util/Iterator.next:()Ljava/lang/Object;
     243: checkcast     #61                 // class org/apache/dubbo/registry/AddressListener
     246: astore        7
     248: aload         7
     250: aload_3
     251: aload_0
     252: invokevirtual #69                 // Method getConsumerUrl:()Lorg/apache/dubbo/common/URL;
     255: aload_0
     256: invokeinterface #70,  4           // InterfaceMethod org/apache/dubbo/registry/AddressListener.notify:(Ljava/util/List;Lorg/apache/dubbo/common/URL;Lorg/apache/dubbo/rpc/cluster/Directory;)Ljava/util/List;
     261: astore_3
     262: goto          226
     265: aload_0
     266: aload_3
     267: invokevirtual #71                 // Method refreshOverrideAndInvoker:(Ljava/util/List;)V
     270: return

  public boolean isServiceDiscovery();
    Code:
       0: iconst_0
       1: ireturn

  private java.lang.String judgeCategory(org.apache.dubbo.common.URL);
    Code:
       0: aload_1
       1: invokestatic  #72                 // Method org/apache/dubbo/common/utils/UrlUtils.isConfigurator:(Lorg/apache/dubbo/common/URL;)Z
       4: ifeq          10
       7: ldc           #47                 // String configurators
       9: areturn
      10: aload_1
      11: invokestatic  #73                 // Method org/apache/dubbo/common/utils/UrlUtils.isRoute:(Lorg/apache/dubbo/common/URL;)Z
      14: ifeq          20
      17: ldc           #54                 // String routers
      19: areturn
      20: aload_1
      21: invokestatic  #74                 // Method org/apache/dubbo/common/utils/UrlUtils.isProvider:(Lorg/apache/dubbo/common/URL;)Z
      24: ifeq          30
      27: ldc           #58                 // String providers
      29: areturn
      30: ldc           #75                 // String
      32: areturn

  protected synchronized void refreshOverrideAndInvoker(java.util.List<org.apache.dubbo.common.URL>);
    Code:
       0: aload_0
       1: aload_0
       2: aload_0
       3: invokevirtual #76                 // Method getOriginalConsumerUrl:()Lorg/apache/dubbo/common/URL;
       6: invokevirtual #77                 // Method overrideWithConfigurator:(Lorg/apache/dubbo/common/URL;)Lorg/apache/dubbo/common/URL;
       9: putfield      #78                 // Field directoryUrl:Lorg/apache/dubbo/common/URL;
      12: aload_0
      13: aload_1
      14: invokespecial #79                 // Method refreshInvoker:(Ljava/util/List;)V
      17: return

  private void refreshInvoker(java.util.List<org.apache.dubbo.common.URL>);
    Code:
       0: aload_1
       1: ldc           #80                 // String invokerUrls should not be null
       3: invokestatic  #81                 // Method org/apache/dubbo/common/utils/Assert.notNull:(Ljava/lang/Object;Ljava/lang/String;)V
       6: aload_1
       7: invokeinterface #82,  1           // InterfaceMethod java/util/List.size:()I
      12: iconst_1
      13: if_icmpne     67
      16: aload_1
      17: iconst_0
      18: invokeinterface #83,  2           // InterfaceMethod java/util/List.get:(I)Ljava/lang/Object;
      23: ifnull        67
      26: ldc           #84                 // String empty
      28: aload_1
      29: iconst_0
      30: invokeinterface #83,  2           // InterfaceMethod java/util/List.get:(I)Ljava/lang/Object;
      35: checkcast     #85                 // class org/apache/dubbo/common/URL
      38: invokevirtual #86                 // Method org/apache/dubbo/common/URL.getProtocol:()Ljava/lang/String;
      41: invokevirtual #87                 // Method java/lang/String.equals:(Ljava/lang/Object;)Z
      44: ifeq          67
      47: aload_0
      48: invokestatic  #88                 // Method org/apache/dubbo/rpc/cluster/router/state/BitList.emptyList:()Lorg/apache/dubbo/rpc/cluster/router/state/BitList;
      51: aload_0
      52: invokedynamic #89,  0             // InvokeDynamic #7:run:(Lorg/apache/dubbo/registry/integration/RegistryDirectory;)Ljava/lang/Runnable;
      57: invokevirtual #90                 // Method refreshRouter:(Lorg/apache/dubbo/rpc/cluster/router/state/BitList;Ljava/lang/Runnable;)V
      60: aload_0
      61: invokevirtual #91                 // Method destroyAllInvokers:()V
      64: goto          433
      67: aload_0
      68: iconst_0
      69: putfield      #92                 // Field forbidden:Z
      72: aload_1
      73: invokestatic  #48                 // Method java/util/Collections.emptyList:()Ljava/util/List;
      76: if_acmpne     87
      79: new           #93                 // class java/util/ArrayList
      82: dup
      83: invokespecial #94                 // Method java/util/ArrayList."<init>":()V
      86: astore_1
      87: aload_0
      88: getfield      #95                 // Field cachedInvokerUrls:Ljava/util/Set;
      91: astore_2
      92: aload_1
      93: invokeinterface #65,  1           // InterfaceMethod java/util/List.isEmpty:()Z
      98: ifeq          160
     101: aload_2
     102: invokestatic  #96                 // Method org/apache/dubbo/common/utils/CollectionUtils.isNotEmpty:(Ljava/util/Collection;)Z
     105: ifeq          181
     108: getstatic     #97                 // Field logger:Lorg/apache/dubbo/common/logger/ErrorTypeAwareLogger;
     111: ldc           #98                 // String 1-4
     113: ldc           #99                 // String configuration
     115: ldc           #75                 // String
     117: new           #100                // class java/lang/StringBuilder
     120: dup
     121: invokespecial #101                // Method java/lang/StringBuilder."<init>":()V
     124: ldc           #102                // String Service
     126: invokevirtual #103                // Method java/lang/StringBuilder.append:(Ljava/lang/String;)Ljava/lang/StringBuilder;
     129: aload_0
     130: getfield      #104                // Field serviceKey:Ljava/lang/String;
     133: invokevirtual #103                // Method java/lang/StringBuilder.append:(Ljava/lang/String;)Ljava/lang/StringBuilder;
     136: ldc           #105                // String  received empty address list with no EMPTY protocol set, trigger empty protection.
     138: invokevirtual #103                // Method java/lang/StringBuilder.append:(Ljava/lang/String;)Ljava/lang/StringBuilder;
     141: invokevirtual #106                // Method java/lang/StringBuilder.toString:()Ljava/lang/String;
     144: invokeinterface #107,  5          // InterfaceMethod org/apache/dubbo/common/logger/ErrorTypeAwareLogger.warn:(Ljava/lang/String;Ljava/lang/String;Ljava/lang/String;Ljava/lang/String;)V
     149: aload_1
     150: aload_2
     151: invokeinterface #108,  2          // InterfaceMethod java/util/List.addAll:(Ljava/util/Collection;)Z
     156: pop
     157: goto          181
     160: new           #109                // class java/util/HashSet
     163: dup
     164: invokespecial #110                // Method java/util/HashSet."<init>":()V
     167: astore_2
     168: aload_2
     169: aload_1
     170: invokeinterface #111,  2          // InterfaceMethod java/util/Set.addAll:(Ljava/util/Collection;)Z
     175: pop
     176: aload_0
     177: aload_2
     178: putfield      #95                 // Field cachedInvokerUrls:Ljava/util/Set;
     181: aload_1
     182: invokeinterface #65,  1           // InterfaceMethod java/util/List.isEmpty:()Z
     187: ifeq          191
     190: return
     191: aload_0
     192: getfield      #112                // Field urlInvokerMap:Ljava/util/Map;
     195: astore_3
     196: aconst_null
     197: astore        4
     199: aload_3
     200: ifnull        245
     203: new           #113                // class java/util/LinkedHashMap
     206: dup
     207: fconst_1
     208: aload_3
     209: invokeinterface #114,  1          // InterfaceMethod java/util/Map.size:()I
     214: i2f
     215: ldc           #115                // float 0.75f
     217: fdiv
     218: fadd
     219: invokestatic  #116                // Method java/lang/Math.round:(F)I
     222: invokespecial #117                // Method java/util/LinkedHashMap."<init>":(I)V
     225: astore        4
     227: aload_3
     228: aload         4
     230: dup
     231: invokevirtual #118                // Method java/lang/Object.getClass:()Ljava/lang/Class;
     234: pop
     235: invokedynamic #119,  0            // InvokeDynamic #8:accept:(Ljava/util/Map;)Ljava/util/function/BiConsumer;
     240: invokeinterface #120,  2          // InterfaceMethod java/util/Map.forEach:(Ljava/util/function/BiConsumer;)V
     245: aload_0
     246: aload         4
     248: aload_1
     249: invokespecial #121                // Method toInvokers:(Ljava/util/Map;Ljava/util/List;)Ljava/util/Map;
     252: astore        5
     254: aload         5
     256: invokestatic  #122                // Method org/apache/dubbo/common/utils/CollectionUtils.isEmptyMap:(Ljava/util/Map;)Z
     259: ifeq          322
     262: getstatic     #97                 // Field logger:Lorg/apache/dubbo/common/logger/ErrorTypeAwareLogger;
     265: ldc           #123                // String 3-1
     267: ldc           #124                // String inconsistency between the client protocol and the protocol of the server
     269: ldc           #75                 // String
     271: ldc           #125                // String urls to invokers error
     273: new           #126                // class java/lang/IllegalStateException
     276: dup
     277: new           #100                // class java/lang/StringBuilder
     280: dup
     281: invokespecial #101                // Method java/lang/StringBuilder."<init>":()V
     284: ldc           #127                // String urls to invokers error. invokerUrls.size :
     286: invokevirtual #103                // Method java/lang/StringBuilder.append:(Ljava/lang/String;)Ljava/lang/StringBuilder;
     289: aload_1
     290: invokeinterface #82,  1           // InterfaceMethod java/util/List.size:()I
     295: invokevirtual #128                // Method java/lang/StringBuilder.append:(I)Ljava/lang/StringBuilder;
     298: ldc           #129                // String , invoker.size :0. urls :
     300: invokevirtual #103                // Method java/lang/StringBuilder.append:(Ljava/lang/String;)Ljava/lang/StringBuilder;
     303: aload_1
     304: invokevirtual #130                // Method java/lang/Object.toString:()Ljava/lang/String;
     307: invokevirtual #103                // Method java/lang/StringBuilder.append:(Ljava/lang/String;)Ljava/lang/StringBuilder;
     310: invokevirtual #106                // Method java/lang/StringBuilder.toString:()Ljava/lang/String;
     313: invokespecial #131                // Method java/lang/IllegalStateException."<init>":(Ljava/lang/String;)V
     316: invokeinterface #132,  6          // InterfaceMethod org/apache/dubbo/common/logger/ErrorTypeAwareLogger.error:(Ljava/lang/String;Ljava/lang/String;Ljava/lang/String;Ljava/lang/String;Ljava/lang/Throwable;)V
     321: return
     322: new           #93                 // class java/util/ArrayList
     325: dup
     326: aload         5
     328: invokeinterface #133,  1          // InterfaceMethod java/util/Map.values:()Ljava/util/Collection;
     333: invokespecial #134                // Method java/util/ArrayList."<init>":(Ljava/util/Collection;)V
     336: invokestatic  #135                // Method java/util/Collections.unmodifiableList:(Ljava/util/List;)Ljava/util/List;
     339: astore        6
     341: aload_0
     342: getfield      #136                // Field multiGroup:Z
     345: ifeq          364
     348: new           #137                // class org/apache/dubbo/rpc/cluster/router/state/BitList
     351: dup
     352: aload_0
     353: aload         6
     355: invokespecial #138                // Method toMergeInvokerList:(Ljava/util/List;)Ljava/util/List;
     358: invokespecial #139                // Method org/apache/dubbo/rpc/cluster/router/state/BitList."<init>":(Ljava/util/List;)V
     361: goto          373
     364: new           #137                // class org/apache/dubbo/rpc/cluster/router/state/BitList
     367: dup
     368: aload         6
     370: invokespecial #139                // Method org/apache/dubbo/rpc/cluster/router/state/BitList."<init>":(Ljava/util/List;)V
     373: astore        7
     375: aload_0
     376: aload         7
     378: invokevirtual #140                // Method org/apache/dubbo/rpc/cluster/router/state/BitList.clone:()Lorg/apache/dubbo/rpc/cluster/router/state/BitList;
     381: aload_0
     382: aload         7
     384: invokedynamic #141,  0            // InvokeDynamic #9:run:(Lorg/apache/dubbo/registry/integration/RegistryDirectory;Lorg/apache/dubbo/rpc/cluster/router/state/BitList;)Ljava/lang/Runnable;
     389: invokevirtual #90                 // Method refreshRouter:(Lorg/apache/dubbo/rpc/cluster/router/state/BitList;Ljava/lang/Runnable;)V
     392: aload_0
     393: aload         5
     395: putfield      #112                // Field urlInvokerMap:Ljava/util/Map;
     398: aload_0
     399: aload         4
     401: aload         5
     403: invokespecial #142                // Method destroyUnusedInvokers:(Ljava/util/Map;Ljava/util/Map;)V
     406: goto          429
     409: astore        8
     411: getstatic     #97                 // Field logger:Lorg/apache/dubbo/common/logger/ErrorTypeAwareLogger;
     414: ldc           #144                // String 1-15
     416: ldc           #75                 // String
     418: ldc           #75                 // String
     420: ldc           #145                // String destroyUnusedInvokers error.
     422: aload         8
     424: invokeinterface #146,  6          // InterfaceMethod org/apache/dubbo/common/logger/ErrorTypeAwareLogger.warn:(Ljava/lang/String;Ljava/lang/String;Ljava/lang/String;Ljava/lang/String;Ljava/lang/Throwable;)V
     429: aload_0
     430: invokevirtual #147                // Method invokersChanged:()V
     433: getstatic     #97                 // Field logger:Lorg/apache/dubbo/common/logger/ErrorTypeAwareLogger;
     436: new           #100                // class java/lang/StringBuilder
     439: dup
     440: invokespecial #101                // Method java/lang/StringBuilder."<init>":()V
     443: ldc           #148                // String Received invokers changed event from registry. Registry type: interface. Service Key:
     445: invokevirtual #103                // Method java/lang/StringBuilder.append:(Ljava/lang/String;)Ljava/lang/StringBuilder;
     448: aload_0
     449: invokevirtual #69                 // Method getConsumerUrl:()Lorg/apache/dubbo/common/URL;
     452: invokevirtual #149                // Method org/apache/dubbo/common/URL.getServiceKey:()Ljava/lang/String;
     455: invokevirtual #103                // Method java/lang/StringBuilder.append:(Ljava/lang/String;)Ljava/lang/StringBuilder;
     458: ldc           #150                // String . Urls Size :
     460: invokevirtual #103                // Method java/lang/StringBuilder.append:(Ljava/lang/String;)Ljava/lang/StringBuilder;
     463: aload_1
     464: invokeinterface #82,  1           // InterfaceMethod java/util/List.size:()I
     469: invokevirtual #128                // Method java/lang/StringBuilder.append:(I)Ljava/lang/StringBuilder;
     472: ldc           #151                // String . Invokers Size :
     474: invokevirtual #103                // Method java/lang/StringBuilder.append:(Ljava/lang/String;)Ljava/lang/StringBuilder;
     477: aload_0
     478: invokevirtual #152                // Method getInvokers:()Lorg/apache/dubbo/rpc/cluster/router/state/BitList;
     481: invokevirtual #153                // Method org/apache/dubbo/rpc/cluster/router/state/BitList.size:()I
     484: invokevirtual #128                // Method java/lang/StringBuilder.append:(I)Ljava/lang/StringBuilder;
     487: ldc           #154                // String . Available Size:
     489: invokevirtual #103                // Method java/lang/StringBuilder.append:(Ljava/lang/String;)Ljava/lang/StringBuilder;
     492: aload_0
     493: invokevirtual #155                // Method getValidInvokers:()Lorg/apache/dubbo/rpc/cluster/router/state/BitList;
     496: invokevirtual #153                // Method org/apache/dubbo/rpc/cluster/router/state/BitList.size:()I
     499: invokevirtual #128                // Method java/lang/StringBuilder.append:(I)Ljava/lang/StringBuilder;
     502: ldc           #156                // String . Available Invokers :
     504: invokevirtual #103                // Method java/lang/StringBuilder.append:(Ljava/lang/String;)Ljava/lang/StringBuilder;
     507: aload_0
     508: invokevirtual #157                // Method joinValidInvokerAddresses:()Ljava/lang/String;
     511: invokevirtual #103                // Method java/lang/StringBuilder.append:(Ljava/lang/String;)Ljava/lang/StringBuilder;
     514: invokevirtual #106                // Method java/lang/StringBuilder.toString:()Ljava/lang/String;
     517: invokeinterface #158,  2          // InterfaceMethod org/apache/dubbo/common/logger/ErrorTypeAwareLogger.info:(Ljava/lang/String;)V
     522: return
    Exception table:
       from    to  target type
         398   406   409   Class java/lang/Exception

  private java.util.List<org.apache.dubbo.rpc.Invoker<T>> toMergeInvokerList(java.util.List<org.apache.dubbo.rpc.Invoker<T>>);
    Code:
       0: new           #93                 // class java/util/ArrayList
       3: dup
       4: invokespecial #94                 // Method java/util/ArrayList."<init>":()V
       7: astore_2
       8: new           #159                // class java/util/HashMap
      11: dup
      12: invokespecial #160                // Method java/util/HashMap."<init>":()V
      15: astore_3
      16: aload_1
      17: invokeinterface #66,  1           // InterfaceMethod java/util/List.iterator:()Ljava/util/Iterator;
      22: astore        4
      24: aload         4
      26: invokeinterface #67,  1           // InterfaceMethod java/util/Iterator.hasNext:()Z
      31: ifeq          96
      34: aload         4
      36: invokeinterface #68,  1           // InterfaceMethod java/util/Iterator.next:()Ljava/lang/Object;
      41: checkcast     #161                // class org/apache/dubbo/rpc/Invoker
      44: astore        5
      46: aload         5
      48: invokeinterface #162,  1          // InterfaceMethod org/apache/dubbo/rpc/Invoker.getUrl:()Lorg/apache/dubbo/common/URL;
      53: ldc           #75                 // String
      55: invokevirtual #163                // Method org/apache/dubbo/common/URL.getGroup:(Ljava/lang/String;)Ljava/lang/String;
      58: astore        6
      60: aload_3
      61: aload         6
      63: invokedynamic #164,  0            // InvokeDynamic #10:apply:()Ljava/util/function/Function;
      68: invokeinterface #165,  3          // InterfaceMethod java/util/Map.computeIfAbsent:(Ljava/lang/Object;Ljava/util/function/Function;)Ljava/lang/Object;
      73: pop
      74: aload_3
      75: aload         6
      77: invokeinterface #166,  2          // InterfaceMethod java/util/Map.get:(Ljava/lang/Object;)Ljava/lang/Object;
      82: checkcast     #50                 // class java/util/List
      85: aload         5
      87: invokeinterface #167,  2          // InterfaceMethod java/util/List.add:(Ljava/lang/Object;)Z
      92: pop
      93: goto          24
      96: aload_3
      97: invokeinterface #114,  1          // InterfaceMethod java/util/Map.size:()I
     102: iconst_1
     103: if_icmpne     135
     106: aload_2
     107: aload_3
     108: invokeinterface #133,  1          // InterfaceMethod java/util/Map.values:()Ljava/util/Collection;
     113: invokeinterface #168,  1          // InterfaceMethod java/util/Collection.iterator:()Ljava/util/Iterator;
     118: invokeinterface #68,  1           // InterfaceMethod java/util/Iterator.next:()Ljava/lang/Object;
     123: checkcast     #169                // class java/util/Collection
     126: invokeinterface #108,  2          // InterfaceMethod java/util/List.addAll:(Ljava/util/Collection;)Z
     131: pop
     132: goto          223
     135: aload_3
     136: invokeinterface #114,  1          // InterfaceMethod java/util/Map.size:()I
     141: iconst_1
     142: if_icmple     221
     145: aload_3
     146: invokeinterface #133,  1          // InterfaceMethod java/util/Map.values:()Ljava/util/Collection;
     151: invokeinterface #168,  1          // InterfaceMethod java/util/Collection.iterator:()Ljava/util/Iterator;
     156: astore        4
     158: aload         4
     160: invokeinterface #67,  1           // InterfaceMethod java/util/Iterator.hasNext:()Z
     165: ifeq          218
     168: aload         4
     170: invokeinterface #68,  1           // InterfaceMethod java/util/Iterator.next:()Ljava/lang/Object;
     175: checkcast     #50                 // class java/util/List
     178: astore        5
     180: new           #170                // class org/apache/dubbo/rpc/cluster/directory/StaticDirectory
     183: dup
     184: aload         5
     186: invokespecial #171                // Method org/apache/dubbo/rpc/cluster/directory/StaticDirectory."<init>":(Ljava/util/List;)V
     189: astore        6
     191: aload         6
     193: invokevirtual #172                // Method org/apache/dubbo/rpc/cluster/directory/StaticDirectory.buildRouterChain:()V
     196: aload_2
     197: aload_0
     198: getfield      #173                // Field cluster:Lorg/apache/dubbo/rpc/cluster/Cluster;
     201: aload         6
     203: iconst_0
     204: invokeinterface #174,  3          // InterfaceMethod org/apache/dubbo/rpc/cluster/Cluster.join:(Lorg/apache/dubbo/rpc/cluster/Directory;Z)Lorg/apache/dubbo/rpc/Invoker;
     209: invokeinterface #167,  2          // InterfaceMethod java/util/List.add:(Ljava/lang/Object;)Z
     214: pop
     215: goto          158
     218: goto          223
     221: aload_1
     222: astore_2
     223: aload_2
     224: areturn

  private java.util.Optional<java.util.List<org.apache.dubbo.rpc.cluster.Router>> toRouters(java.util.List<org.apache.dubbo.common.URL>);
    Code:
       0: aload_1
       1: ifnull        13
       4: aload_1
       5: invokeinterface #65,  1           // InterfaceMethod java/util/List.isEmpty:()Z
      10: ifeq          17
      13: invokestatic  #175                // Method java/util/Optional.empty:()Ljava/util/Optional;
      16: areturn
      17: new           #93                 // class java/util/ArrayList
      20: dup
      21: invokespecial #94                 // Method java/util/ArrayList."<init>":()V
      24: astore_2
      25: aload_1
      26: invokeinterface #66,  1           // InterfaceMethod java/util/List.iterator:()Ljava/util/Iterator;
      31: astore_3
      32: aload_3
      33: invokeinterface #67,  1           // InterfaceMethod java/util/Iterator.hasNext:()Z
      38: ifeq          176
      41: aload_3
      42: invokeinterface #68,  1           // InterfaceMethod java/util/Iterator.next:()Ljava/lang/Object;
      47: checkcast     #85                 // class org/apache/dubbo/common/URL
      50: astore        4
      52: ldc           #84                 // String empty
      54: aload         4
      56: invokevirtual #86                 // Method org/apache/dubbo/common/URL.getProtocol:()Ljava/lang/String;
      59: invokevirtual #87                 // Method java/lang/String.equals:(Ljava/lang/Object;)Z
      62: ifeq          68
      65: goto          32
      68: aload         4
      70: ldc           #176                // String router
      72: invokevirtual #177                // Method org/apache/dubbo/common/URL.getParameter:(Ljava/lang/String;)Ljava/lang/String;
      75: astore        5
      77: aload         5
      79: ifnull        99
      82: aload         5
      84: invokevirtual #178                // Method java/lang/String.length:()I
      87: ifle          99
      90: aload         4
      92: aload         5
      94: invokevirtual #179                // Method org/apache/dubbo/common/URL.setProtocol:(Ljava/lang/String;)Lorg/apache/dubbo/common/URL;
      97: astore        4
      99: aload_0
     100: getfield      #180                // Field routerFactory:Lorg/apache/dubbo/rpc/cluster/RouterFactory;
     103: aload         4
     105: invokeinterface #181,  2          // InterfaceMethod org/apache/dubbo/rpc/cluster/RouterFactory.getRouter:(Lorg/apache/dubbo/common/URL;)Lorg/apache/dubbo/rpc/cluster/Router;
     110: astore        6
     112: aload_2
     113: aload         6
     115: invokeinterface #182,  2          // InterfaceMethod java/util/List.contains:(Ljava/lang/Object;)Z
     120: ifne          132
     123: aload_2
     124: aload         6
     126: invokeinterface #167,  2          // InterfaceMethod java/util/List.add:(Ljava/lang/Object;)Z
     131: pop
     132: goto          173
     135: astore        6
     137: getstatic     #97                 // Field logger:Lorg/apache/dubbo/common/logger/ErrorTypeAwareLogger;
     140: ldc           #123                // String 3-1
     142: ldc           #75                 // String
     144: ldc           #75                 // String
     146: new           #100                // class java/lang/StringBuilder
     149: dup
     150: invokespecial #101                // Method java/lang/StringBuilder."<init>":()V
     153: ldc           #184                // String convert router url to router error, url:
     155: invokevirtual #103                // Method java/lang/StringBuilder.append:(Ljava/lang/String;)Ljava/lang/StringBuilder;
     158: aload         4
     160: invokevirtual #185                // Method java/lang/StringBuilder.append:(Ljava/lang/Object;)Ljava/lang/StringBuilder;
     163: invokevirtual #106                // Method java/lang/StringBuilder.toString:()Ljava/lang/String;
     166: aload         6
     168: invokeinterface #132,  6          // InterfaceMethod org/apache/dubbo/common/logger/ErrorTypeAwareLogger.error:(Ljava/lang/String;Ljava/lang/String;Ljava/lang/String;Ljava/lang/String;Ljava/lang/Throwable;)V
     173: goto          32
     176: aload_2
     177: invokestatic  #186                // Method java/util/Optional.of:(Ljava/lang/Object;)Ljava/util/Optional;
     180: areturn
    Exception table:
       from    to  target type
          99   132   135   Class java/lang/Throwable

  private java.util.Map<org.apache.dubbo.common.URL, org.apache.dubbo.rpc.Invoker<T>> toInvokers(java.util.Map<org.apache.dubbo.common.URL, org.apache.dubbo.rpc.Invoker<T>>, java.util.List<org.apache.dubbo.common.URL>);
    Code:
       0: new           #187                // class java/util/concurrent/ConcurrentHashMap
       3: dup
       4: aload_2
       5: ifnonnull     12
       8: iconst_1
       9: goto          25
      12: aload_2
      13: invokeinterface #82,  1           // InterfaceMethod java/util/List.size:()I
      18: i2f
      19: ldc           #115                // float 0.75f
      21: fdiv
      22: fconst_1
      23: fadd
      24: f2i
      25: invokespecial #188                // Method java/util/concurrent/ConcurrentHashMap."<init>":(I)V
      28: astore_3
      29: aload_2
      30: ifnull        42
      33: aload_2
      34: invokeinterface #65,  1           // InterfaceMethod java/util/List.isEmpty:()Z
      39: ifeq          44
      42: aload_3
      43: areturn
      44: aload_0
      45: getfield      #189                // Field queryMap:Ljava/util/Map;
      48: ldc           #190                // String protocol
      50: invokeinterface #166,  2          // InterfaceMethod java/util/Map.get:(Ljava/lang/Object;)Ljava/lang/Object;
      55: checkcast     #191                // class java/lang/String
      58: astore        4
      60: aload_2
      61: invokeinterface #66,  1           // InterfaceMethod java/util/List.iterator:()Ljava/util/Iterator;
      66: astore        5
      68: aload         5
      70: invokeinterface #67,  1           // InterfaceMethod java/util/Iterator.hasNext:()Z
      75: ifeq          388
      78: aload         5
      80: invokeinterface #68,  1           // InterfaceMethod java/util/Iterator.next:()Ljava/lang/Object;
      85: checkcast     #85                 // class org/apache/dubbo/common/URL
      88: astore        6
      90: aload_0
      91: aload         4
      93: aload         6
      95: invokespecial #192                // Method checkProtocolValid:(Ljava/lang/String;Lorg/apache/dubbo/common/URL;)Z
      98: ifne          104
     101: goto          68
     104: aload_0
     105: aload         6
     107: invokespecial #193                // Method mergeUrl:(Lorg/apache/dubbo/common/URL;)Lorg/apache/dubbo/common/URL;
     110: astore        7
     112: aload_1
     113: ifnonnull     120
     116: aconst_null
     117: goto          131
     120: aload_1
     121: aload         7
     123: invokeinterface #194,  2          // InterfaceMethod java/util/Map.remove:(Ljava/lang/Object;)Ljava/lang/Object;
     128: checkcast     #161                // class org/apache/dubbo/rpc/Invoker
     131: astore        8
     133: aload         8
     135: ifnonnull     374
     138: iconst_1
     139: istore        9
     141: aload         7
     143: ldc           #195                // String disabled
     145: invokevirtual #196                // Method org/apache/dubbo/common/URL.hasParameter:(Ljava/lang/String;)Z
     148: ifeq          172
     151: aload         7
     153: ldc           #195                // String disabled
     155: iconst_0
     156: invokevirtual #197                // Method org/apache/dubbo/common/URL.getParameter:(Ljava/lang/String;Z)Z
     159: ifne          166
     162: iconst_1
     163: goto          167
     166: iconst_0
     167: istore        9
     169: goto          182
     172: aload         7
     174: ldc           #198                // String enabled
     176: iconst_1
     177: invokevirtual #197                // Method org/apache/dubbo/common/URL.getParameter:(Ljava/lang/String;Z)Z
     180: istore        9
     182: iload         9
     184: ifeq          204
     187: aload_0
     188: getfield      #199                // Field protocol:Lorg/apache/dubbo/rpc/Protocol;
     191: aload_0
     192: getfield      #200                // Field serviceType:Ljava/lang/Class;
     195: aload         7
     197: invokeinterface #201,  3          // InterfaceMethod org/apache/dubbo/rpc/Protocol.refer:(Ljava/lang/Class;Lorg/apache/dubbo/common/URL;)Lorg/apache/dubbo/rpc/Invoker;
     202: astore        8
     204: goto          355
     207: astore        9
     209: aload         9
     211: instanceof    #202                // class org/apache/dubbo/rpc/RpcException
     214: ifeq          294
     217: aload         9
     219: invokevirtual #203                // Method java/lang/Throwable.getMessage:()Ljava/lang/String;
     222: ldc           #204                // String serialization optimizer
     224: invokevirtual #205                // Method java/lang/String.contains:(Ljava/lang/CharSequence;)Z
     227: ifeq          294
     230: getstatic     #97                 // Field logger:Lorg/apache/dubbo/common/logger/ErrorTypeAwareLogger;
     233: ldc           #206                // String 4-2
     235: ldc           #207                // String typo in optimizer class
     237: ldc           #75                 // String
     239: new           #100                // class java/lang/StringBuilder
     242: dup
     243: invokespecial #101                // Method java/lang/StringBuilder."<init>":()V
     246: ldc           #208                // String Failed to refer invoker for interface:
     248: invokevirtual #103                // Method java/lang/StringBuilder.append:(Ljava/lang/String;)Ljava/lang/StringBuilder;
     251: aload_0
     252: getfield      #200                // Field serviceType:Ljava/lang/Class;
     255: invokevirtual #185                // Method java/lang/StringBuilder.append:(Ljava/lang/Object;)Ljava/lang/StringBuilder;
     258: ldc           #209                // String ,url:(
     260: invokevirtual #103                // Method java/lang/StringBuilder.append:(Ljava/lang/String;)Ljava/lang/StringBuilder;
     263: aload         7
     265: invokevirtual #185                // Method java/lang/StringBuilder.append:(Ljava/lang/Object;)Ljava/lang/StringBuilder;
     268: ldc           #210                // String )
     270: invokevirtual #103                // Method java/lang/StringBuilder.append:(Ljava/lang/String;)Ljava/lang/StringBuilder;
     273: aload         9
     275: invokevirtual #203                // Method java/lang/Throwable.getMessage:()Ljava/lang/String;
     278: invokevirtual #103                // Method java/lang/StringBuilder.append:(Ljava/lang/String;)Ljava/lang/StringBuilder;
     281: invokevirtual #106                // Method java/lang/StringBuilder.toString:()Ljava/lang/String;
     284: aload         9
     286: invokeinterface #132,  6          // InterfaceMethod org/apache/dubbo/common/logger/ErrorTypeAwareLogger.error:(Ljava/lang/String;Ljava/lang/String;Ljava/lang/String;Ljava/lang/String;Ljava/lang/Throwable;)V
     291: goto          355
     294: getstatic     #97                 // Field logger:Lorg/apache/dubbo/common/logger/ErrorTypeAwareLogger;
     297: ldc           #211                // String 4-3
     299: ldc           #75                 // String
     301: ldc           #75                 // String
     303: new           #100                // class java/lang/StringBuilder
     306: dup
     307: invokespecial #101                // Method java/lang/StringBuilder."<init>":()V
     310: ldc           #208                // String Failed to refer invoker for interface:
     312: invokevirtual #103                // Method java/lang/StringBuilder.append:(Ljava/lang/String;)Ljava/lang/StringBuilder;
     315: aload_0
     316: getfield      #200                // Field serviceType:Ljava/lang/Class;
     319: invokevirtual #185                // Method java/lang/StringBuilder.append:(Ljava/lang/Object;)Ljava/lang/StringBuilder;
     322: ldc           #209                // String ,url:(
     324: invokevirtual #103                // Method java/lang/StringBuilder.append:(Ljava/lang/String;)Ljava/lang/StringBuilder;
     327: aload         7
     329: invokevirtual #185                // Method java/lang/StringBuilder.append:(Ljava/lang/Object;)Ljava/lang/StringBuilder;
     332: ldc           #210                // String )
     334: invokevirtual #103                // Method java/lang/StringBuilder.append:(Ljava/lang/String;)Ljava/lang/StringBuilder;
     337: aload         9
     339: invokevirtual #203                // Method java/lang/Throwable.getMessage:()Ljava/lang/String;
     342: invokevirtual #103                // Method java/lang/StringBuilder.append:(Ljava/lang/String;)Ljava/lang/StringBuilder;
     345: invokevirtual #106                // Method java/lang/StringBuilder.toString:()Ljava/lang/String;
     348: aload         9
     350: invokeinterface #132,  6          // InterfaceMethod org/apache/dubbo/common/logger/ErrorTypeAwareLogger.error:(Ljava/lang/String;Ljava/lang/String;Ljava/lang/String;Ljava/lang/String;Ljava/lang/Throwable;)V
     355: aload         8
     357: ifnull        385
     360: aload_3
     361: aload         7
     363: aload         8
     365: invokeinterface #212,  3          // InterfaceMethod java/util/Map.put:(Ljava/lang/Object;Ljava/lang/Object;)Ljava/lang/Object;
     370: pop
     371: goto          385
     374: aload_3
     375: aload         7
     377: aload         8
     379: invokeinterface #212,  3          // InterfaceMethod java/util/Map.put:(Ljava/lang/Object;Ljava/lang/Object;)Ljava/lang/Object;
     384: pop
     385: goto          68
     388: aload_3
     389: areturn
    Exception table:
       from    to  target type
         138   204   207   Class java/lang/Throwable

  private boolean checkProtocolValid(java.lang.String, org.apache.dubbo.common.URL);
    Code:
       0: aload_1
       1: ifnull        76
       4: aload_1
       5: invokevirtual #178                // Method java/lang/String.length:()I
       8: ifle          76
      11: iconst_0
      12: istore_3
      13: aload_1
      14: ldc           #213                // String ,
      16: invokevirtual #214                // Method java/lang/String.split:(Ljava/lang/String;)[Ljava/lang/String;
      19: astore        4
      21: aload         4
      23: astore        5
      25: aload         5
      27: arraylength
      28: istore        6
      30: iconst_0
      31: istore        7
      33: iload         7
      35: iload         6
      37: if_icmpge     70
      40: aload         5
      42: iload         7
      44: aaload
      45: astore        8
      47: aload_2
      48: invokevirtual #86                 // Method org/apache/dubbo/common/URL.getProtocol:()Ljava/lang/String;
      51: aload         8
      53: invokevirtual #87                 // Method java/lang/String.equals:(Ljava/lang/Object;)Z
      56: ifeq          64
      59: iconst_1
      60: istore_3
      61: goto          70
      64: iinc          7, 1
      67: goto          33
      70: iload_3
      71: ifne          76
      74: iconst_0
      75: ireturn
      76: ldc           #84                 // String empty
      78: aload_2
      79: invokevirtual #86                 // Method org/apache/dubbo/common/URL.getProtocol:()Ljava/lang/String;
      82: invokevirtual #87                 // Method java/lang/String.equals:(Ljava/lang/Object;)Z
      85: ifeq          90
      88: iconst_0
      89: ireturn
      90: aload_0
      91: invokevirtual #59                 // Method getUrl:()Lorg/apache/dubbo/common/URL;
      94: invokevirtual #215                // Method org/apache/dubbo/common/URL.getOrDefaultFrameworkModel:()Lorg/apache/dubbo/rpc/model/FrameworkModel;
      97: ldc           #216                // class org/apache/dubbo/rpc/Protocol
      99: invokevirtual #217                // Method org/apache/dubbo/rpc/model/FrameworkModel.getExtensionLoader:(Ljava/lang/Class;)Lorg/apache/dubbo/common/extension/ExtensionLoader;
     102: aload_2
     103: invokevirtual #86                 // Method org/apache/dubbo/common/URL.getProtocol:()Ljava/lang/String;
     106: invokevirtual #218                // Method org/apache/dubbo/common/extension/ExtensionLoader.hasExtension:(Ljava/lang/String;)Z
     109: ifne          217
     112: getstatic     #97                 // Field logger:Lorg/apache/dubbo/common/logger/ErrorTypeAwareLogger;
     115: ldc           #219                // String 4-1
     117: ldc           #220                // String protocol extension does not installed
     119: ldc           #75                 // String
     121: ldc           #221                // String Unsupported protocol.
     123: new           #126                // class java/lang/IllegalStateException
     126: dup
     127: new           #100                // class java/lang/StringBuilder
     130: dup
     131: invokespecial #101                // Method java/lang/StringBuilder."<init>":()V
     134: ldc           #222                // String Unsupported protocol
     136: invokevirtual #103                // Method java/lang/StringBuilder.append:(Ljava/lang/String;)Ljava/lang/StringBuilder;
     139: aload_2
     140: invokevirtual #86                 // Method org/apache/dubbo/common/URL.getProtocol:()Ljava/lang/String;
     143: invokevirtual #103                // Method java/lang/StringBuilder.append:(Ljava/lang/String;)Ljava/lang/StringBuilder;
     146: ldc           #223                // String  in notified url:
     148: invokevirtual #103                // Method java/lang/StringBuilder.append:(Ljava/lang/String;)Ljava/lang/StringBuilder;
     151: aload_2
     152: invokevirtual #185                // Method java/lang/StringBuilder.append:(Ljava/lang/Object;)Ljava/lang/StringBuilder;
     155: ldc           #224                // String  from registry
     157: invokevirtual #103                // Method java/lang/StringBuilder.append:(Ljava/lang/String;)Ljava/lang/StringBuilder;
     160: aload_0
     161: invokevirtual #59                 // Method getUrl:()Lorg/apache/dubbo/common/URL;
     164: invokevirtual #225                // Method org/apache/dubbo/common/URL.getAddress:()Ljava/lang/String;
     167: invokevirtual #103                // Method java/lang/StringBuilder.append:(Ljava/lang/String;)Ljava/lang/StringBuilder;
     170: ldc           #226                // String  to consumer
     172: invokevirtual #103                // Method java/lang/StringBuilder.append:(Ljava/lang/String;)Ljava/lang/StringBuilder;
     175: invokestatic  #227                // Method org/apache/dubbo/common/utils/NetUtils.getLocalHost:()Ljava/lang/String;
     178: invokevirtual #103                // Method java/lang/StringBuilder.append:(Ljava/lang/String;)Ljava/lang/StringBuilder;
     181: ldc           #228                // String , supported protocol:
     183: invokevirtual #103                // Method java/lang/StringBuilder.append:(Ljava/lang/String;)Ljava/lang/StringBuilder;
     186: aload_0
     187: invokevirtual #59                 // Method getUrl:()Lorg/apache/dubbo/common/URL;
     190: invokevirtual #215                // Method org/apache/dubbo/common/URL.getOrDefaultFrameworkModel:()Lorg/apache/dubbo/rpc/model/FrameworkModel;
     193: ldc           #216                // class org/apache/dubbo/rpc/Protocol
     195: invokevirtual #217                // Method org/apache/dubbo/rpc/model/FrameworkModel.getExtensionLoader:(Ljava/lang/Class;)Lorg/apache/dubbo/common/extension/ExtensionLoader;
     198: invokevirtual #229                // Method org/apache/dubbo/common/extension/ExtensionLoader.getSupportedExtensions:()Ljava/util/Set;
     201: invokevirtual #185                // Method java/lang/StringBuilder.append:(Ljava/lang/Object;)Ljava/lang/StringBuilder;
     204: invokevirtual #106                // Method java/lang/StringBuilder.toString:()Ljava/lang/String;
     207: invokespecial #131                // Method java/lang/IllegalStateException."<init>":(Ljava/lang/String;)V
     210: invokeinterface #132,  6          // InterfaceMethod org/apache/dubbo/common/logger/ErrorTypeAwareLogger.error:(Ljava/lang/String;Ljava/lang/String;Ljava/lang/String;Ljava/lang/String;Ljava/lang/Throwable;)V
     215: iconst_0
     216: ireturn
     217: iconst_1
     218: ireturn

  private org.apache.dubbo.common.URL mergeUrl(org.apache.dubbo.common.URL);
    Code:
       0: aload_1
       1: instanceof    #230                // class org/apache/dubbo/common/url/component/ServiceAddressURL
       4: ifeq          16
       7: aload_0
       8: aload_1
       9: invokevirtual #77                 // Method overrideWithConfigurator:(Lorg/apache/dubbo/common/URL;)Lorg/apache/dubbo/common/URL;
      12: astore_1
      13: goto          60
      16: aload_0
      17: getfield      #10                 // Field moduleModel:Lorg/apache/dubbo/rpc/model/ModuleModel;
      20: invokevirtual #231                // Method org/apache/dubbo/rpc/model/ModuleModel.getApplicationModel:()Lorg/apache/dubbo/rpc/model/ApplicationModel;
      23: invokevirtual #232                // Method org/apache/dubbo/rpc/model/ApplicationModel.getBeanFactory:()Lorg/apache/dubbo/common/beans/factory/ScopeBeanFactory;
      26: ldc           #233                // class org/apache/dubbo/rpc/cluster/support/ClusterUtils
      28: invokevirtual #234                // Method org/apache/dubbo/common/beans/factory/ScopeBeanFactory.getBean:(Ljava/lang/Class;)Ljava/lang/Object;
      31: checkcast     #233                // class org/apache/dubbo/rpc/cluster/support/ClusterUtils
      34: aload_1
      35: aload_0
      36: getfield      #189                // Field queryMap:Ljava/util/Map;
      39: invokevirtual #235                // Method org/apache/dubbo/rpc/cluster/support/ClusterUtils.mergeUrl:(Lorg/apache/dubbo/common/URL;Ljava/util/Map;)Lorg/apache/dubbo/common/URL;
      42: astore_1
      43: aload_0
      44: aload_1
      45: invokevirtual #77                 // Method overrideWithConfigurator:(Lorg/apache/dubbo/common/URL;)Lorg/apache/dubbo/common/URL;
      48: astore_1
      49: aload_1
      50: ldc           #237                // String check
      52: iconst_0
      53: invokestatic  #238                // Method java/lang/String.valueOf:(Z)Ljava/lang/String;
      56: invokevirtual #239                // Method org/apache/dubbo/common/URL.addParameter:(Ljava/lang/String;Ljava/lang/String;)Lorg/apache/dubbo/common/URL;
      59: astore_1
      60: aload_1
      61: ldc           #240                // String mock
      63: invokevirtual #196                // Method org/apache/dubbo/common/URL.hasParameter:(Ljava/lang/String;)Z
      66: ifne          78
      69: aload_1
      70: ldc           #240                // String mock
      72: invokevirtual #241                // Method org/apache/dubbo/common/URL.getAnyMethodParameter:(Ljava/lang/String;)Ljava/lang/String;
      75: ifnull        85
      78: aload_1
      79: ldc           #242                // String dubbo.tag
      81: invokevirtual #243                // Method org/apache/dubbo/common/URL.removeParameter:(Ljava/lang/String;)Lorg/apache/dubbo/common/URL;
      84: astore_1
      85: aload_1
      86: invokevirtual #244                // Method org/apache/dubbo/common/URL.getPath:()Ljava/lang/String;
      89: ifnull        102
      92: aload_1
      93: invokevirtual #244                // Method org/apache/dubbo/common/URL.getPath:()Ljava/lang/String;
      96: invokevirtual #178                // Method java/lang/String.length:()I
      99: ifne          169
     102: ldc           #245                // String dubbo
     104: aload_1
     105: invokevirtual #86                 // Method org/apache/dubbo/common/URL.getProtocol:()Ljava/lang/String;
     108: invokevirtual #87                 // Method java/lang/String.equals:(Ljava/lang/Object;)Z
     111: ifeq          169
     114: aload_0
     115: getfield      #78                 // Field directoryUrl:Lorg/apache/dubbo/common/URL;
     118: invokevirtual #246                // Method org/apache/dubbo/common/URL.getServiceInterface:()Ljava/lang/String;
     121: astore_2
     122: aload_2
     123: ifnull        169
     126: aload_2
     127: bipush        47
     129: invokevirtual #247                // Method java/lang/String.indexOf:(I)I
     132: istore_3
     133: iload_3
     134: iflt          145
     137: aload_2
     138: iload_3
     139: iconst_1
     140: iadd
     141: invokevirtual #248                // Method java/lang/String.substring:(I)Ljava/lang/String;
     144: astore_2
     145: aload_2
     146: bipush        58
     148: invokevirtual #249                // Method java/lang/String.lastIndexOf:(I)I
     151: istore_3
     152: iload_3
     153: iflt          163
     156: aload_2
     157: iconst_0
     158: iload_3
     159: invokevirtual #250                // Method java/lang/String.substring:(II)Ljava/lang/String;
     162: astore_2
     163: aload_1
     164: aload_2
     165: invokevirtual #251                // Method org/apache/dubbo/common/URL.setPath:(Ljava/lang/String;)Lorg/apache/dubbo/common/URL;
     168: astore_1
     169: aload_1
     170: areturn

  protected org.apache.dubbo.common.URL overrideWithConfigurator(org.apache.dubbo.common.URL);
    Code:
       0: aload_0
       1: aload_0
       2: getfield      #52                 // Field configurators:Ljava/util/List;
       5: aload_1
       6: invokespecial #252                // Method overrideWithConfigurators:(Ljava/util/List;Lorg/apache/dubbo/common/URL;)Lorg/apache/dubbo/common/URL;
       9: astore_1
      10: aload_0
      11: aload_0
      12: getfield      #12                 // Field consumerConfigurationListener:Lorg/apache/dubbo/registry/integration/RegistryDirectory$ConsumerConfigurationListener;
      15: invokevirtual #253                // Method org/apache/dubbo/registry/integration/RegistryDirectory$ConsumerConfigurationListener.getConfigurators:()Ljava/util/List;
      18: aload_1
      19: invokespecial #252                // Method overrideWithConfigurators:(Ljava/util/List;Lorg/apache/dubbo/common/URL;)Lorg/apache/dubbo/common/URL;
      22: astore_1
      23: aload_0
      24: getfield      #27                 // Field referenceConfigurationListener:Lorg/apache/dubbo/registry/integration/RegistryDirectory$ReferenceConfigurationListener;
      27: ifnull        43
      30: aload_0
      31: aload_0
      32: getfield      #27                 // Field referenceConfigurationListener:Lorg/apache/dubbo/registry/integration/RegistryDirectory$ReferenceConfigurationListener;
      35: invokevirtual #254                // Method org/apache/dubbo/registry/integration/RegistryDirectory$ReferenceConfigurationListener.getConfigurators:()Ljava/util/List;
      38: aload_1
      39: invokespecial #252                // Method overrideWithConfigurators:(Ljava/util/List;Lorg/apache/dubbo/common/URL;)Lorg/apache/dubbo/common/URL;
      42: astore_1
      43: aload_1
      44: areturn

  private org.apache.dubbo.common.URL overrideWithConfigurators(java.util.List<org.apache.dubbo.rpc.cluster.Configurator>, org.apache.dubbo.common.URL);
    Code:
       0: aload_1
       1: invokestatic  #96                 // Method org/apache/dubbo/common/utils/CollectionUtils.isNotEmpty:(Ljava/util/Collection;)Z
       4: ifeq          181
       7: aload_2
       8: instanceof    #255                // class org/apache/dubbo/common/url/component/DubboServiceAddressURL
      11: ifeq          142
      14: aload_2
      15: checkcast     #255                // class org/apache/dubbo/common/url/component/DubboServiceAddressURL
      18: astore_3
      19: aload_3
      20: invokevirtual #256                // Method org/apache/dubbo/common/url/component/DubboServiceAddressURL.getOverrideURL:()Lorg/apache/dubbo/common/url/component/ServiceConfigURL;
      23: astore        4
      25: aload         4
      27: ifnonnull     70
      30: aload_3
      31: invokevirtual #257                // Method org/apache/dubbo/common/url/component/DubboServiceAddressURL.getApplication:()Ljava/lang/String;
      34: astore        5
      36: aload_3
      37: invokevirtual #258                // Method org/apache/dubbo/common/url/component/DubboServiceAddressURL.getSide:()Ljava/lang/String;
      40: astore        6
      42: aload_3
      43: invokestatic  #259                // Method org/apache/dubbo/common/URLBuilder.from:(Lorg/apache/dubbo/common/URL;)Lorg/apache/dubbo/common/URLBuilder;
      46: invokevirtual #260                // Method org/apache/dubbo/common/URLBuilder.clearParameters:()Lorg/apache/dubbo/common/URLBuilder;
      49: ldc_w         #261                // String application
      52: aload         5
      54: invokevirtual #262                // Method org/apache/dubbo/common/URLBuilder.addParameter:(Ljava/lang/String;Ljava/lang/String;)Lorg/apache/dubbo/common/URLBuilder;
      57: ldc_w         #263                // String side
      60: aload         6
      62: invokevirtual #262                // Method org/apache/dubbo/common/URLBuilder.addParameter:(Ljava/lang/String;Ljava/lang/String;)Lorg/apache/dubbo/common/URLBuilder;
      65: invokevirtual #264                // Method org/apache/dubbo/common/URLBuilder.build:()Lorg/apache/dubbo/common/url/component/ServiceConfigURL;
      68: astore        4
      70: aload_1
      71: invokeinterface #66,  1           // InterfaceMethod java/util/List.iterator:()Ljava/util/Iterator;
      76: astore        5
      78: aload         5
      80: invokeinterface #67,  1           // InterfaceMethod java/util/Iterator.hasNext:()Z
      85: ifeq          114
      88: aload         5
      90: invokeinterface #68,  1           // InterfaceMethod java/util/Iterator.next:()Ljava/lang/Object;
      95: checkcast     #265                // class org/apache/dubbo/rpc/cluster/Configurator
      98: astore        6
     100: aload         6
     102: aload         4
     104: invokeinterface #266,  2          // InterfaceMethod org/apache/dubbo/rpc/cluster/Configurator.configure:(Lorg/apache/dubbo/common/URL;)Lorg/apache/dubbo/common/URL;
     109: astore        4
     111: goto          78
     114: new           #255                // class org/apache/dubbo/common/url/component/DubboServiceAddressURL
     117: dup
     118: aload_3
     119: invokevirtual #267                // Method org/apache/dubbo/common/url/component/DubboServiceAddressURL.getUrlAddress:()Lorg/apache/dubbo/common/url/component/URLAddress;
     122: aload_3
     123: invokevirtual #268                // Method org/apache/dubbo/common/url/component/DubboServiceAddressURL.getUrlParam:()Lorg/apache/dubbo/common/url/component/URLParam;
     126: aload_3
     127: invokevirtual #269                // Method org/apache/dubbo/common/url/component/DubboServiceAddressURL.getConsumerURL:()Lorg/apache/dubbo/common/URL;
     130: aload         4
     132: checkcast     #270                // class org/apache/dubbo/common/url/component/ServiceConfigURL
     135: invokespecial #271                // Method org/apache/dubbo/common/url/component/DubboServiceAddressURL."<init>":(Lorg/apache/dubbo/common/url/component/URLAddress;Lorg/apache/dubbo/common/url/component/URLParam;Lorg/apache/dubbo/common/URL;Lorg/apache/dubbo/common/url/component/ServiceConfigURL;)V
     138: astore_2
     139: goto          181
     142: aload_1
     143: invokeinterface #66,  1           // InterfaceMethod java/util/List.iterator:()Ljava/util/Iterator;
     148: astore_3
     149: aload_3
     150: invokeinterface #67,  1           // InterfaceMethod java/util/Iterator.hasNext:()Z
     155: ifeq          181
     158: aload_3
     159: invokeinterface #68,  1           // InterfaceMethod java/util/Iterator.next:()Ljava/lang/Object;
     164: checkcast     #265                // class org/apache/dubbo/rpc/cluster/Configurator
     167: astore        4
     169: aload         4
     171: aload_2
     172: invokeinterface #266,  2          // InterfaceMethod org/apache/dubbo/rpc/cluster/Configurator.configure:(Lorg/apache/dubbo/common/URL;)Lorg/apache/dubbo/common/URL;
     177: astore_2
     178: goto          149
     181: aload_2
     182: areturn

  protected void destroyAllInvokers();
    Code:
       0: aload_0
       1: getfield      #112                // Field urlInvokerMap:Ljava/util/Map;
       4: astore_1
       5: aload_1
       6: invokestatic  #122                // Method org/apache/dubbo/common/utils/CollectionUtils.isEmptyMap:(Ljava/util/Map;)Z
       9: ifne          122
      12: new           #93                 // class java/util/ArrayList
      15: dup
      16: aload_1
      17: invokeinterface #133,  1          // InterfaceMethod java/util/Map.values:()Ljava/util/Collection;
      22: invokespecial #134                // Method java/util/ArrayList."<init>":(Ljava/util/Collection;)V
      25: invokevirtual #272                // Method java/util/ArrayList.iterator:()Ljava/util/Iterator;
      28: astore_2
      29: aload_2
      30: invokeinterface #67,  1           // InterfaceMethod java/util/Iterator.hasNext:()Z
      35: ifeq          116
      38: aload_2
      39: invokeinterface #68,  1           // InterfaceMethod java/util/Iterator.next:()Ljava/lang/Object;
      44: checkcast     #161                // class org/apache/dubbo/rpc/Invoker
      47: astore_3
      48: aload_3
      49: invokeinterface #273,  1          // InterfaceMethod org/apache/dubbo/rpc/Invoker.destroy:()V
      54: goto          113
      57: astore        4
      59: getstatic     #97                 // Field logger:Lorg/apache/dubbo/common/logger/ErrorTypeAwareLogger;
      62: ldc           #144                // String 1-15
      64: ldc           #75                 // String
      66: ldc           #75                 // String
      68: new           #100                // class java/lang/StringBuilder
      71: dup
      72: invokespecial #101                // Method java/lang/StringBuilder."<init>":()V
      75: ldc_w         #274                // String Failed to destroy service
      78: invokevirtual #103                // Method java/lang/StringBuilder.append:(Ljava/lang/String;)Ljava/lang/StringBuilder;
      81: aload_0
      82: getfield      #104                // Field serviceKey:Ljava/lang/String;
      85: invokevirtual #103                // Method java/lang/StringBuilder.append:(Ljava/lang/String;)Ljava/lang/StringBuilder;
      88: ldc_w         #275                // String  to provider
      91: invokevirtual #103                // Method java/lang/StringBuilder.append:(Ljava/lang/String;)Ljava/lang/StringBuilder;
      94: aload_3
      95: invokeinterface #162,  1          // InterfaceMethod org/apache/dubbo/rpc/Invoker.getUrl:()Lorg/apache/dubbo/common/URL;
     100: invokevirtual #185                // Method java/lang/StringBuilder.append:(Ljava/lang/Object;)Ljava/lang/StringBuilder;
     103: invokevirtual #106                // Method java/lang/StringBuilder.toString:()Ljava/lang/String;
     106: aload         4
     108: invokeinterface #146,  6          // InterfaceMethod org/apache/dubbo/common/logger/ErrorTypeAwareLogger.warn:(Ljava/lang/String;Ljava/lang/String;Ljava/lang/String;Ljava/lang/String;Ljava/lang/Throwable;)V
     113: goto          29
     116: aload_1
     117: invokeinterface #276,  1          // InterfaceMethod java/util/Map.clear:()V
     122: aload_0
     123: aconst_null
     124: putfield      #112                // Field urlInvokerMap:Ljava/util/Map;
     127: aload_0
     128: aconst_null
     129: putfield      #95                 // Field cachedInvokerUrls:Ljava/util/Set;
     132: aload_0
     133: invokevirtual #277                // Method destroyInvokers:()V
     136: return
    Exception table:
       from    to  target type
          48    54    57   Class java/lang/Throwable

  private void destroyUnusedInvokers(java.util.Map<org.apache.dubbo.common.URL, org.apache.dubbo.rpc.Invoker<T>>, java.util.Map<org.apache.dubbo.common.URL, org.apache.dubbo.rpc.Invoker<T>>);
    Code:
       0: aload_2
       1: invokestatic  #122                // Method org/apache/dubbo/common/utils/CollectionUtils.isEmptyMap:(Ljava/util/Map;)Z
       4: ifeq          12
       7: aload_0
       8: invokevirtual #91                 // Method destroyAllInvokers:()V
      11: return
      12: aload_1
      13: invokestatic  #122                // Method org/apache/dubbo/common/utils/CollectionUtils.isEmptyMap:(Ljava/util/Map;)Z
      16: ifeq          20
      19: return
      20: aload_1
      21: invokeinterface #278,  1          // InterfaceMethod java/util/Map.entrySet:()Ljava/util/Set;
      26: invokeinterface #279,  1          // InterfaceMethod java/util/Set.iterator:()Ljava/util/Iterator;
      31: astore_3
      32: aload_3
      33: invokeinterface #67,  1           // InterfaceMethod java/util/Iterator.hasNext:()Z
      38: ifeq          191
      41: aload_3
      42: invokeinterface #68,  1           // InterfaceMethod java/util/Iterator.next:()Ljava/lang/Object;
      47: checkcast     #280                // class java/util/Map$Entry
      50: astore        4
      52: aload         4
      54: invokeinterface #281,  1          // InterfaceMethod java/util/Map$Entry.getValue:()Ljava/lang/Object;
      59: checkcast     #161                // class org/apache/dubbo/rpc/Invoker
      62: astore        5
      64: aload         5
      66: ifnull        188
      69: aload         5
      71: invokeinterface #273,  1          // InterfaceMethod org/apache/dubbo/rpc/Invoker.destroy:()V
      76: getstatic     #97                 // Field logger:Lorg/apache/dubbo/common/logger/ErrorTypeAwareLogger;
      79: invokeinterface #282,  1          // InterfaceMethod org/apache/dubbo/common/logger/ErrorTypeAwareLogger.isDebugEnabled:()Z
      84: ifeq          127
      87: getstatic     #97                 // Field logger:Lorg/apache/dubbo/common/logger/ErrorTypeAwareLogger;
      90: new           #100                // class java/lang/StringBuilder
      93: dup
      94: invokespecial #101                // Method java/lang/StringBuilder."<init>":()V
      97: ldc_w         #283                // String destroy invoker[
     100: invokevirtual #103                // Method java/lang/StringBuilder.append:(Ljava/lang/String;)Ljava/lang/StringBuilder;
     103: aload         5
     105: invokeinterface #162,  1          // InterfaceMethod org/apache/dubbo/rpc/Invoker.getUrl:()Lorg/apache/dubbo/common/URL;
     110: invokevirtual #185                // Method java/lang/StringBuilder.append:(Ljava/lang/Object;)Ljava/lang/StringBuilder;
     113: ldc_w         #284                // String ] success.
     116: invokevirtual #103                // Method java/lang/StringBuilder.append:(Ljava/lang/String;)Ljava/lang/StringBuilder;
     119: invokevirtual #106                // Method java/lang/StringBuilder.toString:()Ljava/lang/String;
     122: invokeinterface #285,  2          // InterfaceMethod org/apache/dubbo/common/logger/ErrorTypeAwareLogger.debug:(Ljava/lang/String;)V
     127: goto          188
     130: astore        6
     132: getstatic     #97                 // Field logger:Lorg/apache/dubbo/common/logger/ErrorTypeAwareLogger;
     135: ldc           #144                // String 1-15
     137: ldc           #75                 // String
     139: ldc           #75                 // String
     141: new           #100                // class java/lang/StringBuilder
     144: dup
     145: invokespecial #101                // Method java/lang/StringBuilder."<init>":()V
     148: ldc_w         #283                // String destroy invoker[
     151: invokevirtual #103                // Method java/lang/StringBuilder.append:(Ljava/lang/String;)Ljava/lang/StringBuilder;
     154: aload         5
     156: invokeinterface #162,  1          // InterfaceMethod org/apache/dubbo/rpc/Invoker.getUrl:()Lorg/apache/dubbo/common/URL;
     161: invokevirtual #185                // Method java/lang/StringBuilder.append:(Ljava/lang/Object;)Ljava/lang/StringBuilder;
     164: ldc_w         #286                // String ] failed.
     167: invokevirtual #103                // Method java/lang/StringBuilder.append:(Ljava/lang/String;)Ljava/lang/StringBuilder;
     170: aload         6
     172: invokevirtual #287                // Method java/lang/Exception.getMessage:()Ljava/lang/String;
     175: invokevirtual #103                // Method java/lang/StringBuilder.append:(Ljava/lang/String;)Ljava/lang/StringBuilder;
     178: invokevirtual #106                // Method java/lang/StringBuilder.toString:()Ljava/lang/String;
     181: aload         6
     183: invokeinterface #146,  6          // InterfaceMethod org/apache/dubbo/common/logger/ErrorTypeAwareLogger.warn:(Ljava/lang/String;Ljava/lang/String;Ljava/lang/String;Ljava/lang/String;Ljava/lang/Throwable;)V
     188: goto          32
     191: getstatic     #97                 // Field logger:Lorg/apache/dubbo/common/logger/ErrorTypeAwareLogger;
     194: new           #100                // class java/lang/StringBuilder
     197: dup
     198: invokespecial #101                // Method java/lang/StringBuilder."<init>":()V
     201: ldc_w         #288                // String New url total size,
     204: invokevirtual #103                // Method java/lang/StringBuilder.append:(Ljava/lang/String;)Ljava/lang/StringBuilder;
     207: aload_2
     208: invokeinterface #114,  1          // InterfaceMethod java/util/Map.size:()I
     213: invokevirtual #128                // Method java/lang/StringBuilder.append:(I)Ljava/lang/StringBuilder;
     216: ldc_w         #289                // String , destroyed total size
     219: invokevirtual #103                // Method java/lang/StringBuilder.append:(Ljava/lang/String;)Ljava/lang/StringBuilder;
     222: aload_1
     223: invokeinterface #114,  1          // InterfaceMethod java/util/Map.size:()I
     228: invokevirtual #128                // Method java/lang/StringBuilder.append:(I)Ljava/lang/StringBuilder;
     231: invokevirtual #106                // Method java/lang/StringBuilder.toString:()Ljava/lang/String;
     234: invokeinterface #158,  2          // InterfaceMethod org/apache/dubbo/common/logger/ErrorTypeAwareLogger.info:(Ljava/lang/String;)V
     239: return
    Exception table:
       from    to  target type
          69   127   130   Class java/lang/Exception

  public java.util.Map<org.apache.dubbo.common.URL, org.apache.dubbo.rpc.Invoker<T>> getUrlInvokerMap();
    Code:
       0: aload_0
       1: getfield      #112                // Field urlInvokerMap:Ljava/util/Map;
       4: areturn

  private boolean isValidCategory(org.apache.dubbo.common.URL);
    Code:
       0: aload_1
       1: ldc           #58                 // String providers
       3: invokevirtual #290                // Method org/apache/dubbo/common/URL.getCategory:(Ljava/lang/String;)Ljava/lang/String;
       6: astore_2
       7: ldc           #54                 // String routers
       9: aload_2
      10: invokevirtual #87                 // Method java/lang/String.equals:(Ljava/lang/Object;)Z
      13: ifne          67
      16: ldc_w         #291                // String route
      19: aload_1
      20: invokevirtual #86                 // Method org/apache/dubbo/common/URL.getProtocol:()Ljava/lang/String;
      23: invokevirtual #87                 // Method java/lang/String.equals:(Ljava/lang/Object;)Z
      26: ifne          67
      29: ldc           #58                 // String providers
      31: aload_2
      32: invokevirtual #87                 // Method java/lang/String.equals:(Ljava/lang/Object;)Z
      35: ifne          67
      38: ldc           #47                 // String configurators
      40: aload_2
      41: invokevirtual #87                 // Method java/lang/String.equals:(Ljava/lang/Object;)Z
      44: ifne          67
      47: ldc_w         #292                // String dynamicconfigurators
      50: aload_2
      51: invokevirtual #87                 // Method java/lang/String.equals:(Ljava/lang/Object;)Z
      54: ifne          67
      57: ldc_w         #293                // String appdynamicconfigurators
      60: aload_2
      61: invokevirtual #87                 // Method java/lang/String.equals:(Ljava/lang/Object;)Z
      64: ifeq          69
      67: iconst_1
      68: ireturn
      69: getstatic     #97                 // Field logger:Lorg/apache/dubbo/common/logger/ErrorTypeAwareLogger;
      72: ldc_w         #294                // String 1-16
      75: ldc           #75                 // String
      77: ldc           #75                 // String
      79: new           #100                // class java/lang/StringBuilder
      82: dup
      83: invokespecial #101                // Method java/lang/StringBuilder."<init>":()V
      86: ldc_w         #295                // String Unsupported category
      89: invokevirtual #103                // Method java/lang/StringBuilder.append:(Ljava/lang/String;)Ljava/lang/StringBuilder;
      92: aload_2
      93: invokevirtual #103                // Method java/lang/StringBuilder.append:(Ljava/lang/String;)Ljava/lang/StringBuilder;
      96: ldc           #223                // String  in notified url:
      98: invokevirtual #103                // Method java/lang/StringBuilder.append:(Ljava/lang/String;)Ljava/lang/StringBuilder;
     101: aload_1
     102: invokevirtual #185                // Method java/lang/StringBuilder.append:(Ljava/lang/Object;)Ljava/lang/StringBuilder;
     105: ldc           #224                // String  from registry
     107: invokevirtual #103                // Method java/lang/StringBuilder.append:(Ljava/lang/String;)Ljava/lang/StringBuilder;
     110: aload_0
     111: invokevirtual #59                 // Method getUrl:()Lorg/apache/dubbo/common/URL;
     114: invokevirtual #225                // Method org/apache/dubbo/common/URL.getAddress:()Ljava/lang/String;
     117: invokevirtual #103                // Method java/lang/StringBuilder.append:(Ljava/lang/String;)Ljava/lang/StringBuilder;
     120: ldc           #226                // String  to consumer
     122: invokevirtual #103                // Method java/lang/StringBuilder.append:(Ljava/lang/String;)Ljava/lang/StringBuilder;
     125: invokestatic  #227                // Method org/apache/dubbo/common/utils/NetUtils.getLocalHost:()Ljava/lang/String;
     128: invokevirtual #103                // Method java/lang/StringBuilder.append:(Ljava/lang/String;)Ljava/lang/StringBuilder;
     131: invokevirtual #106                // Method java/lang/StringBuilder.toString:()Ljava/lang/String;
     134: invokeinterface #107,  5          // InterfaceMethod org/apache/dubbo/common/logger/ErrorTypeAwareLogger.warn:(Ljava/lang/String;Ljava/lang/String;Ljava/lang/String;Ljava/lang/String;)V
     139: iconst_0
     140: ireturn

  private boolean isNotCompatibleFor26x(org.apache.dubbo.common.URL);
    Code:
       0: aload_1
       1: ldc_w         #296                // String compatible_config
       4: invokevirtual #177                // Method org/apache/dubbo/common/URL.getParameter:(Ljava/lang/String;)Ljava/lang/String;
       7: invokestatic  #297                // Method org/apache/dubbo/common/utils/StringUtils.isEmpty:(Ljava/lang/String;)Z
      10: ireturn

  private static java.util.List lambda$toMergeInvokerList$4(java.lang.String);
    Code:
       0: new           #93                 // class java/util/ArrayList
       3: dup
       4: invokespecial #94                 // Method java/util/ArrayList."<init>":()V
       7: areturn

  private void lambda$refreshInvoker$3(org.apache.dubbo.rpc.cluster.router.state.BitList);
    Code:
       0: aload_0
       1: aload_1
       2: invokevirtual #298                // Method setInvokers:(Lorg/apache/dubbo/rpc/cluster/router/state/BitList;)V
       5: return

  private void lambda$refreshInvoker$2();
    Code:
       0: aload_0
       1: iconst_1
       2: putfield      #92                 // Field forbidden:Z
       5: return

  private static org.apache.dubbo.registry.integration.RegistryDirectory$ConsumerConfigurationListener lambda$getConsumerConfigurationListener$1(org.apache.dubbo.rpc.model.ModuleModel, java.lang.Class);
    Code:
       0: new           #29                 // class org/apache/dubbo/registry/integration/RegistryDirectory$ConsumerConfigurationListener
       3: dup
       4: aload_0
       5: invokespecial #299                // Method org/apache/dubbo/registry/integration/RegistryDirectory$ConsumerConfigurationListener."<init>":(Lorg/apache/dubbo/rpc/model/ModuleModel;)V
       8: areturn

  private java.lang.Object lambda$subscribe$0(org.apache.dubbo.common.URL);
    Code:
       0: aload_0
       1: aload_1
       2: invokespecial #300                // Method org/apache/dubbo/registry/integration/DynamicDirectory.subscribe:(Lorg/apache/dubbo/common/URL;)V
       5: aconst_null
       6: areturn

  static {};
    Code:
       0: ldc_w         #301                // class org/apache/dubbo/registry/integration/RegistryDirectory
       3: invokestatic  #302                // Method org/apache/dubbo/common/logger/LoggerFactory.getErrorTypeAwareLogger:(Ljava/lang/Class;)Lorg/apache/dubbo/common/logger/ErrorTypeAwareLogger;
       6: putstatic     #97                 // Field logger:Lorg/apache/dubbo/common/logger/ErrorTypeAwareLogger;
       9: return
}
