Compiled from "RegistryProtocol.java"
class org.apache.dubbo.registry.integration.RegistryProtocol$ExporterChangeableWrapper<T> implements org.apache.dubbo.rpc.Exporter<T> {
  private final java.util.concurrent.ScheduledExecutorService executor;

  private final org.apache.dubbo.rpc.Invoker<T> originInvoker;

  private org.apache.dubbo.rpc.Exporter<T> exporter;

  private org.apache.dubbo.common.URL subscribeUrl;

  private org.apache.dubbo.common.URL registerUrl;

  private org.apache.dubbo.registry.NotifyListener notifyListener;

  private final java.util.concurrent.atomic.AtomicBoolean unregistered;

  final org.apache.dubbo.registry.integration.RegistryProtocol this$0;

  public org.apache.dubbo.registry.integration.RegistryProtocol$ExporterChangeableWrapper(org.apache.dubbo.rpc.Exporter<T>, org.apache.dubbo.rpc.Invoker<T>);
    Code:
       0: aload_0
       1: aload_1
       2: putfield      #3                  // Field this$0:Lorg/apache/dubbo/registry/integration/RegistryProtocol;
       5: aload_0
       6: invokespecial #4                  // Method java/lang/Object."<init>":()V
       9: aload_0
      10: new           #5                  // class java/util/concurrent/atomic/AtomicBoolean
      13: dup
      14: iconst_0
      15: invokespecial #6                  // Method java/util/concurrent/atomic/AtomicBoolean."<init>":(Z)V
      18: putfield      #7                  // Field unregistered:Ljava/util/concurrent/atomic/AtomicBoolean;
      21: aload_0
      22: aload_2
      23: putfield      #8                  // Field exporter:Lorg/apache/dubbo/rpc/Exporter;
      26: aload_0
      27: aload_3
      28: putfield      #9                  // Field originInvoker:Lorg/apache/dubbo/rpc/Invoker;
      31: aload_3
      32: invokeinterface #10,  1           // InterfaceMethod org/apache/dubbo/rpc/Invoker.getUrl:()Lorg/apache/dubbo/common/URL;
      37: invokevirtual #11                 // Method org/apache/dubbo/common/URL.getOrDefaultFrameworkModel:()Lorg/apache/dubbo/rpc/model/FrameworkModel;
      40: invokevirtual #12                 // Method org/apache/dubbo/rpc/model/FrameworkModel.getBeanFactory:()Lorg/apache/dubbo/common/beans/factory/ScopeBeanFactory;
      43: ldc           #13                 // class org/apache/dubbo/common/threadpool/manager/FrameworkExecutorRepository
      45: invokevirtual #14                 // Method org/apache/dubbo/common/beans/factory/ScopeBeanFactory.getBean:(Ljava/lang/Class;)Ljava/lang/Object;
      48: checkcast     #13                 // class org/apache/dubbo/common/threadpool/manager/FrameworkExecutorRepository
      51: astore        4
      53: aload_0
      54: aload         4
      56: invokevirtual #15                 // Method org/apache/dubbo/common/threadpool/manager/FrameworkExecutorRepository.getSharedScheduledExecutor:()Ljava/util/concurrent/ScheduledExecutorService;
      59: putfield      #16                 // Field executor:Ljava/util/concurrent/ScheduledExecutorService;
      62: return

  public org.apache.dubbo.rpc.Invoker<T> getOriginInvoker();
    Code:
       0: aload_0
       1: getfield      #9                  // Field originInvoker:Lorg/apache/dubbo/rpc/Invoker;
       4: areturn

  public org.apache.dubbo.rpc.Invoker<T> getInvoker();
    Code:
       0: aload_0
       1: getfield      #8                  // Field exporter:Lorg/apache/dubbo/rpc/Exporter;
       4: invokeinterface #17,  1           // InterfaceMethod org/apache/dubbo/rpc/Exporter.getInvoker:()Lorg/apache/dubbo/rpc/Invoker;
       9: areturn

  public void setExporter(org.apache.dubbo.rpc.Exporter<T>);
    Code:
       0: aload_0
       1: aload_1
       2: putfield      #8                  // Field exporter:Lorg/apache/dubbo/rpc/Exporter;
       5: return

  public synchronized void unregister();
    Code:
       0: aload_0
       1: getfield      #7                  // Field unregistered:Ljava/util/concurrent/atomic/AtomicBoolean;
       4: iconst_0
       5: iconst_1
       6: invokevirtual #18                 // Method java/util/concurrent/atomic/AtomicBoolean.compareAndSet:(ZZ)Z
       9: ifeq          369
      12: aload_0
      13: getfield      #3                  // Field this$0:Lorg/apache/dubbo/registry/integration/RegistryProtocol;
      16: aload_0
      17: getfield      #3                  // Field this$0:Lorg/apache/dubbo/registry/integration/RegistryProtocol;
      20: aload_0
      21: getfield      #9                  // Field originInvoker:Lorg/apache/dubbo/rpc/Invoker;
      24: invokevirtual #19                 // Method org/apache/dubbo/registry/integration/RegistryProtocol.getRegistryUrl:(Lorg/apache/dubbo/rpc/Invoker;)Lorg/apache/dubbo/common/URL;
      27: invokevirtual #20                 // Method org/apache/dubbo/registry/integration/RegistryProtocol.getRegistry:(Lorg/apache/dubbo/common/URL;)Lorg/apache/dubbo/registry/Registry;
      30: astore_1
      31: aload_1
      32: aload_0
      33: getfield      #21                 // Field registerUrl:Lorg/apache/dubbo/common/URL;
      36: invokeinterface #22,  2           // InterfaceMethod org/apache/dubbo/registry/Registry.unregister:(Lorg/apache/dubbo/common/URL;)V
      41: goto          64
      44: astore_2
      45: invokestatic  #24                 // Method org/apache/dubbo/registry/integration/RegistryProtocol.access$200:()Lorg/apache/dubbo/common/logger/ErrorTypeAwareLogger;
      48: ldc           #25                 // String 99-0
      50: ldc           #26                 // String unknown error in registry module
      52: ldc           #27                 // String
      54: aload_2
      55: invokevirtual #28                 // Method java/lang/Throwable.getMessage:()Ljava/lang/String;
      58: aload_2
      59: invokeinterface #29,  6           // InterfaceMethod org/apache/dubbo/common/logger/ErrorTypeAwareLogger.warn:(Ljava/lang/String;Ljava/lang/String;Ljava/lang/String;Ljava/lang/String;Ljava/lang/Throwable;)V
      64: aload_0
      65: getfield      #30                 // Field subscribeUrl:Lorg/apache/dubbo/common/URL;
      68: ifnull        346
      71: aload_0
      72: getfield      #3                  // Field this$0:Lorg/apache/dubbo/registry/integration/RegistryProtocol;
      75: aload_0
      76: getfield      #30                 // Field subscribeUrl:Lorg/apache/dubbo/common/URL;
      79: invokestatic  #31                 // Method org/apache/dubbo/registry/integration/RegistryProtocol.access$700:(Lorg/apache/dubbo/registry/integration/RegistryProtocol;Lorg/apache/dubbo/common/URL;)Lorg/apache/dubbo/registry/integration/RegistryProtocol$ProviderConfigurationListener;
      82: invokevirtual #32                 // Method org/apache/dubbo/registry/integration/RegistryProtocol$ProviderConfigurationListener.getOverrideListeners:()Ljava/util/Map;
      85: astore_2
      86: aload_2
      87: aload_0
      88: getfield      #30                 // Field subscribeUrl:Lorg/apache/dubbo/common/URL;
      91: invokeinterface #33,  2           // InterfaceMethod java/util/Map.get:(Ljava/lang/Object;)Ljava/lang/Object;
      96: checkcast     #34                 // class java/util/Set
      99: astore_3
     100: aload_3
     101: ifnull        346
     104: aload_3
     105: aload_0
     106: getfield      #35                 // Field notifyListener:Lorg/apache/dubbo/registry/NotifyListener;
     109: invokeinterface #36,  2           // InterfaceMethod java/util/Set.remove:(Ljava/lang/Object;)Z
     114: ifeq          326
     117: aload_0
     118: getfield      #21                 // Field registerUrl:Lorg/apache/dubbo/common/URL;
     121: invokevirtual #37                 // Method org/apache/dubbo/common/URL.getScopeModel:()Lorg/apache/dubbo/rpc/model/ScopeModel;
     124: invokestatic  #38                 // Method org/apache/dubbo/rpc/model/ScopeModelUtil.getApplicationModel:(Lorg/apache/dubbo/rpc/model/ScopeModel;)Lorg/apache/dubbo/rpc/model/ApplicationModel;
     127: astore        4
     129: aload         4
     131: invokevirtual #39                 // Method org/apache/dubbo/rpc/model/ApplicationModel.getModelEnvironment:()Lorg/apache/dubbo/common/config/Environment;
     134: invokevirtual #40                 // Method org/apache/dubbo/common/config/Environment.getConfiguration:()Lorg/apache/dubbo/common/config/CompositeConfiguration;
     137: ldc           #41                 // class java/lang/Boolean
     139: ldc           #42                 // String enable-26x-configuration-listen
     141: iconst_1
     142: invokestatic  #43                 // Method java/lang/Boolean.valueOf:(Z)Ljava/lang/Boolean;
     145: invokevirtual #44                 // Method org/apache/dubbo/common/config/CompositeConfiguration.convert:(Ljava/lang/Class;Ljava/lang/String;Ljava/lang/Object;)Ljava/lang/Object;
     148: checkcast     #41                 // class java/lang/Boolean
     151: invokevirtual #45                 // Method java/lang/Boolean.booleanValue:()Z
     154: ifeq          180
     157: aload_1
     158: invokeinterface #46,  1           // InterfaceMethod org/apache/dubbo/registry/Registry.isServiceDiscovery:()Z
     163: ifne          180
     166: aload_1
     167: aload_0
     168: getfield      #30                 // Field subscribeUrl:Lorg/apache/dubbo/common/URL;
     171: aload_0
     172: getfield      #35                 // Field notifyListener:Lorg/apache/dubbo/registry/NotifyListener;
     175: invokeinterface #47,  3           // InterfaceMethod org/apache/dubbo/registry/Registry.unsubscribe:(Lorg/apache/dubbo/common/URL;Lorg/apache/dubbo/registry/NotifyListener;)V
     180: aload         4
     182: invokevirtual #39                 // Method org/apache/dubbo/rpc/model/ApplicationModel.getModelEnvironment:()Lorg/apache/dubbo/common/config/Environment;
     185: invokevirtual #40                 // Method org/apache/dubbo/common/config/Environment.getConfiguration:()Lorg/apache/dubbo/common/config/CompositeConfiguration;
     188: ldc           #41                 // class java/lang/Boolean
     190: ldc           #48                 // String enable-configuration-listen
     192: iconst_1
     193: invokestatic  #43                 // Method java/lang/Boolean.valueOf:(Z)Ljava/lang/Boolean;
     196: invokevirtual #44                 // Method org/apache/dubbo/common/config/CompositeConfiguration.convert:(Ljava/lang/Class;Ljava/lang/String;Ljava/lang/Object;)Ljava/lang/Object;
     199: checkcast     #41                 // class java/lang/Boolean
     202: invokevirtual #45                 // Method java/lang/Boolean.booleanValue:()Z
     205: ifeq          326
     208: aload         4
     210: invokevirtual #49                 // Method org/apache/dubbo/rpc/model/ApplicationModel.getPubModuleModels:()Ljava/util/List;
     213: invokeinterface #50,  1           // InterfaceMethod java/util/List.iterator:()Ljava/util/Iterator;
     218: astore        5
     220: aload         5
     222: invokeinterface #51,  1           // InterfaceMethod java/util/Iterator.hasNext:()Z
     227: ifeq          326
     230: aload         5
     232: invokeinterface #52,  1           // InterfaceMethod java/util/Iterator.next:()Ljava/lang/Object;
     237: checkcast     #53                 // class org/apache/dubbo/rpc/model/ModuleModel
     240: astore        6
     242: aload         6
     244: invokevirtual #54                 // Method org/apache/dubbo/rpc/model/ModuleModel.getServiceRepository:()Lorg/apache/dubbo/rpc/model/ModuleServiceRepository;
     247: invokevirtual #55                 // Method org/apache/dubbo/rpc/model/ModuleServiceRepository.getExportedServices:()Ljava/util/List;
     250: invokeinterface #56,  1           // InterfaceMethod java/util/List.size:()I
     255: ifle          323
     258: aload         6
     260: ldc           #57                 // class org/apache/dubbo/rpc/cluster/governance/GovernanceRuleRepository
     262: invokevirtual #58                 // Method org/apache/dubbo/rpc/model/ModuleModel.getExtensionLoader:(Ljava/lang/Class;)Lorg/apache/dubbo/common/extension/ExtensionLoader;
     265: invokevirtual #59                 // Method org/apache/dubbo/common/extension/ExtensionLoader.getDefaultExtension:()Ljava/lang/Object;
     268: checkcast     #57                 // class org/apache/dubbo/rpc/cluster/governance/GovernanceRuleRepository
     271: new           #60                 // class java/lang/StringBuilder
     274: dup
     275: invokespecial #61                 // Method java/lang/StringBuilder."<init>":()V
     278: aload_0
     279: getfield      #30                 // Field subscribeUrl:Lorg/apache/dubbo/common/URL;
     282: invokevirtual #62                 // Method org/apache/dubbo/common/URL.getServiceKey:()Ljava/lang/String;
     285: invokevirtual #63                 // Method java/lang/StringBuilder.append:(Ljava/lang/String;)Ljava/lang/StringBuilder;
     288: ldc           #64                 // String .configurators
     290: invokevirtual #63                 // Method java/lang/StringBuilder.append:(Ljava/lang/String;)Ljava/lang/StringBuilder;
     293: invokevirtual #65                 // Method java/lang/StringBuilder.toString:()Ljava/lang/String;
     296: aload_0
     297: getfield      #3                  // Field this$0:Lorg/apache/dubbo/registry/integration/RegistryProtocol;
     300: invokestatic  #66                 // Method org/apache/dubbo/registry/integration/RegistryProtocol.access$800:(Lorg/apache/dubbo/registry/integration/RegistryProtocol;)Ljava/util/Map;
     303: aload_0
     304: getfield      #30                 // Field subscribeUrl:Lorg/apache/dubbo/common/URL;
     307: invokevirtual #62                 // Method org/apache/dubbo/common/URL.getServiceKey:()Ljava/lang/String;
     310: invokeinterface #67,  2           // InterfaceMethod java/util/Map.remove:(Ljava/lang/Object;)Ljava/lang/Object;
     315: checkcast     #68                 // class org/apache/dubbo/common/config/configcenter/ConfigurationListener
     318: invokeinterface #69,  3           // InterfaceMethod org/apache/dubbo/rpc/cluster/governance/GovernanceRuleRepository.removeListener:(Ljava/lang/String;Lorg/apache/dubbo/common/config/configcenter/ConfigurationListener;)V
     323: goto          220
     326: aload_3
     327: invokeinterface #70,  1           // InterfaceMethod java/util/Set.isEmpty:()Z
     332: ifeq          346
     335: aload_2
     336: aload_0
     337: getfield      #30                 // Field subscribeUrl:Lorg/apache/dubbo/common/URL;
     340: invokeinterface #67,  2           // InterfaceMethod java/util/Map.remove:(Ljava/lang/Object;)Ljava/lang/Object;
     345: pop
     346: goto          369
     349: astore_2
     350: invokestatic  #24                 // Method org/apache/dubbo/registry/integration/RegistryProtocol.access$200:()Lorg/apache/dubbo/common/logger/ErrorTypeAwareLogger;
     353: ldc           #25                 // String 99-0
     355: ldc           #26                 // String unknown error in registry module
     357: ldc           #27                 // String
     359: aload_2
     360: invokevirtual #28                 // Method java/lang/Throwable.getMessage:()Ljava/lang/String;
     363: aload_2
     364: invokeinterface #29,  6           // InterfaceMethod org/apache/dubbo/common/logger/ErrorTypeAwareLogger.warn:(Ljava/lang/String;Ljava/lang/String;Ljava/lang/String;Ljava/lang/String;Ljava/lang/Throwable;)V
     369: return
    Exception table:
       from    to  target type
          31    41    44   Class java/lang/Throwable
          64   346   349   Class java/lang/Throwable

  public synchronized void unexport();
    Code:
       0: aload_0
       1: getfield      #3                  // Field this$0:Lorg/apache/dubbo/registry/integration/RegistryProtocol;
       4: aload_0
       5: getfield      #9                  // Field originInvoker:Lorg/apache/dubbo/rpc/Invoker;
       8: invokestatic  #71                 // Method org/apache/dubbo/registry/integration/RegistryProtocol.access$400:(Lorg/apache/dubbo/registry/integration/RegistryProtocol;Lorg/apache/dubbo/rpc/Invoker;)Ljava/lang/String;
      11: astore_1
      12: aload_0
      13: getfield      #3                  // Field this$0:Lorg/apache/dubbo/registry/integration/RegistryProtocol;
      16: invokestatic  #72                 // Method org/apache/dubbo/registry/integration/RegistryProtocol.access$500:(Lorg/apache/dubbo/registry/integration/RegistryProtocol;)Ljava/util/concurrent/ConcurrentMap;
      19: aload_1
      20: invokeinterface #73,  2           // InterfaceMethod java/util/concurrent/ConcurrentMap.remove:(Ljava/lang/Object;)Ljava/lang/Object;
      25: pop
      26: aload_0
      27: invokevirtual #74                 // Method unregister:()V
      30: aload_0
      31: invokespecial #75                 // Method doUnExport:()V
      34: return

  private void doUnExport();
    Code:
       0: aload_0
       1: getfield      #8                  // Field exporter:Lorg/apache/dubbo/rpc/Exporter;
       4: invokeinterface #76,  1           // InterfaceMethod org/apache/dubbo/rpc/Exporter.unexport:()V
       9: goto          32
      12: astore_1
      13: invokestatic  #24                 // Method org/apache/dubbo/registry/integration/RegistryProtocol.access$200:()Lorg/apache/dubbo/common/logger/ErrorTypeAwareLogger;
      16: ldc           #25                 // String 99-0
      18: ldc           #26                 // String unknown error in registry module
      20: ldc           #27                 // String
      22: aload_1
      23: invokevirtual #28                 // Method java/lang/Throwable.getMessage:()Ljava/lang/String;
      26: aload_1
      27: invokeinterface #29,  6           // InterfaceMethod org/apache/dubbo/common/logger/ErrorTypeAwareLogger.warn:(Ljava/lang/String;Ljava/lang/String;Ljava/lang/String;Ljava/lang/String;Ljava/lang/Throwable;)V
      32: return
    Exception table:
       from    to  target type
           0     9    12   Class java/lang/Throwable

  public void setSubscribeUrl(org.apache.dubbo.common.URL);
    Code:
       0: aload_0
       1: aload_1
       2: putfield      #30                 // Field subscribeUrl:Lorg/apache/dubbo/common/URL;
       5: return

  public void setRegisterUrl(org.apache.dubbo.common.URL);
    Code:
       0: aload_0
       1: aload_1
       2: putfield      #21                 // Field registerUrl:Lorg/apache/dubbo/common/URL;
       5: return

  public void setNotifyListener(org.apache.dubbo.registry.NotifyListener);
    Code:
       0: aload_0
       1: aload_1
       2: putfield      #35                 // Field notifyListener:Lorg/apache/dubbo/registry/NotifyListener;
       5: return

  public org.apache.dubbo.common.URL getRegisterUrl();
    Code:
       0: aload_0
       1: getfield      #21                 // Field registerUrl:Lorg/apache/dubbo/common/URL;
       4: areturn
}
