Compiled from "RegistryProtocol.java"
class org.apache.dubbo.registry.integration.RegistryProtocol$OverrideListener implements org.apache.dubbo.registry.NotifyListener {
  private final org.apache.dubbo.common.URL subscribeUrl;

  private final org.apache.dubbo.rpc.Invoker originInvoker;

  private java.util.List<org.apache.dubbo.rpc.cluster.Configurator> configurators;

  final org.apache.dubbo.registry.integration.RegistryProtocol this$0;

  public org.apache.dubbo.registry.integration.RegistryProtocol$OverrideListener(org.apache.dubbo.registry.integration.RegistryProtocol, org.apache.dubbo.common.URL, org.apache.dubbo.rpc.Invoker);
    Code:
       0: aload_0
       1: aload_1
       2: putfield      #3                  // Field this$0:Lorg/apache/dubbo/registry/integration/RegistryProtocol;
       5: aload_0
       6: invokespecial #4                  // Method java/lang/Object."<init>":()V
       9: aload_0
      10: aload_2
      11: putfield      #5                  // Field subscribeUrl:Lorg/apache/dubbo/common/URL;
      14: aload_0
      15: aload_3
      16: putfield      #6                  // Field originInvoker:Lorg/apache/dubbo/rpc/Invoker;
      19: return

  public synchronized void notify(java.util.List<org.apache.dubbo.common.URL>);
    Code:
       0: invokestatic  #7                  // Method org/apache/dubbo/registry/integration/RegistryProtocol.access$200:()Lorg/apache/dubbo/common/logger/ErrorTypeAwareLogger;
       3: invokeinterface #8,  1            // InterfaceMethod org/apache/dubbo/common/logger/ErrorTypeAwareLogger.isDebugEnabled:()Z
       8: ifeq          38
      11: invokestatic  #7                  // Method org/apache/dubbo/registry/integration/RegistryProtocol.access$200:()Lorg/apache/dubbo/common/logger/ErrorTypeAwareLogger;
      14: new           #9                  // class java/lang/StringBuilder
      17: dup
      18: invokespecial #10                 // Method java/lang/StringBuilder."<init>":()V
      21: ldc           #11                 // String original override urls:
      23: invokevirtual #12                 // Method java/lang/StringBuilder.append:(Ljava/lang/String;)Ljava/lang/StringBuilder;
      26: aload_1
      27: invokevirtual #13                 // Method java/lang/StringBuilder.append:(Ljava/lang/Object;)Ljava/lang/StringBuilder;
      30: invokevirtual #14                 // Method java/lang/StringBuilder.toString:()Ljava/lang/String;
      33: invokeinterface #15,  2           // InterfaceMethod org/apache/dubbo/common/logger/ErrorTypeAwareLogger.debug:(Ljava/lang/String;)V
      38: aload_0
      39: aload_1
      40: aload_0
      41: getfield      #5                  // Field subscribeUrl:Lorg/apache/dubbo/common/URL;
      44: invokespecial #16                 // Method getMatchedUrls:(Ljava/util/List;Lorg/apache/dubbo/common/URL;)Ljava/util/List;
      47: astore_2
      48: invokestatic  #7                  // Method org/apache/dubbo/registry/integration/RegistryProtocol.access$200:()Lorg/apache/dubbo/common/logger/ErrorTypeAwareLogger;
      51: invokeinterface #8,  1            // InterfaceMethod org/apache/dubbo/common/logger/ErrorTypeAwareLogger.isDebugEnabled:()Z
      56: ifeq          98
      59: invokestatic  #7                  // Method org/apache/dubbo/registry/integration/RegistryProtocol.access$200:()Lorg/apache/dubbo/common/logger/ErrorTypeAwareLogger;
      62: new           #9                  // class java/lang/StringBuilder
      65: dup
      66: invokespecial #10                 // Method java/lang/StringBuilder."<init>":()V
      69: ldc           #17                 // String subscribe url:
      71: invokevirtual #12                 // Method java/lang/StringBuilder.append:(Ljava/lang/String;)Ljava/lang/StringBuilder;
      74: aload_0
      75: getfield      #5                  // Field subscribeUrl:Lorg/apache/dubbo/common/URL;
      78: invokevirtual #13                 // Method java/lang/StringBuilder.append:(Ljava/lang/Object;)Ljava/lang/StringBuilder;
      81: ldc           #18                 // String , override urls:
      83: invokevirtual #12                 // Method java/lang/StringBuilder.append:(Ljava/lang/String;)Ljava/lang/StringBuilder;
      86: aload_2
      87: invokevirtual #13                 // Method java/lang/StringBuilder.append:(Ljava/lang/Object;)Ljava/lang/StringBuilder;
      90: invokevirtual #14                 // Method java/lang/StringBuilder.toString:()Ljava/lang/String;
      93: invokeinterface #15,  2           // InterfaceMethod org/apache/dubbo/common/logger/ErrorTypeAwareLogger.debug:(Ljava/lang/String;)V
      98: aload_2
      99: invokeinterface #19,  1           // InterfaceMethod java/util/List.isEmpty:()Z
     104: ifeq          108
     107: return
     108: aload_0
     109: aload_2
     110: invokedynamic #20,  0             // InvokeDynamic #0:test:()Ljava/util/function/Predicate;
     115: invokestatic  #21                 // Method org/apache/dubbo/common/utils/UrlUtils.classifyUrls:(Ljava/util/List;Ljava/util/function/Predicate;)Ljava/util/List;
     118: invokestatic  #22                 // InterfaceMethod org/apache/dubbo/rpc/cluster/Configurator.toConfigurators:(Ljava/util/List;)Ljava/util/Optional;
     121: aload_0
     122: getfield      #23                 // Field configurators:Ljava/util/List;
     125: invokevirtual #24                 // Method java/util/Optional.orElse:(Ljava/lang/Object;)Ljava/lang/Object;
     128: checkcast     #25                 // class java/util/List
     131: putfield      #23                 // Field configurators:Ljava/util/List;
     134: aload_0
     135: getfield      #5                  // Field subscribeUrl:Lorg/apache/dubbo/common/URL;
     138: invokevirtual #26                 // Method org/apache/dubbo/common/URL.getOrDefaultApplicationModel:()Lorg/apache/dubbo/rpc/model/ApplicationModel;
     141: invokevirtual #27                 // Method org/apache/dubbo/rpc/model/ApplicationModel.getDeployer:()Lorg/apache/dubbo/common/deploy/ApplicationDeployer;
     144: astore_3
     145: aload_3
     146: invokeinterface #28,  1           // InterfaceMethod org/apache/dubbo/common/deploy/ApplicationDeployer.increaseServiceRefreshCount:()V
     151: aload_0
     152: invokevirtual #29                 // Method doOverrideIfNecessary:()V
     155: aload_3
     156: invokeinterface #30,  1           // InterfaceMethod org/apache/dubbo/common/deploy/ApplicationDeployer.decreaseServiceRefreshCount:()V
     161: goto          175
     164: astore        4
     166: aload_3
     167: invokeinterface #30,  1           // InterfaceMethod org/apache/dubbo/common/deploy/ApplicationDeployer.decreaseServiceRefreshCount:()V
     172: aload         4
     174: athrow
     175: return
    Exception table:
       from    to  target type
         145   155   164   any
         164   166   164   any

  public synchronized void doOverrideIfNecessary();
    Code:
       0: aload_0
       1: getfield      #6                  // Field originInvoker:Lorg/apache/dubbo/rpc/Invoker;
       4: instanceof    #31                 // class org/apache/dubbo/registry/integration/RegistryProtocol$InvokerDelegate
       7: ifeq          24
      10: aload_0
      11: getfield      #6                  // Field originInvoker:Lorg/apache/dubbo/rpc/Invoker;
      14: checkcast     #31                 // class org/apache/dubbo/registry/integration/RegistryProtocol$InvokerDelegate
      17: invokevirtual #32                 // Method org/apache/dubbo/registry/integration/RegistryProtocol$InvokerDelegate.getInvoker:()Lorg/apache/dubbo/rpc/Invoker;
      20: astore_1
      21: goto          29
      24: aload_0
      25: getfield      #6                  // Field originInvoker:Lorg/apache/dubbo/rpc/Invoker;
      28: astore_1
      29: aload_0
      30: getfield      #3                  // Field this$0:Lorg/apache/dubbo/registry/integration/RegistryProtocol;
      33: aload_1
      34: invokestatic  #33                 // Method org/apache/dubbo/registry/integration/RegistryProtocol.access$300:(Lorg/apache/dubbo/registry/integration/RegistryProtocol;Lorg/apache/dubbo/rpc/Invoker;)Lorg/apache/dubbo/common/URL;
      37: astore_2
      38: aload_0
      39: getfield      #3                  // Field this$0:Lorg/apache/dubbo/registry/integration/RegistryProtocol;
      42: aload_0
      43: getfield      #6                  // Field originInvoker:Lorg/apache/dubbo/rpc/Invoker;
      46: invokestatic  #34                 // Method org/apache/dubbo/registry/integration/RegistryProtocol.access$400:(Lorg/apache/dubbo/registry/integration/RegistryProtocol;Lorg/apache/dubbo/rpc/Invoker;)Ljava/lang/String;
      49: astore_3
      50: aload_0
      51: getfield      #3                  // Field this$0:Lorg/apache/dubbo/registry/integration/RegistryProtocol;
      54: invokestatic  #35                 // Method org/apache/dubbo/registry/integration/RegistryProtocol.access$500:(Lorg/apache/dubbo/registry/integration/RegistryProtocol;)Ljava/util/concurrent/ConcurrentMap;
      57: aload_3
      58: invokeinterface #36,  2           // InterfaceMethod java/util/concurrent/ConcurrentMap.get:(Ljava/lang/Object;)Ljava/lang/Object;
      63: checkcast     #37                 // class org/apache/dubbo/registry/integration/RegistryProtocol$ExporterChangeableWrapper
      66: astore        4
      68: aload         4
      70: ifnonnull     99
      73: invokestatic  #7                  // Method org/apache/dubbo/registry/integration/RegistryProtocol.access$200:()Lorg/apache/dubbo/common/logger/ErrorTypeAwareLogger;
      76: ldc           #38                 // String 99-0
      78: ldc           #39                 // String unknown error in registry module
      80: ldc           #40                 // String
      82: ldc           #41                 // String error state, exporter should not be null
      84: new           #42                 // class java/lang/IllegalStateException
      87: dup
      88: ldc           #41                 // String error state, exporter should not be null
      90: invokespecial #43                 // Method java/lang/IllegalStateException."<init>":(Ljava/lang/String;)V
      93: invokeinterface #44,  6           // InterfaceMethod org/apache/dubbo/common/logger/ErrorTypeAwareLogger.warn:(Ljava/lang/String;Ljava/lang/String;Ljava/lang/String;Ljava/lang/String;Ljava/lang/Throwable;)V
      98: return
      99: aload         4
     101: invokevirtual #45                 // Method org/apache/dubbo/registry/integration/RegistryProtocol$ExporterChangeableWrapper.getInvoker:()Lorg/apache/dubbo/rpc/Invoker;
     104: astore        5
     106: aload         5
     108: ifnonnull     115
     111: aconst_null
     112: goto          122
     115: aload         5
     117: invokeinterface #46,  1           // InterfaceMethod org/apache/dubbo/rpc/Invoker.getUrl:()Lorg/apache/dubbo/common/URL;
     122: astore        6
     124: aload_0
     125: getfield      #23                 // Field configurators:Ljava/util/List;
     128: aload_2
     129: invokestatic  #47                 // Method org/apache/dubbo/registry/integration/RegistryProtocol.access$600:(Ljava/util/List;Lorg/apache/dubbo/common/URL;)Lorg/apache/dubbo/common/URL;
     132: astore        7
     134: aload_0
     135: getfield      #3                  // Field this$0:Lorg/apache/dubbo/registry/integration/RegistryProtocol;
     138: aload_2
     139: invokestatic  #48                 // Method org/apache/dubbo/registry/integration/RegistryProtocol.access$700:(Lorg/apache/dubbo/registry/integration/RegistryProtocol;Lorg/apache/dubbo/common/URL;)Lorg/apache/dubbo/registry/integration/RegistryProtocol$ProviderConfigurationListener;
     142: invokevirtual #49                 // Method org/apache/dubbo/registry/integration/RegistryProtocol$ProviderConfigurationListener.getConfigurators:()Ljava/util/List;
     145: aload         7
     147: invokestatic  #47                 // Method org/apache/dubbo/registry/integration/RegistryProtocol.access$600:(Ljava/util/List;Lorg/apache/dubbo/common/URL;)Lorg/apache/dubbo/common/URL;
     150: astore        7
     152: aload_0
     153: getfield      #3                  // Field this$0:Lorg/apache/dubbo/registry/integration/RegistryProtocol;
     156: invokestatic  #50                 // Method org/apache/dubbo/registry/integration/RegistryProtocol.access$800:(Lorg/apache/dubbo/registry/integration/RegistryProtocol;)Ljava/util/Map;
     159: aload_2
     160: invokevirtual #51                 // Method org/apache/dubbo/common/URL.getServiceKey:()Ljava/lang/String;
     163: invokeinterface #52,  2           // InterfaceMethod java/util/Map.get:(Ljava/lang/Object;)Ljava/lang/Object;
     168: checkcast     #53                 // class org/apache/dubbo/registry/integration/RegistryProtocol$ServiceConfigurationListener
     171: invokevirtual #54                 // Method org/apache/dubbo/registry/integration/RegistryProtocol$ServiceConfigurationListener.getConfigurators:()Ljava/util/List;
     174: aload         7
     176: invokestatic  #47                 // Method org/apache/dubbo/registry/integration/RegistryProtocol.access$600:(Ljava/util/List;Lorg/apache/dubbo/common/URL;)Lorg/apache/dubbo/common/URL;
     179: astore        7
     181: aload         7
     183: aload         6
     185: invokevirtual #55                 // Method org/apache/dubbo/common/URL.equals:(Ljava/lang/Object;)Z
     188: ifne          262
     191: aload         7
     193: ldc           #57                 // String need-reexport
     195: iconst_1
     196: invokevirtual #58                 // Method org/apache/dubbo/common/URL.getParameter:(Ljava/lang/String;Z)Z
     199: ifeq          215
     202: aload_0
     203: getfield      #3                  // Field this$0:Lorg/apache/dubbo/registry/integration/RegistryProtocol;
     206: aload_0
     207: getfield      #6                  // Field originInvoker:Lorg/apache/dubbo/rpc/Invoker;
     210: aload         7
     212: invokevirtual #59                 // Method org/apache/dubbo/registry/integration/RegistryProtocol.reExport:(Lorg/apache/dubbo/rpc/Invoker;Lorg/apache/dubbo/common/URL;)V
     215: invokestatic  #7                  // Method org/apache/dubbo/registry/integration/RegistryProtocol.access$200:()Lorg/apache/dubbo/common/logger/ErrorTypeAwareLogger;
     218: new           #9                  // class java/lang/StringBuilder
     221: dup
     222: invokespecial #10                 // Method java/lang/StringBuilder."<init>":()V
     225: ldc           #60                 // String exported provider url changed, origin url:
     227: invokevirtual #12                 // Method java/lang/StringBuilder.append:(Ljava/lang/String;)Ljava/lang/StringBuilder;
     230: aload_2
     231: invokevirtual #13                 // Method java/lang/StringBuilder.append:(Ljava/lang/Object;)Ljava/lang/StringBuilder;
     234: ldc           #61                 // String , old export url:
     236: invokevirtual #12                 // Method java/lang/StringBuilder.append:(Ljava/lang/String;)Ljava/lang/StringBuilder;
     239: aload         6
     241: invokevirtual #13                 // Method java/lang/StringBuilder.append:(Ljava/lang/Object;)Ljava/lang/StringBuilder;
     244: ldc           #62                 // String , new export url:
     246: invokevirtual #12                 // Method java/lang/StringBuilder.append:(Ljava/lang/String;)Ljava/lang/StringBuilder;
     249: aload         7
     251: invokevirtual #13                 // Method java/lang/StringBuilder.append:(Ljava/lang/Object;)Ljava/lang/StringBuilder;
     254: invokevirtual #14                 // Method java/lang/StringBuilder.toString:()Ljava/lang/String;
     257: invokeinterface #63,  2           // InterfaceMethod org/apache/dubbo/common/logger/ErrorTypeAwareLogger.info:(Ljava/lang/String;)V
     262: return

  private java.util.List<org.apache.dubbo.common.URL> getMatchedUrls(java.util.List<org.apache.dubbo.common.URL>, org.apache.dubbo.common.URL);
    Code:
       0: new           #64                 // class java/util/ArrayList
       3: dup
       4: invokespecial #65                 // Method java/util/ArrayList."<init>":()V
       7: astore_3
       8: aload_1
       9: invokeinterface #66,  1           // InterfaceMethod java/util/List.iterator:()Ljava/util/Iterator;
      14: astore        4
      16: aload         4
      18: invokeinterface #67,  1           // InterfaceMethod java/util/Iterator.hasNext:()Z
      23: ifeq          95
      26: aload         4
      28: invokeinterface #68,  1           // InterfaceMethod java/util/Iterator.next:()Ljava/lang/Object;
      33: checkcast     #69                 // class org/apache/dubbo/common/URL
      36: astore        5
      38: aload         5
      40: astore        6
      42: aload         5
      44: invokevirtual #70                 // Method org/apache/dubbo/common/URL.getCategory:()Ljava/lang/String;
      47: ifnonnull     74
      50: ldc           #71                 // String override
      52: aload         5
      54: invokevirtual #72                 // Method org/apache/dubbo/common/URL.getProtocol:()Ljava/lang/String;
      57: invokevirtual #73                 // Method java/lang/String.equals:(Ljava/lang/Object;)Z
      60: ifeq          74
      63: aload         5
      65: ldc           #74                 // String category
      67: ldc           #75                 // String configurators
      69: invokevirtual #76                 // Method org/apache/dubbo/common/URL.addParameter:(Ljava/lang/String;Ljava/lang/String;)Lorg/apache/dubbo/common/URL;
      72: astore        6
      74: aload_2
      75: aload         6
      77: invokestatic  #77                 // Method org/apache/dubbo/common/utils/UrlUtils.isMatch:(Lorg/apache/dubbo/common/URL;Lorg/apache/dubbo/common/URL;)Z
      80: ifeq          92
      83: aload_3
      84: aload         5
      86: invokeinterface #78,  2           // InterfaceMethod java/util/List.add:(Ljava/lang/Object;)Z
      91: pop
      92: goto          16
      95: aload_3
      96: areturn
}
