Compiled from "RegistryDirectory.java"
class org.apache.dubbo.registry.integration.RegistryDirectory$ConsumerConfigurationListener extends org.apache.dubbo.registry.integration.AbstractConfiguratorListener {
  java.util.List<org.apache.dubbo.registry.integration.RegistryDirectory> listeners;

  org.apache.dubbo.registry.integration.RegistryDirectory$ConsumerConfigurationListener(org.apache.dubbo.rpc.model.ModuleModel);
    Code:
       0: aload_0
       1: aload_1
       2: invokespecial #2                  // Method org/apache/dubbo/registry/integration/AbstractConfiguratorListener."<init>":(Lorg/apache/dubbo/rpc/model/ModuleModel;)V
       5: aload_0
       6: new           #3                  // class java/util/ArrayList
       9: dup
      10: invokespecial #4                  // Method java/util/ArrayList."<init>":()V
      13: putfield      #5                  // Field listeners:Ljava/util/List;
      16: aload_0
      17: new           #6                  // class java/lang/StringBuilder
      20: dup
      21: invokespecial #7                  // Method java/lang/StringBuilder."<init>":()V
      24: aload_1
      25: invokevirtual #8                  // Method org/apache/dubbo/rpc/model/ModuleModel.getApplicationModel:()Lorg/apache/dubbo/rpc/model/ApplicationModel;
      28: invokevirtual #9                  // Method org/apache/dubbo/rpc/model/ApplicationModel.getApplicationName:()Ljava/lang/String;
      31: invokevirtual #10                 // Method java/lang/StringBuilder.append:(Ljava/lang/String;)Ljava/lang/StringBuilder;
      34: ldc           #11                 // String .configurators
      36: invokevirtual #10                 // Method java/lang/StringBuilder.append:(Ljava/lang/String;)Ljava/lang/StringBuilder;
      39: invokevirtual #12                 // Method java/lang/StringBuilder.toString:()Ljava/lang/String;
      42: invokevirtual #13                 // Method initWith:(Ljava/lang/String;)V
      45: return

  void addNotifyListener(org.apache.dubbo.registry.integration.RegistryDirectory);
    Code:
       0: aload_0
       1: getfield      #5                  // Field listeners:Ljava/util/List;
       4: aload_1
       5: invokeinterface #14,  2           // InterfaceMethod java/util/List.add:(Ljava/lang/Object;)Z
      10: pop
      11: return

  void removeNotifyListener(org.apache.dubbo.registry.integration.RegistryDirectory);
    Code:
       0: aload_0
       1: getfield      #5                  // Field listeners:Ljava/util/List;
       4: aload_1
       5: invokeinterface #15,  2           // InterfaceMethod java/util/List.remove:(Ljava/lang/Object;)Z
      10: pop
      11: return

  protected void notifyOverrides();
    Code:
       0: aload_0
       1: getfield      #5                  // Field listeners:Ljava/util/List;
       4: invokedynamic #16,  0             // InvokeDynamic #0:accept:()Ljava/util/function/Consumer;
       9: invokeinterface #17,  2           // InterfaceMethod java/util/List.forEach:(Ljava/util/function/Consumer;)V
      14: return

  private static void lambda$notifyOverrides$0(org.apache.dubbo.registry.integration.RegistryDirectory);
    Code:
       0: aload_0
       1: invokestatic  #18                 // Method java/util/Collections.emptyList:()Ljava/util/List;
       4: invokevirtual #19                 // Method org/apache/dubbo/registry/integration/RegistryDirectory.refreshOverrideAndInvoker:(Ljava/util/List;)V
       7: return
}
