Compiled from "RegistryProtocol.java"
public class org.apache.dubbo.registry.integration.RegistryProtocol implements org.apache.dubbo.rpc.Protocol,org.apache.dubbo.rpc.model.ScopeModelAware {
  public static final java.lang.String[] DEFAULT_REGISTER_PROVIDER_KEYS;

  public static final java.lang.String[] DEFAULT_REGISTER_CONSUMER_KEYS;

  private static final org.apache.dubbo.common.logger.ErrorTypeAwareLogger logger;

  private final java.util.Map<java.lang.String, org.apache.dubbo.registry.integration.RegistryProtocol$ServiceConfigurationListener> serviceConfigurationListeners;

  private final java.util.concurrent.ConcurrentMap<java.lang.String, org.apache.dubbo.registry.integration.RegistryProtocol$ExporterChangeableWrapper<?>> bounds;

  protected org.apache.dubbo.rpc.Protocol protocol;

  protected org.apache.dubbo.rpc.ProxyFactory proxyFactory;

  private java.util.concurrent.ConcurrentMap<org.apache.dubbo.common.URL, org.apache.dubbo.registry.retry.ReExportTask> reExportFailedTasks;

  private org.apache.dubbo.common.timer.HashedWheelTimer retryTimer;

  private org.apache.dubbo.rpc.model.FrameworkModel frameworkModel;

  private static java.lang.String[] getFilteredKeys(org.apache.dubbo.common.URL);
    Code:
       0: aload_0
       1: invokevirtual #17                 // Method org/apache/dubbo/common/URL.getParameters:()Ljava/util/Map;
       4: astore_1
       5: aload_1
       6: invokestatic  #18                 // Method org/apache/dubbo/common/utils/CollectionUtils.isNotEmptyMap:(Ljava/util/Map;)Z
       9: ifeq          47
      12: aload_1
      13: invokeinterface #19,  1           // InterfaceMethod java/util/Map.keySet:()Ljava/util/Set;
      18: invokeinterface #20,  1           // InterfaceMethod java/util/Set.stream:()Ljava/util/stream/Stream;
      23: invokedynamic #21,  0             // InvokeDynamic #0:test:()Ljava/util/function/Predicate;
      28: invokeinterface #22,  2           // InterfaceMethod java/util/stream/Stream.filter:(Ljava/util/function/Predicate;)Ljava/util/stream/Stream;
      33: invokedynamic #23,  0             // InvokeDynamic #1:apply:()Ljava/util/function/IntFunction;
      38: invokeinterface #24,  2           // InterfaceMethod java/util/stream/Stream.toArray:(Ljava/util/function/IntFunction;)[Ljava/lang/Object;
      43: checkcast     #25                 // class "[Ljava/lang/String;"
      46: areturn
      47: iconst_0
      48: anewarray     #26                 // class java/lang/String
      51: areturn

  public org.apache.dubbo.registry.integration.RegistryProtocol();
    Code:
       0: aload_0
       1: invokespecial #27                 // Method java/lang/Object."<init>":()V
       4: aload_0
       5: new           #28                 // class java/util/concurrent/ConcurrentHashMap
       8: dup
       9: invokespecial #29                 // Method java/util/concurrent/ConcurrentHashMap."<init>":()V
      12: putfield      #10                 // Field serviceConfigurationListeners:Ljava/util/Map;
      15: aload_0
      16: new           #28                 // class java/util/concurrent/ConcurrentHashMap
      19: dup
      20: invokespecial #29                 // Method java/util/concurrent/ConcurrentHashMap."<init>":()V
      23: putfield      #13                 // Field bounds:Ljava/util/concurrent/ConcurrentMap;
      26: aload_0
      27: new           #28                 // class java/util/concurrent/ConcurrentHashMap
      30: dup
      31: invokespecial #29                 // Method java/util/concurrent/ConcurrentHashMap."<init>":()V
      34: putfield      #30                 // Field reExportFailedTasks:Ljava/util/concurrent/ConcurrentMap;
      37: aload_0
      38: new           #31                 // class org/apache/dubbo/common/timer/HashedWheelTimer
      41: dup
      42: new           #32                 // class org/apache/dubbo/common/utils/NamedThreadFactory
      45: dup
      46: ldc           #33                 // String DubboReexportTimer
      48: iconst_1
      49: invokespecial #34                 // Method org/apache/dubbo/common/utils/NamedThreadFactory."<init>":(Ljava/lang/String;Z)V
      52: ldc2_w        #35                 // long 5000l
      55: getstatic     #37                 // Field java/util/concurrent/TimeUnit.MILLISECONDS:Ljava/util/concurrent/TimeUnit;
      58: sipush        128
      61: invokespecial #38                 // Method org/apache/dubbo/common/timer/HashedWheelTimer."<init>":(Ljava/util/concurrent/ThreadFactory;JLjava/util/concurrent/TimeUnit;I)V
      64: putfield      #39                 // Field retryTimer:Lorg/apache/dubbo/common/timer/HashedWheelTimer;
      67: return

  public void setFrameworkModel(org.apache.dubbo.rpc.model.FrameworkModel);
    Code:
       0: aload_0
       1: aload_1
       2: putfield      #40                 // Field frameworkModel:Lorg/apache/dubbo/rpc/model/FrameworkModel;
       5: return

  public void setProtocol(org.apache.dubbo.rpc.Protocol);
    Code:
       0: aload_0
       1: aload_1
       2: putfield      #41                 // Field protocol:Lorg/apache/dubbo/rpc/Protocol;
       5: return

  public void setProxyFactory(org.apache.dubbo.rpc.ProxyFactory);
    Code:
       0: aload_0
       1: aload_1
       2: putfield      #42                 // Field proxyFactory:Lorg/apache/dubbo/rpc/ProxyFactory;
       5: return

  public int getDefaultPort();
    Code:
       0: sipush        9090
       3: ireturn

  public java.util.Map<org.apache.dubbo.common.URL, java.util.Set<org.apache.dubbo.registry.NotifyListener>> getOverrideListeners();
    Code:
       0: new           #43                 // class java/util/HashMap
       3: dup
       4: invokespecial #44                 // Method java/util/HashMap."<init>":()V
       7: astore_1
       8: aload_0
       9: getfield      #40                 // Field frameworkModel:Lorg/apache/dubbo/rpc/model/FrameworkModel;
      12: invokevirtual #45                 // Method org/apache/dubbo/rpc/model/FrameworkModel.getApplicationModels:()Ljava/util/List;
      15: astore_2
      16: aload_2
      17: invokeinterface #46,  1           // InterfaceMethod java/util/List.size:()I
      22: iconst_1
      23: if_icmpne     51
      26: aload_2
      27: iconst_0
      28: invokeinterface #47,  2           // InterfaceMethod java/util/List.get:(I)Ljava/lang/Object;
      33: checkcast     #48                 // class org/apache/dubbo/rpc/model/ApplicationModel
      36: invokevirtual #49                 // Method org/apache/dubbo/rpc/model/ApplicationModel.getBeanFactory:()Lorg/apache/dubbo/common/beans/factory/ScopeBeanFactory;
      39: ldc           #50                 // class org/apache/dubbo/registry/integration/RegistryProtocol$ProviderConfigurationListener
      41: invokevirtual #51                 // Method org/apache/dubbo/common/beans/factory/ScopeBeanFactory.getBean:(Ljava/lang/Class;)Ljava/lang/Object;
      44: checkcast     #50                 // class org/apache/dubbo/registry/integration/RegistryProtocol$ProviderConfigurationListener
      47: invokevirtual #52                 // Method org/apache/dubbo/registry/integration/RegistryProtocol$ProviderConfigurationListener.getOverrideListeners:()Ljava/util/Map;
      50: areturn
      51: aload_2
      52: invokeinterface #53,  1           // InterfaceMethod java/util/List.iterator:()Ljava/util/Iterator;
      57: astore_3
      58: aload_3
      59: invokeinterface #54,  1           // InterfaceMethod java/util/Iterator.hasNext:()Z
      64: ifeq          103
      67: aload_3
      68: invokeinterface #55,  1           // InterfaceMethod java/util/Iterator.next:()Ljava/lang/Object;
      73: checkcast     #48                 // class org/apache/dubbo/rpc/model/ApplicationModel
      76: astore        4
      78: aload_1
      79: aload         4
      81: invokevirtual #49                 // Method org/apache/dubbo/rpc/model/ApplicationModel.getBeanFactory:()Lorg/apache/dubbo/common/beans/factory/ScopeBeanFactory;
      84: ldc           #50                 // class org/apache/dubbo/registry/integration/RegistryProtocol$ProviderConfigurationListener
      86: invokevirtual #51                 // Method org/apache/dubbo/common/beans/factory/ScopeBeanFactory.getBean:(Ljava/lang/Class;)Ljava/lang/Object;
      89: checkcast     #50                 // class org/apache/dubbo/registry/integration/RegistryProtocol$ProviderConfigurationListener
      92: invokevirtual #52                 // Method org/apache/dubbo/registry/integration/RegistryProtocol$ProviderConfigurationListener.getOverrideListeners:()Ljava/util/Map;
      95: invokeinterface #56,  2           // InterfaceMethod java/util/Map.putAll:(Ljava/util/Map;)V
     100: goto          58
     103: aload_1
     104: areturn

  private void register(org.apache.dubbo.registry.Registry, org.apache.dubbo.common.URL);
    Code:
       0: aload_2
       1: invokevirtual #57                 // Method org/apache/dubbo/common/URL.getOrDefaultApplicationModel:()Lorg/apache/dubbo/rpc/model/ApplicationModel;
       4: invokevirtual #58                 // Method org/apache/dubbo/rpc/model/ApplicationModel.getDeployer:()Lorg/apache/dubbo/common/deploy/ApplicationDeployer;
       7: astore_3
       8: aload_3
       9: invokeinterface #59,  1           // InterfaceMethod org/apache/dubbo/common/deploy/ApplicationDeployer.increaseServiceRefreshCount:()V
      14: aload_1
      15: aload_2
      16: invokeinterface #60,  2           // InterfaceMethod org/apache/dubbo/registry/Registry.register:(Lorg/apache/dubbo/common/URL;)V
      21: aload_3
      22: invokeinterface #61,  1           // InterfaceMethod org/apache/dubbo/common/deploy/ApplicationDeployer.decreaseServiceRefreshCount:()V
      27: goto          41
      30: astore        4
      32: aload_3
      33: invokeinterface #61,  1           // InterfaceMethod org/apache/dubbo/common/deploy/ApplicationDeployer.decreaseServiceRefreshCount:()V
      38: aload         4
      40: athrow
      41: return
    Exception table:
       from    to  target type
           8    21    30   any
          30    32    30   any

  private void registerStatedUrl(org.apache.dubbo.common.URL, org.apache.dubbo.common.URL, boolean);
    Code:
       0: aload_2
       1: invokevirtual #62                 // Method org/apache/dubbo/common/URL.getServiceModel:()Lorg/apache/dubbo/rpc/model/ServiceModel;
       4: checkcast     #63                 // class org/apache/dubbo/rpc/model/ProviderModel
       7: astore        4
       9: aload         4
      11: new           #64                 // class org/apache/dubbo/rpc/model/ProviderModel$RegisterStatedURL
      14: dup
      15: aload_2
      16: aload_1
      17: iload_3
      18: invokespecial #65                 // Method org/apache/dubbo/rpc/model/ProviderModel$RegisterStatedURL."<init>":(Lorg/apache/dubbo/common/URL;Lorg/apache/dubbo/common/URL;Z)V
      21: invokevirtual #66                 // Method org/apache/dubbo/rpc/model/ProviderModel.addStatedUrl:(Lorg/apache/dubbo/rpc/model/ProviderModel$RegisterStatedURL;)V
      24: return

  public <T> org.apache.dubbo.rpc.Exporter<T> export(org.apache.dubbo.rpc.Invoker<T>) throws org.apache.dubbo.rpc.RpcException;
    Code:
       0: aload_0
       1: aload_1
       2: invokevirtual #67                 // Method getRegistryUrl:(Lorg/apache/dubbo/rpc/Invoker;)Lorg/apache/dubbo/common/URL;
       5: astore_2
       6: aload_0
       7: aload_1
       8: invokespecial #15                 // Method getProviderUrl:(Lorg/apache/dubbo/rpc/Invoker;)Lorg/apache/dubbo/common/URL;
      11: astore_3
      12: aload_0
      13: aload_3
      14: invokespecial #68                 // Method getSubscribedOverrideUrl:(Lorg/apache/dubbo/common/URL;)Lorg/apache/dubbo/common/URL;
      17: astore        4
      19: new           #69                 // class org/apache/dubbo/registry/integration/RegistryProtocol$OverrideListener
      22: dup
      23: aload_0
      24: aload         4
      26: aload_1
      27: invokespecial #70                 // Method org/apache/dubbo/registry/integration/RegistryProtocol$OverrideListener."<init>":(Lorg/apache/dubbo/registry/integration/RegistryProtocol;Lorg/apache/dubbo/common/URL;Lorg/apache/dubbo/rpc/Invoker;)V
      30: astore        5
      32: aload_0
      33: aload         4
      35: invokespecial #11                 // Method getProviderConfigurationListener:(Lorg/apache/dubbo/common/URL;)Lorg/apache/dubbo/registry/integration/RegistryProtocol$ProviderConfigurationListener;
      38: invokevirtual #52                 // Method org/apache/dubbo/registry/integration/RegistryProtocol$ProviderConfigurationListener.getOverrideListeners:()Ljava/util/Map;
      41: astore        6
      43: aload         6
      45: aload         4
      47: invokedynamic #71,  0             // InvokeDynamic #2:apply:()Ljava/util/function/Function;
      52: invokeinterface #72,  3           // InterfaceMethod java/util/Map.computeIfAbsent:(Ljava/lang/Object;Ljava/util/function/Function;)Ljava/lang/Object;
      57: checkcast     #73                 // class java/util/Set
      60: aload         5
      62: invokeinterface #74,  2           // InterfaceMethod java/util/Set.add:(Ljava/lang/Object;)Z
      67: pop
      68: aload_0
      69: aload_3
      70: aload         5
      72: invokespecial #75                 // Method overrideUrlWithConfig:(Lorg/apache/dubbo/common/URL;Lorg/apache/dubbo/registry/integration/RegistryProtocol$OverrideListener;)Lorg/apache/dubbo/common/URL;
      75: astore_3
      76: aload_0
      77: aload_1
      78: aload_3
      79: invokespecial #76                 // Method doLocalExport:(Lorg/apache/dubbo/rpc/Invoker;Lorg/apache/dubbo/common/URL;)Lorg/apache/dubbo/registry/integration/RegistryProtocol$ExporterChangeableWrapper;
      82: astore        7
      84: aload_0
      85: aload_2
      86: invokevirtual #77                 // Method getRegistry:(Lorg/apache/dubbo/common/URL;)Lorg/apache/dubbo/registry/Registry;
      89: astore        8
      91: aload_0
      92: aload_3
      93: aload_2
      94: invokespecial #78                 // Method getUrlToRegistry:(Lorg/apache/dubbo/common/URL;Lorg/apache/dubbo/common/URL;)Lorg/apache/dubbo/common/URL;
      97: astore        9
      99: aload_3
     100: ldc           #79                 // String register
     102: iconst_1
     103: invokevirtual #80                 // Method org/apache/dubbo/common/URL.getParameter:(Ljava/lang/String;Z)Z
     106: ifeq          123
     109: aload_2
     110: ldc           #79                 // String register
     112: iconst_1
     113: invokevirtual #80                 // Method org/apache/dubbo/common/URL.getParameter:(Ljava/lang/String;Z)Z
     116: ifeq          123
     119: iconst_1
     120: goto          124
     123: iconst_0
     124: istore        10
     126: iload         10
     128: ifeq          139
     131: aload_0
     132: aload         8
     134: aload         9
     136: invokespecial #81                 // Method register:(Lorg/apache/dubbo/registry/Registry;Lorg/apache/dubbo/common/URL;)V
     139: aload_0
     140: aload_2
     141: aload         9
     143: iload         10
     145: invokespecial #82                 // Method registerStatedUrl:(Lorg/apache/dubbo/common/URL;Lorg/apache/dubbo/common/URL;Z)V
     148: aload         7
     150: aload         9
     152: invokevirtual #83                 // Method org/apache/dubbo/registry/integration/RegistryProtocol$ExporterChangeableWrapper.setRegisterUrl:(Lorg/apache/dubbo/common/URL;)V
     155: aload         7
     157: aload         4
     159: invokevirtual #84                 // Method org/apache/dubbo/registry/integration/RegistryProtocol$ExporterChangeableWrapper.setSubscribeUrl:(Lorg/apache/dubbo/common/URL;)V
     162: aload         7
     164: aload         5
     166: invokevirtual #85                 // Method org/apache/dubbo/registry/integration/RegistryProtocol$ExporterChangeableWrapper.setNotifyListener:(Lorg/apache/dubbo/registry/NotifyListener;)V
     169: aload_3
     170: invokevirtual #86                 // Method org/apache/dubbo/common/URL.getScopeModel:()Lorg/apache/dubbo/rpc/model/ScopeModel;
     173: invokestatic  #87                 // Method org/apache/dubbo/rpc/model/ScopeModelUtil.getApplicationModel:(Lorg/apache/dubbo/rpc/model/ScopeModel;)Lorg/apache/dubbo/rpc/model/ApplicationModel;
     176: astore        11
     178: aload         11
     180: invokevirtual #88                 // Method org/apache/dubbo/rpc/model/ApplicationModel.getModelEnvironment:()Lorg/apache/dubbo/common/config/Environment;
     183: invokevirtual #89                 // Method org/apache/dubbo/common/config/Environment.getConfiguration:()Lorg/apache/dubbo/common/config/CompositeConfiguration;
     186: ldc           #90                 // class java/lang/Boolean
     188: ldc           #91                 // String enable-26x-configuration-listen
     190: iconst_1
     191: invokestatic  #92                 // Method java/lang/Boolean.valueOf:(Z)Ljava/lang/Boolean;
     194: invokevirtual #93                 // Method org/apache/dubbo/common/config/CompositeConfiguration.convert:(Ljava/lang/Class;Ljava/lang/String;Ljava/lang/Object;)Ljava/lang/Object;
     197: checkcast     #90                 // class java/lang/Boolean
     200: invokevirtual #94                 // Method java/lang/Boolean.booleanValue:()Z
     203: ifeq          227
     206: aload         8
     208: invokeinterface #95,  1           // InterfaceMethod org/apache/dubbo/registry/Registry.isServiceDiscovery:()Z
     213: ifne          227
     216: aload         8
     218: aload         4
     220: aload         5
     222: invokeinterface #96,  3           // InterfaceMethod org/apache/dubbo/registry/Registry.subscribe:(Lorg/apache/dubbo/common/URL;Lorg/apache/dubbo/registry/NotifyListener;)V
     227: aload_0
     228: aload         7
     230: invokespecial #97                 // Method notifyExport:(Lorg/apache/dubbo/registry/integration/RegistryProtocol$ExporterChangeableWrapper;)V
     233: new           #98                 // class org/apache/dubbo/registry/integration/RegistryProtocol$DestroyableExporter
     236: dup
     237: aload         7
     239: invokespecial #99                 // Method org/apache/dubbo/registry/integration/RegistryProtocol$DestroyableExporter."<init>":(Lorg/apache/dubbo/rpc/Exporter;)V
     242: areturn

  private <T> void notifyExport(org.apache.dubbo.registry.integration.RegistryProtocol$ExporterChangeableWrapper<T>);
    Code:
       0: aload_1
       1: invokevirtual #100                // Method org/apache/dubbo/registry/integration/RegistryProtocol$ExporterChangeableWrapper.getRegisterUrl:()Lorg/apache/dubbo/common/URL;
       4: invokevirtual #86                 // Method org/apache/dubbo/common/URL.getScopeModel:()Lorg/apache/dubbo/rpc/model/ScopeModel;
       7: astore_2
       8: ldc           #101                // class org/apache/dubbo/registry/integration/RegistryProtocolListener
      10: aload_2
      11: invokestatic  #102                // Method org/apache/dubbo/rpc/model/ScopeModelUtil.getExtensionLoader:(Ljava/lang/Class;Lorg/apache/dubbo/rpc/model/ScopeModel;)Lorg/apache/dubbo/common/extension/ExtensionLoader;
      14: aload_1
      15: invokevirtual #103                // Method org/apache/dubbo/registry/integration/RegistryProtocol$ExporterChangeableWrapper.getOriginInvoker:()Lorg/apache/dubbo/rpc/Invoker;
      18: invokeinterface #104,  1          // InterfaceMethod org/apache/dubbo/rpc/Invoker.getUrl:()Lorg/apache/dubbo/common/URL;
      23: ldc           #105                // String registry.protocol.listener
      25: invokevirtual #106                // Method org/apache/dubbo/common/extension/ExtensionLoader.getActivateExtension:(Lorg/apache/dubbo/common/URL;Ljava/lang/String;)Ljava/util/List;
      28: astore_3
      29: aload_3
      30: invokestatic  #107                // Method org/apache/dubbo/common/utils/CollectionUtils.isNotEmpty:(Ljava/util/Collection;)Z
      33: ifeq          78
      36: aload_3
      37: invokeinterface #53,  1           // InterfaceMethod java/util/List.iterator:()Ljava/util/Iterator;
      42: astore        4
      44: aload         4
      46: invokeinterface #54,  1           // InterfaceMethod java/util/Iterator.hasNext:()Z
      51: ifeq          78
      54: aload         4
      56: invokeinterface #55,  1           // InterfaceMethod java/util/Iterator.next:()Ljava/lang/Object;
      61: checkcast     #101                // class org/apache/dubbo/registry/integration/RegistryProtocolListener
      64: astore        5
      66: aload         5
      68: aload_0
      69: aload_1
      70: invokeinterface #108,  3          // InterfaceMethod org/apache/dubbo/registry/integration/RegistryProtocolListener.onExport:(Lorg/apache/dubbo/registry/integration/RegistryProtocol;Lorg/apache/dubbo/rpc/Exporter;)V
      75: goto          44
      78: return

  private org.apache.dubbo.common.URL overrideUrlWithConfig(org.apache.dubbo.common.URL, org.apache.dubbo.registry.integration.RegistryProtocol$OverrideListener);
    Code:
       0: aload_0
       1: aload_1
       2: invokespecial #11                 // Method getProviderConfigurationListener:(Lorg/apache/dubbo/common/URL;)Lorg/apache/dubbo/registry/integration/RegistryProtocol$ProviderConfigurationListener;
       5: astore_3
       6: aload_3
       7: aload_1
       8: invokestatic  #109                // Method org/apache/dubbo/registry/integration/RegistryProtocol$ProviderConfigurationListener.access$000:(Lorg/apache/dubbo/registry/integration/RegistryProtocol$ProviderConfigurationListener;Lorg/apache/dubbo/common/URL;)Lorg/apache/dubbo/common/URL;
      11: astore_1
      12: new           #110                // class org/apache/dubbo/registry/integration/RegistryProtocol$ServiceConfigurationListener
      15: dup
      16: aload_0
      17: aload_1
      18: invokevirtual #111                // Method org/apache/dubbo/common/URL.getOrDefaultModuleModel:()Lorg/apache/dubbo/rpc/model/ModuleModel;
      21: aload_1
      22: aload_2
      23: invokespecial #112                // Method org/apache/dubbo/registry/integration/RegistryProtocol$ServiceConfigurationListener."<init>":(Lorg/apache/dubbo/registry/integration/RegistryProtocol;Lorg/apache/dubbo/rpc/model/ModuleModel;Lorg/apache/dubbo/common/URL;Lorg/apache/dubbo/registry/integration/RegistryProtocol$OverrideListener;)V
      26: astore        4
      28: aload_0
      29: getfield      #10                 // Field serviceConfigurationListeners:Ljava/util/Map;
      32: aload_1
      33: invokevirtual #113                // Method org/apache/dubbo/common/URL.getServiceKey:()Ljava/lang/String;
      36: aload         4
      38: invokeinterface #114,  3          // InterfaceMethod java/util/Map.put:(Ljava/lang/Object;Ljava/lang/Object;)Ljava/lang/Object;
      43: pop
      44: aload         4
      46: aload_1
      47: invokestatic  #115                // Method org/apache/dubbo/registry/integration/RegistryProtocol$ServiceConfigurationListener.access$100:(Lorg/apache/dubbo/registry/integration/RegistryProtocol$ServiceConfigurationListener;Lorg/apache/dubbo/common/URL;)Lorg/apache/dubbo/common/URL;
      50: areturn

  private <T> org.apache.dubbo.registry.integration.RegistryProtocol$ExporterChangeableWrapper<T> doLocalExport(org.apache.dubbo.rpc.Invoker<T>, org.apache.dubbo.common.URL);
    Code:
       0: aload_0
       1: aload_1
       2: invokespecial #14                 // Method getCacheKey:(Lorg/apache/dubbo/rpc/Invoker;)Ljava/lang/String;
       5: astore_3
       6: aload_0
       7: getfield      #13                 // Field bounds:Ljava/util/concurrent/ConcurrentMap;
      10: aload_3
      11: aload_0
      12: aload_1
      13: aload_2
      14: invokedynamic #116,  0            // InvokeDynamic #3:apply:(Lorg/apache/dubbo/registry/integration/RegistryProtocol;Lorg/apache/dubbo/rpc/Invoker;Lorg/apache/dubbo/common/URL;)Ljava/util/function/Function;
      19: invokeinterface #117,  3          // InterfaceMethod java/util/concurrent/ConcurrentMap.computeIfAbsent:(Ljava/lang/Object;Ljava/util/function/Function;)Ljava/lang/Object;
      24: checkcast     #118                // class org/apache/dubbo/registry/integration/RegistryProtocol$ExporterChangeableWrapper
      27: areturn

  public <T> void reExport(org.apache.dubbo.rpc.Exporter<T>, org.apache.dubbo.common.URL);
    Code:
       0: aload_1
       1: instanceof    #118                // class org/apache/dubbo/registry/integration/RegistryProtocol$ExporterChangeableWrapper
       4: ifeq          25
       7: aload_1
       8: checkcast     #118                // class org/apache/dubbo/registry/integration/RegistryProtocol$ExporterChangeableWrapper
      11: astore_3
      12: aload_3
      13: invokevirtual #103                // Method org/apache/dubbo/registry/integration/RegistryProtocol$ExporterChangeableWrapper.getOriginInvoker:()Lorg/apache/dubbo/rpc/Invoker;
      16: astore        4
      18: aload_0
      19: aload         4
      21: aload_2
      22: invokevirtual #119                // Method reExport:(Lorg/apache/dubbo/rpc/Invoker;Lorg/apache/dubbo/common/URL;)V
      25: return

  public <T> void reExport(org.apache.dubbo.rpc.Invoker<T>, org.apache.dubbo.common.URL);
    Code:
       0: aload_0
       1: aload_1
       2: invokespecial #14                 // Method getCacheKey:(Lorg/apache/dubbo/rpc/Invoker;)Ljava/lang/String;
       5: astore_3
       6: aload_0
       7: getfield      #13                 // Field bounds:Ljava/util/concurrent/ConcurrentMap;
      10: aload_3
      11: invokeinterface #120,  2          // InterfaceMethod java/util/concurrent/ConcurrentMap.get:(Ljava/lang/Object;)Ljava/lang/Object;
      16: checkcast     #118                // class org/apache/dubbo/registry/integration/RegistryProtocol$ExporterChangeableWrapper
      19: astore        4
      21: aload         4
      23: invokevirtual #100                // Method org/apache/dubbo/registry/integration/RegistryProtocol$ExporterChangeableWrapper.getRegisterUrl:()Lorg/apache/dubbo/common/URL;
      26: astore        5
      28: aload_0
      29: aload_1
      30: invokevirtual #67                 // Method getRegistryUrl:(Lorg/apache/dubbo/rpc/Invoker;)Lorg/apache/dubbo/common/URL;
      33: astore        6
      35: aload_0
      36: aload_2
      37: aload         6
      39: invokespecial #78                 // Method getUrlToRegistry:(Lorg/apache/dubbo/common/URL;Lorg/apache/dubbo/common/URL;)Lorg/apache/dubbo/common/URL;
      42: astore        7
      44: new           #121                // class org/apache/dubbo/registry/integration/RegistryProtocol$InvokerDelegate
      47: dup
      48: aload_1
      49: aload_2
      50: invokespecial #122                // Method org/apache/dubbo/registry/integration/RegistryProtocol$InvokerDelegate."<init>":(Lorg/apache/dubbo/rpc/Invoker;Lorg/apache/dubbo/common/URL;)V
      53: astore        8
      55: aload         4
      57: aload_0
      58: getfield      #41                 // Field protocol:Lorg/apache/dubbo/rpc/Protocol;
      61: aload         8
      63: invokeinterface #123,  2          // InterfaceMethod org/apache/dubbo/rpc/Protocol.export:(Lorg/apache/dubbo/rpc/Invoker;)Lorg/apache/dubbo/rpc/Exporter;
      68: invokevirtual #124                // Method org/apache/dubbo/registry/integration/RegistryProtocol$ExporterChangeableWrapper.setExporter:(Lorg/apache/dubbo/rpc/Exporter;)V
      71: aload         7
      73: aload         5
      75: invokevirtual #125                // Method org/apache/dubbo/common/URL.equals:(Ljava/lang/Object;)Z
      78: ifne          195
      81: aload_0
      82: aload_1
      83: aload         4
      85: aload         6
      87: aload         5
      89: aload         7
      91: invokespecial #126                // Method doReExport:(Lorg/apache/dubbo/rpc/Invoker;Lorg/apache/dubbo/registry/integration/RegistryProtocol$ExporterChangeableWrapper;Lorg/apache/dubbo/common/URL;Lorg/apache/dubbo/common/URL;Lorg/apache/dubbo/common/URL;)V
      94: goto          195
      97: astore        9
      99: aload_0
     100: getfield      #30                 // Field reExportFailedTasks:Ljava/util/concurrent/ConcurrentMap;
     103: aload         5
     105: invokeinterface #120,  2          // InterfaceMethod java/util/concurrent/ConcurrentMap.get:(Ljava/lang/Object;)Ljava/lang/Object;
     110: checkcast     #128                // class org/apache/dubbo/registry/retry/ReExportTask
     113: astore        10
     115: aload         10
     117: ifnull        121
     120: return
     121: new           #128                // class org/apache/dubbo/registry/retry/ReExportTask
     124: dup
     125: aload_0
     126: aload_1
     127: aload         4
     129: aload         6
     131: aload         5
     133: aload         7
     135: invokedynamic #129,  0            // InvokeDynamic #4:run:(Lorg/apache/dubbo/registry/integration/RegistryProtocol;Lorg/apache/dubbo/rpc/Invoker;Lorg/apache/dubbo/registry/integration/RegistryProtocol$ExporterChangeableWrapper;Lorg/apache/dubbo/common/URL;Lorg/apache/dubbo/common/URL;Lorg/apache/dubbo/common/URL;)Ljava/lang/Runnable;
     140: aload         5
     142: aconst_null
     143: invokespecial #130                // Method org/apache/dubbo/registry/retry/ReExportTask."<init>":(Ljava/lang/Runnable;Lorg/apache/dubbo/common/URL;Lorg/apache/dubbo/registry/support/FailbackRegistry;)V
     146: astore        11
     148: aload_0
     149: getfield      #30                 // Field reExportFailedTasks:Ljava/util/concurrent/ConcurrentMap;
     152: aload         5
     154: aload         11
     156: invokeinterface #131,  3          // InterfaceMethod java/util/concurrent/ConcurrentMap.putIfAbsent:(Ljava/lang/Object;Ljava/lang/Object;)Ljava/lang/Object;
     161: checkcast     #128                // class org/apache/dubbo/registry/retry/ReExportTask
     164: astore        10
     166: aload         10
     168: ifnonnull     195
     171: aload_0
     172: getfield      #39                 // Field retryTimer:Lorg/apache/dubbo/common/timer/HashedWheelTimer;
     175: aload         11
     177: aload         6
     179: ldc           #132                // String retry.period
     181: sipush        5000
     184: invokevirtual #133                // Method org/apache/dubbo/common/URL.getParameter:(Ljava/lang/String;I)I
     187: i2l
     188: getstatic     #37                 // Field java/util/concurrent/TimeUnit.MILLISECONDS:Ljava/util/concurrent/TimeUnit;
     191: invokevirtual #134                // Method org/apache/dubbo/common/timer/HashedWheelTimer.newTimeout:(Lorg/apache/dubbo/common/timer/TimerTask;JLjava/util/concurrent/TimeUnit;)Lorg/apache/dubbo/common/timer/Timeout;
     194: pop
     195: return
    Exception table:
       from    to  target type
          81    94    97   Class java/lang/Exception

  private <T> void doReExport(org.apache.dubbo.rpc.Invoker<T>, org.apache.dubbo.registry.integration.RegistryProtocol$ExporterChangeableWrapper<T>, org.apache.dubbo.common.URL, org.apache.dubbo.common.URL, org.apache.dubbo.common.URL);
    Code:
       0: aload_0
       1: aload_1
       2: invokespecial #15                 // Method getProviderUrl:(Lorg/apache/dubbo/rpc/Invoker;)Lorg/apache/dubbo/common/URL;
       5: ldc           #79                 // String register
       7: iconst_1
       8: invokevirtual #80                 // Method org/apache/dubbo/common/URL.getParameter:(Ljava/lang/String;Z)Z
      11: ifeq          114
      14: aload_0
      15: aload_0
      16: aload_1
      17: invokevirtual #67                 // Method getRegistryUrl:(Lorg/apache/dubbo/rpc/Invoker;)Lorg/apache/dubbo/common/URL;
      20: invokevirtual #77                 // Method getRegistry:(Lorg/apache/dubbo/common/URL;)Lorg/apache/dubbo/registry/Registry;
      23: astore        6
      25: goto          40
      28: astore        7
      30: new           #135                // class org/apache/dubbo/registry/support/SkipFailbackWrapperException
      33: dup
      34: aload         7
      36: invokespecial #136                // Method org/apache/dubbo/registry/support/SkipFailbackWrapperException."<init>":(Ljava/lang/Throwable;)V
      39: athrow
      40: getstatic     #16                 // Field logger:Lorg/apache/dubbo/common/logger/ErrorTypeAwareLogger;
      43: new           #137                // class java/lang/StringBuilder
      46: dup
      47: invokespecial #138                // Method java/lang/StringBuilder."<init>":()V
      50: ldc           #139                // String Try to unregister old url:
      52: invokevirtual #140                // Method java/lang/StringBuilder.append:(Ljava/lang/String;)Ljava/lang/StringBuilder;
      55: aload         4
      57: invokevirtual #141                // Method java/lang/StringBuilder.append:(Ljava/lang/Object;)Ljava/lang/StringBuilder;
      60: invokevirtual #142                // Method java/lang/StringBuilder.toString:()Ljava/lang/String;
      63: invokeinterface #143,  2          // InterfaceMethod org/apache/dubbo/common/logger/ErrorTypeAwareLogger.info:(Ljava/lang/String;)V
      68: aload         6
      70: aload         4
      72: invokeinterface #144,  2          // InterfaceMethod org/apache/dubbo/registry/Registry.reExportUnregister:(Lorg/apache/dubbo/common/URL;)V
      77: getstatic     #16                 // Field logger:Lorg/apache/dubbo/common/logger/ErrorTypeAwareLogger;
      80: new           #137                // class java/lang/StringBuilder
      83: dup
      84: invokespecial #138                // Method java/lang/StringBuilder."<init>":()V
      87: ldc           #145                // String Try to register new url:
      89: invokevirtual #140                // Method java/lang/StringBuilder.append:(Ljava/lang/String;)Ljava/lang/StringBuilder;
      92: aload         5
      94: invokevirtual #141                // Method java/lang/StringBuilder.append:(Ljava/lang/Object;)Ljava/lang/StringBuilder;
      97: invokevirtual #142                // Method java/lang/StringBuilder.toString:()Ljava/lang/String;
     100: invokeinterface #143,  2          // InterfaceMethod org/apache/dubbo/common/logger/ErrorTypeAwareLogger.info:(Ljava/lang/String;)V
     105: aload         6
     107: aload         5
     109: invokeinterface #146,  2          // InterfaceMethod org/apache/dubbo/registry/Registry.reExportRegister:(Lorg/apache/dubbo/common/URL;)V
     114: aload_0
     115: aload_3
     116: aload         5
     118: invokespecial #147                // Method getStatedUrl:(Lorg/apache/dubbo/common/URL;Lorg/apache/dubbo/common/URL;)Lorg/apache/dubbo/rpc/model/ProviderModel$RegisterStatedURL;
     121: astore        6
     123: aload         6
     125: aload         5
     127: invokevirtual #148                // Method org/apache/dubbo/rpc/model/ProviderModel$RegisterStatedURL.setProviderUrl:(Lorg/apache/dubbo/common/URL;)V
     130: aload_2
     131: aload         5
     133: invokevirtual #83                 // Method org/apache/dubbo/registry/integration/RegistryProtocol$ExporterChangeableWrapper.setRegisterUrl:(Lorg/apache/dubbo/common/URL;)V
     136: goto          151
     139: astore        6
     141: new           #135                // class org/apache/dubbo/registry/support/SkipFailbackWrapperException
     144: dup
     145: aload         6
     147: invokespecial #136                // Method org/apache/dubbo/registry/support/SkipFailbackWrapperException."<init>":(Ljava/lang/Throwable;)V
     150: athrow
     151: return
    Exception table:
       from    to  target type
          14    25    28   Class java/lang/Exception
         114   136   139   Class java/lang/Exception

  private org.apache.dubbo.rpc.model.ProviderModel$RegisterStatedURL getStatedUrl(org.apache.dubbo.common.URL, org.apache.dubbo.common.URL);
    Code:
       0: aload_0
       1: getfield      #40                 // Field frameworkModel:Lorg/apache/dubbo/rpc/model/FrameworkModel;
       4: invokevirtual #149                // Method org/apache/dubbo/rpc/model/FrameworkModel.getServiceRepository:()Lorg/apache/dubbo/rpc/model/FrameworkServiceRepository;
       7: aload_2
       8: invokevirtual #113                // Method org/apache/dubbo/common/URL.getServiceKey:()Ljava/lang/String;
      11: invokevirtual #150                // Method org/apache/dubbo/rpc/model/FrameworkServiceRepository.lookupExportedService:(Ljava/lang/String;)Lorg/apache/dubbo/rpc/model/ProviderModel;
      14: astore_3
      15: aload_3
      16: invokevirtual #151                // Method org/apache/dubbo/rpc/model/ProviderModel.getStatedUrl:()Ljava/util/List;
      19: astore        4
      21: aload         4
      23: invokeinterface #152,  1          // InterfaceMethod java/util/List.stream:()Ljava/util/stream/Stream;
      28: aload_1
      29: aload_2
      30: invokedynamic #153,  0            // InvokeDynamic #5:test:(Lorg/apache/dubbo/common/URL;Lorg/apache/dubbo/common/URL;)Ljava/util/function/Predicate;
      35: invokeinterface #22,  2           // InterfaceMethod java/util/stream/Stream.filter:(Ljava/util/function/Predicate;)Ljava/util/stream/Stream;
      40: invokeinterface #154,  1          // InterfaceMethod java/util/stream/Stream.findFirst:()Ljava/util/Optional;
      45: invokedynamic #155,  0            // InvokeDynamic #6:get:()Ljava/util/function/Supplier;
      50: invokevirtual #156                // Method java/util/Optional.orElseThrow:(Ljava/util/function/Supplier;)Ljava/lang/Object;
      53: checkcast     #64                 // class org/apache/dubbo/rpc/model/ProviderModel$RegisterStatedURL
      56: areturn

  protected org.apache.dubbo.registry.Registry getRegistry(org.apache.dubbo.common.URL);
    Code:
       0: ldc           #157                // class org/apache/dubbo/registry/RegistryFactory
       2: aload_1
       3: invokevirtual #86                 // Method org/apache/dubbo/common/URL.getScopeModel:()Lorg/apache/dubbo/rpc/model/ScopeModel;
       6: invokestatic  #102                // Method org/apache/dubbo/rpc/model/ScopeModelUtil.getExtensionLoader:(Ljava/lang/Class;Lorg/apache/dubbo/rpc/model/ScopeModel;)Lorg/apache/dubbo/common/extension/ExtensionLoader;
       9: invokevirtual #158                // Method org/apache/dubbo/common/extension/ExtensionLoader.getAdaptiveExtension:()Ljava/lang/Object;
      12: checkcast     #157                // class org/apache/dubbo/registry/RegistryFactory
      15: astore_2
      16: aload_2
      17: aload_1
      18: invokeinterface #159,  2          // InterfaceMethod org/apache/dubbo/registry/RegistryFactory.getRegistry:(Lorg/apache/dubbo/common/URL;)Lorg/apache/dubbo/registry/Registry;
      23: areturn

  protected org.apache.dubbo.common.URL getRegistryUrl(org.apache.dubbo.rpc.Invoker<?>);
    Code:
       0: aload_1
       1: invokeinterface #104,  1          // InterfaceMethod org/apache/dubbo/rpc/Invoker.getUrl:()Lorg/apache/dubbo/common/URL;
       6: areturn

  protected org.apache.dubbo.common.URL getRegistryUrl(org.apache.dubbo.common.URL);
    Code:
       0: ldc           #160                // String service-discovery-registry
       2: aload_1
       3: invokevirtual #161                // Method org/apache/dubbo/common/URL.getProtocol:()Ljava/lang/String;
       6: invokevirtual #162                // Method java/lang/String.equals:(Ljava/lang/Object;)Z
       9: ifeq          14
      12: aload_1
      13: areturn
      14: aload_1
      15: ldc           #163                // String registry
      17: aload_1
      18: invokevirtual #161                // Method org/apache/dubbo/common/URL.getProtocol:()Ljava/lang/String;
      21: invokevirtual #164                // Method org/apache/dubbo/common/URL.addParameter:(Ljava/lang/String;Ljava/lang/String;)Lorg/apache/dubbo/common/URL;
      24: ldc           #160                // String service-discovery-registry
      26: invokevirtual #165                // Method org/apache/dubbo/common/URL.setProtocol:(Ljava/lang/String;)Lorg/apache/dubbo/common/URL;
      29: areturn

  private org.apache.dubbo.common.URL getUrlToRegistry(org.apache.dubbo.common.URL, org.apache.dubbo.common.URL);
    Code:
       0: aload_2
       1: ldc           #166                // String simplified
       3: iconst_0
       4: invokevirtual #80                 // Method org/apache/dubbo/common/URL.getParameter:(Ljava/lang/String;Z)Z
       7: ifne          111
      10: aload_1
      11: aload_1
      12: invokestatic  #167                // Method getFilteredKeys:(Lorg/apache/dubbo/common/URL;)[Ljava/lang/String;
      15: invokevirtual #168                // Method org/apache/dubbo/common/URL.removeParameters:([Ljava/lang/String;)Lorg/apache/dubbo/common/URL;
      18: bipush        15
      20: anewarray     #26                 // class java/lang/String
      23: dup
      24: iconst_0
      25: ldc           #169                // String monitor
      27: aastore
      28: dup
      29: iconst_1
      30: ldc           #170                // String bind.ip
      32: aastore
      33: dup
      34: iconst_2
      35: ldc           #171                // String bind.port
      37: aastore
      38: dup
      39: iconst_3
      40: ldc           #172                // String qos.enable
      42: aastore
      43: dup
      44: iconst_4
      45: ldc           #173                // String qos.host
      47: aastore
      48: dup
      49: iconst_5
      50: ldc           #174                // String qos.port
      52: aastore
      53: dup
      54: bipush        6
      56: ldc           #175                // String qos.accept.foreign.ip
      58: aastore
      59: dup
      60: bipush        7
      62: ldc           #176                // String validation
      64: aastore
      65: dup
      66: bipush        8
      68: ldc           #177                // String interfaces
      70: aastore
      71: dup
      72: bipush        9
      74: ldc           #178                // String register-mode
      76: aastore
      77: dup
      78: bipush        10
      80: ldc           #179                // String pid
      82: aastore
      83: dup
      84: bipush        11
      86: ldc           #180                // String file-cache
      88: aastore
      89: dup
      90: bipush        12
      92: ldc           #181                // String executor-management-mode
      94: aastore
      95: dup
      96: bipush        13
      98: ldc           #182                // String background
     100: aastore
     101: dup
     102: bipush        14
     104: ldc           #183                // String anyhost
     106: aastore
     107: invokevirtual #168                // Method org/apache/dubbo/common/URL.removeParameters:([Ljava/lang/String;)Lorg/apache/dubbo/common/URL;
     110: areturn
     111: aload_2
     112: ldc           #184                // String extra-keys
     114: ldc           #185                // String
     116: invokevirtual #186                // Method org/apache/dubbo/common/URL.getParameter:(Ljava/lang/String;Ljava/lang/String;)Ljava/lang/String;
     119: astore_3
     120: aload_1
     121: invokevirtual #187                // Method org/apache/dubbo/common/URL.getPath:()Ljava/lang/String;
     124: aload_1
     125: ldc           #188                // String interface
     127: invokevirtual #189                // Method org/apache/dubbo/common/URL.getParameter:(Ljava/lang/String;)Ljava/lang/String;
     130: invokevirtual #162                // Method java/lang/String.equals:(Ljava/lang/Object;)Z
     133: ifne          183
     136: aload_3
     137: invokestatic  #190                // Method org/apache/dubbo/common/utils/StringUtils.isNotEmpty:(Ljava/lang/String;)Z
     140: ifeq          163
     143: new           #137                // class java/lang/StringBuilder
     146: dup
     147: invokespecial #138                // Method java/lang/StringBuilder."<init>":()V
     150: aload_3
     151: invokevirtual #140                // Method java/lang/StringBuilder.append:(Ljava/lang/String;)Ljava/lang/StringBuilder;
     154: ldc           #191                // String ,
     156: invokevirtual #140                // Method java/lang/StringBuilder.append:(Ljava/lang/String;)Ljava/lang/StringBuilder;
     159: invokevirtual #142                // Method java/lang/StringBuilder.toString:()Ljava/lang/String;
     162: astore_3
     163: new           #137                // class java/lang/StringBuilder
     166: dup
     167: invokespecial #138                // Method java/lang/StringBuilder."<init>":()V
     170: aload_3
     171: invokevirtual #140                // Method java/lang/StringBuilder.append:(Ljava/lang/String;)Ljava/lang/StringBuilder;
     174: ldc           #188                // String interface
     176: invokevirtual #140                // Method java/lang/StringBuilder.append:(Ljava/lang/String;)Ljava/lang/StringBuilder;
     179: invokevirtual #142                // Method java/lang/StringBuilder.toString:()Ljava/lang/String;
     182: astore_3
     183: aload_0
     184: getstatic     #192                // Field DEFAULT_REGISTER_PROVIDER_KEYS:[Ljava/lang/String;
     187: getstatic     #193                // Field org/apache/dubbo/common/constants/CommonConstants.COMMA_SPLIT_PATTERN:Ljava/util/regex/Pattern;
     190: aload_3
     191: invokevirtual #194                // Method java/util/regex/Pattern.split:(Ljava/lang/CharSequence;)[Ljava/lang/String;
     194: invokevirtual #195                // Method getParamsToRegistry:([Ljava/lang/String;[Ljava/lang/String;)[Ljava/lang/String;
     197: astore        4
     199: aload_1
     200: aload         4
     202: aload_1
     203: ldc           #196                // String methods
     205: aconst_null
     206: checkcast     #25                 // class "[Ljava/lang/String;"
     209: invokevirtual #197                // Method org/apache/dubbo/common/URL.getParameter:(Ljava/lang/String;[Ljava/lang/String;)[Ljava/lang/String;
     212: invokestatic  #198                // Method org/apache/dubbo/common/URL.valueOf:(Lorg/apache/dubbo/common/URL;[Ljava/lang/String;[Ljava/lang/String;)Lorg/apache/dubbo/common/URL;
     215: areturn

  private org.apache.dubbo.common.URL getSubscribedOverrideUrl(org.apache.dubbo.common.URL);
    Code:
       0: aload_1
       1: ldc           #199                // String provider
       3: invokevirtual #165                // Method org/apache/dubbo/common/URL.setProtocol:(Ljava/lang/String;)Lorg/apache/dubbo/common/URL;
       6: iconst_4
       7: anewarray     #26                 // class java/lang/String
      10: dup
      11: iconst_0
      12: ldc           #200                // String category
      14: aastore
      15: dup
      16: iconst_1
      17: ldc           #201                // String configurators
      19: aastore
      20: dup
      21: iconst_2
      22: ldc           #202                // String check
      24: aastore
      25: dup
      26: iconst_3
      27: iconst_0
      28: invokestatic  #203                // Method java/lang/String.valueOf:(Z)Ljava/lang/String;
      31: aastore
      32: invokevirtual #204                // Method org/apache/dubbo/common/URL.addParameters:([Ljava/lang/String;)Lorg/apache/dubbo/common/URL;
      35: areturn

  private org.apache.dubbo.common.URL getProviderUrl(org.apache.dubbo.rpc.Invoker<?>);
    Code:
       0: aload_1
       1: invokeinterface #104,  1          // InterfaceMethod org/apache/dubbo/rpc/Invoker.getUrl:()Lorg/apache/dubbo/common/URL;
       6: ldc           #205                // String export
       8: invokevirtual #206                // Method org/apache/dubbo/common/URL.getAttribute:(Ljava/lang/String;)Ljava/lang/Object;
      11: astore_2
      12: aload_2
      13: instanceof    #207                // class org/apache/dubbo/common/URL
      16: ifne          54
      19: new           #208                // class java/lang/IllegalArgumentException
      22: dup
      23: new           #137                // class java/lang/StringBuilder
      26: dup
      27: invokespecial #138                // Method java/lang/StringBuilder."<init>":()V
      30: ldc           #209                // String The registry export url is null! registry:
      32: invokevirtual #140                // Method java/lang/StringBuilder.append:(Ljava/lang/String;)Ljava/lang/StringBuilder;
      35: aload_1
      36: invokeinterface #104,  1          // InterfaceMethod org/apache/dubbo/rpc/Invoker.getUrl:()Lorg/apache/dubbo/common/URL;
      41: invokevirtual #210                // Method org/apache/dubbo/common/URL.getAddress:()Ljava/lang/String;
      44: invokevirtual #140                // Method java/lang/StringBuilder.append:(Ljava/lang/String;)Ljava/lang/StringBuilder;
      47: invokevirtual #142                // Method java/lang/StringBuilder.toString:()Ljava/lang/String;
      50: invokespecial #211                // Method java/lang/IllegalArgumentException."<init>":(Ljava/lang/String;)V
      53: athrow
      54: aload_2
      55: checkcast     #207                // class org/apache/dubbo/common/URL
      58: areturn

  private java.lang.String getCacheKey(org.apache.dubbo.rpc.Invoker<?>);
    Code:
       0: aload_0
       1: aload_1
       2: invokespecial #15                 // Method getProviderUrl:(Lorg/apache/dubbo/rpc/Invoker;)Lorg/apache/dubbo/common/URL;
       5: astore_2
       6: aload_2
       7: iconst_2
       8: anewarray     #26                 // class java/lang/String
      11: dup
      12: iconst_0
      13: ldc           #212                // String dynamic
      15: aastore
      16: dup
      17: iconst_1
      18: ldc           #213                // String enabled
      20: aastore
      21: invokevirtual #168                // Method org/apache/dubbo/common/URL.removeParameters:([Ljava/lang/String;)Lorg/apache/dubbo/common/URL;
      24: invokevirtual #214                // Method org/apache/dubbo/common/URL.toFullString:()Ljava/lang/String;
      27: astore_3
      28: aload_3
      29: areturn

  public <T> org.apache.dubbo.rpc.Invoker<T> refer(java.lang.Class<T>, org.apache.dubbo.common.URL) throws org.apache.dubbo.rpc.RpcException;
    Code:
       0: aload_0
       1: aload_2
       2: invokevirtual #215                // Method getRegistryUrl:(Lorg/apache/dubbo/common/URL;)Lorg/apache/dubbo/common/URL;
       5: astore_2
       6: aload_0
       7: aload_2
       8: invokevirtual #77                 // Method getRegistry:(Lorg/apache/dubbo/common/URL;)Lorg/apache/dubbo/registry/Registry;
      11: astore_3
      12: ldc           #216                // class org/apache/dubbo/registry/RegistryService
      14: aload_1
      15: invokevirtual #217                // Method java/lang/Object.equals:(Ljava/lang/Object;)Z
      18: ifeq          34
      21: aload_0
      22: getfield      #42                 // Field proxyFactory:Lorg/apache/dubbo/rpc/ProxyFactory;
      25: aload_3
      26: aload_1
      27: aload_2
      28: invokeinterface #218,  4          // InterfaceMethod org/apache/dubbo/rpc/ProxyFactory.getInvoker:(Ljava/lang/Object;Ljava/lang/Class;Lorg/apache/dubbo/common/URL;)Lorg/apache/dubbo/rpc/Invoker;
      33: areturn
      34: aload_2
      35: ldc           #219                // String refer
      37: invokevirtual #206                // Method org/apache/dubbo/common/URL.getAttribute:(Ljava/lang/String;)Ljava/lang/Object;
      40: checkcast     #220                // class java/util/Map
      43: astore        4
      45: aload         4
      47: ldc           #221                // String group
      49: invokeinterface #222,  2          // InterfaceMethod java/util/Map.get:(Ljava/lang/Object;)Ljava/lang/Object;
      54: checkcast     #26                 // class java/lang/String
      57: astore        5
      59: aload         5
      61: invokestatic  #190                // Method org/apache/dubbo/common/utils/StringUtils.isNotEmpty:(Ljava/lang/String;)Z
      64: ifeq          109
      67: getstatic     #193                // Field org/apache/dubbo/common/constants/CommonConstants.COMMA_SPLIT_PATTERN:Ljava/util/regex/Pattern;
      70: aload         5
      72: invokevirtual #194                // Method java/util/regex/Pattern.split:(Ljava/lang/CharSequence;)[Ljava/lang/String;
      75: arraylength
      76: iconst_1
      77: if_icmpgt     90
      80: ldc           #223                // String *
      82: aload         5
      84: invokevirtual #162                // Method java/lang/String.equals:(Ljava/lang/Object;)Z
      87: ifeq          109
      90: aload_0
      91: aload_2
      92: invokevirtual #86                 // Method org/apache/dubbo/common/URL.getScopeModel:()Lorg/apache/dubbo/rpc/model/ScopeModel;
      95: ldc           #225                // String mergeable
      97: invokestatic  #226                // InterfaceMethod org/apache/dubbo/rpc/cluster/Cluster.getCluster:(Lorg/apache/dubbo/rpc/model/ScopeModel;Ljava/lang/String;)Lorg/apache/dubbo/rpc/cluster/Cluster;
     100: aload_3
     101: aload_1
     102: aload_2
     103: aload         4
     105: invokevirtual #227                // Method doRefer:(Lorg/apache/dubbo/rpc/cluster/Cluster;Lorg/apache/dubbo/registry/Registry;Ljava/lang/Class;Lorg/apache/dubbo/common/URL;Ljava/util/Map;)Lorg/apache/dubbo/rpc/Invoker;
     108: areturn
     109: aload_2
     110: invokevirtual #86                 // Method org/apache/dubbo/common/URL.getScopeModel:()Lorg/apache/dubbo/rpc/model/ScopeModel;
     113: aload         4
     115: ldc           #228                // String cluster
     117: invokeinterface #222,  2          // InterfaceMethod java/util/Map.get:(Ljava/lang/Object;)Ljava/lang/Object;
     122: checkcast     #26                 // class java/lang/String
     125: invokestatic  #226                // InterfaceMethod org/apache/dubbo/rpc/cluster/Cluster.getCluster:(Lorg/apache/dubbo/rpc/model/ScopeModel;Ljava/lang/String;)Lorg/apache/dubbo/rpc/cluster/Cluster;
     128: astore        6
     130: aload_0
     131: aload         6
     133: aload_3
     134: aload_1
     135: aload_2
     136: aload         4
     138: invokevirtual #227                // Method doRefer:(Lorg/apache/dubbo/rpc/cluster/Cluster;Lorg/apache/dubbo/registry/Registry;Ljava/lang/Class;Lorg/apache/dubbo/common/URL;Ljava/util/Map;)Lorg/apache/dubbo/rpc/Invoker;
     141: areturn

  protected <T> org.apache.dubbo.rpc.Invoker<T> doRefer(org.apache.dubbo.rpc.cluster.Cluster, org.apache.dubbo.registry.Registry, java.lang.Class<T>, org.apache.dubbo.common.URL, java.util.Map<java.lang.String, java.lang.String>);
    Code:
       0: new           #43                 // class java/util/HashMap
       3: dup
       4: aload         4
       6: invokevirtual #229                // Method org/apache/dubbo/common/URL.getAttributes:()Ljava/util/Map;
       9: invokespecial #230                // Method java/util/HashMap."<init>":(Ljava/util/Map;)V
      12: astore        6
      14: aload         6
      16: ldc           #219                // String refer
      18: invokeinterface #231,  2          // InterfaceMethod java/util/Map.remove:(Ljava/lang/Object;)Ljava/lang/Object;
      23: pop
      24: aload         5
      26: ldc           #232                // String protocol
      28: invokeinterface #222,  2          // InterfaceMethod java/util/Map.get:(Ljava/lang/Object;)Ljava/lang/Object;
      33: checkcast     #26                 // class java/lang/String
      36: invokestatic  #233                // Method org/apache/dubbo/common/utils/StringUtils.isEmpty:(Ljava/lang/String;)Z
      39: ifeq          47
      42: ldc           #234                // String consumer
      44: goto          59
      47: aload         5
      49: ldc           #232                // String protocol
      51: invokeinterface #222,  2          // InterfaceMethod java/util/Map.get:(Ljava/lang/Object;)Ljava/lang/Object;
      56: checkcast     #26                 // class java/lang/String
      59: astore        7
      61: new           #235                // class org/apache/dubbo/common/url/component/ServiceConfigURL
      64: dup
      65: aload         7
      67: aconst_null
      68: aconst_null
      69: aload         5
      71: ldc           #236                // String register.ip
      73: invokeinterface #222,  2          // InterfaceMethod java/util/Map.get:(Ljava/lang/Object;)Ljava/lang/Object;
      78: checkcast     #26                 // class java/lang/String
      81: iconst_0
      82: aload_0
      83: aload         5
      85: aload_3
      86: invokespecial #237                // Method getPath:(Ljava/util/Map;Ljava/lang/Class;)Ljava/lang/String;
      89: aload         5
      91: aload         6
      93: invokespecial #238                // Method org/apache/dubbo/common/url/component/ServiceConfigURL."<init>":(Ljava/lang/String;Ljava/lang/String;Ljava/lang/String;Ljava/lang/String;ILjava/lang/String;Ljava/util/Map;Ljava/util/Map;)V
      96: astore        8
      98: aload         4
     100: ldc           #239                // String CONSUMER_URL
     102: aload         8
     104: invokevirtual #240                // Method org/apache/dubbo/common/URL.putAttribute:(Ljava/lang/String;Ljava/lang/Object;)Lorg/apache/dubbo/common/URL;
     107: astore        4
     109: aload_0
     110: aload_0
     111: aload_1
     112: aload_2
     113: aload_3
     114: aload         4
     116: aload         8
     118: invokevirtual #241                // Method getMigrationInvoker:(Lorg/apache/dubbo/registry/integration/RegistryProtocol;Lorg/apache/dubbo/rpc/cluster/Cluster;Lorg/apache/dubbo/registry/Registry;Ljava/lang/Class;Lorg/apache/dubbo/common/URL;Lorg/apache/dubbo/common/URL;)Lorg/apache/dubbo/rpc/cluster/ClusterInvoker;
     121: astore        9
     123: aload_0
     124: aload         9
     126: aload         4
     128: aload         8
     130: invokevirtual #242                // Method interceptInvoker:(Lorg/apache/dubbo/rpc/cluster/ClusterInvoker;Lorg/apache/dubbo/common/URL;Lorg/apache/dubbo/common/URL;)Lorg/apache/dubbo/rpc/Invoker;
     133: areturn

  private java.lang.String getPath(java.util.Map<java.lang.String, java.lang.String>, java.lang.Class<?>);
    Code:
       0: aload_1
       1: ldc           #243                // String generic
       3: invokeinterface #222,  2          // InterfaceMethod java/util/Map.get:(Ljava/lang/Object;)Ljava/lang/Object;
       8: checkcast     #26                 // class java/lang/String
      11: invokestatic  #244                // Method org/apache/dubbo/rpc/support/ProtocolUtils.isGeneric:(Ljava/lang/String;)Z
      14: ifne          24
      17: aload_2
      18: invokevirtual #245                // Method java/lang/Class.getName:()Ljava/lang/String;
      21: goto          35
      24: aload_1
      25: ldc           #188                // String interface
      27: invokeinterface #222,  2          // InterfaceMethod java/util/Map.get:(Ljava/lang/Object;)Ljava/lang/Object;
      32: checkcast     #26                 // class java/lang/String
      35: areturn

  protected <T> org.apache.dubbo.rpc.cluster.ClusterInvoker<T> getMigrationInvoker(org.apache.dubbo.registry.integration.RegistryProtocol, org.apache.dubbo.rpc.cluster.Cluster, org.apache.dubbo.registry.Registry, java.lang.Class<T>, org.apache.dubbo.common.URL, org.apache.dubbo.common.URL);
    Code:
       0: new           #246                // class org/apache/dubbo/registry/client/migration/ServiceDiscoveryMigrationInvoker
       3: dup
       4: aload_1
       5: aload_2
       6: aload_3
       7: aload         4
       9: aload         5
      11: aload         6
      13: invokespecial #247                // Method org/apache/dubbo/registry/client/migration/ServiceDiscoveryMigrationInvoker."<init>":(Lorg/apache/dubbo/registry/integration/RegistryProtocol;Lorg/apache/dubbo/rpc/cluster/Cluster;Lorg/apache/dubbo/registry/Registry;Ljava/lang/Class;Lorg/apache/dubbo/common/URL;Lorg/apache/dubbo/common/URL;)V
      16: areturn

  protected <T> org.apache.dubbo.rpc.Invoker<T> interceptInvoker(org.apache.dubbo.rpc.cluster.ClusterInvoker<T>, org.apache.dubbo.common.URL, org.apache.dubbo.common.URL);
    Code:
       0: aload_0
       1: aload_2
       2: invokevirtual #248                // Method findRegistryProtocolListeners:(Lorg/apache/dubbo/common/URL;)Ljava/util/List;
       5: astore        4
       7: aload         4
       9: invokestatic  #249                // Method org/apache/dubbo/common/utils/CollectionUtils.isEmpty:(Ljava/util/Collection;)Z
      12: ifeq          17
      15: aload_1
      16: areturn
      17: aload         4
      19: invokeinterface #53,  1           // InterfaceMethod java/util/List.iterator:()Ljava/util/Iterator;
      24: astore        5
      26: aload         5
      28: invokeinterface #54,  1           // InterfaceMethod java/util/Iterator.hasNext:()Z
      33: ifeq          62
      36: aload         5
      38: invokeinterface #55,  1           // InterfaceMethod java/util/Iterator.next:()Ljava/lang/Object;
      43: checkcast     #101                // class org/apache/dubbo/registry/integration/RegistryProtocolListener
      46: astore        6
      48: aload         6
      50: aload_0
      51: aload_1
      52: aload_3
      53: aload_2
      54: invokeinterface #250,  5          // InterfaceMethod org/apache/dubbo/registry/integration/RegistryProtocolListener.onRefer:(Lorg/apache/dubbo/registry/integration/RegistryProtocol;Lorg/apache/dubbo/rpc/cluster/ClusterInvoker;Lorg/apache/dubbo/common/URL;Lorg/apache/dubbo/common/URL;)V
      59: goto          26
      62: aload_1
      63: areturn

  public <T> org.apache.dubbo.rpc.cluster.ClusterInvoker<T> getServiceDiscoveryInvoker(org.apache.dubbo.rpc.cluster.Cluster, org.apache.dubbo.registry.Registry, java.lang.Class<T>, org.apache.dubbo.common.URL);
    Code:
       0: new           #251                // class org/apache/dubbo/registry/client/ServiceDiscoveryRegistryDirectory
       3: dup
       4: aload_3
       5: aload         4
       7: invokespecial #252                // Method org/apache/dubbo/registry/client/ServiceDiscoveryRegistryDirectory."<init>":(Ljava/lang/Class;Lorg/apache/dubbo/common/URL;)V
      10: astore        5
      12: aload_0
      13: aload         5
      15: aload_1
      16: aload_2
      17: aload_3
      18: invokevirtual #253                // Method doCreateInvoker:(Lorg/apache/dubbo/registry/integration/DynamicDirectory;Lorg/apache/dubbo/rpc/cluster/Cluster;Lorg/apache/dubbo/registry/Registry;Ljava/lang/Class;)Lorg/apache/dubbo/rpc/cluster/ClusterInvoker;
      21: areturn

  public <T> org.apache.dubbo.rpc.cluster.ClusterInvoker<T> getInvoker(org.apache.dubbo.rpc.cluster.Cluster, org.apache.dubbo.registry.Registry, java.lang.Class<T>, org.apache.dubbo.common.URL);
    Code:
       0: new           #254                // class org/apache/dubbo/registry/integration/RegistryDirectory
       3: dup
       4: aload_3
       5: aload         4
       7: invokespecial #255                // Method org/apache/dubbo/registry/integration/RegistryDirectory."<init>":(Ljava/lang/Class;Lorg/apache/dubbo/common/URL;)V
      10: astore        5
      12: aload_0
      13: aload         5
      15: aload_1
      16: aload_2
      17: aload_3
      18: invokevirtual #253                // Method doCreateInvoker:(Lorg/apache/dubbo/registry/integration/DynamicDirectory;Lorg/apache/dubbo/rpc/cluster/Cluster;Lorg/apache/dubbo/registry/Registry;Ljava/lang/Class;)Lorg/apache/dubbo/rpc/cluster/ClusterInvoker;
      21: areturn

  protected <T> org.apache.dubbo.rpc.cluster.ClusterInvoker<T> doCreateInvoker(org.apache.dubbo.registry.integration.DynamicDirectory<T>, org.apache.dubbo.rpc.cluster.Cluster, org.apache.dubbo.registry.Registry, java.lang.Class<T>);
    Code:
       0: aload_1
       1: aload_3
       2: invokevirtual #256                // Method org/apache/dubbo/registry/integration/DynamicDirectory.setRegistry:(Lorg/apache/dubbo/registry/Registry;)V
       5: aload_1
       6: aload_0
       7: getfield      #41                 // Field protocol:Lorg/apache/dubbo/rpc/Protocol;
      10: invokevirtual #257                // Method org/apache/dubbo/registry/integration/DynamicDirectory.setProtocol:(Lorg/apache/dubbo/rpc/Protocol;)V
      13: new           #43                 // class java/util/HashMap
      16: dup
      17: aload_1
      18: invokevirtual #258                // Method org/apache/dubbo/registry/integration/DynamicDirectory.getConsumerUrl:()Lorg/apache/dubbo/common/URL;
      21: invokevirtual #17                 // Method org/apache/dubbo/common/URL.getParameters:()Ljava/util/Map;
      24: invokespecial #230                // Method java/util/HashMap."<init>":(Ljava/util/Map;)V
      27: astore        5
      29: new           #235                // class org/apache/dubbo/common/url/component/ServiceConfigURL
      32: dup
      33: aload         5
      35: ldc           #232                // String protocol
      37: invokeinterface #222,  2          // InterfaceMethod java/util/Map.get:(Ljava/lang/Object;)Ljava/lang/Object;
      42: ifnonnull     50
      45: ldc           #234                // String consumer
      47: goto          62
      50: aload         5
      52: ldc           #232                // String protocol
      54: invokeinterface #222,  2          // InterfaceMethod java/util/Map.get:(Ljava/lang/Object;)Ljava/lang/Object;
      59: checkcast     #26                 // class java/lang/String
      62: aload         5
      64: ldc           #236                // String register.ip
      66: invokeinterface #231,  2          // InterfaceMethod java/util/Map.remove:(Ljava/lang/Object;)Ljava/lang/Object;
      71: checkcast     #26                 // class java/lang/String
      74: iconst_0
      75: aload_0
      76: aload         5
      78: aload         4
      80: invokespecial #237                // Method getPath:(Ljava/util/Map;Ljava/lang/Class;)Ljava/lang/String;
      83: aload         5
      85: invokespecial #259                // Method org/apache/dubbo/common/url/component/ServiceConfigURL."<init>":(Ljava/lang/String;Ljava/lang/String;ILjava/lang/String;Ljava/util/Map;)V
      88: astore        6
      90: aload         6
      92: aload_1
      93: invokevirtual #258                // Method org/apache/dubbo/registry/integration/DynamicDirectory.getConsumerUrl:()Lorg/apache/dubbo/common/URL;
      96: invokevirtual #86                 // Method org/apache/dubbo/common/URL.getScopeModel:()Lorg/apache/dubbo/rpc/model/ScopeModel;
      99: invokevirtual #260                // Method org/apache/dubbo/common/URL.setScopeModel:(Lorg/apache/dubbo/rpc/model/ScopeModel;)Lorg/apache/dubbo/common/URL;
     102: astore        6
     104: aload         6
     106: aload_1
     107: invokevirtual #258                // Method org/apache/dubbo/registry/integration/DynamicDirectory.getConsumerUrl:()Lorg/apache/dubbo/common/URL;
     110: invokevirtual #62                 // Method org/apache/dubbo/common/URL.getServiceModel:()Lorg/apache/dubbo/rpc/model/ServiceModel;
     113: invokevirtual #261                // Method org/apache/dubbo/common/URL.setServiceModel:(Lorg/apache/dubbo/rpc/model/ServiceModel;)Lorg/apache/dubbo/common/URL;
     116: astore        6
     118: aload_1
     119: invokevirtual #262                // Method org/apache/dubbo/registry/integration/DynamicDirectory.isShouldRegister:()Z
     122: ifeq          141
     125: aload_1
     126: aload         6
     128: invokevirtual #263                // Method org/apache/dubbo/registry/integration/DynamicDirectory.setRegisteredConsumerUrl:(Lorg/apache/dubbo/common/URL;)V
     131: aload_3
     132: aload_1
     133: invokevirtual #264                // Method org/apache/dubbo/registry/integration/DynamicDirectory.getRegisteredConsumerUrl:()Lorg/apache/dubbo/common/URL;
     136: invokeinterface #60,  2           // InterfaceMethod org/apache/dubbo/registry/Registry.register:(Lorg/apache/dubbo/common/URL;)V
     141: aload_1
     142: aload         6
     144: invokevirtual #265                // Method org/apache/dubbo/registry/integration/DynamicDirectory.buildRouterChain:(Lorg/apache/dubbo/common/URL;)V
     147: aload_1
     148: aload         6
     150: invokestatic  #266                // Method toSubscribeUrl:(Lorg/apache/dubbo/common/URL;)Lorg/apache/dubbo/common/URL;
     153: invokevirtual #267                // Method org/apache/dubbo/registry/integration/DynamicDirectory.subscribe:(Lorg/apache/dubbo/common/URL;)V
     156: aload_2
     157: aload_1
     158: iconst_1
     159: invokeinterface #268,  3          // InterfaceMethod org/apache/dubbo/rpc/cluster/Cluster.join:(Lorg/apache/dubbo/rpc/cluster/Directory;Z)Lorg/apache/dubbo/rpc/Invoker;
     164: checkcast     #269                // class org/apache/dubbo/rpc/cluster/ClusterInvoker
     167: areturn

  public <T> void reRefer(org.apache.dubbo.rpc.cluster.ClusterInvoker<?>, org.apache.dubbo.common.URL);
    Code:
       0: aload_1
       1: instanceof    #270                // class org/apache/dubbo/registry/client/migration/MigrationClusterInvoker
       4: ifne          46
       7: getstatic     #16                 // Field logger:Lorg/apache/dubbo/common/logger/ErrorTypeAwareLogger;
      10: ldc_w         #271                // String 1-16
      13: ldc           #185                // String
      15: ldc           #185                // String
      17: new           #137                // class java/lang/StringBuilder
      20: dup
      21: invokespecial #138                // Method java/lang/StringBuilder."<init>":()V
      24: ldc_w         #272                // String Only invoker type of MigrationClusterInvoker supports reRefer, current invoker is
      27: invokevirtual #140                // Method java/lang/StringBuilder.append:(Ljava/lang/String;)Ljava/lang/StringBuilder;
      30: aload_1
      31: invokevirtual #273                // Method java/lang/Object.getClass:()Ljava/lang/Class;
      34: invokevirtual #141                // Method java/lang/StringBuilder.append:(Ljava/lang/Object;)Ljava/lang/StringBuilder;
      37: invokevirtual #142                // Method java/lang/StringBuilder.toString:()Ljava/lang/String;
      40: invokeinterface #274,  5          // InterfaceMethod org/apache/dubbo/common/logger/ErrorTypeAwareLogger.error:(Ljava/lang/String;Ljava/lang/String;Ljava/lang/String;Ljava/lang/String;)V
      45: return
      46: aload_1
      47: checkcast     #270                // class org/apache/dubbo/registry/client/migration/MigrationClusterInvoker
      50: astore_3
      51: aload_3
      52: aload_2
      53: invokeinterface #275,  2          // InterfaceMethod org/apache/dubbo/registry/client/migration/MigrationClusterInvoker.reRefer:(Lorg/apache/dubbo/common/URL;)V
      58: return

  public static org.apache.dubbo.common.URL toSubscribeUrl(org.apache.dubbo.common.URL);
    Code:
       0: aload_0
       1: ldc           #200                // String category
       3: ldc_w         #276                // String providers,configurators,routers
       6: invokevirtual #164                // Method org/apache/dubbo/common/URL.addParameter:(Ljava/lang/String;Ljava/lang/String;)Lorg/apache/dubbo/common/URL;
       9: areturn

  protected java.util.List<org.apache.dubbo.registry.integration.RegistryProtocolListener> findRegistryProtocolListeners(org.apache.dubbo.common.URL);
    Code:
       0: ldc           #101                // class org/apache/dubbo/registry/integration/RegistryProtocolListener
       2: aload_1
       3: invokevirtual #86                 // Method org/apache/dubbo/common/URL.getScopeModel:()Lorg/apache/dubbo/rpc/model/ScopeModel;
       6: invokestatic  #102                // Method org/apache/dubbo/rpc/model/ScopeModelUtil.getExtensionLoader:(Ljava/lang/Class;Lorg/apache/dubbo/rpc/model/ScopeModel;)Lorg/apache/dubbo/common/extension/ExtensionLoader;
       9: aload_1
      10: ldc           #105                // String registry.protocol.listener
      12: invokevirtual #106                // Method org/apache/dubbo/common/extension/ExtensionLoader.getActivateExtension:(Lorg/apache/dubbo/common/URL;Ljava/lang/String;)Ljava/util/List;
      15: areturn

  public java.lang.String[] getParamsToRegistry(java.lang.String[], java.lang.String[]);
    Code:
       0: aload_2
       1: arraylength
       2: istore_3
       3: aload_1
       4: arraylength
       5: iload_3
       6: iadd
       7: anewarray     #26                 // class java/lang/String
      10: astore        4
      12: aload_1
      13: iconst_0
      14: aload         4
      16: iconst_0
      17: aload_1
      18: arraylength
      19: invokestatic  #277                // Method java/lang/System.arraycopy:(Ljava/lang/Object;ILjava/lang/Object;II)V
      22: aload_2
      23: iconst_0
      24: aload         4
      26: aload_1
      27: arraylength
      28: iload_3
      29: invokestatic  #277                // Method java/lang/System.arraycopy:(Ljava/lang/Object;ILjava/lang/Object;II)V
      32: aload         4
      34: areturn

  public void destroy();
    Code:
       0: aload_0
       1: getfield      #40                 // Field frameworkModel:Lorg/apache/dubbo/rpc/model/FrameworkModel;
       4: invokevirtual #45                 // Method org/apache/dubbo/rpc/model/FrameworkModel.getApplicationModels:()Ljava/util/List;
       7: invokeinterface #53,  1           // InterfaceMethod java/util/List.iterator:()Ljava/util/Iterator;
      12: astore_1
      13: aload_1
      14: invokeinterface #54,  1           // InterfaceMethod java/util/Iterator.hasNext:()Z
      19: ifeq          129
      22: aload_1
      23: invokeinterface #55,  1           // InterfaceMethod java/util/Iterator.next:()Ljava/lang/Object;
      28: checkcast     #48                 // class org/apache/dubbo/rpc/model/ApplicationModel
      31: astore_2
      32: aload_2
      33: invokevirtual #278                // Method org/apache/dubbo/rpc/model/ApplicationModel.getModuleModels:()Ljava/util/List;
      36: invokeinterface #53,  1           // InterfaceMethod java/util/List.iterator:()Ljava/util/Iterator;
      41: astore_3
      42: aload_3
      43: invokeinterface #54,  1           // InterfaceMethod java/util/Iterator.hasNext:()Z
      48: ifeq          126
      51: aload_3
      52: invokeinterface #55,  1           // InterfaceMethod java/util/Iterator.next:()Ljava/lang/Object;
      57: checkcast     #279                // class org/apache/dubbo/rpc/model/ModuleModel
      60: astore        4
      62: aload         4
      64: ldc           #101                // class org/apache/dubbo/registry/integration/RegistryProtocolListener
      66: invokevirtual #280                // Method org/apache/dubbo/rpc/model/ModuleModel.getExtensionLoader:(Ljava/lang/Class;)Lorg/apache/dubbo/common/extension/ExtensionLoader;
      69: invokevirtual #281                // Method org/apache/dubbo/common/extension/ExtensionLoader.getLoadedExtensionInstances:()Ljava/util/List;
      72: astore        5
      74: aload         5
      76: invokestatic  #107                // Method org/apache/dubbo/common/utils/CollectionUtils.isNotEmpty:(Ljava/util/Collection;)Z
      79: ifeq          123
      82: aload         5
      84: invokeinterface #53,  1           // InterfaceMethod java/util/List.iterator:()Ljava/util/Iterator;
      89: astore        6
      91: aload         6
      93: invokeinterface #54,  1           // InterfaceMethod java/util/Iterator.hasNext:()Z
      98: ifeq          123
     101: aload         6
     103: invokeinterface #55,  1           // InterfaceMethod java/util/Iterator.next:()Ljava/lang/Object;
     108: checkcast     #101                // class org/apache/dubbo/registry/integration/RegistryProtocolListener
     111: astore        7
     113: aload         7
     115: invokeinterface #282,  1          // InterfaceMethod org/apache/dubbo/registry/integration/RegistryProtocolListener.onDestroy:()V
     120: goto          91
     123: goto          42
     126: goto          13
     129: aload_0
     130: getfield      #40                 // Field frameworkModel:Lorg/apache/dubbo/rpc/model/FrameworkModel;
     133: invokevirtual #45                 // Method org/apache/dubbo/rpc/model/FrameworkModel.getApplicationModels:()Ljava/util/List;
     136: invokeinterface #53,  1           // InterfaceMethod java/util/List.iterator:()Ljava/util/Iterator;
     141: astore_1
     142: aload_1
     143: invokeinterface #54,  1           // InterfaceMethod java/util/Iterator.hasNext:()Z
     148: ifeq          301
     151: aload_1
     152: invokeinterface #55,  1           // InterfaceMethod java/util/Iterator.next:()Ljava/lang/Object;
     157: checkcast     #48                 // class org/apache/dubbo/rpc/model/ApplicationModel
     160: astore_2
     161: aload_2
     162: invokevirtual #88                 // Method org/apache/dubbo/rpc/model/ApplicationModel.getModelEnvironment:()Lorg/apache/dubbo/common/config/Environment;
     165: invokevirtual #89                 // Method org/apache/dubbo/common/config/Environment.getConfiguration:()Lorg/apache/dubbo/common/config/CompositeConfiguration;
     168: ldc           #90                 // class java/lang/Boolean
     170: ldc_w         #283                // String enable-configuration-listen
     173: iconst_1
     174: invokestatic  #92                 // Method java/lang/Boolean.valueOf:(Z)Ljava/lang/Boolean;
     177: invokevirtual #93                 // Method org/apache/dubbo/common/config/CompositeConfiguration.convert:(Ljava/lang/Class;Ljava/lang/String;Ljava/lang/Object;)Ljava/lang/Object;
     180: checkcast     #90                 // class java/lang/Boolean
     183: invokevirtual #94                 // Method java/lang/Boolean.booleanValue:()Z
     186: ifeq          298
     189: aload_2
     190: invokevirtual #284                // Method org/apache/dubbo/rpc/model/ApplicationModel.getPubModuleModels:()Ljava/util/List;
     193: invokeinterface #53,  1           // InterfaceMethod java/util/List.iterator:()Ljava/util/Iterator;
     198: astore_3
     199: aload_3
     200: invokeinterface #54,  1           // InterfaceMethod java/util/Iterator.hasNext:()Z
     205: ifeq          298
     208: aload_3
     209: invokeinterface #55,  1           // InterfaceMethod java/util/Iterator.next:()Ljava/lang/Object;
     214: checkcast     #279                // class org/apache/dubbo/rpc/model/ModuleModel
     217: astore        4
     219: aload_2
     220: invokevirtual #285                // Method org/apache/dubbo/rpc/model/ApplicationModel.tryGetApplicationName:()Ljava/lang/String;
     223: astore        5
     225: aload         5
     227: ifnonnull     233
     230: goto          199
     233: aload         4
     235: invokevirtual #286                // Method org/apache/dubbo/rpc/model/ModuleModel.getServiceRepository:()Lorg/apache/dubbo/rpc/model/ModuleServiceRepository;
     238: invokevirtual #287                // Method org/apache/dubbo/rpc/model/ModuleServiceRepository.getExportedServices:()Ljava/util/List;
     241: invokeinterface #46,  1           // InterfaceMethod java/util/List.size:()I
     246: ifle          295
     249: aload         4
     251: ldc_w         #288                // class org/apache/dubbo/rpc/cluster/governance/GovernanceRuleRepository
     254: invokevirtual #280                // Method org/apache/dubbo/rpc/model/ModuleModel.getExtensionLoader:(Ljava/lang/Class;)Lorg/apache/dubbo/common/extension/ExtensionLoader;
     257: invokevirtual #289                // Method org/apache/dubbo/common/extension/ExtensionLoader.getDefaultExtension:()Ljava/lang/Object;
     260: checkcast     #288                // class org/apache/dubbo/rpc/cluster/governance/GovernanceRuleRepository
     263: new           #137                // class java/lang/StringBuilder
     266: dup
     267: invokespecial #138                // Method java/lang/StringBuilder."<init>":()V
     270: aload         5
     272: invokevirtual #140                // Method java/lang/StringBuilder.append:(Ljava/lang/String;)Ljava/lang/StringBuilder;
     275: ldc_w         #290                // String .configurators
     278: invokevirtual #140                // Method java/lang/StringBuilder.append:(Ljava/lang/String;)Ljava/lang/StringBuilder;
     281: invokevirtual #142                // Method java/lang/StringBuilder.toString:()Ljava/lang/String;
     284: aload_0
     285: aload         4
     287: invokespecial #291                // Method getProviderConfigurationListener:(Lorg/apache/dubbo/rpc/model/ModuleModel;)Lorg/apache/dubbo/registry/integration/RegistryProtocol$ProviderConfigurationListener;
     290: invokeinterface #292,  3          // InterfaceMethod org/apache/dubbo/rpc/cluster/governance/GovernanceRuleRepository.removeListener:(Ljava/lang/String;Lorg/apache/dubbo/common/config/configcenter/ConfigurationListener;)V
     295: goto          199
     298: goto          142
     301: new           #293                // class java/util/ArrayList
     304: dup
     305: aload_0
     306: getfield      #13                 // Field bounds:Ljava/util/concurrent/ConcurrentMap;
     309: invokeinterface #294,  1          // InterfaceMethod java/util/concurrent/ConcurrentMap.values:()Ljava/util/Collection;
     314: invokespecial #295                // Method java/util/ArrayList."<init>":(Ljava/util/Collection;)V
     317: astore_1
     318: aload_1
     319: invokeinterface #53,  1           // InterfaceMethod java/util/List.iterator:()Ljava/util/Iterator;
     324: astore_2
     325: aload_2
     326: invokeinterface #54,  1           // InterfaceMethod java/util/Iterator.hasNext:()Z
     331: ifeq          353
     334: aload_2
     335: invokeinterface #55,  1           // InterfaceMethod java/util/Iterator.next:()Ljava/lang/Object;
     340: checkcast     #296                // class org/apache/dubbo/rpc/Exporter
     343: astore_3
     344: aload_3
     345: invokeinterface #297,  1          // InterfaceMethod org/apache/dubbo/rpc/Exporter.unexport:()V
     350: goto          325
     353: aload_0
     354: getfield      #13                 // Field bounds:Ljava/util/concurrent/ConcurrentMap;
     357: invokeinterface #298,  1          // InterfaceMethod java/util/concurrent/ConcurrentMap.clear:()V
     362: return

  public java.util.List<org.apache.dubbo.rpc.ProtocolServer> getServers();
    Code:
       0: aload_0
       1: getfield      #41                 // Field protocol:Lorg/apache/dubbo/rpc/Protocol;
       4: invokeinterface #299,  1          // InterfaceMethod org/apache/dubbo/rpc/Protocol.getServers:()Ljava/util/List;
       9: areturn

  private static org.apache.dubbo.common.URL getConfiguredInvokerUrl(java.util.List<org.apache.dubbo.rpc.cluster.Configurator>, org.apache.dubbo.common.URL);
    Code:
       0: aload_0
       1: invokestatic  #107                // Method org/apache/dubbo/common/utils/CollectionUtils.isNotEmpty:(Ljava/util/Collection;)Z
       4: ifeq          44
       7: aload_0
       8: invokeinterface #53,  1           // InterfaceMethod java/util/List.iterator:()Ljava/util/Iterator;
      13: astore_2
      14: aload_2
      15: invokeinterface #54,  1           // InterfaceMethod java/util/Iterator.hasNext:()Z
      20: ifeq          44
      23: aload_2
      24: invokeinterface #55,  1           // InterfaceMethod java/util/Iterator.next:()Ljava/lang/Object;
      29: checkcast     #300                // class org/apache/dubbo/rpc/cluster/Configurator
      32: astore_3
      33: aload_3
      34: aload_1
      35: invokeinterface #301,  2          // InterfaceMethod org/apache/dubbo/rpc/cluster/Configurator.configure:(Lorg/apache/dubbo/common/URL;)Lorg/apache/dubbo/common/URL;
      40: astore_1
      41: goto          14
      44: aload_1
      45: areturn

  private org.apache.dubbo.registry.integration.RegistryProtocol$ProviderConfigurationListener getProviderConfigurationListener(org.apache.dubbo.common.URL);
    Code:
       0: aload_0
       1: aload_1
       2: invokevirtual #111                // Method org/apache/dubbo/common/URL.getOrDefaultModuleModel:()Lorg/apache/dubbo/rpc/model/ModuleModel;
       5: invokespecial #291                // Method getProviderConfigurationListener:(Lorg/apache/dubbo/rpc/model/ModuleModel;)Lorg/apache/dubbo/registry/integration/RegistryProtocol$ProviderConfigurationListener;
       8: areturn

  private org.apache.dubbo.registry.integration.RegistryProtocol$ProviderConfigurationListener getProviderConfigurationListener(org.apache.dubbo.rpc.model.ModuleModel);
    Code:
       0: aload_1
       1: invokevirtual #302                // Method org/apache/dubbo/rpc/model/ModuleModel.getBeanFactory:()Lorg/apache/dubbo/common/beans/factory/ScopeBeanFactory;
       4: ldc           #50                 // class org/apache/dubbo/registry/integration/RegistryProtocol$ProviderConfigurationListener
       6: aload_0
       7: aload_1
       8: invokedynamic #303,  0            // InvokeDynamic #7:apply:(Lorg/apache/dubbo/registry/integration/RegistryProtocol;Lorg/apache/dubbo/rpc/model/ModuleModel;)Ljava/util/function/Function;
      13: invokevirtual #304                // Method org/apache/dubbo/common/beans/factory/ScopeBeanFactory.getOrRegisterBean:(Ljava/lang/Class;Ljava/util/function/Function;)Ljava/lang/Object;
      16: checkcast     #50                 // class org/apache/dubbo/registry/integration/RegistryProtocol$ProviderConfigurationListener
      19: areturn

  private org.apache.dubbo.registry.integration.RegistryProtocol$ProviderConfigurationListener lambda$getProviderConfigurationListener$7(org.apache.dubbo.rpc.model.ModuleModel, java.lang.Class);
    Code:
       0: new           #50                 // class org/apache/dubbo/registry/integration/RegistryProtocol$ProviderConfigurationListener
       3: dup
       4: aload_0
       5: aload_1
       6: invokespecial #305                // Method org/apache/dubbo/registry/integration/RegistryProtocol$ProviderConfigurationListener."<init>":(Lorg/apache/dubbo/registry/integration/RegistryProtocol;Lorg/apache/dubbo/rpc/model/ModuleModel;)V
       9: areturn

  private static java.lang.IllegalStateException lambda$getStatedUrl$6();
    Code:
       0: new           #306                // class java/lang/IllegalStateException
       3: dup
       4: ldc_w         #307                // String There should have at least one registered url.
       7: invokespecial #308                // Method java/lang/IllegalStateException."<init>":(Ljava/lang/String;)V
      10: areturn

  private static boolean lambda$getStatedUrl$5(org.apache.dubbo.common.URL, org.apache.dubbo.common.URL, org.apache.dubbo.rpc.model.ProviderModel$RegisterStatedURL);
    Code:
       0: aload_2
       1: invokevirtual #309                // Method org/apache/dubbo/rpc/model/ProviderModel$RegisterStatedURL.getRegistryUrl:()Lorg/apache/dubbo/common/URL;
       4: aload_0
       5: invokevirtual #125                // Method org/apache/dubbo/common/URL.equals:(Ljava/lang/Object;)Z
       8: ifeq          32
      11: aload_2
      12: invokevirtual #310                // Method org/apache/dubbo/rpc/model/ProviderModel$RegisterStatedURL.getProviderUrl:()Lorg/apache/dubbo/common/URL;
      15: invokevirtual #161                // Method org/apache/dubbo/common/URL.getProtocol:()Ljava/lang/String;
      18: aload_1
      19: invokevirtual #161                // Method org/apache/dubbo/common/URL.getProtocol:()Ljava/lang/String;
      22: invokevirtual #162                // Method java/lang/String.equals:(Ljava/lang/Object;)Z
      25: ifeq          32
      28: iconst_1
      29: goto          33
      32: iconst_0
      33: ireturn

  private void lambda$reExport$4(org.apache.dubbo.rpc.Invoker, org.apache.dubbo.registry.integration.RegistryProtocol$ExporterChangeableWrapper, org.apache.dubbo.common.URL, org.apache.dubbo.common.URL, org.apache.dubbo.common.URL);
    Code:
       0: aload_0
       1: aload_1
       2: aload_2
       3: aload_3
       4: aload         4
       6: aload         5
       8: invokespecial #126                // Method doReExport:(Lorg/apache/dubbo/rpc/Invoker;Lorg/apache/dubbo/registry/integration/RegistryProtocol$ExporterChangeableWrapper;Lorg/apache/dubbo/common/URL;Lorg/apache/dubbo/common/URL;Lorg/apache/dubbo/common/URL;)V
      11: return

  private org.apache.dubbo.registry.integration.RegistryProtocol$ExporterChangeableWrapper lambda$doLocalExport$3(org.apache.dubbo.rpc.Invoker, org.apache.dubbo.common.URL, java.lang.String);
    Code:
       0: new           #121                // class org/apache/dubbo/registry/integration/RegistryProtocol$InvokerDelegate
       3: dup
       4: aload_1
       5: aload_2
       6: invokespecial #122                // Method org/apache/dubbo/registry/integration/RegistryProtocol$InvokerDelegate."<init>":(Lorg/apache/dubbo/rpc/Invoker;Lorg/apache/dubbo/common/URL;)V
       9: astore        4
      11: new           #118                // class org/apache/dubbo/registry/integration/RegistryProtocol$ExporterChangeableWrapper
      14: dup
      15: aload_0
      16: aload_0
      17: getfield      #41                 // Field protocol:Lorg/apache/dubbo/rpc/Protocol;
      20: aload         4
      22: invokeinterface #123,  2          // InterfaceMethod org/apache/dubbo/rpc/Protocol.export:(Lorg/apache/dubbo/rpc/Invoker;)Lorg/apache/dubbo/rpc/Exporter;
      27: aload_1
      28: invokespecial #311                // Method org/apache/dubbo/registry/integration/RegistryProtocol$ExporterChangeableWrapper."<init>":(Lorg/apache/dubbo/registry/integration/RegistryProtocol;Lorg/apache/dubbo/rpc/Exporter;Lorg/apache/dubbo/rpc/Invoker;)V
      31: areturn

  private static java.util.Set lambda$export$2(org.apache.dubbo.common.URL);
    Code:
       0: new           #312                // class org/apache/dubbo/common/utils/ConcurrentHashSet
       3: dup
       4: invokespecial #313                // Method org/apache/dubbo/common/utils/ConcurrentHashSet."<init>":()V
       7: areturn

  private static java.lang.String[] lambda$getFilteredKeys$1(int);
    Code:
       0: iload_0
       1: anewarray     #26                 // class java/lang/String
       4: areturn

  private static boolean lambda$getFilteredKeys$0(java.lang.String);
    Code:
       0: aload_0
       1: ldc_w         #314                // String .
       4: invokevirtual #315                // Method java/lang/String.startsWith:(Ljava/lang/String;)Z
       7: ireturn

  static org.apache.dubbo.common.logger.ErrorTypeAwareLogger access$200();
    Code:
       0: getstatic     #16                 // Field logger:Lorg/apache/dubbo/common/logger/ErrorTypeAwareLogger;
       3: areturn

  static org.apache.dubbo.common.URL access$300(org.apache.dubbo.registry.integration.RegistryProtocol, org.apache.dubbo.rpc.Invoker);
    Code:
       0: aload_0
       1: aload_1
       2: invokespecial #15                 // Method getProviderUrl:(Lorg/apache/dubbo/rpc/Invoker;)Lorg/apache/dubbo/common/URL;
       5: areturn

  static java.lang.String access$400(org.apache.dubbo.registry.integration.RegistryProtocol, org.apache.dubbo.rpc.Invoker);
    Code:
       0: aload_0
       1: aload_1
       2: invokespecial #14                 // Method getCacheKey:(Lorg/apache/dubbo/rpc/Invoker;)Ljava/lang/String;
       5: areturn

  static java.util.concurrent.ConcurrentMap access$500(org.apache.dubbo.registry.integration.RegistryProtocol);
    Code:
       0: aload_0
       1: getfield      #13                 // Field bounds:Ljava/util/concurrent/ConcurrentMap;
       4: areturn

  static org.apache.dubbo.common.URL access$600(java.util.List, org.apache.dubbo.common.URL);
    Code:
       0: aload_0
       1: aload_1
       2: invokestatic  #12                 // Method getConfiguredInvokerUrl:(Ljava/util/List;Lorg/apache/dubbo/common/URL;)Lorg/apache/dubbo/common/URL;
       5: areturn

  static org.apache.dubbo.registry.integration.RegistryProtocol$ProviderConfigurationListener access$700(org.apache.dubbo.registry.integration.RegistryProtocol, org.apache.dubbo.common.URL);
    Code:
       0: aload_0
       1: aload_1
       2: invokespecial #11                 // Method getProviderConfigurationListener:(Lorg/apache/dubbo/common/URL;)Lorg/apache/dubbo/registry/integration/RegistryProtocol$ProviderConfigurationListener;
       5: areturn

  static java.util.Map access$800(org.apache.dubbo.registry.integration.RegistryProtocol);
    Code:
       0: aload_0
       1: getfield      #10                 // Field serviceConfigurationListeners:Ljava/util/Map;
       4: areturn

  static {};
    Code:
       0: bipush        22
       2: anewarray     #26                 // class java/lang/String
       5: dup
       6: iconst_0
       7: ldc_w         #316                // String application
      10: aastore
      11: dup
      12: iconst_1
      13: ldc_w         #317                // String codec
      16: aastore
      17: dup
      18: iconst_2
      19: ldc_w         #318                // String exchanger
      22: aastore
      23: dup
      24: iconst_3
      25: ldc_w         #319                // String serialization
      28: aastore
      29: dup
      30: iconst_4
      31: ldc_w         #320                // String prefer.serialization
      34: aastore
      35: dup
      36: iconst_5
      37: ldc           #228                // String cluster
      39: aastore
      40: dup
      41: bipush        6
      43: ldc_w         #321                // String connections
      46: aastore
      47: dup
      48: bipush        7
      50: ldc_w         #322                // String deprecated
      53: aastore
      54: dup
      55: bipush        8
      57: ldc           #221                // String group
      59: aastore
      60: dup
      61: bipush        9
      63: ldc_w         #323                // String loadbalance
      66: aastore
      67: dup
      68: bipush        10
      70: ldc_w         #324                // String mock
      73: aastore
      74: dup
      75: bipush        11
      77: ldc_w         #325                // String path
      80: aastore
      81: dup
      82: bipush        12
      84: ldc_w         #326                // String timeout
      87: aastore
      88: dup
      89: bipush        13
      91: ldc_w         #327                // String token
      94: aastore
      95: dup
      96: bipush        14
      98: ldc_w         #328                // String version
     101: aastore
     102: dup
     103: bipush        15
     105: ldc_w         #329                // String warmup
     108: aastore
     109: dup
     110: bipush        16
     112: ldc_w         #330                // String weight
     115: aastore
     116: dup
     117: bipush        17
     119: ldc_w         #331                // String dubbo
     122: aastore
     123: dup
     124: bipush        18
     126: ldc_w         #332                // String release
     129: aastore
     130: dup
     131: bipush        19
     133: ldc_w         #333                // String side
     136: aastore
     137: dup
     138: bipush        20
     140: ldc_w         #334                // String ipv6
     143: aastore
     144: dup
     145: bipush        21
     147: ldc_w         #335                // String serialize.packable.factory
     150: aastore
     151: putstatic     #192                // Field DEFAULT_REGISTER_PROVIDER_KEYS:[Ljava/lang/String;
     154: iconst_5
     155: anewarray     #26                 // class java/lang/String
     158: dup
     159: iconst_0
     160: ldc_w         #316                // String application
     163: aastore
     164: dup
     165: iconst_1
     166: ldc_w         #328                // String version
     169: aastore
     170: dup
     171: iconst_2
     172: ldc           #221                // String group
     174: aastore
     175: dup
     176: iconst_3
     177: ldc_w         #331                // String dubbo
     180: aastore
     181: dup
     182: iconst_4
     183: ldc_w         #332                // String release
     186: aastore
     187: putstatic     #336                // Field DEFAULT_REGISTER_CONSUMER_KEYS:[Ljava/lang/String;
     190: ldc_w         #337                // class org/apache/dubbo/registry/integration/RegistryProtocol
     193: invokestatic  #338                // Method org/apache/dubbo/common/logger/LoggerFactory.getErrorTypeAwareLogger:(Ljava/lang/Class;)Lorg/apache/dubbo/common/logger/ErrorTypeAwareLogger;
     196: putstatic     #16                 // Field logger:Lorg/apache/dubbo/common/logger/ErrorTypeAwareLogger;
     199: return
}
