Compiled from "RegistryProtocol.java"
class org.apache.dubbo.registry.integration.RegistryProtocol$DestroyableExporter<T> implements org.apache.dubbo.rpc.Exporter<T> {
  private org.apache.dubbo.rpc.Exporter<T> exporter;

  public org.apache.dubbo.registry.integration.RegistryProtocol$DestroyableExporter(org.apache.dubbo.rpc.Exporter<T>);
    Code:
       0: aload_0
       1: invokespecial #1                  // Method java/lang/Object."<init>":()V
       4: aload_0
       5: aload_1
       6: putfield      #2                  // Field exporter:Lorg/apache/dubbo/rpc/Exporter;
       9: return

  public org.apache.dubbo.rpc.Invoker<T> getInvoker();
    Code:
       0: aload_0
       1: getfield      #2                  // Field exporter:Lorg/apache/dubbo/rpc/Exporter;
       4: invokeinterface #3,  1            // InterfaceMethod org/apache/dubbo/rpc/Exporter.getInvoker:()Lorg/apache/dubbo/rpc/Invoker;
       9: areturn

  public void unexport();
    Code:
       0: aload_0
       1: getfield      #2                  // Field exporter:Lorg/apache/dubbo/rpc/Exporter;
       4: invokeinterface #4,  1            // InterfaceMethod org/apache/dubbo/rpc/Exporter.unexport:()V
       9: return

  public void unregister();
    Code:
       0: aload_0
       1: getfield      #2                  // Field exporter:Lorg/apache/dubbo/rpc/Exporter;
       4: invokeinterface #5,  1            // InterfaceMethod org/apache/dubbo/rpc/Exporter.unregister:()V
       9: return
}
