Compiled from "RegistryDirectory.java"
class org.apache.dubbo.registry.integration.RegistryDirectory$ReferenceConfigurationListener extends org.apache.dubbo.registry.integration.AbstractConfiguratorListener {
  private org.apache.dubbo.registry.integration.RegistryDirectory directory;

  private org.apache.dubbo.common.URL url;

  org.apache.dubbo.registry.integration.RegistryDirectory$ReferenceConfigurationListener(org.apache.dubbo.rpc.model.ModuleModel, org.apache.dubbo.registry.integration.RegistryDirectory, org.apache.dubbo.common.URL);
    Code:
       0: aload_0
       1: aload_1
       2: invokespecial #2                  // Method org/apache/dubbo/registry/integration/AbstractConfiguratorListener."<init>":(Lorg/apache/dubbo/rpc/model/ModuleModel;)V
       5: aload_0
       6: aload_2
       7: putfield      #3                  // Field directory:Lorg/apache/dubbo/registry/integration/RegistryDirectory;
      10: aload_0
      11: aload_3
      12: putfield      #4                  // Field url:Lorg/apache/dubbo/common/URL;
      15: aload_0
      16: new           #5                  // class java/lang/StringBuilder
      19: dup
      20: invokespecial #6                  // Method java/lang/StringBuilder."<init>":()V
      23: aload_3
      24: invokestatic  #7                  // InterfaceMethod org/apache/dubbo/common/config/configcenter/DynamicConfiguration.getRuleKey:(Lorg/apache/dubbo/common/URL;)Ljava/lang/String;
      27: invokevirtual #8                  // Method java/lang/StringBuilder.append:(Ljava/lang/String;)Ljava/lang/StringBuilder;
      30: ldc           #9                  // String .configurators
      32: invokevirtual #8                  // Method java/lang/StringBuilder.append:(Ljava/lang/String;)Ljava/lang/StringBuilder;
      35: invokevirtual #10                 // Method java/lang/StringBuilder.toString:()Ljava/lang/String;
      38: invokevirtual #11                 // Method initWith:(Ljava/lang/String;)V
      41: return

  void stop();
    Code:
       0: aload_0
       1: new           #5                  // class java/lang/StringBuilder
       4: dup
       5: invokespecial #6                  // Method java/lang/StringBuilder."<init>":()V
       8: aload_0
       9: getfield      #4                  // Field url:Lorg/apache/dubbo/common/URL;
      12: invokestatic  #7                  // InterfaceMethod org/apache/dubbo/common/config/configcenter/DynamicConfiguration.getRuleKey:(Lorg/apache/dubbo/common/URL;)Ljava/lang/String;
      15: invokevirtual #8                  // Method java/lang/StringBuilder.append:(Ljava/lang/String;)Ljava/lang/StringBuilder;
      18: ldc           #9                  // String .configurators
      20: invokevirtual #8                  // Method java/lang/StringBuilder.append:(Ljava/lang/String;)Ljava/lang/StringBuilder;
      23: invokevirtual #10                 // Method java/lang/StringBuilder.toString:()Ljava/lang/String;
      26: invokevirtual #12                 // Method stopListen:(Ljava/lang/String;)V
      29: return

  protected void notifyOverrides();
    Code:
       0: aload_0
       1: getfield      #3                  // Field directory:Lorg/apache/dubbo/registry/integration/RegistryDirectory;
       4: invokestatic  #13                 // Method java/util/Collections.emptyList:()Ljava/util/List;
       7: invokevirtual #14                 // Method org/apache/dubbo/registry/integration/RegistryDirectory.refreshOverrideAndInvoker:(Ljava/util/List;)V
      10: return
}
