Compiled from "DecodedBitStreamParser.java"
final class com.google.zxing.maxicode.decoder.DecodedBitStreamParser {
  private static final char SHIFTA;

  private static final char SHIFTB;

  private static final char SHIFTC;

  private static final char SHIFTD;

  private static final char SHIFTE;

  private static final char TWOSHIFTA;

  private static final char THREESHIFTA;

  private static final char LATCHA;

  private static final char LATCHB;

  private static final char LOCK;

  private static final char ECI;

  private static final char NS;

  private static final char PAD;

  private static final char FS;

  private static final char GS;

  private static final char RS;

  private static final byte[] COUNTRY_BYTES;

  private static final byte[] SERVICE_CLASS_BYTES;

  private static final byte[] POSTCODE_2_LENGTH_BYTES;

  private static final byte[] POSTCODE_2_BYTES;

  private static final byte[][] POSTCODE_3_BYTES;

  private static final java.lang.String[] SETS;

  private com.google.zxing.maxicode.decoder.DecodedBitStreamParser();
    Code:
       0: aload_0
       1: invokespecial #1                  // Method java/lang/Object."<init>":()V
       4: return

  static com.google.zxing.common.DecoderResult decode(byte[], int) throws com.google.zxing.FormatException;
    Code:
       0: new           #2                  // class java/lang/StringBuilder
       3: dup
       4: sipush        144
       7: invokespecial #3                  // Method java/lang/StringBuilder."<init>":(I)V
      10: astore_2
      11: iload_1
      12: tableswitch   { // 2 to 5
                     2: 44
                     3: 44
                     4: 263
                     5: 278
               default: 290
          }
      44: iload_1
      45: iconst_2
      46: if_icmpne     101
      49: aload_0
      50: invokestatic  #4                  // Method getPostCode2:([B)I
      53: istore        4
      55: aload_0
      56: invokestatic  #5                  // Method getPostCode2Length:([B)I
      59: istore        5
      61: iload         5
      63: bipush        10
      65: if_icmple     72
      68: invokestatic  #6                  // Method com/google/zxing/FormatException.getFormatInstance:()Lcom/google/zxing/FormatException;
      71: athrow
      72: new           #7                  // class java/text/DecimalFormat
      75: dup
      76: ldc           #8                  // String 0000000000
      78: iconst_0
      79: iload         5
      81: invokevirtual #9                  // Method java/lang/String.substring:(II)Ljava/lang/String;
      84: invokespecial #10                 // Method java/text/DecimalFormat."<init>":(Ljava/lang/String;)V
      87: astore        6
      89: aload         6
      91: iload         4
      93: i2l
      94: invokevirtual #11                 // Method java/text/NumberFormat.format:(J)Ljava/lang/String;
      97: astore_3
      98: goto          106
     101: aload_0
     102: invokestatic  #12                 // Method getPostCode3:([B)Ljava/lang/String;
     105: astore_3
     106: new           #7                  // class java/text/DecimalFormat
     109: dup
     110: ldc           #13                 // String 000
     112: invokespecial #10                 // Method java/text/DecimalFormat."<init>":(Ljava/lang/String;)V
     115: astore        4
     117: aload         4
     119: aload_0
     120: invokestatic  #14                 // Method getCountry:([B)I
     123: i2l
     124: invokevirtual #11                 // Method java/text/NumberFormat.format:(J)Ljava/lang/String;
     127: astore        5
     129: aload         4
     131: aload_0
     132: invokestatic  #15                 // Method getServiceClass:([B)I
     135: i2l
     136: invokevirtual #11                 // Method java/text/NumberFormat.format:(J)Ljava/lang/String;
     139: astore        6
     141: aload_2
     142: aload_0
     143: bipush        10
     145: bipush        84
     147: invokestatic  #16                 // Method getMessage:([BII)Ljava/lang/String;
     150: invokevirtual #17                 // Method java/lang/StringBuilder.append:(Ljava/lang/String;)Ljava/lang/StringBuilder;
     153: pop
     154: aload_2
     155: invokevirtual #18                 // Method java/lang/StringBuilder.toString:()Ljava/lang/String;
     158: ldc           #20                 // String [)>\u001e01\u001d
     160: invokevirtual #21                 // Method java/lang/String.startsWith:(Ljava/lang/String;)Z
     163: ifeq          215
     166: aload_2
     167: bipush        9
     169: new           #2                  // class java/lang/StringBuilder
     172: dup
     173: invokespecial #22                 // Method java/lang/StringBuilder."<init>":()V
     176: aload_3
     177: invokevirtual #17                 // Method java/lang/StringBuilder.append:(Ljava/lang/String;)Ljava/lang/StringBuilder;
     180: bipush        29
     182: invokevirtual #23                 // Method java/lang/StringBuilder.append:(C)Ljava/lang/StringBuilder;
     185: aload         5
     187: invokevirtual #17                 // Method java/lang/StringBuilder.append:(Ljava/lang/String;)Ljava/lang/StringBuilder;
     190: bipush        29
     192: invokevirtual #23                 // Method java/lang/StringBuilder.append:(C)Ljava/lang/StringBuilder;
     195: aload         6
     197: invokevirtual #17                 // Method java/lang/StringBuilder.append:(Ljava/lang/String;)Ljava/lang/StringBuilder;
     200: bipush        29
     202: invokevirtual #23                 // Method java/lang/StringBuilder.append:(C)Ljava/lang/StringBuilder;
     205: invokevirtual #18                 // Method java/lang/StringBuilder.toString:()Ljava/lang/String;
     208: invokevirtual #24                 // Method java/lang/StringBuilder.insert:(ILjava/lang/String;)Ljava/lang/StringBuilder;
     211: pop
     212: goto          290
     215: aload_2
     216: iconst_0
     217: new           #2                  // class java/lang/StringBuilder
     220: dup
     221: invokespecial #22                 // Method java/lang/StringBuilder."<init>":()V
     224: aload_3
     225: invokevirtual #17                 // Method java/lang/StringBuilder.append:(Ljava/lang/String;)Ljava/lang/StringBuilder;
     228: bipush        29
     230: invokevirtual #23                 // Method java/lang/StringBuilder.append:(C)Ljava/lang/StringBuilder;
     233: aload         5
     235: invokevirtual #17                 // Method java/lang/StringBuilder.append:(Ljava/lang/String;)Ljava/lang/StringBuilder;
     238: bipush        29
     240: invokevirtual #23                 // Method java/lang/StringBuilder.append:(C)Ljava/lang/StringBuilder;
     243: aload         6
     245: invokevirtual #17                 // Method java/lang/StringBuilder.append:(Ljava/lang/String;)Ljava/lang/StringBuilder;
     248: bipush        29
     250: invokevirtual #23                 // Method java/lang/StringBuilder.append:(C)Ljava/lang/StringBuilder;
     253: invokevirtual #18                 // Method java/lang/StringBuilder.toString:()Ljava/lang/String;
     256: invokevirtual #24                 // Method java/lang/StringBuilder.insert:(ILjava/lang/String;)Ljava/lang/StringBuilder;
     259: pop
     260: goto          290
     263: aload_2
     264: aload_0
     265: iconst_1
     266: bipush        93
     268: invokestatic  #16                 // Method getMessage:([BII)Ljava/lang/String;
     271: invokevirtual #17                 // Method java/lang/StringBuilder.append:(Ljava/lang/String;)Ljava/lang/StringBuilder;
     274: pop
     275: goto          290
     278: aload_2
     279: aload_0
     280: iconst_1
     281: bipush        77
     283: invokestatic  #16                 // Method getMessage:([BII)Ljava/lang/String;
     286: invokevirtual #17                 // Method java/lang/StringBuilder.append:(Ljava/lang/String;)Ljava/lang/StringBuilder;
     289: pop
     290: new           #25                 // class com/google/zxing/common/DecoderResult
     293: dup
     294: aload_0
     295: aload_2
     296: invokevirtual #18                 // Method java/lang/StringBuilder.toString:()Ljava/lang/String;
     299: aconst_null
     300: iload_1
     301: invokestatic  #26                 // Method java/lang/String.valueOf:(I)Ljava/lang/String;
     304: invokespecial #27                 // Method com/google/zxing/common/DecoderResult."<init>":([BLjava/lang/String;Ljava/util/List;Ljava/lang/String;)V
     307: areturn

  private static int getBit(int, byte[]);
    Code:
       0: iinc          0, -1
       3: aload_1
       4: iload_0
       5: bipush        6
       7: idiv
       8: baload
       9: iconst_1
      10: iconst_5
      11: iload_0
      12: bipush        6
      14: irem
      15: isub
      16: ishl
      17: iand
      18: ifne          25
      21: iconst_0
      22: goto          26
      25: iconst_1
      26: ireturn

  private static int getInt(byte[], byte[]);
    Code:
       0: iconst_0
       1: istore_2
       2: iconst_0
       3: istore_3
       4: iload_3
       5: aload_1
       6: arraylength
       7: if_icmpge     33
      10: iload_2
      11: aload_1
      12: iload_3
      13: baload
      14: aload_0
      15: invokestatic  #28                 // Method getBit:(I[B)I
      18: aload_1
      19: arraylength
      20: iload_3
      21: isub
      22: iconst_1
      23: isub
      24: ishl
      25: iadd
      26: istore_2
      27: iinc          3, 1
      30: goto          4
      33: iload_2
      34: ireturn

  private static int getCountry(byte[]);
    Code:
       0: aload_0
       1: getstatic     #29                 // Field COUNTRY_BYTES:[B
       4: invokestatic  #30                 // Method getInt:([B[B)I
       7: ireturn

  private static int getServiceClass(byte[]);
    Code:
       0: aload_0
       1: getstatic     #31                 // Field SERVICE_CLASS_BYTES:[B
       4: invokestatic  #30                 // Method getInt:([B[B)I
       7: ireturn

  private static int getPostCode2Length(byte[]);
    Code:
       0: aload_0
       1: getstatic     #32                 // Field POSTCODE_2_LENGTH_BYTES:[B
       4: invokestatic  #30                 // Method getInt:([B[B)I
       7: ireturn

  private static int getPostCode2(byte[]);
    Code:
       0: aload_0
       1: getstatic     #33                 // Field POSTCODE_2_BYTES:[B
       4: invokestatic  #30                 // Method getInt:([B[B)I
       7: ireturn

  private static java.lang.String getPostCode3(byte[]);
    Code:
       0: new           #2                  // class java/lang/StringBuilder
       3: dup
       4: getstatic     #34                 // Field POSTCODE_3_BYTES:[[B
       7: arraylength
       8: invokespecial #3                  // Method java/lang/StringBuilder."<init>":(I)V
      11: astore_1
      12: getstatic     #34                 // Field POSTCODE_3_BYTES:[[B
      15: astore_2
      16: aload_2
      17: arraylength
      18: istore_3
      19: iconst_0
      20: istore        4
      22: iload         4
      24: iload_3
      25: if_icmpge     59
      28: aload_2
      29: iload         4
      31: aaload
      32: astore        5
      34: aload_1
      35: getstatic     #35                 // Field SETS:[Ljava/lang/String;
      38: iconst_0
      39: aaload
      40: aload_0
      41: aload         5
      43: invokestatic  #30                 // Method getInt:([B[B)I
      46: invokevirtual #36                 // Method java/lang/String.charAt:(I)C
      49: invokevirtual #23                 // Method java/lang/StringBuilder.append:(C)Ljava/lang/StringBuilder;
      52: pop
      53: iinc          4, 1
      56: goto          22
      59: aload_1
      60: invokevirtual #18                 // Method java/lang/StringBuilder.toString:()Ljava/lang/String;
      63: areturn

  private static java.lang.String getMessage(byte[], int, int);
    Code:
       0: new           #2                  // class java/lang/StringBuilder
       3: dup
       4: invokespecial #22                 // Method java/lang/StringBuilder."<init>":()V
       7: astore_3
       8: iconst_m1
       9: istore        4
      11: iconst_0
      12: istore        5
      14: iconst_0
      15: istore        6
      17: iload_1
      18: istore        7
      20: iload         7
      22: iload_1
      23: iload_2
      24: iadd
      25: if_icmpge     276
      28: getstatic     #35                 // Field SETS:[Ljava/lang/String;
      31: iload         5
      33: aaload
      34: aload_0
      35: iload         7
      37: baload
      38: invokevirtual #36                 // Method java/lang/String.charAt:(I)C
      41: istore        8
      43: iload         8
      45: tableswitch   { // 65520 to 65531
                 65520: 126
                 65521: 126
                 65522: 126
                 65523: 126
                 65524: 126
                 65525: 143
                 65526: 156
                 65527: 108
                 65528: 117
                 65529: 245
                 65530: 251
                 65531: 169
               default: 251
          }
     108: iconst_0
     109: istore        5
     111: iconst_m1
     112: istore        4
     114: goto          258
     117: iconst_1
     118: istore        5
     120: iconst_m1
     121: istore        4
     123: goto          258
     126: iload         5
     128: istore        6
     130: iload         8
     132: ldc           #37                 // int 65520
     134: isub
     135: istore        5
     137: iconst_1
     138: istore        4
     140: goto          258
     143: iload         5
     145: istore        6
     147: iconst_0
     148: istore        5
     150: iconst_2
     151: istore        4
     153: goto          258
     156: iload         5
     158: istore        6
     160: iconst_0
     161: istore        5
     163: iconst_3
     164: istore        4
     166: goto          258
     169: aload_0
     170: iinc          7, 1
     173: iload         7
     175: baload
     176: bipush        24
     178: ishl
     179: aload_0
     180: iinc          7, 1
     183: iload         7
     185: baload
     186: bipush        18
     188: ishl
     189: iadd
     190: aload_0
     191: iinc          7, 1
     194: iload         7
     196: baload
     197: bipush        12
     199: ishl
     200: iadd
     201: aload_0
     202: iinc          7, 1
     205: iload         7
     207: baload
     208: bipush        6
     210: ishl
     211: iadd
     212: aload_0
     213: iinc          7, 1
     216: iload         7
     218: baload
     219: iadd
     220: istore        9
     222: aload_3
     223: new           #7                  // class java/text/DecimalFormat
     226: dup
     227: ldc           #38                 // String 000000000
     229: invokespecial #10                 // Method java/text/DecimalFormat."<init>":(Ljava/lang/String;)V
     232: iload         9
     234: i2l
     235: invokevirtual #39                 // Method java/text/DecimalFormat.format:(J)Ljava/lang/String;
     238: invokevirtual #17                 // Method java/lang/StringBuilder.append:(Ljava/lang/String;)Ljava/lang/StringBuilder;
     241: pop
     242: goto          258
     245: iconst_m1
     246: istore        4
     248: goto          258
     251: aload_3
     252: iload         8
     254: invokevirtual #23                 // Method java/lang/StringBuilder.append:(C)Ljava/lang/StringBuilder;
     257: pop
     258: iload         4
     260: iinc          4, -1
     263: ifne          270
     266: iload         6
     268: istore        5
     270: iinc          7, 1
     273: goto          20
     276: aload_3
     277: invokevirtual #40                 // Method java/lang/StringBuilder.length:()I
     280: ifle          311
     283: aload_3
     284: aload_3
     285: invokevirtual #40                 // Method java/lang/StringBuilder.length:()I
     288: iconst_1
     289: isub
     290: invokevirtual #41                 // Method java/lang/StringBuilder.charAt:(I)C
     293: ldc           #42                 // int 65532
     295: if_icmpne     311
     298: aload_3
     299: aload_3
     300: invokevirtual #40                 // Method java/lang/StringBuilder.length:()I
     303: iconst_1
     304: isub
     305: invokevirtual #43                 // Method java/lang/StringBuilder.setLength:(I)V
     308: goto          276
     311: aload_3
     312: invokevirtual #18                 // Method java/lang/StringBuilder.toString:()Ljava/lang/String;
     315: areturn

  static {};
    Code:
       0: bipush        10
       2: newarray       byte
       4: dup
       5: iconst_0
       6: bipush        53
       8: bastore
       9: dup
      10: iconst_1
      11: bipush        54
      13: bastore
      14: dup
      15: iconst_2
      16: bipush        43
      18: bastore
      19: dup
      20: iconst_3
      21: bipush        44
      23: bastore
      24: dup
      25: iconst_4
      26: bipush        45
      28: bastore
      29: dup
      30: iconst_5
      31: bipush        46
      33: bastore
      34: dup
      35: bipush        6
      37: bipush        47
      39: bastore
      40: dup
      41: bipush        7
      43: bipush        48
      45: bastore
      46: dup
      47: bipush        8
      49: bipush        37
      51: bastore
      52: dup
      53: bipush        9
      55: bipush        38
      57: bastore
      58: putstatic     #29                 // Field COUNTRY_BYTES:[B
      61: bipush        10
      63: newarray       byte
      65: dup
      66: iconst_0
      67: bipush        55
      69: bastore
      70: dup
      71: iconst_1
      72: bipush        56
      74: bastore
      75: dup
      76: iconst_2
      77: bipush        57
      79: bastore
      80: dup
      81: iconst_3
      82: bipush        58
      84: bastore
      85: dup
      86: iconst_4
      87: bipush        59
      89: bastore
      90: dup
      91: iconst_5
      92: bipush        60
      94: bastore
      95: dup
      96: bipush        6
      98: bipush        49
     100: bastore
     101: dup
     102: bipush        7
     104: bipush        50
     106: bastore
     107: dup
     108: bipush        8
     110: bipush        51
     112: bastore
     113: dup
     114: bipush        9
     116: bipush        52
     118: bastore
     119: putstatic     #31                 // Field SERVICE_CLASS_BYTES:[B
     122: bipush        6
     124: newarray       byte
     126: dup
     127: iconst_0
     128: bipush        39
     130: bastore
     131: dup
     132: iconst_1
     133: bipush        40
     135: bastore
     136: dup
     137: iconst_2
     138: bipush        41
     140: bastore
     141: dup
     142: iconst_3
     143: bipush        42
     145: bastore
     146: dup
     147: iconst_4
     148: bipush        31
     150: bastore
     151: dup
     152: iconst_5
     153: bipush        32
     155: bastore
     156: putstatic     #32                 // Field POSTCODE_2_LENGTH_BYTES:[B
     159: bipush        30
     161: newarray       byte
     163: dup
     164: iconst_0
     165: bipush        33
     167: bastore
     168: dup
     169: iconst_1
     170: bipush        34
     172: bastore
     173: dup
     174: iconst_2
     175: bipush        35
     177: bastore
     178: dup
     179: iconst_3
     180: bipush        36
     182: bastore
     183: dup
     184: iconst_4
     185: bipush        25
     187: bastore
     188: dup
     189: iconst_5
     190: bipush        26
     192: bastore
     193: dup
     194: bipush        6
     196: bipush        27
     198: bastore
     199: dup
     200: bipush        7
     202: bipush        28
     204: bastore
     205: dup
     206: bipush        8
     208: bipush        29
     210: bastore
     211: dup
     212: bipush        9
     214: bipush        30
     216: bastore
     217: dup
     218: bipush        10
     220: bipush        19
     222: bastore
     223: dup
     224: bipush        11
     226: bipush        20
     228: bastore
     229: dup
     230: bipush        12
     232: bipush        21
     234: bastore
     235: dup
     236: bipush        13
     238: bipush        22
     240: bastore
     241: dup
     242: bipush        14
     244: bipush        23
     246: bastore
     247: dup
     248: bipush        15
     250: bipush        24
     252: bastore
     253: dup
     254: bipush        16
     256: bipush        13
     258: bastore
     259: dup
     260: bipush        17
     262: bipush        14
     264: bastore
     265: dup
     266: bipush        18
     268: bipush        15
     270: bastore
     271: dup
     272: bipush        19
     274: bipush        16
     276: bastore
     277: dup
     278: bipush        20
     280: bipush        17
     282: bastore
     283: dup
     284: bipush        21
     286: bipush        18
     288: bastore
     289: dup
     290: bipush        22
     292: bipush        7
     294: bastore
     295: dup
     296: bipush        23
     298: bipush        8
     300: bastore
     301: dup
     302: bipush        24
     304: bipush        9
     306: bastore
     307: dup
     308: bipush        25
     310: bipush        10
     312: bastore
     313: dup
     314: bipush        26
     316: bipush        11
     318: bastore
     319: dup
     320: bipush        27
     322: bipush        12
     324: bastore
     325: dup
     326: bipush        28
     328: iconst_1
     329: bastore
     330: dup
     331: bipush        29
     333: iconst_2
     334: bastore
     335: putstatic     #33                 // Field POSTCODE_2_BYTES:[B
     338: bipush        6
     340: anewarray     #44                 // class "[B"
     343: dup
     344: iconst_0
     345: bipush        6
     347: newarray       byte
     349: dup
     350: iconst_0
     351: bipush        39
     353: bastore
     354: dup
     355: iconst_1
     356: bipush        40
     358: bastore
     359: dup
     360: iconst_2
     361: bipush        41
     363: bastore
     364: dup
     365: iconst_3
     366: bipush        42
     368: bastore
     369: dup
     370: iconst_4
     371: bipush        31
     373: bastore
     374: dup
     375: iconst_5
     376: bipush        32
     378: bastore
     379: aastore
     380: dup
     381: iconst_1
     382: bipush        6
     384: newarray       byte
     386: dup
     387: iconst_0
     388: bipush        33
     390: bastore
     391: dup
     392: iconst_1
     393: bipush        34
     395: bastore
     396: dup
     397: iconst_2
     398: bipush        35
     400: bastore
     401: dup
     402: iconst_3
     403: bipush        36
     405: bastore
     406: dup
     407: iconst_4
     408: bipush        25
     410: bastore
     411: dup
     412: iconst_5
     413: bipush        26
     415: bastore
     416: aastore
     417: dup
     418: iconst_2
     419: bipush        6
     421: newarray       byte
     423: dup
     424: iconst_0
     425: bipush        27
     427: bastore
     428: dup
     429: iconst_1
     430: bipush        28
     432: bastore
     433: dup
     434: iconst_2
     435: bipush        29
     437: bastore
     438: dup
     439: iconst_3
     440: bipush        30
     442: bastore
     443: dup
     444: iconst_4
     445: bipush        19
     447: bastore
     448: dup
     449: iconst_5
     450: bipush        20
     452: bastore
     453: aastore
     454: dup
     455: iconst_3
     456: bipush        6
     458: newarray       byte
     460: dup
     461: iconst_0
     462: bipush        21
     464: bastore
     465: dup
     466: iconst_1
     467: bipush        22
     469: bastore
     470: dup
     471: iconst_2
     472: bipush        23
     474: bastore
     475: dup
     476: iconst_3
     477: bipush        24
     479: bastore
     480: dup
     481: iconst_4
     482: bipush        13
     484: bastore
     485: dup
     486: iconst_5
     487: bipush        14
     489: bastore
     490: aastore
     491: dup
     492: iconst_4
     493: bipush        6
     495: newarray       byte
     497: dup
     498: iconst_0
     499: bipush        15
     501: bastore
     502: dup
     503: iconst_1
     504: bipush        16
     506: bastore
     507: dup
     508: iconst_2
     509: bipush        17
     511: bastore
     512: dup
     513: iconst_3
     514: bipush        18
     516: bastore
     517: dup
     518: iconst_4
     519: bipush        7
     521: bastore
     522: dup
     523: iconst_5
     524: bipush        8
     526: bastore
     527: aastore
     528: dup
     529: iconst_5
     530: bipush        6
     532: newarray       byte
     534: dup
     535: iconst_0
     536: bipush        9
     538: bastore
     539: dup
     540: iconst_1
     541: bipush        10
     543: bastore
     544: dup
     545: iconst_2
     546: bipush        11
     548: bastore
     549: dup
     550: iconst_3
     551: bipush        12
     553: bastore
     554: dup
     555: iconst_4
     556: iconst_1
     557: bastore
     558: dup
     559: iconst_5
     560: iconst_2
     561: bastore
     562: aastore
     563: putstatic     #34                 // Field POSTCODE_3_BYTES:[[B
     566: iconst_5
     567: anewarray     #45                 // class java/lang/String
     570: dup
     571: iconst_0
     572: ldc           #46                 // String \rABCDEFGHIJKLMNOPQRSTUVWXYZ?\u001c\u001d\u001e? ?\"#$%&\'()*+,-./0123456789:?????
     574: aastore
     575: dup
     576: iconst_1
     577: ldc           #47                 // String `abcdefghijklmnopqrstuvwxyz?\u001c\u001d\u001e?{?}~\u007f;<=>?[\\]^_ ,./:@!|?????????
     579: aastore
     580: dup
     581: iconst_2
     582: ldc           #48                 // String ??????¨¡?????????¨¢??????¡¿¨ª???\u001c\u001d\u001e????¨­©¬¨£?¡¾©÷©ø?©ö¨¬¨ù¨ö¨ú\u0080\u0081\u0082\u0083\u0084\u0085\u0086\u0087\u0088\u0089? ????
     584: aastore
     585: dup
     586: iconst_3
     587: ldc           #49                 // String ??????©¡?????????©£??????¡À©ª???\u001c\u001d\u001e????©­?¢®¡§??¡Æ¢¥¡¤¢¬?¢¯\u008a\u008b\u008c\u008d\u008e\u008f\u0090\u0091\u0092\u0093\u0094? ????
     589: aastore
     590: dup
     591: iconst_4
     592: ldc           #50                 // String \u0000\u0001\u0002\u0003\u0004\u0005\u0006\u0007\b\t\n\u000b\f\r\u000e\u000f\u0010\u0011\u0012\u0013\u0014\u0015\u0016\u0017\u0018\u0019\u001a???\u001b?\u001c\u001d\u001e\u001f\u009f???¢´??¡×?¡©¢ç¢Ò\u0095\u0096\u0097\u0098\u0099\u009a\u009b\u009c\u009d\u009e? ????
     594: aastore
     595: putstatic     #35                 // Field SETS:[Ljava/lang/String;
     598: return
}
