Compiled from "CacheFilter.java"
public class org.apache.dubbo.cache.filter.CacheFilter implements org.apache.dubbo.rpc.Filter {
  private org.apache.dubbo.cache.CacheFactory cacheFactory;

  public org.apache.dubbo.cache.filter.CacheFilter();
    Code:
       0: aload_0
       1: invokespecial #2                  // Method java/lang/Object."<init>":()V
       4: return

  public void setCacheFactory(org.apache.dubbo.cache.CacheFactory);
    Code:
       0: aload_0
       1: aload_1
       2: putfield      #3                  // Field cacheFactory:Lorg/apache/dubbo/cache/CacheFactory;
       5: return

  public org.apache.dubbo.rpc.Result invoke(org.apache.dubbo.rpc.Invoker<?>, org.apache.dubbo.rpc.Invocation) throws org.apache.dubbo.rpc.RpcException;
    Code:
       0: aload_0
       1: getfield      #3                  // Field cacheFactory:Lorg/apache/dubbo/cache/CacheFactory;
       4: ifnull        30
       7: aload_1
       8: invokeinterface #4,  1            // InterfaceMethod org/apache/dubbo/rpc/Invoker.getUrl:()Lorg/apache/dubbo/common/URL;
      13: aload_2
      14: invokeinterface #5,  1            // InterfaceMethod org/apache/dubbo/rpc/Invocation.getMethodName:()Ljava/lang/String;
      19: ldc           #6                  // String cache
      21: invokevirtual #7                  // Method org/apache/dubbo/common/URL.getMethodParameter:(Ljava/lang/String;Ljava/lang/String;)Ljava/lang/String;
      24: invokestatic  #8                  // Method org/apache/dubbo/common/utils/ConfigUtils.isEmpty:(Ljava/lang/String;)Z
      27: ifeq          38
      30: aload_1
      31: aload_2
      32: invokeinterface #9,  2            // InterfaceMethod org/apache/dubbo/rpc/Invoker.invoke:(Lorg/apache/dubbo/rpc/Invocation;)Lorg/apache/dubbo/rpc/Result;
      37: areturn
      38: aload_0
      39: getfield      #3                  // Field cacheFactory:Lorg/apache/dubbo/cache/CacheFactory;
      42: aload_1
      43: invokeinterface #4,  1            // InterfaceMethod org/apache/dubbo/rpc/Invoker.getUrl:()Lorg/apache/dubbo/common/URL;
      48: aload_2
      49: invokeinterface #10,  3           // InterfaceMethod org/apache/dubbo/cache/CacheFactory.getCache:(Lorg/apache/dubbo/common/URL;Lorg/apache/dubbo/rpc/Invocation;)Lorg/apache/dubbo/cache/Cache;
      54: astore_3
      55: aload_3
      56: ifnonnull     67
      59: aload_1
      60: aload_2
      61: invokeinterface #9,  2            // InterfaceMethod org/apache/dubbo/rpc/Invoker.invoke:(Lorg/apache/dubbo/rpc/Invocation;)Lorg/apache/dubbo/rpc/Result;
      66: areturn
      67: aload_2
      68: invokeinterface #11,  1           // InterfaceMethod org/apache/dubbo/rpc/Invocation.getArguments:()[Ljava/lang/Object;
      73: invokestatic  #12                 // Method org/apache/dubbo/common/utils/StringUtils.toArgumentString:([Ljava/lang/Object;)Ljava/lang/String;
      76: astore        4
      78: aload_3
      79: aload         4
      81: invokeinterface #13,  2           // InterfaceMethod org/apache/dubbo/cache/Cache.get:(Ljava/lang/Object;)Ljava/lang/Object;
      86: astore        5
      88: aload         5
      90: ifnull        103
      93: aload_0
      94: aload_2
      95: aload         5
      97: invokespecial #14                 // Method onCacheValuePresent:(Lorg/apache/dubbo/rpc/Invocation;Ljava/lang/Object;)Lorg/apache/dubbo/rpc/Result;
     100: goto          112
     103: aload_0
     104: aload_1
     105: aload_2
     106: aload_3
     107: aload         4
     109: invokespecial #15                 // Method onCacheValueNotPresent:(Lorg/apache/dubbo/rpc/Invoker;Lorg/apache/dubbo/rpc/Invocation;Lorg/apache/dubbo/cache/Cache;Ljava/lang/String;)Lorg/apache/dubbo/rpc/Result;
     112: areturn

  private org.apache.dubbo.rpc.Result onCacheValuePresent(org.apache.dubbo.rpc.Invocation, java.lang.Object);
    Code:
       0: aload_2
       1: instanceof    #16                 // class org/apache/dubbo/cache/filter/CacheFilter$ValueWrapper
       4: ifeq          19
       7: aload_2
       8: checkcast     #16                 // class org/apache/dubbo/cache/filter/CacheFilter$ValueWrapper
      11: invokevirtual #17                 // Method org/apache/dubbo/cache/filter/CacheFilter$ValueWrapper.get:()Ljava/lang/Object;
      14: aload_1
      15: invokestatic  #18                 // Method org/apache/dubbo/rpc/AsyncRpcResult.newDefaultAsyncResult:(Ljava/lang/Object;Lorg/apache/dubbo/rpc/Invocation;)Lorg/apache/dubbo/rpc/AsyncRpcResult;
      18: areturn
      19: aload_2
      20: aload_1
      21: invokestatic  #18                 // Method org/apache/dubbo/rpc/AsyncRpcResult.newDefaultAsyncResult:(Ljava/lang/Object;Lorg/apache/dubbo/rpc/Invocation;)Lorg/apache/dubbo/rpc/AsyncRpcResult;
      24: areturn

  private org.apache.dubbo.rpc.Result onCacheValueNotPresent(org.apache.dubbo.rpc.Invoker<?>, org.apache.dubbo.rpc.Invocation, org.apache.dubbo.cache.Cache, java.lang.String);
    Code:
       0: aload_1
       1: aload_2
       2: invokeinterface #9,  2            // InterfaceMethod org/apache/dubbo/rpc/Invoker.invoke:(Lorg/apache/dubbo/rpc/Invocation;)Lorg/apache/dubbo/rpc/Result;
       7: astore        5
       9: aload         5
      11: invokeinterface #19,  1           // InterfaceMethod org/apache/dubbo/rpc/Result.hasException:()Z
      16: ifne          41
      19: aload_3
      20: aload         4
      22: new           #16                 // class org/apache/dubbo/cache/filter/CacheFilter$ValueWrapper
      25: dup
      26: aload         5
      28: invokeinterface #20,  1           // InterfaceMethod org/apache/dubbo/rpc/Result.getValue:()Ljava/lang/Object;
      33: invokespecial #21                 // Method org/apache/dubbo/cache/filter/CacheFilter$ValueWrapper."<init>":(Ljava/lang/Object;)V
      36: invokeinterface #22,  3           // InterfaceMethod org/apache/dubbo/cache/Cache.put:(Ljava/lang/Object;Ljava/lang/Object;)V
      41: aload         5
      43: areturn
}
