Compiled from "CacheFilter.java"
class org.apache.dubbo.cache.filter.CacheFilter$ValueWrapper implements java.io.Serializable {
  private static final long serialVersionUID;

  private final java.lang.Object value;

  public org.apache.dubbo.cache.filter.CacheFilter$ValueWrapper(java.lang.Object);
    Code:
       0: aload_0
       1: invokespecial #1                  // Method java/lang/Object."<init>":()V
       4: aload_0
       5: aload_1
       6: putfield      #2                  // Field value:Ljava/lang/Object;
       9: return

  public java.lang.Object get();
    Code:
       0: aload_0
       1: getfield      #2                  // Field value:Ljava/lang/Object;
       4: areturn
}
