Compiled from "MetadataSubDispatcher.java"
interface org.apache.dubbo.metrics.metadata.event.MetadataSubDispatcher$CategorySet {
  public static final org.apache.dubbo.metrics.model.key.CategoryOverall APPLICATION_PUSH;

  public static final org.apache.dubbo.metrics.model.key.CategoryOverall APPLICATION_SUBSCRIBE;

  public static final org.apache.dubbo.metrics.model.key.CategoryOverall SERVICE_SUBSCRIBE;

  public static final java.util.List<org.apache.dubbo.metrics.model.key.CategoryOverall> ALL;

  static {};
    Code:
       0: new           #1                  // class org/apache/dubbo/metrics/model/key/CategoryOverall
       3: dup
       4: getstatic     #2                  // Field org/apache/dubbo/metrics/metadata/MetadataMetricsConstants.OP_TYPE_PUSH:Lorg/apache/dubbo/metrics/model/key/MetricsPlaceValue;
       7: getstatic     #3                  // Field org/apache/dubbo/metrics/metadata/event/MetadataSubDispatcher$MCat.APPLICATION_PUSH_POST:Lorg/apache/dubbo/metrics/model/key/MetricsCat;
      10: getstatic     #4                  // Field org/apache/dubbo/metrics/metadata/event/MetadataSubDispatcher$MCat.APPLICATION_PUSH_FINISH:Lorg/apache/dubbo/metrics/model/key/MetricsCat;
      13: getstatic     #5                  // Field org/apache/dubbo/metrics/metadata/event/MetadataSubDispatcher$MCat.APPLICATION_PUSH_ERROR:Lorg/apache/dubbo/metrics/model/key/MetricsCat;
      16: invokespecial #6                  // Method org/apache/dubbo/metrics/model/key/CategoryOverall."<init>":(Lorg/apache/dubbo/metrics/model/key/MetricsPlaceValue;Lorg/apache/dubbo/metrics/model/key/MetricsCat;Lorg/apache/dubbo/metrics/model/key/MetricsCat;Lorg/apache/dubbo/metrics/model/key/MetricsCat;)V
      19: putstatic     #7                  // Field APPLICATION_PUSH:Lorg/apache/dubbo/metrics/model/key/CategoryOverall;
      22: new           #1                  // class org/apache/dubbo/metrics/model/key/CategoryOverall
      25: dup
      26: getstatic     #8                  // Field org/apache/dubbo/metrics/metadata/MetadataMetricsConstants.OP_TYPE_SUBSCRIBE:Lorg/apache/dubbo/metrics/model/key/MetricsPlaceValue;
      29: getstatic     #9                  // Field org/apache/dubbo/metrics/metadata/event/MetadataSubDispatcher$MCat.APPLICATION_SUBSCRIBE_POST:Lorg/apache/dubbo/metrics/model/key/MetricsCat;
      32: getstatic     #10                 // Field org/apache/dubbo/metrics/metadata/event/MetadataSubDispatcher$MCat.APPLICATION_SUBSCRIBE_FINISH:Lorg/apache/dubbo/metrics/model/key/MetricsCat;
      35: getstatic     #11                 // Field org/apache/dubbo/metrics/metadata/event/MetadataSubDispatcher$MCat.APPLICATION_SUBSCRIBE_ERROR:Lorg/apache/dubbo/metrics/model/key/MetricsCat;
      38: invokespecial #6                  // Method org/apache/dubbo/metrics/model/key/CategoryOverall."<init>":(Lorg/apache/dubbo/metrics/model/key/MetricsPlaceValue;Lorg/apache/dubbo/metrics/model/key/MetricsCat;Lorg/apache/dubbo/metrics/model/key/MetricsCat;Lorg/apache/dubbo/metrics/model/key/MetricsCat;)V
      41: putstatic     #12                 // Field APPLICATION_SUBSCRIBE:Lorg/apache/dubbo/metrics/model/key/CategoryOverall;
      44: new           #1                  // class org/apache/dubbo/metrics/model/key/CategoryOverall
      47: dup
      48: getstatic     #13                 // Field org/apache/dubbo/metrics/metadata/MetadataMetricsConstants.OP_TYPE_STORE_PROVIDER_INTERFACE:Lorg/apache/dubbo/metrics/model/key/MetricsPlaceValue;
      51: getstatic     #14                 // Field org/apache/dubbo/metrics/metadata/event/MetadataSubDispatcher$MCat.SERVICE_SUBSCRIBE_POST:Lorg/apache/dubbo/metrics/model/key/MetricsCat;
      54: getstatic     #15                 // Field org/apache/dubbo/metrics/metadata/event/MetadataSubDispatcher$MCat.SERVICE_SUBSCRIBE_FINISH:Lorg/apache/dubbo/metrics/model/key/MetricsCat;
      57: getstatic     #16                 // Field org/apache/dubbo/metrics/metadata/event/MetadataSubDispatcher$MCat.SERVICE_SUBSCRIBE_ERROR:Lorg/apache/dubbo/metrics/model/key/MetricsCat;
      60: invokespecial #6                  // Method org/apache/dubbo/metrics/model/key/CategoryOverall."<init>":(Lorg/apache/dubbo/metrics/model/key/MetricsPlaceValue;Lorg/apache/dubbo/metrics/model/key/MetricsCat;Lorg/apache/dubbo/metrics/model/key/MetricsCat;Lorg/apache/dubbo/metrics/model/key/MetricsCat;)V
      63: putstatic     #17                 // Field SERVICE_SUBSCRIBE:Lorg/apache/dubbo/metrics/model/key/CategoryOverall;
      66: iconst_3
      67: anewarray     #1                  // class org/apache/dubbo/metrics/model/key/CategoryOverall
      70: dup
      71: iconst_0
      72: getstatic     #7                  // Field APPLICATION_PUSH:Lorg/apache/dubbo/metrics/model/key/CategoryOverall;
      75: aastore
      76: dup
      77: iconst_1
      78: getstatic     #12                 // Field APPLICATION_SUBSCRIBE:Lorg/apache/dubbo/metrics/model/key/CategoryOverall;
      81: aastore
      82: dup
      83: iconst_2
      84: getstatic     #17                 // Field SERVICE_SUBSCRIBE:Lorg/apache/dubbo/metrics/model/key/CategoryOverall;
      87: aastore
      88: invokestatic  #18                 // Method java/util/Arrays.asList:([Ljava/lang/Object;)Ljava/util/List;
      91: putstatic     #19                 // Field ALL:Ljava/util/List;
      94: return
}
