Compiled from "MetadataEvent.java"
public class org.apache.dubbo.metrics.metadata.event.MetadataEvent extends org.apache.dubbo.metrics.event.TimeCounterEvent {
  public org.apache.dubbo.metrics.metadata.event.MetadataEvent(org.apache.dubbo.rpc.model.ApplicationModel, org.apache.dubbo.metrics.model.key.TypeWrapper);
    Code:
       0: aload_0
       1: aload_1
       2: aload_2
       3: invokespecial #2                  // Method org/apache/dubbo/metrics/event/TimeCounterEvent."<init>":(Lorg/apache/dubbo/rpc/model/ApplicationModel;Lorg/apache/dubbo/metrics/model/key/TypeWrapper;)V
       6: aload_1
       7: invokevirtual #3                  // Method org/apache/dubbo/rpc/model/ApplicationModel.getBeanFactory:()Lorg/apache/dubbo/common/beans/factory/ScopeBeanFactory;
      10: astore_3
      11: aload_3
      12: invokevirtual #4                  // Method org/apache/dubbo/common/beans/factory/ScopeBeanFactory.isDestroyed:()Z
      15: ifne          51
      18: aload_3
      19: ldc           #5                  // class org/apache/dubbo/metrics/metadata/collector/MetadataMetricsCollector
      21: invokevirtual #6                  // Method org/apache/dubbo/common/beans/factory/ScopeBeanFactory.getBean:(Ljava/lang/Class;)Ljava/lang/Object;
      24: checkcast     #5                  // class org/apache/dubbo/metrics/metadata/collector/MetadataMetricsCollector
      27: astore        4
      29: aload_0
      30: aload         4
      32: ifnull        47
      35: aload         4
      37: invokevirtual #7                  // Method org/apache/dubbo/metrics/metadata/collector/MetadataMetricsCollector.isCollectEnabled:()Z
      40: ifeq          47
      43: iconst_1
      44: goto          48
      47: iconst_0
      48: invokespecial #8                  // Method org/apache/dubbo/metrics/event/TimeCounterEvent.setAvailable:(Z)V
      51: return

  public static org.apache.dubbo.metrics.metadata.event.MetadataEvent toPushEvent(org.apache.dubbo.rpc.model.ApplicationModel);
    Code:
       0: new           #9                  // class org/apache/dubbo/metrics/metadata/event/MetadataEvent
       3: dup
       4: aload_0
       5: new           #10                 // class org/apache/dubbo/metrics/model/key/TypeWrapper
       8: dup
       9: getstatic     #11                 // Field org/apache/dubbo/metrics/model/key/MetricsLevel.APP:Lorg/apache/dubbo/metrics/model/key/MetricsLevel;
      12: getstatic     #12                 // Field org/apache/dubbo/metrics/model/key/MetricsKey.METADATA_PUSH_METRIC_NUM:Lorg/apache/dubbo/metrics/model/key/MetricsKey;
      15: getstatic     #13                 // Field org/apache/dubbo/metrics/model/key/MetricsKey.METADATA_PUSH_METRIC_NUM_SUCCEED:Lorg/apache/dubbo/metrics/model/key/MetricsKey;
      18: getstatic     #14                 // Field org/apache/dubbo/metrics/model/key/MetricsKey.METADATA_PUSH_METRIC_NUM_FAILED:Lorg/apache/dubbo/metrics/model/key/MetricsKey;
      21: invokespecial #15                 // Method org/apache/dubbo/metrics/model/key/TypeWrapper."<init>":(Lorg/apache/dubbo/metrics/model/key/MetricsLevel;Lorg/apache/dubbo/metrics/model/key/MetricsKey;Lorg/apache/dubbo/metrics/model/key/MetricsKey;Lorg/apache/dubbo/metrics/model/key/MetricsKey;)V
      24: invokespecial #16                 // Method "<init>":(Lorg/apache/dubbo/rpc/model/ApplicationModel;Lorg/apache/dubbo/metrics/model/key/TypeWrapper;)V
      27: areturn

  public static org.apache.dubbo.metrics.metadata.event.MetadataEvent toSubscribeEvent(org.apache.dubbo.rpc.model.ApplicationModel);
    Code:
       0: new           #9                  // class org/apache/dubbo/metrics/metadata/event/MetadataEvent
       3: dup
       4: aload_0
       5: new           #10                 // class org/apache/dubbo/metrics/model/key/TypeWrapper
       8: dup
       9: getstatic     #11                 // Field org/apache/dubbo/metrics/model/key/MetricsLevel.APP:Lorg/apache/dubbo/metrics/model/key/MetricsLevel;
      12: getstatic     #17                 // Field org/apache/dubbo/metrics/model/key/MetricsKey.METADATA_SUBSCRIBE_METRIC_NUM:Lorg/apache/dubbo/metrics/model/key/MetricsKey;
      15: getstatic     #18                 // Field org/apache/dubbo/metrics/model/key/MetricsKey.METADATA_SUBSCRIBE_METRIC_NUM_SUCCEED:Lorg/apache/dubbo/metrics/model/key/MetricsKey;
      18: getstatic     #19                 // Field org/apache/dubbo/metrics/model/key/MetricsKey.METADATA_SUBSCRIBE_METRIC_NUM_FAILED:Lorg/apache/dubbo/metrics/model/key/MetricsKey;
      21: invokespecial #15                 // Method org/apache/dubbo/metrics/model/key/TypeWrapper."<init>":(Lorg/apache/dubbo/metrics/model/key/MetricsLevel;Lorg/apache/dubbo/metrics/model/key/MetricsKey;Lorg/apache/dubbo/metrics/model/key/MetricsKey;Lorg/apache/dubbo/metrics/model/key/MetricsKey;)V
      24: invokespecial #16                 // Method "<init>":(Lorg/apache/dubbo/rpc/model/ApplicationModel;Lorg/apache/dubbo/metrics/model/key/TypeWrapper;)V
      27: areturn

  public static org.apache.dubbo.metrics.metadata.event.MetadataEvent toServiceSubscribeEvent(org.apache.dubbo.rpc.model.ApplicationModel, java.lang.String);
    Code:
       0: new           #9                  // class org/apache/dubbo/metrics/metadata/event/MetadataEvent
       3: dup
       4: aload_0
       5: new           #10                 // class org/apache/dubbo/metrics/model/key/TypeWrapper
       8: dup
       9: getstatic     #11                 // Field org/apache/dubbo/metrics/model/key/MetricsLevel.APP:Lorg/apache/dubbo/metrics/model/key/MetricsLevel;
      12: getstatic     #20                 // Field org/apache/dubbo/metrics/model/key/MetricsKey.STORE_PROVIDER_METADATA:Lorg/apache/dubbo/metrics/model/key/MetricsKey;
      15: getstatic     #21                 // Field org/apache/dubbo/metrics/model/key/MetricsKey.STORE_PROVIDER_METADATA_SUCCEED:Lorg/apache/dubbo/metrics/model/key/MetricsKey;
      18: getstatic     #22                 // Field org/apache/dubbo/metrics/model/key/MetricsKey.STORE_PROVIDER_METADATA_FAILED:Lorg/apache/dubbo/metrics/model/key/MetricsKey;
      21: invokespecial #15                 // Method org/apache/dubbo/metrics/model/key/TypeWrapper."<init>":(Lorg/apache/dubbo/metrics/model/key/MetricsLevel;Lorg/apache/dubbo/metrics/model/key/MetricsKey;Lorg/apache/dubbo/metrics/model/key/MetricsKey;Lorg/apache/dubbo/metrics/model/key/MetricsKey;)V
      24: invokespecial #16                 // Method "<init>":(Lorg/apache/dubbo/rpc/model/ApplicationModel;Lorg/apache/dubbo/metrics/model/key/TypeWrapper;)V
      27: astore_2
      28: aload_2
      29: ldc           #23                 // String serviceKey
      31: aload_1
      32: invokevirtual #24                 // Method putAttachment:(Ljava/lang/String;Ljava/lang/Object;)V
      35: aload_2
      36: areturn
}
