Compiled from "MetadataSubDispatcher.java"
interface org.apache.dubbo.metrics.metadata.event.MetadataSubDispatcher$MCat {
  public static final org.apache.dubbo.metrics.model.key.MetricsCat APPLICATION_PUSH_POST;

  public static final org.apache.dubbo.metrics.model.key.MetricsCat APPLICATION_PUSH_FINISH;

  public static final org.apache.dubbo.metrics.model.key.MetricsCat APPLICATION_PUSH_ERROR;

  public static final org.apache.dubbo.metrics.model.key.MetricsCat APPLICATION_SUBSCRIBE_POST;

  public static final org.apache.dubbo.metrics.model.key.MetricsCat APPLICATION_SUBSCRIBE_FINISH;

  public static final org.apache.dubbo.metrics.model.key.MetricsCat APPLICATION_SUBSCRIBE_ERROR;

  public static final org.apache.dubbo.metrics.model.key.MetricsCat SERVICE_SUBSCRIBE_POST;

  public static final org.apache.dubbo.metrics.model.key.MetricsCat SERVICE_SUBSCRIBE_FINISH;

  public static final org.apache.dubbo.metrics.model.key.MetricsCat SERVICE_SUBSCRIBE_ERROR;

  static {};
    Code:
       0: new           #1                  // class org/apache/dubbo/metrics/model/key/MetricsCat
       3: dup
       4: getstatic     #2                  // Field org/apache/dubbo/metrics/model/key/MetricsKey.METADATA_PUSH_METRIC_NUM:Lorg/apache/dubbo/metrics/model/key/MetricsKey;
       7: invokedynamic #3,  0              // InvokeDynamic #0:apply:()Ljava/util/function/BiFunction;
      12: invokespecial #4                  // Method org/apache/dubbo/metrics/model/key/MetricsCat."<init>":(Lorg/apache/dubbo/metrics/model/key/MetricsKey;Ljava/util/function/BiFunction;)V
      15: putstatic     #5                  // Field APPLICATION_PUSH_POST:Lorg/apache/dubbo/metrics/model/key/MetricsCat;
      18: new           #1                  // class org/apache/dubbo/metrics/model/key/MetricsCat
      21: dup
      22: getstatic     #6                  // Field org/apache/dubbo/metrics/model/key/MetricsKey.METADATA_PUSH_METRIC_NUM_SUCCEED:Lorg/apache/dubbo/metrics/model/key/MetricsKey;
      25: invokedynamic #7,  0              // InvokeDynamic #1:apply:()Lorg/apache/dubbo/metrics/model/key/MetricsCat$TpFunction;
      30: invokespecial #8                  // Method org/apache/dubbo/metrics/model/key/MetricsCat."<init>":(Lorg/apache/dubbo/metrics/model/key/MetricsKey;Lorg/apache/dubbo/metrics/model/key/MetricsCat$TpFunction;)V
      33: putstatic     #9                  // Field APPLICATION_PUSH_FINISH:Lorg/apache/dubbo/metrics/model/key/MetricsCat;
      36: new           #1                  // class org/apache/dubbo/metrics/model/key/MetricsCat
      39: dup
      40: getstatic     #10                 // Field org/apache/dubbo/metrics/model/key/MetricsKey.METADATA_PUSH_METRIC_NUM_FAILED:Lorg/apache/dubbo/metrics/model/key/MetricsKey;
      43: invokedynamic #11,  0             // InvokeDynamic #2:apply:()Lorg/apache/dubbo/metrics/model/key/MetricsCat$TpFunction;
      48: invokespecial #8                  // Method org/apache/dubbo/metrics/model/key/MetricsCat."<init>":(Lorg/apache/dubbo/metrics/model/key/MetricsKey;Lorg/apache/dubbo/metrics/model/key/MetricsCat$TpFunction;)V
      51: putstatic     #12                 // Field APPLICATION_PUSH_ERROR:Lorg/apache/dubbo/metrics/model/key/MetricsCat;
      54: new           #1                  // class org/apache/dubbo/metrics/model/key/MetricsCat
      57: dup
      58: getstatic     #13                 // Field org/apache/dubbo/metrics/model/key/MetricsKey.METADATA_SUBSCRIBE_METRIC_NUM:Lorg/apache/dubbo/metrics/model/key/MetricsKey;
      61: invokedynamic #3,  0              // InvokeDynamic #0:apply:()Ljava/util/function/BiFunction;
      66: invokespecial #4                  // Method org/apache/dubbo/metrics/model/key/MetricsCat."<init>":(Lorg/apache/dubbo/metrics/model/key/MetricsKey;Ljava/util/function/BiFunction;)V
      69: putstatic     #14                 // Field APPLICATION_SUBSCRIBE_POST:Lorg/apache/dubbo/metrics/model/key/MetricsCat;
      72: new           #1                  // class org/apache/dubbo/metrics/model/key/MetricsCat
      75: dup
      76: getstatic     #15                 // Field org/apache/dubbo/metrics/model/key/MetricsKey.METADATA_SUBSCRIBE_METRIC_NUM_SUCCEED:Lorg/apache/dubbo/metrics/model/key/MetricsKey;
      79: invokedynamic #7,  0              // InvokeDynamic #1:apply:()Lorg/apache/dubbo/metrics/model/key/MetricsCat$TpFunction;
      84: invokespecial #8                  // Method org/apache/dubbo/metrics/model/key/MetricsCat."<init>":(Lorg/apache/dubbo/metrics/model/key/MetricsKey;Lorg/apache/dubbo/metrics/model/key/MetricsCat$TpFunction;)V
      87: putstatic     #16                 // Field APPLICATION_SUBSCRIBE_FINISH:Lorg/apache/dubbo/metrics/model/key/MetricsCat;
      90: new           #1                  // class org/apache/dubbo/metrics/model/key/MetricsCat
      93: dup
      94: getstatic     #17                 // Field org/apache/dubbo/metrics/model/key/MetricsKey.METADATA_SUBSCRIBE_METRIC_NUM_FAILED:Lorg/apache/dubbo/metrics/model/key/MetricsKey;
      97: invokedynamic #11,  0             // InvokeDynamic #2:apply:()Lorg/apache/dubbo/metrics/model/key/MetricsCat$TpFunction;
     102: invokespecial #8                  // Method org/apache/dubbo/metrics/model/key/MetricsCat."<init>":(Lorg/apache/dubbo/metrics/model/key/MetricsKey;Lorg/apache/dubbo/metrics/model/key/MetricsCat$TpFunction;)V
     105: putstatic     #18                 // Field APPLICATION_SUBSCRIBE_ERROR:Lorg/apache/dubbo/metrics/model/key/MetricsCat;
     108: new           #1                  // class org/apache/dubbo/metrics/model/key/MetricsCat
     111: dup
     112: getstatic     #19                 // Field org/apache/dubbo/metrics/model/key/MetricsKey.STORE_PROVIDER_METADATA:Lorg/apache/dubbo/metrics/model/key/MetricsKey;
     115: invokedynamic #20,  0             // InvokeDynamic #3:apply:()Lorg/apache/dubbo/metrics/model/key/MetricsCat$TpFunction;
     120: invokespecial #8                  // Method org/apache/dubbo/metrics/model/key/MetricsCat."<init>":(Lorg/apache/dubbo/metrics/model/key/MetricsKey;Lorg/apache/dubbo/metrics/model/key/MetricsCat$TpFunction;)V
     123: putstatic     #21                 // Field SERVICE_SUBSCRIBE_POST:Lorg/apache/dubbo/metrics/model/key/MetricsCat;
     126: new           #1                  // class org/apache/dubbo/metrics/model/key/MetricsCat
     129: dup
     130: getstatic     #22                 // Field org/apache/dubbo/metrics/model/key/MetricsKey.STORE_PROVIDER_METADATA_SUCCEED:Lorg/apache/dubbo/metrics/model/key/MetricsKey;
     133: invokedynamic #23,  0             // InvokeDynamic #4:apply:()Lorg/apache/dubbo/metrics/model/key/MetricsCat$TpFunction;
     138: invokespecial #8                  // Method org/apache/dubbo/metrics/model/key/MetricsCat."<init>":(Lorg/apache/dubbo/metrics/model/key/MetricsKey;Lorg/apache/dubbo/metrics/model/key/MetricsCat$TpFunction;)V
     141: putstatic     #24                 // Field SERVICE_SUBSCRIBE_FINISH:Lorg/apache/dubbo/metrics/model/key/MetricsCat;
     144: new           #1                  // class org/apache/dubbo/metrics/model/key/MetricsCat
     147: dup
     148: getstatic     #25                 // Field org/apache/dubbo/metrics/model/key/MetricsKey.STORE_PROVIDER_METADATA_FAILED:Lorg/apache/dubbo/metrics/model/key/MetricsKey;
     151: invokedynamic #26,  0             // InvokeDynamic #5:apply:()Lorg/apache/dubbo/metrics/model/key/MetricsCat$TpFunction;
     156: invokespecial #8                  // Method org/apache/dubbo/metrics/model/key/MetricsCat."<init>":(Lorg/apache/dubbo/metrics/model/key/MetricsKey;Lorg/apache/dubbo/metrics/model/key/MetricsCat$TpFunction;)V
     159: putstatic     #27                 // Field SERVICE_SUBSCRIBE_ERROR:Lorg/apache/dubbo/metrics/model/key/MetricsCat;
     162: return
}
