Compiled from "NativeJavaObjectInput.java"
public class org.apache.dubbo.common.serialize.nativejava.NativeJavaObjectInput implements org.apache.dubbo.common.serialize.ObjectInput {
  private final java.io.ObjectInputStream inputStream;

  public org.apache.dubbo.common.serialize.nativejava.NativeJavaObjectInput(java.io.InputStream) throws java.io.IOException;
    Code:
       0: aload_0
       1: new           #1                  // class java/io/ObjectInputStream
       4: dup
       5: aload_1
       6: invokespecial #2                  // Method java/io/ObjectInputStream."<init>":(Ljava/io/InputStream;)V
       9: invokespecial #3                  // Method "<init>":(Ljava/io/ObjectInputStream;)V
      12: return

  protected org.apache.dubbo.common.serialize.nativejava.NativeJavaObjectInput(java.io.ObjectInputStream);
    Code:
       0: aload_0
       1: invokespecial #4                  // Method java/lang/Object."<init>":()V
       4: aload_1
       5: ldc           #5                  // String input == null
       7: invokestatic  #6                  // Method org/apache/dubbo/common/utils/Assert.notNull:(Ljava/lang/Object;Ljava/lang/String;)V
      10: aload_0
      11: aload_1
      12: putfield      #7                  // Field inputStream:Ljava/io/ObjectInputStream;
      15: return

  protected java.io.ObjectInputStream getObjectInputStream();
    Code:
       0: aload_0
       1: getfield      #7                  // Field inputStream:Ljava/io/ObjectInputStream;
       4: areturn

  public java.lang.Object readObject() throws java.io.IOException, java.lang.ClassNotFoundException;
    Code:
       0: aload_0
       1: getfield      #7                  // Field inputStream:Ljava/io/ObjectInputStream;
       4: invokevirtual #8                  // Method java/io/ObjectInputStream.readObject:()Ljava/lang/Object;
       7: areturn

  public <T> T readObject(java.lang.Class<T>) throws java.io.IOException, java.lang.ClassNotFoundException;
    Code:
       0: aload_0
       1: invokevirtual #9                  // Method readObject:()Ljava/lang/Object;
       4: areturn

  public <T> T readObject(java.lang.Class<T>, java.lang.reflect.Type) throws java.io.IOException, java.lang.ClassNotFoundException;
    Code:
       0: aload_0
       1: invokevirtual #9                  // Method readObject:()Ljava/lang/Object;
       4: areturn

  public boolean readBool() throws java.io.IOException;
    Code:
       0: aload_0
       1: getfield      #7                  // Field inputStream:Ljava/io/ObjectInputStream;
       4: invokevirtual #10                 // Method java/io/ObjectInputStream.readBoolean:()Z
       7: ireturn

  public byte readByte() throws java.io.IOException;
    Code:
       0: aload_0
       1: getfield      #7                  // Field inputStream:Ljava/io/ObjectInputStream;
       4: invokevirtual #11                 // Method java/io/ObjectInputStream.readByte:()B
       7: ireturn

  public short readShort() throws java.io.IOException;
    Code:
       0: aload_0
       1: getfield      #7                  // Field inputStream:Ljava/io/ObjectInputStream;
       4: invokevirtual #12                 // Method java/io/ObjectInputStream.readShort:()S
       7: ireturn

  public int readInt() throws java.io.IOException;
    Code:
       0: aload_0
       1: getfield      #7                  // Field inputStream:Ljava/io/ObjectInputStream;
       4: invokevirtual #13                 // Method java/io/ObjectInputStream.readInt:()I
       7: ireturn

  public long readLong() throws java.io.IOException;
    Code:
       0: aload_0
       1: getfield      #7                  // Field inputStream:Ljava/io/ObjectInputStream;
       4: invokevirtual #14                 // Method java/io/ObjectInputStream.readLong:()J
       7: lreturn

  public float readFloat() throws java.io.IOException;
    Code:
       0: aload_0
       1: getfield      #7                  // Field inputStream:Ljava/io/ObjectInputStream;
       4: invokevirtual #15                 // Method java/io/ObjectInputStream.readFloat:()F
       7: freturn

  public double readDouble() throws java.io.IOException;
    Code:
       0: aload_0
       1: getfield      #7                  // Field inputStream:Ljava/io/ObjectInputStream;
       4: invokevirtual #16                 // Method java/io/ObjectInputStream.readDouble:()D
       7: dreturn

  public java.lang.String readUTF() throws java.io.IOException;
    Code:
       0: aload_0
       1: getfield      #7                  // Field inputStream:Ljava/io/ObjectInputStream;
       4: invokevirtual #17                 // Method java/io/ObjectInputStream.readUTF:()Ljava/lang/String;
       7: areturn

  public byte[] readBytes() throws java.io.IOException;
    Code:
       0: aload_0
       1: getfield      #7                  // Field inputStream:Ljava/io/ObjectInputStream;
       4: invokevirtual #13                 // Method java/io/ObjectInputStream.readInt:()I
       7: istore_1
       8: iload_1
       9: ifge          14
      12: aconst_null
      13: areturn
      14: iload_1
      15: ifne          22
      18: iconst_0
      19: newarray       byte
      21: areturn
      22: iload_1
      23: newarray       byte
      25: astore_2
      26: aload_0
      27: getfield      #7                  // Field inputStream:Ljava/io/ObjectInputStream;
      30: aload_2
      31: invokevirtual #18                 // Method java/io/ObjectInputStream.readFully:([B)V
      34: aload_2
      35: areturn
}
