Compiled from "NativeJavaObjectOutput.java"
public class org.apache.dubbo.common.serialize.nativejava.NativeJavaObjectOutput implements org.apache.dubbo.common.serialize.ObjectOutput {
  private final java.io.ObjectOutputStream outputStream;

  public org.apache.dubbo.common.serialize.nativejava.NativeJavaObjectOutput(java.io.OutputStream) throws java.io.IOException;
    Code:
       0: aload_0
       1: new           #1                  // class java/io/ObjectOutputStream
       4: dup
       5: aload_1
       6: invokespecial #2                  // Method java/io/ObjectOutputStream."<init>":(Ljava/io/OutputStream;)V
       9: invokespecial #3                  // Method "<init>":(Ljava/io/ObjectOutputStream;)V
      12: return

  protected org.apache.dubbo.common.serialize.nativejava.NativeJavaObjectOutput(java.io.ObjectOutputStream);
    Code:
       0: aload_0
       1: invokespecial #4                  // Method java/lang/Object."<init>":()V
       4: aload_1
       5: ldc           #5                  // String output == null
       7: invokestatic  #6                  // Method org/apache/dubbo/common/utils/Assert.notNull:(Ljava/lang/Object;Ljava/lang/String;)V
      10: aload_0
      11: aload_1
      12: putfield      #7                  // Field outputStream:Ljava/io/ObjectOutputStream;
      15: return

  protected java.io.ObjectOutputStream getObjectOutputStream();
    Code:
       0: aload_0
       1: getfield      #7                  // Field outputStream:Ljava/io/ObjectOutputStream;
       4: areturn

  public void writeObject(java.lang.Object) throws java.io.IOException;
    Code:
       0: aload_0
       1: getfield      #7                  // Field outputStream:Ljava/io/ObjectOutputStream;
       4: aload_1
       5: invokevirtual #8                  // Method java/io/ObjectOutputStream.writeObject:(Ljava/lang/Object;)V
       8: return

  public void writeBool(boolean) throws java.io.IOException;
    Code:
       0: aload_0
       1: getfield      #7                  // Field outputStream:Ljava/io/ObjectOutputStream;
       4: iload_1
       5: invokevirtual #9                  // Method java/io/ObjectOutputStream.writeBoolean:(Z)V
       8: return

  public void writeByte(byte) throws java.io.IOException;
    Code:
       0: aload_0
       1: getfield      #7                  // Field outputStream:Ljava/io/ObjectOutputStream;
       4: iload_1
       5: invokevirtual #10                 // Method java/io/ObjectOutputStream.writeByte:(I)V
       8: return

  public void writeShort(short) throws java.io.IOException;
    Code:
       0: aload_0
       1: getfield      #7                  // Field outputStream:Ljava/io/ObjectOutputStream;
       4: iload_1
       5: invokevirtual #11                 // Method java/io/ObjectOutputStream.writeShort:(I)V
       8: return

  public void writeInt(int) throws java.io.IOException;
    Code:
       0: aload_0
       1: getfield      #7                  // Field outputStream:Ljava/io/ObjectOutputStream;
       4: iload_1
       5: invokevirtual #12                 // Method java/io/ObjectOutputStream.writeInt:(I)V
       8: return

  public void writeLong(long) throws java.io.IOException;
    Code:
       0: aload_0
       1: getfield      #7                  // Field outputStream:Ljava/io/ObjectOutputStream;
       4: lload_1
       5: invokevirtual #13                 // Method java/io/ObjectOutputStream.writeLong:(J)V
       8: return

  public void writeFloat(float) throws java.io.IOException;
    Code:
       0: aload_0
       1: getfield      #7                  // Field outputStream:Ljava/io/ObjectOutputStream;
       4: fload_1
       5: invokevirtual #14                 // Method java/io/ObjectOutputStream.writeFloat:(F)V
       8: return

  public void writeDouble(double) throws java.io.IOException;
    Code:
       0: aload_0
       1: getfield      #7                  // Field outputStream:Ljava/io/ObjectOutputStream;
       4: dload_1
       5: invokevirtual #15                 // Method java/io/ObjectOutputStream.writeDouble:(D)V
       8: return

  public void writeUTF(java.lang.String) throws java.io.IOException;
    Code:
       0: aload_0
       1: getfield      #7                  // Field outputStream:Ljava/io/ObjectOutputStream;
       4: aload_1
       5: invokevirtual #16                 // Method java/io/ObjectOutputStream.writeUTF:(Ljava/lang/String;)V
       8: return

  public void writeBytes(byte[]) throws java.io.IOException;
    Code:
       0: aload_1
       1: ifnonnull     15
       4: aload_0
       5: getfield      #7                  // Field outputStream:Ljava/io/ObjectOutputStream;
       8: iconst_m1
       9: invokevirtual #12                 // Method java/io/ObjectOutputStream.writeInt:(I)V
      12: goto          23
      15: aload_0
      16: aload_1
      17: iconst_0
      18: aload_1
      19: arraylength
      20: invokevirtual #17                 // Method writeBytes:([BII)V
      23: return

  public void writeBytes(byte[], int, int) throws java.io.IOException;
    Code:
       0: aload_1
       1: ifnonnull     15
       4: aload_0
       5: getfield      #7                  // Field outputStream:Ljava/io/ObjectOutputStream;
       8: iconst_m1
       9: invokevirtual #12                 // Method java/io/ObjectOutputStream.writeInt:(I)V
      12: goto          33
      15: aload_0
      16: getfield      #7                  // Field outputStream:Ljava/io/ObjectOutputStream;
      19: iload_3
      20: invokevirtual #12                 // Method java/io/ObjectOutputStream.writeInt:(I)V
      23: aload_0
      24: getfield      #7                  // Field outputStream:Ljava/io/ObjectOutputStream;
      27: aload_1
      28: iload_2
      29: iload_3
      30: invokevirtual #18                 // Method java/io/ObjectOutputStream.write:([BII)V
      33: return

  public void flushBuffer() throws java.io.IOException;
    Code:
       0: aload_0
       1: getfield      #7                  // Field outputStream:Ljava/io/ObjectOutputStream;
       4: invokevirtual #19                 // Method java/io/ObjectOutputStream.flush:()V
       7: return
}
