Compiled from "NettyHttpRestServer.java"
class org.apache.dubbo.rpc.protocol.rest.NettyHttpRestServer$1 implements org.apache.dubbo.rpc.protocol.rest.netty.UnSharedHandlerCreator {
  final org.apache.dubbo.rpc.protocol.rest.NettyHttpRestServer this$0;

  org.apache.dubbo.rpc.protocol.rest.NettyHttpRestServer$1(org.apache.dubbo.rpc.protocol.rest.NettyHttpRestServer);
    Code:
       0: aload_0
       1: aload_1
       2: putfield      #1                  // Field this$0:Lorg/apache/dubbo/rpc/protocol/rest/NettyHttpRestServer;
       5: aload_0
       6: invokespecial #2                  // Method java/lang/Object."<init>":()V
       9: return

  public java.util.List<io.netty.channel.ChannelHandler> getUnSharedHandlers(org.apache.dubbo.common.URL);
    Code:
       0: iconst_5
       1: anewarray     #3                  // class io/netty/channel/ChannelHandler
       4: dup
       5: iconst_0
       6: new           #4                  // class org/apache/dubbo/rpc/protocol/rest/netty/ssl/SslServerTlsHandler
       9: dup
      10: aload_1
      11: invokespecial #5                  // Method org/apache/dubbo/rpc/protocol/rest/netty/ssl/SslServerTlsHandler."<init>":(Lorg/apache/dubbo/common/URL;)V
      14: aastore
      15: dup
      16: iconst_1
      17: new           #6                  // class io/netty/handler/codec/http/HttpRequestDecoder
      20: dup
      21: aload_1
      22: ldc           #8                  // String max.initial.line.length
      24: sipush        4096
      27: invokevirtual #9                  // Method org/apache/dubbo/common/URL.getParameter:(Ljava/lang/String;I)I
      30: aload_1
      31: ldc           #10                 // String max.header.size
      33: sipush        8192
      36: invokevirtual #9                  // Method org/apache/dubbo/common/URL.getParameter:(Ljava/lang/String;I)I
      39: aload_1
      40: ldc           #11                 // String max.chunk.size
      42: sipush        8192
      45: invokevirtual #9                  // Method org/apache/dubbo/common/URL.getParameter:(Ljava/lang/String;I)I
      48: invokespecial #12                 // Method io/netty/handler/codec/http/HttpRequestDecoder."<init>":(III)V
      51: aastore
      52: dup
      53: iconst_2
      54: new           #13                 // class io/netty/handler/codec/http/HttpObjectAggregator
      57: dup
      58: aload_1
      59: ldc           #14                 // String max.request.size
      61: ldc           #15                 // int 10485760
      63: invokevirtual #9                  // Method org/apache/dubbo/common/URL.getParameter:(Ljava/lang/String;I)I
      66: invokespecial #16                 // Method io/netty/handler/codec/http/HttpObjectAggregator."<init>":(I)V
      69: aastore
      70: dup
      71: iconst_3
      72: new           #17                 // class io/netty/handler/codec/http/HttpResponseEncoder
      75: dup
      76: invokespecial #18                 // Method io/netty/handler/codec/http/HttpResponseEncoder."<init>":()V
      79: aastore
      80: dup
      81: iconst_4
      82: new           #19                 // class org/apache/dubbo/rpc/protocol/rest/netty/RestHttpRequestDecoder
      85: dup
      86: new           #20                 // class org/apache/dubbo/rpc/protocol/rest/handler/NettyHttpHandler
      89: dup
      90: aload_0
      91: getfield      #1                  // Field this$0:Lorg/apache/dubbo/rpc/protocol/rest/NettyHttpRestServer;
      94: invokestatic  #21                 // Method org/apache/dubbo/rpc/protocol/rest/NettyHttpRestServer.access$000:(Lorg/apache/dubbo/rpc/protocol/rest/NettyHttpRestServer;)Lorg/apache/dubbo/rpc/protocol/rest/PathAndInvokerMapper;
      97: aload_0
      98: getfield      #1                  // Field this$0:Lorg/apache/dubbo/rpc/protocol/rest/NettyHttpRestServer;
     101: invokestatic  #22                 // Method org/apache/dubbo/rpc/protocol/rest/NettyHttpRestServer.access$100:(Lorg/apache/dubbo/rpc/protocol/rest/NettyHttpRestServer;)Lorg/apache/dubbo/rpc/protocol/rest/exception/mapper/ExceptionMapper;
     104: invokespecial #23                 // Method org/apache/dubbo/rpc/protocol/rest/handler/NettyHttpHandler."<init>":(Lorg/apache/dubbo/rpc/protocol/rest/PathAndInvokerMapper;Lorg/apache/dubbo/rpc/protocol/rest/exception/mapper/ExceptionMapper;)V
     107: aload_1
     108: invokespecial #24                 // Method org/apache/dubbo/rpc/protocol/rest/netty/RestHttpRequestDecoder."<init>":(Lorg/apache/dubbo/rpc/protocol/rest/handler/NettyHttpHandler;Lorg/apache/dubbo/common/URL;)V
     111: aastore
     112: invokestatic  #25                 // Method java/util/Arrays.asList:([Ljava/lang/Object;)Ljava/util/List;
     115: areturn
}
