Compiled from "PathAndInvokerMapper.java"
public class org.apache.dubbo.rpc.protocol.rest.PathAndInvokerMapper {
  private static final org.apache.dubbo.common.logger.ErrorTypeAwareLogger logger;

  private final java.util.Map<org.apache.dubbo.metadata.rest.PathMatcher, org.apache.dubbo.rpc.protocol.rest.pair.InvokerAndRestMethodMetadataPair> pathToServiceMapContainPathVariable;

  private final java.util.Map<org.apache.dubbo.metadata.rest.PathMatcher, org.apache.dubbo.rpc.protocol.rest.pair.InvokerAndRestMethodMetadataPair> pathToServiceMapNoPathVariable;

  public org.apache.dubbo.rpc.protocol.rest.PathAndInvokerMapper();
    Code:
       0: aload_0
       1: invokespecial #1                  // Method java/lang/Object."<init>":()V
       4: aload_0
       5: new           #2                  // class java/util/concurrent/ConcurrentHashMap
       8: dup
       9: invokespecial #3                  // Method java/util/concurrent/ConcurrentHashMap."<init>":()V
      12: putfield      #4                  // Field pathToServiceMapContainPathVariable:Ljava/util/Map;
      15: aload_0
      16: new           #2                  // class java/util/concurrent/ConcurrentHashMap
      19: dup
      20: invokespecial #3                  // Method java/util/concurrent/ConcurrentHashMap."<init>":()V
      23: putfield      #5                  // Field pathToServiceMapNoPathVariable:Ljava/util/Map;
      26: return

  public void addPathAndInvoker(java.util.Map<org.apache.dubbo.metadata.rest.PathMatcher, org.apache.dubbo.metadata.rest.RestMethodMetadata>, org.apache.dubbo.rpc.Invoker);
    Code:
       0: aload_1
       1: invokeinterface #6,  1            // InterfaceMethod java/util/Map.entrySet:()Ljava/util/Set;
       6: invokeinterface #7,  1            // InterfaceMethod java/util/Set.stream:()Ljava/util/stream/Stream;
      11: aload_0
      12: aload_2
      13: invokedynamic #8,  0              // InvokeDynamic #0:accept:(Lorg/apache/dubbo/rpc/protocol/rest/PathAndInvokerMapper;Lorg/apache/dubbo/rpc/Invoker;)Ljava/util/function/Consumer;
      18: invokeinterface #9,  2            // InterfaceMethod java/util/stream/Stream.forEach:(Ljava/util/function/Consumer;)V
      23: return

  public org.apache.dubbo.rpc.protocol.rest.pair.InvokerAndRestMethodMetadataPair getRestMethodMetadata(java.lang.String, java.lang.String, java.lang.String, java.lang.Integer, java.lang.String);
    Code:
       0: aload_1
       1: aload_2
       2: aload_3
       3: aload         4
       5: aload         5
       7: invokestatic  #10                 // Method org/apache/dubbo/metadata/rest/PathMatcher.getInvokeCreatePathMatcher:(Ljava/lang/String;Ljava/lang/String;Ljava/lang/String;Ljava/lang/Integer;Ljava/lang/String;)Lorg/apache/dubbo/metadata/rest/PathMatcher;
      10: astore        6
      12: aload_0
      13: getfield      #5                  // Field pathToServiceMapNoPathVariable:Ljava/util/Map;
      16: aload         6
      18: invokeinterface #11,  2           // InterfaceMethod java/util/Map.containsKey:(Ljava/lang/Object;)Z
      23: ifeq          41
      26: aload_0
      27: getfield      #5                  // Field pathToServiceMapNoPathVariable:Ljava/util/Map;
      30: aload         6
      32: invokeinterface #12,  2           // InterfaceMethod java/util/Map.get:(Ljava/lang/Object;)Ljava/lang/Object;
      37: checkcast     #13                 // class org/apache/dubbo/rpc/protocol/rest/pair/InvokerAndRestMethodMetadataPair
      40: areturn
      41: aload_0
      42: getfield      #4                  // Field pathToServiceMapContainPathVariable:Ljava/util/Map;
      45: aload         6
      47: invokeinterface #11,  2           // InterfaceMethod java/util/Map.containsKey:(Ljava/lang/Object;)Z
      52: ifeq          70
      55: aload_0
      56: getfield      #4                  // Field pathToServiceMapContainPathVariable:Ljava/util/Map;
      59: aload         6
      61: invokeinterface #12,  2           // InterfaceMethod java/util/Map.get:(Ljava/lang/Object;)Ljava/lang/Object;
      66: checkcast     #13                 // class org/apache/dubbo/rpc/protocol/rest/pair/InvokerAndRestMethodMetadataPair
      69: areturn
      70: new           #14                 // class org/apache/dubbo/rpc/protocol/rest/exception/PathNoFoundException
      73: dup
      74: new           #15                 // class java/lang/StringBuilder
      77: dup
      78: invokespecial #16                 // Method java/lang/StringBuilder."<init>":()V
      81: ldc           #17                 // String rest service Path no found, current path info:
      83: invokevirtual #18                 // Method java/lang/StringBuilder.append:(Ljava/lang/String;)Ljava/lang/StringBuilder;
      86: aload         6
      88: invokevirtual #19                 // Method java/lang/StringBuilder.append:(Ljava/lang/Object;)Ljava/lang/StringBuilder;
      91: invokevirtual #20                 // Method java/lang/StringBuilder.toString:()Ljava/lang/String;
      94: invokespecial #21                 // Method org/apache/dubbo/rpc/protocol/rest/exception/PathNoFoundException."<init>":(Ljava/lang/String;)V
      97: athrow

  public void removePath(org.apache.dubbo.metadata.rest.PathMatcher);
    Code:
       0: aload_0
       1: getfield      #4                  // Field pathToServiceMapContainPathVariable:Ljava/util/Map;
       4: aload_1
       5: invokeinterface #22,  2           // InterfaceMethod java/util/Map.remove:(Ljava/lang/Object;)Ljava/lang/Object;
      10: checkcast     #13                 // class org/apache/dubbo/rpc/protocol/rest/pair/InvokerAndRestMethodMetadataPair
      13: astore_2
      14: aload_0
      15: getfield      #5                  // Field pathToServiceMapNoPathVariable:Ljava/util/Map;
      18: aload_1
      19: invokeinterface #22,  2           // InterfaceMethod java/util/Map.remove:(Ljava/lang/Object;)Ljava/lang/Object;
      24: checkcast     #13                 // class org/apache/dubbo/rpc/protocol/rest/pair/InvokerAndRestMethodMetadataPair
      27: astore_3
      28: getstatic     #23                 // Field logger:Lorg/apache/dubbo/common/logger/ErrorTypeAwareLogger;
      31: new           #15                 // class java/lang/StringBuilder
      34: dup
      35: invokespecial #16                 // Method java/lang/StringBuilder."<init>":()V
      38: ldc           #24                 // String dubbo rest undeploy pathMatcher:
      40: invokevirtual #18                 // Method java/lang/StringBuilder.append:(Ljava/lang/String;)Ljava/lang/StringBuilder;
      43: aload_1
      44: invokevirtual #19                 // Method java/lang/StringBuilder.append:(Ljava/lang/Object;)Ljava/lang/StringBuilder;
      47: ldc           #25                 // String , and path variable method is :
      49: invokevirtual #18                 // Method java/lang/StringBuilder.append:(Ljava/lang/String;)Ljava/lang/StringBuilder;
      52: aload_2
      53: ifnonnull     60
      56: aconst_null
      57: goto          67
      60: aload_2
      61: invokevirtual #26                 // Method org/apache/dubbo/rpc/protocol/rest/pair/InvokerAndRestMethodMetadataPair.getRestMethodMetadata:()Lorg/apache/dubbo/metadata/rest/RestMethodMetadata;
      64: invokevirtual #27                 // Method org/apache/dubbo/metadata/rest/RestMethodMetadata.getReflectMethod:()Ljava/lang/reflect/Method;
      67: invokevirtual #19                 // Method java/lang/StringBuilder.append:(Ljava/lang/Object;)Ljava/lang/StringBuilder;
      70: ldc           #28                 // String , and no path variable  method is :
      72: invokevirtual #18                 // Method java/lang/StringBuilder.append:(Ljava/lang/String;)Ljava/lang/StringBuilder;
      75: aload_3
      76: ifnonnull     83
      79: aconst_null
      80: goto          90
      83: aload_3
      84: invokevirtual #26                 // Method org/apache/dubbo/rpc/protocol/rest/pair/InvokerAndRestMethodMetadataPair.getRestMethodMetadata:()Lorg/apache/dubbo/metadata/rest/RestMethodMetadata;
      87: invokevirtual #27                 // Method org/apache/dubbo/metadata/rest/RestMethodMetadata.getReflectMethod:()Ljava/lang/reflect/Method;
      90: invokevirtual #19                 // Method java/lang/StringBuilder.append:(Ljava/lang/Object;)Ljava/lang/StringBuilder;
      93: invokevirtual #20                 // Method java/lang/StringBuilder.toString:()Ljava/lang/String;
      96: invokeinterface #29,  2           // InterfaceMethod org/apache/dubbo/common/logger/ErrorTypeAwareLogger.info:(Ljava/lang/String;)V
     101: return

  public void addPathMatcherToPathMap(org.apache.dubbo.metadata.rest.PathMatcher, java.util.Map<org.apache.dubbo.metadata.rest.PathMatcher, org.apache.dubbo.rpc.protocol.rest.pair.InvokerAndRestMethodMetadataPair>, org.apache.dubbo.rpc.protocol.rest.pair.InvokerAndRestMethodMetadataPair);
    Code:
       0: aload_2
       1: aload_1
       2: invokeinterface #11,  2           // InterfaceMethod java/util/Map.containsKey:(Ljava/lang/Object;)Z
       7: ifeq          80
      10: aload_2
      11: aload_1
      12: invokeinterface #12,  2           // InterfaceMethod java/util/Map.get:(Ljava/lang/Object;)Ljava/lang/Object;
      17: checkcast     #13                 // class org/apache/dubbo/rpc/protocol/rest/pair/InvokerAndRestMethodMetadataPair
      20: astore        4
      22: new           #30                 // class org/apache/dubbo/rpc/protocol/rest/exception/DoublePathCheckException
      25: dup
      26: new           #15                 // class java/lang/StringBuilder
      29: dup
      30: invokespecial #16                 // Method java/lang/StringBuilder."<init>":()V
      33: ldc           #31                 // String dubbo rest double path check error, current path is:
      35: invokevirtual #18                 // Method java/lang/StringBuilder.append:(Ljava/lang/String;)Ljava/lang/StringBuilder;
      38: aload_1
      39: invokevirtual #19                 // Method java/lang/StringBuilder.append:(Ljava/lang/Object;)Ljava/lang/StringBuilder;
      42: ldc           #32                 // String  ,and service method is:
      44: invokevirtual #18                 // Method java/lang/StringBuilder.append:(Ljava/lang/String;)Ljava/lang/StringBuilder;
      47: aload_3
      48: invokevirtual #26                 // Method org/apache/dubbo/rpc/protocol/rest/pair/InvokerAndRestMethodMetadataPair.getRestMethodMetadata:()Lorg/apache/dubbo/metadata/rest/RestMethodMetadata;
      51: invokevirtual #27                 // Method org/apache/dubbo/metadata/rest/RestMethodMetadata.getReflectMethod:()Ljava/lang/reflect/Method;
      54: invokevirtual #19                 // Method java/lang/StringBuilder.append:(Ljava/lang/Object;)Ljava/lang/StringBuilder;
      57: ldc           #33                 // String before service  method is:
      59: invokevirtual #18                 // Method java/lang/StringBuilder.append:(Ljava/lang/String;)Ljava/lang/StringBuilder;
      62: aload         4
      64: invokevirtual #26                 // Method org/apache/dubbo/rpc/protocol/rest/pair/InvokerAndRestMethodMetadataPair.getRestMethodMetadata:()Lorg/apache/dubbo/metadata/rest/RestMethodMetadata;
      67: invokevirtual #27                 // Method org/apache/dubbo/metadata/rest/RestMethodMetadata.getReflectMethod:()Ljava/lang/reflect/Method;
      70: invokevirtual #19                 // Method java/lang/StringBuilder.append:(Ljava/lang/Object;)Ljava/lang/StringBuilder;
      73: invokevirtual #20                 // Method java/lang/StringBuilder.toString:()Ljava/lang/String;
      76: invokespecial #34                 // Method org/apache/dubbo/rpc/protocol/rest/exception/DoublePathCheckException."<init>":(Ljava/lang/String;)V
      79: athrow
      80: aload_2
      81: aload_1
      82: aload_3
      83: invokeinterface #35,  3           // InterfaceMethod java/util/Map.put:(Ljava/lang/Object;Ljava/lang/Object;)Ljava/lang/Object;
      88: pop
      89: getstatic     #23                 // Field logger:Lorg/apache/dubbo/common/logger/ErrorTypeAwareLogger;
      92: new           #15                 // class java/lang/StringBuilder
      95: dup
      96: invokespecial #16                 // Method java/lang/StringBuilder."<init>":()V
      99: ldc           #36                 // String dubbo rest deploy pathMatcher:
     101: invokevirtual #18                 // Method java/lang/StringBuilder.append:(Ljava/lang/String;)Ljava/lang/StringBuilder;
     104: aload_1
     105: invokevirtual #19                 // Method java/lang/StringBuilder.append:(Ljava/lang/Object;)Ljava/lang/StringBuilder;
     108: ldc           #37                 // String , and service method is :
     110: invokevirtual #18                 // Method java/lang/StringBuilder.append:(Ljava/lang/String;)Ljava/lang/StringBuilder;
     113: aload_3
     114: invokevirtual #26                 // Method org/apache/dubbo/rpc/protocol/rest/pair/InvokerAndRestMethodMetadataPair.getRestMethodMetadata:()Lorg/apache/dubbo/metadata/rest/RestMethodMetadata;
     117: invokevirtual #27                 // Method org/apache/dubbo/metadata/rest/RestMethodMetadata.getReflectMethod:()Ljava/lang/reflect/Method;
     120: invokevirtual #19                 // Method java/lang/StringBuilder.append:(Ljava/lang/Object;)Ljava/lang/StringBuilder;
     123: invokevirtual #20                 // Method java/lang/StringBuilder.toString:()Ljava/lang/String;
     126: invokeinterface #29,  2           // InterfaceMethod org/apache/dubbo/common/logger/ErrorTypeAwareLogger.info:(Ljava/lang/String;)V
     131: return

  private void lambda$addPathAndInvoker$0(org.apache.dubbo.rpc.Invoker, java.util.Map$Entry);
    Code:
       0: aload_2
       1: invokeinterface #38,  1           // InterfaceMethod java/util/Map$Entry.getKey:()Ljava/lang/Object;
       6: checkcast     #39                 // class org/apache/dubbo/metadata/rest/PathMatcher
       9: astore_3
      10: aload_3
      11: invokevirtual #40                 // Method org/apache/dubbo/metadata/rest/PathMatcher.hasPathVariable:()Z
      14: ifeq          42
      17: aload_0
      18: aload_3
      19: aload_0
      20: getfield      #4                  // Field pathToServiceMapContainPathVariable:Ljava/util/Map;
      23: aload_1
      24: aload_2
      25: invokeinterface #41,  1           // InterfaceMethod java/util/Map$Entry.getValue:()Ljava/lang/Object;
      30: checkcast     #42                 // class org/apache/dubbo/metadata/rest/RestMethodMetadata
      33: invokestatic  #43                 // Method org/apache/dubbo/rpc/protocol/rest/pair/InvokerAndRestMethodMetadataPair.pair:(Lorg/apache/dubbo/rpc/Invoker;Lorg/apache/dubbo/metadata/rest/RestMethodMetadata;)Lorg/apache/dubbo/rpc/protocol/rest/pair/InvokerAndRestMethodMetadataPair;
      36: invokevirtual #44                 // Method addPathMatcherToPathMap:(Lorg/apache/dubbo/metadata/rest/PathMatcher;Ljava/util/Map;Lorg/apache/dubbo/rpc/protocol/rest/pair/InvokerAndRestMethodMetadataPair;)V
      39: goto          64
      42: aload_0
      43: aload_3
      44: aload_0
      45: getfield      #5                  // Field pathToServiceMapNoPathVariable:Ljava/util/Map;
      48: aload_1
      49: aload_2
      50: invokeinterface #41,  1           // InterfaceMethod java/util/Map$Entry.getValue:()Ljava/lang/Object;
      55: checkcast     #42                 // class org/apache/dubbo/metadata/rest/RestMethodMetadata
      58: invokestatic  #43                 // Method org/apache/dubbo/rpc/protocol/rest/pair/InvokerAndRestMethodMetadataPair.pair:(Lorg/apache/dubbo/rpc/Invoker;Lorg/apache/dubbo/metadata/rest/RestMethodMetadata;)Lorg/apache/dubbo/rpc/protocol/rest/pair/InvokerAndRestMethodMetadataPair;
      61: invokevirtual #44                 // Method addPathMatcherToPathMap:(Lorg/apache/dubbo/metadata/rest/PathMatcher;Ljava/util/Map;Lorg/apache/dubbo/rpc/protocol/rest/pair/InvokerAndRestMethodMetadataPair;)V
      64: return

  static {};
    Code:
       0: ldc           #45                 // class org/apache/dubbo/rpc/protocol/rest/PathAndInvokerMapper
       2: invokestatic  #46                 // Method org/apache/dubbo/common/logger/LoggerFactory.getErrorTypeAwareLogger:(Ljava/lang/Class;)Lorg/apache/dubbo/common/logger/ErrorTypeAwareLogger;
       5: putstatic     #23                 // Field logger:Lorg/apache/dubbo/common/logger/ErrorTypeAwareLogger;
       8: return
}
