Compiled from "ReferenceCountedClient.java"
public class org.apache.dubbo.rpc.protocol.rest.ReferenceCountedClient<T extends org.apache.dubbo.remoting.http.RestClient> extends org.apache.dubbo.common.reference.ReferenceCountedResource {
  private static final org.apache.dubbo.common.logger.ErrorTypeAwareLogger logger;

  private java.util.concurrent.ConcurrentMap<java.lang.String, org.apache.dubbo.rpc.protocol.rest.ReferenceCountedClient<? extends org.apache.dubbo.remoting.http.RestClient>> clients;

  private org.apache.dubbo.common.URL url;

  private org.apache.dubbo.remoting.http.factory.RestClientFactory clientFactory;

  private T client;

  public org.apache.dubbo.rpc.protocol.rest.ReferenceCountedClient(T, java.util.concurrent.ConcurrentMap<java.lang.String, org.apache.dubbo.rpc.protocol.rest.ReferenceCountedClient<? extends org.apache.dubbo.remoting.http.RestClient>>, org.apache.dubbo.remoting.http.factory.RestClientFactory, org.apache.dubbo.common.URL);
    Code:
       0: aload_0
       1: invokespecial #2                  // Method org/apache/dubbo/common/reference/ReferenceCountedResource."<init>":()V
       4: aload_0
       5: aload_1
       6: putfield      #3                  // Field client:Lorg/apache/dubbo/remoting/http/RestClient;
       9: aload_0
      10: aload_2
      11: putfield      #4                  // Field clients:Ljava/util/concurrent/ConcurrentMap;
      14: aload_0
      15: aload_3
      16: putfield      #5                  // Field clientFactory:Lorg/apache/dubbo/remoting/http/factory/RestClientFactory;
      19: aload_0
      20: aload         4
      22: putfield      #6                  // Field url:Lorg/apache/dubbo/common/URL;
      25: return

  public T getClient();
    Code:
       0: aload_0
       1: dup
       2: astore_1
       3: monitorenter
       4: aload_0
       5: getfield      #4                  // Field clients:Ljava/util/concurrent/ConcurrentMap;
       8: aload_0
       9: getfield      #6                  // Field url:Lorg/apache/dubbo/common/URL;
      12: invokevirtual #7                  // Method org/apache/dubbo/common/URL.getAddress:()Ljava/lang/String;
      15: invokeinterface #8,  2            // InterfaceMethod java/util/concurrent/ConcurrentMap.get:(Ljava/lang/Object;)Ljava/lang/Object;
      20: checkcast     #9                  // class org/apache/dubbo/rpc/protocol/rest/ReferenceCountedClient
      23: astore_2
      24: aload_2
      25: invokevirtual #10                 // Method isDestroyed:()Z
      28: ifeq          138
      31: aload_0
      32: dup
      33: astore_3
      34: monitorenter
      35: aload_0
      36: getfield      #4                  // Field clients:Ljava/util/concurrent/ConcurrentMap;
      39: aload_0
      40: getfield      #6                  // Field url:Lorg/apache/dubbo/common/URL;
      43: invokevirtual #7                  // Method org/apache/dubbo/common/URL.getAddress:()Ljava/lang/String;
      46: invokeinterface #8,  2            // InterfaceMethod java/util/concurrent/ConcurrentMap.get:(Ljava/lang/Object;)Ljava/lang/Object;
      51: checkcast     #9                  // class org/apache/dubbo/rpc/protocol/rest/ReferenceCountedClient
      54: astore_2
      55: aload_2
      56: invokevirtual #10                 // Method isDestroyed:()Z
      59: ifeq          122
      62: aload_0
      63: getfield      #5                  // Field clientFactory:Lorg/apache/dubbo/remoting/http/factory/RestClientFactory;
      66: aload_0
      67: getfield      #6                  // Field url:Lorg/apache/dubbo/common/URL;
      70: invokeinterface #11,  2           // InterfaceMethod org/apache/dubbo/remoting/http/factory/RestClientFactory.createRestClient:(Lorg/apache/dubbo/common/URL;)Lorg/apache/dubbo/remoting/http/RestClient;
      75: astore        4
      77: aload_0
      78: getfield      #4                  // Field clients:Ljava/util/concurrent/ConcurrentMap;
      81: aload_0
      82: getfield      #6                  // Field url:Lorg/apache/dubbo/common/URL;
      85: invokevirtual #7                  // Method org/apache/dubbo/common/URL.getAddress:()Ljava/lang/String;
      88: new           #9                  // class org/apache/dubbo/rpc/protocol/rest/ReferenceCountedClient
      91: dup
      92: aload         4
      94: aload_0
      95: getfield      #4                  // Field clients:Ljava/util/concurrent/ConcurrentMap;
      98: aload_0
      99: getfield      #5                  // Field clientFactory:Lorg/apache/dubbo/remoting/http/factory/RestClientFactory;
     102: aload_0
     103: getfield      #6                  // Field url:Lorg/apache/dubbo/common/URL;
     106: invokespecial #12                 // Method "<init>":(Lorg/apache/dubbo/remoting/http/RestClient;Ljava/util/concurrent/ConcurrentMap;Lorg/apache/dubbo/remoting/http/factory/RestClientFactory;Lorg/apache/dubbo/common/URL;)V
     109: invokeinterface #13,  3           // InterfaceMethod java/util/concurrent/ConcurrentMap.put:(Ljava/lang/Object;Ljava/lang/Object;)Ljava/lang/Object;
     114: pop
     115: aload         4
     117: aload_3
     118: monitorexit
     119: aload_1
     120: monitorexit
     121: areturn
     122: aload_2
     123: getfield      #3                  // Field client:Lorg/apache/dubbo/remoting/http/RestClient;
     126: aload_3
     127: monitorexit
     128: aload_1
     129: monitorexit
     130: areturn
     131: astore        5
     133: aload_3
     134: monitorexit
     135: aload         5
     137: athrow
     138: aload_0
     139: getfield      #3                  // Field client:Lorg/apache/dubbo/remoting/http/RestClient;
     142: aload_1
     143: monitorexit
     144: areturn
     145: astore        6
     147: aload_1
     148: monitorexit
     149: aload         6
     151: athrow
    Exception table:
       from    to  target type
          35   119   131   any
         122   128   131   any
         131   135   131   any
           4   121   145   any
         122   130   145   any
         131   144   145   any
         145   149   145   any

  public boolean isDestroyed();
    Code:
       0: aload_0
       1: getfield      #3                  // Field client:Lorg/apache/dubbo/remoting/http/RestClient;
       4: invokeinterface #14,  1           // InterfaceMethod org/apache/dubbo/remoting/http/RestClient.isClosed:()Z
       9: ireturn

  protected void destroy();
    Code:
       0: aload_0
       1: getfield      #3                  // Field client:Lorg/apache/dubbo/remoting/http/RestClient;
       4: invokeinterface #15,  1           // InterfaceMethod org/apache/dubbo/remoting/http/RestClient.close:()V
       9: goto          30
      12: astore_1
      13: getstatic     #17                 // Field logger:Lorg/apache/dubbo/common/logger/ErrorTypeAwareLogger;
      16: ldc           #18                 // String 4-7
      18: ldc           #19                 // String
      20: ldc           #19                 // String
      22: ldc           #20                 // String Close resteasy client error
      24: aload_1
      25: invokeinterface #21,  6           // InterfaceMethod org/apache/dubbo/common/logger/ErrorTypeAwareLogger.error:(Ljava/lang/String;Ljava/lang/String;Ljava/lang/String;Ljava/lang/String;Ljava/lang/Throwable;)V
      30: return
    Exception table:
       from    to  target type
           0     9    12   Class java/lang/Exception

  static {};
    Code:
       0: ldc           #9                  // class org/apache/dubbo/rpc/protocol/rest/ReferenceCountedClient
       2: invokestatic  #22                 // Method org/apache/dubbo/common/logger/LoggerFactory.getErrorTypeAwareLogger:(Ljava/lang/Class;)Lorg/apache/dubbo/common/logger/ErrorTypeAwareLogger;
       5: putstatic     #17                 // Field logger:Lorg/apache/dubbo/common/logger/ErrorTypeAwareLogger;
       8: return
}
