Compiled from "RestProtocol.java"
public class org.apache.dubbo.rpc.protocol.rest.RestProtocol extends org.apache.dubbo.rpc.protocol.AbstractProtocol {
  private static final int DEFAULT_PORT;

  private static final java.lang.String DEFAULT_SERVER;

  private final org.apache.dubbo.rpc.protocol.rest.RestServerFactory serverFactory;

  private final java.util.concurrent.ConcurrentMap<java.lang.String, org.apache.dubbo.rpc.protocol.rest.ReferenceCountedClient<? extends org.apache.dubbo.remoting.http.RestClient>> clients;

  private final org.apache.dubbo.remoting.http.factory.RestClientFactory clientFactory;

  private final java.util.Set<org.apache.dubbo.rpc.protocol.rest.annotation.consumer.HttpConnectionPreBuildIntercept> httpConnectionPreBuildIntercepts;

  public org.apache.dubbo.rpc.protocol.rest.RestProtocol(org.apache.dubbo.rpc.model.FrameworkModel);
    Code:
       0: aload_0
       1: invokespecial #8                  // Method org/apache/dubbo/rpc/protocol/AbstractProtocol."<init>":()V
       4: aload_0
       5: new           #9                  // class org/apache/dubbo/rpc/protocol/rest/RestServerFactory
       8: dup
       9: invokespecial #10                 // Method org/apache/dubbo/rpc/protocol/rest/RestServerFactory."<init>":()V
      12: putfield      #11                 // Field serverFactory:Lorg/apache/dubbo/rpc/protocol/rest/RestServerFactory;
      15: aload_0
      16: new           #12                 // class java/util/concurrent/ConcurrentHashMap
      19: dup
      20: invokespecial #13                 // Method java/util/concurrent/ConcurrentHashMap."<init>":()V
      23: putfield      #14                 // Field clients:Ljava/util/concurrent/ConcurrentMap;
      26: aload_0
      27: aload_1
      28: ldc           #15                 // class org/apache/dubbo/remoting/http/factory/RestClientFactory
      30: invokevirtual #16                 // Method org/apache/dubbo/rpc/model/FrameworkModel.getExtensionLoader:(Ljava/lang/Class;)Lorg/apache/dubbo/common/extension/ExtensionLoader;
      33: invokevirtual #17                 // Method org/apache/dubbo/common/extension/ExtensionLoader.getAdaptiveExtension:()Ljava/lang/Object;
      36: checkcast     #15                 // class org/apache/dubbo/remoting/http/factory/RestClientFactory
      39: putfield      #18                 // Field clientFactory:Lorg/apache/dubbo/remoting/http/factory/RestClientFactory;
      42: aload_0
      43: aload_1
      44: ldc           #19                 // class org/apache/dubbo/rpc/protocol/rest/annotation/consumer/HttpConnectionPreBuildIntercept
      46: invokevirtual #16                 // Method org/apache/dubbo/rpc/model/FrameworkModel.getExtensionLoader:(Ljava/lang/Class;)Lorg/apache/dubbo/common/extension/ExtensionLoader;
      49: invokevirtual #20                 // Method org/apache/dubbo/common/extension/ExtensionLoader.getSupportedExtensionInstances:()Ljava/util/Set;
      52: putfield      #21                 // Field httpConnectionPreBuildIntercepts:Ljava/util/Set;
      55: return

  public int getDefaultPort();
    Code:
       0: bipush        80
       2: ireturn

  public <T> org.apache.dubbo.rpc.Exporter<T> export(org.apache.dubbo.rpc.Invoker<T>) throws org.apache.dubbo.rpc.RpcException;
    Code:
       0: aload_1
       1: invokeinterface #23,  1           // InterfaceMethod org/apache/dubbo/rpc/Invoker.getUrl:()Lorg/apache/dubbo/common/URL;
       6: astore_2
       7: aload_2
       8: invokestatic  #24                 // Method serviceKey:(Lorg/apache/dubbo/common/URL;)Ljava/lang/String;
      11: astore_3
      12: aload_0
      13: getfield      #6                  // Field exporterMap:Ljava/util/Map;
      16: aload_3
      17: invokeinterface #25,  2           // InterfaceMethod java/util/Map.get:(Ljava/lang/Object;)Ljava/lang/Object;
      22: checkcast     #26                 // class org/apache/dubbo/rpc/Exporter
      25: astore        4
      27: aload         4
      29: ifnull        59
      32: aload         4
      34: invokeinterface #27,  1           // InterfaceMethod org/apache/dubbo/rpc/Exporter.getInvoker:()Lorg/apache/dubbo/rpc/Invoker;
      39: invokeinterface #23,  1           // InterfaceMethod org/apache/dubbo/rpc/Invoker.getUrl:()Lorg/apache/dubbo/common/URL;
      44: aload_1
      45: invokeinterface #23,  1           // InterfaceMethod org/apache/dubbo/rpc/Invoker.getUrl:()Lorg/apache/dubbo/common/URL;
      50: invokestatic  #28                 // Method java/util/Objects.equals:(Ljava/lang/Object;Ljava/lang/Object;)Z
      53: ifeq          59
      56: aload         4
      58: areturn
      59: aload_2
      60: invokevirtual #29                 // Method org/apache/dubbo/common/URL.getServiceModel:()Lorg/apache/dubbo/rpc/model/ServiceModel;
      63: invokevirtual #30                 // Method org/apache/dubbo/rpc/model/ServiceModel.getProxyObject:()Ljava/lang/Object;
      66: invokevirtual #31                 // Method java/lang/Object.getClass:()Ljava/lang/Class;
      69: aload_2
      70: aload_0
      71: aload_2
      72: invokespecial #32                 // Method getContextPath:(Lorg/apache/dubbo/common/URL;)Ljava/lang/String;
      75: invokestatic  #33                 // Method org/apache/dubbo/rpc/protocol/rest/annotation/metadata/MetadataResolver.resolveProviderServiceMetadata:(Ljava/lang/Class;Lorg/apache/dubbo/common/URL;Ljava/lang/String;)Lorg/apache/dubbo/metadata/rest/ServiceRestMetadata;
      78: astore        5
      80: aload_0
      81: getfield      #34                 // Field serverMap:Ljava/util/concurrent/ConcurrentMap;
      84: aload_0
      85: aload_2
      86: invokevirtual #35                 // Method getAddr:(Lorg/apache/dubbo/common/URL;)Ljava/lang/String;
      89: aload_0
      90: aload_2
      91: invokedynamic #36,  0             // InvokeDynamic #0:apply:(Lorg/apache/dubbo/rpc/protocol/rest/RestProtocol;Lorg/apache/dubbo/common/URL;)Ljava/util/function/Function;
      96: invokestatic  #37                 // Method org/apache/dubbo/common/utils/ConcurrentHashMapUtils.computeIfAbsent:(Ljava/util/concurrent/ConcurrentMap;Ljava/lang/Object;Ljava/util/function/Function;)Ljava/lang/Object;
      99: checkcast     #38                 // class org/apache/dubbo/rpc/protocol/rest/RestProtocolServer
     102: astore        6
     104: aload         6
     106: aload         5
     108: aload_1
     109: invokeinterface #39,  3           // InterfaceMethod org/apache/dubbo/rpc/protocol/rest/RestProtocolServer.deploy:(Lorg/apache/dubbo/metadata/rest/ServiceRestMetadata;Lorg/apache/dubbo/rpc/Invoker;)V
     114: new           #40                 // class org/apache/dubbo/rpc/protocol/rest/RestProtocol$1
     117: dup
     118: aload_0
     119: aload_1
     120: aload_2
     121: aload_3
     122: aload         6
     124: aload         5
     126: invokespecial #41                 // Method org/apache/dubbo/rpc/protocol/rest/RestProtocol$1."<init>":(Lorg/apache/dubbo/rpc/protocol/rest/RestProtocol;Lorg/apache/dubbo/rpc/Invoker;Lorg/apache/dubbo/common/URL;Ljava/lang/String;Lorg/apache/dubbo/rpc/protocol/rest/RestProtocolServer;Lorg/apache/dubbo/metadata/rest/ServiceRestMetadata;)V
     129: astore        4
     131: aload_0
     132: getfield      #6                  // Field exporterMap:Ljava/util/Map;
     135: aload_3
     136: aload         4
     138: invokeinterface #42,  3           // InterfaceMethod java/util/Map.put:(Ljava/lang/Object;Ljava/lang/Object;)Ljava/lang/Object;
     143: pop
     144: aload         4
     146: areturn

  protected <T> org.apache.dubbo.rpc.Invoker<T> protocolBindingRefer(java.lang.Class<T>, org.apache.dubbo.common.URL) throws org.apache.dubbo.rpc.RpcException;
    Code:
       0: aload_0
       1: getfield      #14                 // Field clients:Ljava/util/concurrent/ConcurrentMap;
       4: aload_2
       5: invokevirtual #43                 // Method org/apache/dubbo/common/URL.getAddress:()Ljava/lang/String;
       8: invokeinterface #44,  2           // InterfaceMethod java/util/concurrent/ConcurrentMap.get:(Ljava/lang/Object;)Ljava/lang/Object;
      13: checkcast     #45                 // class org/apache/dubbo/rpc/protocol/rest/ReferenceCountedClient
      16: astore_3
      17: aload_3
      18: ifnull        28
      21: aload_3
      22: invokevirtual #46                 // Method org/apache/dubbo/rpc/protocol/rest/ReferenceCountedClient.isDestroyed:()Z
      25: ifeq          100
      28: aload_0
      29: getfield      #14                 // Field clients:Ljava/util/concurrent/ConcurrentMap;
      32: dup
      33: astore        4
      35: monitorenter
      36: aload_0
      37: getfield      #14                 // Field clients:Ljava/util/concurrent/ConcurrentMap;
      40: aload_2
      41: invokevirtual #43                 // Method org/apache/dubbo/common/URL.getAddress:()Ljava/lang/String;
      44: invokeinterface #44,  2           // InterfaceMethod java/util/concurrent/ConcurrentMap.get:(Ljava/lang/Object;)Ljava/lang/Object;
      49: checkcast     #45                 // class org/apache/dubbo/rpc/protocol/rest/ReferenceCountedClient
      52: astore_3
      53: aload_3
      54: ifnull        64
      57: aload_3
      58: invokevirtual #46                 // Method org/apache/dubbo/rpc/protocol/rest/ReferenceCountedClient.isDestroyed:()Z
      61: ifeq          86
      64: aload_0
      65: getfield      #14                 // Field clients:Ljava/util/concurrent/ConcurrentMap;
      68: aload_2
      69: invokevirtual #43                 // Method org/apache/dubbo/common/URL.getAddress:()Ljava/lang/String;
      72: aload_0
      73: aload_2
      74: invokedynamic #47,  0             // InvokeDynamic #1:apply:(Lorg/apache/dubbo/rpc/protocol/rest/RestProtocol;Lorg/apache/dubbo/common/URL;)Ljava/util/function/Function;
      79: invokestatic  #37                 // Method org/apache/dubbo/common/utils/ConcurrentHashMapUtils.computeIfAbsent:(Ljava/util/concurrent/ConcurrentMap;Ljava/lang/Object;Ljava/util/function/Function;)Ljava/lang/Object;
      82: checkcast     #45                 // class org/apache/dubbo/rpc/protocol/rest/ReferenceCountedClient
      85: astore_3
      86: aload         4
      88: monitorexit
      89: goto          100
      92: astore        5
      94: aload         4
      96: monitorexit
      97: aload         5
      99: athrow
     100: aload_3
     101: invokevirtual #48                 // Method org/apache/dubbo/rpc/protocol/rest/ReferenceCountedClient.retain:()Lorg/apache/dubbo/common/reference/ReferenceCountedResource;
     104: pop
     105: aload_0
     106: aload_2
     107: invokespecial #32                 // Method getContextPath:(Lorg/apache/dubbo/common/URL;)Ljava/lang/String;
     110: astore        4
     112: aload_1
     113: aload_2
     114: aload         4
     116: invokestatic  #49                 // Method org/apache/dubbo/rpc/protocol/rest/annotation/metadata/MetadataResolver.resolveConsumerServiceMetadata:(Ljava/lang/Class;Lorg/apache/dubbo/common/URL;Ljava/lang/String;)Lorg/apache/dubbo/metadata/rest/ServiceRestMetadata;
     119: astore        5
     121: new           #50                 // class org/apache/dubbo/rpc/protocol/rest/RestInvoker
     124: dup
     125: aload_1
     126: aload_2
     127: aload_3
     128: aload_0
     129: getfield      #21                 // Field httpConnectionPreBuildIntercepts:Ljava/util/Set;
     132: aload         5
     134: invokespecial #51                 // Method org/apache/dubbo/rpc/protocol/rest/RestInvoker."<init>":(Ljava/lang/Class;Lorg/apache/dubbo/common/URL;Lorg/apache/dubbo/rpc/protocol/rest/ReferenceCountedClient;Ljava/util/Set;Lorg/apache/dubbo/metadata/rest/ServiceRestMetadata;)V
     137: astore        6
     139: aload_0
     140: getfield      #52                 // Field invokers:Ljava/util/Set;
     143: aload         6
     145: invokeinterface #53,  2           // InterfaceMethod java/util/Set.add:(Ljava/lang/Object;)Z
     150: pop
     151: aload         6
     153: areturn
    Exception table:
       from    to  target type
          36    89    92   any
          92    97    92   any

  private org.apache.dubbo.rpc.protocol.rest.ReferenceCountedClient<? extends org.apache.dubbo.remoting.http.RestClient> createReferenceCountedClient(org.apache.dubbo.common.URL) throws org.apache.dubbo.rpc.RpcException;
    Code:
       0: aload_0
       1: getfield      #18                 // Field clientFactory:Lorg/apache/dubbo/remoting/http/factory/RestClientFactory;
       4: aload_1
       5: invokeinterface #54,  2           // InterfaceMethod org/apache/dubbo/remoting/http/factory/RestClientFactory.createRestClient:(Lorg/apache/dubbo/common/URL;)Lorg/apache/dubbo/remoting/http/RestClient;
      10: astore_2
      11: new           #45                 // class org/apache/dubbo/rpc/protocol/rest/ReferenceCountedClient
      14: dup
      15: aload_2
      16: aload_0
      17: getfield      #14                 // Field clients:Ljava/util/concurrent/ConcurrentMap;
      20: aload_0
      21: getfield      #18                 // Field clientFactory:Lorg/apache/dubbo/remoting/http/factory/RestClientFactory;
      24: aload_1
      25: invokespecial #55                 // Method org/apache/dubbo/rpc/protocol/rest/ReferenceCountedClient."<init>":(Lorg/apache/dubbo/remoting/http/RestClient;Ljava/util/concurrent/ConcurrentMap;Lorg/apache/dubbo/remoting/http/factory/RestClientFactory;Lorg/apache/dubbo/common/URL;)V
      28: areturn

  public void destroy();
    Code:
       0: aload_0
       1: getfield      #56                 // Field logger:Lorg/apache/dubbo/common/logger/ErrorTypeAwareLogger;
       4: invokeinterface #57,  1           // InterfaceMethod org/apache/dubbo/common/logger/ErrorTypeAwareLogger.isInfoEnabled:()Z
       9: ifeq          51
      12: aload_0
      13: getfield      #56                 // Field logger:Lorg/apache/dubbo/common/logger/ErrorTypeAwareLogger;
      16: new           #58                 // class java/lang/StringBuilder
      19: dup
      20: invokespecial #59                 // Method java/lang/StringBuilder."<init>":()V
      23: ldc           #60                 // String Destroying protocol [
      25: invokevirtual #61                 // Method java/lang/StringBuilder.append:(Ljava/lang/String;)Ljava/lang/StringBuilder;
      28: aload_0
      29: invokevirtual #31                 // Method java/lang/Object.getClass:()Ljava/lang/Class;
      32: invokevirtual #62                 // Method java/lang/Class.getSimpleName:()Ljava/lang/String;
      35: invokevirtual #61                 // Method java/lang/StringBuilder.append:(Ljava/lang/String;)Ljava/lang/StringBuilder;
      38: ldc           #63                 // String ] ...
      40: invokevirtual #61                 // Method java/lang/StringBuilder.append:(Ljava/lang/String;)Ljava/lang/StringBuilder;
      43: invokevirtual #64                 // Method java/lang/StringBuilder.toString:()Ljava/lang/String;
      46: invokeinterface #65,  2           // InterfaceMethod org/apache/dubbo/common/logger/ErrorTypeAwareLogger.info:(Ljava/lang/String;)V
      51: aload_0
      52: invokespecial #66                 // Method org/apache/dubbo/rpc/protocol/AbstractProtocol.destroy:()V
      55: aload_0
      56: getfield      #34                 // Field serverMap:Ljava/util/concurrent/ConcurrentMap;
      59: invokeinterface #67,  1           // InterfaceMethod java/util/concurrent/ConcurrentMap.entrySet:()Ljava/util/Set;
      64: invokeinterface #68,  1           // InterfaceMethod java/util/Set.iterator:()Ljava/util/Iterator;
      69: astore_1
      70: aload_1
      71: invokeinterface #69,  1           // InterfaceMethod java/util/Iterator.hasNext:()Z
      76: ifeq          176
      79: aload_1
      80: invokeinterface #70,  1           // InterfaceMethod java/util/Iterator.next:()Ljava/lang/Object;
      85: checkcast     #71                 // class java/util/Map$Entry
      88: astore_2
      89: aload_0
      90: getfield      #56                 // Field logger:Lorg/apache/dubbo/common/logger/ErrorTypeAwareLogger;
      93: invokeinterface #57,  1           // InterfaceMethod org/apache/dubbo/common/logger/ErrorTypeAwareLogger.isInfoEnabled:()Z
      98: ifeq          137
     101: aload_0
     102: getfield      #56                 // Field logger:Lorg/apache/dubbo/common/logger/ErrorTypeAwareLogger;
     105: new           #58                 // class java/lang/StringBuilder
     108: dup
     109: invokespecial #59                 // Method java/lang/StringBuilder."<init>":()V
     112: ldc           #72                 // String Closing the rest server at
     114: invokevirtual #61                 // Method java/lang/StringBuilder.append:(Ljava/lang/String;)Ljava/lang/StringBuilder;
     117: aload_2
     118: invokeinterface #73,  1           // InterfaceMethod java/util/Map$Entry.getKey:()Ljava/lang/Object;
     123: checkcast     #74                 // class java/lang/String
     126: invokevirtual #61                 // Method java/lang/StringBuilder.append:(Ljava/lang/String;)Ljava/lang/StringBuilder;
     129: invokevirtual #64                 // Method java/lang/StringBuilder.toString:()Ljava/lang/String;
     132: invokeinterface #65,  2           // InterfaceMethod org/apache/dubbo/common/logger/ErrorTypeAwareLogger.info:(Ljava/lang/String;)V
     137: aload_2
     138: invokeinterface #75,  1           // InterfaceMethod java/util/Map$Entry.getValue:()Ljava/lang/Object;
     143: checkcast     #76                 // class org/apache/dubbo/rpc/ProtocolServer
     146: invokeinterface #77,  1           // InterfaceMethod org/apache/dubbo/rpc/ProtocolServer.close:()V
     151: goto          173
     154: astore_3
     155: aload_0
     156: getfield      #56                 // Field logger:Lorg/apache/dubbo/common/logger/ErrorTypeAwareLogger;
     159: ldc           #79                 // String 4-8
     161: ldc           #80                 // String
     163: ldc           #80                 // String
     165: ldc           #81                 // String Error closing rest server
     167: aload_3
     168: invokeinterface #82,  6           // InterfaceMethod org/apache/dubbo/common/logger/ErrorTypeAwareLogger.warn:(Ljava/lang/String;Ljava/lang/String;Ljava/lang/String;Ljava/lang/String;Ljava/lang/Throwable;)V
     173: goto          70
     176: aload_0
     177: getfield      #34                 // Field serverMap:Ljava/util/concurrent/ConcurrentMap;
     180: invokeinterface #83,  1           // InterfaceMethod java/util/concurrent/ConcurrentMap.clear:()V
     185: aload_0
     186: getfield      #56                 // Field logger:Lorg/apache/dubbo/common/logger/ErrorTypeAwareLogger;
     189: invokeinterface #57,  1           // InterfaceMethod org/apache/dubbo/common/logger/ErrorTypeAwareLogger.isInfoEnabled:()Z
     194: ifeq          208
     197: aload_0
     198: getfield      #56                 // Field logger:Lorg/apache/dubbo/common/logger/ErrorTypeAwareLogger;
     201: ldc           #84                 // String Closing rest clients
     203: invokeinterface #65,  2           // InterfaceMethod org/apache/dubbo/common/logger/ErrorTypeAwareLogger.info:(Ljava/lang/String;)V
     208: aload_0
     209: getfield      #14                 // Field clients:Ljava/util/concurrent/ConcurrentMap;
     212: invokeinterface #85,  1           // InterfaceMethod java/util/concurrent/ConcurrentMap.values:()Ljava/util/Collection;
     217: invokeinterface #86,  1           // InterfaceMethod java/util/Collection.iterator:()Ljava/util/Iterator;
     222: astore_1
     223: aload_1
     224: invokeinterface #69,  1           // InterfaceMethod java/util/Iterator.hasNext:()Z
     229: ifeq          271
     232: aload_1
     233: invokeinterface #70,  1           // InterfaceMethod java/util/Iterator.next:()Ljava/lang/Object;
     238: checkcast     #45                 // class org/apache/dubbo/rpc/protocol/rest/ReferenceCountedClient
     241: astore_2
     242: aload_2
     243: invokevirtual #87                 // Method org/apache/dubbo/rpc/protocol/rest/ReferenceCountedClient.destroy:()V
     246: goto          268
     249: astore_3
     250: aload_0
     251: getfield      #56                 // Field logger:Lorg/apache/dubbo/common/logger/ErrorTypeAwareLogger;
     254: ldc           #88                 // String 4-7
     256: ldc           #80                 // String
     258: ldc           #80                 // String
     260: ldc           #89                 // String Error closing rest client
     262: aload_3
     263: invokeinterface #82,  6           // InterfaceMethod org/apache/dubbo/common/logger/ErrorTypeAwareLogger.warn:(Ljava/lang/String;Ljava/lang/String;Ljava/lang/String;Ljava/lang/String;Ljava/lang/Throwable;)V
     268: goto          223
     271: aload_0
     272: getfield      #14                 // Field clients:Ljava/util/concurrent/ConcurrentMap;
     275: invokeinterface #83,  1           // InterfaceMethod java/util/concurrent/ConcurrentMap.clear:()V
     280: return
    Exception table:
       from    to  target type
          89   151   154   Class java/lang/Throwable
         242   246   249   Class java/lang/Throwable

  private java.lang.String getContextPath(org.apache.dubbo.common.URL);
    Code:
       0: aload_1
       1: invokevirtual #90                 // Method org/apache/dubbo/common/URL.getPath:()Ljava/lang/String;
       4: astore_2
       5: aload_2
       6: ifnull        79
       9: aload_2
      10: aload_1
      11: ldc           #91                 // String interface
      13: invokevirtual #92                 // Method org/apache/dubbo/common/URL.getParameter:(Ljava/lang/String;)Ljava/lang/String;
      16: invokevirtual #93                 // Method java/lang/String.equalsIgnoreCase:(Ljava/lang/String;)Z
      19: ifeq          25
      22: ldc           #80                 // String
      24: areturn
      25: aload_2
      26: aload_1
      27: ldc           #91                 // String interface
      29: invokevirtual #92                 // Method org/apache/dubbo/common/URL.getParameter:(Ljava/lang/String;)Ljava/lang/String;
      32: invokevirtual #94                 // Method java/lang/String.endsWith:(Ljava/lang/String;)Z
      35: ifeq          54
      38: aload_2
      39: iconst_0
      40: aload_2
      41: aload_1
      42: ldc           #91                 // String interface
      44: invokevirtual #92                 // Method org/apache/dubbo/common/URL.getParameter:(Ljava/lang/String;)Ljava/lang/String;
      47: invokevirtual #95                 // Method java/lang/String.lastIndexOf:(Ljava/lang/String;)I
      50: invokevirtual #96                 // Method java/lang/String.substring:(II)Ljava/lang/String;
      53: astore_2
      54: aload_2
      55: ldc           #97                 // String /
      57: invokevirtual #94                 // Method java/lang/String.endsWith:(Ljava/lang/String;)Z
      60: ifeq          77
      63: aload_2
      64: iconst_0
      65: aload_2
      66: invokevirtual #98                 // Method java/lang/String.length:()I
      69: iconst_1
      70: isub
      71: invokevirtual #96                 // Method java/lang/String.substring:(II)Ljava/lang/String;
      74: goto          78
      77: aload_2
      78: areturn
      79: ldc           #80                 // String
      81: areturn

  private void destroyInternal(org.apache.dubbo.common.URL);
    Code:
       0: aload_0
       1: getfield      #14                 // Field clients:Ljava/util/concurrent/ConcurrentMap;
       4: aload_1
       5: invokevirtual #43                 // Method org/apache/dubbo/common/URL.getAddress:()Ljava/lang/String;
       8: invokeinterface #44,  2           // InterfaceMethod java/util/concurrent/ConcurrentMap.get:(Ljava/lang/Object;)Ljava/lang/Object;
      13: checkcast     #45                 // class org/apache/dubbo/rpc/protocol/rest/ReferenceCountedClient
      16: astore_2
      17: aload_2
      18: ifnull        42
      21: aload_2
      22: invokevirtual #99                 // Method org/apache/dubbo/rpc/protocol/rest/ReferenceCountedClient.release:()Z
      25: ifeq          42
      28: aload_0
      29: getfield      #14                 // Field clients:Ljava/util/concurrent/ConcurrentMap;
      32: aload_1
      33: invokevirtual #43                 // Method org/apache/dubbo/common/URL.getAddress:()Ljava/lang/String;
      36: invokeinterface #100,  2          // InterfaceMethod java/util/concurrent/ConcurrentMap.remove:(Ljava/lang/Object;)Ljava/lang/Object;
      41: pop
      42: goto          89
      45: astore_2
      46: aload_0
      47: getfield      #56                 // Field logger:Lorg/apache/dubbo/common/logger/ErrorTypeAwareLogger;
      50: ldc           #88                 // String 4-7
      52: ldc           #80                 // String
      54: ldc           #80                 // String
      56: new           #58                 // class java/lang/StringBuilder
      59: dup
      60: invokespecial #59                 // Method java/lang/StringBuilder."<init>":()V
      63: ldc           #102                // String Failed to close unused resources in rest protocol. interfaceName [
      65: invokevirtual #61                 // Method java/lang/StringBuilder.append:(Ljava/lang/String;)Ljava/lang/StringBuilder;
      68: aload_1
      69: invokevirtual #103                // Method org/apache/dubbo/common/URL.getServiceInterface:()Ljava/lang/String;
      72: invokevirtual #61                 // Method java/lang/StringBuilder.append:(Ljava/lang/String;)Ljava/lang/StringBuilder;
      75: ldc           #104                // String ]
      77: invokevirtual #61                 // Method java/lang/StringBuilder.append:(Ljava/lang/String;)Ljava/lang/StringBuilder;
      80: invokevirtual #64                 // Method java/lang/StringBuilder.toString:()Ljava/lang/String;
      83: aload_2
      84: invokeinterface #82,  6           // InterfaceMethod org/apache/dubbo/common/logger/ErrorTypeAwareLogger.warn:(Ljava/lang/String;Ljava/lang/String;Ljava/lang/String;Ljava/lang/String;Ljava/lang/Throwable;)V
      89: return
    Exception table:
       from    to  target type
           0    42    45   Class java/lang/Exception

  private org.apache.dubbo.rpc.protocol.rest.ReferenceCountedClient lambda$protocolBindingRefer$1(org.apache.dubbo.common.URL, java.lang.String);
    Code:
       0: aload_0
       1: aload_1
       2: invokespecial #105                // Method createReferenceCountedClient:(Lorg/apache/dubbo/common/URL;)Lorg/apache/dubbo/rpc/protocol/rest/ReferenceCountedClient;
       5: areturn

  private org.apache.dubbo.rpc.ProtocolServer lambda$export$0(org.apache.dubbo.common.URL, java.lang.String);
    Code:
       0: aload_0
       1: getfield      #11                 // Field serverFactory:Lorg/apache/dubbo/rpc/protocol/rest/RestServerFactory;
       4: aload_1
       5: ldc           #106                // String server
       7: ldc           #107                // String netty_http
       9: invokevirtual #108                // Method org/apache/dubbo/common/URL.getParameter:(Ljava/lang/String;Ljava/lang/String;)Ljava/lang/String;
      12: invokevirtual #109                // Method org/apache/dubbo/rpc/protocol/rest/RestServerFactory.createServer:(Ljava/lang/String;)Lorg/apache/dubbo/rpc/protocol/rest/RestProtocolServer;
      15: astore_3
      16: aload_3
      17: aload_1
      18: invokevirtual #43                 // Method org/apache/dubbo/common/URL.getAddress:()Ljava/lang/String;
      21: invokeinterface #110,  2          // InterfaceMethod org/apache/dubbo/rpc/protocol/rest/RestProtocolServer.setAddress:(Ljava/lang/String;)V
      26: aload_3
      27: aload_1
      28: invokeinterface #111,  2          // InterfaceMethod org/apache/dubbo/rpc/protocol/rest/RestProtocolServer.start:(Lorg/apache/dubbo/common/URL;)V
      33: aload_3
      34: areturn

  static void access$000(org.apache.dubbo.rpc.protocol.rest.RestProtocol, org.apache.dubbo.common.URL);
    Code:
       0: aload_0
       1: aload_1
       2: invokespecial #7                  // Method destroyInternal:(Lorg/apache/dubbo/common/URL;)V
       5: return

  static java.util.Map access$100(org.apache.dubbo.rpc.protocol.rest.RestProtocol);
    Code:
       0: aload_0
       1: getfield      #6                  // Field exporterMap:Ljava/util/Map;
       4: areturn
}
