Compiled from "RestProtocol.java"
class org.apache.dubbo.rpc.protocol.rest.RestProtocol$1 extends org.apache.dubbo.rpc.protocol.AbstractExporter<T> {
  final org.apache.dubbo.common.URL val$url;

  final java.lang.String val$uri;

  final org.apache.dubbo.rpc.protocol.rest.RestProtocolServer val$server;

  final org.apache.dubbo.metadata.rest.ServiceRestMetadata val$serviceRestMetadata;

  final org.apache.dubbo.rpc.protocol.rest.RestProtocol this$0;

  org.apache.dubbo.rpc.protocol.rest.RestProtocol$1(org.apache.dubbo.rpc.protocol.rest.RestProtocol, org.apache.dubbo.rpc.Invoker, org.apache.dubbo.common.URL, java.lang.String, org.apache.dubbo.rpc.protocol.rest.RestProtocolServer, org.apache.dubbo.metadata.rest.ServiceRestMetadata);
    Code:
       0: aload_0
       1: aload_1
       2: putfield      #1                  // Field this$0:Lorg/apache/dubbo/rpc/protocol/rest/RestProtocol;
       5: aload_0
       6: aload_3
       7: putfield      #2                  // Field val$url:Lorg/apache/dubbo/common/URL;
      10: aload_0
      11: aload         4
      13: putfield      #3                  // Field val$uri:Ljava/lang/String;
      16: aload_0
      17: aload         5
      19: putfield      #4                  // Field val$server:Lorg/apache/dubbo/rpc/protocol/rest/RestProtocolServer;
      22: aload_0
      23: aload         6
      25: putfield      #5                  // Field val$serviceRestMetadata:Lorg/apache/dubbo/metadata/rest/ServiceRestMetadata;
      28: aload_0
      29: aload_2
      30: invokespecial #6                  // Method org/apache/dubbo/rpc/protocol/AbstractExporter."<init>":(Lorg/apache/dubbo/rpc/Invoker;)V
      33: return

  public void afterUnExport();
    Code:
       0: aload_0
       1: getfield      #1                  // Field this$0:Lorg/apache/dubbo/rpc/protocol/rest/RestProtocol;
       4: aload_0
       5: getfield      #2                  // Field val$url:Lorg/apache/dubbo/common/URL;
       8: invokestatic  #7                  // Method org/apache/dubbo/rpc/protocol/rest/RestProtocol.access$000:(Lorg/apache/dubbo/rpc/protocol/rest/RestProtocol;Lorg/apache/dubbo/common/URL;)V
      11: aload_0
      12: getfield      #1                  // Field this$0:Lorg/apache/dubbo/rpc/protocol/rest/RestProtocol;
      15: invokestatic  #8                  // Method org/apache/dubbo/rpc/protocol/rest/RestProtocol.access$100:(Lorg/apache/dubbo/rpc/protocol/rest/RestProtocol;)Ljava/util/Map;
      18: aload_0
      19: getfield      #3                  // Field val$uri:Ljava/lang/String;
      22: invokeinterface #9,  2            // InterfaceMethod java/util/Map.remove:(Ljava/lang/Object;)Ljava/lang/Object;
      27: pop
      28: aload_0
      29: getfield      #4                  // Field val$server:Lorg/apache/dubbo/rpc/protocol/rest/RestProtocolServer;
      32: aload_0
      33: getfield      #5                  // Field val$serviceRestMetadata:Lorg/apache/dubbo/metadata/rest/ServiceRestMetadata;
      36: invokeinterface #10,  2           // InterfaceMethod org/apache/dubbo/rpc/protocol/rest/RestProtocolServer.undeploy:(Lorg/apache/dubbo/metadata/rest/ServiceRestMetadata;)V
      41: return
}
