Compiled from "RestRPCInvocationUtil.java"
public class org.apache.dubbo.rpc.protocol.rest.RestRPCInvocationUtil {
  private static final org.apache.dubbo.common.logger.ErrorTypeAwareLogger logger;

  public org.apache.dubbo.rpc.protocol.rest.RestRPCInvocationUtil();
    Code:
       0: aload_0
       1: invokespecial #1                  // Method java/lang/Object."<init>":()V
       4: return

  public static void parseMethodArgs(org.apache.dubbo.rpc.RpcInvocation, org.apache.dubbo.rpc.protocol.rest.request.RequestFacade, java.lang.Object, java.lang.Object, org.apache.dubbo.metadata.rest.RestMethodMetadata);
    Code:
       0: aload_1
       1: aload_2
       2: aload_3
       3: aload         4
       5: invokestatic  #2                  // Method createParseContext:(Lorg/apache/dubbo/rpc/protocol/rest/request/RequestFacade;Ljava/lang/Object;Ljava/lang/Object;Lorg/apache/dubbo/metadata/rest/RestMethodMetadata;)Lorg/apache/dubbo/rpc/protocol/rest/annotation/param/parse/provider/ProviderParseContext;
       8: astore        5
      10: aload         5
      12: invokestatic  #3                  // Method org/apache/dubbo/rpc/protocol/rest/annotation/ParamParserManager.providerParamParse:(Lorg/apache/dubbo/rpc/protocol/rest/annotation/param/parse/provider/ProviderParseContext;)[Ljava/lang/Object;
      15: astore        6
      17: aload         5
      19: invokevirtual #4                  // Method org/apache/dubbo/rpc/protocol/rest/annotation/param/parse/provider/ProviderParseContext.getArgInfos:()Ljava/util/List;
      22: astore        7
      24: aload         7
      26: invokeinterface #5,  1            // InterfaceMethod java/util/List.iterator:()Ljava/util/Iterator;
      31: astore        8
      33: aload         8
      35: invokeinterface #6,  1            // InterfaceMethod java/util/Iterator.hasNext:()Z
      40: ifeq          137
      43: aload         8
      45: invokeinterface #7,  1            // InterfaceMethod java/util/Iterator.next:()Ljava/lang/Object;
      50: checkcast     #8                  // class org/apache/dubbo/metadata/rest/ArgInfo
      53: astore        9
      55: aload         9
      57: invokevirtual #9                  // Method org/apache/dubbo/metadata/rest/ArgInfo.getParamType:()Ljava/lang/Class;
      60: invokevirtual #10                 // Method java/lang/Class.isPrimitive:()Z
      63: ifeq          134
      66: aload         6
      68: aload         9
      70: invokevirtual #11                 // Method org/apache/dubbo/metadata/rest/ArgInfo.getIndex:()I
      73: aaload
      74: ifnonnull     134
      77: new           #12                 // class org/apache/dubbo/rpc/protocol/rest/exception/ParamParseException
      80: dup
      81: new           #13                 // class java/lang/StringBuilder
      84: dup
      85: invokespecial #14                 // Method java/lang/StringBuilder."<init>":()V
      88: ldc           #15                 // String \n dubbo provider primitive arg not exist in request, method is:
      90: invokevirtual #16                 // Method java/lang/StringBuilder.append:(Ljava/lang/String;)Ljava/lang/StringBuilder;
      93: aload         4
      95: invokevirtual #17                 // Method org/apache/dubbo/metadata/rest/RestMethodMetadata.getReflectMethod:()Ljava/lang/reflect/Method;
      98: invokevirtual #18                 // Method java/lang/StringBuilder.append:(Ljava/lang/Object;)Ljava/lang/StringBuilder;
     101: ldc           #19                 // String \n type is:
     103: invokevirtual #16                 // Method java/lang/StringBuilder.append:(Ljava/lang/String;)Ljava/lang/StringBuilder;
     106: aload         9
     108: invokevirtual #9                  // Method org/apache/dubbo/metadata/rest/ArgInfo.getParamType:()Ljava/lang/Class;
     111: invokevirtual #18                 // Method java/lang/StringBuilder.append:(Ljava/lang/Object;)Ljava/lang/StringBuilder;
     114: ldc           #20                 // String  \n and arg index is:
     116: invokevirtual #16                 // Method java/lang/StringBuilder.append:(Ljava/lang/String;)Ljava/lang/StringBuilder;
     119: aload         9
     121: invokevirtual #11                 // Method org/apache/dubbo/metadata/rest/ArgInfo.getIndex:()I
     124: invokevirtual #21                 // Method java/lang/StringBuilder.append:(I)Ljava/lang/StringBuilder;
     127: invokevirtual #22                 // Method java/lang/StringBuilder.toString:()Ljava/lang/String;
     130: invokespecial #23                 // Method org/apache/dubbo/rpc/protocol/rest/exception/ParamParseException."<init>":(Ljava/lang/String;)V
     133: athrow
     134: goto          33
     137: aload_0
     138: aload         6
     140: invokevirtual #24                 // Method org/apache/dubbo/rpc/RpcInvocation.setArguments:([Ljava/lang/Object;)V
     143: goto          182
     146: astore        5
     148: getstatic     #26                 // Field logger:Lorg/apache/dubbo/common/logger/ErrorTypeAwareLogger;
     151: ldc           #27                 // String
     153: aload         5
     155: invokevirtual #28                 // Method java/lang/Exception.getMessage:()Ljava/lang/String;
     158: ldc           #27                 // String
     160: ldc           #29                 // String dubbo rest provider method args parse error:
     162: aload         5
     164: invokeinterface #30,  6           // InterfaceMethod org/apache/dubbo/common/logger/ErrorTypeAwareLogger.error:(Ljava/lang/String;Ljava/lang/String;Ljava/lang/String;Ljava/lang/String;Ljava/lang/Throwable;)V
     169: new           #12                 // class org/apache/dubbo/rpc/protocol/rest/exception/ParamParseException
     172: dup
     173: aload         5
     175: invokevirtual #28                 // Method java/lang/Exception.getMessage:()Ljava/lang/String;
     178: invokespecial #23                 // Method org/apache/dubbo/rpc/protocol/rest/exception/ParamParseException."<init>":(Ljava/lang/String;)V
     181: athrow
     182: return
    Exception table:
       from    to  target type
           0   143   146   Class java/lang/Exception

  private static org.apache.dubbo.rpc.protocol.rest.annotation.param.parse.provider.ProviderParseContext createParseContext(org.apache.dubbo.rpc.protocol.rest.request.RequestFacade, java.lang.Object, java.lang.Object, org.apache.dubbo.metadata.rest.RestMethodMetadata);
    Code:
       0: new           #31                 // class org/apache/dubbo/rpc/protocol/rest/annotation/param/parse/provider/ProviderParseContext
       3: dup
       4: aload_0
       5: invokespecial #32                 // Method org/apache/dubbo/rpc/protocol/rest/annotation/param/parse/provider/ProviderParseContext."<init>":(Lorg/apache/dubbo/rpc/protocol/rest/request/RequestFacade;)V
       8: astore        4
      10: aload         4
      12: aload_2
      13: invokevirtual #33                 // Method org/apache/dubbo/rpc/protocol/rest/annotation/param/parse/provider/ProviderParseContext.setResponse:(Ljava/lang/Object;)V
      16: aload         4
      18: aload_1
      19: invokevirtual #34                 // Method org/apache/dubbo/rpc/protocol/rest/annotation/param/parse/provider/ProviderParseContext.setRequest:(Ljava/lang/Object;)V
      22: aload_3
      23: invokevirtual #35                 // Method org/apache/dubbo/metadata/rest/RestMethodMetadata.getArgInfos:()Ljava/util/List;
      26: invokeinterface #36,  1           // InterfaceMethod java/util/List.size:()I
      31: anewarray     #37                 // class java/lang/Object
      34: astore        5
      36: aload         4
      38: aload         5
      40: invokestatic  #38                 // Method java/util/Arrays.asList:([Ljava/lang/Object;)Ljava/util/List;
      43: invokevirtual #39                 // Method org/apache/dubbo/rpc/protocol/rest/annotation/param/parse/provider/ProviderParseContext.setArgs:(Ljava/util/List;)V
      46: aload         4
      48: aload_3
      49: invokevirtual #35                 // Method org/apache/dubbo/metadata/rest/RestMethodMetadata.getArgInfos:()Ljava/util/List;
      52: invokevirtual #40                 // Method org/apache/dubbo/rpc/protocol/rest/annotation/param/parse/provider/ProviderParseContext.setArgInfos:(Ljava/util/List;)V
      55: aload         4
      57: areturn

  public static org.apache.dubbo.rpc.RpcInvocation createBaseRpcInvocation(org.apache.dubbo.rpc.protocol.rest.request.RequestFacade, org.apache.dubbo.metadata.rest.RestMethodMetadata);
    Code:
       0: new           #41                 // class org/apache/dubbo/rpc/RpcInvocation
       3: dup
       4: invokespecial #42                 // Method org/apache/dubbo/rpc/RpcInvocation."<init>":()V
       7: astore_2
       8: aload_2
       9: aload_1
      10: invokevirtual #17                 // Method org/apache/dubbo/metadata/rest/RestMethodMetadata.getReflectMethod:()Ljava/lang/reflect/Method;
      13: invokevirtual #43                 // Method java/lang/reflect/Method.getParameterTypes:()[Ljava/lang/Class;
      16: invokevirtual #44                 // Method org/apache/dubbo/rpc/RpcInvocation.setParameterTypes:([Ljava/lang/Class;)V
      19: aload_2
      20: aload_1
      21: invokevirtual #17                 // Method org/apache/dubbo/metadata/rest/RestMethodMetadata.getReflectMethod:()Ljava/lang/reflect/Method;
      24: invokevirtual #45                 // Method java/lang/reflect/Method.getReturnType:()Ljava/lang/Class;
      27: invokevirtual #46                 // Method org/apache/dubbo/rpc/RpcInvocation.setReturnType:(Ljava/lang/Class;)V
      30: aload_2
      31: aload_1
      32: invokevirtual #47                 // Method org/apache/dubbo/metadata/rest/RestMethodMetadata.getMethod:()Lorg/apache/dubbo/metadata/definition/model/MethodDefinition;
      35: invokevirtual #48                 // Method org/apache/dubbo/metadata/definition/model/MethodDefinition.getName:()Ljava/lang/String;
      38: invokevirtual #49                 // Method org/apache/dubbo/rpc/RpcInvocation.setMethodName:(Ljava/lang/String;)V
      41: aload_2
      42: aload_0
      43: invokestatic  #50                 // Method org/apache/dubbo/rpc/protocol/rest/util/HttpHeaderUtil.parseRequest:(Lorg/apache/dubbo/rpc/RpcInvocation;Lorg/apache/dubbo/rpc/protocol/rest/request/RequestFacade;)V
      46: aload_0
      47: getstatic     #51                 // Field org/apache/dubbo/rpc/protocol/rest/RestHeaderEnum.PATH:Lorg/apache/dubbo/rpc/protocol/rest/RestHeaderEnum;
      50: invokevirtual #52                 // Method org/apache/dubbo/rpc/protocol/rest/RestHeaderEnum.getHeader:()Ljava/lang/String;
      53: invokevirtual #53                 // Method org/apache/dubbo/rpc/protocol/rest/request/RequestFacade.getHeader:(Ljava/lang/String;)Ljava/lang/String;
      56: aload_0
      57: getstatic     #54                 // Field org/apache/dubbo/rpc/protocol/rest/RestHeaderEnum.GROUP:Lorg/apache/dubbo/rpc/protocol/rest/RestHeaderEnum;
      60: invokevirtual #52                 // Method org/apache/dubbo/rpc/protocol/rest/RestHeaderEnum.getHeader:()Ljava/lang/String;
      63: invokevirtual #53                 // Method org/apache/dubbo/rpc/protocol/rest/request/RequestFacade.getHeader:(Ljava/lang/String;)Ljava/lang/String;
      66: aload_0
      67: getstatic     #55                 // Field org/apache/dubbo/rpc/protocol/rest/RestHeaderEnum.VERSION:Lorg/apache/dubbo/rpc/protocol/rest/RestHeaderEnum;
      70: invokevirtual #52                 // Method org/apache/dubbo/rpc/protocol/rest/RestHeaderEnum.getHeader:()Ljava/lang/String;
      73: invokevirtual #53                 // Method org/apache/dubbo/rpc/protocol/rest/request/RequestFacade.getHeader:(Ljava/lang/String;)Ljava/lang/String;
      76: invokestatic  #56                 // Method org/apache/dubbo/common/BaseServiceMetadata.buildServiceKey:(Ljava/lang/String;Ljava/lang/String;Ljava/lang/String;)Ljava/lang/String;
      79: astore_3
      80: aload_2
      81: aload_3
      82: invokevirtual #57                 // Method org/apache/dubbo/rpc/RpcInvocation.setTargetServiceUniqueName:(Ljava/lang/String;)V
      85: aload_2
      86: areturn

  public static org.apache.dubbo.rpc.protocol.rest.pair.InvokerAndRestMethodMetadataPair getRestMethodMetadata(org.apache.dubbo.rpc.protocol.rest.request.RequestFacade, org.apache.dubbo.rpc.protocol.rest.PathAndInvokerMapper);
    Code:
       0: aload_0
       1: invokevirtual #58                 // Method org/apache/dubbo/rpc/protocol/rest/request/RequestFacade.getPath:()Ljava/lang/String;
       4: astore_2
       5: aload_0
       6: getstatic     #55                 // Field org/apache/dubbo/rpc/protocol/rest/RestHeaderEnum.VERSION:Lorg/apache/dubbo/rpc/protocol/rest/RestHeaderEnum;
       9: invokevirtual #52                 // Method org/apache/dubbo/rpc/protocol/rest/RestHeaderEnum.getHeader:()Ljava/lang/String;
      12: invokevirtual #53                 // Method org/apache/dubbo/rpc/protocol/rest/request/RequestFacade.getHeader:(Ljava/lang/String;)Ljava/lang/String;
      15: astore_3
      16: aload_0
      17: getstatic     #54                 // Field org/apache/dubbo/rpc/protocol/rest/RestHeaderEnum.GROUP:Lorg/apache/dubbo/rpc/protocol/rest/RestHeaderEnum;
      20: invokevirtual #52                 // Method org/apache/dubbo/rpc/protocol/rest/RestHeaderEnum.getHeader:()Ljava/lang/String;
      23: invokevirtual #53                 // Method org/apache/dubbo/rpc/protocol/rest/request/RequestFacade.getHeader:(Ljava/lang/String;)Ljava/lang/String;
      26: astore        4
      28: aload_0
      29: invokevirtual #59                 // Method org/apache/dubbo/rpc/protocol/rest/request/RequestFacade.getMethod:()Ljava/lang/String;
      32: astore        5
      34: aload_1
      35: aload_2
      36: aload_3
      37: aload         4
      39: aconst_null
      40: aload         5
      42: invokevirtual #60                 // Method org/apache/dubbo/rpc/protocol/rest/PathAndInvokerMapper.getRestMethodMetadata:(Ljava/lang/String;Ljava/lang/String;Ljava/lang/String;Ljava/lang/Integer;Ljava/lang/String;)Lorg/apache/dubbo/rpc/protocol/rest/pair/InvokerAndRestMethodMetadataPair;
      45: areturn

  static {};
    Code:
       0: ldc           #61                 // class org/apache/dubbo/rpc/protocol/rest/RestRPCInvocationUtil
       2: invokestatic  #62                 // Method org/apache/dubbo/common/logger/LoggerFactory.getErrorTypeAwareLogger:(Ljava/lang/Class;)Lorg/apache/dubbo/common/logger/ErrorTypeAwareLogger;
       5: putstatic     #26                 // Field logger:Lorg/apache/dubbo/common/logger/ErrorTypeAwareLogger;
       8: return
}
