Compiled from "RestHeaderEnum.java"
public final class org.apache.dubbo.rpc.protocol.rest.RestHeaderEnum extends java.lang.Enum<org.apache.dubbo.rpc.protocol.rest.RestHeaderEnum> {
  public static final org.apache.dubbo.rpc.protocol.rest.RestHeaderEnum CONTENT_TYPE;

  public static final org.apache.dubbo.rpc.protocol.rest.RestHeaderEnum ACCEPT;

  public static final org.apache.dubbo.rpc.protocol.rest.RestHeaderEnum GROUP;

  public static final org.apache.dubbo.rpc.protocol.rest.RestHeaderEnum VERSION;

  public static final org.apache.dubbo.rpc.protocol.rest.RestHeaderEnum PATH;

  public static final org.apache.dubbo.rpc.protocol.rest.RestHeaderEnum KEEP_ALIVE_HEADER;

  public static final org.apache.dubbo.rpc.protocol.rest.RestHeaderEnum CONNECTION;

  public static final org.apache.dubbo.rpc.protocol.rest.RestHeaderEnum REST_HEADER_PREFIX;

  public static final org.apache.dubbo.rpc.protocol.rest.RestHeaderEnum TOKEN_KEY;

  private final java.lang.String header;

  private static final org.apache.dubbo.rpc.protocol.rest.RestHeaderEnum[] $VALUES;

  public static org.apache.dubbo.rpc.protocol.rest.RestHeaderEnum[] values();
    Code:
       0: getstatic     #1                  // Field $VALUES:[Lorg/apache/dubbo/rpc/protocol/rest/RestHeaderEnum;
       3: invokevirtual #2                  // Method "[Lorg/apache/dubbo/rpc/protocol/rest/RestHeaderEnum;".clone:()Ljava/lang/Object;
       6: checkcast     #3                  // class "[Lorg/apache/dubbo/rpc/protocol/rest/RestHeaderEnum;"
       9: areturn

  public static org.apache.dubbo.rpc.protocol.rest.RestHeaderEnum valueOf(java.lang.String);
    Code:
       0: ldc           #4                  // class org/apache/dubbo/rpc/protocol/rest/RestHeaderEnum
       2: aload_0
       3: invokestatic  #5                  // Method java/lang/Enum.valueOf:(Ljava/lang/Class;Ljava/lang/String;)Ljava/lang/Enum;
       6: checkcast     #4                  // class org/apache/dubbo/rpc/protocol/rest/RestHeaderEnum
       9: areturn

  private org.apache.dubbo.rpc.protocol.rest.RestHeaderEnum(java.lang.String);
    Code:
       0: aload_0
       1: aload_1
       2: iload_2
       3: invokespecial #6                  // Method java/lang/Enum."<init>":(Ljava/lang/String;I)V
       6: aload_0
       7: aload_3
       8: putfield      #7                  // Field header:Ljava/lang/String;
      11: return

  public java.lang.String getHeader();
    Code:
       0: aload_0
       1: getfield      #7                  // Field header:Ljava/lang/String;
       4: areturn

  static {};
    Code:
       0: new           #4                  // class org/apache/dubbo/rpc/protocol/rest/RestHeaderEnum
       3: dup
       4: ldc           #8                  // String CONTENT_TYPE
       6: iconst_0
       7: ldc           #10                 // String Content-Type
       9: invokespecial #11                 // Method "<init>":(Ljava/lang/String;ILjava/lang/String;)V
      12: putstatic     #12                 // Field CONTENT_TYPE:Lorg/apache/dubbo/rpc/protocol/rest/RestHeaderEnum;
      15: new           #4                  // class org/apache/dubbo/rpc/protocol/rest/RestHeaderEnum
      18: dup
      19: ldc           #13                 // String ACCEPT
      21: iconst_1
      22: ldc           #14                 // String Accept
      24: invokespecial #11                 // Method "<init>":(Ljava/lang/String;ILjava/lang/String;)V
      27: putstatic     #15                 // Field ACCEPT:Lorg/apache/dubbo/rpc/protocol/rest/RestHeaderEnum;
      30: new           #4                  // class org/apache/dubbo/rpc/protocol/rest/RestHeaderEnum
      33: dup
      34: ldc           #16                 // String GROUP
      36: iconst_2
      37: ldc           #17                 // String rest-service-group
      39: invokespecial #11                 // Method "<init>":(Ljava/lang/String;ILjava/lang/String;)V
      42: putstatic     #18                 // Field GROUP:Lorg/apache/dubbo/rpc/protocol/rest/RestHeaderEnum;
      45: new           #4                  // class org/apache/dubbo/rpc/protocol/rest/RestHeaderEnum
      48: dup
      49: ldc           #19                 // String VERSION
      51: iconst_3
      52: ldc           #20                 // String rest-service-version
      54: invokespecial #11                 // Method "<init>":(Ljava/lang/String;ILjava/lang/String;)V
      57: putstatic     #21                 // Field VERSION:Lorg/apache/dubbo/rpc/protocol/rest/RestHeaderEnum;
      60: new           #4                  // class org/apache/dubbo/rpc/protocol/rest/RestHeaderEnum
      63: dup
      64: ldc           #22                 // String PATH
      66: iconst_4
      67: ldc           #23                 // String rest-service-path
      69: invokespecial #11                 // Method "<init>":(Ljava/lang/String;ILjava/lang/String;)V
      72: putstatic     #24                 // Field PATH:Lorg/apache/dubbo/rpc/protocol/rest/RestHeaderEnum;
      75: new           #4                  // class org/apache/dubbo/rpc/protocol/rest/RestHeaderEnum
      78: dup
      79: ldc           #25                 // String KEEP_ALIVE_HEADER
      81: iconst_5
      82: ldc           #26                 // String Keep-Alive
      84: invokespecial #11                 // Method "<init>":(Ljava/lang/String;ILjava/lang/String;)V
      87: putstatic     #27                 // Field KEEP_ALIVE_HEADER:Lorg/apache/dubbo/rpc/protocol/rest/RestHeaderEnum;
      90: new           #4                  // class org/apache/dubbo/rpc/protocol/rest/RestHeaderEnum
      93: dup
      94: ldc           #28                 // String CONNECTION
      96: bipush        6
      98: ldc           #29                 // String Connection
     100: invokespecial #11                 // Method "<init>":(Ljava/lang/String;ILjava/lang/String;)V
     103: putstatic     #30                 // Field CONNECTION:Lorg/apache/dubbo/rpc/protocol/rest/RestHeaderEnum;
     106: new           #4                  // class org/apache/dubbo/rpc/protocol/rest/RestHeaderEnum
     109: dup
     110: ldc           #31                 // String REST_HEADER_PREFIX
     112: bipush        7
     114: ldc           #32                 // String rest-service-
     116: invokespecial #11                 // Method "<init>":(Ljava/lang/String;ILjava/lang/String;)V
     119: putstatic     #33                 // Field REST_HEADER_PREFIX:Lorg/apache/dubbo/rpc/protocol/rest/RestHeaderEnum;
     122: new           #4                  // class org/apache/dubbo/rpc/protocol/rest/RestHeaderEnum
     125: dup
     126: ldc           #34                 // String TOKEN_KEY
     128: bipush        8
     130: ldc           #35                 // String rest-service-token
     132: invokespecial #11                 // Method "<init>":(Ljava/lang/String;ILjava/lang/String;)V
     135: putstatic     #36                 // Field TOKEN_KEY:Lorg/apache/dubbo/rpc/protocol/rest/RestHeaderEnum;
     138: bipush        9
     140: anewarray     #4                  // class org/apache/dubbo/rpc/protocol/rest/RestHeaderEnum
     143: dup
     144: iconst_0
     145: getstatic     #12                 // Field CONTENT_TYPE:Lorg/apache/dubbo/rpc/protocol/rest/RestHeaderEnum;
     148: aastore
     149: dup
     150: iconst_1
     151: getstatic     #15                 // Field ACCEPT:Lorg/apache/dubbo/rpc/protocol/rest/RestHeaderEnum;
     154: aastore
     155: dup
     156: iconst_2
     157: getstatic     #18                 // Field GROUP:Lorg/apache/dubbo/rpc/protocol/rest/RestHeaderEnum;
     160: aastore
     161: dup
     162: iconst_3
     163: getstatic     #21                 // Field VERSION:Lorg/apache/dubbo/rpc/protocol/rest/RestHeaderEnum;
     166: aastore
     167: dup
     168: iconst_4
     169: getstatic     #24                 // Field PATH:Lorg/apache/dubbo/rpc/protocol/rest/RestHeaderEnum;
     172: aastore
     173: dup
     174: iconst_5
     175: getstatic     #27                 // Field KEEP_ALIVE_HEADER:Lorg/apache/dubbo/rpc/protocol/rest/RestHeaderEnum;
     178: aastore
     179: dup
     180: bipush        6
     182: getstatic     #30                 // Field CONNECTION:Lorg/apache/dubbo/rpc/protocol/rest/RestHeaderEnum;
     185: aastore
     186: dup
     187: bipush        7
     189: getstatic     #33                 // Field REST_HEADER_PREFIX:Lorg/apache/dubbo/rpc/protocol/rest/RestHeaderEnum;
     192: aastore
     193: dup
     194: bipush        8
     196: getstatic     #36                 // Field TOKEN_KEY:Lorg/apache/dubbo/rpc/protocol/rest/RestHeaderEnum;
     199: aastore
     200: putstatic     #1                  // Field $VALUES:[Lorg/apache/dubbo/rpc/protocol/rest/RestHeaderEnum;
     203: return
}
