Compiled from "RestConstraintViolation.java"
public class org.apache.dubbo.rpc.protocol.rest.RestConstraintViolation implements java.io.Serializable {
  private static final long serialVersionUID;

  private java.lang.String path;

  private java.lang.String message;

  private java.lang.String value;

  public org.apache.dubbo.rpc.protocol.rest.RestConstraintViolation(java.lang.String, java.lang.String, java.lang.String);
    Code:
       0: aload_0
       1: invokespecial #1                  // Method java/lang/Object."<init>":()V
       4: aload_0
       5: aload_1
       6: putfield      #2                  // Field path:Ljava/lang/String;
       9: aload_0
      10: aload_2
      11: putfield      #3                  // Field message:Ljava/lang/String;
      14: aload_0
      15: aload_3
      16: putfield      #4                  // Field value:Ljava/lang/String;
      19: return

  public org.apache.dubbo.rpc.protocol.rest.RestConstraintViolation();
    Code:
       0: aload_0
       1: invokespecial #1                  // Method java/lang/Object."<init>":()V
       4: return

  public java.lang.String getPath();
    Code:
       0: aload_0
       1: getfield      #2                  // Field path:Ljava/lang/String;
       4: areturn

  public void setPath(java.lang.String);
    Code:
       0: aload_0
       1: aload_1
       2: putfield      #2                  // Field path:Ljava/lang/String;
       5: return

  public java.lang.String getMessage();
    Code:
       0: aload_0
       1: getfield      #3                  // Field message:Ljava/lang/String;
       4: areturn

  public void setMessage(java.lang.String);
    Code:
       0: aload_0
       1: aload_1
       2: putfield      #3                  // Field message:Ljava/lang/String;
       5: return

  public java.lang.String getValue();
    Code:
       0: aload_0
       1: getfield      #4                  // Field value:Ljava/lang/String;
       4: areturn

  public void setValue(java.lang.String);
    Code:
       0: aload_0
       1: aload_1
       2: putfield      #4                  // Field value:Ljava/lang/String;
       5: return
}
