Compiled from "RpcExceptionMapper.java"
public class org.apache.dubbo.rpc.protocol.rest.RpcExceptionMapper implements org.apache.dubbo.rpc.protocol.rest.exception.mapper.ExceptionHandler<org.apache.dubbo.rpc.RpcException> {
  public org.apache.dubbo.rpc.protocol.rest.RpcExceptionMapper();
    Code:
       0: aload_0
       1: invokespecial #1                  // Method java/lang/Object."<init>":()V
       4: return

  public java.lang.Object result(org.apache.dubbo.rpc.RpcException);
    Code:
       0: aload_0
       1: invokespecial #2                  // Method violationDependency:()Z
       4: ifeq          19
       7: aload_1
       8: invokestatic  #3                  // Method org/apache/dubbo/rpc/protocol/rest/util/ConstraintViolationExceptionConvert.needConvert:(Lorg/apache/dubbo/rpc/RpcException;)Z
      11: ifeq          19
      14: aload_1
      15: invokestatic  #4                  // Method org/apache/dubbo/rpc/protocol/rest/util/ConstraintViolationExceptionConvert.handleConstraintViolationException:(Lorg/apache/dubbo/rpc/RpcException;)Ljava/lang/Object;
      18: areturn
      19: new           #5                  // class java/lang/StringBuilder
      22: dup
      23: invokespecial #6                  // Method java/lang/StringBuilder."<init>":()V
      26: ldc           #7                  // String Internal server error:
      28: invokevirtual #8                  // Method java/lang/StringBuilder.append:(Ljava/lang/String;)Ljava/lang/StringBuilder;
      31: aload_1
      32: invokevirtual #9                  // Method org/apache/dubbo/rpc/RpcException.getMessage:()Ljava/lang/String;
      35: invokevirtual #8                  // Method java/lang/StringBuilder.append:(Ljava/lang/String;)Ljava/lang/StringBuilder;
      38: invokevirtual #10                 // Method java/lang/StringBuilder.toString:()Ljava/lang/String;
      41: areturn

  private boolean violationDependency();
    Code:
       0: ldc           #11                 // String javax.validation.ConstraintViolationException
       2: ldc           #12                 // class org/apache/dubbo/rpc/protocol/rest/RpcExceptionMapper
       4: invokevirtual #13                 // Method java/lang/Class.getClassLoader:()Ljava/lang/ClassLoader;
       7: invokestatic  #14                 // Method org/apache/dubbo/common/utils/ClassUtils.isPresent:(Ljava/lang/String;Ljava/lang/ClassLoader;)Z
      10: ireturn

  public java.lang.Object result(java.lang.Throwable);
    Code:
       0: aload_0
       1: aload_1
       2: checkcast     #15                 // class org/apache/dubbo/rpc/RpcException
       5: invokevirtual #16                 // Method result:(Lorg/apache/dubbo/rpc/RpcException;)Ljava/lang/Object;
       8: areturn
}
