Compiled from "ViolationReport.java"
public class org.apache.dubbo.rpc.protocol.rest.ViolationReport implements java.io.Serializable {
  private static final long serialVersionUID;

  private java.util.List<org.apache.dubbo.rpc.protocol.rest.RestConstraintViolation> constraintViolations;

  public org.apache.dubbo.rpc.protocol.rest.ViolationReport();
    Code:
       0: aload_0
       1: invokespecial #1                  // Method java/lang/Object."<init>":()V
       4: return

  public java.util.List<org.apache.dubbo.rpc.protocol.rest.RestConstraintViolation> getConstraintViolations();
    Code:
       0: aload_0
       1: getfield      #2                  // Field constraintViolations:Ljava/util/List;
       4: areturn

  public void setConstraintViolations(java.util.List<org.apache.dubbo.rpc.protocol.rest.RestConstraintViolation>);
    Code:
       0: aload_0
       1: aload_1
       2: putfield      #2                  // Field constraintViolations:Ljava/util/List;
       5: return

  public void addConstraintViolation(org.apache.dubbo.rpc.protocol.rest.RestConstraintViolation);
    Code:
       0: aload_0
       1: getfield      #2                  // Field constraintViolations:Ljava/util/List;
       4: ifnonnull     18
       7: aload_0
       8: new           #3                  // class java/util/LinkedList
      11: dup
      12: invokespecial #4                  // Method java/util/LinkedList."<init>":()V
      15: putfield      #2                  // Field constraintViolations:Ljava/util/List;
      18: aload_0
      19: getfield      #2                  // Field constraintViolations:Ljava/util/List;
      22: aload_1
      23: invokeinterface #5,  2            // InterfaceMethod java/util/List.add:(Ljava/lang/Object;)Z
      28: pop
      29: return
}
