Compiled from "BaseCommand.java"
public interface com.alibaba.dubbo.qos.command.BaseCommand extends org.apache.dubbo.qos.api.BaseCommand {
  public abstract java.lang.String execute(com.alibaba.dubbo.qos.command.CommandContext, java.lang.String[]);

  public default java.lang.String execute(org.apache.dubbo.qos.api.CommandContext, java.lang.String[]);
    Code:
       0: aload_0
       1: new           #1                  // class com/alibaba/dubbo/qos/command/CommandContext
       4: dup
       5: aload_1
       6: invokespecial #2                  // Method com/alibaba/dubbo/qos/command/CommandContext."<init>":(Lorg/apache/dubbo/qos/api/CommandContext;)V
       9: aload_2
      10: invokeinterface #3,  3            // InterfaceMethod execute:(Lcom/alibaba/dubbo/qos/command/CommandContext;[Ljava/lang/String;)Ljava/lang/String;
      15: areturn
}
