Compiled from "CommandContext.java"
public class com.alibaba.dubbo.qos.command.CommandContext extends org.apache.dubbo.qos.api.CommandContext {
  public com.alibaba.dubbo.qos.command.CommandContext(org.apache.dubbo.qos.api.CommandContext);
    Code:
       0: aload_0
       1: aload_1
       2: invokevirtual #1                  // Method org/apache/dubbo/qos/api/CommandContext.getCommandName:()Ljava/lang/String;
       5: aload_1
       6: invokevirtual #2                  // Method org/apache/dubbo/qos/api/CommandContext.getArgs:()[Ljava/lang/String;
       9: aload_1
      10: invokevirtual #3                  // Method org/apache/dubbo/qos/api/CommandContext.isHttp:()Z
      13: invokespecial #4                  // Method org/apache/dubbo/qos/api/CommandContext."<init>":(Ljava/lang/String;[Ljava/lang/String;Z)V
      16: aload_0
      17: aload_1
      18: invokevirtual #5                  // Method org/apache/dubbo/qos/api/CommandContext.getRemote:()Lio/netty/channel/Channel;
      21: invokevirtual #6                  // Method setRemote:(Lio/netty/channel/Channel;)V
      24: aload_0
      25: aload_1
      26: invokevirtual #7                  // Method org/apache/dubbo/qos/api/CommandContext.getOriginRequest:()Ljava/lang/Object;
      29: invokevirtual #8                  // Method setOriginRequest:(Ljava/lang/Object;)V
      32: return

  public com.alibaba.dubbo.qos.command.CommandContext(java.lang.String);
    Code:
       0: aload_0
       1: aload_1
       2: invokespecial #9                  // Method org/apache/dubbo/qos/api/CommandContext."<init>":(Ljava/lang/String;)V
       5: return

  public com.alibaba.dubbo.qos.command.CommandContext(java.lang.String, java.lang.String[], boolean);
    Code:
       0: aload_0
       1: aload_1
       2: aload_2
       3: iload_3
       4: invokespecial #4                  // Method org/apache/dubbo/qos/api/CommandContext."<init>":(Ljava/lang/String;[Ljava/lang/String;Z)V
       7: return
}
