Compiled from "Ca.java"
public final class org.apache.dubbo.auth.v1alpha1.Ca {
  static final com.google.protobuf.Descriptors$Descriptor internal_static_org_apache_dubbo_auth_v1alpha1_DubboCertificateRequest_descriptor;

  static final com.google.protobuf.GeneratedMessageV3$FieldAccessorTable internal_static_org_apache_dubbo_auth_v1alpha1_DubboCertificateRequest_fieldAccessorTable;

  static final com.google.protobuf.Descriptors$Descriptor internal_static_org_apache_dubbo_auth_v1alpha1_DubboCertificateResponse_descriptor;

  static final com.google.protobuf.GeneratedMessageV3$FieldAccessorTable internal_static_org_apache_dubbo_auth_v1alpha1_DubboCertificateResponse_fieldAccessorTable;

  private static com.google.protobuf.Descriptors$FileDescriptor descriptor;

  private org.apache.dubbo.auth.v1alpha1.Ca();
    Code:
       0: aload_0
       1: invokespecial #1                  // Method java/lang/Object."<init>":()V
       4: return

  public static void registerAllExtensions(com.google.protobuf.ExtensionRegistryLite);
    Code:
       0: return

  public static void registerAllExtensions(com.google.protobuf.ExtensionRegistry);
    Code:
       0: aload_0
       1: invokestatic  #2                  // Method registerAllExtensions:(Lcom/google/protobuf/ExtensionRegistryLite;)V
       4: return

  public static com.google.protobuf.Descriptors$FileDescriptor getDescriptor();
    Code:
       0: getstatic     #3                  // Field descriptor:Lcom/google/protobuf/Descriptors$FileDescriptor;
       3: areturn

  static {};
    Code:
       0: iconst_1
       1: anewarray     #4                  // class java/lang/String
       4: dup
       5: iconst_0
       6: ldc           #5                  // String \n\bca.proto\u0012\u001eorg.apache.dubbo.auth.v1alpha1\u001a\u001cgoogle/protobuf/struct.proto\"_\n\u0017DubboCertificateRequest\u0012\u000b\n\u0003csr\u0018\u0001 \u0001(\t\u0012\f\n\u0004type\u0018\u0002 \u0001(\t\u0012)\n\bmetadata\u0018\u0003 \u0001(\u000b2\u0017.google.protobuf.Struct\"x\n\u0018DubboCertificateResponse\u0012\u000f\n\u0007success\u0018\u0001 \u0001(\b\u0012\u0010\n\bcert_pem\u0018\u0002 \u0001(\t\u0012\u0013\n\u000btrust_certs\u0018\u0003 \u0003(\t\u0012\u0013\n\u000bexpire_time\u0018\u0004 \u0001(\u0003\u0012\u000f\n\u0007message\u0018\u0005 \u0001(\t2¢´\u0001\n\u0017DubboCertificateService\u0012\u0088\u0001\n\u0011CreateCertificate\u00127.org.apache.dubbo.auth.v1alpha1.DubboCertificateRequest\u001a8.org.apache.dubbo.auth.v1alpha1.DubboCertificateResponse\"\u0000B-P\u0001Z)github.com/apache/dubbo-admin/ca/v1alpha1b\u0006proto3
       8: aastore
       9: astore_0
      10: aload_0
      11: iconst_1
      12: anewarray     #6                  // class com/google/protobuf/Descriptors$FileDescriptor
      15: dup
      16: iconst_0
      17: invokestatic  #7                  // Method com/google/protobuf/StructProto.getDescriptor:()Lcom/google/protobuf/Descriptors$FileDescriptor;
      20: aastore
      21: invokestatic  #8                  // Method com/google/protobuf/Descriptors$FileDescriptor.internalBuildGeneratedFileFrom:([Ljava/lang/String;[Lcom/google/protobuf/Descriptors$FileDescriptor;)Lcom/google/protobuf/Descriptors$FileDescriptor;
      24: putstatic     #3                  // Field descriptor:Lcom/google/protobuf/Descriptors$FileDescriptor;
      27: invokestatic  #9                  // Method getDescriptor:()Lcom/google/protobuf/Descriptors$FileDescriptor;
      30: invokevirtual #10                 // Method com/google/protobuf/Descriptors$FileDescriptor.getMessageTypes:()Ljava/util/List;
      33: iconst_0
      34: invokeinterface #11,  2           // InterfaceMethod java/util/List.get:(I)Ljava/lang/Object;
      39: checkcast     #12                 // class com/google/protobuf/Descriptors$Descriptor
      42: putstatic     #13                 // Field internal_static_org_apache_dubbo_auth_v1alpha1_DubboCertificateRequest_descriptor:Lcom/google/protobuf/Descriptors$Descriptor;
      45: new           #14                 // class com/google/protobuf/GeneratedMessageV3$FieldAccessorTable
      48: dup
      49: getstatic     #13                 // Field internal_static_org_apache_dubbo_auth_v1alpha1_DubboCertificateRequest_descriptor:Lcom/google/protobuf/Descriptors$Descriptor;
      52: iconst_3
      53: anewarray     #4                  // class java/lang/String
      56: dup
      57: iconst_0
      58: ldc           #15                 // String Csr
      60: aastore
      61: dup
      62: iconst_1
      63: ldc           #16                 // String Type
      65: aastore
      66: dup
      67: iconst_2
      68: ldc           #17                 // String Metadata
      70: aastore
      71: invokespecial #18                 // Method com/google/protobuf/GeneratedMessageV3$FieldAccessorTable."<init>":(Lcom/google/protobuf/Descriptors$Descriptor;[Ljava/lang/String;)V
      74: putstatic     #19                 // Field internal_static_org_apache_dubbo_auth_v1alpha1_DubboCertificateRequest_fieldAccessorTable:Lcom/google/protobuf/GeneratedMessageV3$FieldAccessorTable;
      77: invokestatic  #9                  // Method getDescriptor:()Lcom/google/protobuf/Descriptors$FileDescriptor;
      80: invokevirtual #10                 // Method com/google/protobuf/Descriptors$FileDescriptor.getMessageTypes:()Ljava/util/List;
      83: iconst_1
      84: invokeinterface #11,  2           // InterfaceMethod java/util/List.get:(I)Ljava/lang/Object;
      89: checkcast     #12                 // class com/google/protobuf/Descriptors$Descriptor
      92: putstatic     #20                 // Field internal_static_org_apache_dubbo_auth_v1alpha1_DubboCertificateResponse_descriptor:Lcom/google/protobuf/Descriptors$Descriptor;
      95: new           #14                 // class com/google/protobuf/GeneratedMessageV3$FieldAccessorTable
      98: dup
      99: getstatic     #20                 // Field internal_static_org_apache_dubbo_auth_v1alpha1_DubboCertificateResponse_descriptor:Lcom/google/protobuf/Descriptors$Descriptor;
     102: iconst_5
     103: anewarray     #4                  // class java/lang/String
     106: dup
     107: iconst_0
     108: ldc           #21                 // String Success
     110: aastore
     111: dup
     112: iconst_1
     113: ldc           #22                 // String CertPem
     115: aastore
     116: dup
     117: iconst_2
     118: ldc           #23                 // String TrustCerts
     120: aastore
     121: dup
     122: iconst_3
     123: ldc           #24                 // String ExpireTime
     125: aastore
     126: dup
     127: iconst_4
     128: ldc           #25                 // String Message
     130: aastore
     131: invokespecial #18                 // Method com/google/protobuf/GeneratedMessageV3$FieldAccessorTable."<init>":(Lcom/google/protobuf/Descriptors$Descriptor;[Ljava/lang/String;)V
     134: putstatic     #26                 // Field internal_static_org_apache_dubbo_auth_v1alpha1_DubboCertificateResponse_fieldAccessorTable:Lcom/google/protobuf/GeneratedMessageV3$FieldAccessorTable;
     137: invokestatic  #7                  // Method com/google/protobuf/StructProto.getDescriptor:()Lcom/google/protobuf/Descriptors$FileDescriptor;
     140: pop
     141: return
}
