Compiled from "DubboCertificateRequest.java"
public final class org.apache.dubbo.auth.v1alpha1.DubboCertificateRequest extends com.google.protobuf.GeneratedMessageV3 implements org.apache.dubbo.auth.v1alpha1.DubboCertificateRequestOrBuilder {
  private static final long serialVersionUID;

  public static final int CSR_FIELD_NUMBER;

  private volatile java.lang.Object csr_;

  public static final int TYPE_FIELD_NUMBER;

  private volatile java.lang.Object type_;

  public static final int METADATA_FIELD_NUMBER;

  private com.google.protobuf.Struct metadata_;

  private byte memoizedIsInitialized;

  private static final org.apache.dubbo.auth.v1alpha1.DubboCertificateRequest DEFAULT_INSTANCE;

  private static final com.google.protobuf.Parser<org.apache.dubbo.auth.v1alpha1.DubboCertificateRequest> PARSER;

  private org.apache.dubbo.auth.v1alpha1.DubboCertificateRequest(com.google.protobuf.GeneratedMessageV3$Builder<?>);
    Code:
       0: aload_0
       1: aload_1
       2: invokespecial #6                  // Method com/google/protobuf/GeneratedMessageV3."<init>":(Lcom/google/protobuf/GeneratedMessageV3$Builder;)V
       5: aload_0
       6: ldc           #7                  // String
       8: putfield      #4                  // Field csr_:Ljava/lang/Object;
      11: aload_0
      12: ldc           #7                  // String
      14: putfield      #3                  // Field type_:Ljava/lang/Object;
      17: aload_0
      18: iconst_m1
      19: putfield      #8                  // Field memoizedIsInitialized:B
      22: return

  private org.apache.dubbo.auth.v1alpha1.DubboCertificateRequest();
    Code:
       0: aload_0
       1: invokespecial #9                  // Method com/google/protobuf/GeneratedMessageV3."<init>":()V
       4: aload_0
       5: ldc           #7                  // String
       7: putfield      #4                  // Field csr_:Ljava/lang/Object;
      10: aload_0
      11: ldc           #7                  // String
      13: putfield      #3                  // Field type_:Ljava/lang/Object;
      16: aload_0
      17: iconst_m1
      18: putfield      #8                  // Field memoizedIsInitialized:B
      21: aload_0
      22: ldc           #7                  // String
      24: putfield      #4                  // Field csr_:Ljava/lang/Object;
      27: aload_0
      28: ldc           #7                  // String
      30: putfield      #3                  // Field type_:Ljava/lang/Object;
      33: return

  protected java.lang.Object newInstance(com.google.protobuf.GeneratedMessageV3$UnusedPrivateParameter);
    Code:
       0: new           #10                 // class org/apache/dubbo/auth/v1alpha1/DubboCertificateRequest
       3: dup
       4: invokespecial #11                 // Method "<init>":()V
       7: areturn

  public static final com.google.protobuf.Descriptors$Descriptor getDescriptor();
    Code:
       0: getstatic     #12                 // Field org/apache/dubbo/auth/v1alpha1/Ca.internal_static_org_apache_dubbo_auth_v1alpha1_DubboCertificateRequest_descriptor:Lcom/google/protobuf/Descriptors$Descriptor;
       3: areturn

  protected com.google.protobuf.GeneratedMessageV3$FieldAccessorTable internalGetFieldAccessorTable();
    Code:
       0: getstatic     #13                 // Field org/apache/dubbo/auth/v1alpha1/Ca.internal_static_org_apache_dubbo_auth_v1alpha1_DubboCertificateRequest_fieldAccessorTable:Lcom/google/protobuf/GeneratedMessageV3$FieldAccessorTable;
       3: ldc           #10                 // class org/apache/dubbo/auth/v1alpha1/DubboCertificateRequest
       5: ldc           #14                 // class org/apache/dubbo/auth/v1alpha1/DubboCertificateRequest$Builder
       7: invokevirtual #15                 // Method com/google/protobuf/GeneratedMessageV3$FieldAccessorTable.ensureFieldAccessorsInitialized:(Ljava/lang/Class;Ljava/lang/Class;)Lcom/google/protobuf/GeneratedMessageV3$FieldAccessorTable;
      10: areturn

  public java.lang.String getCsr();
    Code:
       0: aload_0
       1: getfield      #4                  // Field csr_:Ljava/lang/Object;
       4: astore_1
       5: aload_1
       6: instanceof    #16                 // class java/lang/String
       9: ifeq          17
      12: aload_1
      13: checkcast     #16                 // class java/lang/String
      16: areturn
      17: aload_1
      18: checkcast     #17                 // class com/google/protobuf/ByteString
      21: astore_2
      22: aload_2
      23: invokevirtual #18                 // Method com/google/protobuf/ByteString.toStringUtf8:()Ljava/lang/String;
      26: astore_3
      27: aload_0
      28: aload_3
      29: putfield      #4                  // Field csr_:Ljava/lang/Object;
      32: aload_3
      33: areturn

  public com.google.protobuf.ByteString getCsrBytes();
    Code:
       0: aload_0
       1: getfield      #4                  // Field csr_:Ljava/lang/Object;
       4: astore_1
       5: aload_1
       6: instanceof    #16                 // class java/lang/String
       9: ifeq          27
      12: aload_1
      13: checkcast     #16                 // class java/lang/String
      16: invokestatic  #19                 // Method com/google/protobuf/ByteString.copyFromUtf8:(Ljava/lang/String;)Lcom/google/protobuf/ByteString;
      19: astore_2
      20: aload_0
      21: aload_2
      22: putfield      #4                  // Field csr_:Ljava/lang/Object;
      25: aload_2
      26: areturn
      27: aload_1
      28: checkcast     #17                 // class com/google/protobuf/ByteString
      31: areturn

  public java.lang.String getType();
    Code:
       0: aload_0
       1: getfield      #3                  // Field type_:Ljava/lang/Object;
       4: astore_1
       5: aload_1
       6: instanceof    #16                 // class java/lang/String
       9: ifeq          17
      12: aload_1
      13: checkcast     #16                 // class java/lang/String
      16: areturn
      17: aload_1
      18: checkcast     #17                 // class com/google/protobuf/ByteString
      21: astore_2
      22: aload_2
      23: invokevirtual #18                 // Method com/google/protobuf/ByteString.toStringUtf8:()Ljava/lang/String;
      26: astore_3
      27: aload_0
      28: aload_3
      29: putfield      #3                  // Field type_:Ljava/lang/Object;
      32: aload_3
      33: areturn

  public com.google.protobuf.ByteString getTypeBytes();
    Code:
       0: aload_0
       1: getfield      #3                  // Field type_:Ljava/lang/Object;
       4: astore_1
       5: aload_1
       6: instanceof    #16                 // class java/lang/String
       9: ifeq          27
      12: aload_1
      13: checkcast     #16                 // class java/lang/String
      16: invokestatic  #19                 // Method com/google/protobuf/ByteString.copyFromUtf8:(Ljava/lang/String;)Lcom/google/protobuf/ByteString;
      19: astore_2
      20: aload_0
      21: aload_2
      22: putfield      #3                  // Field type_:Ljava/lang/Object;
      25: aload_2
      26: areturn
      27: aload_1
      28: checkcast     #17                 // class com/google/protobuf/ByteString
      31: areturn

  public boolean hasMetadata();
    Code:
       0: aload_0
       1: getfield      #2                  // Field metadata_:Lcom/google/protobuf/Struct;
       4: ifnull        11
       7: iconst_1
       8: goto          12
      11: iconst_0
      12: ireturn

  public com.google.protobuf.Struct getMetadata();
    Code:
       0: aload_0
       1: getfield      #2                  // Field metadata_:Lcom/google/protobuf/Struct;
       4: ifnonnull     13
       7: invokestatic  #20                 // Method com/google/protobuf/Struct.getDefaultInstance:()Lcom/google/protobuf/Struct;
      10: goto          17
      13: aload_0
      14: getfield      #2                  // Field metadata_:Lcom/google/protobuf/Struct;
      17: areturn

  public com.google.protobuf.StructOrBuilder getMetadataOrBuilder();
    Code:
       0: aload_0
       1: getfield      #2                  // Field metadata_:Lcom/google/protobuf/Struct;
       4: ifnonnull     13
       7: invokestatic  #20                 // Method com/google/protobuf/Struct.getDefaultInstance:()Lcom/google/protobuf/Struct;
      10: goto          17
      13: aload_0
      14: getfield      #2                  // Field metadata_:Lcom/google/protobuf/Struct;
      17: areturn

  public final boolean isInitialized();
    Code:
       0: aload_0
       1: getfield      #8                  // Field memoizedIsInitialized:B
       4: istore_1
       5: iload_1
       6: iconst_1
       7: if_icmpne     12
      10: iconst_1
      11: ireturn
      12: iload_1
      13: ifne          18
      16: iconst_0
      17: ireturn
      18: aload_0
      19: iconst_1
      20: putfield      #8                  // Field memoizedIsInitialized:B
      23: iconst_1
      24: ireturn

  public void writeTo(com.google.protobuf.CodedOutputStream) throws java.io.IOException;
    Code:
       0: aload_0
       1: getfield      #4                  // Field csr_:Ljava/lang/Object;
       4: invokestatic  #21                 // Method com/google/protobuf/GeneratedMessageV3.isStringEmpty:(Ljava/lang/Object;)Z
       7: ifne          19
      10: aload_1
      11: iconst_1
      12: aload_0
      13: getfield      #4                  // Field csr_:Ljava/lang/Object;
      16: invokestatic  #22                 // Method com/google/protobuf/GeneratedMessageV3.writeString:(Lcom/google/protobuf/CodedOutputStream;ILjava/lang/Object;)V
      19: aload_0
      20: getfield      #3                  // Field type_:Ljava/lang/Object;
      23: invokestatic  #21                 // Method com/google/protobuf/GeneratedMessageV3.isStringEmpty:(Ljava/lang/Object;)Z
      26: ifne          38
      29: aload_1
      30: iconst_2
      31: aload_0
      32: getfield      #3                  // Field type_:Ljava/lang/Object;
      35: invokestatic  #22                 // Method com/google/protobuf/GeneratedMessageV3.writeString:(Lcom/google/protobuf/CodedOutputStream;ILjava/lang/Object;)V
      38: aload_0
      39: getfield      #2                  // Field metadata_:Lcom/google/protobuf/Struct;
      42: ifnull        54
      45: aload_1
      46: iconst_3
      47: aload_0
      48: invokevirtual #23                 // Method getMetadata:()Lcom/google/protobuf/Struct;
      51: invokevirtual #24                 // Method com/google/protobuf/CodedOutputStream.writeMessage:(ILcom/google/protobuf/MessageLite;)V
      54: aload_0
      55: invokevirtual #25                 // Method getUnknownFields:()Lcom/google/protobuf/UnknownFieldSet;
      58: aload_1
      59: invokevirtual #26                 // Method com/google/protobuf/UnknownFieldSet.writeTo:(Lcom/google/protobuf/CodedOutputStream;)V
      62: return

  public int getSerializedSize();
    Code:
       0: aload_0
       1: getfield      #27                 // Field memoizedSize:I
       4: istore_1
       5: iload_1
       6: iconst_m1
       7: if_icmpeq     12
      10: iload_1
      11: ireturn
      12: iconst_0
      13: istore_1
      14: aload_0
      15: getfield      #4                  // Field csr_:Ljava/lang/Object;
      18: invokestatic  #21                 // Method com/google/protobuf/GeneratedMessageV3.isStringEmpty:(Ljava/lang/Object;)Z
      21: ifne          35
      24: iload_1
      25: iconst_1
      26: aload_0
      27: getfield      #4                  // Field csr_:Ljava/lang/Object;
      30: invokestatic  #28                 // Method com/google/protobuf/GeneratedMessageV3.computeStringSize:(ILjava/lang/Object;)I
      33: iadd
      34: istore_1
      35: aload_0
      36: getfield      #3                  // Field type_:Ljava/lang/Object;
      39: invokestatic  #21                 // Method com/google/protobuf/GeneratedMessageV3.isStringEmpty:(Ljava/lang/Object;)Z
      42: ifne          56
      45: iload_1
      46: iconst_2
      47: aload_0
      48: getfield      #3                  // Field type_:Ljava/lang/Object;
      51: invokestatic  #28                 // Method com/google/protobuf/GeneratedMessageV3.computeStringSize:(ILjava/lang/Object;)I
      54: iadd
      55: istore_1
      56: aload_0
      57: getfield      #2                  // Field metadata_:Lcom/google/protobuf/Struct;
      60: ifnull        74
      63: iload_1
      64: iconst_3
      65: aload_0
      66: invokevirtual #23                 // Method getMetadata:()Lcom/google/protobuf/Struct;
      69: invokestatic  #29                 // Method com/google/protobuf/CodedOutputStream.computeMessageSize:(ILcom/google/protobuf/MessageLite;)I
      72: iadd
      73: istore_1
      74: iload_1
      75: aload_0
      76: invokevirtual #25                 // Method getUnknownFields:()Lcom/google/protobuf/UnknownFieldSet;
      79: invokevirtual #30                 // Method com/google/protobuf/UnknownFieldSet.getSerializedSize:()I
      82: iadd
      83: istore_1
      84: aload_0
      85: iload_1
      86: putfield      #27                 // Field memoizedSize:I
      89: iload_1
      90: ireturn

  public boolean equals(java.lang.Object);
    Code:
       0: aload_1
       1: aload_0
       2: if_acmpne     7
       5: iconst_1
       6: ireturn
       7: aload_1
       8: instanceof    #10                 // class org/apache/dubbo/auth/v1alpha1/DubboCertificateRequest
      11: ifne          20
      14: aload_0
      15: aload_1
      16: invokespecial #31                 // Method com/google/protobuf/GeneratedMessageV3.equals:(Ljava/lang/Object;)Z
      19: ireturn
      20: aload_1
      21: checkcast     #10                 // class org/apache/dubbo/auth/v1alpha1/DubboCertificateRequest
      24: astore_2
      25: aload_0
      26: invokevirtual #32                 // Method getCsr:()Ljava/lang/String;
      29: aload_2
      30: invokevirtual #32                 // Method getCsr:()Ljava/lang/String;
      33: invokevirtual #33                 // Method java/lang/String.equals:(Ljava/lang/Object;)Z
      36: ifne          41
      39: iconst_0
      40: ireturn
      41: aload_0
      42: invokevirtual #34                 // Method getType:()Ljava/lang/String;
      45: aload_2
      46: invokevirtual #34                 // Method getType:()Ljava/lang/String;
      49: invokevirtual #33                 // Method java/lang/String.equals:(Ljava/lang/Object;)Z
      52: ifne          57
      55: iconst_0
      56: ireturn
      57: aload_0
      58: invokevirtual #35                 // Method hasMetadata:()Z
      61: aload_2
      62: invokevirtual #35                 // Method hasMetadata:()Z
      65: if_icmpeq     70
      68: iconst_0
      69: ireturn
      70: aload_0
      71: invokevirtual #35                 // Method hasMetadata:()Z
      74: ifeq          93
      77: aload_0
      78: invokevirtual #23                 // Method getMetadata:()Lcom/google/protobuf/Struct;
      81: aload_2
      82: invokevirtual #23                 // Method getMetadata:()Lcom/google/protobuf/Struct;
      85: invokevirtual #36                 // Method com/google/protobuf/Struct.equals:(Ljava/lang/Object;)Z
      88: ifne          93
      91: iconst_0
      92: ireturn
      93: aload_0
      94: invokevirtual #25                 // Method getUnknownFields:()Lcom/google/protobuf/UnknownFieldSet;
      97: aload_2
      98: invokevirtual #25                 // Method getUnknownFields:()Lcom/google/protobuf/UnknownFieldSet;
     101: invokevirtual #37                 // Method com/google/protobuf/UnknownFieldSet.equals:(Ljava/lang/Object;)Z
     104: ifne          109
     107: iconst_0
     108: ireturn
     109: iconst_1
     110: ireturn

  public int hashCode();
    Code:
       0: aload_0
       1: getfield      #38                 // Field memoizedHashCode:I
       4: ifeq          12
       7: aload_0
       8: getfield      #38                 // Field memoizedHashCode:I
      11: ireturn
      12: bipush        41
      14: istore_1
      15: bipush        19
      17: iload_1
      18: imul
      19: invokestatic  #39                 // Method getDescriptor:()Lcom/google/protobuf/Descriptors$Descriptor;
      22: invokevirtual #40                 // Method java/lang/Object.hashCode:()I
      25: iadd
      26: istore_1
      27: bipush        37
      29: iload_1
      30: imul
      31: iconst_1
      32: iadd
      33: istore_1
      34: bipush        53
      36: iload_1
      37: imul
      38: aload_0
      39: invokevirtual #32                 // Method getCsr:()Ljava/lang/String;
      42: invokevirtual #41                 // Method java/lang/String.hashCode:()I
      45: iadd
      46: istore_1
      47: bipush        37
      49: iload_1
      50: imul
      51: iconst_2
      52: iadd
      53: istore_1
      54: bipush        53
      56: iload_1
      57: imul
      58: aload_0
      59: invokevirtual #34                 // Method getType:()Ljava/lang/String;
      62: invokevirtual #41                 // Method java/lang/String.hashCode:()I
      65: iadd
      66: istore_1
      67: aload_0
      68: invokevirtual #35                 // Method hasMetadata:()Z
      71: ifeq          94
      74: bipush        37
      76: iload_1
      77: imul
      78: iconst_3
      79: iadd
      80: istore_1
      81: bipush        53
      83: iload_1
      84: imul
      85: aload_0
      86: invokevirtual #23                 // Method getMetadata:()Lcom/google/protobuf/Struct;
      89: invokevirtual #42                 // Method com/google/protobuf/Struct.hashCode:()I
      92: iadd
      93: istore_1
      94: bipush        29
      96: iload_1
      97: imul
      98: aload_0
      99: invokevirtual #25                 // Method getUnknownFields:()Lcom/google/protobuf/UnknownFieldSet;
     102: invokevirtual #43                 // Method com/google/protobuf/UnknownFieldSet.hashCode:()I
     105: iadd
     106: istore_1
     107: aload_0
     108: iload_1
     109: putfield      #38                 // Field memoizedHashCode:I
     112: iload_1
     113: ireturn

  public static org.apache.dubbo.auth.v1alpha1.DubboCertificateRequest parseFrom(java.nio.ByteBuffer) throws com.google.protobuf.InvalidProtocolBufferException;
    Code:
       0: getstatic     #44                 // Field PARSER:Lcom/google/protobuf/Parser;
       3: aload_0
       4: invokeinterface #45,  2           // InterfaceMethod com/google/protobuf/Parser.parseFrom:(Ljava/nio/ByteBuffer;)Ljava/lang/Object;
       9: checkcast     #10                 // class org/apache/dubbo/auth/v1alpha1/DubboCertificateRequest
      12: areturn

  public static org.apache.dubbo.auth.v1alpha1.DubboCertificateRequest parseFrom(java.nio.ByteBuffer, com.google.protobuf.ExtensionRegistryLite) throws com.google.protobuf.InvalidProtocolBufferException;
    Code:
       0: getstatic     #44                 // Field PARSER:Lcom/google/protobuf/Parser;
       3: aload_0
       4: aload_1
       5: invokeinterface #46,  3           // InterfaceMethod com/google/protobuf/Parser.parseFrom:(Ljava/nio/ByteBuffer;Lcom/google/protobuf/ExtensionRegistryLite;)Ljava/lang/Object;
      10: checkcast     #10                 // class org/apache/dubbo/auth/v1alpha1/DubboCertificateRequest
      13: areturn

  public static org.apache.dubbo.auth.v1alpha1.DubboCertificateRequest parseFrom(com.google.protobuf.ByteString) throws com.google.protobuf.InvalidProtocolBufferException;
    Code:
       0: getstatic     #44                 // Field PARSER:Lcom/google/protobuf/Parser;
       3: aload_0
       4: invokeinterface #47,  2           // InterfaceMethod com/google/protobuf/Parser.parseFrom:(Lcom/google/protobuf/ByteString;)Ljava/lang/Object;
       9: checkcast     #10                 // class org/apache/dubbo/auth/v1alpha1/DubboCertificateRequest
      12: areturn

  public static org.apache.dubbo.auth.v1alpha1.DubboCertificateRequest parseFrom(com.google.protobuf.ByteString, com.google.protobuf.ExtensionRegistryLite) throws com.google.protobuf.InvalidProtocolBufferException;
    Code:
       0: getstatic     #44                 // Field PARSER:Lcom/google/protobuf/Parser;
       3: aload_0
       4: aload_1
       5: invokeinterface #48,  3           // InterfaceMethod com/google/protobuf/Parser.parseFrom:(Lcom/google/protobuf/ByteString;Lcom/google/protobuf/ExtensionRegistryLite;)Ljava/lang/Object;
      10: checkcast     #10                 // class org/apache/dubbo/auth/v1alpha1/DubboCertificateRequest
      13: areturn

  public static org.apache.dubbo.auth.v1alpha1.DubboCertificateRequest parseFrom(byte[]) throws com.google.protobuf.InvalidProtocolBufferException;
    Code:
       0: getstatic     #44                 // Field PARSER:Lcom/google/protobuf/Parser;
       3: aload_0
       4: invokeinterface #49,  2           // InterfaceMethod com/google/protobuf/Parser.parseFrom:([B)Ljava/lang/Object;
       9: checkcast     #10                 // class org/apache/dubbo/auth/v1alpha1/DubboCertificateRequest
      12: areturn

  public static org.apache.dubbo.auth.v1alpha1.DubboCertificateRequest parseFrom(byte[], com.google.protobuf.ExtensionRegistryLite) throws com.google.protobuf.InvalidProtocolBufferException;
    Code:
       0: getstatic     #44                 // Field PARSER:Lcom/google/protobuf/Parser;
       3: aload_0
       4: aload_1
       5: invokeinterface #50,  3           // InterfaceMethod com/google/protobuf/Parser.parseFrom:([BLcom/google/protobuf/ExtensionRegistryLite;)Ljava/lang/Object;
      10: checkcast     #10                 // class org/apache/dubbo/auth/v1alpha1/DubboCertificateRequest
      13: areturn

  public static org.apache.dubbo.auth.v1alpha1.DubboCertificateRequest parseFrom(java.io.InputStream) throws java.io.IOException;
    Code:
       0: getstatic     #44                 // Field PARSER:Lcom/google/protobuf/Parser;
       3: aload_0
       4: invokestatic  #51                 // Method com/google/protobuf/GeneratedMessageV3.parseWithIOException:(Lcom/google/protobuf/Parser;Ljava/io/InputStream;)Lcom/google/protobuf/Message;
       7: checkcast     #10                 // class org/apache/dubbo/auth/v1alpha1/DubboCertificateRequest
      10: areturn

  public static org.apache.dubbo.auth.v1alpha1.DubboCertificateRequest parseFrom(java.io.InputStream, com.google.protobuf.ExtensionRegistryLite) throws java.io.IOException;
    Code:
       0: getstatic     #44                 // Field PARSER:Lcom/google/protobuf/Parser;
       3: aload_0
       4: aload_1
       5: invokestatic  #52                 // Method com/google/protobuf/GeneratedMessageV3.parseWithIOException:(Lcom/google/protobuf/Parser;Ljava/io/InputStream;Lcom/google/protobuf/ExtensionRegistryLite;)Lcom/google/protobuf/Message;
       8: checkcast     #10                 // class org/apache/dubbo/auth/v1alpha1/DubboCertificateRequest
      11: areturn

  public static org.apache.dubbo.auth.v1alpha1.DubboCertificateRequest parseDelimitedFrom(java.io.InputStream) throws java.io.IOException;
    Code:
       0: getstatic     #44                 // Field PARSER:Lcom/google/protobuf/Parser;
       3: aload_0
       4: invokestatic  #53                 // Method com/google/protobuf/GeneratedMessageV3.parseDelimitedWithIOException:(Lcom/google/protobuf/Parser;Ljava/io/InputStream;)Lcom/google/protobuf/Message;
       7: checkcast     #10                 // class org/apache/dubbo/auth/v1alpha1/DubboCertificateRequest
      10: areturn

  public static org.apache.dubbo.auth.v1alpha1.DubboCertificateRequest parseDelimitedFrom(java.io.InputStream, com.google.protobuf.ExtensionRegistryLite) throws java.io.IOException;
    Code:
       0: getstatic     #44                 // Field PARSER:Lcom/google/protobuf/Parser;
       3: aload_0
       4: aload_1
       5: invokestatic  #54                 // Method com/google/protobuf/GeneratedMessageV3.parseDelimitedWithIOException:(Lcom/google/protobuf/Parser;Ljava/io/InputStream;Lcom/google/protobuf/ExtensionRegistryLite;)Lcom/google/protobuf/Message;
       8: checkcast     #10                 // class org/apache/dubbo/auth/v1alpha1/DubboCertificateRequest
      11: areturn

  public static org.apache.dubbo.auth.v1alpha1.DubboCertificateRequest parseFrom(com.google.protobuf.CodedInputStream) throws java.io.IOException;
    Code:
       0: getstatic     #44                 // Field PARSER:Lcom/google/protobuf/Parser;
       3: aload_0
       4: invokestatic  #55                 // Method com/google/protobuf/GeneratedMessageV3.parseWithIOException:(Lcom/google/protobuf/Parser;Lcom/google/protobuf/CodedInputStream;)Lcom/google/protobuf/Message;
       7: checkcast     #10                 // class org/apache/dubbo/auth/v1alpha1/DubboCertificateRequest
      10: areturn

  public static org.apache.dubbo.auth.v1alpha1.DubboCertificateRequest parseFrom(com.google.protobuf.CodedInputStream, com.google.protobuf.ExtensionRegistryLite) throws java.io.IOException;
    Code:
       0: getstatic     #44                 // Field PARSER:Lcom/google/protobuf/Parser;
       3: aload_0
       4: aload_1
       5: invokestatic  #56                 // Method com/google/protobuf/GeneratedMessageV3.parseWithIOException:(Lcom/google/protobuf/Parser;Lcom/google/protobuf/CodedInputStream;Lcom/google/protobuf/ExtensionRegistryLite;)Lcom/google/protobuf/Message;
       8: checkcast     #10                 // class org/apache/dubbo/auth/v1alpha1/DubboCertificateRequest
      11: areturn

  public org.apache.dubbo.auth.v1alpha1.DubboCertificateRequest$Builder newBuilderForType();
    Code:
       0: invokestatic  #57                 // Method newBuilder:()Lorg/apache/dubbo/auth/v1alpha1/DubboCertificateRequest$Builder;
       3: areturn

  public static org.apache.dubbo.auth.v1alpha1.DubboCertificateRequest$Builder newBuilder();
    Code:
       0: getstatic     #58                 // Field DEFAULT_INSTANCE:Lorg/apache/dubbo/auth/v1alpha1/DubboCertificateRequest;
       3: invokevirtual #59                 // Method toBuilder:()Lorg/apache/dubbo/auth/v1alpha1/DubboCertificateRequest$Builder;
       6: areturn

  public static org.apache.dubbo.auth.v1alpha1.DubboCertificateRequest$Builder newBuilder(org.apache.dubbo.auth.v1alpha1.DubboCertificateRequest);
    Code:
       0: getstatic     #58                 // Field DEFAULT_INSTANCE:Lorg/apache/dubbo/auth/v1alpha1/DubboCertificateRequest;
       3: invokevirtual #59                 // Method toBuilder:()Lorg/apache/dubbo/auth/v1alpha1/DubboCertificateRequest$Builder;
       6: aload_0
       7: invokevirtual #60                 // Method org/apache/dubbo/auth/v1alpha1/DubboCertificateRequest$Builder.mergeFrom:(Lorg/apache/dubbo/auth/v1alpha1/DubboCertificateRequest;)Lorg/apache/dubbo/auth/v1alpha1/DubboCertificateRequest$Builder;
      10: areturn

  public org.apache.dubbo.auth.v1alpha1.DubboCertificateRequest$Builder toBuilder();
    Code:
       0: aload_0
       1: getstatic     #58                 // Field DEFAULT_INSTANCE:Lorg/apache/dubbo/auth/v1alpha1/DubboCertificateRequest;
       4: if_acmpne     18
       7: new           #14                 // class org/apache/dubbo/auth/v1alpha1/DubboCertificateRequest$Builder
      10: dup
      11: aconst_null
      12: invokespecial #61                 // Method org/apache/dubbo/auth/v1alpha1/DubboCertificateRequest$Builder."<init>":(Lorg/apache/dubbo/auth/v1alpha1/DubboCertificateRequest$1;)V
      15: goto          30
      18: new           #14                 // class org/apache/dubbo/auth/v1alpha1/DubboCertificateRequest$Builder
      21: dup
      22: aconst_null
      23: invokespecial #61                 // Method org/apache/dubbo/auth/v1alpha1/DubboCertificateRequest$Builder."<init>":(Lorg/apache/dubbo/auth/v1alpha1/DubboCertificateRequest$1;)V
      26: aload_0
      27: invokevirtual #60                 // Method org/apache/dubbo/auth/v1alpha1/DubboCertificateRequest$Builder.mergeFrom:(Lorg/apache/dubbo/auth/v1alpha1/DubboCertificateRequest;)Lorg/apache/dubbo/auth/v1alpha1/DubboCertificateRequest$Builder;
      30: areturn

  protected org.apache.dubbo.auth.v1alpha1.DubboCertificateRequest$Builder newBuilderForType(com.google.protobuf.GeneratedMessageV3$BuilderParent);
    Code:
       0: new           #14                 // class org/apache/dubbo/auth/v1alpha1/DubboCertificateRequest$Builder
       3: dup
       4: aload_1
       5: aconst_null
       6: invokespecial #62                 // Method org/apache/dubbo/auth/v1alpha1/DubboCertificateRequest$Builder."<init>":(Lcom/google/protobuf/GeneratedMessageV3$BuilderParent;Lorg/apache/dubbo/auth/v1alpha1/DubboCertificateRequest$1;)V
       9: astore_2
      10: aload_2
      11: areturn

  public static org.apache.dubbo.auth.v1alpha1.DubboCertificateRequest getDefaultInstance();
    Code:
       0: getstatic     #58                 // Field DEFAULT_INSTANCE:Lorg/apache/dubbo/auth/v1alpha1/DubboCertificateRequest;
       3: areturn

  public static com.google.protobuf.Parser<org.apache.dubbo.auth.v1alpha1.DubboCertificateRequest> parser();
    Code:
       0: getstatic     #44                 // Field PARSER:Lcom/google/protobuf/Parser;
       3: areturn

  public com.google.protobuf.Parser<org.apache.dubbo.auth.v1alpha1.DubboCertificateRequest> getParserForType();
    Code:
       0: getstatic     #44                 // Field PARSER:Lcom/google/protobuf/Parser;
       3: areturn

  public org.apache.dubbo.auth.v1alpha1.DubboCertificateRequest getDefaultInstanceForType();
    Code:
       0: getstatic     #58                 // Field DEFAULT_INSTANCE:Lorg/apache/dubbo/auth/v1alpha1/DubboCertificateRequest;
       3: areturn

  protected com.google.protobuf.Message$Builder newBuilderForType(com.google.protobuf.GeneratedMessageV3$BuilderParent);
    Code:
       0: aload_0
       1: aload_1
       2: invokevirtual #63                 // Method newBuilderForType:(Lcom/google/protobuf/GeneratedMessageV3$BuilderParent;)Lorg/apache/dubbo/auth/v1alpha1/DubboCertificateRequest$Builder;
       5: areturn

  public com.google.protobuf.Message$Builder toBuilder();
    Code:
       0: aload_0
       1: invokevirtual #59                 // Method toBuilder:()Lorg/apache/dubbo/auth/v1alpha1/DubboCertificateRequest$Builder;
       4: areturn

  public com.google.protobuf.Message$Builder newBuilderForType();
    Code:
       0: aload_0
       1: invokevirtual #64                 // Method newBuilderForType:()Lorg/apache/dubbo/auth/v1alpha1/DubboCertificateRequest$Builder;
       4: areturn

  public com.google.protobuf.MessageLite$Builder toBuilder();
    Code:
       0: aload_0
       1: invokevirtual #59                 // Method toBuilder:()Lorg/apache/dubbo/auth/v1alpha1/DubboCertificateRequest$Builder;
       4: areturn

  public com.google.protobuf.MessageLite$Builder newBuilderForType();
    Code:
       0: aload_0
       1: invokevirtual #64                 // Method newBuilderForType:()Lorg/apache/dubbo/auth/v1alpha1/DubboCertificateRequest$Builder;
       4: areturn

  public com.google.protobuf.MessageLite getDefaultInstanceForType();
    Code:
       0: aload_0
       1: invokevirtual #65                 // Method getDefaultInstanceForType:()Lorg/apache/dubbo/auth/v1alpha1/DubboCertificateRequest;
       4: areturn

  public com.google.protobuf.Message getDefaultInstanceForType();
    Code:
       0: aload_0
       1: invokevirtual #65                 // Method getDefaultInstanceForType:()Lorg/apache/dubbo/auth/v1alpha1/DubboCertificateRequest;
       4: areturn

  org.apache.dubbo.auth.v1alpha1.DubboCertificateRequest(com.google.protobuf.GeneratedMessageV3$Builder, org.apache.dubbo.auth.v1alpha1.DubboCertificateRequest$1);
    Code:
       0: aload_0
       1: aload_1
       2: invokespecial #5                  // Method "<init>":(Lcom/google/protobuf/GeneratedMessageV3$Builder;)V
       5: return

  static java.lang.Object access$302(org.apache.dubbo.auth.v1alpha1.DubboCertificateRequest, java.lang.Object);
    Code:
       0: aload_0
       1: aload_1
       2: dup_x1
       3: putfield      #4                  // Field csr_:Ljava/lang/Object;
       6: areturn

  static java.lang.Object access$402(org.apache.dubbo.auth.v1alpha1.DubboCertificateRequest, java.lang.Object);
    Code:
       0: aload_0
       1: aload_1
       2: dup_x1
       3: putfield      #3                  // Field type_:Ljava/lang/Object;
       6: areturn

  static com.google.protobuf.Struct access$502(org.apache.dubbo.auth.v1alpha1.DubboCertificateRequest, com.google.protobuf.Struct);
    Code:
       0: aload_0
       1: aload_1
       2: dup_x1
       3: putfield      #2                  // Field metadata_:Lcom/google/protobuf/Struct;
       6: areturn

  static java.lang.Object access$300(org.apache.dubbo.auth.v1alpha1.DubboCertificateRequest);
    Code:
       0: aload_0
       1: getfield      #4                  // Field csr_:Ljava/lang/Object;
       4: areturn

  static java.lang.Object access$400(org.apache.dubbo.auth.v1alpha1.DubboCertificateRequest);
    Code:
       0: aload_0
       1: getfield      #3                  // Field type_:Ljava/lang/Object;
       4: areturn

  static void access$600(com.google.protobuf.ByteString) throws java.lang.IllegalArgumentException;
    Code:
       0: aload_0
       1: invokestatic  #1                  // Method checkByteStringIsUtf8:(Lcom/google/protobuf/ByteString;)V
       4: return

  static void access$700(com.google.protobuf.ByteString) throws java.lang.IllegalArgumentException;
    Code:
       0: aload_0
       1: invokestatic  #1                  // Method checkByteStringIsUtf8:(Lcom/google/protobuf/ByteString;)V
       4: return

  static {};
    Code:
       0: new           #10                 // class org/apache/dubbo/auth/v1alpha1/DubboCertificateRequest
       3: dup
       4: invokespecial #11                 // Method "<init>":()V
       7: putstatic     #58                 // Field DEFAULT_INSTANCE:Lorg/apache/dubbo/auth/v1alpha1/DubboCertificateRequest;
      10: new           #66                 // class org/apache/dubbo/auth/v1alpha1/DubboCertificateRequest$1
      13: dup
      14: invokespecial #67                 // Method org/apache/dubbo/auth/v1alpha1/DubboCertificateRequest$1."<init>":()V
      17: putstatic     #44                 // Field PARSER:Lcom/google/protobuf/Parser;
      20: return
}
