Compiled from "DubboCertificateServiceGrpc.java"
final class org.apache.dubbo.auth.v1alpha1.DubboCertificateServiceGrpc$3 implements io.grpc.stub.AbstractStub$StubFactory<org.apache.dubbo.auth.v1alpha1.DubboCertificateServiceGrpc$DubboCertificateServiceFutureStub> {
  org.apache.dubbo.auth.v1alpha1.DubboCertificateServiceGrpc$3();
    Code:
       0: aload_0
       1: invokespecial #1                  // Method java/lang/Object."<init>":()V
       4: return

  public org.apache.dubbo.auth.v1alpha1.DubboCertificateServiceGrpc$DubboCertificateServiceFutureStub newStub(io.grpc.Channel, io.grpc.CallOptions);
    Code:
       0: new           #2                  // class org/apache/dubbo/auth/v1alpha1/DubboCertificateServiceGrpc$DubboCertificateServiceFutureStub
       3: dup
       4: aload_1
       5: aload_2
       6: aconst_null
       7: invokespecial #3                  // Method org/apache/dubbo/auth/v1alpha1/DubboCertificateServiceGrpc$DubboCertificateServiceFutureStub."<init>":(Lio/grpc/Channel;Lio/grpc/CallOptions;Lorg/apache/dubbo/auth/v1alpha1/DubboCertificateServiceGrpc$1;)V
      10: areturn

  public io.grpc.stub.AbstractStub newStub(io.grpc.Channel, io.grpc.CallOptions);
    Code:
       0: aload_0
       1: aload_1
       2: aload_2
       3: invokevirtual #4                  // Method newStub:(Lio/grpc/Channel;Lio/grpc/CallOptions;)Lorg/apache/dubbo/auth/v1alpha1/DubboCertificateServiceGrpc$DubboCertificateServiceFutureStub;
       6: areturn
}
