Compiled from "DubboCertificateServiceGrpc.java"
public abstract class org.apache.dubbo.auth.v1alpha1.DubboCertificateServiceGrpc$DubboCertificateServiceImplBase implements io.grpc.BindableService {
  public org.apache.dubbo.auth.v1alpha1.DubboCertificateServiceGrpc$DubboCertificateServiceImplBase();
    Code:
       0: aload_0
       1: invokespecial #2                  // Method java/lang/Object."<init>":()V
       4: return

  public void createCertificate(org.apache.dubbo.auth.v1alpha1.DubboCertificateRequest, io.grpc.stub.StreamObserver<org.apache.dubbo.auth.v1alpha1.DubboCertificateResponse>);
    Code:
       0: invokestatic  #3                  // Method org/apache/dubbo/auth/v1alpha1/DubboCertificateServiceGrpc.getCreateCertificateMethod:()Lio/grpc/MethodDescriptor;
       3: aload_2
       4: invokestatic  #4                  // Method io/grpc/stub/ServerCalls.asyncUnimplementedUnaryCall:(Lio/grpc/MethodDescriptor;Lio/grpc/stub/StreamObserver;)V
       7: return

  public final io.grpc.ServerServiceDefinition bindService();
    Code:
       0: invokestatic  #5                  // Method org/apache/dubbo/auth/v1alpha1/DubboCertificateServiceGrpc.getServiceDescriptor:()Lio/grpc/ServiceDescriptor;
       3: invokestatic  #6                  // Method io/grpc/ServerServiceDefinition.builder:(Lio/grpc/ServiceDescriptor;)Lio/grpc/ServerServiceDefinition$Builder;
       6: invokestatic  #3                  // Method org/apache/dubbo/auth/v1alpha1/DubboCertificateServiceGrpc.getCreateCertificateMethod:()Lio/grpc/MethodDescriptor;
       9: new           #7                  // class org/apache/dubbo/auth/v1alpha1/DubboCertificateServiceGrpc$MethodHandlers
      12: dup
      13: aload_0
      14: iconst_0
      15: invokespecial #8                  // Method org/apache/dubbo/auth/v1alpha1/DubboCertificateServiceGrpc$MethodHandlers."<init>":(Lorg/apache/dubbo/auth/v1alpha1/DubboCertificateServiceGrpc$DubboCertificateServiceImplBase;I)V
      18: invokestatic  #9                  // Method io/grpc/stub/ServerCalls.asyncUnaryCall:(Lio/grpc/stub/ServerCalls$UnaryMethod;)Lio/grpc/ServerCallHandler;
      21: invokevirtual #10                 // Method io/grpc/ServerServiceDefinition$Builder.addMethod:(Lio/grpc/MethodDescriptor;Lio/grpc/ServerCallHandler;)Lio/grpc/ServerServiceDefinition$Builder;
      24: invokevirtual #11                 // Method io/grpc/ServerServiceDefinition$Builder.build:()Lio/grpc/ServerServiceDefinition;
      27: areturn
}
