Compiled from "DubboCertificateServiceGrpc.java"
abstract class org.apache.dubbo.auth.v1alpha1.DubboCertificateServiceGrpc$DubboCertificateServiceBaseDescriptorSupplier implements io.grpc.protobuf.ProtoFileDescriptorSupplier,io.grpc.protobuf.ProtoServiceDescriptorSupplier {
  org.apache.dubbo.auth.v1alpha1.DubboCertificateServiceGrpc$DubboCertificateServiceBaseDescriptorSupplier();
    Code:
       0: aload_0
       1: invokespecial #1                  // Method java/lang/Object."<init>":()V
       4: return

  public com.google.protobuf.Descriptors$FileDescriptor getFileDescriptor();
    Code:
       0: invokestatic  #2                  // Method org/apache/dubbo/auth/v1alpha1/Ca.getDescriptor:()Lcom/google/protobuf/Descriptors$FileDescriptor;
       3: areturn

  public com.google.protobuf.Descriptors$ServiceDescriptor getServiceDescriptor();
    Code:
       0: aload_0
       1: invokevirtual #3                  // Method getFileDescriptor:()Lcom/google/protobuf/Descriptors$FileDescriptor;
       4: ldc           #4                  // String DubboCertificateService
       6: invokevirtual #5                  // Method com/google/protobuf/Descriptors$FileDescriptor.findServiceByName:(Ljava/lang/String;)Lcom/google/protobuf/Descriptors$ServiceDescriptor;
       9: areturn
}
