Compiled from "DubboCertificateServiceGrpc.java"
public final class org.apache.dubbo.auth.v1alpha1.DubboCertificateServiceGrpc$DubboCertificateServiceBlockingStub extends io.grpc.stub.AbstractBlockingStub<org.apache.dubbo.auth.v1alpha1.DubboCertificateServiceGrpc$DubboCertificateServiceBlockingStub> {
  private org.apache.dubbo.auth.v1alpha1.DubboCertificateServiceGrpc$DubboCertificateServiceBlockingStub(io.grpc.Channel, io.grpc.CallOptions);
    Code:
       0: aload_0
       1: aload_1
       2: aload_2
       3: invokespecial #2                  // Method io/grpc/stub/AbstractBlockingStub."<init>":(Lio/grpc/Channel;Lio/grpc/CallOptions;)V
       6: return

  protected org.apache.dubbo.auth.v1alpha1.DubboCertificateServiceGrpc$DubboCertificateServiceBlockingStub build(io.grpc.Channel, io.grpc.CallOptions);
    Code:
       0: new           #3                  // class org/apache/dubbo/auth/v1alpha1/DubboCertificateServiceGrpc$DubboCertificateServiceBlockingStub
       3: dup
       4: aload_1
       5: aload_2
       6: invokespecial #1                  // Method "<init>":(Lio/grpc/Channel;Lio/grpc/CallOptions;)V
       9: areturn

  public org.apache.dubbo.auth.v1alpha1.DubboCertificateResponse createCertificate(org.apache.dubbo.auth.v1alpha1.DubboCertificateRequest);
    Code:
       0: aload_0
       1: invokevirtual #4                  // Method getChannel:()Lio/grpc/Channel;
       4: invokestatic  #5                  // Method org/apache/dubbo/auth/v1alpha1/DubboCertificateServiceGrpc.getCreateCertificateMethod:()Lio/grpc/MethodDescriptor;
       7: aload_0
       8: invokevirtual #6                  // Method getCallOptions:()Lio/grpc/CallOptions;
      11: aload_1
      12: invokestatic  #7                  // Method io/grpc/stub/ClientCalls.blockingUnaryCall:(Lio/grpc/Channel;Lio/grpc/MethodDescriptor;Lio/grpc/CallOptions;Ljava/lang/Object;)Ljava/lang/Object;
      15: checkcast     #8                  // class org/apache/dubbo/auth/v1alpha1/DubboCertificateResponse
      18: areturn

  protected io.grpc.stub.AbstractStub build(io.grpc.Channel, io.grpc.CallOptions);
    Code:
       0: aload_0
       1: aload_1
       2: aload_2
       3: invokevirtual #9                  // Method build:(Lio/grpc/Channel;Lio/grpc/CallOptions;)Lorg/apache/dubbo/auth/v1alpha1/DubboCertificateServiceGrpc$DubboCertificateServiceBlockingStub;
       6: areturn

  org.apache.dubbo.auth.v1alpha1.DubboCertificateServiceGrpc$DubboCertificateServiceBlockingStub(io.grpc.Channel, io.grpc.CallOptions, org.apache.dubbo.auth.v1alpha1.DubboCertificateServiceGrpc$1);
    Code:
       0: aload_0
       1: aload_1
       2: aload_2
       3: invokespecial #1                  // Method "<init>":(Lio/grpc/Channel;Lio/grpc/CallOptions;)V
       6: return
}
