Compiled from "DubboCertificateResponse.java"
public final class org.apache.dubbo.auth.v1alpha1.DubboCertificateResponse$Builder extends com.google.protobuf.GeneratedMessageV3$Builder<org.apache.dubbo.auth.v1alpha1.DubboCertificateResponse$Builder> implements org.apache.dubbo.auth.v1alpha1.DubboCertificateResponseOrBuilder {
  private int bitField0_;

  private boolean success_;

  private java.lang.Object certPem_;

  private com.google.protobuf.LazyStringArrayList trustCerts_;

  private long expireTime_;

  private java.lang.Object message_;

  public static final com.google.protobuf.Descriptors$Descriptor getDescriptor();
    Code:
       0: getstatic     #3                  // Field org/apache/dubbo/auth/v1alpha1/Ca.internal_static_org_apache_dubbo_auth_v1alpha1_DubboCertificateResponse_descriptor:Lcom/google/protobuf/Descriptors$Descriptor;
       3: areturn

  protected com.google.protobuf.GeneratedMessageV3$FieldAccessorTable internalGetFieldAccessorTable();
    Code:
       0: getstatic     #4                  // Field org/apache/dubbo/auth/v1alpha1/Ca.internal_static_org_apache_dubbo_auth_v1alpha1_DubboCertificateResponse_fieldAccessorTable:Lcom/google/protobuf/GeneratedMessageV3$FieldAccessorTable;
       3: ldc           #5                  // class org/apache/dubbo/auth/v1alpha1/DubboCertificateResponse
       5: ldc           #6                  // class org/apache/dubbo/auth/v1alpha1/DubboCertificateResponse$Builder
       7: invokevirtual #7                  // Method com/google/protobuf/GeneratedMessageV3$FieldAccessorTable.ensureFieldAccessorsInitialized:(Ljava/lang/Class;Ljava/lang/Class;)Lcom/google/protobuf/GeneratedMessageV3$FieldAccessorTable;
      10: areturn

  private org.apache.dubbo.auth.v1alpha1.DubboCertificateResponse$Builder();
    Code:
       0: aload_0
       1: invokespecial #8                  // Method com/google/protobuf/GeneratedMessageV3$Builder."<init>":()V
       4: aload_0
       5: ldc           #9                  // String
       7: putfield      #10                 // Field certPem_:Ljava/lang/Object;
      10: aload_0
      11: invokestatic  #11                 // Method com/google/protobuf/LazyStringArrayList.emptyList:()Lcom/google/protobuf/LazyStringArrayList;
      14: putfield      #12                 // Field trustCerts_:Lcom/google/protobuf/LazyStringArrayList;
      17: aload_0
      18: ldc           #9                  // String
      20: putfield      #13                 // Field message_:Ljava/lang/Object;
      23: return

  private org.apache.dubbo.auth.v1alpha1.DubboCertificateResponse$Builder(com.google.protobuf.GeneratedMessageV3$BuilderParent);
    Code:
       0: aload_0
       1: aload_1
       2: invokespecial #14                 // Method com/google/protobuf/GeneratedMessageV3$Builder."<init>":(Lcom/google/protobuf/GeneratedMessageV3$BuilderParent;)V
       5: aload_0
       6: ldc           #9                  // String
       8: putfield      #10                 // Field certPem_:Ljava/lang/Object;
      11: aload_0
      12: invokestatic  #11                 // Method com/google/protobuf/LazyStringArrayList.emptyList:()Lcom/google/protobuf/LazyStringArrayList;
      15: putfield      #12                 // Field trustCerts_:Lcom/google/protobuf/LazyStringArrayList;
      18: aload_0
      19: ldc           #9                  // String
      21: putfield      #13                 // Field message_:Ljava/lang/Object;
      24: return

  public org.apache.dubbo.auth.v1alpha1.DubboCertificateResponse$Builder clear();
    Code:
       0: aload_0
       1: invokespecial #15                 // Method com/google/protobuf/GeneratedMessageV3$Builder.clear:()Lcom/google/protobuf/GeneratedMessageV3$Builder;
       4: pop
       5: aload_0
       6: iconst_0
       7: putfield      #16                 // Field bitField0_:I
      10: aload_0
      11: iconst_0
      12: putfield      #17                 // Field success_:Z
      15: aload_0
      16: ldc           #9                  // String
      18: putfield      #10                 // Field certPem_:Ljava/lang/Object;
      21: aload_0
      22: invokestatic  #11                 // Method com/google/protobuf/LazyStringArrayList.emptyList:()Lcom/google/protobuf/LazyStringArrayList;
      25: putfield      #12                 // Field trustCerts_:Lcom/google/protobuf/LazyStringArrayList;
      28: aload_0
      29: lconst_0
      30: putfield      #18                 // Field expireTime_:J
      33: aload_0
      34: ldc           #9                  // String
      36: putfield      #13                 // Field message_:Ljava/lang/Object;
      39: aload_0
      40: areturn

  public com.google.protobuf.Descriptors$Descriptor getDescriptorForType();
    Code:
       0: getstatic     #3                  // Field org/apache/dubbo/auth/v1alpha1/Ca.internal_static_org_apache_dubbo_auth_v1alpha1_DubboCertificateResponse_descriptor:Lcom/google/protobuf/Descriptors$Descriptor;
       3: areturn

  public org.apache.dubbo.auth.v1alpha1.DubboCertificateResponse getDefaultInstanceForType();
    Code:
       0: invokestatic  #19                 // Method org/apache/dubbo/auth/v1alpha1/DubboCertificateResponse.getDefaultInstance:()Lorg/apache/dubbo/auth/v1alpha1/DubboCertificateResponse;
       3: areturn

  public org.apache.dubbo.auth.v1alpha1.DubboCertificateResponse build();
    Code:
       0: aload_0
       1: invokevirtual #20                 // Method buildPartial:()Lorg/apache/dubbo/auth/v1alpha1/DubboCertificateResponse;
       4: astore_1
       5: aload_1
       6: invokevirtual #21                 // Method org/apache/dubbo/auth/v1alpha1/DubboCertificateResponse.isInitialized:()Z
       9: ifne          17
      12: aload_1
      13: invokestatic  #22                 // Method newUninitializedMessageException:(Lcom/google/protobuf/Message;)Lcom/google/protobuf/UninitializedMessageException;
      16: athrow
      17: aload_1
      18: areturn

  public org.apache.dubbo.auth.v1alpha1.DubboCertificateResponse buildPartial();
    Code:
       0: new           #5                  // class org/apache/dubbo/auth/v1alpha1/DubboCertificateResponse
       3: dup
       4: aload_0
       5: aconst_null
       6: invokespecial #23                 // Method org/apache/dubbo/auth/v1alpha1/DubboCertificateResponse."<init>":(Lcom/google/protobuf/GeneratedMessageV3$Builder;Lorg/apache/dubbo/auth/v1alpha1/DubboCertificateResponse$1;)V
       9: astore_1
      10: aload_0
      11: getfield      #16                 // Field bitField0_:I
      14: ifeq          22
      17: aload_0
      18: aload_1
      19: invokespecial #24                 // Method buildPartial0:(Lorg/apache/dubbo/auth/v1alpha1/DubboCertificateResponse;)V
      22: aload_0
      23: invokevirtual #25                 // Method onBuilt:()V
      26: aload_1
      27: areturn

  private void buildPartial0(org.apache.dubbo.auth.v1alpha1.DubboCertificateResponse);
    Code:
       0: aload_0
       1: getfield      #16                 // Field bitField0_:I
       4: istore_2
       5: iload_2
       6: iconst_1
       7: iand
       8: ifeq          20
      11: aload_1
      12: aload_0
      13: getfield      #17                 // Field success_:Z
      16: invokestatic  #26                 // Method org/apache/dubbo/auth/v1alpha1/DubboCertificateResponse.access$302:(Lorg/apache/dubbo/auth/v1alpha1/DubboCertificateResponse;Z)Z
      19: pop
      20: iload_2
      21: iconst_2
      22: iand
      23: ifeq          35
      26: aload_1
      27: aload_0
      28: getfield      #10                 // Field certPem_:Ljava/lang/Object;
      31: invokestatic  #27                 // Method org/apache/dubbo/auth/v1alpha1/DubboCertificateResponse.access$402:(Lorg/apache/dubbo/auth/v1alpha1/DubboCertificateResponse;Ljava/lang/Object;)Ljava/lang/Object;
      34: pop
      35: iload_2
      36: iconst_4
      37: iand
      38: ifeq          57
      41: aload_0
      42: getfield      #12                 // Field trustCerts_:Lcom/google/protobuf/LazyStringArrayList;
      45: invokevirtual #28                 // Method com/google/protobuf/LazyStringArrayList.makeImmutable:()V
      48: aload_1
      49: aload_0
      50: getfield      #12                 // Field trustCerts_:Lcom/google/protobuf/LazyStringArrayList;
      53: invokestatic  #29                 // Method org/apache/dubbo/auth/v1alpha1/DubboCertificateResponse.access$502:(Lorg/apache/dubbo/auth/v1alpha1/DubboCertificateResponse;Lcom/google/protobuf/LazyStringArrayList;)Lcom/google/protobuf/LazyStringArrayList;
      56: pop
      57: iload_2
      58: bipush        8
      60: iand
      61: ifeq          73
      64: aload_1
      65: aload_0
      66: getfield      #18                 // Field expireTime_:J
      69: invokestatic  #30                 // Method org/apache/dubbo/auth/v1alpha1/DubboCertificateResponse.access$602:(Lorg/apache/dubbo/auth/v1alpha1/DubboCertificateResponse;J)J
      72: pop2
      73: iload_2
      74: bipush        16
      76: iand
      77: ifeq          89
      80: aload_1
      81: aload_0
      82: getfield      #13                 // Field message_:Ljava/lang/Object;
      85: invokestatic  #31                 // Method org/apache/dubbo/auth/v1alpha1/DubboCertificateResponse.access$702:(Lorg/apache/dubbo/auth/v1alpha1/DubboCertificateResponse;Ljava/lang/Object;)Ljava/lang/Object;
      88: pop
      89: return

  public org.apache.dubbo.auth.v1alpha1.DubboCertificateResponse$Builder mergeFrom(com.google.protobuf.Message);
    Code:
       0: aload_1
       1: instanceof    #5                  // class org/apache/dubbo/auth/v1alpha1/DubboCertificateResponse
       4: ifeq          16
       7: aload_0
       8: aload_1
       9: checkcast     #5                  // class org/apache/dubbo/auth/v1alpha1/DubboCertificateResponse
      12: invokevirtual #32                 // Method mergeFrom:(Lorg/apache/dubbo/auth/v1alpha1/DubboCertificateResponse;)Lorg/apache/dubbo/auth/v1alpha1/DubboCertificateResponse$Builder;
      15: areturn
      16: aload_0
      17: aload_1
      18: invokespecial #33                 // Method com/google/protobuf/GeneratedMessageV3$Builder.mergeFrom:(Lcom/google/protobuf/Message;)Lcom/google/protobuf/AbstractMessage$Builder;
      21: pop
      22: aload_0
      23: areturn

  public org.apache.dubbo.auth.v1alpha1.DubboCertificateResponse$Builder mergeFrom(org.apache.dubbo.auth.v1alpha1.DubboCertificateResponse);
    Code:
       0: aload_1
       1: invokestatic  #19                 // Method org/apache/dubbo/auth/v1alpha1/DubboCertificateResponse.getDefaultInstance:()Lorg/apache/dubbo/auth/v1alpha1/DubboCertificateResponse;
       4: if_acmpne     9
       7: aload_0
       8: areturn
       9: aload_1
      10: invokevirtual #34                 // Method org/apache/dubbo/auth/v1alpha1/DubboCertificateResponse.getSuccess:()Z
      13: ifeq          25
      16: aload_0
      17: aload_1
      18: invokevirtual #34                 // Method org/apache/dubbo/auth/v1alpha1/DubboCertificateResponse.getSuccess:()Z
      21: invokevirtual #35                 // Method setSuccess:(Z)Lorg/apache/dubbo/auth/v1alpha1/DubboCertificateResponse$Builder;
      24: pop
      25: aload_1
      26: invokevirtual #36                 // Method org/apache/dubbo/auth/v1alpha1/DubboCertificateResponse.getCertPem:()Ljava/lang/String;
      29: invokevirtual #37                 // Method java/lang/String.isEmpty:()Z
      32: ifne          57
      35: aload_0
      36: aload_1
      37: invokestatic  #38                 // Method org/apache/dubbo/auth/v1alpha1/DubboCertificateResponse.access$400:(Lorg/apache/dubbo/auth/v1alpha1/DubboCertificateResponse;)Ljava/lang/Object;
      40: putfield      #10                 // Field certPem_:Ljava/lang/Object;
      43: aload_0
      44: dup
      45: getfield      #16                 // Field bitField0_:I
      48: iconst_2
      49: ior
      50: putfield      #16                 // Field bitField0_:I
      53: aload_0
      54: invokevirtual #39                 // Method onChanged:()V
      57: aload_1
      58: invokestatic  #40                 // Method org/apache/dubbo/auth/v1alpha1/DubboCertificateResponse.access$500:(Lorg/apache/dubbo/auth/v1alpha1/DubboCertificateResponse;)Lcom/google/protobuf/LazyStringArrayList;
      61: invokevirtual #41                 // Method com/google/protobuf/LazyStringArrayList.isEmpty:()Z
      64: ifne          118
      67: aload_0
      68: getfield      #12                 // Field trustCerts_:Lcom/google/protobuf/LazyStringArrayList;
      71: invokevirtual #41                 // Method com/google/protobuf/LazyStringArrayList.isEmpty:()Z
      74: ifeq          98
      77: aload_0
      78: aload_1
      79: invokestatic  #40                 // Method org/apache/dubbo/auth/v1alpha1/DubboCertificateResponse.access$500:(Lorg/apache/dubbo/auth/v1alpha1/DubboCertificateResponse;)Lcom/google/protobuf/LazyStringArrayList;
      82: putfield      #12                 // Field trustCerts_:Lcom/google/protobuf/LazyStringArrayList;
      85: aload_0
      86: dup
      87: getfield      #16                 // Field bitField0_:I
      90: iconst_4
      91: ior
      92: putfield      #16                 // Field bitField0_:I
      95: goto          114
      98: aload_0
      99: invokespecial #42                 // Method ensureTrustCertsIsMutable:()V
     102: aload_0
     103: getfield      #12                 // Field trustCerts_:Lcom/google/protobuf/LazyStringArrayList;
     106: aload_1
     107: invokestatic  #40                 // Method org/apache/dubbo/auth/v1alpha1/DubboCertificateResponse.access$500:(Lorg/apache/dubbo/auth/v1alpha1/DubboCertificateResponse;)Lcom/google/protobuf/LazyStringArrayList;
     110: invokevirtual #43                 // Method com/google/protobuf/LazyStringArrayList.addAll:(Ljava/util/Collection;)Z
     113: pop
     114: aload_0
     115: invokevirtual #39                 // Method onChanged:()V
     118: aload_1
     119: invokevirtual #44                 // Method org/apache/dubbo/auth/v1alpha1/DubboCertificateResponse.getExpireTime:()J
     122: lconst_0
     123: lcmp
     124: ifeq          136
     127: aload_0
     128: aload_1
     129: invokevirtual #44                 // Method org/apache/dubbo/auth/v1alpha1/DubboCertificateResponse.getExpireTime:()J
     132: invokevirtual #45                 // Method setExpireTime:(J)Lorg/apache/dubbo/auth/v1alpha1/DubboCertificateResponse$Builder;
     135: pop
     136: aload_1
     137: invokevirtual #46                 // Method org/apache/dubbo/auth/v1alpha1/DubboCertificateResponse.getMessage:()Ljava/lang/String;
     140: invokevirtual #37                 // Method java/lang/String.isEmpty:()Z
     143: ifne          169
     146: aload_0
     147: aload_1
     148: invokestatic  #47                 // Method org/apache/dubbo/auth/v1alpha1/DubboCertificateResponse.access$700:(Lorg/apache/dubbo/auth/v1alpha1/DubboCertificateResponse;)Ljava/lang/Object;
     151: putfield      #13                 // Field message_:Ljava/lang/Object;
     154: aload_0
     155: dup
     156: getfield      #16                 // Field bitField0_:I
     159: bipush        16
     161: ior
     162: putfield      #16                 // Field bitField0_:I
     165: aload_0
     166: invokevirtual #39                 // Method onChanged:()V
     169: aload_0
     170: aload_1
     171: invokevirtual #48                 // Method org/apache/dubbo/auth/v1alpha1/DubboCertificateResponse.getUnknownFields:()Lcom/google/protobuf/UnknownFieldSet;
     174: invokevirtual #49                 // Method mergeUnknownFields:(Lcom/google/protobuf/UnknownFieldSet;)Lorg/apache/dubbo/auth/v1alpha1/DubboCertificateResponse$Builder;
     177: pop
     178: aload_0
     179: invokevirtual #39                 // Method onChanged:()V
     182: aload_0
     183: areturn

  public final boolean isInitialized();
    Code:
       0: iconst_1
       1: ireturn

  public org.apache.dubbo.auth.v1alpha1.DubboCertificateResponse$Builder mergeFrom(com.google.protobuf.CodedInputStream, com.google.protobuf.ExtensionRegistryLite) throws java.io.IOException;
    Code:
       0: aload_2
       1: ifnonnull     12
       4: new           #50                 // class java/lang/NullPointerException
       7: dup
       8: invokespecial #51                 // Method java/lang/NullPointerException."<init>":()V
      11: athrow
      12: iconst_0
      13: istore_3
      14: iload_3
      15: ifne          214
      18: aload_1
      19: invokevirtual #52                 // Method com/google/protobuf/CodedInputStream.readTag:()I
      22: istore        4
      24: iload         4
      26: lookupswitch  { // 6
                     0: 84
                     8: 89
                    18: 110
                    26: 131
                    32: 154
                    42: 176
               default: 198
          }
      84: iconst_1
      85: istore_3
      86: goto          211
      89: aload_0
      90: aload_1
      91: invokevirtual #53                 // Method com/google/protobuf/CodedInputStream.readBool:()Z
      94: putfield      #17                 // Field success_:Z
      97: aload_0
      98: dup
      99: getfield      #16                 // Field bitField0_:I
     102: iconst_1
     103: ior
     104: putfield      #16                 // Field bitField0_:I
     107: goto          211
     110: aload_0
     111: aload_1
     112: invokevirtual #54                 // Method com/google/protobuf/CodedInputStream.readStringRequireUtf8:()Ljava/lang/String;
     115: putfield      #10                 // Field certPem_:Ljava/lang/Object;
     118: aload_0
     119: dup
     120: getfield      #16                 // Field bitField0_:I
     123: iconst_2
     124: ior
     125: putfield      #16                 // Field bitField0_:I
     128: goto          211
     131: aload_1
     132: invokevirtual #54                 // Method com/google/protobuf/CodedInputStream.readStringRequireUtf8:()Ljava/lang/String;
     135: astore        5
     137: aload_0
     138: invokespecial #42                 // Method ensureTrustCertsIsMutable:()V
     141: aload_0
     142: getfield      #12                 // Field trustCerts_:Lcom/google/protobuf/LazyStringArrayList;
     145: aload         5
     147: invokevirtual #55                 // Method com/google/protobuf/LazyStringArrayList.add:(Ljava/lang/Object;)Z
     150: pop
     151: goto          211
     154: aload_0
     155: aload_1
     156: invokevirtual #56                 // Method com/google/protobuf/CodedInputStream.readInt64:()J
     159: putfield      #18                 // Field expireTime_:J
     162: aload_0
     163: dup
     164: getfield      #16                 // Field bitField0_:I
     167: bipush        8
     169: ior
     170: putfield      #16                 // Field bitField0_:I
     173: goto          211
     176: aload_0
     177: aload_1
     178: invokevirtual #54                 // Method com/google/protobuf/CodedInputStream.readStringRequireUtf8:()Ljava/lang/String;
     181: putfield      #13                 // Field message_:Ljava/lang/Object;
     184: aload_0
     185: dup
     186: getfield      #16                 // Field bitField0_:I
     189: bipush        16
     191: ior
     192: putfield      #16                 // Field bitField0_:I
     195: goto          211
     198: aload_0
     199: aload_1
     200: aload_2
     201: iload         4
     203: invokespecial #57                 // Method com/google/protobuf/GeneratedMessageV3$Builder.parseUnknownField:(Lcom/google/protobuf/CodedInputStream;Lcom/google/protobuf/ExtensionRegistryLite;I)Z
     206: ifne          211
     209: iconst_1
     210: istore_3
     211: goto          14
     214: aload_0
     215: invokevirtual #39                 // Method onChanged:()V
     218: goto          236
     221: astore_3
     222: aload_3
     223: invokevirtual #59                 // Method com/google/protobuf/InvalidProtocolBufferException.unwrapIOException:()Ljava/io/IOException;
     226: athrow
     227: astore        6
     229: aload_0
     230: invokevirtual #39                 // Method onChanged:()V
     233: aload         6
     235: athrow
     236: aload_0
     237: areturn
    Exception table:
       from    to  target type
          12   214   221   Class com/google/protobuf/InvalidProtocolBufferException
          12   214   227   any
         221   229   227   any

  public boolean getSuccess();
    Code:
       0: aload_0
       1: getfield      #17                 // Field success_:Z
       4: ireturn

  public org.apache.dubbo.auth.v1alpha1.DubboCertificateResponse$Builder setSuccess(boolean);
    Code:
       0: aload_0
       1: iload_1
       2: putfield      #17                 // Field success_:Z
       5: aload_0
       6: dup
       7: getfield      #16                 // Field bitField0_:I
      10: iconst_1
      11: ior
      12: putfield      #16                 // Field bitField0_:I
      15: aload_0
      16: invokevirtual #39                 // Method onChanged:()V
      19: aload_0
      20: areturn

  public org.apache.dubbo.auth.v1alpha1.DubboCertificateResponse$Builder clearSuccess();
    Code:
       0: aload_0
       1: aload_0
       2: getfield      #16                 // Field bitField0_:I
       5: bipush        -2
       7: iand
       8: putfield      #16                 // Field bitField0_:I
      11: aload_0
      12: iconst_0
      13: putfield      #17                 // Field success_:Z
      16: aload_0
      17: invokevirtual #39                 // Method onChanged:()V
      20: aload_0
      21: areturn

  public java.lang.String getCertPem();
    Code:
       0: aload_0
       1: getfield      #10                 // Field certPem_:Ljava/lang/Object;
       4: astore_1
       5: aload_1
       6: instanceof    #60                 // class java/lang/String
       9: ifne          29
      12: aload_1
      13: checkcast     #61                 // class com/google/protobuf/ByteString
      16: astore_2
      17: aload_2
      18: invokevirtual #62                 // Method com/google/protobuf/ByteString.toStringUtf8:()Ljava/lang/String;
      21: astore_3
      22: aload_0
      23: aload_3
      24: putfield      #10                 // Field certPem_:Ljava/lang/Object;
      27: aload_3
      28: areturn
      29: aload_1
      30: checkcast     #60                 // class java/lang/String
      33: areturn

  public com.google.protobuf.ByteString getCertPemBytes();
    Code:
       0: aload_0
       1: getfield      #10                 // Field certPem_:Ljava/lang/Object;
       4: astore_1
       5: aload_1
       6: instanceof    #60                 // class java/lang/String
       9: ifeq          27
      12: aload_1
      13: checkcast     #60                 // class java/lang/String
      16: invokestatic  #63                 // Method com/google/protobuf/ByteString.copyFromUtf8:(Ljava/lang/String;)Lcom/google/protobuf/ByteString;
      19: astore_2
      20: aload_0
      21: aload_2
      22: putfield      #10                 // Field certPem_:Ljava/lang/Object;
      25: aload_2
      26: areturn
      27: aload_1
      28: checkcast     #61                 // class com/google/protobuf/ByteString
      31: areturn

  public org.apache.dubbo.auth.v1alpha1.DubboCertificateResponse$Builder setCertPem(java.lang.String);
    Code:
       0: aload_1
       1: ifnonnull     12
       4: new           #50                 // class java/lang/NullPointerException
       7: dup
       8: invokespecial #51                 // Method java/lang/NullPointerException."<init>":()V
      11: athrow
      12: aload_0
      13: aload_1
      14: putfield      #10                 // Field certPem_:Ljava/lang/Object;
      17: aload_0
      18: dup
      19: getfield      #16                 // Field bitField0_:I
      22: iconst_2
      23: ior
      24: putfield      #16                 // Field bitField0_:I
      27: aload_0
      28: invokevirtual #39                 // Method onChanged:()V
      31: aload_0
      32: areturn

  public org.apache.dubbo.auth.v1alpha1.DubboCertificateResponse$Builder clearCertPem();
    Code:
       0: aload_0
       1: invokestatic  #19                 // Method org/apache/dubbo/auth/v1alpha1/DubboCertificateResponse.getDefaultInstance:()Lorg/apache/dubbo/auth/v1alpha1/DubboCertificateResponse;
       4: invokevirtual #36                 // Method org/apache/dubbo/auth/v1alpha1/DubboCertificateResponse.getCertPem:()Ljava/lang/String;
       7: putfield      #10                 // Field certPem_:Ljava/lang/Object;
      10: aload_0
      11: aload_0
      12: getfield      #16                 // Field bitField0_:I
      15: bipush        -3
      17: iand
      18: putfield      #16                 // Field bitField0_:I
      21: aload_0
      22: invokevirtual #39                 // Method onChanged:()V
      25: aload_0
      26: areturn

  public org.apache.dubbo.auth.v1alpha1.DubboCertificateResponse$Builder setCertPemBytes(com.google.protobuf.ByteString);
    Code:
       0: aload_1
       1: ifnonnull     12
       4: new           #50                 // class java/lang/NullPointerException
       7: dup
       8: invokespecial #51                 // Method java/lang/NullPointerException."<init>":()V
      11: athrow
      12: aload_1
      13: invokestatic  #64                 // Method org/apache/dubbo/auth/v1alpha1/DubboCertificateResponse.access$800:(Lcom/google/protobuf/ByteString;)V
      16: aload_0
      17: aload_1
      18: putfield      #10                 // Field certPem_:Ljava/lang/Object;
      21: aload_0
      22: dup
      23: getfield      #16                 // Field bitField0_:I
      26: iconst_2
      27: ior
      28: putfield      #16                 // Field bitField0_:I
      31: aload_0
      32: invokevirtual #39                 // Method onChanged:()V
      35: aload_0
      36: areturn

  private void ensureTrustCertsIsMutable();
    Code:
       0: aload_0
       1: getfield      #12                 // Field trustCerts_:Lcom/google/protobuf/LazyStringArrayList;
       4: invokevirtual #65                 // Method com/google/protobuf/LazyStringArrayList.isModifiable:()Z
       7: ifne          25
      10: aload_0
      11: new           #66                 // class com/google/protobuf/LazyStringArrayList
      14: dup
      15: aload_0
      16: getfield      #12                 // Field trustCerts_:Lcom/google/protobuf/LazyStringArrayList;
      19: invokespecial #67                 // Method com/google/protobuf/LazyStringArrayList."<init>":(Lcom/google/protobuf/LazyStringList;)V
      22: putfield      #12                 // Field trustCerts_:Lcom/google/protobuf/LazyStringArrayList;
      25: aload_0
      26: dup
      27: getfield      #16                 // Field bitField0_:I
      30: iconst_4
      31: ior
      32: putfield      #16                 // Field bitField0_:I
      35: return

  public com.google.protobuf.ProtocolStringList getTrustCertsList();
    Code:
       0: aload_0
       1: getfield      #12                 // Field trustCerts_:Lcom/google/protobuf/LazyStringArrayList;
       4: invokevirtual #28                 // Method com/google/protobuf/LazyStringArrayList.makeImmutable:()V
       7: aload_0
       8: getfield      #12                 // Field trustCerts_:Lcom/google/protobuf/LazyStringArrayList;
      11: areturn

  public int getTrustCertsCount();
    Code:
       0: aload_0
       1: getfield      #12                 // Field trustCerts_:Lcom/google/protobuf/LazyStringArrayList;
       4: invokevirtual #68                 // Method com/google/protobuf/LazyStringArrayList.size:()I
       7: ireturn

  public java.lang.String getTrustCerts(int);
    Code:
       0: aload_0
       1: getfield      #12                 // Field trustCerts_:Lcom/google/protobuf/LazyStringArrayList;
       4: iload_1
       5: invokevirtual #69                 // Method com/google/protobuf/LazyStringArrayList.get:(I)Ljava/lang/String;
       8: areturn

  public com.google.protobuf.ByteString getTrustCertsBytes(int);
    Code:
       0: aload_0
       1: getfield      #12                 // Field trustCerts_:Lcom/google/protobuf/LazyStringArrayList;
       4: iload_1
       5: invokevirtual #70                 // Method com/google/protobuf/LazyStringArrayList.getByteString:(I)Lcom/google/protobuf/ByteString;
       8: areturn

  public org.apache.dubbo.auth.v1alpha1.DubboCertificateResponse$Builder setTrustCerts(int, java.lang.String);
    Code:
       0: aload_2
       1: ifnonnull     12
       4: new           #50                 // class java/lang/NullPointerException
       7: dup
       8: invokespecial #51                 // Method java/lang/NullPointerException."<init>":()V
      11: athrow
      12: aload_0
      13: invokespecial #42                 // Method ensureTrustCertsIsMutable:()V
      16: aload_0
      17: getfield      #12                 // Field trustCerts_:Lcom/google/protobuf/LazyStringArrayList;
      20: iload_1
      21: aload_2
      22: invokevirtual #71                 // Method com/google/protobuf/LazyStringArrayList.set:(ILjava/lang/String;)Ljava/lang/String;
      25: pop
      26: aload_0
      27: dup
      28: getfield      #16                 // Field bitField0_:I
      31: iconst_4
      32: ior
      33: putfield      #16                 // Field bitField0_:I
      36: aload_0
      37: invokevirtual #39                 // Method onChanged:()V
      40: aload_0
      41: areturn

  public org.apache.dubbo.auth.v1alpha1.DubboCertificateResponse$Builder addTrustCerts(java.lang.String);
    Code:
       0: aload_1
       1: ifnonnull     12
       4: new           #50                 // class java/lang/NullPointerException
       7: dup
       8: invokespecial #51                 // Method java/lang/NullPointerException."<init>":()V
      11: athrow
      12: aload_0
      13: invokespecial #42                 // Method ensureTrustCertsIsMutable:()V
      16: aload_0
      17: getfield      #12                 // Field trustCerts_:Lcom/google/protobuf/LazyStringArrayList;
      20: aload_1
      21: invokevirtual #55                 // Method com/google/protobuf/LazyStringArrayList.add:(Ljava/lang/Object;)Z
      24: pop
      25: aload_0
      26: dup
      27: getfield      #16                 // Field bitField0_:I
      30: iconst_4
      31: ior
      32: putfield      #16                 // Field bitField0_:I
      35: aload_0
      36: invokevirtual #39                 // Method onChanged:()V
      39: aload_0
      40: areturn

  public org.apache.dubbo.auth.v1alpha1.DubboCertificateResponse$Builder addAllTrustCerts(java.lang.Iterable<java.lang.String>);
    Code:
       0: aload_0
       1: invokespecial #42                 // Method ensureTrustCertsIsMutable:()V
       4: aload_1
       5: aload_0
       6: getfield      #12                 // Field trustCerts_:Lcom/google/protobuf/LazyStringArrayList;
       9: invokestatic  #72                 // Method com/google/protobuf/AbstractMessageLite$Builder.addAll:(Ljava/lang/Iterable;Ljava/util/List;)V
      12: aload_0
      13: dup
      14: getfield      #16                 // Field bitField0_:I
      17: iconst_4
      18: ior
      19: putfield      #16                 // Field bitField0_:I
      22: aload_0
      23: invokevirtual #39                 // Method onChanged:()V
      26: aload_0
      27: areturn

  public org.apache.dubbo.auth.v1alpha1.DubboCertificateResponse$Builder clearTrustCerts();
    Code:
       0: aload_0
       1: invokestatic  #11                 // Method com/google/protobuf/LazyStringArrayList.emptyList:()Lcom/google/protobuf/LazyStringArrayList;
       4: putfield      #12                 // Field trustCerts_:Lcom/google/protobuf/LazyStringArrayList;
       7: aload_0
       8: aload_0
       9: getfield      #16                 // Field bitField0_:I
      12: bipush        -5
      14: iand
      15: putfield      #16                 // Field bitField0_:I
      18: aload_0
      19: invokevirtual #39                 // Method onChanged:()V
      22: aload_0
      23: areturn

  public org.apache.dubbo.auth.v1alpha1.DubboCertificateResponse$Builder addTrustCertsBytes(com.google.protobuf.ByteString);
    Code:
       0: aload_1
       1: ifnonnull     12
       4: new           #50                 // class java/lang/NullPointerException
       7: dup
       8: invokespecial #51                 // Method java/lang/NullPointerException."<init>":()V
      11: athrow
      12: aload_1
      13: invokestatic  #73                 // Method org/apache/dubbo/auth/v1alpha1/DubboCertificateResponse.access$900:(Lcom/google/protobuf/ByteString;)V
      16: aload_0
      17: invokespecial #42                 // Method ensureTrustCertsIsMutable:()V
      20: aload_0
      21: getfield      #12                 // Field trustCerts_:Lcom/google/protobuf/LazyStringArrayList;
      24: aload_1
      25: invokevirtual #74                 // Method com/google/protobuf/LazyStringArrayList.add:(Lcom/google/protobuf/ByteString;)V
      28: aload_0
      29: dup
      30: getfield      #16                 // Field bitField0_:I
      33: iconst_4
      34: ior
      35: putfield      #16                 // Field bitField0_:I
      38: aload_0
      39: invokevirtual #39                 // Method onChanged:()V
      42: aload_0
      43: areturn

  public long getExpireTime();
    Code:
       0: aload_0
       1: getfield      #18                 // Field expireTime_:J
       4: lreturn

  public org.apache.dubbo.auth.v1alpha1.DubboCertificateResponse$Builder setExpireTime(long);
    Code:
       0: aload_0
       1: lload_1
       2: putfield      #18                 // Field expireTime_:J
       5: aload_0
       6: dup
       7: getfield      #16                 // Field bitField0_:I
      10: bipush        8
      12: ior
      13: putfield      #16                 // Field bitField0_:I
      16: aload_0
      17: invokevirtual #39                 // Method onChanged:()V
      20: aload_0
      21: areturn

  public org.apache.dubbo.auth.v1alpha1.DubboCertificateResponse$Builder clearExpireTime();
    Code:
       0: aload_0
       1: aload_0
       2: getfield      #16                 // Field bitField0_:I
       5: bipush        -9
       7: iand
       8: putfield      #16                 // Field bitField0_:I
      11: aload_0
      12: lconst_0
      13: putfield      #18                 // Field expireTime_:J
      16: aload_0
      17: invokevirtual #39                 // Method onChanged:()V
      20: aload_0
      21: areturn

  public java.lang.String getMessage();
    Code:
       0: aload_0
       1: getfield      #13                 // Field message_:Ljava/lang/Object;
       4: astore_1
       5: aload_1
       6: instanceof    #60                 // class java/lang/String
       9: ifne          29
      12: aload_1
      13: checkcast     #61                 // class com/google/protobuf/ByteString
      16: astore_2
      17: aload_2
      18: invokevirtual #62                 // Method com/google/protobuf/ByteString.toStringUtf8:()Ljava/lang/String;
      21: astore_3
      22: aload_0
      23: aload_3
      24: putfield      #13                 // Field message_:Ljava/lang/Object;
      27: aload_3
      28: areturn
      29: aload_1
      30: checkcast     #60                 // class java/lang/String
      33: areturn

  public com.google.protobuf.ByteString getMessageBytes();
    Code:
       0: aload_0
       1: getfield      #13                 // Field message_:Ljava/lang/Object;
       4: astore_1
       5: aload_1
       6: instanceof    #60                 // class java/lang/String
       9: ifeq          27
      12: aload_1
      13: checkcast     #60                 // class java/lang/String
      16: invokestatic  #63                 // Method com/google/protobuf/ByteString.copyFromUtf8:(Ljava/lang/String;)Lcom/google/protobuf/ByteString;
      19: astore_2
      20: aload_0
      21: aload_2
      22: putfield      #13                 // Field message_:Ljava/lang/Object;
      25: aload_2
      26: areturn
      27: aload_1
      28: checkcast     #61                 // class com/google/protobuf/ByteString
      31: areturn

  public org.apache.dubbo.auth.v1alpha1.DubboCertificateResponse$Builder setMessage(java.lang.String);
    Code:
       0: aload_1
       1: ifnonnull     12
       4: new           #50                 // class java/lang/NullPointerException
       7: dup
       8: invokespecial #51                 // Method java/lang/NullPointerException."<init>":()V
      11: athrow
      12: aload_0
      13: aload_1
      14: putfield      #13                 // Field message_:Ljava/lang/Object;
      17: aload_0
      18: dup
      19: getfield      #16                 // Field bitField0_:I
      22: bipush        16
      24: ior
      25: putfield      #16                 // Field bitField0_:I
      28: aload_0
      29: invokevirtual #39                 // Method onChanged:()V
      32: aload_0
      33: areturn

  public org.apache.dubbo.auth.v1alpha1.DubboCertificateResponse$Builder clearMessage();
    Code:
       0: aload_0
       1: invokestatic  #19                 // Method org/apache/dubbo/auth/v1alpha1/DubboCertificateResponse.getDefaultInstance:()Lorg/apache/dubbo/auth/v1alpha1/DubboCertificateResponse;
       4: invokevirtual #46                 // Method org/apache/dubbo/auth/v1alpha1/DubboCertificateResponse.getMessage:()Ljava/lang/String;
       7: putfield      #13                 // Field message_:Ljava/lang/Object;
      10: aload_0
      11: aload_0
      12: getfield      #16                 // Field bitField0_:I
      15: bipush        -17
      17: iand
      18: putfield      #16                 // Field bitField0_:I
      21: aload_0
      22: invokevirtual #39                 // Method onChanged:()V
      25: aload_0
      26: areturn

  public org.apache.dubbo.auth.v1alpha1.DubboCertificateResponse$Builder setMessageBytes(com.google.protobuf.ByteString);
    Code:
       0: aload_1
       1: ifnonnull     12
       4: new           #50                 // class java/lang/NullPointerException
       7: dup
       8: invokespecial #51                 // Method java/lang/NullPointerException."<init>":()V
      11: athrow
      12: aload_1
      13: invokestatic  #75                 // Method org/apache/dubbo/auth/v1alpha1/DubboCertificateResponse.access$1000:(Lcom/google/protobuf/ByteString;)V
      16: aload_0
      17: aload_1
      18: putfield      #13                 // Field message_:Ljava/lang/Object;
      21: aload_0
      22: dup
      23: getfield      #16                 // Field bitField0_:I
      26: bipush        16
      28: ior
      29: putfield      #16                 // Field bitField0_:I
      32: aload_0
      33: invokevirtual #39                 // Method onChanged:()V
      36: aload_0
      37: areturn

  public final org.apache.dubbo.auth.v1alpha1.DubboCertificateResponse$Builder setUnknownFields(com.google.protobuf.UnknownFieldSet);
    Code:
       0: aload_0
       1: aload_1
       2: invokespecial #76                 // Method com/google/protobuf/GeneratedMessageV3$Builder.setUnknownFields:(Lcom/google/protobuf/UnknownFieldSet;)Lcom/google/protobuf/GeneratedMessageV3$Builder;
       5: checkcast     #6                  // class org/apache/dubbo/auth/v1alpha1/DubboCertificateResponse$Builder
       8: areturn

  public final org.apache.dubbo.auth.v1alpha1.DubboCertificateResponse$Builder mergeUnknownFields(com.google.protobuf.UnknownFieldSet);
    Code:
       0: aload_0
       1: aload_1
       2: invokespecial #77                 // Method com/google/protobuf/GeneratedMessageV3$Builder.mergeUnknownFields:(Lcom/google/protobuf/UnknownFieldSet;)Lcom/google/protobuf/GeneratedMessageV3$Builder;
       5: checkcast     #6                  // class org/apache/dubbo/auth/v1alpha1/DubboCertificateResponse$Builder
       8: areturn

  public com.google.protobuf.GeneratedMessageV3$Builder mergeUnknownFields(com.google.protobuf.UnknownFieldSet);
    Code:
       0: aload_0
       1: aload_1
       2: invokevirtual #49                 // Method mergeUnknownFields:(Lcom/google/protobuf/UnknownFieldSet;)Lorg/apache/dubbo/auth/v1alpha1/DubboCertificateResponse$Builder;
       5: areturn

  public com.google.protobuf.GeneratedMessageV3$Builder setUnknownFields(com.google.protobuf.UnknownFieldSet);
    Code:
       0: aload_0
       1: aload_1
       2: invokevirtual #78                 // Method setUnknownFields:(Lcom/google/protobuf/UnknownFieldSet;)Lorg/apache/dubbo/auth/v1alpha1/DubboCertificateResponse$Builder;
       5: areturn

  public com.google.protobuf.GeneratedMessageV3$Builder clear();
    Code:
       0: aload_0
       1: invokevirtual #79                 // Method clear:()Lorg/apache/dubbo/auth/v1alpha1/DubboCertificateResponse$Builder;
       4: areturn

  public com.google.protobuf.AbstractMessage$Builder mergeUnknownFields(com.google.protobuf.UnknownFieldSet);
    Code:
       0: aload_0
       1: aload_1
       2: invokevirtual #49                 // Method mergeUnknownFields:(Lcom/google/protobuf/UnknownFieldSet;)Lorg/apache/dubbo/auth/v1alpha1/DubboCertificateResponse$Builder;
       5: areturn

  public com.google.protobuf.AbstractMessage$Builder mergeFrom(com.google.protobuf.CodedInputStream, com.google.protobuf.ExtensionRegistryLite) throws java.io.IOException;
    Code:
       0: aload_0
       1: aload_1
       2: aload_2
       3: invokevirtual #80                 // Method mergeFrom:(Lcom/google/protobuf/CodedInputStream;Lcom/google/protobuf/ExtensionRegistryLite;)Lorg/apache/dubbo/auth/v1alpha1/DubboCertificateResponse$Builder;
       6: areturn

  public com.google.protobuf.AbstractMessage$Builder mergeFrom(com.google.protobuf.Message);
    Code:
       0: aload_0
       1: aload_1
       2: invokevirtual #81                 // Method mergeFrom:(Lcom/google/protobuf/Message;)Lorg/apache/dubbo/auth/v1alpha1/DubboCertificateResponse$Builder;
       5: areturn

  public com.google.protobuf.AbstractMessage$Builder clear();
    Code:
       0: aload_0
       1: invokevirtual #79                 // Method clear:()Lorg/apache/dubbo/auth/v1alpha1/DubboCertificateResponse$Builder;
       4: areturn

  public com.google.protobuf.Message$Builder mergeUnknownFields(com.google.protobuf.UnknownFieldSet);
    Code:
       0: aload_0
       1: aload_1
       2: invokevirtual #49                 // Method mergeUnknownFields:(Lcom/google/protobuf/UnknownFieldSet;)Lorg/apache/dubbo/auth/v1alpha1/DubboCertificateResponse$Builder;
       5: areturn

  public com.google.protobuf.Message$Builder setUnknownFields(com.google.protobuf.UnknownFieldSet);
    Code:
       0: aload_0
       1: aload_1
       2: invokevirtual #78                 // Method setUnknownFields:(Lcom/google/protobuf/UnknownFieldSet;)Lorg/apache/dubbo/auth/v1alpha1/DubboCertificateResponse$Builder;
       5: areturn

  public com.google.protobuf.Message$Builder mergeFrom(com.google.protobuf.CodedInputStream, com.google.protobuf.ExtensionRegistryLite) throws java.io.IOException;
    Code:
       0: aload_0
       1: aload_1
       2: aload_2
       3: invokevirtual #80                 // Method mergeFrom:(Lcom/google/protobuf/CodedInputStream;Lcom/google/protobuf/ExtensionRegistryLite;)Lorg/apache/dubbo/auth/v1alpha1/DubboCertificateResponse$Builder;
       6: areturn

  public com.google.protobuf.Message buildPartial();
    Code:
       0: aload_0
       1: invokevirtual #20                 // Method buildPartial:()Lorg/apache/dubbo/auth/v1alpha1/DubboCertificateResponse;
       4: areturn

  public com.google.protobuf.Message build();
    Code:
       0: aload_0
       1: invokevirtual #82                 // Method build:()Lorg/apache/dubbo/auth/v1alpha1/DubboCertificateResponse;
       4: areturn

  public com.google.protobuf.Message$Builder mergeFrom(com.google.protobuf.Message);
    Code:
       0: aload_0
       1: aload_1
       2: invokevirtual #81                 // Method mergeFrom:(Lcom/google/protobuf/Message;)Lorg/apache/dubbo/auth/v1alpha1/DubboCertificateResponse$Builder;
       5: areturn

  public com.google.protobuf.Message$Builder clear();
    Code:
       0: aload_0
       1: invokevirtual #79                 // Method clear:()Lorg/apache/dubbo/auth/v1alpha1/DubboCertificateResponse$Builder;
       4: areturn

  public com.google.protobuf.MessageLite$Builder mergeFrom(com.google.protobuf.CodedInputStream, com.google.protobuf.ExtensionRegistryLite) throws java.io.IOException;
    Code:
       0: aload_0
       1: aload_1
       2: aload_2
       3: invokevirtual #80                 // Method mergeFrom:(Lcom/google/protobuf/CodedInputStream;Lcom/google/protobuf/ExtensionRegistryLite;)Lorg/apache/dubbo/auth/v1alpha1/DubboCertificateResponse$Builder;
       6: areturn

  public com.google.protobuf.MessageLite buildPartial();
    Code:
       0: aload_0
       1: invokevirtual #20                 // Method buildPartial:()Lorg/apache/dubbo/auth/v1alpha1/DubboCertificateResponse;
       4: areturn

  public com.google.protobuf.MessageLite build();
    Code:
       0: aload_0
       1: invokevirtual #82                 // Method build:()Lorg/apache/dubbo/auth/v1alpha1/DubboCertificateResponse;
       4: areturn

  public com.google.protobuf.MessageLite$Builder clear();
    Code:
       0: aload_0
       1: invokevirtual #79                 // Method clear:()Lorg/apache/dubbo/auth/v1alpha1/DubboCertificateResponse$Builder;
       4: areturn

  public com.google.protobuf.MessageLite getDefaultInstanceForType();
    Code:
       0: aload_0
       1: invokevirtual #83                 // Method getDefaultInstanceForType:()Lorg/apache/dubbo/auth/v1alpha1/DubboCertificateResponse;
       4: areturn

  public com.google.protobuf.Message getDefaultInstanceForType();
    Code:
       0: aload_0
       1: invokevirtual #83                 // Method getDefaultInstanceForType:()Lorg/apache/dubbo/auth/v1alpha1/DubboCertificateResponse;
       4: areturn

  public com.google.protobuf.AbstractMessageLite$Builder mergeFrom(com.google.protobuf.CodedInputStream, com.google.protobuf.ExtensionRegistryLite) throws java.io.IOException;
    Code:
       0: aload_0
       1: aload_1
       2: aload_2
       3: invokevirtual #80                 // Method mergeFrom:(Lcom/google/protobuf/CodedInputStream;Lcom/google/protobuf/ExtensionRegistryLite;)Lorg/apache/dubbo/auth/v1alpha1/DubboCertificateResponse$Builder;
       6: areturn

  public java.util.List getTrustCertsList();
    Code:
       0: aload_0
       1: invokevirtual #84                 // Method getTrustCertsList:()Lcom/google/protobuf/ProtocolStringList;
       4: areturn

  org.apache.dubbo.auth.v1alpha1.DubboCertificateResponse$Builder(org.apache.dubbo.auth.v1alpha1.DubboCertificateResponse$1);
    Code:
       0: aload_0
       1: invokespecial #2                  // Method "<init>":()V
       4: return

  org.apache.dubbo.auth.v1alpha1.DubboCertificateResponse$Builder(com.google.protobuf.GeneratedMessageV3$BuilderParent, org.apache.dubbo.auth.v1alpha1.DubboCertificateResponse$1);
    Code:
       0: aload_0
       1: aload_1
       2: invokespecial #1                  // Method "<init>":(Lcom/google/protobuf/GeneratedMessageV3$BuilderParent;)V
       5: return
}
