Compiled from "Suppliers.java"
class com.google.common.base.Suppliers$NonSerializableMemoizingSupplier<T> implements com.google.common.base.Supplier<T> {
  private static final com.google.common.base.Supplier<java.lang.Void> SUCCESSFULLY_COMPUTED;

  private volatile com.google.common.base.Supplier<T> delegate;

  private T value;

  com.google.common.base.Suppliers$NonSerializableMemoizingSupplier(com.google.common.base.Supplier<T>);
    Code:
       0: aload_0
       1: invokespecial #1                  // Method java/lang/Object."<init>":()V
       4: aload_0
       5: aload_1
       6: invokestatic  #2                  // Method com/google/common/base/Preconditions.checkNotNull:(Ljava/lang/Object;)Ljava/lang/Object;
       9: checkcast     #3                  // class com/google/common/base/Supplier
      12: putfield      #4                  // Field delegate:Lcom/google/common/base/Supplier;
      15: return

  public T get();
    Code:
       0: aload_0
       1: getfield      #4                  // Field delegate:Lcom/google/common/base/Supplier;
       4: getstatic     #5                  // Field SUCCESSFULLY_COMPUTED:Lcom/google/common/base/Supplier;
       7: if_acmpeq     60
      10: aload_0
      11: dup
      12: astore_1
      13: monitorenter
      14: aload_0
      15: getfield      #4                  // Field delegate:Lcom/google/common/base/Supplier;
      18: getstatic     #5                  // Field SUCCESSFULLY_COMPUTED:Lcom/google/common/base/Supplier;
      21: if_acmpeq     50
      24: aload_0
      25: getfield      #4                  // Field delegate:Lcom/google/common/base/Supplier;
      28: invokeinterface #6,  1            // InterfaceMethod com/google/common/base/Supplier.get:()Ljava/lang/Object;
      33: astore_2
      34: aload_0
      35: aload_2
      36: putfield      #7                  // Field value:Ljava/lang/Object;
      39: aload_0
      40: getstatic     #5                  // Field SUCCESSFULLY_COMPUTED:Lcom/google/common/base/Supplier;
      43: putfield      #4                  // Field delegate:Lcom/google/common/base/Supplier;
      46: aload_2
      47: aload_1
      48: monitorexit
      49: areturn
      50: aload_1
      51: monitorexit
      52: goto          60
      55: astore_3
      56: aload_1
      57: monitorexit
      58: aload_3
      59: athrow
      60: aload_0
      61: getfield      #7                  // Field value:Ljava/lang/Object;
      64: invokestatic  #8                  // Method com/google/common/base/NullnessCasts.uncheckedCastNullableTToT:(Ljava/lang/Object;)Ljava/lang/Object;
      67: areturn
    Exception table:
       from    to  target type
          14    49    55   any
          50    52    55   any
          55    58    55   any

  public java.lang.String toString();
    Code:
       0: aload_0
       1: getfield      #4                  // Field delegate:Lcom/google/common/base/Supplier;
       4: astore_1
       5: new           #9                  // class java/lang/StringBuilder
       8: dup
       9: invokespecial #10                 // Method java/lang/StringBuilder."<init>":()V
      12: ldc           #11                 // String Suppliers.memoize(
      14: invokevirtual #12                 // Method java/lang/StringBuilder.append:(Ljava/lang/String;)Ljava/lang/StringBuilder;
      17: aload_1
      18: getstatic     #5                  // Field SUCCESSFULLY_COMPUTED:Lcom/google/common/base/Supplier;
      21: if_acmpne     54
      24: new           #9                  // class java/lang/StringBuilder
      27: dup
      28: invokespecial #10                 // Method java/lang/StringBuilder."<init>":()V
      31: ldc           #13                 // String <supplier that returned
      33: invokevirtual #12                 // Method java/lang/StringBuilder.append:(Ljava/lang/String;)Ljava/lang/StringBuilder;
      36: aload_0
      37: getfield      #7                  // Field value:Ljava/lang/Object;
      40: invokevirtual #14                 // Method java/lang/StringBuilder.append:(Ljava/lang/Object;)Ljava/lang/StringBuilder;
      43: ldc           #15                 // String >
      45: invokevirtual #12                 // Method java/lang/StringBuilder.append:(Ljava/lang/String;)Ljava/lang/StringBuilder;
      48: invokevirtual #16                 // Method java/lang/StringBuilder.toString:()Ljava/lang/String;
      51: goto          55
      54: aload_1
      55: invokevirtual #14                 // Method java/lang/StringBuilder.append:(Ljava/lang/Object;)Ljava/lang/StringBuilder;
      58: ldc           #17                 // String )
      60: invokevirtual #12                 // Method java/lang/StringBuilder.append:(Ljava/lang/String;)Ljava/lang/StringBuilder;
      63: invokevirtual #16                 // Method java/lang/StringBuilder.toString:()Ljava/lang/String;
      66: areturn

  private static java.lang.Void lambda$static$0();
    Code:
       0: new           #18                 // class java/lang/IllegalStateException
       3: dup
       4: invokespecial #19                 // Method java/lang/IllegalStateException."<init>":()V
       7: athrow

  static {};
    Code:
       0: invokedynamic #20,  0             // InvokeDynamic #0:get:()Lcom/google/common/base/Supplier;
       5: putstatic     #5                  // Field SUCCESSFULLY_COMPUTED:Lcom/google/common/base/Supplier;
       8: return
}
