Compiled from "AdaptiveLoadBalance.java"
public class org.apache.dubbo.rpc.cluster.loadbalance.AdaptiveLoadBalance extends org.apache.dubbo.rpc.cluster.loadbalance.AbstractLoadBalance {
  public static final java.lang.String NAME;

  private java.lang.String attachmentKey;

  private final org.apache.dubbo.rpc.AdaptiveMetrics adaptiveMetrics;

  public org.apache.dubbo.rpc.cluster.loadbalance.AdaptiveLoadBalance(org.apache.dubbo.rpc.model.ApplicationModel);
    Code:
       0: aload_0
       1: invokespecial #2                  // Method org/apache/dubbo/rpc/cluster/loadbalance/AbstractLoadBalance."<init>":()V
       4: aload_0
       5: ldc           #3                  // String mem,load
       7: putfield      #4                  // Field attachmentKey:Ljava/lang/String;
      10: aload_0
      11: aload_1
      12: invokevirtual #5                  // Method org/apache/dubbo/rpc/model/ApplicationModel.getBeanFactory:()Lorg/apache/dubbo/common/beans/factory/ScopeBeanFactory;
      15: ldc           #6                  // class org/apache/dubbo/rpc/AdaptiveMetrics
      17: invokevirtual #7                  // Method org/apache/dubbo/common/beans/factory/ScopeBeanFactory.getBean:(Ljava/lang/Class;)Ljava/lang/Object;
      20: checkcast     #6                  // class org/apache/dubbo/rpc/AdaptiveMetrics
      23: putfield      #8                  // Field adaptiveMetrics:Lorg/apache/dubbo/rpc/AdaptiveMetrics;
      26: return

  protected <T> org.apache.dubbo.rpc.Invoker<T> doSelect(java.util.List<org.apache.dubbo.rpc.Invoker<T>>, org.apache.dubbo.common.URL, org.apache.dubbo.rpc.Invocation);
    Code:
       0: aload_0
       1: aload_1
       2: aload_3
       3: invokespecial #9                  // Method selectByP2C:(Ljava/util/List;Lorg/apache/dubbo/rpc/Invocation;)Lorg/apache/dubbo/rpc/Invoker;
       6: astore        4
       8: aload_3
       9: ldc           #11                 // String lb_adaptive
      11: aload_0
      12: getfield      #4                  // Field attachmentKey:Ljava/lang/String;
      15: invokeinterface #12,  3           // InterfaceMethod org/apache/dubbo/rpc/Invocation.setAttachment:(Ljava/lang/String;Ljava/lang/String;)V
      20: invokestatic  #13                 // Method java/lang/System.currentTimeMillis:()J
      23: lstore        5
      25: aload_3
      26: invokeinterface #14,  1           // InterfaceMethod org/apache/dubbo/rpc/Invocation.getAttributes:()Ljava/util/Map;
      31: ldc           #15                 // String adaptive_startTime
      33: lload         5
      35: invokestatic  #16                 // Method java/lang/Long.valueOf:(J)Ljava/lang/Long;
      38: invokeinterface #17,  3           // InterfaceMethod java/util/Map.put:(Ljava/lang/Object;Ljava/lang/Object;)Ljava/lang/Object;
      43: pop
      44: aload_3
      45: invokeinterface #14,  1           // InterfaceMethod org/apache/dubbo/rpc/Invocation.getAttributes:()Ljava/util/Map;
      50: ldc           #18                 // String loadbalance
      52: ldc           #20                 // String adaptive
      54: invokeinterface #17,  3           // InterfaceMethod java/util/Map.put:(Ljava/lang/Object;Ljava/lang/Object;)Ljava/lang/Object;
      59: pop
      60: aload_0
      61: getfield      #8                  // Field adaptiveMetrics:Lorg/apache/dubbo/rpc/AdaptiveMetrics;
      64: aload_0
      65: aload         4
      67: aload_3
      68: invokespecial #21                 // Method getServiceKey:(Lorg/apache/dubbo/rpc/Invoker;Lorg/apache/dubbo/rpc/Invocation;)Ljava/lang/String;
      71: invokevirtual #22                 // Method org/apache/dubbo/rpc/AdaptiveMetrics.addConsumerReq:(Ljava/lang/String;)V
      74: aload_0
      75: getfield      #8                  // Field adaptiveMetrics:Lorg/apache/dubbo/rpc/AdaptiveMetrics;
      78: aload_0
      79: aload         4
      81: aload_3
      82: invokespecial #21                 // Method getServiceKey:(Lorg/apache/dubbo/rpc/Invoker;Lorg/apache/dubbo/rpc/Invocation;)Ljava/lang/String;
      85: lload         5
      87: invokevirtual #23                 // Method org/apache/dubbo/rpc/AdaptiveMetrics.setPickTime:(Ljava/lang/String;J)V
      90: aload         4
      92: areturn

  private <T> org.apache.dubbo.rpc.Invoker<T> selectByP2C(java.util.List<org.apache.dubbo.rpc.Invoker<T>>, org.apache.dubbo.rpc.Invocation);
    Code:
       0: aload_1
       1: invokeinterface #24,  1           // InterfaceMethod java/util/List.size:()I
       6: istore_3
       7: iload_3
       8: iconst_1
       9: if_icmpne     23
      12: aload_1
      13: iconst_0
      14: invokeinterface #25,  2           // InterfaceMethod java/util/List.get:(I)Ljava/lang/Object;
      19: checkcast     #26                 // class org/apache/dubbo/rpc/Invoker
      22: areturn
      23: iload_3
      24: iconst_2
      25: if_icmpne     54
      28: aload_0
      29: aload_1
      30: iconst_0
      31: invokeinterface #25,  2           // InterfaceMethod java/util/List.get:(I)Ljava/lang/Object;
      36: checkcast     #26                 // class org/apache/dubbo/rpc/Invoker
      39: aload_1
      40: iconst_1
      41: invokeinterface #25,  2           // InterfaceMethod java/util/List.get:(I)Ljava/lang/Object;
      46: checkcast     #26                 // class org/apache/dubbo/rpc/Invoker
      49: aload_2
      50: invokespecial #27                 // Method chooseLowLoadInvoker:(Lorg/apache/dubbo/rpc/Invoker;Lorg/apache/dubbo/rpc/Invoker;Lorg/apache/dubbo/rpc/Invocation;)Lorg/apache/dubbo/rpc/Invoker;
      53: areturn
      54: invokestatic  #28                 // Method java/util/concurrent/ThreadLocalRandom.current:()Ljava/util/concurrent/ThreadLocalRandom;
      57: iload_3
      58: invokevirtual #29                 // Method java/util/concurrent/ThreadLocalRandom.nextInt:(I)I
      61: istore        4
      63: invokestatic  #28                 // Method java/util/concurrent/ThreadLocalRandom.current:()Ljava/util/concurrent/ThreadLocalRandom;
      66: iload_3
      67: iconst_1
      68: isub
      69: invokevirtual #29                 // Method java/util/concurrent/ThreadLocalRandom.nextInt:(I)I
      72: istore        5
      74: iload         5
      76: iload         4
      78: if_icmplt     87
      81: iload         5
      83: iconst_1
      84: iadd
      85: istore        5
      87: aload_0
      88: aload_1
      89: iload         4
      91: invokeinterface #25,  2           // InterfaceMethod java/util/List.get:(I)Ljava/lang/Object;
      96: checkcast     #26                 // class org/apache/dubbo/rpc/Invoker
      99: aload_1
     100: iload         5
     102: invokeinterface #25,  2           // InterfaceMethod java/util/List.get:(I)Ljava/lang/Object;
     107: checkcast     #26                 // class org/apache/dubbo/rpc/Invoker
     110: aload_2
     111: invokespecial #27                 // Method chooseLowLoadInvoker:(Lorg/apache/dubbo/rpc/Invoker;Lorg/apache/dubbo/rpc/Invoker;Lorg/apache/dubbo/rpc/Invocation;)Lorg/apache/dubbo/rpc/Invoker;
     114: areturn

  private java.lang.String getServiceKey(org.apache.dubbo.rpc.Invoker<?>, org.apache.dubbo.rpc.Invocation);
    Code:
       0: aload_2
       1: invokeinterface #14,  1           // InterfaceMethod org/apache/dubbo/rpc/Invocation.getAttributes:()Ljava/util/Map;
       6: aload_1
       7: invokeinterface #30,  2           // InterfaceMethod java/util/Map.get:(Ljava/lang/Object;)Ljava/lang/Object;
      12: checkcast     #31                 // class java/lang/String
      15: astore_3
      16: aload_3
      17: invokestatic  #32                 // Method org/apache/dubbo/common/utils/StringUtils.isNotEmpty:(Ljava/lang/String;)Z
      20: ifeq          25
      23: aload_3
      24: areturn
      25: aload_0
      26: aload_1
      27: aload_2
      28: invokespecial #33                 // Method buildServiceKey:(Lorg/apache/dubbo/rpc/Invoker;Lorg/apache/dubbo/rpc/Invocation;)Ljava/lang/String;
      31: astore_3
      32: aload_2
      33: invokeinterface #14,  1           // InterfaceMethod org/apache/dubbo/rpc/Invocation.getAttributes:()Ljava/util/Map;
      38: aload_1
      39: aload_3
      40: invokeinterface #17,  3           // InterfaceMethod java/util/Map.put:(Ljava/lang/Object;Ljava/lang/Object;)Ljava/lang/Object;
      45: pop
      46: aload_3
      47: areturn

  private java.lang.String buildServiceKey(org.apache.dubbo.rpc.Invoker<?>, org.apache.dubbo.rpc.Invocation);
    Code:
       0: aload_1
       1: invokeinterface #34,  1           // InterfaceMethod org/apache/dubbo/rpc/Invoker.getUrl:()Lorg/apache/dubbo/common/URL;
       6: astore_3
       7: new           #35                 // class java/lang/StringBuilder
      10: dup
      11: sipush        128
      14: invokespecial #36                 // Method java/lang/StringBuilder."<init>":(I)V
      17: astore        4
      19: aload         4
      21: aload_3
      22: invokevirtual #37                 // Method org/apache/dubbo/common/URL.getAddress:()Ljava/lang/String;
      25: invokevirtual #38                 // Method java/lang/StringBuilder.append:(Ljava/lang/String;)Ljava/lang/StringBuilder;
      28: ldc           #39                 // String :
      30: invokevirtual #38                 // Method java/lang/StringBuilder.append:(Ljava/lang/String;)Ljava/lang/StringBuilder;
      33: aload_2
      34: invokeinterface #40,  1           // InterfaceMethod org/apache/dubbo/rpc/Invocation.getProtocolServiceKey:()Ljava/lang/String;
      39: invokevirtual #38                 // Method java/lang/StringBuilder.append:(Ljava/lang/String;)Ljava/lang/StringBuilder;
      42: pop
      43: aload         4
      45: invokevirtual #41                 // Method java/lang/StringBuilder.toString:()Ljava/lang/String;
      48: areturn

  private int getTimeout(org.apache.dubbo.rpc.Invoker<?>, org.apache.dubbo.rpc.Invocation);
    Code:
       0: aload_1
       1: invokeinterface #34,  1           // InterfaceMethod org/apache/dubbo/rpc/Invoker.getUrl:()Lorg/apache/dubbo/common/URL;
       6: astore_3
       7: aload_2
       8: invokestatic  #42                 // Method org/apache/dubbo/rpc/support/RpcUtils.getMethodName:(Lorg/apache/dubbo/rpc/Invocation;)Ljava/lang/String;
      11: astore        4
      13: aload_3
      14: aload         4
      16: invokestatic  #43                 // Method org/apache/dubbo/rpc/RpcContext.getClientAttachment:()Lorg/apache/dubbo/rpc/RpcContextAttachment;
      19: aload_2
      20: ldc2_w        #44                 // long 1000l
      23: invokestatic  #46                 // Method org/apache/dubbo/rpc/support/RpcUtils.getTimeout:(Lorg/apache/dubbo/common/URL;Ljava/lang/String;Lorg/apache/dubbo/rpc/RpcContext;Lorg/apache/dubbo/rpc/Invocation;J)J
      26: l2i
      27: ireturn

  private <T> org.apache.dubbo.rpc.Invoker<T> chooseLowLoadInvoker(org.apache.dubbo.rpc.Invoker<T>, org.apache.dubbo.rpc.Invoker<T>, org.apache.dubbo.rpc.Invocation);
    Code:
       0: aload_0
       1: aload_1
       2: aload_3
       3: invokevirtual #47                 // Method getWeight:(Lorg/apache/dubbo/rpc/Invoker;Lorg/apache/dubbo/rpc/Invocation;)I
       6: istore        4
       8: aload_0
       9: aload_2
      10: aload_3
      11: invokevirtual #47                 // Method getWeight:(Lorg/apache/dubbo/rpc/Invoker;Lorg/apache/dubbo/rpc/Invocation;)I
      14: istore        5
      16: aload_0
      17: aload_2
      18: aload_3
      19: invokespecial #48                 // Method getTimeout:(Lorg/apache/dubbo/rpc/Invoker;Lorg/apache/dubbo/rpc/Invocation;)I
      22: istore        6
      24: aload_0
      25: aload_2
      26: aload_3
      27: invokespecial #48                 // Method getTimeout:(Lorg/apache/dubbo/rpc/Invoker;Lorg/apache/dubbo/rpc/Invocation;)I
      30: istore        7
      32: aload_0
      33: getfield      #8                  // Field adaptiveMetrics:Lorg/apache/dubbo/rpc/AdaptiveMetrics;
      36: aload_0
      37: aload_1
      38: aload_3
      39: invokespecial #21                 // Method getServiceKey:(Lorg/apache/dubbo/rpc/Invoker;Lorg/apache/dubbo/rpc/Invocation;)Ljava/lang/String;
      42: iload         4
      44: iload         6
      46: invokevirtual #49                 // Method org/apache/dubbo/rpc/AdaptiveMetrics.getLoad:(Ljava/lang/String;II)D
      49: invokestatic  #50                 // Method java/lang/Double.doubleToLongBits:(D)J
      52: lstore        8
      54: aload_0
      55: getfield      #8                  // Field adaptiveMetrics:Lorg/apache/dubbo/rpc/AdaptiveMetrics;
      58: aload_0
      59: aload_2
      60: aload_3
      61: invokespecial #21                 // Method getServiceKey:(Lorg/apache/dubbo/rpc/Invoker;Lorg/apache/dubbo/rpc/Invocation;)Ljava/lang/String;
      64: iload         5
      66: iload         7
      68: invokevirtual #49                 // Method org/apache/dubbo/rpc/AdaptiveMetrics.getLoad:(Ljava/lang/String;II)D
      71: invokestatic  #50                 // Method java/lang/Double.doubleToLongBits:(D)J
      74: lstore        10
      76: lload         8
      78: lload         10
      80: lcmp
      81: ifne          133
      84: iload         4
      86: iload         5
      88: iadd
      89: istore        12
      91: iload         12
      93: ifle          117
      96: invokestatic  #28                 // Method java/util/concurrent/ThreadLocalRandom.current:()Ljava/util/concurrent/ThreadLocalRandom;
      99: iload         12
     101: invokevirtual #29                 // Method java/util/concurrent/ThreadLocalRandom.nextInt:(I)I
     104: istore        13
     106: iload         13
     108: iload         4
     110: if_icmpge     115
     113: aload_1
     114: areturn
     115: aload_2
     116: areturn
     117: invokestatic  #28                 // Method java/util/concurrent/ThreadLocalRandom.current:()Ljava/util/concurrent/ThreadLocalRandom;
     120: iconst_2
     121: invokevirtual #29                 // Method java/util/concurrent/ThreadLocalRandom.nextInt:(I)I
     124: ifne          131
     127: aload_1
     128: goto          132
     131: aload_2
     132: areturn
     133: lload         8
     135: lload         10
     137: lcmp
     138: ifle          145
     141: aload_2
     142: goto          146
     145: aload_1
     146: areturn
}
