Compiled from "ConsistentHashLoadBalance.java"
public class org.apache.dubbo.rpc.cluster.loadbalance.ConsistentHashLoadBalance extends org.apache.dubbo.rpc.cluster.loadbalance.AbstractLoadBalance {
  public static final java.lang.String NAME;

  public static final java.lang.String HASH_NODES;

  public static final java.lang.String HASH_ARGUMENTS;

  private final java.util.concurrent.ConcurrentMap<java.lang.String, org.apache.dubbo.rpc.cluster.loadbalance.ConsistentHashLoadBalance$ConsistentHashSelector<?>> selectors;

  public org.apache.dubbo.rpc.cluster.loadbalance.ConsistentHashLoadBalance();
    Code:
       0: aload_0
       1: invokespecial #1                  // Method org/apache/dubbo/rpc/cluster/loadbalance/AbstractLoadBalance."<init>":()V
       4: aload_0
       5: new           #2                  // class java/util/concurrent/ConcurrentHashMap
       8: dup
       9: invokespecial #3                  // Method java/util/concurrent/ConcurrentHashMap."<init>":()V
      12: putfield      #4                  // Field selectors:Ljava/util/concurrent/ConcurrentMap;
      15: return

  protected <T> org.apache.dubbo.rpc.Invoker<T> doSelect(java.util.List<org.apache.dubbo.rpc.Invoker<T>>, org.apache.dubbo.common.URL, org.apache.dubbo.rpc.Invocation);
    Code:
       0: aload_3
       1: invokestatic  #5                  // Method org/apache/dubbo/rpc/support/RpcUtils.getMethodName:(Lorg/apache/dubbo/rpc/Invocation;)Ljava/lang/String;
       4: astore        4
       6: new           #6                  // class java/lang/StringBuilder
       9: dup
      10: invokespecial #7                  // Method java/lang/StringBuilder."<init>":()V
      13: aload_1
      14: iconst_0
      15: invokeinterface #8,  2            // InterfaceMethod java/util/List.get:(I)Ljava/lang/Object;
      20: checkcast     #9                  // class org/apache/dubbo/rpc/Invoker
      23: invokeinterface #10,  1           // InterfaceMethod org/apache/dubbo/rpc/Invoker.getUrl:()Lorg/apache/dubbo/common/URL;
      28: invokevirtual #11                 // Method org/apache/dubbo/common/URL.getServiceKey:()Ljava/lang/String;
      31: invokevirtual #12                 // Method java/lang/StringBuilder.append:(Ljava/lang/String;)Ljava/lang/StringBuilder;
      34: ldc           #13                 // String .
      36: invokevirtual #12                 // Method java/lang/StringBuilder.append:(Ljava/lang/String;)Ljava/lang/StringBuilder;
      39: aload         4
      41: invokevirtual #12                 // Method java/lang/StringBuilder.append:(Ljava/lang/String;)Ljava/lang/StringBuilder;
      44: invokevirtual #14                 // Method java/lang/StringBuilder.toString:()Ljava/lang/String;
      47: astore        5
      49: aload_1
      50: invokeinterface #15,  1           // InterfaceMethod java/util/List.hashCode:()I
      55: istore        6
      57: aload_0
      58: getfield      #4                  // Field selectors:Ljava/util/concurrent/ConcurrentMap;
      61: aload         5
      63: invokeinterface #16,  2           // InterfaceMethod java/util/concurrent/ConcurrentMap.get:(Ljava/lang/Object;)Ljava/lang/Object;
      68: checkcast     #17                 // class org/apache/dubbo/rpc/cluster/loadbalance/ConsistentHashLoadBalance$ConsistentHashSelector
      71: astore        7
      73: aload         7
      75: ifnull        88
      78: aload         7
      80: invokestatic  #18                 // Method org/apache/dubbo/rpc/cluster/loadbalance/ConsistentHashLoadBalance$ConsistentHashSelector.access$000:(Lorg/apache/dubbo/rpc/cluster/loadbalance/ConsistentHashLoadBalance$ConsistentHashSelector;)I
      83: iload         6
      85: if_icmpeq     128
      88: aload_0
      89: getfield      #4                  // Field selectors:Ljava/util/concurrent/ConcurrentMap;
      92: aload         5
      94: new           #17                 // class org/apache/dubbo/rpc/cluster/loadbalance/ConsistentHashLoadBalance$ConsistentHashSelector
      97: dup
      98: aload_1
      99: aload         4
     101: iload         6
     103: invokespecial #19                 // Method org/apache/dubbo/rpc/cluster/loadbalance/ConsistentHashLoadBalance$ConsistentHashSelector."<init>":(Ljava/util/List;Ljava/lang/String;I)V
     106: invokeinterface #20,  3           // InterfaceMethod java/util/concurrent/ConcurrentMap.put:(Ljava/lang/Object;Ljava/lang/Object;)Ljava/lang/Object;
     111: pop
     112: aload_0
     113: getfield      #4                  // Field selectors:Ljava/util/concurrent/ConcurrentMap;
     116: aload         5
     118: invokeinterface #16,  2           // InterfaceMethod java/util/concurrent/ConcurrentMap.get:(Ljava/lang/Object;)Ljava/lang/Object;
     123: checkcast     #17                 // class org/apache/dubbo/rpc/cluster/loadbalance/ConsistentHashLoadBalance$ConsistentHashSelector
     126: astore        7
     128: aload         7
     130: aload_3
     131: invokevirtual #21                 // Method org/apache/dubbo/rpc/cluster/loadbalance/ConsistentHashLoadBalance$ConsistentHashSelector.select:(Lorg/apache/dubbo/rpc/Invocation;)Lorg/apache/dubbo/rpc/Invoker;
     134: areturn
}
