Compiled from "RoundRobinLoadBalance.java"
public class org.apache.dubbo.rpc.cluster.loadbalance.RoundRobinLoadBalance$WeightedRoundRobin {
  private int weight;

  private final java.util.concurrent.atomic.AtomicLong current;

  private long lastUpdate;

  protected org.apache.dubbo.rpc.cluster.loadbalance.RoundRobinLoadBalance$WeightedRoundRobin();
    Code:
       0: aload_0
       1: invokespecial #1                  // Method java/lang/Object."<init>":()V
       4: aload_0
       5: new           #2                  // class java/util/concurrent/atomic/AtomicLong
       8: dup
       9: lconst_0
      10: invokespecial #3                  // Method java/util/concurrent/atomic/AtomicLong."<init>":(J)V
      13: putfield      #4                  // Field current:Ljava/util/concurrent/atomic/AtomicLong;
      16: return

  public int getWeight();
    Code:
       0: aload_0
       1: getfield      #5                  // Field weight:I
       4: ireturn

  public void setWeight(int);
    Code:
       0: aload_0
       1: iload_1
       2: putfield      #5                  // Field weight:I
       5: aload_0
       6: getfield      #4                  // Field current:Ljava/util/concurrent/atomic/AtomicLong;
       9: lconst_0
      10: invokevirtual #6                  // Method java/util/concurrent/atomic/AtomicLong.set:(J)V
      13: return

  public long increaseCurrent();
    Code:
       0: aload_0
       1: getfield      #4                  // Field current:Ljava/util/concurrent/atomic/AtomicLong;
       4: aload_0
       5: getfield      #5                  // Field weight:I
       8: i2l
       9: invokevirtual #7                  // Method java/util/concurrent/atomic/AtomicLong.addAndGet:(J)J
      12: lreturn

  public void sel(int);
    Code:
       0: aload_0
       1: getfield      #4                  // Field current:Ljava/util/concurrent/atomic/AtomicLong;
       4: iconst_m1
       5: iload_1
       6: imul
       7: i2l
       8: invokevirtual #7                  // Method java/util/concurrent/atomic/AtomicLong.addAndGet:(J)J
      11: pop2
      12: return

  public long getLastUpdate();
    Code:
       0: aload_0
       1: getfield      #8                  // Field lastUpdate:J
       4: lreturn

  public void setLastUpdate(long);
    Code:
       0: aload_0
       1: lload_1
       2: putfield      #8                  // Field lastUpdate:J
       5: return
}
