Compiled from "RoundRobinLoadBalance.java"
public class org.apache.dubbo.rpc.cluster.loadbalance.RoundRobinLoadBalance extends org.apache.dubbo.rpc.cluster.loadbalance.AbstractLoadBalance {
  public static final java.lang.String NAME;

  private static final int RECYCLE_PERIOD;

  private final java.util.concurrent.ConcurrentMap<java.lang.String, java.util.concurrent.ConcurrentMap<java.lang.String, org.apache.dubbo.rpc.cluster.loadbalance.RoundRobinLoadBalance$WeightedRoundRobin>> methodWeightMap;

  public org.apache.dubbo.rpc.cluster.loadbalance.RoundRobinLoadBalance();
    Code:
       0: aload_0
       1: invokespecial #1                  // Method org/apache/dubbo/rpc/cluster/loadbalance/AbstractLoadBalance."<init>":()V
       4: aload_0
       5: new           #2                  // class java/util/concurrent/ConcurrentHashMap
       8: dup
       9: invokespecial #3                  // Method java/util/concurrent/ConcurrentHashMap."<init>":()V
      12: putfield      #4                  // Field methodWeightMap:Ljava/util/concurrent/ConcurrentMap;
      15: return

  protected <T> java.util.Collection<java.lang.String> getInvokerAddrList(java.util.List<org.apache.dubbo.rpc.Invoker<T>>, org.apache.dubbo.rpc.Invocation);
    Code:
       0: new           #5                  // class java/lang/StringBuilder
       3: dup
       4: invokespecial #6                  // Method java/lang/StringBuilder."<init>":()V
       7: aload_1
       8: iconst_0
       9: invokeinterface #7,  2            // InterfaceMethod java/util/List.get:(I)Ljava/lang/Object;
      14: checkcast     #8                  // class org/apache/dubbo/rpc/Invoker
      17: invokeinterface #9,  1            // InterfaceMethod org/apache/dubbo/rpc/Invoker.getUrl:()Lorg/apache/dubbo/common/URL;
      22: invokevirtual #10                 // Method org/apache/dubbo/common/URL.getServiceKey:()Ljava/lang/String;
      25: invokevirtual #11                 // Method java/lang/StringBuilder.append:(Ljava/lang/String;)Ljava/lang/StringBuilder;
      28: ldc           #12                 // String .
      30: invokevirtual #11                 // Method java/lang/StringBuilder.append:(Ljava/lang/String;)Ljava/lang/StringBuilder;
      33: aload_2
      34: invokeinterface #13,  1           // InterfaceMethod org/apache/dubbo/rpc/Invocation.getMethodName:()Ljava/lang/String;
      39: invokevirtual #11                 // Method java/lang/StringBuilder.append:(Ljava/lang/String;)Ljava/lang/StringBuilder;
      42: invokevirtual #14                 // Method java/lang/StringBuilder.toString:()Ljava/lang/String;
      45: astore_3
      46: aload_0
      47: getfield      #4                  // Field methodWeightMap:Ljava/util/concurrent/ConcurrentMap;
      50: aload_3
      51: invokeinterface #15,  2           // InterfaceMethod java/util/concurrent/ConcurrentMap.get:(Ljava/lang/Object;)Ljava/lang/Object;
      56: checkcast     #16                 // class java/util/Map
      59: astore        4
      61: aload         4
      63: ifnull        74
      66: aload         4
      68: invokeinterface #17,  1           // InterfaceMethod java/util/Map.keySet:()Ljava/util/Set;
      73: areturn
      74: aconst_null
      75: areturn

  protected <T> org.apache.dubbo.rpc.Invoker<T> doSelect(java.util.List<org.apache.dubbo.rpc.Invoker<T>>, org.apache.dubbo.common.URL, org.apache.dubbo.rpc.Invocation);
    Code:
       0: new           #5                  // class java/lang/StringBuilder
       3: dup
       4: invokespecial #6                  // Method java/lang/StringBuilder."<init>":()V
       7: aload_1
       8: iconst_0
       9: invokeinterface #7,  2            // InterfaceMethod java/util/List.get:(I)Ljava/lang/Object;
      14: checkcast     #8                  // class org/apache/dubbo/rpc/Invoker
      17: invokeinterface #9,  1            // InterfaceMethod org/apache/dubbo/rpc/Invoker.getUrl:()Lorg/apache/dubbo/common/URL;
      22: invokevirtual #10                 // Method org/apache/dubbo/common/URL.getServiceKey:()Ljava/lang/String;
      25: invokevirtual #11                 // Method java/lang/StringBuilder.append:(Ljava/lang/String;)Ljava/lang/StringBuilder;
      28: ldc           #12                 // String .
      30: invokevirtual #11                 // Method java/lang/StringBuilder.append:(Ljava/lang/String;)Ljava/lang/StringBuilder;
      33: aload_3
      34: invokeinterface #13,  1           // InterfaceMethod org/apache/dubbo/rpc/Invocation.getMethodName:()Ljava/lang/String;
      39: invokevirtual #11                 // Method java/lang/StringBuilder.append:(Ljava/lang/String;)Ljava/lang/StringBuilder;
      42: invokevirtual #14                 // Method java/lang/StringBuilder.toString:()Ljava/lang/String;
      45: astore        4
      47: aload_0
      48: getfield      #4                  // Field methodWeightMap:Ljava/util/concurrent/ConcurrentMap;
      51: aload         4
      53: invokedynamic #18,  0             // InvokeDynamic #0:apply:()Ljava/util/function/Function;
      58: invokestatic  #19                 // Method org/apache/dubbo/common/utils/ConcurrentHashMapUtils.computeIfAbsent:(Ljava/util/concurrent/ConcurrentMap;Ljava/lang/Object;Ljava/util/function/Function;)Ljava/lang/Object;
      61: checkcast     #20                 // class java/util/concurrent/ConcurrentMap
      64: astore        5
      66: iconst_0
      67: istore        6
      69: ldc2_w        #22                 // long -9223372036854775808l
      72: lstore        7
      74: invokestatic  #24                 // Method java/lang/System.currentTimeMillis:()J
      77: lstore        9
      79: aconst_null
      80: astore        11
      82: aconst_null
      83: astore        12
      85: aload_1
      86: invokeinterface #25,  1           // InterfaceMethod java/util/List.iterator:()Ljava/util/Iterator;
      91: astore        13
      93: aload         13
      95: invokeinterface #26,  1           // InterfaceMethod java/util/Iterator.hasNext:()Z
     100: ifeq          216
     103: aload         13
     105: invokeinterface #27,  1           // InterfaceMethod java/util/Iterator.next:()Ljava/lang/Object;
     110: checkcast     #8                  // class org/apache/dubbo/rpc/Invoker
     113: astore        14
     115: aload         14
     117: invokeinterface #9,  1            // InterfaceMethod org/apache/dubbo/rpc/Invoker.getUrl:()Lorg/apache/dubbo/common/URL;
     122: invokevirtual #28                 // Method org/apache/dubbo/common/URL.toIdentityString:()Ljava/lang/String;
     125: astore        15
     127: aload_0
     128: aload         14
     130: aload_3
     131: invokevirtual #29                 // Method getWeight:(Lorg/apache/dubbo/rpc/Invoker;Lorg/apache/dubbo/rpc/Invocation;)I
     134: istore        16
     136: aload         5
     138: aload         15
     140: iload         16
     142: invokedynamic #30,  0             // InvokeDynamic #1:apply:(I)Ljava/util/function/Function;
     147: invokestatic  #19                 // Method org/apache/dubbo/common/utils/ConcurrentHashMapUtils.computeIfAbsent:(Ljava/util/concurrent/ConcurrentMap;Ljava/lang/Object;Ljava/util/function/Function;)Ljava/lang/Object;
     150: checkcast     #31                 // class org/apache/dubbo/rpc/cluster/loadbalance/RoundRobinLoadBalance$WeightedRoundRobin
     153: astore        17
     155: iload         16
     157: aload         17
     159: invokevirtual #32                 // Method org/apache/dubbo/rpc/cluster/loadbalance/RoundRobinLoadBalance$WeightedRoundRobin.getWeight:()I
     162: if_icmpeq     172
     165: aload         17
     167: iload         16
     169: invokevirtual #33                 // Method org/apache/dubbo/rpc/cluster/loadbalance/RoundRobinLoadBalance$WeightedRoundRobin.setWeight:(I)V
     172: aload         17
     174: invokevirtual #34                 // Method org/apache/dubbo/rpc/cluster/loadbalance/RoundRobinLoadBalance$WeightedRoundRobin.increaseCurrent:()J
     177: lstore        18
     179: aload         17
     181: lload         9
     183: invokevirtual #35                 // Method org/apache/dubbo/rpc/cluster/loadbalance/RoundRobinLoadBalance$WeightedRoundRobin.setLastUpdate:(J)V
     186: lload         18
     188: lload         7
     190: lcmp
     191: ifle          206
     194: lload         18
     196: lstore        7
     198: aload         14
     200: astore        11
     202: aload         17
     204: astore        12
     206: iload         6
     208: iload         16
     210: iadd
     211: istore        6
     213: goto          93
     216: aload_1
     217: invokeinterface #36,  1           // InterfaceMethod java/util/List.size:()I
     222: aload         5
     224: invokeinterface #37,  1           // InterfaceMethod java/util/concurrent/ConcurrentMap.size:()I
     229: if_icmpeq     252
     232: aload         5
     234: invokeinterface #38,  1           // InterfaceMethod java/util/concurrent/ConcurrentMap.entrySet:()Ljava/util/Set;
     239: lload         9
     241: invokedynamic #39,  0             // InvokeDynamic #2:test:(J)Ljava/util/function/Predicate;
     246: invokeinterface #40,  2           // InterfaceMethod java/util/Set.removeIf:(Ljava/util/function/Predicate;)Z
     251: pop
     252: aload         11
     254: ifnull        267
     257: aload         12
     259: iload         6
     261: invokevirtual #41                 // Method org/apache/dubbo/rpc/cluster/loadbalance/RoundRobinLoadBalance$WeightedRoundRobin.sel:(I)V
     264: aload         11
     266: areturn
     267: aload_1
     268: iconst_0
     269: invokeinterface #7,  2            // InterfaceMethod java/util/List.get:(I)Ljava/lang/Object;
     274: checkcast     #8                  // class org/apache/dubbo/rpc/Invoker
     277: areturn

  private static boolean lambda$doSelect$2(long, java.util.Map$Entry);
    Code:
       0: lload_0
       1: aload_2
       2: invokeinterface #42,  1           // InterfaceMethod java/util/Map$Entry.getValue:()Ljava/lang/Object;
       7: checkcast     #31                 // class org/apache/dubbo/rpc/cluster/loadbalance/RoundRobinLoadBalance$WeightedRoundRobin
      10: invokevirtual #43                 // Method org/apache/dubbo/rpc/cluster/loadbalance/RoundRobinLoadBalance$WeightedRoundRobin.getLastUpdate:()J
      13: lsub
      14: ldc2_w        #45                 // long 60000l
      17: lcmp
      18: ifle          25
      21: iconst_1
      22: goto          26
      25: iconst_0
      26: ireturn

  private static org.apache.dubbo.rpc.cluster.loadbalance.RoundRobinLoadBalance$WeightedRoundRobin lambda$doSelect$1(int, java.lang.String);
    Code:
       0: new           #31                 // class org/apache/dubbo/rpc/cluster/loadbalance/RoundRobinLoadBalance$WeightedRoundRobin
       3: dup
       4: invokespecial #47                 // Method org/apache/dubbo/rpc/cluster/loadbalance/RoundRobinLoadBalance$WeightedRoundRobin."<init>":()V
       7: astore_2
       8: aload_2
       9: iload_0
      10: invokevirtual #33                 // Method org/apache/dubbo/rpc/cluster/loadbalance/RoundRobinLoadBalance$WeightedRoundRobin.setWeight:(I)V
      13: aload_2
      14: areturn

  private static java.util.concurrent.ConcurrentMap lambda$doSelect$0(java.lang.String);
    Code:
       0: new           #2                  // class java/util/concurrent/ConcurrentHashMap
       3: dup
       4: invokespecial #3                  // Method java/util/concurrent/ConcurrentHashMap."<init>":()V
       7: areturn
}
