Compiled from "ShortestResponseLoadBalance.java"
public class org.apache.dubbo.rpc.cluster.loadbalance.ShortestResponseLoadBalance extends org.apache.dubbo.rpc.cluster.loadbalance.AbstractLoadBalance implements org.apache.dubbo.rpc.model.ScopeModelAware {
  public static final java.lang.String NAME;

  private int slidePeriod;

  private final java.util.concurrent.ConcurrentMap<org.apache.dubbo.rpc.RpcStatus, org.apache.dubbo.rpc.cluster.loadbalance.ShortestResponseLoadBalance$SlideWindowData> methodMap;

  private final java.util.concurrent.atomic.AtomicBoolean onResetSlideWindow;

  private volatile long lastUpdateTime;

  private java.util.concurrent.ExecutorService executorService;

  public org.apache.dubbo.rpc.cluster.loadbalance.ShortestResponseLoadBalance();
    Code:
       0: aload_0
       1: invokespecial #1                  // Method org/apache/dubbo/rpc/cluster/loadbalance/AbstractLoadBalance."<init>":()V
       4: aload_0
       5: sipush        30000
       8: putfield      #2                  // Field slidePeriod:I
      11: aload_0
      12: new           #3                  // class java/util/concurrent/ConcurrentHashMap
      15: dup
      16: invokespecial #4                  // Method java/util/concurrent/ConcurrentHashMap."<init>":()V
      19: putfield      #5                  // Field methodMap:Ljava/util/concurrent/ConcurrentMap;
      22: aload_0
      23: new           #6                  // class java/util/concurrent/atomic/AtomicBoolean
      26: dup
      27: iconst_0
      28: invokespecial #7                  // Method java/util/concurrent/atomic/AtomicBoolean."<init>":(Z)V
      31: putfield      #8                  // Field onResetSlideWindow:Ljava/util/concurrent/atomic/AtomicBoolean;
      34: aload_0
      35: invokestatic  #9                  // Method java/lang/System.currentTimeMillis:()J
      38: putfield      #10                 // Field lastUpdateTime:J
      41: return

  public void setApplicationModel(org.apache.dubbo.rpc.model.ApplicationModel);
    Code:
       0: aload_0
       1: aload_1
       2: invokevirtual #11                 // Method org/apache/dubbo/rpc/model/ApplicationModel.getModelEnvironment:()Lorg/apache/dubbo/common/config/Environment;
       5: invokevirtual #12                 // Method org/apache/dubbo/common/config/Environment.getConfiguration:()Lorg/apache/dubbo/common/config/CompositeConfiguration;
       8: ldc           #14                 // String shortestResponseSlidePeriod
      10: sipush        30000
      13: invokevirtual #15                 // Method org/apache/dubbo/common/config/CompositeConfiguration.getInt:(Ljava/lang/String;I)I
      16: putfield      #2                  // Field slidePeriod:I
      19: aload_0
      20: aload_1
      21: invokevirtual #16                 // Method org/apache/dubbo/rpc/model/ApplicationModel.getFrameworkModel:()Lorg/apache/dubbo/rpc/model/FrameworkModel;
      24: invokevirtual #17                 // Method org/apache/dubbo/rpc/model/FrameworkModel.getBeanFactory:()Lorg/apache/dubbo/common/beans/factory/ScopeBeanFactory;
      27: ldc           #18                 // class org/apache/dubbo/common/threadpool/manager/FrameworkExecutorRepository
      29: invokevirtual #19                 // Method org/apache/dubbo/common/beans/factory/ScopeBeanFactory.getBean:(Ljava/lang/Class;)Ljava/lang/Object;
      32: checkcast     #18                 // class org/apache/dubbo/common/threadpool/manager/FrameworkExecutorRepository
      35: invokevirtual #20                 // Method org/apache/dubbo/common/threadpool/manager/FrameworkExecutorRepository.getSharedExecutor:()Ljava/util/concurrent/ExecutorService;
      38: putfield      #21                 // Field executorService:Ljava/util/concurrent/ExecutorService;
      41: return

  protected <T> org.apache.dubbo.rpc.Invoker<T> doSelect(java.util.List<org.apache.dubbo.rpc.Invoker<T>>, org.apache.dubbo.common.URL, org.apache.dubbo.rpc.Invocation);
    Code:
       0: aload_1
       1: invokeinterface #22,  1           // InterfaceMethod java/util/List.size:()I
       6: istore        4
       8: ldc2_w        #24                 // long 9223372036854775807l
      11: lstore        5
      13: iconst_0
      14: istore        7
      16: iload         4
      18: newarray       int
      20: astore        8
      22: iload         4
      24: newarray       int
      26: astore        9
      28: iconst_0
      29: istore        10
      31: iconst_0
      32: istore        11
      34: iconst_1
      35: istore        12
      37: iconst_0
      38: istore        13
      40: iload         13
      42: iload         4
      44: if_icmpge     206
      47: aload_1
      48: iload         13
      50: invokeinterface #26,  2           // InterfaceMethod java/util/List.get:(I)Ljava/lang/Object;
      55: checkcast     #27                 // class org/apache/dubbo/rpc/Invoker
      58: astore        14
      60: aload         14
      62: invokeinterface #28,  1           // InterfaceMethod org/apache/dubbo/rpc/Invoker.getUrl:()Lorg/apache/dubbo/common/URL;
      67: aload_3
      68: invokeinterface #29,  1           // InterfaceMethod org/apache/dubbo/rpc/Invocation.getMethodName:()Ljava/lang/String;
      73: invokestatic  #30                 // Method org/apache/dubbo/rpc/RpcStatus.getStatus:(Lorg/apache/dubbo/common/URL;Ljava/lang/String;)Lorg/apache/dubbo/rpc/RpcStatus;
      76: astore        15
      78: aload_0
      79: getfield      #5                  // Field methodMap:Ljava/util/concurrent/ConcurrentMap;
      82: aload         15
      84: invokedynamic #31,  0             // InvokeDynamic #0:apply:()Ljava/util/function/Function;
      89: invokestatic  #32                 // Method org/apache/dubbo/common/utils/ConcurrentHashMapUtils.computeIfAbsent:(Ljava/util/concurrent/ConcurrentMap;Ljava/lang/Object;Ljava/util/function/Function;)Ljava/lang/Object;
      92: checkcast     #33                 // class org/apache/dubbo/rpc/cluster/loadbalance/ShortestResponseLoadBalance$SlideWindowData
      95: astore        16
      97: aload         16
      99: invokevirtual #34                 // Method org/apache/dubbo/rpc/cluster/loadbalance/ShortestResponseLoadBalance$SlideWindowData.getEstimateResponse:()J
     102: lstore        17
     104: aload_0
     105: aload         14
     107: aload_3
     108: invokevirtual #35                 // Method getWeight:(Lorg/apache/dubbo/rpc/Invoker;Lorg/apache/dubbo/rpc/Invocation;)I
     111: istore        19
     113: aload         9
     115: iload         13
     117: iload         19
     119: iastore
     120: lload         17
     122: lload         5
     124: lcmp
     125: ifge          155
     128: lload         17
     130: lstore        5
     132: iconst_1
     133: istore        7
     135: aload         8
     137: iconst_0
     138: iload         13
     140: iastore
     141: iload         19
     143: istore        10
     145: iload         19
     147: istore        11
     149: iconst_1
     150: istore        12
     152: goto          200
     155: lload         17
     157: lload         5
     159: lcmp
     160: ifne          200
     163: aload         8
     165: iload         7
     167: iinc          7, 1
     170: iload         13
     172: iastore
     173: iload         10
     175: iload         19
     177: iadd
     178: istore        10
     180: iload         12
     182: ifeq          200
     185: iload         13
     187: ifle          200
     190: iload         19
     192: iload         11
     194: if_icmpeq     200
     197: iconst_0
     198: istore        12
     200: iinc          13, 1
     203: goto          40
     206: invokestatic  #9                  // Method java/lang/System.currentTimeMillis:()J
     209: aload_0
     210: getfield      #10                 // Field lastUpdateTime:J
     213: lsub
     214: aload_0
     215: getfield      #2                  // Field slidePeriod:I
     218: i2l
     219: lcmp
     220: ifle          250
     223: aload_0
     224: getfield      #8                  // Field onResetSlideWindow:Ljava/util/concurrent/atomic/AtomicBoolean;
     227: iconst_0
     228: iconst_1
     229: invokevirtual #36                 // Method java/util/concurrent/atomic/AtomicBoolean.compareAndSet:(ZZ)Z
     232: ifeq          250
     235: aload_0
     236: getfield      #21                 // Field executorService:Ljava/util/concurrent/ExecutorService;
     239: aload_0
     240: invokedynamic #37,  0             // InvokeDynamic #1:run:(Lorg/apache/dubbo/rpc/cluster/loadbalance/ShortestResponseLoadBalance;)Ljava/lang/Runnable;
     245: invokeinterface #38,  2           // InterfaceMethod java/util/concurrent/ExecutorService.execute:(Ljava/lang/Runnable;)V
     250: iload         7
     252: iconst_1
     253: if_icmpne     270
     256: aload_1
     257: aload         8
     259: iconst_0
     260: iaload
     261: invokeinterface #26,  2           // InterfaceMethod java/util/List.get:(I)Ljava/lang/Object;
     266: checkcast     #27                 // class org/apache/dubbo/rpc/Invoker
     269: areturn
     270: iload         12
     272: ifne          340
     275: iload         10
     277: ifle          340
     280: invokestatic  #39                 // Method java/util/concurrent/ThreadLocalRandom.current:()Ljava/util/concurrent/ThreadLocalRandom;
     283: iload         10
     285: invokevirtual #40                 // Method java/util/concurrent/ThreadLocalRandom.nextInt:(I)I
     288: istore        13
     290: iconst_0
     291: istore        14
     293: iload         14
     295: iload         7
     297: if_icmpge     340
     300: aload         8
     302: iload         14
     304: iaload
     305: istore        15
     307: iload         13
     309: aload         9
     311: iload         15
     313: iaload
     314: isub
     315: istore        13
     317: iload         13
     319: ifge          334
     322: aload_1
     323: iload         15
     325: invokeinterface #26,  2           // InterfaceMethod java/util/List.get:(I)Ljava/lang/Object;
     330: checkcast     #27                 // class org/apache/dubbo/rpc/Invoker
     333: areturn
     334: iinc          14, 1
     337: goto          293
     340: aload_1
     341: aload         8
     343: invokestatic  #39                 // Method java/util/concurrent/ThreadLocalRandom.current:()Ljava/util/concurrent/ThreadLocalRandom;
     346: iload         7
     348: invokevirtual #40                 // Method java/util/concurrent/ThreadLocalRandom.nextInt:(I)I
     351: iaload
     352: invokeinterface #26,  2           // InterfaceMethod java/util/List.get:(I)Ljava/lang/Object;
     357: checkcast     #27                 // class org/apache/dubbo/rpc/Invoker
     360: areturn

  private void lambda$doSelect$0();
    Code:
       0: aload_0
       1: getfield      #5                  // Field methodMap:Ljava/util/concurrent/ConcurrentMap;
       4: invokeinterface #41,  1           // InterfaceMethod java/util/concurrent/ConcurrentMap.values:()Ljava/util/Collection;
       9: invokedynamic #42,  0             // InvokeDynamic #2:accept:()Ljava/util/function/Consumer;
      14: invokeinterface #43,  2           // InterfaceMethod java/util/Collection.forEach:(Ljava/util/function/Consumer;)V
      19: aload_0
      20: invokestatic  #9                  // Method java/lang/System.currentTimeMillis:()J
      23: putfield      #10                 // Field lastUpdateTime:J
      26: aload_0
      27: getfield      #8                  // Field onResetSlideWindow:Ljava/util/concurrent/atomic/AtomicBoolean;
      30: iconst_0
      31: invokevirtual #44                 // Method java/util/concurrent/atomic/AtomicBoolean.set:(Z)V
      34: return
}
