Compiled from "ShortestResponseLoadBalance.java"
public class org.apache.dubbo.rpc.cluster.loadbalance.ShortestResponseLoadBalance$SlideWindowData {
  private long succeededOffset;

  private long succeededElapsedOffset;

  private final org.apache.dubbo.rpc.RpcStatus rpcStatus;

  public org.apache.dubbo.rpc.cluster.loadbalance.ShortestResponseLoadBalance$SlideWindowData(org.apache.dubbo.rpc.RpcStatus);
    Code:
       0: aload_0
       1: invokespecial #1                  // Method java/lang/Object."<init>":()V
       4: aload_0
       5: aload_1
       6: putfield      #2                  // Field rpcStatus:Lorg/apache/dubbo/rpc/RpcStatus;
       9: aload_0
      10: lconst_0
      11: putfield      #3                  // Field succeededOffset:J
      14: aload_0
      15: lconst_0
      16: putfield      #4                  // Field succeededElapsedOffset:J
      19: return

  public void reset();
    Code:
       0: aload_0
       1: aload_0
       2: getfield      #2                  // Field rpcStatus:Lorg/apache/dubbo/rpc/RpcStatus;
       5: invokevirtual #5                  // Method org/apache/dubbo/rpc/RpcStatus.getSucceeded:()J
       8: putfield      #3                  // Field succeededOffset:J
      11: aload_0
      12: aload_0
      13: getfield      #2                  // Field rpcStatus:Lorg/apache/dubbo/rpc/RpcStatus;
      16: invokevirtual #6                  // Method org/apache/dubbo/rpc/RpcStatus.getSucceededElapsed:()J
      19: putfield      #4                  // Field succeededElapsedOffset:J
      22: return

  private long getSucceededAverageElapsed();
    Code:
       0: aload_0
       1: getfield      #2                  // Field rpcStatus:Lorg/apache/dubbo/rpc/RpcStatus;
       4: invokevirtual #5                  // Method org/apache/dubbo/rpc/RpcStatus.getSucceeded:()J
       7: aload_0
       8: getfield      #3                  // Field succeededOffset:J
      11: lsub
      12: lstore_1
      13: lload_1
      14: lconst_0
      15: lcmp
      16: ifne          21
      19: lconst_0
      20: lreturn
      21: aload_0
      22: getfield      #2                  // Field rpcStatus:Lorg/apache/dubbo/rpc/RpcStatus;
      25: invokevirtual #6                  // Method org/apache/dubbo/rpc/RpcStatus.getSucceededElapsed:()J
      28: aload_0
      29: getfield      #4                  // Field succeededElapsedOffset:J
      32: lsub
      33: lload_1
      34: ldiv
      35: lreturn

  public long getEstimateResponse();
    Code:
       0: aload_0
       1: getfield      #2                  // Field rpcStatus:Lorg/apache/dubbo/rpc/RpcStatus;
       4: invokevirtual #7                  // Method org/apache/dubbo/rpc/RpcStatus.getActive:()I
       7: iconst_1
       8: iadd
       9: istore_1
      10: aload_0
      11: invokespecial #8                  // Method getSucceededAverageElapsed:()J
      14: iload_1
      15: i2l
      16: lmul
      17: lreturn
}
