Compiled from "DataSourceScriptDatabaseInitializerDetector.java"
class org.springframework.boot.jdbc.init.DataSourceScriptDatabaseInitializerDetector extends org.springframework.boot.sql.init.dependency.AbstractBeansOfTypeDatabaseInitializerDetector {
  static final int PRECEDENCE;

  org.springframework.boot.jdbc.init.DataSourceScriptDatabaseInitializerDetector();
    Code:
       0: aload_0
       1: invokespecial #3                  // Method org/springframework/boot/sql/init/dependency/AbstractBeansOfTypeDatabaseInitializerDetector."<init>":()V
       4: return

  protected java.util.Set<java.lang.Class<?>> getDatabaseInitializerBeanTypes();
    Code:
       0: ldc           #9                  // class org/springframework/boot/jdbc/init/DataSourceScriptDatabaseInitializer
       2: invokestatic  #11                 // Method java/util/Collections.singleton:(Ljava/lang/Object;)Ljava/util/Set;
       5: areturn

  public int getOrder();
    Code:
       0: ldc           #19                 // int 2147483547
       2: ireturn
}
