Compiled from "DataSourceScriptDatabaseInitializer.java"
public class org.springframework.boot.jdbc.init.DataSourceScriptDatabaseInitializer extends org.springframework.boot.sql.init.AbstractScriptDatabaseInitializer {
  private static final org.apache.commons.logging.Log logger;

  private final javax.sql.DataSource dataSource;

  public org.springframework.boot.jdbc.init.DataSourceScriptDatabaseInitializer(javax.sql.DataSource, org.springframework.boot.sql.init.DatabaseInitializationSettings);
    Code:
       0: aload_0
       1: aload_2
       2: invokespecial #1                  // Method org/springframework/boot/sql/init/AbstractScriptDatabaseInitializer."<init>":(Lorg/springframework/boot/sql/init/DatabaseInitializationSettings;)V
       5: aload_0
       6: aload_1
       7: putfield      #7                  // Field dataSource:Ljavax/sql/DataSource;
      10: return

  protected final javax.sql.DataSource getDataSource();
    Code:
       0: aload_0
       1: getfield      #7                  // Field dataSource:Ljavax/sql/DataSource;
       4: areturn

  protected boolean isEmbeddedDatabase();
    Code:
       0: aload_0
       1: getfield      #7                  // Field dataSource:Ljavax/sql/DataSource;
       4: invokestatic  #13                 // Method org/springframework/boot/jdbc/EmbeddedDatabaseConnection.isEmbedded:(Ljavax/sql/DataSource;)Z
       7: ireturn
       8: astore_1
       9: getstatic     #21                 // Field logger:Lorg/apache/commons/logging/Log;
      12: ldc           #25                 // String Could not determine if datasource is embedded
      14: aload_1
      15: invokeinterface #27,  3           // InterfaceMethod org/apache/commons/logging/Log.debug:(Ljava/lang/Object;Ljava/lang/Throwable;)V
      20: iconst_0
      21: ireturn
    Exception table:
       from    to  target type
           0     7     8   Class java/lang/Exception

  protected void runScripts(org.springframework.boot.sql.init.AbstractScriptDatabaseInitializer$Scripts);
    Code:
       0: new           #33                 // class org/springframework/jdbc/datasource/init/ResourceDatabasePopulator
       3: dup
       4: invokespecial #35                 // Method org/springframework/jdbc/datasource/init/ResourceDatabasePopulator."<init>":()V
       7: astore_2
       8: aload_2
       9: aload_1
      10: invokevirtual #38                 // Method org/springframework/boot/sql/init/AbstractScriptDatabaseInitializer$Scripts.isContinueOnError:()Z
      13: invokevirtual #44                 // Method org/springframework/jdbc/datasource/init/ResourceDatabasePopulator.setContinueOnError:(Z)V
      16: aload_2
      17: aload_1
      18: invokevirtual #48                 // Method org/springframework/boot/sql/init/AbstractScriptDatabaseInitializer$Scripts.getSeparator:()Ljava/lang/String;
      21: invokevirtual #52                 // Method org/springframework/jdbc/datasource/init/ResourceDatabasePopulator.setSeparator:(Ljava/lang/String;)V
      24: aload_1
      25: invokevirtual #56                 // Method org/springframework/boot/sql/init/AbstractScriptDatabaseInitializer$Scripts.getEncoding:()Ljava/nio/charset/Charset;
      28: ifnull        42
      31: aload_2
      32: aload_1
      33: invokevirtual #56                 // Method org/springframework/boot/sql/init/AbstractScriptDatabaseInitializer$Scripts.getEncoding:()Ljava/nio/charset/Charset;
      36: invokevirtual #60                 // Method java/nio/charset/Charset.name:()Ljava/lang/String;
      39: invokevirtual #65                 // Method org/springframework/jdbc/datasource/init/ResourceDatabasePopulator.setSqlScriptEncoding:(Ljava/lang/String;)V
      42: aload_1
      43: invokevirtual #68                 // Method org/springframework/boot/sql/init/AbstractScriptDatabaseInitializer$Scripts.iterator:()Ljava/util/Iterator;
      46: astore_3
      47: aload_3
      48: invokeinterface #72,  1           // InterfaceMethod java/util/Iterator.hasNext:()Z
      53: ifeq          76
      56: aload_3
      57: invokeinterface #77,  1           // InterfaceMethod java/util/Iterator.next:()Ljava/lang/Object;
      62: checkcast     #81                 // class org/springframework/core/io/Resource
      65: astore        4
      67: aload_2
      68: aload         4
      70: invokevirtual #83                 // Method org/springframework/jdbc/datasource/init/ResourceDatabasePopulator.addScript:(Lorg/springframework/core/io/Resource;)V
      73: goto          47
      76: aload_0
      77: aload_2
      78: invokevirtual #87                 // Method customize:(Lorg/springframework/jdbc/datasource/init/ResourceDatabasePopulator;)V
      81: aload_2
      82: aload_0
      83: getfield      #7                  // Field dataSource:Ljavax/sql/DataSource;
      86: invokestatic  #91                 // Method org/springframework/jdbc/datasource/init/DatabasePopulatorUtils.execute:(Lorg/springframework/jdbc/datasource/init/DatabasePopulator;Ljavax/sql/DataSource;)V
      89: return

  protected void customize(org.springframework.jdbc.datasource.init.ResourceDatabasePopulator);
    Code:
       0: return

  static {};
    Code:
       0: ldc           #8                  // class org/springframework/boot/jdbc/init/DataSourceScriptDatabaseInitializer
       2: invokestatic  #97                 // Method org/apache/commons/logging/LogFactory.getLog:(Ljava/lang/Class;)Lorg/apache/commons/logging/Log;
       5: putstatic     #21                 // Field logger:Lorg/apache/commons/logging/Log;
       8: return
}
