Compiled from "PlatformPlaceholderDatabaseDriverResolver.java"
public class org.springframework.boot.jdbc.init.PlatformPlaceholderDatabaseDriverResolver {
  private final java.lang.String placeholder;

  private final java.util.Map<org.springframework.boot.jdbc.DatabaseDriver, java.lang.String> driverMappings;

  public org.springframework.boot.jdbc.init.PlatformPlaceholderDatabaseDriverResolver();
    Code:
       0: aload_0
       1: ldc           #1                  // String @@platform@@
       3: invokespecial #3                  // Method "<init>":(Ljava/lang/String;)V
       6: return

  public org.springframework.boot.jdbc.init.PlatformPlaceholderDatabaseDriverResolver(java.lang.String);
    Code:
       0: aload_0
       1: aload_1
       2: invokestatic  #9                  // Method java/util/Collections.emptyMap:()Ljava/util/Map;
       5: invokespecial #15                 // Method "<init>":(Ljava/lang/String;Ljava/util/Map;)V
       8: return

  private org.springframework.boot.jdbc.init.PlatformPlaceholderDatabaseDriverResolver(java.lang.String, java.util.Map<org.springframework.boot.jdbc.DatabaseDriver, java.lang.String>);
    Code:
       0: aload_0
       1: invokespecial #18                 // Method java/lang/Object."<init>":()V
       4: aload_0
       5: aload_1
       6: putfield      #23                 // Field placeholder:Ljava/lang/String;
       9: aload_0
      10: aload_2
      11: putfield      #27                 // Field driverMappings:Ljava/util/Map;
      14: return

  public org.springframework.boot.jdbc.init.PlatformPlaceholderDatabaseDriverResolver withDriverPlatform(org.springframework.boot.jdbc.DatabaseDriver, java.lang.String);
    Code:
       0: new           #31                 // class java/util/LinkedHashMap
       3: dup
       4: aload_0
       5: getfield      #27                 // Field driverMappings:Ljava/util/Map;
       8: invokespecial #33                 // Method java/util/LinkedHashMap."<init>":(Ljava/util/Map;)V
      11: astore_3
      12: aload_3
      13: aload_1
      14: aload_2
      15: invokeinterface #36,  3           // InterfaceMethod java/util/Map.put:(Ljava/lang/Object;Ljava/lang/Object;)Ljava/lang/Object;
      20: pop
      21: new           #4                  // class org/springframework/boot/jdbc/init/PlatformPlaceholderDatabaseDriverResolver
      24: dup
      25: aload_0
      26: getfield      #23                 // Field placeholder:Ljava/lang/String;
      29: aload_3
      30: invokespecial #15                 // Method "<init>":(Ljava/lang/String;Ljava/util/Map;)V
      33: areturn

  public java.util.List<java.lang.String> resolveAll(javax.sql.DataSource, java.lang.String...);
    Code:
       0: aload_1
       1: ldc           #42                 // String DataSource must not be null
       3: invokestatic  #44                 // Method org/springframework/util/Assert.notNull:(Ljava/lang/Object;Ljava/lang/String;)V
       6: aload_0
       7: aload_0
       8: aload_1
       9: invokedynamic #50,  0             // InvokeDynamic #0:get:(Lorg/springframework/boot/jdbc/init/PlatformPlaceholderDatabaseDriverResolver;Ljavax/sql/DataSource;)Ljava/util/function/Supplier;
      14: aload_2
      15: invokevirtual #54                 // Method resolveAll:(Ljava/util/function/Supplier;[Ljava/lang/String;)Ljava/util/List;
      18: areturn

  public java.util.List<java.lang.String> resolveAll(java.lang.String, java.lang.String...);
    Code:
       0: aload_1
       1: ldc           #58                 // String Platform must not be null
       3: invokestatic  #44                 // Method org/springframework/util/Assert.notNull:(Ljava/lang/Object;Ljava/lang/String;)V
       6: aload_0
       7: aload_1
       8: invokedynamic #60,  0             // InvokeDynamic #1:get:(Ljava/lang/String;)Ljava/util/function/Supplier;
      13: aload_2
      14: invokevirtual #54                 // Method resolveAll:(Ljava/util/function/Supplier;[Ljava/lang/String;)Ljava/util/List;
      17: areturn

  private java.util.List<java.lang.String> resolveAll(java.util.function.Supplier<java.lang.String>, java.lang.String...);
    Code:
       0: aload_2
       1: invokestatic  #63                 // Method org/springframework/util/ObjectUtils.isEmpty:([Ljava/lang/Object;)Z
       4: ifeq          11
       7: invokestatic  #69                 // Method java/util/Collections.emptyList:()Ljava/util/List;
      10: areturn
      11: new           #73                 // class java/util/ArrayList
      14: dup
      15: aload_2
      16: arraylength
      17: invokespecial #75                 // Method java/util/ArrayList."<init>":(I)V
      20: astore_3
      21: aconst_null
      22: astore        4
      24: aload_2
      25: astore        5
      27: aload         5
      29: arraylength
      30: istore        6
      32: iconst_0
      33: istore        7
      35: iload         7
      37: iload         6
      39: if_icmpge     118
      42: aload         5
      44: iload         7
      46: aaload
      47: astore        8
      49: aload         8
      51: invokestatic  #78                 // Method org/springframework/util/StringUtils.hasLength:(Ljava/lang/String;)Z
      54: ifeq          103
      57: aload         8
      59: aload_0
      60: getfield      #23                 // Field placeholder:Ljava/lang/String;
      63: invokevirtual #84                 // Method java/lang/String.contains:(Ljava/lang/CharSequence;)Z
      66: ifeq          103
      69: aload         4
      71: ifnull        79
      74: aload         4
      76: goto          88
      79: aload_1
      80: invokeinterface #90,  1           // InterfaceMethod java/util/function/Supplier.get:()Ljava/lang/Object;
      85: checkcast     #85                 // class java/lang/String
      88: astore        4
      90: aload         8
      92: aload_0
      93: getfield      #23                 // Field placeholder:Ljava/lang/String;
      96: aload         4
      98: invokevirtual #95                 // Method java/lang/String.replace:(Ljava/lang/CharSequence;Ljava/lang/CharSequence;)Ljava/lang/String;
     101: astore        8
     103: aload_3
     104: aload         8
     106: invokeinterface #99,  2           // InterfaceMethod java/util/List.add:(Ljava/lang/Object;)Z
     111: pop
     112: iinc          7, 1
     115: goto          35
     118: aload_3
     119: invokestatic  #105                // Method java/util/Collections.unmodifiableList:(Ljava/util/List;)Ljava/util/List;
     122: areturn

  private java.lang.String determinePlatform(javax.sql.DataSource);
    Code:
       0: aload_0
       1: aload_1
       2: invokevirtual #109                // Method getDatabaseDriver:(Ljavax/sql/DataSource;)Lorg/springframework/boot/jdbc/DatabaseDriver;
       5: astore_2
       6: aload_2
       7: getstatic     #113                // Field org/springframework/boot/jdbc/DatabaseDriver.UNKNOWN:Lorg/springframework/boot/jdbc/DatabaseDriver;
      10: if_acmpeq     17
      13: iconst_1
      14: goto          18
      17: iconst_0
      18: ldc           #119                // String Unable to detect database type
      20: invokestatic  #121                // Method org/springframework/util/Assert.state:(ZLjava/lang/String;)V
      23: aload_0
      24: getfield      #27                 // Field driverMappings:Ljava/util/Map;
      27: aload_2
      28: aload_2
      29: invokevirtual #125                // Method org/springframework/boot/jdbc/DatabaseDriver.getId:()Ljava/lang/String;
      32: invokeinterface #129,  3          // InterfaceMethod java/util/Map.getOrDefault:(Ljava/lang/Object;Ljava/lang/Object;)Ljava/lang/Object;
      37: checkcast     #85                 // class java/lang/String
      40: areturn

  org.springframework.boot.jdbc.DatabaseDriver getDatabaseDriver(javax.sql.DataSource);
    Code:
       0: aload_1
       1: invokestatic  #132                // Method org/springframework/boot/jdbc/DatabaseDriver.fromDataSource:(Ljavax/sql/DataSource;)Lorg/springframework/boot/jdbc/DatabaseDriver;
       4: areturn

  private static java.lang.String lambda$resolveAll$1(java.lang.String);
    Code:
       0: aload_0
       1: areturn

  private java.lang.String lambda$resolveAll$0(javax.sql.DataSource);
    Code:
       0: aload_0
       1: aload_1
       2: invokevirtual #135                // Method determinePlatform:(Ljavax/sql/DataSource;)Ljava/lang/String;
       5: areturn
}
