Compiled from "RegistrySubDispatcher.java"
interface org.apache.dubbo.metrics.registry.event.RegistrySubDispatcher$CategorySet {
  public static final org.apache.dubbo.metrics.model.key.CategoryOverall APPLICATION_REGISTER;

  public static final org.apache.dubbo.metrics.model.key.CategoryOverall APPLICATION_SUBSCRIBE;

  public static final org.apache.dubbo.metrics.model.key.CategoryOverall APPLICATION_NOTIFY;

  public static final org.apache.dubbo.metrics.model.key.CategoryOverall SERVICE_DIRECTORY;

  public static final org.apache.dubbo.metrics.model.key.CategoryOverall SERVICE_REGISTER;

  public static final org.apache.dubbo.metrics.model.key.CategoryOverall SERVICE_SUBSCRIBE;

  public static final java.util.List<org.apache.dubbo.metrics.model.key.CategoryOverall> ALL;

  static {};
    Code:
       0: new           #1                  // class org/apache/dubbo/metrics/model/key/CategoryOverall
       3: dup
       4: getstatic     #2                  // Field org/apache/dubbo/metrics/registry/RegistryMetricsConstants.OP_TYPE_REGISTER:Lorg/apache/dubbo/metrics/model/key/MetricsPlaceValue;
       7: getstatic     #3                  // Field org/apache/dubbo/metrics/registry/event/RegistrySubDispatcher$MCat.APPLICATION_REGISTER_POST:Lorg/apache/dubbo/metrics/model/key/MetricsCat;
      10: getstatic     #4                  // Field org/apache/dubbo/metrics/registry/event/RegistrySubDispatcher$MCat.APPLICATION_REGISTER_FINISH:Lorg/apache/dubbo/metrics/model/key/MetricsCat;
      13: getstatic     #5                  // Field org/apache/dubbo/metrics/registry/event/RegistrySubDispatcher$MCat.APPLICATION_REGISTER_ERROR:Lorg/apache/dubbo/metrics/model/key/MetricsCat;
      16: invokespecial #6                  // Method org/apache/dubbo/metrics/model/key/CategoryOverall."<init>":(Lorg/apache/dubbo/metrics/model/key/MetricsPlaceValue;Lorg/apache/dubbo/metrics/model/key/MetricsCat;Lorg/apache/dubbo/metrics/model/key/MetricsCat;Lorg/apache/dubbo/metrics/model/key/MetricsCat;)V
      19: putstatic     #7                  // Field APPLICATION_REGISTER:Lorg/apache/dubbo/metrics/model/key/CategoryOverall;
      22: new           #1                  // class org/apache/dubbo/metrics/model/key/CategoryOverall
      25: dup
      26: getstatic     #8                  // Field org/apache/dubbo/metrics/registry/RegistryMetricsConstants.OP_TYPE_SUBSCRIBE:Lorg/apache/dubbo/metrics/model/key/MetricsPlaceValue;
      29: getstatic     #9                  // Field org/apache/dubbo/metrics/registry/event/RegistrySubDispatcher$MCat.APPLICATION_SUBSCRIBE_POST:Lorg/apache/dubbo/metrics/model/key/MetricsCat;
      32: getstatic     #10                 // Field org/apache/dubbo/metrics/registry/event/RegistrySubDispatcher$MCat.APPLICATION_SUBSCRIBE_FINISH:Lorg/apache/dubbo/metrics/model/key/MetricsCat;
      35: getstatic     #11                 // Field org/apache/dubbo/metrics/registry/event/RegistrySubDispatcher$MCat.APPLICATION_SUBSCRIBE_ERROR:Lorg/apache/dubbo/metrics/model/key/MetricsCat;
      38: invokespecial #6                  // Method org/apache/dubbo/metrics/model/key/CategoryOverall."<init>":(Lorg/apache/dubbo/metrics/model/key/MetricsPlaceValue;Lorg/apache/dubbo/metrics/model/key/MetricsCat;Lorg/apache/dubbo/metrics/model/key/MetricsCat;Lorg/apache/dubbo/metrics/model/key/MetricsCat;)V
      41: putstatic     #12                 // Field APPLICATION_SUBSCRIBE:Lorg/apache/dubbo/metrics/model/key/CategoryOverall;
      44: new           #1                  // class org/apache/dubbo/metrics/model/key/CategoryOverall
      47: dup
      48: getstatic     #13                 // Field org/apache/dubbo/metrics/registry/RegistryMetricsConstants.OP_TYPE_NOTIFY:Lorg/apache/dubbo/metrics/model/key/MetricsPlaceValue;
      51: getstatic     #14                 // Field org/apache/dubbo/metrics/registry/event/RegistrySubDispatcher$MCat.APPLICATION_NOTIFY_POST:Lorg/apache/dubbo/metrics/model/key/MetricsCat;
      54: getstatic     #15                 // Field org/apache/dubbo/metrics/registry/event/RegistrySubDispatcher$MCat.APPLICATION_NOTIFY_FINISH:Lorg/apache/dubbo/metrics/model/key/MetricsCat;
      57: aconst_null
      58: invokespecial #6                  // Method org/apache/dubbo/metrics/model/key/CategoryOverall."<init>":(Lorg/apache/dubbo/metrics/model/key/MetricsPlaceValue;Lorg/apache/dubbo/metrics/model/key/MetricsCat;Lorg/apache/dubbo/metrics/model/key/MetricsCat;Lorg/apache/dubbo/metrics/model/key/MetricsCat;)V
      61: putstatic     #16                 // Field APPLICATION_NOTIFY:Lorg/apache/dubbo/metrics/model/key/CategoryOverall;
      64: new           #1                  // class org/apache/dubbo/metrics/model/key/CategoryOverall
      67: dup
      68: getstatic     #17                 // Field org/apache/dubbo/metrics/registry/RegistryMetricsConstants.OP_TYPE_DIRECTORY:Lorg/apache/dubbo/metrics/model/key/MetricsPlaceValue;
      71: getstatic     #18                 // Field org/apache/dubbo/metrics/registry/event/RegistrySubDispatcher$MCat.APPLICATION_DIRECTORY_POST:Lorg/apache/dubbo/metrics/model/key/MetricsCat;
      74: aconst_null
      75: aconst_null
      76: invokespecial #6                  // Method org/apache/dubbo/metrics/model/key/CategoryOverall."<init>":(Lorg/apache/dubbo/metrics/model/key/MetricsPlaceValue;Lorg/apache/dubbo/metrics/model/key/MetricsCat;Lorg/apache/dubbo/metrics/model/key/MetricsCat;Lorg/apache/dubbo/metrics/model/key/MetricsCat;)V
      79: putstatic     #19                 // Field SERVICE_DIRECTORY:Lorg/apache/dubbo/metrics/model/key/CategoryOverall;
      82: new           #1                  // class org/apache/dubbo/metrics/model/key/CategoryOverall
      85: dup
      86: getstatic     #20                 // Field org/apache/dubbo/metrics/registry/RegistryMetricsConstants.OP_TYPE_REGISTER_SERVICE:Lorg/apache/dubbo/metrics/model/key/MetricsPlaceValue;
      89: getstatic     #21                 // Field org/apache/dubbo/metrics/registry/event/RegistrySubDispatcher$MCat.SERVICE_REGISTER_POST:Lorg/apache/dubbo/metrics/model/key/MetricsCat;
      92: getstatic     #22                 // Field org/apache/dubbo/metrics/registry/event/RegistrySubDispatcher$MCat.SERVICE_REGISTER_FINISH:Lorg/apache/dubbo/metrics/model/key/MetricsCat;
      95: getstatic     #23                 // Field org/apache/dubbo/metrics/registry/event/RegistrySubDispatcher$MCat.SERVICE_REGISTER_ERROR:Lorg/apache/dubbo/metrics/model/key/MetricsCat;
      98: invokespecial #6                  // Method org/apache/dubbo/metrics/model/key/CategoryOverall."<init>":(Lorg/apache/dubbo/metrics/model/key/MetricsPlaceValue;Lorg/apache/dubbo/metrics/model/key/MetricsCat;Lorg/apache/dubbo/metrics/model/key/MetricsCat;Lorg/apache/dubbo/metrics/model/key/MetricsCat;)V
     101: putstatic     #24                 // Field SERVICE_REGISTER:Lorg/apache/dubbo/metrics/model/key/CategoryOverall;
     104: new           #1                  // class org/apache/dubbo/metrics/model/key/CategoryOverall
     107: dup
     108: getstatic     #25                 // Field org/apache/dubbo/metrics/registry/RegistryMetricsConstants.OP_TYPE_SUBSCRIBE_SERVICE:Lorg/apache/dubbo/metrics/model/key/MetricsPlaceValue;
     111: getstatic     #26                 // Field org/apache/dubbo/metrics/registry/event/RegistrySubDispatcher$MCat.SERVICE_SUBSCRIBE_POST:Lorg/apache/dubbo/metrics/model/key/MetricsCat;
     114: getstatic     #27                 // Field org/apache/dubbo/metrics/registry/event/RegistrySubDispatcher$MCat.SERVICE_SUBSCRIBE_FINISH:Lorg/apache/dubbo/metrics/model/key/MetricsCat;
     117: getstatic     #28                 // Field org/apache/dubbo/metrics/registry/event/RegistrySubDispatcher$MCat.SERVICE_SUBSCRIBE_ERROR:Lorg/apache/dubbo/metrics/model/key/MetricsCat;
     120: invokespecial #6                  // Method org/apache/dubbo/metrics/model/key/CategoryOverall."<init>":(Lorg/apache/dubbo/metrics/model/key/MetricsPlaceValue;Lorg/apache/dubbo/metrics/model/key/MetricsCat;Lorg/apache/dubbo/metrics/model/key/MetricsCat;Lorg/apache/dubbo/metrics/model/key/MetricsCat;)V
     123: putstatic     #29                 // Field SERVICE_SUBSCRIBE:Lorg/apache/dubbo/metrics/model/key/CategoryOverall;
     126: bipush        6
     128: anewarray     #1                  // class org/apache/dubbo/metrics/model/key/CategoryOverall
     131: dup
     132: iconst_0
     133: getstatic     #7                  // Field APPLICATION_REGISTER:Lorg/apache/dubbo/metrics/model/key/CategoryOverall;
     136: aastore
     137: dup
     138: iconst_1
     139: getstatic     #12                 // Field APPLICATION_SUBSCRIBE:Lorg/apache/dubbo/metrics/model/key/CategoryOverall;
     142: aastore
     143: dup
     144: iconst_2
     145: getstatic     #16                 // Field APPLICATION_NOTIFY:Lorg/apache/dubbo/metrics/model/key/CategoryOverall;
     148: aastore
     149: dup
     150: iconst_3
     151: getstatic     #19                 // Field SERVICE_DIRECTORY:Lorg/apache/dubbo/metrics/model/key/CategoryOverall;
     154: aastore
     155: dup
     156: iconst_4
     157: getstatic     #24                 // Field SERVICE_REGISTER:Lorg/apache/dubbo/metrics/model/key/CategoryOverall;
     160: aastore
     161: dup
     162: iconst_5
     163: getstatic     #29                 // Field SERVICE_SUBSCRIBE:Lorg/apache/dubbo/metrics/model/key/CategoryOverall;
     166: aastore
     167: invokestatic  #30                 // Method java/util/Arrays.asList:([Ljava/lang/Object;)Ljava/util/List;
     170: putstatic     #31                 // Field ALL:Ljava/util/List;
     173: return
}
