Compiled from "RegistryEvent.java"
final class org.apache.dubbo.metrics.registry.event.RegistryEvent$1 extends org.apache.dubbo.metrics.registry.event.RegistryEvent {
  org.apache.dubbo.metrics.registry.event.RegistryEvent$1(org.apache.dubbo.rpc.model.ApplicationModel, org.apache.dubbo.metrics.model.key.TypeWrapper);
    Code:
       0: aload_0
       1: aload_1
       2: aload_2
       3: invokespecial #2                  // Method org/apache/dubbo/metrics/registry/event/RegistryEvent."<init>":(Lorg/apache/dubbo/rpc/model/ApplicationModel;Lorg/apache/dubbo/metrics/model/key/TypeWrapper;)V
       6: return

  public void customAfterPost(java.lang.Object);
    Code:
       0: aload_0
       1: ldc           #3                  // String lastNumMap
       3: aload_1
       4: invokespecial #4                  // Method org/apache/dubbo/metrics/registry/event/RegistryEvent.putAttachment:(Ljava/lang/String;Ljava/lang/Object;)V
       7: return
}
