Compiled from "RegistrySubDispatcher.java"
interface org.apache.dubbo.metrics.registry.event.RegistrySubDispatcher$MCat {
  public static final org.apache.dubbo.metrics.model.key.MetricsCat APPLICATION_REGISTER_POST;

  public static final org.apache.dubbo.metrics.model.key.MetricsCat APPLICATION_REGISTER_FINISH;

  public static final org.apache.dubbo.metrics.model.key.MetricsCat APPLICATION_REGISTER_ERROR;

  public static final org.apache.dubbo.metrics.model.key.MetricsCat APPLICATION_SUBSCRIBE_POST;

  public static final org.apache.dubbo.metrics.model.key.MetricsCat APPLICATION_SUBSCRIBE_FINISH;

  public static final org.apache.dubbo.metrics.model.key.MetricsCat APPLICATION_SUBSCRIBE_ERROR;

  public static final org.apache.dubbo.metrics.model.key.MetricsCat APPLICATION_NOTIFY_POST;

  public static final org.apache.dubbo.metrics.model.key.MetricsCat APPLICATION_NOTIFY_FINISH;

  public static final org.apache.dubbo.metrics.model.key.MetricsCat APPLICATION_DIRECTORY_POST;

  public static final org.apache.dubbo.metrics.model.key.MetricsCat SERVICE_REGISTER_POST;

  public static final org.apache.dubbo.metrics.model.key.MetricsCat SERVICE_REGISTER_FINISH;

  public static final org.apache.dubbo.metrics.model.key.MetricsCat SERVICE_REGISTER_ERROR;

  public static final org.apache.dubbo.metrics.model.key.MetricsCat SERVICE_SUBSCRIBE_POST;

  public static final org.apache.dubbo.metrics.model.key.MetricsCat SERVICE_SUBSCRIBE_FINISH;

  public static final org.apache.dubbo.metrics.model.key.MetricsCat SERVICE_SUBSCRIBE_ERROR;

  private static org.apache.dubbo.metrics.listener.AbstractMetricsKeyListener lambda$static$6(org.apache.dubbo.metrics.model.key.MetricsKey, org.apache.dubbo.metrics.model.key.MetricsPlaceValue, org.apache.dubbo.metrics.collector.CombMetricsCollector);
    Code:
       0: aload_0
       1: aload_2
       2: invokedynamic #2,  0              // InvokeDynamic #0:accept:(Lorg/apache/dubbo/metrics/collector/CombMetricsCollector;)Ljava/util/function/Consumer;
       7: invokestatic  #3                  // Method org/apache/dubbo/metrics/listener/AbstractMetricsKeyListener.onEvent:(Lorg/apache/dubbo/metrics/model/key/MetricsKey;Ljava/util/function/Consumer;)Lorg/apache/dubbo/metrics/listener/AbstractMetricsKeyListener;
      10: areturn

  private static void lambda$null$5(org.apache.dubbo.metrics.collector.CombMetricsCollector, org.apache.dubbo.metrics.event.TimeCounterEvent);
    Code:
       0: aload_1
       1: ldc           #4                  // String dirNum
       3: invokevirtual #5                  // Method org/apache/dubbo/metrics/event/TimeCounterEvent.getAttachmentValue:(Ljava/lang/String;)Ljava/lang/Object;
       6: checkcast     #6                  // class java/util/Map
       9: astore_2
      10: aload_2
      11: aload_0
      12: invokedynamic #7,  0              // InvokeDynamic #1:accept:(Lorg/apache/dubbo/metrics/collector/CombMetricsCollector;)Ljava/util/function/BiConsumer;
      17: invokeinterface #8,  2            // InterfaceMethod java/util/Map.forEach:(Ljava/util/function/BiConsumer;)V
      22: return

  private static void lambda$null$4(org.apache.dubbo.metrics.collector.CombMetricsCollector, org.apache.dubbo.metrics.model.key.MetricsKey, java.util.Map);
    Code:
       0: aload_2
       1: aload_0
       2: aload_1
       3: invokedynamic #9,  0              // InvokeDynamic #2:accept:(Lorg/apache/dubbo/metrics/collector/CombMetricsCollector;Lorg/apache/dubbo/metrics/model/key/MetricsKey;)Ljava/util/function/BiConsumer;
       8: invokeinterface #8,  2            // InterfaceMethod java/util/Map.forEach:(Ljava/util/function/BiConsumer;)V
      13: return

  private static void lambda$null$3(org.apache.dubbo.metrics.collector.CombMetricsCollector, org.apache.dubbo.metrics.model.key.MetricsKey, java.lang.String, java.lang.Integer);
    Code:
       0: aload_0
       1: new           #10                 // class org/apache/dubbo/metrics/model/key/MetricsKeyWrapper
       4: dup
       5: aload_1
       6: getstatic     #11                 // Field org/apache/dubbo/metrics/registry/RegistryMetricsConstants.OP_TYPE_DIRECTORY:Lorg/apache/dubbo/metrics/model/key/MetricsPlaceValue;
       9: invokespecial #12                 // Method org/apache/dubbo/metrics/model/key/MetricsKeyWrapper."<init>":(Lorg/apache/dubbo/metrics/model/key/MetricsKey;Lorg/apache/dubbo/metrics/model/key/MetricsPlaceValue;)V
      12: aload_2
      13: aload_3
      14: invokevirtual #13                 // Method java/lang/Integer.intValue:()I
      17: invokevirtual #14                 // Method org/apache/dubbo/metrics/collector/CombMetricsCollector.setNum:(Lorg/apache/dubbo/metrics/model/key/MetricsKeyWrapper;Ljava/lang/String;I)V
      20: return

  private static org.apache.dubbo.metrics.listener.AbstractMetricsKeyListener lambda$static$2(org.apache.dubbo.metrics.model.key.MetricsKey, org.apache.dubbo.metrics.model.key.MetricsPlaceValue, org.apache.dubbo.metrics.collector.CombMetricsCollector);
    Code:
       0: aload_0
       1: aload_2
       2: aload_1
       3: aload_0
       4: invokedynamic #15,  0             // InvokeDynamic #3:accept:(Lorg/apache/dubbo/metrics/collector/CombMetricsCollector;Lorg/apache/dubbo/metrics/model/key/MetricsPlaceValue;Lorg/apache/dubbo/metrics/model/key/MetricsKey;)Ljava/util/function/Consumer;
       9: invokestatic  #16                 // Method org/apache/dubbo/metrics/listener/AbstractMetricsKeyListener.onFinish:(Lorg/apache/dubbo/metrics/model/key/MetricsKey;Ljava/util/function/Consumer;)Lorg/apache/dubbo/metrics/listener/AbstractMetricsKeyListener;
      12: areturn

  private static void lambda$null$1(org.apache.dubbo.metrics.collector.CombMetricsCollector, org.apache.dubbo.metrics.model.key.MetricsPlaceValue, org.apache.dubbo.metrics.model.key.MetricsKey, org.apache.dubbo.metrics.event.TimeCounterEvent);
    Code:
       0: aload_0
       1: aload_3
       2: invokevirtual #17                 // Method org/apache/dubbo/metrics/event/TimeCounterEvent.appName:()Ljava/lang/String;
       5: aload_1
       6: invokevirtual #18                 // Method org/apache/dubbo/metrics/model/key/MetricsPlaceValue.getType:()Ljava/lang/String;
       9: aload_3
      10: invokevirtual #19                 // Method org/apache/dubbo/metrics/event/TimeCounterEvent.getTimePair:()Lorg/apache/dubbo/metrics/model/TimePair;
      13: invokevirtual #20                 // Method org/apache/dubbo/metrics/model/TimePair.calc:()J
      16: invokestatic  #21                 // Method java/lang/Long.valueOf:(J)Ljava/lang/Long;
      19: invokevirtual #22                 // Method org/apache/dubbo/metrics/collector/CombMetricsCollector.addRt:(Ljava/lang/String;Ljava/lang/String;Ljava/lang/Long;)V
      22: aload_3
      23: ldc           #23                 // String lastNumMap
      25: invokevirtual #5                  // Method org/apache/dubbo/metrics/event/TimeCounterEvent.getAttachmentValue:(Ljava/lang/String;)Ljava/lang/Object;
      28: checkcast     #6                  // class java/util/Map
      31: invokestatic  #24                 // Method java/util/Collections.unmodifiableMap:(Ljava/util/Map;)Ljava/util/Map;
      34: astore        4
      36: aload         4
      38: aload_0
      39: aload_2
      40: invokedynamic #25,  0             // InvokeDynamic #4:accept:(Lorg/apache/dubbo/metrics/collector/CombMetricsCollector;Lorg/apache/dubbo/metrics/model/key/MetricsKey;)Ljava/util/function/BiConsumer;
      45: invokeinterface #8,  2            // InterfaceMethod java/util/Map.forEach:(Ljava/util/function/BiConsumer;)V
      50: return

  private static void lambda$null$0(org.apache.dubbo.metrics.collector.CombMetricsCollector, org.apache.dubbo.metrics.model.key.MetricsKey, java.lang.String, java.lang.Integer);
    Code:
       0: aload_0
       1: new           #10                 // class org/apache/dubbo/metrics/model/key/MetricsKeyWrapper
       4: dup
       5: aload_1
       6: getstatic     #26                 // Field org/apache/dubbo/metrics/registry/RegistryMetricsConstants.OP_TYPE_NOTIFY:Lorg/apache/dubbo/metrics/model/key/MetricsPlaceValue;
       9: invokespecial #12                 // Method org/apache/dubbo/metrics/model/key/MetricsKeyWrapper."<init>":(Lorg/apache/dubbo/metrics/model/key/MetricsKey;Lorg/apache/dubbo/metrics/model/key/MetricsPlaceValue;)V
      12: aload_2
      13: aload_3
      14: invokevirtual #13                 // Method java/lang/Integer.intValue:()I
      17: invokevirtual #14                 // Method org/apache/dubbo/metrics/collector/CombMetricsCollector.setNum:(Lorg/apache/dubbo/metrics/model/key/MetricsKeyWrapper;Ljava/lang/String;I)V
      20: return

  static {};
    Code:
       0: new           #27                 // class org/apache/dubbo/metrics/model/key/MetricsCat
       3: dup
       4: getstatic     #28                 // Field org/apache/dubbo/metrics/model/key/MetricsKey.REGISTER_METRIC_REQUESTS:Lorg/apache/dubbo/metrics/model/key/MetricsKey;
       7: invokedynamic #29,  0             // InvokeDynamic #5:apply:()Ljava/util/function/BiFunction;
      12: invokespecial #30                 // Method org/apache/dubbo/metrics/model/key/MetricsCat."<init>":(Lorg/apache/dubbo/metrics/model/key/MetricsKey;Ljava/util/function/BiFunction;)V
      15: putstatic     #31                 // Field APPLICATION_REGISTER_POST:Lorg/apache/dubbo/metrics/model/key/MetricsCat;
      18: new           #27                 // class org/apache/dubbo/metrics/model/key/MetricsCat
      21: dup
      22: getstatic     #32                 // Field org/apache/dubbo/metrics/model/key/MetricsKey.REGISTER_METRIC_REQUESTS_SUCCEED:Lorg/apache/dubbo/metrics/model/key/MetricsKey;
      25: invokedynamic #33,  0             // InvokeDynamic #6:apply:()Lorg/apache/dubbo/metrics/model/key/MetricsCat$TpFunction;
      30: invokespecial #34                 // Method org/apache/dubbo/metrics/model/key/MetricsCat."<init>":(Lorg/apache/dubbo/metrics/model/key/MetricsKey;Lorg/apache/dubbo/metrics/model/key/MetricsCat$TpFunction;)V
      33: putstatic     #35                 // Field APPLICATION_REGISTER_FINISH:Lorg/apache/dubbo/metrics/model/key/MetricsCat;
      36: new           #27                 // class org/apache/dubbo/metrics/model/key/MetricsCat
      39: dup
      40: getstatic     #36                 // Field org/apache/dubbo/metrics/model/key/MetricsKey.REGISTER_METRIC_REQUESTS_FAILED:Lorg/apache/dubbo/metrics/model/key/MetricsKey;
      43: invokedynamic #37,  0             // InvokeDynamic #7:apply:()Lorg/apache/dubbo/metrics/model/key/MetricsCat$TpFunction;
      48: invokespecial #34                 // Method org/apache/dubbo/metrics/model/key/MetricsCat."<init>":(Lorg/apache/dubbo/metrics/model/key/MetricsKey;Lorg/apache/dubbo/metrics/model/key/MetricsCat$TpFunction;)V
      51: putstatic     #38                 // Field APPLICATION_REGISTER_ERROR:Lorg/apache/dubbo/metrics/model/key/MetricsCat;
      54: new           #27                 // class org/apache/dubbo/metrics/model/key/MetricsCat
      57: dup
      58: getstatic     #39                 // Field org/apache/dubbo/metrics/model/key/MetricsKey.SUBSCRIBE_METRIC_NUM:Lorg/apache/dubbo/metrics/model/key/MetricsKey;
      61: invokedynamic #29,  0             // InvokeDynamic #5:apply:()Ljava/util/function/BiFunction;
      66: invokespecial #30                 // Method org/apache/dubbo/metrics/model/key/MetricsCat."<init>":(Lorg/apache/dubbo/metrics/model/key/MetricsKey;Ljava/util/function/BiFunction;)V
      69: putstatic     #40                 // Field APPLICATION_SUBSCRIBE_POST:Lorg/apache/dubbo/metrics/model/key/MetricsCat;
      72: new           #27                 // class org/apache/dubbo/metrics/model/key/MetricsCat
      75: dup
      76: getstatic     #41                 // Field org/apache/dubbo/metrics/model/key/MetricsKey.SUBSCRIBE_METRIC_NUM_SUCCEED:Lorg/apache/dubbo/metrics/model/key/MetricsKey;
      79: invokedynamic #33,  0             // InvokeDynamic #6:apply:()Lorg/apache/dubbo/metrics/model/key/MetricsCat$TpFunction;
      84: invokespecial #34                 // Method org/apache/dubbo/metrics/model/key/MetricsCat."<init>":(Lorg/apache/dubbo/metrics/model/key/MetricsKey;Lorg/apache/dubbo/metrics/model/key/MetricsCat$TpFunction;)V
      87: putstatic     #42                 // Field APPLICATION_SUBSCRIBE_FINISH:Lorg/apache/dubbo/metrics/model/key/MetricsCat;
      90: new           #27                 // class org/apache/dubbo/metrics/model/key/MetricsCat
      93: dup
      94: getstatic     #43                 // Field org/apache/dubbo/metrics/model/key/MetricsKey.SUBSCRIBE_METRIC_NUM_FAILED:Lorg/apache/dubbo/metrics/model/key/MetricsKey;
      97: invokedynamic #37,  0             // InvokeDynamic #7:apply:()Lorg/apache/dubbo/metrics/model/key/MetricsCat$TpFunction;
     102: invokespecial #34                 // Method org/apache/dubbo/metrics/model/key/MetricsCat."<init>":(Lorg/apache/dubbo/metrics/model/key/MetricsKey;Lorg/apache/dubbo/metrics/model/key/MetricsCat$TpFunction;)V
     105: putstatic     #44                 // Field APPLICATION_SUBSCRIBE_ERROR:Lorg/apache/dubbo/metrics/model/key/MetricsCat;
     108: new           #27                 // class org/apache/dubbo/metrics/model/key/MetricsCat
     111: dup
     112: getstatic     #45                 // Field org/apache/dubbo/metrics/model/key/MetricsKey.NOTIFY_METRIC_REQUESTS:Lorg/apache/dubbo/metrics/model/key/MetricsKey;
     115: invokedynamic #29,  0             // InvokeDynamic #5:apply:()Ljava/util/function/BiFunction;
     120: invokespecial #30                 // Method org/apache/dubbo/metrics/model/key/MetricsCat."<init>":(Lorg/apache/dubbo/metrics/model/key/MetricsKey;Ljava/util/function/BiFunction;)V
     123: putstatic     #46                 // Field APPLICATION_NOTIFY_POST:Lorg/apache/dubbo/metrics/model/key/MetricsCat;
     126: new           #27                 // class org/apache/dubbo/metrics/model/key/MetricsCat
     129: dup
     130: getstatic     #47                 // Field org/apache/dubbo/metrics/model/key/MetricsKey.NOTIFY_METRIC_NUM_LAST:Lorg/apache/dubbo/metrics/model/key/MetricsKey;
     133: invokedynamic #48,  0             // InvokeDynamic #8:apply:()Lorg/apache/dubbo/metrics/model/key/MetricsCat$TpFunction;
     138: invokespecial #34                 // Method org/apache/dubbo/metrics/model/key/MetricsCat."<init>":(Lorg/apache/dubbo/metrics/model/key/MetricsKey;Lorg/apache/dubbo/metrics/model/key/MetricsCat$TpFunction;)V
     141: putstatic     #49                 // Field APPLICATION_NOTIFY_FINISH:Lorg/apache/dubbo/metrics/model/key/MetricsCat;
     144: new           #27                 // class org/apache/dubbo/metrics/model/key/MetricsCat
     147: dup
     148: getstatic     #50                 // Field org/apache/dubbo/metrics/model/key/MetricsKey.DIRECTORY_METRIC_NUM_VALID:Lorg/apache/dubbo/metrics/model/key/MetricsKey;
     151: invokedynamic #51,  0             // InvokeDynamic #9:apply:()Lorg/apache/dubbo/metrics/model/key/MetricsCat$TpFunction;
     156: invokespecial #34                 // Method org/apache/dubbo/metrics/model/key/MetricsCat."<init>":(Lorg/apache/dubbo/metrics/model/key/MetricsKey;Lorg/apache/dubbo/metrics/model/key/MetricsCat$TpFunction;)V
     159: putstatic     #52                 // Field APPLICATION_DIRECTORY_POST:Lorg/apache/dubbo/metrics/model/key/MetricsCat;
     162: new           #27                 // class org/apache/dubbo/metrics/model/key/MetricsCat
     165: dup
     166: getstatic     #53                 // Field org/apache/dubbo/metrics/model/key/MetricsKey.SERVICE_REGISTER_METRIC_REQUESTS:Lorg/apache/dubbo/metrics/model/key/MetricsKey;
     169: invokedynamic #54,  0             // InvokeDynamic #10:apply:()Lorg/apache/dubbo/metrics/model/key/MetricsCat$TpFunction;
     174: invokespecial #34                 // Method org/apache/dubbo/metrics/model/key/MetricsCat."<init>":(Lorg/apache/dubbo/metrics/model/key/MetricsKey;Lorg/apache/dubbo/metrics/model/key/MetricsCat$TpFunction;)V
     177: putstatic     #55                 // Field SERVICE_REGISTER_POST:Lorg/apache/dubbo/metrics/model/key/MetricsCat;
     180: new           #27                 // class org/apache/dubbo/metrics/model/key/MetricsCat
     183: dup
     184: getstatic     #56                 // Field org/apache/dubbo/metrics/model/key/MetricsKey.SERVICE_REGISTER_METRIC_REQUESTS_SUCCEED:Lorg/apache/dubbo/metrics/model/key/MetricsKey;
     187: invokedynamic #57,  0             // InvokeDynamic #11:apply:()Lorg/apache/dubbo/metrics/model/key/MetricsCat$TpFunction;
     192: invokespecial #34                 // Method org/apache/dubbo/metrics/model/key/MetricsCat."<init>":(Lorg/apache/dubbo/metrics/model/key/MetricsKey;Lorg/apache/dubbo/metrics/model/key/MetricsCat$TpFunction;)V
     195: putstatic     #58                 // Field SERVICE_REGISTER_FINISH:Lorg/apache/dubbo/metrics/model/key/MetricsCat;
     198: new           #27                 // class org/apache/dubbo/metrics/model/key/MetricsCat
     201: dup
     202: getstatic     #59                 // Field org/apache/dubbo/metrics/model/key/MetricsKey.SERVICE_REGISTER_METRIC_REQUESTS_FAILED:Lorg/apache/dubbo/metrics/model/key/MetricsKey;
     205: invokedynamic #60,  0             // InvokeDynamic #12:apply:()Lorg/apache/dubbo/metrics/model/key/MetricsCat$TpFunction;
     210: invokespecial #34                 // Method org/apache/dubbo/metrics/model/key/MetricsCat."<init>":(Lorg/apache/dubbo/metrics/model/key/MetricsKey;Lorg/apache/dubbo/metrics/model/key/MetricsCat$TpFunction;)V
     213: putstatic     #61                 // Field SERVICE_REGISTER_ERROR:Lorg/apache/dubbo/metrics/model/key/MetricsCat;
     216: new           #27                 // class org/apache/dubbo/metrics/model/key/MetricsCat
     219: dup
     220: getstatic     #62                 // Field org/apache/dubbo/metrics/model/key/MetricsKey.SERVICE_SUBSCRIBE_METRIC_NUM:Lorg/apache/dubbo/metrics/model/key/MetricsKey;
     223: invokedynamic #54,  0             // InvokeDynamic #10:apply:()Lorg/apache/dubbo/metrics/model/key/MetricsCat$TpFunction;
     228: invokespecial #34                 // Method org/apache/dubbo/metrics/model/key/MetricsCat."<init>":(Lorg/apache/dubbo/metrics/model/key/MetricsKey;Lorg/apache/dubbo/metrics/model/key/MetricsCat$TpFunction;)V
     231: putstatic     #63                 // Field SERVICE_SUBSCRIBE_POST:Lorg/apache/dubbo/metrics/model/key/MetricsCat;
     234: new           #27                 // class org/apache/dubbo/metrics/model/key/MetricsCat
     237: dup
     238: getstatic     #64                 // Field org/apache/dubbo/metrics/model/key/MetricsKey.SERVICE_SUBSCRIBE_METRIC_NUM_SUCCEED:Lorg/apache/dubbo/metrics/model/key/MetricsKey;
     241: invokedynamic #57,  0             // InvokeDynamic #11:apply:()Lorg/apache/dubbo/metrics/model/key/MetricsCat$TpFunction;
     246: invokespecial #34                 // Method org/apache/dubbo/metrics/model/key/MetricsCat."<init>":(Lorg/apache/dubbo/metrics/model/key/MetricsKey;Lorg/apache/dubbo/metrics/model/key/MetricsCat$TpFunction;)V
     249: putstatic     #65                 // Field SERVICE_SUBSCRIBE_FINISH:Lorg/apache/dubbo/metrics/model/key/MetricsCat;
     252: new           #27                 // class org/apache/dubbo/metrics/model/key/MetricsCat
     255: dup
     256: getstatic     #66                 // Field org/apache/dubbo/metrics/model/key/MetricsKey.SERVICE_SUBSCRIBE_METRIC_NUM_FAILED:Lorg/apache/dubbo/metrics/model/key/MetricsKey;
     259: invokedynamic #60,  0             // InvokeDynamic #12:apply:()Lorg/apache/dubbo/metrics/model/key/MetricsCat$TpFunction;
     264: invokespecial #34                 // Method org/apache/dubbo/metrics/model/key/MetricsCat."<init>":(Lorg/apache/dubbo/metrics/model/key/MetricsKey;Lorg/apache/dubbo/metrics/model/key/MetricsCat$TpFunction;)V
     267: putstatic     #67                 // Field SERVICE_SUBSCRIBE_ERROR:Lorg/apache/dubbo/metrics/model/key/MetricsCat;
     270: return
}
