Compiled from "RegistrySubDispatcher.java"
public final class org.apache.dubbo.metrics.registry.event.RegistrySubDispatcher extends org.apache.dubbo.metrics.event.SimpleMetricsEventMulticaster {
  public org.apache.dubbo.metrics.registry.event.RegistrySubDispatcher(org.apache.dubbo.metrics.registry.collector.RegistryMetricsCollector);
    Code:
       0: aload_0
       1: invokespecial #1                  // Method org/apache/dubbo/metrics/event/SimpleMetricsEventMulticaster."<init>":()V
       4: getstatic     #2                  // Field org/apache/dubbo/metrics/registry/event/RegistrySubDispatcher$CategorySet.ALL:Ljava/util/List;
       7: aload_0
       8: aload_1
       9: invokedynamic #3,  0              // InvokeDynamic #0:accept:(Lorg/apache/dubbo/metrics/registry/event/RegistrySubDispatcher;Lorg/apache/dubbo/metrics/registry/collector/RegistryMetricsCollector;)Ljava/util/function/Consumer;
      14: invokeinterface #4,  2            // InterfaceMethod java/util/List.forEach:(Ljava/util/function/Consumer;)V
      19: return

  private void lambda$new$0(org.apache.dubbo.metrics.registry.collector.RegistryMetricsCollector, org.apache.dubbo.metrics.model.key.CategoryOverall);
    Code:
       0: aload_0
       1: aload_2
       2: invokevirtual #5                  // Method org/apache/dubbo/metrics/model/key/CategoryOverall.getPost:()Lorg/apache/dubbo/metrics/model/key/MetricsCat;
       5: invokevirtual #6                  // Method org/apache/dubbo/metrics/model/key/MetricsCat.getEventFunc:()Ljava/util/function/Function;
       8: aload_1
       9: invokeinterface #7,  2            // InterfaceMethod java/util/function/Function.apply:(Ljava/lang/Object;)Ljava/lang/Object;
      14: checkcast     #8                  // class org/apache/dubbo/metrics/listener/MetricsListener
      17: invokespecial #9                  // Method org/apache/dubbo/metrics/event/SimpleMetricsEventMulticaster.addListener:(Lorg/apache/dubbo/metrics/listener/MetricsListener;)V
      20: aload_2
      21: invokevirtual #10                 // Method org/apache/dubbo/metrics/model/key/CategoryOverall.getFinish:()Lorg/apache/dubbo/metrics/model/key/MetricsCat;
      24: ifnull        47
      27: aload_0
      28: aload_2
      29: invokevirtual #10                 // Method org/apache/dubbo/metrics/model/key/CategoryOverall.getFinish:()Lorg/apache/dubbo/metrics/model/key/MetricsCat;
      32: invokevirtual #6                  // Method org/apache/dubbo/metrics/model/key/MetricsCat.getEventFunc:()Ljava/util/function/Function;
      35: aload_1
      36: invokeinterface #7,  2            // InterfaceMethod java/util/function/Function.apply:(Ljava/lang/Object;)Ljava/lang/Object;
      41: checkcast     #8                  // class org/apache/dubbo/metrics/listener/MetricsListener
      44: invokespecial #9                  // Method org/apache/dubbo/metrics/event/SimpleMetricsEventMulticaster.addListener:(Lorg/apache/dubbo/metrics/listener/MetricsListener;)V
      47: aload_2
      48: invokevirtual #11                 // Method org/apache/dubbo/metrics/model/key/CategoryOverall.getError:()Lorg/apache/dubbo/metrics/model/key/MetricsCat;
      51: ifnull        74
      54: aload_0
      55: aload_2
      56: invokevirtual #11                 // Method org/apache/dubbo/metrics/model/key/CategoryOverall.getError:()Lorg/apache/dubbo/metrics/model/key/MetricsCat;
      59: invokevirtual #6                  // Method org/apache/dubbo/metrics/model/key/MetricsCat.getEventFunc:()Ljava/util/function/Function;
      62: aload_1
      63: invokeinterface #7,  2            // InterfaceMethod java/util/function/Function.apply:(Ljava/lang/Object;)Ljava/lang/Object;
      68: checkcast     #8                  // class org/apache/dubbo/metrics/listener/MetricsListener
      71: invokespecial #9                  // Method org/apache/dubbo/metrics/event/SimpleMetricsEventMulticaster.addListener:(Lorg/apache/dubbo/metrics/listener/MetricsListener;)V
      74: return
}
