Compiled from "RegistryEvent.java"
public class org.apache.dubbo.metrics.registry.event.RegistryEvent extends org.apache.dubbo.metrics.event.TimeCounterEvent {
  public org.apache.dubbo.metrics.registry.event.RegistryEvent(org.apache.dubbo.rpc.model.ApplicationModel, org.apache.dubbo.metrics.model.key.TypeWrapper);
    Code:
       0: aload_0
       1: aload_1
       2: aload_2
       3: invokespecial #2                  // Method org/apache/dubbo/metrics/event/TimeCounterEvent."<init>":(Lorg/apache/dubbo/rpc/model/ApplicationModel;Lorg/apache/dubbo/metrics/model/key/TypeWrapper;)V
       6: aload_0
       7: invokevirtual #3                  // Method getSource:()Lorg/apache/dubbo/rpc/model/ApplicationModel;
      10: invokevirtual #4                  // Method org/apache/dubbo/rpc/model/ApplicationModel.getBeanFactory:()Lorg/apache/dubbo/common/beans/factory/ScopeBeanFactory;
      13: astore_3
      14: aload_3
      15: invokevirtual #5                  // Method org/apache/dubbo/common/beans/factory/ScopeBeanFactory.isDestroyed:()Z
      18: ifne          54
      21: aload_3
      22: ldc           #6                  // class org/apache/dubbo/metrics/registry/collector/RegistryMetricsCollector
      24: invokevirtual #7                  // Method org/apache/dubbo/common/beans/factory/ScopeBeanFactory.getBean:(Ljava/lang/Class;)Ljava/lang/Object;
      27: checkcast     #6                  // class org/apache/dubbo/metrics/registry/collector/RegistryMetricsCollector
      30: astore        4
      32: aload_0
      33: aload         4
      35: ifnull        50
      38: aload         4
      40: invokevirtual #8                  // Method org/apache/dubbo/metrics/registry/collector/RegistryMetricsCollector.isCollectEnabled:()Z
      43: ifeq          50
      46: iconst_1
      47: goto          51
      50: iconst_0
      51: invokespecial #9                  // Method org/apache/dubbo/metrics/event/TimeCounterEvent.setAvailable:(Z)V
      54: return

  public static org.apache.dubbo.metrics.registry.event.RegistryEvent toRegisterEvent(org.apache.dubbo.rpc.model.ApplicationModel);
    Code:
       0: new           #10                 // class org/apache/dubbo/metrics/registry/event/RegistryEvent
       3: dup
       4: aload_0
       5: new           #11                 // class org/apache/dubbo/metrics/model/key/TypeWrapper
       8: dup
       9: getstatic     #12                 // Field org/apache/dubbo/metrics/model/key/MetricsLevel.APP:Lorg/apache/dubbo/metrics/model/key/MetricsLevel;
      12: getstatic     #13                 // Field org/apache/dubbo/metrics/model/key/MetricsKey.REGISTER_METRIC_REQUESTS:Lorg/apache/dubbo/metrics/model/key/MetricsKey;
      15: getstatic     #14                 // Field org/apache/dubbo/metrics/model/key/MetricsKey.REGISTER_METRIC_REQUESTS_SUCCEED:Lorg/apache/dubbo/metrics/model/key/MetricsKey;
      18: getstatic     #15                 // Field org/apache/dubbo/metrics/model/key/MetricsKey.REGISTER_METRIC_REQUESTS_FAILED:Lorg/apache/dubbo/metrics/model/key/MetricsKey;
      21: invokespecial #16                 // Method org/apache/dubbo/metrics/model/key/TypeWrapper."<init>":(Lorg/apache/dubbo/metrics/model/key/MetricsLevel;Lorg/apache/dubbo/metrics/model/key/MetricsKey;Lorg/apache/dubbo/metrics/model/key/MetricsKey;Lorg/apache/dubbo/metrics/model/key/MetricsKey;)V
      24: invokespecial #17                 // Method "<init>":(Lorg/apache/dubbo/rpc/model/ApplicationModel;Lorg/apache/dubbo/metrics/model/key/TypeWrapper;)V
      27: areturn

  public static org.apache.dubbo.metrics.registry.event.RegistryEvent toSubscribeEvent(org.apache.dubbo.rpc.model.ApplicationModel);
    Code:
       0: new           #10                 // class org/apache/dubbo/metrics/registry/event/RegistryEvent
       3: dup
       4: aload_0
       5: new           #11                 // class org/apache/dubbo/metrics/model/key/TypeWrapper
       8: dup
       9: getstatic     #12                 // Field org/apache/dubbo/metrics/model/key/MetricsLevel.APP:Lorg/apache/dubbo/metrics/model/key/MetricsLevel;
      12: getstatic     #18                 // Field org/apache/dubbo/metrics/model/key/MetricsKey.SUBSCRIBE_METRIC_NUM:Lorg/apache/dubbo/metrics/model/key/MetricsKey;
      15: getstatic     #19                 // Field org/apache/dubbo/metrics/model/key/MetricsKey.SUBSCRIBE_METRIC_NUM_SUCCEED:Lorg/apache/dubbo/metrics/model/key/MetricsKey;
      18: getstatic     #20                 // Field org/apache/dubbo/metrics/model/key/MetricsKey.SUBSCRIBE_METRIC_NUM_FAILED:Lorg/apache/dubbo/metrics/model/key/MetricsKey;
      21: invokespecial #16                 // Method org/apache/dubbo/metrics/model/key/TypeWrapper."<init>":(Lorg/apache/dubbo/metrics/model/key/MetricsLevel;Lorg/apache/dubbo/metrics/model/key/MetricsKey;Lorg/apache/dubbo/metrics/model/key/MetricsKey;Lorg/apache/dubbo/metrics/model/key/MetricsKey;)V
      24: invokespecial #17                 // Method "<init>":(Lorg/apache/dubbo/rpc/model/ApplicationModel;Lorg/apache/dubbo/metrics/model/key/TypeWrapper;)V
      27: areturn

  public static org.apache.dubbo.metrics.registry.event.RegistryEvent toNotifyEvent(org.apache.dubbo.rpc.model.ApplicationModel);
    Code:
       0: new           #21                 // class org/apache/dubbo/metrics/registry/event/RegistryEvent$1
       3: dup
       4: aload_0
       5: new           #11                 // class org/apache/dubbo/metrics/model/key/TypeWrapper
       8: dup
       9: getstatic     #12                 // Field org/apache/dubbo/metrics/model/key/MetricsLevel.APP:Lorg/apache/dubbo/metrics/model/key/MetricsLevel;
      12: getstatic     #22                 // Field org/apache/dubbo/metrics/model/key/MetricsKey.NOTIFY_METRIC_REQUESTS:Lorg/apache/dubbo/metrics/model/key/MetricsKey;
      15: getstatic     #23                 // Field org/apache/dubbo/metrics/model/key/MetricsKey.NOTIFY_METRIC_NUM_LAST:Lorg/apache/dubbo/metrics/model/key/MetricsKey;
      18: aconst_null
      19: checkcast     #24                 // class org/apache/dubbo/metrics/model/key/MetricsKey
      22: invokespecial #16                 // Method org/apache/dubbo/metrics/model/key/TypeWrapper."<init>":(Lorg/apache/dubbo/metrics/model/key/MetricsLevel;Lorg/apache/dubbo/metrics/model/key/MetricsKey;Lorg/apache/dubbo/metrics/model/key/MetricsKey;Lorg/apache/dubbo/metrics/model/key/MetricsKey;)V
      25: invokespecial #25                 // Method org/apache/dubbo/metrics/registry/event/RegistryEvent$1."<init>":(Lorg/apache/dubbo/rpc/model/ApplicationModel;Lorg/apache/dubbo/metrics/model/key/TypeWrapper;)V
      28: areturn

  public static org.apache.dubbo.metrics.registry.event.RegistryEvent toRsEvent(org.apache.dubbo.rpc.model.ApplicationModel, java.lang.String, int);
    Code:
       0: new           #10                 // class org/apache/dubbo/metrics/registry/event/RegistryEvent
       3: dup
       4: aload_0
       5: new           #11                 // class org/apache/dubbo/metrics/model/key/TypeWrapper
       8: dup
       9: getstatic     #26                 // Field org/apache/dubbo/metrics/model/key/MetricsLevel.SERVICE:Lorg/apache/dubbo/metrics/model/key/MetricsLevel;
      12: getstatic     #27                 // Field org/apache/dubbo/metrics/model/key/MetricsKey.SERVICE_REGISTER_METRIC_REQUESTS:Lorg/apache/dubbo/metrics/model/key/MetricsKey;
      15: getstatic     #28                 // Field org/apache/dubbo/metrics/model/key/MetricsKey.SERVICE_REGISTER_METRIC_REQUESTS_SUCCEED:Lorg/apache/dubbo/metrics/model/key/MetricsKey;
      18: getstatic     #29                 // Field org/apache/dubbo/metrics/model/key/MetricsKey.SERVICE_REGISTER_METRIC_REQUESTS_FAILED:Lorg/apache/dubbo/metrics/model/key/MetricsKey;
      21: invokespecial #16                 // Method org/apache/dubbo/metrics/model/key/TypeWrapper."<init>":(Lorg/apache/dubbo/metrics/model/key/MetricsLevel;Lorg/apache/dubbo/metrics/model/key/MetricsKey;Lorg/apache/dubbo/metrics/model/key/MetricsKey;Lorg/apache/dubbo/metrics/model/key/MetricsKey;)V
      24: invokespecial #17                 // Method "<init>":(Lorg/apache/dubbo/rpc/model/ApplicationModel;Lorg/apache/dubbo/metrics/model/key/TypeWrapper;)V
      27: astore_3
      28: aload_3
      29: ldc           #30                 // String serviceKey
      31: aload_1
      32: invokevirtual #31                 // Method putAttachment:(Ljava/lang/String;Ljava/lang/Object;)V
      35: aload_3
      36: ldc           #32                 // String size
      38: iload_2
      39: invokestatic  #33                 // Method java/lang/Integer.valueOf:(I)Ljava/lang/Integer;
      42: invokevirtual #31                 // Method putAttachment:(Ljava/lang/String;Ljava/lang/Object;)V
      45: aload_3
      46: areturn

  public static org.apache.dubbo.metrics.registry.event.RegistryEvent toSsEvent(org.apache.dubbo.rpc.model.ApplicationModel, java.lang.String);
    Code:
       0: new           #10                 // class org/apache/dubbo/metrics/registry/event/RegistryEvent
       3: dup
       4: aload_0
       5: new           #11                 // class org/apache/dubbo/metrics/model/key/TypeWrapper
       8: dup
       9: getstatic     #26                 // Field org/apache/dubbo/metrics/model/key/MetricsLevel.SERVICE:Lorg/apache/dubbo/metrics/model/key/MetricsLevel;
      12: getstatic     #34                 // Field org/apache/dubbo/metrics/model/key/MetricsKey.SERVICE_SUBSCRIBE_METRIC_NUM:Lorg/apache/dubbo/metrics/model/key/MetricsKey;
      15: getstatic     #35                 // Field org/apache/dubbo/metrics/model/key/MetricsKey.SERVICE_SUBSCRIBE_METRIC_NUM_SUCCEED:Lorg/apache/dubbo/metrics/model/key/MetricsKey;
      18: getstatic     #36                 // Field org/apache/dubbo/metrics/model/key/MetricsKey.SERVICE_SUBSCRIBE_METRIC_NUM_FAILED:Lorg/apache/dubbo/metrics/model/key/MetricsKey;
      21: invokespecial #16                 // Method org/apache/dubbo/metrics/model/key/TypeWrapper."<init>":(Lorg/apache/dubbo/metrics/model/key/MetricsLevel;Lorg/apache/dubbo/metrics/model/key/MetricsKey;Lorg/apache/dubbo/metrics/model/key/MetricsKey;Lorg/apache/dubbo/metrics/model/key/MetricsKey;)V
      24: invokespecial #17                 // Method "<init>":(Lorg/apache/dubbo/rpc/model/ApplicationModel;Lorg/apache/dubbo/metrics/model/key/TypeWrapper;)V
      27: astore_2
      28: aload_2
      29: ldc           #30                 // String serviceKey
      31: aload_1
      32: invokevirtual #31                 // Method putAttachment:(Ljava/lang/String;Ljava/lang/Object;)V
      35: aload_2
      36: areturn

  public static org.apache.dubbo.metrics.registry.event.RegistryEvent refreshDirectoryEvent(org.apache.dubbo.rpc.model.ApplicationModel, java.util.Map<org.apache.dubbo.metrics.model.key.MetricsKey, java.util.Map<java.lang.String, java.lang.Integer>>);
    Code:
       0: new           #10                 // class org/apache/dubbo/metrics/registry/event/RegistryEvent
       3: dup
       4: aload_0
       5: new           #11                 // class org/apache/dubbo/metrics/model/key/TypeWrapper
       8: dup
       9: getstatic     #12                 // Field org/apache/dubbo/metrics/model/key/MetricsLevel.APP:Lorg/apache/dubbo/metrics/model/key/MetricsLevel;
      12: getstatic     #37                 // Field org/apache/dubbo/metrics/model/key/MetricsKey.DIRECTORY_METRIC_NUM_VALID:Lorg/apache/dubbo/metrics/model/key/MetricsKey;
      15: aconst_null
      16: aconst_null
      17: invokespecial #16                 // Method org/apache/dubbo/metrics/model/key/TypeWrapper."<init>":(Lorg/apache/dubbo/metrics/model/key/MetricsLevel;Lorg/apache/dubbo/metrics/model/key/MetricsKey;Lorg/apache/dubbo/metrics/model/key/MetricsKey;Lorg/apache/dubbo/metrics/model/key/MetricsKey;)V
      20: invokespecial #17                 // Method "<init>":(Lorg/apache/dubbo/rpc/model/ApplicationModel;Lorg/apache/dubbo/metrics/model/key/TypeWrapper;)V
      23: astore_2
      24: aload_2
      25: ldc           #38                 // String dirNum
      27: aload_1
      28: invokevirtual #31                 // Method putAttachment:(Ljava/lang/String;Ljava/lang/Object;)V
      31: aload_2
      32: areturn
}
