Compiled from "DubboBootstrapStopedEvent.java"
public class org.apache.dubbo.config.spring.context.event.DubboBootstrapStopedEvent extends org.springframework.context.ApplicationEvent {
  public org.apache.dubbo.config.spring.context.event.DubboBootstrapStopedEvent(org.apache.dubbo.config.bootstrap.DubboBootstrap);
    Code:
       0: aload_0
       1: aload_1
       2: invokespecial #1                  // Method org/springframework/context/ApplicationEvent."<init>":(Ljava/lang/Object;)V
       5: return

  public org.apache.dubbo.config.bootstrap.DubboBootstrap getDubboBootstrap();
    Code:
       0: aload_0
       1: invokespecial #2                  // Method org/springframework/context/ApplicationEvent.getSource:()Ljava/lang/Object;
       4: checkcast     #3                  // class org/apache/dubbo/config/bootstrap/DubboBootstrap
       7: areturn
}
