Compiled from "DubboApplicationStateEvent.java"
public class org.apache.dubbo.config.spring.context.event.DubboApplicationStateEvent extends org.springframework.context.ApplicationEvent {
  private final org.apache.dubbo.common.deploy.DeployState state;

  private java.lang.Throwable cause;

  public org.apache.dubbo.config.spring.context.event.DubboApplicationStateEvent(org.apache.dubbo.rpc.model.ApplicationModel, org.apache.dubbo.common.deploy.DeployState);
    Code:
       0: aload_0
       1: aload_1
       2: invokespecial #1                  // Method org/springframework/context/ApplicationEvent."<init>":(Ljava/lang/Object;)V
       5: aload_0
       6: aload_2
       7: putfield      #2                  // Field state:Lorg/apache/dubbo/common/deploy/DeployState;
      10: return

  public org.apache.dubbo.config.spring.context.event.DubboApplicationStateEvent(org.apache.dubbo.rpc.model.ApplicationModel, org.apache.dubbo.common.deploy.DeployState, java.lang.Throwable);
    Code:
       0: aload_0
       1: aload_1
       2: invokespecial #1                  // Method org/springframework/context/ApplicationEvent."<init>":(Ljava/lang/Object;)V
       5: aload_0
       6: aload_2
       7: putfield      #2                  // Field state:Lorg/apache/dubbo/common/deploy/DeployState;
      10: aload_0
      11: aload_3
      12: putfield      #3                  // Field cause:Ljava/lang/Throwable;
      15: return

  public org.apache.dubbo.rpc.model.ApplicationModel getApplicationModel();
    Code:
       0: aload_0
       1: invokevirtual #4                  // Method getSource:()Ljava/lang/Object;
       4: checkcast     #5                  // class org/apache/dubbo/rpc/model/ApplicationModel
       7: areturn

  public org.apache.dubbo.common.deploy.DeployState getState();
    Code:
       0: aload_0
       1: getfield      #2                  // Field state:Lorg/apache/dubbo/common/deploy/DeployState;
       4: areturn

  public java.lang.Throwable getCause();
    Code:
       0: aload_0
       1: getfield      #3                  // Field cause:Ljava/lang/Throwable;
       4: areturn
}
