Compiled from "DubboConfigInitEvent.java"
public class org.apache.dubbo.config.spring.context.event.DubboConfigInitEvent extends org.springframework.context.ApplicationEvent {
  public org.apache.dubbo.config.spring.context.event.DubboConfigInitEvent(org.springframework.context.ApplicationContext);
    Code:
       0: aload_0
       1: aload_1
       2: invokespecial #1                  // Method org/springframework/context/ApplicationEvent."<init>":(Ljava/lang/Object;)V
       5: return

  public final org.springframework.context.ApplicationContext getApplicationContext();
    Code:
       0: aload_0
       1: invokevirtual #2                  // Method getSource:()Ljava/lang/Object;
       4: checkcast     #3                  // class org/springframework/context/ApplicationContext
       7: areturn
}
