Compiled from "ServiceBeanExportedEvent.java"
public class org.apache.dubbo.config.spring.context.event.ServiceBeanExportedEvent extends org.springframework.context.ApplicationEvent {
  public org.apache.dubbo.config.spring.context.event.ServiceBeanExportedEvent(org.apache.dubbo.config.spring.ServiceBean);
    Code:
       0: aload_0
       1: aload_1
       2: invokespecial #1                  // Method org/springframework/context/ApplicationEvent."<init>":(Ljava/lang/Object;)V
       5: return

  public org.apache.dubbo.config.spring.ServiceBean getServiceBean();
    Code:
       0: aload_0
       1: invokespecial #2                  // Method org/springframework/context/ApplicationEvent.getSource:()Ljava/lang/Object;
       4: checkcast     #3                  // class org/apache/dubbo/config/spring/ServiceBean
       7: areturn
}
