Compiled from "RdsProtocol.java"
public class org.apache.dubbo.registry.xds.util.protocol.impl.RdsProtocol extends org.apache.dubbo.registry.xds.util.protocol.AbstractProtocol<org.apache.dubbo.registry.xds.util.protocol.message.RouteResult, org.apache.dubbo.registry.xds.util.protocol.delta.DeltaRoute> {
  private static final org.apache.dubbo.common.logger.ErrorTypeAwareLogger logger;

  public org.apache.dubbo.registry.xds.util.protocol.impl.RdsProtocol(org.apache.dubbo.registry.xds.util.AdsObserver, io.envoyproxy.envoy.config.core.v3.Node, int);
    Code:
       0: aload_0
       1: aload_1
       2: aload_2
       3: iload_3
       4: invokespecial #2                  // Method org/apache/dubbo/registry/xds/util/protocol/AbstractProtocol."<init>":(Lorg/apache/dubbo/registry/xds/util/AdsObserver;Lio/envoyproxy/envoy/config/core/v3/Node;I)V
       7: return

  public java.lang.String getTypeUrl();
    Code:
       0: ldc           #3                  // String type.googleapis.com/envoy.config.route.v3.RouteConfiguration
       2: areturn

  protected java.util.Map<java.lang.String, org.apache.dubbo.registry.xds.util.protocol.message.RouteResult> decodeDiscoveryResponse(io.envoyproxy.envoy.service.discovery.v3.DiscoveryResponse);
    Code:
       0: aload_0
       1: invokevirtual #4                  // Method getTypeUrl:()Ljava/lang/String;
       4: aload_1
       5: invokevirtual #5                  // Method io/envoyproxy/envoy/service/discovery/v3/DiscoveryResponse.getTypeUrl:()Ljava/lang/String;
       8: invokevirtual #6                  // Method java/lang/String.equals:(Ljava/lang/Object;)Z
      11: ifeq          66
      14: aload_1
      15: invokevirtual #7                  // Method io/envoyproxy/envoy/service/discovery/v3/DiscoveryResponse.getResourcesList:()Ljava/util/List;
      18: invokeinterface #8,  1            // InterfaceMethod java/util/List.stream:()Ljava/util/stream/Stream;
      23: invokedynamic #9,  0              // InvokeDynamic #0:apply:()Ljava/util/function/Function;
      28: invokeinterface #10,  2           // InterfaceMethod java/util/stream/Stream.map:(Ljava/util/function/Function;)Ljava/util/stream/Stream;
      33: invokedynamic #11,  0             // InvokeDynamic #1:test:()Ljava/util/function/Predicate;
      38: invokeinterface #12,  2           // InterfaceMethod java/util/stream/Stream.filter:(Ljava/util/function/Predicate;)Ljava/util/stream/Stream;
      43: invokedynamic #13,  0             // InvokeDynamic #2:apply:()Ljava/util/function/Function;
      48: aload_0
      49: invokedynamic #14,  0             // InvokeDynamic #3:apply:(Lorg/apache/dubbo/registry/xds/util/protocol/impl/RdsProtocol;)Ljava/util/function/Function;
      54: invokestatic  #15                 // Method java/util/stream/Collectors.toConcurrentMap:(Ljava/util/function/Function;Ljava/util/function/Function;)Ljava/util/stream/Collector;
      57: invokeinterface #16,  2           // InterfaceMethod java/util/stream/Stream.collect:(Ljava/util/stream/Collector;)Ljava/lang/Object;
      62: checkcast     #17                 // class java/util/Map
      65: areturn
      66: new           #18                 // class java/util/HashMap
      69: dup
      70: invokespecial #19                 // Method java/util/HashMap."<init>":()V
      73: areturn

  private org.apache.dubbo.registry.xds.util.protocol.message.RouteResult decodeResourceToListener(io.envoyproxy.envoy.config.route.v3.RouteConfiguration);
    Code:
       0: new           #18                 // class java/util/HashMap
       3: dup
       4: invokespecial #19                 // Method java/util/HashMap."<init>":()V
       7: astore_2
       8: new           #20                 // class java/util/concurrent/ConcurrentHashMap
      11: dup
      12: invokespecial #21                 // Method java/util/concurrent/ConcurrentHashMap."<init>":()V
      15: astore_3
      16: aload_1
      17: invokevirtual #22                 // Method io/envoyproxy/envoy/config/route/v3/RouteConfiguration.getVirtualHostsList:()Ljava/util/List;
      20: aload_2
      21: aload_3
      22: invokedynamic #23,  0             // InvokeDynamic #4:accept:(Ljava/util/Map;Ljava/util/Map;)Ljava/util/function/Consumer;
      27: invokeinterface #24,  2           // InterfaceMethod java/util/List.forEach:(Ljava/util/function/Consumer;)V
      32: new           #25                 // class org/apache/dubbo/registry/xds/util/protocol/message/RouteResult
      35: dup
      36: aload_2
      37: aload_3
      38: invokespecial #26                 // Method org/apache/dubbo/registry/xds/util/protocol/message/RouteResult."<init>":(Ljava/util/Map;Ljava/util/Map;)V
      41: areturn

  private static io.envoyproxy.envoy.config.route.v3.RouteConfiguration unpackRouteConfiguration(com.google.protobuf.Any);
    Code:
       0: aload_0
       1: ldc           #27                 // class io/envoyproxy/envoy/config/route/v3/RouteConfiguration
       3: invokevirtual #28                 // Method com/google/protobuf/Any.unpack:(Ljava/lang/Class;)Lcom/google/protobuf/Message;
       6: checkcast     #27                 // class io/envoyproxy/envoy/config/route/v3/RouteConfiguration
       9: areturn
      10: astore_1
      11: getstatic     #30                 // Field logger:Lorg/apache/dubbo/common/logger/ErrorTypeAwareLogger;
      14: ldc           #31                 // String 1-31
      16: ldc           #32                 // String
      18: ldc           #32                 // String
      20: ldc           #33                 // String Error occur when decode xDS response.
      22: aload_1
      23: invokeinterface #34,  6           // InterfaceMethod org/apache/dubbo/common/logger/ErrorTypeAwareLogger.error:(Ljava/lang/String;Ljava/lang/String;Ljava/lang/String;Ljava/lang/String;Ljava/lang/Throwable;)V
      28: aconst_null
      29: areturn
    Exception table:
       from    to  target type
           0     9    10   Class com/google/protobuf/InvalidProtocolBufferException

  private static void lambda$decodeResourceToListener$0(java.util.Map, java.util.Map, io.envoyproxy.envoy.config.route.v3.VirtualHost);
    Code:
       0: aload_2
       1: invokevirtual #35                 // Method io/envoyproxy/envoy/config/route/v3/VirtualHost.getRoutesList:()Ljava/util/List;
       4: invokeinterface #8,  1            // InterfaceMethod java/util/List.stream:()Ljava/util/stream/Stream;
       9: invokedynamic #36,  0             // InvokeDynamic #5:apply:()Ljava/util/function/Function;
      14: invokeinterface #10,  2           // InterfaceMethod java/util/stream/Stream.map:(Ljava/util/function/Function;)Ljava/util/stream/Stream;
      19: invokedynamic #37,  0             // InvokeDynamic #6:apply:()Ljava/util/function/Function;
      24: invokeinterface #10,  2           // InterfaceMethod java/util/stream/Stream.map:(Ljava/util/function/Function;)Ljava/util/stream/Stream;
      29: invokestatic  #38                 // Method java/util/stream/Collectors.toSet:()Ljava/util/stream/Collector;
      32: invokeinterface #16,  2           // InterfaceMethod java/util/stream/Stream.collect:(Ljava/util/stream/Collector;)Ljava/lang/Object;
      37: checkcast     #39                 // class java/util/Set
      40: astore_3
      41: aload_2
      42: invokevirtual #40                 // Method io/envoyproxy/envoy/config/route/v3/VirtualHost.getDomainsList:()Lcom/google/protobuf/ProtocolStringList;
      45: invokeinterface #41,  1           // InterfaceMethod com/google/protobuf/ProtocolStringList.iterator:()Ljava/util/Iterator;
      50: astore        4
      52: aload         4
      54: invokeinterface #42,  1           // InterfaceMethod java/util/Iterator.hasNext:()Z
      59: ifeq          97
      62: aload         4
      64: invokeinterface #43,  1           // InterfaceMethod java/util/Iterator.next:()Ljava/lang/Object;
      69: checkcast     #44                 // class java/lang/String
      72: astore        5
      74: aload_0
      75: aload         5
      77: aload_3
      78: invokeinterface #45,  3           // InterfaceMethod java/util/Map.put:(Ljava/lang/Object;Ljava/lang/Object;)Ljava/lang/Object;
      83: pop
      84: aload_1
      85: aload         5
      87: aload_2
      88: invokeinterface #45,  3           // InterfaceMethod java/util/Map.put:(Ljava/lang/Object;Ljava/lang/Object;)Ljava/lang/Object;
      93: pop
      94: goto          52
      97: return

  static {};
    Code:
       0: ldc           #46                 // class org/apache/dubbo/registry/xds/util/protocol/impl/RdsProtocol
       2: invokestatic  #47                 // Method org/apache/dubbo/common/logger/LoggerFactory.getErrorTypeAwareLogger:(Ljava/lang/Class;)Lorg/apache/dubbo/common/logger/ErrorTypeAwareLogger;
       5: putstatic     #30                 // Field logger:Lorg/apache/dubbo/common/logger/ErrorTypeAwareLogger;
       8: return
}
