Compiled from "ReferenceCountedResource.java"
public abstract class org.apache.dubbo.common.reference.ReferenceCountedResource implements java.lang.AutoCloseable {
  private static final org.apache.dubbo.common.logger.ErrorTypeAwareLogger logger;

  private static final java.util.concurrent.atomic.AtomicLongFieldUpdater<org.apache.dubbo.common.reference.ReferenceCountedResource> COUNTER_UPDATER;

  private volatile long counter;

  public org.apache.dubbo.common.reference.ReferenceCountedResource();
    Code:
       0: aload_0
       1: invokespecial #2                  // Method java/lang/Object."<init>":()V
       4: aload_0
       5: lconst_1
       6: putfield      #3                  // Field counter:J
       9: return

  public final org.apache.dubbo.common.reference.ReferenceCountedResource retain();
    Code:
       0: getstatic     #4                  // Field COUNTER_UPDATER:Ljava/util/concurrent/atomic/AtomicLongFieldUpdater;
       3: aload_0
       4: invokevirtual #5                  // Method java/util/concurrent/atomic/AtomicLongFieldUpdater.getAndIncrement:(Ljava/lang/Object;)J
       7: lstore_1
       8: lload_1
       9: lconst_0
      10: lcmp
      11: ifgt          32
      14: getstatic     #4                  // Field COUNTER_UPDATER:Ljava/util/concurrent/atomic/AtomicLongFieldUpdater;
      17: aload_0
      18: invokevirtual #6                  // Method java/util/concurrent/atomic/AtomicLongFieldUpdater.getAndDecrement:(Ljava/lang/Object;)J
      21: pop2
      22: new           #7                  // class java/lang/AssertionError
      25: dup
      26: ldc           #8                  // String This instance has been destroyed
      28: invokespecial #9                  // Method java/lang/AssertionError."<init>":(Ljava/lang/Object;)V
      31: athrow
      32: aload_0
      33: areturn

  public final boolean release();
    Code:
       0: getstatic     #4                  // Field COUNTER_UPDATER:Ljava/util/concurrent/atomic/AtomicLongFieldUpdater;
       3: aload_0
       4: invokevirtual #10                 // Method java/util/concurrent/atomic/AtomicLongFieldUpdater.decrementAndGet:(Ljava/lang/Object;)J
       7: lstore_1
       8: lload_1
       9: lconst_0
      10: lcmp
      11: ifne          20
      14: aload_0
      15: invokevirtual #11                 // Method destroy:()V
      18: iconst_1
      19: ireturn
      20: lload_1
      21: ldc2_w        #12                 // long -1l
      24: lcmp
      25: ifgt          46
      28: getstatic     #14                 // Field logger:Lorg/apache/dubbo/common/logger/ErrorTypeAwareLogger;
      31: ldc           #15                 // String 4-7
      33: ldc           #16                 // String
      35: ldc           #16                 // String
      37: ldc           #8                  // String This instance has been destroyed
      39: invokeinterface #17,  5           // InterfaceMethod org/apache/dubbo/common/logger/ErrorTypeAwareLogger.warn:(Ljava/lang/String;Ljava/lang/String;Ljava/lang/String;Ljava/lang/String;)V
      44: iconst_0
      45: ireturn
      46: iconst_0
      47: ireturn

  public final void close();
    Code:
       0: aload_0
       1: invokevirtual #18                 // Method release:()Z
       4: pop
       5: return

  protected abstract void destroy();

  static {};
    Code:
       0: ldc           #19                 // class org/apache/dubbo/common/reference/ReferenceCountedResource
       2: invokestatic  #20                 // Method org/apache/dubbo/common/logger/LoggerFactory.getErrorTypeAwareLogger:(Ljava/lang/Class;)Lorg/apache/dubbo/common/logger/ErrorTypeAwareLogger;
       5: putstatic     #14                 // Field logger:Lorg/apache/dubbo/common/logger/ErrorTypeAwareLogger;
       8: ldc           #19                 // class org/apache/dubbo/common/reference/ReferenceCountedResource
      10: ldc           #21                 // String counter
      12: invokestatic  #22                 // Method java/util/concurrent/atomic/AtomicLongFieldUpdater.newUpdater:(Ljava/lang/Class;Ljava/lang/String;)Ljava/util/concurrent/atomic/AtomicLongFieldUpdater;
      15: putstatic     #4                  // Field COUNTER_UPDATER:Ljava/util/concurrent/atomic/AtomicLongFieldUpdater;
      18: return
}
