Compiled from "AbstractDynamicConfigurationFactory.java"
public abstract class org.apache.dubbo.common.config.configcenter.AbstractDynamicConfigurationFactory implements org.apache.dubbo.common.config.configcenter.DynamicConfigurationFactory {
  private volatile java.util.concurrent.ConcurrentHashMap<java.lang.String, org.apache.dubbo.common.config.configcenter.DynamicConfiguration> dynamicConfigurations;

  public org.apache.dubbo.common.config.configcenter.AbstractDynamicConfigurationFactory();
    Code:
       0: aload_0
       1: invokespecial #2                  // Method java/lang/Object."<init>":()V
       4: aload_0
       5: new           #3                  // class java/util/concurrent/ConcurrentHashMap
       8: dup
       9: invokespecial #4                  // Method java/util/concurrent/ConcurrentHashMap."<init>":()V
      12: putfield      #5                  // Field dynamicConfigurations:Ljava/util/concurrent/ConcurrentHashMap;
      15: return

  public final org.apache.dubbo.common.config.configcenter.DynamicConfiguration getDynamicConfiguration(org.apache.dubbo.common.URL);
    Code:
       0: aload_1
       1: ifnonnull     9
       4: ldc           #6                  // String default
       6: goto          13
       9: aload_1
      10: invokevirtual #7                  // Method org/apache/dubbo/common/URL.toServiceString:()Ljava/lang/String;
      13: astore_2
      14: aload_0
      15: getfield      #5                  // Field dynamicConfigurations:Ljava/util/concurrent/ConcurrentHashMap;
      18: aload_2
      19: aload_0
      20: aload_1
      21: invokedynamic #8,  0              // InvokeDynamic #0:apply:(Lorg/apache/dubbo/common/config/configcenter/AbstractDynamicConfigurationFactory;Lorg/apache/dubbo/common/URL;)Ljava/util/function/Function;
      26: invokestatic  #9                  // Method org/apache/dubbo/common/utils/ConcurrentHashMapUtils.computeIfAbsent:(Ljava/util/concurrent/ConcurrentMap;Ljava/lang/Object;Ljava/util/function/Function;)Ljava/lang/Object;
      29: checkcast     #10                 // class org/apache/dubbo/common/config/configcenter/DynamicConfiguration
      32: areturn

  protected abstract org.apache.dubbo.common.config.configcenter.DynamicConfiguration createDynamicConfiguration(org.apache.dubbo.common.URL);

  private org.apache.dubbo.common.config.configcenter.DynamicConfiguration lambda$getDynamicConfiguration$0(org.apache.dubbo.common.URL, java.lang.String);
    Code:
       0: aload_0
       1: aload_1
       2: invokevirtual #11                 // Method createDynamicConfiguration:(Lorg/apache/dubbo/common/URL;)Lorg/apache/dubbo/common/config/configcenter/DynamicConfiguration;
       5: areturn
}
