Compiled from "ConfigChangeType.java"
public final class org.apache.dubbo.common.config.configcenter.ConfigChangeType extends java.lang.Enum<org.apache.dubbo.common.config.configcenter.ConfigChangeType> {
  public static final org.apache.dubbo.common.config.configcenter.ConfigChangeType ADDED;

  public static final org.apache.dubbo.common.config.configcenter.ConfigChangeType MODIFIED;

  public static final org.apache.dubbo.common.config.configcenter.ConfigChangeType DELETED;

  private static final org.apache.dubbo.common.config.configcenter.ConfigChangeType[] $VALUES;

  public static org.apache.dubbo.common.config.configcenter.ConfigChangeType[] values();
    Code:
       0: getstatic     #1                  // Field $VALUES:[Lorg/apache/dubbo/common/config/configcenter/ConfigChangeType;
       3: invokevirtual #2                  // Method "[Lorg/apache/dubbo/common/config/configcenter/ConfigChangeType;".clone:()Ljava/lang/Object;
       6: checkcast     #3                  // class "[Lorg/apache/dubbo/common/config/configcenter/ConfigChangeType;"
       9: areturn

  public static org.apache.dubbo.common.config.configcenter.ConfigChangeType valueOf(java.lang.String);
    Code:
       0: ldc           #4                  // class org/apache/dubbo/common/config/configcenter/ConfigChangeType
       2: aload_0
       3: invokestatic  #5                  // Method java/lang/Enum.valueOf:(Ljava/lang/Class;Ljava/lang/String;)Ljava/lang/Enum;
       6: checkcast     #4                  // class org/apache/dubbo/common/config/configcenter/ConfigChangeType
       9: areturn

  private org.apache.dubbo.common.config.configcenter.ConfigChangeType();
    Code:
       0: aload_0
       1: aload_1
       2: iload_2
       3: invokespecial #6                  // Method java/lang/Enum."<init>":(Ljava/lang/String;I)V
       6: return

  static {};
    Code:
       0: new           #4                  // class org/apache/dubbo/common/config/configcenter/ConfigChangeType
       3: dup
       4: ldc           #7                  // String ADDED
       6: iconst_0
       7: invokespecial #8                  // Method "<init>":(Ljava/lang/String;I)V
      10: putstatic     #9                  // Field ADDED:Lorg/apache/dubbo/common/config/configcenter/ConfigChangeType;
      13: new           #4                  // class org/apache/dubbo/common/config/configcenter/ConfigChangeType
      16: dup
      17: ldc           #10                 // String MODIFIED
      19: iconst_1
      20: invokespecial #8                  // Method "<init>":(Ljava/lang/String;I)V
      23: putstatic     #11                 // Field MODIFIED:Lorg/apache/dubbo/common/config/configcenter/ConfigChangeType;
      26: new           #4                  // class org/apache/dubbo/common/config/configcenter/ConfigChangeType
      29: dup
      30: ldc           #12                 // String DELETED
      32: iconst_2
      33: invokespecial #8                  // Method "<init>":(Ljava/lang/String;I)V
      36: putstatic     #13                 // Field DELETED:Lorg/apache/dubbo/common/config/configcenter/ConfigChangeType;
      39: iconst_3
      40: anewarray     #4                  // class org/apache/dubbo/common/config/configcenter/ConfigChangeType
      43: dup
      44: iconst_0
      45: getstatic     #9                  // Field ADDED:Lorg/apache/dubbo/common/config/configcenter/ConfigChangeType;
      48: aastore
      49: dup
      50: iconst_1
      51: getstatic     #11                 // Field MODIFIED:Lorg/apache/dubbo/common/config/configcenter/ConfigChangeType;
      54: aastore
      55: dup
      56: iconst_2
      57: getstatic     #13                 // Field DELETED:Lorg/apache/dubbo/common/config/configcenter/ConfigChangeType;
      60: aastore
      61: putstatic     #1                  // Field $VALUES:[Lorg/apache/dubbo/common/config/configcenter/ConfigChangeType;
      64: return
}
