Compiled from "ConfigChangedEvent.java"
public class org.apache.dubbo.common.config.configcenter.ConfigChangedEvent extends java.util.EventObject {
  private final java.lang.String key;

  private final java.lang.String group;

  private final java.lang.String content;

  private final org.apache.dubbo.common.config.configcenter.ConfigChangeType changeType;

  public org.apache.dubbo.common.config.configcenter.ConfigChangedEvent(java.lang.String, java.lang.String, java.lang.String);
    Code:
       0: aload_0
       1: aload_1
       2: aload_2
       3: aload_3
       4: getstatic     #1                  // Field org/apache/dubbo/common/config/configcenter/ConfigChangeType.MODIFIED:Lorg/apache/dubbo/common/config/configcenter/ConfigChangeType;
       7: invokespecial #2                  // Method "<init>":(Ljava/lang/String;Ljava/lang/String;Ljava/lang/String;Lorg/apache/dubbo/common/config/configcenter/ConfigChangeType;)V
      10: return

  public org.apache.dubbo.common.config.configcenter.ConfigChangedEvent(java.lang.String, java.lang.String, java.lang.String, org.apache.dubbo.common.config.configcenter.ConfigChangeType);
    Code:
       0: aload_0
       1: new           #3                  // class java/lang/StringBuilder
       4: dup
       5: invokespecial #4                  // Method java/lang/StringBuilder."<init>":()V
       8: aload_1
       9: invokevirtual #5                  // Method java/lang/StringBuilder.append:(Ljava/lang/String;)Ljava/lang/StringBuilder;
      12: ldc           #6                  // String ,
      14: invokevirtual #5                  // Method java/lang/StringBuilder.append:(Ljava/lang/String;)Ljava/lang/StringBuilder;
      17: aload_2
      18: invokevirtual #5                  // Method java/lang/StringBuilder.append:(Ljava/lang/String;)Ljava/lang/StringBuilder;
      21: invokevirtual #7                  // Method java/lang/StringBuilder.toString:()Ljava/lang/String;
      24: invokespecial #8                  // Method java/util/EventObject."<init>":(Ljava/lang/Object;)V
      27: aload_0
      28: aload_1
      29: putfield      #9                  // Field key:Ljava/lang/String;
      32: aload_0
      33: aload_2
      34: putfield      #10                 // Field group:Ljava/lang/String;
      37: aload_0
      38: aload_3
      39: putfield      #11                 // Field content:Ljava/lang/String;
      42: aload_0
      43: aload         4
      45: putfield      #12                 // Field changeType:Lorg/apache/dubbo/common/config/configcenter/ConfigChangeType;
      48: return

  public java.lang.String getKey();
    Code:
       0: aload_0
       1: getfield      #9                  // Field key:Ljava/lang/String;
       4: areturn

  public java.lang.String getGroup();
    Code:
       0: aload_0
       1: getfield      #10                 // Field group:Ljava/lang/String;
       4: areturn

  public java.lang.String getContent();
    Code:
       0: aload_0
       1: getfield      #11                 // Field content:Ljava/lang/String;
       4: areturn

  public org.apache.dubbo.common.config.configcenter.ConfigChangeType getChangeType();
    Code:
       0: aload_0
       1: getfield      #12                 // Field changeType:Lorg/apache/dubbo/common/config/configcenter/ConfigChangeType;
       4: areturn

  public java.lang.String toString();
    Code:
       0: new           #3                  // class java/lang/StringBuilder
       3: dup
       4: invokespecial #4                  // Method java/lang/StringBuilder."<init>":()V
       7: ldc           #13                 // String ConfigChangedEvent{key=\'
       9: invokevirtual #5                  // Method java/lang/StringBuilder.append:(Ljava/lang/String;)Ljava/lang/StringBuilder;
      12: aload_0
      13: getfield      #9                  // Field key:Ljava/lang/String;
      16: invokevirtual #5                  // Method java/lang/StringBuilder.append:(Ljava/lang/String;)Ljava/lang/StringBuilder;
      19: bipush        39
      21: invokevirtual #14                 // Method java/lang/StringBuilder.append:(C)Ljava/lang/StringBuilder;
      24: ldc           #15                 // String , group=\'
      26: invokevirtual #5                  // Method java/lang/StringBuilder.append:(Ljava/lang/String;)Ljava/lang/StringBuilder;
      29: aload_0
      30: getfield      #10                 // Field group:Ljava/lang/String;
      33: invokevirtual #5                  // Method java/lang/StringBuilder.append:(Ljava/lang/String;)Ljava/lang/StringBuilder;
      36: bipush        39
      38: invokevirtual #14                 // Method java/lang/StringBuilder.append:(C)Ljava/lang/StringBuilder;
      41: ldc           #16                 // String , content=\'
      43: invokevirtual #5                  // Method java/lang/StringBuilder.append:(Ljava/lang/String;)Ljava/lang/StringBuilder;
      46: aload_0
      47: getfield      #11                 // Field content:Ljava/lang/String;
      50: invokevirtual #5                  // Method java/lang/StringBuilder.append:(Ljava/lang/String;)Ljava/lang/StringBuilder;
      53: bipush        39
      55: invokevirtual #14                 // Method java/lang/StringBuilder.append:(C)Ljava/lang/StringBuilder;
      58: ldc           #17                 // String , changeType=
      60: invokevirtual #5                  // Method java/lang/StringBuilder.append:(Ljava/lang/String;)Ljava/lang/StringBuilder;
      63: aload_0
      64: getfield      #12                 // Field changeType:Lorg/apache/dubbo/common/config/configcenter/ConfigChangeType;
      67: invokevirtual #18                 // Method java/lang/StringBuilder.append:(Ljava/lang/Object;)Ljava/lang/StringBuilder;
      70: ldc           #19                 // String }
      72: invokevirtual #5                  // Method java/lang/StringBuilder.append:(Ljava/lang/String;)Ljava/lang/StringBuilder;
      75: aload_0
      76: invokespecial #20                 // Method java/util/EventObject.toString:()Ljava/lang/String;
      79: invokevirtual #5                  // Method java/lang/StringBuilder.append:(Ljava/lang/String;)Ljava/lang/StringBuilder;
      82: invokevirtual #7                  // Method java/lang/StringBuilder.toString:()Ljava/lang/String;
      85: areturn

  public boolean equals(java.lang.Object);
    Code:
       0: aload_0
       1: aload_1
       2: if_acmpne     7
       5: iconst_1
       6: ireturn
       7: aload_1
       8: instanceof    #21                 // class org/apache/dubbo/common/config/configcenter/ConfigChangedEvent
      11: ifne          16
      14: iconst_0
      15: ireturn
      16: aload_1
      17: checkcast     #21                 // class org/apache/dubbo/common/config/configcenter/ConfigChangedEvent
      20: astore_2
      21: aload_0
      22: invokevirtual #22                 // Method getKey:()Ljava/lang/String;
      25: aload_2
      26: invokevirtual #22                 // Method getKey:()Ljava/lang/String;
      29: invokestatic  #23                 // Method java/util/Objects.equals:(Ljava/lang/Object;Ljava/lang/Object;)Z
      32: ifeq          78
      35: aload_0
      36: invokevirtual #24                 // Method getGroup:()Ljava/lang/String;
      39: aload_2
      40: invokevirtual #24                 // Method getGroup:()Ljava/lang/String;
      43: invokestatic  #23                 // Method java/util/Objects.equals:(Ljava/lang/Object;Ljava/lang/Object;)Z
      46: ifeq          78
      49: aload_0
      50: invokevirtual #25                 // Method getContent:()Ljava/lang/String;
      53: aload_2
      54: invokevirtual #25                 // Method getContent:()Ljava/lang/String;
      57: invokestatic  #23                 // Method java/util/Objects.equals:(Ljava/lang/Object;Ljava/lang/Object;)Z
      60: ifeq          78
      63: aload_0
      64: invokevirtual #26                 // Method getChangeType:()Lorg/apache/dubbo/common/config/configcenter/ConfigChangeType;
      67: aload_2
      68: invokevirtual #26                 // Method getChangeType:()Lorg/apache/dubbo/common/config/configcenter/ConfigChangeType;
      71: if_acmpne     78
      74: iconst_1
      75: goto          79
      78: iconst_0
      79: ireturn

  public int hashCode();
    Code:
       0: iconst_4
       1: anewarray     #27                 // class java/lang/Object
       4: dup
       5: iconst_0
       6: aload_0
       7: invokevirtual #22                 // Method getKey:()Ljava/lang/String;
      10: aastore
      11: dup
      12: iconst_1
      13: aload_0
      14: invokevirtual #24                 // Method getGroup:()Ljava/lang/String;
      17: aastore
      18: dup
      19: iconst_2
      20: aload_0
      21: invokevirtual #25                 // Method getContent:()Ljava/lang/String;
      24: aastore
      25: dup
      26: iconst_3
      27: aload_0
      28: invokevirtual #26                 // Method getChangeType:()Lorg/apache/dubbo/common/config/configcenter/ConfigChangeType;
      31: aastore
      32: invokestatic  #28                 // Method java/util/Objects.hash:([Ljava/lang/Object;)I
      35: ireturn
}
