Compiled from "ConfigItem.java"
public class org.apache.dubbo.common.config.configcenter.ConfigItem {
  private java.lang.String content;

  private java.lang.Object ticket;

  public java.lang.String getContent();
    Code:
       0: aload_0
       1: getfield      #1                  // Field content:Ljava/lang/String;
       4: areturn

  public void setContent(java.lang.String);
    Code:
       0: aload_0
       1: aload_1
       2: putfield      #1                  // Field content:Ljava/lang/String;
       5: return

  public java.lang.Object getTicket();
    Code:
       0: aload_0
       1: getfield      #2                  // Field ticket:Ljava/lang/Object;
       4: areturn

  public void setTicket(java.lang.Object);
    Code:
       0: aload_0
       1: aload_1
       2: putfield      #2                  // Field ticket:Ljava/lang/Object;
       5: return

  public org.apache.dubbo.common.config.configcenter.ConfigItem(java.lang.String, java.lang.Object);
    Code:
       0: aload_0
       1: invokespecial #3                  // Method java/lang/Object."<init>":()V
       4: aload_0
       5: aload_1
       6: putfield      #1                  // Field content:Ljava/lang/String;
       9: aload_0
      10: aload_2
      11: putfield      #2                  // Field ticket:Ljava/lang/Object;
      14: return

  public org.apache.dubbo.common.config.configcenter.ConfigItem();
    Code:
       0: aload_0
       1: invokespecial #3                  // Method java/lang/Object."<init>":()V
       4: return
}
