Compiled from "DynamicConfiguration.java"
public interface org.apache.dubbo.common.config.configcenter.DynamicConfiguration extends org.apache.dubbo.common.config.Configuration,java.lang.AutoCloseable {
  public static final java.lang.String DEFAULT_GROUP;

  public default void addListener(java.lang.String, org.apache.dubbo.common.config.configcenter.ConfigurationListener);
    Code:
       0: aload_0
       1: aload_1
       2: aload_0
       3: invokeinterface #1,  1            // InterfaceMethod getDefaultGroup:()Ljava/lang/String;
       8: aload_2
       9: invokeinterface #2,  4            // InterfaceMethod addListener:(Ljava/lang/String;Ljava/lang/String;Lorg/apache/dubbo/common/config/configcenter/ConfigurationListener;)V
      14: return

  public default void removeListener(java.lang.String, org.apache.dubbo.common.config.configcenter.ConfigurationListener);
    Code:
       0: aload_0
       1: aload_1
       2: aload_0
       3: invokeinterface #1,  1            // InterfaceMethod getDefaultGroup:()Ljava/lang/String;
       8: aload_2
       9: invokeinterface #3,  4            // InterfaceMethod removeListener:(Ljava/lang/String;Ljava/lang/String;Lorg/apache/dubbo/common/config/configcenter/ConfigurationListener;)V
      14: return

  public abstract void addListener(java.lang.String, java.lang.String, org.apache.dubbo.common.config.configcenter.ConfigurationListener);

  public abstract void removeListener(java.lang.String, java.lang.String, org.apache.dubbo.common.config.configcenter.ConfigurationListener);

  public default java.lang.String getConfig(java.lang.String, java.lang.String);
    Code:
       0: aload_0
       1: aload_1
       2: aload_2
       3: aload_0
       4: invokeinterface #4,  1            // InterfaceMethod getDefaultTimeout:()J
       9: invokeinterface #5,  5            // InterfaceMethod getConfig:(Ljava/lang/String;Ljava/lang/String;J)Ljava/lang/String;
      14: areturn

  public default org.apache.dubbo.common.config.configcenter.ConfigItem getConfigItem(java.lang.String, java.lang.String);
    Code:
       0: aload_0
       1: aload_1
       2: aload_2
       3: invokeinterface #6,  3            // InterfaceMethod getConfig:(Ljava/lang/String;Ljava/lang/String;)Ljava/lang/String;
       8: astore_3
       9: new           #7                  // class org/apache/dubbo/common/config/configcenter/ConfigItem
      12: dup
      13: aload_3
      14: aconst_null
      15: invokespecial #8                  // Method org/apache/dubbo/common/config/configcenter/ConfigItem."<init>":(Ljava/lang/String;Ljava/lang/Object;)V
      18: areturn

  public abstract java.lang.String getConfig(java.lang.String, java.lang.String, long) throws java.lang.IllegalStateException;

  public default java.lang.String getProperties(java.lang.String, java.lang.String) throws java.lang.IllegalStateException;
    Code:
       0: aload_0
       1: aload_1
       2: aload_2
       3: aload_0
       4: invokeinterface #4,  1            // InterfaceMethod getDefaultTimeout:()J
       9: invokeinterface #9,  5            // InterfaceMethod getProperties:(Ljava/lang/String;Ljava/lang/String;J)Ljava/lang/String;
      14: areturn

  public default java.lang.String getProperties(java.lang.String, java.lang.String, long) throws java.lang.IllegalStateException;
    Code:
       0: aload_0
       1: aload_1
       2: aload_2
       3: lload_3
       4: invokeinterface #5,  5            // InterfaceMethod getConfig:(Ljava/lang/String;Ljava/lang/String;J)Ljava/lang/String;
       9: areturn

  public default boolean publishConfig(java.lang.String, java.lang.String) throws java.lang.UnsupportedOperationException;
    Code:
       0: aload_0
       1: aload_1
       2: aload_0
       3: invokeinterface #1,  1            // InterfaceMethod getDefaultGroup:()Ljava/lang/String;
       8: aload_2
       9: invokeinterface #10,  4           // InterfaceMethod publishConfig:(Ljava/lang/String;Ljava/lang/String;Ljava/lang/String;)Z
      14: ireturn

  public default boolean publishConfig(java.lang.String, java.lang.String, java.lang.String) throws java.lang.UnsupportedOperationException;
    Code:
       0: iconst_0
       1: ireturn

  public default boolean publishConfigCas(java.lang.String, java.lang.String, java.lang.String, java.lang.Object) throws java.lang.UnsupportedOperationException;
    Code:
       0: iconst_0
       1: ireturn

  public default java.lang.String getDefaultGroup();
    Code:
       0: ldc           #12                 // String dubbo
       2: areturn

  public default long getDefaultTimeout();
    Code:
       0: ldc2_w        #13                 // long -1l
       3: lreturn

  public default void close() throws java.lang.Exception;
    Code:
       0: new           #15                 // class java/lang/UnsupportedOperationException
       3: dup
       4: invokespecial #16                 // Method java/lang/UnsupportedOperationException."<init>":()V
       7: athrow

  public static java.lang.String getRuleKey(org.apache.dubbo.common.URL);
    Code:
       0: aload_0
       1: invokevirtual #17                 // Method org/apache/dubbo/common/URL.getColonSeparatedKey:()Ljava/lang/String;
       4: areturn

  public default boolean removeConfig(java.lang.String, java.lang.String);
    Code:
       0: iconst_1
       1: ireturn
}
