Compiled from "TreePathDynamicConfiguration.java"
public abstract class org.apache.dubbo.common.config.configcenter.TreePathDynamicConfiguration extends org.apache.dubbo.common.config.configcenter.AbstractDynamicConfiguration {
  public static final java.lang.String CONFIG_ROOT_PATH_PARAM_NAME;

  public static final java.lang.String CONFIG_BASE_PATH_PARAM_NAME;

  public static final java.lang.String DEFAULT_CONFIG_BASE_PATH;

  protected final java.lang.String rootPath;

  public org.apache.dubbo.common.config.configcenter.TreePathDynamicConfiguration(org.apache.dubbo.common.URL);
    Code:
       0: aload_0
       1: aload_1
       2: invokespecial #3                  // Method org/apache/dubbo/common/config/configcenter/AbstractDynamicConfiguration."<init>":(Lorg/apache/dubbo/common/URL;)V
       5: aload_0
       6: aload_0
       7: aload_1
       8: invokevirtual #4                  // Method getRootPath:(Lorg/apache/dubbo/common/URL;)Ljava/lang/String;
      11: putfield      #5                  // Field rootPath:Ljava/lang/String;
      14: return

  public org.apache.dubbo.common.config.configcenter.TreePathDynamicConfiguration(java.lang.String, java.lang.String, int, long, java.lang.String, long);
    Code:
       0: aload_0
       1: aload_2
       2: iload_3
       3: lload         4
       5: aload         6
       7: lload         7
       9: invokespecial #6                  // Method org/apache/dubbo/common/config/configcenter/AbstractDynamicConfiguration."<init>":(Ljava/lang/String;IJLjava/lang/String;J)V
      12: aload_0
      13: aload_1
      14: putfield      #5                  // Field rootPath:Ljava/lang/String;
      17: return

  protected final java.lang.String doGetConfig(java.lang.String, java.lang.String) throws java.lang.Exception;
    Code:
       0: aload_0
       1: aload_2
       2: aload_1
       3: invokevirtual #7                  // Method buildPathKey:(Ljava/lang/String;Ljava/lang/String;)Ljava/lang/String;
       6: astore_3
       7: aload_0
       8: aload_3
       9: invokevirtual #8                  // Method doGetConfig:(Ljava/lang/String;)Ljava/lang/String;
      12: areturn

  public final boolean publishConfig(java.lang.String, java.lang.String, java.lang.String);
    Code:
       0: aload_0
       1: aload_2
       2: aload_1
       3: invokevirtual #7                  // Method buildPathKey:(Ljava/lang/String;Ljava/lang/String;)Ljava/lang/String;
       6: astore        4
       8: getstatic     #9                  // Field java/lang/Boolean.TRUE:Ljava/lang/Boolean;
      11: aload_0
      12: aload_0
      13: aload         4
      15: aload_3
      16: invokedynamic #10,  0             // InvokeDynamic #0:call:(Lorg/apache/dubbo/common/config/configcenter/TreePathDynamicConfiguration;Ljava/lang/String;Ljava/lang/String;)Ljava/util/concurrent/Callable;
      21: aload_0
      22: invokevirtual #11                 // Method getDefaultTimeout:()J
      25: invokevirtual #12                 // Method execute:(Ljava/util/concurrent/Callable;J)Ljava/lang/Object;
      28: invokevirtual #13                 // Method java/lang/Boolean.equals:(Ljava/lang/Object;)Z
      31: ireturn

  protected final boolean doRemoveConfig(java.lang.String, java.lang.String) throws java.lang.Exception;
    Code:
       0: aload_0
       1: aload_2
       2: aload_1
       3: invokevirtual #7                  // Method buildPathKey:(Ljava/lang/String;Ljava/lang/String;)Ljava/lang/String;
       6: astore_3
       7: aload_0
       8: aload_3
       9: invokevirtual #14                 // Method doRemoveConfig:(Ljava/lang/String;)Z
      12: ireturn

  public final void addListener(java.lang.String, java.lang.String, org.apache.dubbo.common.config.configcenter.ConfigurationListener);
    Code:
       0: aload_0
       1: aload_2
       2: aload_1
       3: invokevirtual #7                  // Method buildPathKey:(Ljava/lang/String;Ljava/lang/String;)Ljava/lang/String;
       6: astore        4
       8: aload_0
       9: aload         4
      11: aload_3
      12: aload_1
      13: aload_2
      14: invokevirtual #15                 // Method doAddListener:(Ljava/lang/String;Lorg/apache/dubbo/common/config/configcenter/ConfigurationListener;Ljava/lang/String;Ljava/lang/String;)V
      17: return

  public final void removeListener(java.lang.String, java.lang.String, org.apache.dubbo.common.config.configcenter.ConfigurationListener);
    Code:
       0: aload_0
       1: aload_2
       2: aload_1
       3: invokevirtual #7                  // Method buildPathKey:(Ljava/lang/String;Ljava/lang/String;)Ljava/lang/String;
       6: astore        4
       8: aload_0
       9: aload         4
      11: aload_3
      12: invokevirtual #16                 // Method doRemoveListener:(Ljava/lang/String;Lorg/apache/dubbo/common/config/configcenter/ConfigurationListener;)V
      15: return

  protected abstract boolean doPublishConfig(java.lang.String, java.lang.String) throws java.lang.Exception;

  protected abstract java.lang.String doGetConfig(java.lang.String) throws java.lang.Exception;

  protected abstract boolean doRemoveConfig(java.lang.String) throws java.lang.Exception;

  protected abstract java.util.Collection<java.lang.String> doGetConfigKeys(java.lang.String);

  protected abstract void doAddListener(java.lang.String, org.apache.dubbo.common.config.configcenter.ConfigurationListener, java.lang.String, java.lang.String);

  protected abstract void doRemoveListener(java.lang.String, org.apache.dubbo.common.config.configcenter.ConfigurationListener);

  protected java.lang.String buildGroupPath(java.lang.String);
    Code:
       0: aload_0
       1: getfield      #5                  // Field rootPath:Ljava/lang/String;
       4: iconst_1
       5: anewarray     #17                 // class java/lang/String
       8: dup
       9: iconst_0
      10: aload_1
      11: aastore
      12: invokestatic  #18                 // InterfaceMethod org/apache/dubbo/common/utils/PathUtils.buildPath:(Ljava/lang/String;[Ljava/lang/String;)Ljava/lang/String;
      15: areturn

  protected java.lang.String buildPathKey(java.lang.String, java.lang.String);
    Code:
       0: aload_0
       1: aload_1
       2: invokevirtual #19                 // Method buildGroupPath:(Ljava/lang/String;)Ljava/lang/String;
       5: iconst_1
       6: anewarray     #17                 // class java/lang/String
       9: dup
      10: iconst_0
      11: aload_2
      12: aastore
      13: invokestatic  #18                 // InterfaceMethod org/apache/dubbo/common/utils/PathUtils.buildPath:(Ljava/lang/String;[Ljava/lang/String;)Ljava/lang/String;
      16: areturn

  protected java.lang.String getRootPath(org.apache.dubbo.common.URL);
    Code:
       0: aload_1
       1: ldc           #21                 // String dubbo.config-center.root-path
       3: aload_0
       4: aload_1
       5: invokespecial #22                 // Method buildRootPath:(Lorg/apache/dubbo/common/URL;)Ljava/lang/String;
       8: invokevirtual #23                 // Method org/apache/dubbo/common/URL.getParameter:(Ljava/lang/String;Ljava/lang/String;)Ljava/lang/String;
      11: astore_2
      12: aload_2
      13: invokestatic  #24                 // InterfaceMethod org/apache/dubbo/common/utils/PathUtils.normalize:(Ljava/lang/String;)Ljava/lang/String;
      16: astore_2
      17: aload_2
      18: invokevirtual #25                 // Method java/lang/String.length:()I
      21: istore_3
      22: iload_3
      23: iconst_1
      24: if_icmple     45
      27: aload_2
      28: ldc           #26                 // String /
      30: invokevirtual #27                 // Method java/lang/String.endsWith:(Ljava/lang/String;)Z
      33: ifeq          45
      36: aload_2
      37: iconst_0
      38: iload_3
      39: iconst_1
      40: isub
      41: invokevirtual #28                 // Method java/lang/String.substring:(II)Ljava/lang/String;
      44: astore_2
      45: aload_2
      46: areturn

  private java.lang.String buildRootPath(org.apache.dubbo.common.URL);
    Code:
       0: new           #29                 // class java/lang/StringBuilder
       3: dup
       4: invokespecial #30                 // Method java/lang/StringBuilder."<init>":()V
       7: ldc           #26                 // String /
       9: invokevirtual #31                 // Method java/lang/StringBuilder.append:(Ljava/lang/String;)Ljava/lang/StringBuilder;
      12: aload_0
      13: aload_1
      14: invokevirtual #32                 // Method getConfigNamespace:(Lorg/apache/dubbo/common/URL;)Ljava/lang/String;
      17: invokevirtual #31                 // Method java/lang/StringBuilder.append:(Ljava/lang/String;)Ljava/lang/StringBuilder;
      20: aload_0
      21: aload_1
      22: invokevirtual #33                 // Method getConfigBasePath:(Lorg/apache/dubbo/common/URL;)Ljava/lang/String;
      25: invokevirtual #31                 // Method java/lang/StringBuilder.append:(Ljava/lang/String;)Ljava/lang/StringBuilder;
      28: invokevirtual #34                 // Method java/lang/StringBuilder.toString:()Ljava/lang/String;
      31: areturn

  protected java.lang.String getConfigNamespace(org.apache.dubbo.common.URL);
    Code:
       0: aload_1
       1: ldc           #35                 // String namespace
       3: ldc           #37                 // String dubbo
       5: invokevirtual #23                 // Method org/apache/dubbo/common/URL.getParameter:(Ljava/lang/String;Ljava/lang/String;)Ljava/lang/String;
       8: areturn

  protected java.lang.String getConfigBasePath(org.apache.dubbo.common.URL);
    Code:
       0: aload_1
       1: ldc           #38                 // String dubbo.config-center.base-path
       3: ldc           #39                 // String /config
       5: invokevirtual #23                 // Method org/apache/dubbo/common/URL.getParameter:(Ljava/lang/String;Ljava/lang/String;)Ljava/lang/String;
       8: astore_2
       9: aload_2
      10: invokestatic  #40                 // Method org/apache/dubbo/common/utils/StringUtils.isNotEmpty:(Ljava/lang/String;)Z
      13: ifeq          45
      16: aload_2
      17: ldc           #26                 // String /
      19: invokevirtual #41                 // Method java/lang/String.startsWith:(Ljava/lang/String;)Z
      22: ifne          45
      25: new           #29                 // class java/lang/StringBuilder
      28: dup
      29: invokespecial #30                 // Method java/lang/StringBuilder."<init>":()V
      32: ldc           #26                 // String /
      34: invokevirtual #31                 // Method java/lang/StringBuilder.append:(Ljava/lang/String;)Ljava/lang/StringBuilder;
      37: aload_2
      38: invokevirtual #31                 // Method java/lang/StringBuilder.append:(Ljava/lang/String;)Ljava/lang/StringBuilder;
      41: invokevirtual #34                 // Method java/lang/StringBuilder.toString:()Ljava/lang/String;
      44: astore_2
      45: aload_2
      46: areturn

  private java.lang.Boolean lambda$publishConfig$0(java.lang.String, java.lang.String) throws java.lang.Exception;
    Code:
       0: aload_0
       1: aload_1
       2: aload_2
       3: invokevirtual #42                 // Method doPublishConfig:(Ljava/lang/String;Ljava/lang/String;)Z
       6: invokestatic  #43                 // Method java/lang/Boolean.valueOf:(Z)Ljava/lang/Boolean;
       9: areturn
}
