Compiled from "CodaBarWriter.java"
public final class com.google.zxing.oned.CodaBarWriter extends com.google.zxing.oned.OneDimensionalCodeWriter {
  private static final char[] START_END_CHARS;

  private static final char[] ALT_START_END_CHARS;

  private static final char[] CHARS_WHICH_ARE_TEN_LENGTH_EACH_AFTER_DECODED;

  private static final char DEFAULT_GUARD;

  public com.google.zxing.oned.CodaBarWriter();
    Code:
       0: aload_0
       1: invokespecial #1                  // Method com/google/zxing/oned/OneDimensionalCodeWriter."<init>":()V
       4: return

  protected java.util.Collection<com.google.zxing.BarcodeFormat> getSupportedWriteFormats();
    Code:
       0: getstatic     #2                  // Field com/google/zxing/BarcodeFormat.CODABAR:Lcom/google/zxing/BarcodeFormat;
       3: invokestatic  #3                  // Method java/util/Collections.singleton:(Ljava/lang/Object;)Ljava/util/Set;
       6: areturn

  public boolean[] encode(java.lang.String);
    Code:
       0: aload_1
       1: invokevirtual #4                  // Method java/lang/String.length:()I
       4: iconst_2
       5: if_icmpge     38
       8: new           #5                  // class java/lang/StringBuilder
      11: dup
      12: invokespecial #6                  // Method java/lang/StringBuilder."<init>":()V
      15: getstatic     #7                  // Field DEFAULT_GUARD:C
      18: invokevirtual #8                  // Method java/lang/StringBuilder.append:(C)Ljava/lang/StringBuilder;
      21: aload_1
      22: invokevirtual #9                  // Method java/lang/StringBuilder.append:(Ljava/lang/String;)Ljava/lang/StringBuilder;
      25: getstatic     #7                  // Field DEFAULT_GUARD:C
      28: invokevirtual #8                  // Method java/lang/StringBuilder.append:(C)Ljava/lang/StringBuilder;
      31: invokevirtual #10                 // Method java/lang/StringBuilder.toString:()Ljava/lang/String;
      34: astore_1
      35: goto          235
      38: aload_1
      39: iconst_0
      40: invokevirtual #11                 // Method java/lang/String.charAt:(I)C
      43: invokestatic  #12                 // Method java/lang/Character.toUpperCase:(C)C
      46: istore_2
      47: aload_1
      48: aload_1
      49: invokevirtual #4                  // Method java/lang/String.length:()I
      52: iconst_1
      53: isub
      54: invokevirtual #11                 // Method java/lang/String.charAt:(I)C
      57: invokestatic  #12                 // Method java/lang/Character.toUpperCase:(C)C
      60: istore_3
      61: getstatic     #13                 // Field START_END_CHARS:[C
      64: iload_2
      65: invokestatic  #14                 // Method com/google/zxing/oned/CodaBarReader.arrayContains:([CC)Z
      68: istore        4
      70: getstatic     #13                 // Field START_END_CHARS:[C
      73: iload_3
      74: invokestatic  #14                 // Method com/google/zxing/oned/CodaBarReader.arrayContains:([CC)Z
      77: istore        5
      79: getstatic     #15                 // Field ALT_START_END_CHARS:[C
      82: iload_2
      83: invokestatic  #14                 // Method com/google/zxing/oned/CodaBarReader.arrayContains:([CC)Z
      86: istore        6
      88: getstatic     #15                 // Field ALT_START_END_CHARS:[C
      91: iload_3
      92: invokestatic  #14                 // Method com/google/zxing/oned/CodaBarReader.arrayContains:([CC)Z
      95: istore        7
      97: iload         4
      99: ifeq          134
     102: iload         5
     104: ifne          235
     107: new           #16                 // class java/lang/IllegalArgumentException
     110: dup
     111: new           #5                  // class java/lang/StringBuilder
     114: dup
     115: invokespecial #6                  // Method java/lang/StringBuilder."<init>":()V
     118: ldc           #17                 // String Invalid start/end guards:
     120: invokevirtual #9                  // Method java/lang/StringBuilder.append:(Ljava/lang/String;)Ljava/lang/StringBuilder;
     123: aload_1
     124: invokevirtual #9                  // Method java/lang/StringBuilder.append:(Ljava/lang/String;)Ljava/lang/StringBuilder;
     127: invokevirtual #10                 // Method java/lang/StringBuilder.toString:()Ljava/lang/String;
     130: invokespecial #18                 // Method java/lang/IllegalArgumentException."<init>":(Ljava/lang/String;)V
     133: athrow
     134: iload         6
     136: ifeq          171
     139: iload         7
     141: ifne          235
     144: new           #16                 // class java/lang/IllegalArgumentException
     147: dup
     148: new           #5                  // class java/lang/StringBuilder
     151: dup
     152: invokespecial #6                  // Method java/lang/StringBuilder."<init>":()V
     155: ldc           #17                 // String Invalid start/end guards:
     157: invokevirtual #9                  // Method java/lang/StringBuilder.append:(Ljava/lang/String;)Ljava/lang/StringBuilder;
     160: aload_1
     161: invokevirtual #9                  // Method java/lang/StringBuilder.append:(Ljava/lang/String;)Ljava/lang/StringBuilder;
     164: invokevirtual #10                 // Method java/lang/StringBuilder.toString:()Ljava/lang/String;
     167: invokespecial #18                 // Method java/lang/IllegalArgumentException."<init>":(Ljava/lang/String;)V
     170: athrow
     171: iload         5
     173: ifne          181
     176: iload         7
     178: ifeq          208
     181: new           #16                 // class java/lang/IllegalArgumentException
     184: dup
     185: new           #5                  // class java/lang/StringBuilder
     188: dup
     189: invokespecial #6                  // Method java/lang/StringBuilder."<init>":()V
     192: ldc           #17                 // String Invalid start/end guards:
     194: invokevirtual #9                  // Method java/lang/StringBuilder.append:(Ljava/lang/String;)Ljava/lang/StringBuilder;
     197: aload_1
     198: invokevirtual #9                  // Method java/lang/StringBuilder.append:(Ljava/lang/String;)Ljava/lang/StringBuilder;
     201: invokevirtual #10                 // Method java/lang/StringBuilder.toString:()Ljava/lang/String;
     204: invokespecial #18                 // Method java/lang/IllegalArgumentException."<init>":(Ljava/lang/String;)V
     207: athrow
     208: new           #5                  // class java/lang/StringBuilder
     211: dup
     212: invokespecial #6                  // Method java/lang/StringBuilder."<init>":()V
     215: getstatic     #7                  // Field DEFAULT_GUARD:C
     218: invokevirtual #8                  // Method java/lang/StringBuilder.append:(C)Ljava/lang/StringBuilder;
     221: aload_1
     222: invokevirtual #9                  // Method java/lang/StringBuilder.append:(Ljava/lang/String;)Ljava/lang/StringBuilder;
     225: getstatic     #7                  // Field DEFAULT_GUARD:C
     228: invokevirtual #8                  // Method java/lang/StringBuilder.append:(C)Ljava/lang/StringBuilder;
     231: invokevirtual #10                 // Method java/lang/StringBuilder.toString:()Ljava/lang/String;
     234: astore_1
     235: bipush        20
     237: istore_2
     238: iconst_1
     239: istore_3
     240: iload_3
     241: aload_1
     242: invokevirtual #4                  // Method java/lang/String.length:()I
     245: iconst_1
     246: isub
     247: if_icmpge     349
     250: aload_1
     251: iload_3
     252: invokevirtual #11                 // Method java/lang/String.charAt:(I)C
     255: invokestatic  #19                 // Method java/lang/Character.isDigit:(C)Z
     258: ifne          281
     261: aload_1
     262: iload_3
     263: invokevirtual #11                 // Method java/lang/String.charAt:(I)C
     266: bipush        45
     268: if_icmpeq     281
     271: aload_1
     272: iload_3
     273: invokevirtual #11                 // Method java/lang/String.charAt:(I)C
     276: bipush        36
     278: if_icmpne     287
     281: iinc          2, 9
     284: goto          343
     287: getstatic     #20                 // Field CHARS_WHICH_ARE_TEN_LENGTH_EACH_AFTER_DECODED:[C
     290: aload_1
     291: iload_3
     292: invokevirtual #11                 // Method java/lang/String.charAt:(I)C
     295: invokestatic  #14                 // Method com/google/zxing/oned/CodaBarReader.arrayContains:([CC)Z
     298: ifeq          307
     301: iinc          2, 10
     304: goto          343
     307: new           #16                 // class java/lang/IllegalArgumentException
     310: dup
     311: new           #5                  // class java/lang/StringBuilder
     314: dup
     315: invokespecial #6                  // Method java/lang/StringBuilder."<init>":()V
     318: ldc           #21                 // String Cannot encode : \'
     320: invokevirtual #9                  // Method java/lang/StringBuilder.append:(Ljava/lang/String;)Ljava/lang/StringBuilder;
     323: aload_1
     324: iload_3
     325: invokevirtual #11                 // Method java/lang/String.charAt:(I)C
     328: invokevirtual #8                  // Method java/lang/StringBuilder.append:(C)Ljava/lang/StringBuilder;
     331: bipush        39
     333: invokevirtual #8                  // Method java/lang/StringBuilder.append:(C)Ljava/lang/StringBuilder;
     336: invokevirtual #10                 // Method java/lang/StringBuilder.toString:()Ljava/lang/String;
     339: invokespecial #18                 // Method java/lang/IllegalArgumentException."<init>":(Ljava/lang/String;)V
     342: athrow
     343: iinc          3, 1
     346: goto          240
     349: iload_2
     350: aload_1
     351: invokevirtual #4                  // Method java/lang/String.length:()I
     354: iconst_1
     355: isub
     356: iadd
     357: istore_2
     358: iload_2
     359: newarray       boolean
     361: astore_3
     362: iconst_0
     363: istore        4
     365: iconst_0
     366: istore        5
     368: iload         5
     370: aload_1
     371: invokevirtual #4                  // Method java/lang/String.length:()I
     374: if_icmpge     612
     377: aload_1
     378: iload         5
     380: invokevirtual #11                 // Method java/lang/String.charAt:(I)C
     383: invokestatic  #12                 // Method java/lang/Character.toUpperCase:(C)C
     386: istore        6
     388: iload         5
     390: ifeq          404
     393: iload         5
     395: aload_1
     396: invokevirtual #4                  // Method java/lang/String.length:()I
     399: iconst_1
     400: isub
     401: if_icmpne     473
     404: iload         6
     406: lookupswitch  { // 4
                    42: 462
                    69: 469
                    78: 455
                    84: 448
               default: 473
          }
     448: bipush        65
     450: istore        6
     452: goto          473
     455: bipush        66
     457: istore        6
     459: goto          473
     462: bipush        67
     464: istore        6
     466: goto          473
     469: bipush        68
     471: istore        6
     473: iconst_0
     474: istore        7
     476: iconst_0
     477: istore        8
     479: iload         8
     481: getstatic     #22                 // Field com/google/zxing/oned/CodaBarReader.ALPHABET:[C
     484: arraylength
     485: if_icmpge     516
     488: iload         6
     490: getstatic     #22                 // Field com/google/zxing/oned/CodaBarReader.ALPHABET:[C
     493: iload         8
     495: caload
     496: if_icmpne     510
     499: getstatic     #23                 // Field com/google/zxing/oned/CodaBarReader.CHARACTER_ENCODINGS:[I
     502: iload         8
     504: iaload
     505: istore        7
     507: goto          516
     510: iinc          8, 1
     513: goto          479
     516: iconst_1
     517: istore        8
     519: iconst_0
     520: istore        9
     522: iconst_0
     523: istore        10
     525: iload         10
     527: bipush        7
     529: if_icmpge     587
     532: aload_3
     533: iload         4
     535: iload         8
     537: bastore
     538: iinc          4, 1
     541: iload         7
     543: bipush        6
     545: iload         10
     547: isub
     548: ishr
     549: iconst_1
     550: iand
     551: ifeq          560
     554: iload         9
     556: iconst_1
     557: if_icmpne     581
     560: iload         8
     562: ifne          569
     565: iconst_1
     566: goto          570
     569: iconst_0
     570: istore        8
     572: iinc          10, 1
     575: iconst_0
     576: istore        9
     578: goto          525
     581: iinc          9, 1
     584: goto          525
     587: iload         5
     589: aload_1
     590: invokevirtual #4                  // Method java/lang/String.length:()I
     593: iconst_1
     594: isub
     595: if_icmpge     606
     598: aload_3
     599: iload         4
     601: iconst_0
     602: bastore
     603: iinc          4, 1
     606: iinc          5, 1
     609: goto          368
     612: aload_3
     613: areturn

  static {};
    Code:
       0: iconst_4
       1: newarray       char
       3: dup
       4: iconst_0
       5: bipush        65
       7: castore
       8: dup
       9: iconst_1
      10: bipush        66
      12: castore
      13: dup
      14: iconst_2
      15: bipush        67
      17: castore
      18: dup
      19: iconst_3
      20: bipush        68
      22: castore
      23: putstatic     #13                 // Field START_END_CHARS:[C
      26: iconst_4
      27: newarray       char
      29: dup
      30: iconst_0
      31: bipush        84
      33: castore
      34: dup
      35: iconst_1
      36: bipush        78
      38: castore
      39: dup
      40: iconst_2
      41: bipush        42
      43: castore
      44: dup
      45: iconst_3
      46: bipush        69
      48: castore
      49: putstatic     #15                 // Field ALT_START_END_CHARS:[C
      52: iconst_4
      53: newarray       char
      55: dup
      56: iconst_0
      57: bipush        47
      59: castore
      60: dup
      61: iconst_1
      62: bipush        58
      64: castore
      65: dup
      66: iconst_2
      67: bipush        43
      69: castore
      70: dup
      71: iconst_3
      72: bipush        46
      74: castore
      75: putstatic     #20                 // Field CHARS_WHICH_ARE_TEN_LENGTH_EACH_AFTER_DECODED:[C
      78: getstatic     #13                 // Field START_END_CHARS:[C
      81: iconst_0
      82: caload
      83: putstatic     #7                  // Field DEFAULT_GUARD:C
      86: return
}
