Compiled from "Code128Writer.java"
final class com.google.zxing.oned.Code128Writer$MinimalEncoder$Latch extends java.lang.Enum<com.google.zxing.oned.Code128Writer$MinimalEncoder$Latch> {
  public static final com.google.zxing.oned.Code128Writer$MinimalEncoder$Latch A;

  public static final com.google.zxing.oned.Code128Writer$MinimalEncoder$Latch B;

  public static final com.google.zxing.oned.Code128Writer$MinimalEncoder$Latch C;

  public static final com.google.zxing.oned.Code128Writer$MinimalEncoder$Latch SHIFT;

  public static final com.google.zxing.oned.Code128Writer$MinimalEncoder$Latch NONE;

  private static final com.google.zxing.oned.Code128Writer$MinimalEncoder$Latch[] $VALUES;

  public static com.google.zxing.oned.Code128Writer$MinimalEncoder$Latch[] values();
    Code:
       0: getstatic     #1                  // Field $VALUES:[Lcom/google/zxing/oned/Code128Writer$MinimalEncoder$Latch;
       3: invokevirtual #2                  // Method "[Lcom/google/zxing/oned/Code128Writer$MinimalEncoder$Latch;".clone:()Ljava/lang/Object;
       6: checkcast     #3                  // class "[Lcom/google/zxing/oned/Code128Writer$MinimalEncoder$Latch;"
       9: areturn

  public static com.google.zxing.oned.Code128Writer$MinimalEncoder$Latch valueOf(java.lang.String);
    Code:
       0: ldc           #4                  // class com/google/zxing/oned/Code128Writer$MinimalEncoder$Latch
       2: aload_0
       3: invokestatic  #5                  // Method java/lang/Enum.valueOf:(Ljava/lang/Class;Ljava/lang/String;)Ljava/lang/Enum;
       6: checkcast     #4                  // class com/google/zxing/oned/Code128Writer$MinimalEncoder$Latch
       9: areturn

  private com.google.zxing.oned.Code128Writer$MinimalEncoder$Latch();
    Code:
       0: aload_0
       1: aload_1
       2: iload_2
       3: invokespecial #6                  // Method java/lang/Enum."<init>":(Ljava/lang/String;I)V
       6: return

  static {};
    Code:
       0: new           #4                  // class com/google/zxing/oned/Code128Writer$MinimalEncoder$Latch
       3: dup
       4: ldc           #7                  // String A
       6: iconst_0
       7: invokespecial #8                  // Method "<init>":(Ljava/lang/String;I)V
      10: putstatic     #9                  // Field A:Lcom/google/zxing/oned/Code128Writer$MinimalEncoder$Latch;
      13: new           #4                  // class com/google/zxing/oned/Code128Writer$MinimalEncoder$Latch
      16: dup
      17: ldc           #10                 // String B
      19: iconst_1
      20: invokespecial #8                  // Method "<init>":(Ljava/lang/String;I)V
      23: putstatic     #11                 // Field B:Lcom/google/zxing/oned/Code128Writer$MinimalEncoder$Latch;
      26: new           #4                  // class com/google/zxing/oned/Code128Writer$MinimalEncoder$Latch
      29: dup
      30: ldc           #12                 // String C
      32: iconst_2
      33: invokespecial #8                  // Method "<init>":(Ljava/lang/String;I)V
      36: putstatic     #13                 // Field C:Lcom/google/zxing/oned/Code128Writer$MinimalEncoder$Latch;
      39: new           #4                  // class com/google/zxing/oned/Code128Writer$MinimalEncoder$Latch
      42: dup
      43: ldc           #14                 // String SHIFT
      45: iconst_3
      46: invokespecial #8                  // Method "<init>":(Ljava/lang/String;I)V
      49: putstatic     #15                 // Field SHIFT:Lcom/google/zxing/oned/Code128Writer$MinimalEncoder$Latch;
      52: new           #4                  // class com/google/zxing/oned/Code128Writer$MinimalEncoder$Latch
      55: dup
      56: ldc           #16                 // String NONE
      58: iconst_4
      59: invokespecial #8                  // Method "<init>":(Ljava/lang/String;I)V
      62: putstatic     #17                 // Field NONE:Lcom/google/zxing/oned/Code128Writer$MinimalEncoder$Latch;
      65: iconst_5
      66: anewarray     #4                  // class com/google/zxing/oned/Code128Writer$MinimalEncoder$Latch
      69: dup
      70: iconst_0
      71: getstatic     #9                  // Field A:Lcom/google/zxing/oned/Code128Writer$MinimalEncoder$Latch;
      74: aastore
      75: dup
      76: iconst_1
      77: getstatic     #11                 // Field B:Lcom/google/zxing/oned/Code128Writer$MinimalEncoder$Latch;
      80: aastore
      81: dup
      82: iconst_2
      83: getstatic     #13                 // Field C:Lcom/google/zxing/oned/Code128Writer$MinimalEncoder$Latch;
      86: aastore
      87: dup
      88: iconst_3
      89: getstatic     #15                 // Field SHIFT:Lcom/google/zxing/oned/Code128Writer$MinimalEncoder$Latch;
      92: aastore
      93: dup
      94: iconst_4
      95: getstatic     #17                 // Field NONE:Lcom/google/zxing/oned/Code128Writer$MinimalEncoder$Latch;
      98: aastore
      99: putstatic     #1                  // Field $VALUES:[Lcom/google/zxing/oned/Code128Writer$MinimalEncoder$Latch;
     102: return
}
