Compiled from "Code128Writer.java"
public final class com.google.zxing.oned.Code128Writer extends com.google.zxing.oned.OneDimensionalCodeWriter {
  private static final int CODE_START_A;

  private static final int CODE_START_B;

  private static final int CODE_START_C;

  private static final int CODE_CODE_A;

  private static final int CODE_CODE_B;

  private static final int CODE_CODE_C;

  private static final int CODE_STOP;

  private static final char ESCAPE_FNC_1;

  private static final char ESCAPE_FNC_2;

  private static final char ESCAPE_FNC_3;

  private static final char ESCAPE_FNC_4;

  private static final int CODE_FNC_1;

  private static final int CODE_FNC_2;

  private static final int CODE_FNC_3;

  private static final int CODE_FNC_4_A;

  private static final int CODE_FNC_4_B;

  public com.google.zxing.oned.Code128Writer();
    Code:
       0: aload_0
       1: invokespecial #1                  // Method com/google/zxing/oned/OneDimensionalCodeWriter."<init>":()V
       4: return

  protected java.util.Collection<com.google.zxing.BarcodeFormat> getSupportedWriteFormats();
    Code:
       0: getstatic     #2                  // Field com/google/zxing/BarcodeFormat.CODE_128:Lcom/google/zxing/BarcodeFormat;
       3: invokestatic  #3                  // Method java/util/Collections.singleton:(Ljava/lang/Object;)Ljava/util/Set;
       6: areturn

  public boolean[] encode(java.lang.String);
    Code:
       0: aload_0
       1: aload_1
       2: aconst_null
       3: invokevirtual #4                  // Method encode:(Ljava/lang/String;Ljava/util/Map;)[Z
       6: areturn

  protected boolean[] encode(java.lang.String, java.util.Map<com.google.zxing.EncodeHintType, ?>);
    Code:
       0: aload_1
       1: aload_2
       2: invokestatic  #5                  // Method check:(Ljava/lang/String;Ljava/util/Map;)I
       5: istore_3
       6: aload_2
       7: ifnull        44
      10: aload_2
      11: getstatic     #6                  // Field com/google/zxing/EncodeHintType.CODE128_COMPACT:Lcom/google/zxing/EncodeHintType;
      14: invokeinterface #7,  2            // InterfaceMethod java/util/Map.containsKey:(Ljava/lang/Object;)Z
      19: ifeq          44
      22: aload_2
      23: getstatic     #6                  // Field com/google/zxing/EncodeHintType.CODE128_COMPACT:Lcom/google/zxing/EncodeHintType;
      26: invokeinterface #8,  2            // InterfaceMethod java/util/Map.get:(Ljava/lang/Object;)Ljava/lang/Object;
      31: invokevirtual #9                  // Method java/lang/Object.toString:()Ljava/lang/String;
      34: invokestatic  #10                 // Method java/lang/Boolean.parseBoolean:(Ljava/lang/String;)Z
      37: ifeq          44
      40: iconst_1
      41: goto          45
      44: iconst_0
      45: istore        4
      47: iload         4
      49: ifeq          67
      52: new           #11                 // class com/google/zxing/oned/Code128Writer$MinimalEncoder
      55: dup
      56: aconst_null
      57: invokespecial #12                 // Method com/google/zxing/oned/Code128Writer$MinimalEncoder."<init>":(Lcom/google/zxing/oned/Code128Writer$1;)V
      60: aload_1
      61: invokestatic  #13                 // Method com/google/zxing/oned/Code128Writer$MinimalEncoder.access$100:(Lcom/google/zxing/oned/Code128Writer$MinimalEncoder;Ljava/lang/String;)[Z
      64: goto          72
      67: aload_1
      68: iload_3
      69: invokestatic  #14                 // Method encodeFast:(Ljava/lang/String;I)[Z
      72: areturn

  private static int check(java.lang.String, java.util.Map<com.google.zxing.EncodeHintType, ?>);
    Code:
       0: aload_0
       1: invokevirtual #15                 // Method java/lang/String.length:()I
       4: istore_2
       5: iload_2
       6: iconst_1
       7: if_icmplt     16
      10: iload_2
      11: bipush        80
      13: if_icmple     43
      16: new           #16                 // class java/lang/IllegalArgumentException
      19: dup
      20: new           #17                 // class java/lang/StringBuilder
      23: dup
      24: invokespecial #18                 // Method java/lang/StringBuilder."<init>":()V
      27: ldc           #19                 // String Contents length should be between 1 and 80 characters, but got
      29: invokevirtual #20                 // Method java/lang/StringBuilder.append:(Ljava/lang/String;)Ljava/lang/StringBuilder;
      32: iload_2
      33: invokevirtual #21                 // Method java/lang/StringBuilder.append:(I)Ljava/lang/StringBuilder;
      36: invokevirtual #22                 // Method java/lang/StringBuilder.toString:()Ljava/lang/String;
      39: invokespecial #23                 // Method java/lang/IllegalArgumentException."<init>":(Ljava/lang/String;)V
      42: athrow
      43: iconst_m1
      44: istore_3
      45: aload_1
      46: ifnull        230
      49: aload_1
      50: getstatic     #24                 // Field com/google/zxing/EncodeHintType.FORCE_CODE_SET:Lcom/google/zxing/EncodeHintType;
      53: invokeinterface #7,  2            // InterfaceMethod java/util/Map.containsKey:(Ljava/lang/Object;)Z
      58: ifeq          230
      61: aload_1
      62: getstatic     #24                 // Field com/google/zxing/EncodeHintType.FORCE_CODE_SET:Lcom/google/zxing/EncodeHintType;
      65: invokeinterface #8,  2            // InterfaceMethod java/util/Map.get:(Ljava/lang/Object;)Ljava/lang/Object;
      70: invokevirtual #9                  // Method java/lang/Object.toString:()Ljava/lang/String;
      73: astore        4
      75: aload         4
      77: astore        5
      79: iconst_m1
      80: istore        6
      82: aload         5
      84: invokevirtual #25                 // Method java/lang/String.hashCode:()I
      87: tableswitch   { // 65 to 67
                    65: 112
                    66: 128
                    67: 144
               default: 157
          }
     112: aload         5
     114: ldc           #26                 // String A
     116: invokevirtual #27                 // Method java/lang/String.equals:(Ljava/lang/Object;)Z
     119: ifeq          157
     122: iconst_0
     123: istore        6
     125: goto          157
     128: aload         5
     130: ldc           #28                 // String B
     132: invokevirtual #27                 // Method java/lang/String.equals:(Ljava/lang/Object;)Z
     135: ifeq          157
     138: iconst_1
     139: istore        6
     141: goto          157
     144: aload         5
     146: ldc           #29                 // String C
     148: invokevirtual #27                 // Method java/lang/String.equals:(Ljava/lang/Object;)Z
     151: ifeq          157
     154: iconst_2
     155: istore        6
     157: iload         6
     159: tableswitch   { // 0 to 2
                     0: 184
                     1: 190
                     2: 196
               default: 202
          }
     184: bipush        101
     186: istore_3
     187: goto          230
     190: bipush        100
     192: istore_3
     193: goto          230
     196: bipush        99
     198: istore_3
     199: goto          230
     202: new           #16                 // class java/lang/IllegalArgumentException
     205: dup
     206: new           #17                 // class java/lang/StringBuilder
     209: dup
     210: invokespecial #18                 // Method java/lang/StringBuilder."<init>":()V
     213: ldc           #31                 // String Unsupported code set hint:
     215: invokevirtual #20                 // Method java/lang/StringBuilder.append:(Ljava/lang/String;)Ljava/lang/StringBuilder;
     218: aload         4
     220: invokevirtual #20                 // Method java/lang/StringBuilder.append:(Ljava/lang/String;)Ljava/lang/StringBuilder;
     223: invokevirtual #22                 // Method java/lang/StringBuilder.toString:()Ljava/lang/String;
     226: invokespecial #23                 // Method java/lang/IllegalArgumentException."<init>":(Ljava/lang/String;)V
     229: athrow
     230: iconst_0
     231: istore        4
     233: iload         4
     235: iload_2
     236: if_icmpge     500
     239: aload_0
     240: iload         4
     242: invokevirtual #32                 // Method java/lang/String.charAt:(I)C
     245: istore        5
     247: iload         5
     249: tableswitch   { // 241 to 244
                   241: 280
                   242: 280
                   243: 280
                   244: 280
               default: 283
          }
     280: goto          318
     283: iload         5
     285: bipush        127
     287: if_icmple     318
     290: new           #16                 // class java/lang/IllegalArgumentException
     293: dup
     294: new           #17                 // class java/lang/StringBuilder
     297: dup
     298: invokespecial #18                 // Method java/lang/StringBuilder."<init>":()V
     301: ldc           #33                 // String Bad character in input: ASCII value=
     303: invokevirtual #20                 // Method java/lang/StringBuilder.append:(Ljava/lang/String;)Ljava/lang/StringBuilder;
     306: iload         5
     308: invokevirtual #21                 // Method java/lang/StringBuilder.append:(I)Ljava/lang/StringBuilder;
     311: invokevirtual #22                 // Method java/lang/StringBuilder.toString:()Ljava/lang/String;
     314: invokespecial #23                 // Method java/lang/IllegalArgumentException."<init>":(Ljava/lang/String;)V
     317: athrow
     318: iload_3
     319: tableswitch   { // 99 to 101
                    99: 421
                   100: 386
                   101: 344
               default: 494
          }
     344: iload         5
     346: bipush        95
     348: if_icmple     494
     351: iload         5
     353: bipush        127
     355: if_icmpgt     494
     358: new           #16                 // class java/lang/IllegalArgumentException
     361: dup
     362: new           #17                 // class java/lang/StringBuilder
     365: dup
     366: invokespecial #18                 // Method java/lang/StringBuilder."<init>":()V
     369: ldc           #34                 // String Bad character in input for forced code set A: ASCII value=
     371: invokevirtual #20                 // Method java/lang/StringBuilder.append:(Ljava/lang/String;)Ljava/lang/StringBuilder;
     374: iload         5
     376: invokevirtual #21                 // Method java/lang/StringBuilder.append:(I)Ljava/lang/StringBuilder;
     379: invokevirtual #22                 // Method java/lang/StringBuilder.toString:()Ljava/lang/String;
     382: invokespecial #23                 // Method java/lang/IllegalArgumentException."<init>":(Ljava/lang/String;)V
     385: athrow
     386: iload         5
     388: bipush        32
     390: if_icmpgt     494
     393: new           #16                 // class java/lang/IllegalArgumentException
     396: dup
     397: new           #17                 // class java/lang/StringBuilder
     400: dup
     401: invokespecial #18                 // Method java/lang/StringBuilder."<init>":()V
     404: ldc           #35                 // String Bad character in input for forced code set B: ASCII value=
     406: invokevirtual #20                 // Method java/lang/StringBuilder.append:(Ljava/lang/String;)Ljava/lang/StringBuilder;
     409: iload         5
     411: invokevirtual #21                 // Method java/lang/StringBuilder.append:(I)Ljava/lang/StringBuilder;
     414: invokevirtual #22                 // Method java/lang/StringBuilder.toString:()Ljava/lang/String;
     417: invokespecial #23                 // Method java/lang/IllegalArgumentException."<init>":(Ljava/lang/String;)V
     420: athrow
     421: iload         5
     423: bipush        48
     425: if_icmplt     466
     428: iload         5
     430: bipush        57
     432: if_icmple     442
     435: iload         5
     437: bipush        127
     439: if_icmple     466
     442: iload         5
     444: sipush        242
     447: if_icmpeq     466
     450: iload         5
     452: sipush        243
     455: if_icmpeq     466
     458: iload         5
     460: sipush        244
     463: if_icmpne     494
     466: new           #16                 // class java/lang/IllegalArgumentException
     469: dup
     470: new           #17                 // class java/lang/StringBuilder
     473: dup
     474: invokespecial #18                 // Method java/lang/StringBuilder."<init>":()V
     477: ldc           #36                 // String Bad character in input for forced code set C: ASCII value=
     479: invokevirtual #20                 // Method java/lang/StringBuilder.append:(Ljava/lang/String;)Ljava/lang/StringBuilder;
     482: iload         5
     484: invokevirtual #21                 // Method java/lang/StringBuilder.append:(I)Ljava/lang/StringBuilder;
     487: invokevirtual #22                 // Method java/lang/StringBuilder.toString:()Ljava/lang/String;
     490: invokespecial #23                 // Method java/lang/IllegalArgumentException."<init>":(Ljava/lang/String;)V
     493: athrow
     494: iinc          4, 1
     497: goto          233
     500: iload_3
     501: ireturn

  private static boolean[] encodeFast(java.lang.String, int);
    Code:
       0: aload_0
       1: invokevirtual #15                 // Method java/lang/String.length:()I
       4: istore_2
       5: new           #37                 // class java/util/ArrayList
       8: dup
       9: invokespecial #38                 // Method java/util/ArrayList."<init>":()V
      12: astore_3
      13: iconst_0
      14: istore        4
      16: iconst_1
      17: istore        5
      19: iconst_0
      20: istore        6
      22: iconst_0
      23: istore        7
      25: iload         7
      27: iload_2
      28: if_icmpge     343
      31: iload_1
      32: iconst_m1
      33: if_icmpne     49
      36: aload_0
      37: iload         7
      39: iload         6
      41: invokestatic  #39                 // Method chooseCode:(Ljava/lang/CharSequence;II)I
      44: istore        8
      46: goto          52
      49: iload_1
      50: istore        8
      52: iload         8
      54: iload         6
      56: if_icmpne     246
      59: aload_0
      60: iload         7
      62: invokevirtual #32                 // Method java/lang/String.charAt:(I)C
      65: tableswitch   { // 241 to 244
                   241: 96
                   242: 103
                   243: 110
                   244: 117
               default: 138
          }
      96: bipush        102
      98: istore        9
     100: goto          240
     103: bipush        97
     105: istore        9
     107: goto          240
     110: bipush        96
     112: istore        9
     114: goto          240
     117: iload         6
     119: bipush        101
     121: if_icmpne     131
     124: bipush        101
     126: istore        9
     128: goto          240
     131: bipush        100
     133: istore        9
     135: goto          240
     138: iload         6
     140: lookupswitch  { // 2
                   100: 190
                   101: 168
               default: 204
          }
     168: aload_0
     169: iload         7
     171: invokevirtual #32                 // Method java/lang/String.charAt:(I)C
     174: bipush        32
     176: isub
     177: istore        9
     179: iload         9
     181: ifge          240
     184: iinc          9, 96
     187: goto          240
     190: aload_0
     191: iload         7
     193: invokevirtual #32                 // Method java/lang/String.charAt:(I)C
     196: bipush        32
     198: isub
     199: istore        9
     201: goto          240
     204: iload         7
     206: iconst_1
     207: iadd
     208: iload_2
     209: if_icmpne     222
     212: new           #16                 // class java/lang/IllegalArgumentException
     215: dup
     216: ldc           #40                 // String Bad number of characters for digit only encoding.
     218: invokespecial #23                 // Method java/lang/IllegalArgumentException."<init>":(Ljava/lang/String;)V
     221: athrow
     222: aload_0
     223: iload         7
     225: iload         7
     227: iconst_2
     228: iadd
     229: invokevirtual #41                 // Method java/lang/String.substring:(II)Ljava/lang/String;
     232: invokestatic  #42                 // Method java/lang/Integer.parseInt:(Ljava/lang/String;)I
     235: istore        9
     237: iinc          7, 1
     240: iinc          7, 1
     243: goto          309
     246: iload         6
     248: ifne          301
     251: iload         8
     253: lookupswitch  { // 2
                   100: 287
                   101: 280
               default: 294
          }
     280: bipush        103
     282: istore        9
     284: goto          305
     287: bipush        104
     289: istore        9
     291: goto          305
     294: bipush        105
     296: istore        9
     298: goto          305
     301: iload         8
     303: istore        9
     305: iload         8
     307: istore        6
     309: aload_3
     310: getstatic     #43                 // Field com/google/zxing/oned/Code128Reader.CODE_PATTERNS:[[I
     313: iload         9
     315: aaload
     316: invokeinterface #44,  2           // InterfaceMethod java/util/Collection.add:(Ljava/lang/Object;)Z
     321: pop
     322: iload         4
     324: iload         9
     326: iload         5
     328: imul
     329: iadd
     330: istore        4
     332: iload         7
     334: ifeq          340
     337: iinc          5, 1
     340: goto          25
     343: aload_3
     344: iload         4
     346: invokestatic  #45                 // Method produceResult:(Ljava/util/Collection;I)[Z
     349: areturn

  static boolean[] produceResult(java.util.Collection<int[]>, int);
    Code:
       0: iload_1
       1: bipush        103
       3: irem
       4: istore_1
       5: aload_0
       6: getstatic     #43                 // Field com/google/zxing/oned/Code128Reader.CODE_PATTERNS:[[I
       9: iload_1
      10: aaload
      11: invokeinterface #44,  2           // InterfaceMethod java/util/Collection.add:(Ljava/lang/Object;)Z
      16: pop
      17: aload_0
      18: getstatic     #43                 // Field com/google/zxing/oned/Code128Reader.CODE_PATTERNS:[[I
      21: bipush        106
      23: aaload
      24: invokeinterface #44,  2           // InterfaceMethod java/util/Collection.add:(Ljava/lang/Object;)Z
      29: pop
      30: iconst_0
      31: istore_2
      32: aload_0
      33: invokeinterface #46,  1           // InterfaceMethod java/util/Collection.iterator:()Ljava/util/Iterator;
      38: astore_3
      39: aload_3
      40: invokeinterface #47,  1           // InterfaceMethod java/util/Iterator.hasNext:()Z
      45: ifeq          99
      48: aload_3
      49: invokeinterface #48,  1           // InterfaceMethod java/util/Iterator.next:()Ljava/lang/Object;
      54: checkcast     #49                 // class "[I"
      57: astore        4
      59: aload         4
      61: astore        5
      63: aload         5
      65: arraylength
      66: istore        6
      68: iconst_0
      69: istore        7
      71: iload         7
      73: iload         6
      75: if_icmpge     96
      78: aload         5
      80: iload         7
      82: iaload
      83: istore        8
      85: iload_2
      86: iload         8
      88: iadd
      89: istore_2
      90: iinc          7, 1
      93: goto          71
      96: goto          39
      99: iload_2
     100: newarray       boolean
     102: astore_3
     103: iconst_0
     104: istore        4
     106: aload_0
     107: invokeinterface #46,  1           // InterfaceMethod java/util/Collection.iterator:()Ljava/util/Iterator;
     112: astore        5
     114: aload         5
     116: invokeinterface #47,  1           // InterfaceMethod java/util/Iterator.hasNext:()Z
     121: ifeq          153
     124: aload         5
     126: invokeinterface #48,  1           // InterfaceMethod java/util/Iterator.next:()Ljava/lang/Object;
     131: checkcast     #49                 // class "[I"
     134: astore        6
     136: iload         4
     138: aload_3
     139: iload         4
     141: aload         6
     143: iconst_1
     144: invokestatic  #50                 // Method appendPattern:([ZI[IZ)I
     147: iadd
     148: istore        4
     150: goto          114
     153: aload_3
     154: areturn

  private static com.google.zxing.oned.Code128Writer$CType findCType(java.lang.CharSequence, int);
    Code:
       0: aload_0
       1: invokeinterface #51,  1           // InterfaceMethod java/lang/CharSequence.length:()I
       6: istore_2
       7: iload_1
       8: iload_2
       9: if_icmplt     16
      12: getstatic     #52                 // Field com/google/zxing/oned/Code128Writer$CType.UNCODABLE:Lcom/google/zxing/oned/Code128Writer$CType;
      15: areturn
      16: aload_0
      17: iload_1
      18: invokeinterface #53,  2           // InterfaceMethod java/lang/CharSequence.charAt:(I)C
      23: istore_3
      24: iload_3
      25: sipush        241
      28: if_icmpne     35
      31: getstatic     #54                 // Field com/google/zxing/oned/Code128Writer$CType.FNC_1:Lcom/google/zxing/oned/Code128Writer$CType;
      34: areturn
      35: iload_3
      36: bipush        48
      38: if_icmplt     47
      41: iload_3
      42: bipush        57
      44: if_icmple     51
      47: getstatic     #52                 // Field com/google/zxing/oned/Code128Writer$CType.UNCODABLE:Lcom/google/zxing/oned/Code128Writer$CType;
      50: areturn
      51: iload_1
      52: iconst_1
      53: iadd
      54: iload_2
      55: if_icmplt     62
      58: getstatic     #55                 // Field com/google/zxing/oned/Code128Writer$CType.ONE_DIGIT:Lcom/google/zxing/oned/Code128Writer$CType;
      61: areturn
      62: aload_0
      63: iload_1
      64: iconst_1
      65: iadd
      66: invokeinterface #53,  2           // InterfaceMethod java/lang/CharSequence.charAt:(I)C
      71: istore_3
      72: iload_3
      73: bipush        48
      75: if_icmplt     84
      78: iload_3
      79: bipush        57
      81: if_icmple     88
      84: getstatic     #55                 // Field com/google/zxing/oned/Code128Writer$CType.ONE_DIGIT:Lcom/google/zxing/oned/Code128Writer$CType;
      87: areturn
      88: getstatic     #56                 // Field com/google/zxing/oned/Code128Writer$CType.TWO_DIGITS:Lcom/google/zxing/oned/Code128Writer$CType;
      91: areturn

  private static int chooseCode(java.lang.CharSequence, int, int);
    Code:
       0: aload_0
       1: iload_1
       2: invokestatic  #57                 // Method findCType:(Ljava/lang/CharSequence;I)Lcom/google/zxing/oned/Code128Writer$CType;
       5: astore_3
       6: aload_3
       7: getstatic     #55                 // Field com/google/zxing/oned/Code128Writer$CType.ONE_DIGIT:Lcom/google/zxing/oned/Code128Writer$CType;
      10: if_acmpne     25
      13: iload_2
      14: bipush        101
      16: if_icmpne     22
      19: bipush        101
      21: ireturn
      22: bipush        100
      24: ireturn
      25: aload_3
      26: getstatic     #52                 // Field com/google/zxing/oned/Code128Writer$CType.UNCODABLE:Lcom/google/zxing/oned/Code128Writer$CType;
      29: if_acmpne     93
      32: iload_1
      33: aload_0
      34: invokeinterface #51,  1           // InterfaceMethod java/lang/CharSequence.length:()I
      39: if_icmpge     90
      42: aload_0
      43: iload_1
      44: invokeinterface #53,  2           // InterfaceMethod java/lang/CharSequence.charAt:(I)C
      49: istore        4
      51: iload         4
      53: bipush        32
      55: if_icmplt     87
      58: iload_2
      59: bipush        101
      61: if_icmpne     90
      64: iload         4
      66: bipush        96
      68: if_icmplt     87
      71: iload         4
      73: sipush        241
      76: if_icmplt     90
      79: iload         4
      81: sipush        244
      84: if_icmpgt     90
      87: bipush        101
      89: ireturn
      90: bipush        100
      92: ireturn
      93: iload_2
      94: bipush        101
      96: if_icmpne     109
      99: aload_3
     100: getstatic     #54                 // Field com/google/zxing/oned/Code128Writer$CType.FNC_1:Lcom/google/zxing/oned/Code128Writer$CType;
     103: if_acmpne     109
     106: bipush        101
     108: ireturn
     109: iload_2
     110: bipush        99
     112: if_icmpne     118
     115: bipush        99
     117: ireturn
     118: iload_2
     119: bipush        100
     121: if_icmpne     225
     124: aload_3
     125: getstatic     #54                 // Field com/google/zxing/oned/Code128Writer$CType.FNC_1:Lcom/google/zxing/oned/Code128Writer$CType;
     128: if_acmpne     134
     131: bipush        100
     133: ireturn
     134: aload_0
     135: iload_1
     136: iconst_2
     137: iadd
     138: invokestatic  #57                 // Method findCType:(Ljava/lang/CharSequence;I)Lcom/google/zxing/oned/Code128Writer$CType;
     141: astore_3
     142: aload_3
     143: getstatic     #52                 // Field com/google/zxing/oned/Code128Writer$CType.UNCODABLE:Lcom/google/zxing/oned/Code128Writer$CType;
     146: if_acmpeq     156
     149: aload_3
     150: getstatic     #55                 // Field com/google/zxing/oned/Code128Writer$CType.ONE_DIGIT:Lcom/google/zxing/oned/Code128Writer$CType;
     153: if_acmpne     159
     156: bipush        100
     158: ireturn
     159: aload_3
     160: getstatic     #54                 // Field com/google/zxing/oned/Code128Writer$CType.FNC_1:Lcom/google/zxing/oned/Code128Writer$CType;
     163: if_acmpne     187
     166: aload_0
     167: iload_1
     168: iconst_3
     169: iadd
     170: invokestatic  #57                 // Method findCType:(Ljava/lang/CharSequence;I)Lcom/google/zxing/oned/Code128Writer$CType;
     173: astore_3
     174: aload_3
     175: getstatic     #56                 // Field com/google/zxing/oned/Code128Writer$CType.TWO_DIGITS:Lcom/google/zxing/oned/Code128Writer$CType;
     178: if_acmpne     184
     181: bipush        99
     183: ireturn
     184: bipush        100
     186: ireturn
     187: iload_1
     188: iconst_4
     189: iadd
     190: istore        4
     192: aload_0
     193: iload         4
     195: invokestatic  #57                 // Method findCType:(Ljava/lang/CharSequence;I)Lcom/google/zxing/oned/Code128Writer$CType;
     198: dup
     199: astore_3
     200: getstatic     #56                 // Field com/google/zxing/oned/Code128Writer$CType.TWO_DIGITS:Lcom/google/zxing/oned/Code128Writer$CType;
     203: if_acmpne     212
     206: iinc          4, 2
     209: goto          192
     212: aload_3
     213: getstatic     #55                 // Field com/google/zxing/oned/Code128Writer$CType.ONE_DIGIT:Lcom/google/zxing/oned/Code128Writer$CType;
     216: if_acmpne     222
     219: bipush        100
     221: ireturn
     222: bipush        99
     224: ireturn
     225: aload_3
     226: getstatic     #54                 // Field com/google/zxing/oned/Code128Writer$CType.FNC_1:Lcom/google/zxing/oned/Code128Writer$CType;
     229: if_acmpne     240
     232: aload_0
     233: iload_1
     234: iconst_1
     235: iadd
     236: invokestatic  #57                 // Method findCType:(Ljava/lang/CharSequence;I)Lcom/google/zxing/oned/Code128Writer$CType;
     239: astore_3
     240: aload_3
     241: getstatic     #56                 // Field com/google/zxing/oned/Code128Writer$CType.TWO_DIGITS:Lcom/google/zxing/oned/Code128Writer$CType;
     244: if_acmpne     250
     247: bipush        99
     249: ireturn
     250: bipush        100
     252: ireturn
}
