Compiled from "Code128Writer.java"
class com.google.zxing.oned.Code128Writer$1 {
  static final int[] $SwitchMap$com$google$zxing$oned$Code128Writer$MinimalEncoder$Latch;

  static final int[] $SwitchMap$com$google$zxing$oned$Code128Writer$MinimalEncoder$Charset;

  static {};
    Code:
       0: invokestatic  #1                  // Method com/google/zxing/oned/Code128Writer$MinimalEncoder$Charset.values:()[Lcom/google/zxing/oned/Code128Writer$MinimalEncoder$Charset;
       3: arraylength
       4: newarray       int
       6: putstatic     #2                  // Field $SwitchMap$com$google$zxing$oned$Code128Writer$MinimalEncoder$Charset:[I
       9: getstatic     #2                  // Field $SwitchMap$com$google$zxing$oned$Code128Writer$MinimalEncoder$Charset:[I
      12: getstatic     #3                  // Field com/google/zxing/oned/Code128Writer$MinimalEncoder$Charset.A:Lcom/google/zxing/oned/Code128Writer$MinimalEncoder$Charset;
      15: invokevirtual #4                  // Method com/google/zxing/oned/Code128Writer$MinimalEncoder$Charset.ordinal:()I
      18: iconst_1
      19: iastore
      20: goto          24
      23: astore_0
      24: getstatic     #2                  // Field $SwitchMap$com$google$zxing$oned$Code128Writer$MinimalEncoder$Charset:[I
      27: getstatic     #6                  // Field com/google/zxing/oned/Code128Writer$MinimalEncoder$Charset.B:Lcom/google/zxing/oned/Code128Writer$MinimalEncoder$Charset;
      30: invokevirtual #4                  // Method com/google/zxing/oned/Code128Writer$MinimalEncoder$Charset.ordinal:()I
      33: iconst_2
      34: iastore
      35: goto          39
      38: astore_0
      39: getstatic     #2                  // Field $SwitchMap$com$google$zxing$oned$Code128Writer$MinimalEncoder$Charset:[I
      42: getstatic     #7                  // Field com/google/zxing/oned/Code128Writer$MinimalEncoder$Charset.C:Lcom/google/zxing/oned/Code128Writer$MinimalEncoder$Charset;
      45: invokevirtual #4                  // Method com/google/zxing/oned/Code128Writer$MinimalEncoder$Charset.ordinal:()I
      48: iconst_3
      49: iastore
      50: goto          54
      53: astore_0
      54: invokestatic  #8                  // Method com/google/zxing/oned/Code128Writer$MinimalEncoder$Latch.values:()[Lcom/google/zxing/oned/Code128Writer$MinimalEncoder$Latch;
      57: arraylength
      58: newarray       int
      60: putstatic     #9                  // Field $SwitchMap$com$google$zxing$oned$Code128Writer$MinimalEncoder$Latch:[I
      63: getstatic     #9                  // Field $SwitchMap$com$google$zxing$oned$Code128Writer$MinimalEncoder$Latch:[I
      66: getstatic     #10                 // Field com/google/zxing/oned/Code128Writer$MinimalEncoder$Latch.A:Lcom/google/zxing/oned/Code128Writer$MinimalEncoder$Latch;
      69: invokevirtual #11                 // Method com/google/zxing/oned/Code128Writer$MinimalEncoder$Latch.ordinal:()I
      72: iconst_1
      73: iastore
      74: goto          78
      77: astore_0
      78: getstatic     #9                  // Field $SwitchMap$com$google$zxing$oned$Code128Writer$MinimalEncoder$Latch:[I
      81: getstatic     #12                 // Field com/google/zxing/oned/Code128Writer$MinimalEncoder$Latch.B:Lcom/google/zxing/oned/Code128Writer$MinimalEncoder$Latch;
      84: invokevirtual #11                 // Method com/google/zxing/oned/Code128Writer$MinimalEncoder$Latch.ordinal:()I
      87: iconst_2
      88: iastore
      89: goto          93
      92: astore_0
      93: getstatic     #9                  // Field $SwitchMap$com$google$zxing$oned$Code128Writer$MinimalEncoder$Latch:[I
      96: getstatic     #13                 // Field com/google/zxing/oned/Code128Writer$MinimalEncoder$Latch.C:Lcom/google/zxing/oned/Code128Writer$MinimalEncoder$Latch;
      99: invokevirtual #11                 // Method com/google/zxing/oned/Code128Writer$MinimalEncoder$Latch.ordinal:()I
     102: iconst_3
     103: iastore
     104: goto          108
     107: astore_0
     108: getstatic     #9                  // Field $SwitchMap$com$google$zxing$oned$Code128Writer$MinimalEncoder$Latch:[I
     111: getstatic     #14                 // Field com/google/zxing/oned/Code128Writer$MinimalEncoder$Latch.SHIFT:Lcom/google/zxing/oned/Code128Writer$MinimalEncoder$Latch;
     114: invokevirtual #11                 // Method com/google/zxing/oned/Code128Writer$MinimalEncoder$Latch.ordinal:()I
     117: iconst_4
     118: iastore
     119: goto          123
     122: astore_0
     123: return
    Exception table:
       from    to  target type
           9    20    23   Class java/lang/NoSuchFieldError
          24    35    38   Class java/lang/NoSuchFieldError
          39    50    53   Class java/lang/NoSuchFieldError
          63    74    77   Class java/lang/NoSuchFieldError
          78    89    92   Class java/lang/NoSuchFieldError
          93   104   107   Class java/lang/NoSuchFieldError
         108   119   122   Class java/lang/NoSuchFieldError
}
