Compiled from "OneDimensionalCodeWriter.java"
public abstract class com.google.zxing.oned.OneDimensionalCodeWriter implements com.google.zxing.Writer {
  private static final java.util.regex.Pattern NUMERIC;

  public com.google.zxing.oned.OneDimensionalCodeWriter();
    Code:
       0: aload_0
       1: invokespecial #1                  // Method java/lang/Object."<init>":()V
       4: return

  public abstract boolean[] encode(java.lang.String);

  protected boolean[] encode(java.lang.String, java.util.Map<com.google.zxing.EncodeHintType, ?>);
    Code:
       0: aload_0
       1: aload_1
       2: invokevirtual #2                  // Method encode:(Ljava/lang/String;)[Z
       5: areturn

  public final com.google.zxing.common.BitMatrix encode(java.lang.String, com.google.zxing.BarcodeFormat, int, int);
    Code:
       0: aload_0
       1: aload_1
       2: aload_2
       3: iload_3
       4: iload         4
       6: aconst_null
       7: invokevirtual #3                  // Method encode:(Ljava/lang/String;Lcom/google/zxing/BarcodeFormat;IILjava/util/Map;)Lcom/google/zxing/common/BitMatrix;
      10: areturn

  public com.google.zxing.common.BitMatrix encode(java.lang.String, com.google.zxing.BarcodeFormat, int, int, java.util.Map<com.google.zxing.EncodeHintType, ?>);
    Code:
       0: aload_1
       1: invokevirtual #4                  // Method java/lang/String.isEmpty:()Z
       4: ifeq          17
       7: new           #5                  // class java/lang/IllegalArgumentException
      10: dup
      11: ldc           #6                  // String Found empty contents
      13: invokespecial #7                  // Method java/lang/IllegalArgumentException."<init>":(Ljava/lang/String;)V
      16: athrow
      17: iload_3
      18: iflt          26
      21: iload         4
      23: ifge          63
      26: new           #5                  // class java/lang/IllegalArgumentException
      29: dup
      30: new           #8                  // class java/lang/StringBuilder
      33: dup
      34: invokespecial #9                  // Method java/lang/StringBuilder."<init>":()V
      37: ldc           #10                 // String Negative size is not allowed. Input:
      39: invokevirtual #11                 // Method java/lang/StringBuilder.append:(Ljava/lang/String;)Ljava/lang/StringBuilder;
      42: iload_3
      43: invokevirtual #12                 // Method java/lang/StringBuilder.append:(I)Ljava/lang/StringBuilder;
      46: bipush        120
      48: invokevirtual #13                 // Method java/lang/StringBuilder.append:(C)Ljava/lang/StringBuilder;
      51: iload         4
      53: invokevirtual #12                 // Method java/lang/StringBuilder.append:(I)Ljava/lang/StringBuilder;
      56: invokevirtual #14                 // Method java/lang/StringBuilder.toString:()Ljava/lang/String;
      59: invokespecial #7                  // Method java/lang/IllegalArgumentException."<init>":(Ljava/lang/String;)V
      62: athrow
      63: aload_0
      64: invokevirtual #15                 // Method getSupportedWriteFormats:()Ljava/util/Collection;
      67: astore        6
      69: aload         6
      71: ifnull        122
      74: aload         6
      76: aload_2
      77: invokeinterface #16,  2           // InterfaceMethod java/util/Collection.contains:(Ljava/lang/Object;)Z
      82: ifne          122
      85: new           #5                  // class java/lang/IllegalArgumentException
      88: dup
      89: new           #8                  // class java/lang/StringBuilder
      92: dup
      93: invokespecial #9                  // Method java/lang/StringBuilder."<init>":()V
      96: ldc           #17                 // String Can only encode
      98: invokevirtual #11                 // Method java/lang/StringBuilder.append:(Ljava/lang/String;)Ljava/lang/StringBuilder;
     101: aload         6
     103: invokevirtual #18                 // Method java/lang/StringBuilder.append:(Ljava/lang/Object;)Ljava/lang/StringBuilder;
     106: ldc           #19                 // String , but got
     108: invokevirtual #11                 // Method java/lang/StringBuilder.append:(Ljava/lang/String;)Ljava/lang/StringBuilder;
     111: aload_2
     112: invokevirtual #18                 // Method java/lang/StringBuilder.append:(Ljava/lang/Object;)Ljava/lang/StringBuilder;
     115: invokevirtual #14                 // Method java/lang/StringBuilder.toString:()Ljava/lang/String;
     118: invokespecial #7                  // Method java/lang/IllegalArgumentException."<init>":(Ljava/lang/String;)V
     121: athrow
     122: aload_0
     123: invokevirtual #20                 // Method getDefaultMargin:()I
     126: istore        7
     128: aload         5
     130: ifnull        164
     133: aload         5
     135: getstatic     #21                 // Field com/google/zxing/EncodeHintType.MARGIN:Lcom/google/zxing/EncodeHintType;
     138: invokeinterface #22,  2           // InterfaceMethod java/util/Map.containsKey:(Ljava/lang/Object;)Z
     143: ifeq          164
     146: aload         5
     148: getstatic     #21                 // Field com/google/zxing/EncodeHintType.MARGIN:Lcom/google/zxing/EncodeHintType;
     151: invokeinterface #23,  2           // InterfaceMethod java/util/Map.get:(Ljava/lang/Object;)Ljava/lang/Object;
     156: invokevirtual #24                 // Method java/lang/Object.toString:()Ljava/lang/String;
     159: invokestatic  #25                 // Method java/lang/Integer.parseInt:(Ljava/lang/String;)I
     162: istore        7
     164: aload_0
     165: aload_1
     166: aload         5
     168: invokevirtual #26                 // Method encode:(Ljava/lang/String;Ljava/util/Map;)[Z
     171: astore        8
     173: aload         8
     175: iload_3
     176: iload         4
     178: iload         7
     180: invokestatic  #27                 // Method renderResult:([ZIII)Lcom/google/zxing/common/BitMatrix;
     183: areturn

  protected java.util.Collection<com.google.zxing.BarcodeFormat> getSupportedWriteFormats();
    Code:
       0: aconst_null
       1: areturn

  private static com.google.zxing.common.BitMatrix renderResult(boolean[], int, int, int);
    Code:
       0: aload_0
       1: arraylength
       2: istore        4
       4: iload         4
       6: iload_3
       7: iadd
       8: istore        5
      10: iload_1
      11: iload         5
      13: invokestatic  #28                 // Method java/lang/Math.max:(II)I
      16: istore        6
      18: iconst_1
      19: iload_2
      20: invokestatic  #28                 // Method java/lang/Math.max:(II)I
      23: istore        7
      25: iload         6
      27: iload         5
      29: idiv
      30: istore        8
      32: iload         6
      34: iload         4
      36: iload         8
      38: imul
      39: isub
      40: iconst_2
      41: idiv
      42: istore        9
      44: new           #29                 // class com/google/zxing/common/BitMatrix
      47: dup
      48: iload         6
      50: iload         7
      52: invokespecial #30                 // Method com/google/zxing/common/BitMatrix."<init>":(II)V
      55: astore        10
      57: iconst_0
      58: istore        11
      60: iload         9
      62: istore        12
      64: iload         11
      66: iload         4
      68: if_icmpge     103
      71: aload_0
      72: iload         11
      74: baload
      75: ifeq          90
      78: aload         10
      80: iload         12
      82: iconst_0
      83: iload         8
      85: iload         7
      87: invokevirtual #31                 // Method com/google/zxing/common/BitMatrix.setRegion:(IIII)V
      90: iinc          11, 1
      93: iload         12
      95: iload         8
      97: iadd
      98: istore        12
     100: goto          64
     103: aload         10
     105: areturn

  protected static void checkNumeric(java.lang.String);
    Code:
       0: getstatic     #32                 // Field NUMERIC:Ljava/util/regex/Pattern;
       3: aload_0
       4: invokevirtual #33                 // Method java/util/regex/Pattern.matcher:(Ljava/lang/CharSequence;)Ljava/util/regex/Matcher;
       7: invokevirtual #34                 // Method java/util/regex/Matcher.matches:()Z
      10: ifne          23
      13: new           #5                  // class java/lang/IllegalArgumentException
      16: dup
      17: ldc           #35                 // String Input should only contain digits 0-9
      19: invokespecial #7                  // Method java/lang/IllegalArgumentException."<init>":(Ljava/lang/String;)V
      22: athrow
      23: return

  protected static int appendPattern(boolean[], int, int[], boolean);
    Code:
       0: iload_3
       1: istore        4
       3: iconst_0
       4: istore        5
       6: aload_2
       7: astore        6
       9: aload         6
      11: arraylength
      12: istore        7
      14: iconst_0
      15: istore        8
      17: iload         8
      19: iload         7
      21: if_icmpge     80
      24: aload         6
      26: iload         8
      28: iaload
      29: istore        9
      31: iconst_0
      32: istore        10
      34: iload         10
      36: iload         9
      38: if_icmpge     55
      41: aload_0
      42: iload_1
      43: iinc          1, 1
      46: iload         4
      48: bastore
      49: iinc          10, 1
      52: goto          34
      55: iload         5
      57: iload         9
      59: iadd
      60: istore        5
      62: iload         4
      64: ifne          71
      67: iconst_1
      68: goto          72
      71: iconst_0
      72: istore        4
      74: iinc          8, 1
      77: goto          17
      80: iload         5
      82: ireturn

  public int getDefaultMargin();
    Code:
       0: bipush        10
       2: ireturn

  static {};
    Code:
       0: ldc           #36                 // String [0-9]+
       2: invokestatic  #37                 // Method java/util/regex/Pattern.compile:(Ljava/lang/String;)Ljava/util/regex/Pattern;
       5: putstatic     #32                 // Field NUMERIC:Ljava/util/regex/Pattern;
       8: return
}
