Compiled from "UPCAWriter.java"
public final class com.google.zxing.oned.UPCAWriter implements com.google.zxing.Writer {
  private final com.google.zxing.oned.EAN13Writer subWriter;

  public com.google.zxing.oned.UPCAWriter();
    Code:
       0: aload_0
       1: invokespecial #1                  // Method java/lang/Object."<init>":()V
       4: aload_0
       5: new           #2                  // class com/google/zxing/oned/EAN13Writer
       8: dup
       9: invokespecial #3                  // Method com/google/zxing/oned/EAN13Writer."<init>":()V
      12: putfield      #4                  // Field subWriter:Lcom/google/zxing/oned/EAN13Writer;
      15: return

  public com.google.zxing.common.BitMatrix encode(java.lang.String, com.google.zxing.BarcodeFormat, int, int);
    Code:
       0: aload_0
       1: aload_1
       2: aload_2
       3: iload_3
       4: iload         4
       6: aconst_null
       7: invokevirtual #5                  // Method encode:(Ljava/lang/String;Lcom/google/zxing/BarcodeFormat;IILjava/util/Map;)Lcom/google/zxing/common/BitMatrix;
      10: areturn

  public com.google.zxing.common.BitMatrix encode(java.lang.String, com.google.zxing.BarcodeFormat, int, int, java.util.Map<com.google.zxing.EncodeHintType, ?>);
    Code:
       0: aload_2
       1: getstatic     #6                  // Field com/google/zxing/BarcodeFormat.UPC_A:Lcom/google/zxing/BarcodeFormat;
       4: if_acmpeq     34
       7: new           #7                  // class java/lang/IllegalArgumentException
      10: dup
      11: new           #8                  // class java/lang/StringBuilder
      14: dup
      15: invokespecial #9                  // Method java/lang/StringBuilder."<init>":()V
      18: ldc           #10                 // String Can only encode UPC-A, but got
      20: invokevirtual #11                 // Method java/lang/StringBuilder.append:(Ljava/lang/String;)Ljava/lang/StringBuilder;
      23: aload_2
      24: invokevirtual #12                 // Method java/lang/StringBuilder.append:(Ljava/lang/Object;)Ljava/lang/StringBuilder;
      27: invokevirtual #13                 // Method java/lang/StringBuilder.toString:()Ljava/lang/String;
      30: invokespecial #14                 // Method java/lang/IllegalArgumentException."<init>":(Ljava/lang/String;)V
      33: athrow
      34: aload_0
      35: getfield      #4                  // Field subWriter:Lcom/google/zxing/oned/EAN13Writer;
      38: new           #8                  // class java/lang/StringBuilder
      41: dup
      42: invokespecial #9                  // Method java/lang/StringBuilder."<init>":()V
      45: bipush        48
      47: invokevirtual #15                 // Method java/lang/StringBuilder.append:(C)Ljava/lang/StringBuilder;
      50: aload_1
      51: invokevirtual #11                 // Method java/lang/StringBuilder.append:(Ljava/lang/String;)Ljava/lang/StringBuilder;
      54: invokevirtual #13                 // Method java/lang/StringBuilder.toString:()Ljava/lang/String;
      57: getstatic     #16                 // Field com/google/zxing/BarcodeFormat.EAN_13:Lcom/google/zxing/BarcodeFormat;
      60: iload_3
      61: iload         4
      63: aload         5
      65: invokevirtual #17                 // Method com/google/zxing/oned/EAN13Writer.encode:(Ljava/lang/String;Lcom/google/zxing/BarcodeFormat;IILjava/util/Map;)Lcom/google/zxing/common/BitMatrix;
      68: areturn
}
