Compiled from "UPCAReader.java"
public final class com.google.zxing.oned.UPCAReader extends com.google.zxing.oned.UPCEANReader {
  private final com.google.zxing.oned.UPCEANReader ean13Reader;

  public com.google.zxing.oned.UPCAReader();
    Code:
       0: aload_0
       1: invokespecial #1                  // Method com/google/zxing/oned/UPCEANReader."<init>":()V
       4: aload_0
       5: new           #2                  // class com/google/zxing/oned/EAN13Reader
       8: dup
       9: invokespecial #3                  // Method com/google/zxing/oned/EAN13Reader."<init>":()V
      12: putfield      #4                  // Field ean13Reader:Lcom/google/zxing/oned/UPCEANReader;
      15: return

  public com.google.zxing.Result decodeRow(int, com.google.zxing.common.BitArray, int[], java.util.Map<com.google.zxing.DecodeHintType, ?>) throws com.google.zxing.NotFoundException, com.google.zxing.FormatException, com.google.zxing.ChecksumException;
    Code:
       0: aload_0
       1: getfield      #4                  // Field ean13Reader:Lcom/google/zxing/oned/UPCEANReader;
       4: iload_1
       5: aload_2
       6: aload_3
       7: aload         4
       9: invokevirtual #5                  // Method com/google/zxing/oned/UPCEANReader.decodeRow:(ILcom/google/zxing/common/BitArray;[ILjava/util/Map;)Lcom/google/zxing/Result;
      12: invokestatic  #6                  // Method maybeReturnResult:(Lcom/google/zxing/Result;)Lcom/google/zxing/Result;
      15: areturn

  public com.google.zxing.Result decodeRow(int, com.google.zxing.common.BitArray, java.util.Map<com.google.zxing.DecodeHintType, ?>) throws com.google.zxing.NotFoundException, com.google.zxing.FormatException, com.google.zxing.ChecksumException;
    Code:
       0: aload_0
       1: getfield      #4                  // Field ean13Reader:Lcom/google/zxing/oned/UPCEANReader;
       4: iload_1
       5: aload_2
       6: aload_3
       7: invokevirtual #7                  // Method com/google/zxing/oned/UPCEANReader.decodeRow:(ILcom/google/zxing/common/BitArray;Ljava/util/Map;)Lcom/google/zxing/Result;
      10: invokestatic  #6                  // Method maybeReturnResult:(Lcom/google/zxing/Result;)Lcom/google/zxing/Result;
      13: areturn

  public com.google.zxing.Result decode(com.google.zxing.BinaryBitmap) throws com.google.zxing.NotFoundException, com.google.zxing.FormatException;
    Code:
       0: aload_0
       1: getfield      #4                  // Field ean13Reader:Lcom/google/zxing/oned/UPCEANReader;
       4: aload_1
       5: invokevirtual #8                  // Method com/google/zxing/oned/UPCEANReader.decode:(Lcom/google/zxing/BinaryBitmap;)Lcom/google/zxing/Result;
       8: invokestatic  #6                  // Method maybeReturnResult:(Lcom/google/zxing/Result;)Lcom/google/zxing/Result;
      11: areturn

  public com.google.zxing.Result decode(com.google.zxing.BinaryBitmap, java.util.Map<com.google.zxing.DecodeHintType, ?>) throws com.google.zxing.NotFoundException, com.google.zxing.FormatException;
    Code:
       0: aload_0
       1: getfield      #4                  // Field ean13Reader:Lcom/google/zxing/oned/UPCEANReader;
       4: aload_1
       5: aload_2
       6: invokevirtual #9                  // Method com/google/zxing/oned/UPCEANReader.decode:(Lcom/google/zxing/BinaryBitmap;Ljava/util/Map;)Lcom/google/zxing/Result;
       9: invokestatic  #6                  // Method maybeReturnResult:(Lcom/google/zxing/Result;)Lcom/google/zxing/Result;
      12: areturn

  com.google.zxing.BarcodeFormat getBarcodeFormat();
    Code:
       0: getstatic     #10                 // Field com/google/zxing/BarcodeFormat.UPC_A:Lcom/google/zxing/BarcodeFormat;
       3: areturn

  protected int decodeMiddle(com.google.zxing.common.BitArray, int[], java.lang.StringBuilder) throws com.google.zxing.NotFoundException;
    Code:
       0: aload_0
       1: getfield      #4                  // Field ean13Reader:Lcom/google/zxing/oned/UPCEANReader;
       4: aload_1
       5: aload_2
       6: aload_3
       7: invokevirtual #11                 // Method com/google/zxing/oned/UPCEANReader.decodeMiddle:(Lcom/google/zxing/common/BitArray;[ILjava/lang/StringBuilder;)I
      10: ireturn

  private static com.google.zxing.Result maybeReturnResult(com.google.zxing.Result) throws com.google.zxing.FormatException;
    Code:
       0: aload_0
       1: invokevirtual #12                 // Method com/google/zxing/Result.getText:()Ljava/lang/String;
       4: astore_1
       5: aload_1
       6: iconst_0
       7: invokevirtual #13                 // Method java/lang/String.charAt:(I)C
      10: bipush        48
      12: if_icmpne     53
      15: new           #14                 // class com/google/zxing/Result
      18: dup
      19: aload_1
      20: iconst_1
      21: invokevirtual #15                 // Method java/lang/String.substring:(I)Ljava/lang/String;
      24: aconst_null
      25: aload_0
      26: invokevirtual #16                 // Method com/google/zxing/Result.getResultPoints:()[Lcom/google/zxing/ResultPoint;
      29: getstatic     #10                 // Field com/google/zxing/BarcodeFormat.UPC_A:Lcom/google/zxing/BarcodeFormat;
      32: invokespecial #17                 // Method com/google/zxing/Result."<init>":(Ljava/lang/String;[B[Lcom/google/zxing/ResultPoint;Lcom/google/zxing/BarcodeFormat;)V
      35: astore_2
      36: aload_0
      37: invokevirtual #18                 // Method com/google/zxing/Result.getResultMetadata:()Ljava/util/Map;
      40: ifnull        51
      43: aload_2
      44: aload_0
      45: invokevirtual #18                 // Method com/google/zxing/Result.getResultMetadata:()Ljava/util/Map;
      48: invokevirtual #19                 // Method com/google/zxing/Result.putAllMetadata:(Ljava/util/Map;)V
      51: aload_2
      52: areturn
      53: invokestatic  #20                 // Method com/google/zxing/FormatException.getFormatInstance:()Lcom/google/zxing/FormatException;
      56: athrow
}
