Compiled from "UPCEANExtensionSupport.java"
final class com.google.zxing.oned.UPCEANExtensionSupport {
  private static final int[] EXTENSION_START_PATTERN;

  private final com.google.zxing.oned.UPCEANExtension2Support twoSupport;

  private final com.google.zxing.oned.UPCEANExtension5Support fiveSupport;

  com.google.zxing.oned.UPCEANExtensionSupport();
    Code:
       0: aload_0
       1: invokespecial #1                  // Method java/lang/Object."<init>":()V
       4: aload_0
       5: new           #2                  // class com/google/zxing/oned/UPCEANExtension2Support
       8: dup
       9: invokespecial #3                  // Method com/google/zxing/oned/UPCEANExtension2Support."<init>":()V
      12: putfield      #4                  // Field twoSupport:Lcom/google/zxing/oned/UPCEANExtension2Support;
      15: aload_0
      16: new           #5                  // class com/google/zxing/oned/UPCEANExtension5Support
      19: dup
      20: invokespecial #6                  // Method com/google/zxing/oned/UPCEANExtension5Support."<init>":()V
      23: putfield      #7                  // Field fiveSupport:Lcom/google/zxing/oned/UPCEANExtension5Support;
      26: return

  com.google.zxing.Result decodeRow(int, com.google.zxing.common.BitArray, int) throws com.google.zxing.NotFoundException;
    Code:
       0: aload_2
       1: iload_3
       2: iconst_0
       3: getstatic     #8                  // Field EXTENSION_START_PATTERN:[I
       6: invokestatic  #9                  // Method com/google/zxing/oned/UPCEANReader.findGuardPattern:(Lcom/google/zxing/common/BitArray;IZ[I)[I
       9: astore        4
      11: aload_0
      12: getfield      #7                  // Field fiveSupport:Lcom/google/zxing/oned/UPCEANExtension5Support;
      15: iload_1
      16: aload_2
      17: aload         4
      19: invokevirtual #10                 // Method com/google/zxing/oned/UPCEANExtension5Support.decodeRow:(ILcom/google/zxing/common/BitArray;[I)Lcom/google/zxing/Result;
      22: areturn
      23: astore        5
      25: aload_0
      26: getfield      #4                  // Field twoSupport:Lcom/google/zxing/oned/UPCEANExtension2Support;
      29: iload_1
      30: aload_2
      31: aload         4
      33: invokevirtual #12                 // Method com/google/zxing/oned/UPCEANExtension2Support.decodeRow:(ILcom/google/zxing/common/BitArray;[I)Lcom/google/zxing/Result;
      36: areturn
    Exception table:
       from    to  target type
          11    22    23   Class com/google/zxing/ReaderException

  static {};
    Code:
       0: iconst_3
       1: newarray       int
       3: dup
       4: iconst_0
       5: iconst_1
       6: iastore
       7: dup
       8: iconst_1
       9: iconst_1
      10: iastore
      11: dup
      12: iconst_2
      13: iconst_2
      14: iastore
      15: putstatic     #8                  // Field EXTENSION_START_PATTERN:[I
      18: return
}
