Compiled from "UPCEANReader.java"
public abstract class com.google.zxing.oned.UPCEANReader extends com.google.zxing.oned.OneDReader {
  private static final float MAX_AVG_VARIANCE;

  private static final float MAX_INDIVIDUAL_VARIANCE;

  static final int[] START_END_PATTERN;

  static final int[] MIDDLE_PATTERN;

  static final int[] END_PATTERN;

  static final int[][] L_PATTERNS;

  static final int[][] L_AND_G_PATTERNS;

  private final java.lang.StringBuilder decodeRowStringBuffer;

  private final com.google.zxing.oned.UPCEANExtensionSupport extensionReader;

  private final com.google.zxing.oned.EANManufacturerOrgSupport eanManSupport;

  protected com.google.zxing.oned.UPCEANReader();
    Code:
       0: aload_0
       1: invokespecial #1                  // Method com/google/zxing/oned/OneDReader."<init>":()V
       4: aload_0
       5: new           #2                  // class java/lang/StringBuilder
       8: dup
       9: bipush        20
      11: invokespecial #3                  // Method java/lang/StringBuilder."<init>":(I)V
      14: putfield      #4                  // Field decodeRowStringBuffer:Ljava/lang/StringBuilder;
      17: aload_0
      18: new           #5                  // class com/google/zxing/oned/UPCEANExtensionSupport
      21: dup
      22: invokespecial #6                  // Method com/google/zxing/oned/UPCEANExtensionSupport."<init>":()V
      25: putfield      #7                  // Field extensionReader:Lcom/google/zxing/oned/UPCEANExtensionSupport;
      28: aload_0
      29: new           #8                  // class com/google/zxing/oned/EANManufacturerOrgSupport
      32: dup
      33: invokespecial #9                  // Method com/google/zxing/oned/EANManufacturerOrgSupport."<init>":()V
      36: putfield      #10                 // Field eanManSupport:Lcom/google/zxing/oned/EANManufacturerOrgSupport;
      39: return

  static int[] findStartGuardPattern(com.google.zxing.common.BitArray) throws com.google.zxing.NotFoundException;
    Code:
       0: iconst_0
       1: istore_1
       2: aconst_null
       3: astore_2
       4: iconst_0
       5: istore_3
       6: getstatic     #11                 // Field START_END_PATTERN:[I
       9: arraylength
      10: newarray       int
      12: astore        4
      14: iload_1
      15: ifne          77
      18: aload         4
      20: iconst_0
      21: getstatic     #11                 // Field START_END_PATTERN:[I
      24: arraylength
      25: iconst_0
      26: invokestatic  #12                 // Method java/util/Arrays.fill:([IIII)V
      29: aload_0
      30: iload_3
      31: iconst_0
      32: getstatic     #11                 // Field START_END_PATTERN:[I
      35: aload         4
      37: invokestatic  #13                 // Method findGuardPattern:(Lcom/google/zxing/common/BitArray;IZ[I[I)[I
      40: astore_2
      41: aload_2
      42: iconst_0
      43: iaload
      44: istore        5
      46: aload_2
      47: iconst_1
      48: iaload
      49: istore_3
      50: iload         5
      52: iload_3
      53: iload         5
      55: isub
      56: isub
      57: istore        6
      59: iload         6
      61: iflt          74
      64: aload_0
      65: iload         6
      67: iload         5
      69: iconst_0
      70: invokevirtual #14                 // Method com/google/zxing/common/BitArray.isRange:(IIZ)Z
      73: istore_1
      74: goto          14
      77: aload_2
      78: areturn

  public com.google.zxing.Result decodeRow(int, com.google.zxing.common.BitArray, java.util.Map<com.google.zxing.DecodeHintType, ?>) throws com.google.zxing.NotFoundException, com.google.zxing.ChecksumException, com.google.zxing.FormatException;
    Code:
       0: aload_0
       1: iload_1
       2: aload_2
       3: aload_2
       4: invokestatic  #15                 // Method findStartGuardPattern:(Lcom/google/zxing/common/BitArray;)[I
       7: aload_3
       8: invokevirtual #16                 // Method decodeRow:(ILcom/google/zxing/common/BitArray;[ILjava/util/Map;)Lcom/google/zxing/Result;
      11: areturn

  public com.google.zxing.Result decodeRow(int, com.google.zxing.common.BitArray, int[], java.util.Map<com.google.zxing.DecodeHintType, ?>) throws com.google.zxing.NotFoundException, com.google.zxing.ChecksumException, com.google.zxing.FormatException;
    Code:
       0: aload         4
       2: ifnonnull     9
       5: aconst_null
       6: goto          22
       9: aload         4
      11: getstatic     #17                 // Field com/google/zxing/DecodeHintType.NEED_RESULT_POINT_CALLBACK:Lcom/google/zxing/DecodeHintType;
      14: invokeinterface #18,  2           // InterfaceMethod java/util/Map.get:(Ljava/lang/Object;)Ljava/lang/Object;
      19: checkcast     #19                 // class com/google/zxing/ResultPointCallback
      22: astore        5
      24: iconst_0
      25: istore        6
      27: aload         5
      29: ifnull        58
      32: aload         5
      34: new           #20                 // class com/google/zxing/ResultPoint
      37: dup
      38: aload_3
      39: iconst_0
      40: iaload
      41: aload_3
      42: iconst_1
      43: iaload
      44: iadd
      45: i2f
      46: fconst_2
      47: fdiv
      48: iload_1
      49: i2f
      50: invokespecial #21                 // Method com/google/zxing/ResultPoint."<init>":(FF)V
      53: invokeinterface #22,  2           // InterfaceMethod com/google/zxing/ResultPointCallback.foundPossibleResultPoint:(Lcom/google/zxing/ResultPoint;)V
      58: aload_0
      59: getfield      #4                  // Field decodeRowStringBuffer:Ljava/lang/StringBuilder;
      62: astore        7
      64: aload         7
      66: iconst_0
      67: invokevirtual #23                 // Method java/lang/StringBuilder.setLength:(I)V
      70: aload_0
      71: aload_2
      72: aload_3
      73: aload         7
      75: invokevirtual #24                 // Method decodeMiddle:(Lcom/google/zxing/common/BitArray;[ILjava/lang/StringBuilder;)I
      78: istore        8
      80: aload         5
      82: ifnull        104
      85: aload         5
      87: new           #20                 // class com/google/zxing/ResultPoint
      90: dup
      91: iload         8
      93: i2f
      94: iload_1
      95: i2f
      96: invokespecial #21                 // Method com/google/zxing/ResultPoint."<init>":(FF)V
      99: invokeinterface #22,  2           // InterfaceMethod com/google/zxing/ResultPointCallback.foundPossibleResultPoint:(Lcom/google/zxing/ResultPoint;)V
     104: aload_0
     105: aload_2
     106: iload         8
     108: invokevirtual #25                 // Method decodeEnd:(Lcom/google/zxing/common/BitArray;I)[I
     111: astore        9
     113: aload         5
     115: ifnull        146
     118: aload         5
     120: new           #20                 // class com/google/zxing/ResultPoint
     123: dup
     124: aload         9
     126: iconst_0
     127: iaload
     128: aload         9
     130: iconst_1
     131: iaload
     132: iadd
     133: i2f
     134: fconst_2
     135: fdiv
     136: iload_1
     137: i2f
     138: invokespecial #21                 // Method com/google/zxing/ResultPoint."<init>":(FF)V
     141: invokeinterface #22,  2           // InterfaceMethod com/google/zxing/ResultPointCallback.foundPossibleResultPoint:(Lcom/google/zxing/ResultPoint;)V
     146: aload         9
     148: iconst_1
     149: iaload
     150: istore        10
     152: iload         10
     154: iload         10
     156: aload         9
     158: iconst_0
     159: iaload
     160: isub
     161: iadd
     162: istore        11
     164: iload         11
     166: aload_2
     167: invokevirtual #26                 // Method com/google/zxing/common/BitArray.getSize:()I
     170: if_icmpge     185
     173: aload_2
     174: iload         10
     176: iload         11
     178: iconst_0
     179: invokevirtual #14                 // Method com/google/zxing/common/BitArray.isRange:(IIZ)Z
     182: ifne          189
     185: invokestatic  #27                 // Method com/google/zxing/NotFoundException.getNotFoundInstance:()Lcom/google/zxing/NotFoundException;
     188: athrow
     189: aload         7
     191: invokevirtual #28                 // Method java/lang/StringBuilder.toString:()Ljava/lang/String;
     194: astore        12
     196: aload         12
     198: invokevirtual #29                 // Method java/lang/String.length:()I
     201: bipush        8
     203: if_icmpge     210
     206: invokestatic  #30                 // Method com/google/zxing/FormatException.getFormatInstance:()Lcom/google/zxing/FormatException;
     209: athrow
     210: aload_0
     211: aload         12
     213: invokevirtual #31                 // Method checkChecksum:(Ljava/lang/String;)Z
     216: ifne          223
     219: invokestatic  #32                 // Method com/google/zxing/ChecksumException.getChecksumInstance:()Lcom/google/zxing/ChecksumException;
     222: athrow
     223: aload_3
     224: iconst_1
     225: iaload
     226: aload_3
     227: iconst_0
     228: iaload
     229: iadd
     230: i2f
     231: fconst_2
     232: fdiv
     233: fstore        13
     235: aload         9
     237: iconst_1
     238: iaload
     239: aload         9
     241: iconst_0
     242: iaload
     243: iadd
     244: i2f
     245: fconst_2
     246: fdiv
     247: fstore        14
     249: aload_0
     250: invokevirtual #33                 // Method getBarcodeFormat:()Lcom/google/zxing/BarcodeFormat;
     253: astore        15
     255: new           #34                 // class com/google/zxing/Result
     258: dup
     259: aload         12
     261: aconst_null
     262: iconst_2
     263: anewarray     #20                 // class com/google/zxing/ResultPoint
     266: dup
     267: iconst_0
     268: new           #20                 // class com/google/zxing/ResultPoint
     271: dup
     272: fload         13
     274: iload_1
     275: i2f
     276: invokespecial #21                 // Method com/google/zxing/ResultPoint."<init>":(FF)V
     279: aastore
     280: dup
     281: iconst_1
     282: new           #20                 // class com/google/zxing/ResultPoint
     285: dup
     286: fload         14
     288: iload_1
     289: i2f
     290: invokespecial #21                 // Method com/google/zxing/ResultPoint."<init>":(FF)V
     293: aastore
     294: aload         15
     296: invokespecial #35                 // Method com/google/zxing/Result."<init>":(Ljava/lang/String;[B[Lcom/google/zxing/ResultPoint;Lcom/google/zxing/BarcodeFormat;)V
     299: astore        16
     301: iconst_0
     302: istore        17
     304: aload_0
     305: getfield      #7                  // Field extensionReader:Lcom/google/zxing/oned/UPCEANExtensionSupport;
     308: iload_1
     309: aload_2
     310: aload         9
     312: iconst_1
     313: iaload
     314: invokevirtual #36                 // Method com/google/zxing/oned/UPCEANExtensionSupport.decodeRow:(ILcom/google/zxing/common/BitArray;I)Lcom/google/zxing/Result;
     317: astore        18
     319: aload         16
     321: getstatic     #37                 // Field com/google/zxing/ResultMetadataType.UPC_EAN_EXTENSION:Lcom/google/zxing/ResultMetadataType;
     324: aload         18
     326: invokevirtual #38                 // Method com/google/zxing/Result.getText:()Ljava/lang/String;
     329: invokevirtual #39                 // Method com/google/zxing/Result.putMetadata:(Lcom/google/zxing/ResultMetadataType;Ljava/lang/Object;)V
     332: aload         16
     334: aload         18
     336: invokevirtual #40                 // Method com/google/zxing/Result.getResultMetadata:()Ljava/util/Map;
     339: invokevirtual #41                 // Method com/google/zxing/Result.putAllMetadata:(Ljava/util/Map;)V
     342: aload         16
     344: aload         18
     346: invokevirtual #42                 // Method com/google/zxing/Result.getResultPoints:()[Lcom/google/zxing/ResultPoint;
     349: invokevirtual #43                 // Method com/google/zxing/Result.addResultPoints:([Lcom/google/zxing/ResultPoint;)V
     352: aload         18
     354: invokevirtual #38                 // Method com/google/zxing/Result.getText:()Ljava/lang/String;
     357: invokevirtual #29                 // Method java/lang/String.length:()I
     360: istore        17
     362: goto          367
     365: astore        18
     367: aload         4
     369: ifnonnull     376
     372: aconst_null
     373: goto          392
     376: aload         4
     378: getstatic     #45                 // Field com/google/zxing/DecodeHintType.ALLOWED_EAN_EXTENSIONS:Lcom/google/zxing/DecodeHintType;
     381: invokeinterface #18,  2           // InterfaceMethod java/util/Map.get:(Ljava/lang/Object;)Ljava/lang/Object;
     386: checkcast     #46                 // class "[I"
     389: checkcast     #46                 // class "[I"
     392: astore        18
     394: aload         18
     396: ifnull        456
     399: iconst_0
     400: istore        19
     402: aload         18
     404: astore        20
     406: aload         20
     408: arraylength
     409: istore        21
     411: iconst_0
     412: istore        22
     414: iload         22
     416: iload         21
     418: if_icmpge     447
     421: aload         20
     423: iload         22
     425: iaload
     426: istore        23
     428: iload         17
     430: iload         23
     432: if_icmpne     441
     435: iconst_1
     436: istore        19
     438: goto          447
     441: iinc          22, 1
     444: goto          414
     447: iload         19
     449: ifne          456
     452: invokestatic  #27                 // Method com/google/zxing/NotFoundException.getNotFoundInstance:()Lcom/google/zxing/NotFoundException;
     455: athrow
     456: aload         15
     458: getstatic     #47                 // Field com/google/zxing/BarcodeFormat.EAN_13:Lcom/google/zxing/BarcodeFormat;
     461: if_acmpeq     472
     464: aload         15
     466: getstatic     #48                 // Field com/google/zxing/BarcodeFormat.UPC_A:Lcom/google/zxing/BarcodeFormat;
     469: if_acmpne     498
     472: aload_0
     473: getfield      #10                 // Field eanManSupport:Lcom/google/zxing/oned/EANManufacturerOrgSupport;
     476: aload         12
     478: invokevirtual #49                 // Method com/google/zxing/oned/EANManufacturerOrgSupport.lookupCountryIdentifier:(Ljava/lang/String;)Ljava/lang/String;
     481: astore        19
     483: aload         19
     485: ifnull        498
     488: aload         16
     490: getstatic     #50                 // Field com/google/zxing/ResultMetadataType.POSSIBLE_COUNTRY:Lcom/google/zxing/ResultMetadataType;
     493: aload         19
     495: invokevirtual #39                 // Method com/google/zxing/Result.putMetadata:(Lcom/google/zxing/ResultMetadataType;Ljava/lang/Object;)V
     498: aload         15
     500: getstatic     #51                 // Field com/google/zxing/BarcodeFormat.EAN_8:Lcom/google/zxing/BarcodeFormat;
     503: if_acmpne     509
     506: iconst_4
     507: istore        6
     509: aload         16
     511: getstatic     #52                 // Field com/google/zxing/ResultMetadataType.SYMBOLOGY_IDENTIFIER:Lcom/google/zxing/ResultMetadataType;
     514: new           #2                  // class java/lang/StringBuilder
     517: dup
     518: invokespecial #53                 // Method java/lang/StringBuilder."<init>":()V
     521: ldc           #54                 // String ]E
     523: invokevirtual #55                 // Method java/lang/StringBuilder.append:(Ljava/lang/String;)Ljava/lang/StringBuilder;
     526: iload         6
     528: invokevirtual #56                 // Method java/lang/StringBuilder.append:(I)Ljava/lang/StringBuilder;
     531: invokevirtual #28                 // Method java/lang/StringBuilder.toString:()Ljava/lang/String;
     534: invokevirtual #39                 // Method com/google/zxing/Result.putMetadata:(Lcom/google/zxing/ResultMetadataType;Ljava/lang/Object;)V
     537: aload         16
     539: areturn
    Exception table:
       from    to  target type
         304   362   365   Class com/google/zxing/ReaderException

  boolean checkChecksum(java.lang.String) throws com.google.zxing.FormatException;
    Code:
       0: aload_1
       1: invokestatic  #57                 // Method checkStandardUPCEANChecksum:(Ljava/lang/CharSequence;)Z
       4: ireturn

  static boolean checkStandardUPCEANChecksum(java.lang.CharSequence) throws com.google.zxing.FormatException;
    Code:
       0: aload_0
       1: invokeinterface #58,  1           // InterfaceMethod java/lang/CharSequence.length:()I
       6: istore_1
       7: iload_1
       8: ifne          13
      11: iconst_0
      12: ireturn
      13: aload_0
      14: iload_1
      15: iconst_1
      16: isub
      17: invokeinterface #59,  2           // InterfaceMethod java/lang/CharSequence.charAt:(I)C
      22: bipush        10
      24: invokestatic  #60                 // Method java/lang/Character.digit:(CI)I
      27: istore_2
      28: aload_0
      29: iconst_0
      30: iload_1
      31: iconst_1
      32: isub
      33: invokeinterface #61,  3           // InterfaceMethod java/lang/CharSequence.subSequence:(II)Ljava/lang/CharSequence;
      38: invokestatic  #62                 // Method getStandardUPCEANChecksum:(Ljava/lang/CharSequence;)I
      41: iload_2
      42: if_icmpne     49
      45: iconst_1
      46: goto          50
      49: iconst_0
      50: ireturn

  static int getStandardUPCEANChecksum(java.lang.CharSequence) throws com.google.zxing.FormatException;
    Code:
       0: aload_0
       1: invokeinterface #58,  1           // InterfaceMethod java/lang/CharSequence.length:()I
       6: istore_1
       7: iconst_0
       8: istore_2
       9: iload_1
      10: iconst_1
      11: isub
      12: istore_3
      13: iload_3
      14: iflt          56
      17: aload_0
      18: iload_3
      19: invokeinterface #59,  2           // InterfaceMethod java/lang/CharSequence.charAt:(I)C
      24: bipush        48
      26: isub
      27: istore        4
      29: iload         4
      31: iflt          41
      34: iload         4
      36: bipush        9
      38: if_icmple     45
      41: invokestatic  #30                 // Method com/google/zxing/FormatException.getFormatInstance:()Lcom/google/zxing/FormatException;
      44: athrow
      45: iload_2
      46: iload         4
      48: iadd
      49: istore_2
      50: iinc          3, -2
      53: goto          13
      56: iload_2
      57: iconst_3
      58: imul
      59: istore_2
      60: iload_1
      61: iconst_2
      62: isub
      63: istore_3
      64: iload_3
      65: iflt          107
      68: aload_0
      69: iload_3
      70: invokeinterface #59,  2           // InterfaceMethod java/lang/CharSequence.charAt:(I)C
      75: bipush        48
      77: isub
      78: istore        4
      80: iload         4
      82: iflt          92
      85: iload         4
      87: bipush        9
      89: if_icmple     96
      92: invokestatic  #30                 // Method com/google/zxing/FormatException.getFormatInstance:()Lcom/google/zxing/FormatException;
      95: athrow
      96: iload_2
      97: iload         4
      99: iadd
     100: istore_2
     101: iinc          3, -2
     104: goto          64
     107: sipush        1000
     110: iload_2
     111: isub
     112: bipush        10
     114: irem
     115: ireturn

  int[] decodeEnd(com.google.zxing.common.BitArray, int) throws com.google.zxing.NotFoundException;
    Code:
       0: aload_1
       1: iload_2
       2: iconst_0
       3: getstatic     #11                 // Field START_END_PATTERN:[I
       6: invokestatic  #63                 // Method findGuardPattern:(Lcom/google/zxing/common/BitArray;IZ[I)[I
       9: areturn

  static int[] findGuardPattern(com.google.zxing.common.BitArray, int, boolean, int[]) throws com.google.zxing.NotFoundException;
    Code:
       0: aload_0
       1: iload_1
       2: iload_2
       3: aload_3
       4: aload_3
       5: arraylength
       6: newarray       int
       8: invokestatic  #13                 // Method findGuardPattern:(Lcom/google/zxing/common/BitArray;IZ[I[I)[I
      11: areturn

  private static int[] findGuardPattern(com.google.zxing.common.BitArray, int, boolean, int[], int[]) throws com.google.zxing.NotFoundException;
    Code:
       0: aload_0
       1: invokevirtual #26                 // Method com/google/zxing/common/BitArray.getSize:()I
       4: istore        5
       6: iload_2
       7: ifeq          18
      10: aload_0
      11: iload_1
      12: invokevirtual #64                 // Method com/google/zxing/common/BitArray.getNextUnset:(I)I
      15: goto          23
      18: aload_0
      19: iload_1
      20: invokevirtual #65                 // Method com/google/zxing/common/BitArray.getNextSet:(I)I
      23: istore_1
      24: iconst_0
      25: istore        6
      27: iload_1
      28: istore        7
      30: aload_3
      31: arraylength
      32: istore        8
      34: iload_2
      35: istore        9
      37: iload_1
      38: istore        10
      40: iload         10
      42: iload         5
      44: if_icmpge     181
      47: aload_0
      48: iload         10
      50: invokevirtual #66                 // Method com/google/zxing/common/BitArray.get:(I)Z
      53: iload         9
      55: if_icmpeq     70
      58: aload         4
      60: iload         6
      62: dup2
      63: iaload
      64: iconst_1
      65: iadd
      66: iastore
      67: goto          175
      70: iload         6
      72: iload         8
      74: iconst_1
      75: isub
      76: if_icmpne     154
      79: aload         4
      81: aload_3
      82: ldc           #68                 // float 0.7f
      84: invokestatic  #69                 // Method patternMatchVariance:([I[IF)F
      87: ldc           #70                 // float 0.48f
      89: fcmpg
      90: ifge          107
      93: iconst_2
      94: newarray       int
      96: dup
      97: iconst_0
      98: iload         7
     100: iastore
     101: dup
     102: iconst_1
     103: iload         10
     105: iastore
     106: areturn
     107: iload         7
     109: aload         4
     111: iconst_0
     112: iaload
     113: aload         4
     115: iconst_1
     116: iaload
     117: iadd
     118: iadd
     119: istore        7
     121: aload         4
     123: iconst_2
     124: aload         4
     126: iconst_0
     127: iload         6
     129: iconst_1
     130: isub
     131: invokestatic  #71                 // Method java/lang/System.arraycopy:(Ljava/lang/Object;ILjava/lang/Object;II)V
     134: aload         4
     136: iload         6
     138: iconst_1
     139: isub
     140: iconst_0
     141: iastore
     142: aload         4
     144: iload         6
     146: iconst_0
     147: iastore
     148: iinc          6, -1
     151: goto          157
     154: iinc          6, 1
     157: aload         4
     159: iload         6
     161: iconst_1
     162: iastore
     163: iload         9
     165: ifne          172
     168: iconst_1
     169: goto          173
     172: iconst_0
     173: istore        9
     175: iinc          10, 1
     178: goto          40
     181: invokestatic  #27                 // Method com/google/zxing/NotFoundException.getNotFoundInstance:()Lcom/google/zxing/NotFoundException;
     184: athrow

  static int decodeDigit(com.google.zxing.common.BitArray, int[], int, int[][]) throws com.google.zxing.NotFoundException;
    Code:
       0: aload_0
       1: iload_2
       2: aload_1
       3: invokestatic  #72                 // Method recordPattern:(Lcom/google/zxing/common/BitArray;I[I)V
       6: ldc           #70                 // float 0.48f
       8: fstore        4
      10: iconst_m1
      11: istore        5
      13: aload_3
      14: arraylength
      15: istore        6
      17: iconst_0
      18: istore        7
      20: iload         7
      22: iload         6
      24: if_icmpge     65
      27: aload_3
      28: iload         7
      30: aaload
      31: astore        8
      33: aload_1
      34: aload         8
      36: ldc           #68                 // float 0.7f
      38: invokestatic  #69                 // Method patternMatchVariance:([I[IF)F
      41: fstore        9
      43: fload         9
      45: fload         4
      47: fcmpg
      48: ifge          59
      51: fload         9
      53: fstore        4
      55: iload         7
      57: istore        5
      59: iinc          7, 1
      62: goto          20
      65: iload         5
      67: iflt          73
      70: iload         5
      72: ireturn
      73: invokestatic  #27                 // Method com/google/zxing/NotFoundException.getNotFoundInstance:()Lcom/google/zxing/NotFoundException;
      76: athrow

  abstract com.google.zxing.BarcodeFormat getBarcodeFormat();

  protected abstract int decodeMiddle(com.google.zxing.common.BitArray, int[], java.lang.StringBuilder) throws com.google.zxing.NotFoundException;

  static {};
    Code:
       0: iconst_3
       1: newarray       int
       3: dup
       4: iconst_0
       5: iconst_1
       6: iastore
       7: dup
       8: iconst_1
       9: iconst_1
      10: iastore
      11: dup
      12: iconst_2
      13: iconst_1
      14: iastore
      15: putstatic     #11                 // Field START_END_PATTERN:[I
      18: iconst_5
      19: newarray       int
      21: dup
      22: iconst_0
      23: iconst_1
      24: iastore
      25: dup
      26: iconst_1
      27: iconst_1
      28: iastore
      29: dup
      30: iconst_2
      31: iconst_1
      32: iastore
      33: dup
      34: iconst_3
      35: iconst_1
      36: iastore
      37: dup
      38: iconst_4
      39: iconst_1
      40: iastore
      41: putstatic     #73                 // Field MIDDLE_PATTERN:[I
      44: bipush        6
      46: newarray       int
      48: dup
      49: iconst_0
      50: iconst_1
      51: iastore
      52: dup
      53: iconst_1
      54: iconst_1
      55: iastore
      56: dup
      57: iconst_2
      58: iconst_1
      59: iastore
      60: dup
      61: iconst_3
      62: iconst_1
      63: iastore
      64: dup
      65: iconst_4
      66: iconst_1
      67: iastore
      68: dup
      69: iconst_5
      70: iconst_1
      71: iastore
      72: putstatic     #74                 // Field END_PATTERN:[I
      75: bipush        10
      77: anewarray     #46                 // class "[I"
      80: dup
      81: iconst_0
      82: iconst_4
      83: newarray       int
      85: dup
      86: iconst_0
      87: iconst_3
      88: iastore
      89: dup
      90: iconst_1
      91: iconst_2
      92: iastore
      93: dup
      94: iconst_2
      95: iconst_1
      96: iastore
      97: dup
      98: iconst_3
      99: iconst_1
     100: iastore
     101: aastore
     102: dup
     103: iconst_1
     104: iconst_4
     105: newarray       int
     107: dup
     108: iconst_0
     109: iconst_2
     110: iastore
     111: dup
     112: iconst_1
     113: iconst_2
     114: iastore
     115: dup
     116: iconst_2
     117: iconst_2
     118: iastore
     119: dup
     120: iconst_3
     121: iconst_1
     122: iastore
     123: aastore
     124: dup
     125: iconst_2
     126: iconst_4
     127: newarray       int
     129: dup
     130: iconst_0
     131: iconst_2
     132: iastore
     133: dup
     134: iconst_1
     135: iconst_1
     136: iastore
     137: dup
     138: iconst_2
     139: iconst_2
     140: iastore
     141: dup
     142: iconst_3
     143: iconst_2
     144: iastore
     145: aastore
     146: dup
     147: iconst_3
     148: iconst_4
     149: newarray       int
     151: dup
     152: iconst_0
     153: iconst_1
     154: iastore
     155: dup
     156: iconst_1
     157: iconst_4
     158: iastore
     159: dup
     160: iconst_2
     161: iconst_1
     162: iastore
     163: dup
     164: iconst_3
     165: iconst_1
     166: iastore
     167: aastore
     168: dup
     169: iconst_4
     170: iconst_4
     171: newarray       int
     173: dup
     174: iconst_0
     175: iconst_1
     176: iastore
     177: dup
     178: iconst_1
     179: iconst_1
     180: iastore
     181: dup
     182: iconst_2
     183: iconst_3
     184: iastore
     185: dup
     186: iconst_3
     187: iconst_2
     188: iastore
     189: aastore
     190: dup
     191: iconst_5
     192: iconst_4
     193: newarray       int
     195: dup
     196: iconst_0
     197: iconst_1
     198: iastore
     199: dup
     200: iconst_1
     201: iconst_2
     202: iastore
     203: dup
     204: iconst_2
     205: iconst_3
     206: iastore
     207: dup
     208: iconst_3
     209: iconst_1
     210: iastore
     211: aastore
     212: dup
     213: bipush        6
     215: iconst_4
     216: newarray       int
     218: dup
     219: iconst_0
     220: iconst_1
     221: iastore
     222: dup
     223: iconst_1
     224: iconst_1
     225: iastore
     226: dup
     227: iconst_2
     228: iconst_1
     229: iastore
     230: dup
     231: iconst_3
     232: iconst_4
     233: iastore
     234: aastore
     235: dup
     236: bipush        7
     238: iconst_4
     239: newarray       int
     241: dup
     242: iconst_0
     243: iconst_1
     244: iastore
     245: dup
     246: iconst_1
     247: iconst_3
     248: iastore
     249: dup
     250: iconst_2
     251: iconst_1
     252: iastore
     253: dup
     254: iconst_3
     255: iconst_2
     256: iastore
     257: aastore
     258: dup
     259: bipush        8
     261: iconst_4
     262: newarray       int
     264: dup
     265: iconst_0
     266: iconst_1
     267: iastore
     268: dup
     269: iconst_1
     270: iconst_2
     271: iastore
     272: dup
     273: iconst_2
     274: iconst_1
     275: iastore
     276: dup
     277: iconst_3
     278: iconst_3
     279: iastore
     280: aastore
     281: dup
     282: bipush        9
     284: iconst_4
     285: newarray       int
     287: dup
     288: iconst_0
     289: iconst_3
     290: iastore
     291: dup
     292: iconst_1
     293: iconst_1
     294: iastore
     295: dup
     296: iconst_2
     297: iconst_1
     298: iastore
     299: dup
     300: iconst_3
     301: iconst_2
     302: iastore
     303: aastore
     304: putstatic     #75                 // Field L_PATTERNS:[[I
     307: bipush        20
     309: anewarray     #46                 // class "[I"
     312: putstatic     #76                 // Field L_AND_G_PATTERNS:[[I
     315: getstatic     #75                 // Field L_PATTERNS:[[I
     318: iconst_0
     319: getstatic     #76                 // Field L_AND_G_PATTERNS:[[I
     322: iconst_0
     323: bipush        10
     325: invokestatic  #71                 // Method java/lang/System.arraycopy:(Ljava/lang/Object;ILjava/lang/Object;II)V
     328: bipush        10
     330: istore_0
     331: iload_0
     332: bipush        20
     334: if_icmpge     388
     337: getstatic     #75                 // Field L_PATTERNS:[[I
     340: iload_0
     341: bipush        10
     343: isub
     344: aaload
     345: astore_1
     346: aload_1
     347: arraylength
     348: newarray       int
     350: astore_2
     351: iconst_0
     352: istore_3
     353: iload_3
     354: aload_1
     355: arraylength
     356: if_icmpge     376
     359: aload_2
     360: iload_3
     361: aload_1
     362: aload_1
     363: arraylength
     364: iload_3
     365: isub
     366: iconst_1
     367: isub
     368: iaload
     369: iastore
     370: iinc          3, 1
     373: goto          353
     376: getstatic     #76                 // Field L_AND_G_PATTERNS:[[I
     379: iload_0
     380: aload_2
     381: aastore
     382: iinc          0, 1
     385: goto          331
     388: return
}
