Compiled from "AdsObserver.java"
class org.apache.dubbo.registry.xds.util.AdsObserver$ResponseObserver implements io.grpc.stub.StreamObserver<io.envoyproxy.envoy.service.discovery.v3.DiscoveryResponse> {
  private org.apache.dubbo.registry.xds.util.AdsObserver adsObserver;

  public org.apache.dubbo.registry.xds.util.AdsObserver$ResponseObserver(org.apache.dubbo.registry.xds.util.AdsObserver);
    Code:
       0: aload_0
       1: invokespecial #2                  // Method java/lang/Object."<init>":()V
       4: aload_0
       5: aload_1
       6: putfield      #3                  // Field adsObserver:Lorg/apache/dubbo/registry/xds/util/AdsObserver;
       9: return

  public void onNext(io.envoyproxy.envoy.service.discovery.v3.DiscoveryResponse);
    Code:
       0: aload_0
       1: getfield      #3                  // Field adsObserver:Lorg/apache/dubbo/registry/xds/util/AdsObserver;
       4: invokestatic  #4                  // Method org/apache/dubbo/registry/xds/util/AdsObserver.access$000:(Lorg/apache/dubbo/registry/xds/util/AdsObserver;)Ljava/util/Map;
       7: aload_1
       8: invokevirtual #5                  // Method io/envoyproxy/envoy/service/discovery/v3/DiscoveryResponse.getTypeUrl:()Ljava/lang/String;
      11: invokeinterface #6,  2            // InterfaceMethod java/util/Map.get:(Ljava/lang/Object;)Ljava/lang/Object;
      16: checkcast     #7                  // class org/apache/dubbo/registry/xds/util/XdsListener
      19: astore_2
      20: aload_2
      21: aload_1
      22: invokeinterface #8,  2            // InterfaceMethod org/apache/dubbo/registry/xds/util/XdsListener.process:(Lio/envoyproxy/envoy/service/discovery/v3/DiscoveryResponse;)V
      27: aload_0
      28: getfield      #3                  // Field adsObserver:Lorg/apache/dubbo/registry/xds/util/AdsObserver;
      31: getfield      #9                  // Field org/apache/dubbo/registry/xds/util/AdsObserver.requestObserver:Lio/grpc/stub/StreamObserver;
      34: aload_0
      35: aload_1
      36: invokevirtual #10                 // Method buildAck:(Lio/envoyproxy/envoy/service/discovery/v3/DiscoveryResponse;)Lio/envoyproxy/envoy/service/discovery/v3/DiscoveryRequest;
      39: invokeinterface #11,  2           // InterfaceMethod io/grpc/stub/StreamObserver.onNext:(Ljava/lang/Object;)V
      44: return

  protected io.envoyproxy.envoy.service.discovery.v3.DiscoveryRequest buildAck(io.envoyproxy.envoy.service.discovery.v3.DiscoveryResponse);
    Code:
       0: invokestatic  #12                 // Method io/envoyproxy/envoy/service/discovery/v3/DiscoveryRequest.newBuilder:()Lio/envoyproxy/envoy/service/discovery/v3/DiscoveryRequest$Builder;
       3: aload_0
       4: getfield      #3                  // Field adsObserver:Lorg/apache/dubbo/registry/xds/util/AdsObserver;
       7: invokestatic  #13                 // Method org/apache/dubbo/registry/xds/util/AdsObserver.access$200:(Lorg/apache/dubbo/registry/xds/util/AdsObserver;)Lio/envoyproxy/envoy/config/core/v3/Node;
      10: invokevirtual #14                 // Method io/envoyproxy/envoy/service/discovery/v3/DiscoveryRequest$Builder.setNode:(Lio/envoyproxy/envoy/config/core/v3/Node;)Lio/envoyproxy/envoy/service/discovery/v3/DiscoveryRequest$Builder;
      13: aload_1
      14: invokevirtual #5                  // Method io/envoyproxy/envoy/service/discovery/v3/DiscoveryResponse.getTypeUrl:()Ljava/lang/String;
      17: invokevirtual #15                 // Method io/envoyproxy/envoy/service/discovery/v3/DiscoveryRequest$Builder.setTypeUrl:(Ljava/lang/String;)Lio/envoyproxy/envoy/service/discovery/v3/DiscoveryRequest$Builder;
      20: aload_1
      21: invokevirtual #16                 // Method io/envoyproxy/envoy/service/discovery/v3/DiscoveryResponse.getVersionInfo:()Ljava/lang/String;
      24: invokevirtual #17                 // Method io/envoyproxy/envoy/service/discovery/v3/DiscoveryRequest$Builder.setVersionInfo:(Ljava/lang/String;)Lio/envoyproxy/envoy/service/discovery/v3/DiscoveryRequest$Builder;
      27: aload_1
      28: invokevirtual #18                 // Method io/envoyproxy/envoy/service/discovery/v3/DiscoveryResponse.getNonce:()Ljava/lang/String;
      31: invokevirtual #19                 // Method io/envoyproxy/envoy/service/discovery/v3/DiscoveryRequest$Builder.setResponseNonce:(Ljava/lang/String;)Lio/envoyproxy/envoy/service/discovery/v3/DiscoveryRequest$Builder;
      34: aload_0
      35: getfield      #3                  // Field adsObserver:Lorg/apache/dubbo/registry/xds/util/AdsObserver;
      38: invokestatic  #20                 // Method org/apache/dubbo/registry/xds/util/AdsObserver.access$100:(Lorg/apache/dubbo/registry/xds/util/AdsObserver;)Ljava/util/Map;
      41: aload_1
      42: invokevirtual #5                  // Method io/envoyproxy/envoy/service/discovery/v3/DiscoveryResponse.getTypeUrl:()Ljava/lang/String;
      45: invokeinterface #6,  2            // InterfaceMethod java/util/Map.get:(Ljava/lang/Object;)Ljava/lang/Object;
      50: checkcast     #21                 // class io/envoyproxy/envoy/service/discovery/v3/DiscoveryRequest
      53: invokevirtual #22                 // Method io/envoyproxy/envoy/service/discovery/v3/DiscoveryRequest.getResourceNamesList:()Lcom/google/protobuf/ProtocolStringList;
      56: invokevirtual #23                 // Method io/envoyproxy/envoy/service/discovery/v3/DiscoveryRequest$Builder.addAllResourceNames:(Ljava/lang/Iterable;)Lio/envoyproxy/envoy/service/discovery/v3/DiscoveryRequest$Builder;
      59: invokevirtual #24                 // Method io/envoyproxy/envoy/service/discovery/v3/DiscoveryRequest$Builder.build:()Lio/envoyproxy/envoy/service/discovery/v3/DiscoveryRequest;
      62: areturn

  public void onError(java.lang.Throwable);
    Code:
       0: invokestatic  #25                 // Method org/apache/dubbo/registry/xds/util/AdsObserver.access$300:()Lorg/apache/dubbo/common/logger/ErrorTypeAwareLogger;
       3: ldc           #26                 // String 1-30
       5: ldc           #27                 // String
       7: ldc           #27                 // String
       9: ldc           #28                 // String xDS Client received error message! detail:
      11: aload_1
      12: invokeinterface #29,  6           // InterfaceMethod org/apache/dubbo/common/logger/ErrorTypeAwareLogger.error:(Ljava/lang/String;Ljava/lang/String;Ljava/lang/String;Ljava/lang/String;Ljava/lang/Throwable;)V
      17: aload_0
      18: getfield      #3                  // Field adsObserver:Lorg/apache/dubbo/registry/xds/util/AdsObserver;
      21: invokestatic  #30                 // Method org/apache/dubbo/registry/xds/util/AdsObserver.access$400:(Lorg/apache/dubbo/registry/xds/util/AdsObserver;)V
      24: return

  public void onCompleted();
    Code:
       0: invokestatic  #25                 // Method org/apache/dubbo/registry/xds/util/AdsObserver.access$300:()Lorg/apache/dubbo/common/logger/ErrorTypeAwareLogger;
       3: ldc           #31                 // String xDS Client completed
       5: invokeinterface #32,  2           // InterfaceMethod org/apache/dubbo/common/logger/ErrorTypeAwareLogger.info:(Ljava/lang/String;)V
      10: aload_0
      11: getfield      #3                  // Field adsObserver:Lorg/apache/dubbo/registry/xds/util/AdsObserver;
      14: invokestatic  #30                 // Method org/apache/dubbo/registry/xds/util/AdsObserver.access$400:(Lorg/apache/dubbo/registry/xds/util/AdsObserver;)V
      17: return

  public void onNext(java.lang.Object);
    Code:
       0: aload_0
       1: aload_1
       2: checkcast     #33                 // class io/envoyproxy/envoy/service/discovery/v3/DiscoveryResponse
       5: invokevirtual #34                 // Method onNext:(Lio/envoyproxy/envoy/service/discovery/v3/DiscoveryResponse;)V
       8: return
}
