Compiled from "NodeBuilder.java"
public class org.apache.dubbo.registry.xds.util.NodeBuilder {
  private static final java.lang.String SVC_CLUSTER_LOCAL;

  public org.apache.dubbo.registry.xds.util.NodeBuilder();
    Code:
       0: aload_0
       1: invokespecial #1                  // Method java/lang/Object."<init>":()V
       4: return

  public static io.envoyproxy.envoy.config.core.v3.Node build();
    Code:
       0: invokestatic  #2                  // Method org/apache/dubbo/registry/xds/istio/IstioEnv.getInstance:()Lorg/apache/dubbo/registry/xds/istio/IstioEnv;
       3: invokevirtual #3                  // Method org/apache/dubbo/registry/xds/istio/IstioEnv.getPodName:()Ljava/lang/String;
       6: astore_0
       7: invokestatic  #2                  // Method org/apache/dubbo/registry/xds/istio/IstioEnv.getInstance:()Lorg/apache/dubbo/registry/xds/istio/IstioEnv;
      10: invokevirtual #4                  // Method org/apache/dubbo/registry/xds/istio/IstioEnv.getWorkloadNameSpace:()Ljava/lang/String;
      13: astore_1
      14: invokestatic  #2                  // Method org/apache/dubbo/registry/xds/istio/IstioEnv.getInstance:()Lorg/apache/dubbo/registry/xds/istio/IstioEnv;
      17: invokevirtual #5                  // Method org/apache/dubbo/registry/xds/istio/IstioEnv.getIstioMetaClusterId:()Ljava/lang/String;
      20: astore_2
      21: invokestatic  #6                  // Method io/envoyproxy/envoy/config/core/v3/Node.newBuilder:()Lio/envoyproxy/envoy/config/core/v3/Node$Builder;
      24: new           #7                  // class java/lang/StringBuilder
      27: dup
      28: invokespecial #8                  // Method java/lang/StringBuilder."<init>":()V
      31: ldc           #9                  // String sidecar~
      33: invokevirtual #10                 // Method java/lang/StringBuilder.append:(Ljava/lang/String;)Ljava/lang/StringBuilder;
      36: invokestatic  #11                 // Method org/apache/dubbo/common/utils/NetUtils.getLocalHost:()Ljava/lang/String;
      39: invokevirtual #10                 // Method java/lang/StringBuilder.append:(Ljava/lang/String;)Ljava/lang/StringBuilder;
      42: ldc           #12                 // String ~
      44: invokevirtual #10                 // Method java/lang/StringBuilder.append:(Ljava/lang/String;)Ljava/lang/StringBuilder;
      47: aload_0
      48: invokevirtual #10                 // Method java/lang/StringBuilder.append:(Ljava/lang/String;)Ljava/lang/StringBuilder;
      51: ldc           #12                 // String ~
      53: invokevirtual #10                 // Method java/lang/StringBuilder.append:(Ljava/lang/String;)Ljava/lang/StringBuilder;
      56: aload_1
      57: invokevirtual #10                 // Method java/lang/StringBuilder.append:(Ljava/lang/String;)Ljava/lang/StringBuilder;
      60: ldc           #14                 // String .svc.cluster.local
      62: invokevirtual #10                 // Method java/lang/StringBuilder.append:(Ljava/lang/String;)Ljava/lang/StringBuilder;
      65: invokevirtual #15                 // Method java/lang/StringBuilder.toString:()Ljava/lang/String;
      68: invokevirtual #16                 // Method io/envoyproxy/envoy/config/core/v3/Node$Builder.setId:(Ljava/lang/String;)Lio/envoyproxy/envoy/config/core/v3/Node$Builder;
      71: aload_2
      72: invokevirtual #17                 // Method io/envoyproxy/envoy/config/core/v3/Node$Builder.setCluster:(Ljava/lang/String;)Lio/envoyproxy/envoy/config/core/v3/Node$Builder;
      75: invokevirtual #18                 // Method io/envoyproxy/envoy/config/core/v3/Node$Builder.build:()Lio/envoyproxy/envoy/config/core/v3/Node;
      78: areturn
}
