Compiled from "PilotExchanger.java"
public class org.apache.dubbo.registry.xds.util.PilotExchanger {
  protected final org.apache.dubbo.registry.xds.util.XdsChannel xdsChannel;

  protected final org.apache.dubbo.registry.xds.util.protocol.impl.LdsProtocol ldsProtocol;

  protected final org.apache.dubbo.registry.xds.util.protocol.impl.RdsProtocol rdsProtocol;

  protected final org.apache.dubbo.registry.xds.util.protocol.impl.EdsProtocol edsProtocol;

  protected java.util.Map<java.lang.String, org.apache.dubbo.registry.xds.util.protocol.message.ListenerResult> listenerResult;

  protected java.util.Map<java.lang.String, org.apache.dubbo.registry.xds.util.protocol.message.RouteResult> routeResult;

  private final java.util.concurrent.atomic.AtomicBoolean isRdsObserve;

  private final java.util.Set<java.lang.String> domainObserveRequest;

  private final java.util.Map<java.lang.String, java.util.Set<java.util.function.Consumer<java.util.Set<org.apache.dubbo.registry.xds.util.protocol.message.Endpoint>>>> domainObserveConsumer;

  private final java.util.Map<java.lang.String, java.util.function.Consumer<org.apache.dubbo.rpc.cluster.router.xds.RdsVirtualHostListener>> rdsObserveConsumer;

  private static org.apache.dubbo.registry.xds.util.PilotExchanger GLOBAL_PILOT_EXCHANGER;

  private final org.apache.dubbo.rpc.model.ApplicationModel applicationModel;

  protected org.apache.dubbo.registry.xds.util.PilotExchanger(org.apache.dubbo.common.URL);
    Code:
       0: aload_0
       1: invokespecial #1                  // Method java/lang/Object."<init>":()V
       4: aload_0
       5: new           #2                  // class java/util/concurrent/atomic/AtomicBoolean
       8: dup
       9: iconst_0
      10: invokespecial #3                  // Method java/util/concurrent/atomic/AtomicBoolean."<init>":(Z)V
      13: putfield      #4                  // Field isRdsObserve:Ljava/util/concurrent/atomic/AtomicBoolean;
      16: aload_0
      17: new           #5                  // class org/apache/dubbo/common/utils/ConcurrentHashSet
      20: dup
      21: invokespecial #6                  // Method org/apache/dubbo/common/utils/ConcurrentHashSet."<init>":()V
      24: putfield      #7                  // Field domainObserveRequest:Ljava/util/Set;
      27: aload_0
      28: new           #8                  // class java/util/concurrent/ConcurrentHashMap
      31: dup
      32: invokespecial #9                  // Method java/util/concurrent/ConcurrentHashMap."<init>":()V
      35: putfield      #10                 // Field domainObserveConsumer:Ljava/util/Map;
      38: aload_0
      39: new           #8                  // class java/util/concurrent/ConcurrentHashMap
      42: dup
      43: invokespecial #9                  // Method java/util/concurrent/ConcurrentHashMap."<init>":()V
      46: putfield      #11                 // Field rdsObserveConsumer:Ljava/util/Map;
      49: aload_0
      50: new           #12                 // class org/apache/dubbo/registry/xds/util/XdsChannel
      53: dup
      54: aload_1
      55: invokespecial #13                 // Method org/apache/dubbo/registry/xds/util/XdsChannel."<init>":(Lorg/apache/dubbo/common/URL;)V
      58: putfield      #14                 // Field xdsChannel:Lorg/apache/dubbo/registry/xds/util/XdsChannel;
      61: aload_1
      62: ldc           #15                 // String pollingTimeout
      64: bipush        10
      66: invokevirtual #16                 // Method org/apache/dubbo/common/URL.getParameter:(Ljava/lang/String;I)I
      69: istore_2
      70: aload_0
      71: aload_1
      72: invokevirtual #17                 // Method org/apache/dubbo/common/URL.getOrDefaultApplicationModel:()Lorg/apache/dubbo/rpc/model/ApplicationModel;
      75: putfield      #18                 // Field applicationModel:Lorg/apache/dubbo/rpc/model/ApplicationModel;
      78: new           #19                 // class org/apache/dubbo/registry/xds/util/AdsObserver
      81: dup
      82: aload_1
      83: invokestatic  #20                 // Method org/apache/dubbo/registry/xds/util/NodeBuilder.build:()Lio/envoyproxy/envoy/config/core/v3/Node;
      86: invokespecial #21                 // Method org/apache/dubbo/registry/xds/util/AdsObserver."<init>":(Lorg/apache/dubbo/common/URL;Lio/envoyproxy/envoy/config/core/v3/Node;)V
      89: astore_3
      90: aload_0
      91: new           #22                 // class org/apache/dubbo/registry/xds/util/protocol/impl/LdsProtocol
      94: dup
      95: aload_3
      96: invokestatic  #20                 // Method org/apache/dubbo/registry/xds/util/NodeBuilder.build:()Lio/envoyproxy/envoy/config/core/v3/Node;
      99: iload_2
     100: invokespecial #23                 // Method org/apache/dubbo/registry/xds/util/protocol/impl/LdsProtocol."<init>":(Lorg/apache/dubbo/registry/xds/util/AdsObserver;Lio/envoyproxy/envoy/config/core/v3/Node;I)V
     103: putfield      #24                 // Field ldsProtocol:Lorg/apache/dubbo/registry/xds/util/protocol/impl/LdsProtocol;
     106: aload_0
     107: new           #25                 // class org/apache/dubbo/registry/xds/util/protocol/impl/RdsProtocol
     110: dup
     111: aload_3
     112: invokestatic  #20                 // Method org/apache/dubbo/registry/xds/util/NodeBuilder.build:()Lio/envoyproxy/envoy/config/core/v3/Node;
     115: iload_2
     116: invokespecial #26                 // Method org/apache/dubbo/registry/xds/util/protocol/impl/RdsProtocol."<init>":(Lorg/apache/dubbo/registry/xds/util/AdsObserver;Lio/envoyproxy/envoy/config/core/v3/Node;I)V
     119: putfield      #27                 // Field rdsProtocol:Lorg/apache/dubbo/registry/xds/util/protocol/impl/RdsProtocol;
     122: aload_0
     123: new           #28                 // class org/apache/dubbo/registry/xds/util/protocol/impl/EdsProtocol
     126: dup
     127: aload_3
     128: invokestatic  #20                 // Method org/apache/dubbo/registry/xds/util/NodeBuilder.build:()Lio/envoyproxy/envoy/config/core/v3/Node;
     131: iload_2
     132: invokespecial #29                 // Method org/apache/dubbo/registry/xds/util/protocol/impl/EdsProtocol."<init>":(Lorg/apache/dubbo/registry/xds/util/AdsObserver;Lio/envoyproxy/envoy/config/core/v3/Node;I)V
     135: putfield      #30                 // Field edsProtocol:Lorg/apache/dubbo/registry/xds/util/protocol/impl/EdsProtocol;
     138: aload_0
     139: aload_0
     140: getfield      #24                 // Field ldsProtocol:Lorg/apache/dubbo/registry/xds/util/protocol/impl/LdsProtocol;
     143: invokevirtual #31                 // Method org/apache/dubbo/registry/xds/util/protocol/impl/LdsProtocol.getListeners:()Ljava/util/Map;
     146: putfield      #32                 // Field listenerResult:Ljava/util/Map;
     149: aload_0
     150: aload_0
     151: getfield      #27                 // Field rdsProtocol:Lorg/apache/dubbo/registry/xds/util/protocol/impl/RdsProtocol;
     154: aload_0
     155: getfield      #32                 // Field listenerResult:Ljava/util/Map;
     158: invokeinterface #33,  1           // InterfaceMethod java/util/Map.values:()Ljava/util/Collection;
     163: invokeinterface #34,  1           // InterfaceMethod java/util/Collection.iterator:()Ljava/util/Iterator;
     168: invokeinterface #35,  1           // InterfaceMethod java/util/Iterator.next:()Ljava/lang/Object;
     173: checkcast     #36                 // class org/apache/dubbo/registry/xds/util/protocol/message/ListenerResult
     176: invokevirtual #37                 // Method org/apache/dubbo/registry/xds/util/protocol/message/ListenerResult.getRouteConfigNames:()Ljava/util/Set;
     179: invokevirtual #38                 // Method org/apache/dubbo/registry/xds/util/protocol/impl/RdsProtocol.getResource:(Ljava/util/Set;)Ljava/util/Map;
     182: putfield      #39                 // Field routeResult:Ljava/util/Map;
     185: new           #40                 // class java/util/HashSet
     188: dup
     189: invokespecial #41                 // Method java/util/HashSet."<init>":()V
     192: astore        4
     194: aload         4
     196: ldc           #43                 // String emptyResourcesName
     198: invokeinterface #44,  2           // InterfaceMethod java/util/Set.add:(Ljava/lang/Object;)Z
     203: pop
     204: aload_0
     205: getfield      #32                 // Field listenerResult:Ljava/util/Map;
     208: invokeinterface #33,  1           // InterfaceMethod java/util/Map.values:()Ljava/util/Collection;
     213: invokeinterface #34,  1           // InterfaceMethod java/util/Collection.iterator:()Ljava/util/Iterator;
     218: invokeinterface #35,  1           // InterfaceMethod java/util/Iterator.next:()Ljava/lang/Object;
     223: checkcast     #36                 // class org/apache/dubbo/registry/xds/util/protocol/message/ListenerResult
     226: invokevirtual #37                 // Method org/apache/dubbo/registry/xds/util/protocol/message/ListenerResult.getRouteConfigNames:()Ljava/util/Set;
     229: invokestatic  #45                 // Method org/apache/dubbo/common/utils/CollectionUtils.isNotEmpty:(Ljava/util/Collection;)Z
     232: ifeq          247
     235: aload_0
     236: invokespecial #46                 // Method createRouteObserve:()V
     239: aload_0
     240: getfield      #4                  // Field isRdsObserve:Ljava/util/concurrent/atomic/AtomicBoolean;
     243: iconst_1
     244: invokevirtual #47                 // Method java/util/concurrent/atomic/AtomicBoolean.set:(Z)V
     247: aload_0
     248: getfield      #24                 // Field ldsProtocol:Lorg/apache/dubbo/registry/xds/util/protocol/impl/LdsProtocol;
     251: aload         4
     253: aload_0
     254: invokedynamic #48,  0             // InvokeDynamic #0:accept:(Lorg/apache/dubbo/registry/xds/util/PilotExchanger;)Ljava/util/function/Consumer;
     259: iconst_0
     260: invokevirtual #49                 // Method org/apache/dubbo/registry/xds/util/protocol/impl/LdsProtocol.observeResource:(Ljava/util/Set;Ljava/util/function/Consumer;Z)V
     263: return

  private void createRouteObserve();
    Code:
       0: aload_0
       1: getfield      #27                 // Field rdsProtocol:Lorg/apache/dubbo/registry/xds/util/protocol/impl/RdsProtocol;
       4: aload_0
       5: getfield      #32                 // Field listenerResult:Ljava/util/Map;
       8: invokeinterface #33,  1           // InterfaceMethod java/util/Map.values:()Ljava/util/Collection;
      13: invokeinterface #34,  1           // InterfaceMethod java/util/Collection.iterator:()Ljava/util/Iterator;
      18: invokeinterface #35,  1           // InterfaceMethod java/util/Iterator.next:()Ljava/lang/Object;
      23: checkcast     #36                 // class org/apache/dubbo/registry/xds/util/protocol/message/ListenerResult
      26: invokevirtual #37                 // Method org/apache/dubbo/registry/xds/util/protocol/message/ListenerResult.getRouteConfigNames:()Ljava/util/Set;
      29: aload_0
      30: invokedynamic #50,  0             // InvokeDynamic #1:accept:(Lorg/apache/dubbo/registry/xds/util/PilotExchanger;)Ljava/util/function/Consumer;
      35: iconst_0
      36: invokevirtual #51                 // Method org/apache/dubbo/registry/xds/util/protocol/impl/RdsProtocol.observeResource:(Ljava/util/Set;Ljava/util/function/Consumer;Z)V
      39: return

  public static org.apache.dubbo.registry.xds.util.PilotExchanger initialize(org.apache.dubbo.common.URL);
    Code:
       0: ldc           #52                 // class org/apache/dubbo/registry/xds/util/PilotExchanger
       2: dup
       3: astore_1
       4: monitorenter
       5: getstatic     #53                 // Field GLOBAL_PILOT_EXCHANGER:Lorg/apache/dubbo/registry/xds/util/PilotExchanger;
       8: ifnull        17
      11: getstatic     #53                 // Field GLOBAL_PILOT_EXCHANGER:Lorg/apache/dubbo/registry/xds/util/PilotExchanger;
      14: aload_1
      15: monitorexit
      16: areturn
      17: new           #52                 // class org/apache/dubbo/registry/xds/util/PilotExchanger
      20: dup
      21: aload_0
      22: invokespecial #54                 // Method "<init>":(Lorg/apache/dubbo/common/URL;)V
      25: dup
      26: putstatic     #53                 // Field GLOBAL_PILOT_EXCHANGER:Lorg/apache/dubbo/registry/xds/util/PilotExchanger;
      29: aload_1
      30: monitorexit
      31: areturn
      32: astore_2
      33: aload_1
      34: monitorexit
      35: aload_2
      36: athrow
    Exception table:
       from    to  target type
           5    16    32   any
          17    31    32   any
          32    35    32   any

  public static org.apache.dubbo.registry.xds.util.PilotExchanger getInstance();
    Code:
       0: ldc           #52                 // class org/apache/dubbo/registry/xds/util/PilotExchanger
       2: dup
       3: astore_0
       4: monitorenter
       5: getstatic     #53                 // Field GLOBAL_PILOT_EXCHANGER:Lorg/apache/dubbo/registry/xds/util/PilotExchanger;
       8: aload_0
       9: monitorexit
      10: areturn
      11: astore_1
      12: aload_0
      13: monitorexit
      14: aload_1
      15: athrow
    Exception table:
       from    to  target type
           5    10    11   any
          11    14    11   any

  public static boolean isEnabled();
    Code:
       0: getstatic     #53                 // Field GLOBAL_PILOT_EXCHANGER:Lorg/apache/dubbo/registry/xds/util/PilotExchanger;
       3: ifnull        10
       6: iconst_1
       7: goto          11
      10: iconst_0
      11: ireturn

  public void destroy();
    Code:
       0: aload_0
       1: getfield      #14                 // Field xdsChannel:Lorg/apache/dubbo/registry/xds/util/XdsChannel;
       4: invokevirtual #55                 // Method org/apache/dubbo/registry/xds/util/XdsChannel.destroy:()V
       7: return

  public java.util.Set<java.lang.String> getServices();
    Code:
       0: new           #40                 // class java/util/HashSet
       3: dup
       4: invokespecial #41                 // Method java/util/HashSet."<init>":()V
       7: astore_1
       8: aload_0
       9: getfield      #39                 // Field routeResult:Ljava/util/Map;
      12: invokeinterface #56,  1           // InterfaceMethod java/util/Map.entrySet:()Ljava/util/Set;
      17: invokeinterface #57,  1           // InterfaceMethod java/util/Set.iterator:()Ljava/util/Iterator;
      22: astore_2
      23: aload_2
      24: invokeinterface #58,  1           // InterfaceMethod java/util/Iterator.hasNext:()Z
      29: ifeq          64
      32: aload_2
      33: invokeinterface #35,  1           // InterfaceMethod java/util/Iterator.next:()Ljava/lang/Object;
      38: checkcast     #59                 // class java/util/Map$Entry
      41: astore_3
      42: aload_1
      43: aload_3
      44: invokeinterface #60,  1           // InterfaceMethod java/util/Map$Entry.getValue:()Ljava/lang/Object;
      49: checkcast     #61                 // class org/apache/dubbo/registry/xds/util/protocol/message/RouteResult
      52: invokevirtual #62                 // Method org/apache/dubbo/registry/xds/util/protocol/message/RouteResult.getDomains:()Ljava/util/Set;
      55: invokeinterface #63,  2           // InterfaceMethod java/util/Set.addAll:(Ljava/util/Collection;)Z
      60: pop
      61: goto          23
      64: aload_1
      65: areturn

  public java.util.Set<org.apache.dubbo.registry.xds.util.protocol.message.Endpoint> getEndpoints(java.lang.String);
    Code:
       0: new           #40                 // class java/util/HashSet
       3: dup
       4: invokespecial #41                 // Method java/util/HashSet."<init>":()V
       7: astore_2
       8: aload_0
       9: getfield      #39                 // Field routeResult:Ljava/util/Map;
      12: invokeinterface #56,  1           // InterfaceMethod java/util/Map.entrySet:()Ljava/util/Set;
      17: invokeinterface #57,  1           // InterfaceMethod java/util/Set.iterator:()Ljava/util/Iterator;
      22: astore_3
      23: aload_3
      24: invokeinterface #58,  1           // InterfaceMethod java/util/Iterator.hasNext:()Z
      29: ifeq          101
      32: aload_3
      33: invokeinterface #35,  1           // InterfaceMethod java/util/Iterator.next:()Ljava/lang/Object;
      38: checkcast     #59                 // class java/util/Map$Entry
      41: astore        4
      43: aload         4
      45: invokeinterface #60,  1           // InterfaceMethod java/util/Map$Entry.getValue:()Ljava/lang/Object;
      50: checkcast     #61                 // class org/apache/dubbo/registry/xds/util/protocol/message/RouteResult
      53: aload_1
      54: invokevirtual #64                 // Method org/apache/dubbo/registry/xds/util/protocol/message/RouteResult.searchDomain:(Ljava/lang/String;)Ljava/util/Set;
      57: astore        5
      59: aload         5
      61: invokestatic  #45                 // Method org/apache/dubbo/common/utils/CollectionUtils.isNotEmpty:(Ljava/util/Collection;)Z
      64: ifeq          94
      67: aload_0
      68: getfield      #30                 // Field edsProtocol:Lorg/apache/dubbo/registry/xds/util/protocol/impl/EdsProtocol;
      71: aload         5
      73: invokevirtual #65                 // Method org/apache/dubbo/registry/xds/util/protocol/impl/EdsProtocol.getResource:(Ljava/util/Set;)Ljava/util/Map;
      76: astore        6
      78: aload         6
      80: aload_2
      81: invokedynamic #66,  0             // InvokeDynamic #2:accept:(Ljava/util/Set;)Ljava/util/function/BiConsumer;
      86: invokeinterface #67,  2           // InterfaceMethod java/util/Map.forEach:(Ljava/util/function/BiConsumer;)V
      91: goto          98
      94: invokestatic  #68                 // Method java/util/Collections.emptySet:()Ljava/util/Set;
      97: areturn
      98: goto          23
     101: aload_2
     102: areturn

  public void observeEndpoints(java.lang.String, java.util.function.Consumer<java.util.Set<org.apache.dubbo.registry.xds.util.protocol.message.Endpoint>>);
    Code:
       0: aload_0
       1: getfield      #10                 // Field domainObserveConsumer:Ljava/util/Map;
       4: aload_1
       5: aload_2
       6: invokedynamic #69,  0             // InvokeDynamic #3:apply:(Ljava/util/function/Consumer;)Ljava/util/function/BiFunction;
      11: invokeinterface #70,  3           // InterfaceMethod java/util/Map.compute:(Ljava/lang/Object;Ljava/util/function/BiFunction;)Ljava/lang/Object;
      16: pop
      17: aload_0
      18: getfield      #7                  // Field domainObserveRequest:Ljava/util/Set;
      21: aload_1
      22: invokeinterface #71,  2           // InterfaceMethod java/util/Set.contains:(Ljava/lang/Object;)Z
      27: ifne          35
      30: aload_0
      31: aload_1
      32: invokespecial #72                 // Method doObserveEndpoints:(Ljava/lang/String;)V
      35: return

  private void doObserveEndpoints(java.lang.String);
    Code:
       0: aload_0
       1: getfield      #39                 // Field routeResult:Ljava/util/Map;
       4: invokeinterface #56,  1           // InterfaceMethod java/util/Map.entrySet:()Ljava/util/Set;
       9: invokeinterface #57,  1           // InterfaceMethod java/util/Set.iterator:()Ljava/util/Iterator;
      14: astore_2
      15: aload_2
      16: invokeinterface #58,  1           // InterfaceMethod java/util/Iterator.hasNext:()Z
      21: ifeq          88
      24: aload_2
      25: invokeinterface #35,  1           // InterfaceMethod java/util/Iterator.next:()Ljava/lang/Object;
      30: checkcast     #59                 // class java/util/Map$Entry
      33: astore_3
      34: aload_3
      35: invokeinterface #60,  1           // InterfaceMethod java/util/Map$Entry.getValue:()Ljava/lang/Object;
      40: checkcast     #61                 // class org/apache/dubbo/registry/xds/util/protocol/message/RouteResult
      43: aload_1
      44: invokevirtual #64                 // Method org/apache/dubbo/registry/xds/util/protocol/message/RouteResult.searchDomain:(Ljava/lang/String;)Ljava/util/Set;
      47: astore        4
      49: aload         4
      51: invokestatic  #45                 // Method org/apache/dubbo/common/utils/CollectionUtils.isNotEmpty:(Ljava/util/Collection;)Z
      54: ifeq          85
      57: aload_0
      58: getfield      #30                 // Field edsProtocol:Lorg/apache/dubbo/registry/xds/util/protocol/impl/EdsProtocol;
      61: aload         4
      63: aload_0
      64: aload_1
      65: invokedynamic #73,  0             // InvokeDynamic #4:accept:(Lorg/apache/dubbo/registry/xds/util/PilotExchanger;Ljava/lang/String;)Ljava/util/function/Consumer;
      70: iconst_0
      71: invokevirtual #74                 // Method org/apache/dubbo/registry/xds/util/protocol/impl/EdsProtocol.observeResource:(Ljava/util/Set;Ljava/util/function/Consumer;Z)V
      74: aload_0
      75: getfield      #7                  // Field domainObserveRequest:Ljava/util/Set;
      78: aload_1
      79: invokeinterface #44,  2           // InterfaceMethod java/util/Set.add:(Ljava/lang/Object;)Z
      84: pop
      85: goto          15
      88: return

  public void unObserveEndpoints(java.lang.String, java.util.function.Consumer<java.util.Set<org.apache.dubbo.registry.xds.util.protocol.message.Endpoint>>);
    Code:
       0: aload_0
       1: getfield      #10                 // Field domainObserveConsumer:Ljava/util/Map;
       4: aload_1
       5: invokeinterface #75,  2           // InterfaceMethod java/util/Map.get:(Ljava/lang/Object;)Ljava/lang/Object;
      10: checkcast     #76                 // class java/util/Set
      13: aload_2
      14: invokeinterface #77,  2           // InterfaceMethod java/util/Set.remove:(Ljava/lang/Object;)Z
      19: pop
      20: aload_0
      21: getfield      #7                  // Field domainObserveRequest:Ljava/util/Set;
      24: aload_1
      25: invokeinterface #77,  2           // InterfaceMethod java/util/Set.remove:(Ljava/lang/Object;)Z
      30: pop
      31: return

  public void observeEds(java.util.Set<java.lang.String>, java.util.function.Consumer<java.util.Map<java.lang.String, org.apache.dubbo.registry.xds.util.protocol.message.EndpointResult>>);
    Code:
       0: aload_0
       1: getfield      #30                 // Field edsProtocol:Lorg/apache/dubbo/registry/xds/util/protocol/impl/EdsProtocol;
       4: aload_1
       5: aload_2
       6: iconst_0
       7: invokevirtual #74                 // Method org/apache/dubbo/registry/xds/util/protocol/impl/EdsProtocol.observeResource:(Ljava/util/Set;Ljava/util/function/Consumer;Z)V
      10: return

  public void unObserveEds(java.util.Set<java.lang.String>, java.util.function.Consumer<java.util.Map<java.lang.String, org.apache.dubbo.registry.xds.util.protocol.message.EndpointResult>>);
    Code:
       0: aload_0
       1: getfield      #30                 // Field edsProtocol:Lorg/apache/dubbo/registry/xds/util/protocol/impl/EdsProtocol;
       4: aload_1
       5: aload_2
       6: invokevirtual #78                 // Method org/apache/dubbo/registry/xds/util/protocol/impl/EdsProtocol.unobserveResource:(Ljava/util/Set;Ljava/util/function/Consumer;)V
       9: return

  public void observeRds(java.util.Set<java.lang.String>, java.util.function.Consumer<java.util.Map<java.lang.String, org.apache.dubbo.registry.xds.util.protocol.message.RouteResult>>);
    Code:
       0: aload_0
       1: getfield      #27                 // Field rdsProtocol:Lorg/apache/dubbo/registry/xds/util/protocol/impl/RdsProtocol;
       4: aload_1
       5: aload_2
       6: iconst_0
       7: invokevirtual #51                 // Method org/apache/dubbo/registry/xds/util/protocol/impl/RdsProtocol.observeResource:(Ljava/util/Set;Ljava/util/function/Consumer;Z)V
      10: return

  public void unObserveRds(java.util.Set<java.lang.String>, java.util.function.Consumer<java.util.Map<java.lang.String, org.apache.dubbo.registry.xds.util.protocol.message.RouteResult>>);
    Code:
       0: aload_0
       1: getfield      #27                 // Field rdsProtocol:Lorg/apache/dubbo/registry/xds/util/protocol/impl/RdsProtocol;
       4: aload_1
       5: aload_2
       6: invokevirtual #79                 // Method org/apache/dubbo/registry/xds/util/protocol/impl/RdsProtocol.unobserveResource:(Ljava/util/Set;Ljava/util/function/Consumer;)V
       9: return

  public void observeLds(java.util.function.Consumer<java.util.Map<java.lang.String, org.apache.dubbo.registry.xds.util.protocol.message.ListenerResult>>);
    Code:
       0: aload_0
       1: getfield      #24                 // Field ldsProtocol:Lorg/apache/dubbo/registry/xds/util/protocol/impl/LdsProtocol;
       4: ldc           #43                 // String emptyResourcesName
       6: invokestatic  #80                 // Method java/util/Collections.singleton:(Ljava/lang/Object;)Ljava/util/Set;
       9: aload_1
      10: iconst_0
      11: invokevirtual #49                 // Method org/apache/dubbo/registry/xds/util/protocol/impl/LdsProtocol.observeResource:(Ljava/util/Set;Ljava/util/function/Consumer;Z)V
      14: return

  public void unObserveLds(java.util.function.Consumer<java.util.Map<java.lang.String, org.apache.dubbo.registry.xds.util.protocol.message.ListenerResult>>);
    Code:
       0: aload_0
       1: getfield      #24                 // Field ldsProtocol:Lorg/apache/dubbo/registry/xds/util/protocol/impl/LdsProtocol;
       4: ldc           #43                 // String emptyResourcesName
       6: invokestatic  #80                 // Method java/util/Collections.singleton:(Ljava/lang/Object;)Ljava/util/Set;
       9: aload_1
      10: invokevirtual #81                 // Method org/apache/dubbo/registry/xds/util/protocol/impl/LdsProtocol.unobserveResource:(Ljava/util/Set;Ljava/util/function/Consumer;)V
      13: return

  private void lambda$doObserveEndpoints$7(java.lang.String, java.util.Map);
    Code:
       0: aload_2
       1: invokeinterface #33,  1           // InterfaceMethod java/util/Map.values:()Ljava/util/Collection;
       6: invokeinterface #82,  1           // InterfaceMethod java/util/Collection.stream:()Ljava/util/stream/Stream;
      11: invokedynamic #83,  0             // InvokeDynamic #5:apply:()Ljava/util/function/Function;
      16: invokeinterface #84,  2           // InterfaceMethod java/util/stream/Stream.map:(Ljava/util/function/Function;)Ljava/util/stream/Stream;
      21: invokedynamic #85,  0             // InvokeDynamic #6:apply:()Ljava/util/function/Function;
      26: invokeinterface #86,  2           // InterfaceMethod java/util/stream/Stream.flatMap:(Ljava/util/function/Function;)Ljava/util/stream/Stream;
      31: invokestatic  #87                 // Method java/util/stream/Collectors.toSet:()Ljava/util/stream/Collector;
      34: invokeinterface #88,  2           // InterfaceMethod java/util/stream/Stream.collect:(Ljava/util/stream/Collector;)Ljava/lang/Object;
      39: checkcast     #76                 // class java/util/Set
      42: astore_3
      43: aload_0
      44: getfield      #10                 // Field domainObserveConsumer:Ljava/util/Map;
      47: aload_1
      48: invokeinterface #75,  2           // InterfaceMethod java/util/Map.get:(Ljava/lang/Object;)Ljava/lang/Object;
      53: checkcast     #76                 // class java/util/Set
      56: invokeinterface #57,  1           // InterfaceMethod java/util/Set.iterator:()Ljava/util/Iterator;
      61: astore        4
      63: aload         4
      65: invokeinterface #58,  1           // InterfaceMethod java/util/Iterator.hasNext:()Z
      70: ifeq          96
      73: aload         4
      75: invokeinterface #35,  1           // InterfaceMethod java/util/Iterator.next:()Ljava/lang/Object;
      80: checkcast     #89                 // class java/util/function/Consumer
      83: astore        5
      85: aload         5
      87: aload_3
      88: invokeinterface #90,  2           // InterfaceMethod java/util/function/Consumer.accept:(Ljava/lang/Object;)V
      93: goto          63
      96: return

  private static java.util.Set lambda$observeEndpoints$6(java.util.function.Consumer, java.lang.String, java.util.Set);
    Code:
       0: aload_2
       1: ifnonnull     12
       4: new           #5                  // class org/apache/dubbo/common/utils/ConcurrentHashSet
       7: dup
       8: invokespecial #6                  // Method org/apache/dubbo/common/utils/ConcurrentHashSet."<init>":()V
      11: astore_2
      12: aload_2
      13: aload_0
      14: invokeinterface #44,  2           // InterfaceMethod java/util/Set.add:(Ljava/lang/Object;)Z
      19: pop
      20: aload_2
      21: areturn

  private static void lambda$getEndpoints$5(java.util.Set, java.lang.String, org.apache.dubbo.registry.xds.util.protocol.message.EndpointResult);
    Code:
       0: aload_0
       1: aload_2
       2: invokevirtual #91                 // Method org/apache/dubbo/registry/xds/util/protocol/message/EndpointResult.getEndpoints:()Ljava/util/Set;
       5: invokeinterface #63,  2           // InterfaceMethod java/util/Set.addAll:(Ljava/util/Collection;)Z
      10: pop
      11: return

  private void lambda$createRouteObserve$4(java.util.Map);
    Code:
       0: new           #92                 // class java/util/LinkedList
       3: dup
       4: invokespecial #93                 // Method java/util/LinkedList."<init>":()V
       7: astore_2
       8: aload_0
       9: getfield      #10                 // Field domainObserveConsumer:Ljava/util/Map;
      12: aload_0
      13: aload_1
      14: aload_2
      15: invokedynamic #94,  0             // InvokeDynamic #7:accept:(Lorg/apache/dubbo/registry/xds/util/PilotExchanger;Ljava/util/Map;Ljava/util/List;)Ljava/util/function/BiConsumer;
      20: invokeinterface #67,  2           // InterfaceMethod java/util/Map.forEach:(Ljava/util/function/BiConsumer;)V
      25: aload_0
      26: aload_1
      27: putfield      #39                 // Field routeResult:Ljava/util/Map;
      30: aload_0
      31: getfield      #18                 // Field applicationModel:Lorg/apache/dubbo/rpc/model/ApplicationModel;
      34: invokevirtual #95                 // Method org/apache/dubbo/rpc/model/ApplicationModel.getFrameworkModel:()Lorg/apache/dubbo/rpc/model/FrameworkModel;
      37: invokevirtual #96                 // Method org/apache/dubbo/rpc/model/FrameworkModel.getBeanFactory:()Lorg/apache/dubbo/common/beans/factory/ScopeBeanFactory;
      40: ldc           #97                 // class org/apache/dubbo/common/threadpool/manager/FrameworkExecutorRepository
      42: invokevirtual #98                 // Method org/apache/dubbo/common/beans/factory/ScopeBeanFactory.getBean:(Ljava/lang/Class;)Ljava/lang/Object;
      45: checkcast     #97                 // class org/apache/dubbo/common/threadpool/manager/FrameworkExecutorRepository
      48: invokevirtual #99                 // Method org/apache/dubbo/common/threadpool/manager/FrameworkExecutorRepository.getSharedExecutor:()Ljava/util/concurrent/ExecutorService;
      51: astore_3
      52: aload_3
      53: aload_0
      54: aload_2
      55: invokedynamic #100,  0            // InvokeDynamic #8:run:(Lorg/apache/dubbo/registry/xds/util/PilotExchanger;Ljava/util/List;)Ljava/lang/Runnable;
      60: invokeinterface #101,  2          // InterfaceMethod java/util/concurrent/ExecutorService.submit:(Ljava/lang/Runnable;)Ljava/util/concurrent/Future;
      65: pop
      66: return

  private void lambda$null$3(java.util.List);
    Code:
       0: aload_1
       1: aload_0
       2: invokedynamic #102,  0            // InvokeDynamic #9:accept:(Lorg/apache/dubbo/registry/xds/util/PilotExchanger;)Ljava/util/function/Consumer;
       7: invokeinterface #103,  2          // InterfaceMethod java/util/List.forEach:(Ljava/util/function/Consumer;)V
      12: return

  private void lambda$null$2(java.util.Map, java.util.List, java.lang.String, java.util.Set);
    Code:
       0: aload_1
       1: invokeinterface #33,  1           // InterfaceMethod java/util/Map.values:()Ljava/util/Collection;
       6: aload_0
       7: aload_3
       8: aload_2
       9: invokedynamic #104,  0            // InvokeDynamic #10:accept:(Lorg/apache/dubbo/registry/xds/util/PilotExchanger;Ljava/lang/String;Ljava/util/List;)Ljava/util/function/Consumer;
      14: invokeinterface #105,  2          // InterfaceMethod java/util/Collection.forEach:(Ljava/util/function/Consumer;)V
      19: return

  private void lambda$null$1(java.lang.String, java.util.List, org.apache.dubbo.registry.xds.util.protocol.message.RouteResult);
    Code:
       0: aload_3
       1: aload_1
       2: invokevirtual #64                 // Method org/apache/dubbo/registry/xds/util/protocol/message/RouteResult.searchDomain:(Ljava/lang/String;)Ljava/util/Set;
       5: astore        4
       7: aload_0
       8: getfield      #39                 // Field routeResult:Ljava/util/Map;
      11: invokeinterface #56,  1           // InterfaceMethod java/util/Map.entrySet:()Ljava/util/Set;
      16: invokeinterface #57,  1           // InterfaceMethod java/util/Set.iterator:()Ljava/util/Iterator;
      21: astore        5
      23: aload         5
      25: invokeinterface #58,  1           // InterfaceMethod java/util/Iterator.hasNext:()Z
      30: ifeq          80
      33: aload         5
      35: invokeinterface #35,  1           // InterfaceMethod java/util/Iterator.next:()Ljava/lang/Object;
      40: checkcast     #59                 // class java/util/Map$Entry
      43: astore        6
      45: aload         6
      47: invokeinterface #60,  1           // InterfaceMethod java/util/Map$Entry.getValue:()Ljava/lang/Object;
      52: checkcast     #61                 // class org/apache/dubbo/registry/xds/util/protocol/message/RouteResult
      55: aload_1
      56: invokevirtual #64                 // Method org/apache/dubbo/registry/xds/util/protocol/message/RouteResult.searchDomain:(Ljava/lang/String;)Ljava/util/Set;
      59: aload         4
      61: invokeinterface #106,  2          // InterfaceMethod java/util/Set.equals:(Ljava/lang/Object;)Z
      66: ifne          77
      69: aload_2
      70: aload_1
      71: invokeinterface #107,  2          // InterfaceMethod java/util/List.add:(Ljava/lang/Object;)Z
      76: pop
      77: goto          23
      80: return

  private void lambda$new$0(java.util.Map);
    Code:
       0: aload_1
       1: aload_0
       2: getfield      #32                 // Field listenerResult:Ljava/util/Map;
       5: invokeinterface #108,  2          // InterfaceMethod java/util/Map.equals:(Ljava/lang/Object;)Z
      10: ifne          32
      13: aload_0
      14: aload_1
      15: putfield      #32                 // Field listenerResult:Ljava/util/Map;
      18: aload_0
      19: getfield      #4                  // Field isRdsObserve:Ljava/util/concurrent/atomic/AtomicBoolean;
      22: invokevirtual #109                // Method java/util/concurrent/atomic/AtomicBoolean.get:()Z
      25: ifeq          32
      28: aload_0
      29: invokespecial #46                 // Method createRouteObserve:()V
      32: return

  static {};
    Code:
       0: aconst_null
       1: putstatic     #53                 // Field GLOBAL_PILOT_EXCHANGER:Lorg/apache/dubbo/registry/xds/util/PilotExchanger;
       4: return
}
