Compiled from "XdsChannel.java"
public class org.apache.dubbo.registry.xds.util.XdsChannel {
  private static final org.apache.dubbo.common.logger.ErrorTypeAwareLogger logger;

  private static final java.lang.String USE_AGENT;

  private org.apache.dubbo.common.URL url;

  private static final java.lang.String SECURE;

  private static final java.lang.String PLAINTEXT;

  private final io.grpc.ManagedChannel channel;

  public org.apache.dubbo.common.URL getUrl();
    Code:
       0: aload_0
       1: getfield      #2                  // Field url:Lorg/apache/dubbo/common/URL;
       4: areturn

  public io.grpc.ManagedChannel getChannel();
    Code:
       0: aload_0
       1: getfield      #3                  // Field channel:Lio/grpc/ManagedChannel;
       4: areturn

  public org.apache.dubbo.registry.xds.util.XdsChannel(org.apache.dubbo.common.URL);
    Code:
       0: aload_0
       1: invokespecial #4                  // Method java/lang/Object."<init>":()V
       4: aconst_null
       5: astore_2
       6: aload_0
       7: aload_1
       8: putfield      #2                  // Field url:Lorg/apache/dubbo/common/URL;
      11: aload_1
      12: ldc           #6                  // String use-agent
      14: iconst_0
      15: invokevirtual #7                  // Method org/apache/dubbo/common/URL.getParameter:(Ljava/lang/String;Z)Z
      18: ifne          165
      21: ldc           #8                  // String plaintext
      23: aload_1
      24: ldc           #9                  // String secure
      26: invokevirtual #10                 // Method org/apache/dubbo/common/URL.getParameter:(Ljava/lang/String;)Ljava/lang/String;
      29: invokevirtual #11                 // Method java/lang/String.equals:(Ljava/lang/Object;)Z
      32: ifeq          56
      35: aload_1
      36: invokevirtual #12                 // Method org/apache/dubbo/common/URL.getHost:()Ljava/lang/String;
      39: aload_1
      40: invokevirtual #13                 // Method org/apache/dubbo/common/URL.getPort:()I
      43: invokestatic  #14                 // Method io/grpc/netty/shaded/io/grpc/netty/NettyChannelBuilder.forAddress:(Ljava/lang/String;I)Lio/grpc/netty/shaded/io/grpc/netty/NettyChannelBuilder;
      46: invokevirtual #15                 // Method io/grpc/netty/shaded/io/grpc/netty/NettyChannelBuilder.usePlaintext:()Lio/grpc/netty/shaded/io/grpc/netty/NettyChannelBuilder;
      49: invokevirtual #16                 // Method io/grpc/netty/shaded/io/grpc/netty/NettyChannelBuilder.build:()Lio/grpc/ManagedChannel;
      52: astore_2
      53: goto          262
      56: aload_1
      57: invokevirtual #17                 // Method org/apache/dubbo/common/URL.getOrDefaultApplicationModel:()Lorg/apache/dubbo/rpc/model/ApplicationModel;
      60: ldc           #18                 // class org/apache/dubbo/registry/xds/XdsCertificateSigner
      62: invokevirtual #19                 // Method org/apache/dubbo/rpc/model/ApplicationModel.getExtensionLoader:(Ljava/lang/Class;)Lorg/apache/dubbo/common/extension/ExtensionLoader;
      65: aload_1
      66: ldc           #20                 // String signer
      68: ldc           #21                 // String istio
      70: invokevirtual #22                 // Method org/apache/dubbo/common/URL.getParameter:(Ljava/lang/String;Ljava/lang/String;)Ljava/lang/String;
      73: invokevirtual #23                 // Method org/apache/dubbo/common/extension/ExtensionLoader.getExtension:(Ljava/lang/String;)Ljava/lang/Object;
      76: checkcast     #18                 // class org/apache/dubbo/registry/xds/XdsCertificateSigner
      79: astore_3
      80: aload_3
      81: aload_1
      82: invokeinterface #24,  2           // InterfaceMethod org/apache/dubbo/registry/xds/XdsCertificateSigner.GenerateCert:(Lorg/apache/dubbo/common/URL;)Lorg/apache/dubbo/registry/xds/XdsCertificateSigner$CertPair;
      87: astore        4
      89: invokestatic  #25                 // Method io/grpc/netty/shaded/io/grpc/netty/GrpcSslContexts.forClient:()Lio/grpc/netty/shaded/io/netty/handler/ssl/SslContextBuilder;
      92: getstatic     #26                 // Field io/grpc/netty/shaded/io/netty/handler/ssl/util/InsecureTrustManagerFactory.INSTANCE:Ljavax/net/ssl/TrustManagerFactory;
      95: invokevirtual #27                 // Method io/grpc/netty/shaded/io/netty/handler/ssl/SslContextBuilder.trustManager:(Ljavax/net/ssl/TrustManagerFactory;)Lio/grpc/netty/shaded/io/netty/handler/ssl/SslContextBuilder;
      98: new           #28                 // class java/io/ByteArrayInputStream
     101: dup
     102: aload         4
     104: invokevirtual #29                 // Method org/apache/dubbo/registry/xds/XdsCertificateSigner$CertPair.getPublicKey:()Ljava/lang/String;
     107: getstatic     #30                 // Field java/nio/charset/StandardCharsets.UTF_8:Ljava/nio/charset/Charset;
     110: invokevirtual #31                 // Method java/lang/String.getBytes:(Ljava/nio/charset/Charset;)[B
     113: invokespecial #32                 // Method java/io/ByteArrayInputStream."<init>":([B)V
     116: new           #28                 // class java/io/ByteArrayInputStream
     119: dup
     120: aload         4
     122: invokevirtual #33                 // Method org/apache/dubbo/registry/xds/XdsCertificateSigner$CertPair.getPrivateKey:()Ljava/lang/String;
     125: getstatic     #30                 // Field java/nio/charset/StandardCharsets.UTF_8:Ljava/nio/charset/Charset;
     128: invokevirtual #31                 // Method java/lang/String.getBytes:(Ljava/nio/charset/Charset;)[B
     131: invokespecial #32                 // Method java/io/ByteArrayInputStream."<init>":([B)V
     134: invokevirtual #34                 // Method io/grpc/netty/shaded/io/netty/handler/ssl/SslContextBuilder.keyManager:(Ljava/io/InputStream;Ljava/io/InputStream;)Lio/grpc/netty/shaded/io/netty/handler/ssl/SslContextBuilder;
     137: invokevirtual #35                 // Method io/grpc/netty/shaded/io/netty/handler/ssl/SslContextBuilder.build:()Lio/grpc/netty/shaded/io/netty/handler/ssl/SslContext;
     140: astore        5
     142: aload_1
     143: invokevirtual #12                 // Method org/apache/dubbo/common/URL.getHost:()Ljava/lang/String;
     146: aload_1
     147: invokevirtual #13                 // Method org/apache/dubbo/common/URL.getPort:()I
     150: invokestatic  #14                 // Method io/grpc/netty/shaded/io/grpc/netty/NettyChannelBuilder.forAddress:(Ljava/lang/String;I)Lio/grpc/netty/shaded/io/grpc/netty/NettyChannelBuilder;
     153: aload         5
     155: invokevirtual #36                 // Method io/grpc/netty/shaded/io/grpc/netty/NettyChannelBuilder.sslContext:(Lio/grpc/netty/shaded/io/netty/handler/ssl/SslContext;)Lio/grpc/netty/shaded/io/grpc/netty/NettyChannelBuilder;
     158: invokevirtual #16                 // Method io/grpc/netty/shaded/io/grpc/netty/NettyChannelBuilder.build:()Lio/grpc/ManagedChannel;
     161: astore_2
     162: goto          262
     165: new           #37                 // class org/apache/dubbo/registry/xds/util/bootstrap/BootstrapperImpl
     168: dup
     169: invokespecial #38                 // Method org/apache/dubbo/registry/xds/util/bootstrap/BootstrapperImpl."<init>":()V
     172: astore_3
     173: aload_3
     174: invokevirtual #39                 // Method org/apache/dubbo/registry/xds/util/bootstrap/BootstrapperImpl.bootstrap:()Lorg/apache/dubbo/registry/xds/util/bootstrap/Bootstrapper$BootstrapInfo;
     177: astore        4
     179: aload         4
     181: invokevirtual #40                 // Method org/apache/dubbo/registry/xds/util/bootstrap/Bootstrapper$BootstrapInfo.servers:()Ljava/util/List;
     184: iconst_0
     185: invokeinterface #41,  2           // InterfaceMethod java/util/List.get:(I)Ljava/lang/Object;
     190: checkcast     #42                 // class org/apache/dubbo/registry/xds/util/bootstrap/Bootstrapper$ServerInfo
     193: invokevirtual #43                 // Method org/apache/dubbo/registry/xds/util/bootstrap/Bootstrapper$ServerInfo.target:()Ljava/lang/String;
     196: aconst_null
     197: iconst_0
     198: invokestatic  #44                 // Method org/apache/dubbo/common/url/component/URLAddress.parse:(Ljava/lang/String;Ljava/lang/String;Z)Lorg/apache/dubbo/common/url/component/URLAddress;
     201: astore        5
     203: new           #45                 // class io/grpc/netty/shaded/io/netty/channel/epoll/EpollEventLoopGroup
     206: dup
     207: invokespecial #46                 // Method io/grpc/netty/shaded/io/netty/channel/epoll/EpollEventLoopGroup."<init>":()V
     210: astore        6
     212: new           #47                 // class io/grpc/netty/shaded/io/netty/channel/unix/DomainSocketAddress
     215: dup
     216: new           #48                 // class java/lang/StringBuilder
     219: dup
     220: invokespecial #49                 // Method java/lang/StringBuilder."<init>":()V
     223: ldc           #50                 // String /
     225: invokevirtual #51                 // Method java/lang/StringBuilder.append:(Ljava/lang/String;)Ljava/lang/StringBuilder;
     228: aload         5
     230: invokevirtual #52                 // Method org/apache/dubbo/common/url/component/URLAddress.getPath:()Ljava/lang/String;
     233: invokevirtual #51                 // Method java/lang/StringBuilder.append:(Ljava/lang/String;)Ljava/lang/StringBuilder;
     236: invokevirtual #53                 // Method java/lang/StringBuilder.toString:()Ljava/lang/String;
     239: invokespecial #54                 // Method io/grpc/netty/shaded/io/netty/channel/unix/DomainSocketAddress."<init>":(Ljava/lang/String;)V
     242: invokestatic  #55                 // Method io/grpc/netty/shaded/io/grpc/netty/NettyChannelBuilder.forAddress:(Ljava/net/SocketAddress;)Lio/grpc/netty/shaded/io/grpc/netty/NettyChannelBuilder;
     245: aload         6
     247: invokevirtual #56                 // Method io/grpc/netty/shaded/io/grpc/netty/NettyChannelBuilder.eventLoopGroup:(Lio/grpc/netty/shaded/io/netty/channel/EventLoopGroup;)Lio/grpc/netty/shaded/io/grpc/netty/NettyChannelBuilder;
     250: ldc           #57                 // class io/grpc/netty/shaded/io/netty/channel/epoll/EpollDomainSocketChannel
     252: invokevirtual #58                 // Method io/grpc/netty/shaded/io/grpc/netty/NettyChannelBuilder.channelType:(Ljava/lang/Class;)Lio/grpc/netty/shaded/io/grpc/netty/NettyChannelBuilder;
     255: invokevirtual #15                 // Method io/grpc/netty/shaded/io/grpc/netty/NettyChannelBuilder.usePlaintext:()Lio/grpc/netty/shaded/io/grpc/netty/NettyChannelBuilder;
     258: invokevirtual #16                 // Method io/grpc/netty/shaded/io/grpc/netty/NettyChannelBuilder.build:()Lio/grpc/ManagedChannel;
     261: astore_2
     262: goto          283
     265: astore_3
     266: getstatic     #60                 // Field logger:Lorg/apache/dubbo/common/logger/ErrorTypeAwareLogger;
     269: ldc           #61                 // String 1-32
     271: ldc           #62                 // String
     273: ldc           #62                 // String
     275: ldc           #63                 // String Error occurred when creating gRPC channel to control panel.
     277: aload_3
     278: invokeinterface #64,  6           // InterfaceMethod org/apache/dubbo/common/logger/ErrorTypeAwareLogger.error:(Ljava/lang/String;Ljava/lang/String;Ljava/lang/String;Ljava/lang/String;Ljava/lang/Throwable;)V
     283: aload_0
     284: aload_2
     285: putfield      #3                  // Field channel:Lio/grpc/ManagedChannel;
     288: return
    Exception table:
       from    to  target type
          11   262   265   Class java/lang/Exception

  public io.grpc.stub.StreamObserver<io.envoyproxy.envoy.service.discovery.v3.DeltaDiscoveryRequest> observeDeltaDiscoveryRequest(io.grpc.stub.StreamObserver<io.envoyproxy.envoy.service.discovery.v3.DeltaDiscoveryResponse>);
    Code:
       0: aload_0
       1: getfield      #3                  // Field channel:Lio/grpc/ManagedChannel;
       4: invokestatic  #65                 // Method io/envoyproxy/envoy/service/discovery/v3/AggregatedDiscoveryServiceGrpc.newStub:(Lio/grpc/Channel;)Lio/envoyproxy/envoy/service/discovery/v3/AggregatedDiscoveryServiceGrpc$AggregatedDiscoveryServiceStub;
       7: aload_1
       8: invokevirtual #66                 // Method io/envoyproxy/envoy/service/discovery/v3/AggregatedDiscoveryServiceGrpc$AggregatedDiscoveryServiceStub.deltaAggregatedResources:(Lio/grpc/stub/StreamObserver;)Lio/grpc/stub/StreamObserver;
      11: areturn

  public io.grpc.stub.StreamObserver<io.envoyproxy.envoy.service.discovery.v3.DiscoveryRequest> createDeltaDiscoveryRequest(io.grpc.stub.StreamObserver<io.envoyproxy.envoy.service.discovery.v3.DiscoveryResponse>);
    Code:
       0: aload_0
       1: getfield      #3                  // Field channel:Lio/grpc/ManagedChannel;
       4: invokestatic  #65                 // Method io/envoyproxy/envoy/service/discovery/v3/AggregatedDiscoveryServiceGrpc.newStub:(Lio/grpc/Channel;)Lio/envoyproxy/envoy/service/discovery/v3/AggregatedDiscoveryServiceGrpc$AggregatedDiscoveryServiceStub;
       7: aload_1
       8: invokevirtual #67                 // Method io/envoyproxy/envoy/service/discovery/v3/AggregatedDiscoveryServiceGrpc$AggregatedDiscoveryServiceStub.streamAggregatedResources:(Lio/grpc/stub/StreamObserver;)Lio/grpc/stub/StreamObserver;
      11: areturn

  public io.grpc.stub.StreamObserver<io.envoyproxy.envoy.api.v2.DeltaDiscoveryRequest> observeDeltaDiscoveryRequestV2(io.grpc.stub.StreamObserver<io.envoyproxy.envoy.api.v2.DeltaDiscoveryResponse>);
    Code:
       0: aload_0
       1: getfield      #3                  // Field channel:Lio/grpc/ManagedChannel;
       4: invokestatic  #68                 // Method io/envoyproxy/envoy/service/discovery/v2/AggregatedDiscoveryServiceGrpc.newStub:(Lio/grpc/Channel;)Lio/envoyproxy/envoy/service/discovery/v2/AggregatedDiscoveryServiceGrpc$AggregatedDiscoveryServiceStub;
       7: aload_1
       8: invokevirtual #69                 // Method io/envoyproxy/envoy/service/discovery/v2/AggregatedDiscoveryServiceGrpc$AggregatedDiscoveryServiceStub.deltaAggregatedResources:(Lio/grpc/stub/StreamObserver;)Lio/grpc/stub/StreamObserver;
      11: areturn

  public io.grpc.stub.StreamObserver<io.envoyproxy.envoy.api.v2.DiscoveryRequest> createDeltaDiscoveryRequestV2(io.grpc.stub.StreamObserver<io.envoyproxy.envoy.api.v2.DiscoveryResponse>);
    Code:
       0: aload_0
       1: getfield      #3                  // Field channel:Lio/grpc/ManagedChannel;
       4: invokestatic  #68                 // Method io/envoyproxy/envoy/service/discovery/v2/AggregatedDiscoveryServiceGrpc.newStub:(Lio/grpc/Channel;)Lio/envoyproxy/envoy/service/discovery/v2/AggregatedDiscoveryServiceGrpc$AggregatedDiscoveryServiceStub;
       7: aload_1
       8: invokevirtual #70                 // Method io/envoyproxy/envoy/service/discovery/v2/AggregatedDiscoveryServiceGrpc$AggregatedDiscoveryServiceStub.streamAggregatedResources:(Lio/grpc/stub/StreamObserver;)Lio/grpc/stub/StreamObserver;
      11: areturn

  public void destroy();
    Code:
       0: aload_0
       1: getfield      #3                  // Field channel:Lio/grpc/ManagedChannel;
       4: invokevirtual #71                 // Method io/grpc/ManagedChannel.shutdown:()Lio/grpc/ManagedChannel;
       7: pop
       8: return

  static {};
    Code:
       0: ldc           #5                  // class org/apache/dubbo/registry/xds/util/XdsChannel
       2: invokestatic  #72                 // Method org/apache/dubbo/common/logger/LoggerFactory.getErrorTypeAwareLogger:(Ljava/lang/Class;)Lorg/apache/dubbo/common/logger/ErrorTypeAwareLogger;
       5: putstatic     #60                 // Field logger:Lorg/apache/dubbo/common/logger/ErrorTypeAwareLogger;
       8: return
}
