Compiled from "OverrideConfigurator.java"
public class org.apache.dubbo.rpc.cluster.configurator.override.OverrideConfigurator extends org.apache.dubbo.rpc.cluster.configurator.AbstractConfigurator {
  public static final org.apache.dubbo.common.logger.Logger logger;

  public org.apache.dubbo.rpc.cluster.configurator.override.OverrideConfigurator(org.apache.dubbo.common.URL);
    Code:
       0: aload_0
       1: aload_1
       2: invokespecial #1                  // Method org/apache/dubbo/rpc/cluster/configurator/AbstractConfigurator."<init>":(Lorg/apache/dubbo/common/URL;)V
       5: return

  public org.apache.dubbo.common.URL doConfigure(org.apache.dubbo.common.URL, org.apache.dubbo.common.URL);
    Code:
       0: getstatic     #2                  // Field logger:Lorg/apache/dubbo/common/logger/Logger;
       3: new           #3                  // class java/lang/StringBuilder
       6: dup
       7: invokespecial #4                  // Method java/lang/StringBuilder."<init>":()V
      10: ldc           #5                  // String Start overriding url
      12: invokevirtual #6                  // Method java/lang/StringBuilder.append:(Ljava/lang/String;)Ljava/lang/StringBuilder;
      15: aload_1
      16: invokevirtual #7                  // Method java/lang/StringBuilder.append:(Ljava/lang/Object;)Ljava/lang/StringBuilder;
      19: ldc           #8                  // String  with override url
      21: invokevirtual #6                  // Method java/lang/StringBuilder.append:(Ljava/lang/String;)Ljava/lang/StringBuilder;
      24: aload_2
      25: invokevirtual #7                  // Method java/lang/StringBuilder.append:(Ljava/lang/Object;)Ljava/lang/StringBuilder;
      28: invokevirtual #9                  // Method java/lang/StringBuilder.toString:()Ljava/lang/String;
      31: invokeinterface #10,  2           // InterfaceMethod org/apache/dubbo/common/logger/Logger.info:(Ljava/lang/String;)V
      36: aload_1
      37: aload_2
      38: invokevirtual #11                 // Method org/apache/dubbo/common/URL.getParameters:()Ljava/util/Map;
      41: invokevirtual #12                 // Method org/apache/dubbo/common/URL.addParameters:(Ljava/util/Map;)Lorg/apache/dubbo/common/URL;
      44: areturn

  static {};
    Code:
       0: ldc           #13                 // class org/apache/dubbo/rpc/cluster/configurator/override/OverrideConfigurator
       2: invokestatic  #14                 // Method org/apache/dubbo/common/logger/LoggerFactory.getLogger:(Ljava/lang/Class;)Lorg/apache/dubbo/common/logger/Logger;
       5: putstatic     #2                  // Field logger:Lorg/apache/dubbo/common/logger/Logger;
       8: return
}
