Compiled from "JclLogger.java"
public class org.apache.dubbo.common.logger.jcl.JclLogger implements org.apache.dubbo.common.logger.Logger {
  private final org.apache.commons.logging.Log logger;

  public org.apache.dubbo.common.logger.jcl.JclLogger(org.apache.commons.logging.Log);
    Code:
       0: aload_0
       1: invokespecial #1                  // Method java/lang/Object."<init>":()V
       4: aload_0
       5: aload_1
       6: putfield      #2                  // Field logger:Lorg/apache/commons/logging/Log;
       9: return

  public void trace(java.lang.String);
    Code:
       0: aload_0
       1: getfield      #2                  // Field logger:Lorg/apache/commons/logging/Log;
       4: aload_1
       5: invokeinterface #3,  2            // InterfaceMethod org/apache/commons/logging/Log.trace:(Ljava/lang/Object;)V
      10: return

  public void trace(java.lang.Throwable);
    Code:
       0: aload_0
       1: getfield      #2                  // Field logger:Lorg/apache/commons/logging/Log;
       4: aload_1
       5: invokeinterface #3,  2            // InterfaceMethod org/apache/commons/logging/Log.trace:(Ljava/lang/Object;)V
      10: return

  public void trace(java.lang.String, java.lang.Throwable);
    Code:
       0: aload_0
       1: getfield      #2                  // Field logger:Lorg/apache/commons/logging/Log;
       4: aload_1
       5: aload_2
       6: invokeinterface #4,  3            // InterfaceMethod org/apache/commons/logging/Log.trace:(Ljava/lang/Object;Ljava/lang/Throwable;)V
      11: return

  public void debug(java.lang.String);
    Code:
       0: aload_0
       1: getfield      #2                  // Field logger:Lorg/apache/commons/logging/Log;
       4: aload_1
       5: invokeinterface #5,  2            // InterfaceMethod org/apache/commons/logging/Log.debug:(Ljava/lang/Object;)V
      10: return

  public void debug(java.lang.Throwable);
    Code:
       0: aload_0
       1: getfield      #2                  // Field logger:Lorg/apache/commons/logging/Log;
       4: aload_1
       5: invokeinterface #5,  2            // InterfaceMethod org/apache/commons/logging/Log.debug:(Ljava/lang/Object;)V
      10: return

  public void debug(java.lang.String, java.lang.Throwable);
    Code:
       0: aload_0
       1: getfield      #2                  // Field logger:Lorg/apache/commons/logging/Log;
       4: aload_1
       5: aload_2
       6: invokeinterface #6,  3            // InterfaceMethod org/apache/commons/logging/Log.debug:(Ljava/lang/Object;Ljava/lang/Throwable;)V
      11: return

  public void info(java.lang.String);
    Code:
       0: aload_0
       1: getfield      #2                  // Field logger:Lorg/apache/commons/logging/Log;
       4: aload_1
       5: invokeinterface #7,  2            // InterfaceMethod org/apache/commons/logging/Log.info:(Ljava/lang/Object;)V
      10: return

  public void info(java.lang.Throwable);
    Code:
       0: aload_0
       1: getfield      #2                  // Field logger:Lorg/apache/commons/logging/Log;
       4: aload_1
       5: invokeinterface #7,  2            // InterfaceMethod org/apache/commons/logging/Log.info:(Ljava/lang/Object;)V
      10: return

  public void info(java.lang.String, java.lang.Throwable);
    Code:
       0: aload_0
       1: getfield      #2                  // Field logger:Lorg/apache/commons/logging/Log;
       4: aload_1
       5: aload_2
       6: invokeinterface #8,  3            // InterfaceMethod org/apache/commons/logging/Log.info:(Ljava/lang/Object;Ljava/lang/Throwable;)V
      11: return

  public void warn(java.lang.String);
    Code:
       0: aload_0
       1: getfield      #2                  // Field logger:Lorg/apache/commons/logging/Log;
       4: aload_1
       5: invokeinterface #9,  2            // InterfaceMethod org/apache/commons/logging/Log.warn:(Ljava/lang/Object;)V
      10: return

  public void warn(java.lang.Throwable);
    Code:
       0: aload_0
       1: getfield      #2                  // Field logger:Lorg/apache/commons/logging/Log;
       4: aload_1
       5: invokeinterface #9,  2            // InterfaceMethod org/apache/commons/logging/Log.warn:(Ljava/lang/Object;)V
      10: return

  public void warn(java.lang.String, java.lang.Throwable);
    Code:
       0: aload_0
       1: getfield      #2                  // Field logger:Lorg/apache/commons/logging/Log;
       4: aload_1
       5: aload_2
       6: invokeinterface #10,  3           // InterfaceMethod org/apache/commons/logging/Log.warn:(Ljava/lang/Object;Ljava/lang/Throwable;)V
      11: return

  public void error(java.lang.String);
    Code:
       0: aload_0
       1: getfield      #2                  // Field logger:Lorg/apache/commons/logging/Log;
       4: aload_1
       5: invokeinterface #11,  2           // InterfaceMethod org/apache/commons/logging/Log.error:(Ljava/lang/Object;)V
      10: return

  public void error(java.lang.Throwable);
    Code:
       0: aload_0
       1: getfield      #2                  // Field logger:Lorg/apache/commons/logging/Log;
       4: aload_1
       5: invokeinterface #11,  2           // InterfaceMethod org/apache/commons/logging/Log.error:(Ljava/lang/Object;)V
      10: return

  public void error(java.lang.String, java.lang.Throwable);
    Code:
       0: aload_0
       1: getfield      #2                  // Field logger:Lorg/apache/commons/logging/Log;
       4: aload_1
       5: aload_2
       6: invokeinterface #12,  3           // InterfaceMethod org/apache/commons/logging/Log.error:(Ljava/lang/Object;Ljava/lang/Throwable;)V
      11: return

  public boolean isTraceEnabled();
    Code:
       0: aload_0
       1: getfield      #2                  // Field logger:Lorg/apache/commons/logging/Log;
       4: invokeinterface #13,  1           // InterfaceMethod org/apache/commons/logging/Log.isTraceEnabled:()Z
       9: ireturn

  public boolean isDebugEnabled();
    Code:
       0: aload_0
       1: getfield      #2                  // Field logger:Lorg/apache/commons/logging/Log;
       4: invokeinterface #14,  1           // InterfaceMethod org/apache/commons/logging/Log.isDebugEnabled:()Z
       9: ireturn

  public boolean isInfoEnabled();
    Code:
       0: aload_0
       1: getfield      #2                  // Field logger:Lorg/apache/commons/logging/Log;
       4: invokeinterface #15,  1           // InterfaceMethod org/apache/commons/logging/Log.isInfoEnabled:()Z
       9: ireturn

  public boolean isWarnEnabled();
    Code:
       0: aload_0
       1: getfield      #2                  // Field logger:Lorg/apache/commons/logging/Log;
       4: invokeinterface #16,  1           // InterfaceMethod org/apache/commons/logging/Log.isWarnEnabled:()Z
       9: ireturn

  public boolean isErrorEnabled();
    Code:
       0: aload_0
       1: getfield      #2                  // Field logger:Lorg/apache/commons/logging/Log;
       4: invokeinterface #17,  1           // InterfaceMethod org/apache/commons/logging/Log.isErrorEnabled:()Z
       9: ireturn
}
