Compiled from "JclLoggerAdapter.java"
public class org.apache.dubbo.common.logger.jcl.JclLoggerAdapter implements org.apache.dubbo.common.logger.LoggerAdapter {
  public static final java.lang.String NAME;

  private org.apache.dubbo.common.logger.Level level;

  private java.io.File file;

  public org.apache.dubbo.common.logger.jcl.JclLoggerAdapter();
    Code:
       0: aload_0
       1: invokespecial #1                  // Method java/lang/Object."<init>":()V
       4: return

  public org.apache.dubbo.common.logger.Logger getLogger(java.lang.String);
    Code:
       0: new           #2                  // class org/apache/dubbo/common/logger/jcl/JclLogger
       3: dup
       4: aload_1
       5: invokestatic  #3                  // Method org/apache/commons/logging/LogFactory.getLog:(Ljava/lang/String;)Lorg/apache/commons/logging/Log;
       8: invokespecial #4                  // Method org/apache/dubbo/common/logger/jcl/JclLogger."<init>":(Lorg/apache/commons/logging/Log;)V
      11: areturn

  public org.apache.dubbo.common.logger.Logger getLogger(java.lang.Class<?>);
    Code:
       0: new           #2                  // class org/apache/dubbo/common/logger/jcl/JclLogger
       3: dup
       4: aload_1
       5: invokestatic  #5                  // Method org/apache/commons/logging/LogFactory.getLog:(Ljava/lang/Class;)Lorg/apache/commons/logging/Log;
       8: invokespecial #4                  // Method org/apache/dubbo/common/logger/jcl/JclLogger."<init>":(Lorg/apache/commons/logging/Log;)V
      11: areturn

  public org.apache.dubbo.common.logger.Level getLevel();
    Code:
       0: aload_0
       1: getfield      #6                  // Field level:Lorg/apache/dubbo/common/logger/Level;
       4: areturn

  public void setLevel(org.apache.dubbo.common.logger.Level);
    Code:
       0: aload_0
       1: aload_1
       2: putfield      #6                  // Field level:Lorg/apache/dubbo/common/logger/Level;
       5: return

  public java.io.File getFile();
    Code:
       0: aload_0
       1: getfield      #7                  // Field file:Ljava/io/File;
       4: areturn

  public void setFile(java.io.File);
    Code:
       0: aload_0
       1: aload_1
       2: putfield      #7                  // Field file:Ljava/io/File;
       5: return
}
