Compiled from "DubboServerReflectionTriple.java"
class io.grpc.reflection.v1alpha.DubboServerReflectionTriple$ServerReflectionImplBase$1 implements java.util.function.BiConsumer<T, org.apache.dubbo.common.stream.StreamObserver<R>> {
  final java.util.function.Function val$syncFun;

  final io.grpc.reflection.v1alpha.DubboServerReflectionTriple$ServerReflectionImplBase this$0;

  io.grpc.reflection.v1alpha.DubboServerReflectionTriple$ServerReflectionImplBase$1(io.grpc.reflection.v1alpha.DubboServerReflectionTriple$ServerReflectionImplBase, java.util.function.Function);
    Code:
       0: aload_0
       1: aload_1
       2: putfield      #1                  // Field this$0:Lio/grpc/reflection/v1alpha/DubboServerReflectionTriple$ServerReflectionImplBase;
       5: aload_0
       6: aload_2
       7: putfield      #2                  // Field val$syncFun:Ljava/util/function/Function;
      10: aload_0
      11: invokespecial #3                  // Method java/lang/Object."<init>":()V
      14: return

  public void accept(T, org.apache.dubbo.common.stream.StreamObserver<R>);
    Code:
       0: aload_0
       1: getfield      #2                  // Field val$syncFun:Ljava/util/function/Function;
       4: aload_1
       5: invokeinterface #4,  2            // InterfaceMethod java/util/function/Function.apply:(Ljava/lang/Object;)Ljava/lang/Object;
      10: astore_3
      11: aload_2
      12: aload_3
      13: invokeinterface #5,  2            // InterfaceMethod org/apache/dubbo/common/stream/StreamObserver.onNext:(Ljava/lang/Object;)V
      18: aload_2
      19: invokeinterface #6,  1            // InterfaceMethod org/apache/dubbo/common/stream/StreamObserver.onCompleted:()V
      24: goto          35
      27: astore_3
      28: aload_2
      29: aload_3
      30: invokeinterface #8,  2            // InterfaceMethod org/apache/dubbo/common/stream/StreamObserver.onError:(Ljava/lang/Throwable;)V
      35: return
    Exception table:
       from    to  target type
           0    24    27   Class java/lang/Throwable

  public void accept(java.lang.Object, java.lang.Object);
    Code:
       0: aload_0
       1: aload_1
       2: aload_2
       3: checkcast     #9                  // class org/apache/dubbo/common/stream/StreamObserver
       6: invokevirtual #10                 // Method accept:(Ljava/lang/Object;Lorg/apache/dubbo/common/stream/StreamObserver;)V
       9: return
}
