Compiled from "DubboServerReflectionTriple.java"
public class io.grpc.reflection.v1alpha.DubboServerReflectionTriple$ServerReflectionStub implements io.grpc.reflection.v1alpha.ServerReflection {
  private final org.apache.dubbo.rpc.Invoker<io.grpc.reflection.v1alpha.ServerReflection> invoker;

  public io.grpc.reflection.v1alpha.DubboServerReflectionTriple$ServerReflectionStub(org.apache.dubbo.rpc.Invoker<io.grpc.reflection.v1alpha.ServerReflection>);
    Code:
       0: aload_0
       1: invokespecial #1                  // Method java/lang/Object."<init>":()V
       4: aload_0
       5: aload_1
       6: putfield      #2                  // Field invoker:Lorg/apache/dubbo/rpc/Invoker;
       9: return

  public org.apache.dubbo.common.stream.StreamObserver<io.grpc.reflection.v1alpha.ServerReflectionRequest> serverReflectionInfo(org.apache.dubbo.common.stream.StreamObserver<io.grpc.reflection.v1alpha.ServerReflectionResponse>);
    Code:
       0: aload_0
       1: getfield      #2                  // Field invoker:Lorg/apache/dubbo/rpc/Invoker;
       4: invokestatic  #3                  // Method io/grpc/reflection/v1alpha/DubboServerReflectionTriple.access$000:()Lorg/apache/dubbo/rpc/model/StubMethodDescriptor;
       7: aload_1
       8: invokestatic  #4                  // Method org/apache/dubbo/rpc/stub/StubInvocationUtil.biOrClientStreamCall:(Lorg/apache/dubbo/rpc/Invoker;Lorg/apache/dubbo/rpc/model/MethodDescriptor;Lorg/apache/dubbo/common/stream/StreamObserver;)Lorg/apache/dubbo/common/stream/StreamObserver;
      11: areturn
}
