Compiled from "ExtensionNumberResponse.java"
public final class io.grpc.reflection.v1alpha.ExtensionNumberResponse$Builder extends com.google.protobuf.GeneratedMessageV3$Builder<io.grpc.reflection.v1alpha.ExtensionNumberResponse$Builder> implements io.grpc.reflection.v1alpha.ExtensionNumberResponseOrBuilder {
  private int bitField0_;

  private java.lang.Object baseTypeName_;

  private com.google.protobuf.Internal$IntList extensionNumber_;

  public static final com.google.protobuf.Descriptors$Descriptor getDescriptor();
    Code:
       0: getstatic     #3                  // Field io/grpc/reflection/v1alpha/ServerReflectionProto.internal_static_grpc_reflection_v1alpha_ExtensionNumberResponse_descriptor:Lcom/google/protobuf/Descriptors$Descriptor;
       3: areturn

  protected com.google.protobuf.GeneratedMessageV3$FieldAccessorTable internalGetFieldAccessorTable();
    Code:
       0: getstatic     #4                  // Field io/grpc/reflection/v1alpha/ServerReflectionProto.internal_static_grpc_reflection_v1alpha_ExtensionNumberResponse_fieldAccessorTable:Lcom/google/protobuf/GeneratedMessageV3$FieldAccessorTable;
       3: ldc           #5                  // class io/grpc/reflection/v1alpha/ExtensionNumberResponse
       5: ldc           #6                  // class io/grpc/reflection/v1alpha/ExtensionNumberResponse$Builder
       7: invokevirtual #7                  // Method com/google/protobuf/GeneratedMessageV3$FieldAccessorTable.ensureFieldAccessorsInitialized:(Ljava/lang/Class;Ljava/lang/Class;)Lcom/google/protobuf/GeneratedMessageV3$FieldAccessorTable;
      10: areturn

  private io.grpc.reflection.v1alpha.ExtensionNumberResponse$Builder();
    Code:
       0: aload_0
       1: invokespecial #8                  // Method com/google/protobuf/GeneratedMessageV3$Builder."<init>":()V
       4: aload_0
       5: ldc           #9                  // String
       7: putfield      #10                 // Field baseTypeName_:Ljava/lang/Object;
      10: aload_0
      11: invokestatic  #11                 // Method io/grpc/reflection/v1alpha/ExtensionNumberResponse.access$700:()Lcom/google/protobuf/Internal$IntList;
      14: putfield      #12                 // Field extensionNumber_:Lcom/google/protobuf/Internal$IntList;
      17: return

  private io.grpc.reflection.v1alpha.ExtensionNumberResponse$Builder(com.google.protobuf.GeneratedMessageV3$BuilderParent);
    Code:
       0: aload_0
       1: aload_1
       2: invokespecial #13                 // Method com/google/protobuf/GeneratedMessageV3$Builder."<init>":(Lcom/google/protobuf/GeneratedMessageV3$BuilderParent;)V
       5: aload_0
       6: ldc           #9                  // String
       8: putfield      #10                 // Field baseTypeName_:Ljava/lang/Object;
      11: aload_0
      12: invokestatic  #11                 // Method io/grpc/reflection/v1alpha/ExtensionNumberResponse.access$700:()Lcom/google/protobuf/Internal$IntList;
      15: putfield      #12                 // Field extensionNumber_:Lcom/google/protobuf/Internal$IntList;
      18: return

  public io.grpc.reflection.v1alpha.ExtensionNumberResponse$Builder clear();
    Code:
       0: aload_0
       1: invokespecial #14                 // Method com/google/protobuf/GeneratedMessageV3$Builder.clear:()Lcom/google/protobuf/GeneratedMessageV3$Builder;
       4: pop
       5: aload_0
       6: iconst_0
       7: putfield      #15                 // Field bitField0_:I
      10: aload_0
      11: ldc           #9                  // String
      13: putfield      #10                 // Field baseTypeName_:Ljava/lang/Object;
      16: aload_0
      17: invokestatic  #16                 // Method io/grpc/reflection/v1alpha/ExtensionNumberResponse.access$200:()Lcom/google/protobuf/Internal$IntList;
      20: putfield      #12                 // Field extensionNumber_:Lcom/google/protobuf/Internal$IntList;
      23: aload_0
      24: areturn

  public com.google.protobuf.Descriptors$Descriptor getDescriptorForType();
    Code:
       0: getstatic     #3                  // Field io/grpc/reflection/v1alpha/ServerReflectionProto.internal_static_grpc_reflection_v1alpha_ExtensionNumberResponse_descriptor:Lcom/google/protobuf/Descriptors$Descriptor;
       3: areturn

  public io.grpc.reflection.v1alpha.ExtensionNumberResponse getDefaultInstanceForType();
    Code:
       0: invokestatic  #17                 // Method io/grpc/reflection/v1alpha/ExtensionNumberResponse.getDefaultInstance:()Lio/grpc/reflection/v1alpha/ExtensionNumberResponse;
       3: areturn

  public io.grpc.reflection.v1alpha.ExtensionNumberResponse build();
    Code:
       0: aload_0
       1: invokevirtual #18                 // Method buildPartial:()Lio/grpc/reflection/v1alpha/ExtensionNumberResponse;
       4: astore_1
       5: aload_1
       6: invokevirtual #19                 // Method io/grpc/reflection/v1alpha/ExtensionNumberResponse.isInitialized:()Z
       9: ifne          17
      12: aload_1
      13: invokestatic  #20                 // Method newUninitializedMessageException:(Lcom/google/protobuf/Message;)Lcom/google/protobuf/UninitializedMessageException;
      16: athrow
      17: aload_1
      18: areturn

  public io.grpc.reflection.v1alpha.ExtensionNumberResponse buildPartial();
    Code:
       0: new           #5                  // class io/grpc/reflection/v1alpha/ExtensionNumberResponse
       3: dup
       4: aload_0
       5: aconst_null
       6: invokespecial #21                 // Method io/grpc/reflection/v1alpha/ExtensionNumberResponse."<init>":(Lcom/google/protobuf/GeneratedMessageV3$Builder;Lio/grpc/reflection/v1alpha/ExtensionNumberResponse$1;)V
       9: astore_1
      10: aload_0
      11: aload_1
      12: invokespecial #22                 // Method buildPartialRepeatedFields:(Lio/grpc/reflection/v1alpha/ExtensionNumberResponse;)V
      15: aload_0
      16: getfield      #15                 // Field bitField0_:I
      19: ifeq          27
      22: aload_0
      23: aload_1
      24: invokespecial #23                 // Method buildPartial0:(Lio/grpc/reflection/v1alpha/ExtensionNumberResponse;)V
      27: aload_0
      28: invokevirtual #24                 // Method onBuilt:()V
      31: aload_1
      32: areturn

  private void buildPartialRepeatedFields(io.grpc.reflection.v1alpha.ExtensionNumberResponse);
    Code:
       0: aload_0
       1: getfield      #15                 // Field bitField0_:I
       4: iconst_2
       5: iand
       6: ifeq          29
       9: aload_0
      10: getfield      #12                 // Field extensionNumber_:Lcom/google/protobuf/Internal$IntList;
      13: invokeinterface #25,  1           // InterfaceMethod com/google/protobuf/Internal$IntList.makeImmutable:()V
      18: aload_0
      19: aload_0
      20: getfield      #15                 // Field bitField0_:I
      23: bipush        -3
      25: iand
      26: putfield      #15                 // Field bitField0_:I
      29: aload_1
      30: aload_0
      31: getfield      #12                 // Field extensionNumber_:Lcom/google/protobuf/Internal$IntList;
      34: invokestatic  #26                 // Method io/grpc/reflection/v1alpha/ExtensionNumberResponse.access$402:(Lio/grpc/reflection/v1alpha/ExtensionNumberResponse;Lcom/google/protobuf/Internal$IntList;)Lcom/google/protobuf/Internal$IntList;
      37: pop
      38: return

  private void buildPartial0(io.grpc.reflection.v1alpha.ExtensionNumberResponse);
    Code:
       0: aload_0
       1: getfield      #15                 // Field bitField0_:I
       4: istore_2
       5: iload_2
       6: iconst_1
       7: iand
       8: ifeq          20
      11: aload_1
      12: aload_0
      13: getfield      #10                 // Field baseTypeName_:Ljava/lang/Object;
      16: invokestatic  #27                 // Method io/grpc/reflection/v1alpha/ExtensionNumberResponse.access$502:(Lio/grpc/reflection/v1alpha/ExtensionNumberResponse;Ljava/lang/Object;)Ljava/lang/Object;
      19: pop
      20: return

  public io.grpc.reflection.v1alpha.ExtensionNumberResponse$Builder mergeFrom(com.google.protobuf.Message);
    Code:
       0: aload_1
       1: instanceof    #5                  // class io/grpc/reflection/v1alpha/ExtensionNumberResponse
       4: ifeq          16
       7: aload_0
       8: aload_1
       9: checkcast     #5                  // class io/grpc/reflection/v1alpha/ExtensionNumberResponse
      12: invokevirtual #28                 // Method mergeFrom:(Lio/grpc/reflection/v1alpha/ExtensionNumberResponse;)Lio/grpc/reflection/v1alpha/ExtensionNumberResponse$Builder;
      15: areturn
      16: aload_0
      17: aload_1
      18: invokespecial #29                 // Method com/google/protobuf/GeneratedMessageV3$Builder.mergeFrom:(Lcom/google/protobuf/Message;)Lcom/google/protobuf/AbstractMessage$Builder;
      21: pop
      22: aload_0
      23: areturn

  public io.grpc.reflection.v1alpha.ExtensionNumberResponse$Builder mergeFrom(io.grpc.reflection.v1alpha.ExtensionNumberResponse);
    Code:
       0: aload_1
       1: invokestatic  #17                 // Method io/grpc/reflection/v1alpha/ExtensionNumberResponse.getDefaultInstance:()Lio/grpc/reflection/v1alpha/ExtensionNumberResponse;
       4: if_acmpne     9
       7: aload_0
       8: areturn
       9: aload_1
      10: invokevirtual #30                 // Method io/grpc/reflection/v1alpha/ExtensionNumberResponse.getBaseTypeName:()Ljava/lang/String;
      13: invokevirtual #31                 // Method java/lang/String.isEmpty:()Z
      16: ifne          41
      19: aload_0
      20: aload_1
      21: invokestatic  #32                 // Method io/grpc/reflection/v1alpha/ExtensionNumberResponse.access$500:(Lio/grpc/reflection/v1alpha/ExtensionNumberResponse;)Ljava/lang/Object;
      24: putfield      #10                 // Field baseTypeName_:Ljava/lang/Object;
      27: aload_0
      28: dup
      29: getfield      #15                 // Field bitField0_:I
      32: iconst_1
      33: ior
      34: putfield      #15                 // Field bitField0_:I
      37: aload_0
      38: invokevirtual #33                 // Method onChanged:()V
      41: aload_1
      42: invokestatic  #34                 // Method io/grpc/reflection/v1alpha/ExtensionNumberResponse.access$400:(Lio/grpc/reflection/v1alpha/ExtensionNumberResponse;)Lcom/google/protobuf/Internal$IntList;
      45: invokeinterface #35,  1           // InterfaceMethod com/google/protobuf/Internal$IntList.isEmpty:()Z
      50: ifne          109
      53: aload_0
      54: getfield      #12                 // Field extensionNumber_:Lcom/google/protobuf/Internal$IntList;
      57: invokeinterface #35,  1           // InterfaceMethod com/google/protobuf/Internal$IntList.isEmpty:()Z
      62: ifeq          87
      65: aload_0
      66: aload_1
      67: invokestatic  #34                 // Method io/grpc/reflection/v1alpha/ExtensionNumberResponse.access$400:(Lio/grpc/reflection/v1alpha/ExtensionNumberResponse;)Lcom/google/protobuf/Internal$IntList;
      70: putfield      #12                 // Field extensionNumber_:Lcom/google/protobuf/Internal$IntList;
      73: aload_0
      74: aload_0
      75: getfield      #15                 // Field bitField0_:I
      78: bipush        -3
      80: iand
      81: putfield      #15                 // Field bitField0_:I
      84: goto          105
      87: aload_0
      88: invokespecial #36                 // Method ensureExtensionNumberIsMutable:()V
      91: aload_0
      92: getfield      #12                 // Field extensionNumber_:Lcom/google/protobuf/Internal$IntList;
      95: aload_1
      96: invokestatic  #34                 // Method io/grpc/reflection/v1alpha/ExtensionNumberResponse.access$400:(Lio/grpc/reflection/v1alpha/ExtensionNumberResponse;)Lcom/google/protobuf/Internal$IntList;
      99: invokeinterface #37,  2           // InterfaceMethod com/google/protobuf/Internal$IntList.addAll:(Ljava/util/Collection;)Z
     104: pop
     105: aload_0
     106: invokevirtual #33                 // Method onChanged:()V
     109: aload_0
     110: aload_1
     111: invokevirtual #38                 // Method io/grpc/reflection/v1alpha/ExtensionNumberResponse.getUnknownFields:()Lcom/google/protobuf/UnknownFieldSet;
     114: invokevirtual #39                 // Method mergeUnknownFields:(Lcom/google/protobuf/UnknownFieldSet;)Lio/grpc/reflection/v1alpha/ExtensionNumberResponse$Builder;
     117: pop
     118: aload_0
     119: invokevirtual #33                 // Method onChanged:()V
     122: aload_0
     123: areturn

  public final boolean isInitialized();
    Code:
       0: iconst_1
       1: ireturn

  public io.grpc.reflection.v1alpha.ExtensionNumberResponse$Builder mergeFrom(com.google.protobuf.CodedInputStream, com.google.protobuf.ExtensionRegistryLite) throws java.io.IOException;
    Code:
       0: aload_2
       1: ifnonnull     12
       4: new           #40                 // class java/lang/NullPointerException
       7: dup
       8: invokespecial #41                 // Method java/lang/NullPointerException."<init>":()V
      11: athrow
      12: iconst_0
      13: istore_3
      14: iload_3
      15: ifne          184
      18: aload_1
      19: invokevirtual #42                 // Method com/google/protobuf/CodedInputStream.readTag:()I
      22: istore        4
      24: iload         4
      26: lookupswitch  { // 4
                     0: 68
                    10: 73
                    16: 94
                    18: 118
               default: 168
          }
      68: iconst_1
      69: istore_3
      70: goto          181
      73: aload_0
      74: aload_1
      75: invokevirtual #43                 // Method com/google/protobuf/CodedInputStream.readStringRequireUtf8:()Ljava/lang/String;
      78: putfield      #10                 // Field baseTypeName_:Ljava/lang/Object;
      81: aload_0
      82: dup
      83: getfield      #15                 // Field bitField0_:I
      86: iconst_1
      87: ior
      88: putfield      #15                 // Field bitField0_:I
      91: goto          181
      94: aload_1
      95: invokevirtual #44                 // Method com/google/protobuf/CodedInputStream.readInt32:()I
      98: istore        5
     100: aload_0
     101: invokespecial #36                 // Method ensureExtensionNumberIsMutable:()V
     104: aload_0
     105: getfield      #12                 // Field extensionNumber_:Lcom/google/protobuf/Internal$IntList;
     108: iload         5
     110: invokeinterface #45,  2           // InterfaceMethod com/google/protobuf/Internal$IntList.addInt:(I)V
     115: goto          181
     118: aload_1
     119: invokevirtual #46                 // Method com/google/protobuf/CodedInputStream.readRawVarint32:()I
     122: istore        5
     124: aload_1
     125: iload         5
     127: invokevirtual #47                 // Method com/google/protobuf/CodedInputStream.pushLimit:(I)I
     130: istore        6
     132: aload_0
     133: invokespecial #36                 // Method ensureExtensionNumberIsMutable:()V
     136: aload_1
     137: invokevirtual #48                 // Method com/google/protobuf/CodedInputStream.getBytesUntilLimit:()I
     140: ifle          159
     143: aload_0
     144: getfield      #12                 // Field extensionNumber_:Lcom/google/protobuf/Internal$IntList;
     147: aload_1
     148: invokevirtual #44                 // Method com/google/protobuf/CodedInputStream.readInt32:()I
     151: invokeinterface #45,  2           // InterfaceMethod com/google/protobuf/Internal$IntList.addInt:(I)V
     156: goto          136
     159: aload_1
     160: iload         6
     162: invokevirtual #49                 // Method com/google/protobuf/CodedInputStream.popLimit:(I)V
     165: goto          181
     168: aload_0
     169: aload_1
     170: aload_2
     171: iload         4
     173: invokespecial #50                 // Method com/google/protobuf/GeneratedMessageV3$Builder.parseUnknownField:(Lcom/google/protobuf/CodedInputStream;Lcom/google/protobuf/ExtensionRegistryLite;I)Z
     176: ifne          181
     179: iconst_1
     180: istore_3
     181: goto          14
     184: aload_0
     185: invokevirtual #33                 // Method onChanged:()V
     188: goto          206
     191: astore_3
     192: aload_3
     193: invokevirtual #52                 // Method com/google/protobuf/InvalidProtocolBufferException.unwrapIOException:()Ljava/io/IOException;
     196: athrow
     197: astore        7
     199: aload_0
     200: invokevirtual #33                 // Method onChanged:()V
     203: aload         7
     205: athrow
     206: aload_0
     207: areturn
    Exception table:
       from    to  target type
          12   184   191   Class com/google/protobuf/InvalidProtocolBufferException
          12   184   197   any
         191   199   197   any

  public java.lang.String getBaseTypeName();
    Code:
       0: aload_0
       1: getfield      #10                 // Field baseTypeName_:Ljava/lang/Object;
       4: astore_1
       5: aload_1
       6: instanceof    #53                 // class java/lang/String
       9: ifne          29
      12: aload_1
      13: checkcast     #54                 // class com/google/protobuf/ByteString
      16: astore_2
      17: aload_2
      18: invokevirtual #55                 // Method com/google/protobuf/ByteString.toStringUtf8:()Ljava/lang/String;
      21: astore_3
      22: aload_0
      23: aload_3
      24: putfield      #10                 // Field baseTypeName_:Ljava/lang/Object;
      27: aload_3
      28: areturn
      29: aload_1
      30: checkcast     #53                 // class java/lang/String
      33: areturn

  public com.google.protobuf.ByteString getBaseTypeNameBytes();
    Code:
       0: aload_0
       1: getfield      #10                 // Field baseTypeName_:Ljava/lang/Object;
       4: astore_1
       5: aload_1
       6: instanceof    #53                 // class java/lang/String
       9: ifeq          27
      12: aload_1
      13: checkcast     #53                 // class java/lang/String
      16: invokestatic  #56                 // Method com/google/protobuf/ByteString.copyFromUtf8:(Ljava/lang/String;)Lcom/google/protobuf/ByteString;
      19: astore_2
      20: aload_0
      21: aload_2
      22: putfield      #10                 // Field baseTypeName_:Ljava/lang/Object;
      25: aload_2
      26: areturn
      27: aload_1
      28: checkcast     #54                 // class com/google/protobuf/ByteString
      31: areturn

  public io.grpc.reflection.v1alpha.ExtensionNumberResponse$Builder setBaseTypeName(java.lang.String);
    Code:
       0: aload_1
       1: ifnonnull     12
       4: new           #40                 // class java/lang/NullPointerException
       7: dup
       8: invokespecial #41                 // Method java/lang/NullPointerException."<init>":()V
      11: athrow
      12: aload_0
      13: aload_1
      14: putfield      #10                 // Field baseTypeName_:Ljava/lang/Object;
      17: aload_0
      18: dup
      19: getfield      #15                 // Field bitField0_:I
      22: iconst_1
      23: ior
      24: putfield      #15                 // Field bitField0_:I
      27: aload_0
      28: invokevirtual #33                 // Method onChanged:()V
      31: aload_0
      32: areturn

  public io.grpc.reflection.v1alpha.ExtensionNumberResponse$Builder clearBaseTypeName();
    Code:
       0: aload_0
       1: invokestatic  #17                 // Method io/grpc/reflection/v1alpha/ExtensionNumberResponse.getDefaultInstance:()Lio/grpc/reflection/v1alpha/ExtensionNumberResponse;
       4: invokevirtual #30                 // Method io/grpc/reflection/v1alpha/ExtensionNumberResponse.getBaseTypeName:()Ljava/lang/String;
       7: putfield      #10                 // Field baseTypeName_:Ljava/lang/Object;
      10: aload_0
      11: aload_0
      12: getfield      #15                 // Field bitField0_:I
      15: bipush        -2
      17: iand
      18: putfield      #15                 // Field bitField0_:I
      21: aload_0
      22: invokevirtual #33                 // Method onChanged:()V
      25: aload_0
      26: areturn

  public io.grpc.reflection.v1alpha.ExtensionNumberResponse$Builder setBaseTypeNameBytes(com.google.protobuf.ByteString);
    Code:
       0: aload_1
       1: ifnonnull     12
       4: new           #40                 // class java/lang/NullPointerException
       7: dup
       8: invokespecial #41                 // Method java/lang/NullPointerException."<init>":()V
      11: athrow
      12: aload_1
      13: invokestatic  #57                 // Method io/grpc/reflection/v1alpha/ExtensionNumberResponse.access$600:(Lcom/google/protobuf/ByteString;)V
      16: aload_0
      17: aload_1
      18: putfield      #10                 // Field baseTypeName_:Ljava/lang/Object;
      21: aload_0
      22: dup
      23: getfield      #15                 // Field bitField0_:I
      26: iconst_1
      27: ior
      28: putfield      #15                 // Field bitField0_:I
      31: aload_0
      32: invokevirtual #33                 // Method onChanged:()V
      35: aload_0
      36: areturn

  private void ensureExtensionNumberIsMutable();
    Code:
       0: aload_0
       1: getfield      #15                 // Field bitField0_:I
       4: iconst_2
       5: iand
       6: ifne          30
       9: aload_0
      10: aload_0
      11: getfield      #12                 // Field extensionNumber_:Lcom/google/protobuf/Internal$IntList;
      14: invokestatic  #58                 // Method io/grpc/reflection/v1alpha/ExtensionNumberResponse.access$800:(Lcom/google/protobuf/Internal$IntList;)Lcom/google/protobuf/Internal$IntList;
      17: putfield      #12                 // Field extensionNumber_:Lcom/google/protobuf/Internal$IntList;
      20: aload_0
      21: dup
      22: getfield      #15                 // Field bitField0_:I
      25: iconst_2
      26: ior
      27: putfield      #15                 // Field bitField0_:I
      30: return

  public java.util.List<java.lang.Integer> getExtensionNumberList();
    Code:
       0: aload_0
       1: getfield      #15                 // Field bitField0_:I
       4: iconst_2
       5: iand
       6: ifeq          19
       9: aload_0
      10: getfield      #12                 // Field extensionNumber_:Lcom/google/protobuf/Internal$IntList;
      13: invokestatic  #59                 // Method java/util/Collections.unmodifiableList:(Ljava/util/List;)Ljava/util/List;
      16: goto          23
      19: aload_0
      20: getfield      #12                 // Field extensionNumber_:Lcom/google/protobuf/Internal$IntList;
      23: areturn

  public int getExtensionNumberCount();
    Code:
       0: aload_0
       1: getfield      #12                 // Field extensionNumber_:Lcom/google/protobuf/Internal$IntList;
       4: invokeinterface #60,  1           // InterfaceMethod com/google/protobuf/Internal$IntList.size:()I
       9: ireturn

  public int getExtensionNumber(int);
    Code:
       0: aload_0
       1: getfield      #12                 // Field extensionNumber_:Lcom/google/protobuf/Internal$IntList;
       4: iload_1
       5: invokeinterface #61,  2           // InterfaceMethod com/google/protobuf/Internal$IntList.getInt:(I)I
      10: ireturn

  public io.grpc.reflection.v1alpha.ExtensionNumberResponse$Builder setExtensionNumber(int, int);
    Code:
       0: aload_0
       1: invokespecial #36                 // Method ensureExtensionNumberIsMutable:()V
       4: aload_0
       5: getfield      #12                 // Field extensionNumber_:Lcom/google/protobuf/Internal$IntList;
       8: iload_1
       9: iload_2
      10: invokeinterface #62,  3           // InterfaceMethod com/google/protobuf/Internal$IntList.setInt:(II)I
      15: pop
      16: aload_0
      17: invokevirtual #33                 // Method onChanged:()V
      20: aload_0
      21: areturn

  public io.grpc.reflection.v1alpha.ExtensionNumberResponse$Builder addExtensionNumber(int);
    Code:
       0: aload_0
       1: invokespecial #36                 // Method ensureExtensionNumberIsMutable:()V
       4: aload_0
       5: getfield      #12                 // Field extensionNumber_:Lcom/google/protobuf/Internal$IntList;
       8: iload_1
       9: invokeinterface #45,  2           // InterfaceMethod com/google/protobuf/Internal$IntList.addInt:(I)V
      14: aload_0
      15: invokevirtual #33                 // Method onChanged:()V
      18: aload_0
      19: areturn

  public io.grpc.reflection.v1alpha.ExtensionNumberResponse$Builder addAllExtensionNumber(java.lang.Iterable<? extends java.lang.Integer>);
    Code:
       0: aload_0
       1: invokespecial #36                 // Method ensureExtensionNumberIsMutable:()V
       4: aload_1
       5: aload_0
       6: getfield      #12                 // Field extensionNumber_:Lcom/google/protobuf/Internal$IntList;
       9: invokestatic  #63                 // Method com/google/protobuf/AbstractMessageLite$Builder.addAll:(Ljava/lang/Iterable;Ljava/util/List;)V
      12: aload_0
      13: invokevirtual #33                 // Method onChanged:()V
      16: aload_0
      17: areturn

  public io.grpc.reflection.v1alpha.ExtensionNumberResponse$Builder clearExtensionNumber();
    Code:
       0: aload_0
       1: invokestatic  #64                 // Method io/grpc/reflection/v1alpha/ExtensionNumberResponse.access$900:()Lcom/google/protobuf/Internal$IntList;
       4: putfield      #12                 // Field extensionNumber_:Lcom/google/protobuf/Internal$IntList;
       7: aload_0
       8: aload_0
       9: getfield      #15                 // Field bitField0_:I
      12: bipush        -3
      14: iand
      15: putfield      #15                 // Field bitField0_:I
      18: aload_0
      19: invokevirtual #33                 // Method onChanged:()V
      22: aload_0
      23: areturn

  public final io.grpc.reflection.v1alpha.ExtensionNumberResponse$Builder setUnknownFields(com.google.protobuf.UnknownFieldSet);
    Code:
       0: aload_0
       1: aload_1
       2: invokespecial #65                 // Method com/google/protobuf/GeneratedMessageV3$Builder.setUnknownFields:(Lcom/google/protobuf/UnknownFieldSet;)Lcom/google/protobuf/GeneratedMessageV3$Builder;
       5: checkcast     #6                  // class io/grpc/reflection/v1alpha/ExtensionNumberResponse$Builder
       8: areturn

  public final io.grpc.reflection.v1alpha.ExtensionNumberResponse$Builder mergeUnknownFields(com.google.protobuf.UnknownFieldSet);
    Code:
       0: aload_0
       1: aload_1
       2: invokespecial #66                 // Method com/google/protobuf/GeneratedMessageV3$Builder.mergeUnknownFields:(Lcom/google/protobuf/UnknownFieldSet;)Lcom/google/protobuf/GeneratedMessageV3$Builder;
       5: checkcast     #6                  // class io/grpc/reflection/v1alpha/ExtensionNumberResponse$Builder
       8: areturn

  public com.google.protobuf.GeneratedMessageV3$Builder mergeUnknownFields(com.google.protobuf.UnknownFieldSet);
    Code:
       0: aload_0
       1: aload_1
       2: invokevirtual #39                 // Method mergeUnknownFields:(Lcom/google/protobuf/UnknownFieldSet;)Lio/grpc/reflection/v1alpha/ExtensionNumberResponse$Builder;
       5: areturn

  public com.google.protobuf.GeneratedMessageV3$Builder setUnknownFields(com.google.protobuf.UnknownFieldSet);
    Code:
       0: aload_0
       1: aload_1
       2: invokevirtual #67                 // Method setUnknownFields:(Lcom/google/protobuf/UnknownFieldSet;)Lio/grpc/reflection/v1alpha/ExtensionNumberResponse$Builder;
       5: areturn

  public com.google.protobuf.GeneratedMessageV3$Builder clear();
    Code:
       0: aload_0
       1: invokevirtual #68                 // Method clear:()Lio/grpc/reflection/v1alpha/ExtensionNumberResponse$Builder;
       4: areturn

  public com.google.protobuf.AbstractMessage$Builder mergeUnknownFields(com.google.protobuf.UnknownFieldSet);
    Code:
       0: aload_0
       1: aload_1
       2: invokevirtual #39                 // Method mergeUnknownFields:(Lcom/google/protobuf/UnknownFieldSet;)Lio/grpc/reflection/v1alpha/ExtensionNumberResponse$Builder;
       5: areturn

  public com.google.protobuf.AbstractMessage$Builder mergeFrom(com.google.protobuf.CodedInputStream, com.google.protobuf.ExtensionRegistryLite) throws java.io.IOException;
    Code:
       0: aload_0
       1: aload_1
       2: aload_2
       3: invokevirtual #69                 // Method mergeFrom:(Lcom/google/protobuf/CodedInputStream;Lcom/google/protobuf/ExtensionRegistryLite;)Lio/grpc/reflection/v1alpha/ExtensionNumberResponse$Builder;
       6: areturn

  public com.google.protobuf.AbstractMessage$Builder mergeFrom(com.google.protobuf.Message);
    Code:
       0: aload_0
       1: aload_1
       2: invokevirtual #70                 // Method mergeFrom:(Lcom/google/protobuf/Message;)Lio/grpc/reflection/v1alpha/ExtensionNumberResponse$Builder;
       5: areturn

  public com.google.protobuf.AbstractMessage$Builder clear();
    Code:
       0: aload_0
       1: invokevirtual #68                 // Method clear:()Lio/grpc/reflection/v1alpha/ExtensionNumberResponse$Builder;
       4: areturn

  public com.google.protobuf.Message$Builder mergeUnknownFields(com.google.protobuf.UnknownFieldSet);
    Code:
       0: aload_0
       1: aload_1
       2: invokevirtual #39                 // Method mergeUnknownFields:(Lcom/google/protobuf/UnknownFieldSet;)Lio/grpc/reflection/v1alpha/ExtensionNumberResponse$Builder;
       5: areturn

  public com.google.protobuf.Message$Builder setUnknownFields(com.google.protobuf.UnknownFieldSet);
    Code:
       0: aload_0
       1: aload_1
       2: invokevirtual #67                 // Method setUnknownFields:(Lcom/google/protobuf/UnknownFieldSet;)Lio/grpc/reflection/v1alpha/ExtensionNumberResponse$Builder;
       5: areturn

  public com.google.protobuf.Message$Builder mergeFrom(com.google.protobuf.CodedInputStream, com.google.protobuf.ExtensionRegistryLite) throws java.io.IOException;
    Code:
       0: aload_0
       1: aload_1
       2: aload_2
       3: invokevirtual #69                 // Method mergeFrom:(Lcom/google/protobuf/CodedInputStream;Lcom/google/protobuf/ExtensionRegistryLite;)Lio/grpc/reflection/v1alpha/ExtensionNumberResponse$Builder;
       6: areturn

  public com.google.protobuf.Message buildPartial();
    Code:
       0: aload_0
       1: invokevirtual #18                 // Method buildPartial:()Lio/grpc/reflection/v1alpha/ExtensionNumberResponse;
       4: areturn

  public com.google.protobuf.Message build();
    Code:
       0: aload_0
       1: invokevirtual #71                 // Method build:()Lio/grpc/reflection/v1alpha/ExtensionNumberResponse;
       4: areturn

  public com.google.protobuf.Message$Builder mergeFrom(com.google.protobuf.Message);
    Code:
       0: aload_0
       1: aload_1
       2: invokevirtual #70                 // Method mergeFrom:(Lcom/google/protobuf/Message;)Lio/grpc/reflection/v1alpha/ExtensionNumberResponse$Builder;
       5: areturn

  public com.google.protobuf.Message$Builder clear();
    Code:
       0: aload_0
       1: invokevirtual #68                 // Method clear:()Lio/grpc/reflection/v1alpha/ExtensionNumberResponse$Builder;
       4: areturn

  public com.google.protobuf.MessageLite$Builder mergeFrom(com.google.protobuf.CodedInputStream, com.google.protobuf.ExtensionRegistryLite) throws java.io.IOException;
    Code:
       0: aload_0
       1: aload_1
       2: aload_2
       3: invokevirtual #69                 // Method mergeFrom:(Lcom/google/protobuf/CodedInputStream;Lcom/google/protobuf/ExtensionRegistryLite;)Lio/grpc/reflection/v1alpha/ExtensionNumberResponse$Builder;
       6: areturn

  public com.google.protobuf.MessageLite buildPartial();
    Code:
       0: aload_0
       1: invokevirtual #18                 // Method buildPartial:()Lio/grpc/reflection/v1alpha/ExtensionNumberResponse;
       4: areturn

  public com.google.protobuf.MessageLite build();
    Code:
       0: aload_0
       1: invokevirtual #71                 // Method build:()Lio/grpc/reflection/v1alpha/ExtensionNumberResponse;
       4: areturn

  public com.google.protobuf.MessageLite$Builder clear();
    Code:
       0: aload_0
       1: invokevirtual #68                 // Method clear:()Lio/grpc/reflection/v1alpha/ExtensionNumberResponse$Builder;
       4: areturn

  public com.google.protobuf.MessageLite getDefaultInstanceForType();
    Code:
       0: aload_0
       1: invokevirtual #72                 // Method getDefaultInstanceForType:()Lio/grpc/reflection/v1alpha/ExtensionNumberResponse;
       4: areturn

  public com.google.protobuf.Message getDefaultInstanceForType();
    Code:
       0: aload_0
       1: invokevirtual #72                 // Method getDefaultInstanceForType:()Lio/grpc/reflection/v1alpha/ExtensionNumberResponse;
       4: areturn

  public com.google.protobuf.AbstractMessageLite$Builder mergeFrom(com.google.protobuf.CodedInputStream, com.google.protobuf.ExtensionRegistryLite) throws java.io.IOException;
    Code:
       0: aload_0
       1: aload_1
       2: aload_2
       3: invokevirtual #69                 // Method mergeFrom:(Lcom/google/protobuf/CodedInputStream;Lcom/google/protobuf/ExtensionRegistryLite;)Lio/grpc/reflection/v1alpha/ExtensionNumberResponse$Builder;
       6: areturn

  io.grpc.reflection.v1alpha.ExtensionNumberResponse$Builder(io.grpc.reflection.v1alpha.ExtensionNumberResponse$1);
    Code:
       0: aload_0
       1: invokespecial #2                  // Method "<init>":()V
       4: return

  io.grpc.reflection.v1alpha.ExtensionNumberResponse$Builder(com.google.protobuf.GeneratedMessageV3$BuilderParent, io.grpc.reflection.v1alpha.ExtensionNumberResponse$1);
    Code:
       0: aload_0
       1: aload_1
       2: invokespecial #1                  // Method "<init>":(Lcom/google/protobuf/GeneratedMessageV3$BuilderParent;)V
       5: return
}
