Compiled from "FileDescriptorResponse.java"
public final class io.grpc.reflection.v1alpha.FileDescriptorResponse$Builder extends com.google.protobuf.GeneratedMessageV3$Builder<io.grpc.reflection.v1alpha.FileDescriptorResponse$Builder> implements io.grpc.reflection.v1alpha.FileDescriptorResponseOrBuilder {
  private int bitField0_;

  private java.util.List<com.google.protobuf.ByteString> fileDescriptorProto_;

  public static final com.google.protobuf.Descriptors$Descriptor getDescriptor();
    Code:
       0: getstatic     #3                  // Field io/grpc/reflection/v1alpha/ServerReflectionProto.internal_static_grpc_reflection_v1alpha_FileDescriptorResponse_descriptor:Lcom/google/protobuf/Descriptors$Descriptor;
       3: areturn

  protected com.google.protobuf.GeneratedMessageV3$FieldAccessorTable internalGetFieldAccessorTable();
    Code:
       0: getstatic     #4                  // Field io/grpc/reflection/v1alpha/ServerReflectionProto.internal_static_grpc_reflection_v1alpha_FileDescriptorResponse_fieldAccessorTable:Lcom/google/protobuf/GeneratedMessageV3$FieldAccessorTable;
       3: ldc           #5                  // class io/grpc/reflection/v1alpha/FileDescriptorResponse
       5: ldc           #6                  // class io/grpc/reflection/v1alpha/FileDescriptorResponse$Builder
       7: invokevirtual #7                  // Method com/google/protobuf/GeneratedMessageV3$FieldAccessorTable.ensureFieldAccessorsInitialized:(Ljava/lang/Class;Ljava/lang/Class;)Lcom/google/protobuf/GeneratedMessageV3$FieldAccessorTable;
      10: areturn

  private io.grpc.reflection.v1alpha.FileDescriptorResponse$Builder();
    Code:
       0: aload_0
       1: invokespecial #8                  // Method com/google/protobuf/GeneratedMessageV3$Builder."<init>":()V
       4: aload_0
       5: invokestatic  #9                  // Method java/util/Collections.emptyList:()Ljava/util/List;
       8: putfield      #10                 // Field fileDescriptorProto_:Ljava/util/List;
      11: return

  private io.grpc.reflection.v1alpha.FileDescriptorResponse$Builder(com.google.protobuf.GeneratedMessageV3$BuilderParent);
    Code:
       0: aload_0
       1: aload_1
       2: invokespecial #11                 // Method com/google/protobuf/GeneratedMessageV3$Builder."<init>":(Lcom/google/protobuf/GeneratedMessageV3$BuilderParent;)V
       5: aload_0
       6: invokestatic  #9                  // Method java/util/Collections.emptyList:()Ljava/util/List;
       9: putfield      #10                 // Field fileDescriptorProto_:Ljava/util/List;
      12: return

  public io.grpc.reflection.v1alpha.FileDescriptorResponse$Builder clear();
    Code:
       0: aload_0
       1: invokespecial #12                 // Method com/google/protobuf/GeneratedMessageV3$Builder.clear:()Lcom/google/protobuf/GeneratedMessageV3$Builder;
       4: pop
       5: aload_0
       6: iconst_0
       7: putfield      #13                 // Field bitField0_:I
      10: aload_0
      11: invokestatic  #9                  // Method java/util/Collections.emptyList:()Ljava/util/List;
      14: putfield      #10                 // Field fileDescriptorProto_:Ljava/util/List;
      17: aload_0
      18: areturn

  public com.google.protobuf.Descriptors$Descriptor getDescriptorForType();
    Code:
       0: getstatic     #3                  // Field io/grpc/reflection/v1alpha/ServerReflectionProto.internal_static_grpc_reflection_v1alpha_FileDescriptorResponse_descriptor:Lcom/google/protobuf/Descriptors$Descriptor;
       3: areturn

  public io.grpc.reflection.v1alpha.FileDescriptorResponse getDefaultInstanceForType();
    Code:
       0: invokestatic  #14                 // Method io/grpc/reflection/v1alpha/FileDescriptorResponse.getDefaultInstance:()Lio/grpc/reflection/v1alpha/FileDescriptorResponse;
       3: areturn

  public io.grpc.reflection.v1alpha.FileDescriptorResponse build();
    Code:
       0: aload_0
       1: invokevirtual #15                 // Method buildPartial:()Lio/grpc/reflection/v1alpha/FileDescriptorResponse;
       4: astore_1
       5: aload_1
       6: invokevirtual #16                 // Method io/grpc/reflection/v1alpha/FileDescriptorResponse.isInitialized:()Z
       9: ifne          17
      12: aload_1
      13: invokestatic  #17                 // Method newUninitializedMessageException:(Lcom/google/protobuf/Message;)Lcom/google/protobuf/UninitializedMessageException;
      16: athrow
      17: aload_1
      18: areturn

  public io.grpc.reflection.v1alpha.FileDescriptorResponse buildPartial();
    Code:
       0: new           #5                  // class io/grpc/reflection/v1alpha/FileDescriptorResponse
       3: dup
       4: aload_0
       5: aconst_null
       6: invokespecial #18                 // Method io/grpc/reflection/v1alpha/FileDescriptorResponse."<init>":(Lcom/google/protobuf/GeneratedMessageV3$Builder;Lio/grpc/reflection/v1alpha/FileDescriptorResponse$1;)V
       9: astore_1
      10: aload_0
      11: aload_1
      12: invokespecial #19                 // Method buildPartialRepeatedFields:(Lio/grpc/reflection/v1alpha/FileDescriptorResponse;)V
      15: aload_0
      16: getfield      #13                 // Field bitField0_:I
      19: ifeq          27
      22: aload_0
      23: aload_1
      24: invokespecial #20                 // Method buildPartial0:(Lio/grpc/reflection/v1alpha/FileDescriptorResponse;)V
      27: aload_0
      28: invokevirtual #21                 // Method onBuilt:()V
      31: aload_1
      32: areturn

  private void buildPartialRepeatedFields(io.grpc.reflection.v1alpha.FileDescriptorResponse);
    Code:
       0: aload_0
       1: getfield      #13                 // Field bitField0_:I
       4: iconst_1
       5: iand
       6: ifeq          31
       9: aload_0
      10: aload_0
      11: getfield      #10                 // Field fileDescriptorProto_:Ljava/util/List;
      14: invokestatic  #22                 // Method java/util/Collections.unmodifiableList:(Ljava/util/List;)Ljava/util/List;
      17: putfield      #10                 // Field fileDescriptorProto_:Ljava/util/List;
      20: aload_0
      21: aload_0
      22: getfield      #13                 // Field bitField0_:I
      25: bipush        -2
      27: iand
      28: putfield      #13                 // Field bitField0_:I
      31: aload_1
      32: aload_0
      33: getfield      #10                 // Field fileDescriptorProto_:Ljava/util/List;
      36: invokestatic  #23                 // Method io/grpc/reflection/v1alpha/FileDescriptorResponse.access$302:(Lio/grpc/reflection/v1alpha/FileDescriptorResponse;Ljava/util/List;)Ljava/util/List;
      39: pop
      40: return

  private void buildPartial0(io.grpc.reflection.v1alpha.FileDescriptorResponse);
    Code:
       0: aload_0
       1: getfield      #13                 // Field bitField0_:I
       4: istore_2
       5: return

  public io.grpc.reflection.v1alpha.FileDescriptorResponse$Builder mergeFrom(com.google.protobuf.Message);
    Code:
       0: aload_1
       1: instanceof    #5                  // class io/grpc/reflection/v1alpha/FileDescriptorResponse
       4: ifeq          16
       7: aload_0
       8: aload_1
       9: checkcast     #5                  // class io/grpc/reflection/v1alpha/FileDescriptorResponse
      12: invokevirtual #24                 // Method mergeFrom:(Lio/grpc/reflection/v1alpha/FileDescriptorResponse;)Lio/grpc/reflection/v1alpha/FileDescriptorResponse$Builder;
      15: areturn
      16: aload_0
      17: aload_1
      18: invokespecial #25                 // Method com/google/protobuf/GeneratedMessageV3$Builder.mergeFrom:(Lcom/google/protobuf/Message;)Lcom/google/protobuf/AbstractMessage$Builder;
      21: pop
      22: aload_0
      23: areturn

  public io.grpc.reflection.v1alpha.FileDescriptorResponse$Builder mergeFrom(io.grpc.reflection.v1alpha.FileDescriptorResponse);
    Code:
       0: aload_1
       1: invokestatic  #14                 // Method io/grpc/reflection/v1alpha/FileDescriptorResponse.getDefaultInstance:()Lio/grpc/reflection/v1alpha/FileDescriptorResponse;
       4: if_acmpne     9
       7: aload_0
       8: areturn
       9: aload_1
      10: invokestatic  #26                 // Method io/grpc/reflection/v1alpha/FileDescriptorResponse.access$300:(Lio/grpc/reflection/v1alpha/FileDescriptorResponse;)Ljava/util/List;
      13: invokeinterface #27,  1           // InterfaceMethod java/util/List.isEmpty:()Z
      18: ifne          77
      21: aload_0
      22: getfield      #10                 // Field fileDescriptorProto_:Ljava/util/List;
      25: invokeinterface #27,  1           // InterfaceMethod java/util/List.isEmpty:()Z
      30: ifeq          55
      33: aload_0
      34: aload_1
      35: invokestatic  #26                 // Method io/grpc/reflection/v1alpha/FileDescriptorResponse.access$300:(Lio/grpc/reflection/v1alpha/FileDescriptorResponse;)Ljava/util/List;
      38: putfield      #10                 // Field fileDescriptorProto_:Ljava/util/List;
      41: aload_0
      42: aload_0
      43: getfield      #13                 // Field bitField0_:I
      46: bipush        -2
      48: iand
      49: putfield      #13                 // Field bitField0_:I
      52: goto          73
      55: aload_0
      56: invokespecial #28                 // Method ensureFileDescriptorProtoIsMutable:()V
      59: aload_0
      60: getfield      #10                 // Field fileDescriptorProto_:Ljava/util/List;
      63: aload_1
      64: invokestatic  #26                 // Method io/grpc/reflection/v1alpha/FileDescriptorResponse.access$300:(Lio/grpc/reflection/v1alpha/FileDescriptorResponse;)Ljava/util/List;
      67: invokeinterface #29,  2           // InterfaceMethod java/util/List.addAll:(Ljava/util/Collection;)Z
      72: pop
      73: aload_0
      74: invokevirtual #30                 // Method onChanged:()V
      77: aload_0
      78: aload_1
      79: invokevirtual #31                 // Method io/grpc/reflection/v1alpha/FileDescriptorResponse.getUnknownFields:()Lcom/google/protobuf/UnknownFieldSet;
      82: invokevirtual #32                 // Method mergeUnknownFields:(Lcom/google/protobuf/UnknownFieldSet;)Lio/grpc/reflection/v1alpha/FileDescriptorResponse$Builder;
      85: pop
      86: aload_0
      87: invokevirtual #30                 // Method onChanged:()V
      90: aload_0
      91: areturn

  public final boolean isInitialized();
    Code:
       0: iconst_1
       1: ireturn

  public io.grpc.reflection.v1alpha.FileDescriptorResponse$Builder mergeFrom(com.google.protobuf.CodedInputStream, com.google.protobuf.ExtensionRegistryLite) throws java.io.IOException;
    Code:
       0: aload_2
       1: ifnonnull     12
       4: new           #33                 // class java/lang/NullPointerException
       7: dup
       8: invokespecial #34                 // Method java/lang/NullPointerException."<init>":()V
      11: athrow
      12: iconst_0
      13: istore_3
      14: iload_3
      15: ifne          98
      18: aload_1
      19: invokevirtual #35                 // Method com/google/protobuf/CodedInputStream.readTag:()I
      22: istore        4
      24: iload         4
      26: lookupswitch  { // 2
                     0: 52
                    10: 57
               default: 82
          }
      52: iconst_1
      53: istore_3
      54: goto          95
      57: aload_1
      58: invokevirtual #36                 // Method com/google/protobuf/CodedInputStream.readBytes:()Lcom/google/protobuf/ByteString;
      61: astore        5
      63: aload_0
      64: invokespecial #28                 // Method ensureFileDescriptorProtoIsMutable:()V
      67: aload_0
      68: getfield      #10                 // Field fileDescriptorProto_:Ljava/util/List;
      71: aload         5
      73: invokeinterface #37,  2           // InterfaceMethod java/util/List.add:(Ljava/lang/Object;)Z
      78: pop
      79: goto          95
      82: aload_0
      83: aload_1
      84: aload_2
      85: iload         4
      87: invokespecial #38                 // Method com/google/protobuf/GeneratedMessageV3$Builder.parseUnknownField:(Lcom/google/protobuf/CodedInputStream;Lcom/google/protobuf/ExtensionRegistryLite;I)Z
      90: ifne          95
      93: iconst_1
      94: istore_3
      95: goto          14
      98: aload_0
      99: invokevirtual #30                 // Method onChanged:()V
     102: goto          120
     105: astore_3
     106: aload_3
     107: invokevirtual #40                 // Method com/google/protobuf/InvalidProtocolBufferException.unwrapIOException:()Ljava/io/IOException;
     110: athrow
     111: astore        6
     113: aload_0
     114: invokevirtual #30                 // Method onChanged:()V
     117: aload         6
     119: athrow
     120: aload_0
     121: areturn
    Exception table:
       from    to  target type
          12    98   105   Class com/google/protobuf/InvalidProtocolBufferException
          12    98   111   any
         105   113   111   any

  private void ensureFileDescriptorProtoIsMutable();
    Code:
       0: aload_0
       1: getfield      #13                 // Field bitField0_:I
       4: iconst_1
       5: iand
       6: ifne          34
       9: aload_0
      10: new           #41                 // class java/util/ArrayList
      13: dup
      14: aload_0
      15: getfield      #10                 // Field fileDescriptorProto_:Ljava/util/List;
      18: invokespecial #42                 // Method java/util/ArrayList."<init>":(Ljava/util/Collection;)V
      21: putfield      #10                 // Field fileDescriptorProto_:Ljava/util/List;
      24: aload_0
      25: dup
      26: getfield      #13                 // Field bitField0_:I
      29: iconst_1
      30: ior
      31: putfield      #13                 // Field bitField0_:I
      34: return

  public java.util.List<com.google.protobuf.ByteString> getFileDescriptorProtoList();
    Code:
       0: aload_0
       1: getfield      #13                 // Field bitField0_:I
       4: iconst_1
       5: iand
       6: ifeq          19
       9: aload_0
      10: getfield      #10                 // Field fileDescriptorProto_:Ljava/util/List;
      13: invokestatic  #22                 // Method java/util/Collections.unmodifiableList:(Ljava/util/List;)Ljava/util/List;
      16: goto          23
      19: aload_0
      20: getfield      #10                 // Field fileDescriptorProto_:Ljava/util/List;
      23: areturn

  public int getFileDescriptorProtoCount();
    Code:
       0: aload_0
       1: getfield      #10                 // Field fileDescriptorProto_:Ljava/util/List;
       4: invokeinterface #43,  1           // InterfaceMethod java/util/List.size:()I
       9: ireturn

  public com.google.protobuf.ByteString getFileDescriptorProto(int);
    Code:
       0: aload_0
       1: getfield      #10                 // Field fileDescriptorProto_:Ljava/util/List;
       4: iload_1
       5: invokeinterface #44,  2           // InterfaceMethod java/util/List.get:(I)Ljava/lang/Object;
      10: checkcast     #45                 // class com/google/protobuf/ByteString
      13: areturn

  public io.grpc.reflection.v1alpha.FileDescriptorResponse$Builder setFileDescriptorProto(int, com.google.protobuf.ByteString);
    Code:
       0: aload_2
       1: ifnonnull     12
       4: new           #33                 // class java/lang/NullPointerException
       7: dup
       8: invokespecial #34                 // Method java/lang/NullPointerException."<init>":()V
      11: athrow
      12: aload_0
      13: invokespecial #28                 // Method ensureFileDescriptorProtoIsMutable:()V
      16: aload_0
      17: getfield      #10                 // Field fileDescriptorProto_:Ljava/util/List;
      20: iload_1
      21: aload_2
      22: invokeinterface #46,  3           // InterfaceMethod java/util/List.set:(ILjava/lang/Object;)Ljava/lang/Object;
      27: pop
      28: aload_0
      29: invokevirtual #30                 // Method onChanged:()V
      32: aload_0
      33: areturn

  public io.grpc.reflection.v1alpha.FileDescriptorResponse$Builder addFileDescriptorProto(com.google.protobuf.ByteString);
    Code:
       0: aload_1
       1: ifnonnull     12
       4: new           #33                 // class java/lang/NullPointerException
       7: dup
       8: invokespecial #34                 // Method java/lang/NullPointerException."<init>":()V
      11: athrow
      12: aload_0
      13: invokespecial #28                 // Method ensureFileDescriptorProtoIsMutable:()V
      16: aload_0
      17: getfield      #10                 // Field fileDescriptorProto_:Ljava/util/List;
      20: aload_1
      21: invokeinterface #37,  2           // InterfaceMethod java/util/List.add:(Ljava/lang/Object;)Z
      26: pop
      27: aload_0
      28: invokevirtual #30                 // Method onChanged:()V
      31: aload_0
      32: areturn

  public io.grpc.reflection.v1alpha.FileDescriptorResponse$Builder addAllFileDescriptorProto(java.lang.Iterable<? extends com.google.protobuf.ByteString>);
    Code:
       0: aload_0
       1: invokespecial #28                 // Method ensureFileDescriptorProtoIsMutable:()V
       4: aload_1
       5: aload_0
       6: getfield      #10                 // Field fileDescriptorProto_:Ljava/util/List;
       9: invokestatic  #47                 // Method com/google/protobuf/AbstractMessageLite$Builder.addAll:(Ljava/lang/Iterable;Ljava/util/List;)V
      12: aload_0
      13: invokevirtual #30                 // Method onChanged:()V
      16: aload_0
      17: areturn

  public io.grpc.reflection.v1alpha.FileDescriptorResponse$Builder clearFileDescriptorProto();
    Code:
       0: aload_0
       1: invokestatic  #9                  // Method java/util/Collections.emptyList:()Ljava/util/List;
       4: putfield      #10                 // Field fileDescriptorProto_:Ljava/util/List;
       7: aload_0
       8: aload_0
       9: getfield      #13                 // Field bitField0_:I
      12: bipush        -2
      14: iand
      15: putfield      #13                 // Field bitField0_:I
      18: aload_0
      19: invokevirtual #30                 // Method onChanged:()V
      22: aload_0
      23: areturn

  public final io.grpc.reflection.v1alpha.FileDescriptorResponse$Builder setUnknownFields(com.google.protobuf.UnknownFieldSet);
    Code:
       0: aload_0
       1: aload_1
       2: invokespecial #48                 // Method com/google/protobuf/GeneratedMessageV3$Builder.setUnknownFields:(Lcom/google/protobuf/UnknownFieldSet;)Lcom/google/protobuf/GeneratedMessageV3$Builder;
       5: checkcast     #6                  // class io/grpc/reflection/v1alpha/FileDescriptorResponse$Builder
       8: areturn

  public final io.grpc.reflection.v1alpha.FileDescriptorResponse$Builder mergeUnknownFields(com.google.protobuf.UnknownFieldSet);
    Code:
       0: aload_0
       1: aload_1
       2: invokespecial #49                 // Method com/google/protobuf/GeneratedMessageV3$Builder.mergeUnknownFields:(Lcom/google/protobuf/UnknownFieldSet;)Lcom/google/protobuf/GeneratedMessageV3$Builder;
       5: checkcast     #6                  // class io/grpc/reflection/v1alpha/FileDescriptorResponse$Builder
       8: areturn

  public com.google.protobuf.GeneratedMessageV3$Builder mergeUnknownFields(com.google.protobuf.UnknownFieldSet);
    Code:
       0: aload_0
       1: aload_1
       2: invokevirtual #32                 // Method mergeUnknownFields:(Lcom/google/protobuf/UnknownFieldSet;)Lio/grpc/reflection/v1alpha/FileDescriptorResponse$Builder;
       5: areturn

  public com.google.protobuf.GeneratedMessageV3$Builder setUnknownFields(com.google.protobuf.UnknownFieldSet);
    Code:
       0: aload_0
       1: aload_1
       2: invokevirtual #50                 // Method setUnknownFields:(Lcom/google/protobuf/UnknownFieldSet;)Lio/grpc/reflection/v1alpha/FileDescriptorResponse$Builder;
       5: areturn

  public com.google.protobuf.GeneratedMessageV3$Builder clear();
    Code:
       0: aload_0
       1: invokevirtual #51                 // Method clear:()Lio/grpc/reflection/v1alpha/FileDescriptorResponse$Builder;
       4: areturn

  public com.google.protobuf.AbstractMessage$Builder mergeUnknownFields(com.google.protobuf.UnknownFieldSet);
    Code:
       0: aload_0
       1: aload_1
       2: invokevirtual #32                 // Method mergeUnknownFields:(Lcom/google/protobuf/UnknownFieldSet;)Lio/grpc/reflection/v1alpha/FileDescriptorResponse$Builder;
       5: areturn

  public com.google.protobuf.AbstractMessage$Builder mergeFrom(com.google.protobuf.CodedInputStream, com.google.protobuf.ExtensionRegistryLite) throws java.io.IOException;
    Code:
       0: aload_0
       1: aload_1
       2: aload_2
       3: invokevirtual #52                 // Method mergeFrom:(Lcom/google/protobuf/CodedInputStream;Lcom/google/protobuf/ExtensionRegistryLite;)Lio/grpc/reflection/v1alpha/FileDescriptorResponse$Builder;
       6: areturn

  public com.google.protobuf.AbstractMessage$Builder mergeFrom(com.google.protobuf.Message);
    Code:
       0: aload_0
       1: aload_1
       2: invokevirtual #53                 // Method mergeFrom:(Lcom/google/protobuf/Message;)Lio/grpc/reflection/v1alpha/FileDescriptorResponse$Builder;
       5: areturn

  public com.google.protobuf.AbstractMessage$Builder clear();
    Code:
       0: aload_0
       1: invokevirtual #51                 // Method clear:()Lio/grpc/reflection/v1alpha/FileDescriptorResponse$Builder;
       4: areturn

  public com.google.protobuf.Message$Builder mergeUnknownFields(com.google.protobuf.UnknownFieldSet);
    Code:
       0: aload_0
       1: aload_1
       2: invokevirtual #32                 // Method mergeUnknownFields:(Lcom/google/protobuf/UnknownFieldSet;)Lio/grpc/reflection/v1alpha/FileDescriptorResponse$Builder;
       5: areturn

  public com.google.protobuf.Message$Builder setUnknownFields(com.google.protobuf.UnknownFieldSet);
    Code:
       0: aload_0
       1: aload_1
       2: invokevirtual #50                 // Method setUnknownFields:(Lcom/google/protobuf/UnknownFieldSet;)Lio/grpc/reflection/v1alpha/FileDescriptorResponse$Builder;
       5: areturn

  public com.google.protobuf.Message$Builder mergeFrom(com.google.protobuf.CodedInputStream, com.google.protobuf.ExtensionRegistryLite) throws java.io.IOException;
    Code:
       0: aload_0
       1: aload_1
       2: aload_2
       3: invokevirtual #52                 // Method mergeFrom:(Lcom/google/protobuf/CodedInputStream;Lcom/google/protobuf/ExtensionRegistryLite;)Lio/grpc/reflection/v1alpha/FileDescriptorResponse$Builder;
       6: areturn

  public com.google.protobuf.Message buildPartial();
    Code:
       0: aload_0
       1: invokevirtual #15                 // Method buildPartial:()Lio/grpc/reflection/v1alpha/FileDescriptorResponse;
       4: areturn

  public com.google.protobuf.Message build();
    Code:
       0: aload_0
       1: invokevirtual #54                 // Method build:()Lio/grpc/reflection/v1alpha/FileDescriptorResponse;
       4: areturn

  public com.google.protobuf.Message$Builder mergeFrom(com.google.protobuf.Message);
    Code:
       0: aload_0
       1: aload_1
       2: invokevirtual #53                 // Method mergeFrom:(Lcom/google/protobuf/Message;)Lio/grpc/reflection/v1alpha/FileDescriptorResponse$Builder;
       5: areturn

  public com.google.protobuf.Message$Builder clear();
    Code:
       0: aload_0
       1: invokevirtual #51                 // Method clear:()Lio/grpc/reflection/v1alpha/FileDescriptorResponse$Builder;
       4: areturn

  public com.google.protobuf.MessageLite$Builder mergeFrom(com.google.protobuf.CodedInputStream, com.google.protobuf.ExtensionRegistryLite) throws java.io.IOException;
    Code:
       0: aload_0
       1: aload_1
       2: aload_2
       3: invokevirtual #52                 // Method mergeFrom:(Lcom/google/protobuf/CodedInputStream;Lcom/google/protobuf/ExtensionRegistryLite;)Lio/grpc/reflection/v1alpha/FileDescriptorResponse$Builder;
       6: areturn

  public com.google.protobuf.MessageLite buildPartial();
    Code:
       0: aload_0
       1: invokevirtual #15                 // Method buildPartial:()Lio/grpc/reflection/v1alpha/FileDescriptorResponse;
       4: areturn

  public com.google.protobuf.MessageLite build();
    Code:
       0: aload_0
       1: invokevirtual #54                 // Method build:()Lio/grpc/reflection/v1alpha/FileDescriptorResponse;
       4: areturn

  public com.google.protobuf.MessageLite$Builder clear();
    Code:
       0: aload_0
       1: invokevirtual #51                 // Method clear:()Lio/grpc/reflection/v1alpha/FileDescriptorResponse$Builder;
       4: areturn

  public com.google.protobuf.MessageLite getDefaultInstanceForType();
    Code:
       0: aload_0
       1: invokevirtual #55                 // Method getDefaultInstanceForType:()Lio/grpc/reflection/v1alpha/FileDescriptorResponse;
       4: areturn

  public com.google.protobuf.Message getDefaultInstanceForType();
    Code:
       0: aload_0
       1: invokevirtual #55                 // Method getDefaultInstanceForType:()Lio/grpc/reflection/v1alpha/FileDescriptorResponse;
       4: areturn

  public com.google.protobuf.AbstractMessageLite$Builder mergeFrom(com.google.protobuf.CodedInputStream, com.google.protobuf.ExtensionRegistryLite) throws java.io.IOException;
    Code:
       0: aload_0
       1: aload_1
       2: aload_2
       3: invokevirtual #52                 // Method mergeFrom:(Lcom/google/protobuf/CodedInputStream;Lcom/google/protobuf/ExtensionRegistryLite;)Lio/grpc/reflection/v1alpha/FileDescriptorResponse$Builder;
       6: areturn

  io.grpc.reflection.v1alpha.FileDescriptorResponse$Builder(io.grpc.reflection.v1alpha.FileDescriptorResponse$1);
    Code:
       0: aload_0
       1: invokespecial #2                  // Method "<init>":()V
       4: return

  io.grpc.reflection.v1alpha.FileDescriptorResponse$Builder(com.google.protobuf.GeneratedMessageV3$BuilderParent, io.grpc.reflection.v1alpha.FileDescriptorResponse$1);
    Code:
       0: aload_0
       1: aload_1
       2: invokespecial #1                  // Method "<init>":(Lcom/google/protobuf/GeneratedMessageV3$BuilderParent;)V
       5: return
}
