Compiled from "ListServiceResponse.java"
public final class io.grpc.reflection.v1alpha.ListServiceResponse$Builder extends com.google.protobuf.GeneratedMessageV3$Builder<io.grpc.reflection.v1alpha.ListServiceResponse$Builder> implements io.grpc.reflection.v1alpha.ListServiceResponseOrBuilder {
  private int bitField0_;

  private java.util.List<io.grpc.reflection.v1alpha.ServiceResponse> service_;

  private com.google.protobuf.RepeatedFieldBuilderV3<io.grpc.reflection.v1alpha.ServiceResponse, io.grpc.reflection.v1alpha.ServiceResponse$Builder, io.grpc.reflection.v1alpha.ServiceResponseOrBuilder> serviceBuilder_;

  public static final com.google.protobuf.Descriptors$Descriptor getDescriptor();
    Code:
       0: getstatic     #3                  // Field io/grpc/reflection/v1alpha/ServerReflectionProto.internal_static_grpc_reflection_v1alpha_ListServiceResponse_descriptor:Lcom/google/protobuf/Descriptors$Descriptor;
       3: areturn

  protected com.google.protobuf.GeneratedMessageV3$FieldAccessorTable internalGetFieldAccessorTable();
    Code:
       0: getstatic     #4                  // Field io/grpc/reflection/v1alpha/ServerReflectionProto.internal_static_grpc_reflection_v1alpha_ListServiceResponse_fieldAccessorTable:Lcom/google/protobuf/GeneratedMessageV3$FieldAccessorTable;
       3: ldc           #5                  // class io/grpc/reflection/v1alpha/ListServiceResponse
       5: ldc           #6                  // class io/grpc/reflection/v1alpha/ListServiceResponse$Builder
       7: invokevirtual #7                  // Method com/google/protobuf/GeneratedMessageV3$FieldAccessorTable.ensureFieldAccessorsInitialized:(Ljava/lang/Class;Ljava/lang/Class;)Lcom/google/protobuf/GeneratedMessageV3$FieldAccessorTable;
      10: areturn

  private io.grpc.reflection.v1alpha.ListServiceResponse$Builder();
    Code:
       0: aload_0
       1: invokespecial #8                  // Method com/google/protobuf/GeneratedMessageV3$Builder."<init>":()V
       4: aload_0
       5: invokestatic  #9                  // Method java/util/Collections.emptyList:()Ljava/util/List;
       8: putfield      #10                 // Field service_:Ljava/util/List;
      11: return

  private io.grpc.reflection.v1alpha.ListServiceResponse$Builder(com.google.protobuf.GeneratedMessageV3$BuilderParent);
    Code:
       0: aload_0
       1: aload_1
       2: invokespecial #11                 // Method com/google/protobuf/GeneratedMessageV3$Builder."<init>":(Lcom/google/protobuf/GeneratedMessageV3$BuilderParent;)V
       5: aload_0
       6: invokestatic  #9                  // Method java/util/Collections.emptyList:()Ljava/util/List;
       9: putfield      #10                 // Field service_:Ljava/util/List;
      12: return

  public io.grpc.reflection.v1alpha.ListServiceResponse$Builder clear();
    Code:
       0: aload_0
       1: invokespecial #12                 // Method com/google/protobuf/GeneratedMessageV3$Builder.clear:()Lcom/google/protobuf/GeneratedMessageV3$Builder;
       4: pop
       5: aload_0
       6: iconst_0
       7: putfield      #13                 // Field bitField0_:I
      10: aload_0
      11: getfield      #14                 // Field serviceBuilder_:Lcom/google/protobuf/RepeatedFieldBuilderV3;
      14: ifnonnull     27
      17: aload_0
      18: invokestatic  #9                  // Method java/util/Collections.emptyList:()Ljava/util/List;
      21: putfield      #10                 // Field service_:Ljava/util/List;
      24: goto          39
      27: aload_0
      28: aconst_null
      29: putfield      #10                 // Field service_:Ljava/util/List;
      32: aload_0
      33: getfield      #14                 // Field serviceBuilder_:Lcom/google/protobuf/RepeatedFieldBuilderV3;
      36: invokevirtual #15                 // Method com/google/protobuf/RepeatedFieldBuilderV3.clear:()V
      39: aload_0
      40: aload_0
      41: getfield      #13                 // Field bitField0_:I
      44: bipush        -2
      46: iand
      47: putfield      #13                 // Field bitField0_:I
      50: aload_0
      51: areturn

  public com.google.protobuf.Descriptors$Descriptor getDescriptorForType();
    Code:
       0: getstatic     #3                  // Field io/grpc/reflection/v1alpha/ServerReflectionProto.internal_static_grpc_reflection_v1alpha_ListServiceResponse_descriptor:Lcom/google/protobuf/Descriptors$Descriptor;
       3: areturn

  public io.grpc.reflection.v1alpha.ListServiceResponse getDefaultInstanceForType();
    Code:
       0: invokestatic  #16                 // Method io/grpc/reflection/v1alpha/ListServiceResponse.getDefaultInstance:()Lio/grpc/reflection/v1alpha/ListServiceResponse;
       3: areturn

  public io.grpc.reflection.v1alpha.ListServiceResponse build();
    Code:
       0: aload_0
       1: invokevirtual #17                 // Method buildPartial:()Lio/grpc/reflection/v1alpha/ListServiceResponse;
       4: astore_1
       5: aload_1
       6: invokevirtual #18                 // Method io/grpc/reflection/v1alpha/ListServiceResponse.isInitialized:()Z
       9: ifne          17
      12: aload_1
      13: invokestatic  #19                 // Method newUninitializedMessageException:(Lcom/google/protobuf/Message;)Lcom/google/protobuf/UninitializedMessageException;
      16: athrow
      17: aload_1
      18: areturn

  public io.grpc.reflection.v1alpha.ListServiceResponse buildPartial();
    Code:
       0: new           #5                  // class io/grpc/reflection/v1alpha/ListServiceResponse
       3: dup
       4: aload_0
       5: aconst_null
       6: invokespecial #20                 // Method io/grpc/reflection/v1alpha/ListServiceResponse."<init>":(Lcom/google/protobuf/GeneratedMessageV3$Builder;Lio/grpc/reflection/v1alpha/ListServiceResponse$1;)V
       9: astore_1
      10: aload_0
      11: aload_1
      12: invokespecial #21                 // Method buildPartialRepeatedFields:(Lio/grpc/reflection/v1alpha/ListServiceResponse;)V
      15: aload_0
      16: getfield      #13                 // Field bitField0_:I
      19: ifeq          27
      22: aload_0
      23: aload_1
      24: invokespecial #22                 // Method buildPartial0:(Lio/grpc/reflection/v1alpha/ListServiceResponse;)V
      27: aload_0
      28: invokevirtual #23                 // Method onBuilt:()V
      31: aload_1
      32: areturn

  private void buildPartialRepeatedFields(io.grpc.reflection.v1alpha.ListServiceResponse);
    Code:
       0: aload_0
       1: getfield      #14                 // Field serviceBuilder_:Lcom/google/protobuf/RepeatedFieldBuilderV3;
       4: ifnonnull     50
       7: aload_0
       8: getfield      #13                 // Field bitField0_:I
      11: iconst_1
      12: iand
      13: ifeq          38
      16: aload_0
      17: aload_0
      18: getfield      #10                 // Field service_:Ljava/util/List;
      21: invokestatic  #24                 // Method java/util/Collections.unmodifiableList:(Ljava/util/List;)Ljava/util/List;
      24: putfield      #10                 // Field service_:Ljava/util/List;
      27: aload_0
      28: aload_0
      29: getfield      #13                 // Field bitField0_:I
      32: bipush        -2
      34: iand
      35: putfield      #13                 // Field bitField0_:I
      38: aload_1
      39: aload_0
      40: getfield      #10                 // Field service_:Ljava/util/List;
      43: invokestatic  #25                 // Method io/grpc/reflection/v1alpha/ListServiceResponse.access$302:(Lio/grpc/reflection/v1alpha/ListServiceResponse;Ljava/util/List;)Ljava/util/List;
      46: pop
      47: goto          62
      50: aload_1
      51: aload_0
      52: getfield      #14                 // Field serviceBuilder_:Lcom/google/protobuf/RepeatedFieldBuilderV3;
      55: invokevirtual #26                 // Method com/google/protobuf/RepeatedFieldBuilderV3.build:()Ljava/util/List;
      58: invokestatic  #25                 // Method io/grpc/reflection/v1alpha/ListServiceResponse.access$302:(Lio/grpc/reflection/v1alpha/ListServiceResponse;Ljava/util/List;)Ljava/util/List;
      61: pop
      62: return

  private void buildPartial0(io.grpc.reflection.v1alpha.ListServiceResponse);
    Code:
       0: aload_0
       1: getfield      #13                 // Field bitField0_:I
       4: istore_2
       5: return

  public io.grpc.reflection.v1alpha.ListServiceResponse$Builder mergeFrom(com.google.protobuf.Message);
    Code:
       0: aload_1
       1: instanceof    #5                  // class io/grpc/reflection/v1alpha/ListServiceResponse
       4: ifeq          16
       7: aload_0
       8: aload_1
       9: checkcast     #5                  // class io/grpc/reflection/v1alpha/ListServiceResponse
      12: invokevirtual #27                 // Method mergeFrom:(Lio/grpc/reflection/v1alpha/ListServiceResponse;)Lio/grpc/reflection/v1alpha/ListServiceResponse$Builder;
      15: areturn
      16: aload_0
      17: aload_1
      18: invokespecial #28                 // Method com/google/protobuf/GeneratedMessageV3$Builder.mergeFrom:(Lcom/google/protobuf/Message;)Lcom/google/protobuf/AbstractMessage$Builder;
      21: pop
      22: aload_0
      23: areturn

  public io.grpc.reflection.v1alpha.ListServiceResponse$Builder mergeFrom(io.grpc.reflection.v1alpha.ListServiceResponse);
    Code:
       0: aload_1
       1: invokestatic  #16                 // Method io/grpc/reflection/v1alpha/ListServiceResponse.getDefaultInstance:()Lio/grpc/reflection/v1alpha/ListServiceResponse;
       4: if_acmpne     9
       7: aload_0
       8: areturn
       9: aload_0
      10: getfield      #14                 // Field serviceBuilder_:Lcom/google/protobuf/RepeatedFieldBuilderV3;
      13: ifnonnull     87
      16: aload_1
      17: invokestatic  #29                 // Method io/grpc/reflection/v1alpha/ListServiceResponse.access$300:(Lio/grpc/reflection/v1alpha/ListServiceResponse;)Ljava/util/List;
      20: invokeinterface #30,  1           // InterfaceMethod java/util/List.isEmpty:()Z
      25: ifne          173
      28: aload_0
      29: getfield      #10                 // Field service_:Ljava/util/List;
      32: invokeinterface #30,  1           // InterfaceMethod java/util/List.isEmpty:()Z
      37: ifeq          62
      40: aload_0
      41: aload_1
      42: invokestatic  #29                 // Method io/grpc/reflection/v1alpha/ListServiceResponse.access$300:(Lio/grpc/reflection/v1alpha/ListServiceResponse;)Ljava/util/List;
      45: putfield      #10                 // Field service_:Ljava/util/List;
      48: aload_0
      49: aload_0
      50: getfield      #13                 // Field bitField0_:I
      53: bipush        -2
      55: iand
      56: putfield      #13                 // Field bitField0_:I
      59: goto          80
      62: aload_0
      63: invokespecial #31                 // Method ensureServiceIsMutable:()V
      66: aload_0
      67: getfield      #10                 // Field service_:Ljava/util/List;
      70: aload_1
      71: invokestatic  #29                 // Method io/grpc/reflection/v1alpha/ListServiceResponse.access$300:(Lio/grpc/reflection/v1alpha/ListServiceResponse;)Ljava/util/List;
      74: invokeinterface #32,  2           // InterfaceMethod java/util/List.addAll:(Ljava/util/Collection;)Z
      79: pop
      80: aload_0
      81: invokevirtual #33                 // Method onChanged:()V
      84: goto          173
      87: aload_1
      88: invokestatic  #29                 // Method io/grpc/reflection/v1alpha/ListServiceResponse.access$300:(Lio/grpc/reflection/v1alpha/ListServiceResponse;)Ljava/util/List;
      91: invokeinterface #30,  1           // InterfaceMethod java/util/List.isEmpty:()Z
      96: ifne          173
      99: aload_0
     100: getfield      #14                 // Field serviceBuilder_:Lcom/google/protobuf/RepeatedFieldBuilderV3;
     103: invokevirtual #34                 // Method com/google/protobuf/RepeatedFieldBuilderV3.isEmpty:()Z
     106: ifeq          161
     109: aload_0
     110: getfield      #14                 // Field serviceBuilder_:Lcom/google/protobuf/RepeatedFieldBuilderV3;
     113: invokevirtual #35                 // Method com/google/protobuf/RepeatedFieldBuilderV3.dispose:()V
     116: aload_0
     117: aconst_null
     118: putfield      #14                 // Field serviceBuilder_:Lcom/google/protobuf/RepeatedFieldBuilderV3;
     121: aload_0
     122: aload_1
     123: invokestatic  #29                 // Method io/grpc/reflection/v1alpha/ListServiceResponse.access$300:(Lio/grpc/reflection/v1alpha/ListServiceResponse;)Ljava/util/List;
     126: putfield      #10                 // Field service_:Ljava/util/List;
     129: aload_0
     130: aload_0
     131: getfield      #13                 // Field bitField0_:I
     134: bipush        -2
     136: iand
     137: putfield      #13                 // Field bitField0_:I
     140: aload_0
     141: invokestatic  #36                 // Method io/grpc/reflection/v1alpha/ListServiceResponse.access$400:()Z
     144: ifeq          154
     147: aload_0
     148: invokespecial #37                 // Method getServiceFieldBuilder:()Lcom/google/protobuf/RepeatedFieldBuilderV3;
     151: goto          155
     154: aconst_null
     155: putfield      #14                 // Field serviceBuilder_:Lcom/google/protobuf/RepeatedFieldBuilderV3;
     158: goto          173
     161: aload_0
     162: getfield      #14                 // Field serviceBuilder_:Lcom/google/protobuf/RepeatedFieldBuilderV3;
     165: aload_1
     166: invokestatic  #29                 // Method io/grpc/reflection/v1alpha/ListServiceResponse.access$300:(Lio/grpc/reflection/v1alpha/ListServiceResponse;)Ljava/util/List;
     169: invokevirtual #38                 // Method com/google/protobuf/RepeatedFieldBuilderV3.addAllMessages:(Ljava/lang/Iterable;)Lcom/google/protobuf/RepeatedFieldBuilderV3;
     172: pop
     173: aload_0
     174: aload_1
     175: invokevirtual #39                 // Method io/grpc/reflection/v1alpha/ListServiceResponse.getUnknownFields:()Lcom/google/protobuf/UnknownFieldSet;
     178: invokevirtual #40                 // Method mergeUnknownFields:(Lcom/google/protobuf/UnknownFieldSet;)Lio/grpc/reflection/v1alpha/ListServiceResponse$Builder;
     181: pop
     182: aload_0
     183: invokevirtual #33                 // Method onChanged:()V
     186: aload_0
     187: areturn

  public final boolean isInitialized();
    Code:
       0: iconst_1
       1: ireturn

  public io.grpc.reflection.v1alpha.ListServiceResponse$Builder mergeFrom(com.google.protobuf.CodedInputStream, com.google.protobuf.ExtensionRegistryLite) throws java.io.IOException;
    Code:
       0: aload_2
       1: ifnonnull     12
       4: new           #41                 // class java/lang/NullPointerException
       7: dup
       8: invokespecial #42                 // Method java/lang/NullPointerException."<init>":()V
      11: athrow
      12: iconst_0
      13: istore_3
      14: iload_3
      15: ifne          125
      18: aload_1
      19: invokevirtual #43                 // Method com/google/protobuf/CodedInputStream.readTag:()I
      22: istore        4
      24: iload         4
      26: lookupswitch  { // 2
                     0: 52
                    10: 57
               default: 109
          }
      52: iconst_1
      53: istore_3
      54: goto          122
      57: aload_1
      58: invokestatic  #44                 // Method io/grpc/reflection/v1alpha/ServiceResponse.parser:()Lcom/google/protobuf/Parser;
      61: aload_2
      62: invokevirtual #45                 // Method com/google/protobuf/CodedInputStream.readMessage:(Lcom/google/protobuf/Parser;Lcom/google/protobuf/ExtensionRegistryLite;)Lcom/google/protobuf/MessageLite;
      65: checkcast     #46                 // class io/grpc/reflection/v1alpha/ServiceResponse
      68: astore        5
      70: aload_0
      71: getfield      #14                 // Field serviceBuilder_:Lcom/google/protobuf/RepeatedFieldBuilderV3;
      74: ifnonnull     96
      77: aload_0
      78: invokespecial #31                 // Method ensureServiceIsMutable:()V
      81: aload_0
      82: getfield      #10                 // Field service_:Ljava/util/List;
      85: aload         5
      87: invokeinterface #47,  2           // InterfaceMethod java/util/List.add:(Ljava/lang/Object;)Z
      92: pop
      93: goto          122
      96: aload_0
      97: getfield      #14                 // Field serviceBuilder_:Lcom/google/protobuf/RepeatedFieldBuilderV3;
     100: aload         5
     102: invokevirtual #48                 // Method com/google/protobuf/RepeatedFieldBuilderV3.addMessage:(Lcom/google/protobuf/AbstractMessage;)Lcom/google/protobuf/RepeatedFieldBuilderV3;
     105: pop
     106: goto          122
     109: aload_0
     110: aload_1
     111: aload_2
     112: iload         4
     114: invokespecial #49                 // Method com/google/protobuf/GeneratedMessageV3$Builder.parseUnknownField:(Lcom/google/protobuf/CodedInputStream;Lcom/google/protobuf/ExtensionRegistryLite;I)Z
     117: ifne          122
     120: iconst_1
     121: istore_3
     122: goto          14
     125: aload_0
     126: invokevirtual #33                 // Method onChanged:()V
     129: goto          147
     132: astore_3
     133: aload_3
     134: invokevirtual #51                 // Method com/google/protobuf/InvalidProtocolBufferException.unwrapIOException:()Ljava/io/IOException;
     137: athrow
     138: astore        6
     140: aload_0
     141: invokevirtual #33                 // Method onChanged:()V
     144: aload         6
     146: athrow
     147: aload_0
     148: areturn
    Exception table:
       from    to  target type
          12   125   132   Class com/google/protobuf/InvalidProtocolBufferException
          12   125   138   any
         132   140   138   any

  private void ensureServiceIsMutable();
    Code:
       0: aload_0
       1: getfield      #13                 // Field bitField0_:I
       4: iconst_1
       5: iand
       6: ifne          34
       9: aload_0
      10: new           #52                 // class java/util/ArrayList
      13: dup
      14: aload_0
      15: getfield      #10                 // Field service_:Ljava/util/List;
      18: invokespecial #53                 // Method java/util/ArrayList."<init>":(Ljava/util/Collection;)V
      21: putfield      #10                 // Field service_:Ljava/util/List;
      24: aload_0
      25: dup
      26: getfield      #13                 // Field bitField0_:I
      29: iconst_1
      30: ior
      31: putfield      #13                 // Field bitField0_:I
      34: return

  public java.util.List<io.grpc.reflection.v1alpha.ServiceResponse> getServiceList();
    Code:
       0: aload_0
       1: getfield      #14                 // Field serviceBuilder_:Lcom/google/protobuf/RepeatedFieldBuilderV3;
       4: ifnonnull     15
       7: aload_0
       8: getfield      #10                 // Field service_:Ljava/util/List;
      11: invokestatic  #24                 // Method java/util/Collections.unmodifiableList:(Ljava/util/List;)Ljava/util/List;
      14: areturn
      15: aload_0
      16: getfield      #14                 // Field serviceBuilder_:Lcom/google/protobuf/RepeatedFieldBuilderV3;
      19: invokevirtual #54                 // Method com/google/protobuf/RepeatedFieldBuilderV3.getMessageList:()Ljava/util/List;
      22: areturn

  public int getServiceCount();
    Code:
       0: aload_0
       1: getfield      #14                 // Field serviceBuilder_:Lcom/google/protobuf/RepeatedFieldBuilderV3;
       4: ifnonnull     17
       7: aload_0
       8: getfield      #10                 // Field service_:Ljava/util/List;
      11: invokeinterface #55,  1           // InterfaceMethod java/util/List.size:()I
      16: ireturn
      17: aload_0
      18: getfield      #14                 // Field serviceBuilder_:Lcom/google/protobuf/RepeatedFieldBuilderV3;
      21: invokevirtual #56                 // Method com/google/protobuf/RepeatedFieldBuilderV3.getCount:()I
      24: ireturn

  public io.grpc.reflection.v1alpha.ServiceResponse getService(int);
    Code:
       0: aload_0
       1: getfield      #14                 // Field serviceBuilder_:Lcom/google/protobuf/RepeatedFieldBuilderV3;
       4: ifnonnull     21
       7: aload_0
       8: getfield      #10                 // Field service_:Ljava/util/List;
      11: iload_1
      12: invokeinterface #57,  2           // InterfaceMethod java/util/List.get:(I)Ljava/lang/Object;
      17: checkcast     #46                 // class io/grpc/reflection/v1alpha/ServiceResponse
      20: areturn
      21: aload_0
      22: getfield      #14                 // Field serviceBuilder_:Lcom/google/protobuf/RepeatedFieldBuilderV3;
      25: iload_1
      26: invokevirtual #58                 // Method com/google/protobuf/RepeatedFieldBuilderV3.getMessage:(I)Lcom/google/protobuf/AbstractMessage;
      29: checkcast     #46                 // class io/grpc/reflection/v1alpha/ServiceResponse
      32: areturn

  public io.grpc.reflection.v1alpha.ListServiceResponse$Builder setService(int, io.grpc.reflection.v1alpha.ServiceResponse);
    Code:
       0: aload_0
       1: getfield      #14                 // Field serviceBuilder_:Lcom/google/protobuf/RepeatedFieldBuilderV3;
       4: ifnonnull     42
       7: aload_2
       8: ifnonnull     19
      11: new           #41                 // class java/lang/NullPointerException
      14: dup
      15: invokespecial #42                 // Method java/lang/NullPointerException."<init>":()V
      18: athrow
      19: aload_0
      20: invokespecial #31                 // Method ensureServiceIsMutable:()V
      23: aload_0
      24: getfield      #10                 // Field service_:Ljava/util/List;
      27: iload_1
      28: aload_2
      29: invokeinterface #59,  3           // InterfaceMethod java/util/List.set:(ILjava/lang/Object;)Ljava/lang/Object;
      34: pop
      35: aload_0
      36: invokevirtual #33                 // Method onChanged:()V
      39: goto          52
      42: aload_0
      43: getfield      #14                 // Field serviceBuilder_:Lcom/google/protobuf/RepeatedFieldBuilderV3;
      46: iload_1
      47: aload_2
      48: invokevirtual #60                 // Method com/google/protobuf/RepeatedFieldBuilderV3.setMessage:(ILcom/google/protobuf/AbstractMessage;)Lcom/google/protobuf/RepeatedFieldBuilderV3;
      51: pop
      52: aload_0
      53: areturn

  public io.grpc.reflection.v1alpha.ListServiceResponse$Builder setService(int, io.grpc.reflection.v1alpha.ServiceResponse$Builder);
    Code:
       0: aload_0
       1: getfield      #14                 // Field serviceBuilder_:Lcom/google/protobuf/RepeatedFieldBuilderV3;
       4: ifnonnull     33
       7: aload_0
       8: invokespecial #31                 // Method ensureServiceIsMutable:()V
      11: aload_0
      12: getfield      #10                 // Field service_:Ljava/util/List;
      15: iload_1
      16: aload_2
      17: invokevirtual #61                 // Method io/grpc/reflection/v1alpha/ServiceResponse$Builder.build:()Lio/grpc/reflection/v1alpha/ServiceResponse;
      20: invokeinterface #59,  3           // InterfaceMethod java/util/List.set:(ILjava/lang/Object;)Ljava/lang/Object;
      25: pop
      26: aload_0
      27: invokevirtual #33                 // Method onChanged:()V
      30: goto          46
      33: aload_0
      34: getfield      #14                 // Field serviceBuilder_:Lcom/google/protobuf/RepeatedFieldBuilderV3;
      37: iload_1
      38: aload_2
      39: invokevirtual #61                 // Method io/grpc/reflection/v1alpha/ServiceResponse$Builder.build:()Lio/grpc/reflection/v1alpha/ServiceResponse;
      42: invokevirtual #60                 // Method com/google/protobuf/RepeatedFieldBuilderV3.setMessage:(ILcom/google/protobuf/AbstractMessage;)Lcom/google/protobuf/RepeatedFieldBuilderV3;
      45: pop
      46: aload_0
      47: areturn

  public io.grpc.reflection.v1alpha.ListServiceResponse$Builder addService(io.grpc.reflection.v1alpha.ServiceResponse);
    Code:
       0: aload_0
       1: getfield      #14                 // Field serviceBuilder_:Lcom/google/protobuf/RepeatedFieldBuilderV3;
       4: ifnonnull     41
       7: aload_1
       8: ifnonnull     19
      11: new           #41                 // class java/lang/NullPointerException
      14: dup
      15: invokespecial #42                 // Method java/lang/NullPointerException."<init>":()V
      18: athrow
      19: aload_0
      20: invokespecial #31                 // Method ensureServiceIsMutable:()V
      23: aload_0
      24: getfield      #10                 // Field service_:Ljava/util/List;
      27: aload_1
      28: invokeinterface #47,  2           // InterfaceMethod java/util/List.add:(Ljava/lang/Object;)Z
      33: pop
      34: aload_0
      35: invokevirtual #33                 // Method onChanged:()V
      38: goto          50
      41: aload_0
      42: getfield      #14                 // Field serviceBuilder_:Lcom/google/protobuf/RepeatedFieldBuilderV3;
      45: aload_1
      46: invokevirtual #48                 // Method com/google/protobuf/RepeatedFieldBuilderV3.addMessage:(Lcom/google/protobuf/AbstractMessage;)Lcom/google/protobuf/RepeatedFieldBuilderV3;
      49: pop
      50: aload_0
      51: areturn

  public io.grpc.reflection.v1alpha.ListServiceResponse$Builder addService(int, io.grpc.reflection.v1alpha.ServiceResponse);
    Code:
       0: aload_0
       1: getfield      #14                 // Field serviceBuilder_:Lcom/google/protobuf/RepeatedFieldBuilderV3;
       4: ifnonnull     41
       7: aload_2
       8: ifnonnull     19
      11: new           #41                 // class java/lang/NullPointerException
      14: dup
      15: invokespecial #42                 // Method java/lang/NullPointerException."<init>":()V
      18: athrow
      19: aload_0
      20: invokespecial #31                 // Method ensureServiceIsMutable:()V
      23: aload_0
      24: getfield      #10                 // Field service_:Ljava/util/List;
      27: iload_1
      28: aload_2
      29: invokeinterface #62,  3           // InterfaceMethod java/util/List.add:(ILjava/lang/Object;)V
      34: aload_0
      35: invokevirtual #33                 // Method onChanged:()V
      38: goto          51
      41: aload_0
      42: getfield      #14                 // Field serviceBuilder_:Lcom/google/protobuf/RepeatedFieldBuilderV3;
      45: iload_1
      46: aload_2
      47: invokevirtual #63                 // Method com/google/protobuf/RepeatedFieldBuilderV3.addMessage:(ILcom/google/protobuf/AbstractMessage;)Lcom/google/protobuf/RepeatedFieldBuilderV3;
      50: pop
      51: aload_0
      52: areturn

  public io.grpc.reflection.v1alpha.ListServiceResponse$Builder addService(io.grpc.reflection.v1alpha.ServiceResponse$Builder);
    Code:
       0: aload_0
       1: getfield      #14                 // Field serviceBuilder_:Lcom/google/protobuf/RepeatedFieldBuilderV3;
       4: ifnonnull     32
       7: aload_0
       8: invokespecial #31                 // Method ensureServiceIsMutable:()V
      11: aload_0
      12: getfield      #10                 // Field service_:Ljava/util/List;
      15: aload_1
      16: invokevirtual #61                 // Method io/grpc/reflection/v1alpha/ServiceResponse$Builder.build:()Lio/grpc/reflection/v1alpha/ServiceResponse;
      19: invokeinterface #47,  2           // InterfaceMethod java/util/List.add:(Ljava/lang/Object;)Z
      24: pop
      25: aload_0
      26: invokevirtual #33                 // Method onChanged:()V
      29: goto          44
      32: aload_0
      33: getfield      #14                 // Field serviceBuilder_:Lcom/google/protobuf/RepeatedFieldBuilderV3;
      36: aload_1
      37: invokevirtual #61                 // Method io/grpc/reflection/v1alpha/ServiceResponse$Builder.build:()Lio/grpc/reflection/v1alpha/ServiceResponse;
      40: invokevirtual #48                 // Method com/google/protobuf/RepeatedFieldBuilderV3.addMessage:(Lcom/google/protobuf/AbstractMessage;)Lcom/google/protobuf/RepeatedFieldBuilderV3;
      43: pop
      44: aload_0
      45: areturn

  public io.grpc.reflection.v1alpha.ListServiceResponse$Builder addService(int, io.grpc.reflection.v1alpha.ServiceResponse$Builder);
    Code:
       0: aload_0
       1: getfield      #14                 // Field serviceBuilder_:Lcom/google/protobuf/RepeatedFieldBuilderV3;
       4: ifnonnull     32
       7: aload_0
       8: invokespecial #31                 // Method ensureServiceIsMutable:()V
      11: aload_0
      12: getfield      #10                 // Field service_:Ljava/util/List;
      15: iload_1
      16: aload_2
      17: invokevirtual #61                 // Method io/grpc/reflection/v1alpha/ServiceResponse$Builder.build:()Lio/grpc/reflection/v1alpha/ServiceResponse;
      20: invokeinterface #62,  3           // InterfaceMethod java/util/List.add:(ILjava/lang/Object;)V
      25: aload_0
      26: invokevirtual #33                 // Method onChanged:()V
      29: goto          45
      32: aload_0
      33: getfield      #14                 // Field serviceBuilder_:Lcom/google/protobuf/RepeatedFieldBuilderV3;
      36: iload_1
      37: aload_2
      38: invokevirtual #61                 // Method io/grpc/reflection/v1alpha/ServiceResponse$Builder.build:()Lio/grpc/reflection/v1alpha/ServiceResponse;
      41: invokevirtual #63                 // Method com/google/protobuf/RepeatedFieldBuilderV3.addMessage:(ILcom/google/protobuf/AbstractMessage;)Lcom/google/protobuf/RepeatedFieldBuilderV3;
      44: pop
      45: aload_0
      46: areturn

  public io.grpc.reflection.v1alpha.ListServiceResponse$Builder addAllService(java.lang.Iterable<? extends io.grpc.reflection.v1alpha.ServiceResponse>);
    Code:
       0: aload_0
       1: getfield      #14                 // Field serviceBuilder_:Lcom/google/protobuf/RepeatedFieldBuilderV3;
       4: ifnonnull     26
       7: aload_0
       8: invokespecial #31                 // Method ensureServiceIsMutable:()V
      11: aload_1
      12: aload_0
      13: getfield      #10                 // Field service_:Ljava/util/List;
      16: invokestatic  #64                 // Method com/google/protobuf/AbstractMessageLite$Builder.addAll:(Ljava/lang/Iterable;Ljava/util/List;)V
      19: aload_0
      20: invokevirtual #33                 // Method onChanged:()V
      23: goto          35
      26: aload_0
      27: getfield      #14                 // Field serviceBuilder_:Lcom/google/protobuf/RepeatedFieldBuilderV3;
      30: aload_1
      31: invokevirtual #38                 // Method com/google/protobuf/RepeatedFieldBuilderV3.addAllMessages:(Ljava/lang/Iterable;)Lcom/google/protobuf/RepeatedFieldBuilderV3;
      34: pop
      35: aload_0
      36: areturn

  public io.grpc.reflection.v1alpha.ListServiceResponse$Builder clearService();
    Code:
       0: aload_0
       1: getfield      #14                 // Field serviceBuilder_:Lcom/google/protobuf/RepeatedFieldBuilderV3;
       4: ifnonnull     32
       7: aload_0
       8: invokestatic  #9                  // Method java/util/Collections.emptyList:()Ljava/util/List;
      11: putfield      #10                 // Field service_:Ljava/util/List;
      14: aload_0
      15: aload_0
      16: getfield      #13                 // Field bitField0_:I
      19: bipush        -2
      21: iand
      22: putfield      #13                 // Field bitField0_:I
      25: aload_0
      26: invokevirtual #33                 // Method onChanged:()V
      29: goto          39
      32: aload_0
      33: getfield      #14                 // Field serviceBuilder_:Lcom/google/protobuf/RepeatedFieldBuilderV3;
      36: invokevirtual #15                 // Method com/google/protobuf/RepeatedFieldBuilderV3.clear:()V
      39: aload_0
      40: areturn

  public io.grpc.reflection.v1alpha.ListServiceResponse$Builder removeService(int);
    Code:
       0: aload_0
       1: getfield      #14                 // Field serviceBuilder_:Lcom/google/protobuf/RepeatedFieldBuilderV3;
       4: ifnonnull     29
       7: aload_0
       8: invokespecial #31                 // Method ensureServiceIsMutable:()V
      11: aload_0
      12: getfield      #10                 // Field service_:Ljava/util/List;
      15: iload_1
      16: invokeinterface #65,  2           // InterfaceMethod java/util/List.remove:(I)Ljava/lang/Object;
      21: pop
      22: aload_0
      23: invokevirtual #33                 // Method onChanged:()V
      26: goto          37
      29: aload_0
      30: getfield      #14                 // Field serviceBuilder_:Lcom/google/protobuf/RepeatedFieldBuilderV3;
      33: iload_1
      34: invokevirtual #66                 // Method com/google/protobuf/RepeatedFieldBuilderV3.remove:(I)V
      37: aload_0
      38: areturn

  public io.grpc.reflection.v1alpha.ServiceResponse$Builder getServiceBuilder(int);
    Code:
       0: aload_0
       1: invokespecial #37                 // Method getServiceFieldBuilder:()Lcom/google/protobuf/RepeatedFieldBuilderV3;
       4: iload_1
       5: invokevirtual #67                 // Method com/google/protobuf/RepeatedFieldBuilderV3.getBuilder:(I)Lcom/google/protobuf/AbstractMessage$Builder;
       8: checkcast     #68                 // class io/grpc/reflection/v1alpha/ServiceResponse$Builder
      11: areturn

  public io.grpc.reflection.v1alpha.ServiceResponseOrBuilder getServiceOrBuilder(int);
    Code:
       0: aload_0
       1: getfield      #14                 // Field serviceBuilder_:Lcom/google/protobuf/RepeatedFieldBuilderV3;
       4: ifnonnull     21
       7: aload_0
       8: getfield      #10                 // Field service_:Ljava/util/List;
      11: iload_1
      12: invokeinterface #57,  2           // InterfaceMethod java/util/List.get:(I)Ljava/lang/Object;
      17: checkcast     #69                 // class io/grpc/reflection/v1alpha/ServiceResponseOrBuilder
      20: areturn
      21: aload_0
      22: getfield      #14                 // Field serviceBuilder_:Lcom/google/protobuf/RepeatedFieldBuilderV3;
      25: iload_1
      26: invokevirtual #70                 // Method com/google/protobuf/RepeatedFieldBuilderV3.getMessageOrBuilder:(I)Lcom/google/protobuf/MessageOrBuilder;
      29: checkcast     #69                 // class io/grpc/reflection/v1alpha/ServiceResponseOrBuilder
      32: areturn

  public java.util.List<? extends io.grpc.reflection.v1alpha.ServiceResponseOrBuilder> getServiceOrBuilderList();
    Code:
       0: aload_0
       1: getfield      #14                 // Field serviceBuilder_:Lcom/google/protobuf/RepeatedFieldBuilderV3;
       4: ifnull        15
       7: aload_0
       8: getfield      #14                 // Field serviceBuilder_:Lcom/google/protobuf/RepeatedFieldBuilderV3;
      11: invokevirtual #71                 // Method com/google/protobuf/RepeatedFieldBuilderV3.getMessageOrBuilderList:()Ljava/util/List;
      14: areturn
      15: aload_0
      16: getfield      #10                 // Field service_:Ljava/util/List;
      19: invokestatic  #24                 // Method java/util/Collections.unmodifiableList:(Ljava/util/List;)Ljava/util/List;
      22: areturn

  public io.grpc.reflection.v1alpha.ServiceResponse$Builder addServiceBuilder();
    Code:
       0: aload_0
       1: invokespecial #37                 // Method getServiceFieldBuilder:()Lcom/google/protobuf/RepeatedFieldBuilderV3;
       4: invokestatic  #72                 // Method io/grpc/reflection/v1alpha/ServiceResponse.getDefaultInstance:()Lio/grpc/reflection/v1alpha/ServiceResponse;
       7: invokevirtual #73                 // Method com/google/protobuf/RepeatedFieldBuilderV3.addBuilder:(Lcom/google/protobuf/AbstractMessage;)Lcom/google/protobuf/AbstractMessage$Builder;
      10: checkcast     #68                 // class io/grpc/reflection/v1alpha/ServiceResponse$Builder
      13: areturn

  public io.grpc.reflection.v1alpha.ServiceResponse$Builder addServiceBuilder(int);
    Code:
       0: aload_0
       1: invokespecial #37                 // Method getServiceFieldBuilder:()Lcom/google/protobuf/RepeatedFieldBuilderV3;
       4: iload_1
       5: invokestatic  #72                 // Method io/grpc/reflection/v1alpha/ServiceResponse.getDefaultInstance:()Lio/grpc/reflection/v1alpha/ServiceResponse;
       8: invokevirtual #74                 // Method com/google/protobuf/RepeatedFieldBuilderV3.addBuilder:(ILcom/google/protobuf/AbstractMessage;)Lcom/google/protobuf/AbstractMessage$Builder;
      11: checkcast     #68                 // class io/grpc/reflection/v1alpha/ServiceResponse$Builder
      14: areturn

  public java.util.List<io.grpc.reflection.v1alpha.ServiceResponse$Builder> getServiceBuilderList();
    Code:
       0: aload_0
       1: invokespecial #37                 // Method getServiceFieldBuilder:()Lcom/google/protobuf/RepeatedFieldBuilderV3;
       4: invokevirtual #75                 // Method com/google/protobuf/RepeatedFieldBuilderV3.getBuilderList:()Ljava/util/List;
       7: areturn

  private com.google.protobuf.RepeatedFieldBuilderV3<io.grpc.reflection.v1alpha.ServiceResponse, io.grpc.reflection.v1alpha.ServiceResponse$Builder, io.grpc.reflection.v1alpha.ServiceResponseOrBuilder> getServiceFieldBuilder();
    Code:
       0: aload_0
       1: getfield      #14                 // Field serviceBuilder_:Lcom/google/protobuf/RepeatedFieldBuilderV3;
       4: ifnonnull     49
       7: aload_0
       8: new           #76                 // class com/google/protobuf/RepeatedFieldBuilderV3
      11: dup
      12: aload_0
      13: getfield      #10                 // Field service_:Ljava/util/List;
      16: aload_0
      17: getfield      #13                 // Field bitField0_:I
      20: iconst_1
      21: iand
      22: ifeq          29
      25: iconst_1
      26: goto          30
      29: iconst_0
      30: aload_0
      31: invokevirtual #77                 // Method getParentForChildren:()Lcom/google/protobuf/GeneratedMessageV3$BuilderParent;
      34: aload_0
      35: invokevirtual #78                 // Method isClean:()Z
      38: invokespecial #79                 // Method com/google/protobuf/RepeatedFieldBuilderV3."<init>":(Ljava/util/List;ZLcom/google/protobuf/AbstractMessage$BuilderParent;Z)V
      41: putfield      #14                 // Field serviceBuilder_:Lcom/google/protobuf/RepeatedFieldBuilderV3;
      44: aload_0
      45: aconst_null
      46: putfield      #10                 // Field service_:Ljava/util/List;
      49: aload_0
      50: getfield      #14                 // Field serviceBuilder_:Lcom/google/protobuf/RepeatedFieldBuilderV3;
      53: areturn

  public final io.grpc.reflection.v1alpha.ListServiceResponse$Builder setUnknownFields(com.google.protobuf.UnknownFieldSet);
    Code:
       0: aload_0
       1: aload_1
       2: invokespecial #80                 // Method com/google/protobuf/GeneratedMessageV3$Builder.setUnknownFields:(Lcom/google/protobuf/UnknownFieldSet;)Lcom/google/protobuf/GeneratedMessageV3$Builder;
       5: checkcast     #6                  // class io/grpc/reflection/v1alpha/ListServiceResponse$Builder
       8: areturn

  public final io.grpc.reflection.v1alpha.ListServiceResponse$Builder mergeUnknownFields(com.google.protobuf.UnknownFieldSet);
    Code:
       0: aload_0
       1: aload_1
       2: invokespecial #81                 // Method com/google/protobuf/GeneratedMessageV3$Builder.mergeUnknownFields:(Lcom/google/protobuf/UnknownFieldSet;)Lcom/google/protobuf/GeneratedMessageV3$Builder;
       5: checkcast     #6                  // class io/grpc/reflection/v1alpha/ListServiceResponse$Builder
       8: areturn

  public com.google.protobuf.GeneratedMessageV3$Builder mergeUnknownFields(com.google.protobuf.UnknownFieldSet);
    Code:
       0: aload_0
       1: aload_1
       2: invokevirtual #40                 // Method mergeUnknownFields:(Lcom/google/protobuf/UnknownFieldSet;)Lio/grpc/reflection/v1alpha/ListServiceResponse$Builder;
       5: areturn

  public com.google.protobuf.GeneratedMessageV3$Builder setUnknownFields(com.google.protobuf.UnknownFieldSet);
    Code:
       0: aload_0
       1: aload_1
       2: invokevirtual #82                 // Method setUnknownFields:(Lcom/google/protobuf/UnknownFieldSet;)Lio/grpc/reflection/v1alpha/ListServiceResponse$Builder;
       5: areturn

  public com.google.protobuf.GeneratedMessageV3$Builder clear();
    Code:
       0: aload_0
       1: invokevirtual #83                 // Method clear:()Lio/grpc/reflection/v1alpha/ListServiceResponse$Builder;
       4: areturn

  public com.google.protobuf.AbstractMessage$Builder mergeUnknownFields(com.google.protobuf.UnknownFieldSet);
    Code:
       0: aload_0
       1: aload_1
       2: invokevirtual #40                 // Method mergeUnknownFields:(Lcom/google/protobuf/UnknownFieldSet;)Lio/grpc/reflection/v1alpha/ListServiceResponse$Builder;
       5: areturn

  public com.google.protobuf.AbstractMessage$Builder mergeFrom(com.google.protobuf.CodedInputStream, com.google.protobuf.ExtensionRegistryLite) throws java.io.IOException;
    Code:
       0: aload_0
       1: aload_1
       2: aload_2
       3: invokevirtual #84                 // Method mergeFrom:(Lcom/google/protobuf/CodedInputStream;Lcom/google/protobuf/ExtensionRegistryLite;)Lio/grpc/reflection/v1alpha/ListServiceResponse$Builder;
       6: areturn

  public com.google.protobuf.AbstractMessage$Builder mergeFrom(com.google.protobuf.Message);
    Code:
       0: aload_0
       1: aload_1
       2: invokevirtual #85                 // Method mergeFrom:(Lcom/google/protobuf/Message;)Lio/grpc/reflection/v1alpha/ListServiceResponse$Builder;
       5: areturn

  public com.google.protobuf.AbstractMessage$Builder clear();
    Code:
       0: aload_0
       1: invokevirtual #83                 // Method clear:()Lio/grpc/reflection/v1alpha/ListServiceResponse$Builder;
       4: areturn

  public com.google.protobuf.Message$Builder mergeUnknownFields(com.google.protobuf.UnknownFieldSet);
    Code:
       0: aload_0
       1: aload_1
       2: invokevirtual #40                 // Method mergeUnknownFields:(Lcom/google/protobuf/UnknownFieldSet;)Lio/grpc/reflection/v1alpha/ListServiceResponse$Builder;
       5: areturn

  public com.google.protobuf.Message$Builder setUnknownFields(com.google.protobuf.UnknownFieldSet);
    Code:
       0: aload_0
       1: aload_1
       2: invokevirtual #82                 // Method setUnknownFields:(Lcom/google/protobuf/UnknownFieldSet;)Lio/grpc/reflection/v1alpha/ListServiceResponse$Builder;
       5: areturn

  public com.google.protobuf.Message$Builder mergeFrom(com.google.protobuf.CodedInputStream, com.google.protobuf.ExtensionRegistryLite) throws java.io.IOException;
    Code:
       0: aload_0
       1: aload_1
       2: aload_2
       3: invokevirtual #84                 // Method mergeFrom:(Lcom/google/protobuf/CodedInputStream;Lcom/google/protobuf/ExtensionRegistryLite;)Lio/grpc/reflection/v1alpha/ListServiceResponse$Builder;
       6: areturn

  public com.google.protobuf.Message buildPartial();
    Code:
       0: aload_0
       1: invokevirtual #17                 // Method buildPartial:()Lio/grpc/reflection/v1alpha/ListServiceResponse;
       4: areturn

  public com.google.protobuf.Message build();
    Code:
       0: aload_0
       1: invokevirtual #86                 // Method build:()Lio/grpc/reflection/v1alpha/ListServiceResponse;
       4: areturn

  public com.google.protobuf.Message$Builder mergeFrom(com.google.protobuf.Message);
    Code:
       0: aload_0
       1: aload_1
       2: invokevirtual #85                 // Method mergeFrom:(Lcom/google/protobuf/Message;)Lio/grpc/reflection/v1alpha/ListServiceResponse$Builder;
       5: areturn

  public com.google.protobuf.Message$Builder clear();
    Code:
       0: aload_0
       1: invokevirtual #83                 // Method clear:()Lio/grpc/reflection/v1alpha/ListServiceResponse$Builder;
       4: areturn

  public com.google.protobuf.MessageLite$Builder mergeFrom(com.google.protobuf.CodedInputStream, com.google.protobuf.ExtensionRegistryLite) throws java.io.IOException;
    Code:
       0: aload_0
       1: aload_1
       2: aload_2
       3: invokevirtual #84                 // Method mergeFrom:(Lcom/google/protobuf/CodedInputStream;Lcom/google/protobuf/ExtensionRegistryLite;)Lio/grpc/reflection/v1alpha/ListServiceResponse$Builder;
       6: areturn

  public com.google.protobuf.MessageLite buildPartial();
    Code:
       0: aload_0
       1: invokevirtual #17                 // Method buildPartial:()Lio/grpc/reflection/v1alpha/ListServiceResponse;
       4: areturn

  public com.google.protobuf.MessageLite build();
    Code:
       0: aload_0
       1: invokevirtual #86                 // Method build:()Lio/grpc/reflection/v1alpha/ListServiceResponse;
       4: areturn

  public com.google.protobuf.MessageLite$Builder clear();
    Code:
       0: aload_0
       1: invokevirtual #83                 // Method clear:()Lio/grpc/reflection/v1alpha/ListServiceResponse$Builder;
       4: areturn

  public com.google.protobuf.MessageLite getDefaultInstanceForType();
    Code:
       0: aload_0
       1: invokevirtual #87                 // Method getDefaultInstanceForType:()Lio/grpc/reflection/v1alpha/ListServiceResponse;
       4: areturn

  public com.google.protobuf.Message getDefaultInstanceForType();
    Code:
       0: aload_0
       1: invokevirtual #87                 // Method getDefaultInstanceForType:()Lio/grpc/reflection/v1alpha/ListServiceResponse;
       4: areturn

  public com.google.protobuf.AbstractMessageLite$Builder mergeFrom(com.google.protobuf.CodedInputStream, com.google.protobuf.ExtensionRegistryLite) throws java.io.IOException;
    Code:
       0: aload_0
       1: aload_1
       2: aload_2
       3: invokevirtual #84                 // Method mergeFrom:(Lcom/google/protobuf/CodedInputStream;Lcom/google/protobuf/ExtensionRegistryLite;)Lio/grpc/reflection/v1alpha/ListServiceResponse$Builder;
       6: areturn

  io.grpc.reflection.v1alpha.ListServiceResponse$Builder(io.grpc.reflection.v1alpha.ListServiceResponse$1);
    Code:
       0: aload_0
       1: invokespecial #2                  // Method "<init>":()V
       4: return

  io.grpc.reflection.v1alpha.ListServiceResponse$Builder(com.google.protobuf.GeneratedMessageV3$BuilderParent, io.grpc.reflection.v1alpha.ListServiceResponse$1);
    Code:
       0: aload_0
       1: aload_1
       2: invokespecial #1                  // Method "<init>":(Lcom/google/protobuf/GeneratedMessageV3$BuilderParent;)V
       5: return
}
