Compiled from "ReferenceBeanBuilder.java"
public class org.apache.dubbo.config.spring.reference.ReferenceBeanBuilder {
  private java.util.Map<java.lang.String, java.lang.Object> attributes;

  public org.apache.dubbo.config.spring.reference.ReferenceBeanBuilder();
    Code:
       0: aload_0
       1: invokespecial #1                  // Method java/lang/Object."<init>":()V
       4: aload_0
       5: new           #2                  // class java/util/HashMap
       8: dup
       9: invokespecial #3                  // Method java/util/HashMap."<init>":()V
      12: putfield      #4                  // Field attributes:Ljava/util/Map;
      15: return

  public <T> org.apache.dubbo.config.spring.ReferenceBean<T> build();
    Code:
       0: new           #5                  // class org/apache/dubbo/config/spring/ReferenceBean
       3: dup
       4: aload_0
       5: getfield      #4                  // Field attributes:Ljava/util/Map;
       8: invokespecial #6                  // Method org/apache/dubbo/config/spring/ReferenceBean."<init>":(Ljava/util/Map;)V
      11: areturn

  public org.apache.dubbo.config.spring.reference.ReferenceBeanBuilder setServices(java.lang.String);
    Code:
       0: aload_0
       1: getfield      #4                  // Field attributes:Ljava/util/Map;
       4: ldc           #8                  // String services
       6: aload_1
       7: invokeinterface #9,  3            // InterfaceMethod java/util/Map.put:(Ljava/lang/Object;Ljava/lang/Object;)Ljava/lang/Object;
      12: pop
      13: aload_0
      14: areturn

  public org.apache.dubbo.config.spring.reference.ReferenceBeanBuilder setInterface(java.lang.String);
    Code:
       0: aload_0
       1: getfield      #4                  // Field attributes:Ljava/util/Map;
       4: ldc           #10                 // String interfaceName
       6: aload_1
       7: invokeinterface #9,  3            // InterfaceMethod java/util/Map.put:(Ljava/lang/Object;Ljava/lang/Object;)Ljava/lang/Object;
      12: pop
      13: aload_0
      14: areturn

  public org.apache.dubbo.config.spring.reference.ReferenceBeanBuilder setInterface(java.lang.Class);
    Code:
       0: aload_0
       1: getfield      #4                  // Field attributes:Ljava/util/Map;
       4: ldc           #11                 // String interfaceClass
       6: aload_1
       7: invokeinterface #9,  3            // InterfaceMethod java/util/Map.put:(Ljava/lang/Object;Ljava/lang/Object;)Ljava/lang/Object;
      12: pop
      13: aload_0
      14: areturn

  public org.apache.dubbo.config.spring.reference.ReferenceBeanBuilder setClient(java.lang.String);
    Code:
       0: aload_0
       1: getfield      #4                  // Field attributes:Ljava/util/Map;
       4: ldc           #12                 // String client
       6: aload_1
       7: invokeinterface #9,  3            // InterfaceMethod java/util/Map.put:(Ljava/lang/Object;Ljava/lang/Object;)Ljava/lang/Object;
      12: pop
      13: aload_0
      14: areturn

  public org.apache.dubbo.config.spring.reference.ReferenceBeanBuilder setUrl(java.lang.String);
    Code:
       0: aload_0
       1: getfield      #4                  // Field attributes:Ljava/util/Map;
       4: ldc           #13                 // String url
       6: aload_1
       7: invokeinterface #9,  3            // InterfaceMethod java/util/Map.put:(Ljava/lang/Object;Ljava/lang/Object;)Ljava/lang/Object;
      12: pop
      13: aload_0
      14: areturn

  public org.apache.dubbo.config.spring.reference.ReferenceBeanBuilder setConsumer(org.apache.dubbo.config.ConsumerConfig);
    Code:
       0: aload_0
       1: getfield      #4                  // Field attributes:Ljava/util/Map;
       4: ldc           #14                 // String consumer
       6: aload_1
       7: invokeinterface #9,  3            // InterfaceMethod java/util/Map.put:(Ljava/lang/Object;Ljava/lang/Object;)Ljava/lang/Object;
      12: pop
      13: aload_0
      14: areturn

  public org.apache.dubbo.config.spring.reference.ReferenceBeanBuilder setConsumer(java.lang.String);
    Code:
       0: aload_0
       1: getfield      #4                  // Field attributes:Ljava/util/Map;
       4: ldc           #14                 // String consumer
       6: aload_1
       7: invokeinterface #9,  3            // InterfaceMethod java/util/Map.put:(Ljava/lang/Object;Ljava/lang/Object;)Ljava/lang/Object;
      12: pop
      13: aload_0
      14: areturn

  public org.apache.dubbo.config.spring.reference.ReferenceBeanBuilder setProtocol(java.lang.String);
    Code:
       0: aload_0
       1: getfield      #4                  // Field attributes:Ljava/util/Map;
       4: ldc           #15                 // String protocol
       6: aload_1
       7: invokeinterface #9,  3            // InterfaceMethod java/util/Map.put:(Ljava/lang/Object;Ljava/lang/Object;)Ljava/lang/Object;
      12: pop
      13: aload_0
      14: areturn

  public org.apache.dubbo.config.spring.reference.ReferenceBeanBuilder setCheck(java.lang.Boolean);
    Code:
       0: aload_0
       1: getfield      #4                  // Field attributes:Ljava/util/Map;
       4: ldc           #16                 // String check
       6: aload_1
       7: invokeinterface #9,  3            // InterfaceMethod java/util/Map.put:(Ljava/lang/Object;Ljava/lang/Object;)Ljava/lang/Object;
      12: pop
      13: aload_0
      14: areturn

  public org.apache.dubbo.config.spring.reference.ReferenceBeanBuilder setInit(java.lang.Boolean);
    Code:
       0: aload_0
       1: getfield      #4                  // Field attributes:Ljava/util/Map;
       4: ldc           #17                 // String init
       6: aload_1
       7: invokeinterface #9,  3            // InterfaceMethod java/util/Map.put:(Ljava/lang/Object;Ljava/lang/Object;)Ljava/lang/Object;
      12: pop
      13: aload_0
      14: areturn

  public org.apache.dubbo.config.spring.reference.ReferenceBeanBuilder setGeneric(java.lang.Boolean);
    Code:
       0: aload_0
       1: getfield      #4                  // Field attributes:Ljava/util/Map;
       4: ldc           #18                 // String generic
       6: aload_1
       7: invokeinterface #9,  3            // InterfaceMethod java/util/Map.put:(Ljava/lang/Object;Ljava/lang/Object;)Ljava/lang/Object;
      12: pop
      13: aload_0
      14: areturn

  public org.apache.dubbo.config.spring.reference.ReferenceBeanBuilder setInjvm(java.lang.Boolean);
    Code:
       0: aload_0
       1: getfield      #4                  // Field attributes:Ljava/util/Map;
       4: ldc           #19                 // String injvm
       6: aload_1
       7: invokeinterface #9,  3            // InterfaceMethod java/util/Map.put:(Ljava/lang/Object;Ljava/lang/Object;)Ljava/lang/Object;
      12: pop
      13: aload_0
      14: areturn

  public org.apache.dubbo.config.spring.reference.ReferenceBeanBuilder setListener(java.lang.String);
    Code:
       0: aload_0
       1: getfield      #4                  // Field attributes:Ljava/util/Map;
       4: ldc           #20                 // String listener
       6: aload_1
       7: invokeinterface #9,  3            // InterfaceMethod java/util/Map.put:(Ljava/lang/Object;Ljava/lang/Object;)Ljava/lang/Object;
      12: pop
      13: aload_0
      14: areturn

  public org.apache.dubbo.config.spring.reference.ReferenceBeanBuilder setLazy(java.lang.Boolean);
    Code:
       0: aload_0
       1: getfield      #4                  // Field attributes:Ljava/util/Map;
       4: ldc           #21                 // String lazy
       6: aload_1
       7: invokeinterface #9,  3            // InterfaceMethod java/util/Map.put:(Ljava/lang/Object;Ljava/lang/Object;)Ljava/lang/Object;
      12: pop
      13: aload_0
      14: areturn

  public org.apache.dubbo.config.spring.reference.ReferenceBeanBuilder setOnconnect(java.lang.String);
    Code:
       0: aload_0
       1: getfield      #4                  // Field attributes:Ljava/util/Map;
       4: ldc           #22                 // String onconnect
       6: aload_1
       7: invokeinterface #9,  3            // InterfaceMethod java/util/Map.put:(Ljava/lang/Object;Ljava/lang/Object;)Ljava/lang/Object;
      12: pop
      13: aload_0
      14: areturn

  public org.apache.dubbo.config.spring.reference.ReferenceBeanBuilder setOndisconnect(java.lang.String);
    Code:
       0: aload_0
       1: getfield      #4                  // Field attributes:Ljava/util/Map;
       4: ldc           #23                 // String ondisconnect
       6: aload_1
       7: invokeinterface #9,  3            // InterfaceMethod java/util/Map.put:(Ljava/lang/Object;Ljava/lang/Object;)Ljava/lang/Object;
      12: pop
      13: aload_0
      14: areturn

  public org.apache.dubbo.config.spring.reference.ReferenceBeanBuilder setReconnect(java.lang.String);
    Code:
       0: aload_0
       1: getfield      #4                  // Field attributes:Ljava/util/Map;
       4: ldc           #24                 // String reconnect
       6: aload_1
       7: invokeinterface #9,  3            // InterfaceMethod java/util/Map.put:(Ljava/lang/Object;Ljava/lang/Object;)Ljava/lang/Object;
      12: pop
      13: aload_0
      14: areturn

  public org.apache.dubbo.config.spring.reference.ReferenceBeanBuilder setSticky(java.lang.Boolean);
    Code:
       0: aload_0
       1: getfield      #4                  // Field attributes:Ljava/util/Map;
       4: ldc           #25                 // String sticky
       6: aload_1
       7: invokeinterface #9,  3            // InterfaceMethod java/util/Map.put:(Ljava/lang/Object;Ljava/lang/Object;)Ljava/lang/Object;
      12: pop
      13: aload_0
      14: areturn

  public org.apache.dubbo.config.spring.reference.ReferenceBeanBuilder setVersion(java.lang.String);
    Code:
       0: aload_0
       1: getfield      #4                  // Field attributes:Ljava/util/Map;
       4: ldc           #26                 // String version
       6: aload_1
       7: invokeinterface #9,  3            // InterfaceMethod java/util/Map.put:(Ljava/lang/Object;Ljava/lang/Object;)Ljava/lang/Object;
      12: pop
      13: aload_0
      14: areturn

  public org.apache.dubbo.config.spring.reference.ReferenceBeanBuilder setGroup(java.lang.String);
    Code:
       0: aload_0
       1: getfield      #4                  // Field attributes:Ljava/util/Map;
       4: ldc           #27                 // String group
       6: aload_1
       7: invokeinterface #9,  3            // InterfaceMethod java/util/Map.put:(Ljava/lang/Object;Ljava/lang/Object;)Ljava/lang/Object;
      12: pop
      13: aload_0
      14: areturn

  public org.apache.dubbo.config.spring.reference.ReferenceBeanBuilder setProvidedBy(java.lang.String);
    Code:
       0: aload_0
       1: getfield      #4                  // Field attributes:Ljava/util/Map;
       4: ldc           #28                 // String providedBy
       6: aload_1
       7: invokeinterface #9,  3            // InterfaceMethod java/util/Map.put:(Ljava/lang/Object;Ljava/lang/Object;)Ljava/lang/Object;
      12: pop
      13: aload_0
      14: areturn

  public org.apache.dubbo.config.spring.reference.ReferenceBeanBuilder setProviderPort(java.lang.Integer);
    Code:
       0: aload_0
       1: getfield      #4                  // Field attributes:Ljava/util/Map;
       4: ldc           #29                 // String providerPort
       6: aload_1
       7: invokeinterface #9,  3            // InterfaceMethod java/util/Map.put:(Ljava/lang/Object;Ljava/lang/Object;)Ljava/lang/Object;
      12: pop
      13: aload_0
      14: areturn

  public org.apache.dubbo.config.spring.reference.ReferenceBeanBuilder setStub(java.lang.String);
    Code:
       0: aload_0
       1: getfield      #4                  // Field attributes:Ljava/util/Map;
       4: ldc           #30                 // String stub
       6: aload_1
       7: invokeinterface #9,  3            // InterfaceMethod java/util/Map.put:(Ljava/lang/Object;Ljava/lang/Object;)Ljava/lang/Object;
      12: pop
      13: aload_0
      14: areturn

  public org.apache.dubbo.config.spring.reference.ReferenceBeanBuilder setCluster(java.lang.String);
    Code:
       0: aload_0
       1: getfield      #4                  // Field attributes:Ljava/util/Map;
       4: ldc           #31                 // String cluster
       6: aload_1
       7: invokeinterface #9,  3            // InterfaceMethod java/util/Map.put:(Ljava/lang/Object;Ljava/lang/Object;)Ljava/lang/Object;
      12: pop
      13: aload_0
      14: areturn

  public org.apache.dubbo.config.spring.reference.ReferenceBeanBuilder setProxy(java.lang.String);
    Code:
       0: aload_0
       1: getfield      #4                  // Field attributes:Ljava/util/Map;
       4: ldc           #32                 // String proxy
       6: aload_1
       7: invokeinterface #9,  3            // InterfaceMethod java/util/Map.put:(Ljava/lang/Object;Ljava/lang/Object;)Ljava/lang/Object;
      12: pop
      13: aload_0
      14: areturn

  public org.apache.dubbo.config.spring.reference.ReferenceBeanBuilder setConnections(java.lang.Integer);
    Code:
       0: aload_0
       1: getfield      #4                  // Field attributes:Ljava/util/Map;
       4: ldc           #33                 // String connections
       6: aload_1
       7: invokeinterface #9,  3            // InterfaceMethod java/util/Map.put:(Ljava/lang/Object;Ljava/lang/Object;)Ljava/lang/Object;
      12: pop
      13: aload_0
      14: areturn

  public org.apache.dubbo.config.spring.reference.ReferenceBeanBuilder setFilter(java.lang.String);
    Code:
       0: aload_0
       1: getfield      #4                  // Field attributes:Ljava/util/Map;
       4: ldc           #34                 // String filter
       6: aload_1
       7: invokeinterface #9,  3            // InterfaceMethod java/util/Map.put:(Ljava/lang/Object;Ljava/lang/Object;)Ljava/lang/Object;
      12: pop
      13: aload_0
      14: areturn

  public org.apache.dubbo.config.spring.reference.ReferenceBeanBuilder setLayer(java.lang.String);
    Code:
       0: aload_0
       1: getfield      #4                  // Field attributes:Ljava/util/Map;
       4: ldc           #35                 // String layer
       6: aload_1
       7: invokeinterface #9,  3            // InterfaceMethod java/util/Map.put:(Ljava/lang/Object;Ljava/lang/Object;)Ljava/lang/Object;
      12: pop
      13: aload_0
      14: areturn

  public org.apache.dubbo.config.spring.reference.ReferenceBeanBuilder setRegistry(java.lang.String[]);
    Code:
       0: aload_0
       1: getfield      #4                  // Field attributes:Ljava/util/Map;
       4: ldc           #36                 // String registry
       6: aload_1
       7: invokeinterface #9,  3            // InterfaceMethod java/util/Map.put:(Ljava/lang/Object;Ljava/lang/Object;)Ljava/lang/Object;
      12: pop
      13: aload_0
      14: areturn

  public org.apache.dubbo.config.spring.reference.ReferenceBeanBuilder setRegistry(org.apache.dubbo.config.RegistryConfig);
    Code:
       0: aload_0
       1: iconst_1
       2: anewarray     #37                 // class org/apache/dubbo/config/RegistryConfig
       5: dup
       6: iconst_0
       7: aload_1
       8: aastore
       9: invokestatic  #38                 // Method java/util/Arrays.asList:([Ljava/lang/Object;)Ljava/util/List;
      12: invokevirtual #39                 // Method setRegistries:(Ljava/util/List;)Lorg/apache/dubbo/config/spring/reference/ReferenceBeanBuilder;
      15: pop
      16: aload_0
      17: areturn

  public org.apache.dubbo.config.spring.reference.ReferenceBeanBuilder setRegistries(java.util.List<? extends org.apache.dubbo.config.RegistryConfig>);
    Code:
       0: aload_0
       1: getfield      #4                  // Field attributes:Ljava/util/Map;
       4: ldc           #40                 // String registries
       6: aload_1
       7: invokeinterface #9,  3            // InterfaceMethod java/util/Map.put:(Ljava/lang/Object;Ljava/lang/Object;)Ljava/lang/Object;
      12: pop
      13: aload_0
      14: areturn

  public org.apache.dubbo.config.spring.reference.ReferenceBeanBuilder setMethods(java.util.List<? extends org.apache.dubbo.config.MethodConfig>);
    Code:
       0: aload_0
       1: getfield      #4                  // Field attributes:Ljava/util/Map;
       4: ldc           #41                 // String methods
       6: aload_1
       7: invokeinterface #9,  3            // InterfaceMethod java/util/Map.put:(Ljava/lang/Object;Ljava/lang/Object;)Ljava/lang/Object;
      12: pop
      13: aload_0
      14: areturn

  public org.apache.dubbo.config.spring.reference.ReferenceBeanBuilder setMonitor(org.apache.dubbo.config.MonitorConfig);
    Code:
       0: aload_0
       1: getfield      #4                  // Field attributes:Ljava/util/Map;
       4: ldc           #42                 // String monitor
       6: aload_1
       7: invokeinterface #9,  3            // InterfaceMethod java/util/Map.put:(Ljava/lang/Object;Ljava/lang/Object;)Ljava/lang/Object;
      12: pop
      13: aload_0
      14: areturn

  public org.apache.dubbo.config.spring.reference.ReferenceBeanBuilder setMonitor(java.lang.String);
    Code:
       0: aload_0
       1: getfield      #4                  // Field attributes:Ljava/util/Map;
       4: ldc           #42                 // String monitor
       6: aload_1
       7: invokeinterface #9,  3            // InterfaceMethod java/util/Map.put:(Ljava/lang/Object;Ljava/lang/Object;)Ljava/lang/Object;
      12: pop
      13: aload_0
      14: areturn

  public org.apache.dubbo.config.spring.reference.ReferenceBeanBuilder setOwner(java.lang.String);
    Code:
       0: aload_0
       1: getfield      #4                  // Field attributes:Ljava/util/Map;
       4: ldc           #43                 // String owner
       6: aload_1
       7: invokeinterface #9,  3            // InterfaceMethod java/util/Map.put:(Ljava/lang/Object;Ljava/lang/Object;)Ljava/lang/Object;
      12: pop
      13: aload_0
      14: areturn

  public org.apache.dubbo.config.spring.reference.ReferenceBeanBuilder setCallbacks(java.lang.Integer);
    Code:
       0: aload_0
       1: getfield      #4                  // Field attributes:Ljava/util/Map;
       4: ldc           #44                 // String callbacks
       6: aload_1
       7: invokeinterface #9,  3            // InterfaceMethod java/util/Map.put:(Ljava/lang/Object;Ljava/lang/Object;)Ljava/lang/Object;
      12: pop
      13: aload_0
      14: areturn

  public org.apache.dubbo.config.spring.reference.ReferenceBeanBuilder setScope(java.lang.String);
    Code:
       0: aload_0
       1: getfield      #4                  // Field attributes:Ljava/util/Map;
       4: ldc           #45                 // String scope
       6: aload_1
       7: invokeinterface #9,  3            // InterfaceMethod java/util/Map.put:(Ljava/lang/Object;Ljava/lang/Object;)Ljava/lang/Object;
      12: pop
      13: aload_0
      14: areturn

  public org.apache.dubbo.config.spring.reference.ReferenceBeanBuilder setTag(java.lang.String);
    Code:
       0: aload_0
       1: getfield      #4                  // Field attributes:Ljava/util/Map;
       4: ldc           #46                 // String tag
       6: aload_1
       7: invokeinterface #9,  3            // InterfaceMethod java/util/Map.put:(Ljava/lang/Object;Ljava/lang/Object;)Ljava/lang/Object;
      12: pop
      13: aload_0
      14: areturn

  public org.apache.dubbo.config.spring.reference.ReferenceBeanBuilder setTimeout(java.lang.Integer);
    Code:
       0: aload_0
       1: getfield      #4                  // Field attributes:Ljava/util/Map;
       4: ldc           #47                 // String timeout
       6: aload_1
       7: invokeinterface #9,  3            // InterfaceMethod java/util/Map.put:(Ljava/lang/Object;Ljava/lang/Object;)Ljava/lang/Object;
      12: pop
      13: aload_0
      14: areturn

  public org.apache.dubbo.config.spring.reference.ReferenceBeanBuilder setRetries(java.lang.Integer);
    Code:
       0: aload_0
       1: getfield      #4                  // Field attributes:Ljava/util/Map;
       4: ldc           #48                 // String retries
       6: aload_1
       7: invokeinterface #9,  3            // InterfaceMethod java/util/Map.put:(Ljava/lang/Object;Ljava/lang/Object;)Ljava/lang/Object;
      12: pop
      13: aload_0
      14: areturn

  public org.apache.dubbo.config.spring.reference.ReferenceBeanBuilder setLoadBalance(java.lang.String);
    Code:
       0: aload_0
       1: getfield      #4                  // Field attributes:Ljava/util/Map;
       4: ldc           #49                 // String loadbalance
       6: aload_1
       7: invokeinterface #9,  3            // InterfaceMethod java/util/Map.put:(Ljava/lang/Object;Ljava/lang/Object;)Ljava/lang/Object;
      12: pop
      13: aload_0
      14: areturn

  public org.apache.dubbo.config.spring.reference.ReferenceBeanBuilder setAsync(java.lang.Boolean);
    Code:
       0: aload_0
       1: getfield      #4                  // Field attributes:Ljava/util/Map;
       4: ldc           #50                 // String async
       6: aload_1
       7: invokeinterface #9,  3            // InterfaceMethod java/util/Map.put:(Ljava/lang/Object;Ljava/lang/Object;)Ljava/lang/Object;
      12: pop
      13: aload_0
      14: areturn

  public org.apache.dubbo.config.spring.reference.ReferenceBeanBuilder setActives(java.lang.Integer);
    Code:
       0: aload_0
       1: getfield      #4                  // Field attributes:Ljava/util/Map;
       4: ldc           #51                 // String actives
       6: aload_1
       7: invokeinterface #9,  3            // InterfaceMethod java/util/Map.put:(Ljava/lang/Object;Ljava/lang/Object;)Ljava/lang/Object;
      12: pop
      13: aload_0
      14: areturn

  public org.apache.dubbo.config.spring.reference.ReferenceBeanBuilder setSent(java.lang.Boolean);
    Code:
       0: aload_0
       1: getfield      #4                  // Field attributes:Ljava/util/Map;
       4: ldc           #52                 // String sent
       6: aload_1
       7: invokeinterface #9,  3            // InterfaceMethod java/util/Map.put:(Ljava/lang/Object;Ljava/lang/Object;)Ljava/lang/Object;
      12: pop
      13: aload_0
      14: areturn

  public org.apache.dubbo.config.spring.reference.ReferenceBeanBuilder setMock(java.lang.String);
    Code:
       0: aload_0
       1: getfield      #4                  // Field attributes:Ljava/util/Map;
       4: ldc           #53                 // String mock
       6: aload_1
       7: invokeinterface #9,  3            // InterfaceMethod java/util/Map.put:(Ljava/lang/Object;Ljava/lang/Object;)Ljava/lang/Object;
      12: pop
      13: aload_0
      14: areturn

  public org.apache.dubbo.config.spring.reference.ReferenceBeanBuilder setMerger(java.lang.String);
    Code:
       0: aload_0
       1: getfield      #4                  // Field attributes:Ljava/util/Map;
       4: ldc           #54                 // String merger
       6: aload_1
       7: invokeinterface #9,  3            // InterfaceMethod java/util/Map.put:(Ljava/lang/Object;Ljava/lang/Object;)Ljava/lang/Object;
      12: pop
      13: aload_0
      14: areturn

  public org.apache.dubbo.config.spring.reference.ReferenceBeanBuilder setCache(java.lang.String);
    Code:
       0: aload_0
       1: getfield      #4                  // Field attributes:Ljava/util/Map;
       4: ldc           #55                 // String cache
       6: aload_1
       7: invokeinterface #9,  3            // InterfaceMethod java/util/Map.put:(Ljava/lang/Object;Ljava/lang/Object;)Ljava/lang/Object;
      12: pop
      13: aload_0
      14: areturn

  public org.apache.dubbo.config.spring.reference.ReferenceBeanBuilder setValidation(java.lang.String);
    Code:
       0: aload_0
       1: getfield      #4                  // Field attributes:Ljava/util/Map;
       4: ldc           #56                 // String validation
       6: aload_1
       7: invokeinterface #9,  3            // InterfaceMethod java/util/Map.put:(Ljava/lang/Object;Ljava/lang/Object;)Ljava/lang/Object;
      12: pop
      13: aload_0
      14: areturn

  public org.apache.dubbo.config.spring.reference.ReferenceBeanBuilder setParameters(java.util.Map<java.lang.String, java.lang.String>);
    Code:
       0: aload_0
       1: getfield      #4                  // Field attributes:Ljava/util/Map;
       4: ldc           #57                 // String parameters
       6: aload_1
       7: invokeinterface #9,  3            // InterfaceMethod java/util/Map.put:(Ljava/lang/Object;Ljava/lang/Object;)Ljava/lang/Object;
      12: pop
      13: aload_0
      14: areturn
}
