Compiled from "ReferenceCreator.java"
public class org.apache.dubbo.config.spring.reference.ReferenceCreator {
  static final java.lang.String[] IGNORE_FIELD_NAMES;

  private static final java.lang.String ONRETURN;

  private static final java.lang.String ONTHROW;

  private static final java.lang.String ONINVOKE;

  private static final java.lang.String ISRETURN;

  private static final java.lang.String METHOD;

  protected final org.apache.dubbo.common.logger.Logger logger;

  protected final java.util.Map<java.lang.String, java.lang.Object> attributes;

  protected final org.springframework.context.ApplicationContext applicationContext;

  protected final java.lang.ClassLoader classLoader;

  protected java.lang.Class<?> defaultInterfaceClass;

  private final org.apache.dubbo.rpc.model.ModuleModel moduleModel;

  private org.apache.dubbo.config.spring.reference.ReferenceCreator(java.util.Map<java.lang.String, java.lang.Object>, org.springframework.context.ApplicationContext);
    Code:
       0: aload_0
       1: invokespecial #1                  // Method java/lang/Object."<init>":()V
       4: aload_0
       5: aload_0
       6: invokevirtual #2                  // Method java/lang/Object.getClass:()Ljava/lang/Class;
       9: invokestatic  #3                  // Method org/apache/dubbo/common/logger/LoggerFactory.getLogger:(Ljava/lang/Class;)Lorg/apache/dubbo/common/logger/Logger;
      12: putfield      #4                  // Field logger:Lorg/apache/dubbo/common/logger/Logger;
      15: aload_1
      16: ldc           #5                  // String The Annotation attributes must not be null!
      18: invokestatic  #6                  // Method org/springframework/util/Assert.notNull:(Ljava/lang/Object;Ljava/lang/String;)V
      21: aload_2
      22: ldc           #7                  // String The ApplicationContext must not be null!
      24: invokestatic  #6                  // Method org/springframework/util/Assert.notNull:(Ljava/lang/Object;Ljava/lang/String;)V
      27: aload_0
      28: aload_1
      29: putfield      #8                  // Field attributes:Ljava/util/Map;
      32: aload_0
      33: aload_2
      34: putfield      #9                  // Field applicationContext:Lorg/springframework/context/ApplicationContext;
      37: aload_0
      38: aload_2
      39: invokeinterface #10,  1           // InterfaceMethod org/springframework/context/ApplicationContext.getClassLoader:()Ljava/lang/ClassLoader;
      44: ifnull        56
      47: aload_2
      48: invokeinterface #10,  1           // InterfaceMethod org/springframework/context/ApplicationContext.getClassLoader:()Ljava/lang/ClassLoader;
      53: goto          62
      56: invokestatic  #11                 // Method java/lang/Thread.currentThread:()Ljava/lang/Thread;
      59: invokevirtual #12                 // Method java/lang/Thread.getContextClassLoader:()Ljava/lang/ClassLoader;
      62: putfield      #13                 // Field classLoader:Ljava/lang/ClassLoader;
      65: aload_0
      66: aload_2
      67: invokestatic  #14                 // InterfaceMethod org/apache/dubbo/config/spring/util/DubboBeanUtils.getModuleModel:(Lorg/springframework/beans/factory/BeanFactory;)Lorg/apache/dubbo/rpc/model/ModuleModel;
      70: putfield      #15                 // Field moduleModel:Lorg/apache/dubbo/rpc/model/ModuleModel;
      73: aload_0
      74: getfield      #15                 // Field moduleModel:Lorg/apache/dubbo/rpc/model/ModuleModel;
      77: ldc           #16                 // String ModuleModel not found in Spring ApplicationContext
      79: invokestatic  #6                  // Method org/springframework/util/Assert.notNull:(Ljava/lang/Object;Ljava/lang/String;)V
      82: return

  public final org.apache.dubbo.config.ReferenceConfig build() throws java.lang.Exception;
    Code:
       0: new           #17                 // class org/apache/dubbo/config/ReferenceConfig
       3: dup
       4: invokespecial #18                 // Method org/apache/dubbo/config/ReferenceConfig."<init>":()V
       7: astore_1
       8: aload_0
       9: aload_1
      10: invokevirtual #19                 // Method configureBean:(Lorg/apache/dubbo/config/ReferenceConfig;)V
      13: aload_0
      14: getfield      #4                  // Field logger:Lorg/apache/dubbo/common/logger/Logger;
      17: invokeinterface #20,  1           // InterfaceMethod org/apache/dubbo/common/logger/Logger.isInfoEnabled:()Z
      22: ifeq          79
      25: aload_0
      26: getfield      #4                  // Field logger:Lorg/apache/dubbo/common/logger/Logger;
      29: new           #21                 // class java/lang/StringBuilder
      32: dup
      33: invokespecial #22                 // Method java/lang/StringBuilder."<init>":()V
      36: ldc           #23                 // String The configBean[type:
      38: invokevirtual #24                 // Method java/lang/StringBuilder.append:(Ljava/lang/String;)Ljava/lang/StringBuilder;
      41: aload_1
      42: invokevirtual #2                  // Method java/lang/Object.getClass:()Ljava/lang/Class;
      45: invokevirtual #25                 // Method java/lang/Class.getSimpleName:()Ljava/lang/String;
      48: invokevirtual #24                 // Method java/lang/StringBuilder.append:(Ljava/lang/String;)Ljava/lang/StringBuilder;
      51: ldc           #26                 // String <
      53: invokevirtual #24                 // Method java/lang/StringBuilder.append:(Ljava/lang/String;)Ljava/lang/StringBuilder;
      56: aload_0
      57: getfield      #27                 // Field defaultInterfaceClass:Ljava/lang/Class;
      60: invokevirtual #28                 // Method java/lang/Class.getTypeName:()Ljava/lang/String;
      63: invokevirtual #24                 // Method java/lang/StringBuilder.append:(Ljava/lang/String;)Ljava/lang/StringBuilder;
      66: ldc           #29                 // String >] has been built.
      68: invokevirtual #24                 // Method java/lang/StringBuilder.append:(Ljava/lang/String;)Ljava/lang/StringBuilder;
      71: invokevirtual #30                 // Method java/lang/StringBuilder.toString:()Ljava/lang/String;
      74: invokeinterface #31,  2           // InterfaceMethod org/apache/dubbo/common/logger/Logger.info:(Ljava/lang/String;)V
      79: aload_1
      80: areturn

  protected void configureBean(org.apache.dubbo.config.ReferenceConfig) throws java.lang.Exception;
    Code:
       0: aload_0
       1: aload_1
       2: invokevirtual #32                 // Method populateBean:(Lorg/apache/dubbo/config/ReferenceConfig;)V
       5: aload_0
       6: aload_1
       7: invokespecial #33                 // Method configureMonitorConfig:(Lorg/apache/dubbo/config/ReferenceConfig;)V
      10: aload_0
      11: aload_1
      12: invokespecial #34                 // Method configureModuleConfig:(Lorg/apache/dubbo/config/ReferenceConfig;)V
      15: aload_0
      16: aload_1
      17: invokespecial #35                 // Method configureConsumerConfig:(Lorg/apache/dubbo/config/ReferenceConfig;)V
      20: return

  private void configureMonitorConfig(org.apache.dubbo.config.ReferenceConfig);
    Code:
       0: aload_0
       1: getfield      #8                  // Field attributes:Ljava/util/Map;
       4: ldc           #36                 // String monitor
       6: invokestatic  #37                 // Method com/alibaba/spring/util/AnnotationUtils.getAttribute:(Ljava/util/Map;Ljava/lang/String;)Ljava/lang/Object;
       9: checkcast     #38                 // class java/lang/String
      12: astore_2
      13: aload_2
      14: invokestatic  #39                 // Method org/springframework/util/StringUtils.hasText:(Ljava/lang/String;)Z
      17: ifeq          36
      20: aload_0
      21: aload_2
      22: ldc           #40                 // class org/apache/dubbo/config/MonitorConfig
      24: invokespecial #41                 // Method getConfig:(Ljava/lang/String;Ljava/lang/Class;)Lorg/apache/dubbo/config/AbstractConfig;
      27: checkcast     #40                 // class org/apache/dubbo/config/MonitorConfig
      30: astore_3
      31: aload_1
      32: aload_3
      33: invokevirtual #42                 // Method org/apache/dubbo/config/ReferenceConfig.setMonitor:(Lorg/apache/dubbo/config/MonitorConfig;)V
      36: return

  private void configureModuleConfig(org.apache.dubbo.config.ReferenceConfig);
    Code:
       0: aload_0
       1: getfield      #8                  // Field attributes:Ljava/util/Map;
       4: ldc           #43                 // String module
       6: invokestatic  #37                 // Method com/alibaba/spring/util/AnnotationUtils.getAttribute:(Ljava/util/Map;Ljava/lang/String;)Ljava/lang/Object;
       9: checkcast     #38                 // class java/lang/String
      12: astore_2
      13: aload_2
      14: invokestatic  #39                 // Method org/springframework/util/StringUtils.hasText:(Ljava/lang/String;)Z
      17: ifeq          36
      20: aload_0
      21: aload_2
      22: ldc           #44                 // class org/apache/dubbo/config/ModuleConfig
      24: invokespecial #41                 // Method getConfig:(Ljava/lang/String;Ljava/lang/Class;)Lorg/apache/dubbo/config/AbstractConfig;
      27: checkcast     #44                 // class org/apache/dubbo/config/ModuleConfig
      30: astore_3
      31: aload_1
      32: aload_3
      33: invokevirtual #45                 // Method org/apache/dubbo/config/ReferenceConfig.setModule:(Lorg/apache/dubbo/config/ModuleConfig;)V
      36: return

  private void configureConsumerConfig(org.apache.dubbo.config.ReferenceConfig<?>);
    Code:
       0: aconst_null
       1: astore_2
       2: aload_0
       3: getfield      #8                  // Field attributes:Ljava/util/Map;
       6: ldc           #46                 // String consumer
       8: invokestatic  #37                 // Method com/alibaba/spring/util/AnnotationUtils.getAttribute:(Ljava/util/Map;Ljava/lang/String;)Ljava/lang/Object;
      11: astore_3
      12: aload_3
      13: ifnull        87
      16: aload_3
      17: instanceof    #38                 // class java/lang/String
      20: ifeq          40
      23: aload_0
      24: aload_3
      25: checkcast     #38                 // class java/lang/String
      28: ldc           #47                 // class org/apache/dubbo/config/ConsumerConfig
      30: invokespecial #41                 // Method getConfig:(Ljava/lang/String;Ljava/lang/Class;)Lorg/apache/dubbo/config/AbstractConfig;
      33: checkcast     #47                 // class org/apache/dubbo/config/ConsumerConfig
      36: astore_2
      37: goto          82
      40: aload_3
      41: instanceof    #47                 // class org/apache/dubbo/config/ConsumerConfig
      44: ifeq          55
      47: aload_3
      48: checkcast     #47                 // class org/apache/dubbo/config/ConsumerConfig
      51: astore_2
      52: goto          82
      55: new           #48                 // class java/lang/IllegalArgumentException
      58: dup
      59: new           #21                 // class java/lang/StringBuilder
      62: dup
      63: invokespecial #22                 // Method java/lang/StringBuilder."<init>":()V
      66: ldc           #49                 // String Unexpected \'consumer\' attribute value:
      68: invokevirtual #24                 // Method java/lang/StringBuilder.append:(Ljava/lang/String;)Ljava/lang/StringBuilder;
      71: aload_3
      72: invokevirtual #50                 // Method java/lang/StringBuilder.append:(Ljava/lang/Object;)Ljava/lang/StringBuilder;
      75: invokevirtual #30                 // Method java/lang/StringBuilder.toString:()Ljava/lang/String;
      78: invokespecial #51                 // Method java/lang/IllegalArgumentException."<init>":(Ljava/lang/String;)V
      81: athrow
      82: aload_1
      83: aload_2
      84: invokevirtual #52                 // Method org/apache/dubbo/config/ReferenceConfig.setConsumer:(Lorg/apache/dubbo/config/ConsumerConfig;)V
      87: return

  private <T extends org.apache.dubbo.config.AbstractConfig> T getConfig(java.lang.String, java.lang.Class<T>);
    Code:
       0: aload_0
       1: getfield      #15                 // Field moduleModel:Lorg/apache/dubbo/rpc/model/ModuleModel;
       4: invokevirtual #53                 // Method org/apache/dubbo/rpc/model/ModuleModel.getConfigManager:()Lorg/apache/dubbo/config/context/ModuleConfigManager;
       7: aload_2
       8: aload_1
       9: invokevirtual #54                 // Method org/apache/dubbo/config/context/ModuleConfigManager.getConfig:(Ljava/lang/Class;Ljava/lang/String;)Ljava/util/Optional;
      12: aconst_null
      13: invokevirtual #55                 // Method java/util/Optional.orElse:(Ljava/lang/Object;)Ljava/lang/Object;
      16: checkcast     #56                 // class org/apache/dubbo/config/AbstractConfig
      19: astore_3
      20: aload_3
      21: ifnonnull     52
      24: aload_0
      25: getfield      #9                  // Field applicationContext:Lorg/springframework/context/ApplicationContext;
      28: aload_1
      29: invokeinterface #57,  2           // InterfaceMethod org/springframework/context/ApplicationContext.containsBean:(Ljava/lang/String;)Z
      34: ifeq          52
      37: aload_0
      38: getfield      #9                  // Field applicationContext:Lorg/springframework/context/ApplicationContext;
      41: aload_1
      42: aload_2
      43: invokeinterface #58,  3           // InterfaceMethod org/springframework/context/ApplicationContext.getBean:(Ljava/lang/String;Ljava/lang/Class;)Ljava/lang/Object;
      48: checkcast     #56                 // class org/apache/dubbo/config/AbstractConfig
      51: astore_3
      52: aload_3
      53: ifnonnull     90
      56: new           #48                 // class java/lang/IllegalArgumentException
      59: dup
      60: new           #21                 // class java/lang/StringBuilder
      63: dup
      64: invokespecial #22                 // Method java/lang/StringBuilder."<init>":()V
      67: aload_2
      68: invokevirtual #25                 // Method java/lang/Class.getSimpleName:()Ljava/lang/String;
      71: invokevirtual #24                 // Method java/lang/StringBuilder.append:(Ljava/lang/String;)Ljava/lang/StringBuilder;
      74: ldc           #59                 // String  not found:
      76: invokevirtual #24                 // Method java/lang/StringBuilder.append:(Ljava/lang/String;)Ljava/lang/StringBuilder;
      79: aload_1
      80: invokevirtual #24                 // Method java/lang/StringBuilder.append:(Ljava/lang/String;)Ljava/lang/StringBuilder;
      83: invokevirtual #30                 // Method java/lang/StringBuilder.toString:()Ljava/lang/String;
      86: invokespecial #51                 // Method java/lang/IllegalArgumentException."<init>":(Ljava/lang/String;)V
      89: athrow
      90: aload_3
      91: areturn

  protected void populateBean(org.apache.dubbo.config.ReferenceConfig);
    Code:
       0: aload_0
       1: getfield      #27                 // Field defaultInterfaceClass:Ljava/lang/Class;
       4: ldc           #60                 // String The default interface class cannot be empty!
       6: invokestatic  #6                  // Method org/springframework/util/Assert.notNull:(Ljava/lang/Object;Ljava/lang/String;)V
       9: aload_0
      10: getfield      #8                  // Field attributes:Ljava/util/Map;
      13: aload_0
      14: getfield      #27                 // Field defaultInterfaceClass:Ljava/lang/Class;
      17: invokestatic  #61                 // Method org/apache/dubbo/config/spring/reference/ReferenceBeanSupport.convertReferenceProps:(Ljava/util/Map;Ljava/lang/Class;)V
      20: new           #62                 // class org/springframework/validation/DataBinder
      23: dup
      24: aload_1
      25: invokespecial #63                 // Method org/springframework/validation/DataBinder."<init>":(Ljava/lang/Object;)V
      28: astore_2
      29: aload_2
      30: ldc           #38                 // class java/lang/String
      32: ldc           #64                 // String filter
      34: new           #65                 // class org/springframework/beans/propertyeditors/StringTrimmerEditor
      37: dup
      38: iconst_1
      39: invokespecial #66                 // Method org/springframework/beans/propertyeditors/StringTrimmerEditor."<init>":(Z)V
      42: invokevirtual #67                 // Method org/springframework/validation/DataBinder.registerCustomEditor:(Ljava/lang/Class;Ljava/lang/String;Ljava/beans/PropertyEditor;)V
      45: aload_2
      46: ldc           #38                 // class java/lang/String
      48: ldc           #68                 // String listener
      50: new           #65                 // class org/springframework/beans/propertyeditors/StringTrimmerEditor
      53: dup
      54: iconst_1
      55: invokespecial #66                 // Method org/springframework/beans/propertyeditors/StringTrimmerEditor."<init>":(Z)V
      58: invokevirtual #67                 // Method org/springframework/validation/DataBinder.registerCustomEditor:(Ljava/lang/Class;Ljava/lang/String;Ljava/beans/PropertyEditor;)V
      61: new           #69                 // class org/springframework/core/convert/support/DefaultConversionService
      64: dup
      65: invokespecial #70                 // Method org/springframework/core/convert/support/DefaultConversionService."<init>":()V
      68: astore_3
      69: aload_3
      70: ldc           #71                 // class "[Ljava/lang/String;"
      72: ldc           #72                 // class java/util/Map
      74: invokedynamic #73,  0             // InvokeDynamic #0:convert:()Lorg/springframework/core/convert/converter/Converter;
      79: invokevirtual #74                 // Method org/springframework/core/convert/support/DefaultConversionService.addConverter:(Ljava/lang/Class;Ljava/lang/Class;Lorg/springframework/core/convert/converter/Converter;)V
      82: aload_3
      83: ldc           #72                 // class java/util/Map
      85: ldc           #75                 // class org/apache/dubbo/config/MethodConfig
      87: aload_0
      88: aload_3
      89: invokedynamic #76,  0             // InvokeDynamic #1:convert:(Lorg/apache/dubbo/config/spring/reference/ReferenceCreator;Lorg/springframework/core/convert/support/DefaultConversionService;)Lorg/springframework/core/convert/converter/Converter;
      94: invokevirtual #74                 // Method org/springframework/core/convert/support/DefaultConversionService.addConverter:(Ljava/lang/Class;Ljava/lang/Class;Lorg/springframework/core/convert/converter/Converter;)V
      97: aload_3
      98: ldc           #77                 // class org/apache/dubbo/config/annotation/Method
     100: ldc           #75                 // class org/apache/dubbo/config/MethodConfig
     102: aload_0
     103: aload_3
     104: invokedynamic #78,  0             // InvokeDynamic #2:convert:(Lorg/apache/dubbo/config/spring/reference/ReferenceCreator;Lorg/springframework/core/convert/support/DefaultConversionService;)Lorg/springframework/core/convert/converter/Converter;
     109: invokevirtual #74                 // Method org/springframework/core/convert/support/DefaultConversionService.addConverter:(Ljava/lang/Class;Ljava/lang/Class;Lorg/springframework/core/convert/converter/Converter;)V
     112: aload_3
     113: ldc           #72                 // class java/util/Map
     115: ldc           #79                 // class org/apache/dubbo/config/ArgumentConfig
     117: aload_0
     118: aload_3
     119: invokedynamic #80,  0             // InvokeDynamic #3:convert:(Lorg/apache/dubbo/config/spring/reference/ReferenceCreator;Lorg/springframework/core/convert/support/DefaultConversionService;)Lorg/springframework/core/convert/converter/Converter;
     124: invokevirtual #74                 // Method org/springframework/core/convert/support/DefaultConversionService.addConverter:(Ljava/lang/Class;Ljava/lang/Class;Lorg/springframework/core/convert/converter/Converter;)V
     127: aload_3
     128: ldc           #81                 // class org/apache/dubbo/config/annotation/Argument
     130: ldc           #79                 // class org/apache/dubbo/config/ArgumentConfig
     132: aload_0
     133: aload_3
     134: invokedynamic #82,  0             // InvokeDynamic #4:convert:(Lorg/apache/dubbo/config/spring/reference/ReferenceCreator;Lorg/springframework/core/convert/support/DefaultConversionService;)Lorg/springframework/core/convert/converter/Converter;
     139: invokevirtual #74                 // Method org/springframework/core/convert/support/DefaultConversionService.addConverter:(Ljava/lang/Class;Ljava/lang/Class;Lorg/springframework/core/convert/converter/Converter;)V
     142: aload_2
     143: aload_3
     144: invokevirtual #83                 // Method org/springframework/validation/DataBinder.setConversionService:(Lorg/springframework/core/convert/ConversionService;)V
     147: aload_2
     148: new           #84                 // class org/apache/dubbo/config/spring/beans/factory/annotation/AnnotationPropertyValuesAdapter
     151: dup
     152: aload_0
     153: getfield      #8                  // Field attributes:Ljava/util/Map;
     156: aload_0
     157: getfield      #9                  // Field applicationContext:Lorg/springframework/context/ApplicationContext;
     160: invokeinterface #85,  1           // InterfaceMethod org/springframework/context/ApplicationContext.getEnvironment:()Lorg/springframework/core/env/Environment;
     165: getstatic     #86                 // Field IGNORE_FIELD_NAMES:[Ljava/lang/String;
     168: invokespecial #87                 // Method org/apache/dubbo/config/spring/beans/factory/annotation/AnnotationPropertyValuesAdapter."<init>":(Ljava/util/Map;Lorg/springframework/core/env/PropertyResolver;[Ljava/lang/String;)V
     171: invokevirtual #88                 // Method org/springframework/validation/DataBinder.bind:(Lorg/springframework/beans/PropertyValues;)V
     174: return

  private org.apache.dubbo.config.MethodConfig createMethodConfig(java.util.Map<java.lang.String, java.lang.Object>, org.springframework.core.convert.support.DefaultConversionService);
    Code:
       0: iconst_3
       1: anewarray     #38                 // class java/lang/String
       4: dup
       5: iconst_0
       6: ldc           #90                 // String oninvoke
       8: aastore
       9: dup
      10: iconst_1
      11: ldc           #91                 // String onreturn
      13: aastore
      14: dup
      15: iconst_2
      16: ldc           #92                 // String onthrow
      18: aastore
      19: astore_3
      20: aload_3
      21: astore        4
      23: aload         4
      25: arraylength
      26: istore        5
      28: iconst_0
      29: istore        6
      31: iload         6
      33: iload         5
      35: if_icmpge     184
      38: aload         4
      40: iload         6
      42: aaload
      43: astore        7
      45: aload_1
      46: aload         7
      48: invokeinterface #93,  2           // InterfaceMethod java/util/Map.get:(Ljava/lang/Object;)Ljava/lang/Object;
      53: astore        8
      55: aload         8
      57: instanceof    #38                 // class java/lang/String
      60: ifeq          178
      63: aload         8
      65: checkcast     #38                 // class java/lang/String
      68: astore        9
      70: aload         9
      72: ldc           #94                 // String .
      74: invokevirtual #95                 // Method java/lang/String.lastIndexOf:(Ljava/lang/String;)I
      77: istore        10
      79: iload         10
      81: iconst_m1
      82: if_icmpeq     158
      85: aload         9
      87: iconst_0
      88: iload         10
      90: invokevirtual #96                 // Method java/lang/String.substring:(II)Ljava/lang/String;
      93: astore        11
      95: aload         9
      97: iload         10
      99: iconst_1
     100: iadd
     101: invokevirtual #97                 // Method java/lang/String.substring:(I)Ljava/lang/String;
     104: astore        12
     106: aload_1
     107: aload         7
     109: aload_0
     110: getfield      #9                  // Field applicationContext:Lorg/springframework/context/ApplicationContext;
     113: aload         11
     115: invokeinterface #98,  2           // InterfaceMethod org/springframework/context/ApplicationContext.getBean:(Ljava/lang/String;)Ljava/lang/Object;
     120: invokeinterface #99,  3           // InterfaceMethod java/util/Map.put:(Ljava/lang/Object;Ljava/lang/Object;)Ljava/lang/Object;
     125: pop
     126: aload_1
     127: new           #21                 // class java/lang/StringBuilder
     130: dup
     131: invokespecial #22                 // Method java/lang/StringBuilder."<init>":()V
     134: aload         7
     136: invokevirtual #24                 // Method java/lang/StringBuilder.append:(Ljava/lang/String;)Ljava/lang/StringBuilder;
     139: ldc           #100                // String Method
     141: invokevirtual #24                 // Method java/lang/StringBuilder.append:(Ljava/lang/String;)Ljava/lang/StringBuilder;
     144: invokevirtual #30                 // Method java/lang/StringBuilder.toString:()Ljava/lang/String;
     147: aload         12
     149: invokeinterface #99,  3           // InterfaceMethod java/util/Map.put:(Ljava/lang/Object;Ljava/lang/Object;)Ljava/lang/Object;
     154: pop
     155: goto          178
     158: aload_1
     159: aload         7
     161: aload_0
     162: getfield      #9                  // Field applicationContext:Lorg/springframework/context/ApplicationContext;
     165: aload         9
     167: invokeinterface #98,  2           // InterfaceMethod org/springframework/context/ApplicationContext.getBean:(Ljava/lang/String;)Ljava/lang/Object;
     172: invokeinterface #99,  3           // InterfaceMethod java/util/Map.put:(Ljava/lang/Object;Ljava/lang/Object;)Ljava/lang/Object;
     177: pop
     178: iinc          6, 1
     181: goto          31
     184: new           #75                 // class org/apache/dubbo/config/MethodConfig
     187: dup
     188: invokespecial #101                // Method org/apache/dubbo/config/MethodConfig."<init>":()V
     191: astore        4
     193: new           #62                 // class org/springframework/validation/DataBinder
     196: dup
     197: aload         4
     199: invokespecial #63                 // Method org/springframework/validation/DataBinder."<init>":(Ljava/lang/Object;)V
     202: astore        5
     204: aload         4
     206: aload_1
     207: ldc           #102                // String isReturn
     209: invokeinterface #93,  2           // InterfaceMethod java/util/Map.get:(Ljava/lang/Object;)Ljava/lang/Object;
     214: checkcast     #103                // class java/lang/Boolean
     217: invokevirtual #104                // Method org/apache/dubbo/config/MethodConfig.setReturn:(Ljava/lang/Boolean;)V
     220: aload         5
     222: aload_2
     223: invokevirtual #83                 // Method org/springframework/validation/DataBinder.setConversionService:(Lorg/springframework/core/convert/ConversionService;)V
     226: new           #84                 // class org/apache/dubbo/config/spring/beans/factory/annotation/AnnotationPropertyValuesAdapter
     229: dup
     230: aload_1
     231: aload_0
     232: getfield      #9                  // Field applicationContext:Lorg/springframework/context/ApplicationContext;
     235: invokeinterface #85,  1           // InterfaceMethod org/springframework/context/ApplicationContext.getEnvironment:()Lorg/springframework/core/env/Environment;
     240: iconst_0
     241: anewarray     #38                 // class java/lang/String
     244: invokespecial #87                 // Method org/apache/dubbo/config/spring/beans/factory/annotation/AnnotationPropertyValuesAdapter."<init>":(Ljava/util/Map;Lorg/springframework/core/env/PropertyResolver;[Ljava/lang/String;)V
     247: astore        6
     249: aload         5
     251: aload         6
     253: invokevirtual #88                 // Method org/springframework/validation/DataBinder.bind:(Lorg/springframework/beans/PropertyValues;)V
     256: aload         4
     258: areturn

  public static org.apache.dubbo.config.spring.reference.ReferenceCreator create(java.util.Map<java.lang.String, java.lang.Object>, org.springframework.context.ApplicationContext);
    Code:
       0: new           #89                 // class org/apache/dubbo/config/spring/reference/ReferenceCreator
       3: dup
       4: aload_0
       5: aload_1
       6: invokespecial #105                // Method "<init>":(Ljava/util/Map;Lorg/springframework/context/ApplicationContext;)V
       9: areturn

  public org.apache.dubbo.config.spring.reference.ReferenceCreator defaultInterfaceClass(java.lang.Class<?>);
    Code:
       0: aload_0
       1: aload_1
       2: putfield      #27                 // Field defaultInterfaceClass:Ljava/lang/Class;
       5: aload_0
       6: areturn

  private org.apache.dubbo.config.ArgumentConfig lambda$populateBean$3(org.springframework.core.convert.support.DefaultConversionService, org.apache.dubbo.config.annotation.Argument);
    Code:
       0: new           #79                 // class org/apache/dubbo/config/ArgumentConfig
       3: dup
       4: invokespecial #106                // Method org/apache/dubbo/config/ArgumentConfig."<init>":()V
       7: astore_3
       8: new           #62                 // class org/springframework/validation/DataBinder
      11: dup
      12: aload_3
      13: invokespecial #63                 // Method org/springframework/validation/DataBinder."<init>":(Ljava/lang/Object;)V
      16: astore        4
      18: aload         4
      20: aload_1
      21: invokevirtual #83                 // Method org/springframework/validation/DataBinder.setConversionService:(Lorg/springframework/core/convert/ConversionService;)V
      24: aload         4
      26: new           #84                 // class org/apache/dubbo/config/spring/beans/factory/annotation/AnnotationPropertyValuesAdapter
      29: dup
      30: aload_2
      31: aload_0
      32: getfield      #9                  // Field applicationContext:Lorg/springframework/context/ApplicationContext;
      35: invokeinterface #85,  1           // InterfaceMethod org/springframework/context/ApplicationContext.getEnvironment:()Lorg/springframework/core/env/Environment;
      40: iconst_0
      41: anewarray     #38                 // class java/lang/String
      44: invokespecial #107                // Method org/apache/dubbo/config/spring/beans/factory/annotation/AnnotationPropertyValuesAdapter."<init>":(Ljava/lang/annotation/Annotation;Lorg/springframework/core/env/PropertyResolver;[Ljava/lang/String;)V
      47: invokevirtual #88                 // Method org/springframework/validation/DataBinder.bind:(Lorg/springframework/beans/PropertyValues;)V
      50: aload_3
      51: areturn

  private org.apache.dubbo.config.ArgumentConfig lambda$populateBean$2(org.springframework.core.convert.support.DefaultConversionService, java.util.Map);
    Code:
       0: new           #79                 // class org/apache/dubbo/config/ArgumentConfig
       3: dup
       4: invokespecial #106                // Method org/apache/dubbo/config/ArgumentConfig."<init>":()V
       7: astore_3
       8: new           #62                 // class org/springframework/validation/DataBinder
      11: dup
      12: aload_3
      13: invokespecial #63                 // Method org/springframework/validation/DataBinder."<init>":(Ljava/lang/Object;)V
      16: astore        4
      18: aload         4
      20: aload_1
      21: invokevirtual #83                 // Method org/springframework/validation/DataBinder.setConversionService:(Lorg/springframework/core/convert/ConversionService;)V
      24: aload         4
      26: new           #84                 // class org/apache/dubbo/config/spring/beans/factory/annotation/AnnotationPropertyValuesAdapter
      29: dup
      30: aload_2
      31: aload_0
      32: getfield      #9                  // Field applicationContext:Lorg/springframework/context/ApplicationContext;
      35: invokeinterface #85,  1           // InterfaceMethod org/springframework/context/ApplicationContext.getEnvironment:()Lorg/springframework/core/env/Environment;
      40: iconst_0
      41: anewarray     #38                 // class java/lang/String
      44: invokespecial #87                 // Method org/apache/dubbo/config/spring/beans/factory/annotation/AnnotationPropertyValuesAdapter."<init>":(Ljava/util/Map;Lorg/springframework/core/env/PropertyResolver;[Ljava/lang/String;)V
      47: invokevirtual #88                 // Method org/springframework/validation/DataBinder.bind:(Lorg/springframework/beans/PropertyValues;)V
      50: aload_3
      51: areturn

  private org.apache.dubbo.config.MethodConfig lambda$populateBean$1(org.springframework.core.convert.support.DefaultConversionService, org.apache.dubbo.config.annotation.Method);
    Code:
       0: aload_2
       1: iconst_1
       2: iconst_0
       3: anewarray     #38                 // class java/lang/String
       6: invokestatic  #108                // Method com/alibaba/spring/util/AnnotationUtils.getAnnotationAttributes:(Ljava/lang/annotation/Annotation;Z[Ljava/lang/String;)Lorg/springframework/core/annotation/AnnotationAttributes;
       9: astore_3
      10: aload_0
      11: aload_3
      12: aload_1
      13: invokespecial #109                // Method createMethodConfig:(Ljava/util/Map;Lorg/springframework/core/convert/support/DefaultConversionService;)Lorg/apache/dubbo/config/MethodConfig;
      16: areturn

  private org.apache.dubbo.config.MethodConfig lambda$populateBean$0(org.springframework.core.convert.support.DefaultConversionService, java.util.Map);
    Code:
       0: aload_0
       1: aload_2
       2: aload_1
       3: invokespecial #109                // Method createMethodConfig:(Ljava/util/Map;Lorg/springframework/core/convert/support/DefaultConversionService;)Lorg/apache/dubbo/config/MethodConfig;
       6: areturn

  static {};
    Code:
       0: bipush        6
       2: anewarray     #38                 // class java/lang/String
       5: dup
       6: iconst_0
       7: ldc           #110                // String application
       9: aastore
      10: dup
      11: iconst_1
      12: ldc           #43                 // String module
      14: aastore
      15: dup
      16: iconst_2
      17: ldc           #46                 // String consumer
      19: aastore
      20: dup
      21: iconst_3
      22: ldc           #36                 // String monitor
      24: aastore
      25: dup
      26: iconst_4
      27: ldc           #111                // String registry
      29: aastore
      30: dup
      31: iconst_5
      32: ldc           #112                // String interfaceClass
      34: aastore
      35: invokestatic  #113                // Method com/alibaba/spring/util/ObjectUtils.of:([Ljava/lang/Object;)[Ljava/lang/Object;
      38: checkcast     #71                 // class "[Ljava/lang/String;"
      41: putstatic     #86                 // Field IGNORE_FIELD_NAMES:[Ljava/lang/String;
      44: return
}
