Compiled from "StreamUtils.java"
public class org.apache.dubbo.common.io.StreamUtils {
  private org.apache.dubbo.common.io.StreamUtils();
    Code:
       0: aload_0
       1: invokespecial #1                  // Method java/lang/Object."<init>":()V
       4: return

  public static java.io.InputStream limitedInputStream(java.io.InputStream, int) throws java.io.IOException;
    Code:
       0: new           #2                  // class org/apache/dubbo/common/io/StreamUtils$1
       3: dup
       4: iload_1
       5: aload_0
       6: invokespecial #3                  // Method org/apache/dubbo/common/io/StreamUtils$1."<init>":(ILjava/io/InputStream;)V
       9: areturn

  public static java.io.InputStream markSupportedInputStream(java.io.InputStream, int);
    Code:
       0: aload_0
       1: invokevirtual #4                  // Method java/io/InputStream.markSupported:()Z
       4: ifeq          9
       7: aload_0
       8: areturn
       9: new           #5                  // class org/apache/dubbo/common/io/StreamUtils$2
      12: dup
      13: aload_0
      14: iload_1
      15: invokespecial #6                  // Method org/apache/dubbo/common/io/StreamUtils$2."<init>":(Ljava/io/InputStream;I)V
      18: areturn

  public static java.io.InputStream markSupportedInputStream(java.io.InputStream);
    Code:
       0: aload_0
       1: sipush        1024
       4: invokestatic  #7                  // Method markSupportedInputStream:(Ljava/io/InputStream;I)Ljava/io/InputStream;
       7: areturn

  public static void skipUnusedStream(java.io.InputStream) throws java.io.IOException;
    Code:
       0: aload_0
       1: invokevirtual #8                  // Method java/io/InputStream.available:()I
       4: ifle          17
       7: aload_0
       8: aload_0
       9: invokevirtual #8                  // Method java/io/InputStream.available:()I
      12: i2l
      13: invokevirtual #9                  // Method java/io/InputStream.skip:(J)J
      16: pop2
      17: return
}
