Compiled from "BaseOnline.java"
public class org.apache.dubbo.qos.command.impl.BaseOnline implements org.apache.dubbo.qos.api.BaseCommand {
  private static final org.apache.dubbo.common.logger.Logger logger;

  public org.apache.dubbo.rpc.model.FrameworkServiceRepository serviceRepository;

  public org.apache.dubbo.qos.command.impl.BaseOnline(org.apache.dubbo.rpc.model.FrameworkModel);
    Code:
       0: aload_0
       1: invokespecial #1                  // Method java/lang/Object."<init>":()V
       4: aload_0
       5: aload_1
       6: invokevirtual #2                  // Method org/apache/dubbo/rpc/model/FrameworkModel.getServiceRepository:()Lorg/apache/dubbo/rpc/model/FrameworkServiceRepository;
       9: putfield      #3                  // Field serviceRepository:Lorg/apache/dubbo/rpc/model/FrameworkServiceRepository;
      12: return

  public java.lang.String execute(org.apache.dubbo.qos.api.CommandContext, java.lang.String[]);
    Code:
       0: getstatic     #4                  // Field logger:Lorg/apache/dubbo/common/logger/Logger;
       3: ldc           #5                  // String receive online command
       5: invokeinterface #6,  2            // InterfaceMethod org/apache/dubbo/common/logger/Logger.info:(Ljava/lang/String;)V
      10: ldc           #7                  // String .*
      12: astore_3
      13: aload_2
      14: invokestatic  #8                  // Method org/apache/dubbo/common/utils/ArrayUtils.isNotEmpty:([Ljava/lang/Object;)Z
      17: ifeq          42
      20: new           #9                  // class java/lang/StringBuilder
      23: dup
      24: invokespecial #10                 // Method java/lang/StringBuilder."<init>":()V
      27: ldc           #11                 // String
      29: invokevirtual #12                 // Method java/lang/StringBuilder.append:(Ljava/lang/String;)Ljava/lang/StringBuilder;
      32: aload_2
      33: iconst_0
      34: aaload
      35: invokevirtual #12                 // Method java/lang/StringBuilder.append:(Ljava/lang/String;)Ljava/lang/StringBuilder;
      38: invokevirtual #13                 // Method java/lang/StringBuilder.toString:()Ljava/lang/String;
      41: astore_3
      42: aload_0
      43: aload_3
      44: invokevirtual #14                 // Method doExecute:(Ljava/lang/String;)Z
      47: istore        4
      49: iload         4
      51: ifeq          57
      54: ldc           #15                 // String OK
      56: areturn
      57: ldc           #16                 // String service not found
      59: areturn

  public boolean online(java.lang.String);
    Code:
       0: iconst_0
       1: istore_2
       2: aload_0
       3: getfield      #3                  // Field serviceRepository:Lorg/apache/dubbo/rpc/model/FrameworkServiceRepository;
       6: invokevirtual #17                 // Method org/apache/dubbo/rpc/model/FrameworkServiceRepository.allProviderModels:()Ljava/util/List;
       9: astore_3
      10: aload_3
      11: invokeinterface #18,  1           // InterfaceMethod java/util/Collection.iterator:()Ljava/util/Iterator;
      16: astore        4
      18: aload         4
      20: invokeinterface #19,  1           // InterfaceMethod java/util/Iterator.hasNext:()Z
      25: ifeq          131
      28: aload         4
      30: invokeinterface #20,  1           // InterfaceMethod java/util/Iterator.next:()Ljava/lang/Object;
      35: checkcast     #21                 // class org/apache/dubbo/rpc/model/ProviderModel
      38: astore        5
      40: aload         5
      42: invokevirtual #22                 // Method org/apache/dubbo/rpc/model/ProviderModel.getServiceMetadata:()Lorg/apache/dubbo/rpc/model/ServiceMetadata;
      45: astore        6
      47: aload         6
      49: invokevirtual #23                 // Method org/apache/dubbo/rpc/model/ServiceMetadata.getServiceKey:()Ljava/lang/String;
      52: aload_1
      53: invokevirtual #24                 // Method java/lang/String.matches:(Ljava/lang/String;)Z
      56: ifne          71
      59: aload         6
      61: invokevirtual #25                 // Method org/apache/dubbo/rpc/model/ServiceMetadata.getDisplayServiceKey:()Ljava/lang/String;
      64: aload_1
      65: invokevirtual #24                 // Method java/lang/String.matches:(Ljava/lang/String;)Z
      68: ifeq          128
      71: iconst_1
      72: istore_2
      73: aload         5
      75: invokevirtual #26                 // Method org/apache/dubbo/rpc/model/ProviderModel.getStatedUrl:()Ljava/util/List;
      78: astore        7
      80: aload         7
      82: invokeinterface #27,  1           // InterfaceMethod java/util/List.iterator:()Ljava/util/Iterator;
      87: astore        8
      89: aload         8
      91: invokeinterface #19,  1           // InterfaceMethod java/util/Iterator.hasNext:()Z
      96: ifeq          128
      99: aload         8
     101: invokeinterface #20,  1           // InterfaceMethod java/util/Iterator.next:()Ljava/lang/Object;
     106: checkcast     #28                 // class org/apache/dubbo/rpc/model/ProviderModel$RegisterStatedURL
     109: astore        9
     111: aload         9
     113: invokevirtual #29                 // Method org/apache/dubbo/rpc/model/ProviderModel$RegisterStatedURL.isRegistered:()Z
     116: ifne          125
     119: aload_0
     120: aload         9
     122: invokevirtual #30                 // Method doExport:(Lorg/apache/dubbo/rpc/model/ProviderModel$RegisterStatedURL;)V
     125: goto          89
     128: goto          18
     131: iload_2
     132: ireturn

  protected boolean doExecute(java.lang.String);
    Code:
       0: aload_0
       1: aload_1
       2: invokevirtual #31                 // Method online:(Ljava/lang/String;)Z
       5: ireturn

  protected void doExport(org.apache.dubbo.rpc.model.ProviderModel$RegisterStatedURL);
    Code:
       0: aload_1
       1: invokevirtual #32                 // Method org/apache/dubbo/rpc/model/ProviderModel$RegisterStatedURL.getRegistryUrl:()Lorg/apache/dubbo/common/URL;
       4: invokevirtual #33                 // Method org/apache/dubbo/common/URL.getOrDefaultApplicationModel:()Lorg/apache/dubbo/rpc/model/ApplicationModel;
       7: ldc           #34                 // class org/apache/dubbo/registry/RegistryFactory
       9: invokevirtual #35                 // Method org/apache/dubbo/rpc/model/ApplicationModel.getExtensionLoader:(Ljava/lang/Class;)Lorg/apache/dubbo/common/extension/ExtensionLoader;
      12: invokevirtual #36                 // Method org/apache/dubbo/common/extension/ExtensionLoader.getAdaptiveExtension:()Ljava/lang/Object;
      15: checkcast     #34                 // class org/apache/dubbo/registry/RegistryFactory
      18: astore_2
      19: aload_2
      20: aload_1
      21: invokevirtual #32                 // Method org/apache/dubbo/rpc/model/ProviderModel$RegisterStatedURL.getRegistryUrl:()Lorg/apache/dubbo/common/URL;
      24: invokeinterface #37,  2           // InterfaceMethod org/apache/dubbo/registry/RegistryFactory.getRegistry:(Lorg/apache/dubbo/common/URL;)Lorg/apache/dubbo/registry/Registry;
      29: astore_3
      30: aload_3
      31: aload_1
      32: invokevirtual #38                 // Method org/apache/dubbo/rpc/model/ProviderModel$RegisterStatedURL.getProviderUrl:()Lorg/apache/dubbo/common/URL;
      35: invokeinterface #39,  2           // InterfaceMethod org/apache/dubbo/registry/Registry.register:(Lorg/apache/dubbo/common/URL;)V
      40: aload_1
      41: iconst_1
      42: invokevirtual #40                 // Method org/apache/dubbo/rpc/model/ProviderModel$RegisterStatedURL.setRegistered:(Z)V
      45: return

  static {};
    Code:
       0: ldc           #41                 // class org/apache/dubbo/qos/command/impl/BaseOnline
       2: invokestatic  #42                 // Method org/apache/dubbo/common/logger/LoggerFactory.getLogger:(Ljava/lang/Class;)Lorg/apache/dubbo/common/logger/Logger;
       5: putstatic     #4                  // Field logger:Lorg/apache/dubbo/common/logger/Logger;
       8: return
}
