Compiled from "ChangeTelnet.java"
public class org.apache.dubbo.qos.command.impl.ChangeTelnet implements org.apache.dubbo.qos.api.BaseCommand {
  public static final io.netty.util.AttributeKey<java.lang.String> SERVICE_KEY;

  private final org.apache.dubbo.rpc.protocol.dubbo.DubboProtocol dubboProtocol;

  public org.apache.dubbo.qos.command.impl.ChangeTelnet(org.apache.dubbo.rpc.model.FrameworkModel);
    Code:
       0: aload_0
       1: invokespecial #1                  // Method java/lang/Object."<init>":()V
       4: aload_0
       5: aload_1
       6: invokestatic  #2                  // Method org/apache/dubbo/rpc/protocol/dubbo/DubboProtocol.getDubboProtocol:(Lorg/apache/dubbo/rpc/model/ScopeModel;)Lorg/apache/dubbo/rpc/protocol/dubbo/DubboProtocol;
       9: putfield      #3                  // Field dubboProtocol:Lorg/apache/dubbo/rpc/protocol/dubbo/DubboProtocol;
      12: return

  public java.lang.String execute(org.apache.dubbo.qos.api.CommandContext, java.lang.String[]);
    Code:
       0: aload_1
       1: invokevirtual #4                  // Method org/apache/dubbo/qos/api/CommandContext.getRemote:()Lio/netty/channel/Channel;
       4: astore_3
       5: aload_2
       6: invokestatic  #5                  // Method org/apache/dubbo/common/utils/ArrayUtils.isEmpty:([Ljava/lang/Object;)Z
       9: ifeq          15
      12: ldc           #6                  // String Please input service name, eg: \r\ncd XxxService\r\ncd com.xxx.XxxService
      14: areturn
      15: aload_2
      16: iconst_0
      17: aaload
      18: astore        4
      20: new           #7                  // class java/lang/StringBuilder
      23: dup
      24: invokespecial #8                  // Method java/lang/StringBuilder."<init>":()V
      27: astore        5
      29: ldc           #9                  // String /
      31: aload         4
      33: invokevirtual #10                 // Method java/lang/String.equals:(Ljava/lang/Object;)Z
      36: ifne          49
      39: ldc           #11                 // String ..
      41: aload         4
      43: invokevirtual #10                 // Method java/lang/String.equals:(Ljava/lang/Object;)Z
      46: ifeq          89
      49: aload_3
      50: getstatic     #12                 // Field SERVICE_KEY:Lio/netty/util/AttributeKey;
      53: invokeinterface #13,  2           // InterfaceMethod io/netty/channel/Channel.attr:(Lio/netty/util/AttributeKey;)Lio/netty/util/Attribute;
      58: invokeinterface #14,  1           // InterfaceMethod io/netty/util/Attribute.getAndRemove:()Ljava/lang/Object;
      63: checkcast     #15                 // class java/lang/String
      66: astore        6
      68: aload         5
      70: ldc           #16                 // String Cancelled default service
      72: invokevirtual #17                 // Method java/lang/StringBuilder.append:(Ljava/lang/String;)Ljava/lang/StringBuilder;
      75: aload         6
      77: invokevirtual #17                 // Method java/lang/StringBuilder.append:(Ljava/lang/String;)Ljava/lang/StringBuilder;
      80: bipush        46
      82: invokevirtual #18                 // Method java/lang/StringBuilder.append:(C)Ljava/lang/StringBuilder;
      85: pop
      86: goto          261
      89: iconst_0
      90: istore        6
      92: aload_0
      93: getfield      #3                  // Field dubboProtocol:Lorg/apache/dubbo/rpc/protocol/dubbo/DubboProtocol;
      96: invokevirtual #19                 // Method org/apache/dubbo/rpc/protocol/dubbo/DubboProtocol.getExporters:()Ljava/util/Collection;
      99: invokeinterface #20,  1           // InterfaceMethod java/util/Collection.iterator:()Ljava/util/Iterator;
     104: astore        7
     106: aload         7
     108: invokeinterface #21,  1           // InterfaceMethod java/util/Iterator.hasNext:()Z
     113: ifeq          206
     116: aload         7
     118: invokeinterface #22,  1           // InterfaceMethod java/util/Iterator.next:()Ljava/lang/Object;
     123: checkcast     #23                 // class org/apache/dubbo/rpc/Exporter
     126: astore        8
     128: aload         4
     130: aload         8
     132: invokeinterface #24,  1           // InterfaceMethod org/apache/dubbo/rpc/Exporter.getInvoker:()Lorg/apache/dubbo/rpc/Invoker;
     137: invokeinterface #25,  1           // InterfaceMethod org/apache/dubbo/rpc/Invoker.getInterface:()Ljava/lang/Class;
     142: invokevirtual #26                 // Method java/lang/Class.getSimpleName:()Ljava/lang/String;
     145: invokevirtual #10                 // Method java/lang/String.equals:(Ljava/lang/Object;)Z
     148: ifne          197
     151: aload         4
     153: aload         8
     155: invokeinterface #24,  1           // InterfaceMethod org/apache/dubbo/rpc/Exporter.getInvoker:()Lorg/apache/dubbo/rpc/Invoker;
     160: invokeinterface #25,  1           // InterfaceMethod org/apache/dubbo/rpc/Invoker.getInterface:()Ljava/lang/Class;
     165: invokevirtual #27                 // Method java/lang/Class.getName:()Ljava/lang/String;
     168: invokevirtual #10                 // Method java/lang/String.equals:(Ljava/lang/Object;)Z
     171: ifne          197
     174: aload         4
     176: aload         8
     178: invokeinterface #24,  1           // InterfaceMethod org/apache/dubbo/rpc/Exporter.getInvoker:()Lorg/apache/dubbo/rpc/Invoker;
     183: invokeinterface #28,  1           // InterfaceMethod org/apache/dubbo/rpc/Invoker.getUrl:()Lorg/apache/dubbo/common/URL;
     188: invokevirtual #29                 // Method org/apache/dubbo/common/URL.getPath:()Ljava/lang/String;
     191: invokevirtual #10                 // Method java/lang/String.equals:(Ljava/lang/Object;)Z
     194: ifeq          203
     197: iconst_1
     198: istore        6
     200: goto          206
     203: goto          106
     206: iload         6
     208: ifeq          248
     211: aload_3
     212: getstatic     #12                 // Field SERVICE_KEY:Lio/netty/util/AttributeKey;
     215: invokeinterface #13,  2           // InterfaceMethod io/netty/channel/Channel.attr:(Lio/netty/util/AttributeKey;)Lio/netty/util/Attribute;
     220: aload         4
     222: invokeinterface #30,  2           // InterfaceMethod io/netty/util/Attribute.set:(Ljava/lang/Object;)V
     227: aload         5
     229: ldc           #31                 // String Used the
     231: invokevirtual #17                 // Method java/lang/StringBuilder.append:(Ljava/lang/String;)Ljava/lang/StringBuilder;
     234: aload         4
     236: invokevirtual #17                 // Method java/lang/StringBuilder.append:(Ljava/lang/String;)Ljava/lang/StringBuilder;
     239: ldc           #32                 // String  as default.\r\nYou can cancel default service by command: cd /
     241: invokevirtual #17                 // Method java/lang/StringBuilder.append:(Ljava/lang/String;)Ljava/lang/StringBuilder;
     244: pop
     245: goto          261
     248: aload         5
     250: ldc           #33                 // String No such service
     252: invokevirtual #17                 // Method java/lang/StringBuilder.append:(Ljava/lang/String;)Ljava/lang/StringBuilder;
     255: aload         4
     257: invokevirtual #17                 // Method java/lang/StringBuilder.append:(Ljava/lang/String;)Ljava/lang/StringBuilder;
     260: pop
     261: aload         5
     263: invokevirtual #34                 // Method java/lang/StringBuilder.toString:()Ljava/lang/String;
     266: areturn

  static {};
    Code:
       0: ldc           #35                 // String telnet.service
       2: invokestatic  #36                 // Method io/netty/util/AttributeKey.valueOf:(Ljava/lang/String;)Lio/netty/util/AttributeKey;
       5: putstatic     #12                 // Field SERVICE_KEY:Lio/netty/util/AttributeKey;
       8: return
}
