Compiled from "EnableSimpleProfiler.java"
public class org.apache.dubbo.qos.command.impl.EnableSimpleProfiler implements org.apache.dubbo.qos.api.BaseCommand {
  private static final org.apache.dubbo.common.logger.ErrorTypeAwareLogger logger;

  public org.apache.dubbo.qos.command.impl.EnableSimpleProfiler();
    Code:
       0: aload_0
       1: invokespecial #2                  // Method java/lang/Object."<init>":()V
       4: return

  public java.lang.String execute(org.apache.dubbo.qos.api.CommandContext, java.lang.String[]);
    Code:
       0: invokestatic  #3                  // Method org/apache/dubbo/common/profiler/ProfilerSwitch.enableSimpleProfiler:()V
       3: getstatic     #4                  // Field logger:Lorg/apache/dubbo/common/logger/ErrorTypeAwareLogger;
       6: ldc           #5                  // String 7-2
       8: ldc           #6                  // String
      10: ldc           #6                  // String
      12: ldc           #7                  // String Dubbo Invocation Profiler has been enabled.
      14: invokeinterface #8,  5            // InterfaceMethod org/apache/dubbo/common/logger/ErrorTypeAwareLogger.warn:(Ljava/lang/String;Ljava/lang/String;Ljava/lang/String;Ljava/lang/String;)V
      19: ldc           #9                  // String OK
      21: areturn

  static {};
    Code:
       0: ldc           #10                 // class org/apache/dubbo/qos/command/impl/EnableSimpleProfiler
       2: invokestatic  #11                 // Method org/apache/dubbo/common/logger/LoggerFactory.getErrorTypeAwareLogger:(Ljava/lang/Class;)Lorg/apache/dubbo/common/logger/ErrorTypeAwareLogger;
       5: putstatic     #4                  // Field logger:Lorg/apache/dubbo/common/logger/ErrorTypeAwareLogger;
       8: return
}
