Compiled from "GetAddress.java"
public class org.apache.dubbo.qos.command.impl.GetAddress implements org.apache.dubbo.qos.api.BaseCommand {
  public final org.apache.dubbo.rpc.model.FrameworkServiceRepository serviceRepository;

  public org.apache.dubbo.qos.command.impl.GetAddress(org.apache.dubbo.rpc.model.FrameworkModel);
    Code:
       0: aload_0
       1: invokespecial #1                  // Method java/lang/Object."<init>":()V
       4: aload_0
       5: aload_1
       6: invokevirtual #2                  // Method org/apache/dubbo/rpc/model/FrameworkModel.getServiceRepository:()Lorg/apache/dubbo/rpc/model/FrameworkServiceRepository;
       9: putfield      #3                  // Field serviceRepository:Lorg/apache/dubbo/rpc/model/FrameworkServiceRepository;
      12: return

  public java.lang.String execute(org.apache.dubbo.qos.api.CommandContext, java.lang.String[]);
    Code:
       0: aload_2
       1: ifnull        10
       4: aload_2
       5: arraylength
       6: iconst_1
       7: if_icmpeq     13
      10: ldc           #4                  // String Invalid parameters, please input like getAddress com.example.DemoService
      12: areturn
      13: aload_2
      14: iconst_0
      15: aaload
      16: astore_3
      17: new           #5                  // class java/lang/StringBuilder
      20: dup
      21: invokespecial #6                  // Method java/lang/StringBuilder."<init>":()V
      24: astore        4
      26: new           #7                  // class java/util/HashMap
      29: dup
      30: invokespecial #8                  // Method java/util/HashMap."<init>":()V
      33: astore        5
      35: aload_0
      36: getfield      #3                  // Field serviceRepository:Lorg/apache/dubbo/rpc/model/FrameworkServiceRepository;
      39: invokevirtual #9                  // Method org/apache/dubbo/rpc/model/FrameworkServiceRepository.allConsumerModels:()Ljava/util/List;
      42: invokeinterface #10,  1           // InterfaceMethod java/util/List.iterator:()Ljava/util/Iterator;
      47: astore        6
      49: aload         6
      51: invokeinterface #11,  1           // InterfaceMethod java/util/Iterator.hasNext:()Z
      56: ifeq          95
      59: aload         6
      61: invokeinterface #12,  1           // InterfaceMethod java/util/Iterator.next:()Ljava/lang/Object;
      66: checkcast     #13                 // class org/apache/dubbo/rpc/model/ConsumerModel
      69: astore        7
      71: aload_3
      72: aload         7
      74: invokevirtual #14                 // Method org/apache/dubbo/rpc/model/ConsumerModel.getServiceKey:()Ljava/lang/String;
      77: invokevirtual #15                 // Method java/lang/String.equals:(Ljava/lang/Object;)Z
      80: ifeq          92
      83: aload         4
      85: aload         5
      87: aload         7
      89: invokestatic  #16                 // Method appendConsumer:(Ljava/lang/StringBuilder;Ljava/util/Map;Lorg/apache/dubbo/rpc/model/ConsumerModel;)V
      92: goto          49
      95: aload_1
      96: invokevirtual #17                 // Method org/apache/dubbo/qos/api/CommandContext.isHttp:()Z
      99: ifeq          108
     102: aload         5
     104: invokestatic  #18                 // Method org/apache/dubbo/common/utils/JsonUtils.toJson:(Ljava/lang/Object;)Ljava/lang/String;
     107: areturn
     108: aload         4
     110: invokevirtual #19                 // Method java/lang/StringBuilder.toString:()Ljava/lang/String;
     113: areturn

  private static void appendConsumer(java.lang.StringBuilder, java.util.Map<java.lang.String, java.lang.Object>, org.apache.dubbo.rpc.model.ConsumerModel);
    Code:
       0: aload_0
       1: ldc           #20                 // String ConsumerModel:
       3: invokevirtual #21                 // Method java/lang/StringBuilder.append:(Ljava/lang/String;)Ljava/lang/StringBuilder;
       6: aload_2
       7: invokevirtual #14                 // Method org/apache/dubbo/rpc/model/ConsumerModel.getServiceKey:()Ljava/lang/String;
      10: invokevirtual #21                 // Method java/lang/StringBuilder.append:(Ljava/lang/String;)Ljava/lang/StringBuilder;
      13: ldc           #22                 // String @
      15: invokevirtual #21                 // Method java/lang/StringBuilder.append:(Ljava/lang/String;)Ljava/lang/StringBuilder;
      18: aload_2
      19: invokestatic  #23                 // Method java/lang/System.identityHashCode:(Ljava/lang/Object;)I
      22: invokestatic  #24                 // Method java/lang/Integer.toHexString:(I)Ljava/lang/String;
      25: invokevirtual #21                 // Method java/lang/StringBuilder.append:(Ljava/lang/String;)Ljava/lang/StringBuilder;
      28: ldc           #25                 // String \n\n
      30: invokevirtual #21                 // Method java/lang/StringBuilder.append:(Ljava/lang/String;)Ljava/lang/StringBuilder;
      33: pop
      34: new           #7                  // class java/util/HashMap
      37: dup
      38: invokespecial #8                  // Method java/util/HashMap."<init>":()V
      41: astore_3
      42: aload_1
      43: new           #5                  // class java/lang/StringBuilder
      46: dup
      47: invokespecial #6                  // Method java/lang/StringBuilder."<init>":()V
      50: aload_2
      51: invokevirtual #14                 // Method org/apache/dubbo/rpc/model/ConsumerModel.getServiceKey:()Ljava/lang/String;
      54: invokevirtual #21                 // Method java/lang/StringBuilder.append:(Ljava/lang/String;)Ljava/lang/StringBuilder;
      57: ldc           #22                 // String @
      59: invokevirtual #21                 // Method java/lang/StringBuilder.append:(Ljava/lang/String;)Ljava/lang/StringBuilder;
      62: aload_2
      63: invokestatic  #23                 // Method java/lang/System.identityHashCode:(Ljava/lang/Object;)I
      66: invokestatic  #24                 // Method java/lang/Integer.toHexString:(I)Ljava/lang/String;
      69: invokevirtual #21                 // Method java/lang/StringBuilder.append:(Ljava/lang/String;)Ljava/lang/StringBuilder;
      72: invokevirtual #19                 // Method java/lang/StringBuilder.toString:()Ljava/lang/String;
      75: aload_3
      76: invokeinterface #26,  3           // InterfaceMethod java/util/Map.put:(Ljava/lang/Object;Ljava/lang/Object;)Ljava/lang/Object;
      81: pop
      82: aload_2
      83: invokevirtual #27                 // Method org/apache/dubbo/rpc/model/ConsumerModel.getServiceMetadata:()Lorg/apache/dubbo/rpc/model/ServiceMetadata;
      86: ldc           #29                 // String currentClusterInvoker
      88: invokevirtual #30                 // Method org/apache/dubbo/rpc/model/ServiceMetadata.getAttribute:(Ljava/lang/String;)Ljava/lang/Object;
      91: astore        4
      93: aload         4
      95: instanceof    #31                 // class java/util/Map
      98: ifeq          154
     101: aload         4
     103: checkcast     #31                 // class java/util/Map
     106: astore        5
     108: aload         5
     110: invokeinterface #32,  1           // InterfaceMethod java/util/Map.entrySet:()Ljava/util/Set;
     115: invokeinterface #33,  1           // InterfaceMethod java/util/Set.iterator:()Ljava/util/Iterator;
     120: astore        6
     122: aload         6
     124: invokeinterface #11,  1           // InterfaceMethod java/util/Iterator.hasNext:()Z
     129: ifeq          154
     132: aload         6
     134: invokeinterface #12,  1           // InterfaceMethod java/util/Iterator.next:()Ljava/lang/Object;
     139: checkcast     #34                 // class java/util/Map$Entry
     142: astore        7
     144: aload_0
     145: aload_3
     146: aload         7
     148: invokestatic  #35                 // Method appendInvokers:(Ljava/lang/StringBuilder;Ljava/util/Map;Ljava/util/Map$Entry;)V
     151: goto          122
     154: return

  private static void appendInvokers(java.lang.StringBuilder, java.util.Map<java.lang.String, java.lang.Object>, java.util.Map$Entry<org.apache.dubbo.registry.Registry, org.apache.dubbo.registry.client.migration.MigrationInvoker<?>>);
    Code:
       0: aload_2
       1: invokeinterface #36,  1           // InterfaceMethod java/util/Map$Entry.getKey:()Ljava/lang/Object;
       6: checkcast     #37                 // class org/apache/dubbo/registry/Registry
       9: invokeinterface #38,  1           // InterfaceMethod org/apache/dubbo/registry/Registry.getUrl:()Lorg/apache/dubbo/common/URL;
      14: astore_3
      15: aload_0
      16: ldc           #39                 // String Registry:
      18: invokevirtual #21                 // Method java/lang/StringBuilder.append:(Ljava/lang/String;)Ljava/lang/StringBuilder;
      21: aload_3
      22: invokevirtual #40                 // Method java/lang/StringBuilder.append:(Ljava/lang/Object;)Ljava/lang/StringBuilder;
      25: ldc           #41                 // String \n
      27: invokevirtual #21                 // Method java/lang/StringBuilder.append:(Ljava/lang/String;)Ljava/lang/StringBuilder;
      30: pop
      31: new           #7                  // class java/util/HashMap
      34: dup
      35: invokespecial #8                  // Method java/util/HashMap."<init>":()V
      38: astore        4
      40: aload_1
      41: aload_3
      42: invokevirtual #42                 // Method org/apache/dubbo/common/URL.toString:()Ljava/lang/String;
      45: aload         4
      47: invokeinterface #26,  3           // InterfaceMethod java/util/Map.put:(Ljava/lang/Object;Ljava/lang/Object;)Ljava/lang/Object;
      52: pop
      53: aload_2
      54: invokeinterface #43,  1           // InterfaceMethod java/util/Map$Entry.getValue:()Ljava/lang/Object;
      59: checkcast     #44                 // class org/apache/dubbo/registry/client/migration/MigrationInvoker
      62: astore        5
      64: aload         5
      66: invokevirtual #45                 // Method org/apache/dubbo/registry/client/migration/MigrationInvoker.getMigrationStep:()Lorg/apache/dubbo/registry/client/migration/model/MigrationStep;
      69: astore        6
      71: aload_0
      72: ldc           #46                 // String MigrationStep:
      74: invokevirtual #21                 // Method java/lang/StringBuilder.append:(Ljava/lang/String;)Ljava/lang/StringBuilder;
      77: aload         6
      79: invokevirtual #40                 // Method java/lang/StringBuilder.append:(Ljava/lang/Object;)Ljava/lang/StringBuilder;
      82: ldc           #25                 // String \n\n
      84: invokevirtual #21                 // Method java/lang/StringBuilder.append:(Ljava/lang/String;)Ljava/lang/StringBuilder;
      87: pop
      88: aload         4
      90: ldc           #47                 // String MigrationStep
      92: aload         6
      94: invokeinterface #26,  3           // InterfaceMethod java/util/Map.put:(Ljava/lang/Object;Ljava/lang/Object;)Ljava/lang/Object;
      99: pop
     100: new           #7                  // class java/util/HashMap
     103: dup
     104: invokespecial #8                  // Method java/util/HashMap."<init>":()V
     107: astore        7
     109: aload         4
     111: ldc           #48                 // String Invokers
     113: aload         7
     115: invokeinterface #26,  3           // InterfaceMethod java/util/Map.put:(Ljava/lang/Object;Ljava/lang/Object;)Ljava/lang/Object;
     120: pop
     121: invokestatic  #49                 // Method org/apache/dubbo/rpc/RpcContext.getServiceContext:()Lorg/apache/dubbo/rpc/RpcServiceContext;
     124: invokevirtual #50                 // Method org/apache/dubbo/rpc/RpcServiceContext.getConsumerUrl:()Lorg/apache/dubbo/common/URL;
     127: astore        8
     129: invokestatic  #49                 // Method org/apache/dubbo/rpc/RpcContext.getServiceContext:()Lorg/apache/dubbo/rpc/RpcServiceContext;
     132: aload         5
     134: invokevirtual #51                 // Method org/apache/dubbo/registry/client/migration/MigrationInvoker.getConsumerUrl:()Lorg/apache/dubbo/common/URL;
     137: invokevirtual #52                 // Method org/apache/dubbo/rpc/RpcServiceContext.setConsumerUrl:(Lorg/apache/dubbo/common/URL;)V
     140: aload_0
     141: aload         5
     143: aload         7
     145: invokestatic  #53                 // Method appendInterfaceLevel:(Ljava/lang/StringBuilder;Lorg/apache/dubbo/registry/client/migration/MigrationInvoker;Ljava/util/Map;)V
     148: aload_0
     149: aload         5
     151: aload         7
     153: invokestatic  #54                 // Method appendAppLevel:(Ljava/lang/StringBuilder;Lorg/apache/dubbo/registry/client/migration/MigrationInvoker;Ljava/util/Map;)V
     156: invokestatic  #49                 // Method org/apache/dubbo/rpc/RpcContext.getServiceContext:()Lorg/apache/dubbo/rpc/RpcServiceContext;
     159: aload         8
     161: invokevirtual #52                 // Method org/apache/dubbo/rpc/RpcServiceContext.setConsumerUrl:(Lorg/apache/dubbo/common/URL;)V
     164: return

  private static void appendAppLevel(java.lang.StringBuilder, org.apache.dubbo.registry.client.migration.MigrationInvoker<?>, java.util.Map<java.lang.String, java.lang.Object>);
    Code:
       0: new           #7                  // class java/util/HashMap
       3: dup
       4: invokespecial #8                  // Method java/util/HashMap."<init>":()V
       7: astore_3
       8: aload_2
       9: ldc           #55                 // String Application-Level
      11: aload_3
      12: invokeinterface #26,  3           // InterfaceMethod java/util/Map.put:(Ljava/lang/Object;Ljava/lang/Object;)Ljava/lang/Object;
      17: pop
      18: aload_1
      19: invokevirtual #56                 // Method org/apache/dubbo/registry/client/migration/MigrationInvoker.getServiceDiscoveryInvoker:()Lorg/apache/dubbo/rpc/cluster/ClusterInvoker;
      22: invokestatic  #57                 // Method java/util/Optional.ofNullable:(Ljava/lang/Object;)Ljava/util/Optional;
      25: aload_0
      26: invokedynamic #58,  0             // InvokeDynamic #0:accept:(Ljava/lang/StringBuilder;)Ljava/util/function/Consumer;
      31: invokevirtual #59                 // Method java/util/Optional.ifPresent:(Ljava/util/function/Consumer;)V
      34: aload_1
      35: invokevirtual #56                 // Method org/apache/dubbo/registry/client/migration/MigrationInvoker.getServiceDiscoveryInvoker:()Lorg/apache/dubbo/rpc/cluster/ClusterInvoker;
      38: invokestatic  #57                 // Method java/util/Optional.ofNullable:(Ljava/lang/Object;)Ljava/util/Optional;
      41: invokedynamic #60,  0             // InvokeDynamic #1:apply:()Ljava/util/function/Function;
      46: invokevirtual #61                 // Method java/util/Optional.map:(Ljava/util/function/Function;)Ljava/util/Optional;
      49: invokedynamic #62,  0             // InvokeDynamic #2:apply:()Ljava/util/function/Function;
      54: invokevirtual #61                 // Method java/util/Optional.map:(Ljava/util/function/Function;)Ljava/util/Optional;
      57: aload_0
      58: aload_3
      59: invokedynamic #63,  0             // InvokeDynamic #3:accept:(Ljava/lang/StringBuilder;Ljava/util/Map;)Ljava/util/function/Consumer;
      64: invokevirtual #59                 // Method java/util/Optional.ifPresent:(Ljava/util/function/Consumer;)V
      67: aload_1
      68: invokevirtual #56                 // Method org/apache/dubbo/registry/client/migration/MigrationInvoker.getServiceDiscoveryInvoker:()Lorg/apache/dubbo/rpc/cluster/ClusterInvoker;
      71: invokestatic  #57                 // Method java/util/Optional.ofNullable:(Ljava/lang/Object;)Ljava/util/Optional;
      74: invokedynamic #60,  0             // InvokeDynamic #1:apply:()Ljava/util/function/Function;
      79: invokevirtual #61                 // Method java/util/Optional.map:(Ljava/util/function/Function;)Ljava/util/Optional;
      82: invokedynamic #64,  0             // InvokeDynamic #4:apply:()Ljava/util/function/Function;
      87: invokevirtual #61                 // Method java/util/Optional.map:(Ljava/util/function/Function;)Ljava/util/Optional;
      90: invokedynamic #65,  0             // InvokeDynamic #5:apply:()Ljava/util/function/Function;
      95: invokevirtual #61                 // Method java/util/Optional.map:(Ljava/util/function/Function;)Ljava/util/Optional;
      98: aload_0
      99: aload_3
     100: invokedynamic #66,  0             // InvokeDynamic #6:accept:(Ljava/lang/StringBuilder;Ljava/util/Map;)Ljava/util/function/Consumer;
     105: invokevirtual #59                 // Method java/util/Optional.ifPresent:(Ljava/util/function/Consumer;)V
     108: aload_1
     109: invokevirtual #56                 // Method org/apache/dubbo/registry/client/migration/MigrationInvoker.getServiceDiscoveryInvoker:()Lorg/apache/dubbo/rpc/cluster/ClusterInvoker;
     112: invokestatic  #57                 // Method java/util/Optional.ofNullable:(Ljava/lang/Object;)Ljava/util/Optional;
     115: invokedynamic #60,  0             // InvokeDynamic #1:apply:()Ljava/util/function/Function;
     120: invokevirtual #61                 // Method java/util/Optional.map:(Ljava/util/function/Function;)Ljava/util/Optional;
     123: invokedynamic #67,  0             // InvokeDynamic #7:apply:()Ljava/util/function/Function;
     128: invokevirtual #61                 // Method java/util/Optional.map:(Ljava/util/function/Function;)Ljava/util/Optional;
     131: invokedynamic #68,  0             // InvokeDynamic #8:apply:()Ljava/util/function/Function;
     136: invokevirtual #61                 // Method java/util/Optional.map:(Ljava/util/function/Function;)Ljava/util/Optional;
     139: aload_0
     140: aload_3
     141: invokedynamic #69,  0             // InvokeDynamic #9:accept:(Ljava/lang/StringBuilder;Ljava/util/Map;)Ljava/util/function/Consumer;
     146: invokevirtual #59                 // Method java/util/Optional.ifPresent:(Ljava/util/function/Consumer;)V
     149: return

  private static void appendInterfaceLevel(java.lang.StringBuilder, org.apache.dubbo.registry.client.migration.MigrationInvoker<?>, java.util.Map<java.lang.String, java.lang.Object>);
    Code:
       0: new           #7                  // class java/util/HashMap
       3: dup
       4: invokespecial #8                  // Method java/util/HashMap."<init>":()V
       7: astore_3
       8: aload_2
       9: ldc           #70                 // String Interface-Level
      11: aload_3
      12: invokeinterface #26,  3           // InterfaceMethod java/util/Map.put:(Ljava/lang/Object;Ljava/lang/Object;)Ljava/lang/Object;
      17: pop
      18: aload_1
      19: invokevirtual #71                 // Method org/apache/dubbo/registry/client/migration/MigrationInvoker.getInvoker:()Lorg/apache/dubbo/rpc/cluster/ClusterInvoker;
      22: invokestatic  #57                 // Method java/util/Optional.ofNullable:(Ljava/lang/Object;)Ljava/util/Optional;
      25: aload_0
      26: invokedynamic #72,  0             // InvokeDynamic #10:accept:(Ljava/lang/StringBuilder;)Ljava/util/function/Consumer;
      31: invokevirtual #59                 // Method java/util/Optional.ifPresent:(Ljava/util/function/Consumer;)V
      34: aload_1
      35: invokevirtual #71                 // Method org/apache/dubbo/registry/client/migration/MigrationInvoker.getInvoker:()Lorg/apache/dubbo/rpc/cluster/ClusterInvoker;
      38: invokestatic  #57                 // Method java/util/Optional.ofNullable:(Ljava/lang/Object;)Ljava/util/Optional;
      41: invokedynamic #60,  0             // InvokeDynamic #1:apply:()Ljava/util/function/Function;
      46: invokevirtual #61                 // Method java/util/Optional.map:(Ljava/util/function/Function;)Ljava/util/Optional;
      49: invokedynamic #62,  0             // InvokeDynamic #2:apply:()Ljava/util/function/Function;
      54: invokevirtual #61                 // Method java/util/Optional.map:(Ljava/util/function/Function;)Ljava/util/Optional;
      57: aload_0
      58: aload_3
      59: invokedynamic #73,  0             // InvokeDynamic #11:accept:(Ljava/lang/StringBuilder;Ljava/util/Map;)Ljava/util/function/Consumer;
      64: invokevirtual #59                 // Method java/util/Optional.ifPresent:(Ljava/util/function/Consumer;)V
      67: aload_1
      68: invokevirtual #71                 // Method org/apache/dubbo/registry/client/migration/MigrationInvoker.getInvoker:()Lorg/apache/dubbo/rpc/cluster/ClusterInvoker;
      71: invokestatic  #57                 // Method java/util/Optional.ofNullable:(Ljava/lang/Object;)Ljava/util/Optional;
      74: invokedynamic #60,  0             // InvokeDynamic #1:apply:()Ljava/util/function/Function;
      79: invokevirtual #61                 // Method java/util/Optional.map:(Ljava/util/function/Function;)Ljava/util/Optional;
      82: invokedynamic #74,  0             // InvokeDynamic #12:apply:()Ljava/util/function/Function;
      87: invokevirtual #61                 // Method java/util/Optional.map:(Ljava/util/function/Function;)Ljava/util/Optional;
      90: invokedynamic #65,  0             // InvokeDynamic #5:apply:()Ljava/util/function/Function;
      95: invokevirtual #61                 // Method java/util/Optional.map:(Ljava/util/function/Function;)Ljava/util/Optional;
      98: aload_0
      99: aload_3
     100: invokedynamic #75,  0             // InvokeDynamic #13:accept:(Ljava/lang/StringBuilder;Ljava/util/Map;)Ljava/util/function/Consumer;
     105: invokevirtual #59                 // Method java/util/Optional.ifPresent:(Ljava/util/function/Consumer;)V
     108: aload_1
     109: invokevirtual #71                 // Method org/apache/dubbo/registry/client/migration/MigrationInvoker.getInvoker:()Lorg/apache/dubbo/rpc/cluster/ClusterInvoker;
     112: invokestatic  #57                 // Method java/util/Optional.ofNullable:(Ljava/lang/Object;)Ljava/util/Optional;
     115: invokedynamic #60,  0             // InvokeDynamic #1:apply:()Ljava/util/function/Function;
     120: invokevirtual #61                 // Method java/util/Optional.map:(Ljava/util/function/Function;)Ljava/util/Optional;
     123: invokedynamic #76,  0             // InvokeDynamic #14:apply:()Ljava/util/function/Function;
     128: invokevirtual #61                 // Method java/util/Optional.map:(Ljava/util/function/Function;)Ljava/util/Optional;
     131: invokedynamic #68,  0             // InvokeDynamic #8:apply:()Ljava/util/function/Function;
     136: invokevirtual #61                 // Method java/util/Optional.map:(Ljava/util/function/Function;)Ljava/util/Optional;
     139: aload_0
     140: aload_3
     141: invokedynamic #77,  0             // InvokeDynamic #15:accept:(Ljava/lang/StringBuilder;Ljava/util/Map;)Ljava/util/function/Consumer;
     146: invokevirtual #59                 // Method java/util/Optional.ifPresent:(Ljava/util/function/Consumer;)V
     149: return

  private static void lambda$appendInterfaceLevel$11(java.lang.StringBuilder, java.util.Map, java.util.Set);
    Code:
       0: new           #78                 // class java/util/LinkedList
       3: dup
       4: invokespecial #79                 // Method java/util/LinkedList."<init>":()V
       7: astore_3
       8: aload_0
       9: ldc           #80                 // String Disabled Invokers: \n
      11: invokevirtual #21                 // Method java/lang/StringBuilder.append:(Ljava/lang/String;)Ljava/lang/StringBuilder;
      14: pop
      15: aload_2
      16: invokeinterface #33,  1           // InterfaceMethod java/util/Set.iterator:()Ljava/util/Iterator;
      21: astore        4
      23: aload         4
      25: invokeinterface #11,  1           // InterfaceMethod java/util/Iterator.hasNext:()Z
      30: ifeq          85
      33: aload         4
      35: invokeinterface #12,  1           // InterfaceMethod java/util/Iterator.next:()Ljava/lang/Object;
      40: checkcast     #81                 // class org/apache/dubbo/rpc/Invoker
      43: astore        5
      45: aload_3
      46: aload         5
      48: invokeinterface #82,  1           // InterfaceMethod org/apache/dubbo/rpc/Invoker.getUrl:()Lorg/apache/dubbo/common/URL;
      53: invokevirtual #83                 // Method org/apache/dubbo/common/URL.toFullString:()Ljava/lang/String;
      56: invokeinterface #84,  2           // InterfaceMethod java/util/List.add:(Ljava/lang/Object;)Z
      61: pop
      62: aload_0
      63: aload         5
      65: invokeinterface #82,  1           // InterfaceMethod org/apache/dubbo/rpc/Invoker.getUrl:()Lorg/apache/dubbo/common/URL;
      70: invokevirtual #83                 // Method org/apache/dubbo/common/URL.toFullString:()Ljava/lang/String;
      73: invokevirtual #21                 // Method java/lang/StringBuilder.append:(Ljava/lang/String;)Ljava/lang/StringBuilder;
      76: ldc           #41                 // String \n
      78: invokevirtual #21                 // Method java/lang/StringBuilder.append:(Ljava/lang/String;)Ljava/lang/StringBuilder;
      81: pop
      82: goto          23
      85: aload_0
      86: ldc           #41                 // String \n
      88: invokevirtual #21                 // Method java/lang/StringBuilder.append:(Ljava/lang/String;)Ljava/lang/StringBuilder;
      91: pop
      92: aload_1
      93: ldc           #85                 // String Disabled
      95: aload_3
      96: invokeinterface #26,  3           // InterfaceMethod java/util/Map.put:(Ljava/lang/Object;Ljava/lang/Object;)Ljava/lang/Object;
     101: pop
     102: return

  private static org.apache.dubbo.rpc.cluster.directory.AbstractDirectory lambda$appendInterfaceLevel$10(org.apache.dubbo.rpc.cluster.Directory);
    Code:
       0: aload_0
       1: checkcast     #86                 // class org/apache/dubbo/rpc/cluster/directory/AbstractDirectory
       4: areturn

  private static void lambda$appendInterfaceLevel$9(java.lang.StringBuilder, java.util.Map, org.apache.dubbo.rpc.cluster.router.state.BitList);
    Code:
       0: new           #78                 // class java/util/LinkedList
       3: dup
       4: invokespecial #79                 // Method java/util/LinkedList."<init>":()V
       7: astore_3
       8: aload_0
       9: ldc           #87                 // String Valid Invokers: \n
      11: invokevirtual #21                 // Method java/lang/StringBuilder.append:(Ljava/lang/String;)Ljava/lang/StringBuilder;
      14: pop
      15: aload_2
      16: invokevirtual #88                 // Method org/apache/dubbo/rpc/cluster/router/state/BitList.iterator:()Ljava/util/Iterator;
      19: astore        4
      21: aload         4
      23: invokeinterface #11,  1           // InterfaceMethod java/util/Iterator.hasNext:()Z
      28: ifeq          83
      31: aload         4
      33: invokeinterface #12,  1           // InterfaceMethod java/util/Iterator.next:()Ljava/lang/Object;
      38: checkcast     #81                 // class org/apache/dubbo/rpc/Invoker
      41: astore        5
      43: aload_3
      44: aload         5
      46: invokeinterface #82,  1           // InterfaceMethod org/apache/dubbo/rpc/Invoker.getUrl:()Lorg/apache/dubbo/common/URL;
      51: invokevirtual #83                 // Method org/apache/dubbo/common/URL.toFullString:()Ljava/lang/String;
      54: invokeinterface #84,  2           // InterfaceMethod java/util/List.add:(Ljava/lang/Object;)Z
      59: pop
      60: aload_0
      61: aload         5
      63: invokeinterface #82,  1           // InterfaceMethod org/apache/dubbo/rpc/Invoker.getUrl:()Lorg/apache/dubbo/common/URL;
      68: invokevirtual #83                 // Method org/apache/dubbo/common/URL.toFullString:()Ljava/lang/String;
      71: invokevirtual #21                 // Method java/lang/StringBuilder.append:(Ljava/lang/String;)Ljava/lang/StringBuilder;
      74: ldc           #41                 // String \n
      76: invokevirtual #21                 // Method java/lang/StringBuilder.append:(Ljava/lang/String;)Ljava/lang/StringBuilder;
      79: pop
      80: goto          21
      83: aload_0
      84: ldc           #41                 // String \n
      86: invokevirtual #21                 // Method java/lang/StringBuilder.append:(Ljava/lang/String;)Ljava/lang/StringBuilder;
      89: pop
      90: aload_1
      91: ldc           #89                 // String Valid
      93: aload_3
      94: invokeinterface #26,  3           // InterfaceMethod java/util/Map.put:(Ljava/lang/Object;Ljava/lang/Object;)Ljava/lang/Object;
      99: pop
     100: return

  private static org.apache.dubbo.rpc.cluster.directory.AbstractDirectory lambda$appendInterfaceLevel$8(org.apache.dubbo.rpc.cluster.Directory);
    Code:
       0: aload_0
       1: checkcast     #86                 // class org/apache/dubbo/rpc/cluster/directory/AbstractDirectory
       4: areturn

  private static void lambda$appendInterfaceLevel$7(java.lang.StringBuilder, java.util.Map, java.util.List);
    Code:
       0: new           #78                 // class java/util/LinkedList
       3: dup
       4: invokespecial #79                 // Method java/util/LinkedList."<init>":()V
       7: astore_3
       8: aload_0
       9: ldc           #90                 // String All Invokers: \n
      11: invokevirtual #21                 // Method java/lang/StringBuilder.append:(Ljava/lang/String;)Ljava/lang/StringBuilder;
      14: pop
      15: aload_2
      16: invokeinterface #10,  1           // InterfaceMethod java/util/List.iterator:()Ljava/util/Iterator;
      21: astore        4
      23: aload         4
      25: invokeinterface #11,  1           // InterfaceMethod java/util/Iterator.hasNext:()Z
      30: ifeq          85
      33: aload         4
      35: invokeinterface #12,  1           // InterfaceMethod java/util/Iterator.next:()Ljava/lang/Object;
      40: checkcast     #81                 // class org/apache/dubbo/rpc/Invoker
      43: astore        5
      45: aload_3
      46: aload         5
      48: invokeinterface #82,  1           // InterfaceMethod org/apache/dubbo/rpc/Invoker.getUrl:()Lorg/apache/dubbo/common/URL;
      53: invokevirtual #83                 // Method org/apache/dubbo/common/URL.toFullString:()Ljava/lang/String;
      56: invokeinterface #84,  2           // InterfaceMethod java/util/List.add:(Ljava/lang/Object;)Z
      61: pop
      62: aload_0
      63: aload         5
      65: invokeinterface #82,  1           // InterfaceMethod org/apache/dubbo/rpc/Invoker.getUrl:()Lorg/apache/dubbo/common/URL;
      70: invokevirtual #83                 // Method org/apache/dubbo/common/URL.toFullString:()Ljava/lang/String;
      73: invokevirtual #21                 // Method java/lang/StringBuilder.append:(Ljava/lang/String;)Ljava/lang/StringBuilder;
      76: ldc           #41                 // String \n
      78: invokevirtual #21                 // Method java/lang/StringBuilder.append:(Ljava/lang/String;)Ljava/lang/StringBuilder;
      81: pop
      82: goto          23
      85: aload_0
      86: ldc           #41                 // String \n
      88: invokevirtual #21                 // Method java/lang/StringBuilder.append:(Ljava/lang/String;)Ljava/lang/StringBuilder;
      91: pop
      92: aload_1
      93: ldc           #91                 // String All
      95: aload_3
      96: invokeinterface #26,  3           // InterfaceMethod java/util/Map.put:(Ljava/lang/Object;Ljava/lang/Object;)Ljava/lang/Object;
     101: pop
     102: return

  private static void lambda$appendInterfaceLevel$6(java.lang.StringBuilder, org.apache.dubbo.rpc.cluster.ClusterInvoker);
    Code:
       0: aload_0
       1: ldc           #92                 // String Interface-Level: \n
       3: invokevirtual #21                 // Method java/lang/StringBuilder.append:(Ljava/lang/String;)Ljava/lang/StringBuilder;
       6: pop
       7: return

  private static void lambda$appendAppLevel$5(java.lang.StringBuilder, java.util.Map, java.util.Set);
    Code:
       0: new           #78                 // class java/util/LinkedList
       3: dup
       4: invokespecial #79                 // Method java/util/LinkedList."<init>":()V
       7: astore_3
       8: aload_0
       9: ldc           #80                 // String Disabled Invokers: \n
      11: invokevirtual #21                 // Method java/lang/StringBuilder.append:(Ljava/lang/String;)Ljava/lang/StringBuilder;
      14: pop
      15: aload_2
      16: invokeinterface #33,  1           // InterfaceMethod java/util/Set.iterator:()Ljava/util/Iterator;
      21: astore        4
      23: aload         4
      25: invokeinterface #11,  1           // InterfaceMethod java/util/Iterator.hasNext:()Z
      30: ifeq          85
      33: aload         4
      35: invokeinterface #12,  1           // InterfaceMethod java/util/Iterator.next:()Ljava/lang/Object;
      40: checkcast     #81                 // class org/apache/dubbo/rpc/Invoker
      43: astore        5
      45: aload_3
      46: aload         5
      48: invokeinterface #82,  1           // InterfaceMethod org/apache/dubbo/rpc/Invoker.getUrl:()Lorg/apache/dubbo/common/URL;
      53: invokevirtual #83                 // Method org/apache/dubbo/common/URL.toFullString:()Ljava/lang/String;
      56: invokeinterface #84,  2           // InterfaceMethod java/util/List.add:(Ljava/lang/Object;)Z
      61: pop
      62: aload_0
      63: aload         5
      65: invokeinterface #82,  1           // InterfaceMethod org/apache/dubbo/rpc/Invoker.getUrl:()Lorg/apache/dubbo/common/URL;
      70: invokevirtual #83                 // Method org/apache/dubbo/common/URL.toFullString:()Ljava/lang/String;
      73: invokevirtual #21                 // Method java/lang/StringBuilder.append:(Ljava/lang/String;)Ljava/lang/StringBuilder;
      76: ldc           #41                 // String \n
      78: invokevirtual #21                 // Method java/lang/StringBuilder.append:(Ljava/lang/String;)Ljava/lang/StringBuilder;
      81: pop
      82: goto          23
      85: aload_0
      86: ldc           #41                 // String \n
      88: invokevirtual #21                 // Method java/lang/StringBuilder.append:(Ljava/lang/String;)Ljava/lang/StringBuilder;
      91: pop
      92: aload_1
      93: ldc           #85                 // String Disabled
      95: aload_3
      96: invokeinterface #26,  3           // InterfaceMethod java/util/Map.put:(Ljava/lang/Object;Ljava/lang/Object;)Ljava/lang/Object;
     101: pop
     102: return

  private static org.apache.dubbo.rpc.cluster.directory.AbstractDirectory lambda$appendAppLevel$4(org.apache.dubbo.rpc.cluster.Directory);
    Code:
       0: aload_0
       1: checkcast     #86                 // class org/apache/dubbo/rpc/cluster/directory/AbstractDirectory
       4: areturn

  private static void lambda$appendAppLevel$3(java.lang.StringBuilder, java.util.Map, org.apache.dubbo.rpc.cluster.router.state.BitList);
    Code:
       0: new           #78                 // class java/util/LinkedList
       3: dup
       4: invokespecial #79                 // Method java/util/LinkedList."<init>":()V
       7: astore_3
       8: aload_0
       9: ldc           #87                 // String Valid Invokers: \n
      11: invokevirtual #21                 // Method java/lang/StringBuilder.append:(Ljava/lang/String;)Ljava/lang/StringBuilder;
      14: pop
      15: aload_2
      16: invokevirtual #88                 // Method org/apache/dubbo/rpc/cluster/router/state/BitList.iterator:()Ljava/util/Iterator;
      19: astore        4
      21: aload         4
      23: invokeinterface #11,  1           // InterfaceMethod java/util/Iterator.hasNext:()Z
      28: ifeq          83
      31: aload         4
      33: invokeinterface #12,  1           // InterfaceMethod java/util/Iterator.next:()Ljava/lang/Object;
      38: checkcast     #81                 // class org/apache/dubbo/rpc/Invoker
      41: astore        5
      43: aload_3
      44: aload         5
      46: invokeinterface #82,  1           // InterfaceMethod org/apache/dubbo/rpc/Invoker.getUrl:()Lorg/apache/dubbo/common/URL;
      51: invokevirtual #83                 // Method org/apache/dubbo/common/URL.toFullString:()Ljava/lang/String;
      54: invokeinterface #84,  2           // InterfaceMethod java/util/List.add:(Ljava/lang/Object;)Z
      59: pop
      60: aload_0
      61: aload         5
      63: invokeinterface #82,  1           // InterfaceMethod org/apache/dubbo/rpc/Invoker.getUrl:()Lorg/apache/dubbo/common/URL;
      68: invokevirtual #83                 // Method org/apache/dubbo/common/URL.toFullString:()Ljava/lang/String;
      71: invokevirtual #21                 // Method java/lang/StringBuilder.append:(Ljava/lang/String;)Ljava/lang/StringBuilder;
      74: ldc           #41                 // String \n
      76: invokevirtual #21                 // Method java/lang/StringBuilder.append:(Ljava/lang/String;)Ljava/lang/StringBuilder;
      79: pop
      80: goto          21
      83: aload_0
      84: ldc           #41                 // String \n
      86: invokevirtual #21                 // Method java/lang/StringBuilder.append:(Ljava/lang/String;)Ljava/lang/StringBuilder;
      89: pop
      90: aload_1
      91: ldc           #89                 // String Valid
      93: aload_3
      94: invokeinterface #26,  3           // InterfaceMethod java/util/Map.put:(Ljava/lang/Object;Ljava/lang/Object;)Ljava/lang/Object;
      99: pop
     100: return

  private static org.apache.dubbo.rpc.cluster.directory.AbstractDirectory lambda$appendAppLevel$2(org.apache.dubbo.rpc.cluster.Directory);
    Code:
       0: aload_0
       1: checkcast     #86                 // class org/apache/dubbo/rpc/cluster/directory/AbstractDirectory
       4: areturn

  private static void lambda$appendAppLevel$1(java.lang.StringBuilder, java.util.Map, java.util.List);
    Code:
       0: new           #78                 // class java/util/LinkedList
       3: dup
       4: invokespecial #79                 // Method java/util/LinkedList."<init>":()V
       7: astore_3
       8: aload_0
       9: ldc           #90                 // String All Invokers: \n
      11: invokevirtual #21                 // Method java/lang/StringBuilder.append:(Ljava/lang/String;)Ljava/lang/StringBuilder;
      14: pop
      15: aload_2
      16: invokeinterface #10,  1           // InterfaceMethod java/util/List.iterator:()Ljava/util/Iterator;
      21: astore        4
      23: aload         4
      25: invokeinterface #11,  1           // InterfaceMethod java/util/Iterator.hasNext:()Z
      30: ifeq          85
      33: aload         4
      35: invokeinterface #12,  1           // InterfaceMethod java/util/Iterator.next:()Ljava/lang/Object;
      40: checkcast     #81                 // class org/apache/dubbo/rpc/Invoker
      43: astore        5
      45: aload_3
      46: aload         5
      48: invokeinterface #82,  1           // InterfaceMethod org/apache/dubbo/rpc/Invoker.getUrl:()Lorg/apache/dubbo/common/URL;
      53: invokevirtual #83                 // Method org/apache/dubbo/common/URL.toFullString:()Ljava/lang/String;
      56: invokeinterface #84,  2           // InterfaceMethod java/util/List.add:(Ljava/lang/Object;)Z
      61: pop
      62: aload_0
      63: aload         5
      65: invokeinterface #82,  1           // InterfaceMethod org/apache/dubbo/rpc/Invoker.getUrl:()Lorg/apache/dubbo/common/URL;
      70: invokevirtual #83                 // Method org/apache/dubbo/common/URL.toFullString:()Ljava/lang/String;
      73: invokevirtual #21                 // Method java/lang/StringBuilder.append:(Ljava/lang/String;)Ljava/lang/StringBuilder;
      76: ldc           #41                 // String \n
      78: invokevirtual #21                 // Method java/lang/StringBuilder.append:(Ljava/lang/String;)Ljava/lang/StringBuilder;
      81: pop
      82: goto          23
      85: aload_0
      86: ldc           #41                 // String \n
      88: invokevirtual #21                 // Method java/lang/StringBuilder.append:(Ljava/lang/String;)Ljava/lang/StringBuilder;
      91: pop
      92: aload_1
      93: ldc           #91                 // String All
      95: aload_3
      96: invokeinterface #26,  3           // InterfaceMethod java/util/Map.put:(Ljava/lang/Object;Ljava/lang/Object;)Ljava/lang/Object;
     101: pop
     102: return

  private static void lambda$appendAppLevel$0(java.lang.StringBuilder, org.apache.dubbo.rpc.cluster.ClusterInvoker);
    Code:
       0: aload_0
       1: ldc           #93                 // String Application-Level: \n
       3: invokevirtual #21                 // Method java/lang/StringBuilder.append:(Ljava/lang/String;)Ljava/lang/StringBuilder;
       6: pop
       7: return
}
