Compiled from "GetConfig.java"
public class org.apache.dubbo.qos.command.impl.GetConfig implements org.apache.dubbo.qos.api.BaseCommand {
  private final org.apache.dubbo.rpc.model.FrameworkModel frameworkModel;

  public org.apache.dubbo.qos.command.impl.GetConfig(org.apache.dubbo.rpc.model.FrameworkModel);
    Code:
       0: aload_0
       1: invokespecial #1                  // Method java/lang/Object."<init>":()V
       4: aload_0
       5: aload_1
       6: putfield      #2                  // Field frameworkModel:Lorg/apache/dubbo/rpc/model/FrameworkModel;
       9: return

  public java.lang.String execute(org.apache.dubbo.qos.api.CommandContext, java.lang.String[]);
    Code:
       0: aload_1
       1: invokevirtual #3                  // Method org/apache/dubbo/qos/api/CommandContext.isHttp:()Z
       4: istore_3
       5: new           #4                  // class java/lang/StringBuilder
       8: dup
       9: invokespecial #5                  // Method java/lang/StringBuilder."<init>":()V
      12: astore        4
      14: new           #6                  // class java/util/HashMap
      17: dup
      18: invokespecial #7                  // Method java/util/HashMap."<init>":()V
      21: astore        5
      23: aload_0
      24: aload_2
      25: aload         4
      27: aload         5
      29: invokespecial #8                  // Method appendFrameworkConfig:([Ljava/lang/String;Ljava/lang/StringBuilder;Ljava/util/Map;)V
      32: iload_3
      33: ifeq          42
      36: aload         5
      38: invokestatic  #9                  // Method org/apache/dubbo/common/utils/JsonUtils.toJson:(Ljava/lang/Object;)Ljava/lang/String;
      41: areturn
      42: aload         4
      44: invokevirtual #10                 // Method java/lang/StringBuilder.toString:()Ljava/lang/String;
      47: areturn

  private void appendFrameworkConfig(java.lang.String[], java.lang.StringBuilder, java.util.Map<java.lang.String, java.lang.Object>);
    Code:
       0: aload_0
       1: getfield      #2                  // Field frameworkModel:Lorg/apache/dubbo/rpc/model/FrameworkModel;
       4: invokevirtual #11                 // Method org/apache/dubbo/rpc/model/FrameworkModel.getApplicationModels:()Ljava/util/List;
       7: invokeinterface #12,  1           // InterfaceMethod java/util/List.iterator:()Ljava/util/Iterator;
      12: astore        4
      14: aload         4
      16: invokeinterface #13,  1           // InterfaceMethod java/util/Iterator.hasNext:()Z
      21: ifeq          100
      24: aload         4
      26: invokeinterface #14,  1           // InterfaceMethod java/util/Iterator.next:()Ljava/lang/Object;
      31: checkcast     #15                 // class org/apache/dubbo/rpc/model/ApplicationModel
      34: astore        5
      36: new           #6                  // class java/util/HashMap
      39: dup
      40: invokespecial #7                  // Method java/util/HashMap."<init>":()V
      43: astore        6
      45: aload_3
      46: aload         5
      48: invokevirtual #16                 // Method org/apache/dubbo/rpc/model/ApplicationModel.getDesc:()Ljava/lang/String;
      51: aload         6
      53: invokeinterface #17,  3           // InterfaceMethod java/util/Map.put:(Ljava/lang/Object;Ljava/lang/Object;)Ljava/lang/Object;
      58: pop
      59: aload_2
      60: ldc           #18                 // String ApplicationModel:
      62: invokevirtual #19                 // Method java/lang/StringBuilder.append:(Ljava/lang/String;)Ljava/lang/StringBuilder;
      65: aload         5
      67: invokevirtual #16                 // Method org/apache/dubbo/rpc/model/ApplicationModel.getDesc:()Ljava/lang/String;
      70: invokevirtual #19                 // Method java/lang/StringBuilder.append:(Ljava/lang/String;)Ljava/lang/StringBuilder;
      73: ldc           #20                 // String \n
      75: invokevirtual #19                 // Method java/lang/StringBuilder.append:(Ljava/lang/String;)Ljava/lang/StringBuilder;
      78: pop
      79: aload         5
      81: invokevirtual #21                 // Method org/apache/dubbo/rpc/model/ApplicationModel.getApplicationConfigManager:()Lorg/apache/dubbo/config/context/ConfigManager;
      84: astore        7
      86: aload_1
      87: aload_2
      88: aload         5
      90: aload         6
      92: aload         7
      94: invokestatic  #22                 // Method appendApplicationConfigs:([Ljava/lang/String;Ljava/lang/StringBuilder;Lorg/apache/dubbo/rpc/model/ApplicationModel;Ljava/util/Map;Lorg/apache/dubbo/config/context/ConfigManager;)V
      97: goto          14
     100: return

  private static void appendApplicationConfigs(java.lang.String[], java.lang.StringBuilder, org.apache.dubbo.rpc.model.ApplicationModel, java.util.Map<java.lang.String, java.lang.Object>, org.apache.dubbo.config.context.ConfigManager);
    Code:
       0: aload         4
       2: invokevirtual #23                 // Method org/apache/dubbo/config/context/ConfigManager.getApplication:()Ljava/util/Optional;
       5: astore        5
       7: aload         5
       9: aload_1
      10: aload_3
      11: aload_0
      12: invokedynamic #24,  0             // InvokeDynamic #0:accept:(Ljava/lang/StringBuilder;Ljava/util/Map;[Ljava/lang/String;)Ljava/util/function/Consumer;
      17: invokevirtual #25                 // Method java/util/Optional.ifPresent:(Ljava/util/function/Consumer;)V
      20: aload         4
      22: invokevirtual #26                 // Method org/apache/dubbo/config/context/ConfigManager.getProtocols:()Ljava/util/Collection;
      25: invokeinterface #27,  1           // InterfaceMethod java/util/Collection.iterator:()Ljava/util/Iterator;
      30: astore        6
      32: aload         6
      34: invokeinterface #13,  1           // InterfaceMethod java/util/Iterator.hasNext:()Z
      39: ifeq          72
      42: aload         6
      44: invokeinterface #14,  1           // InterfaceMethod java/util/Iterator.next:()Ljava/lang/Object;
      49: checkcast     #28                 // class org/apache/dubbo/config/ProtocolConfig
      52: astore        7
      54: ldc           #29                 // String ProtocolConfig
      56: aload         7
      58: invokevirtual #30                 // Method org/apache/dubbo/config/ProtocolConfig.getName:()Ljava/lang/String;
      61: aload         7
      63: aload_1
      64: aload_3
      65: aload_0
      66: invokestatic  #31                 // Method appendConfigs:(Ljava/lang/String;Ljava/lang/String;Ljava/lang/Object;Ljava/lang/StringBuilder;Ljava/util/Map;[Ljava/lang/String;)V
      69: goto          32
      72: aload         4
      74: invokevirtual #32                 // Method org/apache/dubbo/config/context/ConfigManager.getRegistries:()Ljava/util/Collection;
      77: invokeinterface #27,  1           // InterfaceMethod java/util/Collection.iterator:()Ljava/util/Iterator;
      82: astore        6
      84: aload         6
      86: invokeinterface #13,  1           // InterfaceMethod java/util/Iterator.hasNext:()Z
      91: ifeq          124
      94: aload         6
      96: invokeinterface #14,  1           // InterfaceMethod java/util/Iterator.next:()Ljava/lang/Object;
     101: checkcast     #33                 // class org/apache/dubbo/config/RegistryConfig
     104: astore        7
     106: ldc           #34                 // String RegistryConfig
     108: aload         7
     110: invokevirtual #35                 // Method org/apache/dubbo/config/RegistryConfig.getId:()Ljava/lang/String;
     113: aload         7
     115: aload_1
     116: aload_3
     117: aload_0
     118: invokestatic  #31                 // Method appendConfigs:(Ljava/lang/String;Ljava/lang/String;Ljava/lang/Object;Ljava/lang/StringBuilder;Ljava/util/Map;[Ljava/lang/String;)V
     121: goto          84
     124: aload         4
     126: invokevirtual #36                 // Method org/apache/dubbo/config/context/ConfigManager.getMetadataConfigs:()Ljava/util/Collection;
     129: invokeinterface #27,  1           // InterfaceMethod java/util/Collection.iterator:()Ljava/util/Iterator;
     134: astore        6
     136: aload         6
     138: invokeinterface #13,  1           // InterfaceMethod java/util/Iterator.hasNext:()Z
     143: ifeq          176
     146: aload         6
     148: invokeinterface #14,  1           // InterfaceMethod java/util/Iterator.next:()Ljava/lang/Object;
     153: checkcast     #37                 // class org/apache/dubbo/config/MetadataReportConfig
     156: astore        7
     158: ldc           #38                 // String MetadataReportConfig
     160: aload         7
     162: invokevirtual #39                 // Method org/apache/dubbo/config/MetadataReportConfig.getId:()Ljava/lang/String;
     165: aload         7
     167: aload_1
     168: aload_3
     169: aload_0
     170: invokestatic  #31                 // Method appendConfigs:(Ljava/lang/String;Ljava/lang/String;Ljava/lang/Object;Ljava/lang/StringBuilder;Ljava/util/Map;[Ljava/lang/String;)V
     173: goto          136
     176: aload         4
     178: invokevirtual #40                 // Method org/apache/dubbo/config/context/ConfigManager.getConfigCenters:()Ljava/util/Collection;
     181: invokeinterface #27,  1           // InterfaceMethod java/util/Collection.iterator:()Ljava/util/Iterator;
     186: astore        6
     188: aload         6
     190: invokeinterface #13,  1           // InterfaceMethod java/util/Iterator.hasNext:()Z
     195: ifeq          228
     198: aload         6
     200: invokeinterface #14,  1           // InterfaceMethod java/util/Iterator.next:()Ljava/lang/Object;
     205: checkcast     #41                 // class org/apache/dubbo/config/ConfigCenterConfig
     208: astore        7
     210: ldc           #42                 // String ConfigCenterConfig
     212: aload         7
     214: invokevirtual #43                 // Method org/apache/dubbo/config/ConfigCenterConfig.getId:()Ljava/lang/String;
     217: aload         7
     219: aload_1
     220: aload_3
     221: aload_0
     222: invokestatic  #31                 // Method appendConfigs:(Ljava/lang/String;Ljava/lang/String;Ljava/lang/Object;Ljava/lang/StringBuilder;Ljava/util/Map;[Ljava/lang/String;)V
     225: goto          188
     228: aload         4
     230: invokevirtual #44                 // Method org/apache/dubbo/config/context/ConfigManager.getMetrics:()Ljava/util/Optional;
     233: astore        6
     235: aload         6
     237: aload_1
     238: aload_3
     239: aload_0
     240: invokedynamic #45,  0             // InvokeDynamic #1:accept:(Ljava/lang/StringBuilder;Ljava/util/Map;[Ljava/lang/String;)Ljava/util/function/Consumer;
     245: invokevirtual #25                 // Method java/util/Optional.ifPresent:(Ljava/util/function/Consumer;)V
     248: aload         4
     250: invokevirtual #46                 // Method org/apache/dubbo/config/context/ConfigManager.getTracing:()Ljava/util/Optional;
     253: astore        7
     255: aload         7
     257: aload_1
     258: aload_3
     259: aload_0
     260: invokedynamic #47,  0             // InvokeDynamic #2:accept:(Ljava/lang/StringBuilder;Ljava/util/Map;[Ljava/lang/String;)Ljava/util/function/Consumer;
     265: invokevirtual #25                 // Method java/util/Optional.ifPresent:(Ljava/util/function/Consumer;)V
     268: aload         4
     270: invokevirtual #48                 // Method org/apache/dubbo/config/context/ConfigManager.getMonitor:()Ljava/util/Optional;
     273: astore        8
     275: aload         8
     277: aload_1
     278: aload_3
     279: aload_0
     280: invokedynamic #49,  0             // InvokeDynamic #3:accept:(Ljava/lang/StringBuilder;Ljava/util/Map;[Ljava/lang/String;)Ljava/util/function/Consumer;
     285: invokevirtual #25                 // Method java/util/Optional.ifPresent:(Ljava/util/function/Consumer;)V
     288: aload         4
     290: invokevirtual #50                 // Method org/apache/dubbo/config/context/ConfigManager.getSsl:()Ljava/util/Optional;
     293: astore        9
     295: aload         9
     297: aload_1
     298: aload_3
     299: aload_0
     300: invokedynamic #51,  0             // InvokeDynamic #4:accept:(Ljava/lang/StringBuilder;Ljava/util/Map;[Ljava/lang/String;)Ljava/util/function/Consumer;
     305: invokevirtual #25                 // Method java/util/Optional.ifPresent:(Ljava/util/function/Consumer;)V
     308: aload_2
     309: invokevirtual #52                 // Method org/apache/dubbo/rpc/model/ApplicationModel.getModuleModels:()Ljava/util/List;
     312: invokeinterface #12,  1           // InterfaceMethod java/util/List.iterator:()Ljava/util/Iterator;
     317: astore        10
     319: aload         10
     321: invokeinterface #13,  1           // InterfaceMethod java/util/Iterator.hasNext:()Z
     326: ifeq          403
     329: aload         10
     331: invokeinterface #14,  1           // InterfaceMethod java/util/Iterator.next:()Ljava/lang/Object;
     336: checkcast     #53                 // class org/apache/dubbo/rpc/model/ModuleModel
     339: astore        11
     341: new           #6                  // class java/util/HashMap
     344: dup
     345: invokespecial #7                  // Method java/util/HashMap."<init>":()V
     348: astore        12
     350: aload_3
     351: aload         11
     353: invokevirtual #54                 // Method org/apache/dubbo/rpc/model/ModuleModel.getDesc:()Ljava/lang/String;
     356: aload         12
     358: invokeinterface #17,  3           // InterfaceMethod java/util/Map.put:(Ljava/lang/Object;Ljava/lang/Object;)Ljava/lang/Object;
     363: pop
     364: aload_1
     365: ldc           #55                 // String ModuleModel:
     367: invokevirtual #19                 // Method java/lang/StringBuilder.append:(Ljava/lang/String;)Ljava/lang/StringBuilder;
     370: aload         11
     372: invokevirtual #54                 // Method org/apache/dubbo/rpc/model/ModuleModel.getDesc:()Ljava/lang/String;
     375: invokevirtual #19                 // Method java/lang/StringBuilder.append:(Ljava/lang/String;)Ljava/lang/StringBuilder;
     378: ldc           #20                 // String \n
     380: invokevirtual #19                 // Method java/lang/StringBuilder.append:(Ljava/lang/String;)Ljava/lang/StringBuilder;
     383: pop
     384: aload         11
     386: invokevirtual #56                 // Method org/apache/dubbo/rpc/model/ModuleModel.getConfigManager:()Lorg/apache/dubbo/config/context/ModuleConfigManager;
     389: astore        13
     391: aload_0
     392: aload_1
     393: aload         12
     395: aload         13
     397: invokestatic  #57                 // Method appendModuleConfigs:([Ljava/lang/String;Ljava/lang/StringBuilder;Ljava/util/Map;Lorg/apache/dubbo/config/context/ModuleConfigManager;)V
     400: goto          319
     403: return

  private static void appendModuleConfigs(java.lang.String[], java.lang.StringBuilder, java.util.Map<java.lang.String, java.lang.Object>, org.apache.dubbo.config.context.ModuleConfigManager);
    Code:
       0: aload_3
       1: invokevirtual #58                 // Method org/apache/dubbo/config/context/ModuleConfigManager.getProviders:()Ljava/util/Collection;
       4: invokeinterface #27,  1           // InterfaceMethod java/util/Collection.iterator:()Ljava/util/Iterator;
       9: astore        4
      11: aload         4
      13: invokeinterface #13,  1           // InterfaceMethod java/util/Iterator.hasNext:()Z
      18: ifeq          51
      21: aload         4
      23: invokeinterface #14,  1           // InterfaceMethod java/util/Iterator.next:()Ljava/lang/Object;
      28: checkcast     #59                 // class org/apache/dubbo/config/ProviderConfig
      31: astore        5
      33: ldc           #60                 // String ProviderConfig
      35: aload         5
      37: invokevirtual #61                 // Method org/apache/dubbo/config/ProviderConfig.getId:()Ljava/lang/String;
      40: aload         5
      42: aload_1
      43: aload_2
      44: aload_0
      45: invokestatic  #31                 // Method appendConfigs:(Ljava/lang/String;Ljava/lang/String;Ljava/lang/Object;Ljava/lang/StringBuilder;Ljava/util/Map;[Ljava/lang/String;)V
      48: goto          11
      51: aload_3
      52: invokevirtual #62                 // Method org/apache/dubbo/config/context/ModuleConfigManager.getConsumers:()Ljava/util/Collection;
      55: invokeinterface #27,  1           // InterfaceMethod java/util/Collection.iterator:()Ljava/util/Iterator;
      60: astore        4
      62: aload         4
      64: invokeinterface #13,  1           // InterfaceMethod java/util/Iterator.hasNext:()Z
      69: ifeq          102
      72: aload         4
      74: invokeinterface #14,  1           // InterfaceMethod java/util/Iterator.next:()Ljava/lang/Object;
      79: checkcast     #63                 // class org/apache/dubbo/config/ConsumerConfig
      82: astore        5
      84: ldc           #64                 // String ConsumerConfig
      86: aload         5
      88: invokevirtual #65                 // Method org/apache/dubbo/config/ConsumerConfig.getId:()Ljava/lang/String;
      91: aload         5
      93: aload_1
      94: aload_2
      95: aload_0
      96: invokestatic  #31                 // Method appendConfigs:(Ljava/lang/String;Ljava/lang/String;Ljava/lang/Object;Ljava/lang/StringBuilder;Ljava/util/Map;[Ljava/lang/String;)V
      99: goto          62
     102: aload_3
     103: invokevirtual #66                 // Method org/apache/dubbo/config/context/ModuleConfigManager.getModule:()Ljava/util/Optional;
     106: astore        4
     108: aload         4
     110: aload_1
     111: aload_2
     112: aload_0
     113: invokedynamic #67,  0             // InvokeDynamic #5:accept:(Ljava/lang/StringBuilder;Ljava/util/Map;[Ljava/lang/String;)Ljava/util/function/Consumer;
     118: invokevirtual #25                 // Method java/util/Optional.ifPresent:(Ljava/util/function/Consumer;)V
     121: aload_3
     122: invokevirtual #68                 // Method org/apache/dubbo/config/context/ModuleConfigManager.getServices:()Ljava/util/Collection;
     125: invokeinterface #27,  1           // InterfaceMethod java/util/Collection.iterator:()Ljava/util/Iterator;
     130: astore        5
     132: aload         5
     134: invokeinterface #13,  1           // InterfaceMethod java/util/Iterator.hasNext:()Z
     139: ifeq          172
     142: aload         5
     144: invokeinterface #14,  1           // InterfaceMethod java/util/Iterator.next:()Ljava/lang/Object;
     149: checkcast     #69                 // class org/apache/dubbo/config/ServiceConfigBase
     152: astore        6
     154: ldc           #70                 // String ServiceConfig
     156: aload         6
     158: invokevirtual #71                 // Method org/apache/dubbo/config/ServiceConfigBase.getUniqueServiceName:()Ljava/lang/String;
     161: aload         6
     163: aload_1
     164: aload_2
     165: aload_0
     166: invokestatic  #31                 // Method appendConfigs:(Ljava/lang/String;Ljava/lang/String;Ljava/lang/Object;Ljava/lang/StringBuilder;Ljava/util/Map;[Ljava/lang/String;)V
     169: goto          132
     172: aload_3
     173: invokevirtual #72                 // Method org/apache/dubbo/config/context/ModuleConfigManager.getReferences:()Ljava/util/Collection;
     176: invokeinterface #27,  1           // InterfaceMethod java/util/Collection.iterator:()Ljava/util/Iterator;
     181: astore        5
     183: aload         5
     185: invokeinterface #13,  1           // InterfaceMethod java/util/Iterator.hasNext:()Z
     190: ifeq          223
     193: aload         5
     195: invokeinterface #14,  1           // InterfaceMethod java/util/Iterator.next:()Ljava/lang/Object;
     200: checkcast     #73                 // class org/apache/dubbo/config/ReferenceConfigBase
     203: astore        6
     205: ldc           #74                 // String ReferenceConfig
     207: aload         6
     209: invokevirtual #75                 // Method org/apache/dubbo/config/ReferenceConfigBase.getUniqueServiceName:()Ljava/lang/String;
     212: aload         6
     214: aload_1
     215: aload_2
     216: aload_0
     217: invokestatic  #31                 // Method appendConfigs:(Ljava/lang/String;Ljava/lang/String;Ljava/lang/Object;Ljava/lang/StringBuilder;Ljava/util/Map;[Ljava/lang/String;)V
     220: goto          183
     223: return

  private static void appendConfigs(java.lang.String, java.lang.String, java.lang.Object, java.lang.StringBuilder, java.util.Map<java.lang.String, java.lang.Object>, java.lang.String[]);
    Code:
       0: aload_0
       1: aload_1
       2: aload         5
       4: invokestatic  #76                 // Method isMatch:(Ljava/lang/String;Ljava/lang/String;[Ljava/lang/String;)Z
       7: ifne          11
      10: return
      11: aload_3
      12: aload_0
      13: invokevirtual #19                 // Method java/lang/StringBuilder.append:(Ljava/lang/String;)Ljava/lang/StringBuilder;
      16: ldc           #77                 // String :
      18: invokevirtual #19                 // Method java/lang/StringBuilder.append:(Ljava/lang/String;)Ljava/lang/StringBuilder;
      21: aload_1
      22: invokevirtual #19                 // Method java/lang/StringBuilder.append:(Ljava/lang/String;)Ljava/lang/StringBuilder;
      25: ldc           #20                 // String \n
      27: invokevirtual #19                 // Method java/lang/StringBuilder.append:(Ljava/lang/String;)Ljava/lang/StringBuilder;
      30: aload_2
      31: invokevirtual #78                 // Method java/lang/StringBuilder.append:(Ljava/lang/Object;)Ljava/lang/StringBuilder;
      34: ldc           #79                 // String \n\n
      36: invokevirtual #19                 // Method java/lang/StringBuilder.append:(Ljava/lang/String;)Ljava/lang/StringBuilder;
      39: pop
      40: aload         4
      42: aload_0
      43: invokedynamic #80,  0             // InvokeDynamic #6:apply:()Ljava/util/function/Function;
      48: invokeinterface #81,  3           // InterfaceMethod java/util/Map.computeIfAbsent:(Ljava/lang/Object;Ljava/util/function/Function;)Ljava/lang/Object;
      53: checkcast     #82                 // class java/util/Map
      56: astore        6
      58: aload         6
      60: aload_1
      61: aload_2
      62: invokeinterface #17,  3           // InterfaceMethod java/util/Map.put:(Ljava/lang/Object;Ljava/lang/Object;)Ljava/lang/Object;
      67: pop
      68: return

  private static void appendConfig(java.lang.String, java.lang.String, java.lang.Object, java.lang.StringBuilder, java.util.Map<java.lang.String, java.lang.Object>, java.lang.String[]);
    Code:
       0: aload_0
       1: aload_1
       2: aload         5
       4: invokestatic  #76                 // Method isMatch:(Ljava/lang/String;Ljava/lang/String;[Ljava/lang/String;)Z
       7: ifne          11
      10: return
      11: aload_3
      12: aload_0
      13: invokevirtual #19                 // Method java/lang/StringBuilder.append:(Ljava/lang/String;)Ljava/lang/StringBuilder;
      16: ldc           #77                 // String :
      18: invokevirtual #19                 // Method java/lang/StringBuilder.append:(Ljava/lang/String;)Ljava/lang/StringBuilder;
      21: aload_1
      22: invokevirtual #19                 // Method java/lang/StringBuilder.append:(Ljava/lang/String;)Ljava/lang/StringBuilder;
      25: ldc           #20                 // String \n
      27: invokevirtual #19                 // Method java/lang/StringBuilder.append:(Ljava/lang/String;)Ljava/lang/StringBuilder;
      30: aload_2
      31: invokevirtual #78                 // Method java/lang/StringBuilder.append:(Ljava/lang/Object;)Ljava/lang/StringBuilder;
      34: ldc           #79                 // String \n\n
      36: invokevirtual #19                 // Method java/lang/StringBuilder.append:(Ljava/lang/String;)Ljava/lang/StringBuilder;
      39: pop
      40: aload         4
      42: aload_0
      43: aload_2
      44: invokeinterface #17,  3           // InterfaceMethod java/util/Map.put:(Ljava/lang/Object;Ljava/lang/Object;)Ljava/lang/Object;
      49: pop
      50: return

  private static boolean isMatch(java.lang.String, java.lang.String, java.lang.String[]);
    Code:
       0: aload_2
       1: ifnonnull     6
       4: iconst_1
       5: ireturn
       6: aload_2
       7: arraylength
       8: lookupswitch  { // 2
                     1: 36
                     2: 48
               default: 70
          }
      36: aload_2
      37: iconst_0
      38: aaload
      39: aload_0
      40: invokestatic  #83                 // Method java/util/Objects.equals:(Ljava/lang/Object;Ljava/lang/Object;)Z
      43: ifne          70
      46: iconst_0
      47: ireturn
      48: aload_2
      49: iconst_0
      50: aaload
      51: aload_0
      52: invokestatic  #83                 // Method java/util/Objects.equals:(Ljava/lang/Object;Ljava/lang/Object;)Z
      55: ifeq          68
      58: aload_2
      59: iconst_1
      60: aaload
      61: aload_1
      62: invokestatic  #83                 // Method java/util/Objects.equals:(Ljava/lang/Object;Ljava/lang/Object;)Z
      65: ifne          70
      68: iconst_0
      69: ireturn
      70: iconst_1
      71: ireturn

  private static java.lang.Object lambda$appendConfigs$6(java.lang.String);
    Code:
       0: new           #6                  // class java/util/HashMap
       3: dup
       4: invokespecial #7                  // Method java/util/HashMap."<init>":()V
       7: areturn

  private static void lambda$appendModuleConfigs$5(java.lang.StringBuilder, java.util.Map, java.lang.String[], org.apache.dubbo.config.ModuleConfig);
    Code:
       0: ldc           #84                 // String ModuleConfig
       2: aload_3
       3: invokevirtual #85                 // Method org/apache/dubbo/config/ModuleConfig.getId:()Ljava/lang/String;
       6: aload_3
       7: aload_0
       8: aload_1
       9: aload_2
      10: invokestatic  #86                 // Method appendConfig:(Ljava/lang/String;Ljava/lang/String;Ljava/lang/Object;Ljava/lang/StringBuilder;Ljava/util/Map;[Ljava/lang/String;)V
      13: return

  private static void lambda$appendApplicationConfigs$4(java.lang.StringBuilder, java.util.Map, java.lang.String[], org.apache.dubbo.config.SslConfig);
    Code:
       0: ldc           #87                 // String SslConfig
       2: aload_3
       3: invokevirtual #88                 // Method org/apache/dubbo/config/SslConfig.getId:()Ljava/lang/String;
       6: aload_3
       7: aload_0
       8: aload_1
       9: aload_2
      10: invokestatic  #86                 // Method appendConfig:(Ljava/lang/String;Ljava/lang/String;Ljava/lang/Object;Ljava/lang/StringBuilder;Ljava/util/Map;[Ljava/lang/String;)V
      13: return

  private static void lambda$appendApplicationConfigs$3(java.lang.StringBuilder, java.util.Map, java.lang.String[], org.apache.dubbo.config.MonitorConfig);
    Code:
       0: ldc           #89                 // String MonitorConfig
       2: aload_3
       3: invokevirtual #90                 // Method org/apache/dubbo/config/MonitorConfig.getId:()Ljava/lang/String;
       6: aload_3
       7: aload_0
       8: aload_1
       9: aload_2
      10: invokestatic  #86                 // Method appendConfig:(Ljava/lang/String;Ljava/lang/String;Ljava/lang/Object;Ljava/lang/StringBuilder;Ljava/util/Map;[Ljava/lang/String;)V
      13: return

  private static void lambda$appendApplicationConfigs$2(java.lang.StringBuilder, java.util.Map, java.lang.String[], org.apache.dubbo.config.TracingConfig);
    Code:
       0: ldc           #91                 // String TracingConfig
       2: aload_3
       3: invokevirtual #92                 // Method org/apache/dubbo/config/TracingConfig.getId:()Ljava/lang/String;
       6: aload_3
       7: aload_0
       8: aload_1
       9: aload_2
      10: invokestatic  #86                 // Method appendConfig:(Ljava/lang/String;Ljava/lang/String;Ljava/lang/Object;Ljava/lang/StringBuilder;Ljava/util/Map;[Ljava/lang/String;)V
      13: return

  private static void lambda$appendApplicationConfigs$1(java.lang.StringBuilder, java.util.Map, java.lang.String[], org.apache.dubbo.config.MetricsConfig);
    Code:
       0: ldc           #93                 // String MetricsConfig
       2: aload_3
       3: invokevirtual #94                 // Method org/apache/dubbo/config/MetricsConfig.getId:()Ljava/lang/String;
       6: aload_3
       7: aload_0
       8: aload_1
       9: aload_2
      10: invokestatic  #86                 // Method appendConfig:(Ljava/lang/String;Ljava/lang/String;Ljava/lang/Object;Ljava/lang/StringBuilder;Ljava/util/Map;[Ljava/lang/String;)V
      13: return

  private static void lambda$appendApplicationConfigs$0(java.lang.StringBuilder, java.util.Map, java.lang.String[], org.apache.dubbo.config.ApplicationConfig);
    Code:
       0: ldc           #95                 // String ApplicationConfig
       2: aload_3
       3: invokevirtual #96                 // Method org/apache/dubbo/config/ApplicationConfig.getName:()Ljava/lang/String;
       6: aload_3
       7: aload_0
       8: aload_1
       9: aload_2
      10: invokestatic  #86                 // Method appendConfig:(Ljava/lang/String;Ljava/lang/String;Ljava/lang/Object;Ljava/lang/StringBuilder;Ljava/util/Map;[Ljava/lang/String;)V
      13: return
}
