Compiled from "GetEnabledRouterSnapshot.java"
public class org.apache.dubbo.qos.command.impl.GetEnabledRouterSnapshot implements org.apache.dubbo.qos.api.BaseCommand {
  private final org.apache.dubbo.rpc.cluster.router.RouterSnapshotSwitcher routerSnapshotSwitcher;

  public org.apache.dubbo.qos.command.impl.GetEnabledRouterSnapshot(org.apache.dubbo.rpc.model.FrameworkModel);
    Code:
       0: aload_0
       1: invokespecial #1                  // Method java/lang/Object."<init>":()V
       4: aload_0
       5: aload_1
       6: invokevirtual #2                  // Method org/apache/dubbo/rpc/model/FrameworkModel.getBeanFactory:()Lorg/apache/dubbo/common/beans/factory/ScopeBeanFactory;
       9: ldc           #3                  // class org/apache/dubbo/rpc/cluster/router/RouterSnapshotSwitcher
      11: invokevirtual #4                  // Method org/apache/dubbo/common/beans/factory/ScopeBeanFactory.getBean:(Ljava/lang/Class;)Ljava/lang/Object;
      14: checkcast     #3                  // class org/apache/dubbo/rpc/cluster/router/RouterSnapshotSwitcher
      17: putfield      #5                  // Field routerSnapshotSwitcher:Lorg/apache/dubbo/rpc/cluster/router/RouterSnapshotSwitcher;
      20: return

  public java.lang.String execute(org.apache.dubbo.qos.api.CommandContext, java.lang.String[]);
    Code:
       0: ldc           #6                  // String \n
       2: aload_0
       3: getfield      #5                  // Field routerSnapshotSwitcher:Lorg/apache/dubbo/rpc/cluster/router/RouterSnapshotSwitcher;
       6: invokevirtual #7                  // Method org/apache/dubbo/rpc/cluster/router/RouterSnapshotSwitcher.getEnabledService:()Ljava/util/Set;
       9: invokestatic  #8                  // Method java/lang/String.join:(Ljava/lang/CharSequence;Ljava/lang/Iterable;)Ljava/lang/String;
      12: areturn
}
