Compiled from "GetRecentRouterSnapshot.java"
public class org.apache.dubbo.qos.command.impl.GetRecentRouterSnapshot implements org.apache.dubbo.qos.api.BaseCommand {
  private final org.apache.dubbo.rpc.cluster.router.RouterSnapshotSwitcher routerSnapshotSwitcher;

  public org.apache.dubbo.qos.command.impl.GetRecentRouterSnapshot(org.apache.dubbo.rpc.model.FrameworkModel);
    Code:
       0: aload_0
       1: invokespecial #1                  // Method java/lang/Object."<init>":()V
       4: aload_0
       5: aload_1
       6: invokevirtual #2                  // Method org/apache/dubbo/rpc/model/FrameworkModel.getBeanFactory:()Lorg/apache/dubbo/common/beans/factory/ScopeBeanFactory;
       9: ldc           #3                  // class org/apache/dubbo/rpc/cluster/router/RouterSnapshotSwitcher
      11: invokevirtual #4                  // Method org/apache/dubbo/common/beans/factory/ScopeBeanFactory.getBean:(Ljava/lang/Class;)Ljava/lang/Object;
      14: checkcast     #3                  // class org/apache/dubbo/rpc/cluster/router/RouterSnapshotSwitcher
      17: putfield      #5                  // Field routerSnapshotSwitcher:Lorg/apache/dubbo/rpc/cluster/router/RouterSnapshotSwitcher;
      20: return

  public java.lang.String execute(org.apache.dubbo.qos.api.CommandContext, java.lang.String[]);
    Code:
       0: aload_0
       1: getfield      #5                  // Field routerSnapshotSwitcher:Lorg/apache/dubbo/rpc/cluster/router/RouterSnapshotSwitcher;
       4: invokevirtual #6                  // Method org/apache/dubbo/rpc/cluster/router/RouterSnapshotSwitcher.cloneSnapshot:()[Ljava/lang/String;
       7: invokestatic  #7                  // Method java/util/Arrays.stream:([Ljava/lang/Object;)Ljava/util/stream/Stream;
      10: invokedynamic #8,  0              // InvokeDynamic #0:test:()Ljava/util/function/Predicate;
      15: invokeinterface #9,  2            // InterfaceMethod java/util/stream/Stream.filter:(Ljava/util/function/Predicate;)Ljava/util/stream/Stream;
      20: invokeinterface #10,  1           // InterfaceMethod java/util/stream/Stream.sorted:()Ljava/util/stream/Stream;
      25: ldc           #11                 // String \n\n
      27: invokestatic  #12                 // Method java/util/stream/Collectors.joining:(Ljava/lang/CharSequence;)Ljava/util/stream/Collector;
      30: invokeinterface #13,  2           // InterfaceMethod java/util/stream/Stream.collect:(Ljava/util/stream/Collector;)Ljava/lang/Object;
      35: checkcast     #14                 // class java/lang/String
      38: areturn
}
