Compiled from "GetRouterSnapshot.java"
public class org.apache.dubbo.qos.command.impl.GetRouterSnapshot implements org.apache.dubbo.qos.api.BaseCommand {
  private final org.apache.dubbo.rpc.model.FrameworkModel frameworkModel;

  public org.apache.dubbo.qos.command.impl.GetRouterSnapshot(org.apache.dubbo.rpc.model.FrameworkModel);
    Code:
       0: aload_0
       1: invokespecial #1                  // Method java/lang/Object."<init>":()V
       4: aload_0
       5: aload_1
       6: putfield      #2                  // Field frameworkModel:Lorg/apache/dubbo/rpc/model/FrameworkModel;
       9: return

  public java.lang.String execute(org.apache.dubbo.qos.api.CommandContext, java.lang.String[]);
    Code:
       0: aload_2
       1: arraylength
       2: iconst_1
       3: if_icmpeq     9
       6: ldc           #3                  // String args count should be 1. example getRouterSnapshot xx.xx.xxx.service
       8: areturn
       9: aload_2
      10: iconst_0
      11: aaload
      12: astore_3
      13: new           #4                  // class java/lang/StringBuilder
      16: dup
      17: invokespecial #5                  // Method java/lang/StringBuilder."<init>":()V
      20: astore        4
      22: aload_0
      23: getfield      #2                  // Field frameworkModel:Lorg/apache/dubbo/rpc/model/FrameworkModel;
      26: invokevirtual #6                  // Method org/apache/dubbo/rpc/model/FrameworkModel.getServiceRepository:()Lorg/apache/dubbo/rpc/model/FrameworkServiceRepository;
      29: invokevirtual #7                  // Method org/apache/dubbo/rpc/model/FrameworkServiceRepository.allConsumerModels:()Ljava/util/List;
      32: invokeinterface #8,  1            // InterfaceMethod java/util/List.iterator:()Ljava/util/Iterator;
      37: astore        5
      39: aload         5
      41: invokeinterface #9,  1            // InterfaceMethod java/util/Iterator.hasNext:()Z
      46: ifeq          291
      49: aload         5
      51: invokeinterface #10,  1           // InterfaceMethod java/util/Iterator.next:()Ljava/lang/Object;
      56: checkcast     #11                 // class org/apache/dubbo/rpc/model/ConsumerModel
      59: astore        6
      61: aload         6
      63: invokevirtual #12                 // Method org/apache/dubbo/rpc/model/ConsumerModel.getServiceMetadata:()Lorg/apache/dubbo/rpc/model/ServiceMetadata;
      66: astore        7
      68: aload         7
      70: invokevirtual #13                 // Method org/apache/dubbo/rpc/model/ServiceMetadata.getServiceKey:()Ljava/lang/String;
      73: aload_3
      74: invokevirtual #14                 // Method java/lang/String.matches:(Ljava/lang/String;)Z
      77: ifne          92
      80: aload         7
      82: invokevirtual #15                 // Method org/apache/dubbo/rpc/model/ServiceMetadata.getDisplayServiceKey:()Ljava/lang/String;
      85: aload_3
      86: invokevirtual #14                 // Method java/lang/String.matches:(Ljava/lang/String;)Z
      89: ifeq          283
      92: aload         7
      94: ldc           #17                 // String currentClusterInvoker
      96: invokevirtual #18                 // Method org/apache/dubbo/rpc/model/ServiceMetadata.getAttribute:(Ljava/lang/String;)Ljava/lang/Object;
      99: astore        8
     101: aload         8
     103: instanceof    #19                 // class java/util/Map
     106: ifeq          283
     109: aload         8
     111: checkcast     #19                 // class java/util/Map
     114: astore        9
     116: aload         9
     118: invokeinterface #20,  1           // InterfaceMethod java/util/Map.entrySet:()Ljava/util/Set;
     123: invokeinterface #21,  1           // InterfaceMethod java/util/Set.iterator:()Ljava/util/Iterator;
     128: astore        10
     130: aload         10
     132: invokeinterface #9,  1            // InterfaceMethod java/util/Iterator.hasNext:()Z
     137: ifeq          283
     140: aload         10
     142: invokeinterface #10,  1           // InterfaceMethod java/util/Iterator.next:()Ljava/lang/Object;
     147: checkcast     #22                 // class java/util/Map$Entry
     150: astore        11
     152: aload         11
     154: invokeinterface #23,  1           // InterfaceMethod java/util/Map$Entry.getValue:()Ljava/lang/Object;
     159: checkcast     #24                 // class org/apache/dubbo/registry/client/migration/MigrationInvoker
     162: invokevirtual #25                 // Method org/apache/dubbo/registry/client/migration/MigrationInvoker.getDirectory:()Lorg/apache/dubbo/rpc/cluster/Directory;
     165: astore        12
     167: aload         12
     169: invokeinterface #26,  1           // InterfaceMethod org/apache/dubbo/rpc/cluster/Directory.getRouterChain:()Lorg/apache/dubbo/rpc/cluster/RouterChain;
     174: invokevirtual #27                 // Method org/apache/dubbo/rpc/cluster/RouterChain.getHeadStateRouter:()Lorg/apache/dubbo/rpc/cluster/router/state/StateRouter;
     177: astore        13
     179: aload         4
     181: aload         7
     183: invokevirtual #13                 // Method org/apache/dubbo/rpc/model/ServiceMetadata.getServiceKey:()Ljava/lang/String;
     186: invokevirtual #28                 // Method java/lang/StringBuilder.append:(Ljava/lang/String;)Ljava/lang/StringBuilder;
     189: bipush        64
     191: invokevirtual #29                 // Method java/lang/StringBuilder.append:(C)Ljava/lang/StringBuilder;
     194: aload         7
     196: invokestatic  #30                 // Method java/lang/System.identityHashCode:(Ljava/lang/Object;)I
     199: invokestatic  #31                 // Method java/lang/Integer.toHexString:(I)Ljava/lang/String;
     202: invokevirtual #28                 // Method java/lang/StringBuilder.append:(Ljava/lang/String;)Ljava/lang/StringBuilder;
     205: ldc           #32                 // String \n
     207: invokevirtual #28                 // Method java/lang/StringBuilder.append:(Ljava/lang/String;)Ljava/lang/StringBuilder;
     210: ldc           #33                 // String [ All Invokers:
     212: invokevirtual #28                 // Method java/lang/StringBuilder.append:(Ljava/lang/String;)Ljava/lang/StringBuilder;
     215: aload         12
     217: invokeinterface #34,  1           // InterfaceMethod org/apache/dubbo/rpc/cluster/Directory.getAllInvokers:()Ljava/util/List;
     222: invokeinterface #35,  1           // InterfaceMethod java/util/List.size:()I
     227: invokevirtual #36                 // Method java/lang/StringBuilder.append:(I)Ljava/lang/StringBuilder;
     230: ldc           #37                 // String  ]
     232: invokevirtual #28                 // Method java/lang/StringBuilder.append:(Ljava/lang/String;)Ljava/lang/StringBuilder;
     235: ldc           #38                 // String [ Valid Invokers:
     237: invokevirtual #28                 // Method java/lang/StringBuilder.append:(Ljava/lang/String;)Ljava/lang/StringBuilder;
     240: aload         12
     242: checkcast     #39                 // class org/apache/dubbo/rpc/cluster/directory/AbstractDirectory
     245: invokevirtual #40                 // Method org/apache/dubbo/rpc/cluster/directory/AbstractDirectory.getValidInvokers:()Lorg/apache/dubbo/rpc/cluster/router/state/BitList;
     248: invokevirtual #41                 // Method org/apache/dubbo/rpc/cluster/router/state/BitList.size:()I
     251: invokevirtual #36                 // Method java/lang/StringBuilder.append:(I)Ljava/lang/StringBuilder;
     254: ldc           #42                 // String  ]\n
     256: invokevirtual #28                 // Method java/lang/StringBuilder.append:(Ljava/lang/String;)Ljava/lang/StringBuilder;
     259: ldc           #32                 // String \n
     261: invokevirtual #28                 // Method java/lang/StringBuilder.append:(Ljava/lang/String;)Ljava/lang/StringBuilder;
     264: aload         13
     266: invokeinterface #43,  1           // InterfaceMethod org/apache/dubbo/rpc/cluster/router/state/StateRouter.buildSnapshot:()Ljava/lang/String;
     271: invokevirtual #28                 // Method java/lang/StringBuilder.append:(Ljava/lang/String;)Ljava/lang/StringBuilder;
     274: ldc           #44                 // String \n\n
     276: invokevirtual #28                 // Method java/lang/StringBuilder.append:(Ljava/lang/String;)Ljava/lang/StringBuilder;
     279: pop
     280: goto          130
     283: goto          288
     286: astore        7
     288: goto          39
     291: aload         4
     293: invokevirtual #46                 // Method java/lang/StringBuilder.toString:()Ljava/lang/String;
     296: areturn
    Exception table:
       from    to  target type
          61   283   286   Class java/lang/Throwable
}
