Compiled from "GracefulShutdown.java"
public class org.apache.dubbo.qos.command.impl.GracefulShutdown implements org.apache.dubbo.qos.api.BaseCommand {
  private final org.apache.dubbo.qos.command.impl.Offline offline;

  private final org.apache.dubbo.rpc.model.FrameworkModel frameworkModel;

  public org.apache.dubbo.qos.command.impl.GracefulShutdown(org.apache.dubbo.rpc.model.FrameworkModel);
    Code:
       0: aload_0
       1: invokespecial #1                  // Method java/lang/Object."<init>":()V
       4: aload_0
       5: new           #2                  // class org/apache/dubbo/qos/command/impl/Offline
       8: dup
       9: aload_1
      10: invokespecial #3                  // Method org/apache/dubbo/qos/command/impl/Offline."<init>":(Lorg/apache/dubbo/rpc/model/FrameworkModel;)V
      13: putfield      #4                  // Field offline:Lorg/apache/dubbo/qos/command/impl/Offline;
      16: aload_0
      17: aload_1
      18: putfield      #5                  // Field frameworkModel:Lorg/apache/dubbo/rpc/model/FrameworkModel;
      21: return

  public java.lang.String execute(org.apache.dubbo.qos.api.CommandContext, java.lang.String[]);
    Code:
       0: aload_0
       1: getfield      #4                  // Field offline:Lorg/apache/dubbo/qos/command/impl/Offline;
       4: aload_1
       5: iconst_0
       6: anewarray     #6                  // class java/lang/String
       9: invokevirtual #7                  // Method org/apache/dubbo/qos/command/impl/Offline.execute:(Lorg/apache/dubbo/qos/api/CommandContext;[Ljava/lang/String;)Ljava/lang/String;
      12: pop
      13: aload_0
      14: getfield      #5                  // Field frameworkModel:Lorg/apache/dubbo/rpc/model/FrameworkModel;
      17: invokestatic  #8                  // InterfaceMethod org/apache/dubbo/rpc/GracefulShutdown.getGracefulShutdowns:(Lorg/apache/dubbo/rpc/model/FrameworkModel;)Ljava/util/List;
      20: invokeinterface #9,  1            // InterfaceMethod java/util/List.iterator:()Ljava/util/Iterator;
      25: astore_3
      26: aload_3
      27: invokeinterface #10,  1           // InterfaceMethod java/util/Iterator.hasNext:()Z
      32: ifeq          56
      35: aload_3
      36: invokeinterface #11,  1           // InterfaceMethod java/util/Iterator.next:()Ljava/lang/Object;
      41: checkcast     #12                 // class org/apache/dubbo/rpc/GracefulShutdown
      44: astore        4
      46: aload         4
      48: invokeinterface #13,  1           // InterfaceMethod org/apache/dubbo/rpc/GracefulShutdown.readonly:()V
      53: goto          26
      56: ldc           #14                 // String OK
      58: areturn
}
