Compiled from "Help.java"
class org.apache.dubbo.qos.command.impl.Help$1 implements java.util.Comparator<java.lang.Class<?>> {
  final org.apache.dubbo.qos.command.impl.Help this$0;

  org.apache.dubbo.qos.command.impl.Help$1(org.apache.dubbo.qos.command.impl.Help);
    Code:
       0: aload_0
       1: aload_1
       2: putfield      #1                  // Field this$0:Lorg/apache/dubbo/qos/command/impl/Help;
       5: aload_0
       6: invokespecial #2                  // Method java/lang/Object."<init>":()V
       9: return

  public int compare(java.lang.Class<?>, java.lang.Class<?>);
    Code:
       0: aload_1
       1: ldc           #3                  // class org/apache/dubbo/qos/api/Cmd
       3: invokevirtual #4                  // Method java/lang/Class.getAnnotation:(Ljava/lang/Class;)Ljava/lang/annotation/Annotation;
       6: checkcast     #3                  // class org/apache/dubbo/qos/api/Cmd
       9: invokeinterface #5,  1            // InterfaceMethod org/apache/dubbo/qos/api/Cmd.sort:()I
      14: invokestatic  #6                  // Method java/lang/Integer.valueOf:(I)Ljava/lang/Integer;
      17: astore_3
      18: aload_2
      19: ldc           #3                  // class org/apache/dubbo/qos/api/Cmd
      21: invokevirtual #4                  // Method java/lang/Class.getAnnotation:(Ljava/lang/Class;)Ljava/lang/annotation/Annotation;
      24: checkcast     #3                  // class org/apache/dubbo/qos/api/Cmd
      27: invokeinterface #5,  1            // InterfaceMethod org/apache/dubbo/qos/api/Cmd.sort:()I
      32: invokestatic  #6                  // Method java/lang/Integer.valueOf:(I)Ljava/lang/Integer;
      35: astore        4
      37: aload_3
      38: aload         4
      40: invokevirtual #7                  // Method java/lang/Integer.compareTo:(Ljava/lang/Integer;)I
      43: ireturn

  public int compare(java.lang.Object, java.lang.Object);
    Code:
       0: aload_0
       1: aload_1
       2: checkcast     #8                  // class java/lang/Class
       5: aload_2
       6: checkcast     #8                  // class java/lang/Class
       9: invokevirtual #9                  // Method compare:(Ljava/lang/Class;Ljava/lang/Class;)I
      12: ireturn
}
