Compiled from "Help.java"
public class org.apache.dubbo.qos.command.impl.Help implements org.apache.dubbo.qos.api.BaseCommand {
  private final org.apache.dubbo.qos.command.util.CommandHelper commandHelper;

  private static final java.lang.String MAIN_HELP;

  private static final java.util.Map<java.lang.String, java.lang.String> processedTable;

  public org.apache.dubbo.qos.command.impl.Help(org.apache.dubbo.rpc.model.FrameworkModel);
    Code:
       0: aload_0
       1: invokespecial #1                  // Method java/lang/Object."<init>":()V
       4: aload_0
       5: new           #2                  // class org/apache/dubbo/qos/command/util/CommandHelper
       8: dup
       9: aload_1
      10: invokespecial #3                  // Method org/apache/dubbo/qos/command/util/CommandHelper."<init>":(Lorg/apache/dubbo/rpc/model/FrameworkModel;)V
      13: putfield      #4                  // Field commandHelper:Lorg/apache/dubbo/qos/command/util/CommandHelper;
      16: return

  public java.lang.String execute(org.apache.dubbo.qos.api.CommandContext, java.lang.String[]);
    Code:
       0: aload_2
       1: invokestatic  #5                  // Method org/apache/dubbo/common/utils/ArrayUtils.isNotEmpty:([Ljava/lang/Object;)Z
       4: ifeq          28
       7: getstatic     #6                  // Field processedTable:Ljava/util/Map;
      10: aload_2
      11: iconst_0
      12: aaload
      13: aload_0
      14: invokedynamic #7,  0              // InvokeDynamic #0:apply:(Lorg/apache/dubbo/qos/command/impl/Help;)Ljava/util/function/Function;
      19: invokeinterface #8,  3            // InterfaceMethod java/util/Map.computeIfAbsent:(Ljava/lang/Object;Ljava/util/function/Function;)Ljava/lang/Object;
      24: checkcast     #9                  // class java/lang/String
      27: areturn
      28: getstatic     #6                  // Field processedTable:Ljava/util/Map;
      31: ldc           #11                 // String mainHelp
      33: aload_0
      34: invokedynamic #12,  0             // InvokeDynamic #1:apply:(Lorg/apache/dubbo/qos/command/impl/Help;)Ljava/util/function/Function;
      39: invokeinterface #8,  3            // InterfaceMethod java/util/Map.computeIfAbsent:(Ljava/lang/Object;Ljava/util/function/Function;)Ljava/lang/Object;
      44: checkcast     #9                  // class java/lang/String
      47: areturn

  private java.lang.String commandHelp(java.lang.String);
    Code:
       0: aload_0
       1: getfield      #4                  // Field commandHelper:Lorg/apache/dubbo/qos/command/util/CommandHelper;
       4: aload_1
       5: invokevirtual #13                 // Method org/apache/dubbo/qos/command/util/CommandHelper.hasCommand:(Ljava/lang/String;)Z
       8: ifne          31
      11: new           #14                 // class java/lang/StringBuilder
      14: dup
      15: invokespecial #15                 // Method java/lang/StringBuilder."<init>":()V
      18: ldc           #16                 // String no such command:
      20: invokevirtual #17                 // Method java/lang/StringBuilder.append:(Ljava/lang/String;)Ljava/lang/StringBuilder;
      23: aload_1
      24: invokevirtual #17                 // Method java/lang/StringBuilder.append:(Ljava/lang/String;)Ljava/lang/StringBuilder;
      27: invokevirtual #18                 // Method java/lang/StringBuilder.toString:()Ljava/lang/String;
      30: areturn
      31: aload_0
      32: getfield      #4                  // Field commandHelper:Lorg/apache/dubbo/qos/command/util/CommandHelper;
      35: aload_1
      36: invokevirtual #19                 // Method org/apache/dubbo/qos/command/util/CommandHelper.getCommandClass:(Ljava/lang/String;)Ljava/lang/Class;
      39: astore_2
      40: aload_2
      41: ldc           #20                 // class org/apache/dubbo/qos/api/Cmd
      43: invokevirtual #21                 // Method java/lang/Class.getAnnotation:(Ljava/lang/Class;)Ljava/lang/annotation/Annotation;
      46: checkcast     #20                 // class org/apache/dubbo/qos/api/Cmd
      49: astore_3
      50: new           #22                 // class org/apache/dubbo/qos/textui/TTable
      53: dup
      54: iconst_2
      55: anewarray     #23                 // class org/apache/dubbo/qos/textui/TTable$ColumnDefine
      58: dup
      59: iconst_0
      60: new           #23                 // class org/apache/dubbo/qos/textui/TTable$ColumnDefine
      63: dup
      64: getstatic     #24                 // Field org/apache/dubbo/qos/textui/TTable$Align.RIGHT:Lorg/apache/dubbo/qos/textui/TTable$Align;
      67: invokespecial #25                 // Method org/apache/dubbo/qos/textui/TTable$ColumnDefine."<init>":(Lorg/apache/dubbo/qos/textui/TTable$Align;)V
      70: aastore
      71: dup
      72: iconst_1
      73: new           #23                 // class org/apache/dubbo/qos/textui/TTable$ColumnDefine
      76: dup
      77: bipush        80
      79: iconst_0
      80: getstatic     #26                 // Field org/apache/dubbo/qos/textui/TTable$Align.LEFT:Lorg/apache/dubbo/qos/textui/TTable$Align;
      83: invokespecial #27                 // Method org/apache/dubbo/qos/textui/TTable$ColumnDefine."<init>":(IZLorg/apache/dubbo/qos/textui/TTable$Align;)V
      86: aastore
      87: invokespecial #28                 // Method org/apache/dubbo/qos/textui/TTable."<init>":([Lorg/apache/dubbo/qos/textui/TTable$ColumnDefine;)V
      90: astore        4
      92: aload         4
      94: iconst_2
      95: anewarray     #29                 // class java/lang/Object
      98: dup
      99: iconst_0
     100: ldc           #30                 // String COMMAND NAME
     102: aastore
     103: dup
     104: iconst_1
     105: aload_1
     106: aastore
     107: invokevirtual #31                 // Method org/apache/dubbo/qos/textui/TTable.addRow:([Ljava/lang/Object;)Lorg/apache/dubbo/qos/textui/TTable;
     110: pop
     111: aconst_null
     112: aload_3
     113: invokeinterface #32,  1           // InterfaceMethod org/apache/dubbo/qos/api/Cmd.example:()[Ljava/lang/String;
     118: if_acmpeq     144
     121: aload         4
     123: iconst_2
     124: anewarray     #29                 // class java/lang/Object
     127: dup
     128: iconst_0
     129: ldc           #33                 // String EXAMPLE
     131: aastore
     132: dup
     133: iconst_1
     134: aload_0
     135: aload_3
     136: invokespecial #34                 // Method drawExample:(Lorg/apache/dubbo/qos/api/Cmd;)Ljava/lang/String;
     139: aastore
     140: invokevirtual #31                 // Method org/apache/dubbo/qos/textui/TTable.addRow:([Ljava/lang/Object;)Lorg/apache/dubbo/qos/textui/TTable;
     143: pop
     144: aload         4
     146: iconst_1
     147: invokevirtual #35                 // Method org/apache/dubbo/qos/textui/TTable.padding:(I)Lorg/apache/dubbo/qos/textui/TTable;
     150: invokevirtual #36                 // Method org/apache/dubbo/qos/textui/TTable.rendering:()Ljava/lang/String;
     153: areturn

  private java.lang.String drawExample(org.apache.dubbo.qos.api.Cmd);
    Code:
       0: new           #14                 // class java/lang/StringBuilder
       3: dup
       4: invokespecial #15                 // Method java/lang/StringBuilder."<init>":()V
       7: astore_2
       8: aload_1
       9: invokeinterface #32,  1           // InterfaceMethod org/apache/dubbo/qos/api/Cmd.example:()[Ljava/lang/String;
      14: astore_3
      15: aload_3
      16: arraylength
      17: istore        4
      19: iconst_0
      20: istore        5
      22: iload         5
      24: iload         4
      26: if_icmpge     53
      29: aload_3
      30: iload         5
      32: aaload
      33: astore        6
      35: aload_2
      36: aload         6
      38: invokevirtual #17                 // Method java/lang/StringBuilder.append:(Ljava/lang/String;)Ljava/lang/StringBuilder;
      41: bipush        10
      43: invokevirtual #37                 // Method java/lang/StringBuilder.append:(C)Ljava/lang/StringBuilder;
      46: pop
      47: iinc          5, 1
      50: goto          22
      53: aload_2
      54: invokevirtual #18                 // Method java/lang/StringBuilder.toString:()Ljava/lang/String;
      57: areturn

  private java.lang.String mainHelp();
    Code:
       0: new           #22                 // class org/apache/dubbo/qos/textui/TTable
       3: dup
       4: iconst_2
       5: anewarray     #23                 // class org/apache/dubbo/qos/textui/TTable$ColumnDefine
       8: dup
       9: iconst_0
      10: new           #23                 // class org/apache/dubbo/qos/textui/TTable$ColumnDefine
      13: dup
      14: getstatic     #24                 // Field org/apache/dubbo/qos/textui/TTable$Align.RIGHT:Lorg/apache/dubbo/qos/textui/TTable$Align;
      17: invokespecial #25                 // Method org/apache/dubbo/qos/textui/TTable$ColumnDefine."<init>":(Lorg/apache/dubbo/qos/textui/TTable$Align;)V
      20: aastore
      21: dup
      22: iconst_1
      23: new           #23                 // class org/apache/dubbo/qos/textui/TTable$ColumnDefine
      26: dup
      27: bipush        80
      29: iconst_0
      30: getstatic     #26                 // Field org/apache/dubbo/qos/textui/TTable$Align.LEFT:Lorg/apache/dubbo/qos/textui/TTable$Align;
      33: invokespecial #27                 // Method org/apache/dubbo/qos/textui/TTable$ColumnDefine."<init>":(IZLorg/apache/dubbo/qos/textui/TTable$Align;)V
      36: aastore
      37: invokespecial #28                 // Method org/apache/dubbo/qos/textui/TTable."<init>":([Lorg/apache/dubbo/qos/textui/TTable$ColumnDefine;)V
      40: astore_1
      41: aload_0
      42: getfield      #4                  // Field commandHelper:Lorg/apache/dubbo/qos/command/util/CommandHelper;
      45: invokevirtual #38                 // Method org/apache/dubbo/qos/command/util/CommandHelper.getAllCommandClass:()Ljava/util/List;
      48: astore_2
      49: aload_2
      50: new           #39                 // class org/apache/dubbo/qos/command/impl/Help$1
      53: dup
      54: aload_0
      55: invokespecial #40                 // Method org/apache/dubbo/qos/command/impl/Help$1."<init>":(Lorg/apache/dubbo/qos/command/impl/Help;)V
      58: invokestatic  #41                 // Method java/util/Collections.sort:(Ljava/util/List;Ljava/util/Comparator;)V
      61: aload_2
      62: invokeinterface #42,  1           // InterfaceMethod java/util/List.iterator:()Ljava/util/Iterator;
      67: astore_3
      68: aload_3
      69: invokeinterface #43,  1           // InterfaceMethod java/util/Iterator.hasNext:()Z
      74: ifeq          142
      77: aload_3
      78: invokeinterface #44,  1           // InterfaceMethod java/util/Iterator.next:()Ljava/lang/Object;
      83: checkcast     #45                 // class java/lang/Class
      86: astore        4
      88: aload         4
      90: ldc           #20                 // class org/apache/dubbo/qos/api/Cmd
      92: invokevirtual #46                 // Method java/lang/Class.isAnnotationPresent:(Ljava/lang/Class;)Z
      95: ifeq          139
      98: aload         4
     100: ldc           #20                 // class org/apache/dubbo/qos/api/Cmd
     102: invokevirtual #21                 // Method java/lang/Class.getAnnotation:(Ljava/lang/Class;)Ljava/lang/annotation/Annotation;
     105: checkcast     #20                 // class org/apache/dubbo/qos/api/Cmd
     108: astore        5
     110: aload_1
     111: iconst_2
     112: anewarray     #29                 // class java/lang/Object
     115: dup
     116: iconst_0
     117: aload         5
     119: invokeinterface #47,  1           // InterfaceMethod org/apache/dubbo/qos/api/Cmd.name:()Ljava/lang/String;
     124: aastore
     125: dup
     126: iconst_1
     127: aload         5
     129: invokeinterface #48,  1           // InterfaceMethod org/apache/dubbo/qos/api/Cmd.summary:()Ljava/lang/String;
     134: aastore
     135: invokevirtual #31                 // Method org/apache/dubbo/qos/textui/TTable.addRow:([Ljava/lang/Object;)Lorg/apache/dubbo/qos/textui/TTable;
     138: pop
     139: goto          68
     142: aload_1
     143: iconst_1
     144: invokevirtual #35                 // Method org/apache/dubbo/qos/textui/TTable.padding:(I)Lorg/apache/dubbo/qos/textui/TTable;
     147: invokevirtual #36                 // Method org/apache/dubbo/qos/textui/TTable.rendering:()Ljava/lang/String;
     150: areturn

  private java.lang.String lambda$execute$0(java.lang.String);
    Code:
       0: aload_0
       1: invokespecial #49                 // Method mainHelp:()Ljava/lang/String;
       4: areturn

  static {};
    Code:
       0: new           #50                 // class java/util/WeakHashMap
       3: dup
       4: invokespecial #51                 // Method java/util/WeakHashMap."<init>":()V
       7: putstatic     #6                  // Field processedTable:Ljava/util/Map;
      10: return
}
