Compiled from "LoggerInfo.java"
public class org.apache.dubbo.qos.command.impl.LoggerInfo implements org.apache.dubbo.qos.api.BaseCommand {
  public org.apache.dubbo.qos.command.impl.LoggerInfo();
    Code:
       0: aload_0
       1: invokespecial #1                  // Method java/lang/Object."<init>":()V
       4: return

  public java.lang.String execute(org.apache.dubbo.qos.api.CommandContext, java.lang.String[]);
    Code:
       0: ldc           #2                  // String ,
       2: invokestatic  #3                  // Method org/apache/dubbo/common/logger/LoggerFactory.getAvailableAdapter:()Ljava/util/List;
       5: iconst_0
       6: anewarray     #4                  // class java/lang/String
       9: invokeinterface #5,  2            // InterfaceMethod java/util/List.toArray:([Ljava/lang/Object;)[Ljava/lang/Object;
      14: checkcast     #6                  // class "[Ljava/lang/CharSequence;"
      17: invokestatic  #7                  // Method java/lang/String.join:(Ljava/lang/CharSequence;[Ljava/lang/CharSequence;)Ljava/lang/String;
      20: astore_3
      21: invokestatic  #8                  // Method org/apache/dubbo/common/logger/LoggerFactory.getCurrentAdapter:()Ljava/lang/String;
      24: astore        4
      26: invokestatic  #9                  // Method org/apache/dubbo/common/logger/LoggerFactory.getLevel:()Lorg/apache/dubbo/common/logger/Level;
      29: astore        5
      31: new           #10                 // class java/lang/StringBuilder
      34: dup
      35: invokespecial #11                 // Method java/lang/StringBuilder."<init>":()V
      38: ldc           #12                 // String Available logger adapters: [
      40: invokevirtual #13                 // Method java/lang/StringBuilder.append:(Ljava/lang/String;)Ljava/lang/StringBuilder;
      43: aload_3
      44: invokevirtual #13                 // Method java/lang/StringBuilder.append:(Ljava/lang/String;)Ljava/lang/StringBuilder;
      47: ldc           #14                 // String ]. Current Adapter: [
      49: invokevirtual #13                 // Method java/lang/StringBuilder.append:(Ljava/lang/String;)Ljava/lang/StringBuilder;
      52: aload         4
      54: invokevirtual #13                 // Method java/lang/StringBuilder.append:(Ljava/lang/String;)Ljava/lang/StringBuilder;
      57: ldc           #15                 // String ]. Log level:
      59: invokevirtual #13                 // Method java/lang/StringBuilder.append:(Ljava/lang/String;)Ljava/lang/StringBuilder;
      62: aload         5
      64: invokevirtual #16                 // Method org/apache/dubbo/common/logger/Level.name:()Ljava/lang/String;
      67: invokevirtual #13                 // Method java/lang/StringBuilder.append:(Ljava/lang/String;)Ljava/lang/StringBuilder;
      70: invokevirtual #17                 // Method java/lang/StringBuilder.toString:()Ljava/lang/String;
      73: areturn
}
