Compiled from "Ls.java"
public class org.apache.dubbo.qos.command.impl.Ls implements org.apache.dubbo.qos.api.BaseCommand {
  private final org.apache.dubbo.rpc.model.FrameworkModel frameworkModel;

  public org.apache.dubbo.qos.command.impl.Ls(org.apache.dubbo.rpc.model.FrameworkModel);
    Code:
       0: aload_0
       1: invokespecial #1                  // Method java/lang/Object."<init>":()V
       4: aload_0
       5: aload_1
       6: putfield      #2                  // Field frameworkModel:Lorg/apache/dubbo/rpc/model/FrameworkModel;
       9: return

  public java.lang.String execute(org.apache.dubbo.qos.api.CommandContext, java.lang.String[]);
    Code:
       0: new           #3                  // class java/lang/StringBuilder
       3: dup
       4: invokespecial #4                  // Method java/lang/StringBuilder."<init>":()V
       7: astore_3
       8: aload_3
       9: aload_0
      10: invokevirtual #5                  // Method listProvider:()Ljava/lang/String;
      13: invokevirtual #6                  // Method java/lang/StringBuilder.append:(Ljava/lang/String;)Ljava/lang/StringBuilder;
      16: pop
      17: aload_3
      18: aload_0
      19: invokevirtual #7                  // Method listConsumer:()Ljava/lang/String;
      22: invokevirtual #6                  // Method java/lang/StringBuilder.append:(Ljava/lang/String;)Ljava/lang/StringBuilder;
      25: pop
      26: aload_3
      27: invokevirtual #8                  // Method java/lang/StringBuilder.toString:()Ljava/lang/String;
      30: areturn

  public java.lang.String listProvider();
    Code:
       0: new           #3                  // class java/lang/StringBuilder
       3: dup
       4: invokespecial #4                  // Method java/lang/StringBuilder."<init>":()V
       7: astore_1
       8: aload_1
       9: new           #3                  // class java/lang/StringBuilder
      12: dup
      13: invokespecial #4                  // Method java/lang/StringBuilder."<init>":()V
      16: ldc           #9                  // String As Provider side:
      18: invokevirtual #6                  // Method java/lang/StringBuilder.append:(Ljava/lang/String;)Ljava/lang/StringBuilder;
      21: invokestatic  #10                 // Method java/lang/System.lineSeparator:()Ljava/lang/String;
      24: invokevirtual #6                  // Method java/lang/StringBuilder.append:(Ljava/lang/String;)Ljava/lang/StringBuilder;
      27: invokevirtual #8                  // Method java/lang/StringBuilder.toString:()Ljava/lang/String;
      30: invokevirtual #6                  // Method java/lang/StringBuilder.append:(Ljava/lang/String;)Ljava/lang/StringBuilder;
      33: pop
      34: aload_0
      35: getfield      #2                  // Field frameworkModel:Lorg/apache/dubbo/rpc/model/FrameworkModel;
      38: invokevirtual #11                 // Method org/apache/dubbo/rpc/model/FrameworkModel.getServiceRepository:()Lorg/apache/dubbo/rpc/model/FrameworkServiceRepository;
      41: invokevirtual #12                 // Method org/apache/dubbo/rpc/model/FrameworkServiceRepository.allProviderModels:()Ljava/util/List;
      44: astore_2
      45: new           #13                 // class org/apache/dubbo/qos/textui/TTable
      48: dup
      49: iconst_2
      50: anewarray     #14                 // class org/apache/dubbo/qos/textui/TTable$ColumnDefine
      53: dup
      54: iconst_0
      55: new           #14                 // class org/apache/dubbo/qos/textui/TTable$ColumnDefine
      58: dup
      59: getstatic     #15                 // Field org/apache/dubbo/qos/textui/TTable$Align.MIDDLE:Lorg/apache/dubbo/qos/textui/TTable$Align;
      62: invokespecial #16                 // Method org/apache/dubbo/qos/textui/TTable$ColumnDefine."<init>":(Lorg/apache/dubbo/qos/textui/TTable$Align;)V
      65: aastore
      66: dup
      67: iconst_1
      68: new           #14                 // class org/apache/dubbo/qos/textui/TTable$ColumnDefine
      71: dup
      72: getstatic     #15                 // Field org/apache/dubbo/qos/textui/TTable$Align.MIDDLE:Lorg/apache/dubbo/qos/textui/TTable$Align;
      75: invokespecial #16                 // Method org/apache/dubbo/qos/textui/TTable$ColumnDefine."<init>":(Lorg/apache/dubbo/qos/textui/TTable$Align;)V
      78: aastore
      79: invokespecial #17                 // Method org/apache/dubbo/qos/textui/TTable."<init>":([Lorg/apache/dubbo/qos/textui/TTable$ColumnDefine;)V
      82: astore_3
      83: aload_3
      84: iconst_2
      85: anewarray     #18                 // class java/lang/Object
      88: dup
      89: iconst_0
      90: ldc           #19                 // String Provider Service Name
      92: aastore
      93: dup
      94: iconst_1
      95: ldc           #20                 // String PUB
      97: aastore
      98: invokevirtual #21                 // Method org/apache/dubbo/qos/textui/TTable.addRow:([Ljava/lang/Object;)Lorg/apache/dubbo/qos/textui/TTable;
     101: pop
     102: aload_2
     103: invokeinterface #22,  1           // InterfaceMethod java/util/Collection.iterator:()Ljava/util/Iterator;
     108: astore        4
     110: aload         4
     112: invokeinterface #23,  1           // InterfaceMethod java/util/Iterator.hasNext:()Z
     117: ifeq          217
     120: aload         4
     122: invokeinterface #24,  1           // InterfaceMethod java/util/Iterator.next:()Ljava/lang/Object;
     127: checkcast     #25                 // class org/apache/dubbo/rpc/model/ProviderModel
     130: astore        5
     132: aload         5
     134: invokevirtual #26                 // Method org/apache/dubbo/rpc/model/ProviderModel.getModuleModel:()Lorg/apache/dubbo/rpc/model/ModuleModel;
     137: invokevirtual #27                 // Method org/apache/dubbo/rpc/model/ModuleModel.isInternal:()Z
     140: ifeq          189
     143: aload_3
     144: iconst_2
     145: anewarray     #18                 // class java/lang/Object
     148: dup
     149: iconst_0
     150: new           #3                  // class java/lang/StringBuilder
     153: dup
     154: invokespecial #4                  // Method java/lang/StringBuilder."<init>":()V
     157: ldc           #28                 // String DubboInternal -
     159: invokevirtual #6                  // Method java/lang/StringBuilder.append:(Ljava/lang/String;)Ljava/lang/StringBuilder;
     162: aload         5
     164: invokevirtual #29                 // Method org/apache/dubbo/rpc/model/ProviderModel.getServiceKey:()Ljava/lang/String;
     167: invokevirtual #6                  // Method java/lang/StringBuilder.append:(Ljava/lang/String;)Ljava/lang/StringBuilder;
     170: invokevirtual #8                  // Method java/lang/StringBuilder.toString:()Ljava/lang/String;
     173: aastore
     174: dup
     175: iconst_1
     176: aload         5
     178: invokestatic  #30                 // Method org/apache/dubbo/qos/command/util/ServiceCheckUtils.getRegisterStatus:(Lorg/apache/dubbo/rpc/model/ProviderModel;)Ljava/lang/String;
     181: aastore
     182: invokevirtual #21                 // Method org/apache/dubbo/qos/textui/TTable.addRow:([Ljava/lang/Object;)Lorg/apache/dubbo/qos/textui/TTable;
     185: pop
     186: goto          214
     189: aload_3
     190: iconst_2
     191: anewarray     #18                 // class java/lang/Object
     194: dup
     195: iconst_0
     196: aload         5
     198: invokevirtual #29                 // Method org/apache/dubbo/rpc/model/ProviderModel.getServiceKey:()Ljava/lang/String;
     201: aastore
     202: dup
     203: iconst_1
     204: aload         5
     206: invokestatic  #30                 // Method org/apache/dubbo/qos/command/util/ServiceCheckUtils.getRegisterStatus:(Lorg/apache/dubbo/rpc/model/ProviderModel;)Ljava/lang/String;
     209: aastore
     210: invokevirtual #21                 // Method org/apache/dubbo/qos/textui/TTable.addRow:([Ljava/lang/Object;)Lorg/apache/dubbo/qos/textui/TTable;
     213: pop
     214: goto          110
     217: aload_1
     218: aload_3
     219: invokevirtual #31                 // Method org/apache/dubbo/qos/textui/TTable.rendering:()Ljava/lang/String;
     222: invokevirtual #6                  // Method java/lang/StringBuilder.append:(Ljava/lang/String;)Ljava/lang/StringBuilder;
     225: pop
     226: aload_1
     227: invokevirtual #8                  // Method java/lang/StringBuilder.toString:()Ljava/lang/String;
     230: areturn

  public java.lang.String listConsumer();
    Code:
       0: new           #3                  // class java/lang/StringBuilder
       3: dup
       4: invokespecial #4                  // Method java/lang/StringBuilder."<init>":()V
       7: astore_1
       8: aload_1
       9: new           #3                  // class java/lang/StringBuilder
      12: dup
      13: invokespecial #4                  // Method java/lang/StringBuilder."<init>":()V
      16: ldc           #32                 // String As Consumer side:
      18: invokevirtual #6                  // Method java/lang/StringBuilder.append:(Ljava/lang/String;)Ljava/lang/StringBuilder;
      21: invokestatic  #10                 // Method java/lang/System.lineSeparator:()Ljava/lang/String;
      24: invokevirtual #6                  // Method java/lang/StringBuilder.append:(Ljava/lang/String;)Ljava/lang/StringBuilder;
      27: invokevirtual #8                  // Method java/lang/StringBuilder.toString:()Ljava/lang/String;
      30: invokevirtual #6                  // Method java/lang/StringBuilder.append:(Ljava/lang/String;)Ljava/lang/StringBuilder;
      33: pop
      34: aload_0
      35: getfield      #2                  // Field frameworkModel:Lorg/apache/dubbo/rpc/model/FrameworkModel;
      38: invokevirtual #11                 // Method org/apache/dubbo/rpc/model/FrameworkModel.getServiceRepository:()Lorg/apache/dubbo/rpc/model/FrameworkServiceRepository;
      41: invokevirtual #33                 // Method org/apache/dubbo/rpc/model/FrameworkServiceRepository.allConsumerModels:()Ljava/util/List;
      44: astore_2
      45: new           #13                 // class org/apache/dubbo/qos/textui/TTable
      48: dup
      49: iconst_2
      50: anewarray     #14                 // class org/apache/dubbo/qos/textui/TTable$ColumnDefine
      53: dup
      54: iconst_0
      55: new           #14                 // class org/apache/dubbo/qos/textui/TTable$ColumnDefine
      58: dup
      59: getstatic     #15                 // Field org/apache/dubbo/qos/textui/TTable$Align.MIDDLE:Lorg/apache/dubbo/qos/textui/TTable$Align;
      62: invokespecial #16                 // Method org/apache/dubbo/qos/textui/TTable$ColumnDefine."<init>":(Lorg/apache/dubbo/qos/textui/TTable$Align;)V
      65: aastore
      66: dup
      67: iconst_1
      68: new           #14                 // class org/apache/dubbo/qos/textui/TTable$ColumnDefine
      71: dup
      72: getstatic     #15                 // Field org/apache/dubbo/qos/textui/TTable$Align.MIDDLE:Lorg/apache/dubbo/qos/textui/TTable$Align;
      75: invokespecial #16                 // Method org/apache/dubbo/qos/textui/TTable$ColumnDefine."<init>":(Lorg/apache/dubbo/qos/textui/TTable$Align;)V
      78: aastore
      79: invokespecial #17                 // Method org/apache/dubbo/qos/textui/TTable."<init>":([Lorg/apache/dubbo/qos/textui/TTable$ColumnDefine;)V
      82: astore_3
      83: aload_3
      84: iconst_2
      85: anewarray     #18                 // class java/lang/Object
      88: dup
      89: iconst_0
      90: ldc           #34                 // String Consumer Service Name
      92: aastore
      93: dup
      94: iconst_1
      95: ldc           #35                 // String NUM
      97: aastore
      98: invokevirtual #21                 // Method org/apache/dubbo/qos/textui/TTable.addRow:([Ljava/lang/Object;)Lorg/apache/dubbo/qos/textui/TTable;
     101: pop
     102: aload_2
     103: invokeinterface #22,  1           // InterfaceMethod java/util/Collection.iterator:()Ljava/util/Iterator;
     108: astore        4
     110: aload         4
     112: invokeinterface #23,  1           // InterfaceMethod java/util/Iterator.hasNext:()Z
     117: ifeq          160
     120: aload         4
     122: invokeinterface #24,  1           // InterfaceMethod java/util/Iterator.next:()Ljava/lang/Object;
     127: checkcast     #36                 // class org/apache/dubbo/rpc/model/ConsumerModel
     130: astore        5
     132: aload_3
     133: iconst_2
     134: anewarray     #18                 // class java/lang/Object
     137: dup
     138: iconst_0
     139: aload         5
     141: invokevirtual #37                 // Method org/apache/dubbo/rpc/model/ConsumerModel.getServiceKey:()Ljava/lang/String;
     144: aastore
     145: dup
     146: iconst_1
     147: aload         5
     149: invokestatic  #38                 // Method org/apache/dubbo/qos/command/util/ServiceCheckUtils.getConsumerAddressNum:(Lorg/apache/dubbo/rpc/model/ConsumerModel;)Ljava/lang/String;
     152: aastore
     153: invokevirtual #21                 // Method org/apache/dubbo/qos/textui/TTable.addRow:([Ljava/lang/Object;)Lorg/apache/dubbo/qos/textui/TTable;
     156: pop
     157: goto          110
     160: aload_1
     161: aload_3
     162: invokevirtual #31                 // Method org/apache/dubbo/qos/textui/TTable.rendering:()Ljava/lang/String;
     165: invokevirtual #6                  // Method java/lang/StringBuilder.append:(Ljava/lang/String;)Ljava/lang/StringBuilder;
     168: pop
     169: aload_1
     170: invokevirtual #8                  // Method java/lang/StringBuilder.toString:()Ljava/lang/String;
     173: areturn
}
