Compiled from "OfflineInterface.java"
public class org.apache.dubbo.qos.command.impl.OfflineInterface extends org.apache.dubbo.qos.command.impl.BaseOffline {
  public org.apache.dubbo.qos.command.impl.OfflineInterface(org.apache.dubbo.rpc.model.FrameworkModel);
    Code:
       0: aload_0
       1: aload_1
       2: invokespecial #1                  // Method org/apache/dubbo/qos/command/impl/BaseOffline."<init>":(Lorg/apache/dubbo/rpc/model/FrameworkModel;)V
       5: return

  protected void doUnexport(org.apache.dubbo.rpc.model.ProviderModel$RegisterStatedURL);
    Code:
       0: aload_1
       1: invokevirtual #2                  // Method org/apache/dubbo/rpc/model/ProviderModel$RegisterStatedURL.getRegistryUrl:()Lorg/apache/dubbo/common/URL;
       4: invokestatic  #3                  // Method org/apache/dubbo/common/utils/UrlUtils.isServiceDiscoveryURL:(Lorg/apache/dubbo/common/URL;)Z
       7: ifne          15
      10: aload_0
      11: aload_1
      12: invokespecial #4                  // Method org/apache/dubbo/qos/command/impl/BaseOffline.doUnexport:(Lorg/apache/dubbo/rpc/model/ProviderModel$RegisterStatedURL;)V
      15: return
}
