Compiled from "PublishMetadata.java"
public class org.apache.dubbo.qos.command.impl.PublishMetadata implements org.apache.dubbo.qos.api.BaseCommand {
  private static final org.apache.dubbo.common.logger.ErrorTypeAwareLogger logger;

  private final org.apache.dubbo.rpc.model.FrameworkModel frameworkModel;

  public org.apache.dubbo.qos.command.impl.PublishMetadata(org.apache.dubbo.rpc.model.FrameworkModel);
    Code:
       0: aload_0
       1: invokespecial #2                  // Method java/lang/Object."<init>":()V
       4: aload_0
       5: aload_1
       6: putfield      #3                  // Field frameworkModel:Lorg/apache/dubbo/rpc/model/FrameworkModel;
       9: return

  public java.lang.String execute(org.apache.dubbo.qos.api.CommandContext, java.lang.String[]);
    Code:
       0: getstatic     #4                  // Field logger:Lorg/apache/dubbo/common/logger/ErrorTypeAwareLogger;
       3: ldc           #5                  // String received publishMetadata command.
       5: invokeinterface #6,  2            // InterfaceMethod org/apache/dubbo/common/logger/ErrorTypeAwareLogger.info:(Ljava/lang/String;)V
      10: new           #7                  // class java/lang/StringBuilder
      13: dup
      14: invokespecial #8                  // Method java/lang/StringBuilder."<init>":()V
      17: astore_3
      18: aload_0
      19: getfield      #3                  // Field frameworkModel:Lorg/apache/dubbo/rpc/model/FrameworkModel;
      22: invokevirtual #9                  // Method org/apache/dubbo/rpc/model/FrameworkModel.getApplicationModels:()Ljava/util/List;
      25: astore        4
      27: aload         4
      29: invokeinterface #10,  1           // InterfaceMethod java/util/List.iterator:()Ljava/util/Iterator;
      34: astore        5
      36: aload         5
      38: invokeinterface #11,  1           // InterfaceMethod java/util/Iterator.hasNext:()Z
      43: ifeq          203
      46: aload         5
      48: invokeinterface #12,  1           // InterfaceMethod java/util/Iterator.next:()Ljava/lang/Object;
      53: checkcast     #13                 // class org/apache/dubbo/rpc/model/ApplicationModel
      56: astore        6
      58: aload_2
      59: invokestatic  #14                 // Method org/apache/dubbo/common/utils/ArrayUtils.isEmpty:([Ljava/lang/Object;)Z
      62: ifeq          93
      65: aload         6
      67: invokestatic  #15                 // Method org/apache/dubbo/registry/client/metadata/ServiceInstanceMetadataUtils.refreshMetadataAndInstance:(Lorg/apache/dubbo/rpc/model/ApplicationModel;)V
      70: aload_3
      71: ldc           #16                 // String publish metadata succeeded. App:
      73: invokevirtual #17                 // Method java/lang/StringBuilder.append:(Ljava/lang/String;)Ljava/lang/StringBuilder;
      76: aload         6
      78: invokevirtual #18                 // Method org/apache/dubbo/rpc/model/ApplicationModel.getApplicationName:()Ljava/lang/String;
      81: invokevirtual #17                 // Method java/lang/StringBuilder.append:(Ljava/lang/String;)Ljava/lang/StringBuilder;
      84: ldc           #19                 // String \n
      86: invokevirtual #17                 // Method java/lang/StringBuilder.append:(Ljava/lang/String;)Ljava/lang/StringBuilder;
      89: pop
      90: goto          200
      93: aload_2
      94: iconst_0
      95: aaload
      96: invokestatic  #20                 // Method java/lang/Integer.parseInt:(Ljava/lang/String;)I
      99: istore        7
     101: aload         6
     103: invokevirtual #21                 // Method org/apache/dubbo/rpc/model/ApplicationModel.getFrameworkModel:()Lorg/apache/dubbo/rpc/model/FrameworkModel;
     106: invokevirtual #22                 // Method org/apache/dubbo/rpc/model/FrameworkModel.getBeanFactory:()Lorg/apache/dubbo/common/beans/factory/ScopeBeanFactory;
     109: ldc           #23                 // class org/apache/dubbo/common/threadpool/manager/FrameworkExecutorRepository
     111: invokevirtual #24                 // Method org/apache/dubbo/common/beans/factory/ScopeBeanFactory.getBean:(Ljava/lang/Class;)Ljava/lang/Object;
     114: checkcast     #23                 // class org/apache/dubbo/common/threadpool/manager/FrameworkExecutorRepository
     117: astore        8
     119: aload         8
     121: invokevirtual #25                 // Method org/apache/dubbo/common/threadpool/manager/FrameworkExecutorRepository.nextScheduledExecutor:()Ljava/util/concurrent/ScheduledExecutorService;
     124: aload         6
     126: invokedynamic #26,  0             // InvokeDynamic #0:run:(Lorg/apache/dubbo/rpc/model/ApplicationModel;)Ljava/lang/Runnable;
     131: iload         7
     133: i2l
     134: getstatic     #27                 // Field java/util/concurrent/TimeUnit.SECONDS:Ljava/util/concurrent/TimeUnit;
     137: invokeinterface #28,  5           // InterfaceMethod java/util/concurrent/ScheduledExecutorService.schedule:(Ljava/lang/Runnable;JLjava/util/concurrent/TimeUnit;)Ljava/util/concurrent/ScheduledFuture;
     142: pop
     143: goto          169
     146: astore        7
     148: getstatic     #4                  // Field logger:Lorg/apache/dubbo/common/logger/ErrorTypeAwareLogger;
     151: ldc           #30                 // String 5-17
     153: ldc           #31                 // String
     155: ldc           #31                 // String
     157: ldc           #32                 // String Wrong delay param
     159: aload         7
     161: invokeinterface #33,  6           // InterfaceMethod org/apache/dubbo/common/logger/ErrorTypeAwareLogger.error:(Ljava/lang/String;Ljava/lang/String;Ljava/lang/String;Ljava/lang/String;Ljava/lang/Throwable;)V
     166: ldc           #34                 // String publishMetadata failed! Wrong delay param!
     168: areturn
     169: aload_3
     170: ldc           #35                 // String publish task submitted, will publish in
     172: invokevirtual #17                 // Method java/lang/StringBuilder.append:(Ljava/lang/String;)Ljava/lang/StringBuilder;
     175: aload_2
     176: iconst_0
     177: aaload
     178: invokevirtual #17                 // Method java/lang/StringBuilder.append:(Ljava/lang/String;)Ljava/lang/StringBuilder;
     181: ldc           #36                 // String  seconds. App:
     183: invokevirtual #17                 // Method java/lang/StringBuilder.append:(Ljava/lang/String;)Ljava/lang/StringBuilder;
     186: aload         6
     188: invokevirtual #18                 // Method org/apache/dubbo/rpc/model/ApplicationModel.getApplicationName:()Ljava/lang/String;
     191: invokevirtual #17                 // Method java/lang/StringBuilder.append:(Ljava/lang/String;)Ljava/lang/StringBuilder;
     194: ldc           #19                 // String \n
     196: invokevirtual #17                 // Method java/lang/StringBuilder.append:(Ljava/lang/String;)Ljava/lang/StringBuilder;
     199: pop
     200: goto          36
     203: aload_3
     204: invokevirtual #37                 // Method java/lang/StringBuilder.toString:()Ljava/lang/String;
     207: areturn
    Exception table:
       from    to  target type
          93   143   146   Class java/lang/NumberFormatException

  private static void lambda$execute$0(org.apache.dubbo.rpc.model.ApplicationModel);
    Code:
       0: aload_0
       1: invokestatic  #15                 // Method org/apache/dubbo/registry/client/metadata/ServiceInstanceMetadataUtils.refreshMetadataAndInstance:(Lorg/apache/dubbo/rpc/model/ApplicationModel;)V
       4: return

  static {};
    Code:
       0: ldc           #38                 // class org/apache/dubbo/qos/command/impl/PublishMetadata
       2: invokestatic  #39                 // Method org/apache/dubbo/common/logger/LoggerFactory.getErrorTypeAwareLogger:(Ljava/lang/Class;)Lorg/apache/dubbo/common/logger/ErrorTypeAwareLogger;
       5: putstatic     #4                  // Field logger:Lorg/apache/dubbo/common/logger/ErrorTypeAwareLogger;
       8: return
}
