Compiled from "PwdTelnet.java"
public class org.apache.dubbo.qos.command.impl.PwdTelnet implements org.apache.dubbo.qos.api.BaseCommand {
  public org.apache.dubbo.qos.command.impl.PwdTelnet();
    Code:
       0: aload_0
       1: invokespecial #1                  // Method java/lang/Object."<init>":()V
       4: return

  public java.lang.String execute(org.apache.dubbo.qos.api.CommandContext, java.lang.String[]);
    Code:
       0: aload_2
       1: arraylength
       2: ifle          33
       5: new           #2                  // class java/lang/StringBuilder
       8: dup
       9: invokespecial #3                  // Method java/lang/StringBuilder."<init>":()V
      12: ldc           #4                  // String Unsupported parameter
      14: invokevirtual #5                  // Method java/lang/StringBuilder.append:(Ljava/lang/String;)Ljava/lang/StringBuilder;
      17: aload_2
      18: invokestatic  #6                  // Method java/util/Arrays.toString:([Ljava/lang/Object;)Ljava/lang/String;
      21: invokevirtual #5                  // Method java/lang/StringBuilder.append:(Ljava/lang/String;)Ljava/lang/StringBuilder;
      24: ldc           #7                  // String  for pwd.
      26: invokevirtual #5                  // Method java/lang/StringBuilder.append:(Ljava/lang/String;)Ljava/lang/StringBuilder;
      29: invokevirtual #8                  // Method java/lang/StringBuilder.toString:()Ljava/lang/String;
      32: areturn
      33: aload_1
      34: invokevirtual #9                  // Method org/apache/dubbo/qos/api/CommandContext.getRemote:()Lio/netty/channel/Channel;
      37: getstatic     #10                 // Field org/apache/dubbo/qos/command/impl/ChangeTelnet.SERVICE_KEY:Lio/netty/util/AttributeKey;
      40: invokeinterface #11,  2           // InterfaceMethod io/netty/channel/Channel.attr:(Lio/netty/util/AttributeKey;)Lio/netty/util/Attribute;
      45: invokeinterface #12,  1           // InterfaceMethod io/netty/util/Attribute.get:()Ljava/lang/Object;
      50: checkcast     #13                 // class java/lang/String
      53: astore_3
      54: new           #2                  // class java/lang/StringBuilder
      57: dup
      58: invokespecial #3                  // Method java/lang/StringBuilder."<init>":()V
      61: astore        4
      63: aload_3
      64: invokestatic  #14                 // Method org/apache/dubbo/common/utils/StringUtils.isEmpty:(Ljava/lang/String;)Z
      67: ifeq          81
      70: aload         4
      72: bipush        47
      74: invokevirtual #15                 // Method java/lang/StringBuilder.append:(C)Ljava/lang/StringBuilder;
      77: pop
      78: goto          88
      81: aload         4
      83: aload_3
      84: invokevirtual #5                  // Method java/lang/StringBuilder.append:(Ljava/lang/String;)Ljava/lang/StringBuilder;
      87: pop
      88: aload         4
      90: invokevirtual #8                  // Method java/lang/StringBuilder.toString:()Ljava/lang/String;
      93: areturn
}
