Compiled from "SelectTelnet.java"
public class org.apache.dubbo.qos.command.impl.SelectTelnet implements org.apache.dubbo.qos.api.BaseCommand {
  public static final io.netty.util.AttributeKey<java.lang.Boolean> SELECT_KEY;

  public static final io.netty.util.AttributeKey<java.lang.reflect.Method> SELECT_METHOD_KEY;

  private final org.apache.dubbo.qos.command.impl.InvokeTelnet invokeTelnet;

  public org.apache.dubbo.qos.command.impl.SelectTelnet(org.apache.dubbo.rpc.model.FrameworkModel);
    Code:
       0: aload_0
       1: invokespecial #1                  // Method java/lang/Object."<init>":()V
       4: aload_0
       5: new           #2                  // class org/apache/dubbo/qos/command/impl/InvokeTelnet
       8: dup
       9: aload_1
      10: invokespecial #3                  // Method org/apache/dubbo/qos/command/impl/InvokeTelnet."<init>":(Lorg/apache/dubbo/rpc/model/FrameworkModel;)V
      13: putfield      #4                  // Field invokeTelnet:Lorg/apache/dubbo/qos/command/impl/InvokeTelnet;
      16: return

  public java.lang.String execute(org.apache.dubbo.qos.api.CommandContext, java.lang.String[]);
    Code:
       0: aload_2
       1: invokestatic  #5                  // Method org/apache/dubbo/common/utils/ArrayUtils.isEmpty:([Ljava/lang/Object;)Z
       4: ifeq          10
       7: ldc           #6                  // String Please input the index of the method you want to invoke, eg: \r\n select 1
       9: areturn
      10: aload_1
      11: invokevirtual #7                  // Method org/apache/dubbo/qos/api/CommandContext.getRemote:()Lio/netty/channel/Channel;
      14: astore_3
      15: aload_2
      16: iconst_0
      17: aaload
      18: astore        4
      20: aload_3
      21: getstatic     #8                  // Field org/apache/dubbo/qos/command/impl/InvokeTelnet.INVOKE_METHOD_LIST_KEY:Lio/netty/util/AttributeKey;
      24: invokeinterface #9,  2            // InterfaceMethod io/netty/channel/Channel.attr:(Lio/netty/util/AttributeKey;)Lio/netty/util/Attribute;
      29: invokeinterface #10,  1           // InterfaceMethod io/netty/util/Attribute.get:()Ljava/lang/Object;
      34: checkcast     #11                 // class java/util/List
      37: astore        5
      39: aload         5
      41: invokestatic  #12                 // Method org/apache/dubbo/common/utils/CollectionUtils.isEmpty:(Ljava/util/Collection;)Z
      44: ifeq          50
      47: ldc           #13                 // String Please use the invoke command first.
      49: areturn
      50: aload         4
      52: invokestatic  #14                 // Method org/apache/dubbo/common/utils/StringUtils.isNumber:(Ljava/lang/String;)Z
      55: ifeq          82
      58: aload         4
      60: invokestatic  #15                 // Method java/lang/Integer.parseInt:(Ljava/lang/String;)I
      63: iconst_1
      64: if_icmplt     82
      67: aload         4
      69: invokestatic  #15                 // Method java/lang/Integer.parseInt:(Ljava/lang/String;)I
      72: aload         5
      74: invokeinterface #16,  1           // InterfaceMethod java/util/List.size:()I
      79: if_icmple     108
      82: new           #17                 // class java/lang/StringBuilder
      85: dup
      86: invokespecial #18                 // Method java/lang/StringBuilder."<init>":()V
      89: ldc           #19                 // String Illegal index ,please input select 1~
      91: invokevirtual #20                 // Method java/lang/StringBuilder.append:(Ljava/lang/String;)Ljava/lang/StringBuilder;
      94: aload         5
      96: invokeinterface #16,  1           // InterfaceMethod java/util/List.size:()I
     101: invokevirtual #21                 // Method java/lang/StringBuilder.append:(I)Ljava/lang/StringBuilder;
     104: invokevirtual #22                 // Method java/lang/StringBuilder.toString:()Ljava/lang/String;
     107: areturn
     108: aload         5
     110: aload         4
     112: invokestatic  #15                 // Method java/lang/Integer.parseInt:(Ljava/lang/String;)I
     115: iconst_1
     116: isub
     117: invokeinterface #23,  2           // InterfaceMethod java/util/List.get:(I)Ljava/lang/Object;
     122: checkcast     #24                 // class java/lang/reflect/Method
     125: astore        6
     127: aload_3
     128: getstatic     #25                 // Field SELECT_METHOD_KEY:Lio/netty/util/AttributeKey;
     131: invokeinterface #9,  2            // InterfaceMethod io/netty/channel/Channel.attr:(Lio/netty/util/AttributeKey;)Lio/netty/util/Attribute;
     136: aload         6
     138: invokeinterface #26,  2           // InterfaceMethod io/netty/util/Attribute.set:(Ljava/lang/Object;)V
     143: aload_3
     144: getstatic     #27                 // Field SELECT_KEY:Lio/netty/util/AttributeKey;
     147: invokeinterface #9,  2            // InterfaceMethod io/netty/channel/Channel.attr:(Lio/netty/util/AttributeKey;)Lio/netty/util/Attribute;
     152: getstatic     #28                 // Field java/lang/Boolean.TRUE:Ljava/lang/Boolean;
     155: invokeinterface #26,  2           // InterfaceMethod io/netty/util/Attribute.set:(Ljava/lang/Object;)V
     160: aload_3
     161: getstatic     #29                 // Field org/apache/dubbo/qos/command/impl/InvokeTelnet.INVOKE_MESSAGE_KEY:Lio/netty/util/AttributeKey;
     164: invokeinterface #9,  2            // InterfaceMethod io/netty/channel/Channel.attr:(Lio/netty/util/AttributeKey;)Lio/netty/util/Attribute;
     169: invokeinterface #10,  1           // InterfaceMethod io/netty/util/Attribute.get:()Ljava/lang/Object;
     174: checkcast     #30                 // class java/lang/String
     177: astore        7
     179: aload_0
     180: getfield      #4                  // Field invokeTelnet:Lorg/apache/dubbo/qos/command/impl/InvokeTelnet;
     183: aload_1
     184: iconst_1
     185: anewarray     #30                 // class java/lang/String
     188: dup
     189: iconst_0
     190: aload         7
     192: aastore
     193: invokevirtual #31                 // Method org/apache/dubbo/qos/command/impl/InvokeTelnet.execute:(Lorg/apache/dubbo/qos/api/CommandContext;[Ljava/lang/String;)Ljava/lang/String;
     196: areturn

  static {};
    Code:
       0: ldc           #32                 // String telnet.select
       2: invokestatic  #33                 // Method io/netty/util/AttributeKey.valueOf:(Ljava/lang/String;)Lio/netty/util/AttributeKey;
       5: putstatic     #27                 // Field SELECT_KEY:Lio/netty/util/AttributeKey;
       8: ldc           #34                 // String telnet.select.method
      10: invokestatic  #33                 // Method io/netty/util/AttributeKey.valueOf:(Ljava/lang/String;)Lio/netty/util/AttributeKey;
      13: putstatic     #25                 // Field SELECT_METHOD_KEY:Lio/netty/util/AttributeKey;
      16: return
}
