Compiled from "SerializeCheckStatus.java"
public class org.apache.dubbo.qos.command.impl.SerializeCheckStatus implements org.apache.dubbo.qos.api.BaseCommand {
  private final org.apache.dubbo.qos.command.util.SerializeCheckUtils serializeCheckUtils;

  public org.apache.dubbo.qos.command.impl.SerializeCheckStatus(org.apache.dubbo.rpc.model.FrameworkModel);
    Code:
       0: aload_0
       1: invokespecial #1                  // Method java/lang/Object."<init>":()V
       4: aload_0
       5: aload_1
       6: invokevirtual #2                  // Method org/apache/dubbo/rpc/model/FrameworkModel.getBeanFactory:()Lorg/apache/dubbo/common/beans/factory/ScopeBeanFactory;
       9: ldc           #3                  // class org/apache/dubbo/qos/command/util/SerializeCheckUtils
      11: invokevirtual #4                  // Method org/apache/dubbo/common/beans/factory/ScopeBeanFactory.getBean:(Ljava/lang/Class;)Ljava/lang/Object;
      14: checkcast     #3                  // class org/apache/dubbo/qos/command/util/SerializeCheckUtils
      17: putfield      #5                  // Field serializeCheckUtils:Lorg/apache/dubbo/qos/command/util/SerializeCheckUtils;
      20: return

  public java.lang.String execute(org.apache.dubbo.qos.api.CommandContext, java.lang.String[]);
    Code:
       0: aload_1
       1: invokevirtual #6                  // Method org/apache/dubbo/qos/api/CommandContext.isHttp:()Z
       4: ifeq          87
       7: new           #7                  // class java/util/HashMap
      10: dup
      11: invokespecial #8                  // Method java/util/HashMap."<init>":()V
      14: astore_3
      15: aload_3
      16: ldc           #9                  // String checkStatus
      18: aload_0
      19: getfield      #5                  // Field serializeCheckUtils:Lorg/apache/dubbo/qos/command/util/SerializeCheckUtils;
      22: invokevirtual #10                 // Method org/apache/dubbo/qos/command/util/SerializeCheckUtils.getStatus:()Lorg/apache/dubbo/common/utils/SerializeCheckStatus;
      25: invokeinterface #11,  3           // InterfaceMethod java/util/Map.put:(Ljava/lang/Object;Ljava/lang/Object;)Ljava/lang/Object;
      30: pop
      31: aload_3
      32: ldc           #12                 // String checkSerializable
      34: aload_0
      35: getfield      #5                  // Field serializeCheckUtils:Lorg/apache/dubbo/qos/command/util/SerializeCheckUtils;
      38: invokevirtual #13                 // Method org/apache/dubbo/qos/command/util/SerializeCheckUtils.isCheckSerializable:()Z
      41: invokestatic  #14                 // Method java/lang/Boolean.valueOf:(Z)Ljava/lang/Boolean;
      44: invokeinterface #11,  3           // InterfaceMethod java/util/Map.put:(Ljava/lang/Object;Ljava/lang/Object;)Ljava/lang/Object;
      49: pop
      50: aload_3
      51: ldc           #15                 // String allowedPrefix
      53: aload_0
      54: getfield      #5                  // Field serializeCheckUtils:Lorg/apache/dubbo/qos/command/util/SerializeCheckUtils;
      57: invokevirtual #16                 // Method org/apache/dubbo/qos/command/util/SerializeCheckUtils.getAllowedList:()Ljava/util/Set;
      60: invokeinterface #11,  3           // InterfaceMethod java/util/Map.put:(Ljava/lang/Object;Ljava/lang/Object;)Ljava/lang/Object;
      65: pop
      66: aload_3
      67: ldc           #17                 // String disAllowedPrefix
      69: aload_0
      70: getfield      #5                  // Field serializeCheckUtils:Lorg/apache/dubbo/qos/command/util/SerializeCheckUtils;
      73: invokevirtual #18                 // Method org/apache/dubbo/qos/command/util/SerializeCheckUtils.getDisAllowedList:()Ljava/util/Set;
      76: invokeinterface #11,  3           // InterfaceMethod java/util/Map.put:(Ljava/lang/Object;Ljava/lang/Object;)Ljava/lang/Object;
      81: pop
      82: aload_3
      83: invokestatic  #19                 // Method org/apache/dubbo/common/utils/JsonUtils.toJson:(Ljava/lang/Object;)Ljava/lang/String;
      86: areturn
      87: new           #20                 // class java/lang/StringBuilder
      90: dup
      91: invokespecial #21                 // Method java/lang/StringBuilder."<init>":()V
      94: ldc           #22                 // String CheckStatus:
      96: invokevirtual #23                 // Method java/lang/StringBuilder.append:(Ljava/lang/String;)Ljava/lang/StringBuilder;
      99: aload_0
     100: getfield      #5                  // Field serializeCheckUtils:Lorg/apache/dubbo/qos/command/util/SerializeCheckUtils;
     103: invokevirtual #10                 // Method org/apache/dubbo/qos/command/util/SerializeCheckUtils.getStatus:()Lorg/apache/dubbo/common/utils/SerializeCheckStatus;
     106: invokevirtual #24                 // Method java/lang/StringBuilder.append:(Ljava/lang/Object;)Ljava/lang/StringBuilder;
     109: ldc           #25                 // String \n\nCheckSerializable:
     111: invokevirtual #23                 // Method java/lang/StringBuilder.append:(Ljava/lang/String;)Ljava/lang/StringBuilder;
     114: aload_0
     115: getfield      #5                  // Field serializeCheckUtils:Lorg/apache/dubbo/qos/command/util/SerializeCheckUtils;
     118: invokevirtual #13                 // Method org/apache/dubbo/qos/command/util/SerializeCheckUtils.isCheckSerializable:()Z
     121: invokevirtual #26                 // Method java/lang/StringBuilder.append:(Z)Ljava/lang/StringBuilder;
     124: ldc           #27                 // String \n\nAllowedPrefix:\n
     126: invokevirtual #23                 // Method java/lang/StringBuilder.append:(Ljava/lang/String;)Ljava/lang/StringBuilder;
     129: aload_0
     130: getfield      #5                  // Field serializeCheckUtils:Lorg/apache/dubbo/qos/command/util/SerializeCheckUtils;
     133: invokevirtual #16                 // Method org/apache/dubbo/qos/command/util/SerializeCheckUtils.getAllowedList:()Ljava/util/Set;
     136: invokeinterface #28,  1           // InterfaceMethod java/util/Set.stream:()Ljava/util/stream/Stream;
     141: invokeinterface #29,  1           // InterfaceMethod java/util/stream/Stream.sorted:()Ljava/util/stream/Stream;
     146: ldc           #30                 // String \n
     148: invokestatic  #31                 // Method java/util/stream/Collectors.joining:(Ljava/lang/CharSequence;)Ljava/util/stream/Collector;
     151: invokeinterface #32,  2           // InterfaceMethod java/util/stream/Stream.collect:(Ljava/util/stream/Collector;)Ljava/lang/Object;
     156: checkcast     #33                 // class java/lang/String
     159: invokevirtual #23                 // Method java/lang/StringBuilder.append:(Ljava/lang/String;)Ljava/lang/StringBuilder;
     162: ldc           #34                 // String \n\nDisAllowedPrefix:\n
     164: invokevirtual #23                 // Method java/lang/StringBuilder.append:(Ljava/lang/String;)Ljava/lang/StringBuilder;
     167: aload_0
     168: getfield      #5                  // Field serializeCheckUtils:Lorg/apache/dubbo/qos/command/util/SerializeCheckUtils;
     171: invokevirtual #18                 // Method org/apache/dubbo/qos/command/util/SerializeCheckUtils.getDisAllowedList:()Ljava/util/Set;
     174: invokeinterface #28,  1           // InterfaceMethod java/util/Set.stream:()Ljava/util/stream/Stream;
     179: invokeinterface #29,  1           // InterfaceMethod java/util/stream/Stream.sorted:()Ljava/util/stream/Stream;
     184: ldc           #30                 // String \n
     186: invokestatic  #31                 // Method java/util/stream/Collectors.joining:(Ljava/lang/CharSequence;)Ljava/util/stream/Collector;
     189: invokeinterface #32,  2           // InterfaceMethod java/util/stream/Stream.collect:(Ljava/util/stream/Collector;)Ljava/lang/Object;
     194: checkcast     #33                 // class java/lang/String
     197: invokevirtual #23                 // Method java/lang/StringBuilder.append:(Ljava/lang/String;)Ljava/lang/StringBuilder;
     200: ldc           #35                 // String \n\n
     202: invokevirtual #23                 // Method java/lang/StringBuilder.append:(Ljava/lang/String;)Ljava/lang/StringBuilder;
     205: invokevirtual #36                 // Method java/lang/StringBuilder.toString:()Ljava/lang/String;
     208: areturn
}
