Compiled from "SetProfilerWarnPercent.java"
public class org.apache.dubbo.qos.command.impl.SetProfilerWarnPercent implements org.apache.dubbo.qos.api.BaseCommand {
  private static final org.apache.dubbo.common.logger.ErrorTypeAwareLogger logger;

  public org.apache.dubbo.qos.command.impl.SetProfilerWarnPercent();
    Code:
       0: aload_0
       1: invokespecial #2                  // Method java/lang/Object."<init>":()V
       4: return

  public java.lang.String execute(org.apache.dubbo.qos.api.CommandContext, java.lang.String[]);
    Code:
       0: aload_2
       1: ifnull        10
       4: aload_2
       5: arraylength
       6: iconst_1
       7: if_icmpeq     13
      10: ldc           #3                  // String args error. example: setProfilerWarnPercent 0.75
      12: areturn
      13: aload_2
      14: iconst_0
      15: aaload
      16: invokestatic  #4                  // Method java/lang/Double.parseDouble:(Ljava/lang/String;)D
      19: invokestatic  #5                  // Method org/apache/dubbo/common/profiler/ProfilerSwitch.setWarnPercent:(D)V
      22: getstatic     #6                  // Field logger:Lorg/apache/dubbo/common/logger/ErrorTypeAwareLogger;
      25: ldc           #7                  // String 7-3
      27: ldc           #8                  // String
      29: ldc           #8                  // String
      31: new           #9                  // class java/lang/StringBuilder
      34: dup
      35: invokespecial #10                 // Method java/lang/StringBuilder."<init>":()V
      38: ldc           #11                 // String Dubbo Invocation Profiler warn percent has been set to
      40: invokevirtual #12                 // Method java/lang/StringBuilder.append:(Ljava/lang/String;)Ljava/lang/StringBuilder;
      43: aload_2
      44: iconst_0
      45: aaload
      46: invokevirtual #12                 // Method java/lang/StringBuilder.append:(Ljava/lang/String;)Ljava/lang/StringBuilder;
      49: invokevirtual #13                 // Method java/lang/StringBuilder.toString:()Ljava/lang/String;
      52: invokeinterface #14,  5           // InterfaceMethod org/apache/dubbo/common/logger/ErrorTypeAwareLogger.warn:(Ljava/lang/String;Ljava/lang/String;Ljava/lang/String;Ljava/lang/String;)V
      57: ldc           #15                 // String OK
      59: areturn

  static {};
    Code:
       0: ldc           #16                 // class org/apache/dubbo/qos/command/impl/SetProfilerWarnPercent
       2: invokestatic  #17                 // Method org/apache/dubbo/common/logger/LoggerFactory.getErrorTypeAwareLogger:(Ljava/lang/Class;)Lorg/apache/dubbo/common/logger/ErrorTypeAwareLogger;
       5: putstatic     #6                  // Field logger:Lorg/apache/dubbo/common/logger/ErrorTypeAwareLogger;
       8: return
}
