Compiled from "Startup.java"
public class org.apache.dubbo.qos.command.impl.Startup implements org.apache.dubbo.qos.api.BaseCommand {
  private final org.apache.dubbo.rpc.model.FrameworkModel frameworkModel;

  public org.apache.dubbo.qos.command.impl.Startup(org.apache.dubbo.rpc.model.FrameworkModel);
    Code:
       0: aload_0
       1: invokespecial #1                  // Method java/lang/Object."<init>":()V
       4: aload_0
       5: aload_1
       6: putfield      #2                  // Field frameworkModel:Lorg/apache/dubbo/rpc/model/FrameworkModel;
       9: return

  public java.lang.String execute(org.apache.dubbo.qos.api.CommandContext, java.lang.String[]);
    Code:
       0: aload_0
       1: getfield      #2                  // Field frameworkModel:Lorg/apache/dubbo/rpc/model/FrameworkModel;
       4: invokevirtual #3                  // Method org/apache/dubbo/rpc/model/FrameworkModel.getApplicationModels:()Ljava/util/List;
       7: invokeinterface #4,  1            // InterfaceMethod java/util/List.stream:()Ljava/util/stream/Stream;
      12: invokedynamic #5,  0              // InvokeDynamic #0:apply:()Ljava/util/function/Function;
      17: invokeinterface #6,  2            // InterfaceMethod java/util/stream/Stream.map:(Ljava/util/function/Function;)Ljava/util/stream/Stream;
      22: invokedynamic #7,  0              // InvokeDynamic #1:apply:()Ljava/util/function/Function;
      27: invokeinterface #6,  2            // InterfaceMethod java/util/stream/Stream.map:(Ljava/util/function/Function;)Ljava/util/stream/Stream;
      32: invokedynamic #8,  0              // InvokeDynamic #2:test:()Ljava/util/function/Predicate;
      37: invokeinterface #9,  2            // InterfaceMethod java/util/stream/Stream.filter:(Ljava/util/function/Predicate;)Ljava/util/stream/Stream;
      42: invokedynamic #10,  0             // InvokeDynamic #3:apply:()Ljava/util/function/Function;
      47: invokeinterface #6,  2            // InterfaceMethod java/util/stream/Stream.map:(Ljava/util/function/Function;)Ljava/util/stream/Stream;
      52: invokedynamic #11,  0             // InvokeDynamic #4:test:()Ljava/util/function/Predicate;
      57: invokeinterface #9,  2            // InterfaceMethod java/util/stream/Stream.filter:(Ljava/util/function/Predicate;)Ljava/util/stream/Stream;
      62: ldc           #12                 // String ,
      64: invokestatic  #13                 // Method java/util/stream/Collectors.joining:(Ljava/lang/CharSequence;)Ljava/util/stream/Collector;
      67: invokeinterface #14,  2           // InterfaceMethod java/util/stream/Stream.collect:(Ljava/util/stream/Collector;)Ljava/lang/Object;
      72: checkcast     #15                 // class java/lang/String
      75: astore_3
      76: ldc           #16                 // String application://
      78: invokestatic  #17                 // Method org/apache/dubbo/common/URL.valueOf:(Ljava/lang/String;)Lorg/apache/dubbo/common/URL;
      81: ldc           #19                 // String dubbo.application.startup-probe
      83: aload_3
      84: invokevirtual #20                 // Method org/apache/dubbo/common/URL.addParameter:(Ljava/lang/String;Ljava/lang/String;)Lorg/apache/dubbo/common/URL;
      87: astore        4
      89: aload_0
      90: getfield      #2                  // Field frameworkModel:Lorg/apache/dubbo/rpc/model/FrameworkModel;
      93: ldc           #21                 // class org/apache/dubbo/qos/probe/StartupProbe
      95: invokevirtual #22                 // Method org/apache/dubbo/rpc/model/FrameworkModel.getExtensionLoader:(Ljava/lang/Class;)Lorg/apache/dubbo/common/extension/ExtensionLoader;
      98: aload         4
     100: ldc           #19                 // String dubbo.application.startup-probe
     102: invokevirtual #23                 // Method org/apache/dubbo/common/extension/ExtensionLoader.getActivateExtension:(Lorg/apache/dubbo/common/URL;Ljava/lang/String;)Ljava/util/List;
     105: astore        5
     107: aload         5
     109: invokeinterface #24,  1           // InterfaceMethod java/util/List.isEmpty:()Z
     114: ifne          171
     117: aload         5
     119: invokeinterface #25,  1           // InterfaceMethod java/util/List.iterator:()Ljava/util/Iterator;
     124: astore        6
     126: aload         6
     128: invokeinterface #26,  1           // InterfaceMethod java/util/Iterator.hasNext:()Z
     133: ifeq          171
     136: aload         6
     138: invokeinterface #27,  1           // InterfaceMethod java/util/Iterator.next:()Ljava/lang/Object;
     143: checkcast     #21                 // class org/apache/dubbo/qos/probe/StartupProbe
     146: astore        7
     148: aload         7
     150: invokeinterface #28,  1           // InterfaceMethod org/apache/dubbo/qos/probe/StartupProbe.check:()Z
     155: ifne          168
     158: aload_1
     159: sipush        503
     162: invokevirtual #29                 // Method org/apache/dubbo/qos/api/CommandContext.setHttpCode:(I)V
     165: ldc           #30                 // String false
     167: areturn
     168: goto          126
     171: aload_1
     172: sipush        200
     175: invokevirtual #29                 // Method org/apache/dubbo/qos/api/CommandContext.setHttpCode:(I)V
     178: ldc           #31                 // String true
     180: areturn

  private static org.apache.dubbo.config.ApplicationConfig lambda$execute$1(java.util.Optional);
    Code:
       0: aload_0
       1: aconst_null
       2: invokevirtual #32                 // Method java/util/Optional.orElse:(Ljava/lang/Object;)Ljava/lang/Object;
       5: checkcast     #33                 // class org/apache/dubbo/config/ApplicationConfig
       8: areturn

  private static java.util.Optional lambda$execute$0(org.apache.dubbo.rpc.model.ApplicationModel);
    Code:
       0: aload_0
       1: invokevirtual #34                 // Method org/apache/dubbo/rpc/model/ApplicationModel.getApplicationConfigManager:()Lorg/apache/dubbo/config/context/ConfigManager;
       4: invokevirtual #35                 // Method org/apache/dubbo/config/context/ConfigManager.getApplication:()Ljava/util/Optional;
       7: areturn
}
