Compiled from "SwitchLogger.java"
public class org.apache.dubbo.qos.command.impl.SwitchLogger implements org.apache.dubbo.qos.api.BaseCommand {
  private final org.apache.dubbo.rpc.model.FrameworkModel frameworkModel;

  public org.apache.dubbo.qos.command.impl.SwitchLogger(org.apache.dubbo.rpc.model.FrameworkModel);
    Code:
       0: aload_0
       1: invokespecial #1                  // Method java/lang/Object."<init>":()V
       4: aload_0
       5: aload_1
       6: putfield      #2                  // Field frameworkModel:Lorg/apache/dubbo/rpc/model/FrameworkModel;
       9: return

  public java.lang.String execute(org.apache.dubbo.qos.api.CommandContext, java.lang.String[]);
    Code:
       0: aload_2
       1: arraylength
       2: iconst_1
       3: if_icmpeq     9
       6: ldc           #3                  // String Unexpected argument length.
       8: areturn
       9: invokestatic  #4                  // Method org/apache/dubbo/common/logger/LoggerFactory.getLevel:()Lorg/apache/dubbo/common/logger/Level;
      12: astore_3
      13: aload_0
      14: getfield      #2                  // Field frameworkModel:Lorg/apache/dubbo/rpc/model/FrameworkModel;
      17: aload_2
      18: iconst_0
      19: aaload
      20: invokestatic  #5                  // Method org/apache/dubbo/common/logger/LoggerFactory.setLoggerAdapter:(Lorg/apache/dubbo/rpc/model/FrameworkModel;Ljava/lang/String;)V
      23: aload_3
      24: invokestatic  #6                  // Method org/apache/dubbo/common/logger/LoggerFactory.setLevel:(Lorg/apache/dubbo/common/logger/Level;)V
      27: ldc           #7                  // String OK
      29: areturn
}
