Compiled from "Version.java"
public class org.apache.dubbo.qos.command.impl.Version implements org.apache.dubbo.qos.api.BaseCommand {
  public org.apache.dubbo.qos.command.impl.Version();
    Code:
       0: aload_0
       1: invokespecial #1                  // Method java/lang/Object."<init>":()V
       4: return

  public java.lang.String execute(org.apache.dubbo.qos.api.CommandContext, java.lang.String[]);
    Code:
       0: new           #2                  // class java/lang/StringBuilder
       3: dup
       4: invokespecial #3                  // Method java/lang/StringBuilder."<init>":()V
       7: astore_3
       8: aload_3
       9: ldc           #4                  // String dubbo version \"
      11: invokevirtual #5                  // Method java/lang/StringBuilder.append:(Ljava/lang/String;)Ljava/lang/StringBuilder;
      14: pop
      15: aload_3
      16: invokestatic  #6                  // Method org/apache/dubbo/common/Version.getVersion:()Ljava/lang/String;
      19: invokevirtual #5                  // Method java/lang/StringBuilder.append:(Ljava/lang/String;)Ljava/lang/StringBuilder;
      22: pop
      23: aload_3
      24: bipush        34
      26: invokevirtual #7                  // Method java/lang/StringBuilder.append:(C)Ljava/lang/StringBuilder;
      29: pop
      30: aload_3
      31: invokevirtual #8                  // Method java/lang/StringBuilder.toString:()Ljava/lang/String;
      34: areturn
}
