Compiled from "HashedWheelTimer.java"
final class org.apache.dubbo.common.timer.HashedWheelTimer$Worker implements java.lang.Runnable {
  private final java.util.Set<org.apache.dubbo.common.timer.Timeout> unprocessedTimeouts;

  private long tick;

  final org.apache.dubbo.common.timer.HashedWheelTimer this$0;

  private org.apache.dubbo.common.timer.HashedWheelTimer$Worker(org.apache.dubbo.common.timer.HashedWheelTimer);
    Code:
       0: aload_0
       1: aload_1
       2: putfield      #5                  // Field this$0:Lorg/apache/dubbo/common/timer/HashedWheelTimer;
       5: aload_0
       6: invokespecial #6                  // Method java/lang/Object."<init>":()V
       9: aload_0
      10: new           #7                  // class java/util/HashSet
      13: dup
      14: invokespecial #8                  // Method java/util/HashSet."<init>":()V
      17: putfield      #9                  // Field unprocessedTimeouts:Ljava/util/Set;
      20: return

  public void run();
    Code:
       0: aload_0
       1: getfield      #5                  // Field this$0:Lorg/apache/dubbo/common/timer/HashedWheelTimer;
       4: invokestatic  #10                 // Method java/lang/System.nanoTime:()J
       7: invokestatic  #11                 // Method org/apache/dubbo/common/timer/HashedWheelTimer.access$202:(Lorg/apache/dubbo/common/timer/HashedWheelTimer;J)J
      10: pop2
      11: aload_0
      12: getfield      #5                  // Field this$0:Lorg/apache/dubbo/common/timer/HashedWheelTimer;
      15: invokestatic  #12                 // Method org/apache/dubbo/common/timer/HashedWheelTimer.access$200:(Lorg/apache/dubbo/common/timer/HashedWheelTimer;)J
      18: lconst_0
      19: lcmp
      20: ifne          32
      23: aload_0
      24: getfield      #5                  // Field this$0:Lorg/apache/dubbo/common/timer/HashedWheelTimer;
      27: lconst_1
      28: invokestatic  #11                 // Method org/apache/dubbo/common/timer/HashedWheelTimer.access$202:(Lorg/apache/dubbo/common/timer/HashedWheelTimer;J)J
      31: pop2
      32: aload_0
      33: getfield      #5                  // Field this$0:Lorg/apache/dubbo/common/timer/HashedWheelTimer;
      36: invokestatic  #13                 // Method org/apache/dubbo/common/timer/HashedWheelTimer.access$300:(Lorg/apache/dubbo/common/timer/HashedWheelTimer;)Ljava/util/concurrent/CountDownLatch;
      39: invokevirtual #14                 // Method java/util/concurrent/CountDownLatch.countDown:()V
      42: aload_0
      43: invokespecial #15                 // Method waitForNextTick:()J
      46: lstore_1
      47: lload_1
      48: lconst_0
      49: lcmp
      50: ifle          103
      53: aload_0
      54: getfield      #16                 // Field tick:J
      57: aload_0
      58: getfield      #5                  // Field this$0:Lorg/apache/dubbo/common/timer/HashedWheelTimer;
      61: invokestatic  #17                 // Method org/apache/dubbo/common/timer/HashedWheelTimer.access$400:(Lorg/apache/dubbo/common/timer/HashedWheelTimer;)I
      64: i2l
      65: land
      66: l2i
      67: istore_3
      68: aload_0
      69: invokespecial #18                 // Method processCancelledTasks:()V
      72: aload_0
      73: getfield      #5                  // Field this$0:Lorg/apache/dubbo/common/timer/HashedWheelTimer;
      76: invokestatic  #19                 // Method org/apache/dubbo/common/timer/HashedWheelTimer.access$500:(Lorg/apache/dubbo/common/timer/HashedWheelTimer;)[Lorg/apache/dubbo/common/timer/HashedWheelTimer$HashedWheelBucket;
      79: iload_3
      80: aaload
      81: astore        4
      83: aload_0
      84: invokespecial #20                 // Method transferTimeoutsToBuckets:()V
      87: aload         4
      89: lload_1
      90: invokevirtual #21                 // Method org/apache/dubbo/common/timer/HashedWheelTimer$HashedWheelBucket.expireTimeouts:(J)V
      93: aload_0
      94: dup
      95: getfield      #16                 // Field tick:J
      98: lconst_1
      99: ladd
     100: putfield      #16                 // Field tick:J
     103: invokestatic  #22                 // Method org/apache/dubbo/common/timer/HashedWheelTimer.access$600:()Ljava/util/concurrent/atomic/AtomicIntegerFieldUpdater;
     106: aload_0
     107: getfield      #5                  // Field this$0:Lorg/apache/dubbo/common/timer/HashedWheelTimer;
     110: invokevirtual #23                 // Method java/util/concurrent/atomic/AtomicIntegerFieldUpdater.get:(Ljava/lang/Object;)I
     113: iconst_1
     114: if_icmpeq     42
     117: aload_0
     118: getfield      #5                  // Field this$0:Lorg/apache/dubbo/common/timer/HashedWheelTimer;
     121: invokestatic  #19                 // Method org/apache/dubbo/common/timer/HashedWheelTimer.access$500:(Lorg/apache/dubbo/common/timer/HashedWheelTimer;)[Lorg/apache/dubbo/common/timer/HashedWheelTimer$HashedWheelBucket;
     124: astore_1
     125: aload_1
     126: arraylength
     127: istore_2
     128: iconst_0
     129: istore_3
     130: iload_3
     131: iload_2
     132: if_icmpge     155
     135: aload_1
     136: iload_3
     137: aaload
     138: astore        4
     140: aload         4
     142: aload_0
     143: getfield      #9                  // Field unprocessedTimeouts:Ljava/util/Set;
     146: invokevirtual #24                 // Method org/apache/dubbo/common/timer/HashedWheelTimer$HashedWheelBucket.clearTimeouts:(Ljava/util/Set;)V
     149: iinc          3, 1
     152: goto          130
     155: aload_0
     156: getfield      #5                  // Field this$0:Lorg/apache/dubbo/common/timer/HashedWheelTimer;
     159: invokestatic  #25                 // Method org/apache/dubbo/common/timer/HashedWheelTimer.access$700:(Lorg/apache/dubbo/common/timer/HashedWheelTimer;)Ljava/util/Queue;
     162: invokeinterface #26,  1           // InterfaceMethod java/util/Queue.poll:()Ljava/lang/Object;
     167: checkcast     #3                  // class org/apache/dubbo/common/timer/HashedWheelTimer$HashedWheelTimeout
     170: astore_1
     171: aload_1
     172: ifnonnull     178
     175: goto          199
     178: aload_1
     179: invokevirtual #27                 // Method org/apache/dubbo/common/timer/HashedWheelTimer$HashedWheelTimeout.isCancelled:()Z
     182: ifne          196
     185: aload_0
     186: getfield      #9                  // Field unprocessedTimeouts:Ljava/util/Set;
     189: aload_1
     190: invokeinterface #28,  2           // InterfaceMethod java/util/Set.add:(Ljava/lang/Object;)Z
     195: pop
     196: goto          155
     199: aload_0
     200: invokespecial #18                 // Method processCancelledTasks:()V
     203: return

  private void transferTimeoutsToBuckets();
    Code:
       0: iconst_0
       1: istore_1
       2: iload_1
       3: ldc           #29                 // int 100000
       5: if_icmpge     123
       8: aload_0
       9: getfield      #5                  // Field this$0:Lorg/apache/dubbo/common/timer/HashedWheelTimer;
      12: invokestatic  #25                 // Method org/apache/dubbo/common/timer/HashedWheelTimer.access$700:(Lorg/apache/dubbo/common/timer/HashedWheelTimer;)Ljava/util/Queue;
      15: invokeinterface #26,  1           // InterfaceMethod java/util/Queue.poll:()Ljava/lang/Object;
      20: checkcast     #3                  // class org/apache/dubbo/common/timer/HashedWheelTimer$HashedWheelTimeout
      23: astore_2
      24: aload_2
      25: ifnonnull     31
      28: goto          123
      31: aload_2
      32: invokevirtual #30                 // Method org/apache/dubbo/common/timer/HashedWheelTimer$HashedWheelTimeout.state:()I
      35: iconst_1
      36: if_icmpne     42
      39: goto          117
      42: aload_2
      43: invokestatic  #31                 // Method org/apache/dubbo/common/timer/HashedWheelTimer$HashedWheelTimeout.access$800:(Lorg/apache/dubbo/common/timer/HashedWheelTimer$HashedWheelTimeout;)J
      46: aload_0
      47: getfield      #5                  // Field this$0:Lorg/apache/dubbo/common/timer/HashedWheelTimer;
      50: invokestatic  #32                 // Method org/apache/dubbo/common/timer/HashedWheelTimer.access$900:(Lorg/apache/dubbo/common/timer/HashedWheelTimer;)J
      53: ldiv
      54: lstore_3
      55: aload_2
      56: lload_3
      57: aload_0
      58: getfield      #16                 // Field tick:J
      61: lsub
      62: aload_0
      63: getfield      #5                  // Field this$0:Lorg/apache/dubbo/common/timer/HashedWheelTimer;
      66: invokestatic  #19                 // Method org/apache/dubbo/common/timer/HashedWheelTimer.access$500:(Lorg/apache/dubbo/common/timer/HashedWheelTimer;)[Lorg/apache/dubbo/common/timer/HashedWheelTimer$HashedWheelBucket;
      69: arraylength
      70: i2l
      71: ldiv
      72: putfield      #33                 // Field org/apache/dubbo/common/timer/HashedWheelTimer$HashedWheelTimeout.remainingRounds:J
      75: lload_3
      76: aload_0
      77: getfield      #16                 // Field tick:J
      80: invokestatic  #34                 // Method java/lang/Math.max:(JJ)J
      83: lstore        5
      85: lload         5
      87: aload_0
      88: getfield      #5                  // Field this$0:Lorg/apache/dubbo/common/timer/HashedWheelTimer;
      91: invokestatic  #17                 // Method org/apache/dubbo/common/timer/HashedWheelTimer.access$400:(Lorg/apache/dubbo/common/timer/HashedWheelTimer;)I
      94: i2l
      95: land
      96: l2i
      97: istore        7
      99: aload_0
     100: getfield      #5                  // Field this$0:Lorg/apache/dubbo/common/timer/HashedWheelTimer;
     103: invokestatic  #19                 // Method org/apache/dubbo/common/timer/HashedWheelTimer.access$500:(Lorg/apache/dubbo/common/timer/HashedWheelTimer;)[Lorg/apache/dubbo/common/timer/HashedWheelTimer$HashedWheelBucket;
     106: iload         7
     108: aaload
     109: astore        8
     111: aload         8
     113: aload_2
     114: invokevirtual #35                 // Method org/apache/dubbo/common/timer/HashedWheelTimer$HashedWheelBucket.addTimeout:(Lorg/apache/dubbo/common/timer/HashedWheelTimer$HashedWheelTimeout;)V
     117: iinc          1, 1
     120: goto          2
     123: return

  private void processCancelledTasks();
    Code:
       0: aload_0
       1: getfield      #5                  // Field this$0:Lorg/apache/dubbo/common/timer/HashedWheelTimer;
       4: invokestatic  #36                 // Method org/apache/dubbo/common/timer/HashedWheelTimer.access$1000:(Lorg/apache/dubbo/common/timer/HashedWheelTimer;)Ljava/util/Queue;
       7: invokeinterface #26,  1           // InterfaceMethod java/util/Queue.poll:()Ljava/lang/Object;
      12: checkcast     #3                  // class org/apache/dubbo/common/timer/HashedWheelTimer$HashedWheelTimeout
      15: astore_1
      16: aload_1
      17: ifnonnull     23
      20: goto          62
      23: aload_1
      24: invokevirtual #37                 // Method org/apache/dubbo/common/timer/HashedWheelTimer$HashedWheelTimeout.remove:()V
      27: goto          59
      30: astore_2
      31: invokestatic  #39                 // Method org/apache/dubbo/common/timer/HashedWheelTimer.access$1100:()Lorg/apache/dubbo/common/logger/ErrorTypeAwareLogger;
      34: invokeinterface #40,  1           // InterfaceMethod org/apache/dubbo/common/logger/ErrorTypeAwareLogger.isWarnEnabled:()Z
      39: ifeq          59
      42: invokestatic  #39                 // Method org/apache/dubbo/common/timer/HashedWheelTimer.access$1100:()Lorg/apache/dubbo/common/logger/ErrorTypeAwareLogger;
      45: ldc           #41                 // String 0-19
      47: ldc           #42                 // String
      49: ldc           #42                 // String
      51: ldc           #43                 // String An exception was thrown while process a cancellation task
      53: aload_2
      54: invokeinterface #44,  6           // InterfaceMethod org/apache/dubbo/common/logger/ErrorTypeAwareLogger.warn:(Ljava/lang/String;Ljava/lang/String;Ljava/lang/String;Ljava/lang/String;Ljava/lang/Throwable;)V
      59: goto          0
      62: return
    Exception table:
       from    to  target type
          23    27    30   Class java/lang/Throwable

  private long waitForNextTick();
    Code:
       0: aload_0
       1: getfield      #5                  // Field this$0:Lorg/apache/dubbo/common/timer/HashedWheelTimer;
       4: invokestatic  #32                 // Method org/apache/dubbo/common/timer/HashedWheelTimer.access$900:(Lorg/apache/dubbo/common/timer/HashedWheelTimer;)J
       7: aload_0
       8: getfield      #16                 // Field tick:J
      11: lconst_1
      12: ladd
      13: lmul
      14: lstore_1
      15: invokestatic  #10                 // Method java/lang/System.nanoTime:()J
      18: aload_0
      19: getfield      #5                  // Field this$0:Lorg/apache/dubbo/common/timer/HashedWheelTimer;
      22: invokestatic  #12                 // Method org/apache/dubbo/common/timer/HashedWheelTimer.access$200:(Lorg/apache/dubbo/common/timer/HashedWheelTimer;)J
      25: lsub
      26: lstore_3
      27: lload_1
      28: lload_3
      29: lsub
      30: ldc2_w        #45                 // long 999999l
      33: ladd
      34: ldc2_w        #47                 // long 1000000l
      37: ldiv
      38: lstore        5
      40: lload         5
      42: lconst_0
      43: lcmp
      44: ifgt          61
      47: lload_3
      48: ldc2_w        #50                 // long -9223372036854775808l
      51: lcmp
      52: ifne          59
      55: ldc2_w        #52                 // long -9223372036854775807l
      58: lreturn
      59: lload_3
      60: lreturn
      61: aload_0
      62: getfield      #5                  // Field this$0:Lorg/apache/dubbo/common/timer/HashedWheelTimer;
      65: invokestatic  #54                 // Method org/apache/dubbo/common/timer/HashedWheelTimer.access$1200:(Lorg/apache/dubbo/common/timer/HashedWheelTimer;)Z
      68: ifeq          83
      71: lload         5
      73: ldc2_w        #55                 // long 10l
      76: ldiv
      77: ldc2_w        #55                 // long 10l
      80: lmul
      81: lstore        5
      83: lload         5
      85: invokestatic  #57                 // Method java/lang/Thread.sleep:(J)V
      88: goto          111
      91: astore        7
      93: invokestatic  #22                 // Method org/apache/dubbo/common/timer/HashedWheelTimer.access$600:()Ljava/util/concurrent/atomic/AtomicIntegerFieldUpdater;
      96: aload_0
      97: getfield      #5                  // Field this$0:Lorg/apache/dubbo/common/timer/HashedWheelTimer;
     100: invokevirtual #23                 // Method java/util/concurrent/atomic/AtomicIntegerFieldUpdater.get:(Ljava/lang/Object;)I
     103: iconst_2
     104: if_icmpne     111
     107: ldc2_w        #50                 // long -9223372036854775808l
     110: lreturn
     111: goto          15
    Exception table:
       from    to  target type
          83    88    91   Class java/lang/InterruptedException

  java.util.Set<org.apache.dubbo.common.timer.Timeout> unprocessedTimeouts();
    Code:
       0: aload_0
       1: getfield      #9                  // Field unprocessedTimeouts:Ljava/util/Set;
       4: invokestatic  #59                 // Method java/util/Collections.unmodifiableSet:(Ljava/util/Set;)Ljava/util/Set;
       7: areturn

  org.apache.dubbo.common.timer.HashedWheelTimer$Worker(org.apache.dubbo.common.timer.HashedWheelTimer, org.apache.dubbo.common.timer.HashedWheelTimer$1);
    Code:
       0: aload_0
       1: aload_1
       2: invokespecial #4                  // Method "<init>":(Lorg/apache/dubbo/common/timer/HashedWheelTimer;)V
       5: return
}
