Compiled from "SpiExtensionInjector.java"
public class org.apache.dubbo.common.extension.inject.SpiExtensionInjector implements org.apache.dubbo.common.extension.ExtensionInjector {
  private org.apache.dubbo.common.extension.ExtensionAccessor extensionAccessor;

  public org.apache.dubbo.common.extension.inject.SpiExtensionInjector();
    Code:
       0: aload_0
       1: invokespecial #1                  // Method java/lang/Object."<init>":()V
       4: return

  public void setExtensionAccessor(org.apache.dubbo.common.extension.ExtensionAccessor);
    Code:
       0: aload_0
       1: aload_1
       2: putfield      #2                  // Field extensionAccessor:Lorg/apache/dubbo/common/extension/ExtensionAccessor;
       5: return

  public <T> T getInstance(java.lang.Class<T>, java.lang.String);
    Code:
       0: aload_1
       1: invokevirtual #3                  // Method java/lang/Class.isInterface:()Z
       4: ifeq          16
       7: aload_1
       8: ldc           #4                  // class org/apache/dubbo/common/extension/SPI
      10: invokevirtual #5                  // Method java/lang/Class.isAnnotationPresent:(Ljava/lang/Class;)Z
      13: ifne          18
      16: aconst_null
      17: areturn
      18: aload_0
      19: getfield      #2                  // Field extensionAccessor:Lorg/apache/dubbo/common/extension/ExtensionAccessor;
      22: aload_1
      23: invokeinterface #6,  2            // InterfaceMethod org/apache/dubbo/common/extension/ExtensionAccessor.getExtensionLoader:(Ljava/lang/Class;)Lorg/apache/dubbo/common/extension/ExtensionLoader;
      28: astore_3
      29: aload_3
      30: ifnonnull     35
      33: aconst_null
      34: areturn
      35: aload_3
      36: invokevirtual #7                  // Method org/apache/dubbo/common/extension/ExtensionLoader.getSupportedExtensions:()Ljava/util/Set;
      39: invokeinterface #8,  1            // InterfaceMethod java/util/Set.isEmpty:()Z
      44: ifne          52
      47: aload_3
      48: invokevirtual #9                  // Method org/apache/dubbo/common/extension/ExtensionLoader.getAdaptiveExtension:()Ljava/lang/Object;
      51: areturn
      52: aconst_null
      53: areturn
}
