Compiled from "FutureAdapter.java"
class com.alibaba.dubbo.rpc.protocol.dubbo.FutureAdapter$3 implements java.util.function.BiConsumer<java.lang.Object, java.lang.Throwable> {
  final com.alibaba.dubbo.remoting.exchange.ResponseCallback val$callback;

  final com.alibaba.dubbo.rpc.protocol.dubbo.FutureAdapter this$0;

  com.alibaba.dubbo.rpc.protocol.dubbo.FutureAdapter$3(com.alibaba.dubbo.rpc.protocol.dubbo.FutureAdapter, com.alibaba.dubbo.remoting.exchange.ResponseCallback);
    Code:
       0: aload_0
       1: aload_1
       2: putfield      #1                  // Field this$0:Lcom/alibaba/dubbo/rpc/protocol/dubbo/FutureAdapter;
       5: aload_0
       6: aload_2
       7: putfield      #2                  // Field val$callback:Lcom/alibaba/dubbo/remoting/exchange/ResponseCallback;
      10: aload_0
      11: invokespecial #3                  // Method java/lang/Object."<init>":()V
      14: return

  public void accept(java.lang.Object, java.lang.Throwable);
    Code:
       0: aload_2
       1: ifnull        29
       4: aload_2
       5: instanceof    #4                  // class java/util/concurrent/CompletionException
       8: ifeq          16
      11: aload_2
      12: invokevirtual #5                  // Method java/lang/Throwable.getCause:()Ljava/lang/Throwable;
      15: astore_2
      16: aload_0
      17: getfield      #2                  // Field val$callback:Lcom/alibaba/dubbo/remoting/exchange/ResponseCallback;
      20: aload_2
      21: invokeinterface #6,  2            // InterfaceMethod com/alibaba/dubbo/remoting/exchange/ResponseCallback.caught:(Ljava/lang/Throwable;)V
      26: goto          70
      29: aload_1
      30: checkcast     #7                  // class org/apache/dubbo/rpc/AppResponse
      33: astore_3
      34: aload_3
      35: invokevirtual #8                  // Method org/apache/dubbo/rpc/AppResponse.hasException:()Z
      38: ifeq          57
      41: aload_0
      42: getfield      #2                  // Field val$callback:Lcom/alibaba/dubbo/remoting/exchange/ResponseCallback;
      45: aload_3
      46: invokevirtual #9                  // Method org/apache/dubbo/rpc/AppResponse.getException:()Ljava/lang/Throwable;
      49: invokeinterface #6,  2            // InterfaceMethod com/alibaba/dubbo/remoting/exchange/ResponseCallback.caught:(Ljava/lang/Throwable;)V
      54: goto          70
      57: aload_0
      58: getfield      #2                  // Field val$callback:Lcom/alibaba/dubbo/remoting/exchange/ResponseCallback;
      61: aload_3
      62: invokevirtual #10                 // Method org/apache/dubbo/rpc/AppResponse.getValue:()Ljava/lang/Object;
      65: invokeinterface #11,  2           // InterfaceMethod com/alibaba/dubbo/remoting/exchange/ResponseCallback.done:(Ljava/lang/Object;)V
      70: return

  public void accept(java.lang.Object, java.lang.Object);
    Code:
       0: aload_0
       1: aload_1
       2: aload_2
       3: checkcast     #12                 // class java/lang/Throwable
       6: invokevirtual #13                 // Method accept:(Ljava/lang/Object;Ljava/lang/Throwable;)V
       9: return
}
