Compiled from "FutureAdapter.java"
public class com.alibaba.dubbo.rpc.protocol.dubbo.FutureAdapter<V> implements java.util.concurrent.Future<V> {
  private java.util.concurrent.CompletableFuture<java.lang.Object> future;

  public com.alibaba.dubbo.rpc.protocol.dubbo.FutureAdapter(java.util.concurrent.CompletableFuture<java.lang.Object>);
    Code:
       0: aload_0
       1: invokespecial #2                  // Method java/lang/Object."<init>":()V
       4: aload_0
       5: aload_1
       6: putfield      #1                  // Field future:Ljava/util/concurrent/CompletableFuture;
       9: return

  public com.alibaba.dubbo.rpc.protocol.dubbo.FutureAdapter(com.alibaba.dubbo.remoting.exchange.ResponseFuture);
    Code:
       0: aload_0
       1: invokespecial #2                  // Method java/lang/Object."<init>":()V
       4: aload_0
       5: new           #3                  // class java/util/concurrent/CompletableFuture
       8: dup
       9: invokespecial #4                  // Method java/util/concurrent/CompletableFuture."<init>":()V
      12: putfield      #1                  // Field future:Ljava/util/concurrent/CompletableFuture;
      15: aload_1
      16: new           #5                  // class com/alibaba/dubbo/rpc/protocol/dubbo/FutureAdapter$1
      19: dup
      20: aload_0
      21: invokespecial #6                  // Method com/alibaba/dubbo/rpc/protocol/dubbo/FutureAdapter$1."<init>":(Lcom/alibaba/dubbo/rpc/protocol/dubbo/FutureAdapter;)V
      24: invokeinterface #7,  2            // InterfaceMethod com/alibaba/dubbo/remoting/exchange/ResponseFuture.setCallback:(Lcom/alibaba/dubbo/remoting/exchange/ResponseCallback;)V
      29: return

  public com.alibaba.dubbo.remoting.exchange.ResponseFuture getFuture();
    Code:
       0: new           #8                  // class com/alibaba/dubbo/rpc/protocol/dubbo/FutureAdapter$2
       3: dup
       4: aload_0
       5: invokespecial #9                  // Method com/alibaba/dubbo/rpc/protocol/dubbo/FutureAdapter$2."<init>":(Lcom/alibaba/dubbo/rpc/protocol/dubbo/FutureAdapter;)V
       8: areturn

  void setCallback(com.alibaba.dubbo.remoting.exchange.ResponseCallback);
    Code:
       0: new           #10                 // class com/alibaba/dubbo/rpc/protocol/dubbo/FutureAdapter$3
       3: dup
       4: aload_0
       5: aload_1
       6: invokespecial #11                 // Method com/alibaba/dubbo/rpc/protocol/dubbo/FutureAdapter$3."<init>":(Lcom/alibaba/dubbo/rpc/protocol/dubbo/FutureAdapter;Lcom/alibaba/dubbo/remoting/exchange/ResponseCallback;)V
       9: astore_2
      10: aload_0
      11: getfield      #1                  // Field future:Ljava/util/concurrent/CompletableFuture;
      14: aload_2
      15: invokevirtual #12                 // Method java/util/concurrent/CompletableFuture.whenComplete:(Ljava/util/function/BiConsumer;)Ljava/util/concurrent/CompletableFuture;
      18: pop
      19: return

  public boolean cancel(boolean);
    Code:
       0: iconst_0
       1: ireturn

  public boolean isCancelled();
    Code:
       0: iconst_0
       1: ireturn

  public boolean isDone();
    Code:
       0: aload_0
       1: getfield      #1                  // Field future:Ljava/util/concurrent/CompletableFuture;
       4: invokevirtual #13                 // Method java/util/concurrent/CompletableFuture.isDone:()Z
       7: ireturn

  public V get() throws java.lang.InterruptedException, java.util.concurrent.ExecutionException;
    Code:
       0: aload_0
       1: getfield      #1                  // Field future:Ljava/util/concurrent/CompletableFuture;
       4: invokevirtual #14                 // Method java/util/concurrent/CompletableFuture.get:()Ljava/lang/Object;
       7: checkcast     #15                 // class org/apache/dubbo/rpc/Result
      10: invokeinterface #16,  1           // InterfaceMethod org/apache/dubbo/rpc/Result.recreate:()Ljava/lang/Object;
      15: areturn
      16: astore_1
      17: aload_1
      18: athrow
      19: astore_1
      20: new           #20                 // class com/alibaba/dubbo/rpc/RpcException
      23: dup
      24: aload_1
      25: invokespecial #21                 // Method com/alibaba/dubbo/rpc/RpcException."<init>":(Ljava/lang/Throwable;)V
      28: athrow
    Exception table:
       from    to  target type
           0    15    16   Class java/lang/InterruptedException
           0    15    16   Class java/util/concurrent/ExecutionException
           0    15    19   Class java/lang/Throwable

  public V get(long, java.util.concurrent.TimeUnit) throws java.lang.InterruptedException, java.util.concurrent.ExecutionException, java.util.concurrent.TimeoutException;
    Code:
       0: aload_0
       1: getfield      #1                  // Field future:Ljava/util/concurrent/CompletableFuture;
       4: lload_1
       5: aload_3
       6: invokevirtual #22                 // Method java/util/concurrent/CompletableFuture.get:(JLjava/util/concurrent/TimeUnit;)Ljava/lang/Object;
       9: checkcast     #15                 // class org/apache/dubbo/rpc/Result
      12: invokeinterface #16,  1           // InterfaceMethod org/apache/dubbo/rpc/Result.recreate:()Ljava/lang/Object;
      17: areturn
      18: astore        4
      20: aload         4
      22: athrow
      23: astore        4
      25: new           #20                 // class com/alibaba/dubbo/rpc/RpcException
      28: dup
      29: aload         4
      31: invokespecial #21                 // Method com/alibaba/dubbo/rpc/RpcException."<init>":(Ljava/lang/Throwable;)V
      34: athrow
    Exception table:
       from    to  target type
           0    17    18   Class java/lang/InterruptedException
           0    17    18   Class java/util/concurrent/ExecutionException
           0    17    18   Class java/util/concurrent/TimeoutException
           0    17    23   Class java/lang/Throwable

  static java.util.concurrent.CompletableFuture access$000(com.alibaba.dubbo.rpc.protocol.dubbo.FutureAdapter);
    Code:
       0: aload_0
       1: getfield      #1                  // Field future:Ljava/util/concurrent/CompletableFuture;
       4: areturn
}
