Compiled from "FutureAdapter.java"
class com.alibaba.dubbo.rpc.protocol.dubbo.FutureAdapter$2 implements com.alibaba.dubbo.remoting.exchange.ResponseFuture {
  final com.alibaba.dubbo.rpc.protocol.dubbo.FutureAdapter this$0;

  com.alibaba.dubbo.rpc.protocol.dubbo.FutureAdapter$2(com.alibaba.dubbo.rpc.protocol.dubbo.FutureAdapter);
    Code:
       0: aload_0
       1: aload_1
       2: putfield      #1                  // Field this$0:Lcom/alibaba/dubbo/rpc/protocol/dubbo/FutureAdapter;
       5: aload_0
       6: invokespecial #2                  // Method java/lang/Object."<init>":()V
       9: return

  public java.lang.Object get() throws com.alibaba.dubbo.remoting.RemotingException;
    Code:
       0: aload_0
       1: getfield      #1                  // Field this$0:Lcom/alibaba/dubbo/rpc/protocol/dubbo/FutureAdapter;
       4: invokestatic  #3                  // Method com/alibaba/dubbo/rpc/protocol/dubbo/FutureAdapter.access$000:(Lcom/alibaba/dubbo/rpc/protocol/dubbo/FutureAdapter;)Ljava/util/concurrent/CompletableFuture;
       7: invokevirtual #4                  // Method java/util/concurrent/CompletableFuture.get:()Ljava/lang/Object;
      10: areturn
      11: astore_1
      12: new           #7                  // class com/alibaba/dubbo/remoting/RemotingException
      15: dup
      16: aload_1
      17: invokespecial #8                  // Method com/alibaba/dubbo/remoting/RemotingException."<init>":(Ljava/lang/Exception;)V
      20: athrow
    Exception table:
       from    to  target type
           0    10    11   Class java/lang/InterruptedException
           0    10    11   Class java/util/concurrent/ExecutionException

  public java.lang.Object get(int) throws com.alibaba.dubbo.remoting.RemotingException;
    Code:
       0: aload_0
       1: getfield      #1                  // Field this$0:Lcom/alibaba/dubbo/rpc/protocol/dubbo/FutureAdapter;
       4: invokestatic  #3                  // Method com/alibaba/dubbo/rpc/protocol/dubbo/FutureAdapter.access$000:(Lcom/alibaba/dubbo/rpc/protocol/dubbo/FutureAdapter;)Ljava/util/concurrent/CompletableFuture;
       7: iload_1
       8: i2l
       9: getstatic     #9                  // Field java/util/concurrent/TimeUnit.MILLISECONDS:Ljava/util/concurrent/TimeUnit;
      12: invokevirtual #10                 // Method java/util/concurrent/CompletableFuture.get:(JLjava/util/concurrent/TimeUnit;)Ljava/lang/Object;
      15: areturn
      16: astore_2
      17: new           #7                  // class com/alibaba/dubbo/remoting/RemotingException
      20: dup
      21: aload_2
      22: invokespecial #8                  // Method com/alibaba/dubbo/remoting/RemotingException."<init>":(Ljava/lang/Exception;)V
      25: athrow
    Exception table:
       from    to  target type
           0    15    16   Class java/lang/InterruptedException
           0    15    16   Class java/util/concurrent/TimeoutException
           0    15    16   Class java/util/concurrent/ExecutionException

  public void setCallback(com.alibaba.dubbo.remoting.exchange.ResponseCallback);
    Code:
       0: aload_0
       1: getfield      #1                  // Field this$0:Lcom/alibaba/dubbo/rpc/protocol/dubbo/FutureAdapter;
       4: aload_1
       5: invokevirtual #12                 // Method com/alibaba/dubbo/rpc/protocol/dubbo/FutureAdapter.setCallback:(Lcom/alibaba/dubbo/remoting/exchange/ResponseCallback;)V
       8: return

  public boolean isDone();
    Code:
       0: aload_0
       1: getfield      #1                  // Field this$0:Lcom/alibaba/dubbo/rpc/protocol/dubbo/FutureAdapter;
       4: invokestatic  #3                  // Method com/alibaba/dubbo/rpc/protocol/dubbo/FutureAdapter.access$000:(Lcom/alibaba/dubbo/rpc/protocol/dubbo/FutureAdapter;)Ljava/util/concurrent/CompletableFuture;
       7: invokevirtual #13                 // Method java/util/concurrent/CompletableFuture.isDone:()Z
      10: ireturn
}
