Compiled from "FutureAdapter.java"
class com.alibaba.dubbo.rpc.protocol.dubbo.FutureAdapter$1 implements com.alibaba.dubbo.remoting.exchange.ResponseCallback {
  final com.alibaba.dubbo.rpc.protocol.dubbo.FutureAdapter this$0;

  com.alibaba.dubbo.rpc.protocol.dubbo.FutureAdapter$1(com.alibaba.dubbo.rpc.protocol.dubbo.FutureAdapter);
    Code:
       0: aload_0
       1: aload_1
       2: putfield      #1                  // Field this$0:Lcom/alibaba/dubbo/rpc/protocol/dubbo/FutureAdapter;
       5: aload_0
       6: invokespecial #2                  // Method java/lang/Object."<init>":()V
       9: return

  public void done(java.lang.Object);
    Code:
       0: aload_0
       1: getfield      #1                  // Field this$0:Lcom/alibaba/dubbo/rpc/protocol/dubbo/FutureAdapter;
       4: invokestatic  #3                  // Method com/alibaba/dubbo/rpc/protocol/dubbo/FutureAdapter.access$000:(Lcom/alibaba/dubbo/rpc/protocol/dubbo/FutureAdapter;)Ljava/util/concurrent/CompletableFuture;
       7: aload_1
       8: invokevirtual #4                  // Method java/util/concurrent/CompletableFuture.complete:(Ljava/lang/Object;)Z
      11: pop
      12: return

  public void caught(java.lang.Throwable);
    Code:
       0: aload_0
       1: getfield      #1                  // Field this$0:Lcom/alibaba/dubbo/rpc/protocol/dubbo/FutureAdapter;
       4: invokestatic  #3                  // Method com/alibaba/dubbo/rpc/protocol/dubbo/FutureAdapter.access$000:(Lcom/alibaba/dubbo/rpc/protocol/dubbo/FutureAdapter;)Ljava/util/concurrent/CompletableFuture;
       7: aload_1
       8: invokevirtual #5                  // Method java/util/concurrent/CompletableFuture.completeExceptionally:(Ljava/lang/Throwable;)Z
      11: pop
      12: return
}
