Compiled from "AbstractEmptyQueueFuseable.java"
public abstract class io.reactivex.rxjava3.internal.fuseable.AbstractEmptyQueueFuseable<T> implements io.reactivex.rxjava3.operators.QueueSubscription<T>, io.reactivex.rxjava3.operators.QueueDisposable<T> {
  public io.reactivex.rxjava3.internal.fuseable.AbstractEmptyQueueFuseable();
    Code:
       0: aload_0
       1: invokespecial #1                  // Method java/lang/Object."<init>":()V
       4: return

  public final int requestFusion(int);
    Code:
       0: iload_1
       1: iconst_2
       2: iand
       3: ireturn

  public final boolean offer(T);
    Code:
       0: new           #3                  // class java/lang/UnsupportedOperationException
       3: dup
       4: ldc           #4                  // String Should not be called!
       6: invokespecial #5                  // Method java/lang/UnsupportedOperationException."<init>":(Ljava/lang/String;)V
       9: athrow

  public final boolean offer(T, T);
    Code:
       0: new           #3                  // class java/lang/UnsupportedOperationException
       3: dup
       4: ldc           #4                  // String Should not be called!
       6: invokespecial #5                  // Method java/lang/UnsupportedOperationException."<init>":(Ljava/lang/String;)V
       9: athrow

  public final T poll() throws java.lang.Throwable;
    Code:
       0: aconst_null
       1: areturn

  public final boolean isEmpty();
    Code:
       0: iconst_1
       1: ireturn

  public final void clear();
    Code:
       0: return

  public final void request(long);
    Code:
       0: return

  public void cancel();
    Code:
       0: return

  public void dispose();
    Code:
       0: return

  public boolean isDisposed();
    Code:
       0: iconst_0
       1: ireturn
}
