Compiled from "CancellableQueueFuseable.java"
public final class io.reactivex.rxjava3.internal.fuseable.CancellableQueueFuseable<T> extends io.reactivex.rxjava3.internal.fuseable.AbstractEmptyQueueFuseable<T> {
  volatile boolean disposed;

  public io.reactivex.rxjava3.internal.fuseable.CancellableQueueFuseable();
    Code:
       0: aload_0
       1: invokespecial #1                  // Method io/reactivex/rxjava3/internal/fuseable/AbstractEmptyQueueFuseable."<init>":()V
       4: return

  public void cancel();
    Code:
       0: aload_0
       1: iconst_1
       2: putfield      #2                  // Field disposed:Z
       5: return

  public void dispose();
    Code:
       0: aload_0
       1: iconst_1
       2: putfield      #2                  // Field disposed:Z
       5: return

  public boolean isDisposed();
    Code:
       0: aload_0
       1: getfield      #2                  // Field disposed:Z
       4: ireturn
}
