Compiled from "DefaultSubDispatcher.java"
public final class org.apache.dubbo.metrics.event.DefaultSubDispatcher extends org.apache.dubbo.metrics.event.SimpleMetricsEventMulticaster {
  public org.apache.dubbo.metrics.event.DefaultSubDispatcher(org.apache.dubbo.metrics.collector.DefaultMetricsCollector);
    Code:
       0: aload_0
       1: invokespecial #3                  // Method org/apache/dubbo/metrics/event/SimpleMetricsEventMulticaster."<init>":()V
       4: aload_0
       5: invokespecial #4                  // Method initMethodRequest:()Lorg/apache/dubbo/metrics/model/key/CategoryOverall;
       8: astore_2
       9: aload_0
      10: aload_2
      11: invokevirtual #5                  // Method org/apache/dubbo/metrics/model/key/CategoryOverall.getPost:()Lorg/apache/dubbo/metrics/model/key/MetricsCat;
      14: invokevirtual #6                  // Method org/apache/dubbo/metrics/model/key/MetricsCat.getEventFunc:()Ljava/util/function/Function;
      17: aload_1
      18: invokeinterface #7,  2            // InterfaceMethod java/util/function/Function.apply:(Ljava/lang/Object;)Ljava/lang/Object;
      23: checkcast     #8                  // class org/apache/dubbo/metrics/listener/MetricsListener
      26: invokespecial #9                  // Method org/apache/dubbo/metrics/event/SimpleMetricsEventMulticaster.addListener:(Lorg/apache/dubbo/metrics/listener/MetricsListener;)V
      29: aload_0
      30: aload_2
      31: invokevirtual #10                 // Method org/apache/dubbo/metrics/model/key/CategoryOverall.getFinish:()Lorg/apache/dubbo/metrics/model/key/MetricsCat;
      34: invokevirtual #6                  // Method org/apache/dubbo/metrics/model/key/MetricsCat.getEventFunc:()Ljava/util/function/Function;
      37: aload_1
      38: invokeinterface #7,  2            // InterfaceMethod java/util/function/Function.apply:(Ljava/lang/Object;)Ljava/lang/Object;
      43: checkcast     #8                  // class org/apache/dubbo/metrics/listener/MetricsListener
      46: invokespecial #9                  // Method org/apache/dubbo/metrics/event/SimpleMetricsEventMulticaster.addListener:(Lorg/apache/dubbo/metrics/listener/MetricsListener;)V
      49: aload_0
      50: aload_2
      51: invokevirtual #11                 // Method org/apache/dubbo/metrics/model/key/CategoryOverall.getError:()Lorg/apache/dubbo/metrics/model/key/MetricsCat;
      54: invokevirtual #6                  // Method org/apache/dubbo/metrics/model/key/MetricsCat.getEventFunc:()Ljava/util/function/Function;
      57: aload_1
      58: invokeinterface #7,  2            // InterfaceMethod java/util/function/Function.apply:(Ljava/lang/Object;)Ljava/lang/Object;
      63: checkcast     #8                  // class org/apache/dubbo/metrics/listener/MetricsListener
      66: invokespecial #9                  // Method org/apache/dubbo/metrics/event/SimpleMetricsEventMulticaster.addListener:(Lorg/apache/dubbo/metrics/listener/MetricsListener;)V
      69: aload_0
      70: new           #12                 // class org/apache/dubbo/metrics/event/DefaultSubDispatcher$1
      73: dup
      74: aload_0
      75: aload_1
      76: invokespecial #13                 // Method org/apache/dubbo/metrics/event/DefaultSubDispatcher$1."<init>":(Lorg/apache/dubbo/metrics/event/DefaultSubDispatcher;Lorg/apache/dubbo/metrics/collector/DefaultMetricsCollector;)V
      79: invokespecial #9                  // Method org/apache/dubbo/metrics/event/SimpleMetricsEventMulticaster.addListener:(Lorg/apache/dubbo/metrics/listener/MetricsListener;)V
      82: return

  private org.apache.dubbo.metrics.model.key.CategoryOverall initMethodRequest();
    Code:
       0: new           #14                 // class org/apache/dubbo/metrics/model/key/CategoryOverall
       3: dup
       4: aconst_null
       5: new           #15                 // class org/apache/dubbo/metrics/model/key/MetricsCat
       8: dup
       9: getstatic     #16                 // Field org/apache/dubbo/metrics/model/key/MetricsKey.METRIC_REQUESTS:Lorg/apache/dubbo/metrics/model/key/MetricsKey;
      12: invokedynamic #17,  0             // InvokeDynamic #0:apply:()Lorg/apache/dubbo/metrics/model/key/MetricsCat$TpFunction;
      17: invokespecial #18                 // Method org/apache/dubbo/metrics/model/key/MetricsCat."<init>":(Lorg/apache/dubbo/metrics/model/key/MetricsKey;Lorg/apache/dubbo/metrics/model/key/MetricsCat$TpFunction;)V
      20: new           #15                 // class org/apache/dubbo/metrics/model/key/MetricsCat
      23: dup
      24: getstatic     #19                 // Field org/apache/dubbo/metrics/model/key/MetricsKey.METRIC_REQUESTS_SUCCEED:Lorg/apache/dubbo/metrics/model/key/MetricsKey;
      27: invokedynamic #20,  0             // InvokeDynamic #1:apply:()Lorg/apache/dubbo/metrics/model/key/MetricsCat$TpFunction;
      32: invokespecial #18                 // Method org/apache/dubbo/metrics/model/key/MetricsCat."<init>":(Lorg/apache/dubbo/metrics/model/key/MetricsKey;Lorg/apache/dubbo/metrics/model/key/MetricsCat$TpFunction;)V
      35: new           #15                 // class org/apache/dubbo/metrics/model/key/MetricsCat
      38: dup
      39: getstatic     #21                 // Field org/apache/dubbo/metrics/model/key/MetricsKey.METRIC_REQUEST_BUSINESS_FAILED:Lorg/apache/dubbo/metrics/model/key/MetricsKey;
      42: invokedynamic #22,  0             // InvokeDynamic #2:apply:()Lorg/apache/dubbo/metrics/model/key/MetricsCat$TpFunction;
      47: invokespecial #18                 // Method org/apache/dubbo/metrics/model/key/MetricsCat."<init>":(Lorg/apache/dubbo/metrics/model/key/MetricsKey;Lorg/apache/dubbo/metrics/model/key/MetricsCat$TpFunction;)V
      50: invokespecial #23                 // Method org/apache/dubbo/metrics/model/key/CategoryOverall."<init>":(Lorg/apache/dubbo/metrics/model/key/MetricsPlaceValue;Lorg/apache/dubbo/metrics/model/key/MetricsCat;Lorg/apache/dubbo/metrics/model/key/MetricsCat;Lorg/apache/dubbo/metrics/model/key/MetricsCat;)V
      53: areturn

  private static org.apache.dubbo.metrics.listener.AbstractMetricsKeyListener lambda$initMethodRequest$5(org.apache.dubbo.metrics.model.key.MetricsKey, org.apache.dubbo.metrics.model.key.MetricsPlaceValue, org.apache.dubbo.metrics.collector.CombMetricsCollector);
    Code:
       0: aload_0
       1: aload_2
       2: invokedynamic #24,  0             // InvokeDynamic #3:accept:(Lorg/apache/dubbo/metrics/collector/CombMetricsCollector;)Ljava/util/function/Consumer;
       7: invokestatic  #25                 // Method org/apache/dubbo/metrics/listener/AbstractMetricsKeyListener.onError:(Lorg/apache/dubbo/metrics/model/key/MetricsKey;Ljava/util/function/Consumer;)Lorg/apache/dubbo/metrics/listener/AbstractMetricsKeyListener;
      10: areturn

  private static void lambda$null$4(org.apache.dubbo.metrics.collector.CombMetricsCollector, org.apache.dubbo.metrics.event.TimeCounterEvent);
    Code:
       0: aload_1
       1: ldc           #26                 // String metric_filter_throwable
       3: invokevirtual #27                 // Method org/apache/dubbo/metrics/event/TimeCounterEvent.getAttachmentValue:(Ljava/lang/String;)Ljava/lang/Object;
       6: checkcast     #28                 // class java/lang/Throwable
       9: invokestatic  #29                 // Method org/apache/dubbo/metrics/model/MetricsSupport.getMetricsKey:(Ljava/lang/Throwable;)Lorg/apache/dubbo/metrics/model/key/MetricsKey;
      12: astore_2
      13: aload_1
      14: ldc           #30                 // String metric_filter_side
      16: invokevirtual #27                 // Method org/apache/dubbo/metrics/event/TimeCounterEvent.getAttachmentValue:(Ljava/lang/String;)Ljava/lang/Object;
      19: checkcast     #31                 // class java/lang/String
      22: getstatic     #32                 // Field org/apache/dubbo/metrics/model/key/MetricsLevel.METHOD:Lorg/apache/dubbo/metrics/model/key/MetricsLevel;
      25: invokestatic  #33                 // Method org/apache/dubbo/metrics/model/key/MetricsPlaceValue.of:(Ljava/lang/String;Lorg/apache/dubbo/metrics/model/key/MetricsLevel;)Lorg/apache/dubbo/metrics/model/key/MetricsPlaceValue;
      28: astore_3
      29: getstatic     #34                 // Field org/apache/dubbo/metrics/model/key/MetricsKey.METRIC_REQUESTS_TOTAL_FAILED:Lorg/apache/dubbo/metrics/model/key/MetricsKey;
      32: aload_3
      33: aload_0
      34: aload_1
      35: invokestatic  #35                 // Method org/apache/dubbo/metrics/model/MetricsSupport.increment:(Lorg/apache/dubbo/metrics/model/key/MetricsKey;Lorg/apache/dubbo/metrics/model/key/MetricsPlaceValue;Lorg/apache/dubbo/metrics/collector/MethodMetricsCollector;Lorg/apache/dubbo/metrics/event/MetricsEvent;)V
      38: getstatic     #36                 // Field org/apache/dubbo/metrics/model/key/MetricsKey.METRIC_REQUESTS_PROCESSING:Lorg/apache/dubbo/metrics/model/key/MetricsKey;
      41: aload_3
      42: aload_0
      43: aload_1
      44: invokestatic  #37                 // Method org/apache/dubbo/metrics/model/MetricsSupport.dec:(Lorg/apache/dubbo/metrics/model/key/MetricsKey;Lorg/apache/dubbo/metrics/model/key/MetricsPlaceValue;Lorg/apache/dubbo/metrics/collector/MethodMetricsCollector;Lorg/apache/dubbo/metrics/event/MetricsEvent;)V
      47: aload_2
      48: aload_3
      49: aload_0
      50: aload_1
      51: invokestatic  #38                 // Method org/apache/dubbo/metrics/model/MetricsSupport.incrAndAddRt:(Lorg/apache/dubbo/metrics/model/key/MetricsKey;Lorg/apache/dubbo/metrics/model/key/MetricsPlaceValue;Lorg/apache/dubbo/metrics/collector/MethodMetricsCollector;Lorg/apache/dubbo/metrics/event/TimeCounterEvent;)V
      54: return

  private static org.apache.dubbo.metrics.listener.AbstractMetricsKeyListener lambda$initMethodRequest$3(org.apache.dubbo.metrics.model.key.MetricsKey, org.apache.dubbo.metrics.model.key.MetricsPlaceValue, org.apache.dubbo.metrics.collector.CombMetricsCollector);
    Code:
       0: aload_0
       1: aload_2
       2: aload_0
       3: invokedynamic #39,  0             // InvokeDynamic #4:accept:(Lorg/apache/dubbo/metrics/collector/CombMetricsCollector;Lorg/apache/dubbo/metrics/model/key/MetricsKey;)Ljava/util/function/Consumer;
       8: invokestatic  #40                 // Method org/apache/dubbo/metrics/listener/AbstractMetricsKeyListener.onFinish:(Lorg/apache/dubbo/metrics/model/key/MetricsKey;Ljava/util/function/Consumer;)Lorg/apache/dubbo/metrics/listener/AbstractMetricsKeyListener;
      11: areturn

  private static void lambda$null$2(org.apache.dubbo.metrics.collector.CombMetricsCollector, org.apache.dubbo.metrics.model.key.MetricsKey, org.apache.dubbo.metrics.event.TimeCounterEvent);
    Code:
       0: aload_2
       1: ldc           #30                 // String metric_filter_side
       3: invokevirtual #27                 // Method org/apache/dubbo/metrics/event/TimeCounterEvent.getAttachmentValue:(Ljava/lang/String;)Ljava/lang/Object;
       6: checkcast     #31                 // class java/lang/String
       9: getstatic     #32                 // Field org/apache/dubbo/metrics/model/key/MetricsLevel.METHOD:Lorg/apache/dubbo/metrics/model/key/MetricsLevel;
      12: invokestatic  #33                 // Method org/apache/dubbo/metrics/model/key/MetricsPlaceValue.of:(Ljava/lang/String;Lorg/apache/dubbo/metrics/model/key/MetricsLevel;)Lorg/apache/dubbo/metrics/model/key/MetricsPlaceValue;
      15: astore_3
      16: getstatic     #36                 // Field org/apache/dubbo/metrics/model/key/MetricsKey.METRIC_REQUESTS_PROCESSING:Lorg/apache/dubbo/metrics/model/key/MetricsKey;
      19: aload_3
      20: aload_0
      21: aload_2
      22: invokestatic  #37                 // Method org/apache/dubbo/metrics/model/MetricsSupport.dec:(Lorg/apache/dubbo/metrics/model/key/MetricsKey;Lorg/apache/dubbo/metrics/model/key/MetricsPlaceValue;Lorg/apache/dubbo/metrics/collector/MethodMetricsCollector;Lorg/apache/dubbo/metrics/event/MetricsEvent;)V
      25: aload_2
      26: ldc           #26                 // String metric_filter_throwable
      28: invokevirtual #27                 // Method org/apache/dubbo/metrics/event/TimeCounterEvent.getAttachmentValue:(Ljava/lang/String;)Ljava/lang/Object;
      31: astore        4
      33: aload         4
      35: ifnonnull     44
      38: aload_1
      39: astore        5
      41: goto          54
      44: aload         4
      46: checkcast     #28                 // class java/lang/Throwable
      49: invokestatic  #29                 // Method org/apache/dubbo/metrics/model/MetricsSupport.getMetricsKey:(Ljava/lang/Throwable;)Lorg/apache/dubbo/metrics/model/key/MetricsKey;
      52: astore        5
      54: aload         5
      56: aload_3
      57: aload_0
      58: aload_2
      59: invokestatic  #38                 // Method org/apache/dubbo/metrics/model/MetricsSupport.incrAndAddRt:(Lorg/apache/dubbo/metrics/model/key/MetricsKey;Lorg/apache/dubbo/metrics/model/key/MetricsPlaceValue;Lorg/apache/dubbo/metrics/collector/MethodMetricsCollector;Lorg/apache/dubbo/metrics/event/TimeCounterEvent;)V
      62: return

  private static org.apache.dubbo.metrics.listener.AbstractMetricsKeyListener lambda$initMethodRequest$1(org.apache.dubbo.metrics.model.key.MetricsKey, org.apache.dubbo.metrics.model.key.MetricsPlaceValue, org.apache.dubbo.metrics.collector.CombMetricsCollector);
    Code:
       0: aload_0
       1: aload_0
       2: aload_2
       3: invokedynamic #41,  0             // InvokeDynamic #5:accept:(Lorg/apache/dubbo/metrics/model/key/MetricsKey;Lorg/apache/dubbo/metrics/collector/CombMetricsCollector;)Ljava/util/function/Consumer;
       8: invokestatic  #42                 // Method org/apache/dubbo/metrics/listener/AbstractMetricsKeyListener.onEvent:(Lorg/apache/dubbo/metrics/model/key/MetricsKey;Ljava/util/function/Consumer;)Lorg/apache/dubbo/metrics/listener/AbstractMetricsKeyListener;
      11: areturn

  private static void lambda$null$0(org.apache.dubbo.metrics.model.key.MetricsKey, org.apache.dubbo.metrics.collector.CombMetricsCollector, org.apache.dubbo.metrics.event.TimeCounterEvent);
    Code:
       0: aload_2
       1: ldc           #30                 // String metric_filter_side
       3: invokevirtual #27                 // Method org/apache/dubbo/metrics/event/TimeCounterEvent.getAttachmentValue:(Ljava/lang/String;)Ljava/lang/Object;
       6: checkcast     #31                 // class java/lang/String
       9: getstatic     #32                 // Field org/apache/dubbo/metrics/model/key/MetricsLevel.METHOD:Lorg/apache/dubbo/metrics/model/key/MetricsLevel;
      12: invokestatic  #33                 // Method org/apache/dubbo/metrics/model/key/MetricsPlaceValue.of:(Ljava/lang/String;Lorg/apache/dubbo/metrics/model/key/MetricsLevel;)Lorg/apache/dubbo/metrics/model/key/MetricsPlaceValue;
      15: astore_3
      16: aload_0
      17: aload_3
      18: aload_1
      19: aload_2
      20: invokestatic  #35                 // Method org/apache/dubbo/metrics/model/MetricsSupport.increment:(Lorg/apache/dubbo/metrics/model/key/MetricsKey;Lorg/apache/dubbo/metrics/model/key/MetricsPlaceValue;Lorg/apache/dubbo/metrics/collector/MethodMetricsCollector;Lorg/apache/dubbo/metrics/event/MetricsEvent;)V
      23: aload_2
      24: ldc           #43                 // String metric_filter_invocation
      26: invokevirtual #27                 // Method org/apache/dubbo/metrics/event/TimeCounterEvent.getAttachmentValue:(Ljava/lang/String;)Ljava/lang/Object;
      29: checkcast     #44                 // class org/apache/dubbo/rpc/Invocation
      32: astore        4
      34: aload         4
      36: ldc           #45                 // String metric_filter_invocation_counter
      38: getstatic     #46                 // Field org/apache/dubbo/metrics/model/sample/MetricSample$Type.GAUGE:Lorg/apache/dubbo/metrics/model/sample/MetricSample$Type;
      41: invokeinterface #47,  3           // InterfaceMethod org/apache/dubbo/rpc/Invocation.put:(Ljava/lang/Object;Ljava/lang/Object;)Ljava/lang/Object;
      46: pop
      47: getstatic     #36                 // Field org/apache/dubbo/metrics/model/key/MetricsKey.METRIC_REQUESTS_PROCESSING:Lorg/apache/dubbo/metrics/model/key/MetricsKey;
      50: aload_3
      51: aload_1
      52: aload_2
      53: invokestatic  #35                 // Method org/apache/dubbo/metrics/model/MetricsSupport.increment:(Lorg/apache/dubbo/metrics/model/key/MetricsKey;Lorg/apache/dubbo/metrics/model/key/MetricsPlaceValue;Lorg/apache/dubbo/metrics/collector/MethodMetricsCollector;Lorg/apache/dubbo/metrics/event/MetricsEvent;)V
      56: return
}
