Compiled from "DefaultSubDispatcher.java"
class org.apache.dubbo.metrics.event.DefaultSubDispatcher$1 implements org.apache.dubbo.metrics.listener.MetricsListener<org.apache.dubbo.metrics.event.RequestBeforeEvent> {
  final org.apache.dubbo.metrics.collector.DefaultMetricsCollector val$collector;

  final org.apache.dubbo.metrics.event.DefaultSubDispatcher this$0;

  org.apache.dubbo.metrics.event.DefaultSubDispatcher$1(org.apache.dubbo.metrics.event.DefaultSubDispatcher, org.apache.dubbo.metrics.collector.DefaultMetricsCollector);
    Code:
       0: aload_0
       1: aload_1
       2: putfield      #1                  // Field this$0:Lorg/apache/dubbo/metrics/event/DefaultSubDispatcher;
       5: aload_0
       6: aload_2
       7: putfield      #2                  // Field val$collector:Lorg/apache/dubbo/metrics/collector/DefaultMetricsCollector;
      10: aload_0
      11: invokespecial #3                  // Method java/lang/Object."<init>":()V
      14: return

  public boolean isSupport(org.apache.dubbo.metrics.event.MetricsEvent);
    Code:
       0: aload_1
       1: instanceof    #4                  // class org/apache/dubbo/metrics/event/RequestBeforeEvent
       4: ireturn

  public void onEvent(org.apache.dubbo.metrics.event.RequestBeforeEvent);
    Code:
       0: ldc           #6                  // String consumer
       2: getstatic     #7                  // Field org/apache/dubbo/metrics/model/key/MetricsLevel.METHOD:Lorg/apache/dubbo/metrics/model/key/MetricsLevel;
       5: invokestatic  #8                  // Method org/apache/dubbo/metrics/model/key/MetricsPlaceValue.of:(Ljava/lang/String;Lorg/apache/dubbo/metrics/model/key/MetricsLevel;)Lorg/apache/dubbo/metrics/model/key/MetricsPlaceValue;
       8: astore_2
       9: getstatic     #9                  // Field org/apache/dubbo/metrics/model/key/MetricsKey.METRIC_REQUESTS_SERVICE_UNAVAILABLE_FAILED:Lorg/apache/dubbo/metrics/model/key/MetricsKey;
      12: aload_2
      13: aload_0
      14: getfield      #2                  // Field val$collector:Lorg/apache/dubbo/metrics/collector/DefaultMetricsCollector;
      17: aload_1
      18: invokestatic  #10                 // Method org/apache/dubbo/metrics/model/MetricsSupport.increment:(Lorg/apache/dubbo/metrics/model/key/MetricsKey;Lorg/apache/dubbo/metrics/model/key/MetricsPlaceValue;Lorg/apache/dubbo/metrics/collector/MethodMetricsCollector;Lorg/apache/dubbo/metrics/event/MetricsEvent;)V
      21: return

  public void onEvent(org.apache.dubbo.metrics.event.MetricsEvent);
    Code:
       0: aload_0
       1: aload_1
       2: checkcast     #4                  // class org/apache/dubbo/metrics/event/RequestBeforeEvent
       5: invokevirtual #11                 // Method onEvent:(Lorg/apache/dubbo/metrics/event/RequestBeforeEvent;)V
       8: return
}
