Compiled from "EmptyEvent.java"
public class org.apache.dubbo.metrics.event.EmptyEvent extends org.apache.dubbo.metrics.event.MetricsEvent {
  private static final org.apache.dubbo.metrics.event.EmptyEvent empty;

  private org.apache.dubbo.metrics.event.EmptyEvent(org.apache.dubbo.rpc.model.ApplicationModel);
    Code:
       0: aload_0
       1: aload_1
       2: aconst_null
       3: invokespecial #1                  // Method org/apache/dubbo/metrics/event/MetricsEvent."<init>":(Lorg/apache/dubbo/rpc/model/ApplicationModel;Lorg/apache/dubbo/metrics/model/key/TypeWrapper;)V
       6: return

  public static org.apache.dubbo.metrics.event.EmptyEvent instance();
    Code:
       0: getstatic     #2                  // Field empty:Lorg/apache/dubbo/metrics/event/EmptyEvent;
       3: areturn

  static {};
    Code:
       0: new           #3                  // class org/apache/dubbo/metrics/event/EmptyEvent
       3: dup
       4: aconst_null
       5: invokespecial #4                  // Method "<init>":(Lorg/apache/dubbo/rpc/model/ApplicationModel;)V
       8: putstatic     #2                  // Field empty:Lorg/apache/dubbo/metrics/event/EmptyEvent;
      11: return
}
