Compiled from "MetricsEventBus.java"
public class org.apache.dubbo.metrics.event.MetricsEventBus {
  public org.apache.dubbo.metrics.event.MetricsEventBus();
    Code:
       0: aload_0
       1: invokespecial #1                  // Method java/lang/Object."<init>":()V
       4: return

  public static void publish(org.apache.dubbo.metrics.event.MetricsEvent);
    Code:
       0: aload_0
       1: invokevirtual #2                  // Method org/apache/dubbo/metrics/event/MetricsEvent.getSource:()Lorg/apache/dubbo/rpc/model/ApplicationModel;
       4: ifnonnull     8
       7: return
       8: aload_0
       9: invokevirtual #2                  // Method org/apache/dubbo/metrics/event/MetricsEvent.getSource:()Lorg/apache/dubbo/rpc/model/ApplicationModel;
      12: astore_1
      13: aload_1
      14: invokevirtual #3                  // Method org/apache/dubbo/rpc/model/ApplicationModel.isDestroyed:()Z
      17: ifeq          21
      20: return
      21: aload_1
      22: invokevirtual #4                  // Method org/apache/dubbo/rpc/model/ApplicationModel.getBeanFactory:()Lorg/apache/dubbo/common/beans/factory/ScopeBeanFactory;
      25: astore_2
      26: aload_2
      27: invokevirtual #5                  // Method org/apache/dubbo/common/beans/factory/ScopeBeanFactory.isDestroyed:()Z
      30: ifeq          34
      33: return
      34: aload_2
      35: ldc           #6                  // class org/apache/dubbo/metrics/event/MetricsDispatcher
      37: invokevirtual #7                  // Method org/apache/dubbo/common/beans/factory/ScopeBeanFactory.getBean:(Ljava/lang/Class;)Ljava/lang/Object;
      40: checkcast     #6                  // class org/apache/dubbo/metrics/event/MetricsDispatcher
      43: astore_3
      44: aload_3
      45: invokestatic  #8                  // Method java/util/Optional.ofNullable:(Ljava/lang/Object;)Ljava/util/Optional;
      48: aload_0
      49: invokedynamic #9,  0              // InvokeDynamic #0:accept:(Lorg/apache/dubbo/metrics/event/MetricsEvent;)Ljava/util/function/Consumer;
      54: invokevirtual #10                 // Method java/util/Optional.ifPresent:(Ljava/util/function/Consumer;)V
      57: return

  public static <T> T post(org.apache.dubbo.metrics.event.MetricsEvent, java.util.function.Supplier<T>);
    Code:
       0: aload_0
       1: aload_1
       2: aconst_null
       3: invokestatic  #11                 // Method post:(Lorg/apache/dubbo/metrics/event/MetricsEvent;Ljava/util/function/Supplier;Ljava/util/function/Function;)Ljava/lang/Object;
       6: areturn

  public static <T> T post(org.apache.dubbo.metrics.event.MetricsEvent, java.util.function.Supplier<T>, java.util.function.Function<T, java.lang.Boolean>);
    Code:
       0: aload_0
       1: invokestatic  #12                 // Method before:(Lorg/apache/dubbo/metrics/event/MetricsEvent;)V
       4: aload_2
       5: ifnonnull     35
       8: aload_1
       9: invokeinterface #13,  1           // InterfaceMethod java/util/function/Supplier.get:()Ljava/lang/Object;
      14: astore_3
      15: goto          27
      18: astore        4
      20: aload_0
      21: invokestatic  #15                 // Method error:(Lorg/apache/dubbo/metrics/event/MetricsEvent;)V
      24: aload         4
      26: athrow
      27: aload_0
      28: aload_3
      29: invokestatic  #16                 // Method after:(Lorg/apache/dubbo/metrics/event/MetricsEvent;Ljava/lang/Object;)V
      32: goto          70
      35: aload_1
      36: invokeinterface #13,  1           // InterfaceMethod java/util/function/Supplier.get:()Ljava/lang/Object;
      41: astore_3
      42: aload_2
      43: aload_3
      44: invokeinterface #17,  2           // InterfaceMethod java/util/function/Function.apply:(Ljava/lang/Object;)Ljava/lang/Object;
      49: checkcast     #18                 // class java/lang/Boolean
      52: invokevirtual #19                 // Method java/lang/Boolean.booleanValue:()Z
      55: ifeq          66
      58: aload_0
      59: aload_3
      60: invokestatic  #16                 // Method after:(Lorg/apache/dubbo/metrics/event/MetricsEvent;Ljava/lang/Object;)V
      63: goto          70
      66: aload_0
      67: invokestatic  #15                 // Method error:(Lorg/apache/dubbo/metrics/event/MetricsEvent;)V
      70: aload_3
      71: areturn
    Exception table:
       from    to  target type
           8    15    18   Class java/lang/Throwable

  public static void before(org.apache.dubbo.metrics.event.MetricsEvent);
    Code:
       0: aload_0
       1: aconst_null
       2: invokestatic  #20                 // Method before:(Lorg/apache/dubbo/metrics/event/MetricsEvent;Ljava/lang/Runnable;)V
       5: return

  public static void before(org.apache.dubbo.metrics.event.MetricsEvent, java.lang.Runnable);
    Code:
       0: aload_0
       1: invokestatic  #21                 // Method validate:(Lorg/apache/dubbo/metrics/event/MetricsEvent;)Lorg/apache/dubbo/metrics/event/MetricsDispatcher;
       4: astore_2
       5: aload_2
       6: ifnonnull     10
       9: return
      10: aload_2
      11: aload_0
      12: invokevirtual #22                 // Method org/apache/dubbo/metrics/event/MetricsDispatcher.publishEvent:(Lorg/apache/dubbo/metrics/event/MetricsEvent;)V
      15: aload_1
      16: ifnull        25
      19: aload_1
      20: invokeinterface #23,  1           // InterfaceMethod java/lang/Runnable.run:()V
      25: return

  public static void after(org.apache.dubbo.metrics.event.MetricsEvent, java.lang.Object);
    Code:
       0: aload_0
       1: invokestatic  #21                 // Method validate:(Lorg/apache/dubbo/metrics/event/MetricsEvent;)Lorg/apache/dubbo/metrics/event/MetricsDispatcher;
       4: astore_2
       5: aload_2
       6: ifnonnull     10
       9: return
      10: aload_0
      11: aload_1
      12: invokevirtual #24                 // Method org/apache/dubbo/metrics/event/MetricsEvent.customAfterPost:(Ljava/lang/Object;)V
      15: aload_2
      16: aload_0
      17: checkcast     #25                 // class org/apache/dubbo/metrics/event/TimeCounterEvent
      20: invokevirtual #26                 // Method org/apache/dubbo/metrics/event/MetricsDispatcher.publishFinishEvent:(Lorg/apache/dubbo/metrics/event/TimeCounterEvent;)V
      23: return

  public static void error(org.apache.dubbo.metrics.event.MetricsEvent);
    Code:
       0: aload_0
       1: invokestatic  #21                 // Method validate:(Lorg/apache/dubbo/metrics/event/MetricsEvent;)Lorg/apache/dubbo/metrics/event/MetricsDispatcher;
       4: astore_1
       5: aload_1
       6: ifnonnull     10
       9: return
      10: aload_1
      11: aload_0
      12: checkcast     #25                 // class org/apache/dubbo/metrics/event/TimeCounterEvent
      15: invokevirtual #27                 // Method org/apache/dubbo/metrics/event/MetricsDispatcher.publishErrorEvent:(Lorg/apache/dubbo/metrics/event/TimeCounterEvent;)V
      18: return

  private static org.apache.dubbo.metrics.event.MetricsDispatcher validate(org.apache.dubbo.metrics.event.MetricsEvent);
    Code:
       0: aload_0
       1: invokevirtual #2                  // Method org/apache/dubbo/metrics/event/MetricsEvent.getSource:()Lorg/apache/dubbo/rpc/model/ApplicationModel;
       4: ifnonnull     9
       7: aconst_null
       8: areturn
       9: aload_0
      10: invokevirtual #2                  // Method org/apache/dubbo/metrics/event/MetricsEvent.getSource:()Lorg/apache/dubbo/rpc/model/ApplicationModel;
      13: astore_1
      14: aload_1
      15: invokevirtual #3                  // Method org/apache/dubbo/rpc/model/ApplicationModel.isDestroyed:()Z
      18: ifeq          23
      21: aconst_null
      22: areturn
      23: aload_1
      24: invokevirtual #4                  // Method org/apache/dubbo/rpc/model/ApplicationModel.getBeanFactory:()Lorg/apache/dubbo/common/beans/factory/ScopeBeanFactory;
      27: astore_2
      28: aload_2
      29: invokevirtual #5                  // Method org/apache/dubbo/common/beans/factory/ScopeBeanFactory.isDestroyed:()Z
      32: ifeq          37
      35: aconst_null
      36: areturn
      37: aload_2
      38: ldc           #6                  // class org/apache/dubbo/metrics/event/MetricsDispatcher
      40: invokevirtual #7                  // Method org/apache/dubbo/common/beans/factory/ScopeBeanFactory.getBean:(Ljava/lang/Class;)Ljava/lang/Object;
      43: checkcast     #6                  // class org/apache/dubbo/metrics/event/MetricsDispatcher
      46: astore_3
      47: aload_3
      48: ifnonnull     53
      51: aconst_null
      52: areturn
      53: aload_0
      54: instanceof    #25                 // class org/apache/dubbo/metrics/event/TimeCounterEvent
      57: ifne          62
      60: aconst_null
      61: areturn
      62: aload_3
      63: areturn

  private static void lambda$publish$0(org.apache.dubbo.metrics.event.MetricsEvent, org.apache.dubbo.metrics.event.MetricsDispatcher);
    Code:
       0: aload_1
       1: aload_0
       2: invokevirtual #22                 // Method org/apache/dubbo/metrics/event/MetricsDispatcher.publishEvent:(Lorg/apache/dubbo/metrics/event/MetricsEvent;)V
       5: return
}
