Compiled from "MetricsDispatcher.java"
public class org.apache.dubbo.metrics.event.MetricsDispatcher extends org.apache.dubbo.metrics.event.SimpleMetricsEventMulticaster {
  public org.apache.dubbo.metrics.event.MetricsDispatcher(org.apache.dubbo.rpc.model.ApplicationModel);
    Code:
       0: aload_0
       1: invokespecial #1                  // Method org/apache/dubbo/metrics/event/SimpleMetricsEventMulticaster."<init>":()V
       4: aload_1
       5: invokevirtual #2                  // Method org/apache/dubbo/rpc/model/ApplicationModel.getBeanFactory:()Lorg/apache/dubbo/common/beans/factory/ScopeBeanFactory;
       8: astore_2
       9: aload_1
      10: ldc           #3                  // class org/apache/dubbo/metrics/collector/MetricsCollector
      12: invokevirtual #4                  // Method org/apache/dubbo/rpc/model/ApplicationModel.getExtensionLoader:(Ljava/lang/Class;)Lorg/apache/dubbo/common/extension/ExtensionLoader;
      15: astore_3
      16: aload_3
      17: ifnull        79
      20: aload_3
      21: invokevirtual #5                  // Method org/apache/dubbo/common/extension/ExtensionLoader.getActivateExtensions:()Ljava/util/List;
      24: astore        4
      26: aload         4
      28: invokeinterface #6,  1            // InterfaceMethod java/util/List.iterator:()Ljava/util/Iterator;
      33: astore        5
      35: aload         5
      37: invokeinterface #7,  1            // InterfaceMethod java/util/Iterator.hasNext:()Z
      42: ifeq          66
      45: aload         5
      47: invokeinterface #8,  1            // InterfaceMethod java/util/Iterator.next:()Ljava/lang/Object;
      52: checkcast     #3                  // class org/apache/dubbo/metrics/collector/MetricsCollector
      55: astore        6
      57: aload_2
      58: aload         6
      60: invokevirtual #9                  // Method org/apache/dubbo/common/beans/factory/ScopeBeanFactory.registerBean:(Ljava/lang/Object;)V
      63: goto          35
      66: aload         4
      68: aload_0
      69: invokedynamic #10,  0             // InvokeDynamic #0:accept:(Lorg/apache/dubbo/metrics/event/MetricsDispatcher;)Ljava/util/function/Consumer;
      74: invokeinterface #11,  2           // InterfaceMethod java/util/List.forEach:(Ljava/util/function/Consumer;)V
      79: return
}
