Compiled from "MetricsEvent.java"
public abstract class org.apache.dubbo.metrics.event.MetricsEvent {
  protected transient org.apache.dubbo.rpc.model.ApplicationModel source;

  private boolean available;

  private final org.apache.dubbo.metrics.model.key.TypeWrapper typeWrapper;

  private final java.util.Map<java.lang.String, java.lang.Object> attachment;

  public org.apache.dubbo.metrics.event.MetricsEvent(org.apache.dubbo.rpc.model.ApplicationModel, org.apache.dubbo.metrics.model.key.TypeWrapper);
    Code:
       0: aload_0
       1: invokespecial #1                  // Method java/lang/Object."<init>":()V
       4: aload_0
       5: iconst_1
       6: putfield      #2                  // Field available:Z
       9: aload_0
      10: new           #3                  // class java/util/HashMap
      13: dup
      14: bipush        8
      16: invokespecial #4                  // Method java/util/HashMap."<init>":(I)V
      19: putfield      #5                  // Field attachment:Ljava/util/Map;
      22: aload_0
      23: aload_2
      24: putfield      #6                  // Field typeWrapper:Lorg/apache/dubbo/metrics/model/key/TypeWrapper;
      27: aload_1
      28: ifnonnull     46
      31: aload_0
      32: invokestatic  #7                  // Method org/apache/dubbo/rpc/model/ApplicationModel.defaultModel:()Lorg/apache/dubbo/rpc/model/ApplicationModel;
      35: putfield      #8                  // Field source:Lorg/apache/dubbo/rpc/model/ApplicationModel;
      38: aload_0
      39: iconst_0
      40: putfield      #2                  // Field available:Z
      43: goto          51
      46: aload_0
      47: aload_1
      48: putfield      #8                  // Field source:Lorg/apache/dubbo/rpc/model/ApplicationModel;
      51: return

  public <T> T getAttachmentValue(java.lang.String);
    Code:
       0: aload_1
       1: ifnonnull     14
       4: new           #9                  // class org/apache/dubbo/metrics/exception/MetricsNeverHappenException
       7: dup
       8: ldc           #10                 // String Attachment key is null
      10: invokespecial #11                 // Method org/apache/dubbo/metrics/exception/MetricsNeverHappenException."<init>":(Ljava/lang/String;)V
      13: athrow
      14: aload_0
      15: getfield      #5                  // Field attachment:Ljava/util/Map;
      18: aload_1
      19: invokeinterface #12,  2           // InterfaceMethod java/util/Map.get:(Ljava/lang/Object;)Ljava/lang/Object;
      24: areturn

  public void putAttachment(java.lang.String, java.lang.Object);
    Code:
       0: aload_0
       1: getfield      #5                  // Field attachment:Ljava/util/Map;
       4: aload_1
       5: aload_2
       6: invokeinterface #13,  3           // InterfaceMethod java/util/Map.put:(Ljava/lang/Object;Ljava/lang/Object;)Ljava/lang/Object;
      11: pop
      12: return

  public void setAvailable(boolean);
    Code:
       0: aload_0
       1: iload_1
       2: putfield      #2                  // Field available:Z
       5: return

  public boolean isAvailable();
    Code:
       0: aload_0
       1: getfield      #2                  // Field available:Z
       4: ireturn

  public void customAfterPost(java.lang.Object);
    Code:
       0: return

  public org.apache.dubbo.rpc.model.ApplicationModel getSource();
    Code:
       0: aload_0
       1: getfield      #8                  // Field source:Lorg/apache/dubbo/rpc/model/ApplicationModel;
       4: areturn

  public java.lang.String appName();
    Code:
       0: aload_0
       1: invokevirtual #14                 // Method getSource:()Lorg/apache/dubbo/rpc/model/ApplicationModel;
       4: invokevirtual #15                 // Method org/apache/dubbo/rpc/model/ApplicationModel.getApplicationName:()Ljava/lang/String;
       7: areturn

  public org.apache.dubbo.metrics.model.key.TypeWrapper getTypeWrapper();
    Code:
       0: aload_0
       1: getfield      #6                  // Field typeWrapper:Lorg/apache/dubbo/metrics/model/key/TypeWrapper;
       4: areturn

  public boolean isAssignableFrom(java.lang.Object);
    Code:
       0: aload_0
       1: getfield      #6                  // Field typeWrapper:Lorg/apache/dubbo/metrics/model/key/TypeWrapper;
       4: aload_1
       5: invokevirtual #16                 // Method org/apache/dubbo/metrics/model/key/TypeWrapper.isAssignableFrom:(Ljava/lang/Object;)Z
       8: ireturn

  public java.lang.String toString();
    Code:
       0: new           #17                 // class java/lang/StringBuilder
       3: dup
       4: invokespecial #18                 // Method java/lang/StringBuilder."<init>":()V
       7: aload_0
       8: invokevirtual #19                 // Method java/lang/Object.getClass:()Ljava/lang/Class;
      11: invokevirtual #20                 // Method java/lang/Class.getName:()Ljava/lang/String;
      14: invokevirtual #21                 // Method java/lang/StringBuilder.append:(Ljava/lang/String;)Ljava/lang/StringBuilder;
      17: ldc           #22                 // String [source=
      19: invokevirtual #21                 // Method java/lang/StringBuilder.append:(Ljava/lang/String;)Ljava/lang/StringBuilder;
      22: aload_0
      23: getfield      #8                  // Field source:Lorg/apache/dubbo/rpc/model/ApplicationModel;
      26: invokevirtual #23                 // Method java/lang/StringBuilder.append:(Ljava/lang/Object;)Ljava/lang/StringBuilder;
      29: ldc           #24                 // String ]
      31: invokevirtual #21                 // Method java/lang/StringBuilder.append:(Ljava/lang/String;)Ljava/lang/StringBuilder;
      34: invokevirtual #25                 // Method java/lang/StringBuilder.toString:()Ljava/lang/String;
      37: areturn
}
