Compiled from "MetricsEvent.java"
public final class org.apache.dubbo.metrics.event.MetricsEvent$Type extends java.lang.Enum<org.apache.dubbo.metrics.event.MetricsEvent$Type> {
  public static final org.apache.dubbo.metrics.event.MetricsEvent$Type TOTAL;

  public static final org.apache.dubbo.metrics.event.MetricsEvent$Type SUCCEED;

  public static final org.apache.dubbo.metrics.event.MetricsEvent$Type BUSINESS_FAILED;

  public static final org.apache.dubbo.metrics.event.MetricsEvent$Type REQUEST_TIMEOUT;

  public static final org.apache.dubbo.metrics.event.MetricsEvent$Type REQUEST_LIMIT;

  public static final org.apache.dubbo.metrics.event.MetricsEvent$Type PROCESSING;

  public static final org.apache.dubbo.metrics.event.MetricsEvent$Type UNKNOWN_FAILED;

  public static final org.apache.dubbo.metrics.event.MetricsEvent$Type TOTAL_FAILED;

  public static final org.apache.dubbo.metrics.event.MetricsEvent$Type APPLICATION_INFO;

  public static final org.apache.dubbo.metrics.event.MetricsEvent$Type NETWORK_EXCEPTION;

  public static final org.apache.dubbo.metrics.event.MetricsEvent$Type SERVICE_UNAVAILABLE;

  public static final org.apache.dubbo.metrics.event.MetricsEvent$Type CODEC_EXCEPTION;

  public static final org.apache.dubbo.metrics.event.MetricsEvent$Type NO_INVOKER_AVAILABLE;

  private final java.lang.String name;

  private static final org.apache.dubbo.metrics.event.MetricsEvent$Type[] $VALUES;

  public static org.apache.dubbo.metrics.event.MetricsEvent$Type[] values();
    Code:
       0: getstatic     #1                  // Field $VALUES:[Lorg/apache/dubbo/metrics/event/MetricsEvent$Type;
       3: invokevirtual #2                  // Method "[Lorg/apache/dubbo/metrics/event/MetricsEvent$Type;".clone:()Ljava/lang/Object;
       6: checkcast     #3                  // class "[Lorg/apache/dubbo/metrics/event/MetricsEvent$Type;"
       9: areturn

  public static org.apache.dubbo.metrics.event.MetricsEvent$Type valueOf(java.lang.String);
    Code:
       0: ldc           #4                  // class org/apache/dubbo/metrics/event/MetricsEvent$Type
       2: aload_0
       3: invokestatic  #5                  // Method java/lang/Enum.valueOf:(Ljava/lang/Class;Ljava/lang/String;)Ljava/lang/Enum;
       6: checkcast     #4                  // class org/apache/dubbo/metrics/event/MetricsEvent$Type
       9: areturn

  public final java.lang.String getName();
    Code:
       0: aload_0
       1: getfield      #6                  // Field name:Ljava/lang/String;
       4: areturn

  public final java.lang.String getNameByType(java.lang.String);
    Code:
       0: aload_0
       1: getfield      #6                  // Field name:Ljava/lang/String;
       4: iconst_1
       5: anewarray     #7                  // class java/lang/Object
       8: dup
       9: iconst_0
      10: aload_1
      11: aastore
      12: invokestatic  #8                  // Method java/lang/String.format:(Ljava/lang/String;[Ljava/lang/Object;)Ljava/lang/String;
      15: areturn

  private org.apache.dubbo.metrics.event.MetricsEvent$Type(java.lang.String);
    Code:
       0: aload_0
       1: aload_1
       2: iload_2
       3: invokespecial #9                  // Method java/lang/Enum."<init>":(Ljava/lang/String;I)V
       6: aload_0
       7: aload_3
       8: putfield      #6                  // Field name:Ljava/lang/String;
      11: return

  static {};
    Code:
       0: new           #4                  // class org/apache/dubbo/metrics/event/MetricsEvent$Type
       3: dup
       4: ldc           #10                 // String TOTAL
       6: iconst_0
       7: ldc           #11                 // String TOTAL_%s
       9: invokespecial #12                 // Method "<init>":(Ljava/lang/String;ILjava/lang/String;)V
      12: putstatic     #13                 // Field TOTAL:Lorg/apache/dubbo/metrics/event/MetricsEvent$Type;
      15: new           #4                  // class org/apache/dubbo/metrics/event/MetricsEvent$Type
      18: dup
      19: ldc           #14                 // String SUCCEED
      21: iconst_1
      22: ldc           #15                 // String SUCCEED_%s
      24: invokespecial #12                 // Method "<init>":(Ljava/lang/String;ILjava/lang/String;)V
      27: putstatic     #16                 // Field SUCCEED:Lorg/apache/dubbo/metrics/event/MetricsEvent$Type;
      30: new           #4                  // class org/apache/dubbo/metrics/event/MetricsEvent$Type
      33: dup
      34: ldc           #17                 // String BUSINESS_FAILED
      36: iconst_2
      37: ldc           #18                 // String BUSINESS_FAILED_%s
      39: invokespecial #12                 // Method "<init>":(Ljava/lang/String;ILjava/lang/String;)V
      42: putstatic     #19                 // Field BUSINESS_FAILED:Lorg/apache/dubbo/metrics/event/MetricsEvent$Type;
      45: new           #4                  // class org/apache/dubbo/metrics/event/MetricsEvent$Type
      48: dup
      49: ldc           #20                 // String REQUEST_TIMEOUT
      51: iconst_3
      52: ldc           #21                 // String REQUEST_TIMEOUT_%s
      54: invokespecial #12                 // Method "<init>":(Ljava/lang/String;ILjava/lang/String;)V
      57: putstatic     #22                 // Field REQUEST_TIMEOUT:Lorg/apache/dubbo/metrics/event/MetricsEvent$Type;
      60: new           #4                  // class org/apache/dubbo/metrics/event/MetricsEvent$Type
      63: dup
      64: ldc           #23                 // String REQUEST_LIMIT
      66: iconst_4
      67: ldc           #24                 // String REQUEST_LIMIT_%s
      69: invokespecial #12                 // Method "<init>":(Ljava/lang/String;ILjava/lang/String;)V
      72: putstatic     #25                 // Field REQUEST_LIMIT:Lorg/apache/dubbo/metrics/event/MetricsEvent$Type;
      75: new           #4                  // class org/apache/dubbo/metrics/event/MetricsEvent$Type
      78: dup
      79: ldc           #26                 // String PROCESSING
      81: iconst_5
      82: ldc           #27                 // String PROCESSING_%s
      84: invokespecial #12                 // Method "<init>":(Ljava/lang/String;ILjava/lang/String;)V
      87: putstatic     #28                 // Field PROCESSING:Lorg/apache/dubbo/metrics/event/MetricsEvent$Type;
      90: new           #4                  // class org/apache/dubbo/metrics/event/MetricsEvent$Type
      93: dup
      94: ldc           #29                 // String UNKNOWN_FAILED
      96: bipush        6
      98: ldc           #30                 // String UNKNOWN_FAILED_%s
     100: invokespecial #12                 // Method "<init>":(Ljava/lang/String;ILjava/lang/String;)V
     103: putstatic     #31                 // Field UNKNOWN_FAILED:Lorg/apache/dubbo/metrics/event/MetricsEvent$Type;
     106: new           #4                  // class org/apache/dubbo/metrics/event/MetricsEvent$Type
     109: dup
     110: ldc           #32                 // String TOTAL_FAILED
     112: bipush        7
     114: ldc           #33                 // String TOTAL_FAILED_%s
     116: invokespecial #12                 // Method "<init>":(Ljava/lang/String;ILjava/lang/String;)V
     119: putstatic     #34                 // Field TOTAL_FAILED:Lorg/apache/dubbo/metrics/event/MetricsEvent$Type;
     122: new           #4                  // class org/apache/dubbo/metrics/event/MetricsEvent$Type
     125: dup
     126: ldc           #35                 // String APPLICATION_INFO
     128: bipush        8
     130: ldc           #36                 // String APPLICATION_INFO_%s
     132: invokespecial #12                 // Method "<init>":(Ljava/lang/String;ILjava/lang/String;)V
     135: putstatic     #37                 // Field APPLICATION_INFO:Lorg/apache/dubbo/metrics/event/MetricsEvent$Type;
     138: new           #4                  // class org/apache/dubbo/metrics/event/MetricsEvent$Type
     141: dup
     142: ldc           #38                 // String NETWORK_EXCEPTION
     144: bipush        9
     146: ldc           #39                 // String NETWORK_EXCEPTION_%s
     148: invokespecial #12                 // Method "<init>":(Ljava/lang/String;ILjava/lang/String;)V
     151: putstatic     #40                 // Field NETWORK_EXCEPTION:Lorg/apache/dubbo/metrics/event/MetricsEvent$Type;
     154: new           #4                  // class org/apache/dubbo/metrics/event/MetricsEvent$Type
     157: dup
     158: ldc           #41                 // String SERVICE_UNAVAILABLE
     160: bipush        10
     162: ldc           #42                 // String SERVICE_UNAVAILABLE_%s
     164: invokespecial #12                 // Method "<init>":(Ljava/lang/String;ILjava/lang/String;)V
     167: putstatic     #43                 // Field SERVICE_UNAVAILABLE:Lorg/apache/dubbo/metrics/event/MetricsEvent$Type;
     170: new           #4                  // class org/apache/dubbo/metrics/event/MetricsEvent$Type
     173: dup
     174: ldc           #44                 // String CODEC_EXCEPTION
     176: bipush        11
     178: ldc           #45                 // String CODEC_EXCEPTION_%s
     180: invokespecial #12                 // Method "<init>":(Ljava/lang/String;ILjava/lang/String;)V
     183: putstatic     #46                 // Field CODEC_EXCEPTION:Lorg/apache/dubbo/metrics/event/MetricsEvent$Type;
     186: new           #4                  // class org/apache/dubbo/metrics/event/MetricsEvent$Type
     189: dup
     190: ldc           #47                 // String NO_INVOKER_AVAILABLE
     192: bipush        12
     194: ldc           #48                 // String NO_INVOKER_AVAILABLE_%s
     196: invokespecial #12                 // Method "<init>":(Ljava/lang/String;ILjava/lang/String;)V
     199: putstatic     #49                 // Field NO_INVOKER_AVAILABLE:Lorg/apache/dubbo/metrics/event/MetricsEvent$Type;
     202: bipush        13
     204: anewarray     #4                  // class org/apache/dubbo/metrics/event/MetricsEvent$Type
     207: dup
     208: iconst_0
     209: getstatic     #13                 // Field TOTAL:Lorg/apache/dubbo/metrics/event/MetricsEvent$Type;
     212: aastore
     213: dup
     214: iconst_1
     215: getstatic     #16                 // Field SUCCEED:Lorg/apache/dubbo/metrics/event/MetricsEvent$Type;
     218: aastore
     219: dup
     220: iconst_2
     221: getstatic     #19                 // Field BUSINESS_FAILED:Lorg/apache/dubbo/metrics/event/MetricsEvent$Type;
     224: aastore
     225: dup
     226: iconst_3
     227: getstatic     #22                 // Field REQUEST_TIMEOUT:Lorg/apache/dubbo/metrics/event/MetricsEvent$Type;
     230: aastore
     231: dup
     232: iconst_4
     233: getstatic     #25                 // Field REQUEST_LIMIT:Lorg/apache/dubbo/metrics/event/MetricsEvent$Type;
     236: aastore
     237: dup
     238: iconst_5
     239: getstatic     #28                 // Field PROCESSING:Lorg/apache/dubbo/metrics/event/MetricsEvent$Type;
     242: aastore
     243: dup
     244: bipush        6
     246: getstatic     #31                 // Field UNKNOWN_FAILED:Lorg/apache/dubbo/metrics/event/MetricsEvent$Type;
     249: aastore
     250: dup
     251: bipush        7
     253: getstatic     #34                 // Field TOTAL_FAILED:Lorg/apache/dubbo/metrics/event/MetricsEvent$Type;
     256: aastore
     257: dup
     258: bipush        8
     260: getstatic     #37                 // Field APPLICATION_INFO:Lorg/apache/dubbo/metrics/event/MetricsEvent$Type;
     263: aastore
     264: dup
     265: bipush        9
     267: getstatic     #40                 // Field NETWORK_EXCEPTION:Lorg/apache/dubbo/metrics/event/MetricsEvent$Type;
     270: aastore
     271: dup
     272: bipush        10
     274: getstatic     #43                 // Field SERVICE_UNAVAILABLE:Lorg/apache/dubbo/metrics/event/MetricsEvent$Type;
     277: aastore
     278: dup
     279: bipush        11
     281: getstatic     #46                 // Field CODEC_EXCEPTION:Lorg/apache/dubbo/metrics/event/MetricsEvent$Type;
     284: aastore
     285: dup
     286: bipush        12
     288: getstatic     #49                 // Field NO_INVOKER_AVAILABLE:Lorg/apache/dubbo/metrics/event/MetricsEvent$Type;
     291: aastore
     292: putstatic     #1                  // Field $VALUES:[Lorg/apache/dubbo/metrics/event/MetricsEvent$Type;
     295: return
}
