Compiled from "RequestBeforeEvent.java"
public class org.apache.dubbo.metrics.event.RequestBeforeEvent extends org.apache.dubbo.metrics.event.TimeCounterEvent {
  public org.apache.dubbo.metrics.event.RequestBeforeEvent(org.apache.dubbo.rpc.model.ApplicationModel, org.apache.dubbo.metrics.model.key.TypeWrapper);
    Code:
       0: aload_0
       1: aload_1
       2: aload_2
       3: invokespecial #2                  // Method org/apache/dubbo/metrics/event/TimeCounterEvent."<init>":(Lorg/apache/dubbo/rpc/model/ApplicationModel;Lorg/apache/dubbo/metrics/model/key/TypeWrapper;)V
       6: return

  public static org.apache.dubbo.metrics.event.RequestBeforeEvent toEvent(org.apache.dubbo.rpc.model.ApplicationModel, org.apache.dubbo.rpc.Invocation);
    Code:
       0: new           #3                  // class org/apache/dubbo/metrics/event/RequestBeforeEvent
       3: dup
       4: aload_0
       5: new           #4                  // class org/apache/dubbo/metrics/model/key/TypeWrapper
       8: dup
       9: getstatic     #5                  // Field org/apache/dubbo/metrics/model/key/MetricsLevel.METHOD:Lorg/apache/dubbo/metrics/model/key/MetricsLevel;
      12: getstatic     #6                  // Field org/apache/dubbo/metrics/model/key/MetricsKey.METRIC_REQUESTS:Lorg/apache/dubbo/metrics/model/key/MetricsKey;
      15: invokespecial #7                  // Method org/apache/dubbo/metrics/model/key/TypeWrapper."<init>":(Lorg/apache/dubbo/metrics/model/key/MetricsLevel;Lorg/apache/dubbo/metrics/model/key/MetricsKey;)V
      18: invokespecial #8                  // Method "<init>":(Lorg/apache/dubbo/rpc/model/ApplicationModel;Lorg/apache/dubbo/metrics/model/key/TypeWrapper;)V
      21: astore_2
      22: aload_2
      23: ldc           #9                  // String serviceKey
      25: aload_1
      26: invokestatic  #10                 // Method org/apache/dubbo/metrics/model/MetricsSupport.getInterfaceName:(Lorg/apache/dubbo/rpc/Invocation;)Ljava/lang/String;
      29: invokevirtual #11                 // Method putAttachment:(Ljava/lang/String;Ljava/lang/Object;)V
      32: aload_2
      33: ldc           #12                 // String metric_filter_side
      35: aload_1
      36: invokestatic  #13                 // Method org/apache/dubbo/metrics/model/MetricsSupport.getSide:(Lorg/apache/dubbo/rpc/Invocation;)Ljava/lang/String;
      39: invokevirtual #11                 // Method putAttachment:(Ljava/lang/String;Ljava/lang/Object;)V
      42: aload_2
      43: ldc           #14                 // String metric_filter_invocation
      45: aload_1
      46: invokevirtual #11                 // Method putAttachment:(Ljava/lang/String;Ljava/lang/Object;)V
      49: aload_2
      50: areturn
}
