Compiled from "RequestEvent.java"
final class org.apache.dubbo.metrics.event.RequestEvent$1 extends org.apache.dubbo.metrics.event.RequestEvent {
  org.apache.dubbo.metrics.event.RequestEvent$1(org.apache.dubbo.rpc.model.ApplicationModel, org.apache.dubbo.metrics.model.key.TypeWrapper);
    Code:
       0: aload_0
       1: aload_1
       2: aload_2
       3: invokespecial #2                  // Method org/apache/dubbo/metrics/event/RequestEvent."<init>":(Lorg/apache/dubbo/rpc/model/ApplicationModel;Lorg/apache/dubbo/metrics/model/key/TypeWrapper;)V
       6: return

  public void customAfterPost(java.lang.Object);
    Code:
       0: aload_1
       1: ifnonnull     5
       4: return
       5: aload_1
       6: instanceof    #3                  // class org/apache/dubbo/rpc/Result
       9: ifne          45
      12: new           #4                  // class org/apache/dubbo/metrics/exception/MetricsNeverHappenException
      15: dup
      16: new           #5                  // class java/lang/StringBuilder
      19: dup
      20: invokespecial #6                  // Method java/lang/StringBuilder."<init>":()V
      23: ldc           #7                  // String Result type error, postResult:
      25: invokevirtual #8                  // Method java/lang/StringBuilder.append:(Ljava/lang/String;)Ljava/lang/StringBuilder;
      28: aload_1
      29: invokevirtual #9                  // Method java/lang/Object.getClass:()Ljava/lang/Class;
      32: invokevirtual #10                 // Method java/lang/Class.getName:()Ljava/lang/String;
      35: invokevirtual #8                  // Method java/lang/StringBuilder.append:(Ljava/lang/String;)Ljava/lang/StringBuilder;
      38: invokevirtual #11                 // Method java/lang/StringBuilder.toString:()Ljava/lang/String;
      41: invokespecial #12                 // Method org/apache/dubbo/metrics/exception/MetricsNeverHappenException."<init>":(Ljava/lang/String;)V
      44: athrow
      45: aload_0
      46: ldc           #13                 // String metric_filter_throwable
      48: aload_1
      49: checkcast     #3                  // class org/apache/dubbo/rpc/Result
      52: invokeinterface #14,  1           // InterfaceMethod org/apache/dubbo/rpc/Result.getException:()Ljava/lang/Throwable;
      57: invokespecial #15                 // Method org/apache/dubbo/metrics/event/RequestEvent.putAttachment:(Ljava/lang/String;Ljava/lang/Object;)V
      60: return
}
