Compiled from "TimeCounterEvent.java"
public abstract class org.apache.dubbo.metrics.event.TimeCounterEvent extends org.apache.dubbo.metrics.event.MetricsEvent {
  private final org.apache.dubbo.metrics.model.TimePair timePair;

  public org.apache.dubbo.metrics.event.TimeCounterEvent(org.apache.dubbo.rpc.model.ApplicationModel, org.apache.dubbo.metrics.model.key.TypeWrapper);
    Code:
       0: aload_0
       1: aload_1
       2: aload_2
       3: invokespecial #1                  // Method org/apache/dubbo/metrics/event/MetricsEvent."<init>":(Lorg/apache/dubbo/rpc/model/ApplicationModel;Lorg/apache/dubbo/metrics/model/key/TypeWrapper;)V
       6: aload_0
       7: invokestatic  #2                  // Method org/apache/dubbo/metrics/model/TimePair.start:()Lorg/apache/dubbo/metrics/model/TimePair;
      10: putfield      #3                  // Field timePair:Lorg/apache/dubbo/metrics/model/TimePair;
      13: return

  public org.apache.dubbo.metrics.model.TimePair getTimePair();
    Code:
       0: aload_0
       1: getfield      #3                  // Field timePair:Lorg/apache/dubbo/metrics/model/TimePair;
       4: areturn
}
