Compiled from "CommandContext.java"
public class org.apache.dubbo.qos.api.CommandContext {
  private java.lang.String commandName;

  private java.lang.String[] args;

  private io.netty.channel.Channel remote;

  private boolean isHttp;

  private java.lang.Object originRequest;

  private int httpCode;

  private org.apache.dubbo.qos.api.QosConfiguration qosConfiguration;

  public org.apache.dubbo.qos.api.CommandContext(java.lang.String);
    Code:
       0: aload_0
       1: invokespecial #1                  // Method java/lang/Object."<init>":()V
       4: aload_0
       5: sipush        200
       8: putfield      #2                  // Field httpCode:I
      11: aload_0
      12: aload_1
      13: putfield      #3                  // Field commandName:Ljava/lang/String;
      16: return

  public org.apache.dubbo.qos.api.CommandContext(java.lang.String, java.lang.String[], boolean);
    Code:
       0: aload_0
       1: invokespecial #1                  // Method java/lang/Object."<init>":()V
       4: aload_0
       5: sipush        200
       8: putfield      #2                  // Field httpCode:I
      11: aload_0
      12: aload_1
      13: putfield      #3                  // Field commandName:Ljava/lang/String;
      16: aload_0
      17: aload_2
      18: putfield      #4                  // Field args:[Ljava/lang/String;
      21: aload_0
      22: iload_3
      23: putfield      #5                  // Field isHttp:Z
      26: return

  public java.lang.String getCommandName();
    Code:
       0: aload_0
       1: getfield      #3                  // Field commandName:Ljava/lang/String;
       4: areturn

  public void setCommandName(java.lang.String);
    Code:
       0: aload_0
       1: aload_1
       2: putfield      #3                  // Field commandName:Ljava/lang/String;
       5: return

  public java.lang.String[] getArgs();
    Code:
       0: aload_0
       1: getfield      #4                  // Field args:[Ljava/lang/String;
       4: areturn

  public void setArgs(java.lang.String[]);
    Code:
       0: aload_0
       1: aload_1
       2: putfield      #4                  // Field args:[Ljava/lang/String;
       5: return

  public io.netty.channel.Channel getRemote();
    Code:
       0: aload_0
       1: getfield      #6                  // Field remote:Lio/netty/channel/Channel;
       4: areturn

  public void setRemote(io.netty.channel.Channel);
    Code:
       0: aload_0
       1: aload_1
       2: putfield      #6                  // Field remote:Lio/netty/channel/Channel;
       5: return

  public boolean isHttp();
    Code:
       0: aload_0
       1: getfield      #5                  // Field isHttp:Z
       4: ireturn

  public void setHttp(boolean);
    Code:
       0: aload_0
       1: iload_1
       2: putfield      #5                  // Field isHttp:Z
       5: return

  public java.lang.Object getOriginRequest();
    Code:
       0: aload_0
       1: getfield      #7                  // Field originRequest:Ljava/lang/Object;
       4: areturn

  public void setOriginRequest(java.lang.Object);
    Code:
       0: aload_0
       1: aload_1
       2: putfield      #7                  // Field originRequest:Ljava/lang/Object;
       5: return

  public int getHttpCode();
    Code:
       0: aload_0
       1: getfield      #2                  // Field httpCode:I
       4: ireturn

  public void setHttpCode(int);
    Code:
       0: aload_0
       1: iload_1
       2: putfield      #2                  // Field httpCode:I
       5: return

  public void setQosConfiguration(org.apache.dubbo.qos.api.QosConfiguration);
    Code:
       0: aload_0
       1: aload_1
       2: putfield      #8                  // Field qosConfiguration:Lorg/apache/dubbo/qos/api/QosConfiguration;
       5: return

  public org.apache.dubbo.qos.api.QosConfiguration getQosConfiguration();
    Code:
       0: aload_0
       1: getfield      #8                  // Field qosConfiguration:Lorg/apache/dubbo/qos/api/QosConfiguration;
       4: areturn

  public boolean isAllowAnonymousAccess();
    Code:
       0: aload_0
       1: getfield      #8                  // Field qosConfiguration:Lorg/apache/dubbo/qos/api/QosConfiguration;
       4: invokevirtual #9                  // Method org/apache/dubbo/qos/api/QosConfiguration.isAllowAnonymousAccess:()Z
       7: ireturn
}
