Compiled from "PermissionLevel.java"
public final class org.apache.dubbo.qos.api.PermissionLevel extends java.lang.Enum<org.apache.dubbo.qos.api.PermissionLevel> {
  public static final org.apache.dubbo.qos.api.PermissionLevel PUBLIC;

  public static final org.apache.dubbo.qos.api.PermissionLevel PROTECTED;

  public static final org.apache.dubbo.qos.api.PermissionLevel PRIVATE;

  public static final org.apache.dubbo.qos.api.PermissionLevel NONE;

  private final int level;

  private static final org.apache.dubbo.qos.api.PermissionLevel[] $VALUES;

  public static org.apache.dubbo.qos.api.PermissionLevel[] values();
    Code:
       0: getstatic     #1                  // Field $VALUES:[Lorg/apache/dubbo/qos/api/PermissionLevel;
       3: invokevirtual #2                  // Method "[Lorg/apache/dubbo/qos/api/PermissionLevel;".clone:()Ljava/lang/Object;
       6: checkcast     #3                  // class "[Lorg/apache/dubbo/qos/api/PermissionLevel;"
       9: areturn

  public static org.apache.dubbo.qos.api.PermissionLevel valueOf(java.lang.String);
    Code:
       0: ldc           #4                  // class org/apache/dubbo/qos/api/PermissionLevel
       2: aload_0
       3: invokestatic  #5                  // Method java/lang/Enum.valueOf:(Ljava/lang/Class;Ljava/lang/String;)Ljava/lang/Enum;
       6: checkcast     #4                  // class org/apache/dubbo/qos/api/PermissionLevel
       9: areturn

  private org.apache.dubbo.qos.api.PermissionLevel(int);
    Code:
       0: aload_0
       1: aload_1
       2: iload_2
       3: invokespecial #6                  // Method java/lang/Enum."<init>":(Ljava/lang/String;I)V
       6: aload_0
       7: iload_3
       8: putfield      #7                  // Field level:I
      11: return

  public int getLevel();
    Code:
       0: aload_0
       1: getfield      #7                  // Field level:I
       4: ireturn

  public static org.apache.dubbo.qos.api.PermissionLevel from(java.lang.String);
    Code:
       0: aload_0
       1: invokestatic  #8                  // Method org/apache/dubbo/common/utils/StringUtils.isNumber:(Ljava/lang/String;)Z
       4: ifeq          39
       7: invokestatic  #9                  // Method values:()[Lorg/apache/dubbo/qos/api/PermissionLevel;
      10: invokestatic  #10                 // Method java/util/Arrays.stream:([Ljava/lang/Object;)Ljava/util/stream/Stream;
      13: aload_0
      14: invokedynamic #11,  0             // InvokeDynamic #0:test:(Ljava/lang/String;)Ljava/util/function/Predicate;
      19: invokeinterface #12,  2           // InterfaceMethod java/util/stream/Stream.filter:(Ljava/util/function/Predicate;)Ljava/util/stream/Stream;
      24: invokeinterface #13,  1           // InterfaceMethod java/util/stream/Stream.findFirst:()Ljava/util/Optional;
      29: getstatic     #14                 // Field PUBLIC:Lorg/apache/dubbo/qos/api/PermissionLevel;
      32: invokevirtual #15                 // Method java/util/Optional.orElse:(Ljava/lang/Object;)Ljava/lang/Object;
      35: checkcast     #4                  // class org/apache/dubbo/qos/api/PermissionLevel
      38: areturn
      39: invokestatic  #9                  // Method values:()[Lorg/apache/dubbo/qos/api/PermissionLevel;
      42: invokestatic  #10                 // Method java/util/Arrays.stream:([Ljava/lang/Object;)Ljava/util/stream/Stream;
      45: aload_0
      46: invokedynamic #16,  0             // InvokeDynamic #1:test:(Ljava/lang/String;)Ljava/util/function/Predicate;
      51: invokeinterface #12,  2           // InterfaceMethod java/util/stream/Stream.filter:(Ljava/util/function/Predicate;)Ljava/util/stream/Stream;
      56: invokeinterface #13,  1           // InterfaceMethod java/util/stream/Stream.findFirst:()Ljava/util/Optional;
      61: getstatic     #14                 // Field PUBLIC:Lorg/apache/dubbo/qos/api/PermissionLevel;
      64: invokevirtual #15                 // Method java/util/Optional.orElse:(Ljava/lang/Object;)Ljava/lang/Object;
      67: checkcast     #4                  // class org/apache/dubbo/qos/api/PermissionLevel
      70: areturn

  private static boolean lambda$from$1(java.lang.String, org.apache.dubbo.qos.api.PermissionLevel);
    Code:
       0: aload_1
       1: invokevirtual #17                 // Method name:()Ljava/lang/String;
       4: aload_0
       5: invokestatic  #18                 // Method java/lang/String.valueOf:(Ljava/lang/Object;)Ljava/lang/String;
       8: invokevirtual #19                 // Method java/lang/String.trim:()Ljava/lang/String;
      11: invokevirtual #20                 // Method java/lang/String.equalsIgnoreCase:(Ljava/lang/String;)Z
      14: ireturn

  private static boolean lambda$from$0(java.lang.String, org.apache.dubbo.qos.api.PermissionLevel);
    Code:
       0: aload_1
       1: invokevirtual #21                 // Method getLevel:()I
       4: invokestatic  #22                 // Method java/lang/String.valueOf:(I)Ljava/lang/String;
       7: aload_0
       8: invokevirtual #19                 // Method java/lang/String.trim:()Ljava/lang/String;
      11: invokevirtual #23                 // Method java/lang/String.equals:(Ljava/lang/Object;)Z
      14: ireturn

  static {};
    Code:
       0: new           #4                  // class org/apache/dubbo/qos/api/PermissionLevel
       3: dup
       4: ldc           #24                 // String PUBLIC
       6: iconst_0
       7: iconst_1
       8: invokespecial #25                 // Method "<init>":(Ljava/lang/String;II)V
      11: putstatic     #14                 // Field PUBLIC:Lorg/apache/dubbo/qos/api/PermissionLevel;
      14: new           #4                  // class org/apache/dubbo/qos/api/PermissionLevel
      17: dup
      18: ldc           #26                 // String PROTECTED
      20: iconst_1
      21: iconst_2
      22: invokespecial #25                 // Method "<init>":(Ljava/lang/String;II)V
      25: putstatic     #27                 // Field PROTECTED:Lorg/apache/dubbo/qos/api/PermissionLevel;
      28: new           #4                  // class org/apache/dubbo/qos/api/PermissionLevel
      31: dup
      32: ldc           #28                 // String PRIVATE
      34: iconst_2
      35: iconst_3
      36: invokespecial #25                 // Method "<init>":(Ljava/lang/String;II)V
      39: putstatic     #29                 // Field PRIVATE:Lorg/apache/dubbo/qos/api/PermissionLevel;
      42: new           #4                  // class org/apache/dubbo/qos/api/PermissionLevel
      45: dup
      46: ldc           #30                 // String NONE
      48: iconst_3
      49: ldc           #32                 // int -2147483648
      51: invokespecial #25                 // Method "<init>":(Ljava/lang/String;II)V
      54: putstatic     #33                 // Field NONE:Lorg/apache/dubbo/qos/api/PermissionLevel;
      57: iconst_4
      58: anewarray     #4                  // class org/apache/dubbo/qos/api/PermissionLevel
      61: dup
      62: iconst_0
      63: getstatic     #14                 // Field PUBLIC:Lorg/apache/dubbo/qos/api/PermissionLevel;
      66: aastore
      67: dup
      68: iconst_1
      69: getstatic     #27                 // Field PROTECTED:Lorg/apache/dubbo/qos/api/PermissionLevel;
      72: aastore
      73: dup
      74: iconst_2
      75: getstatic     #29                 // Field PRIVATE:Lorg/apache/dubbo/qos/api/PermissionLevel;
      78: aastore
      79: dup
      80: iconst_3
      81: getstatic     #33                 // Field NONE:Lorg/apache/dubbo/qos/api/PermissionLevel;
      84: aastore
      85: putstatic     #1                  // Field $VALUES:[Lorg/apache/dubbo/qos/api/PermissionLevel;
      88: return
}
