Compiled from "QosConfiguration.java"
public class org.apache.dubbo.qos.api.QosConfiguration$Builder {
  private java.lang.String welcome;

  private boolean acceptForeignIp;

  private java.lang.String acceptForeignIpWhitelist;

  private org.apache.dubbo.qos.api.PermissionLevel anonymousAccessPermissionLevel;

  private java.lang.String anonymousAllowCommands;

  private org.apache.dubbo.qos.api.QosConfiguration$Builder();
    Code:
       0: aload_0
       1: invokespecial #2                  // Method java/lang/Object."<init>":()V
       4: aload_0
       5: getstatic     #3                  // Field org/apache/dubbo/qos/api/PermissionLevel.PUBLIC:Lorg/apache/dubbo/qos/api/PermissionLevel;
       8: putfield      #4                  // Field anonymousAccessPermissionLevel:Lorg/apache/dubbo/qos/api/PermissionLevel;
      11: return

  public org.apache.dubbo.qos.api.QosConfiguration$Builder welcome(java.lang.String);
    Code:
       0: aload_0
       1: aload_1
       2: putfield      #5                  // Field welcome:Ljava/lang/String;
       5: aload_0
       6: areturn

  public org.apache.dubbo.qos.api.QosConfiguration$Builder acceptForeignIp(boolean);
    Code:
       0: aload_0
       1: iload_1
       2: putfield      #6                  // Field acceptForeignIp:Z
       5: aload_0
       6: areturn

  public org.apache.dubbo.qos.api.QosConfiguration$Builder acceptForeignIpWhitelist(java.lang.String);
    Code:
       0: aload_0
       1: aload_1
       2: putfield      #7                  // Field acceptForeignIpWhitelist:Ljava/lang/String;
       5: aload_0
       6: areturn

  public org.apache.dubbo.qos.api.QosConfiguration$Builder anonymousAccessPermissionLevel(java.lang.String);
    Code:
       0: aload_0
       1: aload_1
       2: invokestatic  #8                  // Method org/apache/dubbo/qos/api/PermissionLevel.from:(Ljava/lang/String;)Lorg/apache/dubbo/qos/api/PermissionLevel;
       5: putfield      #4                  // Field anonymousAccessPermissionLevel:Lorg/apache/dubbo/qos/api/PermissionLevel;
       8: aload_0
       9: areturn

  public org.apache.dubbo.qos.api.QosConfiguration$Builder anonymousAllowCommands(java.lang.String);
    Code:
       0: aload_0
       1: aload_1
       2: putfield      #9                  // Field anonymousAllowCommands:Ljava/lang/String;
       5: aload_0
       6: areturn

  public org.apache.dubbo.qos.api.QosConfiguration build();
    Code:
       0: new           #10                 // class org/apache/dubbo/qos/api/QosConfiguration
       3: dup
       4: aload_0
       5: invokespecial #11                 // Method org/apache/dubbo/qos/api/QosConfiguration."<init>":(Lorg/apache/dubbo/qos/api/QosConfiguration$Builder;)V
       8: areturn

  public java.lang.String getWelcome();
    Code:
       0: aload_0
       1: getfield      #5                  // Field welcome:Ljava/lang/String;
       4: areturn

  public boolean isAcceptForeignIp();
    Code:
       0: aload_0
       1: getfield      #6                  // Field acceptForeignIp:Z
       4: ireturn

  public java.lang.String getAcceptForeignIpWhitelist();
    Code:
       0: aload_0
       1: getfield      #7                  // Field acceptForeignIpWhitelist:Ljava/lang/String;
       4: areturn

  public org.apache.dubbo.qos.api.PermissionLevel getAnonymousAccessPermissionLevel();
    Code:
       0: aload_0
       1: getfield      #4                  // Field anonymousAccessPermissionLevel:Lorg/apache/dubbo/qos/api/PermissionLevel;
       4: areturn

  public java.lang.String getAnonymousAllowCommands();
    Code:
       0: aload_0
       1: getfield      #9                  // Field anonymousAllowCommands:Ljava/lang/String;
       4: areturn

  org.apache.dubbo.qos.api.QosConfiguration$Builder(org.apache.dubbo.qos.api.QosConfiguration$1);
    Code:
       0: aload_0
       1: invokespecial #1                  // Method "<init>":()V
       4: return
}
