Compiled from "BufferedStartupStep.java"
class org.springframework.boot.context.metrics.buffering.BufferedStartupStep implements org.springframework.core.metrics.StartupStep {
  private final java.lang.String name;

  private final long id;

  private final org.springframework.boot.context.metrics.buffering.BufferedStartupStep parent;

  private final java.util.List<org.springframework.core.metrics.StartupStep$Tag> tags;

  private final java.util.function.Consumer<org.springframework.boot.context.metrics.buffering.BufferedStartupStep> recorder;

  private final java.time.Instant startTime;

  private final java.util.concurrent.atomic.AtomicBoolean ended;

  org.springframework.boot.context.metrics.buffering.BufferedStartupStep(org.springframework.boot.context.metrics.buffering.BufferedStartupStep, java.lang.String, long, java.time.Instant, java.util.function.Consumer<org.springframework.boot.context.metrics.buffering.BufferedStartupStep>);
    Code:
       0: aload_0
       1: invokespecial #1                  // Method java/lang/Object."<init>":()V
       4: aload_0
       5: new           #7                  // class java/util/ArrayList
       8: dup
       9: invokespecial #9                  // Method java/util/ArrayList."<init>":()V
      12: putfield      #10                 // Field tags:Ljava/util/List;
      15: aload_0
      16: new           #16                 // class java/util/concurrent/atomic/AtomicBoolean
      19: dup
      20: invokespecial #18                 // Method java/util/concurrent/atomic/AtomicBoolean."<init>":()V
      23: putfield      #19                 // Field ended:Ljava/util/concurrent/atomic/AtomicBoolean;
      26: aload_0
      27: aload_1
      28: putfield      #23                 // Field parent:Lorg/springframework/boot/context/metrics/buffering/BufferedStartupStep;
      31: aload_0
      32: aload_2
      33: putfield      #27                 // Field name:Ljava/lang/String;
      36: aload_0
      37: lload_3
      38: putfield      #31                 // Field id:J
      41: aload_0
      42: aload         5
      44: putfield      #35                 // Field startTime:Ljava/time/Instant;
      47: aload_0
      48: aload         6
      50: putfield      #39                 // Field recorder:Ljava/util/function/Consumer;
      53: return

  org.springframework.boot.context.metrics.buffering.BufferedStartupStep getParent();
    Code:
       0: aload_0
       1: getfield      #23                 // Field parent:Lorg/springframework/boot/context/metrics/buffering/BufferedStartupStep;
       4: areturn

  public java.lang.String getName();
    Code:
       0: aload_0
       1: getfield      #27                 // Field name:Ljava/lang/String;
       4: areturn

  public long getId();
    Code:
       0: aload_0
       1: getfield      #31                 // Field id:J
       4: lreturn

  java.time.Instant getStartTime();
    Code:
       0: aload_0
       1: getfield      #35                 // Field startTime:Ljava/time/Instant;
       4: areturn

  public java.lang.Long getParentId();
    Code:
       0: aload_0
       1: getfield      #23                 // Field parent:Lorg/springframework/boot/context/metrics/buffering/BufferedStartupStep;
       4: ifnull        20
       7: aload_0
       8: getfield      #23                 // Field parent:Lorg/springframework/boot/context/metrics/buffering/BufferedStartupStep;
      11: invokevirtual #43                 // Method getId:()J
      14: invokestatic  #47                 // Method java/lang/Long.valueOf:(J)Ljava/lang/Long;
      17: goto          21
      20: aconst_null
      21: areturn

  public org.springframework.core.metrics.StartupStep$Tags getTags();
    Code:
       0: aload_0
       1: getfield      #10                 // Field tags:Ljava/util/List;
       4: invokestatic  #53                 // Method java/util/Collections.unmodifiableList:(Ljava/util/List;)Ljava/util/List;
       7: dup
       8: invokestatic  #59                 // Method java/util/Objects.requireNonNull:(Ljava/lang/Object;)Ljava/lang/Object;
      11: pop
      12: invokedynamic #65,  0             // InvokeDynamic #0:iterator:(Ljava/util/List;)Lorg/springframework/core/metrics/StartupStep$Tags;
      17: areturn

  public org.springframework.core.metrics.StartupStep tag(java.lang.String, java.util.function.Supplier<java.lang.String>);
    Code:
       0: aload_0
       1: aload_1
       2: aload_2
       3: invokeinterface #69,  1           // InterfaceMethod java/util/function/Supplier.get:()Ljava/lang/Object;
       8: checkcast     #75                 // class java/lang/String
      11: invokevirtual #77                 // Method tag:(Ljava/lang/String;Ljava/lang/String;)Lorg/springframework/core/metrics/StartupStep;
      14: areturn

  public org.springframework.core.metrics.StartupStep tag(java.lang.String, java.lang.String);
    Code:
       0: aload_0
       1: getfield      #19                 // Field ended:Ljava/util/concurrent/atomic/AtomicBoolean;
       4: invokevirtual #81                 // Method java/util/concurrent/atomic/AtomicBoolean.get:()Z
       7: ifne          14
      10: iconst_1
      11: goto          15
      14: iconst_0
      15: ldc           #84                 // String StartupStep has already ended.
      17: invokestatic  #86                 // Method org/springframework/util/Assert.state:(ZLjava/lang/String;)V
      20: aload_0
      21: getfield      #10                 // Field tags:Ljava/util/List;
      24: new           #92                 // class org/springframework/boot/context/metrics/buffering/BufferedStartupStep$DefaultTag
      27: dup
      28: aload_1
      29: aload_2
      30: invokespecial #94                 // Method org/springframework/boot/context/metrics/buffering/BufferedStartupStep$DefaultTag."<init>":(Ljava/lang/String;Ljava/lang/String;)V
      33: invokeinterface #97,  2           // InterfaceMethod java/util/List.add:(Ljava/lang/Object;)Z
      38: pop
      39: aload_0
      40: areturn

  public void end();
    Code:
       0: aload_0
       1: getfield      #19                 // Field ended:Ljava/util/concurrent/atomic/AtomicBoolean;
       4: iconst_1
       5: invokevirtual #103                // Method java/util/concurrent/atomic/AtomicBoolean.set:(Z)V
       8: aload_0
       9: getfield      #39                 // Field recorder:Ljava/util/function/Consumer;
      12: aload_0
      13: invokeinterface #107,  2          // InterfaceMethod java/util/function/Consumer.accept:(Ljava/lang/Object;)V
      18: return

  boolean isEnded();
    Code:
       0: aload_0
       1: getfield      #19                 // Field ended:Ljava/util/concurrent/atomic/AtomicBoolean;
       4: invokevirtual #81                 // Method java/util/concurrent/atomic/AtomicBoolean.get:()Z
       7: ireturn
}
