Compiled from "BufferedStartupStep.java"
class org.springframework.boot.context.metrics.buffering.BufferedStartupStep$DefaultTag implements org.springframework.core.metrics.StartupStep$Tag {
  private final java.lang.String key;

  private final java.lang.String value;

  org.springframework.boot.context.metrics.buffering.BufferedStartupStep$DefaultTag(java.lang.String, java.lang.String);
    Code:
       0: aload_0
       1: invokespecial #1                  // Method java/lang/Object."<init>":()V
       4: aload_0
       5: aload_1
       6: putfield      #7                  // Field key:Ljava/lang/String;
       9: aload_0
      10: aload_2
      11: putfield      #13                 // Field value:Ljava/lang/String;
      14: return

  public java.lang.String getKey();
    Code:
       0: aload_0
       1: getfield      #7                  // Field key:Ljava/lang/String;
       4: areturn

  public java.lang.String getValue();
    Code:
       0: aload_0
       1: getfield      #13                 // Field value:Ljava/lang/String;
       4: areturn
}
