Compiled from "StartupTimeline.java"
public class org.springframework.boot.context.metrics.buffering.StartupTimeline {
  private final java.time.Instant startTime;

  private final java.util.List<org.springframework.boot.context.metrics.buffering.StartupTimeline$TimelineEvent> events;

  org.springframework.boot.context.metrics.buffering.StartupTimeline(java.time.Instant, java.util.List<org.springframework.boot.context.metrics.buffering.StartupTimeline$TimelineEvent>);
    Code:
       0: aload_0
       1: invokespecial #1                  // Method java/lang/Object."<init>":()V
       4: aload_0
       5: aload_1
       6: putfield      #7                  // Field startTime:Ljava/time/Instant;
       9: aload_0
      10: aload_2
      11: invokestatic  #13                 // Method java/util/Collections.unmodifiableList:(Ljava/util/List;)Ljava/util/List;
      14: putfield      #19                 // Field events:Ljava/util/List;
      17: return

  public java.time.Instant getStartTime();
    Code:
       0: aload_0
       1: getfield      #7                  // Field startTime:Ljava/time/Instant;
       4: areturn

  public java.util.List<org.springframework.boot.context.metrics.buffering.StartupTimeline$TimelineEvent> getEvents();
    Code:
       0: aload_0
       1: getfield      #19                 // Field events:Ljava/util/List;
       4: areturn
}
