Compiled from "StartupTimeline.java"
public class org.springframework.boot.context.metrics.buffering.StartupTimeline$TimelineEvent {
  private final org.springframework.boot.context.metrics.buffering.BufferedStartupStep step;

  private final java.time.Instant endTime;

  private final java.time.Duration duration;

  org.springframework.boot.context.metrics.buffering.StartupTimeline$TimelineEvent(org.springframework.boot.context.metrics.buffering.BufferedStartupStep, java.time.Instant);
    Code:
       0: aload_0
       1: invokespecial #1                  // Method java/lang/Object."<init>":()V
       4: aload_0
       5: aload_1
       6: putfield      #7                  // Field step:Lorg/springframework/boot/context/metrics/buffering/BufferedStartupStep;
       9: aload_0
      10: aload_2
      11: putfield      #13                 // Field endTime:Ljava/time/Instant;
      14: aload_0
      15: aload_1
      16: invokevirtual #17                 // Method org/springframework/boot/context/metrics/buffering/BufferedStartupStep.getStartTime:()Ljava/time/Instant;
      19: aload_2
      20: invokestatic  #23                 // Method java/time/Duration.between:(Ljava/time/temporal/Temporal;Ljava/time/temporal/Temporal;)Ljava/time/Duration;
      23: putfield      #29                 // Field duration:Ljava/time/Duration;
      26: return

  public java.time.Instant getStartTime();
    Code:
       0: aload_0
       1: getfield      #7                  // Field step:Lorg/springframework/boot/context/metrics/buffering/BufferedStartupStep;
       4: invokevirtual #17                 // Method org/springframework/boot/context/metrics/buffering/BufferedStartupStep.getStartTime:()Ljava/time/Instant;
       7: areturn

  public java.time.Instant getEndTime();
    Code:
       0: aload_0
       1: getfield      #13                 // Field endTime:Ljava/time/Instant;
       4: areturn

  public java.time.Duration getDuration();
    Code:
       0: aload_0
       1: getfield      #29                 // Field duration:Ljava/time/Duration;
       4: areturn

  public org.springframework.core.metrics.StartupStep getStartupStep();
    Code:
       0: aload_0
       1: getfield      #7                  // Field step:Lorg/springframework/boot/context/metrics/buffering/BufferedStartupStep;
       4: areturn
}
