Compiled from "CommandContextFactory.java"
public class org.apache.dubbo.qos.command.CommandContextFactory {
  public org.apache.dubbo.qos.command.CommandContextFactory();
    Code:
       0: aload_0
       1: invokespecial #1                  // Method java/lang/Object."<init>":()V
       4: return

  public static org.apache.dubbo.qos.api.CommandContext newInstance(java.lang.String);
    Code:
       0: new           #2                  // class org/apache/dubbo/qos/api/CommandContext
       3: dup
       4: aload_0
       5: invokespecial #3                  // Method org/apache/dubbo/qos/api/CommandContext."<init>":(Ljava/lang/String;)V
       8: areturn

  public static org.apache.dubbo.qos.api.CommandContext newInstance(java.lang.String, java.lang.String[], boolean);
    Code:
       0: new           #2                  // class org/apache/dubbo/qos/api/CommandContext
       3: dup
       4: aload_0
       5: aload_1
       6: iload_2
       7: invokespecial #4                  // Method org/apache/dubbo/qos/api/CommandContext."<init>":(Ljava/lang/String;[Ljava/lang/String;Z)V
      10: areturn
}
