Compiled from "DefaultCommandExecutor.java"
public class org.apache.dubbo.qos.command.DefaultCommandExecutor implements org.apache.dubbo.qos.command.CommandExecutor {
  private static final org.apache.dubbo.common.logger.Logger logger;

  private final org.apache.dubbo.rpc.model.FrameworkModel frameworkModel;

  public org.apache.dubbo.qos.command.DefaultCommandExecutor(org.apache.dubbo.rpc.model.FrameworkModel);
    Code:
       0: aload_0
       1: invokespecial #1                  // Method java/lang/Object."<init>":()V
       4: aload_0
       5: aload_1
       6: putfield      #2                  // Field frameworkModel:Lorg/apache/dubbo/rpc/model/FrameworkModel;
       9: return

  public java.lang.String execute(org.apache.dubbo.qos.api.CommandContext) throws org.apache.dubbo.qos.command.exception.NoSuchCommandException, org.apache.dubbo.qos.command.exception.PermissionDenyException;
    Code:
       0: aload_1
       1: invokevirtual #3                  // Method org/apache/dubbo/qos/api/CommandContext.getRemote:()Lio/netty/channel/Channel;
       4: invokestatic  #4                  // Method java/util/Optional.ofNullable:(Ljava/lang/Object;)Ljava/util/Optional;
       7: invokedynamic #5,  0              // InvokeDynamic #0:apply:()Ljava/util/function/Function;
      12: invokevirtual #6                  // Method java/util/Optional.map:(Ljava/util/function/Function;)Ljava/util/Optional;
      15: invokedynamic #7,  0              // InvokeDynamic #1:apply:()Ljava/util/function/Function;
      20: invokevirtual #6                  // Method java/util/Optional.map:(Ljava/util/function/Function;)Ljava/util/Optional;
      23: ldc           #8                  // String unknown
      25: invokevirtual #9                  // Method java/util/Optional.orElse:(Ljava/lang/Object;)Ljava/lang/Object;
      28: checkcast     #10                 // class java/lang/String
      31: astore_2
      32: getstatic     #11                 // Field logger:Lorg/apache/dubbo/common/logger/Logger;
      35: new           #12                 // class java/lang/StringBuilder
      38: dup
      39: invokespecial #13                 // Method java/lang/StringBuilder."<init>":()V
      42: ldc           #14                 // String [Dubbo QoS] Command Process start. Command:
      44: invokevirtual #15                 // Method java/lang/StringBuilder.append:(Ljava/lang/String;)Ljava/lang/StringBuilder;
      47: aload_1
      48: invokevirtual #16                 // Method org/apache/dubbo/qos/api/CommandContext.getCommandName:()Ljava/lang/String;
      51: invokevirtual #15                 // Method java/lang/StringBuilder.append:(Ljava/lang/String;)Ljava/lang/StringBuilder;
      54: ldc           #17                 // String , Args:
      56: invokevirtual #15                 // Method java/lang/StringBuilder.append:(Ljava/lang/String;)Ljava/lang/StringBuilder;
      59: aload_1
      60: invokevirtual #18                 // Method org/apache/dubbo/qos/api/CommandContext.getArgs:()[Ljava/lang/String;
      63: invokestatic  #19                 // Method java/util/Arrays.toString:([Ljava/lang/Object;)Ljava/lang/String;
      66: invokevirtual #15                 // Method java/lang/StringBuilder.append:(Ljava/lang/String;)Ljava/lang/StringBuilder;
      69: ldc           #20                 // String , Remote Address:
      71: invokevirtual #15                 // Method java/lang/StringBuilder.append:(Ljava/lang/String;)Ljava/lang/StringBuilder;
      74: aload_2
      75: invokevirtual #15                 // Method java/lang/StringBuilder.append:(Ljava/lang/String;)Ljava/lang/StringBuilder;
      78: invokevirtual #21                 // Method java/lang/StringBuilder.toString:()Ljava/lang/String;
      81: invokeinterface #22,  2           // InterfaceMethod org/apache/dubbo/common/logger/Logger.info:(Ljava/lang/String;)V
      86: aconst_null
      87: astore_3
      88: aload_0
      89: getfield      #2                  // Field frameworkModel:Lorg/apache/dubbo/rpc/model/FrameworkModel;
      92: ldc           #23                 // class org/apache/dubbo/qos/api/BaseCommand
      94: invokevirtual #24                 // Method org/apache/dubbo/rpc/model/FrameworkModel.getExtensionLoader:(Ljava/lang/Class;)Lorg/apache/dubbo/common/extension/ExtensionLoader;
      97: aload_1
      98: invokevirtual #16                 // Method org/apache/dubbo/qos/api/CommandContext.getCommandName:()Ljava/lang/String;
     101: invokevirtual #25                 // Method org/apache/dubbo/common/extension/ExtensionLoader.getExtension:(Ljava/lang/String;)Ljava/lang/Object;
     104: checkcast     #23                 // class org/apache/dubbo/qos/api/BaseCommand
     107: astore_3
     108: goto          113
     111: astore        4
     113: aload_3
     114: ifnonnull     168
     117: getstatic     #11                 // Field logger:Lorg/apache/dubbo/common/logger/Logger;
     120: new           #12                 // class java/lang/StringBuilder
     123: dup
     124: invokespecial #13                 // Method java/lang/StringBuilder."<init>":()V
     127: ldc           #27                 // String [Dubbo QoS] Command Not found. Command:
     129: invokevirtual #15                 // Method java/lang/StringBuilder.append:(Ljava/lang/String;)Ljava/lang/StringBuilder;
     132: aload_1
     133: invokevirtual #16                 // Method org/apache/dubbo/qos/api/CommandContext.getCommandName:()Ljava/lang/String;
     136: invokevirtual #15                 // Method java/lang/StringBuilder.append:(Ljava/lang/String;)Ljava/lang/StringBuilder;
     139: ldc           #20                 // String , Remote Address:
     141: invokevirtual #15                 // Method java/lang/StringBuilder.append:(Ljava/lang/String;)Ljava/lang/StringBuilder;
     144: aload_2
     145: invokevirtual #15                 // Method java/lang/StringBuilder.append:(Ljava/lang/String;)Ljava/lang/StringBuilder;
     148: invokevirtual #21                 // Method java/lang/StringBuilder.toString:()Ljava/lang/String;
     151: invokeinterface #22,  2           // InterfaceMethod org/apache/dubbo/common/logger/Logger.info:(Ljava/lang/String;)V
     156: new           #28                 // class org/apache/dubbo/qos/command/exception/NoSuchCommandException
     159: dup
     160: aload_1
     161: invokevirtual #16                 // Method org/apache/dubbo/qos/api/CommandContext.getCommandName:()Ljava/lang/String;
     164: invokespecial #29                 // Method org/apache/dubbo/qos/command/exception/NoSuchCommandException."<init>":(Ljava/lang/String;)V
     167: athrow
     168: aload_1
     169: invokevirtual #30                 // Method org/apache/dubbo/qos/api/CommandContext.isAllowAnonymousAccess:()Z
     172: ifeq          316
     175: getstatic     #31                 // Field org/apache/dubbo/qos/permission/DefaultAnonymousAccessPermissionChecker.INSTANCE:Lorg/apache/dubbo/qos/permission/DefaultAnonymousAccessPermissionChecker;
     178: astore        4
     180: aload_0
     181: getfield      #2                  // Field frameworkModel:Lorg/apache/dubbo/rpc/model/FrameworkModel;
     184: ldc           #32                 // class org/apache/dubbo/qos/permission/PermissionChecker
     186: invokevirtual #24                 // Method org/apache/dubbo/rpc/model/FrameworkModel.getExtensionLoader:(Ljava/lang/Class;)Lorg/apache/dubbo/common/extension/ExtensionLoader;
     189: ldc           #34                 // String qosPermissionChecker
     191: invokevirtual #25                 // Method org/apache/dubbo/common/extension/ExtensionLoader.getExtension:(Ljava/lang/String;)Ljava/lang/Object;
     194: checkcast     #32                 // class org/apache/dubbo/qos/permission/PermissionChecker
     197: astore        4
     199: goto          204
     202: astore        5
     204: aload_3
     205: invokevirtual #35                 // Method java/lang/Object.getClass:()Ljava/lang/Class;
     208: ldc           #36                 // class org/apache/dubbo/qos/api/Cmd
     210: invokevirtual #37                 // Method java/lang/Class.getAnnotation:(Ljava/lang/Class;)Ljava/lang/annotation/Annotation;
     213: checkcast     #36                 // class org/apache/dubbo/qos/api/Cmd
     216: astore        5
     218: aload         5
     220: invokeinterface #38,  1           // InterfaceMethod org/apache/dubbo/qos/api/Cmd.requiredPermissionLevel:()Lorg/apache/dubbo/qos/api/PermissionLevel;
     225: astore        6
     227: aload         4
     229: aload_1
     230: aload         6
     232: invokeinterface #39,  3           // InterfaceMethod org/apache/dubbo/qos/permission/PermissionChecker.access:(Lorg/apache/dubbo/qos/api/CommandContext;Lorg/apache/dubbo/qos/api/PermissionLevel;)Z
     237: ifne          316
     240: getstatic     #11                 // Field logger:Lorg/apache/dubbo/common/logger/Logger;
     243: new           #12                 // class java/lang/StringBuilder
     246: dup
     247: invokespecial #13                 // Method java/lang/StringBuilder."<init>":()V
     250: ldc           #40                 // String [Dubbo QoS] Command Deny to access. Command:
     252: invokevirtual #15                 // Method java/lang/StringBuilder.append:(Ljava/lang/String;)Ljava/lang/StringBuilder;
     255: aload_1
     256: invokevirtual #16                 // Method org/apache/dubbo/qos/api/CommandContext.getCommandName:()Ljava/lang/String;
     259: invokevirtual #15                 // Method java/lang/StringBuilder.append:(Ljava/lang/String;)Ljava/lang/StringBuilder;
     262: ldc           #17                 // String , Args:
     264: invokevirtual #15                 // Method java/lang/StringBuilder.append:(Ljava/lang/String;)Ljava/lang/StringBuilder;
     267: aload_1
     268: invokevirtual #18                 // Method org/apache/dubbo/qos/api/CommandContext.getArgs:()[Ljava/lang/String;
     271: invokestatic  #19                 // Method java/util/Arrays.toString:([Ljava/lang/Object;)Ljava/lang/String;
     274: invokevirtual #15                 // Method java/lang/StringBuilder.append:(Ljava/lang/String;)Ljava/lang/StringBuilder;
     277: ldc           #41                 // String , Required Permission Level:
     279: invokevirtual #15                 // Method java/lang/StringBuilder.append:(Ljava/lang/String;)Ljava/lang/StringBuilder;
     282: aload         6
     284: invokevirtual #42                 // Method java/lang/StringBuilder.append:(Ljava/lang/Object;)Ljava/lang/StringBuilder;
     287: ldc           #20                 // String , Remote Address:
     289: invokevirtual #15                 // Method java/lang/StringBuilder.append:(Ljava/lang/String;)Ljava/lang/StringBuilder;
     292: aload_2
     293: invokevirtual #15                 // Method java/lang/StringBuilder.append:(Ljava/lang/String;)Ljava/lang/StringBuilder;
     296: invokevirtual #21                 // Method java/lang/StringBuilder.toString:()Ljava/lang/String;
     299: invokeinterface #22,  2           // InterfaceMethod org/apache/dubbo/common/logger/Logger.info:(Ljava/lang/String;)V
     304: new           #43                 // class org/apache/dubbo/qos/command/exception/PermissionDenyException
     307: dup
     308: aload_1
     309: invokevirtual #16                 // Method org/apache/dubbo/qos/api/CommandContext.getCommandName:()Ljava/lang/String;
     312: invokespecial #44                 // Method org/apache/dubbo/qos/command/exception/PermissionDenyException."<init>":(Ljava/lang/String;)V
     315: athrow
     316: aload_3
     317: aload_1
     318: aload_1
     319: invokevirtual #18                 // Method org/apache/dubbo/qos/api/CommandContext.getArgs:()[Ljava/lang/String;
     322: invokeinterface #45,  3           // InterfaceMethod org/apache/dubbo/qos/api/BaseCommand.execute:(Lorg/apache/dubbo/qos/api/CommandContext;[Ljava/lang/String;)Ljava/lang/String;
     327: astore        4
     329: aload_3
     330: invokeinterface #46,  1           // InterfaceMethod org/apache/dubbo/qos/api/BaseCommand.logResult:()Z
     335: ifeq          402
     338: getstatic     #11                 // Field logger:Lorg/apache/dubbo/common/logger/Logger;
     341: new           #12                 // class java/lang/StringBuilder
     344: dup
     345: invokespecial #13                 // Method java/lang/StringBuilder."<init>":()V
     348: ldc           #47                 // String [Dubbo QoS] Command Process success. Command:
     350: invokevirtual #15                 // Method java/lang/StringBuilder.append:(Ljava/lang/String;)Ljava/lang/StringBuilder;
     353: aload_1
     354: invokevirtual #16                 // Method org/apache/dubbo/qos/api/CommandContext.getCommandName:()Ljava/lang/String;
     357: invokevirtual #15                 // Method java/lang/StringBuilder.append:(Ljava/lang/String;)Ljava/lang/StringBuilder;
     360: ldc           #17                 // String , Args:
     362: invokevirtual #15                 // Method java/lang/StringBuilder.append:(Ljava/lang/String;)Ljava/lang/StringBuilder;
     365: aload_1
     366: invokevirtual #18                 // Method org/apache/dubbo/qos/api/CommandContext.getArgs:()[Ljava/lang/String;
     369: invokestatic  #19                 // Method java/util/Arrays.toString:([Ljava/lang/Object;)Ljava/lang/String;
     372: invokevirtual #15                 // Method java/lang/StringBuilder.append:(Ljava/lang/String;)Ljava/lang/StringBuilder;
     375: ldc           #48                 // String , Result:
     377: invokevirtual #15                 // Method java/lang/StringBuilder.append:(Ljava/lang/String;)Ljava/lang/StringBuilder;
     380: aload         4
     382: invokevirtual #15                 // Method java/lang/StringBuilder.append:(Ljava/lang/String;)Ljava/lang/StringBuilder;
     385: ldc           #20                 // String , Remote Address:
     387: invokevirtual #15                 // Method java/lang/StringBuilder.append:(Ljava/lang/String;)Ljava/lang/StringBuilder;
     390: aload_2
     391: invokevirtual #15                 // Method java/lang/StringBuilder.append:(Ljava/lang/String;)Ljava/lang/StringBuilder;
     394: invokevirtual #21                 // Method java/lang/StringBuilder.toString:()Ljava/lang/String;
     397: invokeinterface #22,  2           // InterfaceMethod org/apache/dubbo/common/logger/Logger.info:(Ljava/lang/String;)V
     402: aload         4
     404: areturn
     405: astore        4
     407: getstatic     #11                 // Field logger:Lorg/apache/dubbo/common/logger/Logger;
     410: new           #12                 // class java/lang/StringBuilder
     413: dup
     414: invokespecial #13                 // Method java/lang/StringBuilder."<init>":()V
     417: ldc           #49                 // String [Dubbo QoS] Command Process Failed. Command:
     419: invokevirtual #15                 // Method java/lang/StringBuilder.append:(Ljava/lang/String;)Ljava/lang/StringBuilder;
     422: aload_1
     423: invokevirtual #16                 // Method org/apache/dubbo/qos/api/CommandContext.getCommandName:()Ljava/lang/String;
     426: invokevirtual #15                 // Method java/lang/StringBuilder.append:(Ljava/lang/String;)Ljava/lang/StringBuilder;
     429: ldc           #17                 // String , Args:
     431: invokevirtual #15                 // Method java/lang/StringBuilder.append:(Ljava/lang/String;)Ljava/lang/StringBuilder;
     434: aload_1
     435: invokevirtual #18                 // Method org/apache/dubbo/qos/api/CommandContext.getArgs:()[Ljava/lang/String;
     438: invokestatic  #19                 // Method java/util/Arrays.toString:([Ljava/lang/Object;)Ljava/lang/String;
     441: invokevirtual #15                 // Method java/lang/StringBuilder.append:(Ljava/lang/String;)Ljava/lang/StringBuilder;
     444: ldc           #20                 // String , Remote Address:
     446: invokevirtual #15                 // Method java/lang/StringBuilder.append:(Ljava/lang/String;)Ljava/lang/StringBuilder;
     449: aload_2
     450: invokevirtual #15                 // Method java/lang/StringBuilder.append:(Ljava/lang/String;)Ljava/lang/StringBuilder;
     453: invokevirtual #21                 // Method java/lang/StringBuilder.toString:()Ljava/lang/String;
     456: aload         4
     458: invokeinterface #50,  3           // InterfaceMethod org/apache/dubbo/common/logger/Logger.info:(Ljava/lang/String;Ljava/lang/Throwable;)V
     463: aload         4
     465: athrow
    Exception table:
       from    to  target type
          88   108   111   Class java/lang/Throwable
         180   199   202   Class java/lang/Throwable
         316   404   405   Class java/lang/Throwable

  static {};
    Code:
       0: ldc           #51                 // class org/apache/dubbo/qos/command/DefaultCommandExecutor
       2: invokestatic  #52                 // Method org/apache/dubbo/common/logger/LoggerFactory.getLogger:(Ljava/lang/Class;)Lorg/apache/dubbo/common/logger/Logger;
       5: putstatic     #11                 // Field logger:Lorg/apache/dubbo/common/logger/Logger;
       8: return
}
