Compiled from "JadxAttrType.java"
public final class jadx.api.plugins.input.data.attributes.JadxAttrType<T extends jadx.api.plugins.input.data.attributes.IJadxAttribute> implements jadx.api.plugins.input.data.attributes.IJadxAttrType<T> {
  public static final jadx.api.plugins.input.data.attributes.JadxAttrType<jadx.api.plugins.input.data.attributes.types.AnnotationsAttr> ANNOTATION_LIST;

  public static final jadx.api.plugins.input.data.attributes.JadxAttrType<jadx.api.plugins.input.data.attributes.types.SignatureAttr> SIGNATURE;

  public static final jadx.api.plugins.input.data.attributes.JadxAttrType<jadx.api.plugins.input.data.attributes.types.SourceFileAttr> SOURCE_FILE;

  public static final jadx.api.plugins.input.data.attributes.JadxAttrType<jadx.api.plugins.input.data.attributes.types.InnerClassesAttr> INNER_CLASSES;

  public static final jadx.api.plugins.input.data.attributes.JadxAttrType<jadx.api.plugins.input.data.attributes.types.AnnotationDefaultClassAttr> ANNOTATION_DEFAULT_CLASS;

  public static final jadx.api.plugins.input.data.attributes.JadxAttrType<jadx.api.plugins.input.data.annotations.EncodedValue> CONSTANT_VALUE;

  public static final jadx.api.plugins.input.data.attributes.JadxAttrType<jadx.api.plugins.input.data.attributes.types.AnnotationMethodParamsAttr> ANNOTATION_MTH_PARAMETERS;

  public static final jadx.api.plugins.input.data.attributes.JadxAttrType<jadx.api.plugins.input.data.attributes.types.AnnotationDefaultAttr> ANNOTATION_DEFAULT;

  public static final jadx.api.plugins.input.data.attributes.JadxAttrType<jadx.api.plugins.input.data.attributes.types.ExceptionsAttr> EXCEPTIONS;

  public static final jadx.api.plugins.input.data.attributes.JadxAttrType<jadx.api.plugins.input.data.attributes.types.MethodParametersAttr> METHOD_PARAMETERS;

  private static <T extends jadx.api.plugins.input.data.attributes.IJadxAttribute> jadx.api.plugins.input.data.attributes.JadxAttrType<T> bind();
    Code:
       0: new           #1                  // class jadx/api/plugins/input/data/attributes/JadxAttrType
       3: dup
       4: invokespecial #2                  // Method "<init>":()V
       7: areturn

  private jadx.api.plugins.input.data.attributes.JadxAttrType();
    Code:
       0: aload_0
       1: invokespecial #3                  // Method java/lang/Object."<init>":()V
       4: return

  static {};
    Code:
       0: invokestatic  #4                  // Method bind:()Ljadx/api/plugins/input/data/attributes/JadxAttrType;
       3: putstatic     #5                  // Field ANNOTATION_LIST:Ljadx/api/plugins/input/data/attributes/JadxAttrType;
       6: invokestatic  #4                  // Method bind:()Ljadx/api/plugins/input/data/attributes/JadxAttrType;
       9: putstatic     #6                  // Field SIGNATURE:Ljadx/api/plugins/input/data/attributes/JadxAttrType;
      12: invokestatic  #4                  // Method bind:()Ljadx/api/plugins/input/data/attributes/JadxAttrType;
      15: putstatic     #7                  // Field SOURCE_FILE:Ljadx/api/plugins/input/data/attributes/JadxAttrType;
      18: invokestatic  #4                  // Method bind:()Ljadx/api/plugins/input/data/attributes/JadxAttrType;
      21: putstatic     #8                  // Field INNER_CLASSES:Ljadx/api/plugins/input/data/attributes/JadxAttrType;
      24: invokestatic  #4                  // Method bind:()Ljadx/api/plugins/input/data/attributes/JadxAttrType;
      27: putstatic     #9                  // Field ANNOTATION_DEFAULT_CLASS:Ljadx/api/plugins/input/data/attributes/JadxAttrType;
      30: invokestatic  #4                  // Method bind:()Ljadx/api/plugins/input/data/attributes/JadxAttrType;
      33: putstatic     #10                 // Field CONSTANT_VALUE:Ljadx/api/plugins/input/data/attributes/JadxAttrType;
      36: invokestatic  #4                  // Method bind:()Ljadx/api/plugins/input/data/attributes/JadxAttrType;
      39: putstatic     #11                 // Field ANNOTATION_MTH_PARAMETERS:Ljadx/api/plugins/input/data/attributes/JadxAttrType;
      42: invokestatic  #4                  // Method bind:()Ljadx/api/plugins/input/data/attributes/JadxAttrType;
      45: putstatic     #12                 // Field ANNOTATION_DEFAULT:Ljadx/api/plugins/input/data/attributes/JadxAttrType;
      48: invokestatic  #4                  // Method bind:()Ljadx/api/plugins/input/data/attributes/JadxAttrType;
      51: putstatic     #13                 // Field EXCEPTIONS:Ljadx/api/plugins/input/data/attributes/JadxAttrType;
      54: invokestatic  #4                  // Method bind:()Ljadx/api/plugins/input/data/attributes/JadxAttrType;
      57: putstatic     #14                 // Field METHOD_PARAMETERS:Ljadx/api/plugins/input/data/attributes/JadxAttrType;
      60: return
}
