Compiled from "DubboAnnotationUtils.java"
public class org.apache.dubbo.config.spring.util.DubboAnnotationUtils {
  public org.apache.dubbo.config.spring.util.DubboAnnotationUtils();
    Code:
       0: aload_0
       1: invokespecial #1                  // Method java/lang/Object."<init>":()V
       4: return

  public static java.lang.String resolveInterfaceName(org.apache.dubbo.config.annotation.Service, java.lang.Class<?>) throws java.lang.IllegalStateException;
    Code:
       0: aload_0
       1: invokeinterface #2,  1            // InterfaceMethod org/apache/dubbo/config/annotation/Service.interfaceName:()Ljava/lang/String;
       6: invokestatic  #3                  // Method org/springframework/util/StringUtils.hasText:(Ljava/lang/String;)Z
       9: ifeq          22
      12: aload_0
      13: invokeinterface #2,  1            // InterfaceMethod org/apache/dubbo/config/annotation/Service.interfaceName:()Ljava/lang/String;
      18: astore_2
      19: goto          100
      22: getstatic     #4                  // Field java/lang/Void.TYPE:Ljava/lang/Class;
      25: aload_0
      26: invokeinterface #5,  1            // InterfaceMethod org/apache/dubbo/config/annotation/Service.interfaceClass:()Ljava/lang/Class;
      31: invokevirtual #6                  // Method java/lang/Object.equals:(Ljava/lang/Object;)Z
      34: ifne          50
      37: aload_0
      38: invokeinterface #5,  1            // InterfaceMethod org/apache/dubbo/config/annotation/Service.interfaceClass:()Ljava/lang/Class;
      43: invokevirtual #7                  // Method java/lang/Class.getName:()Ljava/lang/String;
      46: astore_2
      47: goto          100
      50: aload_1
      51: invokevirtual #8                  // Method java/lang/Class.isInterface:()Z
      54: ifeq          65
      57: aload_1
      58: invokevirtual #7                  // Method java/lang/Class.getName:()Ljava/lang/String;
      61: astore_2
      62: goto          100
      65: new           #9                  // class java/lang/IllegalStateException
      68: dup
      69: new           #10                 // class java/lang/StringBuilder
      72: dup
      73: invokespecial #11                 // Method java/lang/StringBuilder."<init>":()V
      76: ldc           #12                 // String The @Service undefined interfaceClass or interfaceName, and the type
      78: invokevirtual #13                 // Method java/lang/StringBuilder.append:(Ljava/lang/String;)Ljava/lang/StringBuilder;
      81: aload_1
      82: invokevirtual #7                  // Method java/lang/Class.getName:()Ljava/lang/String;
      85: invokevirtual #13                 // Method java/lang/StringBuilder.append:(Ljava/lang/String;)Ljava/lang/StringBuilder;
      88: ldc           #14                 // String  is not a interface.
      90: invokevirtual #13                 // Method java/lang/StringBuilder.append:(Ljava/lang/String;)Ljava/lang/StringBuilder;
      93: invokevirtual #15                 // Method java/lang/StringBuilder.toString:()Ljava/lang/String;
      96: invokespecial #16                 // Method java/lang/IllegalStateException."<init>":(Ljava/lang/String;)V
      99: athrow
     100: aload_2
     101: areturn

  public static java.lang.String resolveInterfaceName(java.util.Map<java.lang.String, java.lang.Object>, java.lang.Class<?>);
    Code:
       0: aload_0
       1: ldc           #17                 // String interfaceName
       3: invokestatic  #18                 // Method com/alibaba/spring/util/AnnotationUtils.getAttribute:(Ljava/util/Map;Ljava/lang/String;)Ljava/lang/Object;
       6: checkcast     #19                 // class java/lang/String
       9: astore_2
      10: aload_2
      11: invokestatic  #20                 // Method org/apache/dubbo/common/utils/StringUtils.hasText:(Ljava/lang/CharSequence;)Z
      14: ifeq          70
      17: ldc           #21                 // class org/apache/dubbo/rpc/service/GenericService
      19: invokevirtual #7                  // Method java/lang/Class.getName:()Ljava/lang/String;
      22: aload_2
      23: invokevirtual #22                 // Method java/lang/String.equals:(Ljava/lang/Object;)Z
      26: ifne          41
      29: ldc           #23                 // class com/alibaba/dubbo/rpc/service/GenericService
      31: invokevirtual #7                  // Method java/lang/Class.getName:()Ljava/lang/String;
      34: aload_2
      35: invokevirtual #22                 // Method java/lang/String.equals:(Ljava/lang/Object;)Z
      38: ifeq          68
      41: new           #9                  // class java/lang/IllegalStateException
      44: dup
      45: new           #10                 // class java/lang/StringBuilder
      48: dup
      49: invokespecial #11                 // Method java/lang/StringBuilder."<init>":()V
      52: ldc           #24                 // String @Service interfaceName() cannot be GenericService:
      54: invokevirtual #13                 // Method java/lang/StringBuilder.append:(Ljava/lang/String;)Ljava/lang/StringBuilder;
      57: aload_2
      58: invokevirtual #13                 // Method java/lang/StringBuilder.append:(Ljava/lang/String;)Ljava/lang/StringBuilder;
      61: invokevirtual #15                 // Method java/lang/StringBuilder.toString:()Ljava/lang/String;
      64: invokespecial #16                 // Method java/lang/IllegalStateException."<init>":(Ljava/lang/String;)V
      67: athrow
      68: aload_2
      69: areturn
      70: aload_0
      71: ldc           #25                 // String interfaceClass
      73: invokestatic  #18                 // Method com/alibaba/spring/util/AnnotationUtils.getAttribute:(Ljava/util/Map;Ljava/lang/String;)Ljava/lang/Object;
      76: checkcast     #26                 // class java/lang/Class
      79: astore_3
      80: aload_3
      81: ifnull        94
      84: getstatic     #4                  // Field java/lang/Void.TYPE:Ljava/lang/Class;
      87: aload_3
      88: invokevirtual #6                  // Method java/lang/Object.equals:(Ljava/lang/Object;)Z
      91: ifeq          99
      94: aconst_null
      95: astore_3
      96: goto          138
      99: ldc           #21                 // class org/apache/dubbo/rpc/service/GenericService
     101: aload_3
     102: invokevirtual #27                 // Method java/lang/Class.isAssignableFrom:(Ljava/lang/Class;)Z
     105: ifeq          138
     108: new           #9                  // class java/lang/IllegalStateException
     111: dup
     112: new           #10                 // class java/lang/StringBuilder
     115: dup
     116: invokespecial #11                 // Method java/lang/StringBuilder."<init>":()V
     119: ldc           #28                 // String @Service interfaceClass() cannot be GenericService :
     121: invokevirtual #13                 // Method java/lang/StringBuilder.append:(Ljava/lang/String;)Ljava/lang/StringBuilder;
     124: aload_3
     125: invokevirtual #7                  // Method java/lang/Class.getName:()Ljava/lang/String;
     128: invokevirtual #13                 // Method java/lang/StringBuilder.append:(Ljava/lang/String;)Ljava/lang/StringBuilder;
     131: invokevirtual #15                 // Method java/lang/StringBuilder.toString:()Ljava/lang/String;
     134: invokespecial #16                 // Method java/lang/IllegalStateException."<init>":(Ljava/lang/String;)V
     137: athrow
     138: aload_3
     139: ifnonnull     172
     142: aload_1
     143: ifnull        172
     146: ldc           #21                 // class org/apache/dubbo/rpc/service/GenericService
     148: aload_1
     149: invokevirtual #27                 // Method java/lang/Class.isAssignableFrom:(Ljava/lang/Class;)Z
     152: ifne          172
     155: aload_1
     156: invokestatic  #29                 // Method org/springframework/util/ClassUtils.getAllInterfacesForClass:(Ljava/lang/Class;)[Ljava/lang/Class;
     159: astore        4
     161: aload         4
     163: arraylength
     164: ifle          172
     167: aload         4
     169: iconst_0
     170: aaload
     171: astore_3
     172: aload_3
     173: ldc           #30                 // String @Service interfaceClass() or interfaceName() or interface class must be present!
     175: invokestatic  #31                 // Method org/springframework/util/Assert.notNull:(Ljava/lang/Object;Ljava/lang/String;)V
     178: aload_3
     179: invokevirtual #8                  // Method java/lang/Class.isInterface:()Z
     182: ldc           #32                 // String The annotated type must be an interface!
     184: invokestatic  #33                 // Method org/springframework/util/Assert.isTrue:(ZLjava/lang/String;)V
     187: aload_3
     188: invokevirtual #7                  // Method java/lang/Class.getName:()Ljava/lang/String;
     191: areturn

  public static java.lang.String resolveInterfaceName(org.apache.dubbo.config.annotation.Reference, java.lang.Class<?>) throws java.lang.IllegalStateException;
    Code:
       0: ldc           #34                 // String
       2: aload_0
       3: invokeinterface #35,  1           // InterfaceMethod org/apache/dubbo/config/annotation/Reference.interfaceName:()Ljava/lang/String;
       8: invokevirtual #22                 // Method java/lang/String.equals:(Ljava/lang/Object;)Z
      11: ifne          24
      14: aload_0
      15: invokeinterface #35,  1           // InterfaceMethod org/apache/dubbo/config/annotation/Reference.interfaceName:()Ljava/lang/String;
      20: astore_2
      21: goto          102
      24: getstatic     #4                  // Field java/lang/Void.TYPE:Ljava/lang/Class;
      27: aload_0
      28: invokeinterface #36,  1           // InterfaceMethod org/apache/dubbo/config/annotation/Reference.interfaceClass:()Ljava/lang/Class;
      33: invokevirtual #6                  // Method java/lang/Object.equals:(Ljava/lang/Object;)Z
      36: ifne          52
      39: aload_0
      40: invokeinterface #36,  1           // InterfaceMethod org/apache/dubbo/config/annotation/Reference.interfaceClass:()Ljava/lang/Class;
      45: invokevirtual #7                  // Method java/lang/Class.getName:()Ljava/lang/String;
      48: astore_2
      49: goto          102
      52: aload_1
      53: invokevirtual #8                  // Method java/lang/Class.isInterface:()Z
      56: ifeq          67
      59: aload_1
      60: invokevirtual #7                  // Method java/lang/Class.getName:()Ljava/lang/String;
      63: astore_2
      64: goto          102
      67: new           #9                  // class java/lang/IllegalStateException
      70: dup
      71: new           #10                 // class java/lang/StringBuilder
      74: dup
      75: invokespecial #11                 // Method java/lang/StringBuilder."<init>":()V
      78: ldc           #37                 // String The @Reference undefined interfaceClass or interfaceName, and the type
      80: invokevirtual #13                 // Method java/lang/StringBuilder.append:(Ljava/lang/String;)Ljava/lang/StringBuilder;
      83: aload_1
      84: invokevirtual #7                  // Method java/lang/Class.getName:()Ljava/lang/String;
      87: invokevirtual #13                 // Method java/lang/StringBuilder.append:(Ljava/lang/String;)Ljava/lang/StringBuilder;
      90: ldc           #14                 // String  is not a interface.
      92: invokevirtual #13                 // Method java/lang/StringBuilder.append:(Ljava/lang/String;)Ljava/lang/StringBuilder;
      95: invokevirtual #15                 // Method java/lang/StringBuilder.toString:()Ljava/lang/String;
      98: invokespecial #16                 // Method java/lang/IllegalStateException."<init>":(Ljava/lang/String;)V
     101: athrow
     102: aload_2
     103: areturn

  public static java.util.Map<java.lang.String, java.lang.String> convertParameters(java.lang.String[]);
    Code:
       0: aload_0
       1: invokestatic  #38                 // Method org/apache/dubbo/common/utils/ArrayUtils.isEmpty:([Ljava/lang/Object;)Z
       4: ifeq          11
       7: invokestatic  #39                 // Method java/util/Collections.emptyMap:()Ljava/util/Map;
      10: areturn
      11: aload_0
      12: invokestatic  #40                 // Method java/util/Arrays.stream:([Ljava/lang/Object;)Ljava/util/stream/Stream;
      15: invokedynamic #41,  0             // InvokeDynamic #0:apply:()Ljava/util/function/Function;
      20: invokeinterface #42,  2           // InterfaceMethod java/util/stream/Stream.map:(Ljava/util/function/Function;)Ljava/util/stream/Stream;
      25: new           #43                 // class java/util/ArrayList
      28: dup
      29: aload_0
      30: arraylength
      31: invokespecial #44                 // Method java/util/ArrayList."<init>":(I)V
      34: invokedynamic #45,  0             // InvokeDynamic #1:apply:()Ljava/util/function/BiFunction;
      39: invokedynamic #46,  0             // InvokeDynamic #2:apply:()Ljava/util/function/BinaryOperator;
      44: invokeinterface #47,  4           // InterfaceMethod java/util/stream/Stream.reduce:(Ljava/lang/Object;Ljava/util/function/BiFunction;Ljava/util/function/BinaryOperator;)Ljava/lang/Object;
      49: checkcast     #48                 // class java/util/List
      52: astore_1
      53: aload_1
      54: iconst_0
      55: anewarray     #19                 // class java/lang/String
      58: invokeinterface #49,  2           // InterfaceMethod java/util/List.toArray:([Ljava/lang/Object;)[Ljava/lang/Object;
      63: checkcast     #50                 // class "[Ljava/lang/String;"
      66: invokestatic  #51                 // Method org/apache/dubbo/common/utils/CollectionUtils.toStringMap:([Ljava/lang/String;)Ljava/util/Map;
      69: areturn

  private static java.util.ArrayList lambda$convertParameters$1(java.util.ArrayList, java.util.ArrayList);
    Code:
       0: aload_0
       1: areturn

  private static java.util.ArrayList lambda$convertParameters$0(java.util.ArrayList, java.lang.String);
    Code:
       0: aload_0
       1: invokevirtual #52                 // Method java/util/ArrayList.size:()I
       4: iconst_2
       5: irem
       6: iconst_1
       7: if_icmpne     18
      10: aload_0
      11: aload_1
      12: invokevirtual #53                 // Method java/util/ArrayList.add:(Ljava/lang/Object;)Z
      15: pop
      16: aload_0
      17: areturn
      18: aload_1
      19: ldc           #54                 // String :
      21: invokevirtual #55                 // Method java/lang/String.split:(Ljava/lang/String;)[Ljava/lang/String;
      24: astore_2
      25: aload_2
      26: arraylength
      27: ifle          69
      30: aload_2
      31: arraylength
      32: iconst_2
      33: irem
      34: ifne          69
      37: aload_0
      38: aload_2
      39: invokestatic  #40                 // Method java/util/Arrays.stream:([Ljava/lang/Object;)Ljava/util/stream/Stream;
      42: invokedynamic #41,  0             // InvokeDynamic #0:apply:()Ljava/util/function/Function;
      47: invokeinterface #42,  2           // InterfaceMethod java/util/stream/Stream.map:(Ljava/util/function/Function;)Ljava/util/stream/Stream;
      52: invokestatic  #56                 // Method java/util/stream/Collectors.toList:()Ljava/util/stream/Collector;
      55: invokeinterface #57,  2           // InterfaceMethod java/util/stream/Stream.collect:(Ljava/util/stream/Collector;)Ljava/lang/Object;
      60: checkcast     #58                 // class java/util/Collection
      63: invokevirtual #59                 // Method java/util/ArrayList.addAll:(Ljava/util/Collection;)Z
      66: pop
      67: aload_0
      68: areturn
      69: aload_1
      70: ldc           #60                 // String =
      72: invokevirtual #55                 // Method java/lang/String.split:(Ljava/lang/String;)[Ljava/lang/String;
      75: astore_2
      76: aload_2
      77: arraylength
      78: ifle          120
      81: aload_2
      82: arraylength
      83: iconst_2
      84: irem
      85: ifne          120
      88: aload_0
      89: aload_2
      90: invokestatic  #40                 // Method java/util/Arrays.stream:([Ljava/lang/Object;)Ljava/util/stream/Stream;
      93: invokedynamic #41,  0             // InvokeDynamic #0:apply:()Ljava/util/function/Function;
      98: invokeinterface #42,  2           // InterfaceMethod java/util/stream/Stream.map:(Ljava/util/function/Function;)Ljava/util/stream/Stream;
     103: invokestatic  #56                 // Method java/util/stream/Collectors.toList:()Ljava/util/stream/Collector;
     106: invokeinterface #57,  2           // InterfaceMethod java/util/stream/Stream.collect:(Ljava/util/stream/Collector;)Ljava/lang/Object;
     111: checkcast     #58                 // class java/util/Collection
     114: invokevirtual #59                 // Method java/util/ArrayList.addAll:(Ljava/util/Collection;)Z
     117: pop
     118: aload_0
     119: areturn
     120: aload_0
     121: aload_1
     122: invokevirtual #53                 // Method java/util/ArrayList.add:(Ljava/lang/Object;)Z
     125: pop
     126: aload_0
     127: areturn
}
