Compiled from "DubboBeanUtils.java"
public interface org.apache.dubbo.config.spring.util.DubboBeanUtils {
  public static final org.apache.commons.logging.Log log;

  public static void registerCommonBeans(org.springframework.beans.factory.support.BeanDefinitionRegistry);
    Code:
       0: aload_0
       1: ldc           #2                  // String dubboServicePackagesHolder
       3: ldc           #1                  // class org/apache/dubbo/config/spring/beans/factory/annotation/ServicePackagesHolder
       5: invokestatic  #3                  // InterfaceMethod registerInfrastructureBean:(Lorg/springframework/beans/factory/support/BeanDefinitionRegistry;Ljava/lang/String;Ljava/lang/Class;)Z
       8: pop
       9: aload_0
      10: ldc           #5                  // String dubboReferenceBeanManager
      12: ldc           #4                  // class org/apache/dubbo/config/spring/reference/ReferenceBeanManager
      14: invokestatic  #3                  // InterfaceMethod registerInfrastructureBean:(Lorg/springframework/beans/factory/support/BeanDefinitionRegistry;Ljava/lang/String;Ljava/lang/Class;)Z
      17: pop
      18: aload_0
      19: ldc           #7                  // String referenceAnnotationBeanPostProcessor
      21: ldc           #6                  // class org/apache/dubbo/config/spring/beans/factory/annotation/ReferenceAnnotationBeanPostProcessor
      23: invokestatic  #3                  // InterfaceMethod registerInfrastructureBean:(Lorg/springframework/beans/factory/support/BeanDefinitionRegistry;Ljava/lang/String;Ljava/lang/Class;)Z
      26: pop
      27: aload_0
      28: ldc           #9                  // String dubboConfigAliasPostProcessor
      30: ldc           #8                  // class org/apache/dubbo/config/spring/beans/factory/annotation/DubboConfigAliasPostProcessor
      32: invokestatic  #3                  // InterfaceMethod registerInfrastructureBean:(Lorg/springframework/beans/factory/support/BeanDefinitionRegistry;Ljava/lang/String;Ljava/lang/Class;)Z
      35: pop
      36: aload_0
      37: ldc           #10                 // class org/apache/dubbo/config/spring/context/DubboDeployApplicationListener
      39: invokevirtual #11                 // Method java/lang/Class.getName:()Ljava/lang/String;
      42: ldc           #10                 // class org/apache/dubbo/config/spring/context/DubboDeployApplicationListener
      44: invokestatic  #3                  // InterfaceMethod registerInfrastructureBean:(Lorg/springframework/beans/factory/support/BeanDefinitionRegistry;Ljava/lang/String;Ljava/lang/Class;)Z
      47: pop
      48: aload_0
      49: ldc           #12                 // class org/apache/dubbo/config/spring/context/DubboConfigApplicationListener
      51: invokevirtual #11                 // Method java/lang/Class.getName:()Ljava/lang/String;
      54: ldc           #12                 // class org/apache/dubbo/config/spring/context/DubboConfigApplicationListener
      56: invokestatic  #3                  // InterfaceMethod registerInfrastructureBean:(Lorg/springframework/beans/factory/support/BeanDefinitionRegistry;Ljava/lang/String;Ljava/lang/Class;)Z
      59: pop
      60: aload_0
      61: ldc           #14                 // String dubboConfigDefaultPropertyValueBeanPostProcessor
      63: ldc           #13                 // class org/apache/dubbo/config/spring/beans/factory/config/DubboConfigDefaultPropertyValueBeanPostProcessor
      65: invokestatic  #3                  // InterfaceMethod registerInfrastructureBean:(Lorg/springframework/beans/factory/support/BeanDefinitionRegistry;Ljava/lang/String;Ljava/lang/Class;)Z
      68: pop
      69: aload_0
      70: getstatic     #15                 // Field org/apache/dubbo/config/spring/context/DubboConfigBeanInitializer.BEAN_NAME:Ljava/lang/String;
      73: ldc           #16                 // class org/apache/dubbo/config/spring/context/DubboConfigBeanInitializer
      75: invokestatic  #3                  // InterfaceMethod registerInfrastructureBean:(Lorg/springframework/beans/factory/support/BeanDefinitionRegistry;Ljava/lang/String;Ljava/lang/Class;)Z
      78: pop
      79: aload_0
      80: ldc           #18                 // String dubboInfraBeanRegisterPostProcessor
      82: ldc           #17                 // class org/apache/dubbo/config/spring/context/DubboInfraBeanRegisterPostProcessor
      84: invokestatic  #3                  // InterfaceMethod registerInfrastructureBean:(Lorg/springframework/beans/factory/support/BeanDefinitionRegistry;Ljava/lang/String;Ljava/lang/Class;)Z
      87: pop
      88: return

  public static boolean registerInfrastructureBean(org.springframework.beans.factory.support.BeanDefinitionRegistry, java.lang.String, java.lang.Class<?>);
    Code:
       0: iconst_0
       1: istore_3
       2: aload_0
       3: aload_1
       4: invokeinterface #19,  2           // InterfaceMethod org/springframework/beans/factory/support/BeanDefinitionRegistry.containsBeanDefinition:(Ljava/lang/String;)Z
       9: ifne          92
      12: new           #20                 // class org/springframework/beans/factory/support/RootBeanDefinition
      15: dup
      16: aload_2
      17: invokespecial #21                 // Method org/springframework/beans/factory/support/RootBeanDefinition."<init>":(Ljava/lang/Class;)V
      20: astore        4
      22: aload         4
      24: iconst_2
      25: invokevirtual #23                 // Method org/springframework/beans/factory/support/RootBeanDefinition.setRole:(I)V
      28: aload_0
      29: aload_1
      30: aload         4
      32: invokeinterface #24,  3           // InterfaceMethod org/springframework/beans/factory/support/BeanDefinitionRegistry.registerBeanDefinition:(Ljava/lang/String;Lorg/springframework/beans/factory/config/BeanDefinition;)V
      37: iconst_1
      38: istore_3
      39: getstatic     #25                 // Field log:Lorg/apache/commons/logging/Log;
      42: invokeinterface #26,  1           // InterfaceMethod org/apache/commons/logging/Log.isDebugEnabled:()Z
      47: ifeq          92
      50: getstatic     #25                 // Field log:Lorg/apache/commons/logging/Log;
      53: new           #27                 // class java/lang/StringBuilder
      56: dup
      57: invokespecial #28                 // Method java/lang/StringBuilder."<init>":()V
      60: ldc           #29                 // String The Infrastructure bean definition [
      62: invokevirtual #30                 // Method java/lang/StringBuilder.append:(Ljava/lang/String;)Ljava/lang/StringBuilder;
      65: aload         4
      67: invokevirtual #31                 // Method java/lang/StringBuilder.append:(Ljava/lang/Object;)Ljava/lang/StringBuilder;
      70: ldc           #32                 // String with name [
      72: invokevirtual #30                 // Method java/lang/StringBuilder.append:(Ljava/lang/String;)Ljava/lang/StringBuilder;
      75: aload_1
      76: invokevirtual #30                 // Method java/lang/StringBuilder.append:(Ljava/lang/String;)Ljava/lang/StringBuilder;
      79: ldc           #33                 // String ] has been registered.
      81: invokevirtual #30                 // Method java/lang/StringBuilder.append:(Ljava/lang/String;)Ljava/lang/StringBuilder;
      84: invokevirtual #34                 // Method java/lang/StringBuilder.toString:()Ljava/lang/String;
      87: invokeinterface #35,  2           // InterfaceMethod org/apache/commons/logging/Log.debug:(Ljava/lang/Object;)V
      92: iload_3
      93: ireturn

  public static void registerPlaceholderConfigurerBeanIfNotExists(org.springframework.beans.factory.config.ConfigurableListableBeanFactory, org.springframework.beans.factory.support.BeanDefinitionRegistry);
    Code:
       0: aload_0
       1: ldc           #36                 // class org/springframework/context/support/PropertySourcesPlaceholderConfigurer
       3: invokestatic  #37                 // InterfaceMethod checkBeanExists:(Lorg/springframework/beans/factory/config/ConfigurableListableBeanFactory;Ljava/lang/Class;)Z
       6: ifne          43
       9: new           #38                 // class java/util/HashMap
      12: dup
      13: invokespecial #39                 // Method java/util/HashMap."<init>":()V
      16: astore_2
      17: aload_2
      18: ldc           #40                 // String ignoreUnresolvablePlaceholders
      20: iconst_1
      21: invokestatic  #41                 // Method java/lang/Boolean.valueOf:(Z)Ljava/lang/Boolean;
      24: invokeinterface #42,  3           // InterfaceMethod java/util/Map.put:(Ljava/lang/Object;Ljava/lang/Object;)Ljava/lang/Object;
      29: pop
      30: aload_1
      31: ldc           #36                 // class org/springframework/context/support/PropertySourcesPlaceholderConfigurer
      33: invokevirtual #11                 // Method java/lang/Class.getName:()Ljava/lang/String;
      36: ldc           #36                 // class org/springframework/context/support/PropertySourcesPlaceholderConfigurer
      38: aload_2
      39: invokestatic  #43                 // InterfaceMethod registerBeanDefinition:(Lorg/springframework/beans/factory/support/BeanDefinitionRegistry;Ljava/lang/String;Ljava/lang/Class;Ljava/util/Map;)Z
      42: pop
      43: return

  public static boolean registerBeanDefinition(org.springframework.beans.factory.support.BeanDefinitionRegistry, java.lang.String, java.lang.Class<?>, java.util.Map<java.lang.String, java.lang.Object>);
    Code:
       0: aload_0
       1: aload_1
       2: invokeinterface #19,  2           // InterfaceMethod org/springframework/beans/factory/support/BeanDefinitionRegistry.containsBeanDefinition:(Ljava/lang/String;)Z
       7: ifeq          12
      10: iconst_0
      11: ireturn
      12: aload_2
      13: invokestatic  #44                 // Method org/springframework/beans/factory/support/BeanDefinitionBuilder.genericBeanDefinition:(Ljava/lang/Class;)Lorg/springframework/beans/factory/support/BeanDefinitionBuilder;
      16: invokevirtual #45                 // Method org/springframework/beans/factory/support/BeanDefinitionBuilder.getBeanDefinition:()Lorg/springframework/beans/factory/support/AbstractBeanDefinition;
      19: astore        4
      21: aload_3
      22: ifnull        91
      25: aload_3
      26: invokeinterface #46,  1           // InterfaceMethod java/util/Map.entrySet:()Ljava/util/Set;
      31: invokeinterface #47,  1           // InterfaceMethod java/util/Set.iterator:()Ljava/util/Iterator;
      36: astore        5
      38: aload         5
      40: invokeinterface #48,  1           // InterfaceMethod java/util/Iterator.hasNext:()Z
      45: ifeq          91
      48: aload         5
      50: invokeinterface #49,  1           // InterfaceMethod java/util/Iterator.next:()Ljava/lang/Object;
      55: checkcast     #50                 // class java/util/Map$Entry
      58: astore        6
      60: aload         4
      62: invokeinterface #51,  1           // InterfaceMethod org/springframework/beans/factory/config/BeanDefinition.getPropertyValues:()Lorg/springframework/beans/MutablePropertyValues;
      67: aload         6
      69: invokeinterface #52,  1           // InterfaceMethod java/util/Map$Entry.getKey:()Ljava/lang/Object;
      74: checkcast     #53                 // class java/lang/String
      77: aload         6
      79: invokeinterface #54,  1           // InterfaceMethod java/util/Map$Entry.getValue:()Ljava/lang/Object;
      84: invokevirtual #55                 // Method org/springframework/beans/MutablePropertyValues.add:(Ljava/lang/String;Ljava/lang/Object;)Lorg/springframework/beans/MutablePropertyValues;
      87: pop
      88: goto          38
      91: aload_0
      92: aload_1
      93: aload         4
      95: invokeinterface #24,  3           // InterfaceMethod org/springframework/beans/factory/support/BeanDefinitionRegistry.registerBeanDefinition:(Ljava/lang/String;Lorg/springframework/beans/factory/config/BeanDefinition;)V
     100: iconst_1
     101: ireturn

  public static boolean checkBeanExists(org.springframework.beans.factory.config.ConfigurableListableBeanFactory, java.lang.Class<?>);
    Code:
       0: aload_0
       1: aload_1
       2: iconst_1
       3: iconst_0
       4: invokeinterface #56,  4           // InterfaceMethod org/springframework/beans/factory/config/ConfigurableListableBeanFactory.getBeanNamesForType:(Ljava/lang/Class;ZZ)[Ljava/lang/String;
       9: astore_2
      10: aload_2
      11: ifnull        23
      14: aload_2
      15: arraylength
      16: ifle          23
      19: iconst_1
      20: goto          24
      23: iconst_0
      24: ireturn

  public static org.apache.dubbo.config.spring.beans.factory.annotation.ReferenceAnnotationBeanPostProcessor getReferenceAnnotationBeanPostProcessor(org.springframework.beans.factory.support.AbstractBeanFactory);
    Code:
       0: aload_0
       1: invokevirtual #57                 // Method org/springframework/beans/factory/support/AbstractBeanFactory.getBeanPostProcessors:()Ljava/util/List;
       4: invokeinterface #58,  1           // InterfaceMethod java/util/List.iterator:()Ljava/util/Iterator;
       9: astore_1
      10: aload_1
      11: invokeinterface #48,  1           // InterfaceMethod java/util/Iterator.hasNext:()Z
      16: ifeq          44
      19: aload_1
      20: invokeinterface #49,  1           // InterfaceMethod java/util/Iterator.next:()Ljava/lang/Object;
      25: checkcast     #59                 // class org/springframework/beans/factory/config/BeanPostProcessor
      28: astore_2
      29: aload_2
      30: instanceof    #6                  // class org/apache/dubbo/config/spring/beans/factory/annotation/ReferenceAnnotationBeanPostProcessor
      33: ifeq          41
      36: aload_2
      37: checkcast     #6                  // class org/apache/dubbo/config/spring/beans/factory/annotation/ReferenceAnnotationBeanPostProcessor
      40: areturn
      41: goto          10
      44: aconst_null
      45: areturn

  public static org.apache.dubbo.config.spring.beans.factory.annotation.ReferenceAnnotationBeanPostProcessor getReferenceAnnotationBeanPostProcessor(org.springframework.context.ApplicationContext);
    Code:
       0: aload_0
       1: invokeinterface #60,  1           // InterfaceMethod org/springframework/context/ApplicationContext.getAutowireCapableBeanFactory:()Lorg/springframework/beans/factory/config/AutowireCapableBeanFactory;
       6: checkcast     #61                 // class org/springframework/beans/factory/support/AbstractBeanFactory
       9: invokestatic  #62                 // InterfaceMethod getReferenceAnnotationBeanPostProcessor:(Lorg/springframework/beans/factory/support/AbstractBeanFactory;)Lorg/apache/dubbo/config/spring/beans/factory/annotation/ReferenceAnnotationBeanPostProcessor;
      12: areturn

  public static org.apache.dubbo.config.spring.context.DubboSpringInitContext getInitializationContext(org.springframework.beans.factory.BeanFactory);
    Code:
       0: ldc           #63                 // class org/apache/dubbo/config/spring/context/DubboSpringInitContext
       2: invokevirtual #11                 // Method java/lang/Class.getName:()Ljava/lang/String;
       5: astore_1
       6: aload_0
       7: aload_1
       8: invokeinterface #64,  2           // InterfaceMethod org/springframework/beans/factory/BeanFactory.containsBean:(Ljava/lang/String;)Z
      13: ifeq          29
      16: aload_0
      17: aload_1
      18: ldc           #63                 // class org/apache/dubbo/config/spring/context/DubboSpringInitContext
      20: invokeinterface #65,  3           // InterfaceMethod org/springframework/beans/factory/BeanFactory.getBean:(Ljava/lang/String;Ljava/lang/Class;)Ljava/lang/Object;
      25: checkcast     #63                 // class org/apache/dubbo/config/spring/context/DubboSpringInitContext
      28: areturn
      29: aconst_null
      30: areturn

  public static org.apache.dubbo.rpc.model.ApplicationModel getApplicationModel(org.springframework.beans.factory.BeanFactory);
    Code:
       0: ldc           #66                 // class org/apache/dubbo/rpc/model/ApplicationModel
       2: invokevirtual #11                 // Method java/lang/Class.getName:()Ljava/lang/String;
       5: astore_1
       6: aload_0
       7: aload_1
       8: invokeinterface #64,  2           // InterfaceMethod org/springframework/beans/factory/BeanFactory.containsBean:(Ljava/lang/String;)Z
      13: ifeq          29
      16: aload_0
      17: aload_1
      18: ldc           #66                 // class org/apache/dubbo/rpc/model/ApplicationModel
      20: invokeinterface #65,  3           // InterfaceMethod org/springframework/beans/factory/BeanFactory.getBean:(Ljava/lang/String;Ljava/lang/Class;)Ljava/lang/Object;
      25: checkcast     #66                 // class org/apache/dubbo/rpc/model/ApplicationModel
      28: areturn
      29: aconst_null
      30: areturn

  public static org.apache.dubbo.rpc.model.ModuleModel getModuleModel(org.springframework.beans.factory.BeanFactory);
    Code:
       0: ldc           #67                 // class org/apache/dubbo/rpc/model/ModuleModel
       2: invokevirtual #11                 // Method java/lang/Class.getName:()Ljava/lang/String;
       5: astore_1
       6: aload_0
       7: aload_1
       8: invokeinterface #64,  2           // InterfaceMethod org/springframework/beans/factory/BeanFactory.containsBean:(Ljava/lang/String;)Z
      13: ifeq          29
      16: aload_0
      17: aload_1
      18: ldc           #67                 // class org/apache/dubbo/rpc/model/ModuleModel
      20: invokeinterface #65,  3           // InterfaceMethod org/springframework/beans/factory/BeanFactory.getBean:(Ljava/lang/String;Ljava/lang/Class;)Ljava/lang/Object;
      25: checkcast     #67                 // class org/apache/dubbo/rpc/model/ModuleModel
      28: areturn
      29: aconst_null
      30: areturn

  static {};
    Code:
       0: ldc           #68                 // class org/apache/dubbo/config/spring/util/DubboBeanUtils
       2: invokestatic  #69                 // Method org/apache/commons/logging/LogFactory.getLog:(Ljava/lang/Class;)Lorg/apache/commons/logging/Log;
       5: putstatic     #25                 // Field log:Lorg/apache/commons/logging/Log;
       8: return
}
