Compiled from "EnvironmentUtils.java"
public abstract class org.apache.dubbo.config.spring.util.EnvironmentUtils {
  public static final java.lang.String PROPERTY_NAME_SEPARATOR;

  public static final java.lang.String DUBBO_PREFIX;

  public org.apache.dubbo.config.spring.util.EnvironmentUtils();
    Code:
       0: aload_0
       1: invokespecial #1                  // Method java/lang/Object."<init>":()V
       4: return

  public static java.util.Map<java.lang.String, java.lang.Object> extractProperties(org.springframework.core.env.ConfigurableEnvironment);
    Code:
       0: aload_0
       1: invokestatic  #2                  // Method doExtraProperties:(Lorg/springframework/core/env/ConfigurableEnvironment;)Ljava/util/Map;
       4: invokestatic  #3                  // Method java/util/Collections.unmodifiableMap:(Ljava/util/Map;)Ljava/util/Map;
       7: areturn

  private static java.util.Map<java.lang.String, java.lang.Object> doExtraProperties(org.springframework.core.env.ConfigurableEnvironment);
    Code:
       0: new           #4                  // class java/util/LinkedHashMap
       3: dup
       4: invokespecial #5                  // Method java/util/LinkedHashMap."<init>":()V
       7: astore_1
       8: aload_0
       9: invokestatic  #6                  // Method doGetPropertySources:(Lorg/springframework/core/env/ConfigurableEnvironment;)Ljava/util/Map;
      12: astore_2
      13: aload_2
      14: invokeinterface #7,  1            // InterfaceMethod java/util/Map.values:()Ljava/util/Collection;
      19: invokeinterface #8,  1            // InterfaceMethod java/util/Collection.iterator:()Ljava/util/Iterator;
      24: astore_3
      25: aload_3
      26: invokeinterface #9,  1            // InterfaceMethod java/util/Iterator.hasNext:()Z
      31: ifeq          140
      34: aload_3
      35: invokeinterface #10,  1           // InterfaceMethod java/util/Iterator.next:()Ljava/lang/Object;
      40: checkcast     #11                 // class org/springframework/core/env/PropertySource
      43: astore        4
      45: aload         4
      47: instanceof    #12                 // class org/springframework/core/env/EnumerablePropertySource
      50: ifeq          137
      53: aload         4
      55: checkcast     #12                 // class org/springframework/core/env/EnumerablePropertySource
      58: astore        5
      60: aload         5
      62: invokevirtual #13                 // Method org/springframework/core/env/EnumerablePropertySource.getPropertyNames:()[Ljava/lang/String;
      65: astore        6
      67: aload         6
      69: invokestatic  #14                 // Method org/springframework/util/ObjectUtils.isEmpty:([Ljava/lang/Object;)Z
      72: ifeq          78
      75: goto          25
      78: aload         6
      80: astore        7
      82: aload         7
      84: arraylength
      85: istore        8
      87: iconst_0
      88: istore        9
      90: iload         9
      92: iload         8
      94: if_icmpge     137
      97: aload         7
      99: iload         9
     101: aaload
     102: astore        10
     104: aload_1
     105: aload         10
     107: invokeinterface #15,  2           // InterfaceMethod java/util/Map.containsKey:(Ljava/lang/Object;)Z
     112: ifne          131
     115: aload_1
     116: aload         10
     118: aload         5
     120: aload         10
     122: invokevirtual #16                 // Method org/springframework/core/env/EnumerablePropertySource.getProperty:(Ljava/lang/String;)Ljava/lang/Object;
     125: invokeinterface #17,  3           // InterfaceMethod java/util/Map.put:(Ljava/lang/Object;Ljava/lang/Object;)Ljava/lang/Object;
     130: pop
     131: iinc          9, 1
     134: goto          90
     137: goto          25
     140: aload_1
     141: areturn

  private static java.util.Map<java.lang.String, org.springframework.core.env.PropertySource<?>> doGetPropertySources(org.springframework.core.env.ConfigurableEnvironment);
    Code:
       0: new           #4                  // class java/util/LinkedHashMap
       3: dup
       4: invokespecial #5                  // Method java/util/LinkedHashMap."<init>":()V
       7: astore_1
       8: aload_0
       9: invokeinterface #18,  1           // InterfaceMethod org/springframework/core/env/ConfigurableEnvironment.getPropertySources:()Lorg/springframework/core/env/MutablePropertySources;
      14: astore_2
      15: aload_2
      16: invokevirtual #19                 // Method org/springframework/core/env/MutablePropertySources.iterator:()Ljava/util/Iterator;
      19: astore_3
      20: aload_3
      21: invokeinterface #9,  1            // InterfaceMethod java/util/Iterator.hasNext:()Z
      26: ifeq          51
      29: aload_3
      30: invokeinterface #10,  1           // InterfaceMethod java/util/Iterator.next:()Ljava/lang/Object;
      35: checkcast     #11                 // class org/springframework/core/env/PropertySource
      38: astore        4
      40: ldc           #20                 // String
      42: aload_1
      43: aload         4
      45: invokestatic  #21                 // Method extract:(Ljava/lang/String;Ljava/util/Map;Lorg/springframework/core/env/PropertySource;)V
      48: goto          20
      51: aload_1
      52: areturn

  private static void extract(java.lang.String, java.util.Map<java.lang.String, org.springframework.core.env.PropertySource<?>>, org.springframework.core.env.PropertySource<?>);
    Code:
       0: aload_2
       1: instanceof    #22                 // class org/springframework/core/env/CompositePropertySource
       4: ifeq          74
       7: aload_2
       8: checkcast     #22                 // class org/springframework/core/env/CompositePropertySource
      11: invokevirtual #23                 // Method org/springframework/core/env/CompositePropertySource.getPropertySources:()Ljava/util/Collection;
      14: invokeinterface #8,  1            // InterfaceMethod java/util/Collection.iterator:()Ljava/util/Iterator;
      19: astore_3
      20: aload_3
      21: invokeinterface #9,  1            // InterfaceMethod java/util/Iterator.hasNext:()Z
      26: ifeq          71
      29: aload_3
      30: invokeinterface #10,  1           // InterfaceMethod java/util/Iterator.next:()Ljava/lang/Object;
      35: checkcast     #11                 // class org/springframework/core/env/PropertySource
      38: astore        4
      40: new           #24                 // class java/lang/StringBuilder
      43: dup
      44: invokespecial #25                 // Method java/lang/StringBuilder."<init>":()V
      47: aload_2
      48: invokevirtual #26                 // Method org/springframework/core/env/PropertySource.getName:()Ljava/lang/String;
      51: invokevirtual #27                 // Method java/lang/StringBuilder.append:(Ljava/lang/String;)Ljava/lang/StringBuilder;
      54: ldc           #28                 // String :
      56: invokevirtual #27                 // Method java/lang/StringBuilder.append:(Ljava/lang/String;)Ljava/lang/StringBuilder;
      59: invokevirtual #29                 // Method java/lang/StringBuilder.toString:()Ljava/lang/String;
      62: aload_1
      63: aload         4
      65: invokestatic  #21                 // Method extract:(Ljava/lang/String;Ljava/util/Map;Lorg/springframework/core/env/PropertySource;)V
      68: goto          20
      71: goto          103
      74: aload_1
      75: new           #24                 // class java/lang/StringBuilder
      78: dup
      79: invokespecial #25                 // Method java/lang/StringBuilder."<init>":()V
      82: aload_0
      83: invokevirtual #27                 // Method java/lang/StringBuilder.append:(Ljava/lang/String;)Ljava/lang/StringBuilder;
      86: aload_2
      87: invokevirtual #26                 // Method org/springframework/core/env/PropertySource.getName:()Ljava/lang/String;
      90: invokevirtual #27                 // Method java/lang/StringBuilder.append:(Ljava/lang/String;)Ljava/lang/StringBuilder;
      93: invokevirtual #29                 // Method java/lang/StringBuilder.toString:()Ljava/lang/String;
      96: aload_2
      97: invokeinterface #17,  3           // InterfaceMethod java/util/Map.put:(Ljava/lang/Object;Ljava/lang/Object;)Ljava/lang/Object;
     102: pop
     103: return

  public static java.util.SortedMap<java.lang.String, java.lang.String> filterDubboProperties(org.springframework.core.env.ConfigurableEnvironment);
    Code:
       0: new           #30                 // class java/util/TreeMap
       3: dup
       4: invokespecial #31                 // Method java/util/TreeMap."<init>":()V
       7: astore_1
       8: aload_0
       9: invokestatic  #32                 // Method extractProperties:(Lorg/springframework/core/env/ConfigurableEnvironment;)Ljava/util/Map;
      12: astore_2
      13: aload_2
      14: invokeinterface #33,  1           // InterfaceMethod java/util/Map.entrySet:()Ljava/util/Set;
      19: invokeinterface #34,  1           // InterfaceMethod java/util/Set.iterator:()Ljava/util/Iterator;
      24: astore_3
      25: aload_3
      26: invokeinterface #9,  1            // InterfaceMethod java/util/Iterator.hasNext:()Z
      31: ifeq          105
      34: aload_3
      35: invokeinterface #10,  1           // InterfaceMethod java/util/Iterator.next:()Ljava/lang/Object;
      40: checkcast     #35                 // class java/util/Map$Entry
      43: astore        4
      45: aload         4
      47: invokeinterface #36,  1           // InterfaceMethod java/util/Map$Entry.getKey:()Ljava/lang/Object;
      52: checkcast     #37                 // class java/lang/String
      55: astore        5
      57: aload         5
      59: ldc           #39                 // String dubbo.
      61: invokevirtual #40                 // Method java/lang/String.startsWith:(Ljava/lang/String;)Z
      64: ifeq          102
      67: aload         4
      69: invokeinterface #41,  1           // InterfaceMethod java/util/Map$Entry.getValue:()Ljava/lang/Object;
      74: ifnull        102
      77: aload_1
      78: aload         5
      80: aload_0
      81: aload         4
      83: invokeinterface #41,  1           // InterfaceMethod java/util/Map$Entry.getValue:()Ljava/lang/Object;
      88: invokevirtual #42                 // Method java/lang/Object.toString:()Ljava/lang/String;
      91: invokeinterface #43,  2           // InterfaceMethod org/springframework/core/env/ConfigurableEnvironment.resolvePlaceholders:(Ljava/lang/String;)Ljava/lang/String;
      96: invokeinterface #44,  3           // InterfaceMethod java/util/SortedMap.put:(Ljava/lang/Object;Ljava/lang/Object;)Ljava/lang/Object;
     101: pop
     102: goto          25
     105: aload_1
     106: invokestatic  #45                 // Method java/util/Collections.unmodifiableSortedMap:(Ljava/util/SortedMap;)Ljava/util/SortedMap;
     109: areturn
}
