Compiled from "SpringCompatUtils.java"
public class org.apache.dubbo.config.spring.util.SpringCompatUtils {
  private static volatile java.lang.Boolean factoryMethodMetadataEnabled;

  private static final org.apache.commons.logging.Log logger;

  public org.apache.dubbo.config.spring.util.SpringCompatUtils();
    Code:
       0: aload_0
       1: invokespecial #1                  // Method java/lang/Object."<init>":()V
       4: return

  public static <T> T getPropertyValue(org.springframework.beans.PropertyValues, java.lang.String);
    Code:
       0: aload_0
       1: aload_1
       2: invokeinterface #2,  2            // InterfaceMethod org/springframework/beans/PropertyValues.getPropertyValue:(Ljava/lang/String;)Lorg/springframework/beans/PropertyValue;
       7: astore_2
       8: aload_2
       9: ifnull        19
      12: aload_2
      13: invokevirtual #3                  // Method org/springframework/beans/PropertyValue.getValue:()Ljava/lang/Object;
      16: goto          20
      19: aconst_null
      20: astore_3
      21: aload_3
      22: instanceof    #4                  // class org/springframework/beans/factory/config/TypedStringValue
      25: ifeq          40
      28: aload_3
      29: checkcast     #4                  // class org/springframework/beans/factory/config/TypedStringValue
      32: astore        4
      34: aload         4
      36: invokevirtual #5                  // Method org/springframework/beans/factory/config/TypedStringValue.getValue:()Ljava/lang/String;
      39: areturn
      40: aload_3
      41: areturn

  public static boolean isFactoryMethodMetadataEnabled();
    Code:
       0: getstatic     #6                  // Field factoryMethodMetadataEnabled:Ljava/lang/Boolean;
       3: ifnonnull     48
       6: ldc           #7                  // class org/springframework/beans/factory/annotation/AnnotatedBeanDefinition
       8: ldc           #8                  // String getFactoryMethodMetadata
      10: iconst_0
      11: anewarray     #9                  // class java/lang/Class
      14: invokevirtual #10                 // Method java/lang/Class.getMethod:(Ljava/lang/String;[Ljava/lang/Class;)Ljava/lang/reflect/Method;
      17: pop
      18: ldc           #11                 // class org/springframework/core/type/MethodMetadata
      20: ldc           #12                 // String getReturnTypeName
      22: iconst_0
      23: anewarray     #9                  // class java/lang/Class
      26: invokevirtual #10                 // Method java/lang/Class.getMethod:(Ljava/lang/String;[Ljava/lang/Class;)Ljava/lang/reflect/Method;
      29: pop
      30: iconst_1
      31: invokestatic  #13                 // Method java/lang/Boolean.valueOf:(Z)Ljava/lang/Boolean;
      34: putstatic     #6                  // Field factoryMethodMetadataEnabled:Ljava/lang/Boolean;
      37: goto          48
      40: astore_0
      41: iconst_0
      42: invokestatic  #13                 // Method java/lang/Boolean.valueOf:(Z)Ljava/lang/Boolean;
      45: putstatic     #6                  // Field factoryMethodMetadataEnabled:Ljava/lang/Boolean;
      48: getstatic     #6                  // Field factoryMethodMetadataEnabled:Ljava/lang/Boolean;
      51: invokevirtual #15                 // Method java/lang/Boolean.booleanValue:()Z
      54: ireturn
    Exception table:
       from    to  target type
           6    37    40   Class java/lang/NoSuchMethodException

  public static java.lang.String getFactoryMethodReturnType(org.springframework.beans.factory.annotation.AnnotatedBeanDefinition);
    Code:
       0: invokestatic  #16                 // Method isFactoryMethodMetadataEnabled:()Z
       3: ifeq          28
       6: aload_0
       7: invokeinterface #17,  1           // InterfaceMethod org/springframework/beans/factory/annotation/AnnotatedBeanDefinition.getFactoryMethodMetadata:()Lorg/springframework/core/type/MethodMetadata;
      12: astore_1
      13: aload_1
      14: ifnull        26
      17: aload_1
      18: invokeinterface #18,  1           // InterfaceMethod org/springframework/core/type/MethodMetadata.getReturnTypeName:()Ljava/lang/String;
      23: goto          27
      26: aconst_null
      27: areturn
      28: aload_0
      29: invokeinterface #19,  1           // InterfaceMethod org/springframework/beans/factory/annotation/AnnotatedBeanDefinition.getSource:()Ljava/lang/Object;
      34: astore_1
      35: aload_1
      36: instanceof    #20                 // class org/springframework/core/type/StandardMethodMetadata
      39: ifeq          64
      42: aload_1
      43: checkcast     #20                 // class org/springframework/core/type/StandardMethodMetadata
      46: astore_2
      47: aload_2
      48: invokevirtual #21                 // Method org/springframework/core/type/StandardMethodMetadata.getIntrospectedMethod:()Ljava/lang/reflect/Method;
      51: astore_3
      52: aload_3
      53: ifnull        64
      56: aload_3
      57: invokevirtual #22                 // Method java/lang/reflect/Method.getReturnType:()Ljava/lang/Class;
      60: invokevirtual #23                 // Method java/lang/Class.getName:()Ljava/lang/String;
      63: areturn
      64: goto          90
      67: astore_1
      68: getstatic     #25                 // Field logger:Lorg/apache/commons/logging/Log;
      71: invokeinterface #26,  1           // InterfaceMethod org/apache/commons/logging/Log.isInfoEnabled:()Z
      76: ifeq          90
      79: getstatic     #25                 // Field logger:Lorg/apache/commons/logging/Log;
      82: ldc           #27                 // String get return type of AnnotatedBeanDefinition failed
      84: aload_1
      85: invokeinterface #28,  3           // InterfaceMethod org/apache/commons/logging/Log.info:(Ljava/lang/Object;Ljava/lang/Throwable;)V
      90: aconst_null
      91: areturn
    Exception table:
       from    to  target type
           0    27    67   Class java/lang/Throwable
          28    63    67   Class java/lang/Throwable

  public static org.springframework.core.type.MethodMetadata getFactoryMethodMetadata(org.springframework.beans.factory.annotation.AnnotatedBeanDefinition);
    Code:
       0: invokestatic  #16                 // Method isFactoryMethodMetadataEnabled:()Z
       3: ifeq          13
       6: aload_0
       7: invokeinterface #17,  1           // InterfaceMethod org/springframework/beans/factory/annotation/AnnotatedBeanDefinition.getFactoryMethodMetadata:()Lorg/springframework/core/type/MethodMetadata;
      12: areturn
      13: aload_0
      14: invokeinterface #19,  1           // InterfaceMethod org/springframework/beans/factory/annotation/AnnotatedBeanDefinition.getSource:()Ljava/lang/Object;
      19: astore_1
      20: aload_1
      21: instanceof    #20                 // class org/springframework/core/type/StandardMethodMetadata
      24: ifeq          32
      27: aload_1
      28: checkcast     #11                 // class org/springframework/core/type/MethodMetadata
      31: areturn
      32: aconst_null
      33: areturn

  public static java.lang.Class getGenericTypeOfReturnType(org.springframework.core.type.MethodMetadata);
    Code:
       0: aload_0
       1: instanceof    #20                 // class org/springframework/core/type/StandardMethodMetadata
       4: ifeq          56
       7: aload_0
       8: checkcast     #20                 // class org/springframework/core/type/StandardMethodMetadata
      11: invokevirtual #21                 // Method org/springframework/core/type/StandardMethodMetadata.getIntrospectedMethod:()Ljava/lang/reflect/Method;
      14: astore_1
      15: aload_1
      16: invokevirtual #29                 // Method java/lang/reflect/Method.getGenericReturnType:()Ljava/lang/reflect/Type;
      19: astore_2
      20: aload_2
      21: instanceof    #30                 // class java/lang/reflect/ParameterizedType
      24: ifeq          56
      27: aload_2
      28: checkcast     #30                 // class java/lang/reflect/ParameterizedType
      31: astore_3
      32: aload_3
      33: invokeinterface #31,  1           // InterfaceMethod java/lang/reflect/ParameterizedType.getActualTypeArguments:()[Ljava/lang/reflect/Type;
      38: iconst_0
      39: aaload
      40: astore        4
      42: aload         4
      44: instanceof    #9                  // class java/lang/Class
      47: ifeq          56
      50: aload         4
      52: checkcast     #9                  // class java/lang/Class
      55: areturn
      56: aconst_null
      57: areturn

  static {};
    Code:
       0: aconst_null
       1: putstatic     #6                  // Field factoryMethodMetadataEnabled:Ljava/lang/Boolean;
       4: ldc           #32                 // class org/apache/dubbo/config/spring/util/SpringCompatUtils
       6: invokestatic  #33                 // Method org/apache/commons/logging/LogFactory.getLog:(Ljava/lang/Class;)Lorg/apache/commons/logging/Log;
       9: putstatic     #25                 // Field logger:Lorg/apache/commons/logging/Log;
      12: return
}
