Compiled from "MaxiCodeReader.java"
public final class com.google.zxing.maxicode.MaxiCodeReader implements com.google.zxing.Reader {
  private static final com.google.zxing.ResultPoint[] NO_POINTS;

  private static final int MATRIX_WIDTH;

  private static final int MATRIX_HEIGHT;

  private final com.google.zxing.maxicode.decoder.Decoder decoder;

  public com.google.zxing.maxicode.MaxiCodeReader();
    Code:
       0: aload_0
       1: invokespecial #1                  // Method java/lang/Object."<init>":()V
       4: aload_0
       5: new           #2                  // class com/google/zxing/maxicode/decoder/Decoder
       8: dup
       9: invokespecial #3                  // Method com/google/zxing/maxicode/decoder/Decoder."<init>":()V
      12: putfield      #4                  // Field decoder:Lcom/google/zxing/maxicode/decoder/Decoder;
      15: return

  public com.google.zxing.Result decode(com.google.zxing.BinaryBitmap) throws com.google.zxing.NotFoundException, com.google.zxing.ChecksumException, com.google.zxing.FormatException;
    Code:
       0: aload_0
       1: aload_1
       2: aconst_null
       3: invokevirtual #5                  // Method decode:(Lcom/google/zxing/BinaryBitmap;Ljava/util/Map;)Lcom/google/zxing/Result;
       6: areturn

  public com.google.zxing.Result decode(com.google.zxing.BinaryBitmap, java.util.Map<com.google.zxing.DecodeHintType, ?>) throws com.google.zxing.NotFoundException, com.google.zxing.ChecksumException, com.google.zxing.FormatException;
    Code:
       0: aload_1
       1: invokevirtual #6                  // Method com/google/zxing/BinaryBitmap.getBlackMatrix:()Lcom/google/zxing/common/BitMatrix;
       4: invokestatic  #7                  // Method extractPureBits:(Lcom/google/zxing/common/BitMatrix;)Lcom/google/zxing/common/BitMatrix;
       7: astore_3
       8: aload_0
       9: getfield      #4                  // Field decoder:Lcom/google/zxing/maxicode/decoder/Decoder;
      12: aload_3
      13: aload_2
      14: invokevirtual #8                  // Method com/google/zxing/maxicode/decoder/Decoder.decode:(Lcom/google/zxing/common/BitMatrix;Ljava/util/Map;)Lcom/google/zxing/common/DecoderResult;
      17: astore        4
      19: new           #9                  // class com/google/zxing/Result
      22: dup
      23: aload         4
      25: invokevirtual #10                 // Method com/google/zxing/common/DecoderResult.getText:()Ljava/lang/String;
      28: aload         4
      30: invokevirtual #11                 // Method com/google/zxing/common/DecoderResult.getRawBytes:()[B
      33: getstatic     #12                 // Field NO_POINTS:[Lcom/google/zxing/ResultPoint;
      36: getstatic     #13                 // Field com/google/zxing/BarcodeFormat.MAXICODE:Lcom/google/zxing/BarcodeFormat;
      39: invokespecial #14                 // Method com/google/zxing/Result."<init>":(Ljava/lang/String;[B[Lcom/google/zxing/ResultPoint;Lcom/google/zxing/BarcodeFormat;)V
      42: astore        5
      44: aload         4
      46: invokevirtual #15                 // Method com/google/zxing/common/DecoderResult.getECLevel:()Ljava/lang/String;
      49: astore        6
      51: aload         6
      53: ifnull        66
      56: aload         5
      58: getstatic     #16                 // Field com/google/zxing/ResultMetadataType.ERROR_CORRECTION_LEVEL:Lcom/google/zxing/ResultMetadataType;
      61: aload         6
      63: invokevirtual #17                 // Method com/google/zxing/Result.putMetadata:(Lcom/google/zxing/ResultMetadataType;Ljava/lang/Object;)V
      66: aload         5
      68: areturn

  public void reset();
    Code:
       0: return

  private static com.google.zxing.common.BitMatrix extractPureBits(com.google.zxing.common.BitMatrix) throws com.google.zxing.NotFoundException;
    Code:
       0: aload_0
       1: invokevirtual #18                 // Method com/google/zxing/common/BitMatrix.getEnclosingRectangle:()[I
       4: astore_1
       5: aload_1
       6: ifnonnull     13
       9: invokestatic  #19                 // Method com/google/zxing/NotFoundException.getNotFoundInstance:()Lcom/google/zxing/NotFoundException;
      12: athrow
      13: aload_1
      14: iconst_0
      15: iaload
      16: istore_2
      17: aload_1
      18: iconst_1
      19: iaload
      20: istore_3
      21: aload_1
      22: iconst_2
      23: iaload
      24: istore        4
      26: aload_1
      27: iconst_3
      28: iaload
      29: istore        5
      31: new           #20                 // class com/google/zxing/common/BitMatrix
      34: dup
      35: bipush        30
      37: bipush        33
      39: invokespecial #22                 // Method com/google/zxing/common/BitMatrix."<init>":(II)V
      42: astore        6
      44: iconst_0
      45: istore        7
      47: iload         7
      49: bipush        33
      51: if_icmpge     154
      54: iload_3
      55: iload         7
      57: iload         5
      59: imul
      60: iload         5
      62: iconst_2
      63: idiv
      64: iadd
      65: bipush        33
      67: idiv
      68: iadd
      69: iload         5
      71: iconst_1
      72: isub
      73: invokestatic  #23                 // Method java/lang/Math.min:(II)I
      76: istore        8
      78: iconst_0
      79: istore        9
      81: iload         9
      83: bipush        30
      85: if_icmpge     148
      88: iload_2
      89: iload         9
      91: iload         4
      93: imul
      94: iload         4
      96: iconst_2
      97: idiv
      98: iadd
      99: iload         7
     101: iconst_1
     102: iand
     103: iload         4
     105: imul
     106: iconst_2
     107: idiv
     108: iadd
     109: bipush        30
     111: idiv
     112: iload         4
     114: iconst_1
     115: isub
     116: invokestatic  #23                 // Method java/lang/Math.min:(II)I
     119: iadd
     120: istore        10
     122: aload_0
     123: iload         10
     125: iload         8
     127: invokevirtual #24                 // Method com/google/zxing/common/BitMatrix.get:(II)Z
     130: ifeq          142
     133: aload         6
     135: iload         9
     137: iload         7
     139: invokevirtual #25                 // Method com/google/zxing/common/BitMatrix.set:(II)V
     142: iinc          9, 1
     145: goto          81
     148: iinc          7, 1
     151: goto          47
     154: aload         6
     156: areturn

  static {};
    Code:
       0: iconst_0
       1: anewarray     #26                 // class com/google/zxing/ResultPoint
       4: putstatic     #12                 // Field NO_POINTS:[Lcom/google/zxing/ResultPoint;
       7: return
}
