Compiled from "CategoryOverall.java"
public class org.apache.dubbo.metrics.model.key.CategoryOverall {
  private final org.apache.dubbo.metrics.model.key.MetricsCat post;

  private org.apache.dubbo.metrics.model.key.MetricsCat finish;

  private org.apache.dubbo.metrics.model.key.MetricsCat error;

  public org.apache.dubbo.metrics.model.key.CategoryOverall(org.apache.dubbo.metrics.model.key.MetricsPlaceValue, org.apache.dubbo.metrics.model.key.MetricsCat, org.apache.dubbo.metrics.model.key.MetricsCat, org.apache.dubbo.metrics.model.key.MetricsCat);
    Code:
       0: aload_0
       1: invokespecial #1                  // Method java/lang/Object."<init>":()V
       4: aload_0
       5: aload_2
       6: aload_1
       7: invokevirtual #2                  // Method org/apache/dubbo/metrics/model/key/MetricsCat.setPlaceType:(Lorg/apache/dubbo/metrics/model/key/MetricsPlaceValue;)Lorg/apache/dubbo/metrics/model/key/MetricsCat;
      10: putfield      #3                  // Field post:Lorg/apache/dubbo/metrics/model/key/MetricsCat;
      13: aload_3
      14: ifnull        26
      17: aload_0
      18: aload_3
      19: aload_1
      20: invokevirtual #2                  // Method org/apache/dubbo/metrics/model/key/MetricsCat.setPlaceType:(Lorg/apache/dubbo/metrics/model/key/MetricsPlaceValue;)Lorg/apache/dubbo/metrics/model/key/MetricsCat;
      23: putfield      #4                  // Field finish:Lorg/apache/dubbo/metrics/model/key/MetricsCat;
      26: aload         4
      28: ifnull        41
      31: aload_0
      32: aload         4
      34: aload_1
      35: invokevirtual #2                  // Method org/apache/dubbo/metrics/model/key/MetricsCat.setPlaceType:(Lorg/apache/dubbo/metrics/model/key/MetricsPlaceValue;)Lorg/apache/dubbo/metrics/model/key/MetricsCat;
      38: putfield      #5                  // Field error:Lorg/apache/dubbo/metrics/model/key/MetricsCat;
      41: return

  public org.apache.dubbo.metrics.model.key.MetricsCat getPost();
    Code:
       0: aload_0
       1: getfield      #3                  // Field post:Lorg/apache/dubbo/metrics/model/key/MetricsCat;
       4: areturn

  public org.apache.dubbo.metrics.model.key.MetricsCat getFinish();
    Code:
       0: aload_0
       1: getfield      #4                  // Field finish:Lorg/apache/dubbo/metrics/model/key/MetricsCat;
       4: areturn

  public org.apache.dubbo.metrics.model.key.MetricsCat getError();
    Code:
       0: aload_0
       1: getfield      #5                  // Field error:Lorg/apache/dubbo/metrics/model/key/MetricsCat;
       4: areturn
}
