Compiled from "MetricsKey.java"
public final class org.apache.dubbo.metrics.model.key.MetricsKey extends java.lang.Enum<org.apache.dubbo.metrics.model.key.MetricsKey> {
  public static final org.apache.dubbo.metrics.model.key.MetricsKey APPLICATION_METRIC_INFO;

  public static final org.apache.dubbo.metrics.model.key.MetricsKey CONFIGCENTER_METRIC_TOTAL;

  public static final org.apache.dubbo.metrics.model.key.MetricsKey METRIC_REQUESTS;

  public static final org.apache.dubbo.metrics.model.key.MetricsKey METRIC_REQUESTS_SUCCEED;

  public static final org.apache.dubbo.metrics.model.key.MetricsKey METRIC_REQUEST_BUSINESS_FAILED;

  public static final org.apache.dubbo.metrics.model.key.MetricsKey METRIC_REQUESTS_PROCESSING;

  public static final org.apache.dubbo.metrics.model.key.MetricsKey METRIC_REQUESTS_TIMEOUT;

  public static final org.apache.dubbo.metrics.model.key.MetricsKey METRIC_REQUESTS_LIMIT;

  public static final org.apache.dubbo.metrics.model.key.MetricsKey METRIC_REQUESTS_FAILED;

  public static final org.apache.dubbo.metrics.model.key.MetricsKey METRIC_REQUESTS_TOTAL_FAILED;

  public static final org.apache.dubbo.metrics.model.key.MetricsKey METRIC_REQUESTS_NETWORK_FAILED;

  public static final org.apache.dubbo.metrics.model.key.MetricsKey METRIC_REQUESTS_SERVICE_UNAVAILABLE_FAILED;

  public static final org.apache.dubbo.metrics.model.key.MetricsKey METRIC_REQUESTS_CODEC_FAILED;

  public static final org.apache.dubbo.metrics.model.key.MetricsKey METRIC_REQUESTS_TOTAL_AGG;

  public static final org.apache.dubbo.metrics.model.key.MetricsKey METRIC_REQUESTS_SUCCEED_AGG;

  public static final org.apache.dubbo.metrics.model.key.MetricsKey METRIC_REQUESTS_FAILED_AGG;

  public static final org.apache.dubbo.metrics.model.key.MetricsKey METRIC_REQUEST_BUSINESS_FAILED_AGG;

  public static final org.apache.dubbo.metrics.model.key.MetricsKey METRIC_REQUESTS_TIMEOUT_AGG;

  public static final org.apache.dubbo.metrics.model.key.MetricsKey METRIC_REQUESTS_LIMIT_AGG;

  public static final org.apache.dubbo.metrics.model.key.MetricsKey METRIC_REQUESTS_TOTAL_FAILED_AGG;

  public static final org.apache.dubbo.metrics.model.key.MetricsKey METRIC_REQUESTS_NETWORK_FAILED_AGG;

  public static final org.apache.dubbo.metrics.model.key.MetricsKey METRIC_REQUESTS_CODEC_FAILED_AGG;

  public static final org.apache.dubbo.metrics.model.key.MetricsKey METRIC_REQUESTS_TOTAL_SERVICE_UNAVAILABLE_FAILED_AGG;

  public static final org.apache.dubbo.metrics.model.key.MetricsKey METRIC_QPS;

  public static final org.apache.dubbo.metrics.model.key.MetricsKey METRIC_RT_LAST;

  public static final org.apache.dubbo.metrics.model.key.MetricsKey METRIC_RT_MIN;

  public static final org.apache.dubbo.metrics.model.key.MetricsKey METRIC_RT_MAX;

  public static final org.apache.dubbo.metrics.model.key.MetricsKey METRIC_RT_SUM;

  public static final org.apache.dubbo.metrics.model.key.MetricsKey METRIC_RT_AVG;

  public static final org.apache.dubbo.metrics.model.key.MetricsKey METRIC_RT_P99;

  public static final org.apache.dubbo.metrics.model.key.MetricsKey METRIC_RT_P95;

  public static final org.apache.dubbo.metrics.model.key.MetricsKey METRIC_RT_P90;

  public static final org.apache.dubbo.metrics.model.key.MetricsKey METRIC_RT_P50;

  public static final org.apache.dubbo.metrics.model.key.MetricsKey REGISTER_METRIC_REQUESTS;

  public static final org.apache.dubbo.metrics.model.key.MetricsKey REGISTER_METRIC_REQUESTS_SUCCEED;

  public static final org.apache.dubbo.metrics.model.key.MetricsKey REGISTER_METRIC_REQUESTS_FAILED;

  public static final org.apache.dubbo.metrics.model.key.MetricsKey METRIC_RT_HISTOGRAM;

  public static final org.apache.dubbo.metrics.model.key.MetricsKey GENERIC_METRIC_REQUESTS;

  public static final org.apache.dubbo.metrics.model.key.MetricsKey GENERIC_METRIC_REQUESTS_SUCCEED;

  public static final org.apache.dubbo.metrics.model.key.MetricsKey GENERIC_METRIC_REQUESTS_FAILED;

  public static final org.apache.dubbo.metrics.model.key.MetricsKey SUBSCRIBE_METRIC_NUM;

  public static final org.apache.dubbo.metrics.model.key.MetricsKey SUBSCRIBE_METRIC_NUM_SUCCEED;

  public static final org.apache.dubbo.metrics.model.key.MetricsKey SUBSCRIBE_METRIC_NUM_FAILED;

  public static final org.apache.dubbo.metrics.model.key.MetricsKey DIRECTORY_METRIC_NUM_ALL;

  public static final org.apache.dubbo.metrics.model.key.MetricsKey DIRECTORY_METRIC_NUM_VALID;

  public static final org.apache.dubbo.metrics.model.key.MetricsKey DIRECTORY_METRIC_NUM_TO_RECONNECT;

  public static final org.apache.dubbo.metrics.model.key.MetricsKey DIRECTORY_METRIC_NUM_DISABLE;

  public static final org.apache.dubbo.metrics.model.key.MetricsKey NOTIFY_METRIC_REQUESTS;

  public static final org.apache.dubbo.metrics.model.key.MetricsKey NOTIFY_METRIC_NUM_LAST;

  public static final org.apache.dubbo.metrics.model.key.MetricsKey THREAD_POOL_CORE_SIZE;

  public static final org.apache.dubbo.metrics.model.key.MetricsKey THREAD_POOL_LARGEST_SIZE;

  public static final org.apache.dubbo.metrics.model.key.MetricsKey THREAD_POOL_MAX_SIZE;

  public static final org.apache.dubbo.metrics.model.key.MetricsKey THREAD_POOL_ACTIVE_SIZE;

  public static final org.apache.dubbo.metrics.model.key.MetricsKey THREAD_POOL_THREAD_COUNT;

  public static final org.apache.dubbo.metrics.model.key.MetricsKey THREAD_POOL_QUEUE_SIZE;

  public static final org.apache.dubbo.metrics.model.key.MetricsKey THREAD_POOL_THREAD_REJECT_COUNT;

  public static final org.apache.dubbo.metrics.model.key.MetricsKey METADATA_PUSH_METRIC_NUM;

  public static final org.apache.dubbo.metrics.model.key.MetricsKey METADATA_PUSH_METRIC_NUM_SUCCEED;

  public static final org.apache.dubbo.metrics.model.key.MetricsKey METADATA_PUSH_METRIC_NUM_FAILED;

  public static final org.apache.dubbo.metrics.model.key.MetricsKey METADATA_SUBSCRIBE_METRIC_NUM;

  public static final org.apache.dubbo.metrics.model.key.MetricsKey METADATA_SUBSCRIBE_METRIC_NUM_SUCCEED;

  public static final org.apache.dubbo.metrics.model.key.MetricsKey METADATA_SUBSCRIBE_METRIC_NUM_FAILED;

  public static final org.apache.dubbo.metrics.model.key.MetricsKey SERVICE_REGISTER_METRIC_REQUESTS;

  public static final org.apache.dubbo.metrics.model.key.MetricsKey SERVICE_REGISTER_METRIC_REQUESTS_SUCCEED;

  public static final org.apache.dubbo.metrics.model.key.MetricsKey SERVICE_REGISTER_METRIC_REQUESTS_FAILED;

  public static final org.apache.dubbo.metrics.model.key.MetricsKey SERVICE_SUBSCRIBE_METRIC_NUM;

  public static final org.apache.dubbo.metrics.model.key.MetricsKey SERVICE_SUBSCRIBE_METRIC_NUM_SUCCEED;

  public static final org.apache.dubbo.metrics.model.key.MetricsKey SERVICE_SUBSCRIBE_METRIC_NUM_FAILED;

  public static final org.apache.dubbo.metrics.model.key.MetricsKey STORE_PROVIDER_METADATA;

  public static final org.apache.dubbo.metrics.model.key.MetricsKey STORE_PROVIDER_METADATA_SUCCEED;

  public static final org.apache.dubbo.metrics.model.key.MetricsKey STORE_PROVIDER_METADATA_FAILED;

  public static final org.apache.dubbo.metrics.model.key.MetricsKey METADATA_GIT_COMMITID_METRIC;

  public static final org.apache.dubbo.metrics.model.key.MetricsKey INVOKER_NO_AVAILABLE_COUNT;

  private java.lang.String name;

  private java.lang.String description;

  private static final org.apache.dubbo.metrics.model.key.MetricsKey[] $VALUES;

  public static org.apache.dubbo.metrics.model.key.MetricsKey[] values();
    Code:
       0: getstatic     #1                  // Field $VALUES:[Lorg/apache/dubbo/metrics/model/key/MetricsKey;
       3: invokevirtual #2                  // Method "[Lorg/apache/dubbo/metrics/model/key/MetricsKey;".clone:()Ljava/lang/Object;
       6: checkcast     #3                  // class "[Lorg/apache/dubbo/metrics/model/key/MetricsKey;"
       9: areturn

  public static org.apache.dubbo.metrics.model.key.MetricsKey valueOf(java.lang.String);
    Code:
       0: ldc           #4                  // class org/apache/dubbo/metrics/model/key/MetricsKey
       2: aload_0
       3: invokestatic  #5                  // Method java/lang/Enum.valueOf:(Ljava/lang/Class;Ljava/lang/String;)Ljava/lang/Enum;
       6: checkcast     #4                  // class org/apache/dubbo/metrics/model/key/MetricsKey
       9: areturn

  public final java.lang.String getName();
    Code:
       0: aload_0
       1: getfield      #6                  // Field name:Ljava/lang/String;
       4: areturn

  public final java.lang.String getNameByType(java.lang.String);
    Code:
       0: aload_0
       1: getfield      #6                  // Field name:Ljava/lang/String;
       4: iconst_1
       5: anewarray     #7                  // class java/lang/Object
       8: dup
       9: iconst_0
      10: aload_1
      11: aastore
      12: invokestatic  #8                  // Method java/lang/String.format:(Ljava/lang/String;[Ljava/lang/Object;)Ljava/lang/String;
      15: areturn

  public final org.apache.dubbo.metrics.model.key.MetricsKey formatName(java.lang.String);
    Code:
       0: aload_0
       1: aload_0
       2: getfield      #6                  // Field name:Ljava/lang/String;
       5: iconst_1
       6: anewarray     #7                  // class java/lang/Object
       9: dup
      10: iconst_0
      11: aload_1
      12: aastore
      13: invokestatic  #8                  // Method java/lang/String.format:(Ljava/lang/String;[Ljava/lang/Object;)Ljava/lang/String;
      16: putfield      #6                  // Field name:Ljava/lang/String;
      19: aload_0
      20: areturn

  public final java.lang.String getDescription();
    Code:
       0: aload_0
       1: getfield      #9                  // Field description:Ljava/lang/String;
       4: areturn

  private org.apache.dubbo.metrics.model.key.MetricsKey(java.lang.String, java.lang.String);
    Code:
       0: aload_0
       1: aload_1
       2: iload_2
       3: invokespecial #10                 // Method java/lang/Enum."<init>":(Ljava/lang/String;I)V
       6: aload_0
       7: aload_3
       8: putfield      #6                  // Field name:Ljava/lang/String;
      11: aload_0
      12: aload         4
      14: putfield      #9                  // Field description:Ljava/lang/String;
      17: return

  static {};
    Code:
       0: new           #4                  // class org/apache/dubbo/metrics/model/key/MetricsKey
       3: dup
       4: ldc           #11                 // String APPLICATION_METRIC_INFO
       6: iconst_0
       7: ldc           #12                 // String dubbo.application.info.total
       9: ldc           #13                 // String Total Application Info
      11: invokespecial #14                 // Method "<init>":(Ljava/lang/String;ILjava/lang/String;Ljava/lang/String;)V
      14: putstatic     #15                 // Field APPLICATION_METRIC_INFO:Lorg/apache/dubbo/metrics/model/key/MetricsKey;
      17: new           #4                  // class org/apache/dubbo/metrics/model/key/MetricsKey
      20: dup
      21: ldc           #16                 // String CONFIGCENTER_METRIC_TOTAL
      23: iconst_1
      24: ldc           #17                 // String dubbo.configcenter.total
      26: ldc           #18                 // String Config Changed Total
      28: invokespecial #14                 // Method "<init>":(Ljava/lang/String;ILjava/lang/String;Ljava/lang/String;)V
      31: putstatic     #19                 // Field CONFIGCENTER_METRIC_TOTAL:Lorg/apache/dubbo/metrics/model/key/MetricsKey;
      34: new           #4                  // class org/apache/dubbo/metrics/model/key/MetricsKey
      37: dup
      38: ldc           #20                 // String METRIC_REQUESTS
      40: iconst_2
      41: ldc           #21                 // String dubbo.%s.requests.total
      43: ldc           #22                 // String Total Requests
      45: invokespecial #14                 // Method "<init>":(Ljava/lang/String;ILjava/lang/String;Ljava/lang/String;)V
      48: putstatic     #23                 // Field METRIC_REQUESTS:Lorg/apache/dubbo/metrics/model/key/MetricsKey;
      51: new           #4                  // class org/apache/dubbo/metrics/model/key/MetricsKey
      54: dup
      55: ldc           #24                 // String METRIC_REQUESTS_SUCCEED
      57: iconst_3
      58: ldc           #25                 // String dubbo.%s.requests.succeed.total
      60: ldc           #26                 // String Total Succeed Requests
      62: invokespecial #14                 // Method "<init>":(Ljava/lang/String;ILjava/lang/String;Ljava/lang/String;)V
      65: putstatic     #27                 // Field METRIC_REQUESTS_SUCCEED:Lorg/apache/dubbo/metrics/model/key/MetricsKey;
      68: new           #4                  // class org/apache/dubbo/metrics/model/key/MetricsKey
      71: dup
      72: ldc           #28                 // String METRIC_REQUEST_BUSINESS_FAILED
      74: iconst_4
      75: ldc           #29                 // String dubbo.%s.requests.business.failed.total
      77: ldc           #30                 // String Total Failed Business Requests
      79: invokespecial #14                 // Method "<init>":(Ljava/lang/String;ILjava/lang/String;Ljava/lang/String;)V
      82: putstatic     #31                 // Field METRIC_REQUEST_BUSINESS_FAILED:Lorg/apache/dubbo/metrics/model/key/MetricsKey;
      85: new           #4                  // class org/apache/dubbo/metrics/model/key/MetricsKey
      88: dup
      89: ldc           #32                 // String METRIC_REQUESTS_PROCESSING
      91: iconst_5
      92: ldc           #33                 // String dubbo.%s.requests.processing
      94: ldc           #34                 // String Processing Requests
      96: invokespecial #14                 // Method "<init>":(Ljava/lang/String;ILjava/lang/String;Ljava/lang/String;)V
      99: putstatic     #35                 // Field METRIC_REQUESTS_PROCESSING:Lorg/apache/dubbo/metrics/model/key/MetricsKey;
     102: new           #4                  // class org/apache/dubbo/metrics/model/key/MetricsKey
     105: dup
     106: ldc           #36                 // String METRIC_REQUESTS_TIMEOUT
     108: bipush        6
     110: ldc           #37                 // String dubbo.%s.requests.timeout.total
     112: ldc           #38                 // String Total Timeout Failed Requests
     114: invokespecial #14                 // Method "<init>":(Ljava/lang/String;ILjava/lang/String;Ljava/lang/String;)V
     117: putstatic     #39                 // Field METRIC_REQUESTS_TIMEOUT:Lorg/apache/dubbo/metrics/model/key/MetricsKey;
     120: new           #4                  // class org/apache/dubbo/metrics/model/key/MetricsKey
     123: dup
     124: ldc           #40                 // String METRIC_REQUESTS_LIMIT
     126: bipush        7
     128: ldc           #41                 // String dubbo.%s.requests.limit.total
     130: ldc           #42                 // String Total Limit Failed Requests
     132: invokespecial #14                 // Method "<init>":(Ljava/lang/String;ILjava/lang/String;Ljava/lang/String;)V
     135: putstatic     #43                 // Field METRIC_REQUESTS_LIMIT:Lorg/apache/dubbo/metrics/model/key/MetricsKey;
     138: new           #4                  // class org/apache/dubbo/metrics/model/key/MetricsKey
     141: dup
     142: ldc           #44                 // String METRIC_REQUESTS_FAILED
     144: bipush        8
     146: ldc           #45                 // String dubbo.%s.requests.unknown.failed.total
     148: ldc           #46                 // String Total Unknown Failed Requests
     150: invokespecial #14                 // Method "<init>":(Ljava/lang/String;ILjava/lang/String;Ljava/lang/String;)V
     153: putstatic     #47                 // Field METRIC_REQUESTS_FAILED:Lorg/apache/dubbo/metrics/model/key/MetricsKey;
     156: new           #4                  // class org/apache/dubbo/metrics/model/key/MetricsKey
     159: dup
     160: ldc           #48                 // String METRIC_REQUESTS_TOTAL_FAILED
     162: bipush        9
     164: ldc           #49                 // String dubbo.%s.requests.failed.total
     166: ldc           #50                 // String Total Failed Requests
     168: invokespecial #14                 // Method "<init>":(Ljava/lang/String;ILjava/lang/String;Ljava/lang/String;)V
     171: putstatic     #51                 // Field METRIC_REQUESTS_TOTAL_FAILED:Lorg/apache/dubbo/metrics/model/key/MetricsKey;
     174: new           #4                  // class org/apache/dubbo/metrics/model/key/MetricsKey
     177: dup
     178: ldc           #52                 // String METRIC_REQUESTS_NETWORK_FAILED
     180: bipush        10
     182: ldc           #53                 // String dubbo.%s.requests.failed.network.total
     184: ldc           #54                 // String Total network Failed Requests
     186: invokespecial #14                 // Method "<init>":(Ljava/lang/String;ILjava/lang/String;Ljava/lang/String;)V
     189: putstatic     #55                 // Field METRIC_REQUESTS_NETWORK_FAILED:Lorg/apache/dubbo/metrics/model/key/MetricsKey;
     192: new           #4                  // class org/apache/dubbo/metrics/model/key/MetricsKey
     195: dup
     196: ldc           #56                 // String METRIC_REQUESTS_SERVICE_UNAVAILABLE_FAILED
     198: bipush        11
     200: ldc           #57                 // String dubbo.%s.requests.failed.service.unavailable.total
     202: ldc           #58                 // String Total Service Unavailable Failed Requests
     204: invokespecial #14                 // Method "<init>":(Ljava/lang/String;ILjava/lang/String;Ljava/lang/String;)V
     207: putstatic     #59                 // Field METRIC_REQUESTS_SERVICE_UNAVAILABLE_FAILED:Lorg/apache/dubbo/metrics/model/key/MetricsKey;
     210: new           #4                  // class org/apache/dubbo/metrics/model/key/MetricsKey
     213: dup
     214: ldc           #60                 // String METRIC_REQUESTS_CODEC_FAILED
     216: bipush        12
     218: ldc           #61                 // String dubbo.%s.requests.failed.codec.total
     220: ldc           #62                 // String Total Codec Failed Requests
     222: invokespecial #14                 // Method "<init>":(Ljava/lang/String;ILjava/lang/String;Ljava/lang/String;)V
     225: putstatic     #63                 // Field METRIC_REQUESTS_CODEC_FAILED:Lorg/apache/dubbo/metrics/model/key/MetricsKey;
     228: new           #4                  // class org/apache/dubbo/metrics/model/key/MetricsKey
     231: dup
     232: ldc           #64                 // String METRIC_REQUESTS_TOTAL_AGG
     234: bipush        13
     236: ldc           #65                 // String dubbo.%s.requests.total.aggregate
     238: ldc           #66                 // String Aggregated Total Requests
     240: invokespecial #14                 // Method "<init>":(Ljava/lang/String;ILjava/lang/String;Ljava/lang/String;)V
     243: putstatic     #67                 // Field METRIC_REQUESTS_TOTAL_AGG:Lorg/apache/dubbo/metrics/model/key/MetricsKey;
     246: new           #4                  // class org/apache/dubbo/metrics/model/key/MetricsKey
     249: dup
     250: ldc           #68                 // String METRIC_REQUESTS_SUCCEED_AGG
     252: bipush        14
     254: ldc           #69                 // String dubbo.%s.requests.succeed.aggregate
     256: ldc           #70                 // String Aggregated Succeed Requests
     258: invokespecial #14                 // Method "<init>":(Ljava/lang/String;ILjava/lang/String;Ljava/lang/String;)V
     261: putstatic     #71                 // Field METRIC_REQUESTS_SUCCEED_AGG:Lorg/apache/dubbo/metrics/model/key/MetricsKey;
     264: new           #4                  // class org/apache/dubbo/metrics/model/key/MetricsKey
     267: dup
     268: ldc           #72                 // String METRIC_REQUESTS_FAILED_AGG
     270: bipush        15
     272: ldc           #73                 // String dubbo.%s.requests.failed.aggregate
     274: ldc           #74                 // String Aggregated Failed Requests
     276: invokespecial #14                 // Method "<init>":(Ljava/lang/String;ILjava/lang/String;Ljava/lang/String;)V
     279: putstatic     #75                 // Field METRIC_REQUESTS_FAILED_AGG:Lorg/apache/dubbo/metrics/model/key/MetricsKey;
     282: new           #4                  // class org/apache/dubbo/metrics/model/key/MetricsKey
     285: dup
     286: ldc           #76                 // String METRIC_REQUEST_BUSINESS_FAILED_AGG
     288: bipush        16
     290: ldc           #77                 // String dubbo.%s.requests.business.failed.aggregate
     292: ldc           #78                 // String Aggregated Business Failed Requests
     294: invokespecial #14                 // Method "<init>":(Ljava/lang/String;ILjava/lang/String;Ljava/lang/String;)V
     297: putstatic     #79                 // Field METRIC_REQUEST_BUSINESS_FAILED_AGG:Lorg/apache/dubbo/metrics/model/key/MetricsKey;
     300: new           #4                  // class org/apache/dubbo/metrics/model/key/MetricsKey
     303: dup
     304: ldc           #80                 // String METRIC_REQUESTS_TIMEOUT_AGG
     306: bipush        17
     308: ldc           #81                 // String dubbo.%s.requests.timeout.failed.aggregate
     310: ldc           #82                 // String Aggregated timeout Failed Requests
     312: invokespecial #14                 // Method "<init>":(Ljava/lang/String;ILjava/lang/String;Ljava/lang/String;)V
     315: putstatic     #83                 // Field METRIC_REQUESTS_TIMEOUT_AGG:Lorg/apache/dubbo/metrics/model/key/MetricsKey;
     318: new           #4                  // class org/apache/dubbo/metrics/model/key/MetricsKey
     321: dup
     322: ldc           #84                 // String METRIC_REQUESTS_LIMIT_AGG
     324: bipush        18
     326: ldc           #85                 // String dubbo.%s.requests.limit.aggregate
     328: ldc           #86                 // String Aggregated limit Requests
     330: invokespecial #14                 // Method "<init>":(Ljava/lang/String;ILjava/lang/String;Ljava/lang/String;)V
     333: putstatic     #87                 // Field METRIC_REQUESTS_LIMIT_AGG:Lorg/apache/dubbo/metrics/model/key/MetricsKey;
     336: new           #4                  // class org/apache/dubbo/metrics/model/key/MetricsKey
     339: dup
     340: ldc           #88                 // String METRIC_REQUESTS_TOTAL_FAILED_AGG
     342: bipush        19
     344: ldc           #89                 // String dubbo.%s.requests.failed.total.aggregate
     346: ldc           #90                 // String Aggregated failed total Requests
     348: invokespecial #14                 // Method "<init>":(Ljava/lang/String;ILjava/lang/String;Ljava/lang/String;)V
     351: putstatic     #91                 // Field METRIC_REQUESTS_TOTAL_FAILED_AGG:Lorg/apache/dubbo/metrics/model/key/MetricsKey;
     354: new           #4                  // class org/apache/dubbo/metrics/model/key/MetricsKey
     357: dup
     358: ldc           #92                 // String METRIC_REQUESTS_NETWORK_FAILED_AGG
     360: bipush        20
     362: ldc           #93                 // String dubbo.%s.requests.failed.network.total.aggregate
     364: ldc           #94                 // String Aggregated failed network total Requests
     366: invokespecial #14                 // Method "<init>":(Ljava/lang/String;ILjava/lang/String;Ljava/lang/String;)V
     369: putstatic     #95                 // Field METRIC_REQUESTS_NETWORK_FAILED_AGG:Lorg/apache/dubbo/metrics/model/key/MetricsKey;
     372: new           #4                  // class org/apache/dubbo/metrics/model/key/MetricsKey
     375: dup
     376: ldc           #96                 // String METRIC_REQUESTS_CODEC_FAILED_AGG
     378: bipush        21
     380: ldc           #97                 // String dubbo.%s.requests.failed.codec.total.aggregate
     382: ldc           #98                 // String Aggregated failed codec total Requests
     384: invokespecial #14                 // Method "<init>":(Ljava/lang/String;ILjava/lang/String;Ljava/lang/String;)V
     387: putstatic     #99                 // Field METRIC_REQUESTS_CODEC_FAILED_AGG:Lorg/apache/dubbo/metrics/model/key/MetricsKey;
     390: new           #4                  // class org/apache/dubbo/metrics/model/key/MetricsKey
     393: dup
     394: ldc           #100                // String METRIC_REQUESTS_TOTAL_SERVICE_UNAVAILABLE_FAILED_AGG
     396: bipush        22
     398: ldc           #101                // String dubbo.%s.requests.failed.service.unavailable.total.aggregate
     400: ldc           #98                 // String Aggregated failed codec total Requests
     402: invokespecial #14                 // Method "<init>":(Ljava/lang/String;ILjava/lang/String;Ljava/lang/String;)V
     405: putstatic     #102                // Field METRIC_REQUESTS_TOTAL_SERVICE_UNAVAILABLE_FAILED_AGG:Lorg/apache/dubbo/metrics/model/key/MetricsKey;
     408: new           #4                  // class org/apache/dubbo/metrics/model/key/MetricsKey
     411: dup
     412: ldc           #103                // String METRIC_QPS
     414: bipush        23
     416: ldc           #104                // String dubbo.%s.qps.total
     418: ldc           #105                // String Query Per Seconds
     420: invokespecial #14                 // Method "<init>":(Ljava/lang/String;ILjava/lang/String;Ljava/lang/String;)V
     423: putstatic     #106                // Field METRIC_QPS:Lorg/apache/dubbo/metrics/model/key/MetricsKey;
     426: new           #4                  // class org/apache/dubbo/metrics/model/key/MetricsKey
     429: dup
     430: ldc           #107                // String METRIC_RT_LAST
     432: bipush        24
     434: ldc           #108                // String dubbo.%s.rt.milliseconds.last
     436: ldc           #109                // String Last Response Time
     438: invokespecial #14                 // Method "<init>":(Ljava/lang/String;ILjava/lang/String;Ljava/lang/String;)V
     441: putstatic     #110                // Field METRIC_RT_LAST:Lorg/apache/dubbo/metrics/model/key/MetricsKey;
     444: new           #4                  // class org/apache/dubbo/metrics/model/key/MetricsKey
     447: dup
     448: ldc           #111                // String METRIC_RT_MIN
     450: bipush        25
     452: ldc           #112                // String dubbo.%s.rt.milliseconds.min
     454: ldc           #113                // String Min Response Time
     456: invokespecial #14                 // Method "<init>":(Ljava/lang/String;ILjava/lang/String;Ljava/lang/String;)V
     459: putstatic     #114                // Field METRIC_RT_MIN:Lorg/apache/dubbo/metrics/model/key/MetricsKey;
     462: new           #4                  // class org/apache/dubbo/metrics/model/key/MetricsKey
     465: dup
     466: ldc           #115                // String METRIC_RT_MAX
     468: bipush        26
     470: ldc           #116                // String dubbo.%s.rt.milliseconds.max
     472: ldc           #117                // String Max Response Time
     474: invokespecial #14                 // Method "<init>":(Ljava/lang/String;ILjava/lang/String;Ljava/lang/String;)V
     477: putstatic     #118                // Field METRIC_RT_MAX:Lorg/apache/dubbo/metrics/model/key/MetricsKey;
     480: new           #4                  // class org/apache/dubbo/metrics/model/key/MetricsKey
     483: dup
     484: ldc           #119                // String METRIC_RT_SUM
     486: bipush        27
     488: ldc           #120                // String dubbo.%s.rt.milliseconds.sum
     490: ldc           #121                // String Sum Response Time
     492: invokespecial #14                 // Method "<init>":(Ljava/lang/String;ILjava/lang/String;Ljava/lang/String;)V
     495: putstatic     #122                // Field METRIC_RT_SUM:Lorg/apache/dubbo/metrics/model/key/MetricsKey;
     498: new           #4                  // class org/apache/dubbo/metrics/model/key/MetricsKey
     501: dup
     502: ldc           #123                // String METRIC_RT_AVG
     504: bipush        28
     506: ldc           #124                // String dubbo.%s.rt.milliseconds.avg
     508: ldc           #125                // String Average Response Time
     510: invokespecial #14                 // Method "<init>":(Ljava/lang/String;ILjava/lang/String;Ljava/lang/String;)V
     513: putstatic     #126                // Field METRIC_RT_AVG:Lorg/apache/dubbo/metrics/model/key/MetricsKey;
     516: new           #4                  // class org/apache/dubbo/metrics/model/key/MetricsKey
     519: dup
     520: ldc           #127                // String METRIC_RT_P99
     522: bipush        29
     524: ldc           #128                // String dubbo.%s.rt.milliseconds.p99
     526: ldc           #129                // String Response Time P99
     528: invokespecial #14                 // Method "<init>":(Ljava/lang/String;ILjava/lang/String;Ljava/lang/String;)V
     531: putstatic     #130                // Field METRIC_RT_P99:Lorg/apache/dubbo/metrics/model/key/MetricsKey;
     534: new           #4                  // class org/apache/dubbo/metrics/model/key/MetricsKey
     537: dup
     538: ldc           #131                // String METRIC_RT_P95
     540: bipush        30
     542: ldc           #132                // String dubbo.%s.rt.milliseconds.p95
     544: ldc           #133                // String Response Time P95
     546: invokespecial #14                 // Method "<init>":(Ljava/lang/String;ILjava/lang/String;Ljava/lang/String;)V
     549: putstatic     #134                // Field METRIC_RT_P95:Lorg/apache/dubbo/metrics/model/key/MetricsKey;
     552: new           #4                  // class org/apache/dubbo/metrics/model/key/MetricsKey
     555: dup
     556: ldc           #135                // String METRIC_RT_P90
     558: bipush        31
     560: ldc           #136                // String dubbo.%s.rt.milliseconds.p90
     562: ldc           #137                // String Response Time P90
     564: invokespecial #14                 // Method "<init>":(Ljava/lang/String;ILjava/lang/String;Ljava/lang/String;)V
     567: putstatic     #138                // Field METRIC_RT_P90:Lorg/apache/dubbo/metrics/model/key/MetricsKey;
     570: new           #4                  // class org/apache/dubbo/metrics/model/key/MetricsKey
     573: dup
     574: ldc           #139                // String METRIC_RT_P50
     576: bipush        32
     578: ldc           #140                // String dubbo.%s.rt.milliseconds.p50
     580: ldc           #141                // String Response Time P50
     582: invokespecial #14                 // Method "<init>":(Ljava/lang/String;ILjava/lang/String;Ljava/lang/String;)V
     585: putstatic     #142                // Field METRIC_RT_P50:Lorg/apache/dubbo/metrics/model/key/MetricsKey;
     588: new           #4                  // class org/apache/dubbo/metrics/model/key/MetricsKey
     591: dup
     592: ldc           #143                // String REGISTER_METRIC_REQUESTS
     594: bipush        33
     596: ldc           #144                // String dubbo.registry.register.requests.total
     598: ldc           #145                // String Total Register Requests
     600: invokespecial #14                 // Method "<init>":(Ljava/lang/String;ILjava/lang/String;Ljava/lang/String;)V
     603: putstatic     #146                // Field REGISTER_METRIC_REQUESTS:Lorg/apache/dubbo/metrics/model/key/MetricsKey;
     606: new           #4                  // class org/apache/dubbo/metrics/model/key/MetricsKey
     609: dup
     610: ldc           #147                // String REGISTER_METRIC_REQUESTS_SUCCEED
     612: bipush        34
     614: ldc           #148                // String dubbo.registry.register.requests.succeed.total
     616: ldc           #149                // String Succeed Register Requests
     618: invokespecial #14                 // Method "<init>":(Ljava/lang/String;ILjava/lang/String;Ljava/lang/String;)V
     621: putstatic     #150                // Field REGISTER_METRIC_REQUESTS_SUCCEED:Lorg/apache/dubbo/metrics/model/key/MetricsKey;
     624: new           #4                  // class org/apache/dubbo/metrics/model/key/MetricsKey
     627: dup
     628: ldc           #151                // String REGISTER_METRIC_REQUESTS_FAILED
     630: bipush        35
     632: ldc           #152                // String dubbo.registry.register.requests.failed.total
     634: ldc           #153                // String Failed Register Requests
     636: invokespecial #14                 // Method "<init>":(Ljava/lang/String;ILjava/lang/String;Ljava/lang/String;)V
     639: putstatic     #154                // Field REGISTER_METRIC_REQUESTS_FAILED:Lorg/apache/dubbo/metrics/model/key/MetricsKey;
     642: new           #4                  // class org/apache/dubbo/metrics/model/key/MetricsKey
     645: dup
     646: ldc           #155                // String METRIC_RT_HISTOGRAM
     648: bipush        36
     650: ldc           #156                // String dubbo.%s.rt.milliseconds.histogram
     652: ldc           #157                // String Response Time Histogram
     654: invokespecial #14                 // Method "<init>":(Ljava/lang/String;ILjava/lang/String;Ljava/lang/String;)V
     657: putstatic     #158                // Field METRIC_RT_HISTOGRAM:Lorg/apache/dubbo/metrics/model/key/MetricsKey;
     660: new           #4                  // class org/apache/dubbo/metrics/model/key/MetricsKey
     663: dup
     664: ldc           #159                // String GENERIC_METRIC_REQUESTS
     666: bipush        37
     668: ldc           #21                 // String dubbo.%s.requests.total
     670: ldc           #160                // String Total %s Requests
     672: invokespecial #14                 // Method "<init>":(Ljava/lang/String;ILjava/lang/String;Ljava/lang/String;)V
     675: putstatic     #161                // Field GENERIC_METRIC_REQUESTS:Lorg/apache/dubbo/metrics/model/key/MetricsKey;
     678: new           #4                  // class org/apache/dubbo/metrics/model/key/MetricsKey
     681: dup
     682: ldc           #162                // String GENERIC_METRIC_REQUESTS_SUCCEED
     684: bipush        38
     686: ldc           #25                 // String dubbo.%s.requests.succeed.total
     688: ldc           #163                // String Succeed %s Requests
     690: invokespecial #14                 // Method "<init>":(Ljava/lang/String;ILjava/lang/String;Ljava/lang/String;)V
     693: putstatic     #164                // Field GENERIC_METRIC_REQUESTS_SUCCEED:Lorg/apache/dubbo/metrics/model/key/MetricsKey;
     696: new           #4                  // class org/apache/dubbo/metrics/model/key/MetricsKey
     699: dup
     700: ldc           #165                // String GENERIC_METRIC_REQUESTS_FAILED
     702: bipush        39
     704: ldc           #49                 // String dubbo.%s.requests.failed.total
     706: ldc           #166                // String Failed %s Requests
     708: invokespecial #14                 // Method "<init>":(Ljava/lang/String;ILjava/lang/String;Ljava/lang/String;)V
     711: putstatic     #167                // Field GENERIC_METRIC_REQUESTS_FAILED:Lorg/apache/dubbo/metrics/model/key/MetricsKey;
     714: new           #4                  // class org/apache/dubbo/metrics/model/key/MetricsKey
     717: dup
     718: ldc           #168                // String SUBSCRIBE_METRIC_NUM
     720: bipush        40
     722: ldc           #169                // String dubbo.registry.subscribe.num.total
     724: ldc           #170                // String Total Subscribe Num
     726: invokespecial #14                 // Method "<init>":(Ljava/lang/String;ILjava/lang/String;Ljava/lang/String;)V
     729: putstatic     #171                // Field SUBSCRIBE_METRIC_NUM:Lorg/apache/dubbo/metrics/model/key/MetricsKey;
     732: new           #4                  // class org/apache/dubbo/metrics/model/key/MetricsKey
     735: dup
     736: ldc           #172                // String SUBSCRIBE_METRIC_NUM_SUCCEED
     738: bipush        41
     740: ldc           #173                // String dubbo.registry.subscribe.num.succeed.total
     742: ldc           #174                // String Succeed Subscribe Num
     744: invokespecial #14                 // Method "<init>":(Ljava/lang/String;ILjava/lang/String;Ljava/lang/String;)V
     747: putstatic     #175                // Field SUBSCRIBE_METRIC_NUM_SUCCEED:Lorg/apache/dubbo/metrics/model/key/MetricsKey;
     750: new           #4                  // class org/apache/dubbo/metrics/model/key/MetricsKey
     753: dup
     754: ldc           #176                // String SUBSCRIBE_METRIC_NUM_FAILED
     756: bipush        42
     758: ldc           #177                // String dubbo.registry.subscribe.num.failed.total
     760: ldc           #178                // String Failed Subscribe Num
     762: invokespecial #14                 // Method "<init>":(Ljava/lang/String;ILjava/lang/String;Ljava/lang/String;)V
     765: putstatic     #179                // Field SUBSCRIBE_METRIC_NUM_FAILED:Lorg/apache/dubbo/metrics/model/key/MetricsKey;
     768: new           #4                  // class org/apache/dubbo/metrics/model/key/MetricsKey
     771: dup
     772: ldc           #180                // String DIRECTORY_METRIC_NUM_ALL
     774: bipush        43
     776: ldc           #181                // String dubbo.registry.directory.num.all
     778: ldc           #182                // String All Directory Urls
     780: invokespecial #14                 // Method "<init>":(Ljava/lang/String;ILjava/lang/String;Ljava/lang/String;)V
     783: putstatic     #183                // Field DIRECTORY_METRIC_NUM_ALL:Lorg/apache/dubbo/metrics/model/key/MetricsKey;
     786: new           #4                  // class org/apache/dubbo/metrics/model/key/MetricsKey
     789: dup
     790: ldc           #184                // String DIRECTORY_METRIC_NUM_VALID
     792: bipush        44
     794: ldc           #185                // String dubbo.registry.directory.num.valid.total
     796: ldc           #186                // String Valid Directory Urls
     798: invokespecial #14                 // Method "<init>":(Ljava/lang/String;ILjava/lang/String;Ljava/lang/String;)V
     801: putstatic     #187                // Field DIRECTORY_METRIC_NUM_VALID:Lorg/apache/dubbo/metrics/model/key/MetricsKey;
     804: new           #4                  // class org/apache/dubbo/metrics/model/key/MetricsKey
     807: dup
     808: ldc           #188                // String DIRECTORY_METRIC_NUM_TO_RECONNECT
     810: bipush        45
     812: ldc           #189                // String dubbo.registry.directory.num.to_reconnect.total
     814: ldc           #190                // String ToReconnect Directory Urls
     816: invokespecial #14                 // Method "<init>":(Ljava/lang/String;ILjava/lang/String;Ljava/lang/String;)V
     819: putstatic     #191                // Field DIRECTORY_METRIC_NUM_TO_RECONNECT:Lorg/apache/dubbo/metrics/model/key/MetricsKey;
     822: new           #4                  // class org/apache/dubbo/metrics/model/key/MetricsKey
     825: dup
     826: ldc           #192                // String DIRECTORY_METRIC_NUM_DISABLE
     828: bipush        46
     830: ldc           #193                // String dubbo.registry.directory.num.disable.total
     832: ldc           #194                // String Disable Directory Urls
     834: invokespecial #14                 // Method "<init>":(Ljava/lang/String;ILjava/lang/String;Ljava/lang/String;)V
     837: putstatic     #195                // Field DIRECTORY_METRIC_NUM_DISABLE:Lorg/apache/dubbo/metrics/model/key/MetricsKey;
     840: new           #4                  // class org/apache/dubbo/metrics/model/key/MetricsKey
     843: dup
     844: ldc           #196                // String NOTIFY_METRIC_REQUESTS
     846: bipush        47
     848: ldc           #197                // String dubbo.registry.notify.requests.total
     850: ldc           #198                // String Total Notify Requests
     852: invokespecial #14                 // Method "<init>":(Ljava/lang/String;ILjava/lang/String;Ljava/lang/String;)V
     855: putstatic     #199                // Field NOTIFY_METRIC_REQUESTS:Lorg/apache/dubbo/metrics/model/key/MetricsKey;
     858: new           #4                  // class org/apache/dubbo/metrics/model/key/MetricsKey
     861: dup
     862: ldc           #200                // String NOTIFY_METRIC_NUM_LAST
     864: bipush        48
     866: ldc           #201                // String dubbo.registry.notify.num.last
     868: ldc           #202                // String Last Notify Nums
     870: invokespecial #14                 // Method "<init>":(Ljava/lang/String;ILjava/lang/String;Ljava/lang/String;)V
     873: putstatic     #203                // Field NOTIFY_METRIC_NUM_LAST:Lorg/apache/dubbo/metrics/model/key/MetricsKey;
     876: new           #4                  // class org/apache/dubbo/metrics/model/key/MetricsKey
     879: dup
     880: ldc           #204                // String THREAD_POOL_CORE_SIZE
     882: bipush        49
     884: ldc           #205                // String dubbo.thread.pool.core.size
     886: ldc           #206                // String Thread Pool Core Size
     888: invokespecial #14                 // Method "<init>":(Ljava/lang/String;ILjava/lang/String;Ljava/lang/String;)V
     891: putstatic     #207                // Field THREAD_POOL_CORE_SIZE:Lorg/apache/dubbo/metrics/model/key/MetricsKey;
     894: new           #4                  // class org/apache/dubbo/metrics/model/key/MetricsKey
     897: dup
     898: ldc           #208                // String THREAD_POOL_LARGEST_SIZE
     900: bipush        50
     902: ldc           #209                // String dubbo.thread.pool.largest.size
     904: ldc           #210                // String Thread Pool Largest Size
     906: invokespecial #14                 // Method "<init>":(Ljava/lang/String;ILjava/lang/String;Ljava/lang/String;)V
     909: putstatic     #211                // Field THREAD_POOL_LARGEST_SIZE:Lorg/apache/dubbo/metrics/model/key/MetricsKey;
     912: new           #4                  // class org/apache/dubbo/metrics/model/key/MetricsKey
     915: dup
     916: ldc           #212                // String THREAD_POOL_MAX_SIZE
     918: bipush        51
     920: ldc           #213                // String dubbo.thread.pool.max.size
     922: ldc           #214                // String Thread Pool Max Size
     924: invokespecial #14                 // Method "<init>":(Ljava/lang/String;ILjava/lang/String;Ljava/lang/String;)V
     927: putstatic     #215                // Field THREAD_POOL_MAX_SIZE:Lorg/apache/dubbo/metrics/model/key/MetricsKey;
     930: new           #4                  // class org/apache/dubbo/metrics/model/key/MetricsKey
     933: dup
     934: ldc           #216                // String THREAD_POOL_ACTIVE_SIZE
     936: bipush        52
     938: ldc           #217                // String dubbo.thread.pool.active.size
     940: ldc           #218                // String Thread Pool Active Size
     942: invokespecial #14                 // Method "<init>":(Ljava/lang/String;ILjava/lang/String;Ljava/lang/String;)V
     945: putstatic     #219                // Field THREAD_POOL_ACTIVE_SIZE:Lorg/apache/dubbo/metrics/model/key/MetricsKey;
     948: new           #4                  // class org/apache/dubbo/metrics/model/key/MetricsKey
     951: dup
     952: ldc           #220                // String THREAD_POOL_THREAD_COUNT
     954: bipush        53
     956: ldc           #221                // String dubbo.thread.pool.thread.count
     958: ldc           #222                // String Thread Pool Thread Count
     960: invokespecial #14                 // Method "<init>":(Ljava/lang/String;ILjava/lang/String;Ljava/lang/String;)V
     963: putstatic     #223                // Field THREAD_POOL_THREAD_COUNT:Lorg/apache/dubbo/metrics/model/key/MetricsKey;
     966: new           #4                  // class org/apache/dubbo/metrics/model/key/MetricsKey
     969: dup
     970: ldc           #224                // String THREAD_POOL_QUEUE_SIZE
     972: bipush        54
     974: ldc           #225                // String dubbo.thread.pool.queue.size
     976: ldc           #226                // String Thread Pool Queue Size
     978: invokespecial #14                 // Method "<init>":(Ljava/lang/String;ILjava/lang/String;Ljava/lang/String;)V
     981: putstatic     #227                // Field THREAD_POOL_QUEUE_SIZE:Lorg/apache/dubbo/metrics/model/key/MetricsKey;
     984: new           #4                  // class org/apache/dubbo/metrics/model/key/MetricsKey
     987: dup
     988: ldc           #228                // String THREAD_POOL_THREAD_REJECT_COUNT
     990: bipush        55
     992: ldc           #229                // String dubbo.thread.pool.reject.thread.count
     994: ldc           #230                // String Thread Pool Reject Thread Count
     996: invokespecial #14                 // Method "<init>":(Ljava/lang/String;ILjava/lang/String;Ljava/lang/String;)V
     999: putstatic     #231                // Field THREAD_POOL_THREAD_REJECT_COUNT:Lorg/apache/dubbo/metrics/model/key/MetricsKey;
    1002: new           #4                  // class org/apache/dubbo/metrics/model/key/MetricsKey
    1005: dup
    1006: ldc           #232                // String METADATA_PUSH_METRIC_NUM
    1008: bipush        56
    1010: ldc           #233                // String dubbo.metadata.push.num.total
    1012: ldc           #234                // String Total Push Num
    1014: invokespecial #14                 // Method "<init>":(Ljava/lang/String;ILjava/lang/String;Ljava/lang/String;)V
    1017: putstatic     #235                // Field METADATA_PUSH_METRIC_NUM:Lorg/apache/dubbo/metrics/model/key/MetricsKey;
    1020: new           #4                  // class org/apache/dubbo/metrics/model/key/MetricsKey
    1023: dup
    1024: ldc           #236                // String METADATA_PUSH_METRIC_NUM_SUCCEED
    1026: bipush        57
    1028: ldc           #237                // String dubbo.metadata.push.num.succeed.total
    1030: ldc           #238                // String Succeed Push Num
    1032: invokespecial #14                 // Method "<init>":(Ljava/lang/String;ILjava/lang/String;Ljava/lang/String;)V
    1035: putstatic     #239                // Field METADATA_PUSH_METRIC_NUM_SUCCEED:Lorg/apache/dubbo/metrics/model/key/MetricsKey;
    1038: new           #4                  // class org/apache/dubbo/metrics/model/key/MetricsKey
    1041: dup
    1042: ldc           #240                // String METADATA_PUSH_METRIC_NUM_FAILED
    1044: bipush        58
    1046: ldc           #241                // String dubbo.metadata.push.num.failed.total
    1048: ldc           #242                // String Failed Push Num
    1050: invokespecial #14                 // Method "<init>":(Ljava/lang/String;ILjava/lang/String;Ljava/lang/String;)V
    1053: putstatic     #243                // Field METADATA_PUSH_METRIC_NUM_FAILED:Lorg/apache/dubbo/metrics/model/key/MetricsKey;
    1056: new           #4                  // class org/apache/dubbo/metrics/model/key/MetricsKey
    1059: dup
    1060: ldc           #244                // String METADATA_SUBSCRIBE_METRIC_NUM
    1062: bipush        59
    1064: ldc           #245                // String dubbo.metadata.subscribe.num.total
    1066: ldc           #246                // String Total Metadata Subscribe Num
    1068: invokespecial #14                 // Method "<init>":(Ljava/lang/String;ILjava/lang/String;Ljava/lang/String;)V
    1071: putstatic     #247                // Field METADATA_SUBSCRIBE_METRIC_NUM:Lorg/apache/dubbo/metrics/model/key/MetricsKey;
    1074: new           #4                  // class org/apache/dubbo/metrics/model/key/MetricsKey
    1077: dup
    1078: ldc           #248                // String METADATA_SUBSCRIBE_METRIC_NUM_SUCCEED
    1080: bipush        60
    1082: ldc           #249                // String dubbo.metadata.subscribe.num.succeed.total
    1084: ldc           #250                // String Succeed Metadata Subscribe Num
    1086: invokespecial #14                 // Method "<init>":(Ljava/lang/String;ILjava/lang/String;Ljava/lang/String;)V
    1089: putstatic     #251                // Field METADATA_SUBSCRIBE_METRIC_NUM_SUCCEED:Lorg/apache/dubbo/metrics/model/key/MetricsKey;
    1092: new           #4                  // class org/apache/dubbo/metrics/model/key/MetricsKey
    1095: dup
    1096: ldc           #252                // String METADATA_SUBSCRIBE_METRIC_NUM_FAILED
    1098: bipush        61
    1100: ldc           #253                // String dubbo.metadata.subscribe.num.failed.total
    1102: ldc           #254                // String Failed Metadata Subscribe Num
    1104: invokespecial #14                 // Method "<init>":(Ljava/lang/String;ILjava/lang/String;Ljava/lang/String;)V
    1107: putstatic     #255                // Field METADATA_SUBSCRIBE_METRIC_NUM_FAILED:Lorg/apache/dubbo/metrics/model/key/MetricsKey;
    1110: new           #4                  // class org/apache/dubbo/metrics/model/key/MetricsKey
    1113: dup
    1114: ldc_w         #256                // String SERVICE_REGISTER_METRIC_REQUESTS
    1117: bipush        62
    1119: ldc_w         #257                // String dubbo.registry.register.service.total
    1122: ldc_w         #258                // String Total Service-Level Register Requests
    1125: invokespecial #14                 // Method "<init>":(Ljava/lang/String;ILjava/lang/String;Ljava/lang/String;)V
    1128: putstatic     #259                // Field SERVICE_REGISTER_METRIC_REQUESTS:Lorg/apache/dubbo/metrics/model/key/MetricsKey;
    1131: new           #4                  // class org/apache/dubbo/metrics/model/key/MetricsKey
    1134: dup
    1135: ldc_w         #260                // String SERVICE_REGISTER_METRIC_REQUESTS_SUCCEED
    1138: bipush        63
    1140: ldc_w         #261                // String dubbo.registry.register.service.succeed.total
    1143: ldc_w         #262                // String Succeed Service-Level Register Requests
    1146: invokespecial #14                 // Method "<init>":(Ljava/lang/String;ILjava/lang/String;Ljava/lang/String;)V
    1149: putstatic     #263                // Field SERVICE_REGISTER_METRIC_REQUESTS_SUCCEED:Lorg/apache/dubbo/metrics/model/key/MetricsKey;
    1152: new           #4                  // class org/apache/dubbo/metrics/model/key/MetricsKey
    1155: dup
    1156: ldc_w         #264                // String SERVICE_REGISTER_METRIC_REQUESTS_FAILED
    1159: bipush        64
    1161: ldc_w         #265                // String dubbo.registry.register.service.failed.total
    1164: ldc_w         #266                // String Failed Service-Level Register Requests
    1167: invokespecial #14                 // Method "<init>":(Ljava/lang/String;ILjava/lang/String;Ljava/lang/String;)V
    1170: putstatic     #267                // Field SERVICE_REGISTER_METRIC_REQUESTS_FAILED:Lorg/apache/dubbo/metrics/model/key/MetricsKey;
    1173: new           #4                  // class org/apache/dubbo/metrics/model/key/MetricsKey
    1176: dup
    1177: ldc_w         #268                // String SERVICE_SUBSCRIBE_METRIC_NUM
    1180: bipush        65
    1182: ldc_w         #269                // String dubbo.registry.subscribe.service.num.total
    1185: ldc_w         #270                // String Total Service-Level Subscribe Num
    1188: invokespecial #14                 // Method "<init>":(Ljava/lang/String;ILjava/lang/String;Ljava/lang/String;)V
    1191: putstatic     #271                // Field SERVICE_SUBSCRIBE_METRIC_NUM:Lorg/apache/dubbo/metrics/model/key/MetricsKey;
    1194: new           #4                  // class org/apache/dubbo/metrics/model/key/MetricsKey
    1197: dup
    1198: ldc_w         #272                // String SERVICE_SUBSCRIBE_METRIC_NUM_SUCCEED
    1201: bipush        66
    1203: ldc_w         #273                // String dubbo.registry.subscribe.service.num.succeed.total
    1206: ldc_w         #274                // String Succeed Service-Level Num
    1209: invokespecial #14                 // Method "<init>":(Ljava/lang/String;ILjava/lang/String;Ljava/lang/String;)V
    1212: putstatic     #275                // Field SERVICE_SUBSCRIBE_METRIC_NUM_SUCCEED:Lorg/apache/dubbo/metrics/model/key/MetricsKey;
    1215: new           #4                  // class org/apache/dubbo/metrics/model/key/MetricsKey
    1218: dup
    1219: ldc_w         #276                // String SERVICE_SUBSCRIBE_METRIC_NUM_FAILED
    1222: bipush        67
    1224: ldc_w         #277                // String dubbo.registry.subscribe.service.num.failed.total
    1227: ldc_w         #278                // String Failed Service-Level Num
    1230: invokespecial #14                 // Method "<init>":(Ljava/lang/String;ILjava/lang/String;Ljava/lang/String;)V
    1233: putstatic     #279                // Field SERVICE_SUBSCRIBE_METRIC_NUM_FAILED:Lorg/apache/dubbo/metrics/model/key/MetricsKey;
    1236: new           #4                  // class org/apache/dubbo/metrics/model/key/MetricsKey
    1239: dup
    1240: ldc_w         #280                // String STORE_PROVIDER_METADATA
    1243: bipush        68
    1245: ldc_w         #281                // String dubbo.metadata.store.provider.total
    1248: ldc_w         #282                // String Store Provider Metadata
    1251: invokespecial #14                 // Method "<init>":(Ljava/lang/String;ILjava/lang/String;Ljava/lang/String;)V
    1254: putstatic     #283                // Field STORE_PROVIDER_METADATA:Lorg/apache/dubbo/metrics/model/key/MetricsKey;
    1257: new           #4                  // class org/apache/dubbo/metrics/model/key/MetricsKey
    1260: dup
    1261: ldc_w         #284                // String STORE_PROVIDER_METADATA_SUCCEED
    1264: bipush        69
    1266: ldc_w         #285                // String dubbo.metadata.store.provider.succeed.total
    1269: ldc_w         #286                // String Succeed Store Provider Metadata
    1272: invokespecial #14                 // Method "<init>":(Ljava/lang/String;ILjava/lang/String;Ljava/lang/String;)V
    1275: putstatic     #287                // Field STORE_PROVIDER_METADATA_SUCCEED:Lorg/apache/dubbo/metrics/model/key/MetricsKey;
    1278: new           #4                  // class org/apache/dubbo/metrics/model/key/MetricsKey
    1281: dup
    1282: ldc_w         #288                // String STORE_PROVIDER_METADATA_FAILED
    1285: bipush        70
    1287: ldc_w         #289                // String dubbo.metadata.store.provider.failed.total
    1290: ldc_w         #290                // String Failed Store Provider Metadata
    1293: invokespecial #14                 // Method "<init>":(Ljava/lang/String;ILjava/lang/String;Ljava/lang/String;)V
    1296: putstatic     #291                // Field STORE_PROVIDER_METADATA_FAILED:Lorg/apache/dubbo/metrics/model/key/MetricsKey;
    1299: new           #4                  // class org/apache/dubbo/metrics/model/key/MetricsKey
    1302: dup
    1303: ldc_w         #292                // String METADATA_GIT_COMMITID_METRIC
    1306: bipush        71
    1308: ldc_w         #293                // String git.commit.id
    1311: ldc_w         #294                // String Git Commit Id Metrics
    1314: invokespecial #14                 // Method "<init>":(Ljava/lang/String;ILjava/lang/String;Ljava/lang/String;)V
    1317: putstatic     #295                // Field METADATA_GIT_COMMITID_METRIC:Lorg/apache/dubbo/metrics/model/key/MetricsKey;
    1320: new           #4                  // class org/apache/dubbo/metrics/model/key/MetricsKey
    1323: dup
    1324: ldc_w         #296                // String INVOKER_NO_AVAILABLE_COUNT
    1327: bipush        72
    1329: ldc_w         #297                // String dubbo.consumer.invoker.no.available.count
    1332: ldc_w         #298                // String Request Throw No Invoker Available Exception Count
    1335: invokespecial #14                 // Method "<init>":(Ljava/lang/String;ILjava/lang/String;Ljava/lang/String;)V
    1338: putstatic     #299                // Field INVOKER_NO_AVAILABLE_COUNT:Lorg/apache/dubbo/metrics/model/key/MetricsKey;
    1341: bipush        73
    1343: anewarray     #4                  // class org/apache/dubbo/metrics/model/key/MetricsKey
    1346: dup
    1347: iconst_0
    1348: getstatic     #15                 // Field APPLICATION_METRIC_INFO:Lorg/apache/dubbo/metrics/model/key/MetricsKey;
    1351: aastore
    1352: dup
    1353: iconst_1
    1354: getstatic     #19                 // Field CONFIGCENTER_METRIC_TOTAL:Lorg/apache/dubbo/metrics/model/key/MetricsKey;
    1357: aastore
    1358: dup
    1359: iconst_2
    1360: getstatic     #23                 // Field METRIC_REQUESTS:Lorg/apache/dubbo/metrics/model/key/MetricsKey;
    1363: aastore
    1364: dup
    1365: iconst_3
    1366: getstatic     #27                 // Field METRIC_REQUESTS_SUCCEED:Lorg/apache/dubbo/metrics/model/key/MetricsKey;
    1369: aastore
    1370: dup
    1371: iconst_4
    1372: getstatic     #31                 // Field METRIC_REQUEST_BUSINESS_FAILED:Lorg/apache/dubbo/metrics/model/key/MetricsKey;
    1375: aastore
    1376: dup
    1377: iconst_5
    1378: getstatic     #35                 // Field METRIC_REQUESTS_PROCESSING:Lorg/apache/dubbo/metrics/model/key/MetricsKey;
    1381: aastore
    1382: dup
    1383: bipush        6
    1385: getstatic     #39                 // Field METRIC_REQUESTS_TIMEOUT:Lorg/apache/dubbo/metrics/model/key/MetricsKey;
    1388: aastore
    1389: dup
    1390: bipush        7
    1392: getstatic     #43                 // Field METRIC_REQUESTS_LIMIT:Lorg/apache/dubbo/metrics/model/key/MetricsKey;
    1395: aastore
    1396: dup
    1397: bipush        8
    1399: getstatic     #47                 // Field METRIC_REQUESTS_FAILED:Lorg/apache/dubbo/metrics/model/key/MetricsKey;
    1402: aastore
    1403: dup
    1404: bipush        9
    1406: getstatic     #51                 // Field METRIC_REQUESTS_TOTAL_FAILED:Lorg/apache/dubbo/metrics/model/key/MetricsKey;
    1409: aastore
    1410: dup
    1411: bipush        10
    1413: getstatic     #55                 // Field METRIC_REQUESTS_NETWORK_FAILED:Lorg/apache/dubbo/metrics/model/key/MetricsKey;
    1416: aastore
    1417: dup
    1418: bipush        11
    1420: getstatic     #59                 // Field METRIC_REQUESTS_SERVICE_UNAVAILABLE_FAILED:Lorg/apache/dubbo/metrics/model/key/MetricsKey;
    1423: aastore
    1424: dup
    1425: bipush        12
    1427: getstatic     #63                 // Field METRIC_REQUESTS_CODEC_FAILED:Lorg/apache/dubbo/metrics/model/key/MetricsKey;
    1430: aastore
    1431: dup
    1432: bipush        13
    1434: getstatic     #67                 // Field METRIC_REQUESTS_TOTAL_AGG:Lorg/apache/dubbo/metrics/model/key/MetricsKey;
    1437: aastore
    1438: dup
    1439: bipush        14
    1441: getstatic     #71                 // Field METRIC_REQUESTS_SUCCEED_AGG:Lorg/apache/dubbo/metrics/model/key/MetricsKey;
    1444: aastore
    1445: dup
    1446: bipush        15
    1448: getstatic     #75                 // Field METRIC_REQUESTS_FAILED_AGG:Lorg/apache/dubbo/metrics/model/key/MetricsKey;
    1451: aastore
    1452: dup
    1453: bipush        16
    1455: getstatic     #79                 // Field METRIC_REQUEST_BUSINESS_FAILED_AGG:Lorg/apache/dubbo/metrics/model/key/MetricsKey;
    1458: aastore
    1459: dup
    1460: bipush        17
    1462: getstatic     #83                 // Field METRIC_REQUESTS_TIMEOUT_AGG:Lorg/apache/dubbo/metrics/model/key/MetricsKey;
    1465: aastore
    1466: dup
    1467: bipush        18
    1469: getstatic     #87                 // Field METRIC_REQUESTS_LIMIT_AGG:Lorg/apache/dubbo/metrics/model/key/MetricsKey;
    1472: aastore
    1473: dup
    1474: bipush        19
    1476: getstatic     #91                 // Field METRIC_REQUESTS_TOTAL_FAILED_AGG:Lorg/apache/dubbo/metrics/model/key/MetricsKey;
    1479: aastore
    1480: dup
    1481: bipush        20
    1483: getstatic     #95                 // Field METRIC_REQUESTS_NETWORK_FAILED_AGG:Lorg/apache/dubbo/metrics/model/key/MetricsKey;
    1486: aastore
    1487: dup
    1488: bipush        21
    1490: getstatic     #99                 // Field METRIC_REQUESTS_CODEC_FAILED_AGG:Lorg/apache/dubbo/metrics/model/key/MetricsKey;
    1493: aastore
    1494: dup
    1495: bipush        22
    1497: getstatic     #102                // Field METRIC_REQUESTS_TOTAL_SERVICE_UNAVAILABLE_FAILED_AGG:Lorg/apache/dubbo/metrics/model/key/MetricsKey;
    1500: aastore
    1501: dup
    1502: bipush        23
    1504: getstatic     #106                // Field METRIC_QPS:Lorg/apache/dubbo/metrics/model/key/MetricsKey;
    1507: aastore
    1508: dup
    1509: bipush        24
    1511: getstatic     #110                // Field METRIC_RT_LAST:Lorg/apache/dubbo/metrics/model/key/MetricsKey;
    1514: aastore
    1515: dup
    1516: bipush        25
    1518: getstatic     #114                // Field METRIC_RT_MIN:Lorg/apache/dubbo/metrics/model/key/MetricsKey;
    1521: aastore
    1522: dup
    1523: bipush        26
    1525: getstatic     #118                // Field METRIC_RT_MAX:Lorg/apache/dubbo/metrics/model/key/MetricsKey;
    1528: aastore
    1529: dup
    1530: bipush        27
    1532: getstatic     #122                // Field METRIC_RT_SUM:Lorg/apache/dubbo/metrics/model/key/MetricsKey;
    1535: aastore
    1536: dup
    1537: bipush        28
    1539: getstatic     #126                // Field METRIC_RT_AVG:Lorg/apache/dubbo/metrics/model/key/MetricsKey;
    1542: aastore
    1543: dup
    1544: bipush        29
    1546: getstatic     #130                // Field METRIC_RT_P99:Lorg/apache/dubbo/metrics/model/key/MetricsKey;
    1549: aastore
    1550: dup
    1551: bipush        30
    1553: getstatic     #134                // Field METRIC_RT_P95:Lorg/apache/dubbo/metrics/model/key/MetricsKey;
    1556: aastore
    1557: dup
    1558: bipush        31
    1560: getstatic     #138                // Field METRIC_RT_P90:Lorg/apache/dubbo/metrics/model/key/MetricsKey;
    1563: aastore
    1564: dup
    1565: bipush        32
    1567: getstatic     #142                // Field METRIC_RT_P50:Lorg/apache/dubbo/metrics/model/key/MetricsKey;
    1570: aastore
    1571: dup
    1572: bipush        33
    1574: getstatic     #146                // Field REGISTER_METRIC_REQUESTS:Lorg/apache/dubbo/metrics/model/key/MetricsKey;
    1577: aastore
    1578: dup
    1579: bipush        34
    1581: getstatic     #150                // Field REGISTER_METRIC_REQUESTS_SUCCEED:Lorg/apache/dubbo/metrics/model/key/MetricsKey;
    1584: aastore
    1585: dup
    1586: bipush        35
    1588: getstatic     #154                // Field REGISTER_METRIC_REQUESTS_FAILED:Lorg/apache/dubbo/metrics/model/key/MetricsKey;
    1591: aastore
    1592: dup
    1593: bipush        36
    1595: getstatic     #158                // Field METRIC_RT_HISTOGRAM:Lorg/apache/dubbo/metrics/model/key/MetricsKey;
    1598: aastore
    1599: dup
    1600: bipush        37
    1602: getstatic     #161                // Field GENERIC_METRIC_REQUESTS:Lorg/apache/dubbo/metrics/model/key/MetricsKey;
    1605: aastore
    1606: dup
    1607: bipush        38
    1609: getstatic     #164                // Field GENERIC_METRIC_REQUESTS_SUCCEED:Lorg/apache/dubbo/metrics/model/key/MetricsKey;
    1612: aastore
    1613: dup
    1614: bipush        39
    1616: getstatic     #167                // Field GENERIC_METRIC_REQUESTS_FAILED:Lorg/apache/dubbo/metrics/model/key/MetricsKey;
    1619: aastore
    1620: dup
    1621: bipush        40
    1623: getstatic     #171                // Field SUBSCRIBE_METRIC_NUM:Lorg/apache/dubbo/metrics/model/key/MetricsKey;
    1626: aastore
    1627: dup
    1628: bipush        41
    1630: getstatic     #175                // Field SUBSCRIBE_METRIC_NUM_SUCCEED:Lorg/apache/dubbo/metrics/model/key/MetricsKey;
    1633: aastore
    1634: dup
    1635: bipush        42
    1637: getstatic     #179                // Field SUBSCRIBE_METRIC_NUM_FAILED:Lorg/apache/dubbo/metrics/model/key/MetricsKey;
    1640: aastore
    1641: dup
    1642: bipush        43
    1644: getstatic     #183                // Field DIRECTORY_METRIC_NUM_ALL:Lorg/apache/dubbo/metrics/model/key/MetricsKey;
    1647: aastore
    1648: dup
    1649: bipush        44
    1651: getstatic     #187                // Field DIRECTORY_METRIC_NUM_VALID:Lorg/apache/dubbo/metrics/model/key/MetricsKey;
    1654: aastore
    1655: dup
    1656: bipush        45
    1658: getstatic     #191                // Field DIRECTORY_METRIC_NUM_TO_RECONNECT:Lorg/apache/dubbo/metrics/model/key/MetricsKey;
    1661: aastore
    1662: dup
    1663: bipush        46
    1665: getstatic     #195                // Field DIRECTORY_METRIC_NUM_DISABLE:Lorg/apache/dubbo/metrics/model/key/MetricsKey;
    1668: aastore
    1669: dup
    1670: bipush        47
    1672: getstatic     #199                // Field NOTIFY_METRIC_REQUESTS:Lorg/apache/dubbo/metrics/model/key/MetricsKey;
    1675: aastore
    1676: dup
    1677: bipush        48
    1679: getstatic     #203                // Field NOTIFY_METRIC_NUM_LAST:Lorg/apache/dubbo/metrics/model/key/MetricsKey;
    1682: aastore
    1683: dup
    1684: bipush        49
    1686: getstatic     #207                // Field THREAD_POOL_CORE_SIZE:Lorg/apache/dubbo/metrics/model/key/MetricsKey;
    1689: aastore
    1690: dup
    1691: bipush        50
    1693: getstatic     #211                // Field THREAD_POOL_LARGEST_SIZE:Lorg/apache/dubbo/metrics/model/key/MetricsKey;
    1696: aastore
    1697: dup
    1698: bipush        51
    1700: getstatic     #215                // Field THREAD_POOL_MAX_SIZE:Lorg/apache/dubbo/metrics/model/key/MetricsKey;
    1703: aastore
    1704: dup
    1705: bipush        52
    1707: getstatic     #219                // Field THREAD_POOL_ACTIVE_SIZE:Lorg/apache/dubbo/metrics/model/key/MetricsKey;
    1710: aastore
    1711: dup
    1712: bipush        53
    1714: getstatic     #223                // Field THREAD_POOL_THREAD_COUNT:Lorg/apache/dubbo/metrics/model/key/MetricsKey;
    1717: aastore
    1718: dup
    1719: bipush        54
    1721: getstatic     #227                // Field THREAD_POOL_QUEUE_SIZE:Lorg/apache/dubbo/metrics/model/key/MetricsKey;
    1724: aastore
    1725: dup
    1726: bipush        55
    1728: getstatic     #231                // Field THREAD_POOL_THREAD_REJECT_COUNT:Lorg/apache/dubbo/metrics/model/key/MetricsKey;
    1731: aastore
    1732: dup
    1733: bipush        56
    1735: getstatic     #235                // Field METADATA_PUSH_METRIC_NUM:Lorg/apache/dubbo/metrics/model/key/MetricsKey;
    1738: aastore
    1739: dup
    1740: bipush        57
    1742: getstatic     #239                // Field METADATA_PUSH_METRIC_NUM_SUCCEED:Lorg/apache/dubbo/metrics/model/key/MetricsKey;
    1745: aastore
    1746: dup
    1747: bipush        58
    1749: getstatic     #243                // Field METADATA_PUSH_METRIC_NUM_FAILED:Lorg/apache/dubbo/metrics/model/key/MetricsKey;
    1752: aastore
    1753: dup
    1754: bipush        59
    1756: getstatic     #247                // Field METADATA_SUBSCRIBE_METRIC_NUM:Lorg/apache/dubbo/metrics/model/key/MetricsKey;
    1759: aastore
    1760: dup
    1761: bipush        60
    1763: getstatic     #251                // Field METADATA_SUBSCRIBE_METRIC_NUM_SUCCEED:Lorg/apache/dubbo/metrics/model/key/MetricsKey;
    1766: aastore
    1767: dup
    1768: bipush        61
    1770: getstatic     #255                // Field METADATA_SUBSCRIBE_METRIC_NUM_FAILED:Lorg/apache/dubbo/metrics/model/key/MetricsKey;
    1773: aastore
    1774: dup
    1775: bipush        62
    1777: getstatic     #259                // Field SERVICE_REGISTER_METRIC_REQUESTS:Lorg/apache/dubbo/metrics/model/key/MetricsKey;
    1780: aastore
    1781: dup
    1782: bipush        63
    1784: getstatic     #263                // Field SERVICE_REGISTER_METRIC_REQUESTS_SUCCEED:Lorg/apache/dubbo/metrics/model/key/MetricsKey;
    1787: aastore
    1788: dup
    1789: bipush        64
    1791: getstatic     #267                // Field SERVICE_REGISTER_METRIC_REQUESTS_FAILED:Lorg/apache/dubbo/metrics/model/key/MetricsKey;
    1794: aastore
    1795: dup
    1796: bipush        65
    1798: getstatic     #271                // Field SERVICE_SUBSCRIBE_METRIC_NUM:Lorg/apache/dubbo/metrics/model/key/MetricsKey;
    1801: aastore
    1802: dup
    1803: bipush        66
    1805: getstatic     #275                // Field SERVICE_SUBSCRIBE_METRIC_NUM_SUCCEED:Lorg/apache/dubbo/metrics/model/key/MetricsKey;
    1808: aastore
    1809: dup
    1810: bipush        67
    1812: getstatic     #279                // Field SERVICE_SUBSCRIBE_METRIC_NUM_FAILED:Lorg/apache/dubbo/metrics/model/key/MetricsKey;
    1815: aastore
    1816: dup
    1817: bipush        68
    1819: getstatic     #283                // Field STORE_PROVIDER_METADATA:Lorg/apache/dubbo/metrics/model/key/MetricsKey;
    1822: aastore
    1823: dup
    1824: bipush        69
    1826: getstatic     #287                // Field STORE_PROVIDER_METADATA_SUCCEED:Lorg/apache/dubbo/metrics/model/key/MetricsKey;
    1829: aastore
    1830: dup
    1831: bipush        70
    1833: getstatic     #291                // Field STORE_PROVIDER_METADATA_FAILED:Lorg/apache/dubbo/metrics/model/key/MetricsKey;
    1836: aastore
    1837: dup
    1838: bipush        71
    1840: getstatic     #295                // Field METADATA_GIT_COMMITID_METRIC:Lorg/apache/dubbo/metrics/model/key/MetricsKey;
    1843: aastore
    1844: dup
    1845: bipush        72
    1847: getstatic     #299                // Field INVOKER_NO_AVAILABLE_COUNT:Lorg/apache/dubbo/metrics/model/key/MetricsKey;
    1850: aastore
    1851: putstatic     #1                  // Field $VALUES:[Lorg/apache/dubbo/metrics/model/key/MetricsKey;
    1854: return
}
