Compiled from "MetricsPlaceValue.java"
public class org.apache.dubbo.metrics.model.key.MetricsPlaceValue {
  private final java.lang.String type;

  private final org.apache.dubbo.metrics.model.key.MetricsLevel metricsLevel;

  private org.apache.dubbo.metrics.model.key.MetricsPlaceValue(java.lang.String, org.apache.dubbo.metrics.model.key.MetricsLevel);
    Code:
       0: aload_0
       1: invokespecial #1                  // Method java/lang/Object."<init>":()V
       4: aload_0
       5: aload_1
       6: putfield      #2                  // Field type:Ljava/lang/String;
       9: aload_0
      10: aload_2
      11: putfield      #3                  // Field metricsLevel:Lorg/apache/dubbo/metrics/model/key/MetricsLevel;
      14: return

  public static org.apache.dubbo.metrics.model.key.MetricsPlaceValue of(java.lang.String, org.apache.dubbo.metrics.model.key.MetricsLevel);
    Code:
       0: new           #4                  // class org/apache/dubbo/metrics/model/key/MetricsPlaceValue
       3: dup
       4: aload_0
       5: aload_1
       6: invokespecial #5                  // Method "<init>":(Ljava/lang/String;Lorg/apache/dubbo/metrics/model/key/MetricsLevel;)V
       9: areturn

  public java.lang.String getType();
    Code:
       0: aload_0
       1: getfield      #2                  // Field type:Ljava/lang/String;
       4: areturn

  public org.apache.dubbo.metrics.model.key.MetricsLevel getMetricsLevel();
    Code:
       0: aload_0
       1: getfield      #3                  // Field metricsLevel:Lorg/apache/dubbo/metrics/model/key/MetricsLevel;
       4: areturn

  public boolean equals(java.lang.Object);
    Code:
       0: aload_0
       1: aload_1
       2: if_acmpne     7
       5: iconst_1
       6: ireturn
       7: aload_1
       8: ifnull        22
      11: aload_0
      12: invokevirtual #6                  // Method java/lang/Object.getClass:()Ljava/lang/Class;
      15: aload_1
      16: invokevirtual #6                  // Method java/lang/Object.getClass:()Ljava/lang/Class;
      19: if_acmpeq     24
      22: iconst_0
      23: ireturn
      24: aload_1
      25: checkcast     #4                  // class org/apache/dubbo/metrics/model/key/MetricsPlaceValue
      28: astore_2
      29: aload_0
      30: getfield      #2                  // Field type:Ljava/lang/String;
      33: aload_2
      34: getfield      #2                  // Field type:Ljava/lang/String;
      37: invokevirtual #7                  // Method java/lang/String.equals:(Ljava/lang/Object;)Z
      40: ifne          45
      43: iconst_0
      44: ireturn
      45: aload_0
      46: getfield      #3                  // Field metricsLevel:Lorg/apache/dubbo/metrics/model/key/MetricsLevel;
      49: aload_2
      50: getfield      #3                  // Field metricsLevel:Lorg/apache/dubbo/metrics/model/key/MetricsLevel;
      53: if_acmpne     60
      56: iconst_1
      57: goto          61
      60: iconst_0
      61: ireturn

  public int hashCode();
    Code:
       0: aload_0
       1: getfield      #2                  // Field type:Ljava/lang/String;
       4: invokevirtual #8                  // Method java/lang/String.hashCode:()I
       7: istore_1
       8: bipush        31
      10: iload_1
      11: imul
      12: aload_0
      13: getfield      #3                  // Field metricsLevel:Lorg/apache/dubbo/metrics/model/key/MetricsLevel;
      16: invokevirtual #9                  // Method org/apache/dubbo/metrics/model/key/MetricsLevel.hashCode:()I
      19: iadd
      20: istore_1
      21: iload_1
      22: ireturn
}
