Compiled from "MetricsKeyWrapper.java"
public class org.apache.dubbo.metrics.model.key.MetricsKeyWrapper {
  private final org.apache.dubbo.metrics.model.key.MetricsKey metricsKey;

  private final org.apache.dubbo.metrics.model.key.MetricsPlaceValue placeType;

  public org.apache.dubbo.metrics.model.key.MetricsKeyWrapper(org.apache.dubbo.metrics.model.key.MetricsKey, org.apache.dubbo.metrics.model.key.MetricsPlaceValue);
    Code:
       0: aload_0
       1: invokespecial #1                  // Method java/lang/Object."<init>":()V
       4: aload_0
       5: aload_1
       6: putfield      #2                  // Field metricsKey:Lorg/apache/dubbo/metrics/model/key/MetricsKey;
       9: aload_0
      10: aload_2
      11: putfield      #3                  // Field placeType:Lorg/apache/dubbo/metrics/model/key/MetricsPlaceValue;
      14: return

  public org.apache.dubbo.metrics.model.key.MetricsPlaceValue getPlaceType();
    Code:
       0: aload_0
       1: getfield      #3                  // Field placeType:Lorg/apache/dubbo/metrics/model/key/MetricsPlaceValue;
       4: areturn

  public java.lang.String getType();
    Code:
       0: aload_0
       1: invokevirtual #4                  // Method getPlaceType:()Lorg/apache/dubbo/metrics/model/key/MetricsPlaceValue;
       4: invokevirtual #5                  // Method org/apache/dubbo/metrics/model/key/MetricsPlaceValue.getType:()Ljava/lang/String;
       7: areturn

  public org.apache.dubbo.metrics.model.key.MetricsKey getMetricsKey();
    Code:
       0: aload_0
       1: getfield      #2                  // Field metricsKey:Lorg/apache/dubbo/metrics/model/key/MetricsKey;
       4: areturn

  public boolean isKey(org.apache.dubbo.metrics.model.key.MetricsKey, java.lang.String);
    Code:
       0: aload_1
       1: aload_0
       2: invokevirtual #6                  // Method getMetricsKey:()Lorg/apache/dubbo/metrics/model/key/MetricsKey;
       5: if_acmpne     23
       8: aload_2
       9: aload_0
      10: invokevirtual #7                  // Method getType:()Ljava/lang/String;
      13: invokevirtual #8                  // Method java/lang/String.equals:(Ljava/lang/Object;)Z
      16: ifeq          23
      19: iconst_1
      20: goto          24
      23: iconst_0
      24: ireturn

  public org.apache.dubbo.metrics.model.key.MetricsLevel getLevel();
    Code:
       0: aload_0
       1: invokevirtual #4                  // Method getPlaceType:()Lorg/apache/dubbo/metrics/model/key/MetricsPlaceValue;
       4: invokevirtual #9                  // Method org/apache/dubbo/metrics/model/key/MetricsPlaceValue.getMetricsLevel:()Lorg/apache/dubbo/metrics/model/key/MetricsLevel;
       7: areturn

  public java.lang.String targetKey();
    Code:
       0: aload_0
       1: getfield      #3                  // Field placeType:Lorg/apache/dubbo/metrics/model/key/MetricsPlaceValue;
       4: ifnonnull     15
       7: aload_0
       8: getfield      #2                  // Field metricsKey:Lorg/apache/dubbo/metrics/model/key/MetricsKey;
      11: invokevirtual #10                 // Method org/apache/dubbo/metrics/model/key/MetricsKey.getName:()Ljava/lang/String;
      14: areturn
      15: aload_0
      16: getfield      #2                  // Field metricsKey:Lorg/apache/dubbo/metrics/model/key/MetricsKey;
      19: invokevirtual #10                 // Method org/apache/dubbo/metrics/model/key/MetricsKey.getName:()Ljava/lang/String;
      22: iconst_1
      23: anewarray     #11                 // class java/lang/Object
      26: dup
      27: iconst_0
      28: aload_0
      29: invokevirtual #7                  // Method getType:()Ljava/lang/String;
      32: aastore
      33: invokestatic  #12                 // Method java/lang/String.format:(Ljava/lang/String;[Ljava/lang/Object;)Ljava/lang/String;
      36: areturn
      37: astore_1
      38: aload_0
      39: getfield      #2                  // Field metricsKey:Lorg/apache/dubbo/metrics/model/key/MetricsKey;
      42: invokevirtual #10                 // Method org/apache/dubbo/metrics/model/key/MetricsKey.getName:()Ljava/lang/String;
      45: areturn
    Exception table:
       from    to  target type
          15    36    37   Class java/lang/Exception

  public java.lang.String targetDesc();
    Code:
       0: aload_0
       1: getfield      #3                  // Field placeType:Lorg/apache/dubbo/metrics/model/key/MetricsPlaceValue;
       4: ifnonnull     15
       7: aload_0
       8: getfield      #2                  // Field metricsKey:Lorg/apache/dubbo/metrics/model/key/MetricsKey;
      11: invokevirtual #14                 // Method org/apache/dubbo/metrics/model/key/MetricsKey.getDescription:()Ljava/lang/String;
      14: areturn
      15: aload_0
      16: getfield      #2                  // Field metricsKey:Lorg/apache/dubbo/metrics/model/key/MetricsKey;
      19: invokevirtual #14                 // Method org/apache/dubbo/metrics/model/key/MetricsKey.getDescription:()Ljava/lang/String;
      22: iconst_1
      23: anewarray     #11                 // class java/lang/Object
      26: dup
      27: iconst_0
      28: aload_0
      29: invokevirtual #7                  // Method getType:()Ljava/lang/String;
      32: aastore
      33: invokestatic  #12                 // Method java/lang/String.format:(Ljava/lang/String;[Ljava/lang/Object;)Ljava/lang/String;
      36: areturn
      37: astore_1
      38: aload_0
      39: getfield      #2                  // Field metricsKey:Lorg/apache/dubbo/metrics/model/key/MetricsKey;
      42: invokevirtual #14                 // Method org/apache/dubbo/metrics/model/key/MetricsKey.getDescription:()Ljava/lang/String;
      45: areturn
    Exception table:
       from    to  target type
          15    36    37   Class java/lang/Exception

  public java.util.Map<java.lang.String, java.lang.String> tagName(org.apache.dubbo.rpc.model.ApplicationModel, java.lang.String);
    Code:
       0: aload_0
       1: invokevirtual #15                 // Method getLevel:()Lorg/apache/dubbo/metrics/model/key/MetricsLevel;
       4: astore_3
       5: getstatic     #16                 // Field org/apache/dubbo/metrics/model/key/MetricsKeyWrapper$1.$SwitchMap$org$apache$dubbo$metrics$model$key$MetricsLevel:[I
       8: aload_3
       9: invokevirtual #17                 // Method org/apache/dubbo/metrics/model/key/MetricsLevel.ordinal:()I
      12: iaload
      13: tableswitch   { // 1 to 3
                     1: 40
                     2: 45
                     3: 51
               default: 57
          }
      40: aload_1
      41: invokestatic  #18                 // Method org/apache/dubbo/metrics/model/MetricsSupport.applicationTags:(Lorg/apache/dubbo/rpc/model/ApplicationModel;)Ljava/util/Map;
      44: areturn
      45: aload_1
      46: aload_2
      47: invokestatic  #19                 // Method org/apache/dubbo/metrics/model/MetricsSupport.serviceTags:(Lorg/apache/dubbo/rpc/model/ApplicationModel;Ljava/lang/String;)Ljava/util/Map;
      50: areturn
      51: aload_1
      52: aload_2
      53: invokestatic  #20                 // Method org/apache/dubbo/metrics/model/MetricsSupport.methodTags:(Lorg/apache/dubbo/rpc/model/ApplicationModel;Ljava/lang/String;)Ljava/util/Map;
      56: areturn
      57: aload_1
      58: invokestatic  #18                 // Method org/apache/dubbo/metrics/model/MetricsSupport.applicationTags:(Lorg/apache/dubbo/rpc/model/ApplicationModel;)Ljava/util/Map;
      61: areturn

  public static org.apache.dubbo.metrics.model.key.MetricsKeyWrapper wrapper(org.apache.dubbo.metrics.model.key.MetricsKey);
    Code:
       0: new           #21                 // class org/apache/dubbo/metrics/model/key/MetricsKeyWrapper
       3: dup
       4: aload_0
       5: aconst_null
       6: invokespecial #22                 // Method "<init>":(Lorg/apache/dubbo/metrics/model/key/MetricsKey;Lorg/apache/dubbo/metrics/model/key/MetricsPlaceValue;)V
       9: areturn

  public boolean equals(java.lang.Object);
    Code:
       0: aload_0
       1: aload_1
       2: if_acmpne     7
       5: iconst_1
       6: ireturn
       7: aload_1
       8: ifnull        22
      11: aload_0
      12: invokevirtual #23                 // Method java/lang/Object.getClass:()Ljava/lang/Class;
      15: aload_1
      16: invokevirtual #23                 // Method java/lang/Object.getClass:()Ljava/lang/Class;
      19: if_acmpeq     24
      22: iconst_0
      23: ireturn
      24: aload_1
      25: checkcast     #21                 // class org/apache/dubbo/metrics/model/key/MetricsKeyWrapper
      28: astore_2
      29: aload_0
      30: getfield      #2                  // Field metricsKey:Lorg/apache/dubbo/metrics/model/key/MetricsKey;
      33: aload_2
      34: getfield      #2                  // Field metricsKey:Lorg/apache/dubbo/metrics/model/key/MetricsKey;
      37: if_acmpeq     42
      40: iconst_0
      41: ireturn
      42: aload_0
      43: getfield      #3                  // Field placeType:Lorg/apache/dubbo/metrics/model/key/MetricsPlaceValue;
      46: aload_2
      47: getfield      #3                  // Field placeType:Lorg/apache/dubbo/metrics/model/key/MetricsPlaceValue;
      50: invokestatic  #24                 // Method java/util/Objects.equals:(Ljava/lang/Object;Ljava/lang/Object;)Z
      53: ireturn

  public int hashCode();
    Code:
       0: aload_0
       1: getfield      #2                  // Field metricsKey:Lorg/apache/dubbo/metrics/model/key/MetricsKey;
       4: ifnull        17
       7: aload_0
       8: getfield      #2                  // Field metricsKey:Lorg/apache/dubbo/metrics/model/key/MetricsKey;
      11: invokevirtual #25                 // Method org/apache/dubbo/metrics/model/key/MetricsKey.hashCode:()I
      14: goto          18
      17: iconst_0
      18: istore_1
      19: bipush        31
      21: iload_1
      22: imul
      23: aload_0
      24: getfield      #3                  // Field placeType:Lorg/apache/dubbo/metrics/model/key/MetricsPlaceValue;
      27: ifnull        40
      30: aload_0
      31: getfield      #3                  // Field placeType:Lorg/apache/dubbo/metrics/model/key/MetricsPlaceValue;
      34: invokevirtual #26                 // Method org/apache/dubbo/metrics/model/key/MetricsPlaceValue.hashCode:()I
      37: goto          41
      40: iconst_0
      41: iadd
      42: istore_1
      43: iload_1
      44: ireturn
}
