Compiled from "MetricsLevel.java"
public final class org.apache.dubbo.metrics.model.key.MetricsLevel extends java.lang.Enum<org.apache.dubbo.metrics.model.key.MetricsLevel> {
  public static final org.apache.dubbo.metrics.model.key.MetricsLevel APP;

  public static final org.apache.dubbo.metrics.model.key.MetricsLevel SERVICE;

  public static final org.apache.dubbo.metrics.model.key.MetricsLevel METHOD;

  public static final org.apache.dubbo.metrics.model.key.MetricsLevel CONFIG;

  private static final org.apache.dubbo.metrics.model.key.MetricsLevel[] $VALUES;

  public static org.apache.dubbo.metrics.model.key.MetricsLevel[] values();
    Code:
       0: getstatic     #1                  // Field $VALUES:[Lorg/apache/dubbo/metrics/model/key/MetricsLevel;
       3: invokevirtual #2                  // Method "[Lorg/apache/dubbo/metrics/model/key/MetricsLevel;".clone:()Ljava/lang/Object;
       6: checkcast     #3                  // class "[Lorg/apache/dubbo/metrics/model/key/MetricsLevel;"
       9: areturn

  public static org.apache.dubbo.metrics.model.key.MetricsLevel valueOf(java.lang.String);
    Code:
       0: ldc           #4                  // class org/apache/dubbo/metrics/model/key/MetricsLevel
       2: aload_0
       3: invokestatic  #5                  // Method java/lang/Enum.valueOf:(Ljava/lang/Class;Ljava/lang/String;)Ljava/lang/Enum;
       6: checkcast     #4                  // class org/apache/dubbo/metrics/model/key/MetricsLevel
       9: areturn

  private org.apache.dubbo.metrics.model.key.MetricsLevel();
    Code:
       0: aload_0
       1: aload_1
       2: iload_2
       3: invokespecial #6                  // Method java/lang/Enum."<init>":(Ljava/lang/String;I)V
       6: return

  static {};
    Code:
       0: new           #4                  // class org/apache/dubbo/metrics/model/key/MetricsLevel
       3: dup
       4: ldc           #7                  // String APP
       6: iconst_0
       7: invokespecial #8                  // Method "<init>":(Ljava/lang/String;I)V
      10: putstatic     #9                  // Field APP:Lorg/apache/dubbo/metrics/model/key/MetricsLevel;
      13: new           #4                  // class org/apache/dubbo/metrics/model/key/MetricsLevel
      16: dup
      17: ldc           #10                 // String SERVICE
      19: iconst_1
      20: invokespecial #8                  // Method "<init>":(Ljava/lang/String;I)V
      23: putstatic     #11                 // Field SERVICE:Lorg/apache/dubbo/metrics/model/key/MetricsLevel;
      26: new           #4                  // class org/apache/dubbo/metrics/model/key/MetricsLevel
      29: dup
      30: ldc           #12                 // String METHOD
      32: iconst_2
      33: invokespecial #8                  // Method "<init>":(Ljava/lang/String;I)V
      36: putstatic     #13                 // Field METHOD:Lorg/apache/dubbo/metrics/model/key/MetricsLevel;
      39: new           #4                  // class org/apache/dubbo/metrics/model/key/MetricsLevel
      42: dup
      43: ldc           #14                 // String CONFIG
      45: iconst_3
      46: invokespecial #8                  // Method "<init>":(Ljava/lang/String;I)V
      49: putstatic     #15                 // Field CONFIG:Lorg/apache/dubbo/metrics/model/key/MetricsLevel;
      52: iconst_4
      53: anewarray     #4                  // class org/apache/dubbo/metrics/model/key/MetricsLevel
      56: dup
      57: iconst_0
      58: getstatic     #9                  // Field APP:Lorg/apache/dubbo/metrics/model/key/MetricsLevel;
      61: aastore
      62: dup
      63: iconst_1
      64: getstatic     #11                 // Field SERVICE:Lorg/apache/dubbo/metrics/model/key/MetricsLevel;
      67: aastore
      68: dup
      69: iconst_2
      70: getstatic     #13                 // Field METHOD:Lorg/apache/dubbo/metrics/model/key/MetricsLevel;
      73: aastore
      74: dup
      75: iconst_3
      76: getstatic     #15                 // Field CONFIG:Lorg/apache/dubbo/metrics/model/key/MetricsLevel;
      79: aastore
      80: putstatic     #1                  // Field $VALUES:[Lorg/apache/dubbo/metrics/model/key/MetricsLevel;
      83: return
}
