Compiled from "MetricsCat.java"
public class org.apache.dubbo.metrics.model.key.MetricsCat {
  private org.apache.dubbo.metrics.model.key.MetricsPlaceValue placeType;

  private final java.util.function.Function<org.apache.dubbo.metrics.collector.CombMetricsCollector, org.apache.dubbo.metrics.listener.AbstractMetricsKeyListener> eventFunc;

  public org.apache.dubbo.metrics.model.key.MetricsCat(org.apache.dubbo.metrics.model.key.MetricsKey, java.util.function.BiFunction<org.apache.dubbo.metrics.model.key.MetricsKey, org.apache.dubbo.metrics.collector.CombMetricsCollector, org.apache.dubbo.metrics.listener.AbstractMetricsKeyListener>);
    Code:
       0: aload_0
       1: invokespecial #1                  // Method java/lang/Object."<init>":()V
       4: aload_0
       5: aload_2
       6: aload_1
       7: invokedynamic #2,  0              // InvokeDynamic #0:apply:(Ljava/util/function/BiFunction;Lorg/apache/dubbo/metrics/model/key/MetricsKey;)Ljava/util/function/Function;
      12: putfield      #3                  // Field eventFunc:Ljava/util/function/Function;
      15: return

  public org.apache.dubbo.metrics.model.key.MetricsCat(org.apache.dubbo.metrics.model.key.MetricsKey, org.apache.dubbo.metrics.model.key.MetricsCat$TpFunction<org.apache.dubbo.metrics.model.key.MetricsKey, org.apache.dubbo.metrics.model.key.MetricsPlaceValue, org.apache.dubbo.metrics.collector.CombMetricsCollector, org.apache.dubbo.metrics.listener.AbstractMetricsKeyListener>);
    Code:
       0: aload_0
       1: invokespecial #1                  // Method java/lang/Object."<init>":()V
       4: aload_0
       5: aload_0
       6: aload_2
       7: aload_1
       8: invokedynamic #4,  0              // InvokeDynamic #1:apply:(Lorg/apache/dubbo/metrics/model/key/MetricsCat;Lorg/apache/dubbo/metrics/model/key/MetricsCat$TpFunction;Lorg/apache/dubbo/metrics/model/key/MetricsKey;)Ljava/util/function/Function;
      13: putfield      #3                  // Field eventFunc:Ljava/util/function/Function;
      16: return

  public org.apache.dubbo.metrics.model.key.MetricsCat setPlaceType(org.apache.dubbo.metrics.model.key.MetricsPlaceValue);
    Code:
       0: aload_0
       1: aload_1
       2: putfield      #5                  // Field placeType:Lorg/apache/dubbo/metrics/model/key/MetricsPlaceValue;
       5: aload_0
       6: areturn

  public java.util.function.Function<org.apache.dubbo.metrics.collector.CombMetricsCollector, org.apache.dubbo.metrics.listener.AbstractMetricsKeyListener> getEventFunc();
    Code:
       0: aload_0
       1: getfield      #3                  // Field eventFunc:Ljava/util/function/Function;
       4: areturn

  private org.apache.dubbo.metrics.listener.AbstractMetricsKeyListener lambda$new$1(org.apache.dubbo.metrics.model.key.MetricsCat$TpFunction, org.apache.dubbo.metrics.model.key.MetricsKey, org.apache.dubbo.metrics.collector.CombMetricsCollector);
    Code:
       0: aload_1
       1: aload_2
       2: aload_0
       3: getfield      #5                  // Field placeType:Lorg/apache/dubbo/metrics/model/key/MetricsPlaceValue;
       6: aload_3
       7: invokeinterface #6,  4            // InterfaceMethod org/apache/dubbo/metrics/model/key/MetricsCat$TpFunction.apply:(Ljava/lang/Object;Ljava/lang/Object;Ljava/lang/Object;)Ljava/lang/Object;
      12: checkcast     #7                  // class org/apache/dubbo/metrics/listener/AbstractMetricsKeyListener
      15: areturn

  private static org.apache.dubbo.metrics.listener.AbstractMetricsKeyListener lambda$new$0(java.util.function.BiFunction, org.apache.dubbo.metrics.model.key.MetricsKey, org.apache.dubbo.metrics.collector.CombMetricsCollector);
    Code:
       0: aload_0
       1: aload_1
       2: aload_2
       3: invokeinterface #8,  3            // InterfaceMethod java/util/function/BiFunction.apply:(Ljava/lang/Object;Ljava/lang/Object;)Ljava/lang/Object;
       8: checkcast     #7                  // class org/apache/dubbo/metrics/listener/AbstractMetricsKeyListener
      11: areturn
}
