Compiled from "TypeWrapper.java"
public class org.apache.dubbo.metrics.model.key.TypeWrapper {
  private final org.apache.dubbo.metrics.model.key.MetricsLevel level;

  private final org.apache.dubbo.metrics.model.key.MetricsKey postType;

  private final org.apache.dubbo.metrics.model.key.MetricsKey finishType;

  private final org.apache.dubbo.metrics.model.key.MetricsKey errorType;

  public org.apache.dubbo.metrics.model.key.TypeWrapper(org.apache.dubbo.metrics.model.key.MetricsLevel, org.apache.dubbo.metrics.model.key.MetricsKey);
    Code:
       0: aload_0
       1: aload_1
       2: aload_2
       3: aconst_null
       4: aconst_null
       5: invokespecial #1                  // Method "<init>":(Lorg/apache/dubbo/metrics/model/key/MetricsLevel;Lorg/apache/dubbo/metrics/model/key/MetricsKey;Lorg/apache/dubbo/metrics/model/key/MetricsKey;Lorg/apache/dubbo/metrics/model/key/MetricsKey;)V
       8: return

  public org.apache.dubbo.metrics.model.key.TypeWrapper(org.apache.dubbo.metrics.model.key.MetricsLevel, org.apache.dubbo.metrics.model.key.MetricsKey, org.apache.dubbo.metrics.model.key.MetricsKey, org.apache.dubbo.metrics.model.key.MetricsKey);
    Code:
       0: aload_0
       1: invokespecial #2                  // Method java/lang/Object."<init>":()V
       4: aload_0
       5: aload_1
       6: putfield      #3                  // Field level:Lorg/apache/dubbo/metrics/model/key/MetricsLevel;
       9: aload_0
      10: aload_2
      11: putfield      #4                  // Field postType:Lorg/apache/dubbo/metrics/model/key/MetricsKey;
      14: aload_0
      15: aload_3
      16: putfield      #5                  // Field finishType:Lorg/apache/dubbo/metrics/model/key/MetricsKey;
      19: aload_0
      20: aload         4
      22: putfield      #6                  // Field errorType:Lorg/apache/dubbo/metrics/model/key/MetricsKey;
      25: return

  public org.apache.dubbo.metrics.model.key.MetricsLevel getLevel();
    Code:
       0: aload_0
       1: getfield      #3                  // Field level:Lorg/apache/dubbo/metrics/model/key/MetricsLevel;
       4: areturn

  public boolean isAssignableFrom(java.lang.Object);
    Code:
       0: aload_1
       1: ldc           #7                  // String Type can not be null
       3: invokestatic  #8                  // Method org/apache/dubbo/common/utils/Assert.notNull:(Ljava/lang/Object;Ljava/lang/String;)V
       6: aload_1
       7: aload_0
       8: getfield      #4                  // Field postType:Lorg/apache/dubbo/metrics/model/key/MetricsKey;
      11: invokevirtual #9                  // Method java/lang/Object.equals:(Ljava/lang/Object;)Z
      14: ifne          39
      17: aload_1
      18: aload_0
      19: getfield      #5                  // Field finishType:Lorg/apache/dubbo/metrics/model/key/MetricsKey;
      22: invokevirtual #9                  // Method java/lang/Object.equals:(Ljava/lang/Object;)Z
      25: ifne          39
      28: aload_1
      29: aload_0
      30: getfield      #6                  // Field errorType:Lorg/apache/dubbo/metrics/model/key/MetricsKey;
      33: invokevirtual #9                  // Method java/lang/Object.equals:(Ljava/lang/Object;)Z
      36: ifeq          43
      39: iconst_1
      40: goto          44
      43: iconst_0
      44: ireturn
}
