Compiled from "Opcode.java"
public final class jadx.api.plugins.input.insns.Opcode extends java.lang.Enum<jadx.api.plugins.input.insns.Opcode> {
  public static final jadx.api.plugins.input.insns.Opcode UNKNOWN;

  public static final jadx.api.plugins.input.insns.Opcode NOP;

  public static final jadx.api.plugins.input.insns.Opcode ADD_DOUBLE;

  public static final jadx.api.plugins.input.insns.Opcode ADD_FLOAT;

  public static final jadx.api.plugins.input.insns.Opcode ADD_INT;

  public static final jadx.api.plugins.input.insns.Opcode ADD_INT_LIT;

  public static final jadx.api.plugins.input.insns.Opcode ADD_LONG;

  public static final jadx.api.plugins.input.insns.Opcode AND_INT;

  public static final jadx.api.plugins.input.insns.Opcode AND_INT_LIT;

  public static final jadx.api.plugins.input.insns.Opcode AND_LONG;

  public static final jadx.api.plugins.input.insns.Opcode AGET;

  public static final jadx.api.plugins.input.insns.Opcode AGET_BOOLEAN;

  public static final jadx.api.plugins.input.insns.Opcode AGET_BYTE;

  public static final jadx.api.plugins.input.insns.Opcode AGET_BYTE_BOOLEAN;

  public static final jadx.api.plugins.input.insns.Opcode AGET_CHAR;

  public static final jadx.api.plugins.input.insns.Opcode AGET_OBJECT;

  public static final jadx.api.plugins.input.insns.Opcode AGET_SHORT;

  public static final jadx.api.plugins.input.insns.Opcode AGET_WIDE;

  public static final jadx.api.plugins.input.insns.Opcode APUT;

  public static final jadx.api.plugins.input.insns.Opcode APUT_BOOLEAN;

  public static final jadx.api.plugins.input.insns.Opcode APUT_BYTE;

  public static final jadx.api.plugins.input.insns.Opcode APUT_BYTE_BOOLEAN;

  public static final jadx.api.plugins.input.insns.Opcode APUT_CHAR;

  public static final jadx.api.plugins.input.insns.Opcode APUT_OBJECT;

  public static final jadx.api.plugins.input.insns.Opcode APUT_SHORT;

  public static final jadx.api.plugins.input.insns.Opcode APUT_WIDE;

  public static final jadx.api.plugins.input.insns.Opcode ARITH;

  public static final jadx.api.plugins.input.insns.Opcode ARRAY_LENGTH;

  public static final jadx.api.plugins.input.insns.Opcode CAST;

  public static final jadx.api.plugins.input.insns.Opcode CHECK_CAST;

  public static final jadx.api.plugins.input.insns.Opcode CMPG_DOUBLE;

  public static final jadx.api.plugins.input.insns.Opcode CMPG_FLOAT;

  public static final jadx.api.plugins.input.insns.Opcode CMPL_DOUBLE;

  public static final jadx.api.plugins.input.insns.Opcode CMPL_FLOAT;

  public static final jadx.api.plugins.input.insns.Opcode CMP_LONG;

  public static final jadx.api.plugins.input.insns.Opcode CONST;

  public static final jadx.api.plugins.input.insns.Opcode CONST_CLASS;

  public static final jadx.api.plugins.input.insns.Opcode CONST_STRING;

  public static final jadx.api.plugins.input.insns.Opcode CONST_WIDE;

  public static final jadx.api.plugins.input.insns.Opcode DIV_DOUBLE;

  public static final jadx.api.plugins.input.insns.Opcode DIV_FLOAT;

  public static final jadx.api.plugins.input.insns.Opcode DIV_INT;

  public static final jadx.api.plugins.input.insns.Opcode DIV_INT_LIT;

  public static final jadx.api.plugins.input.insns.Opcode DIV_LONG;

  public static final jadx.api.plugins.input.insns.Opcode DOUBLE_TO_FLOAT;

  public static final jadx.api.plugins.input.insns.Opcode DOUBLE_TO_INT;

  public static final jadx.api.plugins.input.insns.Opcode DOUBLE_TO_LONG;

  public static final jadx.api.plugins.input.insns.Opcode FLOAT_TO_DOUBLE;

  public static final jadx.api.plugins.input.insns.Opcode FLOAT_TO_INT;

  public static final jadx.api.plugins.input.insns.Opcode FLOAT_TO_LONG;

  public static final jadx.api.plugins.input.insns.Opcode GOTO;

  public static final jadx.api.plugins.input.insns.Opcode IF;

  public static final jadx.api.plugins.input.insns.Opcode IF_EQ;

  public static final jadx.api.plugins.input.insns.Opcode IF_EQZ;

  public static final jadx.api.plugins.input.insns.Opcode IF_GE;

  public static final jadx.api.plugins.input.insns.Opcode IF_GEZ;

  public static final jadx.api.plugins.input.insns.Opcode IF_GT;

  public static final jadx.api.plugins.input.insns.Opcode IF_GTZ;

  public static final jadx.api.plugins.input.insns.Opcode IF_LE;

  public static final jadx.api.plugins.input.insns.Opcode IF_LEZ;

  public static final jadx.api.plugins.input.insns.Opcode IF_LT;

  public static final jadx.api.plugins.input.insns.Opcode IF_LTZ;

  public static final jadx.api.plugins.input.insns.Opcode IF_NE;

  public static final jadx.api.plugins.input.insns.Opcode IF_NEZ;

  public static final jadx.api.plugins.input.insns.Opcode INSTANCE_OF;

  public static final jadx.api.plugins.input.insns.Opcode INT_TO_BYTE;

  public static final jadx.api.plugins.input.insns.Opcode INT_TO_CHAR;

  public static final jadx.api.plugins.input.insns.Opcode INT_TO_DOUBLE;

  public static final jadx.api.plugins.input.insns.Opcode INT_TO_FLOAT;

  public static final jadx.api.plugins.input.insns.Opcode INT_TO_LONG;

  public static final jadx.api.plugins.input.insns.Opcode INT_TO_SHORT;

  public static final jadx.api.plugins.input.insns.Opcode INVOKE_DIRECT;

  public static final jadx.api.plugins.input.insns.Opcode INVOKE_DIRECT_RANGE;

  public static final jadx.api.plugins.input.insns.Opcode INVOKE_INTERFACE;

  public static final jadx.api.plugins.input.insns.Opcode INVOKE_INTERFACE_RANGE;

  public static final jadx.api.plugins.input.insns.Opcode INVOKE_STATIC;

  public static final jadx.api.plugins.input.insns.Opcode INVOKE_STATIC_RANGE;

  public static final jadx.api.plugins.input.insns.Opcode INVOKE_SUPER;

  public static final jadx.api.plugins.input.insns.Opcode INVOKE_SUPER_RANGE;

  public static final jadx.api.plugins.input.insns.Opcode INVOKE_VIRTUAL;

  public static final jadx.api.plugins.input.insns.Opcode INVOKE_VIRTUAL_RANGE;

  public static final jadx.api.plugins.input.insns.Opcode INVOKE_SPECIAL;

  public static final jadx.api.plugins.input.insns.Opcode IGET;

  public static final jadx.api.plugins.input.insns.Opcode IPUT;

  public static final jadx.api.plugins.input.insns.Opcode SGET;

  public static final jadx.api.plugins.input.insns.Opcode SPUT;

  public static final jadx.api.plugins.input.insns.Opcode LONG_TO_DOUBLE;

  public static final jadx.api.plugins.input.insns.Opcode LONG_TO_FLOAT;

  public static final jadx.api.plugins.input.insns.Opcode LONG_TO_INT;

  public static final jadx.api.plugins.input.insns.Opcode MONITOR_ENTER;

  public static final jadx.api.plugins.input.insns.Opcode MONITOR_EXIT;

  public static final jadx.api.plugins.input.insns.Opcode MOVE;

  public static final jadx.api.plugins.input.insns.Opcode MOVE_MULTI;

  public static final jadx.api.plugins.input.insns.Opcode MOVE_EXCEPTION;

  public static final jadx.api.plugins.input.insns.Opcode MOVE_OBJECT;

  public static final jadx.api.plugins.input.insns.Opcode MOVE_RESULT;

  public static final jadx.api.plugins.input.insns.Opcode MOVE_WIDE;

  public static final jadx.api.plugins.input.insns.Opcode MUL_DOUBLE;

  public static final jadx.api.plugins.input.insns.Opcode MUL_FLOAT;

  public static final jadx.api.plugins.input.insns.Opcode MUL_INT;

  public static final jadx.api.plugins.input.insns.Opcode MUL_INT_LIT;

  public static final jadx.api.plugins.input.insns.Opcode MUL_LONG;

  public static final jadx.api.plugins.input.insns.Opcode NEG;

  public static final jadx.api.plugins.input.insns.Opcode NEG_DOUBLE;

  public static final jadx.api.plugins.input.insns.Opcode NEG_FLOAT;

  public static final jadx.api.plugins.input.insns.Opcode NEG_INT;

  public static final jadx.api.plugins.input.insns.Opcode NEG_LONG;

  public static final jadx.api.plugins.input.insns.Opcode NEW_INSTANCE;

  public static final jadx.api.plugins.input.insns.Opcode NOT_INT;

  public static final jadx.api.plugins.input.insns.Opcode NOT_LONG;

  public static final jadx.api.plugins.input.insns.Opcode OR_INT;

  public static final jadx.api.plugins.input.insns.Opcode OR_INT_LIT;

  public static final jadx.api.plugins.input.insns.Opcode OR_LONG;

  public static final jadx.api.plugins.input.insns.Opcode REM_DOUBLE;

  public static final jadx.api.plugins.input.insns.Opcode REM_FLOAT;

  public static final jadx.api.plugins.input.insns.Opcode REM_INT;

  public static final jadx.api.plugins.input.insns.Opcode REM_INT_LIT;

  public static final jadx.api.plugins.input.insns.Opcode REM_LONG;

  public static final jadx.api.plugins.input.insns.Opcode RETURN;

  public static final jadx.api.plugins.input.insns.Opcode RETURN_VOID;

  public static final jadx.api.plugins.input.insns.Opcode RSUB_INT;

  public static final jadx.api.plugins.input.insns.Opcode SHL_INT;

  public static final jadx.api.plugins.input.insns.Opcode SHL_INT_LIT;

  public static final jadx.api.plugins.input.insns.Opcode SHL_LONG;

  public static final jadx.api.plugins.input.insns.Opcode SHR_INT;

  public static final jadx.api.plugins.input.insns.Opcode SHR_INT_LIT;

  public static final jadx.api.plugins.input.insns.Opcode SHR_LONG;

  public static final jadx.api.plugins.input.insns.Opcode SUB_DOUBLE;

  public static final jadx.api.plugins.input.insns.Opcode SUB_FLOAT;

  public static final jadx.api.plugins.input.insns.Opcode SUB_INT;

  public static final jadx.api.plugins.input.insns.Opcode SUB_LONG;

  public static final jadx.api.plugins.input.insns.Opcode THROW;

  public static final jadx.api.plugins.input.insns.Opcode USHR_INT;

  public static final jadx.api.plugins.input.insns.Opcode USHR_INT_LIT;

  public static final jadx.api.plugins.input.insns.Opcode USHR_LONG;

  public static final jadx.api.plugins.input.insns.Opcode XOR_INT;

  public static final jadx.api.plugins.input.insns.Opcode XOR_INT_LIT;

  public static final jadx.api.plugins.input.insns.Opcode XOR_LONG;

  public static final jadx.api.plugins.input.insns.Opcode NEW_ARRAY;

  public static final jadx.api.plugins.input.insns.Opcode FILLED_NEW_ARRAY;

  public static final jadx.api.plugins.input.insns.Opcode FILLED_NEW_ARRAY_RANGE;

  public static final jadx.api.plugins.input.insns.Opcode FILL_ARRAY_DATA;

  public static final jadx.api.plugins.input.insns.Opcode FILL_ARRAY_DATA_PAYLOAD;

  public static final jadx.api.plugins.input.insns.Opcode PACKED_SWITCH;

  public static final jadx.api.plugins.input.insns.Opcode PACKED_SWITCH_PAYLOAD;

  public static final jadx.api.plugins.input.insns.Opcode SPARSE_SWITCH;

  public static final jadx.api.plugins.input.insns.Opcode SPARSE_SWITCH_PAYLOAD;

  public static final jadx.api.plugins.input.insns.Opcode INVOKE_POLYMORPHIC;

  public static final jadx.api.plugins.input.insns.Opcode INVOKE_POLYMORPHIC_RANGE;

  public static final jadx.api.plugins.input.insns.Opcode INVOKE_CUSTOM;

  public static final jadx.api.plugins.input.insns.Opcode INVOKE_CUSTOM_RANGE;

  public static final jadx.api.plugins.input.insns.Opcode CONST_METHOD_HANDLE;

  public static final jadx.api.plugins.input.insns.Opcode CONST_METHOD_TYPE;

  private static final jadx.api.plugins.input.insns.Opcode[] $VALUES;

  public static jadx.api.plugins.input.insns.Opcode[] values();
    Code:
       0: getstatic     #1                  // Field $VALUES:[Ljadx/api/plugins/input/insns/Opcode;
       3: invokevirtual #2                  // Method "[Ljadx/api/plugins/input/insns/Opcode;".clone:()Ljava/lang/Object;
       6: checkcast     #3                  // class "[Ljadx/api/plugins/input/insns/Opcode;"
       9: areturn

  public static jadx.api.plugins.input.insns.Opcode valueOf(java.lang.String);
    Code:
       0: ldc           #4                  // class jadx/api/plugins/input/insns/Opcode
       2: aload_0
       3: invokestatic  #5                  // Method java/lang/Enum.valueOf:(Ljava/lang/Class;Ljava/lang/String;)Ljava/lang/Enum;
       6: checkcast     #4                  // class jadx/api/plugins/input/insns/Opcode
       9: areturn

  private jadx.api.plugins.input.insns.Opcode();
    Code:
       0: aload_0
       1: aload_1
       2: iload_2
       3: invokespecial #6                  // Method java/lang/Enum."<init>":(Ljava/lang/String;I)V
       6: return

  static {};
    Code:
       0: new           #4                  // class jadx/api/plugins/input/insns/Opcode
       3: dup
       4: ldc           #7                  // String UNKNOWN
       6: iconst_0
       7: invokespecial #8                  // Method "<init>":(Ljava/lang/String;I)V
      10: putstatic     #9                  // Field UNKNOWN:Ljadx/api/plugins/input/insns/Opcode;
      13: new           #4                  // class jadx/api/plugins/input/insns/Opcode
      16: dup
      17: ldc           #10                 // String NOP
      19: iconst_1
      20: invokespecial #8                  // Method "<init>":(Ljava/lang/String;I)V
      23: putstatic     #11                 // Field NOP:Ljadx/api/plugins/input/insns/Opcode;
      26: new           #4                  // class jadx/api/plugins/input/insns/Opcode
      29: dup
      30: ldc           #12                 // String ADD_DOUBLE
      32: iconst_2
      33: invokespecial #8                  // Method "<init>":(Ljava/lang/String;I)V
      36: putstatic     #13                 // Field ADD_DOUBLE:Ljadx/api/plugins/input/insns/Opcode;
      39: new           #4                  // class jadx/api/plugins/input/insns/Opcode
      42: dup
      43: ldc           #14                 // String ADD_FLOAT
      45: iconst_3
      46: invokespecial #8                  // Method "<init>":(Ljava/lang/String;I)V
      49: putstatic     #15                 // Field ADD_FLOAT:Ljadx/api/plugins/input/insns/Opcode;
      52: new           #4                  // class jadx/api/plugins/input/insns/Opcode
      55: dup
      56: ldc           #16                 // String ADD_INT
      58: iconst_4
      59: invokespecial #8                  // Method "<init>":(Ljava/lang/String;I)V
      62: putstatic     #17                 // Field ADD_INT:Ljadx/api/plugins/input/insns/Opcode;
      65: new           #4                  // class jadx/api/plugins/input/insns/Opcode
      68: dup
      69: ldc           #18                 // String ADD_INT_LIT
      71: iconst_5
      72: invokespecial #8                  // Method "<init>":(Ljava/lang/String;I)V
      75: putstatic     #19                 // Field ADD_INT_LIT:Ljadx/api/plugins/input/insns/Opcode;
      78: new           #4                  // class jadx/api/plugins/input/insns/Opcode
      81: dup
      82: ldc           #20                 // String ADD_LONG
      84: bipush        6
      86: invokespecial #8                  // Method "<init>":(Ljava/lang/String;I)V
      89: putstatic     #21                 // Field ADD_LONG:Ljadx/api/plugins/input/insns/Opcode;
      92: new           #4                  // class jadx/api/plugins/input/insns/Opcode
      95: dup
      96: ldc           #22                 // String AND_INT
      98: bipush        7
     100: invokespecial #8                  // Method "<init>":(Ljava/lang/String;I)V
     103: putstatic     #23                 // Field AND_INT:Ljadx/api/plugins/input/insns/Opcode;
     106: new           #4                  // class jadx/api/plugins/input/insns/Opcode
     109: dup
     110: ldc           #24                 // String AND_INT_LIT
     112: bipush        8
     114: invokespecial #8                  // Method "<init>":(Ljava/lang/String;I)V
     117: putstatic     #25                 // Field AND_INT_LIT:Ljadx/api/plugins/input/insns/Opcode;
     120: new           #4                  // class jadx/api/plugins/input/insns/Opcode
     123: dup
     124: ldc           #26                 // String AND_LONG
     126: bipush        9
     128: invokespecial #8                  // Method "<init>":(Ljava/lang/String;I)V
     131: putstatic     #27                 // Field AND_LONG:Ljadx/api/plugins/input/insns/Opcode;
     134: new           #4                  // class jadx/api/plugins/input/insns/Opcode
     137: dup
     138: ldc           #28                 // String AGET
     140: bipush        10
     142: invokespecial #8                  // Method "<init>":(Ljava/lang/String;I)V
     145: putstatic     #29                 // Field AGET:Ljadx/api/plugins/input/insns/Opcode;
     148: new           #4                  // class jadx/api/plugins/input/insns/Opcode
     151: dup
     152: ldc           #30                 // String AGET_BOOLEAN
     154: bipush        11
     156: invokespecial #8                  // Method "<init>":(Ljava/lang/String;I)V
     159: putstatic     #31                 // Field AGET_BOOLEAN:Ljadx/api/plugins/input/insns/Opcode;
     162: new           #4                  // class jadx/api/plugins/input/insns/Opcode
     165: dup
     166: ldc           #32                 // String AGET_BYTE
     168: bipush        12
     170: invokespecial #8                  // Method "<init>":(Ljava/lang/String;I)V
     173: putstatic     #33                 // Field AGET_BYTE:Ljadx/api/plugins/input/insns/Opcode;
     176: new           #4                  // class jadx/api/plugins/input/insns/Opcode
     179: dup
     180: ldc           #34                 // String AGET_BYTE_BOOLEAN
     182: bipush        13
     184: invokespecial #8                  // Method "<init>":(Ljava/lang/String;I)V
     187: putstatic     #35                 // Field AGET_BYTE_BOOLEAN:Ljadx/api/plugins/input/insns/Opcode;
     190: new           #4                  // class jadx/api/plugins/input/insns/Opcode
     193: dup
     194: ldc           #36                 // String AGET_CHAR
     196: bipush        14
     198: invokespecial #8                  // Method "<init>":(Ljava/lang/String;I)V
     201: putstatic     #37                 // Field AGET_CHAR:Ljadx/api/plugins/input/insns/Opcode;
     204: new           #4                  // class jadx/api/plugins/input/insns/Opcode
     207: dup
     208: ldc           #38                 // String AGET_OBJECT
     210: bipush        15
     212: invokespecial #8                  // Method "<init>":(Ljava/lang/String;I)V
     215: putstatic     #39                 // Field AGET_OBJECT:Ljadx/api/plugins/input/insns/Opcode;
     218: new           #4                  // class jadx/api/plugins/input/insns/Opcode
     221: dup
     222: ldc           #40                 // String AGET_SHORT
     224: bipush        16
     226: invokespecial #8                  // Method "<init>":(Ljava/lang/String;I)V
     229: putstatic     #41                 // Field AGET_SHORT:Ljadx/api/plugins/input/insns/Opcode;
     232: new           #4                  // class jadx/api/plugins/input/insns/Opcode
     235: dup
     236: ldc           #42                 // String AGET_WIDE
     238: bipush        17
     240: invokespecial #8                  // Method "<init>":(Ljava/lang/String;I)V
     243: putstatic     #43                 // Field AGET_WIDE:Ljadx/api/plugins/input/insns/Opcode;
     246: new           #4                  // class jadx/api/plugins/input/insns/Opcode
     249: dup
     250: ldc           #44                 // String APUT
     252: bipush        18
     254: invokespecial #8                  // Method "<init>":(Ljava/lang/String;I)V
     257: putstatic     #45                 // Field APUT:Ljadx/api/plugins/input/insns/Opcode;
     260: new           #4                  // class jadx/api/plugins/input/insns/Opcode
     263: dup
     264: ldc           #46                 // String APUT_BOOLEAN
     266: bipush        19
     268: invokespecial #8                  // Method "<init>":(Ljava/lang/String;I)V
     271: putstatic     #47                 // Field APUT_BOOLEAN:Ljadx/api/plugins/input/insns/Opcode;
     274: new           #4                  // class jadx/api/plugins/input/insns/Opcode
     277: dup
     278: ldc           #48                 // String APUT_BYTE
     280: bipush        20
     282: invokespecial #8                  // Method "<init>":(Ljava/lang/String;I)V
     285: putstatic     #49                 // Field APUT_BYTE:Ljadx/api/plugins/input/insns/Opcode;
     288: new           #4                  // class jadx/api/plugins/input/insns/Opcode
     291: dup
     292: ldc           #50                 // String APUT_BYTE_BOOLEAN
     294: bipush        21
     296: invokespecial #8                  // Method "<init>":(Ljava/lang/String;I)V
     299: putstatic     #51                 // Field APUT_BYTE_BOOLEAN:Ljadx/api/plugins/input/insns/Opcode;
     302: new           #4                  // class jadx/api/plugins/input/insns/Opcode
     305: dup
     306: ldc           #52                 // String APUT_CHAR
     308: bipush        22
     310: invokespecial #8                  // Method "<init>":(Ljava/lang/String;I)V
     313: putstatic     #53                 // Field APUT_CHAR:Ljadx/api/plugins/input/insns/Opcode;
     316: new           #4                  // class jadx/api/plugins/input/insns/Opcode
     319: dup
     320: ldc           #54                 // String APUT_OBJECT
     322: bipush        23
     324: invokespecial #8                  // Method "<init>":(Ljava/lang/String;I)V
     327: putstatic     #55                 // Field APUT_OBJECT:Ljadx/api/plugins/input/insns/Opcode;
     330: new           #4                  // class jadx/api/plugins/input/insns/Opcode
     333: dup
     334: ldc           #56                 // String APUT_SHORT
     336: bipush        24
     338: invokespecial #8                  // Method "<init>":(Ljava/lang/String;I)V
     341: putstatic     #57                 // Field APUT_SHORT:Ljadx/api/plugins/input/insns/Opcode;
     344: new           #4                  // class jadx/api/plugins/input/insns/Opcode
     347: dup
     348: ldc           #58                 // String APUT_WIDE
     350: bipush        25
     352: invokespecial #8                  // Method "<init>":(Ljava/lang/String;I)V
     355: putstatic     #59                 // Field APUT_WIDE:Ljadx/api/plugins/input/insns/Opcode;
     358: new           #4                  // class jadx/api/plugins/input/insns/Opcode
     361: dup
     362: ldc           #60                 // String ARITH
     364: bipush        26
     366: invokespecial #8                  // Method "<init>":(Ljava/lang/String;I)V
     369: putstatic     #61                 // Field ARITH:Ljadx/api/plugins/input/insns/Opcode;
     372: new           #4                  // class jadx/api/plugins/input/insns/Opcode
     375: dup
     376: ldc           #62                 // String ARRAY_LENGTH
     378: bipush        27
     380: invokespecial #8                  // Method "<init>":(Ljava/lang/String;I)V
     383: putstatic     #63                 // Field ARRAY_LENGTH:Ljadx/api/plugins/input/insns/Opcode;
     386: new           #4                  // class jadx/api/plugins/input/insns/Opcode
     389: dup
     390: ldc           #64                 // String CAST
     392: bipush        28
     394: invokespecial #8                  // Method "<init>":(Ljava/lang/String;I)V
     397: putstatic     #65                 // Field CAST:Ljadx/api/plugins/input/insns/Opcode;
     400: new           #4                  // class jadx/api/plugins/input/insns/Opcode
     403: dup
     404: ldc           #66                 // String CHECK_CAST
     406: bipush        29
     408: invokespecial #8                  // Method "<init>":(Ljava/lang/String;I)V
     411: putstatic     #67                 // Field CHECK_CAST:Ljadx/api/plugins/input/insns/Opcode;
     414: new           #4                  // class jadx/api/plugins/input/insns/Opcode
     417: dup
     418: ldc           #68                 // String CMPG_DOUBLE
     420: bipush        30
     422: invokespecial #8                  // Method "<init>":(Ljava/lang/String;I)V
     425: putstatic     #69                 // Field CMPG_DOUBLE:Ljadx/api/plugins/input/insns/Opcode;
     428: new           #4                  // class jadx/api/plugins/input/insns/Opcode
     431: dup
     432: ldc           #70                 // String CMPG_FLOAT
     434: bipush        31
     436: invokespecial #8                  // Method "<init>":(Ljava/lang/String;I)V
     439: putstatic     #71                 // Field CMPG_FLOAT:Ljadx/api/plugins/input/insns/Opcode;
     442: new           #4                  // class jadx/api/plugins/input/insns/Opcode
     445: dup
     446: ldc           #72                 // String CMPL_DOUBLE
     448: bipush        32
     450: invokespecial #8                  // Method "<init>":(Ljava/lang/String;I)V
     453: putstatic     #73                 // Field CMPL_DOUBLE:Ljadx/api/plugins/input/insns/Opcode;
     456: new           #4                  // class jadx/api/plugins/input/insns/Opcode
     459: dup
     460: ldc           #74                 // String CMPL_FLOAT
     462: bipush        33
     464: invokespecial #8                  // Method "<init>":(Ljava/lang/String;I)V
     467: putstatic     #75                 // Field CMPL_FLOAT:Ljadx/api/plugins/input/insns/Opcode;
     470: new           #4                  // class jadx/api/plugins/input/insns/Opcode
     473: dup
     474: ldc           #76                 // String CMP_LONG
     476: bipush        34
     478: invokespecial #8                  // Method "<init>":(Ljava/lang/String;I)V
     481: putstatic     #77                 // Field CMP_LONG:Ljadx/api/plugins/input/insns/Opcode;
     484: new           #4                  // class jadx/api/plugins/input/insns/Opcode
     487: dup
     488: ldc           #78                 // String CONST
     490: bipush        35
     492: invokespecial #8                  // Method "<init>":(Ljava/lang/String;I)V
     495: putstatic     #79                 // Field CONST:Ljadx/api/plugins/input/insns/Opcode;
     498: new           #4                  // class jadx/api/plugins/input/insns/Opcode
     501: dup
     502: ldc           #80                 // String CONST_CLASS
     504: bipush        36
     506: invokespecial #8                  // Method "<init>":(Ljava/lang/String;I)V
     509: putstatic     #81                 // Field CONST_CLASS:Ljadx/api/plugins/input/insns/Opcode;
     512: new           #4                  // class jadx/api/plugins/input/insns/Opcode
     515: dup
     516: ldc           #82                 // String CONST_STRING
     518: bipush        37
     520: invokespecial #8                  // Method "<init>":(Ljava/lang/String;I)V
     523: putstatic     #83                 // Field CONST_STRING:Ljadx/api/plugins/input/insns/Opcode;
     526: new           #4                  // class jadx/api/plugins/input/insns/Opcode
     529: dup
     530: ldc           #84                 // String CONST_WIDE
     532: bipush        38
     534: invokespecial #8                  // Method "<init>":(Ljava/lang/String;I)V
     537: putstatic     #85                 // Field CONST_WIDE:Ljadx/api/plugins/input/insns/Opcode;
     540: new           #4                  // class jadx/api/plugins/input/insns/Opcode
     543: dup
     544: ldc           #86                 // String DIV_DOUBLE
     546: bipush        39
     548: invokespecial #8                  // Method "<init>":(Ljava/lang/String;I)V
     551: putstatic     #87                 // Field DIV_DOUBLE:Ljadx/api/plugins/input/insns/Opcode;
     554: new           #4                  // class jadx/api/plugins/input/insns/Opcode
     557: dup
     558: ldc           #88                 // String DIV_FLOAT
     560: bipush        40
     562: invokespecial #8                  // Method "<init>":(Ljava/lang/String;I)V
     565: putstatic     #89                 // Field DIV_FLOAT:Ljadx/api/plugins/input/insns/Opcode;
     568: new           #4                  // class jadx/api/plugins/input/insns/Opcode
     571: dup
     572: ldc           #90                 // String DIV_INT
     574: bipush        41
     576: invokespecial #8                  // Method "<init>":(Ljava/lang/String;I)V
     579: putstatic     #91                 // Field DIV_INT:Ljadx/api/plugins/input/insns/Opcode;
     582: new           #4                  // class jadx/api/plugins/input/insns/Opcode
     585: dup
     586: ldc           #92                 // String DIV_INT_LIT
     588: bipush        42
     590: invokespecial #8                  // Method "<init>":(Ljava/lang/String;I)V
     593: putstatic     #93                 // Field DIV_INT_LIT:Ljadx/api/plugins/input/insns/Opcode;
     596: new           #4                  // class jadx/api/plugins/input/insns/Opcode
     599: dup
     600: ldc           #94                 // String DIV_LONG
     602: bipush        43
     604: invokespecial #8                  // Method "<init>":(Ljava/lang/String;I)V
     607: putstatic     #95                 // Field DIV_LONG:Ljadx/api/plugins/input/insns/Opcode;
     610: new           #4                  // class jadx/api/plugins/input/insns/Opcode
     613: dup
     614: ldc           #96                 // String DOUBLE_TO_FLOAT
     616: bipush        44
     618: invokespecial #8                  // Method "<init>":(Ljava/lang/String;I)V
     621: putstatic     #97                 // Field DOUBLE_TO_FLOAT:Ljadx/api/plugins/input/insns/Opcode;
     624: new           #4                  // class jadx/api/plugins/input/insns/Opcode
     627: dup
     628: ldc           #98                 // String DOUBLE_TO_INT
     630: bipush        45
     632: invokespecial #8                  // Method "<init>":(Ljava/lang/String;I)V
     635: putstatic     #99                 // Field DOUBLE_TO_INT:Ljadx/api/plugins/input/insns/Opcode;
     638: new           #4                  // class jadx/api/plugins/input/insns/Opcode
     641: dup
     642: ldc           #100                // String DOUBLE_TO_LONG
     644: bipush        46
     646: invokespecial #8                  // Method "<init>":(Ljava/lang/String;I)V
     649: putstatic     #101                // Field DOUBLE_TO_LONG:Ljadx/api/plugins/input/insns/Opcode;
     652: new           #4                  // class jadx/api/plugins/input/insns/Opcode
     655: dup
     656: ldc           #102                // String FLOAT_TO_DOUBLE
     658: bipush        47
     660: invokespecial #8                  // Method "<init>":(Ljava/lang/String;I)V
     663: putstatic     #103                // Field FLOAT_TO_DOUBLE:Ljadx/api/plugins/input/insns/Opcode;
     666: new           #4                  // class jadx/api/plugins/input/insns/Opcode
     669: dup
     670: ldc           #104                // String FLOAT_TO_INT
     672: bipush        48
     674: invokespecial #8                  // Method "<init>":(Ljava/lang/String;I)V
     677: putstatic     #105                // Field FLOAT_TO_INT:Ljadx/api/plugins/input/insns/Opcode;
     680: new           #4                  // class jadx/api/plugins/input/insns/Opcode
     683: dup
     684: ldc           #106                // String FLOAT_TO_LONG
     686: bipush        49
     688: invokespecial #8                  // Method "<init>":(Ljava/lang/String;I)V
     691: putstatic     #107                // Field FLOAT_TO_LONG:Ljadx/api/plugins/input/insns/Opcode;
     694: new           #4                  // class jadx/api/plugins/input/insns/Opcode
     697: dup
     698: ldc           #108                // String GOTO
     700: bipush        50
     702: invokespecial #8                  // Method "<init>":(Ljava/lang/String;I)V
     705: putstatic     #109                // Field GOTO:Ljadx/api/plugins/input/insns/Opcode;
     708: new           #4                  // class jadx/api/plugins/input/insns/Opcode
     711: dup
     712: ldc           #110                // String IF
     714: bipush        51
     716: invokespecial #8                  // Method "<init>":(Ljava/lang/String;I)V
     719: putstatic     #111                // Field IF:Ljadx/api/plugins/input/insns/Opcode;
     722: new           #4                  // class jadx/api/plugins/input/insns/Opcode
     725: dup
     726: ldc           #112                // String IF_EQ
     728: bipush        52
     730: invokespecial #8                  // Method "<init>":(Ljava/lang/String;I)V
     733: putstatic     #113                // Field IF_EQ:Ljadx/api/plugins/input/insns/Opcode;
     736: new           #4                  // class jadx/api/plugins/input/insns/Opcode
     739: dup
     740: ldc           #114                // String IF_EQZ
     742: bipush        53
     744: invokespecial #8                  // Method "<init>":(Ljava/lang/String;I)V
     747: putstatic     #115                // Field IF_EQZ:Ljadx/api/plugins/input/insns/Opcode;
     750: new           #4                  // class jadx/api/plugins/input/insns/Opcode
     753: dup
     754: ldc           #116                // String IF_GE
     756: bipush        54
     758: invokespecial #8                  // Method "<init>":(Ljava/lang/String;I)V
     761: putstatic     #117                // Field IF_GE:Ljadx/api/plugins/input/insns/Opcode;
     764: new           #4                  // class jadx/api/plugins/input/insns/Opcode
     767: dup
     768: ldc           #118                // String IF_GEZ
     770: bipush        55
     772: invokespecial #8                  // Method "<init>":(Ljava/lang/String;I)V
     775: putstatic     #119                // Field IF_GEZ:Ljadx/api/plugins/input/insns/Opcode;
     778: new           #4                  // class jadx/api/plugins/input/insns/Opcode
     781: dup
     782: ldc           #120                // String IF_GT
     784: bipush        56
     786: invokespecial #8                  // Method "<init>":(Ljava/lang/String;I)V
     789: putstatic     #121                // Field IF_GT:Ljadx/api/plugins/input/insns/Opcode;
     792: new           #4                  // class jadx/api/plugins/input/insns/Opcode
     795: dup
     796: ldc           #122                // String IF_GTZ
     798: bipush        57
     800: invokespecial #8                  // Method "<init>":(Ljava/lang/String;I)V
     803: putstatic     #123                // Field IF_GTZ:Ljadx/api/plugins/input/insns/Opcode;
     806: new           #4                  // class jadx/api/plugins/input/insns/Opcode
     809: dup
     810: ldc           #124                // String IF_LE
     812: bipush        58
     814: invokespecial #8                  // Method "<init>":(Ljava/lang/String;I)V
     817: putstatic     #125                // Field IF_LE:Ljadx/api/plugins/input/insns/Opcode;
     820: new           #4                  // class jadx/api/plugins/input/insns/Opcode
     823: dup
     824: ldc           #126                // String IF_LEZ
     826: bipush        59
     828: invokespecial #8                  // Method "<init>":(Ljava/lang/String;I)V
     831: putstatic     #127                // Field IF_LEZ:Ljadx/api/plugins/input/insns/Opcode;
     834: new           #4                  // class jadx/api/plugins/input/insns/Opcode
     837: dup
     838: ldc           #128                // String IF_LT
     840: bipush        60
     842: invokespecial #8                  // Method "<init>":(Ljava/lang/String;I)V
     845: putstatic     #129                // Field IF_LT:Ljadx/api/plugins/input/insns/Opcode;
     848: new           #4                  // class jadx/api/plugins/input/insns/Opcode
     851: dup
     852: ldc           #130                // String IF_LTZ
     854: bipush        61
     856: invokespecial #8                  // Method "<init>":(Ljava/lang/String;I)V
     859: putstatic     #131                // Field IF_LTZ:Ljadx/api/plugins/input/insns/Opcode;
     862: new           #4                  // class jadx/api/plugins/input/insns/Opcode
     865: dup
     866: ldc           #132                // String IF_NE
     868: bipush        62
     870: invokespecial #8                  // Method "<init>":(Ljava/lang/String;I)V
     873: putstatic     #133                // Field IF_NE:Ljadx/api/plugins/input/insns/Opcode;
     876: new           #4                  // class jadx/api/plugins/input/insns/Opcode
     879: dup
     880: ldc           #134                // String IF_NEZ
     882: bipush        63
     884: invokespecial #8                  // Method "<init>":(Ljava/lang/String;I)V
     887: putstatic     #135                // Field IF_NEZ:Ljadx/api/plugins/input/insns/Opcode;
     890: new           #4                  // class jadx/api/plugins/input/insns/Opcode
     893: dup
     894: ldc           #136                // String INSTANCE_OF
     896: bipush        64
     898: invokespecial #8                  // Method "<init>":(Ljava/lang/String;I)V
     901: putstatic     #137                // Field INSTANCE_OF:Ljadx/api/plugins/input/insns/Opcode;
     904: new           #4                  // class jadx/api/plugins/input/insns/Opcode
     907: dup
     908: ldc           #138                // String INT_TO_BYTE
     910: bipush        65
     912: invokespecial #8                  // Method "<init>":(Ljava/lang/String;I)V
     915: putstatic     #139                // Field INT_TO_BYTE:Ljadx/api/plugins/input/insns/Opcode;
     918: new           #4                  // class jadx/api/plugins/input/insns/Opcode
     921: dup
     922: ldc           #140                // String INT_TO_CHAR
     924: bipush        66
     926: invokespecial #8                  // Method "<init>":(Ljava/lang/String;I)V
     929: putstatic     #141                // Field INT_TO_CHAR:Ljadx/api/plugins/input/insns/Opcode;
     932: new           #4                  // class jadx/api/plugins/input/insns/Opcode
     935: dup
     936: ldc           #142                // String INT_TO_DOUBLE
     938: bipush        67
     940: invokespecial #8                  // Method "<init>":(Ljava/lang/String;I)V
     943: putstatic     #143                // Field INT_TO_DOUBLE:Ljadx/api/plugins/input/insns/Opcode;
     946: new           #4                  // class jadx/api/plugins/input/insns/Opcode
     949: dup
     950: ldc           #144                // String INT_TO_FLOAT
     952: bipush        68
     954: invokespecial #8                  // Method "<init>":(Ljava/lang/String;I)V
     957: putstatic     #145                // Field INT_TO_FLOAT:Ljadx/api/plugins/input/insns/Opcode;
     960: new           #4                  // class jadx/api/plugins/input/insns/Opcode
     963: dup
     964: ldc           #146                // String INT_TO_LONG
     966: bipush        69
     968: invokespecial #8                  // Method "<init>":(Ljava/lang/String;I)V
     971: putstatic     #147                // Field INT_TO_LONG:Ljadx/api/plugins/input/insns/Opcode;
     974: new           #4                  // class jadx/api/plugins/input/insns/Opcode
     977: dup
     978: ldc           #148                // String INT_TO_SHORT
     980: bipush        70
     982: invokespecial #8                  // Method "<init>":(Ljava/lang/String;I)V
     985: putstatic     #149                // Field INT_TO_SHORT:Ljadx/api/plugins/input/insns/Opcode;
     988: new           #4                  // class jadx/api/plugins/input/insns/Opcode
     991: dup
     992: ldc           #150                // String INVOKE_DIRECT
     994: bipush        71
     996: invokespecial #8                  // Method "<init>":(Ljava/lang/String;I)V
     999: putstatic     #151                // Field INVOKE_DIRECT:Ljadx/api/plugins/input/insns/Opcode;
    1002: new           #4                  // class jadx/api/plugins/input/insns/Opcode
    1005: dup
    1006: ldc           #152                // String INVOKE_DIRECT_RANGE
    1008: bipush        72
    1010: invokespecial #8                  // Method "<init>":(Ljava/lang/String;I)V
    1013: putstatic     #153                // Field INVOKE_DIRECT_RANGE:Ljadx/api/plugins/input/insns/Opcode;
    1016: new           #4                  // class jadx/api/plugins/input/insns/Opcode
    1019: dup
    1020: ldc           #154                // String INVOKE_INTERFACE
    1022: bipush        73
    1024: invokespecial #8                  // Method "<init>":(Ljava/lang/String;I)V
    1027: putstatic     #155                // Field INVOKE_INTERFACE:Ljadx/api/plugins/input/insns/Opcode;
    1030: new           #4                  // class jadx/api/plugins/input/insns/Opcode
    1033: dup
    1034: ldc           #156                // String INVOKE_INTERFACE_RANGE
    1036: bipush        74
    1038: invokespecial #8                  // Method "<init>":(Ljava/lang/String;I)V
    1041: putstatic     #157                // Field INVOKE_INTERFACE_RANGE:Ljadx/api/plugins/input/insns/Opcode;
    1044: new           #4                  // class jadx/api/plugins/input/insns/Opcode
    1047: dup
    1048: ldc           #158                // String INVOKE_STATIC
    1050: bipush        75
    1052: invokespecial #8                  // Method "<init>":(Ljava/lang/String;I)V
    1055: putstatic     #159                // Field INVOKE_STATIC:Ljadx/api/plugins/input/insns/Opcode;
    1058: new           #4                  // class jadx/api/plugins/input/insns/Opcode
    1061: dup
    1062: ldc           #160                // String INVOKE_STATIC_RANGE
    1064: bipush        76
    1066: invokespecial #8                  // Method "<init>":(Ljava/lang/String;I)V
    1069: putstatic     #161                // Field INVOKE_STATIC_RANGE:Ljadx/api/plugins/input/insns/Opcode;
    1072: new           #4                  // class jadx/api/plugins/input/insns/Opcode
    1075: dup
    1076: ldc           #162                // String INVOKE_SUPER
    1078: bipush        77
    1080: invokespecial #8                  // Method "<init>":(Ljava/lang/String;I)V
    1083: putstatic     #163                // Field INVOKE_SUPER:Ljadx/api/plugins/input/insns/Opcode;
    1086: new           #4                  // class jadx/api/plugins/input/insns/Opcode
    1089: dup
    1090: ldc           #164                // String INVOKE_SUPER_RANGE
    1092: bipush        78
    1094: invokespecial #8                  // Method "<init>":(Ljava/lang/String;I)V
    1097: putstatic     #165                // Field INVOKE_SUPER_RANGE:Ljadx/api/plugins/input/insns/Opcode;
    1100: new           #4                  // class jadx/api/plugins/input/insns/Opcode
    1103: dup
    1104: ldc           #166                // String INVOKE_VIRTUAL
    1106: bipush        79
    1108: invokespecial #8                  // Method "<init>":(Ljava/lang/String;I)V
    1111: putstatic     #167                // Field INVOKE_VIRTUAL:Ljadx/api/plugins/input/insns/Opcode;
    1114: new           #4                  // class jadx/api/plugins/input/insns/Opcode
    1117: dup
    1118: ldc           #168                // String INVOKE_VIRTUAL_RANGE
    1120: bipush        80
    1122: invokespecial #8                  // Method "<init>":(Ljava/lang/String;I)V
    1125: putstatic     #169                // Field INVOKE_VIRTUAL_RANGE:Ljadx/api/plugins/input/insns/Opcode;
    1128: new           #4                  // class jadx/api/plugins/input/insns/Opcode
    1131: dup
    1132: ldc           #170                // String INVOKE_SPECIAL
    1134: bipush        81
    1136: invokespecial #8                  // Method "<init>":(Ljava/lang/String;I)V
    1139: putstatic     #171                // Field INVOKE_SPECIAL:Ljadx/api/plugins/input/insns/Opcode;
    1142: new           #4                  // class jadx/api/plugins/input/insns/Opcode
    1145: dup
    1146: ldc           #172                // String IGET
    1148: bipush        82
    1150: invokespecial #8                  // Method "<init>":(Ljava/lang/String;I)V
    1153: putstatic     #173                // Field IGET:Ljadx/api/plugins/input/insns/Opcode;
    1156: new           #4                  // class jadx/api/plugins/input/insns/Opcode
    1159: dup
    1160: ldc           #174                // String IPUT
    1162: bipush        83
    1164: invokespecial #8                  // Method "<init>":(Ljava/lang/String;I)V
    1167: putstatic     #175                // Field IPUT:Ljadx/api/plugins/input/insns/Opcode;
    1170: new           #4                  // class jadx/api/plugins/input/insns/Opcode
    1173: dup
    1174: ldc           #176                // String SGET
    1176: bipush        84
    1178: invokespecial #8                  // Method "<init>":(Ljava/lang/String;I)V
    1181: putstatic     #177                // Field SGET:Ljadx/api/plugins/input/insns/Opcode;
    1184: new           #4                  // class jadx/api/plugins/input/insns/Opcode
    1187: dup
    1188: ldc           #178                // String SPUT
    1190: bipush        85
    1192: invokespecial #8                  // Method "<init>":(Ljava/lang/String;I)V
    1195: putstatic     #179                // Field SPUT:Ljadx/api/plugins/input/insns/Opcode;
    1198: new           #4                  // class jadx/api/plugins/input/insns/Opcode
    1201: dup
    1202: ldc           #180                // String LONG_TO_DOUBLE
    1204: bipush        86
    1206: invokespecial #8                  // Method "<init>":(Ljava/lang/String;I)V
    1209: putstatic     #181                // Field LONG_TO_DOUBLE:Ljadx/api/plugins/input/insns/Opcode;
    1212: new           #4                  // class jadx/api/plugins/input/insns/Opcode
    1215: dup
    1216: ldc           #182                // String LONG_TO_FLOAT
    1218: bipush        87
    1220: invokespecial #8                  // Method "<init>":(Ljava/lang/String;I)V
    1223: putstatic     #183                // Field LONG_TO_FLOAT:Ljadx/api/plugins/input/insns/Opcode;
    1226: new           #4                  // class jadx/api/plugins/input/insns/Opcode
    1229: dup
    1230: ldc           #184                // String LONG_TO_INT
    1232: bipush        88
    1234: invokespecial #8                  // Method "<init>":(Ljava/lang/String;I)V
    1237: putstatic     #185                // Field LONG_TO_INT:Ljadx/api/plugins/input/insns/Opcode;
    1240: new           #4                  // class jadx/api/plugins/input/insns/Opcode
    1243: dup
    1244: ldc           #186                // String MONITOR_ENTER
    1246: bipush        89
    1248: invokespecial #8                  // Method "<init>":(Ljava/lang/String;I)V
    1251: putstatic     #187                // Field MONITOR_ENTER:Ljadx/api/plugins/input/insns/Opcode;
    1254: new           #4                  // class jadx/api/plugins/input/insns/Opcode
    1257: dup
    1258: ldc           #188                // String MONITOR_EXIT
    1260: bipush        90
    1262: invokespecial #8                  // Method "<init>":(Ljava/lang/String;I)V
    1265: putstatic     #189                // Field MONITOR_EXIT:Ljadx/api/plugins/input/insns/Opcode;
    1268: new           #4                  // class jadx/api/plugins/input/insns/Opcode
    1271: dup
    1272: ldc           #190                // String MOVE
    1274: bipush        91
    1276: invokespecial #8                  // Method "<init>":(Ljava/lang/String;I)V
    1279: putstatic     #191                // Field MOVE:Ljadx/api/plugins/input/insns/Opcode;
    1282: new           #4                  // class jadx/api/plugins/input/insns/Opcode
    1285: dup
    1286: ldc           #192                // String MOVE_MULTI
    1288: bipush        92
    1290: invokespecial #8                  // Method "<init>":(Ljava/lang/String;I)V
    1293: putstatic     #193                // Field MOVE_MULTI:Ljadx/api/plugins/input/insns/Opcode;
    1296: new           #4                  // class jadx/api/plugins/input/insns/Opcode
    1299: dup
    1300: ldc           #194                // String MOVE_EXCEPTION
    1302: bipush        93
    1304: invokespecial #8                  // Method "<init>":(Ljava/lang/String;I)V
    1307: putstatic     #195                // Field MOVE_EXCEPTION:Ljadx/api/plugins/input/insns/Opcode;
    1310: new           #4                  // class jadx/api/plugins/input/insns/Opcode
    1313: dup
    1314: ldc           #196                // String MOVE_OBJECT
    1316: bipush        94
    1318: invokespecial #8                  // Method "<init>":(Ljava/lang/String;I)V
    1321: putstatic     #197                // Field MOVE_OBJECT:Ljadx/api/plugins/input/insns/Opcode;
    1324: new           #4                  // class jadx/api/plugins/input/insns/Opcode
    1327: dup
    1328: ldc           #198                // String MOVE_RESULT
    1330: bipush        95
    1332: invokespecial #8                  // Method "<init>":(Ljava/lang/String;I)V
    1335: putstatic     #199                // Field MOVE_RESULT:Ljadx/api/plugins/input/insns/Opcode;
    1338: new           #4                  // class jadx/api/plugins/input/insns/Opcode
    1341: dup
    1342: ldc           #200                // String MOVE_WIDE
    1344: bipush        96
    1346: invokespecial #8                  // Method "<init>":(Ljava/lang/String;I)V
    1349: putstatic     #201                // Field MOVE_WIDE:Ljadx/api/plugins/input/insns/Opcode;
    1352: new           #4                  // class jadx/api/plugins/input/insns/Opcode
    1355: dup
    1356: ldc           #202                // String MUL_DOUBLE
    1358: bipush        97
    1360: invokespecial #8                  // Method "<init>":(Ljava/lang/String;I)V
    1363: putstatic     #203                // Field MUL_DOUBLE:Ljadx/api/plugins/input/insns/Opcode;
    1366: new           #4                  // class jadx/api/plugins/input/insns/Opcode
    1369: dup
    1370: ldc           #204                // String MUL_FLOAT
    1372: bipush        98
    1374: invokespecial #8                  // Method "<init>":(Ljava/lang/String;I)V
    1377: putstatic     #205                // Field MUL_FLOAT:Ljadx/api/plugins/input/insns/Opcode;
    1380: new           #4                  // class jadx/api/plugins/input/insns/Opcode
    1383: dup
    1384: ldc           #206                // String MUL_INT
    1386: bipush        99
    1388: invokespecial #8                  // Method "<init>":(Ljava/lang/String;I)V
    1391: putstatic     #207                // Field MUL_INT:Ljadx/api/plugins/input/insns/Opcode;
    1394: new           #4                  // class jadx/api/plugins/input/insns/Opcode
    1397: dup
    1398: ldc           #208                // String MUL_INT_LIT
    1400: bipush        100
    1402: invokespecial #8                  // Method "<init>":(Ljava/lang/String;I)V
    1405: putstatic     #209                // Field MUL_INT_LIT:Ljadx/api/plugins/input/insns/Opcode;
    1408: new           #4                  // class jadx/api/plugins/input/insns/Opcode
    1411: dup
    1412: ldc           #210                // String MUL_LONG
    1414: bipush        101
    1416: invokespecial #8                  // Method "<init>":(Ljava/lang/String;I)V
    1419: putstatic     #211                // Field MUL_LONG:Ljadx/api/plugins/input/insns/Opcode;
    1422: new           #4                  // class jadx/api/plugins/input/insns/Opcode
    1425: dup
    1426: ldc           #212                // String NEG
    1428: bipush        102
    1430: invokespecial #8                  // Method "<init>":(Ljava/lang/String;I)V
    1433: putstatic     #213                // Field NEG:Ljadx/api/plugins/input/insns/Opcode;
    1436: new           #4                  // class jadx/api/plugins/input/insns/Opcode
    1439: dup
    1440: ldc           #214                // String NEG_DOUBLE
    1442: bipush        103
    1444: invokespecial #8                  // Method "<init>":(Ljava/lang/String;I)V
    1447: putstatic     #215                // Field NEG_DOUBLE:Ljadx/api/plugins/input/insns/Opcode;
    1450: new           #4                  // class jadx/api/plugins/input/insns/Opcode
    1453: dup
    1454: ldc           #216                // String NEG_FLOAT
    1456: bipush        104
    1458: invokespecial #8                  // Method "<init>":(Ljava/lang/String;I)V
    1461: putstatic     #217                // Field NEG_FLOAT:Ljadx/api/plugins/input/insns/Opcode;
    1464: new           #4                  // class jadx/api/plugins/input/insns/Opcode
    1467: dup
    1468: ldc           #218                // String NEG_INT
    1470: bipush        105
    1472: invokespecial #8                  // Method "<init>":(Ljava/lang/String;I)V
    1475: putstatic     #219                // Field NEG_INT:Ljadx/api/plugins/input/insns/Opcode;
    1478: new           #4                  // class jadx/api/plugins/input/insns/Opcode
    1481: dup
    1482: ldc           #220                // String NEG_LONG
    1484: bipush        106
    1486: invokespecial #8                  // Method "<init>":(Ljava/lang/String;I)V
    1489: putstatic     #221                // Field NEG_LONG:Ljadx/api/plugins/input/insns/Opcode;
    1492: new           #4                  // class jadx/api/plugins/input/insns/Opcode
    1495: dup
    1496: ldc           #222                // String NEW_INSTANCE
    1498: bipush        107
    1500: invokespecial #8                  // Method "<init>":(Ljava/lang/String;I)V
    1503: putstatic     #223                // Field NEW_INSTANCE:Ljadx/api/plugins/input/insns/Opcode;
    1506: new           #4                  // class jadx/api/plugins/input/insns/Opcode
    1509: dup
    1510: ldc           #224                // String NOT_INT
    1512: bipush        108
    1514: invokespecial #8                  // Method "<init>":(Ljava/lang/String;I)V
    1517: putstatic     #225                // Field NOT_INT:Ljadx/api/plugins/input/insns/Opcode;
    1520: new           #4                  // class jadx/api/plugins/input/insns/Opcode
    1523: dup
    1524: ldc           #226                // String NOT_LONG
    1526: bipush        109
    1528: invokespecial #8                  // Method "<init>":(Ljava/lang/String;I)V
    1531: putstatic     #227                // Field NOT_LONG:Ljadx/api/plugins/input/insns/Opcode;
    1534: new           #4                  // class jadx/api/plugins/input/insns/Opcode
    1537: dup
    1538: ldc           #228                // String OR_INT
    1540: bipush        110
    1542: invokespecial #8                  // Method "<init>":(Ljava/lang/String;I)V
    1545: putstatic     #229                // Field OR_INT:Ljadx/api/plugins/input/insns/Opcode;
    1548: new           #4                  // class jadx/api/plugins/input/insns/Opcode
    1551: dup
    1552: ldc           #230                // String OR_INT_LIT
    1554: bipush        111
    1556: invokespecial #8                  // Method "<init>":(Ljava/lang/String;I)V
    1559: putstatic     #231                // Field OR_INT_LIT:Ljadx/api/plugins/input/insns/Opcode;
    1562: new           #4                  // class jadx/api/plugins/input/insns/Opcode
    1565: dup
    1566: ldc           #232                // String OR_LONG
    1568: bipush        112
    1570: invokespecial #8                  // Method "<init>":(Ljava/lang/String;I)V
    1573: putstatic     #233                // Field OR_LONG:Ljadx/api/plugins/input/insns/Opcode;
    1576: new           #4                  // class jadx/api/plugins/input/insns/Opcode
    1579: dup
    1580: ldc           #234                // String REM_DOUBLE
    1582: bipush        113
    1584: invokespecial #8                  // Method "<init>":(Ljava/lang/String;I)V
    1587: putstatic     #235                // Field REM_DOUBLE:Ljadx/api/plugins/input/insns/Opcode;
    1590: new           #4                  // class jadx/api/plugins/input/insns/Opcode
    1593: dup
    1594: ldc           #236                // String REM_FLOAT
    1596: bipush        114
    1598: invokespecial #8                  // Method "<init>":(Ljava/lang/String;I)V
    1601: putstatic     #237                // Field REM_FLOAT:Ljadx/api/plugins/input/insns/Opcode;
    1604: new           #4                  // class jadx/api/plugins/input/insns/Opcode
    1607: dup
    1608: ldc           #238                // String REM_INT
    1610: bipush        115
    1612: invokespecial #8                  // Method "<init>":(Ljava/lang/String;I)V
    1615: putstatic     #239                // Field REM_INT:Ljadx/api/plugins/input/insns/Opcode;
    1618: new           #4                  // class jadx/api/plugins/input/insns/Opcode
    1621: dup
    1622: ldc           #240                // String REM_INT_LIT
    1624: bipush        116
    1626: invokespecial #8                  // Method "<init>":(Ljava/lang/String;I)V
    1629: putstatic     #241                // Field REM_INT_LIT:Ljadx/api/plugins/input/insns/Opcode;
    1632: new           #4                  // class jadx/api/plugins/input/insns/Opcode
    1635: dup
    1636: ldc           #242                // String REM_LONG
    1638: bipush        117
    1640: invokespecial #8                  // Method "<init>":(Ljava/lang/String;I)V
    1643: putstatic     #243                // Field REM_LONG:Ljadx/api/plugins/input/insns/Opcode;
    1646: new           #4                  // class jadx/api/plugins/input/insns/Opcode
    1649: dup
    1650: ldc           #244                // String RETURN
    1652: bipush        118
    1654: invokespecial #8                  // Method "<init>":(Ljava/lang/String;I)V
    1657: putstatic     #245                // Field RETURN:Ljadx/api/plugins/input/insns/Opcode;
    1660: new           #4                  // class jadx/api/plugins/input/insns/Opcode
    1663: dup
    1664: ldc           #246                // String RETURN_VOID
    1666: bipush        119
    1668: invokespecial #8                  // Method "<init>":(Ljava/lang/String;I)V
    1671: putstatic     #247                // Field RETURN_VOID:Ljadx/api/plugins/input/insns/Opcode;
    1674: new           #4                  // class jadx/api/plugins/input/insns/Opcode
    1677: dup
    1678: ldc           #248                // String RSUB_INT
    1680: bipush        120
    1682: invokespecial #8                  // Method "<init>":(Ljava/lang/String;I)V
    1685: putstatic     #249                // Field RSUB_INT:Ljadx/api/plugins/input/insns/Opcode;
    1688: new           #4                  // class jadx/api/plugins/input/insns/Opcode
    1691: dup
    1692: ldc           #250                // String SHL_INT
    1694: bipush        121
    1696: invokespecial #8                  // Method "<init>":(Ljava/lang/String;I)V
    1699: putstatic     #251                // Field SHL_INT:Ljadx/api/plugins/input/insns/Opcode;
    1702: new           #4                  // class jadx/api/plugins/input/insns/Opcode
    1705: dup
    1706: ldc           #252                // String SHL_INT_LIT
    1708: bipush        122
    1710: invokespecial #8                  // Method "<init>":(Ljava/lang/String;I)V
    1713: putstatic     #253                // Field SHL_INT_LIT:Ljadx/api/plugins/input/insns/Opcode;
    1716: new           #4                  // class jadx/api/plugins/input/insns/Opcode
    1719: dup
    1720: ldc           #254                // String SHL_LONG
    1722: bipush        123
    1724: invokespecial #8                  // Method "<init>":(Ljava/lang/String;I)V
    1727: putstatic     #255                // Field SHL_LONG:Ljadx/api/plugins/input/insns/Opcode;
    1730: new           #4                  // class jadx/api/plugins/input/insns/Opcode
    1733: dup
    1734: ldc_w         #256                // String SHR_INT
    1737: bipush        124
    1739: invokespecial #8                  // Method "<init>":(Ljava/lang/String;I)V
    1742: putstatic     #257                // Field SHR_INT:Ljadx/api/plugins/input/insns/Opcode;
    1745: new           #4                  // class jadx/api/plugins/input/insns/Opcode
    1748: dup
    1749: ldc_w         #258                // String SHR_INT_LIT
    1752: bipush        125
    1754: invokespecial #8                  // Method "<init>":(Ljava/lang/String;I)V
    1757: putstatic     #259                // Field SHR_INT_LIT:Ljadx/api/plugins/input/insns/Opcode;
    1760: new           #4                  // class jadx/api/plugins/input/insns/Opcode
    1763: dup
    1764: ldc_w         #260                // String SHR_LONG
    1767: bipush        126
    1769: invokespecial #8                  // Method "<init>":(Ljava/lang/String;I)V
    1772: putstatic     #261                // Field SHR_LONG:Ljadx/api/plugins/input/insns/Opcode;
    1775: new           #4                  // class jadx/api/plugins/input/insns/Opcode
    1778: dup
    1779: ldc_w         #262                // String SUB_DOUBLE
    1782: bipush        127
    1784: invokespecial #8                  // Method "<init>":(Ljava/lang/String;I)V
    1787: putstatic     #263                // Field SUB_DOUBLE:Ljadx/api/plugins/input/insns/Opcode;
    1790: new           #4                  // class jadx/api/plugins/input/insns/Opcode
    1793: dup
    1794: ldc_w         #264                // String SUB_FLOAT
    1797: sipush        128
    1800: invokespecial #8                  // Method "<init>":(Ljava/lang/String;I)V
    1803: putstatic     #265                // Field SUB_FLOAT:Ljadx/api/plugins/input/insns/Opcode;
    1806: new           #4                  // class jadx/api/plugins/input/insns/Opcode
    1809: dup
    1810: ldc_w         #266                // String SUB_INT
    1813: sipush        129
    1816: invokespecial #8                  // Method "<init>":(Ljava/lang/String;I)V
    1819: putstatic     #267                // Field SUB_INT:Ljadx/api/plugins/input/insns/Opcode;
    1822: new           #4                  // class jadx/api/plugins/input/insns/Opcode
    1825: dup
    1826: ldc_w         #268                // String SUB_LONG
    1829: sipush        130
    1832: invokespecial #8                  // Method "<init>":(Ljava/lang/String;I)V
    1835: putstatic     #269                // Field SUB_LONG:Ljadx/api/plugins/input/insns/Opcode;
    1838: new           #4                  // class jadx/api/plugins/input/insns/Opcode
    1841: dup
    1842: ldc_w         #270                // String THROW
    1845: sipush        131
    1848: invokespecial #8                  // Method "<init>":(Ljava/lang/String;I)V
    1851: putstatic     #271                // Field THROW:Ljadx/api/plugins/input/insns/Opcode;
    1854: new           #4                  // class jadx/api/plugins/input/insns/Opcode
    1857: dup
    1858: ldc_w         #272                // String USHR_INT
    1861: sipush        132
    1864: invokespecial #8                  // Method "<init>":(Ljava/lang/String;I)V
    1867: putstatic     #273                // Field USHR_INT:Ljadx/api/plugins/input/insns/Opcode;
    1870: new           #4                  // class jadx/api/plugins/input/insns/Opcode
    1873: dup
    1874: ldc_w         #274                // String USHR_INT_LIT
    1877: sipush        133
    1880: invokespecial #8                  // Method "<init>":(Ljava/lang/String;I)V
    1883: putstatic     #275                // Field USHR_INT_LIT:Ljadx/api/plugins/input/insns/Opcode;
    1886: new           #4                  // class jadx/api/plugins/input/insns/Opcode
    1889: dup
    1890: ldc_w         #276                // String USHR_LONG
    1893: sipush        134
    1896: invokespecial #8                  // Method "<init>":(Ljava/lang/String;I)V
    1899: putstatic     #277                // Field USHR_LONG:Ljadx/api/plugins/input/insns/Opcode;
    1902: new           #4                  // class jadx/api/plugins/input/insns/Opcode
    1905: dup
    1906: ldc_w         #278                // String XOR_INT
    1909: sipush        135
    1912: invokespecial #8                  // Method "<init>":(Ljava/lang/String;I)V
    1915: putstatic     #279                // Field XOR_INT:Ljadx/api/plugins/input/insns/Opcode;
    1918: new           #4                  // class jadx/api/plugins/input/insns/Opcode
    1921: dup
    1922: ldc_w         #280                // String XOR_INT_LIT
    1925: sipush        136
    1928: invokespecial #8                  // Method "<init>":(Ljava/lang/String;I)V
    1931: putstatic     #281                // Field XOR_INT_LIT:Ljadx/api/plugins/input/insns/Opcode;
    1934: new           #4                  // class jadx/api/plugins/input/insns/Opcode
    1937: dup
    1938: ldc_w         #282                // String XOR_LONG
    1941: sipush        137
    1944: invokespecial #8                  // Method "<init>":(Ljava/lang/String;I)V
    1947: putstatic     #283                // Field XOR_LONG:Ljadx/api/plugins/input/insns/Opcode;
    1950: new           #4                  // class jadx/api/plugins/input/insns/Opcode
    1953: dup
    1954: ldc_w         #284                // String NEW_ARRAY
    1957: sipush        138
    1960: invokespecial #8                  // Method "<init>":(Ljava/lang/String;I)V
    1963: putstatic     #285                // Field NEW_ARRAY:Ljadx/api/plugins/input/insns/Opcode;
    1966: new           #4                  // class jadx/api/plugins/input/insns/Opcode
    1969: dup
    1970: ldc_w         #286                // String FILLED_NEW_ARRAY
    1973: sipush        139
    1976: invokespecial #8                  // Method "<init>":(Ljava/lang/String;I)V
    1979: putstatic     #287                // Field FILLED_NEW_ARRAY:Ljadx/api/plugins/input/insns/Opcode;
    1982: new           #4                  // class jadx/api/plugins/input/insns/Opcode
    1985: dup
    1986: ldc_w         #288                // String FILLED_NEW_ARRAY_RANGE
    1989: sipush        140
    1992: invokespecial #8                  // Method "<init>":(Ljava/lang/String;I)V
    1995: putstatic     #289                // Field FILLED_NEW_ARRAY_RANGE:Ljadx/api/plugins/input/insns/Opcode;
    1998: new           #4                  // class jadx/api/plugins/input/insns/Opcode
    2001: dup
    2002: ldc_w         #290                // String FILL_ARRAY_DATA
    2005: sipush        141
    2008: invokespecial #8                  // Method "<init>":(Ljava/lang/String;I)V
    2011: putstatic     #291                // Field FILL_ARRAY_DATA:Ljadx/api/plugins/input/insns/Opcode;
    2014: new           #4                  // class jadx/api/plugins/input/insns/Opcode
    2017: dup
    2018: ldc_w         #292                // String FILL_ARRAY_DATA_PAYLOAD
    2021: sipush        142
    2024: invokespecial #8                  // Method "<init>":(Ljava/lang/String;I)V
    2027: putstatic     #293                // Field FILL_ARRAY_DATA_PAYLOAD:Ljadx/api/plugins/input/insns/Opcode;
    2030: new           #4                  // class jadx/api/plugins/input/insns/Opcode
    2033: dup
    2034: ldc_w         #294                // String PACKED_SWITCH
    2037: sipush        143
    2040: invokespecial #8                  // Method "<init>":(Ljava/lang/String;I)V
    2043: putstatic     #295                // Field PACKED_SWITCH:Ljadx/api/plugins/input/insns/Opcode;
    2046: new           #4                  // class jadx/api/plugins/input/insns/Opcode
    2049: dup
    2050: ldc_w         #296                // String PACKED_SWITCH_PAYLOAD
    2053: sipush        144
    2056: invokespecial #8                  // Method "<init>":(Ljava/lang/String;I)V
    2059: putstatic     #297                // Field PACKED_SWITCH_PAYLOAD:Ljadx/api/plugins/input/insns/Opcode;
    2062: new           #4                  // class jadx/api/plugins/input/insns/Opcode
    2065: dup
    2066: ldc_w         #298                // String SPARSE_SWITCH
    2069: sipush        145
    2072: invokespecial #8                  // Method "<init>":(Ljava/lang/String;I)V
    2075: putstatic     #299                // Field SPARSE_SWITCH:Ljadx/api/plugins/input/insns/Opcode;
    2078: new           #4                  // class jadx/api/plugins/input/insns/Opcode
    2081: dup
    2082: ldc_w         #300                // String SPARSE_SWITCH_PAYLOAD
    2085: sipush        146
    2088: invokespecial #8                  // Method "<init>":(Ljava/lang/String;I)V
    2091: putstatic     #301                // Field SPARSE_SWITCH_PAYLOAD:Ljadx/api/plugins/input/insns/Opcode;
    2094: new           #4                  // class jadx/api/plugins/input/insns/Opcode
    2097: dup
    2098: ldc_w         #302                // String INVOKE_POLYMORPHIC
    2101: sipush        147
    2104: invokespecial #8                  // Method "<init>":(Ljava/lang/String;I)V
    2107: putstatic     #303                // Field INVOKE_POLYMORPHIC:Ljadx/api/plugins/input/insns/Opcode;
    2110: new           #4                  // class jadx/api/plugins/input/insns/Opcode
    2113: dup
    2114: ldc_w         #304                // String INVOKE_POLYMORPHIC_RANGE
    2117: sipush        148
    2120: invokespecial #8                  // Method "<init>":(Ljava/lang/String;I)V
    2123: putstatic     #305                // Field INVOKE_POLYMORPHIC_RANGE:Ljadx/api/plugins/input/insns/Opcode;
    2126: new           #4                  // class jadx/api/plugins/input/insns/Opcode
    2129: dup
    2130: ldc_w         #306                // String INVOKE_CUSTOM
    2133: sipush        149
    2136: invokespecial #8                  // Method "<init>":(Ljava/lang/String;I)V
    2139: putstatic     #307                // Field INVOKE_CUSTOM:Ljadx/api/plugins/input/insns/Opcode;
    2142: new           #4                  // class jadx/api/plugins/input/insns/Opcode
    2145: dup
    2146: ldc_w         #308                // String INVOKE_CUSTOM_RANGE
    2149: sipush        150
    2152: invokespecial #8                  // Method "<init>":(Ljava/lang/String;I)V
    2155: putstatic     #309                // Field INVOKE_CUSTOM_RANGE:Ljadx/api/plugins/input/insns/Opcode;
    2158: new           #4                  // class jadx/api/plugins/input/insns/Opcode
    2161: dup
    2162: ldc_w         #310                // String CONST_METHOD_HANDLE
    2165: sipush        151
    2168: invokespecial #8                  // Method "<init>":(Ljava/lang/String;I)V
    2171: putstatic     #311                // Field CONST_METHOD_HANDLE:Ljadx/api/plugins/input/insns/Opcode;
    2174: new           #4                  // class jadx/api/plugins/input/insns/Opcode
    2177: dup
    2178: ldc_w         #312                // String CONST_METHOD_TYPE
    2181: sipush        152
    2184: invokespecial #8                  // Method "<init>":(Ljava/lang/String;I)V
    2187: putstatic     #313                // Field CONST_METHOD_TYPE:Ljadx/api/plugins/input/insns/Opcode;
    2190: sipush        153
    2193: anewarray     #4                  // class jadx/api/plugins/input/insns/Opcode
    2196: dup
    2197: iconst_0
    2198: getstatic     #9                  // Field UNKNOWN:Ljadx/api/plugins/input/insns/Opcode;
    2201: aastore
    2202: dup
    2203: iconst_1
    2204: getstatic     #11                 // Field NOP:Ljadx/api/plugins/input/insns/Opcode;
    2207: aastore
    2208: dup
    2209: iconst_2
    2210: getstatic     #13                 // Field ADD_DOUBLE:Ljadx/api/plugins/input/insns/Opcode;
    2213: aastore
    2214: dup
    2215: iconst_3
    2216: getstatic     #15                 // Field ADD_FLOAT:Ljadx/api/plugins/input/insns/Opcode;
    2219: aastore
    2220: dup
    2221: iconst_4
    2222: getstatic     #17                 // Field ADD_INT:Ljadx/api/plugins/input/insns/Opcode;
    2225: aastore
    2226: dup
    2227: iconst_5
    2228: getstatic     #19                 // Field ADD_INT_LIT:Ljadx/api/plugins/input/insns/Opcode;
    2231: aastore
    2232: dup
    2233: bipush        6
    2235: getstatic     #21                 // Field ADD_LONG:Ljadx/api/plugins/input/insns/Opcode;
    2238: aastore
    2239: dup
    2240: bipush        7
    2242: getstatic     #23                 // Field AND_INT:Ljadx/api/plugins/input/insns/Opcode;
    2245: aastore
    2246: dup
    2247: bipush        8
    2249: getstatic     #25                 // Field AND_INT_LIT:Ljadx/api/plugins/input/insns/Opcode;
    2252: aastore
    2253: dup
    2254: bipush        9
    2256: getstatic     #27                 // Field AND_LONG:Ljadx/api/plugins/input/insns/Opcode;
    2259: aastore
    2260: dup
    2261: bipush        10
    2263: getstatic     #29                 // Field AGET:Ljadx/api/plugins/input/insns/Opcode;
    2266: aastore
    2267: dup
    2268: bipush        11
    2270: getstatic     #31                 // Field AGET_BOOLEAN:Ljadx/api/plugins/input/insns/Opcode;
    2273: aastore
    2274: dup
    2275: bipush        12
    2277: getstatic     #33                 // Field AGET_BYTE:Ljadx/api/plugins/input/insns/Opcode;
    2280: aastore
    2281: dup
    2282: bipush        13
    2284: getstatic     #35                 // Field AGET_BYTE_BOOLEAN:Ljadx/api/plugins/input/insns/Opcode;
    2287: aastore
    2288: dup
    2289: bipush        14
    2291: getstatic     #37                 // Field AGET_CHAR:Ljadx/api/plugins/input/insns/Opcode;
    2294: aastore
    2295: dup
    2296: bipush        15
    2298: getstatic     #39                 // Field AGET_OBJECT:Ljadx/api/plugins/input/insns/Opcode;
    2301: aastore
    2302: dup
    2303: bipush        16
    2305: getstatic     #41                 // Field AGET_SHORT:Ljadx/api/plugins/input/insns/Opcode;
    2308: aastore
    2309: dup
    2310: bipush        17
    2312: getstatic     #43                 // Field AGET_WIDE:Ljadx/api/plugins/input/insns/Opcode;
    2315: aastore
    2316: dup
    2317: bipush        18
    2319: getstatic     #45                 // Field APUT:Ljadx/api/plugins/input/insns/Opcode;
    2322: aastore
    2323: dup
    2324: bipush        19
    2326: getstatic     #47                 // Field APUT_BOOLEAN:Ljadx/api/plugins/input/insns/Opcode;
    2329: aastore
    2330: dup
    2331: bipush        20
    2333: getstatic     #49                 // Field APUT_BYTE:Ljadx/api/plugins/input/insns/Opcode;
    2336: aastore
    2337: dup
    2338: bipush        21
    2340: getstatic     #51                 // Field APUT_BYTE_BOOLEAN:Ljadx/api/plugins/input/insns/Opcode;
    2343: aastore
    2344: dup
    2345: bipush        22
    2347: getstatic     #53                 // Field APUT_CHAR:Ljadx/api/plugins/input/insns/Opcode;
    2350: aastore
    2351: dup
    2352: bipush        23
    2354: getstatic     #55                 // Field APUT_OBJECT:Ljadx/api/plugins/input/insns/Opcode;
    2357: aastore
    2358: dup
    2359: bipush        24
    2361: getstatic     #57                 // Field APUT_SHORT:Ljadx/api/plugins/input/insns/Opcode;
    2364: aastore
    2365: dup
    2366: bipush        25
    2368: getstatic     #59                 // Field APUT_WIDE:Ljadx/api/plugins/input/insns/Opcode;
    2371: aastore
    2372: dup
    2373: bipush        26
    2375: getstatic     #61                 // Field ARITH:Ljadx/api/plugins/input/insns/Opcode;
    2378: aastore
    2379: dup
    2380: bipush        27
    2382: getstatic     #63                 // Field ARRAY_LENGTH:Ljadx/api/plugins/input/insns/Opcode;
    2385: aastore
    2386: dup
    2387: bipush        28
    2389: getstatic     #65                 // Field CAST:Ljadx/api/plugins/input/insns/Opcode;
    2392: aastore
    2393: dup
    2394: bipush        29
    2396: getstatic     #67                 // Field CHECK_CAST:Ljadx/api/plugins/input/insns/Opcode;
    2399: aastore
    2400: dup
    2401: bipush        30
    2403: getstatic     #69                 // Field CMPG_DOUBLE:Ljadx/api/plugins/input/insns/Opcode;
    2406: aastore
    2407: dup
    2408: bipush        31
    2410: getstatic     #71                 // Field CMPG_FLOAT:Ljadx/api/plugins/input/insns/Opcode;
    2413: aastore
    2414: dup
    2415: bipush        32
    2417: getstatic     #73                 // Field CMPL_DOUBLE:Ljadx/api/plugins/input/insns/Opcode;
    2420: aastore
    2421: dup
    2422: bipush        33
    2424: getstatic     #75                 // Field CMPL_FLOAT:Ljadx/api/plugins/input/insns/Opcode;
    2427: aastore
    2428: dup
    2429: bipush        34
    2431: getstatic     #77                 // Field CMP_LONG:Ljadx/api/plugins/input/insns/Opcode;
    2434: aastore
    2435: dup
    2436: bipush        35
    2438: getstatic     #79                 // Field CONST:Ljadx/api/plugins/input/insns/Opcode;
    2441: aastore
    2442: dup
    2443: bipush        36
    2445: getstatic     #81                 // Field CONST_CLASS:Ljadx/api/plugins/input/insns/Opcode;
    2448: aastore
    2449: dup
    2450: bipush        37
    2452: getstatic     #83                 // Field CONST_STRING:Ljadx/api/plugins/input/insns/Opcode;
    2455: aastore
    2456: dup
    2457: bipush        38
    2459: getstatic     #85                 // Field CONST_WIDE:Ljadx/api/plugins/input/insns/Opcode;
    2462: aastore
    2463: dup
    2464: bipush        39
    2466: getstatic     #87                 // Field DIV_DOUBLE:Ljadx/api/plugins/input/insns/Opcode;
    2469: aastore
    2470: dup
    2471: bipush        40
    2473: getstatic     #89                 // Field DIV_FLOAT:Ljadx/api/plugins/input/insns/Opcode;
    2476: aastore
    2477: dup
    2478: bipush        41
    2480: getstatic     #91                 // Field DIV_INT:Ljadx/api/plugins/input/insns/Opcode;
    2483: aastore
    2484: dup
    2485: bipush        42
    2487: getstatic     #93                 // Field DIV_INT_LIT:Ljadx/api/plugins/input/insns/Opcode;
    2490: aastore
    2491: dup
    2492: bipush        43
    2494: getstatic     #95                 // Field DIV_LONG:Ljadx/api/plugins/input/insns/Opcode;
    2497: aastore
    2498: dup
    2499: bipush        44
    2501: getstatic     #97                 // Field DOUBLE_TO_FLOAT:Ljadx/api/plugins/input/insns/Opcode;
    2504: aastore
    2505: dup
    2506: bipush        45
    2508: getstatic     #99                 // Field DOUBLE_TO_INT:Ljadx/api/plugins/input/insns/Opcode;
    2511: aastore
    2512: dup
    2513: bipush        46
    2515: getstatic     #101                // Field DOUBLE_TO_LONG:Ljadx/api/plugins/input/insns/Opcode;
    2518: aastore
    2519: dup
    2520: bipush        47
    2522: getstatic     #103                // Field FLOAT_TO_DOUBLE:Ljadx/api/plugins/input/insns/Opcode;
    2525: aastore
    2526: dup
    2527: bipush        48
    2529: getstatic     #105                // Field FLOAT_TO_INT:Ljadx/api/plugins/input/insns/Opcode;
    2532: aastore
    2533: dup
    2534: bipush        49
    2536: getstatic     #107                // Field FLOAT_TO_LONG:Ljadx/api/plugins/input/insns/Opcode;
    2539: aastore
    2540: dup
    2541: bipush        50
    2543: getstatic     #109                // Field GOTO:Ljadx/api/plugins/input/insns/Opcode;
    2546: aastore
    2547: dup
    2548: bipush        51
    2550: getstatic     #111                // Field IF:Ljadx/api/plugins/input/insns/Opcode;
    2553: aastore
    2554: dup
    2555: bipush        52
    2557: getstatic     #113                // Field IF_EQ:Ljadx/api/plugins/input/insns/Opcode;
    2560: aastore
    2561: dup
    2562: bipush        53
    2564: getstatic     #115                // Field IF_EQZ:Ljadx/api/plugins/input/insns/Opcode;
    2567: aastore
    2568: dup
    2569: bipush        54
    2571: getstatic     #117                // Field IF_GE:Ljadx/api/plugins/input/insns/Opcode;
    2574: aastore
    2575: dup
    2576: bipush        55
    2578: getstatic     #119                // Field IF_GEZ:Ljadx/api/plugins/input/insns/Opcode;
    2581: aastore
    2582: dup
    2583: bipush        56
    2585: getstatic     #121                // Field IF_GT:Ljadx/api/plugins/input/insns/Opcode;
    2588: aastore
    2589: dup
    2590: bipush        57
    2592: getstatic     #123                // Field IF_GTZ:Ljadx/api/plugins/input/insns/Opcode;
    2595: aastore
    2596: dup
    2597: bipush        58
    2599: getstatic     #125                // Field IF_LE:Ljadx/api/plugins/input/insns/Opcode;
    2602: aastore
    2603: dup
    2604: bipush        59
    2606: getstatic     #127                // Field IF_LEZ:Ljadx/api/plugins/input/insns/Opcode;
    2609: aastore
    2610: dup
    2611: bipush        60
    2613: getstatic     #129                // Field IF_LT:Ljadx/api/plugins/input/insns/Opcode;
    2616: aastore
    2617: dup
    2618: bipush        61
    2620: getstatic     #131                // Field IF_LTZ:Ljadx/api/plugins/input/insns/Opcode;
    2623: aastore
    2624: dup
    2625: bipush        62
    2627: getstatic     #133                // Field IF_NE:Ljadx/api/plugins/input/insns/Opcode;
    2630: aastore
    2631: dup
    2632: bipush        63
    2634: getstatic     #135                // Field IF_NEZ:Ljadx/api/plugins/input/insns/Opcode;
    2637: aastore
    2638: dup
    2639: bipush        64
    2641: getstatic     #137                // Field INSTANCE_OF:Ljadx/api/plugins/input/insns/Opcode;
    2644: aastore
    2645: dup
    2646: bipush        65
    2648: getstatic     #139                // Field INT_TO_BYTE:Ljadx/api/plugins/input/insns/Opcode;
    2651: aastore
    2652: dup
    2653: bipush        66
    2655: getstatic     #141                // Field INT_TO_CHAR:Ljadx/api/plugins/input/insns/Opcode;
    2658: aastore
    2659: dup
    2660: bipush        67
    2662: getstatic     #143                // Field INT_TO_DOUBLE:Ljadx/api/plugins/input/insns/Opcode;
    2665: aastore
    2666: dup
    2667: bipush        68
    2669: getstatic     #145                // Field INT_TO_FLOAT:Ljadx/api/plugins/input/insns/Opcode;
    2672: aastore
    2673: dup
    2674: bipush        69
    2676: getstatic     #147                // Field INT_TO_LONG:Ljadx/api/plugins/input/insns/Opcode;
    2679: aastore
    2680: dup
    2681: bipush        70
    2683: getstatic     #149                // Field INT_TO_SHORT:Ljadx/api/plugins/input/insns/Opcode;
    2686: aastore
    2687: dup
    2688: bipush        71
    2690: getstatic     #151                // Field INVOKE_DIRECT:Ljadx/api/plugins/input/insns/Opcode;
    2693: aastore
    2694: dup
    2695: bipush        72
    2697: getstatic     #153                // Field INVOKE_DIRECT_RANGE:Ljadx/api/plugins/input/insns/Opcode;
    2700: aastore
    2701: dup
    2702: bipush        73
    2704: getstatic     #155                // Field INVOKE_INTERFACE:Ljadx/api/plugins/input/insns/Opcode;
    2707: aastore
    2708: dup
    2709: bipush        74
    2711: getstatic     #157                // Field INVOKE_INTERFACE_RANGE:Ljadx/api/plugins/input/insns/Opcode;
    2714: aastore
    2715: dup
    2716: bipush        75
    2718: getstatic     #159                // Field INVOKE_STATIC:Ljadx/api/plugins/input/insns/Opcode;
    2721: aastore
    2722: dup
    2723: bipush        76
    2725: getstatic     #161                // Field INVOKE_STATIC_RANGE:Ljadx/api/plugins/input/insns/Opcode;
    2728: aastore
    2729: dup
    2730: bipush        77
    2732: getstatic     #163                // Field INVOKE_SUPER:Ljadx/api/plugins/input/insns/Opcode;
    2735: aastore
    2736: dup
    2737: bipush        78
    2739: getstatic     #165                // Field INVOKE_SUPER_RANGE:Ljadx/api/plugins/input/insns/Opcode;
    2742: aastore
    2743: dup
    2744: bipush        79
    2746: getstatic     #167                // Field INVOKE_VIRTUAL:Ljadx/api/plugins/input/insns/Opcode;
    2749: aastore
    2750: dup
    2751: bipush        80
    2753: getstatic     #169                // Field INVOKE_VIRTUAL_RANGE:Ljadx/api/plugins/input/insns/Opcode;
    2756: aastore
    2757: dup
    2758: bipush        81
    2760: getstatic     #171                // Field INVOKE_SPECIAL:Ljadx/api/plugins/input/insns/Opcode;
    2763: aastore
    2764: dup
    2765: bipush        82
    2767: getstatic     #173                // Field IGET:Ljadx/api/plugins/input/insns/Opcode;
    2770: aastore
    2771: dup
    2772: bipush        83
    2774: getstatic     #175                // Field IPUT:Ljadx/api/plugins/input/insns/Opcode;
    2777: aastore
    2778: dup
    2779: bipush        84
    2781: getstatic     #177                // Field SGET:Ljadx/api/plugins/input/insns/Opcode;
    2784: aastore
    2785: dup
    2786: bipush        85
    2788: getstatic     #179                // Field SPUT:Ljadx/api/plugins/input/insns/Opcode;
    2791: aastore
    2792: dup
    2793: bipush        86
    2795: getstatic     #181                // Field LONG_TO_DOUBLE:Ljadx/api/plugins/input/insns/Opcode;
    2798: aastore
    2799: dup
    2800: bipush        87
    2802: getstatic     #183                // Field LONG_TO_FLOAT:Ljadx/api/plugins/input/insns/Opcode;
    2805: aastore
    2806: dup
    2807: bipush        88
    2809: getstatic     #185                // Field LONG_TO_INT:Ljadx/api/plugins/input/insns/Opcode;
    2812: aastore
    2813: dup
    2814: bipush        89
    2816: getstatic     #187                // Field MONITOR_ENTER:Ljadx/api/plugins/input/insns/Opcode;
    2819: aastore
    2820: dup
    2821: bipush        90
    2823: getstatic     #189                // Field MONITOR_EXIT:Ljadx/api/plugins/input/insns/Opcode;
    2826: aastore
    2827: dup
    2828: bipush        91
    2830: getstatic     #191                // Field MOVE:Ljadx/api/plugins/input/insns/Opcode;
    2833: aastore
    2834: dup
    2835: bipush        92
    2837: getstatic     #193                // Field MOVE_MULTI:Ljadx/api/plugins/input/insns/Opcode;
    2840: aastore
    2841: dup
    2842: bipush        93
    2844: getstatic     #195                // Field MOVE_EXCEPTION:Ljadx/api/plugins/input/insns/Opcode;
    2847: aastore
    2848: dup
    2849: bipush        94
    2851: getstatic     #197                // Field MOVE_OBJECT:Ljadx/api/plugins/input/insns/Opcode;
    2854: aastore
    2855: dup
    2856: bipush        95
    2858: getstatic     #199                // Field MOVE_RESULT:Ljadx/api/plugins/input/insns/Opcode;
    2861: aastore
    2862: dup
    2863: bipush        96
    2865: getstatic     #201                // Field MOVE_WIDE:Ljadx/api/plugins/input/insns/Opcode;
    2868: aastore
    2869: dup
    2870: bipush        97
    2872: getstatic     #203                // Field MUL_DOUBLE:Ljadx/api/plugins/input/insns/Opcode;
    2875: aastore
    2876: dup
    2877: bipush        98
    2879: getstatic     #205                // Field MUL_FLOAT:Ljadx/api/plugins/input/insns/Opcode;
    2882: aastore
    2883: dup
    2884: bipush        99
    2886: getstatic     #207                // Field MUL_INT:Ljadx/api/plugins/input/insns/Opcode;
    2889: aastore
    2890: dup
    2891: bipush        100
    2893: getstatic     #209                // Field MUL_INT_LIT:Ljadx/api/plugins/input/insns/Opcode;
    2896: aastore
    2897: dup
    2898: bipush        101
    2900: getstatic     #211                // Field MUL_LONG:Ljadx/api/plugins/input/insns/Opcode;
    2903: aastore
    2904: dup
    2905: bipush        102
    2907: getstatic     #213                // Field NEG:Ljadx/api/plugins/input/insns/Opcode;
    2910: aastore
    2911: dup
    2912: bipush        103
    2914: getstatic     #215                // Field NEG_DOUBLE:Ljadx/api/plugins/input/insns/Opcode;
    2917: aastore
    2918: dup
    2919: bipush        104
    2921: getstatic     #217                // Field NEG_FLOAT:Ljadx/api/plugins/input/insns/Opcode;
    2924: aastore
    2925: dup
    2926: bipush        105
    2928: getstatic     #219                // Field NEG_INT:Ljadx/api/plugins/input/insns/Opcode;
    2931: aastore
    2932: dup
    2933: bipush        106
    2935: getstatic     #221                // Field NEG_LONG:Ljadx/api/plugins/input/insns/Opcode;
    2938: aastore
    2939: dup
    2940: bipush        107
    2942: getstatic     #223                // Field NEW_INSTANCE:Ljadx/api/plugins/input/insns/Opcode;
    2945: aastore
    2946: dup
    2947: bipush        108
    2949: getstatic     #225                // Field NOT_INT:Ljadx/api/plugins/input/insns/Opcode;
    2952: aastore
    2953: dup
    2954: bipush        109
    2956: getstatic     #227                // Field NOT_LONG:Ljadx/api/plugins/input/insns/Opcode;
    2959: aastore
    2960: dup
    2961: bipush        110
    2963: getstatic     #229                // Field OR_INT:Ljadx/api/plugins/input/insns/Opcode;
    2966: aastore
    2967: dup
    2968: bipush        111
    2970: getstatic     #231                // Field OR_INT_LIT:Ljadx/api/plugins/input/insns/Opcode;
    2973: aastore
    2974: dup
    2975: bipush        112
    2977: getstatic     #233                // Field OR_LONG:Ljadx/api/plugins/input/insns/Opcode;
    2980: aastore
    2981: dup
    2982: bipush        113
    2984: getstatic     #235                // Field REM_DOUBLE:Ljadx/api/plugins/input/insns/Opcode;
    2987: aastore
    2988: dup
    2989: bipush        114
    2991: getstatic     #237                // Field REM_FLOAT:Ljadx/api/plugins/input/insns/Opcode;
    2994: aastore
    2995: dup
    2996: bipush        115
    2998: getstatic     #239                // Field REM_INT:Ljadx/api/plugins/input/insns/Opcode;
    3001: aastore
    3002: dup
    3003: bipush        116
    3005: getstatic     #241                // Field REM_INT_LIT:Ljadx/api/plugins/input/insns/Opcode;
    3008: aastore
    3009: dup
    3010: bipush        117
    3012: getstatic     #243                // Field REM_LONG:Ljadx/api/plugins/input/insns/Opcode;
    3015: aastore
    3016: dup
    3017: bipush        118
    3019: getstatic     #245                // Field RETURN:Ljadx/api/plugins/input/insns/Opcode;
    3022: aastore
    3023: dup
    3024: bipush        119
    3026: getstatic     #247                // Field RETURN_VOID:Ljadx/api/plugins/input/insns/Opcode;
    3029: aastore
    3030: dup
    3031: bipush        120
    3033: getstatic     #249                // Field RSUB_INT:Ljadx/api/plugins/input/insns/Opcode;
    3036: aastore
    3037: dup
    3038: bipush        121
    3040: getstatic     #251                // Field SHL_INT:Ljadx/api/plugins/input/insns/Opcode;
    3043: aastore
    3044: dup
    3045: bipush        122
    3047: getstatic     #253                // Field SHL_INT_LIT:Ljadx/api/plugins/input/insns/Opcode;
    3050: aastore
    3051: dup
    3052: bipush        123
    3054: getstatic     #255                // Field SHL_LONG:Ljadx/api/plugins/input/insns/Opcode;
    3057: aastore
    3058: dup
    3059: bipush        124
    3061: getstatic     #257                // Field SHR_INT:Ljadx/api/plugins/input/insns/Opcode;
    3064: aastore
    3065: dup
    3066: bipush        125
    3068: getstatic     #259                // Field SHR_INT_LIT:Ljadx/api/plugins/input/insns/Opcode;
    3071: aastore
    3072: dup
    3073: bipush        126
    3075: getstatic     #261                // Field SHR_LONG:Ljadx/api/plugins/input/insns/Opcode;
    3078: aastore
    3079: dup
    3080: bipush        127
    3082: getstatic     #263                // Field SUB_DOUBLE:Ljadx/api/plugins/input/insns/Opcode;
    3085: aastore
    3086: dup
    3087: sipush        128
    3090: getstatic     #265                // Field SUB_FLOAT:Ljadx/api/plugins/input/insns/Opcode;
    3093: aastore
    3094: dup
    3095: sipush        129
    3098: getstatic     #267                // Field SUB_INT:Ljadx/api/plugins/input/insns/Opcode;
    3101: aastore
    3102: dup
    3103: sipush        130
    3106: getstatic     #269                // Field SUB_LONG:Ljadx/api/plugins/input/insns/Opcode;
    3109: aastore
    3110: dup
    3111: sipush        131
    3114: getstatic     #271                // Field THROW:Ljadx/api/plugins/input/insns/Opcode;
    3117: aastore
    3118: dup
    3119: sipush        132
    3122: getstatic     #273                // Field USHR_INT:Ljadx/api/plugins/input/insns/Opcode;
    3125: aastore
    3126: dup
    3127: sipush        133
    3130: getstatic     #275                // Field USHR_INT_LIT:Ljadx/api/plugins/input/insns/Opcode;
    3133: aastore
    3134: dup
    3135: sipush        134
    3138: getstatic     #277                // Field USHR_LONG:Ljadx/api/plugins/input/insns/Opcode;
    3141: aastore
    3142: dup
    3143: sipush        135
    3146: getstatic     #279                // Field XOR_INT:Ljadx/api/plugins/input/insns/Opcode;
    3149: aastore
    3150: dup
    3151: sipush        136
    3154: getstatic     #281                // Field XOR_INT_LIT:Ljadx/api/plugins/input/insns/Opcode;
    3157: aastore
    3158: dup
    3159: sipush        137
    3162: getstatic     #283                // Field XOR_LONG:Ljadx/api/plugins/input/insns/Opcode;
    3165: aastore
    3166: dup
    3167: sipush        138
    3170: getstatic     #285                // Field NEW_ARRAY:Ljadx/api/plugins/input/insns/Opcode;
    3173: aastore
    3174: dup
    3175: sipush        139
    3178: getstatic     #287                // Field FILLED_NEW_ARRAY:Ljadx/api/plugins/input/insns/Opcode;
    3181: aastore
    3182: dup
    3183: sipush        140
    3186: getstatic     #289                // Field FILLED_NEW_ARRAY_RANGE:Ljadx/api/plugins/input/insns/Opcode;
    3189: aastore
    3190: dup
    3191: sipush        141
    3194: getstatic     #291                // Field FILL_ARRAY_DATA:Ljadx/api/plugins/input/insns/Opcode;
    3197: aastore
    3198: dup
    3199: sipush        142
    3202: getstatic     #293                // Field FILL_ARRAY_DATA_PAYLOAD:Ljadx/api/plugins/input/insns/Opcode;
    3205: aastore
    3206: dup
    3207: sipush        143
    3210: getstatic     #295                // Field PACKED_SWITCH:Ljadx/api/plugins/input/insns/Opcode;
    3213: aastore
    3214: dup
    3215: sipush        144
    3218: getstatic     #297                // Field PACKED_SWITCH_PAYLOAD:Ljadx/api/plugins/input/insns/Opcode;
    3221: aastore
    3222: dup
    3223: sipush        145
    3226: getstatic     #299                // Field SPARSE_SWITCH:Ljadx/api/plugins/input/insns/Opcode;
    3229: aastore
    3230: dup
    3231: sipush        146
    3234: getstatic     #301                // Field SPARSE_SWITCH_PAYLOAD:Ljadx/api/plugins/input/insns/Opcode;
    3237: aastore
    3238: dup
    3239: sipush        147
    3242: getstatic     #303                // Field INVOKE_POLYMORPHIC:Ljadx/api/plugins/input/insns/Opcode;
    3245: aastore
    3246: dup
    3247: sipush        148
    3250: getstatic     #305                // Field INVOKE_POLYMORPHIC_RANGE:Ljadx/api/plugins/input/insns/Opcode;
    3253: aastore
    3254: dup
    3255: sipush        149
    3258: getstatic     #307                // Field INVOKE_CUSTOM:Ljadx/api/plugins/input/insns/Opcode;
    3261: aastore
    3262: dup
    3263: sipush        150
    3266: getstatic     #309                // Field INVOKE_CUSTOM_RANGE:Ljadx/api/plugins/input/insns/Opcode;
    3269: aastore
    3270: dup
    3271: sipush        151
    3274: getstatic     #311                // Field CONST_METHOD_HANDLE:Ljadx/api/plugins/input/insns/Opcode;
    3277: aastore
    3278: dup
    3279: sipush        152
    3282: getstatic     #313                // Field CONST_METHOD_TYPE:Ljadx/api/plugins/input/insns/Opcode;
    3285: aastore
    3286: putstatic     #1                  // Field $VALUES:[Ljadx/api/plugins/input/insns/Opcode;
    3289: return
}
