Compiled from "ScopeBeanFactory.java"
public class org.apache.dubbo.common.beans.factory.ScopeBeanFactory {
  protected static final org.apache.dubbo.common.logger.ErrorTypeAwareLogger LOGGER;

  private final org.apache.dubbo.common.beans.factory.ScopeBeanFactory parent;

  private final org.apache.dubbo.common.extension.ExtensionAccessor extensionAccessor;

  private final java.util.List<org.apache.dubbo.common.extension.ExtensionPostProcessor> extensionPostProcessors;

  private final java.util.concurrent.ConcurrentHashMap<java.lang.Class<?>, java.util.concurrent.atomic.AtomicInteger> beanNameIdCounterMap;

  private final java.util.List<org.apache.dubbo.common.beans.factory.ScopeBeanFactory$BeanInfo> registeredBeanInfos;

  private org.apache.dubbo.common.beans.support.InstantiationStrategy instantiationStrategy;

  private final java.util.concurrent.atomic.AtomicBoolean destroyed;

  private java.util.List<java.lang.Class<?>> registeredClasses;

  public org.apache.dubbo.common.beans.factory.ScopeBeanFactory(org.apache.dubbo.common.beans.factory.ScopeBeanFactory, org.apache.dubbo.common.extension.ExtensionAccessor);
    Code:
       0: aload_0
       1: invokespecial #2                  // Method java/lang/Object."<init>":()V
       4: aload_0
       5: new           #3                  // class java/util/concurrent/ConcurrentHashMap
       8: dup
       9: invokespecial #4                  // Method java/util/concurrent/ConcurrentHashMap."<init>":()V
      12: putfield      #5                  // Field beanNameIdCounterMap:Ljava/util/concurrent/ConcurrentHashMap;
      15: aload_0
      16: new           #6                  // class java/util/concurrent/CopyOnWriteArrayList
      19: dup
      20: invokespecial #7                  // Method java/util/concurrent/CopyOnWriteArrayList."<init>":()V
      23: putfield      #8                  // Field registeredBeanInfos:Ljava/util/List;
      26: aload_0
      27: new           #9                  // class java/util/concurrent/atomic/AtomicBoolean
      30: dup
      31: invokespecial #10                 // Method java/util/concurrent/atomic/AtomicBoolean."<init>":()V
      34: putfield      #11                 // Field destroyed:Ljava/util/concurrent/atomic/AtomicBoolean;
      37: aload_0
      38: new           #12                 // class java/util/ArrayList
      41: dup
      42: invokespecial #13                 // Method java/util/ArrayList."<init>":()V
      45: putfield      #14                 // Field registeredClasses:Ljava/util/List;
      48: aload_0
      49: aload_1
      50: putfield      #15                 // Field parent:Lorg/apache/dubbo/common/beans/factory/ScopeBeanFactory;
      53: aload_0
      54: aload_2
      55: putfield      #16                 // Field extensionAccessor:Lorg/apache/dubbo/common/extension/ExtensionAccessor;
      58: aload_0
      59: aload_2
      60: invokeinterface #17,  1           // InterfaceMethod org/apache/dubbo/common/extension/ExtensionAccessor.getExtensionDirector:()Lorg/apache/dubbo/common/extension/ExtensionDirector;
      65: invokevirtual #18                 // Method org/apache/dubbo/common/extension/ExtensionDirector.getExtensionPostProcessors:()Ljava/util/List;
      68: putfield      #19                 // Field extensionPostProcessors:Ljava/util/List;
      71: aload_0
      72: invokespecial #20                 // Method initInstantiationStrategy:()V
      75: return

  private void initInstantiationStrategy();
    Code:
       0: aload_0
       1: getfield      #19                 // Field extensionPostProcessors:Ljava/util/List;
       4: invokeinterface #21,  1           // InterfaceMethod java/util/List.iterator:()Ljava/util/Iterator;
       9: astore_1
      10: aload_1
      11: invokeinterface #22,  1           // InterfaceMethod java/util/Iterator.hasNext:()Z
      16: ifeq          57
      19: aload_1
      20: invokeinterface #23,  1           // InterfaceMethod java/util/Iterator.next:()Ljava/lang/Object;
      25: checkcast     #24                 // class org/apache/dubbo/common/extension/ExtensionPostProcessor
      28: astore_2
      29: aload_2
      30: instanceof    #25                 // class org/apache/dubbo/rpc/model/ScopeModelAccessor
      33: ifeq          54
      36: aload_0
      37: new           #26                 // class org/apache/dubbo/common/beans/support/InstantiationStrategy
      40: dup
      41: aload_2
      42: checkcast     #25                 // class org/apache/dubbo/rpc/model/ScopeModelAccessor
      45: invokespecial #27                 // Method org/apache/dubbo/common/beans/support/InstantiationStrategy."<init>":(Lorg/apache/dubbo/rpc/model/ScopeModelAccessor;)V
      48: putfield      #28                 // Field instantiationStrategy:Lorg/apache/dubbo/common/beans/support/InstantiationStrategy;
      51: goto          57
      54: goto          10
      57: aload_0
      58: getfield      #28                 // Field instantiationStrategy:Lorg/apache/dubbo/common/beans/support/InstantiationStrategy;
      61: ifnonnull     75
      64: aload_0
      65: new           #26                 // class org/apache/dubbo/common/beans/support/InstantiationStrategy
      68: dup
      69: invokespecial #29                 // Method org/apache/dubbo/common/beans/support/InstantiationStrategy."<init>":()V
      72: putfield      #28                 // Field instantiationStrategy:Lorg/apache/dubbo/common/beans/support/InstantiationStrategy;
      75: return

  public <T> T registerBean(java.lang.Class<T>) throws org.apache.dubbo.common.beans.ScopeBeanException;
    Code:
       0: aload_0
       1: aconst_null
       2: aload_1
       3: invokevirtual #30                 // Method getOrRegisterBean:(Ljava/lang/String;Ljava/lang/Class;)Ljava/lang/Object;
       6: areturn

  public <T> T registerBean(java.lang.String, java.lang.Class<T>) throws org.apache.dubbo.common.beans.ScopeBeanException;
    Code:
       0: aload_0
       1: aload_1
       2: aload_2
       3: invokevirtual #30                 // Method getOrRegisterBean:(Ljava/lang/String;Ljava/lang/Class;)Ljava/lang/Object;
       6: areturn

  private <T> T createAndRegisterBean(java.lang.String, java.lang.Class<T>);
    Code:
       0: aload_0
       1: invokespecial #31                 // Method checkDestroyed:()V
       4: aload_0
       5: aload_1
       6: aload_2
       7: invokevirtual #32                 // Method getBean:(Ljava/lang/String;Ljava/lang/Class;)Ljava/lang/Object;
      10: astore_3
      11: aload_3
      12: ifnull        54
      15: new           #33                 // class org/apache/dubbo/common/beans/ScopeBeanException
      18: dup
      19: new           #34                 // class java/lang/StringBuilder
      22: dup
      23: invokespecial #35                 // Method java/lang/StringBuilder."<init>":()V
      26: ldc           #36                 // String already exists bean with same name and type, name=
      28: invokevirtual #37                 // Method java/lang/StringBuilder.append:(Ljava/lang/String;)Ljava/lang/StringBuilder;
      31: aload_1
      32: invokevirtual #37                 // Method java/lang/StringBuilder.append:(Ljava/lang/String;)Ljava/lang/StringBuilder;
      35: ldc           #38                 // String , type=
      37: invokevirtual #37                 // Method java/lang/StringBuilder.append:(Ljava/lang/String;)Ljava/lang/StringBuilder;
      40: aload_2
      41: invokevirtual #39                 // Method java/lang/Class.getName:()Ljava/lang/String;
      44: invokevirtual #37                 // Method java/lang/StringBuilder.append:(Ljava/lang/String;)Ljava/lang/StringBuilder;
      47: invokevirtual #40                 // Method java/lang/StringBuilder.toString:()Ljava/lang/String;
      50: invokespecial #41                 // Method org/apache/dubbo/common/beans/ScopeBeanException."<init>":(Ljava/lang/String;)V
      53: athrow
      54: aload_0
      55: getfield      #28                 // Field instantiationStrategy:Lorg/apache/dubbo/common/beans/support/InstantiationStrategy;
      58: aload_2
      59: invokevirtual #42                 // Method org/apache/dubbo/common/beans/support/InstantiationStrategy.instantiate:(Ljava/lang/Class;)Ljava/lang/Object;
      62: astore_3
      63: goto          100
      66: astore        4
      68: new           #33                 // class org/apache/dubbo/common/beans/ScopeBeanException
      71: dup
      72: new           #34                 // class java/lang/StringBuilder
      75: dup
      76: invokespecial #35                 // Method java/lang/StringBuilder."<init>":()V
      79: ldc           #44                 // String create bean instance failed, type=
      81: invokevirtual #37                 // Method java/lang/StringBuilder.append:(Ljava/lang/String;)Ljava/lang/StringBuilder;
      84: aload_2
      85: invokevirtual #39                 // Method java/lang/Class.getName:()Ljava/lang/String;
      88: invokevirtual #37                 // Method java/lang/StringBuilder.append:(Ljava/lang/String;)Ljava/lang/StringBuilder;
      91: invokevirtual #40                 // Method java/lang/StringBuilder.toString:()Ljava/lang/String;
      94: aload         4
      96: invokespecial #45                 // Method org/apache/dubbo/common/beans/ScopeBeanException."<init>":(Ljava/lang/String;Ljava/lang/Throwable;)V
      99: athrow
     100: aload_0
     101: aload_1
     102: aload_3
     103: invokevirtual #46                 // Method registerBean:(Ljava/lang/String;Ljava/lang/Object;)V
     106: aload_3
     107: areturn
    Exception table:
       from    to  target type
          54    63    66   Class java/lang/Throwable

  public void registerBean(java.lang.Object);
    Code:
       0: aload_0
       1: aconst_null
       2: aload_1
       3: invokevirtual #46                 // Method registerBean:(Ljava/lang/String;Ljava/lang/Object;)V
       6: return

  public void registerBean(java.lang.String, java.lang.Object);
    Code:
       0: aload_0
       1: invokespecial #31                 // Method checkDestroyed:()V
       4: aload_0
       5: aload_1
       6: aload_2
       7: invokespecial #47                 // Method containsBean:(Ljava/lang/String;Ljava/lang/Object;)Z
      10: ifeq          14
      13: return
      14: aload_2
      15: invokevirtual #48                 // Method java/lang/Object.getClass:()Ljava/lang/Class;
      18: astore_3
      19: aload_1
      20: ifnonnull     54
      23: new           #34                 // class java/lang/StringBuilder
      26: dup
      27: invokespecial #35                 // Method java/lang/StringBuilder."<init>":()V
      30: aload_3
      31: invokevirtual #39                 // Method java/lang/Class.getName:()Ljava/lang/String;
      34: invokevirtual #37                 // Method java/lang/StringBuilder.append:(Ljava/lang/String;)Ljava/lang/StringBuilder;
      37: ldc           #49                 // String #
      39: invokevirtual #37                 // Method java/lang/StringBuilder.append:(Ljava/lang/String;)Ljava/lang/StringBuilder;
      42: aload_0
      43: aload_3
      44: invokespecial #50                 // Method getNextId:(Ljava/lang/Class;)I
      47: invokevirtual #51                 // Method java/lang/StringBuilder.append:(I)Ljava/lang/StringBuilder;
      50: invokevirtual #40                 // Method java/lang/StringBuilder.toString:()Ljava/lang/String;
      53: astore_1
      54: aload_0
      55: aload_1
      56: aload_2
      57: invokespecial #52                 // Method initializeBean:(Ljava/lang/String;Ljava/lang/Object;)V
      60: aload_0
      61: getfield      #8                  // Field registeredBeanInfos:Ljava/util/List;
      64: new           #53                 // class org/apache/dubbo/common/beans/factory/ScopeBeanFactory$BeanInfo
      67: dup
      68: aload_1
      69: aload_2
      70: invokespecial #54                 // Method org/apache/dubbo/common/beans/factory/ScopeBeanFactory$BeanInfo."<init>":(Ljava/lang/String;Ljava/lang/Object;)V
      73: invokeinterface #55,  2           // InterfaceMethod java/util/List.add:(Ljava/lang/Object;)Z
      78: pop
      79: return

  public <T> T getOrRegisterBean(java.lang.Class<T>);
    Code:
       0: aload_0
       1: aconst_null
       2: aload_1
       3: invokevirtual #30                 // Method getOrRegisterBean:(Ljava/lang/String;Ljava/lang/Class;)Ljava/lang/Object;
       6: areturn

  public <T> T getOrRegisterBean(java.lang.String, java.lang.Class<T>);
    Code:
       0: aload_0
       1: aload_1
       2: aload_2
       3: invokevirtual #32                 // Method getBean:(Ljava/lang/String;Ljava/lang/Class;)Ljava/lang/Object;
       6: astore_3
       7: aload_3
       8: ifnonnull     48
      11: aload_2
      12: dup
      13: astore        4
      15: monitorenter
      16: aload_0
      17: aload_1
      18: aload_2
      19: invokevirtual #32                 // Method getBean:(Ljava/lang/String;Ljava/lang/Class;)Ljava/lang/Object;
      22: astore_3
      23: aload_3
      24: ifnonnull     34
      27: aload_0
      28: aload_1
      29: aload_2
      30: invokespecial #56                 // Method createAndRegisterBean:(Ljava/lang/String;Ljava/lang/Class;)Ljava/lang/Object;
      33: astore_3
      34: aload         4
      36: monitorexit
      37: goto          48
      40: astore        5
      42: aload         4
      44: monitorexit
      45: aload         5
      47: athrow
      48: aload_0
      49: getfield      #14                 // Field registeredClasses:Ljava/util/List;
      52: aload_2
      53: invokeinterface #55,  2           // InterfaceMethod java/util/List.add:(Ljava/lang/Object;)Z
      58: pop
      59: aload_3
      60: areturn
    Exception table:
       from    to  target type
          16    37    40   any
          40    45    40   any

  public <T> T getOrRegisterBean(java.lang.Class<T>, java.util.function.Function<? super java.lang.Class<T>, ? extends T>);
    Code:
       0: aload_0
       1: aconst_null
       2: aload_1
       3: aload_2
       4: invokevirtual #57                 // Method getOrRegisterBean:(Ljava/lang/String;Ljava/lang/Class;Ljava/util/function/Function;)Ljava/lang/Object;
       7: areturn

  public <T> T getOrRegisterBean(java.lang.String, java.lang.Class<T>, java.util.function.Function<? super java.lang.Class<T>, ? extends T>);
    Code:
       0: aload_0
       1: aload_1
       2: aload_2
       3: invokevirtual #32                 // Method getBean:(Ljava/lang/String;Ljava/lang/Class;)Ljava/lang/Object;
       6: astore        4
       8: aload         4
      10: ifnonnull     61
      13: aload_2
      14: dup
      15: astore        5
      17: monitorenter
      18: aload_0
      19: aload_1
      20: aload_2
      21: invokevirtual #32                 // Method getBean:(Ljava/lang/String;Ljava/lang/Class;)Ljava/lang/Object;
      24: astore        4
      26: aload         4
      28: ifnonnull     47
      31: aload_3
      32: aload_2
      33: invokeinterface #58,  2           // InterfaceMethod java/util/function/Function.apply:(Ljava/lang/Object;)Ljava/lang/Object;
      38: astore        4
      40: aload_0
      41: aload_1
      42: aload         4
      44: invokevirtual #46                 // Method registerBean:(Ljava/lang/String;Ljava/lang/Object;)V
      47: aload         5
      49: monitorexit
      50: goto          61
      53: astore        6
      55: aload         5
      57: monitorexit
      58: aload         6
      60: athrow
      61: aload         4
      63: areturn
    Exception table:
       from    to  target type
          18    50    53   any
          53    58    53   any

  public <T> T initializeBean(T);
    Code:
       0: aload_0
       1: aconst_null
       2: aload_1
       3: invokespecial #52                 // Method initializeBean:(Ljava/lang/String;Ljava/lang/Object;)V
       6: aload_1
       7: areturn

  private void initializeBean(java.lang.String, java.lang.Object);
    Code:
       0: aload_0
       1: invokespecial #31                 // Method checkDestroyed:()V
       4: aload_2
       5: instanceof    #59                 // class org/apache/dubbo/common/extension/ExtensionAccessorAware
       8: ifeq          24
      11: aload_2
      12: checkcast     #59                 // class org/apache/dubbo/common/extension/ExtensionAccessorAware
      15: aload_0
      16: getfield      #16                 // Field extensionAccessor:Lorg/apache/dubbo/common/extension/ExtensionAccessor;
      19: invokeinterface #60,  2           // InterfaceMethod org/apache/dubbo/common/extension/ExtensionAccessorAware.setExtensionAccessor:(Lorg/apache/dubbo/common/extension/ExtensionAccessor;)V
      24: aload_0
      25: getfield      #19                 // Field extensionPostProcessors:Ljava/util/List;
      28: invokeinterface #21,  1           // InterfaceMethod java/util/List.iterator:()Ljava/util/Iterator;
      33: astore_3
      34: aload_3
      35: invokeinterface #22,  1           // InterfaceMethod java/util/Iterator.hasNext:()Z
      40: ifeq          67
      43: aload_3
      44: invokeinterface #23,  1           // InterfaceMethod java/util/Iterator.next:()Ljava/lang/Object;
      49: checkcast     #24                 // class org/apache/dubbo/common/extension/ExtensionPostProcessor
      52: astore        4
      54: aload         4
      56: aload_2
      57: aload_1
      58: invokeinterface #61,  3           // InterfaceMethod org/apache/dubbo/common/extension/ExtensionPostProcessor.postProcessAfterInitialization:(Ljava/lang/Object;Ljava/lang/String;)Ljava/lang/Object;
      63: pop
      64: goto          34
      67: goto          114
      70: astore_3
      71: new           #33                 // class org/apache/dubbo/common/beans/ScopeBeanException
      74: dup
      75: new           #34                 // class java/lang/StringBuilder
      78: dup
      79: invokespecial #35                 // Method java/lang/StringBuilder."<init>":()V
      82: ldc           #63                 // String register bean failed! name=
      84: invokevirtual #37                 // Method java/lang/StringBuilder.append:(Ljava/lang/String;)Ljava/lang/StringBuilder;
      87: aload_1
      88: invokevirtual #37                 // Method java/lang/StringBuilder.append:(Ljava/lang/String;)Ljava/lang/StringBuilder;
      91: ldc           #38                 // String , type=
      93: invokevirtual #37                 // Method java/lang/StringBuilder.append:(Ljava/lang/String;)Ljava/lang/StringBuilder;
      96: aload_2
      97: invokevirtual #48                 // Method java/lang/Object.getClass:()Ljava/lang/Class;
     100: invokevirtual #39                 // Method java/lang/Class.getName:()Ljava/lang/String;
     103: invokevirtual #37                 // Method java/lang/StringBuilder.append:(Ljava/lang/String;)Ljava/lang/StringBuilder;
     106: invokevirtual #40                 // Method java/lang/StringBuilder.toString:()Ljava/lang/String;
     109: aload_3
     110: invokespecial #45                 // Method org/apache/dubbo/common/beans/ScopeBeanException."<init>":(Ljava/lang/String;Ljava/lang/Throwable;)V
     113: athrow
     114: return
    Exception table:
       from    to  target type
           4    67    70   Class java/lang/Exception

  private boolean containsBean(java.lang.String, java.lang.Object);
    Code:
       0: aload_0
       1: getfield      #8                  // Field registeredBeanInfos:Ljava/util/List;
       4: invokeinterface #21,  1           // InterfaceMethod java/util/List.iterator:()Ljava/util/Iterator;
       9: astore_3
      10: aload_3
      11: invokeinterface #22,  1           // InterfaceMethod java/util/Iterator.hasNext:()Z
      16: ifeq          60
      19: aload_3
      20: invokeinterface #23,  1           // InterfaceMethod java/util/Iterator.next:()Ljava/lang/Object;
      25: checkcast     #53                 // class org/apache/dubbo/common/beans/factory/ScopeBeanFactory$BeanInfo
      28: astore        4
      30: aload         4
      32: invokestatic  #64                 // Method org/apache/dubbo/common/beans/factory/ScopeBeanFactory$BeanInfo.access$000:(Lorg/apache/dubbo/common/beans/factory/ScopeBeanFactory$BeanInfo;)Ljava/lang/Object;
      35: aload_2
      36: if_acmpne     57
      39: aload_1
      40: ifnull        55
      43: aload_1
      44: aload         4
      46: invokestatic  #65                 // Method org/apache/dubbo/common/beans/factory/ScopeBeanFactory$BeanInfo.access$100:(Lorg/apache/dubbo/common/beans/factory/ScopeBeanFactory$BeanInfo;)Ljava/lang/String;
      49: invokestatic  #66                 // Method org/apache/dubbo/common/utils/StringUtils.isEquals:(Ljava/lang/String;Ljava/lang/String;)Z
      52: ifeq          57
      55: iconst_1
      56: ireturn
      57: goto          10
      60: iconst_0
      61: ireturn

  private int getNextId(java.lang.Class<?>);
    Code:
       0: aload_0
       1: getfield      #5                  // Field beanNameIdCounterMap:Ljava/util/concurrent/ConcurrentHashMap;
       4: aload_1
       5: invokedynamic #67,  0             // InvokeDynamic #0:apply:()Ljava/util/function/Function;
      10: invokestatic  #68                 // Method org/apache/dubbo/common/utils/ConcurrentHashMapUtils.computeIfAbsent:(Ljava/util/concurrent/ConcurrentMap;Ljava/lang/Object;Ljava/util/function/Function;)Ljava/lang/Object;
      13: checkcast     #69                 // class java/util/concurrent/atomic/AtomicInteger
      16: invokevirtual #70                 // Method java/util/concurrent/atomic/AtomicInteger.incrementAndGet:()I
      19: ireturn

  public <T> java.util.List<T> getBeansOfType(java.lang.Class<T>);
    Code:
       0: aload_0
       1: getfield      #8                  // Field registeredBeanInfos:Ljava/util/List;
       4: invokeinterface #71,  1           // InterfaceMethod java/util/List.stream:()Ljava/util/stream/Stream;
       9: aload_1
      10: invokedynamic #72,  0             // InvokeDynamic #1:test:(Ljava/lang/Class;)Ljava/util/function/Predicate;
      15: invokeinterface #73,  2           // InterfaceMethod java/util/stream/Stream.filter:(Ljava/util/function/Predicate;)Ljava/util/stream/Stream;
      20: invokedynamic #74,  0             // InvokeDynamic #2:apply:()Ljava/util/function/Function;
      25: invokeinterface #75,  2           // InterfaceMethod java/util/stream/Stream.map:(Ljava/util/function/Function;)Ljava/util/stream/Stream;
      30: invokestatic  #76                 // Method java/util/stream/Collectors.toList:()Ljava/util/stream/Collector;
      33: invokeinterface #77,  2           // InterfaceMethod java/util/stream/Stream.collect:(Ljava/util/stream/Collector;)Ljava/lang/Object;
      38: checkcast     #78                 // class java/util/List
      41: astore_2
      42: aload_0
      43: getfield      #15                 // Field parent:Lorg/apache/dubbo/common/beans/factory/ScopeBeanFactory;
      46: ifnull        64
      49: aload_2
      50: aload_0
      51: getfield      #15                 // Field parent:Lorg/apache/dubbo/common/beans/factory/ScopeBeanFactory;
      54: aload_1
      55: invokevirtual #79                 // Method getBeansOfType:(Ljava/lang/Class;)Ljava/util/List;
      58: invokeinterface #80,  2           // InterfaceMethod java/util/List.addAll:(Ljava/util/Collection;)Z
      63: pop
      64: aload_2
      65: areturn

  public <T> T getBean(java.lang.Class<T>);
    Code:
       0: aload_0
       1: aconst_null
       2: aload_1
       3: invokevirtual #32                 // Method getBean:(Ljava/lang/String;Ljava/lang/Class;)Ljava/lang/Object;
       6: areturn

  public <T> T getBean(java.lang.String, java.lang.Class<T>);
    Code:
       0: aload_0
       1: aload_1
       2: aload_2
       3: invokespecial #81                 // Method getBeanInternal:(Ljava/lang/String;Ljava/lang/Class;)Ljava/lang/Object;
       6: astore_3
       7: aload_3
       8: ifnonnull     28
      11: aload_0
      12: getfield      #15                 // Field parent:Lorg/apache/dubbo/common/beans/factory/ScopeBeanFactory;
      15: ifnull        28
      18: aload_0
      19: getfield      #15                 // Field parent:Lorg/apache/dubbo/common/beans/factory/ScopeBeanFactory;
      22: aload_1
      23: aload_2
      24: invokevirtual #32                 // Method getBean:(Ljava/lang/String;Ljava/lang/Class;)Ljava/lang/Object;
      27: areturn
      28: aload_3
      29: areturn

  private <T> T getBeanInternal(java.lang.String, java.lang.Class<T>);
    Code:
       0: aload_0
       1: invokespecial #31                 // Method checkDestroyed:()V
       4: aload_2
       5: ldc           #82                 // class java/lang/Object
       7: if_acmpne     12
      10: aconst_null
      11: areturn
      12: aconst_null
      13: astore_3
      14: aconst_null
      15: astore        4
      17: aload_0
      18: getfield      #8                  // Field registeredBeanInfos:Ljava/util/List;
      21: invokeinterface #21,  1           // InterfaceMethod java/util/List.iterator:()Ljava/util/Iterator;
      26: astore        5
      28: aload         5
      30: invokeinterface #22,  1           // InterfaceMethod java/util/Iterator.hasNext:()Z
      35: ifeq          128
      38: aload         5
      40: invokeinterface #23,  1           // InterfaceMethod java/util/Iterator.next:()Ljava/lang/Object;
      45: checkcast     #53                 // class org/apache/dubbo/common/beans/factory/ScopeBeanFactory$BeanInfo
      48: astore        6
      50: aload_2
      51: aload         6
      53: invokestatic  #64                 // Method org/apache/dubbo/common/beans/factory/ScopeBeanFactory$BeanInfo.access$000:(Lorg/apache/dubbo/common/beans/factory/ScopeBeanFactory$BeanInfo;)Ljava/lang/Object;
      56: invokevirtual #48                 // Method java/lang/Object.getClass:()Ljava/lang/Class;
      59: invokevirtual #83                 // Method java/lang/Class.isAssignableFrom:(Ljava/lang/Class;)Z
      62: ifeq          125
      65: aload         6
      67: invokestatic  #65                 // Method org/apache/dubbo/common/beans/factory/ScopeBeanFactory$BeanInfo.access$100:(Lorg/apache/dubbo/common/beans/factory/ScopeBeanFactory$BeanInfo;)Ljava/lang/String;
      70: aload_1
      71: invokestatic  #66                 // Method org/apache/dubbo/common/utils/StringUtils.isEquals:(Ljava/lang/String;Ljava/lang/String;)Z
      74: ifeq          83
      77: aload         6
      79: invokestatic  #64                 // Method org/apache/dubbo/common/beans/factory/ScopeBeanFactory$BeanInfo.access$000:(Lorg/apache/dubbo/common/beans/factory/ScopeBeanFactory$BeanInfo;)Ljava/lang/Object;
      82: areturn
      83: aload         4
      85: ifnonnull     95
      88: aload         6
      90: astore        4
      92: goto          125
      95: aload_3
      96: ifnonnull     116
      99: new           #12                 // class java/util/ArrayList
     102: dup
     103: invokespecial #13                 // Method java/util/ArrayList."<init>":()V
     106: astore_3
     107: aload_3
     108: aload         4
     110: invokeinterface #55,  2           // InterfaceMethod java/util/List.add:(Ljava/lang/Object;)Z
     115: pop
     116: aload_3
     117: aload         6
     119: invokeinterface #55,  2           // InterfaceMethod java/util/List.add:(Ljava/lang/Object;)Z
     124: pop
     125: goto          28
     128: aload_3
     129: ifnull        249
     132: aload_3
     133: invokeinterface #84,  1           // InterfaceMethod java/util/List.size:()I
     138: iconst_1
     139: if_icmpne     156
     142: aload_3
     143: iconst_0
     144: invokeinterface #85,  2           // InterfaceMethod java/util/List.get:(I)Ljava/lang/Object;
     149: checkcast     #53                 // class org/apache/dubbo/common/beans/factory/ScopeBeanFactory$BeanInfo
     152: invokestatic  #64                 // Method org/apache/dubbo/common/beans/factory/ScopeBeanFactory$BeanInfo.access$000:(Lorg/apache/dubbo/common/beans/factory/ScopeBeanFactory$BeanInfo;)Ljava/lang/Object;
     155: areturn
     156: aload_3
     157: invokeinterface #84,  1           // InterfaceMethod java/util/List.size:()I
     162: iconst_1
     163: if_icmple     260
     166: aload_3
     167: invokeinterface #71,  1           // InterfaceMethod java/util/List.stream:()Ljava/util/stream/Stream;
     172: invokedynamic #86,  0             // InvokeDynamic #3:apply:()Ljava/util/function/Function;
     177: invokeinterface #75,  2           // InterfaceMethod java/util/stream/Stream.map:(Ljava/util/function/Function;)Ljava/util/stream/Stream;
     182: invokestatic  #76                 // Method java/util/stream/Collectors.toList:()Ljava/util/stream/Collector;
     185: invokeinterface #77,  2           // InterfaceMethod java/util/stream/Stream.collect:(Ljava/util/stream/Collector;)Ljava/lang/Object;
     190: checkcast     #78                 // class java/util/List
     193: astore        5
     195: new           #33                 // class org/apache/dubbo/common/beans/ScopeBeanException
     198: dup
     199: new           #34                 // class java/lang/StringBuilder
     202: dup
     203: invokespecial #35                 // Method java/lang/StringBuilder."<init>":()V
     206: ldc           #87                 // String expected single matching bean but found
     208: invokevirtual #37                 // Method java/lang/StringBuilder.append:(Ljava/lang/String;)Ljava/lang/StringBuilder;
     211: aload_3
     212: invokeinterface #84,  1           // InterfaceMethod java/util/List.size:()I
     217: invokevirtual #51                 // Method java/lang/StringBuilder.append:(I)Ljava/lang/StringBuilder;
     220: ldc           #88                 // String  candidates for type [
     222: invokevirtual #37                 // Method java/lang/StringBuilder.append:(Ljava/lang/String;)Ljava/lang/StringBuilder;
     225: aload_2
     226: invokevirtual #39                 // Method java/lang/Class.getName:()Ljava/lang/String;
     229: invokevirtual #37                 // Method java/lang/StringBuilder.append:(Ljava/lang/String;)Ljava/lang/StringBuilder;
     232: ldc           #89                 // String ]:
     234: invokevirtual #37                 // Method java/lang/StringBuilder.append:(Ljava/lang/String;)Ljava/lang/StringBuilder;
     237: aload         5
     239: invokevirtual #90                 // Method java/lang/StringBuilder.append:(Ljava/lang/Object;)Ljava/lang/StringBuilder;
     242: invokevirtual #40                 // Method java/lang/StringBuilder.toString:()Ljava/lang/String;
     245: invokespecial #41                 // Method org/apache/dubbo/common/beans/ScopeBeanException."<init>":(Ljava/lang/String;)V
     248: athrow
     249: aload         4
     251: ifnull        260
     254: aload         4
     256: invokestatic  #64                 // Method org/apache/dubbo/common/beans/factory/ScopeBeanFactory$BeanInfo.access$000:(Lorg/apache/dubbo/common/beans/factory/ScopeBeanFactory$BeanInfo;)Ljava/lang/Object;
     259: areturn
     260: aconst_null
     261: areturn

  public void destroy();
    Code:
       0: aload_0
       1: getfield      #11                 // Field destroyed:Ljava/util/concurrent/atomic/AtomicBoolean;
       4: iconst_0
       5: iconst_1
       6: invokevirtual #91                 // Method java/util/concurrent/atomic/AtomicBoolean.compareAndSet:(ZZ)Z
       9: ifeq          139
      12: aload_0
      13: getfield      #8                  // Field registeredBeanInfos:Ljava/util/List;
      16: invokeinterface #21,  1           // InterfaceMethod java/util/List.iterator:()Ljava/util/Iterator;
      21: astore_1
      22: aload_1
      23: invokeinterface #22,  1           // InterfaceMethod java/util/Iterator.hasNext:()Z
      28: ifeq          130
      31: aload_1
      32: invokeinterface #23,  1           // InterfaceMethod java/util/Iterator.next:()Ljava/lang/Object;
      37: checkcast     #53                 // class org/apache/dubbo/common/beans/factory/ScopeBeanFactory$BeanInfo
      40: astore_2
      41: aload_2
      42: invokestatic  #64                 // Method org/apache/dubbo/common/beans/factory/ScopeBeanFactory$BeanInfo.access$000:(Lorg/apache/dubbo/common/beans/factory/ScopeBeanFactory$BeanInfo;)Ljava/lang/Object;
      45: instanceof    #92                 // class org/apache/dubbo/common/resource/Disposable
      48: ifeq          127
      51: aload_2
      52: invokestatic  #64                 // Method org/apache/dubbo/common/beans/factory/ScopeBeanFactory$BeanInfo.access$000:(Lorg/apache/dubbo/common/beans/factory/ScopeBeanFactory$BeanInfo;)Ljava/lang/Object;
      55: checkcast     #92                 // class org/apache/dubbo/common/resource/Disposable
      58: astore_3
      59: aload_3
      60: invokeinterface #93,  1           // InterfaceMethod org/apache/dubbo/common/resource/Disposable.destroy:()V
      65: goto          127
      68: astore_3
      69: getstatic     #94                 // Field LOGGER:Lorg/apache/dubbo/common/logger/ErrorTypeAwareLogger;
      72: ldc           #95                 // String 5-3
      74: ldc           #96                 // String
      76: ldc           #96                 // String
      78: new           #34                 // class java/lang/StringBuilder
      81: dup
      82: invokespecial #35                 // Method java/lang/StringBuilder."<init>":()V
      85: ldc           #97                 // String An error occurred when destroy bean [name=
      87: invokevirtual #37                 // Method java/lang/StringBuilder.append:(Ljava/lang/String;)Ljava/lang/StringBuilder;
      90: aload_2
      91: invokestatic  #65                 // Method org/apache/dubbo/common/beans/factory/ScopeBeanFactory$BeanInfo.access$100:(Lorg/apache/dubbo/common/beans/factory/ScopeBeanFactory$BeanInfo;)Ljava/lang/String;
      94: invokevirtual #37                 // Method java/lang/StringBuilder.append:(Ljava/lang/String;)Ljava/lang/StringBuilder;
      97: ldc           #98                 // String , bean=
      99: invokevirtual #37                 // Method java/lang/StringBuilder.append:(Ljava/lang/String;)Ljava/lang/StringBuilder;
     102: aload_2
     103: invokestatic  #64                 // Method org/apache/dubbo/common/beans/factory/ScopeBeanFactory$BeanInfo.access$000:(Lorg/apache/dubbo/common/beans/factory/ScopeBeanFactory$BeanInfo;)Ljava/lang/Object;
     106: invokevirtual #90                 // Method java/lang/StringBuilder.append:(Ljava/lang/Object;)Ljava/lang/StringBuilder;
     109: ldc           #89                 // String ]:
     111: invokevirtual #37                 // Method java/lang/StringBuilder.append:(Ljava/lang/String;)Ljava/lang/StringBuilder;
     114: aload_3
     115: invokevirtual #90                 // Method java/lang/StringBuilder.append:(Ljava/lang/Object;)Ljava/lang/StringBuilder;
     118: invokevirtual #40                 // Method java/lang/StringBuilder.toString:()Ljava/lang/String;
     121: aload_3
     122: invokeinterface #99,  6           // InterfaceMethod org/apache/dubbo/common/logger/ErrorTypeAwareLogger.error:(Ljava/lang/String;Ljava/lang/String;Ljava/lang/String;Ljava/lang/String;Ljava/lang/Throwable;)V
     127: goto          22
     130: aload_0
     131: getfield      #8                  // Field registeredBeanInfos:Ljava/util/List;
     134: invokeinterface #100,  1          // InterfaceMethod java/util/List.clear:()V
     139: return
    Exception table:
       from    to  target type
          51    65    68   Class java/lang/Throwable

  public boolean isDestroyed();
    Code:
       0: aload_0
       1: getfield      #11                 // Field destroyed:Ljava/util/concurrent/atomic/AtomicBoolean;
       4: invokevirtual #101                // Method java/util/concurrent/atomic/AtomicBoolean.get:()Z
       7: ireturn

  private void checkDestroyed();
    Code:
       0: aload_0
       1: getfield      #11                 // Field destroyed:Ljava/util/concurrent/atomic/AtomicBoolean;
       4: invokevirtual #101                // Method java/util/concurrent/atomic/AtomicBoolean.get:()Z
       7: ifeq          20
      10: new           #102                // class java/lang/IllegalStateException
      13: dup
      14: ldc           #103                // String ScopeBeanFactory is destroyed
      16: invokespecial #104                // Method java/lang/IllegalStateException."<init>":(Ljava/lang/String;)V
      19: athrow
      20: return

  public java.util.List<java.lang.Class<?>> getRegisteredClasses();
    Code:
       0: aload_0
       1: getfield      #14                 // Field registeredClasses:Ljava/util/List;
       4: areturn

  private static java.lang.String lambda$getBeanInternal$3(org.apache.dubbo.common.beans.factory.ScopeBeanFactory$BeanInfo);
    Code:
       0: aload_0
       1: invokestatic  #65                 // Method org/apache/dubbo/common/beans/factory/ScopeBeanFactory$BeanInfo.access$100:(Lorg/apache/dubbo/common/beans/factory/ScopeBeanFactory$BeanInfo;)Ljava/lang/String;
       4: areturn

  private static java.lang.Object lambda$getBeansOfType$2(org.apache.dubbo.common.beans.factory.ScopeBeanFactory$BeanInfo);
    Code:
       0: aload_0
       1: invokestatic  #64                 // Method org/apache/dubbo/common/beans/factory/ScopeBeanFactory$BeanInfo.access$000:(Lorg/apache/dubbo/common/beans/factory/ScopeBeanFactory$BeanInfo;)Ljava/lang/Object;
       4: areturn

  private static boolean lambda$getBeansOfType$1(java.lang.Class, org.apache.dubbo.common.beans.factory.ScopeBeanFactory$BeanInfo);
    Code:
       0: aload_0
       1: aload_1
       2: invokestatic  #64                 // Method org/apache/dubbo/common/beans/factory/ScopeBeanFactory$BeanInfo.access$000:(Lorg/apache/dubbo/common/beans/factory/ScopeBeanFactory$BeanInfo;)Ljava/lang/Object;
       5: invokevirtual #105                // Method java/lang/Class.isInstance:(Ljava/lang/Object;)Z
       8: ireturn

  private static java.util.concurrent.atomic.AtomicInteger lambda$getNextId$0(java.lang.Class);
    Code:
       0: new           #69                 // class java/util/concurrent/atomic/AtomicInteger
       3: dup
       4: invokespecial #106                // Method java/util/concurrent/atomic/AtomicInteger."<init>":()V
       7: areturn

  static {};
    Code:
       0: ldc           #107                // class org/apache/dubbo/common/beans/factory/ScopeBeanFactory
       2: invokestatic  #108                // Method org/apache/dubbo/common/logger/LoggerFactory.getErrorTypeAwareLogger:(Ljava/lang/Class;)Lorg/apache/dubbo/common/logger/ErrorTypeAwareLogger;
       5: putstatic     #94                 // Field LOGGER:Lorg/apache/dubbo/common/logger/ErrorTypeAwareLogger;
       8: return
}
