Compiled from "ScopeBeanFactory.java"
class org.apache.dubbo.common.beans.factory.ScopeBeanFactory$BeanInfo {
  private final java.lang.String name;

  private final java.lang.Object instance;

  public org.apache.dubbo.common.beans.factory.ScopeBeanFactory$BeanInfo(java.lang.String, java.lang.Object);
    Code:
       0: aload_0
       1: invokespecial #3                  // Method java/lang/Object."<init>":()V
       4: aload_0
       5: aload_1
       6: putfield      #1                  // Field name:Ljava/lang/String;
       9: aload_0
      10: aload_2
      11: putfield      #2                  // Field instance:Ljava/lang/Object;
      14: return

  static java.lang.Object access$000(org.apache.dubbo.common.beans.factory.ScopeBeanFactory$BeanInfo);
    Code:
       0: aload_0
       1: getfield      #2                  // Field instance:Ljava/lang/Object;
       4: areturn

  static java.lang.String access$100(org.apache.dubbo.common.beans.factory.ScopeBeanFactory$BeanInfo);
    Code:
       0: aload_0
       1: getfield      #1                  // Field name:Ljava/lang/String;
       4: areturn
}
