Compiled from "Configurations.java"
public abstract class org.springframework.boot.context.annotation.Configurations {
  private static final java.util.Comparator<java.lang.Object> COMPARATOR;

  private final java.util.Set<java.lang.Class<?>> classes;

  protected org.springframework.boot.context.annotation.Configurations(java.util.Collection<java.lang.Class<?>>);
    Code:
       0: aload_0
       1: invokespecial #1                  // Method java/lang/Object."<init>":()V
       4: aload_1
       5: ldc           #7                  // String Classes must not be null
       7: invokestatic  #9                  // Method org/springframework/util/Assert.notNull:(Ljava/lang/Object;Ljava/lang/String;)V
      10: aload_0
      11: aload_1
      12: invokevirtual #15                 // Method sort:(Ljava/util/Collection;)Ljava/util/Collection;
      15: astore_2
      16: aload_0
      17: new           #21                 // class java/util/LinkedHashSet
      20: dup
      21: aload_2
      22: invokespecial #23                 // Method java/util/LinkedHashSet."<init>":(Ljava/util/Collection;)V
      25: invokestatic  #26                 // Method java/util/Collections.unmodifiableSet:(Ljava/util/Set;)Ljava/util/Set;
      28: putfield      #32                 // Field classes:Ljava/util/Set;
      31: return

  protected java.util.Collection<java.lang.Class<?>> sort(java.util.Collection<java.lang.Class<?>>);
    Code:
       0: aload_1
       1: areturn

  protected final java.util.Set<java.lang.Class<?>> getClasses();
    Code:
       0: aload_0
       1: getfield      #32                 // Field classes:Ljava/util/Set;
       4: areturn

  protected org.springframework.boot.context.annotation.Configurations merge(org.springframework.boot.context.annotation.Configurations);
    Code:
       0: new           #21                 // class java/util/LinkedHashSet
       3: dup
       4: aload_0
       5: invokevirtual #36                 // Method getClasses:()Ljava/util/Set;
       8: invokespecial #23                 // Method java/util/LinkedHashSet."<init>":(Ljava/util/Collection;)V
      11: astore_2
      12: aload_2
      13: aload_1
      14: invokevirtual #36                 // Method getClasses:()Ljava/util/Set;
      17: invokeinterface #40,  2           // InterfaceMethod java/util/Set.addAll:(Ljava/util/Collection;)Z
      22: pop
      23: aload_0
      24: aload_2
      25: invokevirtual #46                 // Method merge:(Ljava/util/Set;)Lorg/springframework/boot/context/annotation/Configurations;
      28: areturn

  protected abstract org.springframework.boot.context.annotation.Configurations merge(java.util.Set<java.lang.Class<?>>);

  public static java.lang.Class<?>[] getClasses(org.springframework.boot.context.annotation.Configurations...);
    Code:
       0: aload_0
       1: invokestatic  #50                 // Method java/util/Arrays.asList:([Ljava/lang/Object;)Ljava/util/List;
       4: invokestatic  #56                 // Method getClasses:(Ljava/util/Collection;)[Ljava/lang/Class;
       7: areturn

  public static java.lang.Class<?>[] getClasses(java.util.Collection<org.springframework.boot.context.annotation.Configurations>);
    Code:
       0: new           #59                 // class java/util/ArrayList
       3: dup
       4: aload_0
       5: invokespecial #61                 // Method java/util/ArrayList."<init>":(Ljava/util/Collection;)V
       8: astore_1
       9: aload_1
      10: getstatic     #62                 // Field COMPARATOR:Ljava/util/Comparator;
      13: invokeinterface #66,  2           // InterfaceMethod java/util/List.sort:(Ljava/util/Comparator;)V
      18: aload_1
      19: invokestatic  #71                 // Method collate:(Ljava/util/List;)Ljava/util/List;
      22: astore_2
      23: aload_2
      24: invokeinterface #75,  1           // InterfaceMethod java/util/List.stream:()Ljava/util/stream/Stream;
      29: invokedynamic #79,  0             // InvokeDynamic #0:apply:()Ljava/util/function/Function;
      34: invokeinterface #83,  2           // InterfaceMethod java/util/stream/Stream.flatMap:(Ljava/util/function/Function;)Ljava/util/stream/Stream;
      39: invokedynamic #89,  0             // InvokeDynamic #1:get:()Ljava/util/function/Supplier;
      44: invokestatic  #93                 // Method java/util/stream/Collectors.toCollection:(Ljava/util/function/Supplier;)Ljava/util/stream/Collector;
      47: invokeinterface #99,  2           // InterfaceMethod java/util/stream/Stream.collect:(Ljava/util/stream/Collector;)Ljava/lang/Object;
      52: checkcast     #21                 // class java/util/LinkedHashSet
      55: astore_3
      56: aload_3
      57: invokestatic  #103                // Method org/springframework/util/ClassUtils.toClassArray:(Ljava/util/Collection;)[Ljava/lang/Class;
      60: areturn

  private static java.util.stream.Stream<java.lang.Class<?>> streamClasses(org.springframework.boot.context.annotation.Configurations);
    Code:
       0: aload_0
       1: invokevirtual #36                 // Method getClasses:()Ljava/util/Set;
       4: invokeinterface #108,  1          // InterfaceMethod java/util/Set.stream:()Ljava/util/stream/Stream;
       9: areturn

  private static java.util.List<org.springframework.boot.context.annotation.Configurations> collate(java.util.List<org.springframework.boot.context.annotation.Configurations>);
    Code:
       0: new           #109                // class java/util/LinkedList
       3: dup
       4: invokespecial #111                // Method java/util/LinkedList."<init>":()V
       7: astore_1
       8: aload_0
       9: invokeinterface #112,  1          // InterfaceMethod java/util/List.iterator:()Ljava/util/Iterator;
      14: astore_2
      15: aload_2
      16: invokeinterface #116,  1          // InterfaceMethod java/util/Iterator.hasNext:()Z
      21: ifeq          92
      24: aload_2
      25: invokeinterface #122,  1          // InterfaceMethod java/util/Iterator.next:()Ljava/lang/Object;
      30: checkcast     #16                 // class org/springframework/boot/context/annotation/Configurations
      33: astore_3
      34: aload_1
      35: invokevirtual #126                // Method java/util/LinkedList.isEmpty:()Z
      38: ifne          58
      41: aload_1
      42: invokevirtual #129                // Method java/util/LinkedList.getLast:()Ljava/lang/Object;
      45: checkcast     #16                 // class org/springframework/boot/context/annotation/Configurations
      48: invokevirtual #132                // Method java/lang/Object.getClass:()Ljava/lang/Class;
      51: aload_3
      52: invokevirtual #132                // Method java/lang/Object.getClass:()Ljava/lang/Class;
      55: if_acmpeq     67
      58: aload_1
      59: aload_3
      60: invokevirtual #136                // Method java/util/LinkedList.add:(Ljava/lang/Object;)Z
      63: pop
      64: goto          89
      67: aload_1
      68: aload_1
      69: invokevirtual #140                // Method java/util/LinkedList.size:()I
      72: iconst_1
      73: isub
      74: aload_1
      75: invokevirtual #129                // Method java/util/LinkedList.getLast:()Ljava/lang/Object;
      78: checkcast     #16                 // class org/springframework/boot/context/annotation/Configurations
      81: aload_3
      82: invokevirtual #144                // Method merge:(Lorg/springframework/boot/context/annotation/Configurations;)Lorg/springframework/boot/context/annotation/Configurations;
      85: invokevirtual #147                // Method java/util/LinkedList.set:(ILjava/lang/Object;)Ljava/lang/Object;
      88: pop
      89: goto          15
      92: aload_1
      93: areturn

  private static java.lang.String lambda$static$0(java.lang.Object);
    Code:
       0: aload_0
       1: invokevirtual #132                // Method java/lang/Object.getClass:()Ljava/lang/Class;
       4: invokevirtual #151                // Method java/lang/Class.getName:()Ljava/lang/String;
       7: areturn

  static {};
    Code:
       0: getstatic     #157                // Field org/springframework/core/OrderComparator.INSTANCE:Lorg/springframework/core/OrderComparator;
       3: invokedynamic #163,  0            // InvokeDynamic #2:apply:()Ljava/util/function/Function;
       8: invokevirtual #164                // Method org/springframework/core/OrderComparator.thenComparing:(Ljava/util/function/Function;)Ljava/util/Comparator;
      11: putstatic     #62                 // Field COMPARATOR:Ljava/util/Comparator;
      14: return
}
