Compiled from "ImportCandidates.java"
public final class org.springframework.boot.context.annotation.ImportCandidates implements java.lang.Iterable<java.lang.String> {
  private static final java.lang.String LOCATION;

  private static final java.lang.String COMMENT_START;

  private final java.util.List<java.lang.String> candidates;

  private org.springframework.boot.context.annotation.ImportCandidates(java.util.List<java.lang.String>);
    Code:
       0: aload_0
       1: invokespecial #1                  // Method java/lang/Object."<init>":()V
       4: aload_1
       5: ldc           #7                  // String \'candidates\' must not be null
       7: invokestatic  #9                  // Method org/springframework/util/Assert.notNull:(Ljava/lang/Object;Ljava/lang/String;)V
      10: aload_0
      11: aload_1
      12: invokestatic  #15                 // Method java/util/Collections.unmodifiableList:(Ljava/util/List;)Ljava/util/List;
      15: putfield      #21                 // Field candidates:Ljava/util/List;
      18: return

  public java.util.Iterator<java.lang.String> iterator();
    Code:
       0: aload_0
       1: getfield      #21                 // Field candidates:Ljava/util/List;
       4: invokeinterface #27,  1           // InterfaceMethod java/util/List.iterator:()Ljava/util/Iterator;
       9: areturn

  public java.util.List<java.lang.String> getCandidates();
    Code:
       0: aload_0
       1: getfield      #21                 // Field candidates:Ljava/util/List;
       4: areturn

  public static org.springframework.boot.context.annotation.ImportCandidates load(java.lang.Class<?>, java.lang.ClassLoader);
    Code:
       0: aload_0
       1: ldc           #33                 // String \'annotation\' must not be null
       3: invokestatic  #9                  // Method org/springframework/util/Assert.notNull:(Ljava/lang/Object;Ljava/lang/String;)V
       6: aload_1
       7: invokestatic  #35                 // Method decideClassloader:(Ljava/lang/ClassLoader;)Ljava/lang/ClassLoader;
      10: astore_2
      11: ldc           #39                 // String META-INF/spring/%s.imports
      13: iconst_1
      14: anewarray     #2                  // class java/lang/Object
      17: dup
      18: iconst_0
      19: aload_0
      20: invokevirtual #41                 // Method java/lang/Class.getName:()Ljava/lang/String;
      23: aastore
      24: invokestatic  #47                 // Method java/lang/String.format:(Ljava/lang/String;[Ljava/lang/Object;)Ljava/lang/String;
      27: astore_3
      28: aload_2
      29: aload_3
      30: invokestatic  #53                 // Method findUrlsInClasspath:(Ljava/lang/ClassLoader;Ljava/lang/String;)Ljava/util/Enumeration;
      33: astore        4
      35: new           #57                 // class java/util/ArrayList
      38: dup
      39: invokespecial #59                 // Method java/util/ArrayList."<init>":()V
      42: astore        5
      44: aload         4
      46: invokeinterface #60,  1           // InterfaceMethod java/util/Enumeration.hasMoreElements:()Z
      51: ifeq          82
      54: aload         4
      56: invokeinterface #66,  1           // InterfaceMethod java/util/Enumeration.nextElement:()Ljava/lang/Object;
      61: checkcast     #70                 // class java/net/URL
      64: astore        6
      66: aload         5
      68: aload         6
      70: invokestatic  #72                 // Method readCandidateConfigurations:(Ljava/net/URL;)Ljava/util/List;
      73: invokeinterface #76,  2           // InterfaceMethod java/util/List.addAll:(Ljava/util/Collection;)Z
      78: pop
      79: goto          44
      82: new           #22                 // class org/springframework/boot/context/annotation/ImportCandidates
      85: dup
      86: aload         5
      88: invokespecial #80                 // Method "<init>":(Ljava/util/List;)V
      91: areturn

  private static java.lang.ClassLoader decideClassloader(java.lang.ClassLoader);
    Code:
       0: aload_0
       1: ifnonnull     10
       4: ldc           #22                 // class org/springframework/boot/context/annotation/ImportCandidates
       6: invokevirtual #83                 // Method java/lang/Class.getClassLoader:()Ljava/lang/ClassLoader;
       9: areturn
      10: aload_0
      11: areturn

  private static java.util.Enumeration<java.net.URL> findUrlsInClasspath(java.lang.ClassLoader, java.lang.String);
    Code:
       0: aload_0
       1: aload_1
       2: invokevirtual #87                 // Method java/lang/ClassLoader.getResources:(Ljava/lang/String;)Ljava/util/Enumeration;
       5: areturn
       6: astore_2
       7: new           #95                 // class java/lang/IllegalArgumentException
      10: dup
      11: aload_1
      12: invokedynamic #97,  0             // InvokeDynamic #0:makeConcatWithConstants:(Ljava/lang/String;)Ljava/lang/String;
      17: aload_2
      18: invokespecial #101                // Method java/lang/IllegalArgumentException."<init>":(Ljava/lang/String;Ljava/lang/Throwable;)V
      21: athrow
    Exception table:
       from    to  target type
           0     5     6   Class java/io/IOException

  private static java.util.List<java.lang.String> readCandidateConfigurations(java.net.URL);
    Code:
       0: new           #104                // class java/io/BufferedReader
       3: dup
       4: new           #106                // class java/io/InputStreamReader
       7: dup
       8: new           #108                // class org/springframework/core/io/UrlResource
      11: dup
      12: aload_0
      13: invokespecial #110                // Method org/springframework/core/io/UrlResource."<init>":(Ljava/net/URL;)V
      16: invokevirtual #113                // Method org/springframework/core/io/UrlResource.getInputStream:()Ljava/io/InputStream;
      19: getstatic     #117                // Field java/nio/charset/StandardCharsets.UTF_8:Ljava/nio/charset/Charset;
      22: invokespecial #123                // Method java/io/InputStreamReader."<init>":(Ljava/io/InputStream;Ljava/nio/charset/Charset;)V
      25: invokespecial #126                // Method java/io/BufferedReader."<init>":(Ljava/io/Reader;)V
      28: astore_1
      29: new           #57                 // class java/util/ArrayList
      32: dup
      33: invokespecial #59                 // Method java/util/ArrayList."<init>":()V
      36: astore_2
      37: aload_1
      38: invokevirtual #129                // Method java/io/BufferedReader.readLine:()Ljava/lang/String;
      41: dup
      42: astore_3
      43: ifnull        77
      46: aload_3
      47: invokestatic  #132                // Method stripComment:(Ljava/lang/String;)Ljava/lang/String;
      50: astore_3
      51: aload_3
      52: invokevirtual #135                // Method java/lang/String.trim:()Ljava/lang/String;
      55: astore_3
      56: aload_3
      57: invokevirtual #138                // Method java/lang/String.isEmpty:()Z
      60: ifeq          66
      63: goto          37
      66: aload_2
      67: aload_3
      68: invokeinterface #141,  2          // InterfaceMethod java/util/List.add:(Ljava/lang/Object;)Z
      73: pop
      74: goto          37
      77: aload_2
      78: astore        4
      80: aload_1
      81: invokevirtual #145                // Method java/io/BufferedReader.close:()V
      84: aload         4
      86: areturn
      87: astore_2
      88: aload_1
      89: invokevirtual #145                // Method java/io/BufferedReader.close:()V
      92: goto          101
      95: astore_3
      96: aload_2
      97: aload_3
      98: invokevirtual #150                // Method java/lang/Throwable.addSuppressed:(Ljava/lang/Throwable;)V
     101: aload_2
     102: athrow
     103: astore_1
     104: new           #95                 // class java/lang/IllegalArgumentException
     107: dup
     108: aload_0
     109: invokedynamic #154,  0            // InvokeDynamic #1:makeConcatWithConstants:(Ljava/net/URL;)Ljava/lang/String;
     114: aload_1
     115: invokespecial #101                // Method java/lang/IllegalArgumentException."<init>":(Ljava/lang/String;Ljava/lang/Throwable;)V
     118: athrow
    Exception table:
       from    to  target type
          29    80    87   Class java/lang/Throwable
          88    92    95   Class java/lang/Throwable
           0    84   103   Class java/io/IOException
          87   103   103   Class java/io/IOException

  private static java.lang.String stripComment(java.lang.String);
    Code:
       0: aload_0
       1: ldc           #157                // String #
       3: invokevirtual #159                // Method java/lang/String.indexOf:(Ljava/lang/String;)I
       6: istore_1
       7: iload_1
       8: iconst_m1
       9: if_icmpne     14
      12: aload_0
      13: areturn
      14: aload_0
      15: iconst_0
      16: iload_1
      17: invokevirtual #163                // Method java/lang/String.substring:(II)Ljava/lang/String;
      20: areturn
}
