Compiled from "ExpiringCacheFactory.java"
public class org.apache.dubbo.cache.support.expiring.ExpiringCacheFactory extends org.apache.dubbo.cache.support.AbstractCacheFactory {
  public org.apache.dubbo.cache.support.expiring.ExpiringCacheFactory();
    Code:
       0: aload_0
       1: invokespecial #1                  // Method org/apache/dubbo/cache/support/AbstractCacheFactory."<init>":()V
       4: return

  protected org.apache.dubbo.cache.Cache createCache(org.apache.dubbo.common.URL);
    Code:
       0: new           #2                  // class org/apache/dubbo/cache/support/expiring/ExpiringCache
       3: dup
       4: aload_1
       5: invokespecial #3                  // Method org/apache/dubbo/cache/support/expiring/ExpiringCache."<init>":(Lorg/apache/dubbo/common/URL;)V
       8: areturn
}
