Compiled from "ExpiringMap.java"
class org.apache.dubbo.cache.support.expiring.ExpiringMap$ExpiryObject {
  private K key;

  private V value;

  private java.util.concurrent.atomic.AtomicLong lastAccessTime;

  final org.apache.dubbo.cache.support.expiring.ExpiringMap this$0;

  org.apache.dubbo.cache.support.expiring.ExpiringMap$ExpiryObject(K, V, long);
    Code:
       0: aload_0
       1: aload_1
       2: putfield      #1                  // Field this$0:Lorg/apache/dubbo/cache/support/expiring/ExpiringMap;
       5: aload_0
       6: invokespecial #2                  // Method java/lang/Object."<init>":()V
       9: aload_3
      10: ifnonnull     23
      13: new           #3                  // class java/lang/IllegalArgumentException
      16: dup
      17: ldc           #4                  // String An expiring object cannot be null.
      19: invokespecial #5                  // Method java/lang/IllegalArgumentException."<init>":(Ljava/lang/String;)V
      22: athrow
      23: aload_0
      24: aload_2
      25: putfield      #6                  // Field key:Ljava/lang/Object;
      28: aload_0
      29: aload_3
      30: putfield      #7                  // Field value:Ljava/lang/Object;
      33: aload_0
      34: new           #8                  // class java/util/concurrent/atomic/AtomicLong
      37: dup
      38: lload         4
      40: invokespecial #9                  // Method java/util/concurrent/atomic/AtomicLong."<init>":(J)V
      43: putfield      #10                 // Field lastAccessTime:Ljava/util/concurrent/atomic/AtomicLong;
      46: return

  public long getLastAccessTime();
    Code:
       0: aload_0
       1: getfield      #10                 // Field lastAccessTime:Ljava/util/concurrent/atomic/AtomicLong;
       4: invokevirtual #11                 // Method java/util/concurrent/atomic/AtomicLong.get:()J
       7: lreturn

  public void setLastAccessTime(long);
    Code:
       0: aload_0
       1: getfield      #10                 // Field lastAccessTime:Ljava/util/concurrent/atomic/AtomicLong;
       4: lload_1
       5: invokevirtual #12                 // Method java/util/concurrent/atomic/AtomicLong.set:(J)V
       8: return

  public K getKey();
    Code:
       0: aload_0
       1: getfield      #6                  // Field key:Ljava/lang/Object;
       4: areturn

  public V getValue();
    Code:
       0: aload_0
       1: getfield      #7                  // Field value:Ljava/lang/Object;
       4: areturn

  public boolean equals(java.lang.Object);
    Code:
       0: aload_0
       1: aload_1
       2: if_acmpne     7
       5: iconst_1
       6: ireturn
       7: aload_0
       8: getfield      #7                  // Field value:Ljava/lang/Object;
      11: aload_1
      12: invokevirtual #13                 // Method java/lang/Object.equals:(Ljava/lang/Object;)Z
      15: ireturn

  public int hashCode();
    Code:
       0: aload_0
       1: getfield      #7                  // Field value:Ljava/lang/Object;
       4: invokevirtual #14                 // Method java/lang/Object.hashCode:()I
       7: ireturn

  public java.lang.String toString();
    Code:
       0: new           #15                 // class java/lang/StringBuilder
       3: dup
       4: invokespecial #16                 // Method java/lang/StringBuilder."<init>":()V
       7: ldc           #17                 // String ExpiryObject{key=
       9: invokevirtual #18                 // Method java/lang/StringBuilder.append:(Ljava/lang/String;)Ljava/lang/StringBuilder;
      12: aload_0
      13: getfield      #6                  // Field key:Ljava/lang/Object;
      16: invokevirtual #19                 // Method java/lang/StringBuilder.append:(Ljava/lang/Object;)Ljava/lang/StringBuilder;
      19: ldc           #20                 // String , value=
      21: invokevirtual #18                 // Method java/lang/StringBuilder.append:(Ljava/lang/String;)Ljava/lang/StringBuilder;
      24: aload_0
      25: getfield      #7                  // Field value:Ljava/lang/Object;
      28: invokevirtual #19                 // Method java/lang/StringBuilder.append:(Ljava/lang/Object;)Ljava/lang/StringBuilder;
      31: ldc           #21                 // String , lastAccessTime=
      33: invokevirtual #18                 // Method java/lang/StringBuilder.append:(Ljava/lang/String;)Ljava/lang/StringBuilder;
      36: aload_0
      37: getfield      #10                 // Field lastAccessTime:Ljava/util/concurrent/atomic/AtomicLong;
      40: invokevirtual #19                 // Method java/lang/StringBuilder.append:(Ljava/lang/Object;)Ljava/lang/StringBuilder;
      43: bipush        125
      45: invokevirtual #22                 // Method java/lang/StringBuilder.append:(C)Ljava/lang/StringBuilder;
      48: invokevirtual #23                 // Method java/lang/StringBuilder.toString:()Ljava/lang/String;
      51: areturn
}
