Compiled from "ExpiringCache.java"
public class org.apache.dubbo.cache.support.expiring.ExpiringCache implements org.apache.dubbo.cache.Cache {
  private final java.util.Map<java.lang.Object, java.lang.Object> store;

  public org.apache.dubbo.cache.support.expiring.ExpiringCache(org.apache.dubbo.common.URL);
    Code:
       0: aload_0
       1: invokespecial #1                  // Method java/lang/Object."<init>":()V
       4: aload_1
       5: ldc           #2                  // String cache.seconds
       7: sipush        180
      10: invokevirtual #3                  // Method org/apache/dubbo/common/URL.getParameter:(Ljava/lang/String;I)I
      13: istore_2
      14: aload_1
      15: ldc           #4                  // String cache.interval
      17: iconst_4
      18: invokevirtual #3                  // Method org/apache/dubbo/common/URL.getParameter:(Ljava/lang/String;I)I
      21: istore_3
      22: new           #5                  // class org/apache/dubbo/cache/support/expiring/ExpiringMap
      25: dup
      26: iload_2
      27: iload_3
      28: invokespecial #6                  // Method org/apache/dubbo/cache/support/expiring/ExpiringMap."<init>":(II)V
      31: astore        4
      33: aload         4
      35: invokevirtual #7                  // Method org/apache/dubbo/cache/support/expiring/ExpiringMap.getExpireThread:()Lorg/apache/dubbo/cache/support/expiring/ExpiringMap$ExpireThread;
      38: invokevirtual #8                  // Method org/apache/dubbo/cache/support/expiring/ExpiringMap$ExpireThread.startExpiryIfNotStarted:()V
      41: aload_0
      42: aload         4
      44: putfield      #9                  // Field store:Ljava/util/Map;
      47: return

  public void put(java.lang.Object, java.lang.Object);
    Code:
       0: aload_0
       1: getfield      #9                  // Field store:Ljava/util/Map;
       4: aload_1
       5: aload_2
       6: invokeinterface #10,  3           // InterfaceMethod java/util/Map.put:(Ljava/lang/Object;Ljava/lang/Object;)Ljava/lang/Object;
      11: pop
      12: return

  public java.lang.Object get(java.lang.Object);
    Code:
       0: aload_0
       1: getfield      #9                  // Field store:Ljava/util/Map;
       4: aload_1
       5: invokeinterface #11,  2           // InterfaceMethod java/util/Map.get:(Ljava/lang/Object;)Ljava/lang/Object;
      10: areturn
}
