Compiled from "ColorConverter.java"
public class org.springframework.boot.logging.logback.ColorConverter extends ch.qos.logback.core.pattern.CompositeConverter<ch.qos.logback.classic.spi.ILoggingEvent> {
  private static final java.util.Map<java.lang.String, org.springframework.boot.ansi.AnsiElement> ELEMENTS;

  private static final java.util.Map<java.lang.Integer, org.springframework.boot.ansi.AnsiElement> LEVELS;

  public org.springframework.boot.logging.logback.ColorConverter();
    Code:
       0: aload_0
       1: invokespecial #1                  // Method ch/qos/logback/core/pattern/CompositeConverter."<init>":()V
       4: return

  protected java.lang.String transform(ch.qos.logback.classic.spi.ILoggingEvent, java.lang.String);
    Code:
       0: getstatic     #7                  // Field ELEMENTS:Ljava/util/Map;
       3: aload_0
       4: invokevirtual #13                 // Method getFirstOption:()Ljava/lang/String;
       7: invokeinterface #17,  2           // InterfaceMethod java/util/Map.get:(Ljava/lang/Object;)Ljava/lang/Object;
      12: checkcast     #23                 // class org/springframework/boot/ansi/AnsiElement
      15: astore_3
      16: aload_3
      17: ifnonnull     53
      20: getstatic     #25                 // Field LEVELS:Ljava/util/Map;
      23: aload_1
      24: invokeinterface #28,  1           // InterfaceMethod ch/qos/logback/classic/spi/ILoggingEvent.getLevel:()Lch/qos/logback/classic/Level;
      29: invokevirtual #34                 // Method ch/qos/logback/classic/Level.toInteger:()Ljava/lang/Integer;
      32: invokeinterface #17,  2           // InterfaceMethod java/util/Map.get:(Ljava/lang/Object;)Ljava/lang/Object;
      37: checkcast     #23                 // class org/springframework/boot/ansi/AnsiElement
      40: astore_3
      41: aload_3
      42: ifnull        49
      45: aload_3
      46: goto          52
      49: getstatic     #40                 // Field org/springframework/boot/ansi/AnsiColor.GREEN:Lorg/springframework/boot/ansi/AnsiColor;
      52: astore_3
      53: aload_0
      54: aload_2
      55: aload_3
      56: invokevirtual #46                 // Method toAnsiString:(Ljava/lang/String;Lorg/springframework/boot/ansi/AnsiElement;)Ljava/lang/String;
      59: areturn

  protected java.lang.String toAnsiString(java.lang.String, org.springframework.boot.ansi.AnsiElement);
    Code:
       0: iconst_2
       1: anewarray     #50                 // class java/lang/Object
       4: dup
       5: iconst_0
       6: aload_2
       7: aastore
       8: dup
       9: iconst_1
      10: aload_1
      11: aastore
      12: invokestatic  #52                 // Method org/springframework/boot/ansi/AnsiOutput.toString:([Ljava/lang/Object;)Ljava/lang/String;
      15: areturn

  protected java.lang.String transform(java.lang.Object, java.lang.String);
    Code:
       0: aload_0
       1: aload_1
       2: checkcast     #29                 // class ch/qos/logback/classic/spi/ILoggingEvent
       5: aload_2
       6: invokevirtual #58                 // Method transform:(Lch/qos/logback/classic/spi/ILoggingEvent;Ljava/lang/String;)Ljava/lang/String;
       9: areturn

  static {};
    Code:
       0: new           #62                 // class java/util/HashMap
       3: dup
       4: invokespecial #64                 // Method java/util/HashMap."<init>":()V
       7: astore_0
       8: aload_0
       9: ldc           #65                 // String black
      11: getstatic     #67                 // Field org/springframework/boot/ansi/AnsiColor.BLACK:Lorg/springframework/boot/ansi/AnsiColor;
      14: invokeinterface #70,  3           // InterfaceMethod java/util/Map.put:(Ljava/lang/Object;Ljava/lang/Object;)Ljava/lang/Object;
      19: pop
      20: aload_0
      21: ldc           #74                 // String white
      23: getstatic     #76                 // Field org/springframework/boot/ansi/AnsiColor.WHITE:Lorg/springframework/boot/ansi/AnsiColor;
      26: invokeinterface #70,  3           // InterfaceMethod java/util/Map.put:(Ljava/lang/Object;Ljava/lang/Object;)Ljava/lang/Object;
      31: pop
      32: aload_0
      33: ldc           #79                 // String faint
      35: getstatic     #81                 // Field org/springframework/boot/ansi/AnsiStyle.FAINT:Lorg/springframework/boot/ansi/AnsiStyle;
      38: invokeinterface #70,  3           // InterfaceMethod java/util/Map.put:(Ljava/lang/Object;Ljava/lang/Object;)Ljava/lang/Object;
      43: pop
      44: aload_0
      45: ldc           #87                 // String red
      47: getstatic     #89                 // Field org/springframework/boot/ansi/AnsiColor.RED:Lorg/springframework/boot/ansi/AnsiColor;
      50: invokeinterface #70,  3           // InterfaceMethod java/util/Map.put:(Ljava/lang/Object;Ljava/lang/Object;)Ljava/lang/Object;
      55: pop
      56: aload_0
      57: ldc           #92                 // String green
      59: getstatic     #40                 // Field org/springframework/boot/ansi/AnsiColor.GREEN:Lorg/springframework/boot/ansi/AnsiColor;
      62: invokeinterface #70,  3           // InterfaceMethod java/util/Map.put:(Ljava/lang/Object;Ljava/lang/Object;)Ljava/lang/Object;
      67: pop
      68: aload_0
      69: ldc           #94                 // String yellow
      71: getstatic     #96                 // Field org/springframework/boot/ansi/AnsiColor.YELLOW:Lorg/springframework/boot/ansi/AnsiColor;
      74: invokeinterface #70,  3           // InterfaceMethod java/util/Map.put:(Ljava/lang/Object;Ljava/lang/Object;)Ljava/lang/Object;
      79: pop
      80: aload_0
      81: ldc           #99                 // String blue
      83: getstatic     #101                // Field org/springframework/boot/ansi/AnsiColor.BLUE:Lorg/springframework/boot/ansi/AnsiColor;
      86: invokeinterface #70,  3           // InterfaceMethod java/util/Map.put:(Ljava/lang/Object;Ljava/lang/Object;)Ljava/lang/Object;
      91: pop
      92: aload_0
      93: ldc           #104                // String magenta
      95: getstatic     #106                // Field org/springframework/boot/ansi/AnsiColor.MAGENTA:Lorg/springframework/boot/ansi/AnsiColor;
      98: invokeinterface #70,  3           // InterfaceMethod java/util/Map.put:(Ljava/lang/Object;Ljava/lang/Object;)Ljava/lang/Object;
     103: pop
     104: aload_0
     105: ldc           #109                // String cyan
     107: getstatic     #111                // Field org/springframework/boot/ansi/AnsiColor.CYAN:Lorg/springframework/boot/ansi/AnsiColor;
     110: invokeinterface #70,  3           // InterfaceMethod java/util/Map.put:(Ljava/lang/Object;Ljava/lang/Object;)Ljava/lang/Object;
     115: pop
     116: aload_0
     117: ldc           #114                // String bright_black
     119: getstatic     #116                // Field org/springframework/boot/ansi/AnsiColor.BRIGHT_BLACK:Lorg/springframework/boot/ansi/AnsiColor;
     122: invokeinterface #70,  3           // InterfaceMethod java/util/Map.put:(Ljava/lang/Object;Ljava/lang/Object;)Ljava/lang/Object;
     127: pop
     128: aload_0
     129: ldc           #119                // String bright_white
     131: getstatic     #121                // Field org/springframework/boot/ansi/AnsiColor.BRIGHT_WHITE:Lorg/springframework/boot/ansi/AnsiColor;
     134: invokeinterface #70,  3           // InterfaceMethod java/util/Map.put:(Ljava/lang/Object;Ljava/lang/Object;)Ljava/lang/Object;
     139: pop
     140: aload_0
     141: ldc           #124                // String bright_red
     143: getstatic     #126                // Field org/springframework/boot/ansi/AnsiColor.BRIGHT_RED:Lorg/springframework/boot/ansi/AnsiColor;
     146: invokeinterface #70,  3           // InterfaceMethod java/util/Map.put:(Ljava/lang/Object;Ljava/lang/Object;)Ljava/lang/Object;
     151: pop
     152: aload_0
     153: ldc           #129                // String bright_green
     155: getstatic     #131                // Field org/springframework/boot/ansi/AnsiColor.BRIGHT_GREEN:Lorg/springframework/boot/ansi/AnsiColor;
     158: invokeinterface #70,  3           // InterfaceMethod java/util/Map.put:(Ljava/lang/Object;Ljava/lang/Object;)Ljava/lang/Object;
     163: pop
     164: aload_0
     165: ldc           #134                // String bright_yellow
     167: getstatic     #136                // Field org/springframework/boot/ansi/AnsiColor.BRIGHT_YELLOW:Lorg/springframework/boot/ansi/AnsiColor;
     170: invokeinterface #70,  3           // InterfaceMethod java/util/Map.put:(Ljava/lang/Object;Ljava/lang/Object;)Ljava/lang/Object;
     175: pop
     176: aload_0
     177: ldc           #139                // String bright_blue
     179: getstatic     #141                // Field org/springframework/boot/ansi/AnsiColor.BRIGHT_BLUE:Lorg/springframework/boot/ansi/AnsiColor;
     182: invokeinterface #70,  3           // InterfaceMethod java/util/Map.put:(Ljava/lang/Object;Ljava/lang/Object;)Ljava/lang/Object;
     187: pop
     188: aload_0
     189: ldc           #144                // String bright_magenta
     191: getstatic     #146                // Field org/springframework/boot/ansi/AnsiColor.BRIGHT_MAGENTA:Lorg/springframework/boot/ansi/AnsiColor;
     194: invokeinterface #70,  3           // InterfaceMethod java/util/Map.put:(Ljava/lang/Object;Ljava/lang/Object;)Ljava/lang/Object;
     199: pop
     200: aload_0
     201: ldc           #149                // String bright_cyan
     203: getstatic     #151                // Field org/springframework/boot/ansi/AnsiColor.BRIGHT_CYAN:Lorg/springframework/boot/ansi/AnsiColor;
     206: invokeinterface #70,  3           // InterfaceMethod java/util/Map.put:(Ljava/lang/Object;Ljava/lang/Object;)Ljava/lang/Object;
     211: pop
     212: aload_0
     213: invokestatic  #154                // Method java/util/Collections.unmodifiableMap:(Ljava/util/Map;)Ljava/util/Map;
     216: putstatic     #7                  // Field ELEMENTS:Ljava/util/Map;
     219: new           #62                 // class java/util/HashMap
     222: dup
     223: invokespecial #64                 // Method java/util/HashMap."<init>":()V
     226: astore_0
     227: aload_0
     228: getstatic     #160                // Field ch/qos/logback/classic/Level.ERROR_INTEGER:Ljava/lang/Integer;
     231: getstatic     #89                 // Field org/springframework/boot/ansi/AnsiColor.RED:Lorg/springframework/boot/ansi/AnsiColor;
     234: invokeinterface #70,  3           // InterfaceMethod java/util/Map.put:(Ljava/lang/Object;Ljava/lang/Object;)Ljava/lang/Object;
     239: pop
     240: aload_0
     241: getstatic     #164                // Field ch/qos/logback/classic/Level.WARN_INTEGER:Ljava/lang/Integer;
     244: getstatic     #96                 // Field org/springframework/boot/ansi/AnsiColor.YELLOW:Lorg/springframework/boot/ansi/AnsiColor;
     247: invokeinterface #70,  3           // InterfaceMethod java/util/Map.put:(Ljava/lang/Object;Ljava/lang/Object;)Ljava/lang/Object;
     252: pop
     253: aload_0
     254: invokestatic  #154                // Method java/util/Collections.unmodifiableMap:(Ljava/util/Map;)Ljava/util/Map;
     257: putstatic     #25                 // Field LEVELS:Ljava/util/Map;
     260: return
}
