Compiled from "LogbackRuntimeHints.java"
class org.springframework.boot.logging.logback.LogbackRuntimeHints implements org.springframework.aot.hint.RuntimeHintsRegistrar {
  org.springframework.boot.logging.logback.LogbackRuntimeHints();
    Code:
       0: aload_0
       1: invokespecial #1                  // Method java/lang/Object."<init>":()V
       4: return

  public void registerHints(org.springframework.aot.hint.RuntimeHints, java.lang.ClassLoader);
    Code:
       0: ldc           #7                  // String ch.qos.logback.classic.LoggerContext
       2: aload_2
       3: invokestatic  #9                  // Method org/springframework/util/ClassUtils.isPresent:(Ljava/lang/String;Ljava/lang/ClassLoader;)Z
       6: ifne          10
       9: return
      10: aload_1
      11: invokevirtual #15                 // Method org/springframework/aot/hint/RuntimeHints.reflection:()Lorg/springframework/aot/hint/ReflectionHints;
      14: astore_3
      15: aload_0
      16: aload_3
      17: aload_2
      18: invokevirtual #21                 // Method registerHintsForLogbackLoggingSystemTypeChecks:(Lorg/springframework/aot/hint/ReflectionHints;Ljava/lang/ClassLoader;)V
      21: aload_0
      22: aload_3
      23: invokevirtual #27                 // Method registerHintsForBuiltInLogbackConverters:(Lorg/springframework/aot/hint/ReflectionHints;)V
      26: aload_0
      27: aload_3
      28: invokevirtual #31                 // Method registerHintsForSpringBootConverters:(Lorg/springframework/aot/hint/ReflectionHints;)V
      31: return

  private void registerHintsForLogbackLoggingSystemTypeChecks(org.springframework.aot.hint.ReflectionHints, java.lang.ClassLoader);
    Code:
       0: aload_1
       1: ldc           #34                 // class ch/qos/logback/classic/LoggerContext
       3: iconst_0
       4: anewarray     #36                 // class org/springframework/aot/hint/MemberCategory
       7: invokevirtual #38                 // Method org/springframework/aot/hint/ReflectionHints.registerType:(Ljava/lang/Class;[Lorg/springframework/aot/hint/MemberCategory;)Lorg/springframework/aot/hint/ReflectionHints;
      10: pop
      11: aload_1
      12: aload_2
      13: ldc           #44                 // String org.slf4j.bridge.SLF4JBridgeHandler
      15: invokedynamic #46,  0             // InvokeDynamic #0:accept:()Ljava/util/function/Consumer;
      20: invokevirtual #50                 // Method org/springframework/aot/hint/ReflectionHints.registerTypeIfPresent:(Ljava/lang/ClassLoader;Ljava/lang/String;Ljava/util/function/Consumer;)Lorg/springframework/aot/hint/ReflectionHints;
      23: pop
      24: return

  private void registerHintsForBuiltInLogbackConverters(org.springframework.aot.hint.ReflectionHints);
    Code:
       0: aload_0
       1: aload_1
       2: iconst_3
       3: anewarray     #54                 // class java/lang/Class
       6: dup
       7: iconst_0
       8: ldc           #56                 // class ch/qos/logback/core/rolling/helper/DateTokenConverter
      10: aastore
      11: dup
      12: iconst_1
      13: ldc           #58                 // class ch/qos/logback/core/rolling/helper/IntegerTokenConverter
      15: aastore
      16: dup
      17: iconst_2
      18: ldc           #60                 // class ch/qos/logback/classic/pattern/SyslogStartConverter
      20: aastore
      21: invokevirtual #62                 // Method registerForPublicConstructorInvocation:(Lorg/springframework/aot/hint/ReflectionHints;[Ljava/lang/Class;)V
      24: return

  private void registerHintsForSpringBootConverters(org.springframework.aot.hint.ReflectionHints);
    Code:
       0: aload_0
       1: aload_1
       2: iconst_3
       3: anewarray     #54                 // class java/lang/Class
       6: dup
       7: iconst_0
       8: ldc           #66                 // class org/springframework/boot/logging/logback/ColorConverter
      10: aastore
      11: dup
      12: iconst_1
      13: ldc           #68                 // class org/springframework/boot/logging/logback/ExtendedWhitespaceThrowableProxyConverter
      15: aastore
      16: dup
      17: iconst_2
      18: ldc           #70                 // class org/springframework/boot/logging/logback/WhitespaceThrowableProxyConverter
      20: aastore
      21: invokevirtual #62                 // Method registerForPublicConstructorInvocation:(Lorg/springframework/aot/hint/ReflectionHints;[Ljava/lang/Class;)V
      24: return

  private void registerForPublicConstructorInvocation(org.springframework.aot.hint.ReflectionHints, java.lang.Class<?>...);
    Code:
       0: aload_1
       1: aload_2
       2: invokestatic  #72                 // InterfaceMethod org/springframework/aot/hint/TypeReference.listOf:([Ljava/lang/Class;)Ljava/util/List;
       5: invokedynamic #78,  0             // InvokeDynamic #1:accept:()Ljava/util/function/Consumer;
      10: invokevirtual #79                 // Method org/springframework/aot/hint/ReflectionHints.registerTypes:(Ljava/lang/Iterable;Ljava/util/function/Consumer;)Lorg/springframework/aot/hint/ReflectionHints;
      13: pop
      14: return

  private static void lambda$registerForPublicConstructorInvocation$1(org.springframework.aot.hint.TypeHint$Builder);
    Code:
       0: aload_0
       1: iconst_1
       2: anewarray     #36                 // class org/springframework/aot/hint/MemberCategory
       5: dup
       6: iconst_0
       7: getstatic     #83                 // Field org/springframework/aot/hint/MemberCategory.INVOKE_PUBLIC_CONSTRUCTORS:Lorg/springframework/aot/hint/MemberCategory;
      10: aastore
      11: invokevirtual #87                 // Method org/springframework/aot/hint/TypeHint$Builder.withMembers:([Lorg/springframework/aot/hint/MemberCategory;)Lorg/springframework/aot/hint/TypeHint$Builder;
      14: pop
      15: return

  private static void lambda$registerHintsForLogbackLoggingSystemTypeChecks$0(org.springframework.aot.hint.TypeHint$Builder);
    Code:
       0: return
}
