Compiled from "RootLogLevelConfigurator.java"
public class org.springframework.boot.logging.logback.RootLogLevelConfigurator extends ch.qos.logback.core.spi.ContextAwareBase implements ch.qos.logback.classic.spi.Configurator {
  public org.springframework.boot.logging.logback.RootLogLevelConfigurator();
    Code:
       0: aload_0
       1: invokespecial #1                  // Method ch/qos/logback/core/spi/ContextAwareBase."<init>":()V
       4: return

  public ch.qos.logback.classic.spi.Configurator$ExecutionStatus configure(ch.qos.logback.classic.LoggerContext);
    Code:
       0: aload_1
       1: ldc           #9                  // String ROOT
       3: invokevirtual #11                 // Method ch/qos/logback/classic/LoggerContext.getLogger:(Ljava/lang/String;)Lch/qos/logback/classic/Logger;
       6: getstatic     #17                 // Field ch/qos/logback/classic/Level.INFO:Lch/qos/logback/classic/Level;
       9: invokevirtual #23                 // Method ch/qos/logback/classic/Logger.setLevel:(Lch/qos/logback/classic/Level;)V
      12: getstatic     #29                 // Field ch/qos/logback/classic/spi/Configurator$ExecutionStatus.INVOKE_NEXT_IF_ANY:Lch/qos/logback/classic/spi/Configurator$ExecutionStatus;
      15: areturn
}
