Compiled from "SpringProfileModelHandler.java"
class org.springframework.boot.logging.logback.SpringProfileModelHandler extends ch.qos.logback.core.model.processor.ModelHandlerBase {
  private final org.springframework.core.env.Environment environment;

  org.springframework.boot.logging.logback.SpringProfileModelHandler(ch.qos.logback.core.Context, org.springframework.core.env.Environment);
    Code:
       0: aload_0
       1: aload_1
       2: invokespecial #1                  // Method ch/qos/logback/core/model/processor/ModelHandlerBase."<init>":(Lch/qos/logback/core/Context;)V
       5: aload_0
       6: aload_2
       7: putfield      #7                  // Field environment:Lorg/springframework/core/env/Environment;
      10: return

  public void handle(ch.qos.logback.core.model.processor.ModelInterpretationContext, ch.qos.logback.core.model.Model) throws ch.qos.logback.core.model.processor.ModelHandlerException;
    Code:
       0: aload_2
       1: checkcast     #13                 // class org/springframework/boot/logging/logback/SpringProfileModel
       4: astore_3
       5: aload_0
       6: aload_1
       7: aload_3
       8: invokevirtual #15                 // Method acceptsProfiles:(Lch/qos/logback/core/model/processor/ModelInterpretationContext;Lorg/springframework/boot/logging/logback/SpringProfileModel;)Z
      11: ifne          18
      14: aload_2
      15: invokevirtual #19                 // Method ch/qos/logback/core/model/Model.deepMarkAsSkipped:()V
      18: return

  private boolean acceptsProfiles(ch.qos.logback.core.model.processor.ModelInterpretationContext, org.springframework.boot.logging.logback.SpringProfileModel);
    Code:
       0: aload_0
       1: getfield      #7                  // Field environment:Lorg/springframework/core/env/Environment;
       4: ifnonnull     9
       7: iconst_0
       8: ireturn
       9: aload_2
      10: invokevirtual #25                 // Method org/springframework/boot/logging/logback/SpringProfileModel.getName:()Ljava/lang/String;
      13: invokestatic  #29                 // Method org/springframework/util/StringUtils.commaDelimitedListToStringArray:(Ljava/lang/String;)[Ljava/lang/String;
      16: invokestatic  #35                 // Method org/springframework/util/StringUtils.trimArrayElements:([Ljava/lang/String;)[Ljava/lang/String;
      19: astore_3
      20: aload_3
      21: arraylength
      22: ifne          27
      25: iconst_0
      26: ireturn
      27: iconst_0
      28: istore        4
      30: iload         4
      32: aload_3
      33: arraylength
      34: if_icmpge     74
      37: aload_3
      38: iload         4
      40: aload_3
      41: iload         4
      43: aaload
      44: aload_1
      45: aload_0
      46: getfield      #39                 // Field context:Lch/qos/logback/core/Context;
      49: invokestatic  #43                 // Method ch/qos/logback/core/util/OptionHelper.substVars:(Ljava/lang/String;Lch/qos/logback/core/spi/PropertyContainer;Lch/qos/logback/core/spi/PropertyContainer;)Ljava/lang/String;
      52: aastore
      53: goto          68
      56: astore        5
      58: new           #51                 // class java/lang/RuntimeException
      61: dup
      62: aload         5
      64: invokespecial #53                 // Method java/lang/RuntimeException."<init>":(Ljava/lang/Throwable;)V
      67: athrow
      68: iinc          4, 1
      71: goto          30
      74: aload_0
      75: getfield      #7                  // Field environment:Lorg/springframework/core/env/Environment;
      78: aload_3
      79: invokestatic  #56                 // InterfaceMethod org/springframework/core/env/Profiles.of:([Ljava/lang/String;)Lorg/springframework/core/env/Profiles;
      82: invokeinterface #62,  2           // InterfaceMethod org/springframework/core/env/Environment.acceptsProfiles:(Lorg/springframework/core/env/Profiles;)Z
      87: ireturn
    Exception table:
       from    to  target type
          37    53    56   Class ch/qos/logback/core/spi/ScanException
}
