Compiled from "SpringBootJoranConfigurator.java"
final class org.springframework.boot.logging.logback.SpringBootJoranConfigurator$ModelWriter {
  private static final java.lang.String MODEL_RESOURCE_LOCATION;

  private final ch.qos.logback.core.model.Model model;

  private final ch.qos.logback.core.model.processor.ModelInterpretationContext modelInterpretationContext;

  private org.springframework.boot.logging.logback.SpringBootJoranConfigurator$ModelWriter(ch.qos.logback.core.model.Model, ch.qos.logback.core.model.processor.ModelInterpretationContext);
    Code:
       0: aload_0
       1: invokespecial #1                  // Method java/lang/Object."<init>":()V
       4: aload_0
       5: aload_1
       6: putfield      #7                  // Field model:Lch/qos/logback/core/model/Model;
       9: aload_0
      10: aload_2
      11: putfield      #13                 // Field modelInterpretationContext:Lch/qos/logback/core/model/processor/ModelInterpretationContext;
      14: return

  private void writeTo(org.springframework.aot.generate.GenerationContext);
    Code:
       0: new           #17                 // class java/io/ByteArrayOutputStream
       3: dup
       4: invokespecial #19                 // Method java/io/ByteArrayOutputStream."<init>":()V
       7: astore_2
       8: new           #20                 // class java/io/ObjectOutputStream
      11: dup
      12: aload_2
      13: invokespecial #22                 // Method java/io/ObjectOutputStream."<init>":(Ljava/io/OutputStream;)V
      16: astore_3
      17: aload_3
      18: aload_0
      19: getfield      #7                  // Field model:Lch/qos/logback/core/model/Model;
      22: invokevirtual #25                 // Method java/io/ObjectOutputStream.writeObject:(Ljava/lang/Object;)V
      25: aload_3
      26: invokevirtual #29                 // Method java/io/ObjectOutputStream.close:()V
      29: goto          53
      32: astore        4
      34: aload_3
      35: invokevirtual #29                 // Method java/io/ObjectOutputStream.close:()V
      38: goto          50
      41: astore        5
      43: aload         4
      45: aload         5
      47: invokevirtual #34                 // Method java/lang/Throwable.addSuppressed:(Ljava/lang/Throwable;)V
      50: aload         4
      52: athrow
      53: goto          66
      56: astore_3
      57: new           #40                 // class java/lang/RuntimeException
      60: dup
      61: aload_3
      62: invokespecial #42                 // Method java/lang/RuntimeException."<init>":(Ljava/lang/Throwable;)V
      65: athrow
      66: new           #44                 // class org/springframework/core/io/ByteArrayResource
      69: dup
      70: aload_2
      71: invokevirtual #46                 // Method java/io/ByteArrayOutputStream.toByteArray:()[B
      74: invokespecial #50                 // Method org/springframework/core/io/ByteArrayResource."<init>":([B)V
      77: astore_3
      78: aload_1
      79: invokeinterface #53,  1           // InterfaceMethod org/springframework/aot/generate/GenerationContext.getGeneratedFiles:()Lorg/springframework/aot/generate/GeneratedFiles;
      84: ldc           #59                 // String META-INF/spring/logback-model
      86: aload_3
      87: invokeinterface #61,  3           // InterfaceMethod org/springframework/aot/generate/GeneratedFiles.addResourceFile:(Ljava/lang/String;Lorg/springframework/core/io/InputStreamSource;)V
      92: aload_1
      93: invokeinterface #67,  1           // InterfaceMethod org/springframework/aot/generate/GenerationContext.getRuntimeHints:()Lorg/springframework/aot/hint/RuntimeHints;
      98: invokevirtual #71                 // Method org/springframework/aot/hint/RuntimeHints.resources:()Lorg/springframework/aot/hint/ResourceHints;
     101: ldc           #59                 // String META-INF/spring/logback-model
     103: invokevirtual #77                 // Method org/springframework/aot/hint/ResourceHints.registerPattern:(Ljava/lang/String;)Lorg/springframework/aot/hint/ResourceHints;
     106: pop
     107: aload_1
     108: invokeinterface #67,  1           // InterfaceMethod org/springframework/aot/generate/GenerationContext.getRuntimeHints:()Lorg/springframework/aot/hint/RuntimeHints;
     113: invokevirtual #83                 // Method org/springframework/aot/hint/RuntimeHints.serialization:()Lorg/springframework/aot/hint/SerializationHints;
     116: astore        4
     118: aload_0
     119: aload_0
     120: getfield      #7                  // Field model:Lch/qos/logback/core/model/Model;
     123: invokevirtual #87                 // Method serializationTypes:(Lch/qos/logback/core/model/Model;)Ljava/util/Set;
     126: aload         4
     128: dup
     129: invokestatic  #91                 // Method java/util/Objects.requireNonNull:(Ljava/lang/Object;)Ljava/lang/Object;
     132: pop
     133: invokedynamic #97,  0             // InvokeDynamic #0:accept:(Lorg/springframework/aot/hint/SerializationHints;)Ljava/util/function/Consumer;
     138: invokeinterface #101,  2          // InterfaceMethod java/util/Set.forEach:(Ljava/util/function/Consumer;)V
     143: aload_0
     144: aload_0
     145: getfield      #7                  // Field model:Lch/qos/logback/core/model/Model;
     148: invokevirtual #107                // Method reflectionTypes:(Lch/qos/logback/core/model/Model;)Ljava/util/Set;
     151: aload_1
     152: invokedynamic #110,  0            // InvokeDynamic #1:accept:(Lorg/springframework/aot/generate/GenerationContext;)Ljava/util/function/Consumer;
     157: invokeinterface #101,  2          // InterfaceMethod java/util/Set.forEach:(Ljava/util/function/Consumer;)V
     162: return
    Exception table:
       from    to  target type
          17    25    32   Class java/lang/Throwable
          34    38    41   Class java/lang/Throwable
           8    53    56   Class java/io/IOException

  private java.util.Set<java.lang.Class<? extends java.io.Serializable>> serializationTypes(ch.qos.logback.core.model.Model);
    Code:
       0: new           #113                // class java/util/HashSet
       3: dup
       4: invokespecial #115                // Method java/util/HashSet."<init>":()V
       7: astore_2
       8: aload_1
       9: invokevirtual #116                // Method java/lang/Object.getClass:()Ljava/lang/Class;
      12: astore_3
      13: ldc           #120                // class ch/qos/logback/core/model/Model
      15: aload_3
      16: invokevirtual #122                // Method java/lang/Class.isAssignableFrom:(Ljava/lang/Class;)Z
      19: ifeq          51
      22: aload_2
      23: aload_3
      24: invokeinterface #128,  2          // InterfaceMethod java/util/Set.add:(Ljava/lang/Object;)Z
      29: ifeq          13
      32: aload_3
      33: aload_1
      34: aload_2
      35: invokedynamic #132,  0            // InvokeDynamic #2:doWith:(Lch/qos/logback/core/model/Model;Ljava/util/Set;)Lorg/springframework/util/ReflectionUtils$FieldCallback;
      40: invokestatic  #136                // Method org/springframework/util/ReflectionUtils.doWithFields:(Ljava/lang/Class;Lorg/springframework/util/ReflectionUtils$FieldCallback;)V
      43: aload_3
      44: invokevirtual #142                // Method java/lang/Class.getSuperclass:()Ljava/lang/Class;
      47: astore_3
      48: goto          13
      51: aload_1
      52: invokevirtual #145                // Method ch/qos/logback/core/model/Model.getSubModels:()Ljava/util/List;
      55: invokeinterface #149,  1          // InterfaceMethod java/util/List.iterator:()Ljava/util/Iterator;
      60: astore        4
      62: aload         4
      64: invokeinterface #155,  1          // InterfaceMethod java/util/Iterator.hasNext:()Z
      69: ifeq          100
      72: aload         4
      74: invokeinterface #161,  1          // InterfaceMethod java/util/Iterator.next:()Ljava/lang/Object;
      79: checkcast     #120                // class ch/qos/logback/core/model/Model
      82: astore        5
      84: aload_2
      85: aload_0
      86: aload         5
      88: invokevirtual #87                 // Method serializationTypes:(Lch/qos/logback/core/model/Model;)Ljava/util/Set;
      91: invokeinterface #165,  2          // InterfaceMethod java/util/Set.addAll:(Ljava/util/Collection;)Z
      96: pop
      97: goto          62
     100: aload_2
     101: areturn

  private java.util.Set<java.lang.String> reflectionTypes(ch.qos.logback.core.model.Model);
    Code:
       0: aload_0
       1: aload_1
       2: invokedynamic #169,  0            // InvokeDynamic #3:get:()Ljava/util/function/Supplier;
       7: invokevirtual #173                // Method reflectionTypes:(Lch/qos/logback/core/model/Model;Ljava/util/function/Supplier;)Ljava/util/Set;
      10: areturn

  private java.util.Set<java.lang.String> reflectionTypes(ch.qos.logback.core.model.Model, java.util.function.Supplier<java.lang.Object>);
    Code:
       0: new           #113                // class java/util/HashSet
       3: dup
       4: invokespecial #115                // Method java/util/HashSet."<init>":()V
       7: astore_3
       8: aload_0
       9: aload_1
      10: aload_2
      11: invokevirtual #176                // Method determineType:(Lch/qos/logback/core/model/Model;Ljava/util/function/Supplier;)Ljava/lang/Class;
      14: astore        4
      16: aload         4
      18: ifnull        28
      21: aload_0
      22: aload         4
      24: aload_3
      25: invokevirtual #180                // Method processComponent:(Ljava/lang/Class;Ljava/util/Set;)V
      28: aload_0
      29: aload         4
      31: invokedynamic #184,  0            // InvokeDynamic #4:get:(Lorg/springframework/boot/logging/logback/SpringBootJoranConfigurator$ModelWriter;Ljava/lang/Class;)Ljava/util/function/Supplier;
      36: invokestatic  #187                // Method org/springframework/util/function/SingletonSupplier.ofNullable:(Ljava/util/function/Supplier;)Lorg/springframework/util/function/SingletonSupplier;
      39: astore        5
      41: aload_1
      42: invokevirtual #145                // Method ch/qos/logback/core/model/Model.getSubModels:()Ljava/util/List;
      45: invokeinterface #149,  1          // InterfaceMethod java/util/List.iterator:()Ljava/util/Iterator;
      50: astore        6
      52: aload         6
      54: invokeinterface #155,  1          // InterfaceMethod java/util/Iterator.hasNext:()Z
      59: ifeq          92
      62: aload         6
      64: invokeinterface #161,  1          // InterfaceMethod java/util/Iterator.next:()Ljava/lang/Object;
      69: checkcast     #120                // class ch/qos/logback/core/model/Model
      72: astore        7
      74: aload_3
      75: aload_0
      76: aload         7
      78: aload         5
      80: invokevirtual #173                // Method reflectionTypes:(Lch/qos/logback/core/model/Model;Ljava/util/function/Supplier;)Ljava/util/Set;
      83: invokeinterface #165,  2          // InterfaceMethod java/util/Set.addAll:(Ljava/util/Collection;)Z
      88: pop
      89: goto          52
      92: aload_3
      93: areturn

  private java.lang.Class<?> determineType(ch.qos.logback.core.model.Model, java.util.function.Supplier<java.lang.Object>);
    Code:
       0: aload_1
       1: instanceof    #193                // class ch/qos/logback/core/model/ComponentModel
       4: ifeq          21
       7: aload_1
       8: checkcast     #193                // class ch/qos/logback/core/model/ComponentModel
      11: astore        4
      13: aload         4
      15: invokevirtual #195                // Method ch/qos/logback/core/model/ComponentModel.getClassName:()Ljava/lang/String;
      18: goto          22
      21: aconst_null
      22: astore_3
      23: aload_3
      24: ifnull        33
      27: aload_0
      28: aload_3
      29: invokevirtual #199                // Method loadImportType:(Ljava/lang/String;)Ljava/lang/Class;
      32: areturn
      33: aload_1
      34: invokevirtual #203                // Method ch/qos/logback/core/model/Model.getTag:()Ljava/lang/String;
      37: astore        4
      39: aload         4
      41: ifnull        75
      44: aload_0
      45: getfield      #13                 // Field modelInterpretationContext:Lch/qos/logback/core/model/processor/ModelInterpretationContext;
      48: invokevirtual #206                // Method ch/qos/logback/core/model/processor/ModelInterpretationContext.getDefaultNestedComponentRegistry:()Lch/qos/logback/core/joran/spi/DefaultNestedComponentRegistry;
      51: aload         4
      53: invokevirtual #212                // Method ch/qos/logback/core/joran/spi/DefaultNestedComponentRegistry.findDefaultComponentTypeByTag:(Ljava/lang/String;)Ljava/lang/String;
      56: astore_3
      57: aload_3
      58: ifnull        67
      61: aload_0
      62: aload_3
      63: invokevirtual #199                // Method loadImportType:(Ljava/lang/String;)Ljava/lang/Class;
      66: areturn
      67: aload_0
      68: aload_2
      69: aload         4
      71: invokevirtual #218                // Method inferTypeFromParent:(Ljava/util/function/Supplier;Ljava/lang/String;)Ljava/lang/Class;
      74: areturn
      75: aconst_null
      76: areturn

  private java.lang.Class<?> loadImportType(java.lang.String);
    Code:
       0: aload_0
       1: aload_0
       2: getfield      #13                 // Field modelInterpretationContext:Lch/qos/logback/core/model/processor/ModelInterpretationContext;
       5: aload_1
       6: invokevirtual #222                // Method ch/qos/logback/core/model/processor/ModelInterpretationContext.getImport:(Ljava/lang/String;)Ljava/lang/String;
       9: invokevirtual #225                // Method loadComponentType:(Ljava/lang/String;)Ljava/lang/Class;
      12: areturn

  private java.lang.Class<?> inferTypeFromParent(java.util.function.Supplier<java.lang.Object>, java.lang.String);
    Code:
       0: aload_1
       1: invokeinterface #228,  1          // InterfaceMethod java/util/function/Supplier.get:()Ljava/lang/Object;
       6: astore_3
       7: aload_3
       8: ifnull        53
      11: new           #232                // class ch/qos/logback/core/joran/util/PropertySetter
      14: dup
      15: aload_0
      16: getfield      #13                 // Field modelInterpretationContext:Lch/qos/logback/core/model/processor/ModelInterpretationContext;
      19: invokevirtual #234                // Method ch/qos/logback/core/model/processor/ModelInterpretationContext.getBeanDescriptionCache:()Lch/qos/logback/core/joran/util/beans/BeanDescriptionCache;
      22: aload_3
      23: invokespecial #238                // Method ch/qos/logback/core/joran/util/PropertySetter."<init>":(Lch/qos/logback/core/joran/util/beans/BeanDescriptionCache;Ljava/lang/Object;)V
      26: astore        4
      28: aload         4
      30: aload_2
      31: getstatic     #241                // Field ch/qos/logback/core/util/AggregationType.AS_COMPLEX_PROPERTY:Lch/qos/logback/core/util/AggregationType;
      34: aload_0
      35: getfield      #13                 // Field modelInterpretationContext:Lch/qos/logback/core/model/processor/ModelInterpretationContext;
      38: invokevirtual #206                // Method ch/qos/logback/core/model/processor/ModelInterpretationContext.getDefaultNestedComponentRegistry:()Lch/qos/logback/core/joran/spi/DefaultNestedComponentRegistry;
      41: invokevirtual #247                // Method ch/qos/logback/core/joran/util/PropertySetter.getClassNameViaImplicitRules:(Ljava/lang/String;Lch/qos/logback/core/util/AggregationType;Lch/qos/logback/core/joran/spi/DefaultNestedComponentRegistry;)Ljava/lang/Class;
      44: astore        5
      46: aload         5
      48: areturn
      49: astore        4
      51: aconst_null
      52: areturn
      53: aconst_null
      54: areturn
    Exception table:
       from    to  target type
          11    48    49   Class java/lang/Exception

  private java.lang.Class<?> loadComponentType(java.lang.String);
    Code:
       0: aload_0
       1: getfield      #13                 // Field modelInterpretationContext:Lch/qos/logback/core/model/processor/ModelInterpretationContext;
       4: aload_1
       5: invokevirtual #253                // Method ch/qos/logback/core/model/processor/ModelInterpretationContext.subst:(Ljava/lang/String;)Ljava/lang/String;
       8: aload_0
       9: invokevirtual #116                // Method java/lang/Object.getClass:()Ljava/lang/Class;
      12: invokevirtual #256                // Method java/lang/Class.getClassLoader:()Ljava/lang/ClassLoader;
      15: invokestatic  #260                // Method org/springframework/util/ClassUtils.forName:(Ljava/lang/String;Ljava/lang/ClassLoader;)Ljava/lang/Class;
      18: areturn
      19: astore_2
      20: new           #40                 // class java/lang/RuntimeException
      23: dup
      24: aload_1
      25: invokedynamic #266,  0            // InvokeDynamic #5:makeConcatWithConstants:(Ljava/lang/String;)Ljava/lang/String;
      30: aload_2
      31: invokespecial #269                // Method java/lang/RuntimeException."<init>":(Ljava/lang/String;Ljava/lang/Throwable;)V
      34: athrow
    Exception table:
       from    to  target type
           0    18    19   Class java/lang/Throwable

  private java.lang.Object instantiate(java.lang.Class<?>);
    Code:
       0: aload_1
       1: iconst_0
       2: anewarray     #123                // class java/lang/Class
       5: invokevirtual #272                // Method java/lang/Class.getConstructor:([Ljava/lang/Class;)Ljava/lang/reflect/Constructor;
       8: iconst_0
       9: anewarray     #2                  // class java/lang/Object
      12: invokevirtual #276                // Method java/lang/reflect/Constructor.newInstance:([Ljava/lang/Object;)Ljava/lang/Object;
      15: areturn
      16: astore_2
      17: aconst_null
      18: areturn
    Exception table:
       from    to  target type
           0    15    16   Class java/lang/Exception

  private void processComponent(java.lang.Class<?>, java.util.Set<java.lang.String>);
    Code:
       0: aload_0
       1: getfield      #13                 // Field modelInterpretationContext:Lch/qos/logback/core/model/processor/ModelInterpretationContext;
       4: invokevirtual #234                // Method ch/qos/logback/core/model/processor/ModelInterpretationContext.getBeanDescriptionCache:()Lch/qos/logback/core/joran/util/beans/BeanDescriptionCache;
       7: aload_1
       8: invokevirtual #282                // Method ch/qos/logback/core/joran/util/beans/BeanDescriptionCache.getBeanDescription:(Ljava/lang/Class;)Lch/qos/logback/core/joran/util/beans/BeanDescription;
      11: astore_3
      12: aload_2
      13: aload_0
      14: aload_3
      15: invokevirtual #288                // Method ch/qos/logback/core/joran/util/beans/BeanDescription.getPropertyNameToAdder:()Ljava/util/Map;
      18: invokeinterface #294,  1          // InterfaceMethod java/util/Map.values:()Ljava/util/Collection;
      23: invokevirtual #300                // Method parameterTypesNames:(Ljava/util/Collection;)Ljava/util/Collection;
      26: invokeinterface #165,  2          // InterfaceMethod java/util/Set.addAll:(Ljava/util/Collection;)Z
      31: pop
      32: aload_2
      33: aload_0
      34: aload_3
      35: invokevirtual #304                // Method ch/qos/logback/core/joran/util/beans/BeanDescription.getPropertyNameToSetter:()Ljava/util/Map;
      38: invokeinterface #294,  1          // InterfaceMethod java/util/Map.values:()Ljava/util/Collection;
      43: invokevirtual #300                // Method parameterTypesNames:(Ljava/util/Collection;)Ljava/util/Collection;
      46: invokeinterface #165,  2          // InterfaceMethod java/util/Set.addAll:(Ljava/util/Collection;)Z
      51: pop
      52: aload_2
      53: aload_1
      54: invokevirtual #307                // Method java/lang/Class.getCanonicalName:()Ljava/lang/String;
      57: invokeinterface #128,  2          // InterfaceMethod java/util/Set.add:(Ljava/lang/Object;)Z
      62: pop
      63: return

  private java.util.Collection<java.lang.String> parameterTypesNames(java.util.Collection<java.lang.reflect.Method>);
    Code:
       0: aload_1
       1: invokeinterface #310,  1          // InterfaceMethod java/util/Collection.stream:()Ljava/util/stream/Stream;
       6: invokedynamic #316,  0            // InvokeDynamic #6:test:()Ljava/util/function/Predicate;
      11: invokeinterface #320,  2          // InterfaceMethod java/util/stream/Stream.filter:(Ljava/util/function/Predicate;)Ljava/util/stream/Stream;
      16: invokedynamic #326,  0            // InvokeDynamic #7:apply:()Ljava/util/function/Function;
      21: invokeinterface #330,  2          // InterfaceMethod java/util/stream/Stream.map:(Ljava/util/function/Function;)Ljava/util/stream/Stream;
      26: invokedynamic #334,  0            // InvokeDynamic #8:apply:()Ljava/util/function/Function;
      31: invokeinterface #335,  2          // InterfaceMethod java/util/stream/Stream.flatMap:(Ljava/util/function/Function;)Ljava/util/stream/Stream;
      36: invokedynamic #338,  0            // InvokeDynamic #9:test:()Ljava/util/function/Predicate;
      41: invokeinterface #320,  2          // InterfaceMethod java/util/stream/Stream.filter:(Ljava/util/function/Predicate;)Ljava/util/stream/Stream;
      46: invokedynamic #339,  0            // InvokeDynamic #10:apply:()Ljava/util/function/Function;
      51: invokeinterface #330,  2          // InterfaceMethod java/util/stream/Stream.map:(Ljava/util/function/Function;)Ljava/util/stream/Stream;
      56: invokedynamic #340,  0            // InvokeDynamic #11:apply:()Ljava/util/function/Function;
      61: invokeinterface #330,  2          // InterfaceMethod java/util/stream/Stream.map:(Ljava/util/function/Function;)Ljava/util/stream/Stream;
      66: invokeinterface #341,  1          // InterfaceMethod java/util/stream/Stream.toList:()Ljava/util/List;
      71: areturn

  private static java.lang.Class lambda$parameterTypesNames$6(java.lang.Class);
    Code:
       0: aload_0
       1: invokevirtual #344                // Method java/lang/Class.isArray:()Z
       4: ifeq          14
       7: aload_0
       8: invokevirtual #347                // Method java/lang/Class.getComponentType:()Ljava/lang/Class;
      11: goto          15
      14: aload_0
      15: areturn

  private static boolean lambda$parameterTypesNames$5(java.lang.Class);
    Code:
       0: aload_0
       1: invokevirtual #350                // Method java/lang/Class.isPrimitive:()Z
       4: ifne          21
       7: aload_0
       8: ldc_w         #353                // class java/lang/String
      11: invokevirtual #355                // Method java/lang/Object.equals:(Ljava/lang/Object;)Z
      14: ifne          21
      17: iconst_1
      18: goto          22
      21: iconst_0
      22: ireturn

  private static boolean lambda$parameterTypesNames$4(java.lang.reflect.Method);
    Code:
       0: aload_0
       1: invokevirtual #358                // Method java/lang/reflect/Method.getDeclaringClass:()Ljava/lang/Class;
       4: ldc_w         #363                // class ch/qos/logback/core/spi/ContextAware
       7: invokevirtual #355                // Method java/lang/Object.equals:(Ljava/lang/Object;)Z
      10: ifne          30
      13: aload_0
      14: invokevirtual #358                // Method java/lang/reflect/Method.getDeclaringClass:()Ljava/lang/Class;
      17: ldc_w         #365                // class ch/qos/logback/core/spi/ContextAwareBase
      20: invokevirtual #355                // Method java/lang/Object.equals:(Ljava/lang/Object;)Z
      23: ifne          30
      26: iconst_1
      27: goto          31
      30: iconst_0
      31: ireturn

  private java.lang.Object lambda$reflectionTypes$3(java.lang.Class);
    Code:
       0: aload_0
       1: aload_1
       2: invokevirtual #367                // Method instantiate:(Ljava/lang/Class;)Ljava/lang/Object;
       5: areturn

  private static java.lang.Object lambda$reflectionTypes$2();
    Code:
       0: aconst_null
       1: areturn

  private static void lambda$serializationTypes$1(ch.qos.logback.core.model.Model, java.util.Set, java.lang.reflect.Field) throws java.lang.IllegalArgumentException, java.lang.IllegalAccessException;
    Code:
       0: aload_2
       1: invokevirtual #371                // Method java/lang/reflect/Field.getModifiers:()I
       4: invokestatic  #377                // Method java/lang/reflect/Modifier.isStatic:(I)Z
       7: ifeq          11
      10: return
      11: aload_2
      12: invokestatic  #383                // Method org/springframework/util/ReflectionUtils.makeAccessible:(Ljava/lang/reflect/Field;)V
      15: aload_2
      16: aload_0
      17: invokevirtual #387                // Method java/lang/reflect/Field.get:(Ljava/lang/Object;)Ljava/lang/Object;
      20: astore_3
      21: aload_3
      22: ifnull        51
      25: aload_3
      26: invokevirtual #116                // Method java/lang/Object.getClass:()Ljava/lang/Class;
      29: astore        4
      31: ldc_w         #389                // class java/io/Serializable
      34: aload         4
      36: invokevirtual #122                // Method java/lang/Class.isAssignableFrom:(Ljava/lang/Class;)Z
      39: ifeq          51
      42: aload_1
      43: aload         4
      45: invokeinterface #128,  2          // InterfaceMethod java/util/Set.add:(Ljava/lang/Object;)Z
      50: pop
      51: return

  private static void lambda$writeTo$0(org.springframework.aot.generate.GenerationContext, java.lang.String);
    Code:
       0: aload_0
       1: invokeinterface #67,  1           // InterfaceMethod org/springframework/aot/generate/GenerationContext.getRuntimeHints:()Lorg/springframework/aot/hint/RuntimeHints;
       6: invokevirtual #391                // Method org/springframework/aot/hint/RuntimeHints.reflection:()Lorg/springframework/aot/hint/ReflectionHints;
       9: aload_1
      10: invokestatic  #395                // InterfaceMethod org/springframework/aot/hint/TypeReference.of:(Ljava/lang/String;)Lorg/springframework/aot/hint/TypeReference;
      13: iconst_3
      14: anewarray     #401                // class org/springframework/aot/hint/MemberCategory
      17: dup
      18: iconst_0
      19: getstatic     #403                // Field org/springframework/aot/hint/MemberCategory.INTROSPECT_PUBLIC_METHODS:Lorg/springframework/aot/hint/MemberCategory;
      22: aastore
      23: dup
      24: iconst_1
      25: getstatic     #407                // Field org/springframework/aot/hint/MemberCategory.INVOKE_PUBLIC_METHODS:Lorg/springframework/aot/hint/MemberCategory;
      28: aastore
      29: dup
      30: iconst_2
      31: getstatic     #410                // Field org/springframework/aot/hint/MemberCategory.INVOKE_PUBLIC_CONSTRUCTORS:Lorg/springframework/aot/hint/MemberCategory;
      34: aastore
      35: invokevirtual #413                // Method org/springframework/aot/hint/ReflectionHints.registerType:(Lorg/springframework/aot/hint/TypeReference;[Lorg/springframework/aot/hint/MemberCategory;)Lorg/springframework/aot/hint/ReflectionHints;
      38: pop
      39: return
}
