Compiled from "SpringPropertyModelHandler.java"
class org.springframework.boot.logging.logback.SpringPropertyModelHandler extends ch.qos.logback.core.model.processor.ModelHandlerBase {
  private final org.springframework.core.env.Environment environment;

  org.springframework.boot.logging.logback.SpringPropertyModelHandler(ch.qos.logback.core.Context, org.springframework.core.env.Environment);
    Code:
       0: aload_0
       1: aload_1
       2: invokespecial #1                  // Method ch/qos/logback/core/model/processor/ModelHandlerBase."<init>":(Lch/qos/logback/core/Context;)V
       5: aload_0
       6: aload_2
       7: putfield      #7                  // Field environment:Lorg/springframework/core/env/Environment;
      10: return

  public void handle(ch.qos.logback.core.model.processor.ModelInterpretationContext, ch.qos.logback.core.model.Model) throws ch.qos.logback.core.model.processor.ModelHandlerException;
    Code:
       0: aload_2
       1: checkcast     #13                 // class org/springframework/boot/logging/logback/SpringPropertyModel
       4: astore_3
       5: aload_3
       6: invokevirtual #15                 // Method org/springframework/boot/logging/logback/SpringPropertyModel.getScope:()Ljava/lang/String;
       9: invokestatic  #19                 // Method ch/qos/logback/core/joran/action/ActionUtil.stringToScope:(Ljava/lang/String;)Lch/qos/logback/core/joran/action/ActionUtil$Scope;
      12: astore        4
      14: aload_3
      15: invokevirtual #25                 // Method org/springframework/boot/logging/logback/SpringPropertyModel.getDefaultValue:()Ljava/lang/String;
      18: astore        5
      20: aload_3
      21: invokevirtual #28                 // Method org/springframework/boot/logging/logback/SpringPropertyModel.getSource:()Ljava/lang/String;
      24: astore        6
      26: aload_3
      27: invokevirtual #31                 // Method org/springframework/boot/logging/logback/SpringPropertyModel.getName:()Ljava/lang/String;
      30: invokestatic  #34                 // Method ch/qos/logback/core/util/OptionHelper.isNullOrEmpty:(Ljava/lang/String;)Z
      33: ifne          44
      36: aload         6
      38: invokestatic  #34                 // Method ch/qos/logback/core/util/OptionHelper.isNullOrEmpty:(Ljava/lang/String;)Z
      41: ifeq          50
      44: aload_0
      45: ldc           #40                 // String The \"name\" and \"source\" attributes of <springProperty> must be set
      47: invokevirtual #42                 // Method addError:(Ljava/lang/String;)V
      50: aload_1
      51: aload_3
      52: invokevirtual #31                 // Method org/springframework/boot/logging/logback/SpringPropertyModel.getName:()Ljava/lang/String;
      55: aload_0
      56: aload         6
      58: aload         5
      60: invokevirtual #46                 // Method getValue:(Ljava/lang/String;Ljava/lang/String;)Ljava/lang/String;
      63: aload         4
      65: invokestatic  #50                 // Method ch/qos/logback/core/model/ModelUtil.setProperty:(Lch/qos/logback/core/model/processor/ModelInterpretationContext;Ljava/lang/String;Ljava/lang/String;Lch/qos/logback/core/joran/action/ActionUtil$Scope;)V
      68: return

  private java.lang.String getValue(java.lang.String, java.lang.String);
    Code:
       0: aload_0
       1: getfield      #7                  // Field environment:Lorg/springframework/core/env/Environment;
       4: ifnonnull     19
       7: aload_0
       8: aload_1
       9: invokedynamic #56,  0             // InvokeDynamic #0:makeConcatWithConstants:(Ljava/lang/String;)Ljava/lang/String;
      14: invokevirtual #60                 // Method addWarn:(Ljava/lang/String;)V
      17: aload_2
      18: areturn
      19: aload_0
      20: getfield      #7                  // Field environment:Lorg/springframework/core/env/Environment;
      23: aload_1
      24: aload_2
      25: invokeinterface #63,  3           // InterfaceMethod org/springframework/core/env/Environment.getProperty:(Ljava/lang/String;Ljava/lang/String;)Ljava/lang/String;
      30: areturn
}
