Compiled from "SpringBootJoranConfigurator.java"
final class org.springframework.boot.logging.logback.SpringBootJoranConfigurator$PatternRules {
  private static final java.lang.String RESOURCE_LOCATION;

  private final ch.qos.logback.core.Context context;

  private org.springframework.boot.logging.logback.SpringBootJoranConfigurator$PatternRules(ch.qos.logback.core.Context);
    Code:
       0: aload_0
       1: invokespecial #1                  // Method java/lang/Object."<init>":()V
       4: aload_0
       5: aload_1
       6: putfield      #7                  // Field context:Lch/qos/logback/core/Context;
       9: return

  private boolean load();
    Code:
       0: new           #13                 // class org/springframework/core/io/ClassPathResource
       3: dup
       4: ldc           #15                 // String META-INF/spring/logback-pattern-rules
       6: invokespecial #17                 // Method org/springframework/core/io/ClassPathResource."<init>":(Ljava/lang/String;)V
       9: astore_1
      10: aload_1
      11: invokevirtual #20                 // Method org/springframework/core/io/ClassPathResource.exists:()Z
      14: ifne          19
      17: iconst_0
      18: ireturn
      19: aload_1
      20: invokestatic  #24                 // Method org/springframework/core/io/support/PropertiesLoaderUtils.loadProperties:(Lorg/springframework/core/io/Resource;)Ljava/util/Properties;
      23: astore_2
      24: aload_0
      25: invokevirtual #30                 // Method getRegistryMap:()Ljava/util/Map;
      28: astore_3
      29: aload_2
      30: invokevirtual #34                 // Method java/util/Properties.stringPropertyNames:()Ljava/util/Set;
      33: invokeinterface #40,  1           // InterfaceMethod java/util/Set.iterator:()Ljava/util/Iterator;
      38: astore        4
      40: aload         4
      42: invokeinterface #46,  1           // InterfaceMethod java/util/Iterator.hasNext:()Z
      47: ifeq          80
      50: aload         4
      52: invokeinterface #51,  1           // InterfaceMethod java/util/Iterator.next:()Ljava/lang/Object;
      57: checkcast     #55                 // class java/lang/String
      60: astore        5
      62: aload_3
      63: aload         5
      65: aload_2
      66: aload         5
      68: invokevirtual #57                 // Method java/util/Properties.getProperty:(Ljava/lang/String;)Ljava/lang/String;
      71: invokeinterface #61,  3           // InterfaceMethod java/util/Map.put:(Ljava/lang/Object;Ljava/lang/Object;)Ljava/lang/Object;
      76: pop
      77: goto          40
      80: iconst_1
      81: ireturn
      82: astore_1
      83: new           #69                 // class java/lang/RuntimeException
      86: dup
      87: aload_1
      88: invokespecial #71                 // Method java/lang/RuntimeException."<init>":(Ljava/lang/Throwable;)V
      91: athrow
    Exception table:
       from    to  target type
           0    18    82   Class java/lang/Exception
          19    81    82   Class java/lang/Exception

  private java.util.Map<java.lang.String, java.lang.String> getRegistryMap();
    Code:
       0: aload_0
       1: getfield      #7                  // Field context:Lch/qos/logback/core/Context;
       4: ldc           #76                 // String PATTERN_RULE_REGISTRY
       6: invokeinterface #78,  2           // InterfaceMethod ch/qos/logback/core/Context.getObject:(Ljava/lang/String;)Ljava/lang/Object;
      11: checkcast     #62                 // class java/util/Map
      14: astore_1
      15: aload_1
      16: ifnonnull     39
      19: new           #84                 // class java/util/HashMap
      22: dup
      23: invokespecial #86                 // Method java/util/HashMap."<init>":()V
      26: astore_1
      27: aload_0
      28: getfield      #7                  // Field context:Lch/qos/logback/core/Context;
      31: ldc           #76                 // String PATTERN_RULE_REGISTRY
      33: aload_1
      34: invokeinterface #87,  3           // InterfaceMethod ch/qos/logback/core/Context.putObject:(Ljava/lang/String;Ljava/lang/Object;)V
      39: aload_1
      40: areturn

  private void save(org.springframework.aot.generate.GenerationContext);
    Code:
       0: aload_0
       1: invokevirtual #30                 // Method getRegistryMap:()Ljava/util/Map;
       4: astore_2
       5: aload_1
       6: invokeinterface #91,  1           // InterfaceMethod org/springframework/aot/generate/GenerationContext.getGeneratedFiles:()Lorg/springframework/aot/generate/GeneratedFiles;
      11: ldc           #15                 // String META-INF/spring/logback-pattern-rules
      13: aload_0
      14: aload_2
      15: invokedynamic #97,  0             // InvokeDynamic #0:getInputStream:(Lorg/springframework/boot/logging/logback/SpringBootJoranConfigurator$PatternRules;Ljava/util/Map;)Lorg/springframework/core/io/InputStreamSource;
      20: invokeinterface #101,  3          // InterfaceMethod org/springframework/aot/generate/GeneratedFiles.addResourceFile:(Ljava/lang/String;Lorg/springframework/core/io/InputStreamSource;)V
      25: aload_1
      26: invokeinterface #107,  1          // InterfaceMethod org/springframework/aot/generate/GenerationContext.getRuntimeHints:()Lorg/springframework/aot/hint/RuntimeHints;
      31: invokevirtual #111                // Method org/springframework/aot/hint/RuntimeHints.resources:()Lorg/springframework/aot/hint/ResourceHints;
      34: ldc           #15                 // String META-INF/spring/logback-pattern-rules
      36: invokevirtual #117                // Method org/springframework/aot/hint/ResourceHints.registerPattern:(Ljava/lang/String;)Lorg/springframework/aot/hint/ResourceHints;
      39: pop
      40: aload_2
      41: invokeinterface #123,  1          // InterfaceMethod java/util/Map.values:()Ljava/util/Collection;
      46: invokeinterface #127,  1          // InterfaceMethod java/util/Collection.iterator:()Ljava/util/Iterator;
      51: astore_3
      52: aload_3
      53: invokeinterface #46,  1           // InterfaceMethod java/util/Iterator.hasNext:()Z
      58: ifeq          103
      61: aload_3
      62: invokeinterface #51,  1           // InterfaceMethod java/util/Iterator.next:()Ljava/lang/Object;
      67: checkcast     #55                 // class java/lang/String
      70: astore        4
      72: aload_1
      73: invokeinterface #107,  1          // InterfaceMethod org/springframework/aot/generate/GenerationContext.getRuntimeHints:()Lorg/springframework/aot/hint/RuntimeHints;
      78: invokevirtual #130                // Method org/springframework/aot/hint/RuntimeHints.reflection:()Lorg/springframework/aot/hint/ReflectionHints;
      81: aload         4
      83: invokestatic  #134                // InterfaceMethod org/springframework/aot/hint/TypeReference.of:(Ljava/lang/String;)Lorg/springframework/aot/hint/TypeReference;
      86: iconst_1
      87: anewarray     #140                // class org/springframework/aot/hint/MemberCategory
      90: dup
      91: iconst_0
      92: getstatic     #142                // Field org/springframework/aot/hint/MemberCategory.INVOKE_PUBLIC_CONSTRUCTORS:Lorg/springframework/aot/hint/MemberCategory;
      95: aastore
      96: invokevirtual #146                // Method org/springframework/aot/hint/ReflectionHints.registerType:(Lorg/springframework/aot/hint/TypeReference;[Lorg/springframework/aot/hint/MemberCategory;)Lorg/springframework/aot/hint/ReflectionHints;
      99: pop
     100: goto          52
     103: return

  private java.io.InputStream asInputStream(java.util.Map<java.lang.String, java.lang.String>);
    Code:
       0: iconst_1
       1: invokestatic  #152                // Method org/springframework/core/CollectionFactory.createSortedProperties:(Z)Ljava/util/Properties;
       4: astore_2
       5: aload_1
       6: aload_2
       7: dup
       8: invokestatic  #158                // Method java/util/Objects.requireNonNull:(Ljava/lang/Object;)Ljava/lang/Object;
      11: pop
      12: invokedynamic #164,  0            // InvokeDynamic #1:accept:(Ljava/util/Properties;)Ljava/util/function/BiConsumer;
      17: invokeinterface #168,  2          // InterfaceMethod java/util/Map.forEach:(Ljava/util/function/BiConsumer;)V
      22: new           #172                // class java/io/ByteArrayOutputStream
      25: dup
      26: invokespecial #174                // Method java/io/ByteArrayOutputStream."<init>":()V
      29: astore_3
      30: aload_2
      31: aload_3
      32: ldc           #175                // String
      34: invokevirtual #177                // Method java/util/Properties.store:(Ljava/io/OutputStream;Ljava/lang/String;)V
      37: goto          52
      40: astore        4
      42: new           #69                 // class java/lang/RuntimeException
      45: dup
      46: aload         4
      48: invokespecial #71                 // Method java/lang/RuntimeException."<init>":(Ljava/lang/Throwable;)V
      51: athrow
      52: new           #183                // class java/io/ByteArrayInputStream
      55: dup
      56: aload_3
      57: invokevirtual #185                // Method java/io/ByteArrayOutputStream.toByteArray:()[B
      60: invokespecial #189                // Method java/io/ByteArrayInputStream."<init>":([B)V
      63: areturn
    Exception table:
       from    to  target type
          30    37    40   Class java/io/IOException

  private java.io.InputStream lambda$save$0(java.util.Map) throws java.io.IOException;
    Code:
       0: aload_0
       1: aload_1
       2: invokevirtual #192                // Method asInputStream:(Ljava/util/Map;)Ljava/io/InputStream;
       5: areturn
}
