Compiled from "SpringProfileIfNestedWithinSecondPhaseElementSanityChecker.java"
class org.springframework.boot.logging.logback.SpringProfileIfNestedWithinSecondPhaseElementSanityChecker extends ch.qos.logback.core.spi.ContextAwareBase implements ch.qos.logback.core.joran.sanity.SanityChecker {
  private static final java.util.List<java.lang.Class<? extends ch.qos.logback.core.model.Model>> SECOND_PHASE_TYPES;

  org.springframework.boot.logging.logback.SpringProfileIfNestedWithinSecondPhaseElementSanityChecker();
    Code:
       0: aload_0
       1: invokespecial #1                  // Method ch/qos/logback/core/spi/ContextAwareBase."<init>":()V
       4: return

  public void check(ch.qos.logback.core.model.Model);
    Code:
       0: aload_1
       1: ifnonnull     5
       4: return
       5: new           #7                  // class java/util/ArrayList
       8: dup
       9: invokespecial #9                  // Method java/util/ArrayList."<init>":()V
      12: astore_2
      13: getstatic     #10                 // Field SECOND_PHASE_TYPES:Ljava/util/List;
      16: aload_0
      17: aload_2
      18: aload_1
      19: invokedynamic #16,  0             // InvokeDynamic #0:accept:(Lorg/springframework/boot/logging/logback/SpringProfileIfNestedWithinSecondPhaseElementSanityChecker;Ljava/util/List;Lch/qos/logback/core/model/Model;)Ljava/util/function/Consumer;
      24: invokeinterface #20,  2           // InterfaceMethod java/util/List.forEach:(Ljava/util/function/Consumer;)V
      29: aload_0
      30: ldc           #26                 // class org/springframework/boot/logging/logback/SpringProfileModel
      32: aload_2
      33: invokevirtual #28                 // Method deepFindNestedSubModelsOfType:(Ljava/lang/Class;Ljava/util/List;)Ljava/util/List;
      36: astore_3
      37: aload_3
      38: invokeinterface #32,  1           // InterfaceMethod java/util/List.isEmpty:()Z
      43: ifne          64
      46: aload_0
      47: ldc           #36                 // String <springProfile> elements cannot be nested within an <appender>, <logger> or <root> element
      49: invokevirtual #38                 // Method addWarn:(Ljava/lang/String;)V
      52: aload_3
      53: aload_0
      54: invokedynamic #42,  0             // InvokeDynamic #1:accept:(Lorg/springframework/boot/logging/logback/SpringProfileIfNestedWithinSecondPhaseElementSanityChecker;)Ljava/util/function/Consumer;
      59: invokeinterface #20,  2           // InterfaceMethod java/util/List.forEach:(Ljava/util/function/Consumer;)V
      64: return

  private void lambda$check$1(ch.qos.logback.core.joran.sanity.Pair);
    Code:
       0: aload_1
       1: getfield      #45                 // Field ch/qos/logback/core/joran/sanity/Pair.first:Ljava/lang/Object;
       4: checkcast     #51                 // class ch/qos/logback/core/model/Model
       7: astore_2
       8: aload_1
       9: getfield      #53                 // Field ch/qos/logback/core/joran/sanity/Pair.second:Ljava/lang/Object;
      12: checkcast     #51                 // class ch/qos/logback/core/model/Model
      15: astore_3
      16: aload_0
      17: ldc           #56                 // String Element <%s> at line %s contains a nested <%s> element at line %s
      19: iconst_4
      20: anewarray     #58                 // class java/lang/Object
      23: dup
      24: iconst_0
      25: aload_2
      26: invokevirtual #60                 // Method ch/qos/logback/core/model/Model.getTag:()Ljava/lang/String;
      29: aastore
      30: dup
      31: iconst_1
      32: aload_2
      33: invokevirtual #64                 // Method ch/qos/logback/core/model/Model.getLineNumber:()I
      36: invokestatic  #68                 // Method java/lang/Integer.valueOf:(I)Ljava/lang/Integer;
      39: aastore
      40: dup
      41: iconst_2
      42: aload_3
      43: invokevirtual #60                 // Method ch/qos/logback/core/model/Model.getTag:()Ljava/lang/String;
      46: aastore
      47: dup
      48: iconst_3
      49: aload_3
      50: invokevirtual #64                 // Method ch/qos/logback/core/model/Model.getLineNumber:()I
      53: invokestatic  #68                 // Method java/lang/Integer.valueOf:(I)Ljava/lang/Integer;
      56: aastore
      57: invokevirtual #74                 // Method java/lang/String.formatted:([Ljava/lang/Object;)Ljava/lang/String;
      60: invokevirtual #38                 // Method addWarn:(Ljava/lang/String;)V
      63: return

  private void lambda$check$0(java.util.List, ch.qos.logback.core.model.Model, java.lang.Class);
    Code:
       0: aload_0
       1: aload_3
       2: aload_1
       3: aload_2
       4: invokevirtual #80                 // Method deepFindAllModelsOfType:(Ljava/lang/Class;Ljava/util/List;Lch/qos/logback/core/model/Model;)V
       7: return

  static {};
    Code:
       0: ldc           #84                 // class ch/qos/logback/core/model/AppenderModel
       2: ldc           #86                 // class ch/qos/logback/classic/model/LoggerModel
       4: ldc           #88                 // class ch/qos/logback/classic/model/RootLoggerModel
       6: invokestatic  #90                 // InterfaceMethod java/util/List.of:(Ljava/lang/Object;Ljava/lang/Object;Ljava/lang/Object;)Ljava/util/List;
       9: putstatic     #10                 // Field SECOND_PHASE_TYPES:Ljava/util/List;
      12: return
}
