Compiled from "SpringBootJoranConfigurator.java"
final class org.springframework.boot.logging.logback.SpringBootJoranConfigurator$LogbackConfigurationAotContribution implements org.springframework.beans.factory.aot.BeanFactoryInitializationAotContribution {
  private final org.springframework.boot.logging.logback.SpringBootJoranConfigurator$ModelWriter modelWriter;

  private final org.springframework.boot.logging.logback.SpringBootJoranConfigurator$PatternRules patternRules;

  private org.springframework.boot.logging.logback.SpringBootJoranConfigurator$LogbackConfigurationAotContribution(ch.qos.logback.core.model.Model, ch.qos.logback.core.model.processor.ModelInterpretationContext, ch.qos.logback.core.Context);
    Code:
       0: aload_0
       1: invokespecial #1                  // Method java/lang/Object."<init>":()V
       4: aload_0
       5: new           #7                  // class org/springframework/boot/logging/logback/SpringBootJoranConfigurator$ModelWriter
       8: dup
       9: aload_1
      10: aload_2
      11: invokespecial #9                  // Method org/springframework/boot/logging/logback/SpringBootJoranConfigurator$ModelWriter."<init>":(Lch/qos/logback/core/model/Model;Lch/qos/logback/core/model/processor/ModelInterpretationContext;)V
      14: putfield      #12                 // Field modelWriter:Lorg/springframework/boot/logging/logback/SpringBootJoranConfigurator$ModelWriter;
      17: aload_0
      18: new           #18                 // class org/springframework/boot/logging/logback/SpringBootJoranConfigurator$PatternRules
      21: dup
      22: aload_3
      23: invokespecial #20                 // Method org/springframework/boot/logging/logback/SpringBootJoranConfigurator$PatternRules."<init>":(Lch/qos/logback/core/Context;)V
      26: putfield      #23                 // Field patternRules:Lorg/springframework/boot/logging/logback/SpringBootJoranConfigurator$PatternRules;
      29: return

  public void applyTo(org.springframework.aot.generate.GenerationContext, org.springframework.beans.factory.aot.BeanFactoryInitializationCode);
    Code:
       0: aload_0
       1: getfield      #12                 // Field modelWriter:Lorg/springframework/boot/logging/logback/SpringBootJoranConfigurator$ModelWriter;
       4: aload_1
       5: invokevirtual #27                 // Method org/springframework/boot/logging/logback/SpringBootJoranConfigurator$ModelWriter.writeTo:(Lorg/springframework/aot/generate/GenerationContext;)V
       8: aload_0
       9: getfield      #23                 // Field patternRules:Lorg/springframework/boot/logging/logback/SpringBootJoranConfigurator$PatternRules;
      12: aload_1
      13: invokevirtual #31                 // Method org/springframework/boot/logging/logback/SpringBootJoranConfigurator$PatternRules.save:(Lorg/springframework/aot/generate/GenerationContext;)V
      16: return
}
