Compiled from "SpringBootJoranConfigurator.java"
class org.springframework.boot.logging.logback.SpringBootJoranConfigurator extends ch.qos.logback.classic.joran.JoranConfigurator {
  private final org.springframework.boot.logging.LoggingInitializationContext initializationContext;

  org.springframework.boot.logging.logback.SpringBootJoranConfigurator(org.springframework.boot.logging.LoggingInitializationContext);
    Code:
       0: aload_0
       1: invokespecial #1                  // Method ch/qos/logback/classic/joran/JoranConfigurator."<init>":()V
       4: aload_0
       5: aload_1
       6: putfield      #7                  // Field initializationContext:Lorg/springframework/boot/logging/LoggingInitializationContext;
       9: return

  protected void sanityCheck(ch.qos.logback.core.model.Model);
    Code:
       0: aload_0
       1: aload_1
       2: invokespecial #13                 // Method ch/qos/logback/classic/joran/JoranConfigurator.sanityCheck:(Lch/qos/logback/core/model/Model;)V
       5: aload_0
       6: new           #17                 // class org/springframework/boot/logging/logback/SpringProfileIfNestedWithinSecondPhaseElementSanityChecker
       9: dup
      10: invokespecial #19                 // Method org/springframework/boot/logging/logback/SpringProfileIfNestedWithinSecondPhaseElementSanityChecker."<init>":()V
      13: aload_1
      14: invokevirtual #20                 // Method performCheck:(Lch/qos/logback/core/joran/sanity/SanityChecker;Lch/qos/logback/core/model/Model;)V
      17: return

  protected void addModelHandlerAssociations(ch.qos.logback.core.model.processor.DefaultProcessor);
    Code:
       0: aload_1
       1: ldc           #24                 // class org/springframework/boot/logging/logback/SpringPropertyModel
       3: aload_0
       4: invokedynamic #26,  0             // InvokeDynamic #0:make:(Lorg/springframework/boot/logging/logback/SpringBootJoranConfigurator;)Lch/qos/logback/core/model/ModelHandlerFactoryMethod;
       9: invokevirtual #30                 // Method ch/qos/logback/core/model/processor/DefaultProcessor.addHandler:(Ljava/lang/Class;Lch/qos/logback/core/model/ModelHandlerFactoryMethod;)V
      12: aload_1
      13: ldc           #36                 // class org/springframework/boot/logging/logback/SpringProfileModel
      15: aload_0
      16: invokedynamic #38,  0             // InvokeDynamic #1:make:(Lorg/springframework/boot/logging/logback/SpringBootJoranConfigurator;)Lch/qos/logback/core/model/ModelHandlerFactoryMethod;
      21: invokevirtual #30                 // Method ch/qos/logback/core/model/processor/DefaultProcessor.addHandler:(Ljava/lang/Class;Lch/qos/logback/core/model/ModelHandlerFactoryMethod;)V
      24: aload_0
      25: aload_1
      26: invokespecial #39                 // Method ch/qos/logback/classic/joran/JoranConfigurator.addModelHandlerAssociations:(Lch/qos/logback/core/model/processor/DefaultProcessor;)V
      29: return

  public void addElementSelectorAndActionAssociations(ch.qos.logback.core.joran.spi.RuleStore);
    Code:
       0: aload_0
       1: aload_1
       2: invokespecial #43                 // Method ch/qos/logback/classic/joran/JoranConfigurator.addElementSelectorAndActionAssociations:(Lch/qos/logback/core/joran/spi/RuleStore;)V
       5: aload_1
       6: new           #47                 // class ch/qos/logback/core/joran/spi/ElementSelector
       9: dup
      10: ldc           #49                 // String configuration/springProperty
      12: invokespecial #51                 // Method ch/qos/logback/core/joran/spi/ElementSelector."<init>":(Ljava/lang/String;)V
      15: invokedynamic #54,  0             // InvokeDynamic #2:get:()Ljava/util/function/Supplier;
      20: invokeinterface #58,  3           // InterfaceMethod ch/qos/logback/core/joran/spi/RuleStore.addRule:(Lch/qos/logback/core/joran/spi/ElementSelector;Ljava/util/function/Supplier;)V
      25: aload_1
      26: new           #47                 // class ch/qos/logback/core/joran/spi/ElementSelector
      29: dup
      30: ldc           #64                 // String */springProfile
      32: invokespecial #51                 // Method ch/qos/logback/core/joran/spi/ElementSelector."<init>":(Ljava/lang/String;)V
      35: invokedynamic #66,  0             // InvokeDynamic #3:get:()Ljava/util/function/Supplier;
      40: invokeinterface #58,  3           // InterfaceMethod ch/qos/logback/core/joran/spi/RuleStore.addRule:(Lch/qos/logback/core/joran/spi/ElementSelector;Ljava/util/function/Supplier;)V
      45: aload_1
      46: ldc           #67                 // String springProfile
      48: invokeinterface #69,  2           // InterfaceMethod ch/qos/logback/core/joran/spi/RuleStore.addTransparentPathPart:(Ljava/lang/String;)V
      53: return

  boolean configureUsingAotGeneratedArtifacts();
    Code:
       0: new           #72                 // class org/springframework/boot/logging/logback/SpringBootJoranConfigurator$PatternRules
       3: dup
       4: aload_0
       5: invokevirtual #74                 // Method getContext:()Lch/qos/logback/core/Context;
       8: invokespecial #78                 // Method org/springframework/boot/logging/logback/SpringBootJoranConfigurator$PatternRules."<init>":(Lch/qos/logback/core/Context;)V
      11: invokevirtual #81                 // Method org/springframework/boot/logging/logback/SpringBootJoranConfigurator$PatternRules.load:()Z
      14: ifne          19
      17: iconst_0
      18: ireturn
      19: new           #85                 // class org/springframework/boot/logging/logback/SpringBootJoranConfigurator$ModelReader
      22: dup
      23: invokespecial #87                 // Method org/springframework/boot/logging/logback/SpringBootJoranConfigurator$ModelReader."<init>":()V
      26: invokevirtual #88                 // Method org/springframework/boot/logging/logback/SpringBootJoranConfigurator$ModelReader.read:()Lch/qos/logback/core/model/Model;
      29: astore_1
      30: aload_0
      31: aload_1
      32: invokevirtual #92                 // Method processModel:(Lch/qos/logback/core/model/Model;)V
      35: aload_0
      36: aload_1
      37: invokevirtual #95                 // Method registerSafeConfiguration:(Lch/qos/logback/core/model/Model;)V
      40: iconst_1
      41: ireturn

  public void processModel(ch.qos.logback.core.model.Model);
    Code:
       0: aload_0
       1: aload_1
       2: invokespecial #98                 // Method ch/qos/logback/classic/joran/JoranConfigurator.processModel:(Lch/qos/logback/core/model/Model;)V
       5: invokestatic  #99                 // Method org/springframework/core/NativeDetector.inNativeImage:()Z
       8: ifne          48
      11: aload_0
      12: invokevirtual #104                // Method isAotProcessingInProgress:()Z
      15: ifeq          48
      18: aload_0
      19: invokevirtual #74                 // Method getContext:()Lch/qos/logback/core/Context;
      22: ldc           #107                // class org/springframework/beans/factory/aot/BeanFactoryInitializationAotContribution
      24: invokevirtual #109                // Method java/lang/Class.getName:()Ljava/lang/String;
      27: new           #115                // class org/springframework/boot/logging/logback/SpringBootJoranConfigurator$LogbackConfigurationAotContribution
      30: dup
      31: aload_1
      32: aload_0
      33: invokevirtual #117                // Method getModelInterpretationContext:()Lch/qos/logback/core/model/processor/ModelInterpretationContext;
      36: aload_0
      37: invokevirtual #74                 // Method getContext:()Lch/qos/logback/core/Context;
      40: invokespecial #121                // Method org/springframework/boot/logging/logback/SpringBootJoranConfigurator$LogbackConfigurationAotContribution."<init>":(Lch/qos/logback/core/model/Model;Lch/qos/logback/core/model/processor/ModelInterpretationContext;Lch/qos/logback/core/Context;)V
      43: invokeinterface #124,  3          // InterfaceMethod ch/qos/logback/core/Context.putObject:(Ljava/lang/String;Ljava/lang/Object;)V
      48: return

  private boolean isAotProcessingInProgress();
    Code:
       0: ldc           #130                // String spring.aot.processing
       2: invokestatic  #132                // Method java/lang/Boolean.getBoolean:(Ljava/lang/String;)Z
       5: ireturn

  private ch.qos.logback.core.model.processor.ModelHandlerBase lambda$addModelHandlerAssociations$1(ch.qos.logback.core.Context, ch.qos.logback.core.model.processor.ModelInterpretationContext);
    Code:
       0: new           #138                // class org/springframework/boot/logging/logback/SpringProfileModelHandler
       3: dup
       4: aload_0
       5: getfield      #140                // Field context:Lch/qos/logback/core/Context;
       8: aload_0
       9: getfield      #7                  // Field initializationContext:Lorg/springframework/boot/logging/LoggingInitializationContext;
      12: invokevirtual #144                // Method org/springframework/boot/logging/LoggingInitializationContext.getEnvironment:()Lorg/springframework/core/env/Environment;
      15: invokespecial #150                // Method org/springframework/boot/logging/logback/SpringProfileModelHandler."<init>":(Lch/qos/logback/core/Context;Lorg/springframework/core/env/Environment;)V
      18: areturn

  private ch.qos.logback.core.model.processor.ModelHandlerBase lambda$addModelHandlerAssociations$0(ch.qos.logback.core.Context, ch.qos.logback.core.model.processor.ModelInterpretationContext);
    Code:
       0: new           #153                // class org/springframework/boot/logging/logback/SpringPropertyModelHandler
       3: dup
       4: aload_0
       5: getfield      #140                // Field context:Lch/qos/logback/core/Context;
       8: aload_0
       9: getfield      #7                  // Field initializationContext:Lorg/springframework/boot/logging/LoggingInitializationContext;
      12: invokevirtual #144                // Method org/springframework/boot/logging/LoggingInitializationContext.getEnvironment:()Lorg/springframework/core/env/Environment;
      15: invokespecial #155                // Method org/springframework/boot/logging/logback/SpringPropertyModelHandler."<init>":(Lch/qos/logback/core/Context;Lorg/springframework/core/env/Environment;)V
      18: areturn
}
