Compiled from "SpringBootJoranConfigurator.java"
final class org.springframework.boot.logging.logback.SpringBootJoranConfigurator$ModelReader {
  private org.springframework.boot.logging.logback.SpringBootJoranConfigurator$ModelReader();
    Code:
       0: aload_0
       1: invokespecial #1                  // Method java/lang/Object."<init>":()V
       4: return

  private ch.qos.logback.core.model.Model read();
    Code:
       0: aload_0
       1: invokevirtual #7                  // Method java/lang/Object.getClass:()Ljava/lang/Class;
       4: invokevirtual #11                 // Method java/lang/Class.getClassLoader:()Ljava/lang/ClassLoader;
       7: ldc           #19                 // String META-INF/spring/logback-model
       9: invokevirtual #21                 // Method java/lang/ClassLoader.getResourceAsStream:(Ljava/lang/String;)Ljava/io/InputStream;
      12: astore_1
      13: new           #27                 // class java/io/ObjectInputStream
      16: dup
      17: aload_1
      18: invokespecial #29                 // Method java/io/ObjectInputStream."<init>":(Ljava/io/InputStream;)V
      21: astore_2
      22: aload_2
      23: invokevirtual #32                 // Method java/io/ObjectInputStream.readObject:()Ljava/lang/Object;
      26: checkcast     #36                 // class ch/qos/logback/core/model/Model
      29: astore_3
      30: aload_3
      31: invokestatic  #38                 // Method ch/qos/logback/core/model/ModelUtil.resetForReuse:(Lch/qos/logback/core/model/Model;)V
      34: aload_3
      35: astore        4
      37: aload_2
      38: invokevirtual #44                 // Method java/io/ObjectInputStream.close:()V
      41: aload_1
      42: ifnull        49
      45: aload_1
      46: invokevirtual #47                 // Method java/io/InputStream.close:()V
      49: aload         4
      51: areturn
      52: astore_3
      53: aload_2
      54: invokevirtual #44                 // Method java/io/ObjectInputStream.close:()V
      57: goto          68
      60: astore        4
      62: aload_3
      63: aload         4
      65: invokevirtual #52                 // Method java/lang/Throwable.addSuppressed:(Ljava/lang/Throwable;)V
      68: aload_3
      69: athrow
      70: astore_2
      71: aload_1
      72: ifnull        88
      75: aload_1
      76: invokevirtual #47                 // Method java/io/InputStream.close:()V
      79: goto          88
      82: astore_3
      83: aload_2
      84: aload_3
      85: invokevirtual #52                 // Method java/lang/Throwable.addSuppressed:(Ljava/lang/Throwable;)V
      88: aload_2
      89: athrow
      90: astore_1
      91: new           #58                 // class java/lang/RuntimeException
      94: dup
      95: ldc           #60                 // String Failed to load model from \'META-INF/spring/logback-model\'
      97: aload_1
      98: invokespecial #62                 // Method java/lang/RuntimeException."<init>":(Ljava/lang/String;Ljava/lang/Throwable;)V
     101: athrow
    Exception table:
       from    to  target type
          22    37    52   Class java/lang/Throwable
          53    57    60   Class java/lang/Throwable
          13    41    70   Class java/lang/Throwable
          52    70    70   Class java/lang/Throwable
          75    79    82   Class java/lang/Throwable
           0    49    90   Class java/lang/Exception
          52    90    90   Class java/lang/Exception
}
