Compiled from "SpringPropertyModel.java"
class org.springframework.boot.logging.logback.SpringPropertyModel extends ch.qos.logback.core.model.NamedModel {
  private java.lang.String scope;

  private java.lang.String defaultValue;

  private java.lang.String source;

  org.springframework.boot.logging.logback.SpringPropertyModel();
    Code:
       0: aload_0
       1: invokespecial #1                  // Method ch/qos/logback/core/model/NamedModel."<init>":()V
       4: return

  java.lang.String getScope();
    Code:
       0: aload_0
       1: getfield      #7                  // Field scope:Ljava/lang/String;
       4: areturn

  void setScope(java.lang.String);
    Code:
       0: aload_0
       1: aload_1
       2: putfield      #7                  // Field scope:Ljava/lang/String;
       5: return

  java.lang.String getDefaultValue();
    Code:
       0: aload_0
       1: getfield      #13                 // Field defaultValue:Ljava/lang/String;
       4: areturn

  void setDefaultValue(java.lang.String);
    Code:
       0: aload_0
       1: aload_1
       2: putfield      #13                 // Field defaultValue:Ljava/lang/String;
       5: return

  java.lang.String getSource();
    Code:
       0: aload_0
       1: getfield      #16                 // Field source:Ljava/lang/String;
       4: areturn

  void setSource(java.lang.String);
    Code:
       0: aload_0
       1: aload_1
       2: putfield      #16                 // Field source:Ljava/lang/String;
       5: return
}
