Compiled from "WhitespaceThrowableProxyConverter.java"
public class org.springframework.boot.logging.logback.WhitespaceThrowableProxyConverter extends ch.qos.logback.classic.pattern.ThrowableProxyConverter {
  public org.springframework.boot.logging.logback.WhitespaceThrowableProxyConverter();
    Code:
       0: aload_0
       1: invokespecial #1                  // Method ch/qos/logback/classic/pattern/ThrowableProxyConverter."<init>":()V
       4: return

  protected java.lang.String throwableProxyToString(ch.qos.logback.classic.spi.IThrowableProxy);
    Code:
       0: getstatic     #7                  // Field ch/qos/logback/core/CoreConstants.LINE_SEPARATOR:Ljava/lang/String;
       3: aload_0
       4: aload_1
       5: invokespecial #13                 // Method ch/qos/logback/classic/pattern/ThrowableProxyConverter.throwableProxyToString:(Lch/qos/logback/classic/spi/IThrowableProxy;)Ljava/lang/String;
       8: getstatic     #7                  // Field ch/qos/logback/core/CoreConstants.LINE_SEPARATOR:Ljava/lang/String;
      11: invokedynamic #17,  0             // InvokeDynamic #0:makeConcatWithConstants:(Ljava/lang/String;Ljava/lang/String;Ljava/lang/String;)Ljava/lang/String;
      16: areturn
}
