Compiled from "BootstrapInfoImpl.java"
public final class org.apache.dubbo.registry.xds.util.bootstrap.BootstrapInfoImpl$Builder extends org.apache.dubbo.registry.xds.util.bootstrap.Bootstrapper$BootstrapInfo$Builder {
  private java.util.List<org.apache.dubbo.registry.xds.util.bootstrap.Bootstrapper$ServerInfo> servers;

  private io.envoyproxy.envoy.config.core.v3.Node node;

  private java.util.Map<java.lang.String, org.apache.dubbo.registry.xds.util.bootstrap.Bootstrapper$CertificateProviderInfo> certProviders;

  private java.lang.String serverListenerResourceNameTemplate;

  org.apache.dubbo.registry.xds.util.bootstrap.BootstrapInfoImpl$Builder();
    Code:
       0: aload_0
       1: invokespecial #1                  // Method org/apache/dubbo/registry/xds/util/bootstrap/Bootstrapper$BootstrapInfo$Builder."<init>":()V
       4: return

  org.apache.dubbo.registry.xds.util.bootstrap.Bootstrapper$BootstrapInfo$Builder servers(java.util.List<org.apache.dubbo.registry.xds.util.bootstrap.Bootstrapper$ServerInfo>);
    Code:
       0: aload_0
       1: new           #2                  // class java/util/LinkedList
       4: dup
       5: aload_1
       6: invokespecial #3                  // Method java/util/LinkedList."<init>":(Ljava/util/Collection;)V
       9: putfield      #4                  // Field servers:Ljava/util/List;
      12: aload_0
      13: areturn

  org.apache.dubbo.registry.xds.util.bootstrap.Bootstrapper$BootstrapInfo$Builder node(io.envoyproxy.envoy.config.core.v3.Node);
    Code:
       0: aload_1
       1: ifnonnull     14
       4: new           #5                  // class java/lang/NullPointerException
       7: dup
       8: ldc           #6                  // String Null node
      10: invokespecial #7                  // Method java/lang/NullPointerException."<init>":(Ljava/lang/String;)V
      13: athrow
      14: aload_0
      15: aload_1
      16: putfield      #8                  // Field node:Lio/envoyproxy/envoy/config/core/v3/Node;
      19: aload_0
      20: areturn

  org.apache.dubbo.registry.xds.util.bootstrap.Bootstrapper$BootstrapInfo$Builder certProviders(java.util.Map<java.lang.String, org.apache.dubbo.registry.xds.util.bootstrap.Bootstrapper$CertificateProviderInfo>);
    Code:
       0: aload_0
       1: aload_1
       2: putfield      #9                  // Field certProviders:Ljava/util/Map;
       5: aload_0
       6: areturn

  org.apache.dubbo.registry.xds.util.bootstrap.Bootstrapper$BootstrapInfo$Builder serverListenerResourceNameTemplate(java.lang.String);
    Code:
       0: aload_0
       1: aload_1
       2: putfield      #10                 // Field serverListenerResourceNameTemplate:Ljava/lang/String;
       5: aload_0
       6: areturn

  org.apache.dubbo.registry.xds.util.bootstrap.Bootstrapper$BootstrapInfo build();
    Code:
       0: aload_0
       1: getfield      #4                  // Field servers:Ljava/util/List;
       4: ifnull        14
       7: aload_0
       8: getfield      #8                  // Field node:Lio/envoyproxy/envoy/config/core/v3/Node;
      11: ifnonnull     77
      14: new           #11                 // class java/lang/StringBuilder
      17: dup
      18: invokespecial #12                 // Method java/lang/StringBuilder."<init>":()V
      21: astore_1
      22: aload_0
      23: getfield      #4                  // Field servers:Ljava/util/List;
      26: ifnonnull     36
      29: aload_1
      30: ldc           #13                 // String  servers
      32: invokevirtual #14                 // Method java/lang/StringBuilder.append:(Ljava/lang/String;)Ljava/lang/StringBuilder;
      35: pop
      36: aload_0
      37: getfield      #8                  // Field node:Lio/envoyproxy/envoy/config/core/v3/Node;
      40: ifnonnull     50
      43: aload_1
      44: ldc           #15                 // String  node
      46: invokevirtual #14                 // Method java/lang/StringBuilder.append:(Ljava/lang/String;)Ljava/lang/StringBuilder;
      49: pop
      50: new           #16                 // class java/lang/IllegalStateException
      53: dup
      54: new           #11                 // class java/lang/StringBuilder
      57: dup
      58: invokespecial #12                 // Method java/lang/StringBuilder."<init>":()V
      61: ldc           #17                 // String Missing required properties:
      63: invokevirtual #14                 // Method java/lang/StringBuilder.append:(Ljava/lang/String;)Ljava/lang/StringBuilder;
      66: aload_1
      67: invokevirtual #18                 // Method java/lang/StringBuilder.append:(Ljava/lang/Object;)Ljava/lang/StringBuilder;
      70: invokevirtual #19                 // Method java/lang/StringBuilder.toString:()Ljava/lang/String;
      73: invokespecial #20                 // Method java/lang/IllegalStateException."<init>":(Ljava/lang/String;)V
      76: athrow
      77: new           #21                 // class org/apache/dubbo/registry/xds/util/bootstrap/BootstrapInfoImpl
      80: dup
      81: aload_0
      82: getfield      #4                  // Field servers:Ljava/util/List;
      85: aload_0
      86: getfield      #10                 // Field serverListenerResourceNameTemplate:Ljava/lang/String;
      89: aload_0
      90: getfield      #9                  // Field certProviders:Ljava/util/Map;
      93: aload_0
      94: getfield      #8                  // Field node:Lio/envoyproxy/envoy/config/core/v3/Node;
      97: invokespecial #22                 // Method org/apache/dubbo/registry/xds/util/bootstrap/BootstrapInfoImpl."<init>":(Ljava/util/List;Ljava/lang/String;Ljava/util/Map;Lio/envoyproxy/envoy/config/core/v3/Node;)V
     100: areturn
}
