Compiled from "BootstrapperImpl.java"
public class org.apache.dubbo.registry.xds.util.bootstrap.BootstrapperImpl extends org.apache.dubbo.registry.xds.util.bootstrap.Bootstrapper {
  static final java.lang.String BOOTSTRAP_PATH_SYS_ENV_VAR;

  static java.lang.String bootstrapPathFromEnvVar;

  private static final org.apache.dubbo.common.logger.Logger logger;

  private org.apache.dubbo.registry.xds.util.bootstrap.BootstrapperImpl$FileReader reader;

  private static final java.lang.String SERVER_FEATURE_XDS_V3;

  private static final java.lang.String SERVER_FEATURE_IGNORE_RESOURCE_DELETION;

  public org.apache.dubbo.registry.xds.util.bootstrap.BootstrapperImpl();
    Code:
       0: aload_0
       1: invokespecial #1                  // Method org/apache/dubbo/registry/xds/util/bootstrap/Bootstrapper."<init>":()V
       4: aload_0
       5: getstatic     #2                  // Field org/apache/dubbo/registry/xds/util/bootstrap/BootstrapperImpl$LocalFileReader.INSTANCE:Lorg/apache/dubbo/registry/xds/util/bootstrap/BootstrapperImpl$LocalFileReader;
       8: putfield      #3                  // Field reader:Lorg/apache/dubbo/registry/xds/util/bootstrap/BootstrapperImpl$FileReader;
      11: return

  public org.apache.dubbo.registry.xds.util.bootstrap.Bootstrapper$BootstrapInfo bootstrap() throws org.apache.dubbo.registry.xds.XdsInitializationException;
    Code:
       0: getstatic     #4                  // Field bootstrapPathFromEnvVar:Ljava/lang/String;
       3: astore_1
       4: aconst_null
       5: astore_2
       6: aload_1
       7: ifnull        36
      10: aload_0
      11: getfield      #3                  // Field reader:Lorg/apache/dubbo/registry/xds/util/bootstrap/BootstrapperImpl$FileReader;
      14: aload_1
      15: invokeinterface #5,  2            // InterfaceMethod org/apache/dubbo/registry/xds/util/bootstrap/BootstrapperImpl$FileReader.readFile:(Ljava/lang/String;)Ljava/lang/String;
      20: astore_2
      21: goto          36
      24: astore_3
      25: new           #7                  // class org/apache/dubbo/registry/xds/XdsInitializationException
      28: dup
      29: ldc           #8                  // String Fail to read bootstrap file
      31: aload_3
      32: invokespecial #9                  // Method org/apache/dubbo/registry/xds/XdsInitializationException."<init>":(Ljava/lang/String;Ljava/lang/Throwable;)V
      35: athrow
      36: aload_2
      37: ifnonnull     50
      40: new           #7                  // class org/apache/dubbo/registry/xds/XdsInitializationException
      43: dup
      44: ldc           #10                 // String Cannot find bootstrap configuration
      46: invokespecial #11                 // Method org/apache/dubbo/registry/xds/XdsInitializationException."<init>":(Ljava/lang/String;)V
      49: athrow
      50: aload_2
      51: invokestatic  #12                 // Method io/grpc/internal/JsonParser.parse:(Ljava/lang/String;)Ljava/lang/Object;
      54: checkcast     #13                 // class java/util/Map
      57: astore_3
      58: goto          75
      61: astore        4
      63: new           #7                  // class org/apache/dubbo/registry/xds/XdsInitializationException
      66: dup
      67: ldc           #14                 // String Failed to parse JSON
      69: aload         4
      71: invokespecial #9                  // Method org/apache/dubbo/registry/xds/XdsInitializationException."<init>":(Ljava/lang/String;Ljava/lang/Throwable;)V
      74: athrow
      75: aload_0
      76: aload_3
      77: invokevirtual #15                 // Method bootstrap:(Ljava/util/Map;)Lorg/apache/dubbo/registry/xds/util/bootstrap/Bootstrapper$BootstrapInfo;
      80: areturn
    Exception table:
       from    to  target type
          10    21    24   Class java/io/IOException
          50    58    61   Class java/io/IOException

  org.apache.dubbo.registry.xds.util.bootstrap.Bootstrapper$BootstrapInfo bootstrap(java.util.Map<java.lang.String, ?>) throws org.apache.dubbo.registry.xds.XdsInitializationException;
    Code:
       0: new           #16                 // class org/apache/dubbo/registry/xds/util/bootstrap/BootstrapInfoImpl$Builder
       3: dup
       4: invokespecial #17                 // Method org/apache/dubbo/registry/xds/util/bootstrap/BootstrapInfoImpl$Builder."<init>":()V
       7: astore_2
       8: aload_1
       9: ldc           #18                 // String xds_servers
      11: invokestatic  #19                 // Method io/grpc/internal/JsonUtil.getList:(Ljava/util/Map;Ljava/lang/String;)Ljava/util/List;
      14: astore_3
      15: aload_3
      16: ifnonnull     29
      19: new           #7                  // class org/apache/dubbo/registry/xds/XdsInitializationException
      22: dup
      23: ldc           #20                 // String Invalid bootstrap: \'xds_servers\' does not exist.
      25: invokespecial #11                 // Method org/apache/dubbo/registry/xds/XdsInitializationException."<init>":(Ljava/lang/String;)V
      28: athrow
      29: aload_3
      30: invokestatic  #21                 // Method parseServerInfos:(Ljava/util/List;)Ljava/util/List;
      33: astore        4
      35: aload_2
      36: aload         4
      38: invokevirtual #22                 // Method org/apache/dubbo/registry/xds/util/bootstrap/Bootstrapper$BootstrapInfo$Builder.servers:(Ljava/util/List;)Lorg/apache/dubbo/registry/xds/util/bootstrap/Bootstrapper$BootstrapInfo$Builder;
      41: pop
      42: invokestatic  #23                 // Method io/envoyproxy/envoy/config/core/v3/Node.newBuilder:()Lio/envoyproxy/envoy/config/core/v3/Node$Builder;
      45: astore        5
      47: aload_1
      48: ldc           #24                 // String node
      50: invokestatic  #25                 // Method io/grpc/internal/JsonUtil.getObject:(Ljava/util/Map;Ljava/lang/String;)Ljava/util/Map;
      53: astore        6
      55: aload         6
      57: ifnull        122
      60: aload         6
      62: ldc           #26                 // String id
      64: invokestatic  #27                 // Method io/grpc/internal/JsonUtil.getString:(Ljava/util/Map;Ljava/lang/String;)Ljava/lang/String;
      67: astore        7
      69: aload         7
      71: ifnull        82
      74: aload         5
      76: aload         7
      78: invokevirtual #28                 // Method io/envoyproxy/envoy/config/core/v3/Node$Builder.setId:(Ljava/lang/String;)Lio/envoyproxy/envoy/config/core/v3/Node$Builder;
      81: pop
      82: aload         6
      84: ldc           #29                 // String cluster
      86: invokestatic  #27                 // Method io/grpc/internal/JsonUtil.getString:(Ljava/util/Map;Ljava/lang/String;)Ljava/lang/String;
      89: astore        8
      91: aload         8
      93: ifnull        104
      96: aload         5
      98: aload         8
     100: invokevirtual #30                 // Method io/envoyproxy/envoy/config/core/v3/Node$Builder.setCluster:(Ljava/lang/String;)Lio/envoyproxy/envoy/config/core/v3/Node$Builder;
     103: pop
     104: aload         6
     106: ldc           #31                 // String metadata
     108: invokestatic  #25                 // Method io/grpc/internal/JsonUtil.getObject:(Ljava/util/Map;Ljava/lang/String;)Ljava/util/Map;
     111: astore        9
     113: aload         6
     115: ldc           #32                 // String locality
     117: invokestatic  #25                 // Method io/grpc/internal/JsonUtil.getObject:(Ljava/util/Map;Ljava/lang/String;)Ljava/util/Map;
     120: astore        10
     122: aload_2
     123: aload         5
     125: invokevirtual #33                 // Method io/envoyproxy/envoy/config/core/v3/Node$Builder.build:()Lio/envoyproxy/envoy/config/core/v3/Node;
     128: invokevirtual #34                 // Method org/apache/dubbo/registry/xds/util/bootstrap/Bootstrapper$BootstrapInfo$Builder.node:(Lio/envoyproxy/envoy/config/core/v3/Node;)Lorg/apache/dubbo/registry/xds/util/bootstrap/Bootstrapper$BootstrapInfo$Builder;
     131: pop
     132: aload_1
     133: ldc           #35                 // String certificate_providers
     135: invokestatic  #25                 // Method io/grpc/internal/JsonUtil.getObject:(Ljava/util/Map;Ljava/lang/String;)Ljava/util/Map;
     138: astore        7
     140: aload         7
     142: ifnull        275
     145: new           #36                 // class java/util/HashMap
     148: dup
     149: aload         7
     151: invokeinterface #37,  1           // InterfaceMethod java/util/Map.size:()I
     156: invokespecial #38                 // Method java/util/HashMap."<init>":(I)V
     159: astore        8
     161: aload         7
     163: invokeinterface #39,  1           // InterfaceMethod java/util/Map.keySet:()Ljava/util/Set;
     168: invokeinterface #40,  1           // InterfaceMethod java/util/Set.iterator:()Ljava/util/Iterator;
     173: astore        9
     175: aload         9
     177: invokeinterface #41,  1           // InterfaceMethod java/util/Iterator.hasNext:()Z
     182: ifeq          268
     185: aload         9
     187: invokeinterface #42,  1           // InterfaceMethod java/util/Iterator.next:()Ljava/lang/Object;
     192: checkcast     #43                 // class java/lang/String
     195: astore        10
     197: aload         7
     199: aload         10
     201: invokestatic  #25                 // Method io/grpc/internal/JsonUtil.getObject:(Ljava/util/Map;Ljava/lang/String;)Ljava/util/Map;
     204: astore        11
     206: aload         11
     208: ldc           #44                 // String plugin_name
     210: invokestatic  #27                 // Method io/grpc/internal/JsonUtil.getString:(Ljava/util/Map;Ljava/lang/String;)Ljava/lang/String;
     213: ldc           #44                 // String plugin_name
     215: invokestatic  #45                 // Method checkForNull:(Ljava/lang/Object;Ljava/lang/String;)Ljava/lang/Object;
     218: checkcast     #43                 // class java/lang/String
     221: astore        12
     223: aload         11
     225: ldc           #46                 // String config
     227: invokestatic  #25                 // Method io/grpc/internal/JsonUtil.getObject:(Ljava/util/Map;Ljava/lang/String;)Ljava/util/Map;
     230: ldc           #46                 // String config
     232: invokestatic  #45                 // Method checkForNull:(Ljava/lang/Object;Ljava/lang/String;)Ljava/lang/Object;
     235: checkcast     #13                 // class java/util/Map
     238: astore        13
     240: new           #47                 // class org/apache/dubbo/registry/xds/util/bootstrap/CertificateProviderInfoImpl
     243: dup
     244: aload         12
     246: aload         13
     248: invokespecial #48                 // Method org/apache/dubbo/registry/xds/util/bootstrap/CertificateProviderInfoImpl."<init>":(Ljava/lang/String;Ljava/util/Map;)V
     251: astore        14
     253: aload         8
     255: aload         10
     257: aload         14
     259: invokeinterface #49,  3           // InterfaceMethod java/util/Map.put:(Ljava/lang/Object;Ljava/lang/Object;)Ljava/lang/Object;
     264: pop
     265: goto          175
     268: aload_2
     269: aload         8
     271: invokevirtual #50                 // Method org/apache/dubbo/registry/xds/util/bootstrap/Bootstrapper$BootstrapInfo$Builder.certProviders:(Ljava/util/Map;)Lorg/apache/dubbo/registry/xds/util/bootstrap/Bootstrapper$BootstrapInfo$Builder;
     274: pop
     275: aload_2
     276: invokevirtual #51                 // Method org/apache/dubbo/registry/xds/util/bootstrap/Bootstrapper$BootstrapInfo$Builder.build:()Lorg/apache/dubbo/registry/xds/util/bootstrap/Bootstrapper$BootstrapInfo;
     279: areturn

  private static java.util.List<org.apache.dubbo.registry.xds.util.bootstrap.Bootstrapper$ServerInfo> parseServerInfos(java.util.List<?>) throws org.apache.dubbo.registry.xds.XdsInitializationException;
    Code:
       0: new           #52                 // class java/util/LinkedList
       3: dup
       4: invokespecial #53                 // Method java/util/LinkedList."<init>":()V
       7: astore_1
       8: aload_0
       9: invokestatic  #54                 // Method io/grpc/internal/JsonUtil.checkObjectList:(Ljava/util/List;)Ljava/util/List;
      12: astore_2
      13: aload_2
      14: invokeinterface #55,  1           // InterfaceMethod java/util/List.iterator:()Ljava/util/Iterator;
      19: astore_3
      20: aload_3
      21: invokeinterface #41,  1           // InterfaceMethod java/util/Iterator.hasNext:()Z
      26: ifeq          200
      29: aload_3
      30: invokeinterface #42,  1           // InterfaceMethod java/util/Iterator.next:()Ljava/lang/Object;
      35: checkcast     #13                 // class java/util/Map
      38: astore        4
      40: aload         4
      42: ldc           #56                 // String server_uri
      44: invokestatic  #27                 // Method io/grpc/internal/JsonUtil.getString:(Ljava/util/Map;Ljava/lang/String;)Ljava/lang/String;
      47: astore        5
      49: aload         5
      51: ifnonnull     64
      54: new           #7                  // class org/apache/dubbo/registry/xds/XdsInitializationException
      57: dup
      58: ldc           #57                 // String Invalid bootstrap: missing \'server_uri\'
      60: invokespecial #11                 // Method org/apache/dubbo/registry/xds/XdsInitializationException."<init>":(Ljava/lang/String;)V
      63: athrow
      64: aload         4
      66: ldc           #58                 // String channel_creds
      68: invokestatic  #19                 // Method io/grpc/internal/JsonUtil.getList:(Ljava/util/Map;Ljava/lang/String;)Ljava/util/List;
      71: astore        6
      73: aload         6
      75: ifnull        88
      78: aload         6
      80: invokeinterface #59,  1           // InterfaceMethod java/util/List.isEmpty:()Z
      85: ifeq          121
      88: new           #7                  // class org/apache/dubbo/registry/xds/XdsInitializationException
      91: dup
      92: new           #60                 // class java/lang/StringBuilder
      95: dup
      96: invokespecial #61                 // Method java/lang/StringBuilder."<init>":()V
      99: ldc           #62                 // String Invalid bootstrap: server
     101: invokevirtual #63                 // Method java/lang/StringBuilder.append:(Ljava/lang/String;)Ljava/lang/StringBuilder;
     104: aload         5
     106: invokevirtual #63                 // Method java/lang/StringBuilder.append:(Ljava/lang/String;)Ljava/lang/StringBuilder;
     109: ldc           #64                 // String  \'channel_creds\' required
     111: invokevirtual #63                 // Method java/lang/StringBuilder.append:(Ljava/lang/String;)Ljava/lang/StringBuilder;
     114: invokevirtual #65                 // Method java/lang/StringBuilder.toString:()Ljava/lang/String;
     117: invokespecial #11                 // Method org/apache/dubbo/registry/xds/XdsInitializationException."<init>":(Ljava/lang/String;)V
     120: athrow
     121: aload         6
     123: invokestatic  #54                 // Method io/grpc/internal/JsonUtil.checkObjectList:(Ljava/util/List;)Ljava/util/List;
     126: aload         5
     128: invokestatic  #66                 // Method parseChannelCredentials:(Ljava/util/List;Ljava/lang/String;)Lio/grpc/ChannelCredentials;
     131: astore        7
     133: iconst_0
     134: istore        8
     136: iconst_0
     137: istore        9
     139: aload         4
     141: ldc           #67                 // String server_features
     143: invokestatic  #68                 // Method io/grpc/internal/JsonUtil.getListOfStrings:(Ljava/util/Map;Ljava/lang/String;)Ljava/util/List;
     146: astore        10
     148: aload         10
     150: ifnull        175
     153: aload         10
     155: ldc           #70                 // String xds_v3
     157: invokeinterface #71,  2           // InterfaceMethod java/util/List.contains:(Ljava/lang/Object;)Z
     162: istore        8
     164: aload         10
     166: ldc           #72                 // String ignore_resource_deletion
     168: invokeinterface #71,  2           // InterfaceMethod java/util/List.contains:(Ljava/lang/Object;)Z
     173: istore        9
     175: aload_1
     176: new           #73                 // class org/apache/dubbo/registry/xds/util/bootstrap/ServerInfoImpl
     179: dup
     180: aload         5
     182: aload         7
     184: iload         8
     186: iload         9
     188: invokespecial #74                 // Method org/apache/dubbo/registry/xds/util/bootstrap/ServerInfoImpl."<init>":(Ljava/lang/String;Lio/grpc/ChannelCredentials;ZZ)V
     191: invokeinterface #75,  2           // InterfaceMethod java/util/List.add:(Ljava/lang/Object;)Z
     196: pop
     197: goto          20
     200: aload_1
     201: areturn

  void setFileReader(org.apache.dubbo.registry.xds.util.bootstrap.BootstrapperImpl$FileReader);
    Code:
       0: aload_0
       1: aload_1
       2: putfield      #3                  // Field reader:Lorg/apache/dubbo/registry/xds/util/bootstrap/BootstrapperImpl$FileReader;
       5: return

  private static <T> T checkForNull(T, java.lang.String) throws org.apache.dubbo.registry.xds.XdsInitializationException;
    Code:
       0: aload_0
       1: ifnonnull     36
       4: new           #7                  // class org/apache/dubbo/registry/xds/XdsInitializationException
       7: dup
       8: new           #60                 // class java/lang/StringBuilder
      11: dup
      12: invokespecial #61                 // Method java/lang/StringBuilder."<init>":()V
      15: ldc           #76                 // String Invalid bootstrap: \'
      17: invokevirtual #63                 // Method java/lang/StringBuilder.append:(Ljava/lang/String;)Ljava/lang/StringBuilder;
      20: aload_1
      21: invokevirtual #63                 // Method java/lang/StringBuilder.append:(Ljava/lang/String;)Ljava/lang/StringBuilder;
      24: ldc           #77                 // String \' does not exist.
      26: invokevirtual #63                 // Method java/lang/StringBuilder.append:(Ljava/lang/String;)Ljava/lang/StringBuilder;
      29: invokevirtual #65                 // Method java/lang/StringBuilder.toString:()Ljava/lang/String;
      32: invokespecial #11                 // Method org/apache/dubbo/registry/xds/XdsInitializationException."<init>":(Ljava/lang/String;)V
      35: athrow
      36: aload_0
      37: areturn

  private static io.grpc.ChannelCredentials parseChannelCredentials(java.util.List<java.util.Map<java.lang.String, ?>>, java.lang.String) throws org.apache.dubbo.registry.xds.XdsInitializationException;
    Code:
       0: aconst_null
       1: areturn

  static {};
    Code:
       0: ldc           #78                 // String GRPC_XDS_BOOTSTRAP
       2: invokestatic  #79                 // Method java/lang/System.getenv:(Ljava/lang/String;)Ljava/lang/String;
       5: putstatic     #4                  // Field bootstrapPathFromEnvVar:Ljava/lang/String;
       8: ldc           #69                 // class org/apache/dubbo/registry/xds/util/bootstrap/BootstrapperImpl
      10: invokestatic  #80                 // Method org/apache/dubbo/common/logger/LoggerFactory.getLogger:(Ljava/lang/Class;)Lorg/apache/dubbo/common/logger/Logger;
      13: putstatic     #81                 // Field logger:Lorg/apache/dubbo/common/logger/Logger;
      16: return
}
