Compiled from "BootstrapInfoImpl.java"
public final class org.apache.dubbo.registry.xds.util.bootstrap.BootstrapInfoImpl extends org.apache.dubbo.registry.xds.util.bootstrap.Bootstrapper$BootstrapInfo {
  private final java.util.List<org.apache.dubbo.registry.xds.util.bootstrap.Bootstrapper$ServerInfo> servers;

  private final java.lang.String serverListenerResourceNameTemplate;

  private final java.util.Map<java.lang.String, org.apache.dubbo.registry.xds.util.bootstrap.Bootstrapper$CertificateProviderInfo> certProviders;

  private final io.envoyproxy.envoy.config.core.v3.Node node;

  org.apache.dubbo.registry.xds.util.bootstrap.BootstrapInfoImpl(java.util.List<org.apache.dubbo.registry.xds.util.bootstrap.Bootstrapper$ServerInfo>, java.lang.String, java.util.Map<java.lang.String, org.apache.dubbo.registry.xds.util.bootstrap.Bootstrapper$CertificateProviderInfo>, io.envoyproxy.envoy.config.core.v3.Node);
    Code:
       0: aload_0
       1: invokespecial #1                  // Method org/apache/dubbo/registry/xds/util/bootstrap/Bootstrapper$BootstrapInfo."<init>":()V
       4: aload_0
       5: aload_1
       6: putfield      #2                  // Field servers:Ljava/util/List;
       9: aload_0
      10: aload_2
      11: putfield      #3                  // Field serverListenerResourceNameTemplate:Ljava/lang/String;
      14: aload_0
      15: aload_3
      16: putfield      #4                  // Field certProviders:Ljava/util/Map;
      19: aload_0
      20: aload         4
      22: putfield      #5                  // Field node:Lio/envoyproxy/envoy/config/core/v3/Node;
      25: return

  public java.util.List<org.apache.dubbo.registry.xds.util.bootstrap.Bootstrapper$ServerInfo> servers();
    Code:
       0: aload_0
       1: getfield      #2                  // Field servers:Ljava/util/List;
       4: areturn

  public java.util.Map<java.lang.String, org.apache.dubbo.registry.xds.util.bootstrap.Bootstrapper$CertificateProviderInfo> certProviders();
    Code:
       0: aload_0
       1: getfield      #4                  // Field certProviders:Ljava/util/Map;
       4: areturn

  public io.envoyproxy.envoy.config.core.v3.Node node();
    Code:
       0: aload_0
       1: getfield      #5                  // Field node:Lio/envoyproxy/envoy/config/core/v3/Node;
       4: areturn

  public java.lang.String serverListenerResourceNameTemplate();
    Code:
       0: aload_0
       1: getfield      #3                  // Field serverListenerResourceNameTemplate:Ljava/lang/String;
       4: areturn

  public java.lang.String toString();
    Code:
       0: new           #6                  // class java/lang/StringBuilder
       3: dup
       4: invokespecial #7                  // Method java/lang/StringBuilder."<init>":()V
       7: ldc           #8                  // String BootstrapInfo{servers=
       9: invokevirtual #9                  // Method java/lang/StringBuilder.append:(Ljava/lang/String;)Ljava/lang/StringBuilder;
      12: aload_0
      13: getfield      #2                  // Field servers:Ljava/util/List;
      16: invokevirtual #10                 // Method java/lang/StringBuilder.append:(Ljava/lang/Object;)Ljava/lang/StringBuilder;
      19: ldc           #11                 // String , serverListenerResourceNameTemplate=
      21: invokevirtual #9                  // Method java/lang/StringBuilder.append:(Ljava/lang/String;)Ljava/lang/StringBuilder;
      24: aload_0
      25: getfield      #3                  // Field serverListenerResourceNameTemplate:Ljava/lang/String;
      28: invokevirtual #9                  // Method java/lang/StringBuilder.append:(Ljava/lang/String;)Ljava/lang/StringBuilder;
      31: ldc           #12                 // String , node=
      33: invokevirtual #9                  // Method java/lang/StringBuilder.append:(Ljava/lang/String;)Ljava/lang/StringBuilder;
      36: aload_0
      37: getfield      #5                  // Field node:Lio/envoyproxy/envoy/config/core/v3/Node;
      40: invokevirtual #10                 // Method java/lang/StringBuilder.append:(Ljava/lang/Object;)Ljava/lang/StringBuilder;
      43: ldc           #13                 // String , }
      45: invokevirtual #9                  // Method java/lang/StringBuilder.append:(Ljava/lang/String;)Ljava/lang/StringBuilder;
      48: invokevirtual #14                 // Method java/lang/StringBuilder.toString:()Ljava/lang/String;
      51: areturn
}
