Compiled from "BootstrapperImpl.java"
final class org.apache.dubbo.registry.xds.util.bootstrap.BootstrapperImpl$LocalFileReader extends java.lang.Enum<org.apache.dubbo.registry.xds.util.bootstrap.BootstrapperImpl$LocalFileReader> implements org.apache.dubbo.registry.xds.util.bootstrap.BootstrapperImpl$FileReader {
  public static final org.apache.dubbo.registry.xds.util.bootstrap.BootstrapperImpl$LocalFileReader INSTANCE;

  private static final org.apache.dubbo.registry.xds.util.bootstrap.BootstrapperImpl$LocalFileReader[] $VALUES;

  public static org.apache.dubbo.registry.xds.util.bootstrap.BootstrapperImpl$LocalFileReader[] values();
    Code:
       0: getstatic     #1                  // Field $VALUES:[Lorg/apache/dubbo/registry/xds/util/bootstrap/BootstrapperImpl$LocalFileReader;
       3: invokevirtual #2                  // Method "[Lorg/apache/dubbo/registry/xds/util/bootstrap/BootstrapperImpl$LocalFileReader;".clone:()Ljava/lang/Object;
       6: checkcast     #3                  // class "[Lorg/apache/dubbo/registry/xds/util/bootstrap/BootstrapperImpl$LocalFileReader;"
       9: areturn

  public static org.apache.dubbo.registry.xds.util.bootstrap.BootstrapperImpl$LocalFileReader valueOf(java.lang.String);
    Code:
       0: ldc           #4                  // class org/apache/dubbo/registry/xds/util/bootstrap/BootstrapperImpl$LocalFileReader
       2: aload_0
       3: invokestatic  #5                  // Method java/lang/Enum.valueOf:(Ljava/lang/Class;Ljava/lang/String;)Ljava/lang/Enum;
       6: checkcast     #4                  // class org/apache/dubbo/registry/xds/util/bootstrap/BootstrapperImpl$LocalFileReader
       9: areturn

  private org.apache.dubbo.registry.xds.util.bootstrap.BootstrapperImpl$LocalFileReader();
    Code:
       0: aload_0
       1: aload_1
       2: iload_2
       3: invokespecial #6                  // Method java/lang/Enum."<init>":(Ljava/lang/String;I)V
       6: return

  public java.lang.String readFile(java.lang.String) throws java.io.IOException;
    Code:
       0: new           #7                  // class java/lang/String
       3: dup
       4: aload_1
       5: iconst_0
       6: anewarray     #7                  // class java/lang/String
       9: invokestatic  #8                  // Method java/nio/file/Paths.get:(Ljava/lang/String;[Ljava/lang/String;)Ljava/nio/file/Path;
      12: invokestatic  #9                  // Method java/nio/file/Files.readAllBytes:(Ljava/nio/file/Path;)[B
      15: getstatic     #10                 // Field java/nio/charset/StandardCharsets.UTF_8:Ljava/nio/charset/Charset;
      18: invokespecial #11                 // Method java/lang/String."<init>":([BLjava/nio/charset/Charset;)V
      21: areturn

  static {};
    Code:
       0: new           #4                  // class org/apache/dubbo/registry/xds/util/bootstrap/BootstrapperImpl$LocalFileReader
       3: dup
       4: ldc           #12                 // String INSTANCE
       6: iconst_0
       7: invokespecial #13                 // Method "<init>":(Ljava/lang/String;I)V
      10: putstatic     #14                 // Field INSTANCE:Lorg/apache/dubbo/registry/xds/util/bootstrap/BootstrapperImpl$LocalFileReader;
      13: iconst_1
      14: anewarray     #4                  // class org/apache/dubbo/registry/xds/util/bootstrap/BootstrapperImpl$LocalFileReader
      17: dup
      18: iconst_0
      19: getstatic     #14                 // Field INSTANCE:Lorg/apache/dubbo/registry/xds/util/bootstrap/BootstrapperImpl$LocalFileReader;
      22: aastore
      23: putstatic     #1                  // Field $VALUES:[Lorg/apache/dubbo/registry/xds/util/bootstrap/BootstrapperImpl$LocalFileReader;
      26: return
}
