Compiled from "CertificateProviderInfoImpl.java"
final class org.apache.dubbo.registry.xds.util.bootstrap.CertificateProviderInfoImpl extends org.apache.dubbo.registry.xds.util.bootstrap.Bootstrapper$CertificateProviderInfo {
  private final java.lang.String pluginName;

  private final java.util.Map<java.lang.String, ?> config;

  org.apache.dubbo.registry.xds.util.bootstrap.CertificateProviderInfoImpl(java.lang.String, java.util.Map<java.lang.String, ?>);
    Code:
       0: aload_0
       1: invokespecial #1                  // Method org/apache/dubbo/registry/xds/util/bootstrap/Bootstrapper$CertificateProviderInfo."<init>":()V
       4: aload_0
       5: aload_1
       6: putfield      #2                  // Field pluginName:Ljava/lang/String;
       9: aload_0
      10: aload_2
      11: putfield      #3                  // Field config:Ljava/util/Map;
      14: return

  public java.lang.String pluginName();
    Code:
       0: aload_0
       1: getfield      #2                  // Field pluginName:Ljava/lang/String;
       4: areturn

  public java.util.Map<java.lang.String, ?> config();
    Code:
       0: aload_0
       1: getfield      #3                  // Field config:Ljava/util/Map;
       4: areturn

  public java.lang.String toString();
    Code:
       0: new           #4                  // class java/lang/StringBuilder
       3: dup
       4: invokespecial #5                  // Method java/lang/StringBuilder."<init>":()V
       7: ldc           #6                  // String CertificateProviderInfo{pluginName=
       9: invokevirtual #7                  // Method java/lang/StringBuilder.append:(Ljava/lang/String;)Ljava/lang/StringBuilder;
      12: aload_0
      13: getfield      #2                  // Field pluginName:Ljava/lang/String;
      16: invokevirtual #7                  // Method java/lang/StringBuilder.append:(Ljava/lang/String;)Ljava/lang/StringBuilder;
      19: ldc           #8                  // String , config=
      21: invokevirtual #7                  // Method java/lang/StringBuilder.append:(Ljava/lang/String;)Ljava/lang/StringBuilder;
      24: aload_0
      25: getfield      #3                  // Field config:Ljava/util/Map;
      28: invokevirtual #9                  // Method java/lang/StringBuilder.append:(Ljava/lang/Object;)Ljava/lang/StringBuilder;
      31: ldc           #10                 // String }
      33: invokevirtual #7                  // Method java/lang/StringBuilder.append:(Ljava/lang/String;)Ljava/lang/StringBuilder;
      36: invokevirtual #11                 // Method java/lang/StringBuilder.toString:()Ljava/lang/String;
      39: areturn
}
