Compiled from "ServerInfoImpl.java"
final class org.apache.dubbo.registry.xds.util.bootstrap.ServerInfoImpl extends org.apache.dubbo.registry.xds.util.bootstrap.Bootstrapper$ServerInfo {
  private final java.lang.String target;

  private final io.grpc.ChannelCredentials channelCredentials;

  private final boolean useProtocolV3;

  private final boolean ignoreResourceDeletion;

  org.apache.dubbo.registry.xds.util.bootstrap.ServerInfoImpl(java.lang.String, io.grpc.ChannelCredentials, boolean, boolean);
    Code:
       0: aload_0
       1: invokespecial #1                  // Method org/apache/dubbo/registry/xds/util/bootstrap/Bootstrapper$ServerInfo."<init>":()V
       4: aload_0
       5: aload_1
       6: putfield      #2                  // Field target:Ljava/lang/String;
       9: aload_0
      10: aload_2
      11: putfield      #3                  // Field channelCredentials:Lio/grpc/ChannelCredentials;
      14: aload_0
      15: iload_3
      16: putfield      #4                  // Field useProtocolV3:Z
      19: aload_0
      20: iload         4
      22: putfield      #5                  // Field ignoreResourceDeletion:Z
      25: return

  public java.lang.String target();
    Code:
       0: aload_0
       1: getfield      #2                  // Field target:Ljava/lang/String;
       4: areturn

  io.grpc.ChannelCredentials channelCredentials();
    Code:
       0: aload_0
       1: getfield      #3                  // Field channelCredentials:Lio/grpc/ChannelCredentials;
       4: areturn

  boolean useProtocolV3();
    Code:
       0: aload_0
       1: getfield      #4                  // Field useProtocolV3:Z
       4: ireturn

  boolean ignoreResourceDeletion();
    Code:
       0: aload_0
       1: getfield      #5                  // Field ignoreResourceDeletion:Z
       4: ireturn

  public java.lang.String toString();
    Code:
       0: new           #6                  // class java/lang/StringBuilder
       3: dup
       4: invokespecial #7                  // Method java/lang/StringBuilder."<init>":()V
       7: ldc           #8                  // String ServerInfo{target=
       9: invokevirtual #9                  // Method java/lang/StringBuilder.append:(Ljava/lang/String;)Ljava/lang/StringBuilder;
      12: aload_0
      13: getfield      #2                  // Field target:Ljava/lang/String;
      16: invokevirtual #9                  // Method java/lang/StringBuilder.append:(Ljava/lang/String;)Ljava/lang/StringBuilder;
      19: ldc           #10                 // String , channelCredentials=
      21: invokevirtual #9                  // Method java/lang/StringBuilder.append:(Ljava/lang/String;)Ljava/lang/StringBuilder;
      24: aload_0
      25: getfield      #3                  // Field channelCredentials:Lio/grpc/ChannelCredentials;
      28: invokevirtual #11                 // Method java/lang/StringBuilder.append:(Ljava/lang/Object;)Ljava/lang/StringBuilder;
      31: ldc           #12                 // String , useProtocolV3=
      33: invokevirtual #9                  // Method java/lang/StringBuilder.append:(Ljava/lang/String;)Ljava/lang/StringBuilder;
      36: aload_0
      37: getfield      #4                  // Field useProtocolV3:Z
      40: invokevirtual #13                 // Method java/lang/StringBuilder.append:(Z)Ljava/lang/StringBuilder;
      43: ldc           #14                 // String , ignoreResourceDeletion=
      45: invokevirtual #9                  // Method java/lang/StringBuilder.append:(Ljava/lang/String;)Ljava/lang/StringBuilder;
      48: aload_0
      49: getfield      #5                  // Field ignoreResourceDeletion:Z
      52: invokevirtual #13                 // Method java/lang/StringBuilder.append:(Z)Ljava/lang/StringBuilder;
      55: ldc           #15                 // String }
      57: invokevirtual #9                  // Method java/lang/StringBuilder.append:(Ljava/lang/String;)Ljava/lang/StringBuilder;
      60: invokevirtual #16                 // Method java/lang/StringBuilder.toString:()Ljava/lang/String;
      63: areturn
}
