Compiled from "AnsiBackground.java"
public final class org.springframework.boot.ansi.AnsiBackground extends java.lang.Enum<org.springframework.boot.ansi.AnsiBackground> implements org.springframework.boot.ansi.AnsiElement {
  public static final org.springframework.boot.ansi.AnsiBackground DEFAULT;

  public static final org.springframework.boot.ansi.AnsiBackground BLACK;

  public static final org.springframework.boot.ansi.AnsiBackground RED;

  public static final org.springframework.boot.ansi.AnsiBackground GREEN;

  public static final org.springframework.boot.ansi.AnsiBackground YELLOW;

  public static final org.springframework.boot.ansi.AnsiBackground BLUE;

  public static final org.springframework.boot.ansi.AnsiBackground MAGENTA;

  public static final org.springframework.boot.ansi.AnsiBackground CYAN;

  public static final org.springframework.boot.ansi.AnsiBackground WHITE;

  public static final org.springframework.boot.ansi.AnsiBackground BRIGHT_BLACK;

  public static final org.springframework.boot.ansi.AnsiBackground BRIGHT_RED;

  public static final org.springframework.boot.ansi.AnsiBackground BRIGHT_GREEN;

  public static final org.springframework.boot.ansi.AnsiBackground BRIGHT_YELLOW;

  public static final org.springframework.boot.ansi.AnsiBackground BRIGHT_BLUE;

  public static final org.springframework.boot.ansi.AnsiBackground BRIGHT_MAGENTA;

  public static final org.springframework.boot.ansi.AnsiBackground BRIGHT_CYAN;

  public static final org.springframework.boot.ansi.AnsiBackground BRIGHT_WHITE;

  private final java.lang.String code;

  private static final org.springframework.boot.ansi.AnsiBackground[] $VALUES;

  public static org.springframework.boot.ansi.AnsiBackground[] values();
    Code:
       0: getstatic     #55                 // Field $VALUES:[Lorg/springframework/boot/ansi/AnsiBackground;
       3: invokevirtual #59                 // Method "[Lorg/springframework/boot/ansi/AnsiBackground;".clone:()Ljava/lang/Object;
       6: checkcast     #60                 // class "[Lorg/springframework/boot/ansi/AnsiBackground;"
       9: areturn

  public static org.springframework.boot.ansi.AnsiBackground valueOf(java.lang.String);
    Code:
       0: ldc           #1                  // class org/springframework/boot/ansi/AnsiBackground
       2: aload_0
       3: invokestatic  #64                 // Method java/lang/Enum.valueOf:(Ljava/lang/Class;Ljava/lang/String;)Ljava/lang/Enum;
       6: checkcast     #1                  // class org/springframework/boot/ansi/AnsiBackground
       9: areturn

  private org.springframework.boot.ansi.AnsiBackground(java.lang.String);
    Code:
       0: aload_0
       1: aload_1
       2: iload_2
       3: invokespecial #70                 // Method java/lang/Enum."<init>":(Ljava/lang/String;I)V
       6: aload_0
       7: aload_3
       8: putfield      #74                 // Field code:Ljava/lang/String;
      11: return

  public java.lang.String toString();
    Code:
       0: aload_0
       1: getfield      #74                 // Field code:Ljava/lang/String;
       4: areturn

  private static org.springframework.boot.ansi.AnsiBackground[] $values();
    Code:
       0: bipush        17
       2: anewarray     #1                  // class org/springframework/boot/ansi/AnsiBackground
       5: dup
       6: iconst_0
       7: getstatic     #3                  // Field DEFAULT:Lorg/springframework/boot/ansi/AnsiBackground;
      10: aastore
      11: dup
      12: iconst_1
      13: getstatic     #7                  // Field BLACK:Lorg/springframework/boot/ansi/AnsiBackground;
      16: aastore
      17: dup
      18: iconst_2
      19: getstatic     #10                 // Field RED:Lorg/springframework/boot/ansi/AnsiBackground;
      22: aastore
      23: dup
      24: iconst_3
      25: getstatic     #13                 // Field GREEN:Lorg/springframework/boot/ansi/AnsiBackground;
      28: aastore
      29: dup
      30: iconst_4
      31: getstatic     #16                 // Field YELLOW:Lorg/springframework/boot/ansi/AnsiBackground;
      34: aastore
      35: dup
      36: iconst_5
      37: getstatic     #19                 // Field BLUE:Lorg/springframework/boot/ansi/AnsiBackground;
      40: aastore
      41: dup
      42: bipush        6
      44: getstatic     #22                 // Field MAGENTA:Lorg/springframework/boot/ansi/AnsiBackground;
      47: aastore
      48: dup
      49: bipush        7
      51: getstatic     #25                 // Field CYAN:Lorg/springframework/boot/ansi/AnsiBackground;
      54: aastore
      55: dup
      56: bipush        8
      58: getstatic     #28                 // Field WHITE:Lorg/springframework/boot/ansi/AnsiBackground;
      61: aastore
      62: dup
      63: bipush        9
      65: getstatic     #31                 // Field BRIGHT_BLACK:Lorg/springframework/boot/ansi/AnsiBackground;
      68: aastore
      69: dup
      70: bipush        10
      72: getstatic     #34                 // Field BRIGHT_RED:Lorg/springframework/boot/ansi/AnsiBackground;
      75: aastore
      76: dup
      77: bipush        11
      79: getstatic     #37                 // Field BRIGHT_GREEN:Lorg/springframework/boot/ansi/AnsiBackground;
      82: aastore
      83: dup
      84: bipush        12
      86: getstatic     #40                 // Field BRIGHT_YELLOW:Lorg/springframework/boot/ansi/AnsiBackground;
      89: aastore
      90: dup
      91: bipush        13
      93: getstatic     #43                 // Field BRIGHT_BLUE:Lorg/springframework/boot/ansi/AnsiBackground;
      96: aastore
      97: dup
      98: bipush        14
     100: getstatic     #46                 // Field BRIGHT_MAGENTA:Lorg/springframework/boot/ansi/AnsiBackground;
     103: aastore
     104: dup
     105: bipush        15
     107: getstatic     #49                 // Field BRIGHT_CYAN:Lorg/springframework/boot/ansi/AnsiBackground;
     110: aastore
     111: dup
     112: bipush        16
     114: getstatic     #52                 // Field BRIGHT_WHITE:Lorg/springframework/boot/ansi/AnsiBackground;
     117: aastore
     118: areturn

  static {};
    Code:
       0: new           #1                  // class org/springframework/boot/ansi/AnsiBackground
       3: dup
       4: ldc           #78                 // String DEFAULT
       6: iconst_0
       7: ldc           #79                 // String 49
       9: invokespecial #81                 // Method "<init>":(Ljava/lang/String;ILjava/lang/String;)V
      12: putstatic     #3                  // Field DEFAULT:Lorg/springframework/boot/ansi/AnsiBackground;
      15: new           #1                  // class org/springframework/boot/ansi/AnsiBackground
      18: dup
      19: ldc           #84                 // String BLACK
      21: iconst_1
      22: ldc           #85                 // String 40
      24: invokespecial #81                 // Method "<init>":(Ljava/lang/String;ILjava/lang/String;)V
      27: putstatic     #7                  // Field BLACK:Lorg/springframework/boot/ansi/AnsiBackground;
      30: new           #1                  // class org/springframework/boot/ansi/AnsiBackground
      33: dup
      34: ldc           #87                 // String RED
      36: iconst_2
      37: ldc           #88                 // String 41
      39: invokespecial #81                 // Method "<init>":(Ljava/lang/String;ILjava/lang/String;)V
      42: putstatic     #10                 // Field RED:Lorg/springframework/boot/ansi/AnsiBackground;
      45: new           #1                  // class org/springframework/boot/ansi/AnsiBackground
      48: dup
      49: ldc           #90                 // String GREEN
      51: iconst_3
      52: ldc           #91                 // String 42
      54: invokespecial #81                 // Method "<init>":(Ljava/lang/String;ILjava/lang/String;)V
      57: putstatic     #13                 // Field GREEN:Lorg/springframework/boot/ansi/AnsiBackground;
      60: new           #1                  // class org/springframework/boot/ansi/AnsiBackground
      63: dup
      64: ldc           #93                 // String YELLOW
      66: iconst_4
      67: ldc           #94                 // String 43
      69: invokespecial #81                 // Method "<init>":(Ljava/lang/String;ILjava/lang/String;)V
      72: putstatic     #16                 // Field YELLOW:Lorg/springframework/boot/ansi/AnsiBackground;
      75: new           #1                  // class org/springframework/boot/ansi/AnsiBackground
      78: dup
      79: ldc           #96                 // String BLUE
      81: iconst_5
      82: ldc           #97                 // String 44
      84: invokespecial #81                 // Method "<init>":(Ljava/lang/String;ILjava/lang/String;)V
      87: putstatic     #19                 // Field BLUE:Lorg/springframework/boot/ansi/AnsiBackground;
      90: new           #1                  // class org/springframework/boot/ansi/AnsiBackground
      93: dup
      94: ldc           #99                 // String MAGENTA
      96: bipush        6
      98: ldc           #100                // String 45
     100: invokespecial #81                 // Method "<init>":(Ljava/lang/String;ILjava/lang/String;)V
     103: putstatic     #22                 // Field MAGENTA:Lorg/springframework/boot/ansi/AnsiBackground;
     106: new           #1                  // class org/springframework/boot/ansi/AnsiBackground
     109: dup
     110: ldc           #102                // String CYAN
     112: bipush        7
     114: ldc           #103                // String 46
     116: invokespecial #81                 // Method "<init>":(Ljava/lang/String;ILjava/lang/String;)V
     119: putstatic     #25                 // Field CYAN:Lorg/springframework/boot/ansi/AnsiBackground;
     122: new           #1                  // class org/springframework/boot/ansi/AnsiBackground
     125: dup
     126: ldc           #105                // String WHITE
     128: bipush        8
     130: ldc           #106                // String 47
     132: invokespecial #81                 // Method "<init>":(Ljava/lang/String;ILjava/lang/String;)V
     135: putstatic     #28                 // Field WHITE:Lorg/springframework/boot/ansi/AnsiBackground;
     138: new           #1                  // class org/springframework/boot/ansi/AnsiBackground
     141: dup
     142: ldc           #108                // String BRIGHT_BLACK
     144: bipush        9
     146: ldc           #109                // String 100
     148: invokespecial #81                 // Method "<init>":(Ljava/lang/String;ILjava/lang/String;)V
     151: putstatic     #31                 // Field BRIGHT_BLACK:Lorg/springframework/boot/ansi/AnsiBackground;
     154: new           #1                  // class org/springframework/boot/ansi/AnsiBackground
     157: dup
     158: ldc           #111                // String BRIGHT_RED
     160: bipush        10
     162: ldc           #112                // String 101
     164: invokespecial #81                 // Method "<init>":(Ljava/lang/String;ILjava/lang/String;)V
     167: putstatic     #34                 // Field BRIGHT_RED:Lorg/springframework/boot/ansi/AnsiBackground;
     170: new           #1                  // class org/springframework/boot/ansi/AnsiBackground
     173: dup
     174: ldc           #114                // String BRIGHT_GREEN
     176: bipush        11
     178: ldc           #115                // String 102
     180: invokespecial #81                 // Method "<init>":(Ljava/lang/String;ILjava/lang/String;)V
     183: putstatic     #37                 // Field BRIGHT_GREEN:Lorg/springframework/boot/ansi/AnsiBackground;
     186: new           #1                  // class org/springframework/boot/ansi/AnsiBackground
     189: dup
     190: ldc           #117                // String BRIGHT_YELLOW
     192: bipush        12
     194: ldc           #118                // String 103
     196: invokespecial #81                 // Method "<init>":(Ljava/lang/String;ILjava/lang/String;)V
     199: putstatic     #40                 // Field BRIGHT_YELLOW:Lorg/springframework/boot/ansi/AnsiBackground;
     202: new           #1                  // class org/springframework/boot/ansi/AnsiBackground
     205: dup
     206: ldc           #120                // String BRIGHT_BLUE
     208: bipush        13
     210: ldc           #121                // String 104
     212: invokespecial #81                 // Method "<init>":(Ljava/lang/String;ILjava/lang/String;)V
     215: putstatic     #43                 // Field BRIGHT_BLUE:Lorg/springframework/boot/ansi/AnsiBackground;
     218: new           #1                  // class org/springframework/boot/ansi/AnsiBackground
     221: dup
     222: ldc           #123                // String BRIGHT_MAGENTA
     224: bipush        14
     226: ldc           #124                // String 105
     228: invokespecial #81                 // Method "<init>":(Ljava/lang/String;ILjava/lang/String;)V
     231: putstatic     #46                 // Field BRIGHT_MAGENTA:Lorg/springframework/boot/ansi/AnsiBackground;
     234: new           #1                  // class org/springframework/boot/ansi/AnsiBackground
     237: dup
     238: ldc           #126                // String BRIGHT_CYAN
     240: bipush        15
     242: ldc           #127                // String 106
     244: invokespecial #81                 // Method "<init>":(Ljava/lang/String;ILjava/lang/String;)V
     247: putstatic     #49                 // Field BRIGHT_CYAN:Lorg/springframework/boot/ansi/AnsiBackground;
     250: new           #1                  // class org/springframework/boot/ansi/AnsiBackground
     253: dup
     254: ldc           #129                // String BRIGHT_WHITE
     256: bipush        16
     258: ldc           #130                // String 107
     260: invokespecial #81                 // Method "<init>":(Ljava/lang/String;ILjava/lang/String;)V
     263: putstatic     #52                 // Field BRIGHT_WHITE:Lorg/springframework/boot/ansi/AnsiBackground;
     266: invokestatic  #132                // Method $values:()[Lorg/springframework/boot/ansi/AnsiBackground;
     269: putstatic     #55                 // Field $VALUES:[Lorg/springframework/boot/ansi/AnsiBackground;
     272: return
}
