Compiled from "AnsiOutput.java"
public final class org.springframework.boot.ansi.AnsiOutput$Enabled extends java.lang.Enum<org.springframework.boot.ansi.AnsiOutput$Enabled> {
  public static final org.springframework.boot.ansi.AnsiOutput$Enabled DETECT;

  public static final org.springframework.boot.ansi.AnsiOutput$Enabled ALWAYS;

  public static final org.springframework.boot.ansi.AnsiOutput$Enabled NEVER;

  private static final org.springframework.boot.ansi.AnsiOutput$Enabled[] $VALUES;

  public static org.springframework.boot.ansi.AnsiOutput$Enabled[] values();
    Code:
       0: getstatic     #13                 // Field $VALUES:[Lorg/springframework/boot/ansi/AnsiOutput$Enabled;
       3: invokevirtual #17                 // Method "[Lorg/springframework/boot/ansi/AnsiOutput$Enabled;".clone:()Ljava/lang/Object;
       6: checkcast     #18                 // class "[Lorg/springframework/boot/ansi/AnsiOutput$Enabled;"
       9: areturn

  public static org.springframework.boot.ansi.AnsiOutput$Enabled valueOf(java.lang.String);
    Code:
       0: ldc           #1                  // class org/springframework/boot/ansi/AnsiOutput$Enabled
       2: aload_0
       3: invokestatic  #22                 // Method java/lang/Enum.valueOf:(Ljava/lang/Class;Ljava/lang/String;)Ljava/lang/Enum;
       6: checkcast     #1                  // class org/springframework/boot/ansi/AnsiOutput$Enabled
       9: areturn

  private org.springframework.boot.ansi.AnsiOutput$Enabled();
    Code:
       0: aload_0
       1: aload_1
       2: iload_2
       3: invokespecial #28                 // Method java/lang/Enum."<init>":(Ljava/lang/String;I)V
       6: return

  private static org.springframework.boot.ansi.AnsiOutput$Enabled[] $values();
    Code:
       0: iconst_3
       1: anewarray     #1                  // class org/springframework/boot/ansi/AnsiOutput$Enabled
       4: dup
       5: iconst_0
       6: getstatic     #3                  // Field DETECT:Lorg/springframework/boot/ansi/AnsiOutput$Enabled;
       9: aastore
      10: dup
      11: iconst_1
      12: getstatic     #7                  // Field ALWAYS:Lorg/springframework/boot/ansi/AnsiOutput$Enabled;
      15: aastore
      16: dup
      17: iconst_2
      18: getstatic     #10                 // Field NEVER:Lorg/springframework/boot/ansi/AnsiOutput$Enabled;
      21: aastore
      22: areturn

  static {};
    Code:
       0: new           #1                  // class org/springframework/boot/ansi/AnsiOutput$Enabled
       3: dup
       4: ldc           #32                 // String DETECT
       6: iconst_0
       7: invokespecial #33                 // Method "<init>":(Ljava/lang/String;I)V
      10: putstatic     #3                  // Field DETECT:Lorg/springframework/boot/ansi/AnsiOutput$Enabled;
      13: new           #1                  // class org/springframework/boot/ansi/AnsiOutput$Enabled
      16: dup
      17: ldc           #34                 // String ALWAYS
      19: iconst_1
      20: invokespecial #33                 // Method "<init>":(Ljava/lang/String;I)V
      23: putstatic     #7                  // Field ALWAYS:Lorg/springframework/boot/ansi/AnsiOutput$Enabled;
      26: new           #1                  // class org/springframework/boot/ansi/AnsiOutput$Enabled
      29: dup
      30: ldc           #35                 // String NEVER
      32: iconst_2
      33: invokespecial #33                 // Method "<init>":(Ljava/lang/String;I)V
      36: putstatic     #10                 // Field NEVER:Lorg/springframework/boot/ansi/AnsiOutput$Enabled;
      39: invokestatic  #36                 // Method $values:()[Lorg/springframework/boot/ansi/AnsiOutput$Enabled;
      42: putstatic     #13                 // Field $VALUES:[Lorg/springframework/boot/ansi/AnsiOutput$Enabled;
      45: return
}
