Compiled from "AnsiStyle.java"
public final class org.springframework.boot.ansi.AnsiStyle extends java.lang.Enum<org.springframework.boot.ansi.AnsiStyle> implements org.springframework.boot.ansi.AnsiElement {
  public static final org.springframework.boot.ansi.AnsiStyle NORMAL;

  public static final org.springframework.boot.ansi.AnsiStyle BOLD;

  public static final org.springframework.boot.ansi.AnsiStyle FAINT;

  public static final org.springframework.boot.ansi.AnsiStyle ITALIC;

  public static final org.springframework.boot.ansi.AnsiStyle UNDERLINE;

  private final java.lang.String code;

  private static final org.springframework.boot.ansi.AnsiStyle[] $VALUES;

  public static org.springframework.boot.ansi.AnsiStyle[] values();
    Code:
       0: getstatic     #19                 // Field $VALUES:[Lorg/springframework/boot/ansi/AnsiStyle;
       3: invokevirtual #23                 // Method "[Lorg/springframework/boot/ansi/AnsiStyle;".clone:()Ljava/lang/Object;
       6: checkcast     #24                 // class "[Lorg/springframework/boot/ansi/AnsiStyle;"
       9: areturn

  public static org.springframework.boot.ansi.AnsiStyle valueOf(java.lang.String);
    Code:
       0: ldc           #1                  // class org/springframework/boot/ansi/AnsiStyle
       2: aload_0
       3: invokestatic  #28                 // Method java/lang/Enum.valueOf:(Ljava/lang/Class;Ljava/lang/String;)Ljava/lang/Enum;
       6: checkcast     #1                  // class org/springframework/boot/ansi/AnsiStyle
       9: areturn

  private org.springframework.boot.ansi.AnsiStyle(java.lang.String);
    Code:
       0: aload_0
       1: aload_1
       2: iload_2
       3: invokespecial #34                 // Method java/lang/Enum."<init>":(Ljava/lang/String;I)V
       6: aload_0
       7: aload_3
       8: putfield      #38                 // Field code:Ljava/lang/String;
      11: return

  public java.lang.String toString();
    Code:
       0: aload_0
       1: getfield      #38                 // Field code:Ljava/lang/String;
       4: areturn

  private static org.springframework.boot.ansi.AnsiStyle[] $values();
    Code:
       0: iconst_5
       1: anewarray     #1                  // class org/springframework/boot/ansi/AnsiStyle
       4: dup
       5: iconst_0
       6: getstatic     #3                  // Field NORMAL:Lorg/springframework/boot/ansi/AnsiStyle;
       9: aastore
      10: dup
      11: iconst_1
      12: getstatic     #7                  // Field BOLD:Lorg/springframework/boot/ansi/AnsiStyle;
      15: aastore
      16: dup
      17: iconst_2
      18: getstatic     #10                 // Field FAINT:Lorg/springframework/boot/ansi/AnsiStyle;
      21: aastore
      22: dup
      23: iconst_3
      24: getstatic     #13                 // Field ITALIC:Lorg/springframework/boot/ansi/AnsiStyle;
      27: aastore
      28: dup
      29: iconst_4
      30: getstatic     #16                 // Field UNDERLINE:Lorg/springframework/boot/ansi/AnsiStyle;
      33: aastore
      34: areturn

  static {};
    Code:
       0: new           #1                  // class org/springframework/boot/ansi/AnsiStyle
       3: dup
       4: ldc           #42                 // String NORMAL
       6: iconst_0
       7: ldc           #43                 // String 0
       9: invokespecial #45                 // Method "<init>":(Ljava/lang/String;ILjava/lang/String;)V
      12: putstatic     #3                  // Field NORMAL:Lorg/springframework/boot/ansi/AnsiStyle;
      15: new           #1                  // class org/springframework/boot/ansi/AnsiStyle
      18: dup
      19: ldc           #48                 // String BOLD
      21: iconst_1
      22: ldc           #49                 // String 1
      24: invokespecial #45                 // Method "<init>":(Ljava/lang/String;ILjava/lang/String;)V
      27: putstatic     #7                  // Field BOLD:Lorg/springframework/boot/ansi/AnsiStyle;
      30: new           #1                  // class org/springframework/boot/ansi/AnsiStyle
      33: dup
      34: ldc           #51                 // String FAINT
      36: iconst_2
      37: ldc           #52                 // String 2
      39: invokespecial #45                 // Method "<init>":(Ljava/lang/String;ILjava/lang/String;)V
      42: putstatic     #10                 // Field FAINT:Lorg/springframework/boot/ansi/AnsiStyle;
      45: new           #1                  // class org/springframework/boot/ansi/AnsiStyle
      48: dup
      49: ldc           #54                 // String ITALIC
      51: iconst_3
      52: ldc           #55                 // String 3
      54: invokespecial #45                 // Method "<init>":(Ljava/lang/String;ILjava/lang/String;)V
      57: putstatic     #13                 // Field ITALIC:Lorg/springframework/boot/ansi/AnsiStyle;
      60: new           #1                  // class org/springframework/boot/ansi/AnsiStyle
      63: dup
      64: ldc           #57                 // String UNDERLINE
      66: iconst_4
      67: ldc           #58                 // String 4
      69: invokespecial #45                 // Method "<init>":(Ljava/lang/String;ILjava/lang/String;)V
      72: putstatic     #16                 // Field UNDERLINE:Lorg/springframework/boot/ansi/AnsiStyle;
      75: invokestatic  #60                 // Method $values:()[Lorg/springframework/boot/ansi/AnsiStyle;
      78: putstatic     #19                 // Field $VALUES:[Lorg/springframework/boot/ansi/AnsiStyle;
      81: return
}
