Compiled from "DubboLogo.java"
public class org.apache.dubbo.qos.server.DubboLogo {
  public static final java.lang.String DUBBO;

  public org.apache.dubbo.qos.server.DubboLogo();
    Code:
       0: aload_0
       1: invokespecial #1                  // Method java/lang/Object."<init>":()V
       4: return

  static {};
    Code:
       0: new           #2                  // class java/lang/StringBuilder
       3: dup
       4: invokespecial #3                  // Method java/lang/StringBuilder."<init>":()V
       7: ldc           #4                  // String    ___   __  __ ___   ___   ____
       9: invokevirtual #5                  // Method java/lang/StringBuilder.append:(Ljava/lang/String;)Ljava/lang/StringBuilder;
      12: invokestatic  #6                  // Method java/lang/System.lineSeparator:()Ljava/lang/String;
      15: invokevirtual #5                  // Method java/lang/StringBuilder.append:(Ljava/lang/String;)Ljava/lang/StringBuilder;
      18: ldc           #7                  // String   / _ \\ / / / // _ ) / _ ) / __ \\
      20: invokevirtual #5                  // Method java/lang/StringBuilder.append:(Ljava/lang/String;)Ljava/lang/StringBuilder;
      23: invokestatic  #6                  // Method java/lang/System.lineSeparator:()Ljava/lang/String;
      26: invokevirtual #5                  // Method java/lang/StringBuilder.append:(Ljava/lang/String;)Ljava/lang/StringBuilder;
      29: ldc           #8                  // String  / // // /_/ // _  |/ _  |/ /_/ /
      31: invokevirtual #5                  // Method java/lang/StringBuilder.append:(Ljava/lang/String;)Ljava/lang/StringBuilder;
      34: invokestatic  #6                  // Method java/lang/System.lineSeparator:()Ljava/lang/String;
      37: invokevirtual #5                  // Method java/lang/StringBuilder.append:(Ljava/lang/String;)Ljava/lang/StringBuilder;
      40: ldc           #9                  // String /____/ \\____//____//____/ \\____/
      42: invokevirtual #5                  // Method java/lang/StringBuilder.append:(Ljava/lang/String;)Ljava/lang/StringBuilder;
      45: invokestatic  #6                  // Method java/lang/System.lineSeparator:()Ljava/lang/String;
      48: invokevirtual #5                  // Method java/lang/StringBuilder.append:(Ljava/lang/String;)Ljava/lang/StringBuilder;
      51: invokevirtual #10                 // Method java/lang/StringBuilder.toString:()Ljava/lang/String;
      54: putstatic     #11                 // Field DUBBO:Ljava/lang/String;
      57: return
}
