Compiled from "Server.java"
class org.apache.dubbo.qos.server.Server$1 extends io.netty.channel.ChannelInitializer<io.netty.channel.Channel> {
  final org.apache.dubbo.qos.server.Server this$0;

  org.apache.dubbo.qos.server.Server$1(org.apache.dubbo.qos.server.Server);
    Code:
       0: aload_0
       1: aload_1
       2: putfield      #1                  // Field this$0:Lorg/apache/dubbo/qos/server/Server;
       5: aload_0
       6: invokespecial #2                  // Method io/netty/channel/ChannelInitializer."<init>":()V
       9: return

  protected void initChannel(io.netty.channel.Channel) throws java.lang.Exception;
    Code:
       0: aload_1
       1: invokeinterface #3,  1            // InterfaceMethod io/netty/channel/Channel.pipeline:()Lio/netty/channel/ChannelPipeline;
       6: iconst_1
       7: anewarray     #4                  // class io/netty/channel/ChannelHandler
      10: dup
      11: iconst_0
      12: new           #5                  // class org/apache/dubbo/qos/server/handler/QosProcessHandler
      15: dup
      16: aload_0
      17: getfield      #1                  // Field this$0:Lorg/apache/dubbo/qos/server/Server;
      20: invokestatic  #6                  // Method org/apache/dubbo/qos/server/Server.access$000:(Lorg/apache/dubbo/qos/server/Server;)Lorg/apache/dubbo/rpc/model/FrameworkModel;
      23: invokestatic  #7                  // Method org/apache/dubbo/qos/api/QosConfiguration.builder:()Lorg/apache/dubbo/qos/api/QosConfiguration$Builder;
      26: aload_0
      27: getfield      #1                  // Field this$0:Lorg/apache/dubbo/qos/server/Server;
      30: invokestatic  #8                  // Method org/apache/dubbo/qos/server/Server.access$500:(Lorg/apache/dubbo/qos/server/Server;)Ljava/lang/String;
      33: invokevirtual #9                  // Method org/apache/dubbo/qos/api/QosConfiguration$Builder.welcome:(Ljava/lang/String;)Lorg/apache/dubbo/qos/api/QosConfiguration$Builder;
      36: aload_0
      37: getfield      #1                  // Field this$0:Lorg/apache/dubbo/qos/server/Server;
      40: invokestatic  #10                 // Method org/apache/dubbo/qos/server/Server.access$400:(Lorg/apache/dubbo/qos/server/Server;)Z
      43: invokevirtual #11                 // Method org/apache/dubbo/qos/api/QosConfiguration$Builder.acceptForeignIp:(Z)Lorg/apache/dubbo/qos/api/QosConfiguration$Builder;
      46: aload_0
      47: getfield      #1                  // Field this$0:Lorg/apache/dubbo/qos/server/Server;
      50: invokestatic  #12                 // Method org/apache/dubbo/qos/server/Server.access$300:(Lorg/apache/dubbo/qos/server/Server;)Ljava/lang/String;
      53: invokevirtual #13                 // Method org/apache/dubbo/qos/api/QosConfiguration$Builder.acceptForeignIpWhitelist:(Ljava/lang/String;)Lorg/apache/dubbo/qos/api/QosConfiguration$Builder;
      56: aload_0
      57: getfield      #1                  // Field this$0:Lorg/apache/dubbo/qos/server/Server;
      60: invokestatic  #14                 // Method org/apache/dubbo/qos/server/Server.access$200:(Lorg/apache/dubbo/qos/server/Server;)Ljava/lang/String;
      63: invokevirtual #15                 // Method org/apache/dubbo/qos/api/QosConfiguration$Builder.anonymousAccessPermissionLevel:(Ljava/lang/String;)Lorg/apache/dubbo/qos/api/QosConfiguration$Builder;
      66: aload_0
      67: getfield      #1                  // Field this$0:Lorg/apache/dubbo/qos/server/Server;
      70: invokestatic  #16                 // Method org/apache/dubbo/qos/server/Server.access$100:(Lorg/apache/dubbo/qos/server/Server;)Ljava/lang/String;
      73: invokevirtual #17                 // Method org/apache/dubbo/qos/api/QosConfiguration$Builder.anonymousAllowCommands:(Ljava/lang/String;)Lorg/apache/dubbo/qos/api/QosConfiguration$Builder;
      76: invokevirtual #18                 // Method org/apache/dubbo/qos/api/QosConfiguration$Builder.build:()Lorg/apache/dubbo/qos/api/QosConfiguration;
      79: invokespecial #19                 // Method org/apache/dubbo/qos/server/handler/QosProcessHandler."<init>":(Lorg/apache/dubbo/rpc/model/FrameworkModel;Lorg/apache/dubbo/qos/api/QosConfiguration;)V
      82: aastore
      83: invokeinterface #20,  2           // InterfaceMethod io/netty/channel/ChannelPipeline.addLast:([Lio/netty/channel/ChannelHandler;)Lio/netty/channel/ChannelPipeline;
      88: pop
      89: return
}
