Compiled from "Server.java"
public class org.apache.dubbo.qos.server.Server {
  private static final org.apache.dubbo.common.logger.ErrorTypeAwareLogger logger;

  private java.lang.String host;

  private int port;

  private boolean acceptForeignIp;

  private java.lang.String acceptForeignIpWhitelist;

  private java.lang.String anonymousAccessPermissionLevel;

  private java.lang.String anonymousAllowCommands;

  private io.netty.channel.EventLoopGroup boss;

  private io.netty.channel.EventLoopGroup worker;

  private org.apache.dubbo.rpc.model.FrameworkModel frameworkModel;

  private java.lang.String welcome;

  private java.util.concurrent.atomic.AtomicBoolean started;

  public org.apache.dubbo.qos.server.Server(org.apache.dubbo.rpc.model.FrameworkModel);
    Code:
       0: aload_0
       1: invokespecial #8                  // Method java/lang/Object."<init>":()V
       4: aload_0
       5: iconst_1
       6: putfield      #3                  // Field acceptForeignIp:Z
       9: aload_0
      10: ldc           #10                 // String
      12: putfield      #4                  // Field acceptForeignIpWhitelist:Ljava/lang/String;
      15: aload_0
      16: getstatic     #11                 // Field org/apache/dubbo/qos/api/PermissionLevel.NONE:Lorg/apache/dubbo/qos/api/PermissionLevel;
      19: invokevirtual #12                 // Method org/apache/dubbo/qos/api/PermissionLevel.name:()Ljava/lang/String;
      22: putfield      #5                  // Field anonymousAccessPermissionLevel:Ljava/lang/String;
      25: aload_0
      26: ldc           #10                 // String
      28: putfield      #6                  // Field anonymousAllowCommands:Ljava/lang/String;
      31: aload_0
      32: new           #13                 // class java/util/concurrent/atomic/AtomicBoolean
      35: dup
      36: invokespecial #14                 // Method java/util/concurrent/atomic/AtomicBoolean."<init>":()V
      39: putfield      #15                 // Field started:Ljava/util/concurrent/atomic/AtomicBoolean;
      42: aload_0
      43: getstatic     #16                 // Field org/apache/dubbo/qos/server/DubboLogo.DUBBO:Ljava/lang/String;
      46: putfield      #2                  // Field welcome:Ljava/lang/String;
      49: aload_0
      50: aload_1
      51: putfield      #7                  // Field frameworkModel:Lorg/apache/dubbo/rpc/model/FrameworkModel;
      54: return

  public void setWelcome(java.lang.String);
    Code:
       0: aload_0
       1: aload_1
       2: putfield      #2                  // Field welcome:Ljava/lang/String;
       5: return

  public int getPort();
    Code:
       0: aload_0
       1: getfield      #17                 // Field port:I
       4: ireturn

  public void start() throws java.lang.Throwable;
    Code:
       0: aload_0
       1: getfield      #15                 // Field started:Ljava/util/concurrent/atomic/AtomicBoolean;
       4: iconst_0
       5: iconst_1
       6: invokevirtual #18                 // Method java/util/concurrent/atomic/AtomicBoolean.compareAndSet:(ZZ)Z
       9: ifne          13
      12: return
      13: aload_0
      14: new           #19                 // class io/netty/channel/nio/NioEventLoopGroup
      17: dup
      18: iconst_1
      19: new           #20                 // class io/netty/util/concurrent/DefaultThreadFactory
      22: dup
      23: ldc           #21                 // String qos-boss
      25: iconst_1
      26: invokespecial #22                 // Method io/netty/util/concurrent/DefaultThreadFactory."<init>":(Ljava/lang/String;Z)V
      29: invokespecial #23                 // Method io/netty/channel/nio/NioEventLoopGroup."<init>":(ILjava/util/concurrent/ThreadFactory;)V
      32: putfield      #24                 // Field boss:Lio/netty/channel/EventLoopGroup;
      35: aload_0
      36: new           #19                 // class io/netty/channel/nio/NioEventLoopGroup
      39: dup
      40: iconst_0
      41: new           #20                 // class io/netty/util/concurrent/DefaultThreadFactory
      44: dup
      45: ldc           #25                 // String qos-worker
      47: iconst_1
      48: invokespecial #22                 // Method io/netty/util/concurrent/DefaultThreadFactory."<init>":(Ljava/lang/String;Z)V
      51: invokespecial #23                 // Method io/netty/channel/nio/NioEventLoopGroup."<init>":(ILjava/util/concurrent/ThreadFactory;)V
      54: putfield      #26                 // Field worker:Lio/netty/channel/EventLoopGroup;
      57: new           #27                 // class io/netty/bootstrap/ServerBootstrap
      60: dup
      61: invokespecial #28                 // Method io/netty/bootstrap/ServerBootstrap."<init>":()V
      64: astore_1
      65: aload_1
      66: aload_0
      67: getfield      #24                 // Field boss:Lio/netty/channel/EventLoopGroup;
      70: aload_0
      71: getfield      #26                 // Field worker:Lio/netty/channel/EventLoopGroup;
      74: invokevirtual #29                 // Method io/netty/bootstrap/ServerBootstrap.group:(Lio/netty/channel/EventLoopGroup;Lio/netty/channel/EventLoopGroup;)Lio/netty/bootstrap/ServerBootstrap;
      77: pop
      78: aload_1
      79: ldc           #30                 // class io/netty/channel/socket/nio/NioServerSocketChannel
      81: invokevirtual #31                 // Method io/netty/bootstrap/ServerBootstrap.channel:(Ljava/lang/Class;)Lio/netty/bootstrap/AbstractBootstrap;
      84: pop
      85: aload_1
      86: getstatic     #32                 // Field io/netty/channel/ChannelOption.SO_REUSEADDR:Lio/netty/channel/ChannelOption;
      89: iconst_1
      90: invokestatic  #33                 // Method java/lang/Boolean.valueOf:(Z)Ljava/lang/Boolean;
      93: invokevirtual #34                 // Method io/netty/bootstrap/ServerBootstrap.option:(Lio/netty/channel/ChannelOption;Ljava/lang/Object;)Lio/netty/bootstrap/AbstractBootstrap;
      96: pop
      97: aload_1
      98: getstatic     #35                 // Field io/netty/channel/ChannelOption.TCP_NODELAY:Lio/netty/channel/ChannelOption;
     101: iconst_1
     102: invokestatic  #33                 // Method java/lang/Boolean.valueOf:(Z)Ljava/lang/Boolean;
     105: invokevirtual #36                 // Method io/netty/bootstrap/ServerBootstrap.childOption:(Lio/netty/channel/ChannelOption;Ljava/lang/Object;)Lio/netty/bootstrap/ServerBootstrap;
     108: pop
     109: aload_1
     110: new           #37                 // class org/apache/dubbo/qos/server/Server$1
     113: dup
     114: aload_0
     115: invokespecial #38                 // Method org/apache/dubbo/qos/server/Server$1."<init>":(Lorg/apache/dubbo/qos/server/Server;)V
     118: invokevirtual #39                 // Method io/netty/bootstrap/ServerBootstrap.childHandler:(Lio/netty/channel/ChannelHandler;)Lio/netty/bootstrap/ServerBootstrap;
     121: pop
     122: aload_0
     123: getfield      #40                 // Field host:Ljava/lang/String;
     126: invokestatic  #41                 // Method org/apache/dubbo/common/utils/StringUtils.isBlank:(Ljava/lang/CharSequence;)Z
     129: ifeq          149
     132: aload_1
     133: aload_0
     134: getfield      #17                 // Field port:I
     137: invokevirtual #42                 // Method io/netty/bootstrap/ServerBootstrap.bind:(I)Lio/netty/channel/ChannelFuture;
     140: invokeinterface #43,  1           // InterfaceMethod io/netty/channel/ChannelFuture.sync:()Lio/netty/channel/ChannelFuture;
     145: pop
     146: goto          167
     149: aload_1
     150: aload_0
     151: getfield      #40                 // Field host:Ljava/lang/String;
     154: aload_0
     155: getfield      #17                 // Field port:I
     158: invokevirtual #44                 // Method io/netty/bootstrap/ServerBootstrap.bind:(Ljava/lang/String;I)Lio/netty/channel/ChannelFuture;
     161: invokeinterface #43,  1           // InterfaceMethod io/netty/channel/ChannelFuture.sync:()Lio/netty/channel/ChannelFuture;
     166: pop
     167: getstatic     #45                 // Field logger:Lorg/apache/dubbo/common/logger/ErrorTypeAwareLogger;
     170: new           #46                 // class java/lang/StringBuilder
     173: dup
     174: invokespecial #47                 // Method java/lang/StringBuilder."<init>":()V
     177: ldc           #48                 // String qos-server bind localhost:
     179: invokevirtual #49                 // Method java/lang/StringBuilder.append:(Ljava/lang/String;)Ljava/lang/StringBuilder;
     182: aload_0
     183: getfield      #17                 // Field port:I
     186: invokevirtual #50                 // Method java/lang/StringBuilder.append:(I)Ljava/lang/StringBuilder;
     189: invokevirtual #51                 // Method java/lang/StringBuilder.toString:()Ljava/lang/String;
     192: invokeinterface #52,  2           // InterfaceMethod org/apache/dubbo/common/logger/ErrorTypeAwareLogger.info:(Ljava/lang/String;)V
     197: goto          240
     200: astore_2
     201: getstatic     #45                 // Field logger:Lorg/apache/dubbo/common/logger/ErrorTypeAwareLogger;
     204: ldc           #54                 // String 7-4
     206: ldc           #10                 // String
     208: ldc           #10                 // String
     210: new           #46                 // class java/lang/StringBuilder
     213: dup
     214: invokespecial #47                 // Method java/lang/StringBuilder."<init>":()V
     217: ldc           #55                 // String qos-server can not bind localhost:
     219: invokevirtual #49                 // Method java/lang/StringBuilder.append:(Ljava/lang/String;)Ljava/lang/StringBuilder;
     222: aload_0
     223: getfield      #17                 // Field port:I
     226: invokevirtual #50                 // Method java/lang/StringBuilder.append:(I)Ljava/lang/StringBuilder;
     229: invokevirtual #51                 // Method java/lang/StringBuilder.toString:()Ljava/lang/String;
     232: aload_2
     233: invokeinterface #56,  6           // InterfaceMethod org/apache/dubbo/common/logger/ErrorTypeAwareLogger.error:(Ljava/lang/String;Ljava/lang/String;Ljava/lang/String;Ljava/lang/String;Ljava/lang/Throwable;)V
     238: aload_2
     239: athrow
     240: return
    Exception table:
       from    to  target type
         122   197   200   Class java/lang/Throwable

  public void stop();
    Code:
       0: getstatic     #45                 // Field logger:Lorg/apache/dubbo/common/logger/ErrorTypeAwareLogger;
       3: ldc           #57                 // String qos-server stopped.
       5: invokeinterface #52,  2           // InterfaceMethod org/apache/dubbo/common/logger/ErrorTypeAwareLogger.info:(Ljava/lang/String;)V
      10: aload_0
      11: getfield      #24                 // Field boss:Lio/netty/channel/EventLoopGroup;
      14: ifnull        27
      17: aload_0
      18: getfield      #24                 // Field boss:Lio/netty/channel/EventLoopGroup;
      21: invokeinterface #58,  1           // InterfaceMethod io/netty/channel/EventLoopGroup.shutdownGracefully:()Lio/netty/util/concurrent/Future;
      26: pop
      27: aload_0
      28: getfield      #26                 // Field worker:Lio/netty/channel/EventLoopGroup;
      31: ifnull        44
      34: aload_0
      35: getfield      #26                 // Field worker:Lio/netty/channel/EventLoopGroup;
      38: invokeinterface #58,  1           // InterfaceMethod io/netty/channel/EventLoopGroup.shutdownGracefully:()Lio/netty/util/concurrent/Future;
      43: pop
      44: return

  public java.lang.String getHost();
    Code:
       0: aload_0
       1: getfield      #40                 // Field host:Ljava/lang/String;
       4: areturn

  public void setHost(java.lang.String);
    Code:
       0: aload_0
       1: aload_1
       2: putfield      #40                 // Field host:Ljava/lang/String;
       5: return

  public void setPort(int);
    Code:
       0: aload_0
       1: iload_1
       2: putfield      #17                 // Field port:I
       5: return

  public boolean isAcceptForeignIp();
    Code:
       0: aload_0
       1: getfield      #3                  // Field acceptForeignIp:Z
       4: ireturn

  public void setAcceptForeignIp(boolean);
    Code:
       0: aload_0
       1: iload_1
       2: putfield      #3                  // Field acceptForeignIp:Z
       5: return

  public void setAcceptForeignIpWhitelist(java.lang.String);
    Code:
       0: aload_0
       1: aload_1
       2: putfield      #4                  // Field acceptForeignIpWhitelist:Ljava/lang/String;
       5: return

  public void setAnonymousAccessPermissionLevel(java.lang.String);
    Code:
       0: aload_0
       1: aload_1
       2: putfield      #5                  // Field anonymousAccessPermissionLevel:Ljava/lang/String;
       5: return

  public void setAnonymousAllowCommands(java.lang.String);
    Code:
       0: aload_0
       1: aload_1
       2: putfield      #6                  // Field anonymousAllowCommands:Ljava/lang/String;
       5: return

  public java.lang.String getWelcome();
    Code:
       0: aload_0
       1: getfield      #2                  // Field welcome:Ljava/lang/String;
       4: areturn

  public boolean isStarted();
    Code:
       0: aload_0
       1: getfield      #15                 // Field started:Ljava/util/concurrent/atomic/AtomicBoolean;
       4: invokevirtual #59                 // Method java/util/concurrent/atomic/AtomicBoolean.get:()Z
       7: ireturn

  static org.apache.dubbo.rpc.model.FrameworkModel access$000(org.apache.dubbo.qos.server.Server);
    Code:
       0: aload_0
       1: getfield      #7                  // Field frameworkModel:Lorg/apache/dubbo/rpc/model/FrameworkModel;
       4: areturn

  static java.lang.String access$100(org.apache.dubbo.qos.server.Server);
    Code:
       0: aload_0
       1: getfield      #6                  // Field anonymousAllowCommands:Ljava/lang/String;
       4: areturn

  static java.lang.String access$200(org.apache.dubbo.qos.server.Server);
    Code:
       0: aload_0
       1: getfield      #5                  // Field anonymousAccessPermissionLevel:Ljava/lang/String;
       4: areturn

  static java.lang.String access$300(org.apache.dubbo.qos.server.Server);
    Code:
       0: aload_0
       1: getfield      #4                  // Field acceptForeignIpWhitelist:Ljava/lang/String;
       4: areturn

  static boolean access$400(org.apache.dubbo.qos.server.Server);
    Code:
       0: aload_0
       1: getfield      #3                  // Field acceptForeignIp:Z
       4: ireturn

  static java.lang.String access$500(org.apache.dubbo.qos.server.Server);
    Code:
       0: aload_0
       1: getfield      #2                  // Field welcome:Ljava/lang/String;
       4: areturn

  static {};
    Code:
       0: ldc           #60                 // class org/apache/dubbo/qos/server/Server
       2: invokestatic  #61                 // Method org/apache/dubbo/common/logger/LoggerFactory.getErrorTypeAwareLogger:(Ljava/lang/Class;)Lorg/apache/dubbo/common/logger/ErrorTypeAwareLogger;
       5: putstatic     #45                 // Field logger:Lorg/apache/dubbo/common/logger/ErrorTypeAwareLogger;
       8: return
}
