Compiled from "AztecCode.java"
public final class com.google.zxing.aztec.encoder.AztecCode {
  private boolean compact;

  private int size;

  private int layers;

  private int codeWords;

  private com.google.zxing.common.BitMatrix matrix;

  public com.google.zxing.aztec.encoder.AztecCode();
    Code:
       0: aload_0
       1: invokespecial #1                  // Method java/lang/Object."<init>":()V
       4: return

  public boolean isCompact();
    Code:
       0: aload_0
       1: getfield      #2                  // Field compact:Z
       4: ireturn

  public void setCompact(boolean);
    Code:
       0: aload_0
       1: iload_1
       2: putfield      #2                  // Field compact:Z
       5: return

  public int getSize();
    Code:
       0: aload_0
       1: getfield      #3                  // Field size:I
       4: ireturn

  public void setSize(int);
    Code:
       0: aload_0
       1: iload_1
       2: putfield      #3                  // Field size:I
       5: return

  public int getLayers();
    Code:
       0: aload_0
       1: getfield      #4                  // Field layers:I
       4: ireturn

  public void setLayers(int);
    Code:
       0: aload_0
       1: iload_1
       2: putfield      #4                  // Field layers:I
       5: return

  public int getCodeWords();
    Code:
       0: aload_0
       1: getfield      #5                  // Field codeWords:I
       4: ireturn

  public void setCodeWords(int);
    Code:
       0: aload_0
       1: iload_1
       2: putfield      #5                  // Field codeWords:I
       5: return

  public com.google.zxing.common.BitMatrix getMatrix();
    Code:
       0: aload_0
       1: getfield      #6                  // Field matrix:Lcom/google/zxing/common/BitMatrix;
       4: areturn

  public void setMatrix(com.google.zxing.common.BitMatrix);
    Code:
       0: aload_0
       1: aload_1
       2: putfield      #6                  // Field matrix:Lcom/google/zxing/common/BitMatrix;
       5: return
}
