Compiled from "Encoder.java"
public final class com.google.zxing.aztec.encoder.Encoder {
  public static final int DEFAULT_EC_PERCENT;

  public static final int DEFAULT_AZTEC_LAYERS;

  private static final int MAX_NB_BITS;

  private static final int MAX_NB_BITS_COMPACT;

  private static final int[] WORD_SIZE;

  private com.google.zxing.aztec.encoder.Encoder();
    Code:
       0: aload_0
       1: invokespecial #1                  // Method java/lang/Object."<init>":()V
       4: return

  public static com.google.zxing.aztec.encoder.AztecCode encode(java.lang.String);
    Code:
       0: aload_0
       1: getstatic     #2                  // Field java/nio/charset/StandardCharsets.ISO_8859_1:Ljava/nio/charset/Charset;
       4: invokevirtual #3                  // Method java/lang/String.getBytes:(Ljava/nio/charset/Charset;)[B
       7: invokestatic  #4                  // Method encode:([B)Lcom/google/zxing/aztec/encoder/AztecCode;
      10: areturn

  public static com.google.zxing.aztec.encoder.AztecCode encode(java.lang.String, int, int);
    Code:
       0: aload_0
       1: getstatic     #2                  // Field java/nio/charset/StandardCharsets.ISO_8859_1:Ljava/nio/charset/Charset;
       4: invokevirtual #3                  // Method java/lang/String.getBytes:(Ljava/nio/charset/Charset;)[B
       7: iload_1
       8: iload_2
       9: aconst_null
      10: invokestatic  #5                  // Method encode:([BIILjava/nio/charset/Charset;)Lcom/google/zxing/aztec/encoder/AztecCode;
      13: areturn

  public static com.google.zxing.aztec.encoder.AztecCode encode(java.lang.String, int, int, java.nio.charset.Charset);
    Code:
       0: aload_0
       1: aconst_null
       2: aload_3
       3: if_acmpeq     10
       6: aload_3
       7: goto          13
      10: getstatic     #2                  // Field java/nio/charset/StandardCharsets.ISO_8859_1:Ljava/nio/charset/Charset;
      13: invokevirtual #3                  // Method java/lang/String.getBytes:(Ljava/nio/charset/Charset;)[B
      16: astore        4
      18: aload         4
      20: iload_1
      21: iload_2
      22: aload_3
      23: invokestatic  #5                  // Method encode:([BIILjava/nio/charset/Charset;)Lcom/google/zxing/aztec/encoder/AztecCode;
      26: areturn

  public static com.google.zxing.aztec.encoder.AztecCode encode(byte[]);
    Code:
       0: aload_0
       1: bipush        33
       3: iconst_0
       4: aconst_null
       5: invokestatic  #5                  // Method encode:([BIILjava/nio/charset/Charset;)Lcom/google/zxing/aztec/encoder/AztecCode;
       8: areturn

  public static com.google.zxing.aztec.encoder.AztecCode encode(byte[], int, int);
    Code:
       0: aload_0
       1: iload_1
       2: iload_2
       3: aconst_null
       4: invokestatic  #5                  // Method encode:([BIILjava/nio/charset/Charset;)Lcom/google/zxing/aztec/encoder/AztecCode;
       7: areturn

  public static com.google.zxing.aztec.encoder.AztecCode encode(byte[], int, int, java.nio.charset.Charset);
    Code:
       0: new           #7                  // class com/google/zxing/aztec/encoder/HighLevelEncoder
       3: dup
       4: aload_0
       5: aload_3
       6: invokespecial #8                  // Method com/google/zxing/aztec/encoder/HighLevelEncoder."<init>":([BLjava/nio/charset/Charset;)V
       9: invokevirtual #9                  // Method com/google/zxing/aztec/encoder/HighLevelEncoder.encode:()Lcom/google/zxing/common/BitArray;
      12: astore        4
      14: aload         4
      16: invokevirtual #10                 // Method com/google/zxing/common/BitArray.getSize:()I
      19: iload_1
      20: imul
      21: bipush        100
      23: idiv
      24: bipush        11
      26: iadd
      27: istore        5
      29: aload         4
      31: invokevirtual #10                 // Method com/google/zxing/common/BitArray.getSize:()I
      34: iload         5
      36: iadd
      37: istore        6
      39: iload_2
      40: ifeq          190
      43: iload_2
      44: ifge          51
      47: iconst_1
      48: goto          52
      51: iconst_0
      52: istore        7
      54: iload_2
      55: invokestatic  #11                 // Method java/lang/Math.abs:(I)I
      58: istore        8
      60: iload         8
      62: iload         7
      64: ifeq          71
      67: iconst_4
      68: goto          73
      71: bipush        32
      73: if_icmple     100
      76: new           #12                 // class java/lang/IllegalArgumentException
      79: dup
      80: ldc           #13                 // String Illegal value %s for layers
      82: iconst_1
      83: anewarray     #14                 // class java/lang/Object
      86: dup
      87: iconst_0
      88: iload_2
      89: invokestatic  #15                 // Method java/lang/Integer.valueOf:(I)Ljava/lang/Integer;
      92: aastore
      93: invokestatic  #16                 // Method java/lang/String.format:(Ljava/lang/String;[Ljava/lang/Object;)Ljava/lang/String;
      96: invokespecial #17                 // Method java/lang/IllegalArgumentException."<init>":(Ljava/lang/String;)V
      99: athrow
     100: iload         8
     102: iload         7
     104: invokestatic  #18                 // Method totalBitsInLayer:(IZ)I
     107: istore        9
     109: getstatic     #19                 // Field WORD_SIZE:[I
     112: iload         8
     114: iaload
     115: istore        10
     117: iload         9
     119: iload         9
     121: iload         10
     123: irem
     124: isub
     125: istore        12
     127: aload         4
     129: iload         10
     131: invokestatic  #20                 // Method stuffBits:(Lcom/google/zxing/common/BitArray;I)Lcom/google/zxing/common/BitArray;
     134: astore        11
     136: aload         11
     138: invokevirtual #10                 // Method com/google/zxing/common/BitArray.getSize:()I
     141: iload         5
     143: iadd
     144: iload         12
     146: if_icmple     159
     149: new           #12                 // class java/lang/IllegalArgumentException
     152: dup
     153: ldc           #21                 // String Data to large for user specified layer
     155: invokespecial #17                 // Method java/lang/IllegalArgumentException."<init>":(Ljava/lang/String;)V
     158: athrow
     159: iload         7
     161: ifeq          187
     164: aload         11
     166: invokevirtual #10                 // Method com/google/zxing/common/BitArray.getSize:()I
     169: iload         10
     171: bipush        64
     173: imul
     174: if_icmple     187
     177: new           #12                 // class java/lang/IllegalArgumentException
     180: dup
     181: ldc           #21                 // String Data to large for user specified layer
     183: invokespecial #17                 // Method java/lang/IllegalArgumentException."<init>":(Ljava/lang/String;)V
     186: athrow
     187: goto          350
     190: iconst_0
     191: istore        10
     193: aconst_null
     194: astore        11
     196: iconst_0
     197: istore        12
     199: iload         12
     201: bipush        32
     203: if_icmple     216
     206: new           #12                 // class java/lang/IllegalArgumentException
     209: dup
     210: ldc           #22                 // String Data too large for an Aztec code
     212: invokespecial #17                 // Method java/lang/IllegalArgumentException."<init>":(Ljava/lang/String;)V
     215: athrow
     216: iload         12
     218: iconst_3
     219: if_icmpgt     226
     222: iconst_1
     223: goto          227
     226: iconst_0
     227: istore        7
     229: iload         7
     231: ifeq          241
     234: iload         12
     236: iconst_1
     237: iadd
     238: goto          243
     241: iload         12
     243: istore        8
     245: iload         8
     247: iload         7
     249: invokestatic  #18                 // Method totalBitsInLayer:(IZ)I
     252: istore        9
     254: iload         6
     256: iload         9
     258: if_icmple     264
     261: goto          344
     264: aload         11
     266: ifnull        280
     269: iload         10
     271: getstatic     #19                 // Field WORD_SIZE:[I
     274: iload         8
     276: iaload
     277: if_icmpeq     297
     280: getstatic     #19                 // Field WORD_SIZE:[I
     283: iload         8
     285: iaload
     286: istore        10
     288: aload         4
     290: iload         10
     292: invokestatic  #20                 // Method stuffBits:(Lcom/google/zxing/common/BitArray;I)Lcom/google/zxing/common/BitArray;
     295: astore        11
     297: iload         9
     299: iload         9
     301: iload         10
     303: irem
     304: isub
     305: istore        13
     307: iload         7
     309: ifeq          328
     312: aload         11
     314: invokevirtual #10                 // Method com/google/zxing/common/BitArray.getSize:()I
     317: iload         10
     319: bipush        64
     321: imul
     322: if_icmple     328
     325: goto          344
     328: aload         11
     330: invokevirtual #10                 // Method com/google/zxing/common/BitArray.getSize:()I
     333: iload         5
     335: iadd
     336: iload         13
     338: if_icmpgt     344
     341: goto          350
     344: iinc          12, 1
     347: goto          199
     350: aload         11
     352: iload         9
     354: iload         10
     356: invokestatic  #23                 // Method generateCheckWords:(Lcom/google/zxing/common/BitArray;II)Lcom/google/zxing/common/BitArray;
     359: astore        12
     361: aload         11
     363: invokevirtual #10                 // Method com/google/zxing/common/BitArray.getSize:()I
     366: iload         10
     368: idiv
     369: istore        13
     371: iload         7
     373: iload         8
     375: iload         13
     377: invokestatic  #24                 // Method generateModeMessage:(ZII)Lcom/google/zxing/common/BitArray;
     380: astore        14
     382: iload         7
     384: ifeq          392
     387: bipush        11
     389: goto          394
     392: bipush        14
     394: iload         8
     396: iconst_4
     397: imul
     398: iadd
     399: istore        15
     401: iload         15
     403: newarray       int
     405: astore        16
     407: iload         7
     409: ifeq          443
     412: iload         15
     414: istore        17
     416: iconst_0
     417: istore        18
     419: iload         18
     421: aload         16
     423: arraylength
     424: if_icmpge     440
     427: aload         16
     429: iload         18
     431: iload         18
     433: iastore
     434: iinc          18, 1
     437: goto          419
     440: goto          531
     443: iload         15
     445: iconst_1
     446: iadd
     447: iconst_2
     448: iload         15
     450: iconst_2
     451: idiv
     452: iconst_1
     453: isub
     454: bipush        15
     456: idiv
     457: imul
     458: iadd
     459: istore        17
     461: iload         15
     463: iconst_2
     464: idiv
     465: istore        18
     467: iload         17
     469: iconst_2
     470: idiv
     471: istore        19
     473: iconst_0
     474: istore        20
     476: iload         20
     478: iload         18
     480: if_icmpge     531
     483: iload         20
     485: iload         20
     487: bipush        15
     489: idiv
     490: iadd
     491: istore        21
     493: aload         16
     495: iload         18
     497: iload         20
     499: isub
     500: iconst_1
     501: isub
     502: iload         19
     504: iload         21
     506: isub
     507: iconst_1
     508: isub
     509: iastore
     510: aload         16
     512: iload         18
     514: iload         20
     516: iadd
     517: iload         19
     519: iload         21
     521: iadd
     522: iconst_1
     523: iadd
     524: iastore
     525: iinc          20, 1
     528: goto          476
     531: new           #25                 // class com/google/zxing/common/BitMatrix
     534: dup
     535: iload         17
     537: invokespecial #26                 // Method com/google/zxing/common/BitMatrix."<init>":(I)V
     540: astore        18
     542: iconst_0
     543: istore        19
     545: iconst_0
     546: istore        20
     548: iload         19
     550: iload         8
     552: if_icmpge     830
     555: iload         8
     557: iload         19
     559: isub
     560: iconst_4
     561: imul
     562: iload         7
     564: ifeq          572
     567: bipush        9
     569: goto          574
     572: bipush        12
     574: iadd
     575: istore        21
     577: iconst_0
     578: istore        22
     580: iload         22
     582: iload         21
     584: if_icmpge     814
     587: iload         22
     589: iconst_2
     590: imul
     591: istore        23
     593: iconst_0
     594: istore        24
     596: iload         24
     598: iconst_2
     599: if_icmpge     808
     602: aload         12
     604: iload         20
     606: iload         23
     608: iadd
     609: iload         24
     611: iadd
     612: invokevirtual #27                 // Method com/google/zxing/common/BitArray.get:(I)Z
     615: ifeq          643
     618: aload         18
     620: aload         16
     622: iload         19
     624: iconst_2
     625: imul
     626: iload         24
     628: iadd
     629: iaload
     630: aload         16
     632: iload         19
     634: iconst_2
     635: imul
     636: iload         22
     638: iadd
     639: iaload
     640: invokevirtual #28                 // Method com/google/zxing/common/BitMatrix.set:(II)V
     643: aload         12
     645: iload         20
     647: iload         21
     649: iconst_2
     650: imul
     651: iadd
     652: iload         23
     654: iadd
     655: iload         24
     657: iadd
     658: invokevirtual #27                 // Method com/google/zxing/common/BitArray.get:(I)Z
     661: ifeq          694
     664: aload         18
     666: aload         16
     668: iload         19
     670: iconst_2
     671: imul
     672: iload         22
     674: iadd
     675: iaload
     676: aload         16
     678: iload         15
     680: iconst_1
     681: isub
     682: iload         19
     684: iconst_2
     685: imul
     686: isub
     687: iload         24
     689: isub
     690: iaload
     691: invokevirtual #28                 // Method com/google/zxing/common/BitMatrix.set:(II)V
     694: aload         12
     696: iload         20
     698: iload         21
     700: iconst_4
     701: imul
     702: iadd
     703: iload         23
     705: iadd
     706: iload         24
     708: iadd
     709: invokevirtual #27                 // Method com/google/zxing/common/BitArray.get:(I)Z
     712: ifeq          750
     715: aload         18
     717: aload         16
     719: iload         15
     721: iconst_1
     722: isub
     723: iload         19
     725: iconst_2
     726: imul
     727: isub
     728: iload         24
     730: isub
     731: iaload
     732: aload         16
     734: iload         15
     736: iconst_1
     737: isub
     738: iload         19
     740: iconst_2
     741: imul
     742: isub
     743: iload         22
     745: isub
     746: iaload
     747: invokevirtual #28                 // Method com/google/zxing/common/BitMatrix.set:(II)V
     750: aload         12
     752: iload         20
     754: iload         21
     756: bipush        6
     758: imul
     759: iadd
     760: iload         23
     762: iadd
     763: iload         24
     765: iadd
     766: invokevirtual #27                 // Method com/google/zxing/common/BitArray.get:(I)Z
     769: ifeq          802
     772: aload         18
     774: aload         16
     776: iload         15
     778: iconst_1
     779: isub
     780: iload         19
     782: iconst_2
     783: imul
     784: isub
     785: iload         22
     787: isub
     788: iaload
     789: aload         16
     791: iload         19
     793: iconst_2
     794: imul
     795: iload         24
     797: iadd
     798: iaload
     799: invokevirtual #28                 // Method com/google/zxing/common/BitMatrix.set:(II)V
     802: iinc          24, 1
     805: goto          596
     808: iinc          22, 1
     811: goto          580
     814: iload         20
     816: iload         21
     818: bipush        8
     820: imul
     821: iadd
     822: istore        20
     824: iinc          19, 1
     827: goto          548
     830: aload         18
     832: iload         7
     834: iload         17
     836: aload         14
     838: invokestatic  #29                 // Method drawModeMessage:(Lcom/google/zxing/common/BitMatrix;ZILcom/google/zxing/common/BitArray;)V
     841: iload         7
     843: ifeq          859
     846: aload         18
     848: iload         17
     850: iconst_2
     851: idiv
     852: iconst_5
     853: invokestatic  #30                 // Method drawBullsEye:(Lcom/google/zxing/common/BitMatrix;II)V
     856: goto          973
     859: aload         18
     861: iload         17
     863: iconst_2
     864: idiv
     865: bipush        7
     867: invokestatic  #30                 // Method drawBullsEye:(Lcom/google/zxing/common/BitMatrix;II)V
     870: iconst_0
     871: istore        19
     873: iconst_0
     874: istore        20
     876: iload         19
     878: iload         15
     880: iconst_2
     881: idiv
     882: iconst_1
     883: isub
     884: if_icmpge     973
     887: iload         17
     889: iconst_2
     890: idiv
     891: iconst_1
     892: iand
     893: istore        21
     895: iload         21
     897: iload         17
     899: if_icmpge     964
     902: aload         18
     904: iload         17
     906: iconst_2
     907: idiv
     908: iload         20
     910: isub
     911: iload         21
     913: invokevirtual #28                 // Method com/google/zxing/common/BitMatrix.set:(II)V
     916: aload         18
     918: iload         17
     920: iconst_2
     921: idiv
     922: iload         20
     924: iadd
     925: iload         21
     927: invokevirtual #28                 // Method com/google/zxing/common/BitMatrix.set:(II)V
     930: aload         18
     932: iload         21
     934: iload         17
     936: iconst_2
     937: idiv
     938: iload         20
     940: isub
     941: invokevirtual #28                 // Method com/google/zxing/common/BitMatrix.set:(II)V
     944: aload         18
     946: iload         21
     948: iload         17
     950: iconst_2
     951: idiv
     952: iload         20
     954: iadd
     955: invokevirtual #28                 // Method com/google/zxing/common/BitMatrix.set:(II)V
     958: iinc          21, 2
     961: goto          895
     964: iinc          19, 15
     967: iinc          20, 16
     970: goto          876
     973: new           #31                 // class com/google/zxing/aztec/encoder/AztecCode
     976: dup
     977: invokespecial #32                 // Method com/google/zxing/aztec/encoder/AztecCode."<init>":()V
     980: astore        19
     982: aload         19
     984: iload         7
     986: invokevirtual #33                 // Method com/google/zxing/aztec/encoder/AztecCode.setCompact:(Z)V
     989: aload         19
     991: iload         17
     993: invokevirtual #34                 // Method com/google/zxing/aztec/encoder/AztecCode.setSize:(I)V
     996: aload         19
     998: iload         8
    1000: invokevirtual #35                 // Method com/google/zxing/aztec/encoder/AztecCode.setLayers:(I)V
    1003: aload         19
    1005: iload         13
    1007: invokevirtual #36                 // Method com/google/zxing/aztec/encoder/AztecCode.setCodeWords:(I)V
    1010: aload         19
    1012: aload         18
    1014: invokevirtual #37                 // Method com/google/zxing/aztec/encoder/AztecCode.setMatrix:(Lcom/google/zxing/common/BitMatrix;)V
    1017: aload         19
    1019: areturn

  private static void drawBullsEye(com.google.zxing.common.BitMatrix, int, int);
    Code:
       0: iconst_0
       1: istore_3
       2: iload_3
       3: iload_2
       4: if_icmpge     68
       7: iload_1
       8: iload_3
       9: isub
      10: istore        4
      12: iload         4
      14: iload_1
      15: iload_3
      16: iadd
      17: if_icmpgt     62
      20: aload_0
      21: iload         4
      23: iload_1
      24: iload_3
      25: isub
      26: invokevirtual #28                 // Method com/google/zxing/common/BitMatrix.set:(II)V
      29: aload_0
      30: iload         4
      32: iload_1
      33: iload_3
      34: iadd
      35: invokevirtual #28                 // Method com/google/zxing/common/BitMatrix.set:(II)V
      38: aload_0
      39: iload_1
      40: iload_3
      41: isub
      42: iload         4
      44: invokevirtual #28                 // Method com/google/zxing/common/BitMatrix.set:(II)V
      47: aload_0
      48: iload_1
      49: iload_3
      50: iadd
      51: iload         4
      53: invokevirtual #28                 // Method com/google/zxing/common/BitMatrix.set:(II)V
      56: iinc          4, 1
      59: goto          12
      62: iinc          3, 2
      65: goto          2
      68: aload_0
      69: iload_1
      70: iload_2
      71: isub
      72: iload_1
      73: iload_2
      74: isub
      75: invokevirtual #28                 // Method com/google/zxing/common/BitMatrix.set:(II)V
      78: aload_0
      79: iload_1
      80: iload_2
      81: isub
      82: iconst_1
      83: iadd
      84: iload_1
      85: iload_2
      86: isub
      87: invokevirtual #28                 // Method com/google/zxing/common/BitMatrix.set:(II)V
      90: aload_0
      91: iload_1
      92: iload_2
      93: isub
      94: iload_1
      95: iload_2
      96: isub
      97: iconst_1
      98: iadd
      99: invokevirtual #28                 // Method com/google/zxing/common/BitMatrix.set:(II)V
     102: aload_0
     103: iload_1
     104: iload_2
     105: iadd
     106: iload_1
     107: iload_2
     108: isub
     109: invokevirtual #28                 // Method com/google/zxing/common/BitMatrix.set:(II)V
     112: aload_0
     113: iload_1
     114: iload_2
     115: iadd
     116: iload_1
     117: iload_2
     118: isub
     119: iconst_1
     120: iadd
     121: invokevirtual #28                 // Method com/google/zxing/common/BitMatrix.set:(II)V
     124: aload_0
     125: iload_1
     126: iload_2
     127: iadd
     128: iload_1
     129: iload_2
     130: iadd
     131: iconst_1
     132: isub
     133: invokevirtual #28                 // Method com/google/zxing/common/BitMatrix.set:(II)V
     136: return

  static com.google.zxing.common.BitArray generateModeMessage(boolean, int, int);
    Code:
       0: new           #38                 // class com/google/zxing/common/BitArray
       3: dup
       4: invokespecial #39                 // Method com/google/zxing/common/BitArray."<init>":()V
       7: astore_3
       8: iload_0
       9: ifeq          40
      12: aload_3
      13: iload_1
      14: iconst_1
      15: isub
      16: iconst_2
      17: invokevirtual #40                 // Method com/google/zxing/common/BitArray.appendBits:(II)V
      20: aload_3
      21: iload_2
      22: iconst_1
      23: isub
      24: bipush        6
      26: invokevirtual #40                 // Method com/google/zxing/common/BitArray.appendBits:(II)V
      29: aload_3
      30: bipush        28
      32: iconst_4
      33: invokestatic  #23                 // Method generateCheckWords:(Lcom/google/zxing/common/BitArray;II)Lcom/google/zxing/common/BitArray;
      36: astore_3
      37: goto          65
      40: aload_3
      41: iload_1
      42: iconst_1
      43: isub
      44: iconst_5
      45: invokevirtual #40                 // Method com/google/zxing/common/BitArray.appendBits:(II)V
      48: aload_3
      49: iload_2
      50: iconst_1
      51: isub
      52: bipush        11
      54: invokevirtual #40                 // Method com/google/zxing/common/BitArray.appendBits:(II)V
      57: aload_3
      58: bipush        40
      60: iconst_4
      61: invokestatic  #23                 // Method generateCheckWords:(Lcom/google/zxing/common/BitArray;II)Lcom/google/zxing/common/BitArray;
      64: astore_3
      65: aload_3
      66: areturn

  private static void drawModeMessage(com.google.zxing.common.BitMatrix, boolean, int, com.google.zxing.common.BitArray);
    Code:
       0: iload_2
       1: iconst_2
       2: idiv
       3: istore        4
       5: iload_1
       6: ifeq          122
       9: iconst_0
      10: istore        5
      12: iload         5
      14: bipush        7
      16: if_icmpge     119
      19: iload         4
      21: iconst_3
      22: isub
      23: iload         5
      25: iadd
      26: istore        6
      28: aload_3
      29: iload         5
      31: invokevirtual #27                 // Method com/google/zxing/common/BitArray.get:(I)Z
      34: ifeq          47
      37: aload_0
      38: iload         6
      40: iload         4
      42: iconst_5
      43: isub
      44: invokevirtual #28                 // Method com/google/zxing/common/BitMatrix.set:(II)V
      47: aload_3
      48: iload         5
      50: bipush        7
      52: iadd
      53: invokevirtual #27                 // Method com/google/zxing/common/BitArray.get:(I)Z
      56: ifeq          69
      59: aload_0
      60: iload         4
      62: iconst_5
      63: iadd
      64: iload         6
      66: invokevirtual #28                 // Method com/google/zxing/common/BitMatrix.set:(II)V
      69: aload_3
      70: bipush        20
      72: iload         5
      74: isub
      75: invokevirtual #27                 // Method com/google/zxing/common/BitArray.get:(I)Z
      78: ifeq          91
      81: aload_0
      82: iload         6
      84: iload         4
      86: iconst_5
      87: iadd
      88: invokevirtual #28                 // Method com/google/zxing/common/BitMatrix.set:(II)V
      91: aload_3
      92: bipush        27
      94: iload         5
      96: isub
      97: invokevirtual #27                 // Method com/google/zxing/common/BitArray.get:(I)Z
     100: ifeq          113
     103: aload_0
     104: iload         4
     106: iconst_5
     107: isub
     108: iload         6
     110: invokevirtual #28                 // Method com/google/zxing/common/BitMatrix.set:(II)V
     113: iinc          5, 1
     116: goto          12
     119: goto          241
     122: iconst_0
     123: istore        5
     125: iload         5
     127: bipush        10
     129: if_icmpge     241
     132: iload         4
     134: iconst_5
     135: isub
     136: iload         5
     138: iadd
     139: iload         5
     141: iconst_5
     142: idiv
     143: iadd
     144: istore        6
     146: aload_3
     147: iload         5
     149: invokevirtual #27                 // Method com/google/zxing/common/BitArray.get:(I)Z
     152: ifeq          166
     155: aload_0
     156: iload         6
     158: iload         4
     160: bipush        7
     162: isub
     163: invokevirtual #28                 // Method com/google/zxing/common/BitMatrix.set:(II)V
     166: aload_3
     167: iload         5
     169: bipush        10
     171: iadd
     172: invokevirtual #27                 // Method com/google/zxing/common/BitArray.get:(I)Z
     175: ifeq          189
     178: aload_0
     179: iload         4
     181: bipush        7
     183: iadd
     184: iload         6
     186: invokevirtual #28                 // Method com/google/zxing/common/BitMatrix.set:(II)V
     189: aload_3
     190: bipush        29
     192: iload         5
     194: isub
     195: invokevirtual #27                 // Method com/google/zxing/common/BitArray.get:(I)Z
     198: ifeq          212
     201: aload_0
     202: iload         6
     204: iload         4
     206: bipush        7
     208: iadd
     209: invokevirtual #28                 // Method com/google/zxing/common/BitMatrix.set:(II)V
     212: aload_3
     213: bipush        39
     215: iload         5
     217: isub
     218: invokevirtual #27                 // Method com/google/zxing/common/BitArray.get:(I)Z
     221: ifeq          235
     224: aload_0
     225: iload         4
     227: bipush        7
     229: isub
     230: iload         6
     232: invokevirtual #28                 // Method com/google/zxing/common/BitMatrix.set:(II)V
     235: iinc          5, 1
     238: goto          125
     241: return

  private static com.google.zxing.common.BitArray generateCheckWords(com.google.zxing.common.BitArray, int, int);
    Code:
       0: aload_0
       1: invokevirtual #10                 // Method com/google/zxing/common/BitArray.getSize:()I
       4: iload_2
       5: idiv
       6: istore_3
       7: new           #41                 // class com/google/zxing/common/reedsolomon/ReedSolomonEncoder
      10: dup
      11: iload_2
      12: invokestatic  #42                 // Method getGF:(I)Lcom/google/zxing/common/reedsolomon/GenericGF;
      15: invokespecial #43                 // Method com/google/zxing/common/reedsolomon/ReedSolomonEncoder."<init>":(Lcom/google/zxing/common/reedsolomon/GenericGF;)V
      18: astore        4
      20: iload_1
      21: iload_2
      22: idiv
      23: istore        5
      25: aload_0
      26: iload_2
      27: iload         5
      29: invokestatic  #44                 // Method bitsToWords:(Lcom/google/zxing/common/BitArray;II)[I
      32: astore        6
      34: aload         4
      36: aload         6
      38: iload         5
      40: iload_3
      41: isub
      42: invokevirtual #45                 // Method com/google/zxing/common/reedsolomon/ReedSolomonEncoder.encode:([II)V
      45: iload_1
      46: iload_2
      47: irem
      48: istore        7
      50: new           #38                 // class com/google/zxing/common/BitArray
      53: dup
      54: invokespecial #39                 // Method com/google/zxing/common/BitArray."<init>":()V
      57: astore        8
      59: aload         8
      61: iconst_0
      62: iload         7
      64: invokevirtual #40                 // Method com/google/zxing/common/BitArray.appendBits:(II)V
      67: aload         6
      69: astore        9
      71: aload         9
      73: arraylength
      74: istore        10
      76: iconst_0
      77: istore        11
      79: iload         11
      81: iload         10
      83: if_icmpge     107
      86: aload         9
      88: iload         11
      90: iaload
      91: istore        12
      93: aload         8
      95: iload         12
      97: iload_2
      98: invokevirtual #40                 // Method com/google/zxing/common/BitArray.appendBits:(II)V
     101: iinc          11, 1
     104: goto          79
     107: aload         8
     109: areturn

  private static int[] bitsToWords(com.google.zxing.common.BitArray, int, int);
    Code:
       0: iload_2
       1: newarray       int
       3: astore_3
       4: iconst_0
       5: istore        4
       7: aload_0
       8: invokevirtual #10                 // Method com/google/zxing/common/BitArray.getSize:()I
      11: iload_1
      12: idiv
      13: istore        5
      15: iload         4
      17: iload         5
      19: if_icmpge     83
      22: iconst_0
      23: istore        6
      25: iconst_0
      26: istore        7
      28: iload         7
      30: iload_1
      31: if_icmpge     71
      34: iload         6
      36: aload_0
      37: iload         4
      39: iload_1
      40: imul
      41: iload         7
      43: iadd
      44: invokevirtual #27                 // Method com/google/zxing/common/BitArray.get:(I)Z
      47: ifeq          61
      50: iconst_1
      51: iload_1
      52: iload         7
      54: isub
      55: iconst_1
      56: isub
      57: ishl
      58: goto          62
      61: iconst_0
      62: ior
      63: istore        6
      65: iinc          7, 1
      68: goto          28
      71: aload_3
      72: iload         4
      74: iload         6
      76: iastore
      77: iinc          4, 1
      80: goto          15
      83: aload_3
      84: areturn

  private static com.google.zxing.common.reedsolomon.GenericGF getGF(int);
    Code:
       0: iload_0
       1: tableswitch   { // 4 to 12
                     4: 52
                     5: 72
                     6: 56
                     7: 72
                     8: 60
                     9: 72
                    10: 64
                    11: 72
                    12: 68
               default: 72
          }
      52: getstatic     #46                 // Field com/google/zxing/common/reedsolomon/GenericGF.AZTEC_PARAM:Lcom/google/zxing/common/reedsolomon/GenericGF;
      55: areturn
      56: getstatic     #47                 // Field com/google/zxing/common/reedsolomon/GenericGF.AZTEC_DATA_6:Lcom/google/zxing/common/reedsolomon/GenericGF;
      59: areturn
      60: getstatic     #48                 // Field com/google/zxing/common/reedsolomon/GenericGF.AZTEC_DATA_8:Lcom/google/zxing/common/reedsolomon/GenericGF;
      63: areturn
      64: getstatic     #49                 // Field com/google/zxing/common/reedsolomon/GenericGF.AZTEC_DATA_10:Lcom/google/zxing/common/reedsolomon/GenericGF;
      67: areturn
      68: getstatic     #50                 // Field com/google/zxing/common/reedsolomon/GenericGF.AZTEC_DATA_12:Lcom/google/zxing/common/reedsolomon/GenericGF;
      71: areturn
      72: new           #12                 // class java/lang/IllegalArgumentException
      75: dup
      76: new           #51                 // class java/lang/StringBuilder
      79: dup
      80: invokespecial #52                 // Method java/lang/StringBuilder."<init>":()V
      83: ldc           #53                 // String Unsupported word size
      85: invokevirtual #54                 // Method java/lang/StringBuilder.append:(Ljava/lang/String;)Ljava/lang/StringBuilder;
      88: iload_0
      89: invokevirtual #55                 // Method java/lang/StringBuilder.append:(I)Ljava/lang/StringBuilder;
      92: invokevirtual #56                 // Method java/lang/StringBuilder.toString:()Ljava/lang/String;
      95: invokespecial #17                 // Method java/lang/IllegalArgumentException."<init>":(Ljava/lang/String;)V
      98: athrow

  static com.google.zxing.common.BitArray stuffBits(com.google.zxing.common.BitArray, int);
    Code:
       0: new           #38                 // class com/google/zxing/common/BitArray
       3: dup
       4: invokespecial #39                 // Method com/google/zxing/common/BitArray."<init>":()V
       7: astore_2
       8: aload_0
       9: invokevirtual #10                 // Method com/google/zxing/common/BitArray.getSize:()I
      12: istore_3
      13: iconst_1
      14: iload_1
      15: ishl
      16: iconst_2
      17: isub
      18: istore        4
      20: iconst_0
      21: istore        5
      23: iload         5
      25: iload_3
      26: if_icmpge     146
      29: iconst_0
      30: istore        6
      32: iconst_0
      33: istore        7
      35: iload         7
      37: iload_1
      38: if_icmpge     81
      41: iload         5
      43: iload         7
      45: iadd
      46: iload_3
      47: if_icmpge     62
      50: aload_0
      51: iload         5
      53: iload         7
      55: iadd
      56: invokevirtual #27                 // Method com/google/zxing/common/BitArray.get:(I)Z
      59: ifeq          75
      62: iload         6
      64: iconst_1
      65: iload_1
      66: iconst_1
      67: isub
      68: iload         7
      70: isub
      71: ishl
      72: ior
      73: istore        6
      75: iinc          7, 1
      78: goto          35
      81: iload         6
      83: iload         4
      85: iand
      86: iload         4
      88: if_icmpne     107
      91: aload_2
      92: iload         6
      94: iload         4
      96: iand
      97: iload_1
      98: invokevirtual #40                 // Method com/google/zxing/common/BitArray.appendBits:(II)V
     101: iinc          5, -1
     104: goto          137
     107: iload         6
     109: iload         4
     111: iand
     112: ifne          130
     115: aload_2
     116: iload         6
     118: iconst_1
     119: ior
     120: iload_1
     121: invokevirtual #40                 // Method com/google/zxing/common/BitArray.appendBits:(II)V
     124: iinc          5, -1
     127: goto          137
     130: aload_2
     131: iload         6
     133: iload_1
     134: invokevirtual #40                 // Method com/google/zxing/common/BitArray.appendBits:(II)V
     137: iload         5
     139: iload_1
     140: iadd
     141: istore        5
     143: goto          23
     146: aload_2
     147: areturn

  private static int totalBitsInLayer(int, boolean);
    Code:
       0: iload_1
       1: ifeq          9
       4: bipush        88
       6: goto          11
       9: bipush        112
      11: bipush        16
      13: iload_0
      14: imul
      15: iadd
      16: iload_0
      17: imul
      18: ireturn

  static {};
    Code:
       0: bipush        33
       2: newarray       int
       4: dup
       5: iconst_0
       6: iconst_4
       7: iastore
       8: dup
       9: iconst_1
      10: bipush        6
      12: iastore
      13: dup
      14: iconst_2
      15: bipush        6
      17: iastore
      18: dup
      19: iconst_3
      20: bipush        8
      22: iastore
      23: dup
      24: iconst_4
      25: bipush        8
      27: iastore
      28: dup
      29: iconst_5
      30: bipush        8
      32: iastore
      33: dup
      34: bipush        6
      36: bipush        8
      38: iastore
      39: dup
      40: bipush        7
      42: bipush        8
      44: iastore
      45: dup
      46: bipush        8
      48: bipush        8
      50: iastore
      51: dup
      52: bipush        9
      54: bipush        10
      56: iastore
      57: dup
      58: bipush        10
      60: bipush        10
      62: iastore
      63: dup
      64: bipush        11
      66: bipush        10
      68: iastore
      69: dup
      70: bipush        12
      72: bipush        10
      74: iastore
      75: dup
      76: bipush        13
      78: bipush        10
      80: iastore
      81: dup
      82: bipush        14
      84: bipush        10
      86: iastore
      87: dup
      88: bipush        15
      90: bipush        10
      92: iastore
      93: dup
      94: bipush        16
      96: bipush        10
      98: iastore
      99: dup
     100: bipush        17
     102: bipush        10
     104: iastore
     105: dup
     106: bipush        18
     108: bipush        10
     110: iastore
     111: dup
     112: bipush        19
     114: bipush        10
     116: iastore
     117: dup
     118: bipush        20
     120: bipush        10
     122: iastore
     123: dup
     124: bipush        21
     126: bipush        10
     128: iastore
     129: dup
     130: bipush        22
     132: bipush        10
     134: iastore
     135: dup
     136: bipush        23
     138: bipush        12
     140: iastore
     141: dup
     142: bipush        24
     144: bipush        12
     146: iastore
     147: dup
     148: bipush        25
     150: bipush        12
     152: iastore
     153: dup
     154: bipush        26
     156: bipush        12
     158: iastore
     159: dup
     160: bipush        27
     162: bipush        12
     164: iastore
     165: dup
     166: bipush        28
     168: bipush        12
     170: iastore
     171: dup
     172: bipush        29
     174: bipush        12
     176: iastore
     177: dup
     178: bipush        30
     180: bipush        12
     182: iastore
     183: dup
     184: bipush        31
     186: bipush        12
     188: iastore
     189: dup
     190: bipush        32
     192: bipush        12
     194: iastore
     195: putstatic     #19                 // Field WORD_SIZE:[I
     198: return
}
