Compiled from "HighLevelEncoder.java"
class com.google.zxing.aztec.encoder.HighLevelEncoder$1 implements java.util.Comparator<com.google.zxing.aztec.encoder.State> {
  final com.google.zxing.aztec.encoder.HighLevelEncoder this$0;

  com.google.zxing.aztec.encoder.HighLevelEncoder$1(com.google.zxing.aztec.encoder.HighLevelEncoder);
    Code:
       0: aload_0
       1: aload_1
       2: putfield      #1                  // Field this$0:Lcom/google/zxing/aztec/encoder/HighLevelEncoder;
       5: aload_0
       6: invokespecial #2                  // Method java/lang/Object."<init>":()V
       9: return

  public int compare(com.google.zxing.aztec.encoder.State, com.google.zxing.aztec.encoder.State);
    Code:
       0: aload_1
       1: invokevirtual #3                  // Method com/google/zxing/aztec/encoder/State.getBitCount:()I
       4: aload_2
       5: invokevirtual #3                  // Method com/google/zxing/aztec/encoder/State.getBitCount:()I
       8: isub
       9: ireturn

  public int compare(java.lang.Object, java.lang.Object);
    Code:
       0: aload_0
       1: aload_1
       2: checkcast     #4                  // class com/google/zxing/aztec/encoder/State
       5: aload_2
       6: checkcast     #4                  // class com/google/zxing/aztec/encoder/State
       9: invokevirtual #5                  // Method compare:(Lcom/google/zxing/aztec/encoder/State;Lcom/google/zxing/aztec/encoder/State;)I
      12: ireturn
}
