Compiled from "SimpleToken.java"
final class com.google.zxing.aztec.encoder.SimpleToken extends com.google.zxing.aztec.encoder.Token {
  private final short value;

  private final short bitCount;

  com.google.zxing.aztec.encoder.SimpleToken(com.google.zxing.aztec.encoder.Token, int, int);
    Code:
       0: aload_0
       1: aload_1
       2: invokespecial #1                  // Method com/google/zxing/aztec/encoder/Token."<init>":(Lcom/google/zxing/aztec/encoder/Token;)V
       5: aload_0
       6: iload_2
       7: i2s
       8: putfield      #2                  // Field value:S
      11: aload_0
      12: iload_3
      13: i2s
      14: putfield      #3                  // Field bitCount:S
      17: return

  void appendTo(com.google.zxing.common.BitArray, byte[]);
    Code:
       0: aload_1
       1: aload_0
       2: getfield      #2                  // Field value:S
       5: aload_0
       6: getfield      #3                  // Field bitCount:S
       9: invokevirtual #4                  // Method com/google/zxing/common/BitArray.appendBits:(II)V
      12: return

  public java.lang.String toString();
    Code:
       0: aload_0
       1: getfield      #2                  // Field value:S
       4: iconst_1
       5: aload_0
       6: getfield      #3                  // Field bitCount:S
       9: ishl
      10: iconst_1
      11: isub
      12: iand
      13: istore_1
      14: iload_1
      15: iconst_1
      16: aload_0
      17: getfield      #3                  // Field bitCount:S
      20: ishl
      21: ior
      22: istore_1
      23: new           #5                  // class java/lang/StringBuilder
      26: dup
      27: invokespecial #6                  // Method java/lang/StringBuilder."<init>":()V
      30: bipush        60
      32: invokevirtual #7                  // Method java/lang/StringBuilder.append:(C)Ljava/lang/StringBuilder;
      35: iload_1
      36: iconst_1
      37: aload_0
      38: getfield      #3                  // Field bitCount:S
      41: ishl
      42: ior
      43: invokestatic  #8                  // Method java/lang/Integer.toBinaryString:(I)Ljava/lang/String;
      46: iconst_1
      47: invokevirtual #9                  // Method java/lang/String.substring:(I)Ljava/lang/String;
      50: invokevirtual #10                 // Method java/lang/StringBuilder.append:(Ljava/lang/String;)Ljava/lang/StringBuilder;
      53: bipush        62
      55: invokevirtual #7                  // Method java/lang/StringBuilder.append:(C)Ljava/lang/StringBuilder;
      58: invokevirtual #11                 // Method java/lang/StringBuilder.toString:()Ljava/lang/String;
      61: areturn
}
