Compiled from "Token.java"
abstract class com.google.zxing.aztec.encoder.Token {
  static final com.google.zxing.aztec.encoder.Token EMPTY;

  private final com.google.zxing.aztec.encoder.Token previous;

  com.google.zxing.aztec.encoder.Token(com.google.zxing.aztec.encoder.Token);
    Code:
       0: aload_0
       1: invokespecial #1                  // Method java/lang/Object."<init>":()V
       4: aload_0
       5: aload_1
       6: putfield      #2                  // Field previous:Lcom/google/zxing/aztec/encoder/Token;
       9: return

  final com.google.zxing.aztec.encoder.Token getPrevious();
    Code:
       0: aload_0
       1: getfield      #2                  // Field previous:Lcom/google/zxing/aztec/encoder/Token;
       4: areturn

  final com.google.zxing.aztec.encoder.Token add(int, int);
    Code:
       0: new           #3                  // class com/google/zxing/aztec/encoder/SimpleToken
       3: dup
       4: aload_0
       5: iload_1
       6: iload_2
       7: invokespecial #4                  // Method com/google/zxing/aztec/encoder/SimpleToken."<init>":(Lcom/google/zxing/aztec/encoder/Token;II)V
      10: areturn

  final com.google.zxing.aztec.encoder.Token addBinaryShift(int, int);
    Code:
       0: new           #5                  // class com/google/zxing/aztec/encoder/BinaryShiftToken
       3: dup
       4: aload_0
       5: iload_1
       6: iload_2
       7: invokespecial #6                  // Method com/google/zxing/aztec/encoder/BinaryShiftToken."<init>":(Lcom/google/zxing/aztec/encoder/Token;II)V
      10: areturn

  abstract void appendTo(com.google.zxing.common.BitArray, byte[]);

  static {};
    Code:
       0: new           #3                  // class com/google/zxing/aztec/encoder/SimpleToken
       3: dup
       4: aconst_null
       5: iconst_0
       6: iconst_0
       7: invokespecial #4                  // Method com/google/zxing/aztec/encoder/SimpleToken."<init>":(Lcom/google/zxing/aztec/encoder/Token;II)V
      10: putstatic     #7                  // Field EMPTY:Lcom/google/zxing/aztec/encoder/Token;
      13: return
}
