Compiled from "AggregationConfig.java"
public class org.apache.dubbo.config.nested.AggregationConfig implements java.io.Serializable {
  private java.lang.Boolean enabled;

  private java.lang.Integer bucketNum;

  private java.lang.Integer timeWindowSeconds;

  public org.apache.dubbo.config.nested.AggregationConfig();
    Code:
       0: aload_0
       1: invokespecial #1                  // Method java/lang/Object."<init>":()V
       4: return

  public java.lang.Boolean getEnabled();
    Code:
       0: aload_0
       1: getfield      #2                  // Field enabled:Ljava/lang/Boolean;
       4: areturn

  public void setEnabled(java.lang.Boolean);
    Code:
       0: aload_0
       1: aload_1
       2: putfield      #2                  // Field enabled:Ljava/lang/Boolean;
       5: return

  public java.lang.Integer getBucketNum();
    Code:
       0: aload_0
       1: getfield      #3                  // Field bucketNum:Ljava/lang/Integer;
       4: areturn

  public void setBucketNum(java.lang.Integer);
    Code:
       0: aload_0
       1: aload_1
       2: putfield      #3                  // Field bucketNum:Ljava/lang/Integer;
       5: return

  public java.lang.Integer getTimeWindowSeconds();
    Code:
       0: aload_0
       1: getfield      #4                  // Field timeWindowSeconds:Ljava/lang/Integer;
       4: areturn

  public void setTimeWindowSeconds(java.lang.Integer);
    Code:
       0: aload_0
       1: aload_1
       2: putfield      #4                  // Field timeWindowSeconds:Ljava/lang/Integer;
       5: return
}
