Compiled from "BaggageConfig.java"
public class org.apache.dubbo.config.nested.BaggageConfig implements java.io.Serializable {
  private java.lang.Boolean enabled;

  private org.apache.dubbo.config.nested.BaggageConfig$Correlation correlation;

  private java.util.List<java.lang.String> remoteFields;

  public org.apache.dubbo.config.nested.BaggageConfig();
    Code:
       0: aload_0
       1: invokespecial #1                  // Method java/lang/Object."<init>":()V
       4: aload_0
       5: iconst_1
       6: invokestatic  #2                  // Method java/lang/Boolean.valueOf:(Z)Ljava/lang/Boolean;
       9: putfield      #3                  // Field enabled:Ljava/lang/Boolean;
      12: aload_0
      13: new           #4                  // class org/apache/dubbo/config/nested/BaggageConfig$Correlation
      16: dup
      17: invokespecial #5                  // Method org/apache/dubbo/config/nested/BaggageConfig$Correlation."<init>":()V
      20: putfield      #6                  // Field correlation:Lorg/apache/dubbo/config/nested/BaggageConfig$Correlation;
      23: aload_0
      24: new           #7                  // class java/util/ArrayList
      27: dup
      28: invokespecial #8                  // Method java/util/ArrayList."<init>":()V
      31: putfield      #9                  // Field remoteFields:Ljava/util/List;
      34: return

  public java.lang.Boolean getEnabled();
    Code:
       0: aload_0
       1: getfield      #3                  // Field enabled:Ljava/lang/Boolean;
       4: areturn

  public void setEnabled(java.lang.Boolean);
    Code:
       0: aload_0
       1: aload_1
       2: putfield      #3                  // Field enabled:Ljava/lang/Boolean;
       5: return

  public org.apache.dubbo.config.nested.BaggageConfig$Correlation getCorrelation();
    Code:
       0: aload_0
       1: getfield      #6                  // Field correlation:Lorg/apache/dubbo/config/nested/BaggageConfig$Correlation;
       4: areturn

  public void setCorrelation(org.apache.dubbo.config.nested.BaggageConfig$Correlation);
    Code:
       0: aload_0
       1: aload_1
       2: putfield      #6                  // Field correlation:Lorg/apache/dubbo/config/nested/BaggageConfig$Correlation;
       5: return

  public java.util.List<java.lang.String> getRemoteFields();
    Code:
       0: aload_0
       1: getfield      #9                  // Field remoteFields:Ljava/util/List;
       4: areturn

  public void setRemoteFields(java.util.List<java.lang.String>);
    Code:
       0: aload_0
       1: aload_1
       2: putfield      #9                  // Field remoteFields:Ljava/util/List;
       5: return
}
