Compiled from "BaggageConfig.java"
public class org.apache.dubbo.config.nested.BaggageConfig$Correlation implements java.io.Serializable {
  private boolean enabled;

  private java.util.List<java.lang.String> fields;

  public org.apache.dubbo.config.nested.BaggageConfig$Correlation();
    Code:
       0: aload_0
       1: invokespecial #1                  // Method java/lang/Object."<init>":()V
       4: aload_0
       5: iconst_1
       6: putfield      #2                  // Field enabled:Z
       9: aload_0
      10: new           #3                  // class java/util/ArrayList
      13: dup
      14: invokespecial #4                  // Method java/util/ArrayList."<init>":()V
      17: putfield      #5                  // Field fields:Ljava/util/List;
      20: return

  public boolean isEnabled();
    Code:
       0: aload_0
       1: getfield      #2                  // Field enabled:Z
       4: ireturn

  public void setEnabled(boolean);
    Code:
       0: aload_0
       1: iload_1
       2: putfield      #2                  // Field enabled:Z
       5: return

  public java.util.List<java.lang.String> getFields();
    Code:
       0: aload_0
       1: getfield      #5                  // Field fields:Ljava/util/List;
       4: areturn

  public void setFields(java.util.List<java.lang.String>);
    Code:
       0: aload_0
       1: aload_1
       2: putfield      #5                  // Field fields:Ljava/util/List;
       5: return
}
