Compiled from "ExporterConfig.java"
public class org.apache.dubbo.config.nested.ExporterConfig$OtlpConfig implements java.io.Serializable {
  private java.lang.String endpoint;

  private java.time.Duration timeout;

  private java.lang.String compressionMethod;

  private java.util.Map<java.lang.String, java.lang.String> headers;

  public org.apache.dubbo.config.nested.ExporterConfig$OtlpConfig();
    Code:
       0: aload_0
       1: invokespecial #1                  // Method java/lang/Object."<init>":()V
       4: aload_0
       5: ldc2_w        #2                  // long 10l
       8: invokestatic  #4                  // Method java/time/Duration.ofSeconds:(J)Ljava/time/Duration;
      11: putfield      #5                  // Field timeout:Ljava/time/Duration;
      14: aload_0
      15: ldc           #6                  // String none
      17: putfield      #7                  // Field compressionMethod:Ljava/lang/String;
      20: aload_0
      21: new           #8                  // class java/util/HashMap
      24: dup
      25: invokespecial #9                  // Method java/util/HashMap."<init>":()V
      28: putfield      #10                 // Field headers:Ljava/util/Map;
      31: return

  public java.lang.String getEndpoint();
    Code:
       0: aload_0
       1: getfield      #11                 // Field endpoint:Ljava/lang/String;
       4: areturn

  public void setEndpoint(java.lang.String);
    Code:
       0: aload_0
       1: aload_1
       2: putfield      #11                 // Field endpoint:Ljava/lang/String;
       5: return

  public java.time.Duration getTimeout();
    Code:
       0: aload_0
       1: getfield      #5                  // Field timeout:Ljava/time/Duration;
       4: areturn

  public void setTimeout(java.time.Duration);
    Code:
       0: aload_0
       1: aload_1
       2: putfield      #5                  // Field timeout:Ljava/time/Duration;
       5: return

  public java.lang.String getCompressionMethod();
    Code:
       0: aload_0
       1: getfield      #7                  // Field compressionMethod:Ljava/lang/String;
       4: areturn

  public void setCompressionMethod(java.lang.String);
    Code:
       0: aload_0
       1: aload_1
       2: putfield      #7                  // Field compressionMethod:Ljava/lang/String;
       5: return

  public java.util.Map<java.lang.String, java.lang.String> getHeaders();
    Code:
       0: aload_0
       1: getfield      #10                 // Field headers:Ljava/util/Map;
       4: areturn

  public void setHeaders(java.util.Map<java.lang.String, java.lang.String>);
    Code:
       0: aload_0
       1: aload_1
       2: putfield      #10                 // Field headers:Ljava/util/Map;
       5: return
}
