Compiled from "ExporterConfig.java"
public class org.apache.dubbo.config.nested.ExporterConfig$ZipkinConfig implements java.io.Serializable {
  private java.lang.String endpoint;

  private java.time.Duration connectTimeout;

  private java.time.Duration readTimeout;

  public org.apache.dubbo.config.nested.ExporterConfig$ZipkinConfig();
    Code:
       0: aload_0
       1: invokespecial #1                  // Method java/lang/Object."<init>":()V
       4: aload_0
       5: lconst_1
       6: invokestatic  #2                  // Method java/time/Duration.ofSeconds:(J)Ljava/time/Duration;
       9: putfield      #3                  // Field connectTimeout:Ljava/time/Duration;
      12: aload_0
      13: ldc2_w        #4                  // long 10l
      16: invokestatic  #2                  // Method java/time/Duration.ofSeconds:(J)Ljava/time/Duration;
      19: putfield      #6                  // Field readTimeout:Ljava/time/Duration;
      22: return

  public java.lang.String getEndpoint();
    Code:
       0: aload_0
       1: getfield      #7                  // Field endpoint:Ljava/lang/String;
       4: areturn

  public void setEndpoint(java.lang.String);
    Code:
       0: aload_0
       1: aload_1
       2: putfield      #7                  // Field endpoint:Ljava/lang/String;
       5: return

  public java.time.Duration getConnectTimeout();
    Code:
       0: aload_0
       1: getfield      #3                  // Field connectTimeout:Ljava/time/Duration;
       4: areturn

  public void setConnectTimeout(java.time.Duration);
    Code:
       0: aload_0
       1: aload_1
       2: putfield      #3                  // Field connectTimeout:Ljava/time/Duration;
       5: return

  public java.time.Duration getReadTimeout();
    Code:
       0: aload_0
       1: getfield      #6                  // Field readTimeout:Ljava/time/Duration;
       4: areturn

  public void setReadTimeout(java.time.Duration);
    Code:
       0: aload_0
       1: aload_1
       2: putfield      #6                  // Field readTimeout:Ljava/time/Duration;
       5: return
}
