Compiled from "ExporterConfig.java"
public class org.apache.dubbo.config.nested.ExporterConfig implements java.io.Serializable {
  private org.apache.dubbo.config.nested.ExporterConfig$ZipkinConfig zipkinConfig;

  private org.apache.dubbo.config.nested.ExporterConfig$OtlpConfig otlpConfig;

  public org.apache.dubbo.config.nested.ExporterConfig();
    Code:
       0: aload_0
       1: invokespecial #1                  // Method java/lang/Object."<init>":()V
       4: return

  public org.apache.dubbo.config.nested.ExporterConfig$ZipkinConfig getZipkinConfig();
    Code:
       0: aload_0
       1: getfield      #2                  // Field zipkinConfig:Lorg/apache/dubbo/config/nested/ExporterConfig$ZipkinConfig;
       4: areturn

  public void setZipkinConfig(org.apache.dubbo.config.nested.ExporterConfig$ZipkinConfig);
    Code:
       0: aload_0
       1: aload_1
       2: putfield      #2                  // Field zipkinConfig:Lorg/apache/dubbo/config/nested/ExporterConfig$ZipkinConfig;
       5: return

  public org.apache.dubbo.config.nested.ExporterConfig$OtlpConfig getOtlpConfig();
    Code:
       0: aload_0
       1: getfield      #3                  // Field otlpConfig:Lorg/apache/dubbo/config/nested/ExporterConfig$OtlpConfig;
       4: areturn

  public void setOtlpConfig(org.apache.dubbo.config.nested.ExporterConfig$OtlpConfig);
    Code:
       0: aload_0
       1: aload_1
       2: putfield      #3                  // Field otlpConfig:Lorg/apache/dubbo/config/nested/ExporterConfig$OtlpConfig;
       5: return
}
