Compiled from "HistogramConfig.java"
public class org.apache.dubbo.config.nested.HistogramConfig implements java.io.Serializable {
  private java.lang.Boolean enabled;

  private java.lang.Integer[] bucketsMs;

  private java.lang.Integer minExpectedMs;

  private java.lang.Integer maxExpectedMs;

  private java.lang.Boolean enabledPercentiles;

  private double[] percentiles;

  private java.lang.Integer distributionStatisticExpiryMin;

  public org.apache.dubbo.config.nested.HistogramConfig();
    Code:
       0: aload_0
       1: invokespecial #1                  // Method java/lang/Object."<init>":()V
       4: return

  public java.lang.Boolean getEnabled();
    Code:
       0: aload_0
       1: getfield      #2                  // Field enabled:Ljava/lang/Boolean;
       4: areturn

  public void setEnabled(java.lang.Boolean);
    Code:
       0: aload_0
       1: aload_1
       2: putfield      #2                  // Field enabled:Ljava/lang/Boolean;
       5: return

  public java.lang.Integer[] getBucketsMs();
    Code:
       0: aload_0
       1: getfield      #3                  // Field bucketsMs:[Ljava/lang/Integer;
       4: areturn

  public void setBucketsMs(java.lang.Integer[]);
    Code:
       0: aload_0
       1: aload_1
       2: putfield      #3                  // Field bucketsMs:[Ljava/lang/Integer;
       5: return

  public java.lang.Integer getMinExpectedMs();
    Code:
       0: aload_0
       1: getfield      #4                  // Field minExpectedMs:Ljava/lang/Integer;
       4: areturn

  public void setMinExpectedMs(java.lang.Integer);
    Code:
       0: aload_0
       1: aload_1
       2: putfield      #4                  // Field minExpectedMs:Ljava/lang/Integer;
       5: return

  public java.lang.Integer getMaxExpectedMs();
    Code:
       0: aload_0
       1: getfield      #5                  // Field maxExpectedMs:Ljava/lang/Integer;
       4: areturn

  public void setMaxExpectedMs(java.lang.Integer);
    Code:
       0: aload_0
       1: aload_1
       2: putfield      #5                  // Field maxExpectedMs:Ljava/lang/Integer;
       5: return

  public java.lang.Boolean getEnabledPercentiles();
    Code:
       0: aload_0
       1: getfield      #6                  // Field enabledPercentiles:Ljava/lang/Boolean;
       4: areturn

  public void setEnabledPercentiles(java.lang.Boolean);
    Code:
       0: aload_0
       1: aload_1
       2: putfield      #6                  // Field enabledPercentiles:Ljava/lang/Boolean;
       5: return

  public double[] getPercentiles();
    Code:
       0: aload_0
       1: getfield      #7                  // Field percentiles:[D
       4: areturn

  public void setPercentiles(double[]);
    Code:
       0: aload_0
       1: aload_1
       2: putfield      #7                  // Field percentiles:[D
       5: return

  public java.lang.Integer getDistributionStatisticExpiryMin();
    Code:
       0: aload_0
       1: getfield      #8                  // Field distributionStatisticExpiryMin:Ljava/lang/Integer;
       4: areturn

  public void setDistributionStatisticExpiryMin(java.lang.Integer);
    Code:
       0: aload_0
       1: aload_1
       2: putfield      #8                  // Field distributionStatisticExpiryMin:Ljava/lang/Integer;
       5: return
}
