Compiled from "PrometheusConfig.java"
public class org.apache.dubbo.config.nested.PrometheusConfig$Pushgateway implements java.io.Serializable {
  private java.lang.Boolean enabled;

  private java.lang.String baseUrl;

  private java.lang.String username;

  private java.lang.String password;

  private java.lang.Integer pushInterval;

  private java.lang.String job;

  public org.apache.dubbo.config.nested.PrometheusConfig$Pushgateway();
    Code:
       0: aload_0
       1: invokespecial #1                  // Method java/lang/Object."<init>":()V
       4: return

  public java.lang.Boolean getEnabled();
    Code:
       0: aload_0
       1: getfield      #2                  // Field enabled:Ljava/lang/Boolean;
       4: areturn

  public void setEnabled(java.lang.Boolean);
    Code:
       0: aload_0
       1: aload_1
       2: putfield      #2                  // Field enabled:Ljava/lang/Boolean;
       5: return

  public java.lang.String getBaseUrl();
    Code:
       0: aload_0
       1: getfield      #3                  // Field baseUrl:Ljava/lang/String;
       4: areturn

  public void setBaseUrl(java.lang.String);
    Code:
       0: aload_0
       1: aload_1
       2: putfield      #3                  // Field baseUrl:Ljava/lang/String;
       5: return

  public java.lang.String getUsername();
    Code:
       0: aload_0
       1: getfield      #4                  // Field username:Ljava/lang/String;
       4: areturn

  public void setUsername(java.lang.String);
    Code:
       0: aload_0
       1: aload_1
       2: putfield      #4                  // Field username:Ljava/lang/String;
       5: return

  public java.lang.String getPassword();
    Code:
       0: aload_0
       1: getfield      #5                  // Field password:Ljava/lang/String;
       4: areturn

  public void setPassword(java.lang.String);
    Code:
       0: aload_0
       1: aload_1
       2: putfield      #5                  // Field password:Ljava/lang/String;
       5: return

  public java.lang.Integer getPushInterval();
    Code:
       0: aload_0
       1: getfield      #6                  // Field pushInterval:Ljava/lang/Integer;
       4: areturn

  public void setPushInterval(java.lang.Integer);
    Code:
       0: aload_0
       1: aload_1
       2: putfield      #6                  // Field pushInterval:Ljava/lang/Integer;
       5: return

  public java.lang.String getJob();
    Code:
       0: aload_0
       1: getfield      #7                  // Field job:Ljava/lang/String;
       4: areturn

  public void setJob(java.lang.String);
    Code:
       0: aload_0
       1: aload_1
       2: putfield      #7                  // Field job:Ljava/lang/String;
       5: return
}
