Compiled from "PrometheusConfig.java"
public class org.apache.dubbo.config.nested.PrometheusConfig$Exporter implements java.io.Serializable {
  private java.lang.Boolean enabled;

  private java.lang.Boolean enableHttpServiceDiscovery;

  private java.lang.String httpServiceDiscoveryUrl;

  public org.apache.dubbo.config.nested.PrometheusConfig$Exporter();
    Code:
       0: aload_0
       1: invokespecial #1                  // Method java/lang/Object."<init>":()V
       4: return

  public java.lang.Boolean getEnabled();
    Code:
       0: aload_0
       1: getfield      #2                  // Field enabled:Ljava/lang/Boolean;
       4: areturn

  public void setEnabled(java.lang.Boolean);
    Code:
       0: aload_0
       1: aload_1
       2: putfield      #2                  // Field enabled:Ljava/lang/Boolean;
       5: return

  public java.lang.Boolean getEnableHttpServiceDiscovery();
    Code:
       0: aload_0
       1: getfield      #3                  // Field enableHttpServiceDiscovery:Ljava/lang/Boolean;
       4: areturn

  public void setEnableHttpServiceDiscovery(java.lang.Boolean);
    Code:
       0: aload_0
       1: aload_1
       2: putfield      #3                  // Field enableHttpServiceDiscovery:Ljava/lang/Boolean;
       5: return

  public java.lang.String getHttpServiceDiscoveryUrl();
    Code:
       0: aload_0
       1: getfield      #4                  // Field httpServiceDiscoveryUrl:Ljava/lang/String;
       4: areturn

  public void setHttpServiceDiscoveryUrl(java.lang.String);
    Code:
       0: aload_0
       1: aload_1
       2: putfield      #4                  // Field httpServiceDiscoveryUrl:Ljava/lang/String;
       5: return
}
