Compiled from "PrometheusConfig.java"
public class org.apache.dubbo.config.nested.PrometheusConfig implements java.io.Serializable {
  private org.apache.dubbo.config.nested.PrometheusConfig$Exporter exporter;

  private org.apache.dubbo.config.nested.PrometheusConfig$Pushgateway pushgateway;

  public org.apache.dubbo.config.nested.PrometheusConfig();
    Code:
       0: aload_0
       1: invokespecial #1                  // Method java/lang/Object."<init>":()V
       4: return

  public org.apache.dubbo.config.nested.PrometheusConfig$Exporter getExporter();
    Code:
       0: aload_0
       1: getfield      #2                  // Field exporter:Lorg/apache/dubbo/config/nested/PrometheusConfig$Exporter;
       4: areturn

  public void setExporter(org.apache.dubbo.config.nested.PrometheusConfig$Exporter);
    Code:
       0: aload_0
       1: aload_1
       2: putfield      #2                  // Field exporter:Lorg/apache/dubbo/config/nested/PrometheusConfig$Exporter;
       5: return

  public org.apache.dubbo.config.nested.PrometheusConfig$Pushgateway getPushgateway();
    Code:
       0: aload_0
       1: getfield      #3                  // Field pushgateway:Lorg/apache/dubbo/config/nested/PrometheusConfig$Pushgateway;
       4: areturn

  public void setPushgateway(org.apache.dubbo.config.nested.PrometheusConfig$Pushgateway);
    Code:
       0: aload_0
       1: aload_1
       2: putfield      #3                  // Field pushgateway:Lorg/apache/dubbo/config/nested/PrometheusConfig$Pushgateway;
       5: return
}
