Compiled from "PropagationConfig.java"
public class org.apache.dubbo.config.nested.PropagationConfig implements java.io.Serializable {
  public static final java.lang.String B3;

  public static final java.lang.String W3C;

  private java.lang.String type;

  public org.apache.dubbo.config.nested.PropagationConfig();
    Code:
       0: aload_0
       1: invokespecial #1                  // Method java/lang/Object."<init>":()V
       4: aload_0
       5: ldc           #3                  // String W3C
       7: putfield      #4                  // Field type:Ljava/lang/String;
      10: return

  public java.lang.String getType();
    Code:
       0: aload_0
       1: getfield      #4                  // Field type:Ljava/lang/String;
       4: areturn

  public void setType(java.lang.String);
    Code:
       0: aload_0
       1: aload_1
       2: putfield      #4                  // Field type:Ljava/lang/String;
       5: return
}
