Compiled from "GenericGF.java"
public final class com.google.zxing.common.reedsolomon.GenericGF {
  public static final com.google.zxing.common.reedsolomon.GenericGF AZTEC_DATA_12;

  public static final com.google.zxing.common.reedsolomon.GenericGF AZTEC_DATA_10;

  public static final com.google.zxing.common.reedsolomon.GenericGF AZTEC_DATA_6;

  public static final com.google.zxing.common.reedsolomon.GenericGF AZTEC_PARAM;

  public static final com.google.zxing.common.reedsolomon.GenericGF QR_CODE_FIELD_256;

  public static final com.google.zxing.common.reedsolomon.GenericGF DATA_MATRIX_FIELD_256;

  public static final com.google.zxing.common.reedsolomon.GenericGF AZTEC_DATA_8;

  public static final com.google.zxing.common.reedsolomon.GenericGF MAXICODE_FIELD_64;

  private final int[] expTable;

  private final int[] logTable;

  private final com.google.zxing.common.reedsolomon.GenericGFPoly zero;

  private final com.google.zxing.common.reedsolomon.GenericGFPoly one;

  private final int size;

  private final int primitive;

  private final int generatorBase;

  public com.google.zxing.common.reedsolomon.GenericGF(int, int, int);
    Code:
       0: aload_0
       1: invokespecial #1                  // Method java/lang/Object."<init>":()V
       4: aload_0
       5: iload_1
       6: putfield      #2                  // Field primitive:I
       9: aload_0
      10: iload_2
      11: putfield      #3                  // Field size:I
      14: aload_0
      15: iload_3
      16: putfield      #4                  // Field generatorBase:I
      19: aload_0
      20: iload_2
      21: newarray       int
      23: putfield      #5                  // Field expTable:[I
      26: aload_0
      27: iload_2
      28: newarray       int
      30: putfield      #6                  // Field logTable:[I
      33: iconst_1
      34: istore        4
      36: iconst_0
      37: istore        5
      39: iload         5
      41: iload_2
      42: if_icmpge     86
      45: aload_0
      46: getfield      #5                  // Field expTable:[I
      49: iload         5
      51: iload         4
      53: iastore
      54: iload         4
      56: iconst_2
      57: imul
      58: istore        4
      60: iload         4
      62: iload_2
      63: if_icmplt     80
      66: iload         4
      68: iload_1
      69: ixor
      70: istore        4
      72: iload         4
      74: iload_2
      75: iconst_1
      76: isub
      77: iand
      78: istore        4
      80: iinc          5, 1
      83: goto          39
      86: iconst_0
      87: istore        5
      89: iload         5
      91: iload_2
      92: iconst_1
      93: isub
      94: if_icmpge     117
      97: aload_0
      98: getfield      #6                  // Field logTable:[I
     101: aload_0
     102: getfield      #5                  // Field expTable:[I
     105: iload         5
     107: iaload
     108: iload         5
     110: iastore
     111: iinc          5, 1
     114: goto          89
     117: aload_0
     118: new           #7                  // class com/google/zxing/common/reedsolomon/GenericGFPoly
     121: dup
     122: aload_0
     123: iconst_1
     124: newarray       int
     126: dup
     127: iconst_0
     128: iconst_0
     129: iastore
     130: invokespecial #8                  // Method com/google/zxing/common/reedsolomon/GenericGFPoly."<init>":(Lcom/google/zxing/common/reedsolomon/GenericGF;[I)V
     133: putfield      #9                  // Field zero:Lcom/google/zxing/common/reedsolomon/GenericGFPoly;
     136: aload_0
     137: new           #7                  // class com/google/zxing/common/reedsolomon/GenericGFPoly
     140: dup
     141: aload_0
     142: iconst_1
     143: newarray       int
     145: dup
     146: iconst_0
     147: iconst_1
     148: iastore
     149: invokespecial #8                  // Method com/google/zxing/common/reedsolomon/GenericGFPoly."<init>":(Lcom/google/zxing/common/reedsolomon/GenericGF;[I)V
     152: putfield      #10                 // Field one:Lcom/google/zxing/common/reedsolomon/GenericGFPoly;
     155: return

  com.google.zxing.common.reedsolomon.GenericGFPoly getZero();
    Code:
       0: aload_0
       1: getfield      #9                  // Field zero:Lcom/google/zxing/common/reedsolomon/GenericGFPoly;
       4: areturn

  com.google.zxing.common.reedsolomon.GenericGFPoly getOne();
    Code:
       0: aload_0
       1: getfield      #10                 // Field one:Lcom/google/zxing/common/reedsolomon/GenericGFPoly;
       4: areturn

  com.google.zxing.common.reedsolomon.GenericGFPoly buildMonomial(int, int);
    Code:
       0: iload_1
       1: ifge          12
       4: new           #11                 // class java/lang/IllegalArgumentException
       7: dup
       8: invokespecial #12                 // Method java/lang/IllegalArgumentException."<init>":()V
      11: athrow
      12: iload_2
      13: ifne          21
      16: aload_0
      17: getfield      #9                  // Field zero:Lcom/google/zxing/common/reedsolomon/GenericGFPoly;
      20: areturn
      21: iload_1
      22: iconst_1
      23: iadd
      24: newarray       int
      26: astore_3
      27: aload_3
      28: iconst_0
      29: iload_2
      30: iastore
      31: new           #7                  // class com/google/zxing/common/reedsolomon/GenericGFPoly
      34: dup
      35: aload_0
      36: aload_3
      37: invokespecial #8                  // Method com/google/zxing/common/reedsolomon/GenericGFPoly."<init>":(Lcom/google/zxing/common/reedsolomon/GenericGF;[I)V
      40: areturn

  static int addOrSubtract(int, int);
    Code:
       0: iload_0
       1: iload_1
       2: ixor
       3: ireturn

  int exp(int);
    Code:
       0: aload_0
       1: getfield      #5                  // Field expTable:[I
       4: iload_1
       5: iaload
       6: ireturn

  int log(int);
    Code:
       0: iload_1
       1: ifne          12
       4: new           #11                 // class java/lang/IllegalArgumentException
       7: dup
       8: invokespecial #12                 // Method java/lang/IllegalArgumentException."<init>":()V
      11: athrow
      12: aload_0
      13: getfield      #6                  // Field logTable:[I
      16: iload_1
      17: iaload
      18: ireturn

  int inverse(int);
    Code:
       0: iload_1
       1: ifne          12
       4: new           #13                 // class java/lang/ArithmeticException
       7: dup
       8: invokespecial #14                 // Method java/lang/ArithmeticException."<init>":()V
      11: athrow
      12: aload_0
      13: getfield      #5                  // Field expTable:[I
      16: aload_0
      17: getfield      #3                  // Field size:I
      20: aload_0
      21: getfield      #6                  // Field logTable:[I
      24: iload_1
      25: iaload
      26: isub
      27: iconst_1
      28: isub
      29: iaload
      30: ireturn

  int multiply(int, int);
    Code:
       0: iload_1
       1: ifeq          8
       4: iload_2
       5: ifne          10
       8: iconst_0
       9: ireturn
      10: aload_0
      11: getfield      #5                  // Field expTable:[I
      14: aload_0
      15: getfield      #6                  // Field logTable:[I
      18: iload_1
      19: iaload
      20: aload_0
      21: getfield      #6                  // Field logTable:[I
      24: iload_2
      25: iaload
      26: iadd
      27: aload_0
      28: getfield      #3                  // Field size:I
      31: iconst_1
      32: isub
      33: irem
      34: iaload
      35: ireturn

  public int getSize();
    Code:
       0: aload_0
       1: getfield      #3                  // Field size:I
       4: ireturn

  public int getGeneratorBase();
    Code:
       0: aload_0
       1: getfield      #4                  // Field generatorBase:I
       4: ireturn

  public java.lang.String toString();
    Code:
       0: new           #15                 // class java/lang/StringBuilder
       3: dup
       4: invokespecial #16                 // Method java/lang/StringBuilder."<init>":()V
       7: ldc           #17                 // String GF(0x
       9: invokevirtual #18                 // Method java/lang/StringBuilder.append:(Ljava/lang/String;)Ljava/lang/StringBuilder;
      12: aload_0
      13: getfield      #2                  // Field primitive:I
      16: invokestatic  #19                 // Method java/lang/Integer.toHexString:(I)Ljava/lang/String;
      19: invokevirtual #18                 // Method java/lang/StringBuilder.append:(Ljava/lang/String;)Ljava/lang/StringBuilder;
      22: bipush        44
      24: invokevirtual #20                 // Method java/lang/StringBuilder.append:(C)Ljava/lang/StringBuilder;
      27: aload_0
      28: getfield      #3                  // Field size:I
      31: invokevirtual #21                 // Method java/lang/StringBuilder.append:(I)Ljava/lang/StringBuilder;
      34: bipush        41
      36: invokevirtual #20                 // Method java/lang/StringBuilder.append:(C)Ljava/lang/StringBuilder;
      39: invokevirtual #22                 // Method java/lang/StringBuilder.toString:()Ljava/lang/String;
      42: areturn

  static {};
    Code:
       0: new           #23                 // class com/google/zxing/common/reedsolomon/GenericGF
       3: dup
       4: sipush        4201
       7: sipush        4096
      10: iconst_1
      11: invokespecial #24                 // Method "<init>":(III)V
      14: putstatic     #25                 // Field AZTEC_DATA_12:Lcom/google/zxing/common/reedsolomon/GenericGF;
      17: new           #23                 // class com/google/zxing/common/reedsolomon/GenericGF
      20: dup
      21: sipush        1033
      24: sipush        1024
      27: iconst_1
      28: invokespecial #24                 // Method "<init>":(III)V
      31: putstatic     #26                 // Field AZTEC_DATA_10:Lcom/google/zxing/common/reedsolomon/GenericGF;
      34: new           #23                 // class com/google/zxing/common/reedsolomon/GenericGF
      37: dup
      38: bipush        67
      40: bipush        64
      42: iconst_1
      43: invokespecial #24                 // Method "<init>":(III)V
      46: putstatic     #27                 // Field AZTEC_DATA_6:Lcom/google/zxing/common/reedsolomon/GenericGF;
      49: new           #23                 // class com/google/zxing/common/reedsolomon/GenericGF
      52: dup
      53: bipush        19
      55: bipush        16
      57: iconst_1
      58: invokespecial #24                 // Method "<init>":(III)V
      61: putstatic     #28                 // Field AZTEC_PARAM:Lcom/google/zxing/common/reedsolomon/GenericGF;
      64: new           #23                 // class com/google/zxing/common/reedsolomon/GenericGF
      67: dup
      68: sipush        285
      71: sipush        256
      74: iconst_0
      75: invokespecial #24                 // Method "<init>":(III)V
      78: putstatic     #29                 // Field QR_CODE_FIELD_256:Lcom/google/zxing/common/reedsolomon/GenericGF;
      81: new           #23                 // class com/google/zxing/common/reedsolomon/GenericGF
      84: dup
      85: sipush        301
      88: sipush        256
      91: iconst_1
      92: invokespecial #24                 // Method "<init>":(III)V
      95: putstatic     #30                 // Field DATA_MATRIX_FIELD_256:Lcom/google/zxing/common/reedsolomon/GenericGF;
      98: getstatic     #30                 // Field DATA_MATRIX_FIELD_256:Lcom/google/zxing/common/reedsolomon/GenericGF;
     101: putstatic     #31                 // Field AZTEC_DATA_8:Lcom/google/zxing/common/reedsolomon/GenericGF;
     104: getstatic     #27                 // Field AZTEC_DATA_6:Lcom/google/zxing/common/reedsolomon/GenericGF;
     107: putstatic     #32                 // Field MAXICODE_FIELD_64:Lcom/google/zxing/common/reedsolomon/GenericGF;
     110: return
}
