Compiled from "ReedSolomonEncoder.java"
public final class com.google.zxing.common.reedsolomon.ReedSolomonEncoder {
  private final com.google.zxing.common.reedsolomon.GenericGF field;

  private final java.util.List<com.google.zxing.common.reedsolomon.GenericGFPoly> cachedGenerators;

  public com.google.zxing.common.reedsolomon.ReedSolomonEncoder(com.google.zxing.common.reedsolomon.GenericGF);
    Code:
       0: aload_0
       1: invokespecial #1                  // Method java/lang/Object."<init>":()V
       4: aload_0
       5: aload_1
       6: putfield      #2                  // Field field:Lcom/google/zxing/common/reedsolomon/GenericGF;
       9: aload_0
      10: new           #3                  // class java/util/ArrayList
      13: dup
      14: invokespecial #4                  // Method java/util/ArrayList."<init>":()V
      17: putfield      #5                  // Field cachedGenerators:Ljava/util/List;
      20: aload_0
      21: getfield      #5                  // Field cachedGenerators:Ljava/util/List;
      24: new           #6                  // class com/google/zxing/common/reedsolomon/GenericGFPoly
      27: dup
      28: aload_1
      29: iconst_1
      30: newarray       int
      32: dup
      33: iconst_0
      34: iconst_1
      35: iastore
      36: invokespecial #7                  // Method com/google/zxing/common/reedsolomon/GenericGFPoly."<init>":(Lcom/google/zxing/common/reedsolomon/GenericGF;[I)V
      39: invokeinterface #8,  2            // InterfaceMethod java/util/List.add:(Ljava/lang/Object;)Z
      44: pop
      45: return

  private com.google.zxing.common.reedsolomon.GenericGFPoly buildGenerator(int);
    Code:
       0: iload_1
       1: aload_0
       2: getfield      #5                  // Field cachedGenerators:Ljava/util/List;
       5: invokeinterface #9,  1            // InterfaceMethod java/util/List.size:()I
      10: if_icmplt     118
      13: aload_0
      14: getfield      #5                  // Field cachedGenerators:Ljava/util/List;
      17: aload_0
      18: getfield      #5                  // Field cachedGenerators:Ljava/util/List;
      21: invokeinterface #9,  1            // InterfaceMethod java/util/List.size:()I
      26: iconst_1
      27: isub
      28: invokeinterface #10,  2           // InterfaceMethod java/util/List.get:(I)Ljava/lang/Object;
      33: checkcast     #6                  // class com/google/zxing/common/reedsolomon/GenericGFPoly
      36: astore_2
      37: aload_0
      38: getfield      #5                  // Field cachedGenerators:Ljava/util/List;
      41: invokeinterface #9,  1            // InterfaceMethod java/util/List.size:()I
      46: istore_3
      47: iload_3
      48: iload_1
      49: if_icmpgt     118
      52: aload_2
      53: new           #6                  // class com/google/zxing/common/reedsolomon/GenericGFPoly
      56: dup
      57: aload_0
      58: getfield      #2                  // Field field:Lcom/google/zxing/common/reedsolomon/GenericGF;
      61: iconst_2
      62: newarray       int
      64: dup
      65: iconst_0
      66: iconst_1
      67: iastore
      68: dup
      69: iconst_1
      70: aload_0
      71: getfield      #2                  // Field field:Lcom/google/zxing/common/reedsolomon/GenericGF;
      74: iload_3
      75: iconst_1
      76: isub
      77: aload_0
      78: getfield      #2                  // Field field:Lcom/google/zxing/common/reedsolomon/GenericGF;
      81: invokevirtual #11                 // Method com/google/zxing/common/reedsolomon/GenericGF.getGeneratorBase:()I
      84: iadd
      85: invokevirtual #12                 // Method com/google/zxing/common/reedsolomon/GenericGF.exp:(I)I
      88: iastore
      89: invokespecial #7                  // Method com/google/zxing/common/reedsolomon/GenericGFPoly."<init>":(Lcom/google/zxing/common/reedsolomon/GenericGF;[I)V
      92: invokevirtual #13                 // Method com/google/zxing/common/reedsolomon/GenericGFPoly.multiply:(Lcom/google/zxing/common/reedsolomon/GenericGFPoly;)Lcom/google/zxing/common/reedsolomon/GenericGFPoly;
      95: astore        4
      97: aload_0
      98: getfield      #5                  // Field cachedGenerators:Ljava/util/List;
     101: aload         4
     103: invokeinterface #8,  2            // InterfaceMethod java/util/List.add:(Ljava/lang/Object;)Z
     108: pop
     109: aload         4
     111: astore_2
     112: iinc          3, 1
     115: goto          47
     118: aload_0
     119: getfield      #5                  // Field cachedGenerators:Ljava/util/List;
     122: iload_1
     123: invokeinterface #10,  2           // InterfaceMethod java/util/List.get:(I)Ljava/lang/Object;
     128: checkcast     #6                  // class com/google/zxing/common/reedsolomon/GenericGFPoly
     131: areturn

  public void encode(int[], int);
    Code:
       0: iload_2
       1: ifne          14
       4: new           #14                 // class java/lang/IllegalArgumentException
       7: dup
       8: ldc           #15                 // String No error correction bytes
      10: invokespecial #16                 // Method java/lang/IllegalArgumentException."<init>":(Ljava/lang/String;)V
      13: athrow
      14: aload_1
      15: arraylength
      16: iload_2
      17: isub
      18: istore_3
      19: iload_3
      20: ifgt          33
      23: new           #14                 // class java/lang/IllegalArgumentException
      26: dup
      27: ldc           #17                 // String No data bytes provided
      29: invokespecial #16                 // Method java/lang/IllegalArgumentException."<init>":(Ljava/lang/String;)V
      32: athrow
      33: aload_0
      34: iload_2
      35: invokespecial #18                 // Method buildGenerator:(I)Lcom/google/zxing/common/reedsolomon/GenericGFPoly;
      38: astore        4
      40: iload_3
      41: newarray       int
      43: astore        5
      45: aload_1
      46: iconst_0
      47: aload         5
      49: iconst_0
      50: iload_3
      51: invokestatic  #19                 // Method java/lang/System.arraycopy:(Ljava/lang/Object;ILjava/lang/Object;II)V
      54: new           #6                  // class com/google/zxing/common/reedsolomon/GenericGFPoly
      57: dup
      58: aload_0
      59: getfield      #2                  // Field field:Lcom/google/zxing/common/reedsolomon/GenericGF;
      62: aload         5
      64: invokespecial #7                  // Method com/google/zxing/common/reedsolomon/GenericGFPoly."<init>":(Lcom/google/zxing/common/reedsolomon/GenericGF;[I)V
      67: astore        6
      69: aload         6
      71: iload_2
      72: iconst_1
      73: invokevirtual #20                 // Method com/google/zxing/common/reedsolomon/GenericGFPoly.multiplyByMonomial:(II)Lcom/google/zxing/common/reedsolomon/GenericGFPoly;
      76: astore        6
      78: aload         6
      80: aload         4
      82: invokevirtual #21                 // Method com/google/zxing/common/reedsolomon/GenericGFPoly.divide:(Lcom/google/zxing/common/reedsolomon/GenericGFPoly;)[Lcom/google/zxing/common/reedsolomon/GenericGFPoly;
      85: iconst_1
      86: aaload
      87: astore        7
      89: aload         7
      91: invokevirtual #22                 // Method com/google/zxing/common/reedsolomon/GenericGFPoly.getCoefficients:()[I
      94: astore        8
      96: iload_2
      97: aload         8
      99: arraylength
     100: isub
     101: istore        9
     103: iconst_0
     104: istore        10
     106: iload         10
     108: iload         9
     110: if_icmpge     126
     113: aload_1
     114: iload_3
     115: iload         10
     117: iadd
     118: iconst_0
     119: iastore
     120: iinc          10, 1
     123: goto          106
     126: aload         8
     128: iconst_0
     129: aload_1
     130: iload_3
     131: iload         9
     133: iadd
     134: aload         8
     136: arraylength
     137: invokestatic  #19                 // Method java/lang/System.arraycopy:(Ljava/lang/Object;ILjava/lang/Object;II)V
     140: return
}
