Compiled from "ZoneAwareCluster.java"
public class org.apache.dubbo.rpc.cluster.support.registry.ZoneAwareCluster extends org.apache.dubbo.rpc.cluster.support.wrapper.AbstractCluster {
  public static final java.lang.String NAME;

  public org.apache.dubbo.rpc.cluster.support.registry.ZoneAwareCluster();
    Code:
       0: aload_0
       1: invokespecial #1                  // Method org/apache/dubbo/rpc/cluster/support/wrapper/AbstractCluster."<init>":()V
       4: return

  protected <T> org.apache.dubbo.rpc.cluster.support.AbstractClusterInvoker<T> doJoin(org.apache.dubbo.rpc.cluster.Directory<T>) throws org.apache.dubbo.rpc.RpcException;
    Code:
       0: new           #2                  // class org/apache/dubbo/rpc/cluster/support/registry/ZoneAwareClusterInvoker
       3: dup
       4: aload_1
       5: invokespecial #3                  // Method org/apache/dubbo/rpc/cluster/support/registry/ZoneAwareClusterInvoker."<init>":(Lorg/apache/dubbo/rpc/cluster/Directory;)V
       8: areturn
}
