Compiled from "ZoneAwareClusterInvoker.java"
public class org.apache.dubbo.rpc.cluster.support.registry.ZoneAwareClusterInvoker<T> extends org.apache.dubbo.rpc.cluster.support.AbstractClusterInvoker<T> {
  private static final org.apache.dubbo.common.logger.Logger logger;

  private org.apache.dubbo.rpc.ZoneDetector zoneDetector;

  public org.apache.dubbo.rpc.cluster.support.registry.ZoneAwareClusterInvoker(org.apache.dubbo.rpc.cluster.Directory<T>);
    Code:
       0: aload_0
       1: aload_1
       2: invokespecial #3                  // Method org/apache/dubbo/rpc/cluster/support/AbstractClusterInvoker."<init>":(Lorg/apache/dubbo/rpc/cluster/Directory;)V
       5: aload_1
       6: invokeinterface #4,  1            // InterfaceMethod org/apache/dubbo/rpc/cluster/Directory.getConsumerUrl:()Lorg/apache/dubbo/common/URL;
      11: invokevirtual #5                  // Method org/apache/dubbo/common/URL.getOrDefaultApplicationModel:()Lorg/apache/dubbo/rpc/model/ApplicationModel;
      14: ldc           #6                  // class org/apache/dubbo/rpc/ZoneDetector
      16: invokevirtual #7                  // Method org/apache/dubbo/rpc/model/ApplicationModel.getExtensionLoader:(Ljava/lang/Class;)Lorg/apache/dubbo/common/extension/ExtensionLoader;
      19: astore_2
      20: aload_2
      21: ldc           #8                  // String default
      23: invokevirtual #9                  // Method org/apache/dubbo/common/extension/ExtensionLoader.hasExtension:(Ljava/lang/String;)Z
      26: ifeq          42
      29: aload_0
      30: aload_2
      31: ldc           #8                  // String default
      33: invokevirtual #10                 // Method org/apache/dubbo/common/extension/ExtensionLoader.getExtension:(Ljava/lang/String;)Ljava/lang/Object;
      36: checkcast     #6                  // class org/apache/dubbo/rpc/ZoneDetector
      39: putfield      #11                 // Field zoneDetector:Lorg/apache/dubbo/rpc/ZoneDetector;
      42: return

  public org.apache.dubbo.rpc.Result doInvoke(org.apache.dubbo.rpc.Invocation, java.util.List<org.apache.dubbo.rpc.Invoker<T>>, org.apache.dubbo.rpc.cluster.LoadBalance) throws org.apache.dubbo.rpc.RpcException;
    Code:
       0: aload_2
       1: invokeinterface #12,  1           // InterfaceMethod java/util/List.iterator:()Ljava/util/Iterator;
       6: astore        4
       8: aload         4
      10: invokeinterface #13,  1           // InterfaceMethod java/util/Iterator.hasNext:()Z
      15: ifeq          75
      18: aload         4
      20: invokeinterface #14,  1           // InterfaceMethod java/util/Iterator.next:()Ljava/lang/Object;
      25: checkcast     #15                 // class org/apache/dubbo/rpc/Invoker
      28: astore        5
      30: aload         5
      32: checkcast     #16                 // class org/apache/dubbo/rpc/cluster/ClusterInvoker
      35: astore        6
      37: aload         6
      39: invokeinterface #17,  1           // InterfaceMethod org/apache/dubbo/rpc/cluster/ClusterInvoker.isAvailable:()Z
      44: ifeq          72
      47: aload         6
      49: invokeinterface #18,  1           // InterfaceMethod org/apache/dubbo/rpc/cluster/ClusterInvoker.getRegistryUrl:()Lorg/apache/dubbo/common/URL;
      54: ldc           #19                 // String preferred
      56: iconst_0
      57: invokevirtual #20                 // Method org/apache/dubbo/common/URL.getParameter:(Ljava/lang/String;Z)Z
      60: ifeq          72
      63: aload         6
      65: aload_1
      66: invokeinterface #21,  2           // InterfaceMethod org/apache/dubbo/rpc/cluster/ClusterInvoker.invoke:(Lorg/apache/dubbo/rpc/Invocation;)Lorg/apache/dubbo/rpc/Result;
      71: areturn
      72: goto          8
      75: invokestatic  #22                 // Method org/apache/dubbo/rpc/RpcContext.getClientAttachment:()Lorg/apache/dubbo/rpc/RpcContextAttachment;
      78: astore        4
      80: aload         4
      82: ldc           #23                 // String registry_zone
      84: invokevirtual #24                 // Method org/apache/dubbo/rpc/RpcContext.getAttachment:(Ljava/lang/String;)Ljava/lang/String;
      87: astore        5
      89: aload         4
      91: ldc           #25                 // String registry_zone_force
      93: invokevirtual #24                 // Method org/apache/dubbo/rpc/RpcContext.getAttachment:(Ljava/lang/String;)Ljava/lang/String;
      96: astore        6
      98: aload         5
     100: invokestatic  #26                 // Method org/apache/dubbo/common/utils/StringUtils.isEmpty:(Ljava/lang/String;)Z
     103: ifeq          139
     106: aload_0
     107: getfield      #11                 // Field zoneDetector:Lorg/apache/dubbo/rpc/ZoneDetector;
     110: ifnull        139
     113: aload_0
     114: getfield      #11                 // Field zoneDetector:Lorg/apache/dubbo/rpc/ZoneDetector;
     117: aload_1
     118: invokeinterface #27,  2           // InterfaceMethod org/apache/dubbo/rpc/ZoneDetector.getZoneOfCurrentRequest:(Lorg/apache/dubbo/rpc/Invocation;)Ljava/lang/String;
     123: astore        5
     125: aload_0
     126: getfield      #11                 // Field zoneDetector:Lorg/apache/dubbo/rpc/ZoneDetector;
     129: aload_1
     130: aload         5
     132: invokeinterface #28,  3           // InterfaceMethod org/apache/dubbo/rpc/ZoneDetector.isZoneForcingEnabled:(Lorg/apache/dubbo/rpc/Invocation;Ljava/lang/String;)Ljava/lang/String;
     137: astore        6
     139: aload         5
     141: invokestatic  #29                 // Method org/apache/dubbo/common/utils/StringUtils.isNotEmpty:(Ljava/lang/String;)Z
     144: ifeq          309
     147: aload_2
     148: invokeinterface #12,  1           // InterfaceMethod java/util/List.iterator:()Ljava/util/Iterator;
     153: astore        7
     155: aload         7
     157: invokeinterface #13,  1           // InterfaceMethod java/util/Iterator.hasNext:()Z
     162: ifeq          226
     165: aload         7
     167: invokeinterface #14,  1           // InterfaceMethod java/util/Iterator.next:()Ljava/lang/Object;
     172: checkcast     #15                 // class org/apache/dubbo/rpc/Invoker
     175: astore        8
     177: aload         8
     179: checkcast     #16                 // class org/apache/dubbo/rpc/cluster/ClusterInvoker
     182: astore        9
     184: aload         9
     186: invokeinterface #17,  1           // InterfaceMethod org/apache/dubbo/rpc/cluster/ClusterInvoker.isAvailable:()Z
     191: ifeq          223
     194: aload         5
     196: aload         9
     198: invokeinterface #18,  1           // InterfaceMethod org/apache/dubbo/rpc/cluster/ClusterInvoker.getRegistryUrl:()Lorg/apache/dubbo/common/URL;
     203: ldc           #30                 // String zone
     205: invokevirtual #31                 // Method org/apache/dubbo/common/URL.getParameter:(Ljava/lang/String;)Ljava/lang/String;
     208: invokevirtual #32                 // Method java/lang/String.equals:(Ljava/lang/Object;)Z
     211: ifeq          223
     214: aload         9
     216: aload_1
     217: invokeinterface #21,  2           // InterfaceMethod org/apache/dubbo/rpc/cluster/ClusterInvoker.invoke:(Lorg/apache/dubbo/rpc/Invocation;)Lorg/apache/dubbo/rpc/Result;
     222: areturn
     223: goto          155
     226: aload         6
     228: invokestatic  #29                 // Method org/apache/dubbo/common/utils/StringUtils.isNotEmpty:(Ljava/lang/String;)Z
     231: ifeq          309
     234: ldc           #33                 // String true
     236: aload         6
     238: invokevirtual #34                 // Method java/lang/String.equalsIgnoreCase:(Ljava/lang/String;)Z
     241: ifeq          309
     244: new           #35                 // class java/lang/IllegalStateException
     247: dup
     248: new           #36                 // class java/lang/StringBuilder
     251: dup
     252: invokespecial #37                 // Method java/lang/StringBuilder."<init>":()V
     255: ldc           #38                 // String No registry instance in zone or no available providers in the registry, zone:
     257: invokevirtual #39                 // Method java/lang/StringBuilder.append:(Ljava/lang/String;)Ljava/lang/StringBuilder;
     260: aload         5
     262: invokevirtual #39                 // Method java/lang/StringBuilder.append:(Ljava/lang/String;)Ljava/lang/StringBuilder;
     265: ldc           #40                 // String , registries:
     267: invokevirtual #39                 // Method java/lang/StringBuilder.append:(Ljava/lang/String;)Ljava/lang/StringBuilder;
     270: aload_2
     271: invokeinterface #41,  1           // InterfaceMethod java/util/List.stream:()Ljava/util/stream/Stream;
     276: invokedynamic #42,  0             // InvokeDynamic #0:apply:()Ljava/util/function/Function;
     281: invokeinterface #43,  2           // InterfaceMethod java/util/stream/Stream.map:(Ljava/util/function/Function;)Ljava/util/stream/Stream;
     286: ldc           #44                 // String ,
     288: invokestatic  #45                 // Method java/util/stream/Collectors.joining:(Ljava/lang/CharSequence;)Ljava/util/stream/Collector;
     291: invokeinterface #46,  2           // InterfaceMethod java/util/stream/Stream.collect:(Ljava/util/stream/Collector;)Ljava/lang/Object;
     296: checkcast     #47                 // class java/lang/String
     299: invokevirtual #39                 // Method java/lang/StringBuilder.append:(Ljava/lang/String;)Ljava/lang/StringBuilder;
     302: invokevirtual #48                 // Method java/lang/StringBuilder.toString:()Ljava/lang/String;
     305: invokespecial #49                 // Method java/lang/IllegalStateException."<init>":(Ljava/lang/String;)V
     308: athrow
     309: aload_0
     310: aload_3
     311: aload_1
     312: aload_2
     313: aconst_null
     314: invokevirtual #50                 // Method select:(Lorg/apache/dubbo/rpc/cluster/LoadBalance;Lorg/apache/dubbo/rpc/Invocation;Ljava/util/List;Ljava/util/List;)Lorg/apache/dubbo/rpc/Invoker;
     317: astore        7
     319: aload         7
     321: ifnull        343
     324: aload         7
     326: invokeinterface #51,  1           // InterfaceMethod org/apache/dubbo/rpc/Invoker.isAvailable:()Z
     331: ifeq          343
     334: aload         7
     336: aload_1
     337: invokeinterface #52,  2           // InterfaceMethod org/apache/dubbo/rpc/Invoker.invoke:(Lorg/apache/dubbo/rpc/Invocation;)Lorg/apache/dubbo/rpc/Result;
     342: areturn
     343: aload_2
     344: invokeinterface #12,  1           // InterfaceMethod java/util/List.iterator:()Ljava/util/Iterator;
     349: astore        8
     351: aload         8
     353: invokeinterface #13,  1           // InterfaceMethod java/util/Iterator.hasNext:()Z
     358: ifeq          402
     361: aload         8
     363: invokeinterface #14,  1           // InterfaceMethod java/util/Iterator.next:()Ljava/lang/Object;
     368: checkcast     #15                 // class org/apache/dubbo/rpc/Invoker
     371: astore        9
     373: aload         9
     375: checkcast     #16                 // class org/apache/dubbo/rpc/cluster/ClusterInvoker
     378: astore        10
     380: aload         10
     382: invokeinterface #17,  1           // InterfaceMethod org/apache/dubbo/rpc/cluster/ClusterInvoker.isAvailable:()Z
     387: ifeq          399
     390: aload         10
     392: aload_1
     393: invokeinterface #21,  2           // InterfaceMethod org/apache/dubbo/rpc/cluster/ClusterInvoker.invoke:(Lorg/apache/dubbo/rpc/Invocation;)Lorg/apache/dubbo/rpc/Result;
     398: areturn
     399: goto          351
     402: new           #53                 // class org/apache/dubbo/rpc/RpcException
     405: dup
     406: new           #36                 // class java/lang/StringBuilder
     409: dup
     410: invokespecial #37                 // Method java/lang/StringBuilder."<init>":()V
     413: ldc           #54                 // String No provider available in
     415: invokevirtual #39                 // Method java/lang/StringBuilder.append:(Ljava/lang/String;)Ljava/lang/StringBuilder;
     418: aload_2
     419: invokevirtual #55                 // Method java/lang/StringBuilder.append:(Ljava/lang/Object;)Ljava/lang/StringBuilder;
     422: invokevirtual #48                 // Method java/lang/StringBuilder.toString:()Ljava/lang/String;
     425: invokespecial #56                 // Method org/apache/dubbo/rpc/RpcException."<init>":(Ljava/lang/String;)V
     428: athrow

  private static java.lang.String lambda$doInvoke$0(org.apache.dubbo.rpc.Invoker);
    Code:
       0: aload_0
       1: checkcast     #16                 // class org/apache/dubbo/rpc/cluster/ClusterInvoker
       4: invokeinterface #18,  1           // InterfaceMethod org/apache/dubbo/rpc/cluster/ClusterInvoker.getRegistryUrl:()Lorg/apache/dubbo/common/URL;
       9: invokevirtual #57                 // Method org/apache/dubbo/common/URL.toString:()Ljava/lang/String;
      12: areturn

  static {};
    Code:
       0: ldc           #58                 // class org/apache/dubbo/rpc/cluster/support/registry/ZoneAwareClusterInvoker
       2: invokestatic  #59                 // Method org/apache/dubbo/common/logger/LoggerFactory.getLogger:(Ljava/lang/Class;)Lorg/apache/dubbo/common/logger/Logger;
       5: putstatic     #60                 // Field logger:Lorg/apache/dubbo/common/logger/Logger;
       8: return
}
