Compiled from "AbstractChannelHandlerDelegate.java"
public abstract class org.apache.dubbo.remoting.transport.AbstractChannelHandlerDelegate implements org.apache.dubbo.remoting.transport.ChannelHandlerDelegate {
  protected org.apache.dubbo.remoting.ChannelHandler handler;

  protected org.apache.dubbo.remoting.transport.AbstractChannelHandlerDelegate(org.apache.dubbo.remoting.ChannelHandler);
    Code:
       0: aload_0
       1: invokespecial #1                  // Method java/lang/Object."<init>":()V
       4: aload_1
       5: ldc           #2                  // String handler == null
       7: invokestatic  #3                  // Method org/apache/dubbo/common/utils/Assert.notNull:(Ljava/lang/Object;Ljava/lang/String;)V
      10: aload_0
      11: aload_1
      12: putfield      #4                  // Field handler:Lorg/apache/dubbo/remoting/ChannelHandler;
      15: return

  public org.apache.dubbo.remoting.ChannelHandler getHandler();
    Code:
       0: aload_0
       1: getfield      #4                  // Field handler:Lorg/apache/dubbo/remoting/ChannelHandler;
       4: instanceof    #5                  // class org/apache/dubbo/remoting/transport/ChannelHandlerDelegate
       7: ifeq          23
      10: aload_0
      11: getfield      #4                  // Field handler:Lorg/apache/dubbo/remoting/ChannelHandler;
      14: checkcast     #5                  // class org/apache/dubbo/remoting/transport/ChannelHandlerDelegate
      17: invokeinterface #6,  1            // InterfaceMethod org/apache/dubbo/remoting/transport/ChannelHandlerDelegate.getHandler:()Lorg/apache/dubbo/remoting/ChannelHandler;
      22: areturn
      23: aload_0
      24: getfield      #4                  // Field handler:Lorg/apache/dubbo/remoting/ChannelHandler;
      27: areturn

  public void connected(org.apache.dubbo.remoting.Channel) throws org.apache.dubbo.remoting.RemotingException;
    Code:
       0: aload_0
       1: getfield      #4                  // Field handler:Lorg/apache/dubbo/remoting/ChannelHandler;
       4: aload_1
       5: invokeinterface #7,  2            // InterfaceMethod org/apache/dubbo/remoting/ChannelHandler.connected:(Lorg/apache/dubbo/remoting/Channel;)V
      10: return

  public void disconnected(org.apache.dubbo.remoting.Channel) throws org.apache.dubbo.remoting.RemotingException;
    Code:
       0: aload_0
       1: getfield      #4                  // Field handler:Lorg/apache/dubbo/remoting/ChannelHandler;
       4: aload_1
       5: invokeinterface #8,  2            // InterfaceMethod org/apache/dubbo/remoting/ChannelHandler.disconnected:(Lorg/apache/dubbo/remoting/Channel;)V
      10: return

  public void sent(org.apache.dubbo.remoting.Channel, java.lang.Object) throws org.apache.dubbo.remoting.RemotingException;
    Code:
       0: aload_0
       1: getfield      #4                  // Field handler:Lorg/apache/dubbo/remoting/ChannelHandler;
       4: aload_1
       5: aload_2
       6: invokeinterface #9,  3            // InterfaceMethod org/apache/dubbo/remoting/ChannelHandler.sent:(Lorg/apache/dubbo/remoting/Channel;Ljava/lang/Object;)V
      11: return

  public void received(org.apache.dubbo.remoting.Channel, java.lang.Object) throws org.apache.dubbo.remoting.RemotingException;
    Code:
       0: aload_0
       1: getfield      #4                  // Field handler:Lorg/apache/dubbo/remoting/ChannelHandler;
       4: aload_1
       5: aload_2
       6: invokeinterface #10,  3           // InterfaceMethod org/apache/dubbo/remoting/ChannelHandler.received:(Lorg/apache/dubbo/remoting/Channel;Ljava/lang/Object;)V
      11: return

  public void caught(org.apache.dubbo.remoting.Channel, java.lang.Throwable) throws org.apache.dubbo.remoting.RemotingException;
    Code:
       0: aload_0
       1: getfield      #4                  // Field handler:Lorg/apache/dubbo/remoting/ChannelHandler;
       4: aload_1
       5: aload_2
       6: invokeinterface #11,  3           // InterfaceMethod org/apache/dubbo/remoting/ChannelHandler.caught:(Lorg/apache/dubbo/remoting/Channel;Ljava/lang/Throwable;)V
      11: return
}
