Compiled from "AbstractClient.java"
public abstract class org.apache.dubbo.remoting.transport.AbstractClient extends org.apache.dubbo.remoting.transport.AbstractEndpoint implements org.apache.dubbo.remoting.Client {
  protected static final java.lang.String CLIENT_THREAD_POOL_NAME;

  private static final org.apache.dubbo.common.logger.ErrorTypeAwareLogger logger;

  private final java.util.concurrent.locks.Lock connectLock;

  private final boolean needReconnect;

  protected volatile java.util.concurrent.ExecutorService executor;

  public org.apache.dubbo.remoting.transport.AbstractClient(org.apache.dubbo.common.URL, org.apache.dubbo.remoting.ChannelHandler) throws org.apache.dubbo.remoting.RemotingException;
    Code:
       0: aload_0
       1: aload_1
       2: aload_2
       3: invokespecial #3                  // Method org/apache/dubbo/remoting/transport/AbstractEndpoint."<init>":(Lorg/apache/dubbo/common/URL;Lorg/apache/dubbo/remoting/ChannelHandler;)V
       6: aload_0
       7: new           #4                  // class java/util/concurrent/locks/ReentrantLock
      10: dup
      11: invokespecial #5                  // Method java/util/concurrent/locks/ReentrantLock."<init>":()V
      14: putfield      #6                  // Field connectLock:Ljava/util/concurrent/locks/Lock;
      17: aload_0
      18: aload_1
      19: ldc           #8                  // String send.reconnect
      21: iconst_1
      22: invokevirtual #9                  // Method org/apache/dubbo/common/URL.getParameter:(Ljava/lang/String;Z)Z
      25: putfield      #10                 // Field needReconnect:Z
      28: aload_0
      29: aload_1
      30: invokespecial #11                 // Method initExecutor:(Lorg/apache/dubbo/common/URL;)V
      33: aload_0
      34: invokevirtual #12                 // Method doOpen:()V
      37: goto          119
      40: astore_3
      41: aload_0
      42: invokevirtual #14                 // Method close:()V
      45: new           #15                 // class org/apache/dubbo/remoting/RemotingException
      48: dup
      49: aload_1
      50: invokevirtual #16                 // Method org/apache/dubbo/common/URL.toInetSocketAddress:()Ljava/net/InetSocketAddress;
      53: aconst_null
      54: new           #17                 // class java/lang/StringBuilder
      57: dup
      58: invokespecial #18                 // Method java/lang/StringBuilder."<init>":()V
      61: ldc           #19                 // String Failed to start
      63: invokevirtual #20                 // Method java/lang/StringBuilder.append:(Ljava/lang/String;)Ljava/lang/StringBuilder;
      66: aload_0
      67: invokevirtual #21                 // Method java/lang/Object.getClass:()Ljava/lang/Class;
      70: invokevirtual #22                 // Method java/lang/Class.getSimpleName:()Ljava/lang/String;
      73: invokevirtual #20                 // Method java/lang/StringBuilder.append:(Ljava/lang/String;)Ljava/lang/StringBuilder;
      76: ldc           #23                 // String
      78: invokevirtual #20                 // Method java/lang/StringBuilder.append:(Ljava/lang/String;)Ljava/lang/StringBuilder;
      81: invokestatic  #24                 // Method org/apache/dubbo/common/utils/NetUtils.getLocalAddress:()Ljava/net/InetAddress;
      84: invokevirtual #25                 // Method java/lang/StringBuilder.append:(Ljava/lang/Object;)Ljava/lang/StringBuilder;
      87: ldc           #26                 // String  connect to the server
      89: invokevirtual #20                 // Method java/lang/StringBuilder.append:(Ljava/lang/String;)Ljava/lang/StringBuilder;
      92: aload_0
      93: invokevirtual #27                 // Method getRemoteAddress:()Ljava/net/InetSocketAddress;
      96: invokevirtual #25                 // Method java/lang/StringBuilder.append:(Ljava/lang/Object;)Ljava/lang/StringBuilder;
      99: ldc           #28                 // String , cause:
     101: invokevirtual #20                 // Method java/lang/StringBuilder.append:(Ljava/lang/String;)Ljava/lang/StringBuilder;
     104: aload_3
     105: invokevirtual #29                 // Method java/lang/Throwable.getMessage:()Ljava/lang/String;
     108: invokevirtual #20                 // Method java/lang/StringBuilder.append:(Ljava/lang/String;)Ljava/lang/StringBuilder;
     111: invokevirtual #30                 // Method java/lang/StringBuilder.toString:()Ljava/lang/String;
     114: aload_3
     115: invokespecial #31                 // Method org/apache/dubbo/remoting/RemotingException."<init>":(Ljava/net/InetSocketAddress;Ljava/net/InetSocketAddress;Ljava/lang/String;Ljava/lang/Throwable;)V
     118: athrow
     119: aload_0
     120: invokevirtual #32                 // Method connect:()V
     123: getstatic     #33                 // Field logger:Lorg/apache/dubbo/common/logger/ErrorTypeAwareLogger;
     126: invokeinterface #34,  1           // InterfaceMethod org/apache/dubbo/common/logger/ErrorTypeAwareLogger.isInfoEnabled:()Z
     131: ifeq          190
     134: getstatic     #33                 // Field logger:Lorg/apache/dubbo/common/logger/ErrorTypeAwareLogger;
     137: new           #17                 // class java/lang/StringBuilder
     140: dup
     141: invokespecial #18                 // Method java/lang/StringBuilder."<init>":()V
     144: ldc           #35                 // String Start
     146: invokevirtual #20                 // Method java/lang/StringBuilder.append:(Ljava/lang/String;)Ljava/lang/StringBuilder;
     149: aload_0
     150: invokevirtual #21                 // Method java/lang/Object.getClass:()Ljava/lang/Class;
     153: invokevirtual #22                 // Method java/lang/Class.getSimpleName:()Ljava/lang/String;
     156: invokevirtual #20                 // Method java/lang/StringBuilder.append:(Ljava/lang/String;)Ljava/lang/StringBuilder;
     159: ldc           #23                 // String
     161: invokevirtual #20                 // Method java/lang/StringBuilder.append:(Ljava/lang/String;)Ljava/lang/StringBuilder;
     164: invokestatic  #24                 // Method org/apache/dubbo/common/utils/NetUtils.getLocalAddress:()Ljava/net/InetAddress;
     167: invokevirtual #25                 // Method java/lang/StringBuilder.append:(Ljava/lang/Object;)Ljava/lang/StringBuilder;
     170: ldc           #26                 // String  connect to the server
     172: invokevirtual #20                 // Method java/lang/StringBuilder.append:(Ljava/lang/String;)Ljava/lang/StringBuilder;
     175: aload_0
     176: invokevirtual #27                 // Method getRemoteAddress:()Ljava/net/InetSocketAddress;
     179: invokevirtual #25                 // Method java/lang/StringBuilder.append:(Ljava/lang/Object;)Ljava/lang/StringBuilder;
     182: invokevirtual #30                 // Method java/lang/StringBuilder.toString:()Ljava/lang/String;
     185: invokeinterface #36,  2           // InterfaceMethod org/apache/dubbo/common/logger/ErrorTypeAwareLogger.info:(Ljava/lang/String;)V
     190: goto          453
     193: astore_3
     194: aload_1
     195: ldc           #37                 // String lazy
     197: iconst_0
     198: invokevirtual #9                  // Method org/apache/dubbo/common/URL.getParameter:(Ljava/lang/String;Z)Z
     201: ifeq          280
     204: getstatic     #33                 // Field logger:Lorg/apache/dubbo/common/logger/ErrorTypeAwareLogger;
     207: ldc           #38                 // String 6-1
     209: ldc           #39                 // String
     211: ldc           #39                 // String
     213: new           #17                 // class java/lang/StringBuilder
     216: dup
     217: invokespecial #18                 // Method java/lang/StringBuilder."<init>":()V
     220: ldc           #19                 // String Failed to start
     222: invokevirtual #20                 // Method java/lang/StringBuilder.append:(Ljava/lang/String;)Ljava/lang/StringBuilder;
     225: aload_0
     226: invokevirtual #21                 // Method java/lang/Object.getClass:()Ljava/lang/Class;
     229: invokevirtual #22                 // Method java/lang/Class.getSimpleName:()Ljava/lang/String;
     232: invokevirtual #20                 // Method java/lang/StringBuilder.append:(Ljava/lang/String;)Ljava/lang/StringBuilder;
     235: ldc           #23                 // String
     237: invokevirtual #20                 // Method java/lang/StringBuilder.append:(Ljava/lang/String;)Ljava/lang/StringBuilder;
     240: invokestatic  #24                 // Method org/apache/dubbo/common/utils/NetUtils.getLocalAddress:()Ljava/net/InetAddress;
     243: invokevirtual #25                 // Method java/lang/StringBuilder.append:(Ljava/lang/Object;)Ljava/lang/StringBuilder;
     246: ldc           #26                 // String  connect to the server
     248: invokevirtual #20                 // Method java/lang/StringBuilder.append:(Ljava/lang/String;)Ljava/lang/StringBuilder;
     251: aload_0
     252: invokevirtual #27                 // Method getRemoteAddress:()Ljava/net/InetSocketAddress;
     255: invokevirtual #25                 // Method java/lang/StringBuilder.append:(Ljava/lang/Object;)Ljava/lang/StringBuilder;
     258: ldc           #40                 // String  (the connection request is initiated by lazy connect client, ignore and retry later!), cause:
     260: invokevirtual #20                 // Method java/lang/StringBuilder.append:(Ljava/lang/String;)Ljava/lang/StringBuilder;
     263: aload_3
     264: invokevirtual #41                 // Method org/apache/dubbo/remoting/RemotingException.getMessage:()Ljava/lang/String;
     267: invokevirtual #20                 // Method java/lang/StringBuilder.append:(Ljava/lang/String;)Ljava/lang/StringBuilder;
     270: invokevirtual #30                 // Method java/lang/StringBuilder.toString:()Ljava/lang/String;
     273: aload_3
     274: invokeinterface #42,  6           // InterfaceMethod org/apache/dubbo/common/logger/ErrorTypeAwareLogger.warn:(Ljava/lang/String;Ljava/lang/String;Ljava/lang/String;Ljava/lang/String;Ljava/lang/Throwable;)V
     279: return
     280: aload_1
     281: ldc           #43                 // String check
     283: iconst_1
     284: invokevirtual #9                  // Method org/apache/dubbo/common/URL.getParameter:(Ljava/lang/String;Z)Z
     287: ifeq          296
     290: aload_0
     291: invokevirtual #14                 // Method close:()V
     294: aload_3
     295: athrow
     296: getstatic     #33                 // Field logger:Lorg/apache/dubbo/common/logger/ErrorTypeAwareLogger;
     299: ldc           #38                 // String 6-1
     301: ldc           #39                 // String
     303: ldc           #39                 // String
     305: new           #17                 // class java/lang/StringBuilder
     308: dup
     309: invokespecial #18                 // Method java/lang/StringBuilder."<init>":()V
     312: ldc           #19                 // String Failed to start
     314: invokevirtual #20                 // Method java/lang/StringBuilder.append:(Ljava/lang/String;)Ljava/lang/StringBuilder;
     317: aload_0
     318: invokevirtual #21                 // Method java/lang/Object.getClass:()Ljava/lang/Class;
     321: invokevirtual #22                 // Method java/lang/Class.getSimpleName:()Ljava/lang/String;
     324: invokevirtual #20                 // Method java/lang/StringBuilder.append:(Ljava/lang/String;)Ljava/lang/StringBuilder;
     327: ldc           #23                 // String
     329: invokevirtual #20                 // Method java/lang/StringBuilder.append:(Ljava/lang/String;)Ljava/lang/StringBuilder;
     332: invokestatic  #24                 // Method org/apache/dubbo/common/utils/NetUtils.getLocalAddress:()Ljava/net/InetAddress;
     335: invokevirtual #25                 // Method java/lang/StringBuilder.append:(Ljava/lang/Object;)Ljava/lang/StringBuilder;
     338: ldc           #26                 // String  connect to the server
     340: invokevirtual #20                 // Method java/lang/StringBuilder.append:(Ljava/lang/String;)Ljava/lang/StringBuilder;
     343: aload_0
     344: invokevirtual #27                 // Method getRemoteAddress:()Ljava/net/InetSocketAddress;
     347: invokevirtual #25                 // Method java/lang/StringBuilder.append:(Ljava/lang/Object;)Ljava/lang/StringBuilder;
     350: ldc           #44                 // String  (check == false, ignore and retry later!), cause:
     352: invokevirtual #20                 // Method java/lang/StringBuilder.append:(Ljava/lang/String;)Ljava/lang/StringBuilder;
     355: aload_3
     356: invokevirtual #41                 // Method org/apache/dubbo/remoting/RemotingException.getMessage:()Ljava/lang/String;
     359: invokevirtual #20                 // Method java/lang/StringBuilder.append:(Ljava/lang/String;)Ljava/lang/StringBuilder;
     362: invokevirtual #30                 // Method java/lang/StringBuilder.toString:()Ljava/lang/String;
     365: aload_3
     366: invokeinterface #42,  6           // InterfaceMethod org/apache/dubbo/common/logger/ErrorTypeAwareLogger.warn:(Ljava/lang/String;Ljava/lang/String;Ljava/lang/String;Ljava/lang/String;Ljava/lang/Throwable;)V
     371: goto          453
     374: astore_3
     375: aload_0
     376: invokevirtual #14                 // Method close:()V
     379: new           #15                 // class org/apache/dubbo/remoting/RemotingException
     382: dup
     383: aload_1
     384: invokevirtual #16                 // Method org/apache/dubbo/common/URL.toInetSocketAddress:()Ljava/net/InetSocketAddress;
     387: aconst_null
     388: new           #17                 // class java/lang/StringBuilder
     391: dup
     392: invokespecial #18                 // Method java/lang/StringBuilder."<init>":()V
     395: ldc           #19                 // String Failed to start
     397: invokevirtual #20                 // Method java/lang/StringBuilder.append:(Ljava/lang/String;)Ljava/lang/StringBuilder;
     400: aload_0
     401: invokevirtual #21                 // Method java/lang/Object.getClass:()Ljava/lang/Class;
     404: invokevirtual #22                 // Method java/lang/Class.getSimpleName:()Ljava/lang/String;
     407: invokevirtual #20                 // Method java/lang/StringBuilder.append:(Ljava/lang/String;)Ljava/lang/StringBuilder;
     410: ldc           #23                 // String
     412: invokevirtual #20                 // Method java/lang/StringBuilder.append:(Ljava/lang/String;)Ljava/lang/StringBuilder;
     415: invokestatic  #24                 // Method org/apache/dubbo/common/utils/NetUtils.getLocalAddress:()Ljava/net/InetAddress;
     418: invokevirtual #25                 // Method java/lang/StringBuilder.append:(Ljava/lang/Object;)Ljava/lang/StringBuilder;
     421: ldc           #26                 // String  connect to the server
     423: invokevirtual #20                 // Method java/lang/StringBuilder.append:(Ljava/lang/String;)Ljava/lang/StringBuilder;
     426: aload_0
     427: invokevirtual #27                 // Method getRemoteAddress:()Ljava/net/InetSocketAddress;
     430: invokevirtual #25                 // Method java/lang/StringBuilder.append:(Ljava/lang/Object;)Ljava/lang/StringBuilder;
     433: ldc           #28                 // String , cause:
     435: invokevirtual #20                 // Method java/lang/StringBuilder.append:(Ljava/lang/String;)Ljava/lang/StringBuilder;
     438: aload_3
     439: invokevirtual #29                 // Method java/lang/Throwable.getMessage:()Ljava/lang/String;
     442: invokevirtual #20                 // Method java/lang/StringBuilder.append:(Ljava/lang/String;)Ljava/lang/StringBuilder;
     445: invokevirtual #30                 // Method java/lang/StringBuilder.toString:()Ljava/lang/String;
     448: aload_3
     449: invokespecial #31                 // Method org/apache/dubbo/remoting/RemotingException."<init>":(Ljava/net/InetSocketAddress;Ljava/net/InetSocketAddress;Ljava/lang/String;Ljava/lang/Throwable;)V
     452: athrow
     453: return
    Exception table:
       from    to  target type
          33    37    40   Class java/lang/Throwable
         119   190   193   Class org/apache/dubbo/remoting/RemotingException
         119   190   374   Class java/lang/Throwable

  private void initExecutor(org.apache.dubbo.common.URL);
    Code:
       0: aload_1
       1: invokevirtual #45                 // Method org/apache/dubbo/common/URL.getOrDefaultApplicationModel:()Lorg/apache/dubbo/rpc/model/ApplicationModel;
       4: invokestatic  #46                 // InterfaceMethod org/apache/dubbo/common/threadpool/manager/ExecutorRepository.getInstance:(Lorg/apache/dubbo/rpc/model/ApplicationModel;)Lorg/apache/dubbo/common/threadpool/manager/ExecutorRepository;
       7: astore_2
       8: aload_1
       9: ldc           #47                 // String threadname
      11: ldc           #49                 // String DubboClientHandler
      13: invokevirtual #50                 // Method org/apache/dubbo/common/URL.addParameter:(Ljava/lang/String;Ljava/lang/String;)Lorg/apache/dubbo/common/URL;
      16: ldc           #51                 // String threadpool
      18: ldc           #52                 // String cached
      20: invokevirtual #53                 // Method org/apache/dubbo/common/URL.addParameterIfAbsent:(Ljava/lang/String;Ljava/lang/String;)Lorg/apache/dubbo/common/URL;
      23: astore_1
      24: aload_0
      25: aload_2
      26: aload_1
      27: invokeinterface #54,  2           // InterfaceMethod org/apache/dubbo/common/threadpool/manager/ExecutorRepository.createExecutorIfAbsent:(Lorg/apache/dubbo/common/URL;)Ljava/util/concurrent/ExecutorService;
      32: putfield      #55                 // Field executor:Ljava/util/concurrent/ExecutorService;
      35: return

  protected static org.apache.dubbo.remoting.ChannelHandler wrapChannelHandler(org.apache.dubbo.common.URL, org.apache.dubbo.remoting.ChannelHandler);
    Code:
       0: aload_1
       1: aload_0
       2: invokestatic  #56                 // Method org/apache/dubbo/remoting/transport/dispatcher/ChannelHandlers.wrap:(Lorg/apache/dubbo/remoting/ChannelHandler;Lorg/apache/dubbo/common/URL;)Lorg/apache/dubbo/remoting/ChannelHandler;
       5: areturn

  public java.net.InetSocketAddress getConnectAddress();
    Code:
       0: new           #57                 // class java/net/InetSocketAddress
       3: dup
       4: aload_0
       5: invokevirtual #58                 // Method getUrl:()Lorg/apache/dubbo/common/URL;
       8: invokevirtual #59                 // Method org/apache/dubbo/common/URL.getHost:()Ljava/lang/String;
      11: invokestatic  #60                 // Method org/apache/dubbo/common/utils/NetUtils.filterLocalHost:(Ljava/lang/String;)Ljava/lang/String;
      14: aload_0
      15: invokevirtual #58                 // Method getUrl:()Lorg/apache/dubbo/common/URL;
      18: invokevirtual #61                 // Method org/apache/dubbo/common/URL.getPort:()I
      21: invokespecial #62                 // Method java/net/InetSocketAddress."<init>":(Ljava/lang/String;I)V
      24: areturn

  public java.net.InetSocketAddress getRemoteAddress();
    Code:
       0: aload_0
       1: invokevirtual #63                 // Method getChannel:()Lorg/apache/dubbo/remoting/Channel;
       4: astore_1
       5: aload_1
       6: ifnonnull     17
       9: aload_0
      10: invokevirtual #58                 // Method getUrl:()Lorg/apache/dubbo/common/URL;
      13: invokevirtual #16                 // Method org/apache/dubbo/common/URL.toInetSocketAddress:()Ljava/net/InetSocketAddress;
      16: areturn
      17: aload_1
      18: invokeinterface #64,  1           // InterfaceMethod org/apache/dubbo/remoting/Channel.getRemoteAddress:()Ljava/net/InetSocketAddress;
      23: areturn

  public java.net.InetSocketAddress getLocalAddress();
    Code:
       0: aload_0
       1: invokevirtual #63                 // Method getChannel:()Lorg/apache/dubbo/remoting/Channel;
       4: astore_1
       5: aload_1
       6: ifnonnull     17
       9: invokestatic  #65                 // Method org/apache/dubbo/common/utils/NetUtils.getLocalHost:()Ljava/lang/String;
      12: iconst_0
      13: invokestatic  #66                 // Method java/net/InetSocketAddress.createUnresolved:(Ljava/lang/String;I)Ljava/net/InetSocketAddress;
      16: areturn
      17: aload_1
      18: invokeinterface #67,  1           // InterfaceMethod org/apache/dubbo/remoting/Channel.getLocalAddress:()Ljava/net/InetSocketAddress;
      23: areturn

  public boolean isConnected();
    Code:
       0: aload_0
       1: invokevirtual #63                 // Method getChannel:()Lorg/apache/dubbo/remoting/Channel;
       4: astore_1
       5: aload_1
       6: ifnonnull     11
       9: iconst_0
      10: ireturn
      11: aload_1
      12: invokeinterface #68,  1           // InterfaceMethod org/apache/dubbo/remoting/Channel.isConnected:()Z
      17: ireturn

  public java.lang.Object getAttribute(java.lang.String);
    Code:
       0: aload_0
       1: invokevirtual #63                 // Method getChannel:()Lorg/apache/dubbo/remoting/Channel;
       4: astore_2
       5: aload_2
       6: ifnonnull     11
       9: aconst_null
      10: areturn
      11: aload_2
      12: aload_1
      13: invokeinterface #69,  2           // InterfaceMethod org/apache/dubbo/remoting/Channel.getAttribute:(Ljava/lang/String;)Ljava/lang/Object;
      18: areturn

  public void setAttribute(java.lang.String, java.lang.Object);
    Code:
       0: aload_0
       1: invokevirtual #63                 // Method getChannel:()Lorg/apache/dubbo/remoting/Channel;
       4: astore_3
       5: aload_3
       6: ifnonnull     10
       9: return
      10: aload_3
      11: aload_1
      12: aload_2
      13: invokeinterface #70,  3           // InterfaceMethod org/apache/dubbo/remoting/Channel.setAttribute:(Ljava/lang/String;Ljava/lang/Object;)V
      18: return

  public void removeAttribute(java.lang.String);
    Code:
       0: aload_0
       1: invokevirtual #63                 // Method getChannel:()Lorg/apache/dubbo/remoting/Channel;
       4: astore_2
       5: aload_2
       6: ifnonnull     10
       9: return
      10: aload_2
      11: aload_1
      12: invokeinterface #71,  2           // InterfaceMethod org/apache/dubbo/remoting/Channel.removeAttribute:(Ljava/lang/String;)V
      17: return

  public boolean hasAttribute(java.lang.String);
    Code:
       0: aload_0
       1: invokevirtual #63                 // Method getChannel:()Lorg/apache/dubbo/remoting/Channel;
       4: astore_2
       5: aload_2
       6: ifnonnull     11
       9: iconst_0
      10: ireturn
      11: aload_2
      12: aload_1
      13: invokeinterface #72,  2           // InterfaceMethod org/apache/dubbo/remoting/Channel.hasAttribute:(Ljava/lang/String;)Z
      18: ireturn

  public void send(java.lang.Object, boolean) throws org.apache.dubbo.remoting.RemotingException;
    Code:
       0: aload_0
       1: getfield      #10                 // Field needReconnect:Z
       4: ifeq          18
       7: aload_0
       8: invokevirtual #73                 // Method isConnected:()Z
      11: ifne          18
      14: aload_0
      15: invokevirtual #32                 // Method connect:()V
      18: aload_0
      19: invokevirtual #63                 // Method getChannel:()Lorg/apache/dubbo/remoting/Channel;
      22: astore_3
      23: aload_3
      24: ifnull        36
      27: aload_3
      28: invokeinterface #68,  1           // InterfaceMethod org/apache/dubbo/remoting/Channel.isConnected:()Z
      33: ifne          67
      36: new           #15                 // class org/apache/dubbo/remoting/RemotingException
      39: dup
      40: aload_0
      41: new           #17                 // class java/lang/StringBuilder
      44: dup
      45: invokespecial #18                 // Method java/lang/StringBuilder."<init>":()V
      48: ldc           #74                 // String message can not send, because channel is closed . url:
      50: invokevirtual #20                 // Method java/lang/StringBuilder.append:(Ljava/lang/String;)Ljava/lang/StringBuilder;
      53: aload_0
      54: invokevirtual #58                 // Method getUrl:()Lorg/apache/dubbo/common/URL;
      57: invokevirtual #25                 // Method java/lang/StringBuilder.append:(Ljava/lang/Object;)Ljava/lang/StringBuilder;
      60: invokevirtual #30                 // Method java/lang/StringBuilder.toString:()Ljava/lang/String;
      63: invokespecial #75                 // Method org/apache/dubbo/remoting/RemotingException."<init>":(Lorg/apache/dubbo/remoting/Channel;Ljava/lang/String;)V
      66: athrow
      67: aload_3
      68: aload_1
      69: iload_2
      70: invokeinterface #76,  3           // InterfaceMethod org/apache/dubbo/remoting/Channel.send:(Ljava/lang/Object;Z)V
      75: return

  protected void connect() throws org.apache.dubbo.remoting.RemotingException;
    Code:
       0: aload_0
       1: getfield      #6                  // Field connectLock:Ljava/util/concurrent/locks/Lock;
       4: invokeinterface #77,  1           // InterfaceMethod java/util/concurrent/locks/Lock.lock:()V
       9: aload_0
      10: invokevirtual #73                 // Method isConnected:()Z
      13: ifeq          26
      16: aload_0
      17: getfield      #6                  // Field connectLock:Ljava/util/concurrent/locks/Lock;
      20: invokeinterface #78,  1           // InterfaceMethod java/util/concurrent/locks/Lock.unlock:()V
      25: return
      26: aload_0
      27: invokevirtual #79                 // Method isClosed:()Z
      30: ifne          40
      33: aload_0
      34: invokevirtual #80                 // Method isClosing:()Z
      37: ifeq          128
      40: getstatic     #33                 // Field logger:Lorg/apache/dubbo/common/logger/ErrorTypeAwareLogger;
      43: ldc           #38                 // String 6-1
      45: ldc           #39                 // String
      47: ldc           #39                 // String
      49: new           #17                 // class java/lang/StringBuilder
      52: dup
      53: invokespecial #18                 // Method java/lang/StringBuilder."<init>":()V
      56: ldc           #81                 // String No need to connect to server
      58: invokevirtual #20                 // Method java/lang/StringBuilder.append:(Ljava/lang/String;)Ljava/lang/StringBuilder;
      61: aload_0
      62: invokevirtual #27                 // Method getRemoteAddress:()Ljava/net/InetSocketAddress;
      65: invokevirtual #25                 // Method java/lang/StringBuilder.append:(Ljava/lang/Object;)Ljava/lang/StringBuilder;
      68: ldc           #82                 // String  from
      70: invokevirtual #20                 // Method java/lang/StringBuilder.append:(Ljava/lang/String;)Ljava/lang/StringBuilder;
      73: aload_0
      74: invokevirtual #21                 // Method java/lang/Object.getClass:()Ljava/lang/Class;
      77: invokevirtual #22                 // Method java/lang/Class.getSimpleName:()Ljava/lang/String;
      80: invokevirtual #20                 // Method java/lang/StringBuilder.append:(Ljava/lang/String;)Ljava/lang/StringBuilder;
      83: ldc           #23                 // String
      85: invokevirtual #20                 // Method java/lang/StringBuilder.append:(Ljava/lang/String;)Ljava/lang/StringBuilder;
      88: invokestatic  #65                 // Method org/apache/dubbo/common/utils/NetUtils.getLocalHost:()Ljava/lang/String;
      91: invokevirtual #20                 // Method java/lang/StringBuilder.append:(Ljava/lang/String;)Ljava/lang/StringBuilder;
      94: ldc           #83                 // String  using dubbo version
      96: invokevirtual #20                 // Method java/lang/StringBuilder.append:(Ljava/lang/String;)Ljava/lang/StringBuilder;
      99: invokestatic  #84                 // Method org/apache/dubbo/common/Version.getVersion:()Ljava/lang/String;
     102: invokevirtual #20                 // Method java/lang/StringBuilder.append:(Ljava/lang/String;)Ljava/lang/StringBuilder;
     105: ldc           #85                 // String , cause: client status is closed or closing.
     107: invokevirtual #20                 // Method java/lang/StringBuilder.append:(Ljava/lang/String;)Ljava/lang/StringBuilder;
     110: invokevirtual #30                 // Method java/lang/StringBuilder.toString:()Ljava/lang/String;
     113: invokeinterface #86,  5           // InterfaceMethod org/apache/dubbo/common/logger/ErrorTypeAwareLogger.warn:(Ljava/lang/String;Ljava/lang/String;Ljava/lang/String;Ljava/lang/String;)V
     118: aload_0
     119: getfield      #6                  // Field connectLock:Ljava/util/concurrent/locks/Lock;
     122: invokeinterface #78,  1           // InterfaceMethod java/util/concurrent/locks/Lock.unlock:()V
     127: return
     128: aload_0
     129: invokevirtual #87                 // Method doConnect:()V
     132: aload_0
     133: invokevirtual #73                 // Method isConnected:()Z
     136: ifne          224
     139: new           #15                 // class org/apache/dubbo/remoting/RemotingException
     142: dup
     143: aload_0
     144: new           #17                 // class java/lang/StringBuilder
     147: dup
     148: invokespecial #18                 // Method java/lang/StringBuilder."<init>":()V
     151: ldc           #88                 // String Failed to connect to server
     153: invokevirtual #20                 // Method java/lang/StringBuilder.append:(Ljava/lang/String;)Ljava/lang/StringBuilder;
     156: aload_0
     157: invokevirtual #27                 // Method getRemoteAddress:()Ljava/net/InetSocketAddress;
     160: invokevirtual #25                 // Method java/lang/StringBuilder.append:(Ljava/lang/Object;)Ljava/lang/StringBuilder;
     163: ldc           #82                 // String  from
     165: invokevirtual #20                 // Method java/lang/StringBuilder.append:(Ljava/lang/String;)Ljava/lang/StringBuilder;
     168: aload_0
     169: invokevirtual #21                 // Method java/lang/Object.getClass:()Ljava/lang/Class;
     172: invokevirtual #22                 // Method java/lang/Class.getSimpleName:()Ljava/lang/String;
     175: invokevirtual #20                 // Method java/lang/StringBuilder.append:(Ljava/lang/String;)Ljava/lang/StringBuilder;
     178: ldc           #23                 // String
     180: invokevirtual #20                 // Method java/lang/StringBuilder.append:(Ljava/lang/String;)Ljava/lang/StringBuilder;
     183: invokestatic  #65                 // Method org/apache/dubbo/common/utils/NetUtils.getLocalHost:()Ljava/lang/String;
     186: invokevirtual #20                 // Method java/lang/StringBuilder.append:(Ljava/lang/String;)Ljava/lang/StringBuilder;
     189: ldc           #83                 // String  using dubbo version
     191: invokevirtual #20                 // Method java/lang/StringBuilder.append:(Ljava/lang/String;)Ljava/lang/StringBuilder;
     194: invokestatic  #84                 // Method org/apache/dubbo/common/Version.getVersion:()Ljava/lang/String;
     197: invokevirtual #20                 // Method java/lang/StringBuilder.append:(Ljava/lang/String;)Ljava/lang/StringBuilder;
     200: ldc           #89                 // String , cause: Connect wait timeout:
     202: invokevirtual #20                 // Method java/lang/StringBuilder.append:(Ljava/lang/String;)Ljava/lang/StringBuilder;
     205: aload_0
     206: invokevirtual #90                 // Method getConnectTimeout:()I
     209: invokevirtual #91                 // Method java/lang/StringBuilder.append:(I)Ljava/lang/StringBuilder;
     212: ldc           #92                 // String ms.
     214: invokevirtual #20                 // Method java/lang/StringBuilder.append:(Ljava/lang/String;)Ljava/lang/StringBuilder;
     217: invokevirtual #30                 // Method java/lang/StringBuilder.toString:()Ljava/lang/String;
     220: invokespecial #75                 // Method org/apache/dubbo/remoting/RemotingException."<init>":(Lorg/apache/dubbo/remoting/Channel;Ljava/lang/String;)V
     223: athrow
     224: getstatic     #33                 // Field logger:Lorg/apache/dubbo/common/logger/ErrorTypeAwareLogger;
     227: invokeinterface #34,  1           // InterfaceMethod org/apache/dubbo/common/logger/ErrorTypeAwareLogger.isInfoEnabled:()Z
     232: ifeq          314
     235: getstatic     #33                 // Field logger:Lorg/apache/dubbo/common/logger/ErrorTypeAwareLogger;
     238: new           #17                 // class java/lang/StringBuilder
     241: dup
     242: invokespecial #18                 // Method java/lang/StringBuilder."<init>":()V
     245: ldc           #93                 // String Successfully connect to server
     247: invokevirtual #20                 // Method java/lang/StringBuilder.append:(Ljava/lang/String;)Ljava/lang/StringBuilder;
     250: aload_0
     251: invokevirtual #27                 // Method getRemoteAddress:()Ljava/net/InetSocketAddress;
     254: invokevirtual #25                 // Method java/lang/StringBuilder.append:(Ljava/lang/Object;)Ljava/lang/StringBuilder;
     257: ldc           #82                 // String  from
     259: invokevirtual #20                 // Method java/lang/StringBuilder.append:(Ljava/lang/String;)Ljava/lang/StringBuilder;
     262: aload_0
     263: invokevirtual #21                 // Method java/lang/Object.getClass:()Ljava/lang/Class;
     266: invokevirtual #22                 // Method java/lang/Class.getSimpleName:()Ljava/lang/String;
     269: invokevirtual #20                 // Method java/lang/StringBuilder.append:(Ljava/lang/String;)Ljava/lang/StringBuilder;
     272: ldc           #23                 // String
     274: invokevirtual #20                 // Method java/lang/StringBuilder.append:(Ljava/lang/String;)Ljava/lang/StringBuilder;
     277: invokestatic  #65                 // Method org/apache/dubbo/common/utils/NetUtils.getLocalHost:()Ljava/lang/String;
     280: invokevirtual #20                 // Method java/lang/StringBuilder.append:(Ljava/lang/String;)Ljava/lang/StringBuilder;
     283: ldc           #83                 // String  using dubbo version
     285: invokevirtual #20                 // Method java/lang/StringBuilder.append:(Ljava/lang/String;)Ljava/lang/StringBuilder;
     288: invokestatic  #84                 // Method org/apache/dubbo/common/Version.getVersion:()Ljava/lang/String;
     291: invokevirtual #20                 // Method java/lang/StringBuilder.append:(Ljava/lang/String;)Ljava/lang/StringBuilder;
     294: ldc           #94                 // String , channel is
     296: invokevirtual #20                 // Method java/lang/StringBuilder.append:(Ljava/lang/String;)Ljava/lang/StringBuilder;
     299: aload_0
     300: invokevirtual #63                 // Method getChannel:()Lorg/apache/dubbo/remoting/Channel;
     303: invokevirtual #25                 // Method java/lang/StringBuilder.append:(Ljava/lang/Object;)Ljava/lang/StringBuilder;
     306: invokevirtual #30                 // Method java/lang/StringBuilder.toString:()Ljava/lang/String;
     309: invokeinterface #36,  2           // InterfaceMethod org/apache/dubbo/common/logger/ErrorTypeAwareLogger.info:(Ljava/lang/String;)V
     314: aload_0
     315: getfield      #6                  // Field connectLock:Ljava/util/concurrent/locks/Lock;
     318: invokeinterface #78,  1           // InterfaceMethod java/util/concurrent/locks/Lock.unlock:()V
     323: goto          423
     326: astore_1
     327: aload_1
     328: athrow
     329: astore_1
     330: new           #15                 // class org/apache/dubbo/remoting/RemotingException
     333: dup
     334: aload_0
     335: new           #17                 // class java/lang/StringBuilder
     338: dup
     339: invokespecial #18                 // Method java/lang/StringBuilder."<init>":()V
     342: ldc           #88                 // String Failed to connect to server
     344: invokevirtual #20                 // Method java/lang/StringBuilder.append:(Ljava/lang/String;)Ljava/lang/StringBuilder;
     347: aload_0
     348: invokevirtual #27                 // Method getRemoteAddress:()Ljava/net/InetSocketAddress;
     351: invokevirtual #25                 // Method java/lang/StringBuilder.append:(Ljava/lang/Object;)Ljava/lang/StringBuilder;
     354: ldc           #82                 // String  from
     356: invokevirtual #20                 // Method java/lang/StringBuilder.append:(Ljava/lang/String;)Ljava/lang/StringBuilder;
     359: aload_0
     360: invokevirtual #21                 // Method java/lang/Object.getClass:()Ljava/lang/Class;
     363: invokevirtual #22                 // Method java/lang/Class.getSimpleName:()Ljava/lang/String;
     366: invokevirtual #20                 // Method java/lang/StringBuilder.append:(Ljava/lang/String;)Ljava/lang/StringBuilder;
     369: ldc           #23                 // String
     371: invokevirtual #20                 // Method java/lang/StringBuilder.append:(Ljava/lang/String;)Ljava/lang/StringBuilder;
     374: invokestatic  #65                 // Method org/apache/dubbo/common/utils/NetUtils.getLocalHost:()Ljava/lang/String;
     377: invokevirtual #20                 // Method java/lang/StringBuilder.append:(Ljava/lang/String;)Ljava/lang/StringBuilder;
     380: ldc           #83                 // String  using dubbo version
     382: invokevirtual #20                 // Method java/lang/StringBuilder.append:(Ljava/lang/String;)Ljava/lang/StringBuilder;
     385: invokestatic  #84                 // Method org/apache/dubbo/common/Version.getVersion:()Ljava/lang/String;
     388: invokevirtual #20                 // Method java/lang/StringBuilder.append:(Ljava/lang/String;)Ljava/lang/StringBuilder;
     391: ldc           #28                 // String , cause:
     393: invokevirtual #20                 // Method java/lang/StringBuilder.append:(Ljava/lang/String;)Ljava/lang/StringBuilder;
     396: aload_1
     397: invokevirtual #29                 // Method java/lang/Throwable.getMessage:()Ljava/lang/String;
     400: invokevirtual #20                 // Method java/lang/StringBuilder.append:(Ljava/lang/String;)Ljava/lang/StringBuilder;
     403: invokevirtual #30                 // Method java/lang/StringBuilder.toString:()Ljava/lang/String;
     406: aload_1
     407: invokespecial #95                 // Method org/apache/dubbo/remoting/RemotingException."<init>":(Lorg/apache/dubbo/remoting/Channel;Ljava/lang/String;Ljava/lang/Throwable;)V
     410: athrow
     411: astore_2
     412: aload_0
     413: getfield      #6                  // Field connectLock:Ljava/util/concurrent/locks/Lock;
     416: invokeinterface #78,  1           // InterfaceMethod java/util/concurrent/locks/Lock.unlock:()V
     421: aload_2
     422: athrow
     423: return
    Exception table:
       from    to  target type
           9    16   326   Class org/apache/dubbo/remoting/RemotingException
          26   118   326   Class org/apache/dubbo/remoting/RemotingException
         128   314   326   Class org/apache/dubbo/remoting/RemotingException
           9    16   329   Class java/lang/Throwable
          26   118   329   Class java/lang/Throwable
         128   314   329   Class java/lang/Throwable
           9    16   411   any
          26   118   411   any
         128   314   411   any
         326   412   411   any

  public void disconnect();
    Code:
       0: aload_0
       1: getfield      #6                  // Field connectLock:Ljava/util/concurrent/locks/Lock;
       4: invokeinterface #77,  1           // InterfaceMethod java/util/concurrent/locks/Lock.lock:()V
       9: aload_0
      10: invokevirtual #63                 // Method getChannel:()Lorg/apache/dubbo/remoting/Channel;
      13: astore_1
      14: aload_1
      15: ifnull        24
      18: aload_1
      19: invokeinterface #96,  1           // InterfaceMethod org/apache/dubbo/remoting/Channel.close:()V
      24: goto          47
      27: astore_1
      28: getstatic     #33                 // Field logger:Lorg/apache/dubbo/common/logger/ErrorTypeAwareLogger;
      31: ldc           #97                 // String 6-3
      33: ldc           #39                 // String
      35: ldc           #39                 // String
      37: aload_1
      38: invokevirtual #29                 // Method java/lang/Throwable.getMessage:()Ljava/lang/String;
      41: aload_1
      42: invokeinterface #42,  6           // InterfaceMethod org/apache/dubbo/common/logger/ErrorTypeAwareLogger.warn:(Ljava/lang/String;Ljava/lang/String;Ljava/lang/String;Ljava/lang/String;Ljava/lang/Throwable;)V
      47: aload_0
      48: invokevirtual #98                 // Method doDisConnect:()V
      51: goto          74
      54: astore_1
      55: getstatic     #33                 // Field logger:Lorg/apache/dubbo/common/logger/ErrorTypeAwareLogger;
      58: ldc           #97                 // String 6-3
      60: ldc           #39                 // String
      62: ldc           #39                 // String
      64: aload_1
      65: invokevirtual #29                 // Method java/lang/Throwable.getMessage:()Ljava/lang/String;
      68: aload_1
      69: invokeinterface #42,  6           // InterfaceMethod org/apache/dubbo/common/logger/ErrorTypeAwareLogger.warn:(Ljava/lang/String;Ljava/lang/String;Ljava/lang/String;Ljava/lang/String;Ljava/lang/Throwable;)V
      74: aload_0
      75: getfield      #6                  // Field connectLock:Ljava/util/concurrent/locks/Lock;
      78: invokeinterface #78,  1           // InterfaceMethod java/util/concurrent/locks/Lock.unlock:()V
      83: goto          98
      86: astore_2
      87: aload_0
      88: getfield      #6                  // Field connectLock:Ljava/util/concurrent/locks/Lock;
      91: invokeinterface #78,  1           // InterfaceMethod java/util/concurrent/locks/Lock.unlock:()V
      96: aload_2
      97: athrow
      98: return
    Exception table:
       from    to  target type
           9    24    27   Class java/lang/Throwable
          47    51    54   Class java/lang/Throwable
           9    74    86   any

  public void reconnect() throws org.apache.dubbo.remoting.RemotingException;
    Code:
       0: aload_0
       1: getfield      #6                  // Field connectLock:Ljava/util/concurrent/locks/Lock;
       4: invokeinterface #77,  1           // InterfaceMethod java/util/concurrent/locks/Lock.lock:()V
       9: aload_0
      10: invokevirtual #99                 // Method disconnect:()V
      13: aload_0
      14: invokevirtual #32                 // Method connect:()V
      17: aload_0
      18: getfield      #6                  // Field connectLock:Ljava/util/concurrent/locks/Lock;
      21: invokeinterface #78,  1           // InterfaceMethod java/util/concurrent/locks/Lock.unlock:()V
      26: goto          41
      29: astore_1
      30: aload_0
      31: getfield      #6                  // Field connectLock:Ljava/util/concurrent/locks/Lock;
      34: invokeinterface #78,  1           // InterfaceMethod java/util/concurrent/locks/Lock.unlock:()V
      39: aload_1
      40: athrow
      41: return
    Exception table:
       from    to  target type
           9    17    29   any

  public void close();
    Code:
       0: aload_0
       1: invokevirtual #79                 // Method isClosed:()Z
       4: ifeq          86
       7: getstatic     #33                 // Field logger:Lorg/apache/dubbo/common/logger/ErrorTypeAwareLogger;
      10: ldc           #38                 // String 6-1
      12: ldc           #39                 // String
      14: ldc           #39                 // String
      16: new           #17                 // class java/lang/StringBuilder
      19: dup
      20: invokespecial #18                 // Method java/lang/StringBuilder."<init>":()V
      23: ldc           #100                // String No need to close connection to server
      25: invokevirtual #20                 // Method java/lang/StringBuilder.append:(Ljava/lang/String;)Ljava/lang/StringBuilder;
      28: aload_0
      29: invokevirtual #27                 // Method getRemoteAddress:()Ljava/net/InetSocketAddress;
      32: invokevirtual #25                 // Method java/lang/StringBuilder.append:(Ljava/lang/Object;)Ljava/lang/StringBuilder;
      35: ldc           #82                 // String  from
      37: invokevirtual #20                 // Method java/lang/StringBuilder.append:(Ljava/lang/String;)Ljava/lang/StringBuilder;
      40: aload_0
      41: invokevirtual #21                 // Method java/lang/Object.getClass:()Ljava/lang/Class;
      44: invokevirtual #22                 // Method java/lang/Class.getSimpleName:()Ljava/lang/String;
      47: invokevirtual #20                 // Method java/lang/StringBuilder.append:(Ljava/lang/String;)Ljava/lang/StringBuilder;
      50: ldc           #23                 // String
      52: invokevirtual #20                 // Method java/lang/StringBuilder.append:(Ljava/lang/String;)Ljava/lang/StringBuilder;
      55: invokestatic  #65                 // Method org/apache/dubbo/common/utils/NetUtils.getLocalHost:()Ljava/lang/String;
      58: invokevirtual #20                 // Method java/lang/StringBuilder.append:(Ljava/lang/String;)Ljava/lang/StringBuilder;
      61: ldc           #83                 // String  using dubbo version
      63: invokevirtual #20                 // Method java/lang/StringBuilder.append:(Ljava/lang/String;)Ljava/lang/StringBuilder;
      66: invokestatic  #84                 // Method org/apache/dubbo/common/Version.getVersion:()Ljava/lang/String;
      69: invokevirtual #20                 // Method java/lang/StringBuilder.append:(Ljava/lang/String;)Ljava/lang/StringBuilder;
      72: ldc           #101                // String , cause: the client status is closed.
      74: invokevirtual #20                 // Method java/lang/StringBuilder.append:(Ljava/lang/String;)Ljava/lang/StringBuilder;
      77: invokevirtual #30                 // Method java/lang/StringBuilder.toString:()Ljava/lang/String;
      80: invokeinterface #86,  5           // InterfaceMethod org/apache/dubbo/common/logger/ErrorTypeAwareLogger.warn:(Ljava/lang/String;Ljava/lang/String;Ljava/lang/String;Ljava/lang/String;)V
      85: return
      86: aload_0
      87: getfield      #6                  // Field connectLock:Ljava/util/concurrent/locks/Lock;
      90: invokeinterface #77,  1           // InterfaceMethod java/util/concurrent/locks/Lock.lock:()V
      95: aload_0
      96: invokevirtual #79                 // Method isClosed:()Z
      99: ifeq          190
     102: getstatic     #33                 // Field logger:Lorg/apache/dubbo/common/logger/ErrorTypeAwareLogger;
     105: ldc           #38                 // String 6-1
     107: ldc           #39                 // String
     109: ldc           #39                 // String
     111: new           #17                 // class java/lang/StringBuilder
     114: dup
     115: invokespecial #18                 // Method java/lang/StringBuilder."<init>":()V
     118: ldc           #100                // String No need to close connection to server
     120: invokevirtual #20                 // Method java/lang/StringBuilder.append:(Ljava/lang/String;)Ljava/lang/StringBuilder;
     123: aload_0
     124: invokevirtual #27                 // Method getRemoteAddress:()Ljava/net/InetSocketAddress;
     127: invokevirtual #25                 // Method java/lang/StringBuilder.append:(Ljava/lang/Object;)Ljava/lang/StringBuilder;
     130: ldc           #82                 // String  from
     132: invokevirtual #20                 // Method java/lang/StringBuilder.append:(Ljava/lang/String;)Ljava/lang/StringBuilder;
     135: aload_0
     136: invokevirtual #21                 // Method java/lang/Object.getClass:()Ljava/lang/Class;
     139: invokevirtual #22                 // Method java/lang/Class.getSimpleName:()Ljava/lang/String;
     142: invokevirtual #20                 // Method java/lang/StringBuilder.append:(Ljava/lang/String;)Ljava/lang/StringBuilder;
     145: ldc           #23                 // String
     147: invokevirtual #20                 // Method java/lang/StringBuilder.append:(Ljava/lang/String;)Ljava/lang/StringBuilder;
     150: invokestatic  #65                 // Method org/apache/dubbo/common/utils/NetUtils.getLocalHost:()Ljava/lang/String;
     153: invokevirtual #20                 // Method java/lang/StringBuilder.append:(Ljava/lang/String;)Ljava/lang/StringBuilder;
     156: ldc           #83                 // String  using dubbo version
     158: invokevirtual #20                 // Method java/lang/StringBuilder.append:(Ljava/lang/String;)Ljava/lang/StringBuilder;
     161: invokestatic  #84                 // Method org/apache/dubbo/common/Version.getVersion:()Ljava/lang/String;
     164: invokevirtual #20                 // Method java/lang/StringBuilder.append:(Ljava/lang/String;)Ljava/lang/StringBuilder;
     167: ldc           #101                // String , cause: the client status is closed.
     169: invokevirtual #20                 // Method java/lang/StringBuilder.append:(Ljava/lang/String;)Ljava/lang/StringBuilder;
     172: invokevirtual #30                 // Method java/lang/StringBuilder.toString:()Ljava/lang/String;
     175: invokeinterface #86,  5           // InterfaceMethod org/apache/dubbo/common/logger/ErrorTypeAwareLogger.warn:(Ljava/lang/String;Ljava/lang/String;Ljava/lang/String;Ljava/lang/String;)V
     180: aload_0
     181: getfield      #6                  // Field connectLock:Ljava/util/concurrent/locks/Lock;
     184: invokeinterface #78,  1           // InterfaceMethod java/util/concurrent/locks/Lock.unlock:()V
     189: return
     190: aload_0
     191: invokespecial #102                // Method org/apache/dubbo/remoting/transport/AbstractEndpoint.close:()V
     194: goto          217
     197: astore_1
     198: getstatic     #33                 // Field logger:Lorg/apache/dubbo/common/logger/ErrorTypeAwareLogger;
     201: ldc           #97                 // String 6-3
     203: ldc           #39                 // String
     205: ldc           #39                 // String
     207: aload_1
     208: invokevirtual #29                 // Method java/lang/Throwable.getMessage:()Ljava/lang/String;
     211: aload_1
     212: invokeinterface #42,  6           // InterfaceMethod org/apache/dubbo/common/logger/ErrorTypeAwareLogger.warn:(Ljava/lang/String;Ljava/lang/String;Ljava/lang/String;Ljava/lang/String;Ljava/lang/Throwable;)V
     217: aload_0
     218: invokevirtual #99                 // Method disconnect:()V
     221: goto          244
     224: astore_1
     225: getstatic     #33                 // Field logger:Lorg/apache/dubbo/common/logger/ErrorTypeAwareLogger;
     228: ldc           #97                 // String 6-3
     230: ldc           #39                 // String
     232: ldc           #39                 // String
     234: aload_1
     235: invokevirtual #29                 // Method java/lang/Throwable.getMessage:()Ljava/lang/String;
     238: aload_1
     239: invokeinterface #42,  6           // InterfaceMethod org/apache/dubbo/common/logger/ErrorTypeAwareLogger.warn:(Ljava/lang/String;Ljava/lang/String;Ljava/lang/String;Ljava/lang/String;Ljava/lang/Throwable;)V
     244: aload_0
     245: invokevirtual #103                // Method doClose:()V
     248: goto          271
     251: astore_1
     252: getstatic     #33                 // Field logger:Lorg/apache/dubbo/common/logger/ErrorTypeAwareLogger;
     255: ldc           #97                 // String 6-3
     257: ldc           #39                 // String
     259: ldc           #39                 // String
     261: aload_1
     262: invokevirtual #29                 // Method java/lang/Throwable.getMessage:()Ljava/lang/String;
     265: aload_1
     266: invokeinterface #42,  6           // InterfaceMethod org/apache/dubbo/common/logger/ErrorTypeAwareLogger.warn:(Ljava/lang/String;Ljava/lang/String;Ljava/lang/String;Ljava/lang/String;Ljava/lang/Throwable;)V
     271: aload_0
     272: getfield      #6                  // Field connectLock:Ljava/util/concurrent/locks/Lock;
     275: invokeinterface #78,  1           // InterfaceMethod java/util/concurrent/locks/Lock.unlock:()V
     280: goto          295
     283: astore_2
     284: aload_0
     285: getfield      #6                  // Field connectLock:Ljava/util/concurrent/locks/Lock;
     288: invokeinterface #78,  1           // InterfaceMethod java/util/concurrent/locks/Lock.unlock:()V
     293: aload_2
     294: athrow
     295: return
    Exception table:
       from    to  target type
         190   194   197   Class java/lang/Throwable
         217   221   224   Class java/lang/Throwable
         244   248   251   Class java/lang/Throwable
          95   180   283   any
         190   271   283   any

  public void close(int);
    Code:
       0: aload_0
       1: invokevirtual #14                 // Method close:()V
       4: return

  public java.lang.String toString();
    Code:
       0: new           #17                 // class java/lang/StringBuilder
       3: dup
       4: invokespecial #18                 // Method java/lang/StringBuilder."<init>":()V
       7: aload_0
       8: invokevirtual #21                 // Method java/lang/Object.getClass:()Ljava/lang/Class;
      11: invokevirtual #104                // Method java/lang/Class.getName:()Ljava/lang/String;
      14: invokevirtual #20                 // Method java/lang/StringBuilder.append:(Ljava/lang/String;)Ljava/lang/StringBuilder;
      17: ldc           #105                // String  [
      19: invokevirtual #20                 // Method java/lang/StringBuilder.append:(Ljava/lang/String;)Ljava/lang/StringBuilder;
      22: aload_0
      23: invokevirtual #106                // Method getLocalAddress:()Ljava/net/InetSocketAddress;
      26: invokevirtual #25                 // Method java/lang/StringBuilder.append:(Ljava/lang/Object;)Ljava/lang/StringBuilder;
      29: ldc           #107                // String  ->
      31: invokevirtual #20                 // Method java/lang/StringBuilder.append:(Ljava/lang/String;)Ljava/lang/StringBuilder;
      34: aload_0
      35: invokevirtual #27                 // Method getRemoteAddress:()Ljava/net/InetSocketAddress;
      38: invokevirtual #25                 // Method java/lang/StringBuilder.append:(Ljava/lang/Object;)Ljava/lang/StringBuilder;
      41: ldc           #108                // String ]
      43: invokevirtual #20                 // Method java/lang/StringBuilder.append:(Ljava/lang/String;)Ljava/lang/StringBuilder;
      46: invokevirtual #30                 // Method java/lang/StringBuilder.toString:()Ljava/lang/String;
      49: areturn

  protected abstract void doOpen() throws java.lang.Throwable;

  protected abstract void doClose() throws java.lang.Throwable;

  protected abstract void doConnect() throws java.lang.Throwable;

  protected abstract void doDisConnect() throws java.lang.Throwable;

  protected abstract org.apache.dubbo.remoting.Channel getChannel();

  static {};
    Code:
       0: ldc           #48                 // class org/apache/dubbo/remoting/transport/AbstractClient
       2: invokestatic  #109                // Method org/apache/dubbo/common/logger/LoggerFactory.getErrorTypeAwareLogger:(Ljava/lang/Class;)Lorg/apache/dubbo/common/logger/ErrorTypeAwareLogger;
       5: putstatic     #33                 // Field logger:Lorg/apache/dubbo/common/logger/ErrorTypeAwareLogger;
       8: return
}
