Compiled from "AbstractServer.java"
public abstract class org.apache.dubbo.remoting.transport.AbstractServer extends org.apache.dubbo.remoting.transport.AbstractEndpoint implements org.apache.dubbo.remoting.RemotingServer {
  private static final org.apache.dubbo.common.logger.ErrorTypeAwareLogger logger;

  private java.util.Set<java.util.concurrent.ExecutorService> executors;

  private java.net.InetSocketAddress localAddress;

  private java.net.InetSocketAddress bindAddress;

  private int accepts;

  private org.apache.dubbo.common.threadpool.manager.ExecutorRepository executorRepository;

  public org.apache.dubbo.remoting.transport.AbstractServer(org.apache.dubbo.common.URL, org.apache.dubbo.remoting.ChannelHandler) throws org.apache.dubbo.remoting.RemotingException;
    Code:
       0: aload_0
       1: aload_1
       2: aload_2
       3: invokespecial #5                  // Method org/apache/dubbo/remoting/transport/AbstractEndpoint."<init>":(Lorg/apache/dubbo/common/URL;Lorg/apache/dubbo/remoting/ChannelHandler;)V
       6: aload_0
       7: new           #6                  // class org/apache/dubbo/common/utils/ConcurrentHashSet
      10: dup
      11: invokespecial #7                  // Method org/apache/dubbo/common/utils/ConcurrentHashSet."<init>":()V
      14: putfield      #8                  // Field executors:Ljava/util/Set;
      17: aload_0
      18: aload_1
      19: invokevirtual #9                  // Method org/apache/dubbo/common/URL.getOrDefaultApplicationModel:()Lorg/apache/dubbo/rpc/model/ApplicationModel;
      22: invokestatic  #10                 // InterfaceMethod org/apache/dubbo/common/threadpool/manager/ExecutorRepository.getInstance:(Lorg/apache/dubbo/rpc/model/ApplicationModel;)Lorg/apache/dubbo/common/threadpool/manager/ExecutorRepository;
      25: putfield      #11                 // Field executorRepository:Lorg/apache/dubbo/common/threadpool/manager/ExecutorRepository;
      28: aload_0
      29: aload_0
      30: invokevirtual #12                 // Method getUrl:()Lorg/apache/dubbo/common/URL;
      33: invokevirtual #13                 // Method org/apache/dubbo/common/URL.toInetSocketAddress:()Ljava/net/InetSocketAddress;
      36: putfield      #14                 // Field localAddress:Ljava/net/InetSocketAddress;
      39: aload_0
      40: invokevirtual #12                 // Method getUrl:()Lorg/apache/dubbo/common/URL;
      43: ldc           #15                 // String bind.ip
      45: aload_0
      46: invokevirtual #12                 // Method getUrl:()Lorg/apache/dubbo/common/URL;
      49: invokevirtual #16                 // Method org/apache/dubbo/common/URL.getHost:()Ljava/lang/String;
      52: invokevirtual #17                 // Method org/apache/dubbo/common/URL.getParameter:(Ljava/lang/String;Ljava/lang/String;)Ljava/lang/String;
      55: astore_3
      56: aload_0
      57: invokevirtual #12                 // Method getUrl:()Lorg/apache/dubbo/common/URL;
      60: ldc           #18                 // String bind.port
      62: aload_0
      63: invokevirtual #12                 // Method getUrl:()Lorg/apache/dubbo/common/URL;
      66: invokevirtual #19                 // Method org/apache/dubbo/common/URL.getPort:()I
      69: invokevirtual #20                 // Method org/apache/dubbo/common/URL.getParameter:(Ljava/lang/String;I)I
      72: istore        4
      74: aload_1
      75: ldc           #21                 // String anyhost
      77: iconst_0
      78: invokevirtual #22                 // Method org/apache/dubbo/common/URL.getParameter:(Ljava/lang/String;Z)Z
      81: ifne          91
      84: aload_3
      85: invokestatic  #23                 // Method org/apache/dubbo/common/utils/NetUtils.isInvalidLocalHost:(Ljava/lang/String;)Z
      88: ifeq          94
      91: ldc           #24                 // String 0.0.0.0
      93: astore_3
      94: aload_0
      95: new           #25                 // class java/net/InetSocketAddress
      98: dup
      99: aload_3
     100: iload         4
     102: invokespecial #26                 // Method java/net/InetSocketAddress."<init>":(Ljava/lang/String;I)V
     105: putfield      #27                 // Field bindAddress:Ljava/net/InetSocketAddress;
     108: aload_0
     109: aload_1
     110: ldc           #28                 // String accepts
     112: iconst_0
     113: invokevirtual #20                 // Method org/apache/dubbo/common/URL.getParameter:(Ljava/lang/String;I)I
     116: putfield      #29                 // Field accepts:I
     119: aload_0
     120: invokevirtual #30                 // Method doOpen:()V
     123: getstatic     #31                 // Field logger:Lorg/apache/dubbo/common/logger/ErrorTypeAwareLogger;
     126: invokeinterface #32,  1           // InterfaceMethod org/apache/dubbo/common/logger/ErrorTypeAwareLogger.isInfoEnabled:()Z
     131: ifeq          191
     134: getstatic     #31                 // Field logger:Lorg/apache/dubbo/common/logger/ErrorTypeAwareLogger;
     137: new           #33                 // class java/lang/StringBuilder
     140: dup
     141: invokespecial #34                 // Method java/lang/StringBuilder."<init>":()V
     144: ldc           #35                 // String Start
     146: invokevirtual #36                 // Method java/lang/StringBuilder.append:(Ljava/lang/String;)Ljava/lang/StringBuilder;
     149: aload_0
     150: invokevirtual #37                 // Method java/lang/Object.getClass:()Ljava/lang/Class;
     153: invokevirtual #38                 // Method java/lang/Class.getSimpleName:()Ljava/lang/String;
     156: invokevirtual #36                 // Method java/lang/StringBuilder.append:(Ljava/lang/String;)Ljava/lang/StringBuilder;
     159: ldc           #39                 // String  bind
     161: invokevirtual #36                 // Method java/lang/StringBuilder.append:(Ljava/lang/String;)Ljava/lang/StringBuilder;
     164: aload_0
     165: invokevirtual #40                 // Method getBindAddress:()Ljava/net/InetSocketAddress;
     168: invokevirtual #41                 // Method java/lang/StringBuilder.append:(Ljava/lang/Object;)Ljava/lang/StringBuilder;
     171: ldc           #42                 // String , export
     173: invokevirtual #36                 // Method java/lang/StringBuilder.append:(Ljava/lang/String;)Ljava/lang/StringBuilder;
     176: aload_0
     177: invokevirtual #43                 // Method getLocalAddress:()Ljava/net/InetSocketAddress;
     180: invokevirtual #41                 // Method java/lang/StringBuilder.append:(Ljava/lang/Object;)Ljava/lang/StringBuilder;
     183: invokevirtual #44                 // Method java/lang/StringBuilder.toString:()Ljava/lang/String;
     186: invokeinterface #45,  2           // InterfaceMethod org/apache/dubbo/common/logger/ErrorTypeAwareLogger.info:(Ljava/lang/String;)V
     191: goto          261
     194: astore        5
     196: new           #47                 // class org/apache/dubbo/remoting/RemotingException
     199: dup
     200: aload_1
     201: invokevirtual #13                 // Method org/apache/dubbo/common/URL.toInetSocketAddress:()Ljava/net/InetSocketAddress;
     204: aconst_null
     205: new           #33                 // class java/lang/StringBuilder
     208: dup
     209: invokespecial #34                 // Method java/lang/StringBuilder."<init>":()V
     212: ldc           #48                 // String Failed to bind
     214: invokevirtual #36                 // Method java/lang/StringBuilder.append:(Ljava/lang/String;)Ljava/lang/StringBuilder;
     217: aload_0
     218: invokevirtual #37                 // Method java/lang/Object.getClass:()Ljava/lang/Class;
     221: invokevirtual #38                 // Method java/lang/Class.getSimpleName:()Ljava/lang/String;
     224: invokevirtual #36                 // Method java/lang/StringBuilder.append:(Ljava/lang/String;)Ljava/lang/StringBuilder;
     227: ldc           #49                 // String  on
     229: invokevirtual #36                 // Method java/lang/StringBuilder.append:(Ljava/lang/String;)Ljava/lang/StringBuilder;
     232: aload_0
     233: getfield      #27                 // Field bindAddress:Ljava/net/InetSocketAddress;
     236: invokevirtual #41                 // Method java/lang/StringBuilder.append:(Ljava/lang/Object;)Ljava/lang/StringBuilder;
     239: ldc           #50                 // String , cause:
     241: invokevirtual #36                 // Method java/lang/StringBuilder.append:(Ljava/lang/String;)Ljava/lang/StringBuilder;
     244: aload         5
     246: invokevirtual #51                 // Method java/lang/Throwable.getMessage:()Ljava/lang/String;
     249: invokevirtual #36                 // Method java/lang/StringBuilder.append:(Ljava/lang/String;)Ljava/lang/StringBuilder;
     252: invokevirtual #44                 // Method java/lang/StringBuilder.toString:()Ljava/lang/String;
     255: aload         5
     257: invokespecial #52                 // Method org/apache/dubbo/remoting/RemotingException."<init>":(Ljava/net/InetSocketAddress;Ljava/net/InetSocketAddress;Ljava/lang/String;Ljava/lang/Throwable;)V
     260: athrow
     261: aload_0
     262: getfield      #8                  // Field executors:Ljava/util/Set;
     265: aload_0
     266: getfield      #11                 // Field executorRepository:Lorg/apache/dubbo/common/threadpool/manager/ExecutorRepository;
     269: aload_1
     270: ldc           #53                 // String DubboServerHandler
     272: invokestatic  #54                 // Method org/apache/dubbo/common/utils/ExecutorUtil.setThreadName:(Lorg/apache/dubbo/common/URL;Ljava/lang/String;)Lorg/apache/dubbo/common/URL;
     275: invokeinterface #55,  2           // InterfaceMethod org/apache/dubbo/common/threadpool/manager/ExecutorRepository.createExecutorIfAbsent:(Lorg/apache/dubbo/common/URL;)Ljava/util/concurrent/ExecutorService;
     280: invokeinterface #56,  2           // InterfaceMethod java/util/Set.add:(Ljava/lang/Object;)Z
     285: pop
     286: return
    Exception table:
       from    to  target type
         119   191   194   Class java/lang/Throwable

  protected abstract void doOpen() throws java.lang.Throwable;

  protected abstract void doClose() throws java.lang.Throwable;

  protected abstract int getChannelsSize();

  public void reset(org.apache.dubbo.common.URL);
    Code:
       0: aload_1
       1: ifnonnull     5
       4: return
       5: aload_1
       6: ldc           #28                 // String accepts
       8: invokevirtual #57                 // Method org/apache/dubbo/common/URL.hasParameter:(Ljava/lang/String;)Z
      11: ifeq          31
      14: aload_1
      15: ldc           #28                 // String accepts
      17: iconst_0
      18: invokevirtual #20                 // Method org/apache/dubbo/common/URL.getParameter:(Ljava/lang/String;I)I
      21: istore_2
      22: iload_2
      23: ifle          31
      26: aload_0
      27: iload_2
      28: putfield      #29                 // Field accepts:I
      31: goto          54
      34: astore_2
      35: getstatic     #31                 // Field logger:Lorg/apache/dubbo/common/logger/ErrorTypeAwareLogger;
      38: ldc           #58                 // String 99-0
      40: ldc           #59                 // String unknown error in remoting module
      42: ldc           #60                 // String
      44: aload_2
      45: invokevirtual #51                 // Method java/lang/Throwable.getMessage:()Ljava/lang/String;
      48: aload_2
      49: invokeinterface #61,  6           // InterfaceMethod org/apache/dubbo/common/logger/ErrorTypeAwareLogger.error:(Ljava/lang/String;Ljava/lang/String;Ljava/lang/String;Ljava/lang/String;Ljava/lang/Throwable;)V
      54: aload_0
      55: getfield      #11                 // Field executorRepository:Lorg/apache/dubbo/common/threadpool/manager/ExecutorRepository;
      58: aload_1
      59: ldc           #53                 // String DubboServerHandler
      61: invokestatic  #54                 // Method org/apache/dubbo/common/utils/ExecutorUtil.setThreadName:(Lorg/apache/dubbo/common/URL;Ljava/lang/String;)Lorg/apache/dubbo/common/URL;
      64: invokeinterface #55,  2           // InterfaceMethod org/apache/dubbo/common/threadpool/manager/ExecutorRepository.createExecutorIfAbsent:(Lorg/apache/dubbo/common/URL;)Ljava/util/concurrent/ExecutorService;
      69: astore_2
      70: aload_0
      71: getfield      #8                  // Field executors:Ljava/util/Set;
      74: aload_2
      75: invokeinterface #56,  2           // InterfaceMethod java/util/Set.add:(Ljava/lang/Object;)Z
      80: pop
      81: aload_0
      82: getfield      #11                 // Field executorRepository:Lorg/apache/dubbo/common/threadpool/manager/ExecutorRepository;
      85: aload_1
      86: aload_2
      87: invokeinterface #62,  3           // InterfaceMethod org/apache/dubbo/common/threadpool/manager/ExecutorRepository.updateThreadpool:(Lorg/apache/dubbo/common/URL;Ljava/util/concurrent/ExecutorService;)V
      92: aload_0
      93: aload_0
      94: invokevirtual #12                 // Method getUrl:()Lorg/apache/dubbo/common/URL;
      97: aload_1
      98: invokevirtual #63                 // Method org/apache/dubbo/common/URL.getParameters:()Ljava/util/Map;
     101: invokevirtual #64                 // Method org/apache/dubbo/common/URL.addParameters:(Ljava/util/Map;)Lorg/apache/dubbo/common/URL;
     104: invokespecial #65                 // Method org/apache/dubbo/remoting/transport/AbstractEndpoint.setUrl:(Lorg/apache/dubbo/common/URL;)V
     107: return
    Exception table:
       from    to  target type
           5    31    34   Class java/lang/Throwable

  public void send(java.lang.Object, boolean) throws org.apache.dubbo.remoting.RemotingException;
    Code:
       0: aload_0
       1: invokevirtual #66                 // Method getChannels:()Ljava/util/Collection;
       4: astore_3
       5: aload_3
       6: invokeinterface #67,  1           // InterfaceMethod java/util/Collection.iterator:()Ljava/util/Iterator;
      11: astore        4
      13: aload         4
      15: invokeinterface #68,  1           // InterfaceMethod java/util/Iterator.hasNext:()Z
      20: ifeq          57
      23: aload         4
      25: invokeinterface #69,  1           // InterfaceMethod java/util/Iterator.next:()Ljava/lang/Object;
      30: checkcast     #70                 // class org/apache/dubbo/remoting/Channel
      33: astore        5
      35: aload         5
      37: invokeinterface #71,  1           // InterfaceMethod org/apache/dubbo/remoting/Channel.isConnected:()Z
      42: ifeq          54
      45: aload         5
      47: aload_1
      48: iload_2
      49: invokeinterface #72,  3           // InterfaceMethod org/apache/dubbo/remoting/Channel.send:(Ljava/lang/Object;Z)V
      54: goto          13
      57: return

  public void close();
    Code:
       0: getstatic     #31                 // Field logger:Lorg/apache/dubbo/common/logger/ErrorTypeAwareLogger;
       3: invokeinterface #32,  1           // InterfaceMethod org/apache/dubbo/common/logger/ErrorTypeAwareLogger.isInfoEnabled:()Z
       8: ifeq          68
      11: getstatic     #31                 // Field logger:Lorg/apache/dubbo/common/logger/ErrorTypeAwareLogger;
      14: new           #33                 // class java/lang/StringBuilder
      17: dup
      18: invokespecial #34                 // Method java/lang/StringBuilder."<init>":()V
      21: ldc           #73                 // String Close
      23: invokevirtual #36                 // Method java/lang/StringBuilder.append:(Ljava/lang/String;)Ljava/lang/StringBuilder;
      26: aload_0
      27: invokevirtual #37                 // Method java/lang/Object.getClass:()Ljava/lang/Class;
      30: invokevirtual #38                 // Method java/lang/Class.getSimpleName:()Ljava/lang/String;
      33: invokevirtual #36                 // Method java/lang/StringBuilder.append:(Ljava/lang/String;)Ljava/lang/StringBuilder;
      36: ldc           #39                 // String  bind
      38: invokevirtual #36                 // Method java/lang/StringBuilder.append:(Ljava/lang/String;)Ljava/lang/StringBuilder;
      41: aload_0
      42: invokevirtual #40                 // Method getBindAddress:()Ljava/net/InetSocketAddress;
      45: invokevirtual #41                 // Method java/lang/StringBuilder.append:(Ljava/lang/Object;)Ljava/lang/StringBuilder;
      48: ldc           #42                 // String , export
      50: invokevirtual #36                 // Method java/lang/StringBuilder.append:(Ljava/lang/String;)Ljava/lang/StringBuilder;
      53: aload_0
      54: invokevirtual #43                 // Method getLocalAddress:()Ljava/net/InetSocketAddress;
      57: invokevirtual #41                 // Method java/lang/StringBuilder.append:(Ljava/lang/Object;)Ljava/lang/StringBuilder;
      60: invokevirtual #44                 // Method java/lang/StringBuilder.toString:()Ljava/lang/String;
      63: invokeinterface #45,  2           // InterfaceMethod org/apache/dubbo/common/logger/ErrorTypeAwareLogger.info:(Ljava/lang/String;)V
      68: aload_0
      69: getfield      #8                  // Field executors:Ljava/util/Set;
      72: invokeinterface #74,  1           // InterfaceMethod java/util/Set.iterator:()Ljava/util/Iterator;
      77: astore_1
      78: aload_1
      79: invokeinterface #68,  1           // InterfaceMethod java/util/Iterator.hasNext:()Z
      84: ifeq          106
      87: aload_1
      88: invokeinterface #69,  1           // InterfaceMethod java/util/Iterator.next:()Ljava/lang/Object;
      93: checkcast     #75                 // class java/util/concurrent/ExecutorService
      96: astore_2
      97: aload_2
      98: bipush        100
     100: invokestatic  #76                 // Method org/apache/dubbo/common/utils/ExecutorUtil.shutdownNow:(Ljava/util/concurrent/Executor;I)V
     103: goto          78
     106: aload_0
     107: invokespecial #77                 // Method org/apache/dubbo/remoting/transport/AbstractEndpoint.close:()V
     110: goto          133
     113: astore_1
     114: getstatic     #31                 // Field logger:Lorg/apache/dubbo/common/logger/ErrorTypeAwareLogger;
     117: ldc           #58                 // String 99-0
     119: ldc           #59                 // String unknown error in remoting module
     121: ldc           #60                 // String
     123: aload_1
     124: invokevirtual #51                 // Method java/lang/Throwable.getMessage:()Ljava/lang/String;
     127: aload_1
     128: invokeinterface #78,  6           // InterfaceMethod org/apache/dubbo/common/logger/ErrorTypeAwareLogger.warn:(Ljava/lang/String;Ljava/lang/String;Ljava/lang/String;Ljava/lang/String;Ljava/lang/Throwable;)V
     133: aload_0
     134: invokevirtual #79                 // Method doClose:()V
     137: goto          160
     140: astore_1
     141: getstatic     #31                 // Field logger:Lorg/apache/dubbo/common/logger/ErrorTypeAwareLogger;
     144: ldc           #58                 // String 99-0
     146: ldc           #59                 // String unknown error in remoting module
     148: ldc           #60                 // String
     150: aload_1
     151: invokevirtual #51                 // Method java/lang/Throwable.getMessage:()Ljava/lang/String;
     154: aload_1
     155: invokeinterface #78,  6           // InterfaceMethod org/apache/dubbo/common/logger/ErrorTypeAwareLogger.warn:(Ljava/lang/String;Ljava/lang/String;Ljava/lang/String;Ljava/lang/String;Ljava/lang/Throwable;)V
     160: return
    Exception table:
       from    to  target type
         106   110   113   Class java/lang/Throwable
         133   137   140   Class java/lang/Throwable

  public void close(int);
    Code:
       0: aload_0
       1: getfield      #8                  // Field executors:Ljava/util/Set;
       4: invokeinterface #74,  1           // InterfaceMethod java/util/Set.iterator:()Ljava/util/Iterator;
       9: astore_2
      10: aload_2
      11: invokeinterface #68,  1           // InterfaceMethod java/util/Iterator.hasNext:()Z
      16: ifeq          37
      19: aload_2
      20: invokeinterface #69,  1           // InterfaceMethod java/util/Iterator.next:()Ljava/lang/Object;
      25: checkcast     #75                 // class java/util/concurrent/ExecutorService
      28: astore_3
      29: aload_3
      30: iload_1
      31: invokestatic  #80                 // Method org/apache/dubbo/common/utils/ExecutorUtil.gracefulShutdown:(Ljava/util/concurrent/Executor;I)V
      34: goto          10
      37: aload_0
      38: invokevirtual #81                 // Method close:()V
      41: return

  public java.net.InetSocketAddress getLocalAddress();
    Code:
       0: aload_0
       1: getfield      #14                 // Field localAddress:Ljava/net/InetSocketAddress;
       4: areturn

  public java.net.InetSocketAddress getBindAddress();
    Code:
       0: aload_0
       1: getfield      #27                 // Field bindAddress:Ljava/net/InetSocketAddress;
       4: areturn

  public int getAccepts();
    Code:
       0: aload_0
       1: getfield      #29                 // Field accepts:I
       4: ireturn

  public void connected(org.apache.dubbo.remoting.Channel) throws org.apache.dubbo.remoting.RemotingException;
    Code:
       0: aload_0
       1: invokevirtual #82                 // Method isClosing:()Z
       4: ifne          14
       7: aload_0
       8: invokevirtual #83                 // Method isClosed:()Z
      11: ifeq          59
      14: getstatic     #31                 // Field logger:Lorg/apache/dubbo/common/logger/ErrorTypeAwareLogger;
      17: ldc           #58                 // String 99-0
      19: ldc           #59                 // String unknown error in remoting module
      21: ldc           #60                 // String
      23: new           #33                 // class java/lang/StringBuilder
      26: dup
      27: invokespecial #34                 // Method java/lang/StringBuilder."<init>":()V
      30: ldc           #84                 // String Close new channel
      32: invokevirtual #36                 // Method java/lang/StringBuilder.append:(Ljava/lang/String;)Ljava/lang/StringBuilder;
      35: aload_1
      36: invokevirtual #41                 // Method java/lang/StringBuilder.append:(Ljava/lang/Object;)Ljava/lang/StringBuilder;
      39: ldc           #85                 // String , cause: server is closing or has been closed. For example, receive a new connect request while in shutdown process.
      41: invokevirtual #36                 // Method java/lang/StringBuilder.append:(Ljava/lang/String;)Ljava/lang/StringBuilder;
      44: invokevirtual #44                 // Method java/lang/StringBuilder.toString:()Ljava/lang/String;
      47: invokeinterface #86,  5           // InterfaceMethod org/apache/dubbo/common/logger/ErrorTypeAwareLogger.warn:(Ljava/lang/String;Ljava/lang/String;Ljava/lang/String;Ljava/lang/String;)V
      52: aload_1
      53: invokeinterface #87,  1           // InterfaceMethod org/apache/dubbo/remoting/Channel.close:()V
      58: return
      59: aload_0
      60: getfield      #29                 // Field accepts:I
      63: ifle          143
      66: aload_0
      67: invokevirtual #88                 // Method getChannelsSize:()I
      70: aload_0
      71: getfield      #29                 // Field accepts:I
      74: if_icmple     143
      77: getstatic     #31                 // Field logger:Lorg/apache/dubbo/common/logger/ErrorTypeAwareLogger;
      80: ldc           #58                 // String 99-0
      82: ldc           #59                 // String unknown error in remoting module
      84: ldc           #60                 // String
      86: new           #33                 // class java/lang/StringBuilder
      89: dup
      90: invokespecial #34                 // Method java/lang/StringBuilder."<init>":()V
      93: ldc           #89                 // String Close channel
      95: invokevirtual #36                 // Method java/lang/StringBuilder.append:(Ljava/lang/String;)Ljava/lang/StringBuilder;
      98: aload_1
      99: invokevirtual #41                 // Method java/lang/StringBuilder.append:(Ljava/lang/Object;)Ljava/lang/StringBuilder;
     102: ldc           #90                 // String , cause: The server
     104: invokevirtual #36                 // Method java/lang/StringBuilder.append:(Ljava/lang/String;)Ljava/lang/StringBuilder;
     107: aload_1
     108: invokeinterface #91,  1           // InterfaceMethod org/apache/dubbo/remoting/Channel.getLocalAddress:()Ljava/net/InetSocketAddress;
     113: invokevirtual #41                 // Method java/lang/StringBuilder.append:(Ljava/lang/Object;)Ljava/lang/StringBuilder;
     116: ldc           #92                 // String  connections greater than max config
     118: invokevirtual #36                 // Method java/lang/StringBuilder.append:(Ljava/lang/String;)Ljava/lang/StringBuilder;
     121: aload_0
     122: getfield      #29                 // Field accepts:I
     125: invokevirtual #93                 // Method java/lang/StringBuilder.append:(I)Ljava/lang/StringBuilder;
     128: invokevirtual #44                 // Method java/lang/StringBuilder.toString:()Ljava/lang/String;
     131: invokeinterface #94,  5           // InterfaceMethod org/apache/dubbo/common/logger/ErrorTypeAwareLogger.error:(Ljava/lang/String;Ljava/lang/String;Ljava/lang/String;Ljava/lang/String;)V
     136: aload_1
     137: invokeinterface #87,  1           // InterfaceMethod org/apache/dubbo/remoting/Channel.close:()V
     142: return
     143: aload_0
     144: aload_1
     145: invokespecial #95                 // Method org/apache/dubbo/remoting/transport/AbstractEndpoint.connected:(Lorg/apache/dubbo/remoting/Channel;)V
     148: return

  public void disconnected(org.apache.dubbo.remoting.Channel) throws org.apache.dubbo.remoting.RemotingException;
    Code:
       0: aload_0
       1: invokevirtual #88                 // Method getChannelsSize:()I
       4: ifne          50
       7: getstatic     #31                 // Field logger:Lorg/apache/dubbo/common/logger/ErrorTypeAwareLogger;
      10: ldc           #58                 // String 99-0
      12: ldc           #59                 // String unknown error in remoting module
      14: ldc           #60                 // String
      16: new           #33                 // class java/lang/StringBuilder
      19: dup
      20: invokespecial #34                 // Method java/lang/StringBuilder."<init>":()V
      23: ldc           #96                 // String All clients has disconnected from
      25: invokevirtual #36                 // Method java/lang/StringBuilder.append:(Ljava/lang/String;)Ljava/lang/StringBuilder;
      28: aload_1
      29: invokeinterface #91,  1           // InterfaceMethod org/apache/dubbo/remoting/Channel.getLocalAddress:()Ljava/net/InetSocketAddress;
      34: invokevirtual #41                 // Method java/lang/StringBuilder.append:(Ljava/lang/Object;)Ljava/lang/StringBuilder;
      37: ldc           #97                 // String . You can graceful shutdown now.
      39: invokevirtual #36                 // Method java/lang/StringBuilder.append:(Ljava/lang/String;)Ljava/lang/StringBuilder;
      42: invokevirtual #44                 // Method java/lang/StringBuilder.toString:()Ljava/lang/String;
      45: invokeinterface #86,  5           // InterfaceMethod org/apache/dubbo/common/logger/ErrorTypeAwareLogger.warn:(Ljava/lang/String;Ljava/lang/String;Ljava/lang/String;Ljava/lang/String;)V
      50: aload_0
      51: aload_1
      52: invokespecial #98                 // Method org/apache/dubbo/remoting/transport/AbstractEndpoint.disconnected:(Lorg/apache/dubbo/remoting/Channel;)V
      55: return

  static {};
    Code:
       0: ldc           #99                 // class org/apache/dubbo/remoting/transport/AbstractServer
       2: invokestatic  #100                // Method org/apache/dubbo/common/logger/LoggerFactory.getErrorTypeAwareLogger:(Ljava/lang/Class;)Lorg/apache/dubbo/common/logger/ErrorTypeAwareLogger;
       5: putstatic     #31                 // Field logger:Lorg/apache/dubbo/common/logger/ErrorTypeAwareLogger;
       8: return
}
