Compiled from "AbstractCodec.java"
public abstract class org.apache.dubbo.remoting.transport.AbstractCodec implements org.apache.dubbo.remoting.Codec2,org.apache.dubbo.rpc.model.ScopeModelAware {
  private static final org.apache.dubbo.common.logger.ErrorTypeAwareLogger logger;

  private static final java.lang.String CLIENT_SIDE;

  private static final java.lang.String SERVER_SIDE;

  protected org.apache.dubbo.rpc.model.FrameworkModel frameworkModel;

  public org.apache.dubbo.remoting.transport.AbstractCodec();
    Code:
       0: aload_0
       1: invokespecial #3                  // Method java/lang/Object."<init>":()V
       4: return

  public void setFrameworkModel(org.apache.dubbo.rpc.model.FrameworkModel);
    Code:
       0: aload_0
       1: aload_1
       2: putfield      #4                  // Field frameworkModel:Lorg/apache/dubbo/rpc/model/FrameworkModel;
       5: return

  protected static void checkPayload(org.apache.dubbo.remoting.Channel, long) throws java.io.IOException;
    Code:
       0: aload_0
       1: invokestatic  #5                  // Method getPayload:(Lorg/apache/dubbo/remoting/Channel;)I
       4: istore_3
       5: iload_3
       6: lload_1
       7: invokestatic  #6                  // Method isOverPayload:(IJ)Z
      10: istore        4
      12: iload         4
      14: ifeq          87
      17: new           #7                  // class org/apache/dubbo/remoting/transport/ExceedPayloadLimitException
      20: dup
      21: new           #8                  // class java/lang/StringBuilder
      24: dup
      25: invokespecial #9                  // Method java/lang/StringBuilder."<init>":()V
      28: ldc           #10                 // String Data length too large:
      30: invokevirtual #11                 // Method java/lang/StringBuilder.append:(Ljava/lang/String;)Ljava/lang/StringBuilder;
      33: lload_1
      34: invokevirtual #12                 // Method java/lang/StringBuilder.append:(J)Ljava/lang/StringBuilder;
      37: ldc           #13                 // String , max payload:
      39: invokevirtual #11                 // Method java/lang/StringBuilder.append:(Ljava/lang/String;)Ljava/lang/StringBuilder;
      42: iload_3
      43: invokevirtual #14                 // Method java/lang/StringBuilder.append:(I)Ljava/lang/StringBuilder;
      46: ldc           #15                 // String , channel:
      48: invokevirtual #11                 // Method java/lang/StringBuilder.append:(Ljava/lang/String;)Ljava/lang/StringBuilder;
      51: aload_0
      52: invokevirtual #16                 // Method java/lang/StringBuilder.append:(Ljava/lang/Object;)Ljava/lang/StringBuilder;
      55: invokevirtual #17                 // Method java/lang/StringBuilder.toString:()Ljava/lang/String;
      58: invokespecial #18                 // Method org/apache/dubbo/remoting/transport/ExceedPayloadLimitException."<init>":(Ljava/lang/String;)V
      61: astore        5
      63: getstatic     #19                 // Field logger:Lorg/apache/dubbo/common/logger/ErrorTypeAwareLogger;
      66: ldc           #20                 // String 6-10
      68: ldc           #21                 // String
      70: ldc           #21                 // String
      72: aload         5
      74: invokevirtual #22                 // Method org/apache/dubbo/remoting/transport/ExceedPayloadLimitException.getMessage:()Ljava/lang/String;
      77: aload         5
      79: invokeinterface #23,  6           // InterfaceMethod org/apache/dubbo/common/logger/ErrorTypeAwareLogger.error:(Ljava/lang/String;Ljava/lang/String;Ljava/lang/String;Ljava/lang/String;Ljava/lang/Throwable;)V
      84: aload         5
      86: athrow
      87: return

  protected static void checkPayload(org.apache.dubbo.remoting.Channel, int, long) throws java.io.IOException;
    Code:
       0: iload_1
       1: ifgt          9
       4: aload_0
       5: invokestatic  #5                  // Method getPayload:(Lorg/apache/dubbo/remoting/Channel;)I
       8: istore_1
       9: iload_1
      10: lload_2
      11: invokestatic  #6                  // Method isOverPayload:(IJ)Z
      14: istore        4
      16: iload         4
      18: ifeq          91
      21: new           #7                  // class org/apache/dubbo/remoting/transport/ExceedPayloadLimitException
      24: dup
      25: new           #8                  // class java/lang/StringBuilder
      28: dup
      29: invokespecial #9                  // Method java/lang/StringBuilder."<init>":()V
      32: ldc           #10                 // String Data length too large:
      34: invokevirtual #11                 // Method java/lang/StringBuilder.append:(Ljava/lang/String;)Ljava/lang/StringBuilder;
      37: lload_2
      38: invokevirtual #12                 // Method java/lang/StringBuilder.append:(J)Ljava/lang/StringBuilder;
      41: ldc           #13                 // String , max payload:
      43: invokevirtual #11                 // Method java/lang/StringBuilder.append:(Ljava/lang/String;)Ljava/lang/StringBuilder;
      46: iload_1
      47: invokevirtual #14                 // Method java/lang/StringBuilder.append:(I)Ljava/lang/StringBuilder;
      50: ldc           #15                 // String , channel:
      52: invokevirtual #11                 // Method java/lang/StringBuilder.append:(Ljava/lang/String;)Ljava/lang/StringBuilder;
      55: aload_0
      56: invokevirtual #16                 // Method java/lang/StringBuilder.append:(Ljava/lang/Object;)Ljava/lang/StringBuilder;
      59: invokevirtual #17                 // Method java/lang/StringBuilder.toString:()Ljava/lang/String;
      62: invokespecial #18                 // Method org/apache/dubbo/remoting/transport/ExceedPayloadLimitException."<init>":(Ljava/lang/String;)V
      65: astore        5
      67: getstatic     #19                 // Field logger:Lorg/apache/dubbo/common/logger/ErrorTypeAwareLogger;
      70: ldc           #20                 // String 6-10
      72: ldc           #21                 // String
      74: ldc           #21                 // String
      76: aload         5
      78: invokevirtual #22                 // Method org/apache/dubbo/remoting/transport/ExceedPayloadLimitException.getMessage:()Ljava/lang/String;
      81: aload         5
      83: invokeinterface #23,  6           // InterfaceMethod org/apache/dubbo/common/logger/ErrorTypeAwareLogger.error:(Ljava/lang/String;Ljava/lang/String;Ljava/lang/String;Ljava/lang/String;Ljava/lang/Throwable;)V
      88: aload         5
      90: athrow
      91: return

  protected static int getPayload(org.apache.dubbo.remoting.Channel);
    Code:
       0: aload_0
       1: ifnull        27
       4: aload_0
       5: invokeinterface #24,  1           // InterfaceMethod org/apache/dubbo/remoting/Channel.getUrl:()Lorg/apache/dubbo/common/URL;
      10: ifnull        27
      13: aload_0
      14: invokeinterface #24,  1           // InterfaceMethod org/apache/dubbo/remoting/Channel.getUrl:()Lorg/apache/dubbo/common/URL;
      19: ldc           #26                 // String payload
      21: ldc           #27                 // int 8388608
      23: invokevirtual #28                 // Method org/apache/dubbo/common/URL.getParameter:(Ljava/lang/String;I)I
      26: ireturn
      27: ldc           #27                 // int 8388608
      29: ireturn

  protected static boolean isOverPayload(int, long);
    Code:
       0: iload_0
       1: ifle          15
       4: lload_1
       5: iload_0
       6: i2l
       7: lcmp
       8: ifle          15
      11: iconst_1
      12: goto          16
      15: iconst_0
      16: ireturn

  protected org.apache.dubbo.common.serialize.Serialization getSerialization(org.apache.dubbo.remoting.Channel, org.apache.dubbo.remoting.exchange.Request);
    Code:
       0: aload_1
       1: invokeinterface #24,  1           // InterfaceMethod org/apache/dubbo/remoting/Channel.getUrl:()Lorg/apache/dubbo/common/URL;
       6: invokestatic  #29                 // Method org/apache/dubbo/remoting/transport/CodecSupport.getSerialization:(Lorg/apache/dubbo/common/URL;)Lorg/apache/dubbo/common/serialize/Serialization;
       9: areturn

  protected org.apache.dubbo.common.serialize.Serialization getSerialization(org.apache.dubbo.remoting.Channel, org.apache.dubbo.remoting.exchange.Response);
    Code:
       0: aload_1
       1: invokeinterface #24,  1           // InterfaceMethod org/apache/dubbo/remoting/Channel.getUrl:()Lorg/apache/dubbo/common/URL;
       6: invokestatic  #29                 // Method org/apache/dubbo/remoting/transport/CodecSupport.getSerialization:(Lorg/apache/dubbo/common/URL;)Lorg/apache/dubbo/common/serialize/Serialization;
       9: areturn

  protected org.apache.dubbo.common.serialize.Serialization getSerialization(org.apache.dubbo.remoting.Channel);
    Code:
       0: aload_1
       1: invokeinterface #24,  1           // InterfaceMethod org/apache/dubbo/remoting/Channel.getUrl:()Lorg/apache/dubbo/common/URL;
       6: invokestatic  #29                 // Method org/apache/dubbo/remoting/transport/CodecSupport.getSerialization:(Lorg/apache/dubbo/common/URL;)Lorg/apache/dubbo/common/serialize/Serialization;
       9: areturn

  protected boolean isClientSide(org.apache.dubbo.remoting.Channel);
    Code:
       0: aload_1
       1: ldc           #30                 // String side
       3: invokeinterface #31,  2           // InterfaceMethod org/apache/dubbo/remoting/Channel.getAttribute:(Ljava/lang/String;)Ljava/lang/Object;
       8: checkcast     #32                 // class java/lang/String
      11: astore_2
      12: ldc           #34                 // String client
      14: aload_2
      15: invokevirtual #35                 // Method java/lang/String.equals:(Ljava/lang/Object;)Z
      18: ifeq          23
      21: iconst_1
      22: ireturn
      23: ldc           #36                 // String server
      25: aload_2
      26: invokevirtual #35                 // Method java/lang/String.equals:(Ljava/lang/Object;)Z
      29: ifeq          34
      32: iconst_0
      33: ireturn
      34: aload_1
      35: invokeinterface #37,  1           // InterfaceMethod org/apache/dubbo/remoting/Channel.getRemoteAddress:()Ljava/net/InetSocketAddress;
      40: astore_3
      41: aload_1
      42: invokeinterface #24,  1           // InterfaceMethod org/apache/dubbo/remoting/Channel.getUrl:()Lorg/apache/dubbo/common/URL;
      47: astore        4
      49: aload         4
      51: invokevirtual #38                 // Method org/apache/dubbo/common/URL.getPort:()I
      54: aload_3
      55: invokevirtual #39                 // Method java/net/InetSocketAddress.getPort:()I
      58: if_icmpne     89
      61: aload         4
      63: invokevirtual #40                 // Method org/apache/dubbo/common/URL.getIp:()Ljava/lang/String;
      66: invokestatic  #41                 // Method org/apache/dubbo/common/utils/NetUtils.filterLocalHost:(Ljava/lang/String;)Ljava/lang/String;
      69: aload_3
      70: invokevirtual #42                 // Method java/net/InetSocketAddress.getAddress:()Ljava/net/InetAddress;
      73: invokevirtual #43                 // Method java/net/InetAddress.getHostAddress:()Ljava/lang/String;
      76: invokestatic  #41                 // Method org/apache/dubbo/common/utils/NetUtils.filterLocalHost:(Ljava/lang/String;)Ljava/lang/String;
      79: invokevirtual #35                 // Method java/lang/String.equals:(Ljava/lang/Object;)Z
      82: ifeq          89
      85: iconst_1
      86: goto          90
      89: iconst_0
      90: istore        5
      92: aload_1
      93: ldc           #30                 // String side
      95: iload         5
      97: ifeq          105
     100: ldc           #34                 // String client
     102: goto          107
     105: ldc           #36                 // String server
     107: invokeinterface #44,  3           // InterfaceMethod org/apache/dubbo/remoting/Channel.setAttribute:(Ljava/lang/String;Ljava/lang/Object;)V
     112: iload         5
     114: ireturn

  protected boolean isServerSide(org.apache.dubbo.remoting.Channel);
    Code:
       0: aload_0
       1: aload_1
       2: invokevirtual #45                 // Method isClientSide:(Lorg/apache/dubbo/remoting/Channel;)Z
       5: ifne          12
       8: iconst_1
       9: goto          13
      12: iconst_0
      13: ireturn

  static {};
    Code:
       0: ldc           #33                 // class org/apache/dubbo/remoting/transport/AbstractCodec
       2: invokestatic  #46                 // Method org/apache/dubbo/common/logger/LoggerFactory.getErrorTypeAwareLogger:(Ljava/lang/Class;)Lorg/apache/dubbo/common/logger/ErrorTypeAwareLogger;
       5: putstatic     #19                 // Field logger:Lorg/apache/dubbo/common/logger/ErrorTypeAwareLogger;
       8: return
}
