Compiled from "AbstractEndpoint.java"
public abstract class org.apache.dubbo.remoting.transport.AbstractEndpoint extends org.apache.dubbo.remoting.transport.AbstractPeer implements org.apache.dubbo.common.Resetable {
  private static final org.apache.dubbo.common.logger.ErrorTypeAwareLogger logger;

  private org.apache.dubbo.remoting.Codec2 codec;

  private int connectTimeout;

  public org.apache.dubbo.remoting.transport.AbstractEndpoint(org.apache.dubbo.common.URL, org.apache.dubbo.remoting.ChannelHandler);
    Code:
       0: aload_0
       1: aload_1
       2: aload_2
       3: invokespecial #2                  // Method org/apache/dubbo/remoting/transport/AbstractPeer."<init>":(Lorg/apache/dubbo/common/URL;Lorg/apache/dubbo/remoting/ChannelHandler;)V
       6: aload_0
       7: aload_1
       8: invokestatic  #3                  // Method getChannelCodec:(Lorg/apache/dubbo/common/URL;)Lorg/apache/dubbo/remoting/Codec2;
      11: putfield      #4                  // Field codec:Lorg/apache/dubbo/remoting/Codec2;
      14: aload_0
      15: aload_1
      16: ldc           #6                  // String connect.timeout
      18: sipush        3000
      21: invokevirtual #7                  // Method org/apache/dubbo/common/URL.getPositiveParameter:(Ljava/lang/String;I)I
      24: putfield      #8                  // Field connectTimeout:I
      27: return

  protected static org.apache.dubbo.remoting.Codec2 getChannelCodec(org.apache.dubbo.common.URL);
    Code:
       0: aload_0
       1: ldc           #9                  // String codec
       3: invokevirtual #10                 // Method org/apache/dubbo/common/URL.getParameter:(Ljava/lang/String;)Ljava/lang/String;
       6: astore_1
       7: aload_1
       8: invokestatic  #11                 // Method org/apache/dubbo/common/utils/StringUtils.isEmpty:(Ljava/lang/String;)Z
      11: ifeq          19
      14: aload_0
      15: invokevirtual #12                 // Method org/apache/dubbo/common/URL.getProtocol:()Ljava/lang/String;
      18: astore_1
      19: aload_0
      20: invokevirtual #13                 // Method org/apache/dubbo/common/URL.getScopeModel:()Lorg/apache/dubbo/rpc/model/ScopeModel;
      23: invokestatic  #14                 // Method org/apache/dubbo/rpc/model/ScopeModelUtil.getFrameworkModel:(Lorg/apache/dubbo/rpc/model/ScopeModel;)Lorg/apache/dubbo/rpc/model/FrameworkModel;
      26: astore_2
      27: aload_2
      28: ldc           #15                 // class org/apache/dubbo/remoting/Codec2
      30: invokevirtual #16                 // Method org/apache/dubbo/rpc/model/FrameworkModel.getExtensionLoader:(Ljava/lang/Class;)Lorg/apache/dubbo/common/extension/ExtensionLoader;
      33: aload_1
      34: invokevirtual #17                 // Method org/apache/dubbo/common/extension/ExtensionLoader.hasExtension:(Ljava/lang/String;)Z
      37: ifeq          54
      40: aload_2
      41: ldc           #15                 // class org/apache/dubbo/remoting/Codec2
      43: invokevirtual #16                 // Method org/apache/dubbo/rpc/model/FrameworkModel.getExtensionLoader:(Ljava/lang/Class;)Lorg/apache/dubbo/common/extension/ExtensionLoader;
      46: aload_1
      47: invokevirtual #18                 // Method org/apache/dubbo/common/extension/ExtensionLoader.getExtension:(Ljava/lang/String;)Ljava/lang/Object;
      50: checkcast     #15                 // class org/apache/dubbo/remoting/Codec2
      53: areturn
      54: aload_2
      55: ldc           #19                 // class org/apache/dubbo/remoting/Codec
      57: invokevirtual #16                 // Method org/apache/dubbo/rpc/model/FrameworkModel.getExtensionLoader:(Ljava/lang/Class;)Lorg/apache/dubbo/common/extension/ExtensionLoader;
      60: aload_1
      61: invokevirtual #17                 // Method org/apache/dubbo/common/extension/ExtensionLoader.hasExtension:(Ljava/lang/String;)Z
      64: ifeq          88
      67: new           #20                 // class org/apache/dubbo/remoting/transport/codec/CodecAdapter
      70: dup
      71: aload_2
      72: ldc           #19                 // class org/apache/dubbo/remoting/Codec
      74: invokevirtual #16                 // Method org/apache/dubbo/rpc/model/FrameworkModel.getExtensionLoader:(Ljava/lang/Class;)Lorg/apache/dubbo/common/extension/ExtensionLoader;
      77: aload_1
      78: invokevirtual #18                 // Method org/apache/dubbo/common/extension/ExtensionLoader.getExtension:(Ljava/lang/String;)Ljava/lang/Object;
      81: checkcast     #19                 // class org/apache/dubbo/remoting/Codec
      84: invokespecial #21                 // Method org/apache/dubbo/remoting/transport/codec/CodecAdapter."<init>":(Lorg/apache/dubbo/remoting/Codec;)V
      87: areturn
      88: aload_2
      89: ldc           #15                 // class org/apache/dubbo/remoting/Codec2
      91: invokevirtual #16                 // Method org/apache/dubbo/rpc/model/FrameworkModel.getExtensionLoader:(Ljava/lang/Class;)Lorg/apache/dubbo/common/extension/ExtensionLoader;
      94: ldc           #22                 // String default
      96: invokevirtual #18                 // Method org/apache/dubbo/common/extension/ExtensionLoader.getExtension:(Ljava/lang/String;)Ljava/lang/Object;
      99: checkcast     #15                 // class org/apache/dubbo/remoting/Codec2
     102: areturn

  public void reset(org.apache.dubbo.common.URL);
    Code:
       0: aload_0
       1: invokevirtual #23                 // Method isClosed:()Z
       4: ifeq          46
       7: new           #24                 // class java/lang/IllegalStateException
      10: dup
      11: new           #25                 // class java/lang/StringBuilder
      14: dup
      15: invokespecial #26                 // Method java/lang/StringBuilder."<init>":()V
      18: ldc           #27                 // String Failed to reset parameters
      20: invokevirtual #28                 // Method java/lang/StringBuilder.append:(Ljava/lang/String;)Ljava/lang/StringBuilder;
      23: aload_1
      24: invokevirtual #29                 // Method java/lang/StringBuilder.append:(Ljava/lang/Object;)Ljava/lang/StringBuilder;
      27: ldc           #30                 // String , cause: Channel closed. channel:
      29: invokevirtual #28                 // Method java/lang/StringBuilder.append:(Ljava/lang/String;)Ljava/lang/StringBuilder;
      32: aload_0
      33: invokevirtual #31                 // Method getLocalAddress:()Ljava/net/InetSocketAddress;
      36: invokevirtual #29                 // Method java/lang/StringBuilder.append:(Ljava/lang/Object;)Ljava/lang/StringBuilder;
      39: invokevirtual #32                 // Method java/lang/StringBuilder.toString:()Ljava/lang/String;
      42: invokespecial #33                 // Method java/lang/IllegalStateException."<init>":(Ljava/lang/String;)V
      45: athrow
      46: aload_1
      47: ldc           #6                  // String connect.timeout
      49: invokevirtual #34                 // Method org/apache/dubbo/common/URL.hasParameter:(Ljava/lang/String;)Z
      52: ifeq          72
      55: aload_1
      56: ldc           #6                  // String connect.timeout
      58: iconst_0
      59: invokevirtual #35                 // Method org/apache/dubbo/common/URL.getParameter:(Ljava/lang/String;I)I
      62: istore_2
      63: iload_2
      64: ifle          72
      67: aload_0
      68: iload_2
      69: putfield      #8                  // Field connectTimeout:I
      72: goto          95
      75: astore_2
      76: getstatic     #37                 // Field logger:Lorg/apache/dubbo/common/logger/ErrorTypeAwareLogger;
      79: ldc           #38                 // String 99-0
      81: ldc           #39                 // String
      83: ldc           #39                 // String
      85: aload_2
      86: invokevirtual #40                 // Method java/lang/Throwable.getMessage:()Ljava/lang/String;
      89: aload_2
      90: invokeinterface #41,  6           // InterfaceMethod org/apache/dubbo/common/logger/ErrorTypeAwareLogger.error:(Ljava/lang/String;Ljava/lang/String;Ljava/lang/String;Ljava/lang/String;Ljava/lang/Throwable;)V
      95: aload_1
      96: ldc           #9                  // String codec
      98: invokevirtual #34                 // Method org/apache/dubbo/common/URL.hasParameter:(Ljava/lang/String;)Z
     101: ifeq          112
     104: aload_0
     105: aload_1
     106: invokestatic  #3                  // Method getChannelCodec:(Lorg/apache/dubbo/common/URL;)Lorg/apache/dubbo/remoting/Codec2;
     109: putfield      #4                  // Field codec:Lorg/apache/dubbo/remoting/Codec2;
     112: goto          135
     115: astore_2
     116: getstatic     #37                 // Field logger:Lorg/apache/dubbo/common/logger/ErrorTypeAwareLogger;
     119: ldc           #38                 // String 99-0
     121: ldc           #42                 // String unknown error in remoting module
     123: ldc           #39                 // String
     125: aload_2
     126: invokevirtual #40                 // Method java/lang/Throwable.getMessage:()Ljava/lang/String;
     129: aload_2
     130: invokeinterface #41,  6           // InterfaceMethod org/apache/dubbo/common/logger/ErrorTypeAwareLogger.error:(Ljava/lang/String;Ljava/lang/String;Ljava/lang/String;Ljava/lang/String;Ljava/lang/Throwable;)V
     135: return
    Exception table:
       from    to  target type
          46    72    75   Class java/lang/Throwable
          95   112   115   Class java/lang/Throwable

  public void reset(org.apache.dubbo.common.Parameters);
    Code:
       0: aload_0
       1: aload_0
       2: invokevirtual #43                 // Method getUrl:()Lorg/apache/dubbo/common/URL;
       5: aload_1
       6: invokevirtual #44                 // Method org/apache/dubbo/common/Parameters.getParameters:()Ljava/util/Map;
       9: invokevirtual #45                 // Method org/apache/dubbo/common/URL.addParameters:(Ljava/util/Map;)Lorg/apache/dubbo/common/URL;
      12: invokevirtual #46                 // Method reset:(Lorg/apache/dubbo/common/URL;)V
      15: return

  protected org.apache.dubbo.remoting.Codec2 getCodec();
    Code:
       0: aload_0
       1: getfield      #4                  // Field codec:Lorg/apache/dubbo/remoting/Codec2;
       4: areturn

  protected int getConnectTimeout();
    Code:
       0: aload_0
       1: getfield      #8                  // Field connectTimeout:I
       4: ireturn

  static {};
    Code:
       0: ldc           #47                 // class org/apache/dubbo/remoting/transport/AbstractEndpoint
       2: invokestatic  #48                 // Method org/apache/dubbo/common/logger/LoggerFactory.getErrorTypeAwareLogger:(Ljava/lang/Class;)Lorg/apache/dubbo/common/logger/ErrorTypeAwareLogger;
       5: putstatic     #37                 // Field logger:Lorg/apache/dubbo/common/logger/ErrorTypeAwareLogger;
       8: return
}
