Compiled from "AbstractChannel.java"
public abstract class org.apache.dubbo.remoting.transport.AbstractChannel extends org.apache.dubbo.remoting.transport.AbstractPeer implements org.apache.dubbo.remoting.Channel {
  public org.apache.dubbo.remoting.transport.AbstractChannel(org.apache.dubbo.common.URL, org.apache.dubbo.remoting.ChannelHandler);
    Code:
       0: aload_0
       1: aload_1
       2: aload_2
       3: invokespecial #1                  // Method org/apache/dubbo/remoting/transport/AbstractPeer."<init>":(Lorg/apache/dubbo/common/URL;Lorg/apache/dubbo/remoting/ChannelHandler;)V
       6: return

  public void send(java.lang.Object, boolean) throws org.apache.dubbo.remoting.RemotingException;
    Code:
       0: aload_0
       1: invokevirtual #2                  // Method isClosed:()Z
       4: ifeq          86
       7: new           #3                  // class org/apache/dubbo/remoting/RemotingException
      10: dup
      11: aload_0
      12: new           #4                  // class java/lang/StringBuilder
      15: dup
      16: invokespecial #5                  // Method java/lang/StringBuilder."<init>":()V
      19: ldc           #6                  // String Failed to send message
      21: invokevirtual #7                  // Method java/lang/StringBuilder.append:(Ljava/lang/String;)Ljava/lang/StringBuilder;
      24: aload_1
      25: ifnonnull     33
      28: ldc           #8                  // String
      30: goto          40
      33: aload_1
      34: invokevirtual #9                  // Method java/lang/Object.getClass:()Ljava/lang/Class;
      37: invokevirtual #10                 // Method java/lang/Class.getName:()Ljava/lang/String;
      40: invokevirtual #7                  // Method java/lang/StringBuilder.append:(Ljava/lang/String;)Ljava/lang/StringBuilder;
      43: ldc           #11                 // String :
      45: invokevirtual #7                  // Method java/lang/StringBuilder.append:(Ljava/lang/String;)Ljava/lang/StringBuilder;
      48: aload_1
      49: invokestatic  #12                 // Method org/apache/dubbo/remoting/utils/PayloadDropper.getRequestWithoutData:(Ljava/lang/Object;)Ljava/lang/Object;
      52: invokevirtual #13                 // Method java/lang/StringBuilder.append:(Ljava/lang/Object;)Ljava/lang/StringBuilder;
      55: ldc           #14                 // String , cause: Channel closed. channel:
      57: invokevirtual #7                  // Method java/lang/StringBuilder.append:(Ljava/lang/String;)Ljava/lang/StringBuilder;
      60: aload_0
      61: invokevirtual #15                 // Method getLocalAddress:()Ljava/net/InetSocketAddress;
      64: invokevirtual #13                 // Method java/lang/StringBuilder.append:(Ljava/lang/Object;)Ljava/lang/StringBuilder;
      67: ldc           #16                 // String  ->
      69: invokevirtual #7                  // Method java/lang/StringBuilder.append:(Ljava/lang/String;)Ljava/lang/StringBuilder;
      72: aload_0
      73: invokevirtual #17                 // Method getRemoteAddress:()Ljava/net/InetSocketAddress;
      76: invokevirtual #13                 // Method java/lang/StringBuilder.append:(Ljava/lang/Object;)Ljava/lang/StringBuilder;
      79: invokevirtual #18                 // Method java/lang/StringBuilder.toString:()Ljava/lang/String;
      82: invokespecial #19                 // Method org/apache/dubbo/remoting/RemotingException."<init>":(Lorg/apache/dubbo/remoting/Channel;Ljava/lang/String;)V
      85: athrow
      86: return

  public java.lang.String toString();
    Code:
       0: new           #4                  // class java/lang/StringBuilder
       3: dup
       4: invokespecial #5                  // Method java/lang/StringBuilder."<init>":()V
       7: aload_0
       8: invokevirtual #15                 // Method getLocalAddress:()Ljava/net/InetSocketAddress;
      11: invokevirtual #13                 // Method java/lang/StringBuilder.append:(Ljava/lang/Object;)Ljava/lang/StringBuilder;
      14: ldc           #16                 // String  ->
      16: invokevirtual #7                  // Method java/lang/StringBuilder.append:(Ljava/lang/String;)Ljava/lang/StringBuilder;
      19: aload_0
      20: invokevirtual #17                 // Method getRemoteAddress:()Ljava/net/InetSocketAddress;
      23: invokevirtual #13                 // Method java/lang/StringBuilder.append:(Ljava/lang/Object;)Ljava/lang/StringBuilder;
      26: invokevirtual #18                 // Method java/lang/StringBuilder.toString:()Ljava/lang/String;
      29: areturn

  protected void setUrl(org.apache.dubbo.common.URL);
    Code:
       0: aload_0
       1: aload_1
       2: invokespecial #20                 // Method org/apache/dubbo/remoting/transport/AbstractPeer.setUrl:(Lorg/apache/dubbo/common/URL;)V
       5: return
}
