Compiled from "ChannelHandlerDispatcher.java"
public class org.apache.dubbo.remoting.transport.ChannelHandlerDispatcher implements org.apache.dubbo.remoting.ChannelHandler {
  private static final org.apache.dubbo.common.logger.ErrorTypeAwareLogger logger;

  private final java.util.Collection<org.apache.dubbo.remoting.ChannelHandler> channelHandlers;

  public org.apache.dubbo.remoting.transport.ChannelHandlerDispatcher();
    Code:
       0: aload_0
       1: invokespecial #2                  // Method java/lang/Object."<init>":()V
       4: aload_0
       5: new           #3                  // class java/util/concurrent/CopyOnWriteArraySet
       8: dup
       9: invokespecial #4                  // Method java/util/concurrent/CopyOnWriteArraySet."<init>":()V
      12: putfield      #5                  // Field channelHandlers:Ljava/util/Collection;
      15: return

  public org.apache.dubbo.remoting.transport.ChannelHandlerDispatcher(org.apache.dubbo.remoting.ChannelHandler...);
    Code:
       0: aload_0
       1: aload_1
       2: ifnonnull     9
       5: aconst_null
       6: goto          13
       9: aload_1
      10: invokestatic  #6                  // Method java/util/Arrays.asList:([Ljava/lang/Object;)Ljava/util/List;
      13: invokespecial #7                  // Method "<init>":(Ljava/util/Collection;)V
      16: return

  public org.apache.dubbo.remoting.transport.ChannelHandlerDispatcher(java.util.Collection<org.apache.dubbo.remoting.ChannelHandler>);
    Code:
       0: aload_0
       1: invokespecial #2                  // Method java/lang/Object."<init>":()V
       4: aload_0
       5: new           #3                  // class java/util/concurrent/CopyOnWriteArraySet
       8: dup
       9: invokespecial #4                  // Method java/util/concurrent/CopyOnWriteArraySet."<init>":()V
      12: putfield      #5                  // Field channelHandlers:Ljava/util/Collection;
      15: aload_1
      16: invokestatic  #8                  // Method org/apache/dubbo/common/utils/CollectionUtils.isNotEmpty:(Ljava/util/Collection;)Z
      19: ifeq          59
      22: aload_0
      23: getfield      #5                  // Field channelHandlers:Ljava/util/Collection;
      26: aload_1
      27: invokeinterface #9,  1            // InterfaceMethod java/util/Collection.stream:()Ljava/util/stream/Stream;
      32: invokedynamic #10,  0             // InvokeDynamic #0:test:()Ljava/util/function/Predicate;
      37: invokeinterface #11,  2           // InterfaceMethod java/util/stream/Stream.filter:(Ljava/util/function/Predicate;)Ljava/util/stream/Stream;
      42: invokestatic  #12                 // Method java/util/stream/Collectors.toSet:()Ljava/util/stream/Collector;
      45: invokeinterface #13,  2           // InterfaceMethod java/util/stream/Stream.collect:(Ljava/util/stream/Collector;)Ljava/lang/Object;
      50: checkcast     #14                 // class java/util/Collection
      53: invokeinterface #15,  2           // InterfaceMethod java/util/Collection.addAll:(Ljava/util/Collection;)Z
      58: pop
      59: return

  public java.util.Collection<org.apache.dubbo.remoting.ChannelHandler> getChannelHandlers();
    Code:
       0: aload_0
       1: getfield      #5                  // Field channelHandlers:Ljava/util/Collection;
       4: areturn

  public org.apache.dubbo.remoting.transport.ChannelHandlerDispatcher addChannelHandler(org.apache.dubbo.remoting.ChannelHandler);
    Code:
       0: aload_0
       1: getfield      #5                  // Field channelHandlers:Ljava/util/Collection;
       4: aload_1
       5: invokeinterface #16,  2           // InterfaceMethod java/util/Collection.add:(Ljava/lang/Object;)Z
      10: pop
      11: aload_0
      12: areturn

  public org.apache.dubbo.remoting.transport.ChannelHandlerDispatcher removeChannelHandler(org.apache.dubbo.remoting.ChannelHandler);
    Code:
       0: aload_0
       1: getfield      #5                  // Field channelHandlers:Ljava/util/Collection;
       4: aload_1
       5: invokeinterface #17,  2           // InterfaceMethod java/util/Collection.remove:(Ljava/lang/Object;)Z
      10: pop
      11: aload_0
      12: areturn

  public void connected(org.apache.dubbo.remoting.Channel);
    Code:
       0: aload_0
       1: getfield      #5                  // Field channelHandlers:Ljava/util/Collection;
       4: invokeinterface #18,  1           // InterfaceMethod java/util/Collection.iterator:()Ljava/util/Iterator;
       9: astore_2
      10: aload_2
      11: invokeinterface #19,  1           // InterfaceMethod java/util/Iterator.hasNext:()Z
      16: ifeq          65
      19: aload_2
      20: invokeinterface #20,  1           // InterfaceMethod java/util/Iterator.next:()Ljava/lang/Object;
      25: checkcast     #21                 // class org/apache/dubbo/remoting/ChannelHandler
      28: astore_3
      29: aload_3
      30: aload_1
      31: invokeinterface #22,  2           // InterfaceMethod org/apache/dubbo/remoting/ChannelHandler.connected:(Lorg/apache/dubbo/remoting/Channel;)V
      36: goto          62
      39: astore        4
      41: getstatic     #24                 // Field logger:Lorg/apache/dubbo/common/logger/ErrorTypeAwareLogger;
      44: ldc           #25                 // String 99-0
      46: ldc           #26                 // String unknown error in remoting module
      48: ldc           #27                 // String
      50: aload         4
      52: invokevirtual #28                 // Method java/lang/Throwable.getMessage:()Ljava/lang/String;
      55: aload         4
      57: invokeinterface #29,  6           // InterfaceMethod org/apache/dubbo/common/logger/ErrorTypeAwareLogger.error:(Ljava/lang/String;Ljava/lang/String;Ljava/lang/String;Ljava/lang/String;Ljava/lang/Throwable;)V
      62: goto          10
      65: return
    Exception table:
       from    to  target type
          29    36    39   Class java/lang/Throwable

  public void disconnected(org.apache.dubbo.remoting.Channel);
    Code:
       0: aload_0
       1: getfield      #5                  // Field channelHandlers:Ljava/util/Collection;
       4: invokeinterface #18,  1           // InterfaceMethod java/util/Collection.iterator:()Ljava/util/Iterator;
       9: astore_2
      10: aload_2
      11: invokeinterface #19,  1           // InterfaceMethod java/util/Iterator.hasNext:()Z
      16: ifeq          65
      19: aload_2
      20: invokeinterface #20,  1           // InterfaceMethod java/util/Iterator.next:()Ljava/lang/Object;
      25: checkcast     #21                 // class org/apache/dubbo/remoting/ChannelHandler
      28: astore_3
      29: aload_3
      30: aload_1
      31: invokeinterface #30,  2           // InterfaceMethod org/apache/dubbo/remoting/ChannelHandler.disconnected:(Lorg/apache/dubbo/remoting/Channel;)V
      36: goto          62
      39: astore        4
      41: getstatic     #24                 // Field logger:Lorg/apache/dubbo/common/logger/ErrorTypeAwareLogger;
      44: ldc           #25                 // String 99-0
      46: ldc           #26                 // String unknown error in remoting module
      48: ldc           #27                 // String
      50: aload         4
      52: invokevirtual #28                 // Method java/lang/Throwable.getMessage:()Ljava/lang/String;
      55: aload         4
      57: invokeinterface #29,  6           // InterfaceMethod org/apache/dubbo/common/logger/ErrorTypeAwareLogger.error:(Ljava/lang/String;Ljava/lang/String;Ljava/lang/String;Ljava/lang/String;Ljava/lang/Throwable;)V
      62: goto          10
      65: return
    Exception table:
       from    to  target type
          29    36    39   Class java/lang/Throwable

  public void sent(org.apache.dubbo.remoting.Channel, java.lang.Object);
    Code:
       0: aload_0
       1: getfield      #5                  // Field channelHandlers:Ljava/util/Collection;
       4: invokeinterface #18,  1           // InterfaceMethod java/util/Collection.iterator:()Ljava/util/Iterator;
       9: astore_3
      10: aload_3
      11: invokeinterface #19,  1           // InterfaceMethod java/util/Iterator.hasNext:()Z
      16: ifeq          68
      19: aload_3
      20: invokeinterface #20,  1           // InterfaceMethod java/util/Iterator.next:()Ljava/lang/Object;
      25: checkcast     #21                 // class org/apache/dubbo/remoting/ChannelHandler
      28: astore        4
      30: aload         4
      32: aload_1
      33: aload_2
      34: invokeinterface #31,  3           // InterfaceMethod org/apache/dubbo/remoting/ChannelHandler.sent:(Lorg/apache/dubbo/remoting/Channel;Ljava/lang/Object;)V
      39: goto          65
      42: astore        5
      44: getstatic     #24                 // Field logger:Lorg/apache/dubbo/common/logger/ErrorTypeAwareLogger;
      47: ldc           #25                 // String 99-0
      49: ldc           #26                 // String unknown error in remoting module
      51: ldc           #27                 // String
      53: aload         5
      55: invokevirtual #28                 // Method java/lang/Throwable.getMessage:()Ljava/lang/String;
      58: aload         5
      60: invokeinterface #29,  6           // InterfaceMethod org/apache/dubbo/common/logger/ErrorTypeAwareLogger.error:(Ljava/lang/String;Ljava/lang/String;Ljava/lang/String;Ljava/lang/String;Ljava/lang/Throwable;)V
      65: goto          10
      68: return
    Exception table:
       from    to  target type
          30    39    42   Class java/lang/Throwable

  public void received(org.apache.dubbo.remoting.Channel, java.lang.Object);
    Code:
       0: aload_0
       1: getfield      #5                  // Field channelHandlers:Ljava/util/Collection;
       4: invokeinterface #18,  1           // InterfaceMethod java/util/Collection.iterator:()Ljava/util/Iterator;
       9: astore_3
      10: aload_3
      11: invokeinterface #19,  1           // InterfaceMethod java/util/Iterator.hasNext:()Z
      16: ifeq          68
      19: aload_3
      20: invokeinterface #20,  1           // InterfaceMethod java/util/Iterator.next:()Ljava/lang/Object;
      25: checkcast     #21                 // class org/apache/dubbo/remoting/ChannelHandler
      28: astore        4
      30: aload         4
      32: aload_1
      33: aload_2
      34: invokeinterface #32,  3           // InterfaceMethod org/apache/dubbo/remoting/ChannelHandler.received:(Lorg/apache/dubbo/remoting/Channel;Ljava/lang/Object;)V
      39: goto          65
      42: astore        5
      44: getstatic     #24                 // Field logger:Lorg/apache/dubbo/common/logger/ErrorTypeAwareLogger;
      47: ldc           #25                 // String 99-0
      49: ldc           #26                 // String unknown error in remoting module
      51: ldc           #27                 // String
      53: aload         5
      55: invokevirtual #28                 // Method java/lang/Throwable.getMessage:()Ljava/lang/String;
      58: aload         5
      60: invokeinterface #29,  6           // InterfaceMethod org/apache/dubbo/common/logger/ErrorTypeAwareLogger.error:(Ljava/lang/String;Ljava/lang/String;Ljava/lang/String;Ljava/lang/String;Ljava/lang/Throwable;)V
      65: goto          10
      68: return
    Exception table:
       from    to  target type
          30    39    42   Class java/lang/Throwable

  public void caught(org.apache.dubbo.remoting.Channel, java.lang.Throwable);
    Code:
       0: aload_0
       1: getfield      #5                  // Field channelHandlers:Ljava/util/Collection;
       4: invokeinterface #18,  1           // InterfaceMethod java/util/Collection.iterator:()Ljava/util/Iterator;
       9: astore_3
      10: aload_3
      11: invokeinterface #19,  1           // InterfaceMethod java/util/Iterator.hasNext:()Z
      16: ifeq          68
      19: aload_3
      20: invokeinterface #20,  1           // InterfaceMethod java/util/Iterator.next:()Ljava/lang/Object;
      25: checkcast     #21                 // class org/apache/dubbo/remoting/ChannelHandler
      28: astore        4
      30: aload         4
      32: aload_1
      33: aload_2
      34: invokeinterface #33,  3           // InterfaceMethod org/apache/dubbo/remoting/ChannelHandler.caught:(Lorg/apache/dubbo/remoting/Channel;Ljava/lang/Throwable;)V
      39: goto          65
      42: astore        5
      44: getstatic     #24                 // Field logger:Lorg/apache/dubbo/common/logger/ErrorTypeAwareLogger;
      47: ldc           #25                 // String 99-0
      49: ldc           #26                 // String unknown error in remoting module
      51: ldc           #27                 // String
      53: aload         5
      55: invokevirtual #28                 // Method java/lang/Throwable.getMessage:()Ljava/lang/String;
      58: aload         5
      60: invokeinterface #29,  6           // InterfaceMethod org/apache/dubbo/common/logger/ErrorTypeAwareLogger.error:(Ljava/lang/String;Ljava/lang/String;Ljava/lang/String;Ljava/lang/String;Ljava/lang/Throwable;)V
      65: goto          10
      68: return
    Exception table:
       from    to  target type
          30    39    42   Class java/lang/Throwable

  static {};
    Code:
       0: ldc           #34                 // class org/apache/dubbo/remoting/transport/ChannelHandlerDispatcher
       2: invokestatic  #35                 // Method org/apache/dubbo/common/logger/LoggerFactory.getErrorTypeAwareLogger:(Ljava/lang/Class;)Lorg/apache/dubbo/common/logger/ErrorTypeAwareLogger;
       5: putstatic     #24                 // Field logger:Lorg/apache/dubbo/common/logger/ErrorTypeAwareLogger;
       8: return
}
