Compiled from "ChannelDelegate.java"
public class org.apache.dubbo.remoting.transport.ChannelDelegate implements org.apache.dubbo.remoting.Channel {
  private transient org.apache.dubbo.remoting.Channel channel;

  public org.apache.dubbo.remoting.transport.ChannelDelegate();
    Code:
       0: aload_0
       1: invokespecial #1                  // Method java/lang/Object."<init>":()V
       4: return

  public org.apache.dubbo.remoting.transport.ChannelDelegate(org.apache.dubbo.remoting.Channel);
    Code:
       0: aload_0
       1: invokespecial #1                  // Method java/lang/Object."<init>":()V
       4: aload_0
       5: aload_1
       6: invokevirtual #2                  // Method setChannel:(Lorg/apache/dubbo/remoting/Channel;)V
       9: return

  public org.apache.dubbo.remoting.Channel getChannel();
    Code:
       0: aload_0
       1: getfield      #3                  // Field channel:Lorg/apache/dubbo/remoting/Channel;
       4: areturn

  public void setChannel(org.apache.dubbo.remoting.Channel);
    Code:
       0: aload_1
       1: ifnonnull     14
       4: new           #4                  // class java/lang/IllegalArgumentException
       7: dup
       8: ldc           #5                  // String channel == null
      10: invokespecial #6                  // Method java/lang/IllegalArgumentException."<init>":(Ljava/lang/String;)V
      13: athrow
      14: aload_0
      15: aload_1
      16: putfield      #3                  // Field channel:Lorg/apache/dubbo/remoting/Channel;
      19: return

  public org.apache.dubbo.common.URL getUrl();
    Code:
       0: aload_0
       1: getfield      #3                  // Field channel:Lorg/apache/dubbo/remoting/Channel;
       4: invokeinterface #7,  1            // InterfaceMethod org/apache/dubbo/remoting/Channel.getUrl:()Lorg/apache/dubbo/common/URL;
       9: areturn

  public java.net.InetSocketAddress getRemoteAddress();
    Code:
       0: aload_0
       1: getfield      #3                  // Field channel:Lorg/apache/dubbo/remoting/Channel;
       4: invokeinterface #8,  1            // InterfaceMethod org/apache/dubbo/remoting/Channel.getRemoteAddress:()Ljava/net/InetSocketAddress;
       9: areturn

  public org.apache.dubbo.remoting.ChannelHandler getChannelHandler();
    Code:
       0: aload_0
       1: getfield      #3                  // Field channel:Lorg/apache/dubbo/remoting/Channel;
       4: invokeinterface #9,  1            // InterfaceMethod org/apache/dubbo/remoting/Channel.getChannelHandler:()Lorg/apache/dubbo/remoting/ChannelHandler;
       9: areturn

  public boolean isConnected();
    Code:
       0: aload_0
       1: getfield      #3                  // Field channel:Lorg/apache/dubbo/remoting/Channel;
       4: invokeinterface #10,  1           // InterfaceMethod org/apache/dubbo/remoting/Channel.isConnected:()Z
       9: ireturn

  public java.net.InetSocketAddress getLocalAddress();
    Code:
       0: aload_0
       1: getfield      #3                  // Field channel:Lorg/apache/dubbo/remoting/Channel;
       4: invokeinterface #11,  1           // InterfaceMethod org/apache/dubbo/remoting/Channel.getLocalAddress:()Ljava/net/InetSocketAddress;
       9: areturn

  public boolean hasAttribute(java.lang.String);
    Code:
       0: aload_0
       1: getfield      #3                  // Field channel:Lorg/apache/dubbo/remoting/Channel;
       4: aload_1
       5: invokeinterface #12,  2           // InterfaceMethod org/apache/dubbo/remoting/Channel.hasAttribute:(Ljava/lang/String;)Z
      10: ireturn

  public void send(java.lang.Object) throws org.apache.dubbo.remoting.RemotingException;
    Code:
       0: aload_0
       1: getfield      #3                  // Field channel:Lorg/apache/dubbo/remoting/Channel;
       4: aload_1
       5: invokeinterface #13,  2           // InterfaceMethod org/apache/dubbo/remoting/Channel.send:(Ljava/lang/Object;)V
      10: return

  public java.lang.Object getAttribute(java.lang.String);
    Code:
       0: aload_0
       1: getfield      #3                  // Field channel:Lorg/apache/dubbo/remoting/Channel;
       4: aload_1
       5: invokeinterface #14,  2           // InterfaceMethod org/apache/dubbo/remoting/Channel.getAttribute:(Ljava/lang/String;)Ljava/lang/Object;
      10: areturn

  public void setAttribute(java.lang.String, java.lang.Object);
    Code:
       0: aload_0
       1: getfield      #3                  // Field channel:Lorg/apache/dubbo/remoting/Channel;
       4: aload_1
       5: aload_2
       6: invokeinterface #15,  3           // InterfaceMethod org/apache/dubbo/remoting/Channel.setAttribute:(Ljava/lang/String;Ljava/lang/Object;)V
      11: return

  public void send(java.lang.Object, boolean) throws org.apache.dubbo.remoting.RemotingException;
    Code:
       0: aload_0
       1: getfield      #3                  // Field channel:Lorg/apache/dubbo/remoting/Channel;
       4: aload_1
       5: iload_2
       6: invokeinterface #16,  3           // InterfaceMethod org/apache/dubbo/remoting/Channel.send:(Ljava/lang/Object;Z)V
      11: return

  public void removeAttribute(java.lang.String);
    Code:
       0: aload_0
       1: getfield      #3                  // Field channel:Lorg/apache/dubbo/remoting/Channel;
       4: aload_1
       5: invokeinterface #17,  2           // InterfaceMethod org/apache/dubbo/remoting/Channel.removeAttribute:(Ljava/lang/String;)V
      10: return

  public void close();
    Code:
       0: aload_0
       1: getfield      #3                  // Field channel:Lorg/apache/dubbo/remoting/Channel;
       4: invokeinterface #18,  1           // InterfaceMethod org/apache/dubbo/remoting/Channel.close:()V
       9: return

  public void close(int);
    Code:
       0: aload_0
       1: getfield      #3                  // Field channel:Lorg/apache/dubbo/remoting/Channel;
       4: iload_1
       5: invokeinterface #19,  2           // InterfaceMethod org/apache/dubbo/remoting/Channel.close:(I)V
      10: return

  public void startClose();
    Code:
       0: aload_0
       1: getfield      #3                  // Field channel:Lorg/apache/dubbo/remoting/Channel;
       4: invokeinterface #20,  1           // InterfaceMethod org/apache/dubbo/remoting/Channel.startClose:()V
       9: return

  public boolean isClosed();
    Code:
       0: aload_0
       1: getfield      #3                  // Field channel:Lorg/apache/dubbo/remoting/Channel;
       4: invokeinterface #21,  1           // InterfaceMethod org/apache/dubbo/remoting/Channel.isClosed:()Z
       9: ireturn
}
