Compiled from "ClientDelegate.java"
public class org.apache.dubbo.remoting.transport.ClientDelegate implements org.apache.dubbo.remoting.Client {
  private transient org.apache.dubbo.remoting.Client client;

  public org.apache.dubbo.remoting.transport.ClientDelegate();
    Code:
       0: aload_0
       1: invokespecial #1                  // Method java/lang/Object."<init>":()V
       4: return

  public org.apache.dubbo.remoting.transport.ClientDelegate(org.apache.dubbo.remoting.Client);
    Code:
       0: aload_0
       1: invokespecial #1                  // Method java/lang/Object."<init>":()V
       4: aload_0
       5: aload_1
       6: invokevirtual #2                  // Method setClient:(Lorg/apache/dubbo/remoting/Client;)V
       9: return

  public org.apache.dubbo.remoting.Client getClient();
    Code:
       0: aload_0
       1: getfield      #3                  // Field client:Lorg/apache/dubbo/remoting/Client;
       4: areturn

  public void setClient(org.apache.dubbo.remoting.Client);
    Code:
       0: aload_1
       1: ifnonnull     14
       4: new           #4                  // class java/lang/IllegalArgumentException
       7: dup
       8: ldc           #5                  // String client == null
      10: invokespecial #6                  // Method java/lang/IllegalArgumentException."<init>":(Ljava/lang/String;)V
      13: athrow
      14: aload_0
      15: aload_1
      16: putfield      #3                  // Field client:Lorg/apache/dubbo/remoting/Client;
      19: return

  public void reset(org.apache.dubbo.common.URL);
    Code:
       0: aload_0
       1: getfield      #3                  // Field client:Lorg/apache/dubbo/remoting/Client;
       4: aload_1
       5: invokeinterface #7,  2            // InterfaceMethod org/apache/dubbo/remoting/Client.reset:(Lorg/apache/dubbo/common/URL;)V
      10: return

  public void reset(org.apache.dubbo.common.Parameters);
    Code:
       0: aload_0
       1: aload_0
       2: invokevirtual #8                  // Method getUrl:()Lorg/apache/dubbo/common/URL;
       5: aload_1
       6: invokevirtual #9                  // Method org/apache/dubbo/common/Parameters.getParameters:()Ljava/util/Map;
       9: invokevirtual #10                 // Method org/apache/dubbo/common/URL.addParameters:(Ljava/util/Map;)Lorg/apache/dubbo/common/URL;
      12: invokevirtual #11                 // Method reset:(Lorg/apache/dubbo/common/URL;)V
      15: return

  public org.apache.dubbo.common.URL getUrl();
    Code:
       0: aload_0
       1: getfield      #3                  // Field client:Lorg/apache/dubbo/remoting/Client;
       4: invokeinterface #12,  1           // InterfaceMethod org/apache/dubbo/remoting/Client.getUrl:()Lorg/apache/dubbo/common/URL;
       9: areturn

  public java.net.InetSocketAddress getRemoteAddress();
    Code:
       0: aload_0
       1: getfield      #3                  // Field client:Lorg/apache/dubbo/remoting/Client;
       4: invokeinterface #13,  1           // InterfaceMethod org/apache/dubbo/remoting/Client.getRemoteAddress:()Ljava/net/InetSocketAddress;
       9: areturn

  public void reconnect() throws org.apache.dubbo.remoting.RemotingException;
    Code:
       0: aload_0
       1: getfield      #3                  // Field client:Lorg/apache/dubbo/remoting/Client;
       4: invokeinterface #14,  1           // InterfaceMethod org/apache/dubbo/remoting/Client.reconnect:()V
       9: return

  public org.apache.dubbo.remoting.ChannelHandler getChannelHandler();
    Code:
       0: aload_0
       1: getfield      #3                  // Field client:Lorg/apache/dubbo/remoting/Client;
       4: invokeinterface #15,  1           // InterfaceMethod org/apache/dubbo/remoting/Client.getChannelHandler:()Lorg/apache/dubbo/remoting/ChannelHandler;
       9: areturn

  public boolean isConnected();
    Code:
       0: aload_0
       1: getfield      #3                  // Field client:Lorg/apache/dubbo/remoting/Client;
       4: invokeinterface #16,  1           // InterfaceMethod org/apache/dubbo/remoting/Client.isConnected:()Z
       9: ireturn

  public java.net.InetSocketAddress getLocalAddress();
    Code:
       0: aload_0
       1: getfield      #3                  // Field client:Lorg/apache/dubbo/remoting/Client;
       4: invokeinterface #17,  1           // InterfaceMethod org/apache/dubbo/remoting/Client.getLocalAddress:()Ljava/net/InetSocketAddress;
       9: areturn

  public boolean hasAttribute(java.lang.String);
    Code:
       0: aload_0
       1: getfield      #3                  // Field client:Lorg/apache/dubbo/remoting/Client;
       4: aload_1
       5: invokeinterface #18,  2           // InterfaceMethod org/apache/dubbo/remoting/Client.hasAttribute:(Ljava/lang/String;)Z
      10: ireturn

  public void send(java.lang.Object) throws org.apache.dubbo.remoting.RemotingException;
    Code:
       0: aload_0
       1: getfield      #3                  // Field client:Lorg/apache/dubbo/remoting/Client;
       4: aload_1
       5: invokeinterface #19,  2           // InterfaceMethod org/apache/dubbo/remoting/Client.send:(Ljava/lang/Object;)V
      10: return

  public java.lang.Object getAttribute(java.lang.String);
    Code:
       0: aload_0
       1: getfield      #3                  // Field client:Lorg/apache/dubbo/remoting/Client;
       4: aload_1
       5: invokeinterface #20,  2           // InterfaceMethod org/apache/dubbo/remoting/Client.getAttribute:(Ljava/lang/String;)Ljava/lang/Object;
      10: areturn

  public void setAttribute(java.lang.String, java.lang.Object);
    Code:
       0: aload_0
       1: getfield      #3                  // Field client:Lorg/apache/dubbo/remoting/Client;
       4: aload_1
       5: aload_2
       6: invokeinterface #21,  3           // InterfaceMethod org/apache/dubbo/remoting/Client.setAttribute:(Ljava/lang/String;Ljava/lang/Object;)V
      11: return

  public void send(java.lang.Object, boolean) throws org.apache.dubbo.remoting.RemotingException;
    Code:
       0: aload_0
       1: getfield      #3                  // Field client:Lorg/apache/dubbo/remoting/Client;
       4: aload_1
       5: iload_2
       6: invokeinterface #22,  3           // InterfaceMethod org/apache/dubbo/remoting/Client.send:(Ljava/lang/Object;Z)V
      11: return

  public void removeAttribute(java.lang.String);
    Code:
       0: aload_0
       1: getfield      #3                  // Field client:Lorg/apache/dubbo/remoting/Client;
       4: aload_1
       5: invokeinterface #23,  2           // InterfaceMethod org/apache/dubbo/remoting/Client.removeAttribute:(Ljava/lang/String;)V
      10: return

  public void close();
    Code:
       0: aload_0
       1: getfield      #3                  // Field client:Lorg/apache/dubbo/remoting/Client;
       4: invokeinterface #24,  1           // InterfaceMethod org/apache/dubbo/remoting/Client.close:()V
       9: return

  public void close(int);
    Code:
       0: aload_0
       1: getfield      #3                  // Field client:Lorg/apache/dubbo/remoting/Client;
       4: iload_1
       5: invokeinterface #25,  2           // InterfaceMethod org/apache/dubbo/remoting/Client.close:(I)V
      10: return

  public void startClose();
    Code:
       0: aload_0
       1: getfield      #3                  // Field client:Lorg/apache/dubbo/remoting/Client;
       4: invokeinterface #26,  1           // InterfaceMethod org/apache/dubbo/remoting/Client.startClose:()V
       9: return

  public boolean isClosed();
    Code:
       0: aload_0
       1: getfield      #3                  // Field client:Lorg/apache/dubbo/remoting/Client;
       4: invokeinterface #27,  1           // InterfaceMethod org/apache/dubbo/remoting/Client.isClosed:()Z
       9: ireturn
}
