Compiled from "CodecSupport.java"
public class org.apache.dubbo.remoting.transport.CodecSupport {
  private static final org.apache.dubbo.common.logger.ErrorTypeAwareLogger logger;

  private static java.util.Map<java.lang.Byte, org.apache.dubbo.common.serialize.Serialization> ID_SERIALIZATION_MAP;

  private static java.util.Map<java.lang.Byte, java.lang.String> ID_SERIALIZATIONNAME_MAP;

  private static java.util.Map<java.lang.String, java.lang.Byte> SERIALIZATIONNAME_ID_MAP;

  private static java.util.concurrent.ConcurrentMap<java.lang.Byte, byte[]> ID_NULLBYTES_MAP;

  private static final java.lang.ThreadLocal<byte[]> TL_BUFFER;

  private org.apache.dubbo.remoting.transport.CodecSupport();
    Code:
       0: aload_0
       1: invokespecial #2                  // Method java/lang/Object."<init>":()V
       4: return

  public static org.apache.dubbo.common.serialize.Serialization getSerializationById(java.lang.Byte);
    Code:
       0: getstatic     #3                  // Field ID_SERIALIZATION_MAP:Ljava/util/Map;
       3: aload_0
       4: invokeinterface #4,  2            // InterfaceMethod java/util/Map.get:(Ljava/lang/Object;)Ljava/lang/Object;
       9: checkcast     #5                  // class org/apache/dubbo/common/serialize/Serialization
      12: areturn

  public static java.lang.Byte getIDByName(java.lang.String);
    Code:
       0: getstatic     #6                  // Field SERIALIZATIONNAME_ID_MAP:Ljava/util/Map;
       3: aload_0
       4: invokeinterface #4,  2            // InterfaceMethod java/util/Map.get:(Ljava/lang/Object;)Ljava/lang/Object;
       9: checkcast     #7                  // class java/lang/Byte
      12: areturn

  public static org.apache.dubbo.common.serialize.Serialization getSerialization(org.apache.dubbo.common.URL);
    Code:
       0: aload_0
       1: invokevirtual #8                  // Method org/apache/dubbo/common/URL.getOrDefaultFrameworkModel:()Lorg/apache/dubbo/rpc/model/FrameworkModel;
       4: ldc           #5                  // class org/apache/dubbo/common/serialize/Serialization
       6: invokevirtual #9                  // Method org/apache/dubbo/rpc/model/FrameworkModel.getExtensionLoader:(Ljava/lang/Class;)Lorg/apache/dubbo/common/extension/ExtensionLoader;
       9: aload_0
      10: invokestatic  #10                 // Method org/apache/dubbo/remoting/utils/UrlUtils.serializationOrDefault:(Lorg/apache/dubbo/common/URL;)Ljava/lang/String;
      13: invokevirtual #11                 // Method org/apache/dubbo/common/extension/ExtensionLoader.getExtension:(Ljava/lang/String;)Ljava/lang/Object;
      16: checkcast     #5                  // class org/apache/dubbo/common/serialize/Serialization
      19: areturn

  public static org.apache.dubbo.common.serialize.Serialization getSerialization(java.lang.Byte) throws java.io.IOException;
    Code:
       0: aload_0
       1: invokestatic  #12                 // Method getSerializationById:(Ljava/lang/Byte;)Lorg/apache/dubbo/common/serialize/Serialization;
       4: astore_1
       5: aload_1
       6: ifnonnull     36
       9: new           #13                 // class java/io/IOException
      12: dup
      13: new           #14                 // class java/lang/StringBuilder
      16: dup
      17: invokespecial #15                 // Method java/lang/StringBuilder."<init>":()V
      20: ldc           #16                 // String Unrecognized serialize type from consumer:
      22: invokevirtual #17                 // Method java/lang/StringBuilder.append:(Ljava/lang/String;)Ljava/lang/StringBuilder;
      25: aload_0
      26: invokevirtual #18                 // Method java/lang/StringBuilder.append:(Ljava/lang/Object;)Ljava/lang/StringBuilder;
      29: invokevirtual #19                 // Method java/lang/StringBuilder.toString:()Ljava/lang/String;
      32: invokespecial #20                 // Method java/io/IOException."<init>":(Ljava/lang/String;)V
      35: athrow
      36: aload_1
      37: areturn

  public static org.apache.dubbo.common.serialize.ObjectInput deserialize(org.apache.dubbo.common.URL, java.io.InputStream, byte) throws java.io.IOException;
    Code:
       0: iload_2
       1: invokestatic  #21                 // Method java/lang/Byte.valueOf:(B)Ljava/lang/Byte;
       4: invokestatic  #22                 // Method getSerialization:(Ljava/lang/Byte;)Lorg/apache/dubbo/common/serialize/Serialization;
       7: astore_3
       8: aload_3
       9: aload_0
      10: aload_1
      11: invokeinterface #23,  3           // InterfaceMethod org/apache/dubbo/common/serialize/Serialization.deserialize:(Lorg/apache/dubbo/common/URL;Ljava/io/InputStream;)Lorg/apache/dubbo/common/serialize/ObjectInput;
      16: areturn

  public static byte[] getNullBytesOf(org.apache.dubbo.common.serialize.Serialization);
    Code:
       0: getstatic     #24                 // Field ID_NULLBYTES_MAP:Ljava/util/concurrent/ConcurrentMap;
       3: aload_0
       4: invokeinterface #25,  1           // InterfaceMethod org/apache/dubbo/common/serialize/Serialization.getContentTypeId:()B
       9: invokestatic  #21                 // Method java/lang/Byte.valueOf:(B)Ljava/lang/Byte;
      12: aload_0
      13: invokedynamic #26,  0             // InvokeDynamic #0:apply:(Lorg/apache/dubbo/common/serialize/Serialization;)Ljava/util/function/Function;
      18: invokestatic  #27                 // Method org/apache/dubbo/common/utils/ConcurrentHashMapUtils.computeIfAbsent:(Ljava/util/concurrent/ConcurrentMap;Ljava/lang/Object;Ljava/util/function/Function;)Ljava/lang/Object;
      21: checkcast     #28                 // class "[B"
      24: areturn

  public static byte[] getPayload(java.io.InputStream) throws java.io.IOException;
    Code:
       0: new           #29                 // class java/io/ByteArrayOutputStream
       3: dup
       4: invokespecial #30                 // Method java/io/ByteArrayOutputStream."<init>":()V
       7: astore_1
       8: aload_0
       9: invokevirtual #31                 // Method java/io/InputStream.available:()I
      12: invokestatic  #32                 // Method getBuffer:(I)[B
      15: astore_2
      16: aload_0
      17: aload_2
      18: invokevirtual #33                 // Method java/io/InputStream.read:([B)I
      21: dup
      22: istore_3
      23: iconst_m1
      24: if_icmple     37
      27: aload_1
      28: aload_2
      29: iconst_0
      30: iload_3
      31: invokevirtual #34                 // Method java/io/ByteArrayOutputStream.write:([BII)V
      34: goto          16
      37: aload_1
      38: invokevirtual #35                 // Method java/io/ByteArrayOutputStream.flush:()V
      41: aload_1
      42: invokevirtual #36                 // Method java/io/ByteArrayOutputStream.toByteArray:()[B
      45: areturn

  private static byte[] getBuffer(int);
    Code:
       0: getstatic     #37                 // Field TL_BUFFER:Ljava/lang/ThreadLocal;
       3: invokevirtual #38                 // Method java/lang/ThreadLocal.get:()Ljava/lang/Object;
       6: checkcast     #28                 // class "[B"
       9: astore_1
      10: iload_0
      11: aload_1
      12: arraylength
      13: if_icmpgt     18
      16: aload_1
      17: areturn
      18: iload_0
      19: newarray       byte
      21: areturn

  public static boolean isHeartBeat(byte[], byte);
    Code:
       0: aload_0
       1: iload_1
       2: invokestatic  #21                 // Method java/lang/Byte.valueOf:(B)Ljava/lang/Byte;
       5: invokestatic  #12                 // Method getSerializationById:(Ljava/lang/Byte;)Lorg/apache/dubbo/common/serialize/Serialization;
       8: invokestatic  #39                 // Method getNullBytesOf:(Lorg/apache/dubbo/common/serialize/Serialization;)[B
      11: invokestatic  #40                 // Method java/util/Arrays.equals:([B[B)Z
      14: ireturn

  public static void checkSerialization(java.lang.String, org.apache.dubbo.common.URL) throws java.io.IOException;
    Code:
       0: aload_1
       1: invokestatic  #41                 // Method org/apache/dubbo/remoting/utils/UrlUtils.allSerializations:(Lorg/apache/dubbo/common/URL;)Ljava/util/Collection;
       4: astore_2
       5: aload_0
       6: aload_2
       7: invokestatic  #42                 // Method checkSerialization:(Ljava/lang/String;Ljava/util/Collection;)V
      10: return

  public static void checkSerialization(java.lang.String, java.util.Collection<java.lang.String>) throws java.io.IOException;
    Code:
       0: aload_1
       1: invokeinterface #43,  1           // InterfaceMethod java/util/Collection.iterator:()Ljava/util/Iterator;
       6: astore_2
       7: aload_2
       8: invokeinterface #44,  1           // InterfaceMethod java/util/Iterator.hasNext:()Z
      13: ifeq          38
      16: aload_2
      17: invokeinterface #45,  1           // InterfaceMethod java/util/Iterator.next:()Ljava/lang/Object;
      22: checkcast     #46                 // class java/lang/String
      25: astore_3
      26: aload_3
      27: aload_0
      28: invokevirtual #47                 // Method java/lang/String.equals:(Ljava/lang/Object;)Z
      31: ifeq          35
      34: return
      35: goto          7
      38: new           #13                 // class java/io/IOException
      41: dup
      42: new           #14                 // class java/lang/StringBuilder
      45: dup
      46: invokespecial #15                 // Method java/lang/StringBuilder."<init>":()V
      49: ldc           #48                 // String Unexpected serialization type:
      51: invokevirtual #17                 // Method java/lang/StringBuilder.append:(Ljava/lang/String;)Ljava/lang/StringBuilder;
      54: aload_0
      55: invokevirtual #17                 // Method java/lang/StringBuilder.append:(Ljava/lang/String;)Ljava/lang/StringBuilder;
      58: ldc           #49                 // String  received from network, please check if the peer send the right id.
      60: invokevirtual #17                 // Method java/lang/StringBuilder.append:(Ljava/lang/String;)Ljava/lang/StringBuilder;
      63: invokevirtual #19                 // Method java/lang/StringBuilder.toString:()Ljava/lang/String;
      66: invokespecial #20                 // Method java/io/IOException."<init>":(Ljava/lang/String;)V
      69: athrow

  private static byte[] lambda$getNullBytesOf$1(org.apache.dubbo.common.serialize.Serialization, java.lang.Byte);
    Code:
       0: new           #29                 // class java/io/ByteArrayOutputStream
       3: dup
       4: invokespecial #30                 // Method java/io/ByteArrayOutputStream."<init>":()V
       7: astore_2
       8: iconst_0
       9: newarray       byte
      11: astore_3
      12: aload_0
      13: aconst_null
      14: aload_2
      15: invokeinterface #50,  3           // InterfaceMethod org/apache/dubbo/common/serialize/Serialization.serialize:(Lorg/apache/dubbo/common/URL;Ljava/io/OutputStream;)Lorg/apache/dubbo/common/serialize/ObjectOutput;
      20: astore        4
      22: aload         4
      24: aconst_null
      25: invokeinterface #51,  2           // InterfaceMethod org/apache/dubbo/common/serialize/ObjectOutput.writeObject:(Ljava/lang/Object;)V
      30: aload         4
      32: invokeinterface #52,  1           // InterfaceMethod org/apache/dubbo/common/serialize/ObjectOutput.flushBuffer:()V
      37: aload_2
      38: invokevirtual #36                 // Method java/io/ByteArrayOutputStream.toByteArray:()[B
      41: astore_3
      42: aload_2
      43: invokevirtual #53                 // Method java/io/ByteArrayOutputStream.close:()V
      46: goto          95
      49: astore        4
      51: getstatic     #55                 // Field logger:Lorg/apache/dubbo/common/logger/ErrorTypeAwareLogger;
      54: ldc           #56                 // String 6-9
      56: ldc           #57                 // String
      58: ldc           #57                 // String
      60: new           #14                 // class java/lang/StringBuilder
      63: dup
      64: invokespecial #15                 // Method java/lang/StringBuilder."<init>":()V
      67: ldc           #58                 // String Serialization extension
      69: invokevirtual #17                 // Method java/lang/StringBuilder.append:(Ljava/lang/String;)Ljava/lang/StringBuilder;
      72: aload_0
      73: invokevirtual #59                 // Method java/lang/Object.getClass:()Ljava/lang/Class;
      76: invokevirtual #60                 // Method java/lang/Class.getName:()Ljava/lang/String;
      79: invokevirtual #17                 // Method java/lang/StringBuilder.append:(Ljava/lang/String;)Ljava/lang/StringBuilder;
      82: ldc           #61                 // String  not support serializing null object, return an empty bytes instead.
      84: invokevirtual #17                 // Method java/lang/StringBuilder.append:(Ljava/lang/String;)Ljava/lang/StringBuilder;
      87: invokevirtual #19                 // Method java/lang/StringBuilder.toString:()Ljava/lang/String;
      90: invokeinterface #62,  5           // InterfaceMethod org/apache/dubbo/common/logger/ErrorTypeAwareLogger.warn:(Ljava/lang/String;Ljava/lang/String;Ljava/lang/String;Ljava/lang/String;)V
      95: aload_3
      96: areturn
    Exception table:
       from    to  target type
          12    46    49   Class java/lang/Exception

  private static byte[] lambda$static$0();
    Code:
       0: sipush        1024
       3: newarray       byte
       5: areturn

  static {};
    Code:
       0: ldc           #63                 // class org/apache/dubbo/remoting/transport/CodecSupport
       2: invokestatic  #64                 // Method org/apache/dubbo/common/logger/LoggerFactory.getErrorTypeAwareLogger:(Ljava/lang/Class;)Lorg/apache/dubbo/common/logger/ErrorTypeAwareLogger;
       5: putstatic     #55                 // Field logger:Lorg/apache/dubbo/common/logger/ErrorTypeAwareLogger;
       8: new           #65                 // class java/util/HashMap
      11: dup
      12: invokespecial #66                 // Method java/util/HashMap."<init>":()V
      15: putstatic     #3                  // Field ID_SERIALIZATION_MAP:Ljava/util/Map;
      18: new           #65                 // class java/util/HashMap
      21: dup
      22: invokespecial #66                 // Method java/util/HashMap."<init>":()V
      25: putstatic     #67                 // Field ID_SERIALIZATIONNAME_MAP:Ljava/util/Map;
      28: new           #65                 // class java/util/HashMap
      31: dup
      32: invokespecial #66                 // Method java/util/HashMap."<init>":()V
      35: putstatic     #6                  // Field SERIALIZATIONNAME_ID_MAP:Ljava/util/Map;
      38: new           #68                 // class java/util/concurrent/ConcurrentHashMap
      41: dup
      42: invokespecial #69                 // Method java/util/concurrent/ConcurrentHashMap."<init>":()V
      45: putstatic     #24                 // Field ID_NULLBYTES_MAP:Ljava/util/concurrent/ConcurrentMap;
      48: invokedynamic #70,  0             // InvokeDynamic #1:get:()Ljava/util/function/Supplier;
      53: invokestatic  #71                 // Method java/lang/ThreadLocal.withInitial:(Ljava/util/function/Supplier;)Ljava/lang/ThreadLocal;
      56: putstatic     #37                 // Field TL_BUFFER:Ljava/lang/ThreadLocal;
      59: invokestatic  #72                 // Method org/apache/dubbo/rpc/model/FrameworkModel.defaultModel:()Lorg/apache/dubbo/rpc/model/FrameworkModel;
      62: ldc           #5                  // class org/apache/dubbo/common/serialize/Serialization
      64: invokevirtual #9                  // Method org/apache/dubbo/rpc/model/FrameworkModel.getExtensionLoader:(Ljava/lang/Class;)Lorg/apache/dubbo/common/extension/ExtensionLoader;
      67: astore_0
      68: aload_0
      69: invokevirtual #73                 // Method org/apache/dubbo/common/extension/ExtensionLoader.getSupportedExtensions:()Ljava/util/Set;
      72: astore_1
      73: aload_1
      74: invokeinterface #74,  1           // InterfaceMethod java/util/Set.iterator:()Ljava/util/Iterator;
      79: astore_2
      80: aload_2
      81: invokeinterface #44,  1           // InterfaceMethod java/util/Iterator.hasNext:()Z
      86: ifeq          261
      89: aload_2
      90: invokeinterface #45,  1           // InterfaceMethod java/util/Iterator.next:()Ljava/lang/Object;
      95: checkcast     #46                 // class java/lang/String
      98: astore_3
      99: aload_0
     100: aload_3
     101: invokevirtual #11                 // Method org/apache/dubbo/common/extension/ExtensionLoader.getExtension:(Ljava/lang/String;)Ljava/lang/Object;
     104: checkcast     #5                  // class org/apache/dubbo/common/serialize/Serialization
     107: astore        4
     109: aload         4
     111: invokeinterface #25,  1           // InterfaceMethod org/apache/dubbo/common/serialize/Serialization.getContentTypeId:()B
     116: istore        5
     118: getstatic     #3                  // Field ID_SERIALIZATION_MAP:Ljava/util/Map;
     121: iload         5
     123: invokestatic  #21                 // Method java/lang/Byte.valueOf:(B)Ljava/lang/Byte;
     126: invokeinterface #75,  2           // InterfaceMethod java/util/Map.containsKey:(Ljava/lang/Object;)Z
     131: ifeq          212
     134: getstatic     #55                 // Field logger:Lorg/apache/dubbo/common/logger/ErrorTypeAwareLogger;
     137: ldc           #56                 // String 6-9
     139: ldc           #57                 // String
     141: ldc           #57                 // String
     143: new           #14                 // class java/lang/StringBuilder
     146: dup
     147: invokespecial #15                 // Method java/lang/StringBuilder."<init>":()V
     150: ldc           #58                 // String Serialization extension
     152: invokevirtual #17                 // Method java/lang/StringBuilder.append:(Ljava/lang/String;)Ljava/lang/StringBuilder;
     155: aload         4
     157: invokevirtual #59                 // Method java/lang/Object.getClass:()Ljava/lang/Class;
     160: invokevirtual #60                 // Method java/lang/Class.getName:()Ljava/lang/String;
     163: invokevirtual #17                 // Method java/lang/StringBuilder.append:(Ljava/lang/String;)Ljava/lang/StringBuilder;
     166: ldc           #76                 // String  has duplicate id to Serialization extension
     168: invokevirtual #17                 // Method java/lang/StringBuilder.append:(Ljava/lang/String;)Ljava/lang/StringBuilder;
     171: getstatic     #3                  // Field ID_SERIALIZATION_MAP:Ljava/util/Map;
     174: iload         5
     176: invokestatic  #21                 // Method java/lang/Byte.valueOf:(B)Ljava/lang/Byte;
     179: invokeinterface #4,  2            // InterfaceMethod java/util/Map.get:(Ljava/lang/Object;)Ljava/lang/Object;
     184: checkcast     #5                  // class org/apache/dubbo/common/serialize/Serialization
     187: invokevirtual #59                 // Method java/lang/Object.getClass:()Ljava/lang/Class;
     190: invokevirtual #60                 // Method java/lang/Class.getName:()Ljava/lang/String;
     193: invokevirtual #17                 // Method java/lang/StringBuilder.append:(Ljava/lang/String;)Ljava/lang/StringBuilder;
     196: ldc           #77                 // String , ignore this Serialization extension
     198: invokevirtual #17                 // Method java/lang/StringBuilder.append:(Ljava/lang/String;)Ljava/lang/StringBuilder;
     201: invokevirtual #19                 // Method java/lang/StringBuilder.toString:()Ljava/lang/String;
     204: invokeinterface #78,  5           // InterfaceMethod org/apache/dubbo/common/logger/ErrorTypeAwareLogger.error:(Ljava/lang/String;Ljava/lang/String;Ljava/lang/String;Ljava/lang/String;)V
     209: goto          80
     212: getstatic     #3                  // Field ID_SERIALIZATION_MAP:Ljava/util/Map;
     215: iload         5
     217: invokestatic  #21                 // Method java/lang/Byte.valueOf:(B)Ljava/lang/Byte;
     220: aload         4
     222: invokeinterface #79,  3           // InterfaceMethod java/util/Map.put:(Ljava/lang/Object;Ljava/lang/Object;)Ljava/lang/Object;
     227: pop
     228: getstatic     #67                 // Field ID_SERIALIZATIONNAME_MAP:Ljava/util/Map;
     231: iload         5
     233: invokestatic  #21                 // Method java/lang/Byte.valueOf:(B)Ljava/lang/Byte;
     236: aload_3
     237: invokeinterface #79,  3           // InterfaceMethod java/util/Map.put:(Ljava/lang/Object;Ljava/lang/Object;)Ljava/lang/Object;
     242: pop
     243: getstatic     #6                  // Field SERIALIZATIONNAME_ID_MAP:Ljava/util/Map;
     246: aload_3
     247: iload         5
     249: invokestatic  #21                 // Method java/lang/Byte.valueOf:(B)Ljava/lang/Byte;
     252: invokeinterface #79,  3           // InterfaceMethod java/util/Map.put:(Ljava/lang/Object;Ljava/lang/Object;)Ljava/lang/Object;
     257: pop
     258: goto          80
     261: return
}
