Compiled from "DecodeHandler.java"
public class org.apache.dubbo.remoting.transport.DecodeHandler extends org.apache.dubbo.remoting.transport.AbstractChannelHandlerDelegate {
  private static final org.apache.dubbo.common.logger.ErrorTypeAwareLogger log;

  public org.apache.dubbo.remoting.transport.DecodeHandler(org.apache.dubbo.remoting.ChannelHandler);
    Code:
       0: aload_0
       1: aload_1
       2: invokespecial #2                  // Method org/apache/dubbo/remoting/transport/AbstractChannelHandlerDelegate."<init>":(Lorg/apache/dubbo/remoting/ChannelHandler;)V
       5: return

  public void received(org.apache.dubbo.remoting.Channel, java.lang.Object) throws org.apache.dubbo.remoting.RemotingException;
    Code:
       0: aload_2
       1: instanceof    #3                  // class org/apache/dubbo/remoting/Decodeable
       4: ifeq          12
       7: aload_0
       8: aload_2
       9: invokespecial #4                  // Method decode:(Ljava/lang/Object;)V
      12: aload_2
      13: instanceof    #5                  // class org/apache/dubbo/remoting/exchange/Request
      16: ifeq          30
      19: aload_0
      20: aload_2
      21: checkcast     #5                  // class org/apache/dubbo/remoting/exchange/Request
      24: invokevirtual #6                  // Method org/apache/dubbo/remoting/exchange/Request.getData:()Ljava/lang/Object;
      27: invokespecial #4                  // Method decode:(Ljava/lang/Object;)V
      30: aload_2
      31: instanceof    #7                  // class org/apache/dubbo/remoting/exchange/Response
      34: ifeq          48
      37: aload_0
      38: aload_2
      39: checkcast     #7                  // class org/apache/dubbo/remoting/exchange/Response
      42: invokevirtual #8                  // Method org/apache/dubbo/remoting/exchange/Response.getResult:()Ljava/lang/Object;
      45: invokespecial #4                  // Method decode:(Ljava/lang/Object;)V
      48: aload_0
      49: getfield      #9                  // Field handler:Lorg/apache/dubbo/remoting/ChannelHandler;
      52: aload_1
      53: aload_2
      54: invokeinterface #10,  3           // InterfaceMethod org/apache/dubbo/remoting/ChannelHandler.received:(Lorg/apache/dubbo/remoting/Channel;Ljava/lang/Object;)V
      59: return

  private void decode(java.lang.Object);
    Code:
       0: aload_1
       1: instanceof    #3                  // class org/apache/dubbo/remoting/Decodeable
       4: ifne          8
       7: return
       8: aload_1
       9: checkcast     #3                  // class org/apache/dubbo/remoting/Decodeable
      12: invokeinterface #11,  1           // InterfaceMethod org/apache/dubbo/remoting/Decodeable.decode:()V
      17: getstatic     #12                 // Field log:Lorg/apache/dubbo/common/logger/ErrorTypeAwareLogger;
      20: invokeinterface #13,  1           // InterfaceMethod org/apache/dubbo/common/logger/ErrorTypeAwareLogger.isDebugEnabled:()Z
      25: ifeq          61
      28: getstatic     #12                 // Field log:Lorg/apache/dubbo/common/logger/ErrorTypeAwareLogger;
      31: new           #14                 // class java/lang/StringBuilder
      34: dup
      35: invokespecial #15                 // Method java/lang/StringBuilder."<init>":()V
      38: ldc           #16                 // String Decode decodeable message
      40: invokevirtual #17                 // Method java/lang/StringBuilder.append:(Ljava/lang/String;)Ljava/lang/StringBuilder;
      43: aload_1
      44: invokevirtual #18                 // Method java/lang/Object.getClass:()Ljava/lang/Class;
      47: invokevirtual #19                 // Method java/lang/Class.getName:()Ljava/lang/String;
      50: invokevirtual #17                 // Method java/lang/StringBuilder.append:(Ljava/lang/String;)Ljava/lang/StringBuilder;
      53: invokevirtual #20                 // Method java/lang/StringBuilder.toString:()Ljava/lang/String;
      56: invokeinterface #21,  2           // InterfaceMethod org/apache/dubbo/common/logger/ErrorTypeAwareLogger.debug:(Ljava/lang/String;)V
      61: goto          113
      64: astore_2
      65: getstatic     #12                 // Field log:Lorg/apache/dubbo/common/logger/ErrorTypeAwareLogger;
      68: invokeinterface #23,  1           // InterfaceMethod org/apache/dubbo/common/logger/ErrorTypeAwareLogger.isWarnEnabled:()Z
      73: ifeq          113
      76: getstatic     #12                 // Field log:Lorg/apache/dubbo/common/logger/ErrorTypeAwareLogger;
      79: ldc           #24                 // String 6-8
      81: ldc           #25                 // String
      83: ldc           #25                 // String
      85: new           #14                 // class java/lang/StringBuilder
      88: dup
      89: invokespecial #15                 // Method java/lang/StringBuilder."<init>":()V
      92: ldc           #26                 // String Call Decodeable.decode failed:
      94: invokevirtual #17                 // Method java/lang/StringBuilder.append:(Ljava/lang/String;)Ljava/lang/StringBuilder;
      97: aload_2
      98: invokevirtual #27                 // Method java/lang/Throwable.getMessage:()Ljava/lang/String;
     101: invokevirtual #17                 // Method java/lang/StringBuilder.append:(Ljava/lang/String;)Ljava/lang/StringBuilder;
     104: invokevirtual #20                 // Method java/lang/StringBuilder.toString:()Ljava/lang/String;
     107: aload_2
     108: invokeinterface #28,  6           // InterfaceMethod org/apache/dubbo/common/logger/ErrorTypeAwareLogger.warn:(Ljava/lang/String;Ljava/lang/String;Ljava/lang/String;Ljava/lang/String;Ljava/lang/Throwable;)V
     113: return
    Exception table:
       from    to  target type
           8    61    64   Class java/lang/Throwable

  static {};
    Code:
       0: ldc           #29                 // class org/apache/dubbo/remoting/transport/DecodeHandler
       2: invokestatic  #30                 // Method org/apache/dubbo/common/logger/LoggerFactory.getErrorTypeAwareLogger:(Ljava/lang/Class;)Lorg/apache/dubbo/common/logger/ErrorTypeAwareLogger;
       5: putstatic     #12                 // Field log:Lorg/apache/dubbo/common/logger/ErrorTypeAwareLogger;
       8: return
}
