Compiled from "MultiMessageHandler.java"
public class org.apache.dubbo.remoting.transport.MultiMessageHandler extends org.apache.dubbo.remoting.transport.AbstractChannelHandlerDelegate {
  protected static final org.apache.dubbo.common.logger.ErrorTypeAwareLogger logger;

  public org.apache.dubbo.remoting.transport.MultiMessageHandler(org.apache.dubbo.remoting.ChannelHandler);
    Code:
       0: aload_0
       1: aload_1
       2: invokespecial #2                  // Method org/apache/dubbo/remoting/transport/AbstractChannelHandlerDelegate."<init>":(Lorg/apache/dubbo/remoting/ChannelHandler;)V
       5: return

  public void received(org.apache.dubbo.remoting.Channel, java.lang.Object) throws org.apache.dubbo.remoting.RemotingException;
    Code:
       0: aload_2
       1: instanceof    #3                  // class org/apache/dubbo/remoting/exchange/support/MultiMessage
       4: ifeq          113
       7: aload_2
       8: checkcast     #3                  // class org/apache/dubbo/remoting/exchange/support/MultiMessage
      11: astore_3
      12: aload_3
      13: invokevirtual #4                  // Method org/apache/dubbo/remoting/exchange/support/MultiMessage.iterator:()Ljava/util/Iterator;
      16: astore        4
      18: aload         4
      20: invokeinterface #5,  1            // InterfaceMethod java/util/Iterator.hasNext:()Z
      25: ifeq          110
      28: aload         4
      30: invokeinterface #6,  1            // InterfaceMethod java/util/Iterator.next:()Ljava/lang/Object;
      35: astore        5
      37: aload_0
      38: getfield      #7                  // Field handler:Lorg/apache/dubbo/remoting/ChannelHandler;
      41: aload_1
      42: aload         5
      44: invokeinterface #8,  3            // InterfaceMethod org/apache/dubbo/remoting/ChannelHandler.received:(Lorg/apache/dubbo/remoting/Channel;Ljava/lang/Object;)V
      49: goto          107
      52: astore        6
      54: getstatic     #10                 // Field logger:Lorg/apache/dubbo/common/logger/ErrorTypeAwareLogger;
      57: ldc           #11                 // String 99-0
      59: ldc           #12                 // String unknown error in remoting module
      61: ldc           #13                 // String
      63: ldc           #14                 // String MultiMessageHandler received fail.
      65: aload         6
      67: invokeinterface #15,  6           // InterfaceMethod org/apache/dubbo/common/logger/ErrorTypeAwareLogger.error:(Ljava/lang/String;Ljava/lang/String;Ljava/lang/String;Ljava/lang/String;Ljava/lang/Throwable;)V
      72: aload_0
      73: getfield      #7                  // Field handler:Lorg/apache/dubbo/remoting/ChannelHandler;
      76: aload_1
      77: aload         6
      79: invokeinterface #16,  3           // InterfaceMethod org/apache/dubbo/remoting/ChannelHandler.caught:(Lorg/apache/dubbo/remoting/Channel;Ljava/lang/Throwable;)V
      84: goto          107
      87: astore        7
      89: getstatic     #10                 // Field logger:Lorg/apache/dubbo/common/logger/ErrorTypeAwareLogger;
      92: ldc           #11                 // String 99-0
      94: ldc           #12                 // String unknown error in remoting module
      96: ldc           #13                 // String
      98: ldc           #17                 // String MultiMessageHandler caught fail.
     100: aload         7
     102: invokeinterface #15,  6           // InterfaceMethod org/apache/dubbo/common/logger/ErrorTypeAwareLogger.error:(Ljava/lang/String;Ljava/lang/String;Ljava/lang/String;Ljava/lang/String;Ljava/lang/Throwable;)V
     107: goto          18
     110: goto          124
     113: aload_0
     114: getfield      #7                  // Field handler:Lorg/apache/dubbo/remoting/ChannelHandler;
     117: aload_1
     118: aload_2
     119: invokeinterface #8,  3            // InterfaceMethod org/apache/dubbo/remoting/ChannelHandler.received:(Lorg/apache/dubbo/remoting/Channel;Ljava/lang/Object;)V
     124: return
    Exception table:
       from    to  target type
          37    49    52   Class java/lang/Throwable
          72    84    87   Class java/lang/Throwable

  static {};
    Code:
       0: ldc           #18                 // class org/apache/dubbo/remoting/transport/MultiMessageHandler
       2: invokestatic  #19                 // Method org/apache/dubbo/common/logger/LoggerFactory.getErrorTypeAwareLogger:(Ljava/lang/Class;)Lorg/apache/dubbo/common/logger/ErrorTypeAwareLogger;
       5: putstatic     #10                 // Field logger:Lorg/apache/dubbo/common/logger/ErrorTypeAwareLogger;
       8: return
}
