Compiled from "ConnectionOrderedChannelHandler.java"
public class org.apache.dubbo.remoting.transport.dispatcher.connection.ConnectionOrderedChannelHandler extends org.apache.dubbo.remoting.transport.dispatcher.WrappedChannelHandler {
  protected final java.util.concurrent.ThreadPoolExecutor connectionExecutor;

  private final int queueWarningLimit;

  public org.apache.dubbo.remoting.transport.dispatcher.connection.ConnectionOrderedChannelHandler(org.apache.dubbo.remoting.ChannelHandler, org.apache.dubbo.common.URL);
    Code:
       0: aload_0
       1: aload_1
       2: aload_2
       3: invokespecial #4                  // Method org/apache/dubbo/remoting/transport/dispatcher/WrappedChannelHandler."<init>":(Lorg/apache/dubbo/remoting/ChannelHandler;Lorg/apache/dubbo/common/URL;)V
       6: aload_2
       7: ldc           #5                  // String threadname
       9: ldc           #6                  // String Dubbo
      11: invokevirtual #7                  // Method org/apache/dubbo/common/URL.getParameter:(Ljava/lang/String;Ljava/lang/String;)Ljava/lang/String;
      14: astore_3
      15: aload_0
      16: new           #8                  // class java/util/concurrent/ThreadPoolExecutor
      19: dup
      20: iconst_1
      21: iconst_1
      22: lconst_0
      23: getstatic     #9                  // Field java/util/concurrent/TimeUnit.MILLISECONDS:Ljava/util/concurrent/TimeUnit;
      26: new           #10                 // class java/util/concurrent/LinkedBlockingQueue
      29: dup
      30: aload_2
      31: ldc           #11                 // String connect.queue.capacity
      33: ldc           #13                 // int 2147483647
      35: invokevirtual #14                 // Method org/apache/dubbo/common/URL.getPositiveParameter:(Ljava/lang/String;I)I
      38: invokespecial #15                 // Method java/util/concurrent/LinkedBlockingQueue."<init>":(I)V
      41: new           #16                 // class org/apache/dubbo/common/utils/NamedThreadFactory
      44: dup
      45: aload_3
      46: iconst_1
      47: invokespecial #17                 // Method org/apache/dubbo/common/utils/NamedThreadFactory."<init>":(Ljava/lang/String;Z)V
      50: new           #18                 // class org/apache/dubbo/common/threadpool/support/AbortPolicyWithReport
      53: dup
      54: aload_3
      55: aload_2
      56: invokespecial #19                 // Method org/apache/dubbo/common/threadpool/support/AbortPolicyWithReport."<init>":(Ljava/lang/String;Lorg/apache/dubbo/common/URL;)V
      59: invokespecial #20                 // Method java/util/concurrent/ThreadPoolExecutor."<init>":(IIJLjava/util/concurrent/TimeUnit;Ljava/util/concurrent/BlockingQueue;Ljava/util/concurrent/ThreadFactory;Ljava/util/concurrent/RejectedExecutionHandler;)V
      62: putfield      #21                 // Field connectionExecutor:Ljava/util/concurrent/ThreadPoolExecutor;
      65: aload_0
      66: aload_2
      67: ldc           #22                 // String connect.queue.warning.size
      69: sipush        1000
      72: invokevirtual #23                 // Method org/apache/dubbo/common/URL.getParameter:(Ljava/lang/String;I)I
      75: putfield      #24                 // Field queueWarningLimit:I
      78: return

  public void connected(org.apache.dubbo.remoting.Channel) throws org.apache.dubbo.remoting.RemotingException;
    Code:
       0: aload_0
       1: invokespecial #25                 // Method checkQueueLength:()V
       4: aload_0
       5: getfield      #21                 // Field connectionExecutor:Ljava/util/concurrent/ThreadPoolExecutor;
       8: new           #26                 // class org/apache/dubbo/remoting/transport/dispatcher/ChannelEventRunnable
      11: dup
      12: aload_1
      13: aload_0
      14: getfield      #27                 // Field handler:Lorg/apache/dubbo/remoting/ChannelHandler;
      17: getstatic     #28                 // Field org/apache/dubbo/remoting/transport/dispatcher/ChannelEventRunnable$ChannelState.CONNECTED:Lorg/apache/dubbo/remoting/transport/dispatcher/ChannelEventRunnable$ChannelState;
      20: invokespecial #29                 // Method org/apache/dubbo/remoting/transport/dispatcher/ChannelEventRunnable."<init>":(Lorg/apache/dubbo/remoting/Channel;Lorg/apache/dubbo/remoting/ChannelHandler;Lorg/apache/dubbo/remoting/transport/dispatcher/ChannelEventRunnable$ChannelState;)V
      23: invokevirtual #30                 // Method java/util/concurrent/ThreadPoolExecutor.execute:(Ljava/lang/Runnable;)V
      26: goto          64
      29: astore_2
      30: new           #32                 // class org/apache/dubbo/remoting/ExecutionException
      33: dup
      34: ldc           #33                 // String connect event
      36: aload_1
      37: new           #34                 // class java/lang/StringBuilder
      40: dup
      41: invokespecial #35                 // Method java/lang/StringBuilder."<init>":()V
      44: aload_0
      45: invokevirtual #36                 // Method java/lang/Object.getClass:()Ljava/lang/Class;
      48: invokevirtual #37                 // Method java/lang/StringBuilder.append:(Ljava/lang/Object;)Ljava/lang/StringBuilder;
      51: ldc           #38                 // String  error when process connected event .
      53: invokevirtual #39                 // Method java/lang/StringBuilder.append:(Ljava/lang/String;)Ljava/lang/StringBuilder;
      56: invokevirtual #40                 // Method java/lang/StringBuilder.toString:()Ljava/lang/String;
      59: aload_2
      60: invokespecial #41                 // Method org/apache/dubbo/remoting/ExecutionException."<init>":(Ljava/lang/Object;Lorg/apache/dubbo/remoting/Channel;Ljava/lang/String;Ljava/lang/Throwable;)V
      63: athrow
      64: return
    Exception table:
       from    to  target type
           0    26    29   Class java/lang/Throwable

  public void disconnected(org.apache.dubbo.remoting.Channel) throws org.apache.dubbo.remoting.RemotingException;
    Code:
       0: aload_0
       1: invokespecial #25                 // Method checkQueueLength:()V
       4: aload_0
       5: getfield      #21                 // Field connectionExecutor:Ljava/util/concurrent/ThreadPoolExecutor;
       8: new           #26                 // class org/apache/dubbo/remoting/transport/dispatcher/ChannelEventRunnable
      11: dup
      12: aload_1
      13: aload_0
      14: getfield      #27                 // Field handler:Lorg/apache/dubbo/remoting/ChannelHandler;
      17: getstatic     #42                 // Field org/apache/dubbo/remoting/transport/dispatcher/ChannelEventRunnable$ChannelState.DISCONNECTED:Lorg/apache/dubbo/remoting/transport/dispatcher/ChannelEventRunnable$ChannelState;
      20: invokespecial #29                 // Method org/apache/dubbo/remoting/transport/dispatcher/ChannelEventRunnable."<init>":(Lorg/apache/dubbo/remoting/Channel;Lorg/apache/dubbo/remoting/ChannelHandler;Lorg/apache/dubbo/remoting/transport/dispatcher/ChannelEventRunnable$ChannelState;)V
      23: invokevirtual #30                 // Method java/util/concurrent/ThreadPoolExecutor.execute:(Ljava/lang/Runnable;)V
      26: goto          64
      29: astore_2
      30: new           #32                 // class org/apache/dubbo/remoting/ExecutionException
      33: dup
      34: ldc           #43                 // String disconnected event
      36: aload_1
      37: new           #34                 // class java/lang/StringBuilder
      40: dup
      41: invokespecial #35                 // Method java/lang/StringBuilder."<init>":()V
      44: aload_0
      45: invokevirtual #36                 // Method java/lang/Object.getClass:()Ljava/lang/Class;
      48: invokevirtual #37                 // Method java/lang/StringBuilder.append:(Ljava/lang/Object;)Ljava/lang/StringBuilder;
      51: ldc           #44                 // String  error when process disconnected event .
      53: invokevirtual #39                 // Method java/lang/StringBuilder.append:(Ljava/lang/String;)Ljava/lang/StringBuilder;
      56: invokevirtual #40                 // Method java/lang/StringBuilder.toString:()Ljava/lang/String;
      59: aload_2
      60: invokespecial #41                 // Method org/apache/dubbo/remoting/ExecutionException."<init>":(Ljava/lang/Object;Lorg/apache/dubbo/remoting/Channel;Ljava/lang/String;Ljava/lang/Throwable;)V
      63: athrow
      64: return
    Exception table:
       from    to  target type
           0    26    29   Class java/lang/Throwable

  public void received(org.apache.dubbo.remoting.Channel, java.lang.Object) throws org.apache.dubbo.remoting.RemotingException;
    Code:
       0: aload_0
       1: aload_2
       2: invokevirtual #45                 // Method getPreferredExecutorService:(Ljava/lang/Object;)Ljava/util/concurrent/ExecutorService;
       5: astore_3
       6: aload_3
       7: new           #26                 // class org/apache/dubbo/remoting/transport/dispatcher/ChannelEventRunnable
      10: dup
      11: aload_1
      12: aload_0
      13: getfield      #27                 // Field handler:Lorg/apache/dubbo/remoting/ChannelHandler;
      16: getstatic     #46                 // Field org/apache/dubbo/remoting/transport/dispatcher/ChannelEventRunnable$ChannelState.RECEIVED:Lorg/apache/dubbo/remoting/transport/dispatcher/ChannelEventRunnable$ChannelState;
      19: aload_2
      20: invokespecial #47                 // Method org/apache/dubbo/remoting/transport/dispatcher/ChannelEventRunnable."<init>":(Lorg/apache/dubbo/remoting/Channel;Lorg/apache/dubbo/remoting/ChannelHandler;Lorg/apache/dubbo/remoting/transport/dispatcher/ChannelEventRunnable$ChannelState;Ljava/lang/Object;)V
      23: invokeinterface #48,  2           // InterfaceMethod java/util/concurrent/ExecutorService.execute:(Ljava/lang/Runnable;)V
      28: goto          94
      31: astore        4
      33: aload_2
      34: instanceof    #49                 // class org/apache/dubbo/remoting/exchange/Request
      37: ifeq          60
      40: aload         4
      42: instanceof    #50                 // class java/util/concurrent/RejectedExecutionException
      45: ifeq          60
      48: aload_0
      49: aload_1
      50: aload_2
      51: checkcast     #49                 // class org/apache/dubbo/remoting/exchange/Request
      54: aload         4
      56: invokevirtual #51                 // Method sendFeedback:(Lorg/apache/dubbo/remoting/Channel;Lorg/apache/dubbo/remoting/exchange/Request;Ljava/lang/Throwable;)V
      59: return
      60: new           #32                 // class org/apache/dubbo/remoting/ExecutionException
      63: dup
      64: aload_2
      65: aload_1
      66: new           #34                 // class java/lang/StringBuilder
      69: dup
      70: invokespecial #35                 // Method java/lang/StringBuilder."<init>":()V
      73: aload_0
      74: invokevirtual #36                 // Method java/lang/Object.getClass:()Ljava/lang/Class;
      77: invokevirtual #37                 // Method java/lang/StringBuilder.append:(Ljava/lang/Object;)Ljava/lang/StringBuilder;
      80: ldc           #52                 // String  error when process received event .
      82: invokevirtual #39                 // Method java/lang/StringBuilder.append:(Ljava/lang/String;)Ljava/lang/StringBuilder;
      85: invokevirtual #40                 // Method java/lang/StringBuilder.toString:()Ljava/lang/String;
      88: aload         4
      90: invokespecial #41                 // Method org/apache/dubbo/remoting/ExecutionException."<init>":(Ljava/lang/Object;Lorg/apache/dubbo/remoting/Channel;Ljava/lang/String;Ljava/lang/Throwable;)V
      93: athrow
      94: return
    Exception table:
       from    to  target type
           6    28    31   Class java/lang/Throwable

  public void caught(org.apache.dubbo.remoting.Channel, java.lang.Throwable) throws org.apache.dubbo.remoting.RemotingException;
    Code:
       0: aload_0
       1: invokevirtual #53                 // Method getSharedExecutorService:()Ljava/util/concurrent/ExecutorService;
       4: astore_3
       5: aload_3
       6: new           #26                 // class org/apache/dubbo/remoting/transport/dispatcher/ChannelEventRunnable
       9: dup
      10: aload_1
      11: aload_0
      12: getfield      #27                 // Field handler:Lorg/apache/dubbo/remoting/ChannelHandler;
      15: getstatic     #54                 // Field org/apache/dubbo/remoting/transport/dispatcher/ChannelEventRunnable$ChannelState.CAUGHT:Lorg/apache/dubbo/remoting/transport/dispatcher/ChannelEventRunnable$ChannelState;
      18: aload_2
      19: invokespecial #55                 // Method org/apache/dubbo/remoting/transport/dispatcher/ChannelEventRunnable."<init>":(Lorg/apache/dubbo/remoting/Channel;Lorg/apache/dubbo/remoting/ChannelHandler;Lorg/apache/dubbo/remoting/transport/dispatcher/ChannelEventRunnable$ChannelState;Ljava/lang/Throwable;)V
      22: invokeinterface #48,  2           // InterfaceMethod java/util/concurrent/ExecutorService.execute:(Ljava/lang/Runnable;)V
      27: goto          67
      30: astore        4
      32: new           #32                 // class org/apache/dubbo/remoting/ExecutionException
      35: dup
      36: ldc           #56                 // String caught event
      38: aload_1
      39: new           #34                 // class java/lang/StringBuilder
      42: dup
      43: invokespecial #35                 // Method java/lang/StringBuilder."<init>":()V
      46: aload_0
      47: invokevirtual #36                 // Method java/lang/Object.getClass:()Ljava/lang/Class;
      50: invokevirtual #37                 // Method java/lang/StringBuilder.append:(Ljava/lang/Object;)Ljava/lang/StringBuilder;
      53: ldc           #57                 // String  error when process caught event .
      55: invokevirtual #39                 // Method java/lang/StringBuilder.append:(Ljava/lang/String;)Ljava/lang/StringBuilder;
      58: invokevirtual #40                 // Method java/lang/StringBuilder.toString:()Ljava/lang/String;
      61: aload         4
      63: invokespecial #41                 // Method org/apache/dubbo/remoting/ExecutionException."<init>":(Ljava/lang/Object;Lorg/apache/dubbo/remoting/Channel;Ljava/lang/String;Ljava/lang/Throwable;)V
      66: athrow
      67: return
    Exception table:
       from    to  target type
           5    27    30   Class java/lang/Throwable

  private void checkQueueLength();
    Code:
       0: aload_0
       1: getfield      #21                 // Field connectionExecutor:Ljava/util/concurrent/ThreadPoolExecutor;
       4: invokevirtual #58                 // Method java/util/concurrent/ThreadPoolExecutor.getQueue:()Ljava/util/concurrent/BlockingQueue;
       7: invokeinterface #59,  1           // InterfaceMethod java/util/concurrent/BlockingQueue.size:()I
      12: aload_0
      13: getfield      #24                 // Field queueWarningLimit:I
      16: if_icmple     75
      19: getstatic     #60                 // Field logger:Lorg/apache/dubbo/common/logger/ErrorTypeAwareLogger;
      22: ldc           #61                 // String 6-7
      24: ldc           #62                 // String
      26: ldc           #62                 // String
      28: new           #34                 // class java/lang/StringBuilder
      31: dup
      32: invokespecial #35                 // Method java/lang/StringBuilder."<init>":()V
      35: ldc           #63                 // String connectionordered channel handler queue size:
      37: invokevirtual #39                 // Method java/lang/StringBuilder.append:(Ljava/lang/String;)Ljava/lang/StringBuilder;
      40: aload_0
      41: getfield      #21                 // Field connectionExecutor:Ljava/util/concurrent/ThreadPoolExecutor;
      44: invokevirtual #58                 // Method java/util/concurrent/ThreadPoolExecutor.getQueue:()Ljava/util/concurrent/BlockingQueue;
      47: invokeinterface #59,  1           // InterfaceMethod java/util/concurrent/BlockingQueue.size:()I
      52: invokevirtual #64                 // Method java/lang/StringBuilder.append:(I)Ljava/lang/StringBuilder;
      55: ldc           #65                 // String  exceed the warning limit number :
      57: invokevirtual #39                 // Method java/lang/StringBuilder.append:(Ljava/lang/String;)Ljava/lang/StringBuilder;
      60: aload_0
      61: getfield      #24                 // Field queueWarningLimit:I
      64: invokevirtual #64                 // Method java/lang/StringBuilder.append:(I)Ljava/lang/StringBuilder;
      67: invokevirtual #40                 // Method java/lang/StringBuilder.toString:()Ljava/lang/String;
      70: invokeinterface #66,  5           // InterfaceMethod org/apache/dubbo/common/logger/ErrorTypeAwareLogger.warn:(Ljava/lang/String;Ljava/lang/String;Ljava/lang/String;Ljava/lang/String;)V
      75: return
}
