Compiled from "AttachmentConditionMatcher.java"
public class org.apache.dubbo.rpc.cluster.router.condition.matcher.attachment.AttachmentConditionMatcher extends org.apache.dubbo.rpc.cluster.router.condition.matcher.AbstractConditionMatcher {
  private static final org.apache.dubbo.common.logger.ErrorTypeAwareLogger logger;

  private static final java.util.regex.Pattern ATTACHMENTS_PATTERN;

  public org.apache.dubbo.rpc.cluster.router.condition.matcher.attachment.AttachmentConditionMatcher(java.lang.String, org.apache.dubbo.rpc.model.ModuleModel);
    Code:
       0: aload_0
       1: aload_1
       2: aload_2
       3: invokespecial #2                  // Method org/apache/dubbo/rpc/cluster/router/condition/matcher/AbstractConditionMatcher."<init>":(Ljava/lang/String;Lorg/apache/dubbo/rpc/model/ModuleModel;)V
       6: return

  protected java.lang.String getValue(java.util.Map<java.lang.String, java.lang.String>, org.apache.dubbo.common.URL, org.apache.dubbo.rpc.Invocation);
    Code:
       0: aload_0
       1: getfield      #3                  // Field key:Ljava/lang/String;
       4: ldc           #4                  // String \\.
       6: invokevirtual #5                  // Method java/lang/String.split:(Ljava/lang/String;)[Ljava/lang/String;
       9: astore        4
      11: aload         4
      13: iconst_0
      14: aaload
      15: astore        5
      17: getstatic     #6                  // Field ATTACHMENTS_PATTERN:Ljava/util/regex/Pattern;
      20: aload         5
      22: invokevirtual #7                  // Method java/util/regex/Pattern.matcher:(Ljava/lang/CharSequence;)Ljava/util/regex/Matcher;
      25: astore        6
      27: aload         6
      29: invokevirtual #8                  // Method java/util/regex/Matcher.find:()Z
      32: ifne          38
      35: ldc           #10                 // String dubbo_internal_not_found_argument_condition_value
      37: areturn
      38: aload         6
      40: iconst_1
      41: invokevirtual #11                 // Method java/util/regex/Matcher.group:(I)Ljava/lang/String;
      44: astore        7
      46: aload         7
      48: invokestatic  #12                 // Method org/apache/dubbo/common/utils/StringUtils.isEmpty:(Ljava/lang/String;)Z
      51: ifeq          57
      54: ldc           #10                 // String dubbo_internal_not_found_argument_condition_value
      56: areturn
      57: aload_3
      58: aload         7
      60: invokeinterface #13,  2           // InterfaceMethod org/apache/dubbo/rpc/Invocation.getAttachment:(Ljava/lang/String;)Ljava/lang/String;
      65: areturn
      66: astore        4
      68: getstatic     #15                 // Field logger:Lorg/apache/dubbo/common/logger/ErrorTypeAwareLogger;
      71: ldc           #16                 // String 2-7
      73: ldc           #17                 // String condition state router attachment match failed
      75: ldc           #18                 // String
      77: new           #19                 // class java/lang/StringBuilder
      80: dup
      81: invokespecial #20                 // Method java/lang/StringBuilder."<init>":()V
      84: ldc           #21                 // String Invalid match condition:
      86: invokevirtual #22                 // Method java/lang/StringBuilder.append:(Ljava/lang/String;)Ljava/lang/StringBuilder;
      89: aload_0
      90: getfield      #3                  // Field key:Ljava/lang/String;
      93: invokevirtual #22                 // Method java/lang/StringBuilder.append:(Ljava/lang/String;)Ljava/lang/StringBuilder;
      96: invokevirtual #23                 // Method java/lang/StringBuilder.toString:()Ljava/lang/String;
      99: aload         4
     101: invokeinterface #24,  6           // InterfaceMethod org/apache/dubbo/common/logger/ErrorTypeAwareLogger.warn:(Ljava/lang/String;Ljava/lang/String;Ljava/lang/String;Ljava/lang/String;Ljava/lang/Throwable;)V
     106: ldc           #10                 // String dubbo_internal_not_found_argument_condition_value
     108: areturn
    Exception table:
       from    to  target type
           0    37    66   Class java/lang/Exception
          38    56    66   Class java/lang/Exception
          57    65    66   Class java/lang/Exception

  static {};
    Code:
       0: ldc           #25                 // class org/apache/dubbo/rpc/cluster/router/condition/matcher/attachment/AttachmentConditionMatcher
       2: invokestatic  #26                 // Method org/apache/dubbo/common/logger/LoggerFactory.getErrorTypeAwareLogger:(Ljava/lang/Class;)Lorg/apache/dubbo/common/logger/ErrorTypeAwareLogger;
       5: putstatic     #15                 // Field logger:Lorg/apache/dubbo/common/logger/ErrorTypeAwareLogger;
       8: ldc           #27                 // String attachments\\[(.+)\\]
      10: invokestatic  #28                 // Method java/util/regex/Pattern.compile:(Ljava/lang/String;)Ljava/util/regex/Pattern;
      13: putstatic     #6                  // Field ATTACHMENTS_PATTERN:Ljava/util/regex/Pattern;
      16: return
}
