Compiled from "MeshRuleDispatcher.java"
public class org.apache.dubbo.rpc.cluster.router.mesh.util.MeshRuleDispatcher {
  private static final org.apache.dubbo.common.logger.ErrorTypeAwareLogger logger;

  private final java.lang.String appName;

  private final java.util.concurrent.ConcurrentMap<java.lang.String, java.util.Set<org.apache.dubbo.rpc.cluster.router.mesh.util.MeshRuleListener>> listenerMap;

  public org.apache.dubbo.rpc.cluster.router.mesh.util.MeshRuleDispatcher(java.lang.String);
    Code:
       0: aload_0
       1: invokespecial #2                  // Method java/lang/Object."<init>":()V
       4: aload_0
       5: new           #3                  // class java/util/concurrent/ConcurrentHashMap
       8: dup
       9: invokespecial #4                  // Method java/util/concurrent/ConcurrentHashMap."<init>":()V
      12: putfield      #5                  // Field listenerMap:Ljava/util/concurrent/ConcurrentMap;
      15: aload_0
      16: aload_1
      17: putfield      #6                  // Field appName:Ljava/lang/String;
      20: return

  public synchronized void post(java.util.Map<java.lang.String, java.util.List<java.util.Map<java.lang.String, java.lang.Object>>>);
    Code:
       0: aload_1
       1: invokeinterface #7,  1            // InterfaceMethod java/util/Map.isEmpty:()Z
       6: ifeq          101
       9: aload_0
      10: getfield      #5                  // Field listenerMap:Ljava/util/concurrent/ConcurrentMap;
      13: invokeinterface #8,  1            // InterfaceMethod java/util/concurrent/ConcurrentMap.entrySet:()Ljava/util/Set;
      18: invokeinterface #9,  1            // InterfaceMethod java/util/Set.iterator:()Ljava/util/Iterator;
      23: astore_2
      24: aload_2
      25: invokeinterface #10,  1           // InterfaceMethod java/util/Iterator.hasNext:()Z
      30: ifeq          98
      33: aload_2
      34: invokeinterface #11,  1           // InterfaceMethod java/util/Iterator.next:()Ljava/lang/Object;
      39: checkcast     #12                 // class java/util/Map$Entry
      42: astore_3
      43: aload_3
      44: invokeinterface #13,  1           // InterfaceMethod java/util/Map$Entry.getValue:()Ljava/lang/Object;
      49: checkcast     #14                 // class java/util/Set
      52: invokeinterface #9,  1            // InterfaceMethod java/util/Set.iterator:()Ljava/util/Iterator;
      57: astore        4
      59: aload         4
      61: invokeinterface #10,  1           // InterfaceMethod java/util/Iterator.hasNext:()Z
      66: ifeq          95
      69: aload         4
      71: invokeinterface #11,  1           // InterfaceMethod java/util/Iterator.next:()Ljava/lang/Object;
      76: checkcast     #15                 // class org/apache/dubbo/rpc/cluster/router/mesh/util/MeshRuleListener
      79: astore        5
      81: aload         5
      83: aload_0
      84: getfield      #6                  // Field appName:Ljava/lang/String;
      87: invokeinterface #16,  2           // InterfaceMethod org/apache/dubbo/rpc/cluster/router/mesh/util/MeshRuleListener.clearRule:(Ljava/lang/String;)V
      92: goto          59
      95: goto          24
      98: goto          365
     101: aload_1
     102: invokeinterface #17,  1           // InterfaceMethod java/util/Map.entrySet:()Ljava/util/Set;
     107: invokeinterface #9,  1            // InterfaceMethod java/util/Set.iterator:()Ljava/util/Iterator;
     112: astore_2
     113: aload_2
     114: invokeinterface #10,  1           // InterfaceMethod java/util/Iterator.hasNext:()Z
     119: ifeq          261
     122: aload_2
     123: invokeinterface #11,  1           // InterfaceMethod java/util/Iterator.next:()Ljava/lang/Object;
     128: checkcast     #12                 // class java/util/Map$Entry
     131: astore_3
     132: aload_3
     133: invokeinterface #18,  1           // InterfaceMethod java/util/Map$Entry.getKey:()Ljava/lang/Object;
     138: checkcast     #19                 // class java/lang/String
     141: astore        4
     143: aload_0
     144: getfield      #5                  // Field listenerMap:Ljava/util/concurrent/ConcurrentMap;
     147: aload         4
     149: invokeinterface #20,  2           // InterfaceMethod java/util/concurrent/ConcurrentMap.get:(Ljava/lang/Object;)Ljava/lang/Object;
     154: checkcast     #14                 // class java/util/Set
     157: astore        5
     159: aload         5
     161: invokestatic  #21                 // Method org/apache/dubbo/common/utils/CollectionUtils.isNotEmpty:(Ljava/util/Collection;)Z
     164: ifeq          224
     167: aload         5
     169: invokeinterface #9,  1            // InterfaceMethod java/util/Set.iterator:()Ljava/util/Iterator;
     174: astore        6
     176: aload         6
     178: invokeinterface #10,  1           // InterfaceMethod java/util/Iterator.hasNext:()Z
     183: ifeq          221
     186: aload         6
     188: invokeinterface #11,  1           // InterfaceMethod java/util/Iterator.next:()Ljava/lang/Object;
     193: checkcast     #15                 // class org/apache/dubbo/rpc/cluster/router/mesh/util/MeshRuleListener
     196: astore        7
     198: aload         7
     200: aload_0
     201: getfield      #6                  // Field appName:Ljava/lang/String;
     204: aload_3
     205: invokeinterface #13,  1           // InterfaceMethod java/util/Map$Entry.getValue:()Ljava/lang/Object;
     210: checkcast     #22                 // class java/util/List
     213: invokeinterface #23,  3           // InterfaceMethod org/apache/dubbo/rpc/cluster/router/mesh/util/MeshRuleListener.onRuleChange:(Ljava/lang/String;Ljava/util/List;)V
     218: goto          176
     221: goto          258
     224: getstatic     #24                 // Field logger:Lorg/apache/dubbo/common/logger/ErrorTypeAwareLogger;
     227: ldc           #25                 // String 2-18
     229: ldc           #26                 // String Receive mesh rule but none of listener has been registered
     231: ldc           #27                 // String
     233: new           #28                 // class java/lang/StringBuilder
     236: dup
     237: invokespecial #29                 // Method java/lang/StringBuilder."<init>":()V
     240: ldc           #30                 // String Receive rule but none of listener has been registered. Maybe type not matched. Rule Type:
     242: invokevirtual #31                 // Method java/lang/StringBuilder.append:(Ljava/lang/String;)Ljava/lang/StringBuilder;
     245: aload         4
     247: invokevirtual #31                 // Method java/lang/StringBuilder.append:(Ljava/lang/String;)Ljava/lang/StringBuilder;
     250: invokevirtual #32                 // Method java/lang/StringBuilder.toString:()Ljava/lang/String;
     253: invokeinterface #33,  5           // InterfaceMethod org/apache/dubbo/common/logger/ErrorTypeAwareLogger.warn:(Ljava/lang/String;Ljava/lang/String;Ljava/lang/String;Ljava/lang/String;)V
     258: goto          113
     261: aload_0
     262: getfield      #5                  // Field listenerMap:Ljava/util/concurrent/ConcurrentMap;
     265: invokeinterface #8,  1            // InterfaceMethod java/util/concurrent/ConcurrentMap.entrySet:()Ljava/util/Set;
     270: invokeinterface #9,  1            // InterfaceMethod java/util/Set.iterator:()Ljava/util/Iterator;
     275: astore_2
     276: aload_2
     277: invokeinterface #10,  1           // InterfaceMethod java/util/Iterator.hasNext:()Z
     282: ifeq          365
     285: aload_2
     286: invokeinterface #11,  1           // InterfaceMethod java/util/Iterator.next:()Ljava/lang/Object;
     291: checkcast     #12                 // class java/util/Map$Entry
     294: astore_3
     295: aload_1
     296: aload_3
     297: invokeinterface #18,  1           // InterfaceMethod java/util/Map$Entry.getKey:()Ljava/lang/Object;
     302: invokeinterface #34,  2           // InterfaceMethod java/util/Map.containsKey:(Ljava/lang/Object;)Z
     307: ifne          362
     310: aload_3
     311: invokeinterface #13,  1           // InterfaceMethod java/util/Map$Entry.getValue:()Ljava/lang/Object;
     316: checkcast     #14                 // class java/util/Set
     319: invokeinterface #9,  1            // InterfaceMethod java/util/Set.iterator:()Ljava/util/Iterator;
     324: astore        4
     326: aload         4
     328: invokeinterface #10,  1           // InterfaceMethod java/util/Iterator.hasNext:()Z
     333: ifeq          362
     336: aload         4
     338: invokeinterface #11,  1           // InterfaceMethod java/util/Iterator.next:()Ljava/lang/Object;
     343: checkcast     #15                 // class org/apache/dubbo/rpc/cluster/router/mesh/util/MeshRuleListener
     346: astore        5
     348: aload         5
     350: aload_0
     351: getfield      #6                  // Field appName:Ljava/lang/String;
     354: invokeinterface #16,  2           // InterfaceMethod org/apache/dubbo/rpc/cluster/router/mesh/util/MeshRuleListener.clearRule:(Ljava/lang/String;)V
     359: goto          326
     362: goto          276
     365: return

  public synchronized void register(org.apache.dubbo.rpc.cluster.router.mesh.util.MeshRuleListener);
    Code:
       0: aload_1
       1: ifnonnull     5
       4: return
       5: aload_0
       6: getfield      #5                  // Field listenerMap:Ljava/util/concurrent/ConcurrentMap;
       9: aload_1
      10: invokeinterface #35,  1           // InterfaceMethod org/apache/dubbo/rpc/cluster/router/mesh/util/MeshRuleListener.ruleSuffix:()Ljava/lang/String;
      15: invokedynamic #36,  0             // InvokeDynamic #0:apply:()Ljava/util/function/Function;
      20: invokestatic  #37                 // Method org/apache/dubbo/common/utils/ConcurrentHashMapUtils.computeIfAbsent:(Ljava/util/concurrent/ConcurrentMap;Ljava/lang/Object;Ljava/util/function/Function;)Ljava/lang/Object;
      23: checkcast     #14                 // class java/util/Set
      26: aload_1
      27: invokeinterface #38,  2           // InterfaceMethod java/util/Set.add:(Ljava/lang/Object;)Z
      32: pop
      33: return

  public synchronized void unregister(org.apache.dubbo.rpc.cluster.router.mesh.util.MeshRuleListener);
    Code:
       0: aload_1
       1: ifnonnull     5
       4: return
       5: aload_0
       6: getfield      #5                  // Field listenerMap:Ljava/util/concurrent/ConcurrentMap;
       9: aload_1
      10: invokeinterface #35,  1           // InterfaceMethod org/apache/dubbo/rpc/cluster/router/mesh/util/MeshRuleListener.ruleSuffix:()Ljava/lang/String;
      15: invokeinterface #20,  2           // InterfaceMethod java/util/concurrent/ConcurrentMap.get:(Ljava/lang/Object;)Ljava/lang/Object;
      20: checkcast     #14                 // class java/util/Set
      23: astore_2
      24: aload_2
      25: invokestatic  #21                 // Method org/apache/dubbo/common/utils/CollectionUtils.isNotEmpty:(Ljava/util/Collection;)Z
      28: ifeq          39
      31: aload_2
      32: aload_1
      33: invokeinterface #39,  2           // InterfaceMethod java/util/Set.remove:(Ljava/lang/Object;)Z
      38: pop
      39: aload_2
      40: invokestatic  #40                 // Method org/apache/dubbo/common/utils/CollectionUtils.isEmpty:(Ljava/util/Collection;)Z
      43: ifeq          62
      46: aload_0
      47: getfield      #5                  // Field listenerMap:Ljava/util/concurrent/ConcurrentMap;
      50: aload_1
      51: invokeinterface #35,  1           // InterfaceMethod org/apache/dubbo/rpc/cluster/router/mesh/util/MeshRuleListener.ruleSuffix:()Ljava/lang/String;
      56: invokeinterface #41,  2           // InterfaceMethod java/util/concurrent/ConcurrentMap.remove:(Ljava/lang/Object;)Ljava/lang/Object;
      61: pop
      62: return

  public boolean isEmpty();
    Code:
       0: aload_0
       1: getfield      #5                  // Field listenerMap:Ljava/util/concurrent/ConcurrentMap;
       4: invokeinterface #42,  1           // InterfaceMethod java/util/concurrent/ConcurrentMap.isEmpty:()Z
       9: ireturn

  public java.util.Map<java.lang.String, java.util.Set<org.apache.dubbo.rpc.cluster.router.mesh.util.MeshRuleListener>> getListenerMap();
    Code:
       0: aload_0
       1: getfield      #5                  // Field listenerMap:Ljava/util/concurrent/ConcurrentMap;
       4: areturn

  private static java.util.Set lambda$register$0(java.lang.String);
    Code:
       0: new           #43                 // class org/apache/dubbo/common/utils/ConcurrentHashSet
       3: dup
       4: invokespecial #44                 // Method org/apache/dubbo/common/utils/ConcurrentHashSet."<init>":()V
       7: areturn

  static {};
    Code:
       0: ldc           #45                 // class org/apache/dubbo/rpc/cluster/router/mesh/util/MeshRuleDispatcher
       2: invokestatic  #46                 // Method org/apache/dubbo/common/logger/LoggerFactory.getErrorTypeAwareLogger:(Ljava/lang/Class;)Lorg/apache/dubbo/common/logger/ErrorTypeAwareLogger;
       5: putstatic     #24                 // Field logger:Lorg/apache/dubbo/common/logger/ErrorTypeAwareLogger;
       8: return
}
