Compiled from "DebugInfo.java"
public final class com.google.rpc.DebugInfo extends com.google.protobuf.GeneratedMessageV3 implements com.google.rpc.DebugInfoOrBuilder {
  private static final long serialVersionUID;

  public static final int STACK_ENTRIES_FIELD_NUMBER;

  private com.google.protobuf.LazyStringArrayList stackEntries_;

  public static final int DETAIL_FIELD_NUMBER;

  private volatile java.lang.Object detail_;

  private byte memoizedIsInitialized;

  private static final com.google.rpc.DebugInfo DEFAULT_INSTANCE;

  private static final com.google.protobuf.Parser<com.google.rpc.DebugInfo> PARSER;

  private com.google.rpc.DebugInfo(com.google.protobuf.GeneratedMessageV3$Builder<?>);
    Code:
       0: aload_0
       1: aload_1
       2: invokespecial #5                  // Method com/google/protobuf/GeneratedMessageV3."<init>":(Lcom/google/protobuf/GeneratedMessageV3$Builder;)V
       5: aload_0
       6: invokestatic  #6                  // Method com/google/protobuf/LazyStringArrayList.emptyList:()Lcom/google/protobuf/LazyStringArrayList;
       9: putfield      #3                  // Field stackEntries_:Lcom/google/protobuf/LazyStringArrayList;
      12: aload_0
      13: ldc           #7                  // String
      15: putfield      #2                  // Field detail_:Ljava/lang/Object;
      18: aload_0
      19: iconst_m1
      20: putfield      #8                  // Field memoizedIsInitialized:B
      23: return

  private com.google.rpc.DebugInfo();
    Code:
       0: aload_0
       1: invokespecial #9                  // Method com/google/protobuf/GeneratedMessageV3."<init>":()V
       4: aload_0
       5: invokestatic  #6                  // Method com/google/protobuf/LazyStringArrayList.emptyList:()Lcom/google/protobuf/LazyStringArrayList;
       8: putfield      #3                  // Field stackEntries_:Lcom/google/protobuf/LazyStringArrayList;
      11: aload_0
      12: ldc           #7                  // String
      14: putfield      #2                  // Field detail_:Ljava/lang/Object;
      17: aload_0
      18: iconst_m1
      19: putfield      #8                  // Field memoizedIsInitialized:B
      22: aload_0
      23: invokestatic  #6                  // Method com/google/protobuf/LazyStringArrayList.emptyList:()Lcom/google/protobuf/LazyStringArrayList;
      26: putfield      #3                  // Field stackEntries_:Lcom/google/protobuf/LazyStringArrayList;
      29: aload_0
      30: ldc           #7                  // String
      32: putfield      #2                  // Field detail_:Ljava/lang/Object;
      35: return

  protected java.lang.Object newInstance(com.google.protobuf.GeneratedMessageV3$UnusedPrivateParameter);
    Code:
       0: new           #10                 // class com/google/rpc/DebugInfo
       3: dup
       4: invokespecial #11                 // Method "<init>":()V
       7: areturn

  public static final com.google.protobuf.Descriptors$Descriptor getDescriptor();
    Code:
       0: getstatic     #12                 // Field com/google/rpc/ErrorDetailsProto.internal_static_google_rpc_DebugInfo_descriptor:Lcom/google/protobuf/Descriptors$Descriptor;
       3: areturn

  protected com.google.protobuf.GeneratedMessageV3$FieldAccessorTable internalGetFieldAccessorTable();
    Code:
       0: getstatic     #13                 // Field com/google/rpc/ErrorDetailsProto.internal_static_google_rpc_DebugInfo_fieldAccessorTable:Lcom/google/protobuf/GeneratedMessageV3$FieldAccessorTable;
       3: ldc           #10                 // class com/google/rpc/DebugInfo
       5: ldc           #14                 // class com/google/rpc/DebugInfo$Builder
       7: invokevirtual #15                 // Method com/google/protobuf/GeneratedMessageV3$FieldAccessorTable.ensureFieldAccessorsInitialized:(Ljava/lang/Class;Ljava/lang/Class;)Lcom/google/protobuf/GeneratedMessageV3$FieldAccessorTable;
      10: areturn

  public com.google.protobuf.ProtocolStringList getStackEntriesList();
    Code:
       0: aload_0
       1: getfield      #3                  // Field stackEntries_:Lcom/google/protobuf/LazyStringArrayList;
       4: areturn

  public int getStackEntriesCount();
    Code:
       0: aload_0
       1: getfield      #3                  // Field stackEntries_:Lcom/google/protobuf/LazyStringArrayList;
       4: invokevirtual #16                 // Method com/google/protobuf/LazyStringArrayList.size:()I
       7: ireturn

  public java.lang.String getStackEntries(int);
    Code:
       0: aload_0
       1: getfield      #3                  // Field stackEntries_:Lcom/google/protobuf/LazyStringArrayList;
       4: iload_1
       5: invokevirtual #17                 // Method com/google/protobuf/LazyStringArrayList.get:(I)Ljava/lang/String;
       8: areturn

  public com.google.protobuf.ByteString getStackEntriesBytes(int);
    Code:
       0: aload_0
       1: getfield      #3                  // Field stackEntries_:Lcom/google/protobuf/LazyStringArrayList;
       4: iload_1
       5: invokevirtual #18                 // Method com/google/protobuf/LazyStringArrayList.getByteString:(I)Lcom/google/protobuf/ByteString;
       8: areturn

  public java.lang.String getDetail();
    Code:
       0: aload_0
       1: getfield      #2                  // Field detail_:Ljava/lang/Object;
       4: astore_1
       5: aload_1
       6: instanceof    #19                 // class java/lang/String
       9: ifeq          17
      12: aload_1
      13: checkcast     #19                 // class java/lang/String
      16: areturn
      17: aload_1
      18: checkcast     #20                 // class com/google/protobuf/ByteString
      21: astore_2
      22: aload_2
      23: invokevirtual #21                 // Method com/google/protobuf/ByteString.toStringUtf8:()Ljava/lang/String;
      26: astore_3
      27: aload_0
      28: aload_3
      29: putfield      #2                  // Field detail_:Ljava/lang/Object;
      32: aload_3
      33: areturn

  public com.google.protobuf.ByteString getDetailBytes();
    Code:
       0: aload_0
       1: getfield      #2                  // Field detail_:Ljava/lang/Object;
       4: astore_1
       5: aload_1
       6: instanceof    #19                 // class java/lang/String
       9: ifeq          27
      12: aload_1
      13: checkcast     #19                 // class java/lang/String
      16: invokestatic  #22                 // Method com/google/protobuf/ByteString.copyFromUtf8:(Ljava/lang/String;)Lcom/google/protobuf/ByteString;
      19: astore_2
      20: aload_0
      21: aload_2
      22: putfield      #2                  // Field detail_:Ljava/lang/Object;
      25: aload_2
      26: areturn
      27: aload_1
      28: checkcast     #20                 // class com/google/protobuf/ByteString
      31: areturn

  public final boolean isInitialized();
    Code:
       0: aload_0
       1: getfield      #8                  // Field memoizedIsInitialized:B
       4: istore_1
       5: iload_1
       6: iconst_1
       7: if_icmpne     12
      10: iconst_1
      11: ireturn
      12: iload_1
      13: ifne          18
      16: iconst_0
      17: ireturn
      18: aload_0
      19: iconst_1
      20: putfield      #8                  // Field memoizedIsInitialized:B
      23: iconst_1
      24: ireturn

  public void writeTo(com.google.protobuf.CodedOutputStream) throws java.io.IOException;
    Code:
       0: iconst_0
       1: istore_2
       2: iload_2
       3: aload_0
       4: getfield      #3                  // Field stackEntries_:Lcom/google/protobuf/LazyStringArrayList;
       7: invokevirtual #16                 // Method com/google/protobuf/LazyStringArrayList.size:()I
      10: if_icmpge     32
      13: aload_1
      14: iconst_1
      15: aload_0
      16: getfield      #3                  // Field stackEntries_:Lcom/google/protobuf/LazyStringArrayList;
      19: iload_2
      20: invokevirtual #23                 // Method com/google/protobuf/LazyStringArrayList.getRaw:(I)Ljava/lang/Object;
      23: invokestatic  #24                 // Method com/google/protobuf/GeneratedMessageV3.writeString:(Lcom/google/protobuf/CodedOutputStream;ILjava/lang/Object;)V
      26: iinc          2, 1
      29: goto          2
      32: aload_0
      33: getfield      #2                  // Field detail_:Ljava/lang/Object;
      36: invokestatic  #25                 // Method com/google/protobuf/GeneratedMessageV3.isStringEmpty:(Ljava/lang/Object;)Z
      39: ifne          51
      42: aload_1
      43: iconst_2
      44: aload_0
      45: getfield      #2                  // Field detail_:Ljava/lang/Object;
      48: invokestatic  #24                 // Method com/google/protobuf/GeneratedMessageV3.writeString:(Lcom/google/protobuf/CodedOutputStream;ILjava/lang/Object;)V
      51: aload_0
      52: invokevirtual #26                 // Method getUnknownFields:()Lcom/google/protobuf/UnknownFieldSet;
      55: aload_1
      56: invokevirtual #27                 // Method com/google/protobuf/UnknownFieldSet.writeTo:(Lcom/google/protobuf/CodedOutputStream;)V
      59: return

  public int getSerializedSize();
    Code:
       0: aload_0
       1: getfield      #28                 // Field memoizedSize:I
       4: istore_1
       5: iload_1
       6: iconst_m1
       7: if_icmpeq     12
      10: iload_1
      11: ireturn
      12: iconst_0
      13: istore_1
      14: iconst_0
      15: istore_2
      16: iconst_0
      17: istore_3
      18: iload_3
      19: aload_0
      20: getfield      #3                  // Field stackEntries_:Lcom/google/protobuf/LazyStringArrayList;
      23: invokevirtual #16                 // Method com/google/protobuf/LazyStringArrayList.size:()I
      26: if_icmpge     49
      29: iload_2
      30: aload_0
      31: getfield      #3                  // Field stackEntries_:Lcom/google/protobuf/LazyStringArrayList;
      34: iload_3
      35: invokevirtual #23                 // Method com/google/protobuf/LazyStringArrayList.getRaw:(I)Ljava/lang/Object;
      38: invokestatic  #29                 // Method computeStringSizeNoTag:(Ljava/lang/Object;)I
      41: iadd
      42: istore_2
      43: iinc          3, 1
      46: goto          18
      49: iload_1
      50: iload_2
      51: iadd
      52: istore_1
      53: iload_1
      54: iconst_1
      55: aload_0
      56: invokevirtual #30                 // Method getStackEntriesList:()Lcom/google/protobuf/ProtocolStringList;
      59: invokeinterface #31,  1           // InterfaceMethod com/google/protobuf/ProtocolStringList.size:()I
      64: imul
      65: iadd
      66: istore_1
      67: aload_0
      68: getfield      #2                  // Field detail_:Ljava/lang/Object;
      71: invokestatic  #25                 // Method com/google/protobuf/GeneratedMessageV3.isStringEmpty:(Ljava/lang/Object;)Z
      74: ifne          88
      77: iload_1
      78: iconst_2
      79: aload_0
      80: getfield      #2                  // Field detail_:Ljava/lang/Object;
      83: invokestatic  #32                 // Method com/google/protobuf/GeneratedMessageV3.computeStringSize:(ILjava/lang/Object;)I
      86: iadd
      87: istore_1
      88: iload_1
      89: aload_0
      90: invokevirtual #26                 // Method getUnknownFields:()Lcom/google/protobuf/UnknownFieldSet;
      93: invokevirtual #33                 // Method com/google/protobuf/UnknownFieldSet.getSerializedSize:()I
      96: iadd
      97: istore_1
      98: aload_0
      99: iload_1
     100: putfield      #28                 // Field memoizedSize:I
     103: iload_1
     104: ireturn

  public boolean equals(java.lang.Object);
    Code:
       0: aload_1
       1: aload_0
       2: if_acmpne     7
       5: iconst_1
       6: ireturn
       7: aload_1
       8: instanceof    #10                 // class com/google/rpc/DebugInfo
      11: ifne          20
      14: aload_0
      15: aload_1
      16: invokespecial #34                 // Method com/google/protobuf/GeneratedMessageV3.equals:(Ljava/lang/Object;)Z
      19: ireturn
      20: aload_1
      21: checkcast     #10                 // class com/google/rpc/DebugInfo
      24: astore_2
      25: aload_0
      26: invokevirtual #30                 // Method getStackEntriesList:()Lcom/google/protobuf/ProtocolStringList;
      29: aload_2
      30: invokevirtual #30                 // Method getStackEntriesList:()Lcom/google/protobuf/ProtocolStringList;
      33: invokevirtual #35                 // Method java/lang/Object.equals:(Ljava/lang/Object;)Z
      36: ifne          41
      39: iconst_0
      40: ireturn
      41: aload_0
      42: invokevirtual #36                 // Method getDetail:()Ljava/lang/String;
      45: aload_2
      46: invokevirtual #36                 // Method getDetail:()Ljava/lang/String;
      49: invokevirtual #37                 // Method java/lang/String.equals:(Ljava/lang/Object;)Z
      52: ifne          57
      55: iconst_0
      56: ireturn
      57: aload_0
      58: invokevirtual #26                 // Method getUnknownFields:()Lcom/google/protobuf/UnknownFieldSet;
      61: aload_2
      62: invokevirtual #26                 // Method getUnknownFields:()Lcom/google/protobuf/UnknownFieldSet;
      65: invokevirtual #38                 // Method com/google/protobuf/UnknownFieldSet.equals:(Ljava/lang/Object;)Z
      68: ifne          73
      71: iconst_0
      72: ireturn
      73: iconst_1
      74: ireturn

  public int hashCode();
    Code:
       0: aload_0
       1: getfield      #39                 // Field memoizedHashCode:I
       4: ifeq          12
       7: aload_0
       8: getfield      #39                 // Field memoizedHashCode:I
      11: ireturn
      12: bipush        41
      14: istore_1
      15: bipush        19
      17: iload_1
      18: imul
      19: invokestatic  #40                 // Method getDescriptor:()Lcom/google/protobuf/Descriptors$Descriptor;
      22: invokevirtual #41                 // Method java/lang/Object.hashCode:()I
      25: iadd
      26: istore_1
      27: aload_0
      28: invokevirtual #42                 // Method getStackEntriesCount:()I
      31: ifle          54
      34: bipush        37
      36: iload_1
      37: imul
      38: iconst_1
      39: iadd
      40: istore_1
      41: bipush        53
      43: iload_1
      44: imul
      45: aload_0
      46: invokevirtual #30                 // Method getStackEntriesList:()Lcom/google/protobuf/ProtocolStringList;
      49: invokevirtual #41                 // Method java/lang/Object.hashCode:()I
      52: iadd
      53: istore_1
      54: bipush        37
      56: iload_1
      57: imul
      58: iconst_2
      59: iadd
      60: istore_1
      61: bipush        53
      63: iload_1
      64: imul
      65: aload_0
      66: invokevirtual #36                 // Method getDetail:()Ljava/lang/String;
      69: invokevirtual #43                 // Method java/lang/String.hashCode:()I
      72: iadd
      73: istore_1
      74: bipush        29
      76: iload_1
      77: imul
      78: aload_0
      79: invokevirtual #26                 // Method getUnknownFields:()Lcom/google/protobuf/UnknownFieldSet;
      82: invokevirtual #44                 // Method com/google/protobuf/UnknownFieldSet.hashCode:()I
      85: iadd
      86: istore_1
      87: aload_0
      88: iload_1
      89: putfield      #39                 // Field memoizedHashCode:I
      92: iload_1
      93: ireturn

  public static com.google.rpc.DebugInfo parseFrom(java.nio.ByteBuffer) throws com.google.protobuf.InvalidProtocolBufferException;
    Code:
       0: getstatic     #45                 // Field PARSER:Lcom/google/protobuf/Parser;
       3: aload_0
       4: invokeinterface #46,  2           // InterfaceMethod com/google/protobuf/Parser.parseFrom:(Ljava/nio/ByteBuffer;)Ljava/lang/Object;
       9: checkcast     #10                 // class com/google/rpc/DebugInfo
      12: areturn

  public static com.google.rpc.DebugInfo parseFrom(java.nio.ByteBuffer, com.google.protobuf.ExtensionRegistryLite) throws com.google.protobuf.InvalidProtocolBufferException;
    Code:
       0: getstatic     #45                 // Field PARSER:Lcom/google/protobuf/Parser;
       3: aload_0
       4: aload_1
       5: invokeinterface #47,  3           // InterfaceMethod com/google/protobuf/Parser.parseFrom:(Ljava/nio/ByteBuffer;Lcom/google/protobuf/ExtensionRegistryLite;)Ljava/lang/Object;
      10: checkcast     #10                 // class com/google/rpc/DebugInfo
      13: areturn

  public static com.google.rpc.DebugInfo parseFrom(com.google.protobuf.ByteString) throws com.google.protobuf.InvalidProtocolBufferException;
    Code:
       0: getstatic     #45                 // Field PARSER:Lcom/google/protobuf/Parser;
       3: aload_0
       4: invokeinterface #48,  2           // InterfaceMethod com/google/protobuf/Parser.parseFrom:(Lcom/google/protobuf/ByteString;)Ljava/lang/Object;
       9: checkcast     #10                 // class com/google/rpc/DebugInfo
      12: areturn

  public static com.google.rpc.DebugInfo parseFrom(com.google.protobuf.ByteString, com.google.protobuf.ExtensionRegistryLite) throws com.google.protobuf.InvalidProtocolBufferException;
    Code:
       0: getstatic     #45                 // Field PARSER:Lcom/google/protobuf/Parser;
       3: aload_0
       4: aload_1
       5: invokeinterface #49,  3           // InterfaceMethod com/google/protobuf/Parser.parseFrom:(Lcom/google/protobuf/ByteString;Lcom/google/protobuf/ExtensionRegistryLite;)Ljava/lang/Object;
      10: checkcast     #10                 // class com/google/rpc/DebugInfo
      13: areturn

  public static com.google.rpc.DebugInfo parseFrom(byte[]) throws com.google.protobuf.InvalidProtocolBufferException;
    Code:
       0: getstatic     #45                 // Field PARSER:Lcom/google/protobuf/Parser;
       3: aload_0
       4: invokeinterface #50,  2           // InterfaceMethod com/google/protobuf/Parser.parseFrom:([B)Ljava/lang/Object;
       9: checkcast     #10                 // class com/google/rpc/DebugInfo
      12: areturn

  public static com.google.rpc.DebugInfo parseFrom(byte[], com.google.protobuf.ExtensionRegistryLite) throws com.google.protobuf.InvalidProtocolBufferException;
    Code:
       0: getstatic     #45                 // Field PARSER:Lcom/google/protobuf/Parser;
       3: aload_0
       4: aload_1
       5: invokeinterface #51,  3           // InterfaceMethod com/google/protobuf/Parser.parseFrom:([BLcom/google/protobuf/ExtensionRegistryLite;)Ljava/lang/Object;
      10: checkcast     #10                 // class com/google/rpc/DebugInfo
      13: areturn

  public static com.google.rpc.DebugInfo parseFrom(java.io.InputStream) throws java.io.IOException;
    Code:
       0: getstatic     #45                 // Field PARSER:Lcom/google/protobuf/Parser;
       3: aload_0
       4: invokestatic  #52                 // Method com/google/protobuf/GeneratedMessageV3.parseWithIOException:(Lcom/google/protobuf/Parser;Ljava/io/InputStream;)Lcom/google/protobuf/Message;
       7: checkcast     #10                 // class com/google/rpc/DebugInfo
      10: areturn

  public static com.google.rpc.DebugInfo parseFrom(java.io.InputStream, com.google.protobuf.ExtensionRegistryLite) throws java.io.IOException;
    Code:
       0: getstatic     #45                 // Field PARSER:Lcom/google/protobuf/Parser;
       3: aload_0
       4: aload_1
       5: invokestatic  #53                 // Method com/google/protobuf/GeneratedMessageV3.parseWithIOException:(Lcom/google/protobuf/Parser;Ljava/io/InputStream;Lcom/google/protobuf/ExtensionRegistryLite;)Lcom/google/protobuf/Message;
       8: checkcast     #10                 // class com/google/rpc/DebugInfo
      11: areturn

  public static com.google.rpc.DebugInfo parseDelimitedFrom(java.io.InputStream) throws java.io.IOException;
    Code:
       0: getstatic     #45                 // Field PARSER:Lcom/google/protobuf/Parser;
       3: aload_0
       4: invokestatic  #54                 // Method com/google/protobuf/GeneratedMessageV3.parseDelimitedWithIOException:(Lcom/google/protobuf/Parser;Ljava/io/InputStream;)Lcom/google/protobuf/Message;
       7: checkcast     #10                 // class com/google/rpc/DebugInfo
      10: areturn

  public static com.google.rpc.DebugInfo parseDelimitedFrom(java.io.InputStream, com.google.protobuf.ExtensionRegistryLite) throws java.io.IOException;
    Code:
       0: getstatic     #45                 // Field PARSER:Lcom/google/protobuf/Parser;
       3: aload_0
       4: aload_1
       5: invokestatic  #55                 // Method com/google/protobuf/GeneratedMessageV3.parseDelimitedWithIOException:(Lcom/google/protobuf/Parser;Ljava/io/InputStream;Lcom/google/protobuf/ExtensionRegistryLite;)Lcom/google/protobuf/Message;
       8: checkcast     #10                 // class com/google/rpc/DebugInfo
      11: areturn

  public static com.google.rpc.DebugInfo parseFrom(com.google.protobuf.CodedInputStream) throws java.io.IOException;
    Code:
       0: getstatic     #45                 // Field PARSER:Lcom/google/protobuf/Parser;
       3: aload_0
       4: invokestatic  #56                 // Method com/google/protobuf/GeneratedMessageV3.parseWithIOException:(Lcom/google/protobuf/Parser;Lcom/google/protobuf/CodedInputStream;)Lcom/google/protobuf/Message;
       7: checkcast     #10                 // class com/google/rpc/DebugInfo
      10: areturn

  public static com.google.rpc.DebugInfo parseFrom(com.google.protobuf.CodedInputStream, com.google.protobuf.ExtensionRegistryLite) throws java.io.IOException;
    Code:
       0: getstatic     #45                 // Field PARSER:Lcom/google/protobuf/Parser;
       3: aload_0
       4: aload_1
       5: invokestatic  #57                 // Method com/google/protobuf/GeneratedMessageV3.parseWithIOException:(Lcom/google/protobuf/Parser;Lcom/google/protobuf/CodedInputStream;Lcom/google/protobuf/ExtensionRegistryLite;)Lcom/google/protobuf/Message;
       8: checkcast     #10                 // class com/google/rpc/DebugInfo
      11: areturn

  public com.google.rpc.DebugInfo$Builder newBuilderForType();
    Code:
       0: invokestatic  #58                 // Method newBuilder:()Lcom/google/rpc/DebugInfo$Builder;
       3: areturn

  public static com.google.rpc.DebugInfo$Builder newBuilder();
    Code:
       0: getstatic     #59                 // Field DEFAULT_INSTANCE:Lcom/google/rpc/DebugInfo;
       3: invokevirtual #60                 // Method toBuilder:()Lcom/google/rpc/DebugInfo$Builder;
       6: areturn

  public static com.google.rpc.DebugInfo$Builder newBuilder(com.google.rpc.DebugInfo);
    Code:
       0: getstatic     #59                 // Field DEFAULT_INSTANCE:Lcom/google/rpc/DebugInfo;
       3: invokevirtual #60                 // Method toBuilder:()Lcom/google/rpc/DebugInfo$Builder;
       6: aload_0
       7: invokevirtual #61                 // Method com/google/rpc/DebugInfo$Builder.mergeFrom:(Lcom/google/rpc/DebugInfo;)Lcom/google/rpc/DebugInfo$Builder;
      10: areturn

  public com.google.rpc.DebugInfo$Builder toBuilder();
    Code:
       0: aload_0
       1: getstatic     #59                 // Field DEFAULT_INSTANCE:Lcom/google/rpc/DebugInfo;
       4: if_acmpne     18
       7: new           #14                 // class com/google/rpc/DebugInfo$Builder
      10: dup
      11: aconst_null
      12: invokespecial #62                 // Method com/google/rpc/DebugInfo$Builder."<init>":(Lcom/google/rpc/DebugInfo$1;)V
      15: goto          30
      18: new           #14                 // class com/google/rpc/DebugInfo$Builder
      21: dup
      22: aconst_null
      23: invokespecial #62                 // Method com/google/rpc/DebugInfo$Builder."<init>":(Lcom/google/rpc/DebugInfo$1;)V
      26: aload_0
      27: invokevirtual #61                 // Method com/google/rpc/DebugInfo$Builder.mergeFrom:(Lcom/google/rpc/DebugInfo;)Lcom/google/rpc/DebugInfo$Builder;
      30: areturn

  protected com.google.rpc.DebugInfo$Builder newBuilderForType(com.google.protobuf.GeneratedMessageV3$BuilderParent);
    Code:
       0: new           #14                 // class com/google/rpc/DebugInfo$Builder
       3: dup
       4: aload_1
       5: aconst_null
       6: invokespecial #63                 // Method com/google/rpc/DebugInfo$Builder."<init>":(Lcom/google/protobuf/GeneratedMessageV3$BuilderParent;Lcom/google/rpc/DebugInfo$1;)V
       9: astore_2
      10: aload_2
      11: areturn

  public static com.google.rpc.DebugInfo getDefaultInstance();
    Code:
       0: getstatic     #59                 // Field DEFAULT_INSTANCE:Lcom/google/rpc/DebugInfo;
       3: areturn

  public static com.google.protobuf.Parser<com.google.rpc.DebugInfo> parser();
    Code:
       0: getstatic     #45                 // Field PARSER:Lcom/google/protobuf/Parser;
       3: areturn

  public com.google.protobuf.Parser<com.google.rpc.DebugInfo> getParserForType();
    Code:
       0: getstatic     #45                 // Field PARSER:Lcom/google/protobuf/Parser;
       3: areturn

  public com.google.rpc.DebugInfo getDefaultInstanceForType();
    Code:
       0: getstatic     #59                 // Field DEFAULT_INSTANCE:Lcom/google/rpc/DebugInfo;
       3: areturn

  protected com.google.protobuf.Message$Builder newBuilderForType(com.google.protobuf.GeneratedMessageV3$BuilderParent);
    Code:
       0: aload_0
       1: aload_1
       2: invokevirtual #64                 // Method newBuilderForType:(Lcom/google/protobuf/GeneratedMessageV3$BuilderParent;)Lcom/google/rpc/DebugInfo$Builder;
       5: areturn

  public com.google.protobuf.Message$Builder toBuilder();
    Code:
       0: aload_0
       1: invokevirtual #60                 // Method toBuilder:()Lcom/google/rpc/DebugInfo$Builder;
       4: areturn

  public com.google.protobuf.Message$Builder newBuilderForType();
    Code:
       0: aload_0
       1: invokevirtual #65                 // Method newBuilderForType:()Lcom/google/rpc/DebugInfo$Builder;
       4: areturn

  public com.google.protobuf.MessageLite$Builder toBuilder();
    Code:
       0: aload_0
       1: invokevirtual #60                 // Method toBuilder:()Lcom/google/rpc/DebugInfo$Builder;
       4: areturn

  public com.google.protobuf.MessageLite$Builder newBuilderForType();
    Code:
       0: aload_0
       1: invokevirtual #65                 // Method newBuilderForType:()Lcom/google/rpc/DebugInfo$Builder;
       4: areturn

  public com.google.protobuf.MessageLite getDefaultInstanceForType();
    Code:
       0: aload_0
       1: invokevirtual #66                 // Method getDefaultInstanceForType:()Lcom/google/rpc/DebugInfo;
       4: areturn

  public com.google.protobuf.Message getDefaultInstanceForType();
    Code:
       0: aload_0
       1: invokevirtual #66                 // Method getDefaultInstanceForType:()Lcom/google/rpc/DebugInfo;
       4: areturn

  public java.util.List getStackEntriesList();
    Code:
       0: aload_0
       1: invokevirtual #30                 // Method getStackEntriesList:()Lcom/google/protobuf/ProtocolStringList;
       4: areturn

  com.google.rpc.DebugInfo(com.google.protobuf.GeneratedMessageV3$Builder, com.google.rpc.DebugInfo$1);
    Code:
       0: aload_0
       1: aload_1
       2: invokespecial #4                  // Method "<init>":(Lcom/google/protobuf/GeneratedMessageV3$Builder;)V
       5: return

  static com.google.protobuf.LazyStringArrayList access$302(com.google.rpc.DebugInfo, com.google.protobuf.LazyStringArrayList);
    Code:
       0: aload_0
       1: aload_1
       2: dup_x1
       3: putfield      #3                  // Field stackEntries_:Lcom/google/protobuf/LazyStringArrayList;
       6: areturn

  static java.lang.Object access$402(com.google.rpc.DebugInfo, java.lang.Object);
    Code:
       0: aload_0
       1: aload_1
       2: dup_x1
       3: putfield      #2                  // Field detail_:Ljava/lang/Object;
       6: areturn

  static com.google.protobuf.LazyStringArrayList access$300(com.google.rpc.DebugInfo);
    Code:
       0: aload_0
       1: getfield      #3                  // Field stackEntries_:Lcom/google/protobuf/LazyStringArrayList;
       4: areturn

  static java.lang.Object access$400(com.google.rpc.DebugInfo);
    Code:
       0: aload_0
       1: getfield      #2                  // Field detail_:Ljava/lang/Object;
       4: areturn

  static void access$500(com.google.protobuf.ByteString) throws java.lang.IllegalArgumentException;
    Code:
       0: aload_0
       1: invokestatic  #1                  // Method checkByteStringIsUtf8:(Lcom/google/protobuf/ByteString;)V
       4: return

  static void access$600(com.google.protobuf.ByteString) throws java.lang.IllegalArgumentException;
    Code:
       0: aload_0
       1: invokestatic  #1                  // Method checkByteStringIsUtf8:(Lcom/google/protobuf/ByteString;)V
       4: return

  static {};
    Code:
       0: new           #10                 // class com/google/rpc/DebugInfo
       3: dup
       4: invokespecial #11                 // Method "<init>":()V
       7: putstatic     #59                 // Field DEFAULT_INSTANCE:Lcom/google/rpc/DebugInfo;
      10: new           #67                 // class com/google/rpc/DebugInfo$1
      13: dup
      14: invokespecial #68                 // Method com/google/rpc/DebugInfo$1."<init>":()V
      17: putstatic     #45                 // Field PARSER:Lcom/google/protobuf/Parser;
      20: return
}
