Compiled from "DebugInfo.java"
public final class com.google.rpc.DebugInfo$Builder extends com.google.protobuf.GeneratedMessageV3$Builder<com.google.rpc.DebugInfo$Builder> implements com.google.rpc.DebugInfoOrBuilder {
  private int bitField0_;

  private com.google.protobuf.LazyStringArrayList stackEntries_;

  private java.lang.Object detail_;

  public static final com.google.protobuf.Descriptors$Descriptor getDescriptor();
    Code:
       0: getstatic     #3                  // Field com/google/rpc/ErrorDetailsProto.internal_static_google_rpc_DebugInfo_descriptor:Lcom/google/protobuf/Descriptors$Descriptor;
       3: areturn

  protected com.google.protobuf.GeneratedMessageV3$FieldAccessorTable internalGetFieldAccessorTable();
    Code:
       0: getstatic     #4                  // Field com/google/rpc/ErrorDetailsProto.internal_static_google_rpc_DebugInfo_fieldAccessorTable:Lcom/google/protobuf/GeneratedMessageV3$FieldAccessorTable;
       3: ldc           #5                  // class com/google/rpc/DebugInfo
       5: ldc           #6                  // class com/google/rpc/DebugInfo$Builder
       7: invokevirtual #7                  // Method com/google/protobuf/GeneratedMessageV3$FieldAccessorTable.ensureFieldAccessorsInitialized:(Ljava/lang/Class;Ljava/lang/Class;)Lcom/google/protobuf/GeneratedMessageV3$FieldAccessorTable;
      10: areturn

  private com.google.rpc.DebugInfo$Builder();
    Code:
       0: aload_0
       1: invokespecial #8                  // Method com/google/protobuf/GeneratedMessageV3$Builder."<init>":()V
       4: aload_0
       5: invokestatic  #9                  // Method com/google/protobuf/LazyStringArrayList.emptyList:()Lcom/google/protobuf/LazyStringArrayList;
       8: putfield      #10                 // Field stackEntries_:Lcom/google/protobuf/LazyStringArrayList;
      11: aload_0
      12: ldc           #11                 // String
      14: putfield      #12                 // Field detail_:Ljava/lang/Object;
      17: return

  private com.google.rpc.DebugInfo$Builder(com.google.protobuf.GeneratedMessageV3$BuilderParent);
    Code:
       0: aload_0
       1: aload_1
       2: invokespecial #13                 // Method com/google/protobuf/GeneratedMessageV3$Builder."<init>":(Lcom/google/protobuf/GeneratedMessageV3$BuilderParent;)V
       5: aload_0
       6: invokestatic  #9                  // Method com/google/protobuf/LazyStringArrayList.emptyList:()Lcom/google/protobuf/LazyStringArrayList;
       9: putfield      #10                 // Field stackEntries_:Lcom/google/protobuf/LazyStringArrayList;
      12: aload_0
      13: ldc           #11                 // String
      15: putfield      #12                 // Field detail_:Ljava/lang/Object;
      18: return

  public com.google.rpc.DebugInfo$Builder clear();
    Code:
       0: aload_0
       1: invokespecial #14                 // Method com/google/protobuf/GeneratedMessageV3$Builder.clear:()Lcom/google/protobuf/GeneratedMessageV3$Builder;
       4: pop
       5: aload_0
       6: iconst_0
       7: putfield      #15                 // Field bitField0_:I
      10: aload_0
      11: invokestatic  #9                  // Method com/google/protobuf/LazyStringArrayList.emptyList:()Lcom/google/protobuf/LazyStringArrayList;
      14: putfield      #10                 // Field stackEntries_:Lcom/google/protobuf/LazyStringArrayList;
      17: aload_0
      18: ldc           #11                 // String
      20: putfield      #12                 // Field detail_:Ljava/lang/Object;
      23: aload_0
      24: areturn

  public com.google.protobuf.Descriptors$Descriptor getDescriptorForType();
    Code:
       0: getstatic     #3                  // Field com/google/rpc/ErrorDetailsProto.internal_static_google_rpc_DebugInfo_descriptor:Lcom/google/protobuf/Descriptors$Descriptor;
       3: areturn

  public com.google.rpc.DebugInfo getDefaultInstanceForType();
    Code:
       0: invokestatic  #16                 // Method com/google/rpc/DebugInfo.getDefaultInstance:()Lcom/google/rpc/DebugInfo;
       3: areturn

  public com.google.rpc.DebugInfo build();
    Code:
       0: aload_0
       1: invokevirtual #17                 // Method buildPartial:()Lcom/google/rpc/DebugInfo;
       4: astore_1
       5: aload_1
       6: invokevirtual #18                 // Method com/google/rpc/DebugInfo.isInitialized:()Z
       9: ifne          17
      12: aload_1
      13: invokestatic  #19                 // Method newUninitializedMessageException:(Lcom/google/protobuf/Message;)Lcom/google/protobuf/UninitializedMessageException;
      16: athrow
      17: aload_1
      18: areturn

  public com.google.rpc.DebugInfo buildPartial();
    Code:
       0: new           #5                  // class com/google/rpc/DebugInfo
       3: dup
       4: aload_0
       5: aconst_null
       6: invokespecial #20                 // Method com/google/rpc/DebugInfo."<init>":(Lcom/google/protobuf/GeneratedMessageV3$Builder;Lcom/google/rpc/DebugInfo$1;)V
       9: astore_1
      10: aload_0
      11: getfield      #15                 // Field bitField0_:I
      14: ifeq          22
      17: aload_0
      18: aload_1
      19: invokespecial #21                 // Method buildPartial0:(Lcom/google/rpc/DebugInfo;)V
      22: aload_0
      23: invokevirtual #22                 // Method onBuilt:()V
      26: aload_1
      27: areturn

  private void buildPartial0(com.google.rpc.DebugInfo);
    Code:
       0: aload_0
       1: getfield      #15                 // Field bitField0_:I
       4: istore_2
       5: iload_2
       6: iconst_1
       7: iand
       8: ifeq          27
      11: aload_0
      12: getfield      #10                 // Field stackEntries_:Lcom/google/protobuf/LazyStringArrayList;
      15: invokevirtual #23                 // Method com/google/protobuf/LazyStringArrayList.makeImmutable:()V
      18: aload_1
      19: aload_0
      20: getfield      #10                 // Field stackEntries_:Lcom/google/protobuf/LazyStringArrayList;
      23: invokestatic  #24                 // Method com/google/rpc/DebugInfo.access$302:(Lcom/google/rpc/DebugInfo;Lcom/google/protobuf/LazyStringArrayList;)Lcom/google/protobuf/LazyStringArrayList;
      26: pop
      27: iload_2
      28: iconst_2
      29: iand
      30: ifeq          42
      33: aload_1
      34: aload_0
      35: getfield      #12                 // Field detail_:Ljava/lang/Object;
      38: invokestatic  #25                 // Method com/google/rpc/DebugInfo.access$402:(Lcom/google/rpc/DebugInfo;Ljava/lang/Object;)Ljava/lang/Object;
      41: pop
      42: return

  public com.google.rpc.DebugInfo$Builder mergeFrom(com.google.protobuf.Message);
    Code:
       0: aload_1
       1: instanceof    #5                  // class com/google/rpc/DebugInfo
       4: ifeq          16
       7: aload_0
       8: aload_1
       9: checkcast     #5                  // class com/google/rpc/DebugInfo
      12: invokevirtual #26                 // Method mergeFrom:(Lcom/google/rpc/DebugInfo;)Lcom/google/rpc/DebugInfo$Builder;
      15: areturn
      16: aload_0
      17: aload_1
      18: invokespecial #27                 // Method com/google/protobuf/GeneratedMessageV3$Builder.mergeFrom:(Lcom/google/protobuf/Message;)Lcom/google/protobuf/AbstractMessage$Builder;
      21: pop
      22: aload_0
      23: areturn

  public com.google.rpc.DebugInfo$Builder mergeFrom(com.google.rpc.DebugInfo);
    Code:
       0: aload_1
       1: invokestatic  #16                 // Method com/google/rpc/DebugInfo.getDefaultInstance:()Lcom/google/rpc/DebugInfo;
       4: if_acmpne     9
       7: aload_0
       8: areturn
       9: aload_1
      10: invokestatic  #28                 // Method com/google/rpc/DebugInfo.access$300:(Lcom/google/rpc/DebugInfo;)Lcom/google/protobuf/LazyStringArrayList;
      13: invokevirtual #29                 // Method com/google/protobuf/LazyStringArrayList.isEmpty:()Z
      16: ifne          70
      19: aload_0
      20: getfield      #10                 // Field stackEntries_:Lcom/google/protobuf/LazyStringArrayList;
      23: invokevirtual #29                 // Method com/google/protobuf/LazyStringArrayList.isEmpty:()Z
      26: ifeq          50
      29: aload_0
      30: aload_1
      31: invokestatic  #28                 // Method com/google/rpc/DebugInfo.access$300:(Lcom/google/rpc/DebugInfo;)Lcom/google/protobuf/LazyStringArrayList;
      34: putfield      #10                 // Field stackEntries_:Lcom/google/protobuf/LazyStringArrayList;
      37: aload_0
      38: dup
      39: getfield      #15                 // Field bitField0_:I
      42: iconst_1
      43: ior
      44: putfield      #15                 // Field bitField0_:I
      47: goto          66
      50: aload_0
      51: invokespecial #30                 // Method ensureStackEntriesIsMutable:()V
      54: aload_0
      55: getfield      #10                 // Field stackEntries_:Lcom/google/protobuf/LazyStringArrayList;
      58: aload_1
      59: invokestatic  #28                 // Method com/google/rpc/DebugInfo.access$300:(Lcom/google/rpc/DebugInfo;)Lcom/google/protobuf/LazyStringArrayList;
      62: invokevirtual #31                 // Method com/google/protobuf/LazyStringArrayList.addAll:(Ljava/util/Collection;)Z
      65: pop
      66: aload_0
      67: invokevirtual #32                 // Method onChanged:()V
      70: aload_1
      71: invokevirtual #33                 // Method com/google/rpc/DebugInfo.getDetail:()Ljava/lang/String;
      74: invokevirtual #34                 // Method java/lang/String.isEmpty:()Z
      77: ifne          102
      80: aload_0
      81: aload_1
      82: invokestatic  #35                 // Method com/google/rpc/DebugInfo.access$400:(Lcom/google/rpc/DebugInfo;)Ljava/lang/Object;
      85: putfield      #12                 // Field detail_:Ljava/lang/Object;
      88: aload_0
      89: dup
      90: getfield      #15                 // Field bitField0_:I
      93: iconst_2
      94: ior
      95: putfield      #15                 // Field bitField0_:I
      98: aload_0
      99: invokevirtual #32                 // Method onChanged:()V
     102: aload_0
     103: aload_1
     104: invokevirtual #36                 // Method com/google/rpc/DebugInfo.getUnknownFields:()Lcom/google/protobuf/UnknownFieldSet;
     107: invokevirtual #37                 // Method mergeUnknownFields:(Lcom/google/protobuf/UnknownFieldSet;)Lcom/google/rpc/DebugInfo$Builder;
     110: pop
     111: aload_0
     112: invokevirtual #32                 // Method onChanged:()V
     115: aload_0
     116: areturn

  public final boolean isInitialized();
    Code:
       0: iconst_1
       1: ireturn

  public com.google.rpc.DebugInfo$Builder mergeFrom(com.google.protobuf.CodedInputStream, com.google.protobuf.ExtensionRegistryLite) throws java.io.IOException;
    Code:
       0: aload_2
       1: ifnonnull     12
       4: new           #38                 // class java/lang/NullPointerException
       7: dup
       8: invokespecial #39                 // Method java/lang/NullPointerException."<init>":()V
      11: athrow
      12: iconst_0
      13: istore_3
      14: iload_3
      15: ifne          125
      18: aload_1
      19: invokevirtual #40                 // Method com/google/protobuf/CodedInputStream.readTag:()I
      22: istore        4
      24: iload         4
      26: lookupswitch  { // 3
                     0: 60
                    10: 65
                    18: 88
               default: 109
          }
      60: iconst_1
      61: istore_3
      62: goto          122
      65: aload_1
      66: invokevirtual #41                 // Method com/google/protobuf/CodedInputStream.readStringRequireUtf8:()Ljava/lang/String;
      69: astore        5
      71: aload_0
      72: invokespecial #30                 // Method ensureStackEntriesIsMutable:()V
      75: aload_0
      76: getfield      #10                 // Field stackEntries_:Lcom/google/protobuf/LazyStringArrayList;
      79: aload         5
      81: invokevirtual #42                 // Method com/google/protobuf/LazyStringArrayList.add:(Ljava/lang/Object;)Z
      84: pop
      85: goto          122
      88: aload_0
      89: aload_1
      90: invokevirtual #41                 // Method com/google/protobuf/CodedInputStream.readStringRequireUtf8:()Ljava/lang/String;
      93: putfield      #12                 // Field detail_:Ljava/lang/Object;
      96: aload_0
      97: dup
      98: getfield      #15                 // Field bitField0_:I
     101: iconst_2
     102: ior
     103: putfield      #15                 // Field bitField0_:I
     106: goto          122
     109: aload_0
     110: aload_1
     111: aload_2
     112: iload         4
     114: invokespecial #43                 // Method com/google/protobuf/GeneratedMessageV3$Builder.parseUnknownField:(Lcom/google/protobuf/CodedInputStream;Lcom/google/protobuf/ExtensionRegistryLite;I)Z
     117: ifne          122
     120: iconst_1
     121: istore_3
     122: goto          14
     125: aload_0
     126: invokevirtual #32                 // Method onChanged:()V
     129: goto          147
     132: astore_3
     133: aload_3
     134: invokevirtual #45                 // Method com/google/protobuf/InvalidProtocolBufferException.unwrapIOException:()Ljava/io/IOException;
     137: athrow
     138: astore        6
     140: aload_0
     141: invokevirtual #32                 // Method onChanged:()V
     144: aload         6
     146: athrow
     147: aload_0
     148: areturn
    Exception table:
       from    to  target type
          12   125   132   Class com/google/protobuf/InvalidProtocolBufferException
          12   125   138   any
         132   140   138   any

  private void ensureStackEntriesIsMutable();
    Code:
       0: aload_0
       1: getfield      #10                 // Field stackEntries_:Lcom/google/protobuf/LazyStringArrayList;
       4: invokevirtual #46                 // Method com/google/protobuf/LazyStringArrayList.isModifiable:()Z
       7: ifne          25
      10: aload_0
      11: new           #47                 // class com/google/protobuf/LazyStringArrayList
      14: dup
      15: aload_0
      16: getfield      #10                 // Field stackEntries_:Lcom/google/protobuf/LazyStringArrayList;
      19: invokespecial #48                 // Method com/google/protobuf/LazyStringArrayList."<init>":(Lcom/google/protobuf/LazyStringList;)V
      22: putfield      #10                 // Field stackEntries_:Lcom/google/protobuf/LazyStringArrayList;
      25: aload_0
      26: dup
      27: getfield      #15                 // Field bitField0_:I
      30: iconst_1
      31: ior
      32: putfield      #15                 // Field bitField0_:I
      35: return

  public com.google.protobuf.ProtocolStringList getStackEntriesList();
    Code:
       0: aload_0
       1: getfield      #10                 // Field stackEntries_:Lcom/google/protobuf/LazyStringArrayList;
       4: invokevirtual #23                 // Method com/google/protobuf/LazyStringArrayList.makeImmutable:()V
       7: aload_0
       8: getfield      #10                 // Field stackEntries_:Lcom/google/protobuf/LazyStringArrayList;
      11: areturn

  public int getStackEntriesCount();
    Code:
       0: aload_0
       1: getfield      #10                 // Field stackEntries_:Lcom/google/protobuf/LazyStringArrayList;
       4: invokevirtual #49                 // Method com/google/protobuf/LazyStringArrayList.size:()I
       7: ireturn

  public java.lang.String getStackEntries(int);
    Code:
       0: aload_0
       1: getfield      #10                 // Field stackEntries_:Lcom/google/protobuf/LazyStringArrayList;
       4: iload_1
       5: invokevirtual #50                 // Method com/google/protobuf/LazyStringArrayList.get:(I)Ljava/lang/String;
       8: areturn

  public com.google.protobuf.ByteString getStackEntriesBytes(int);
    Code:
       0: aload_0
       1: getfield      #10                 // Field stackEntries_:Lcom/google/protobuf/LazyStringArrayList;
       4: iload_1
       5: invokevirtual #51                 // Method com/google/protobuf/LazyStringArrayList.getByteString:(I)Lcom/google/protobuf/ByteString;
       8: areturn

  public com.google.rpc.DebugInfo$Builder setStackEntries(int, java.lang.String);
    Code:
       0: aload_2
       1: ifnonnull     12
       4: new           #38                 // class java/lang/NullPointerException
       7: dup
       8: invokespecial #39                 // Method java/lang/NullPointerException."<init>":()V
      11: athrow
      12: aload_0
      13: invokespecial #30                 // Method ensureStackEntriesIsMutable:()V
      16: aload_0
      17: getfield      #10                 // Field stackEntries_:Lcom/google/protobuf/LazyStringArrayList;
      20: iload_1
      21: aload_2
      22: invokevirtual #52                 // Method com/google/protobuf/LazyStringArrayList.set:(ILjava/lang/String;)Ljava/lang/String;
      25: pop
      26: aload_0
      27: dup
      28: getfield      #15                 // Field bitField0_:I
      31: iconst_1
      32: ior
      33: putfield      #15                 // Field bitField0_:I
      36: aload_0
      37: invokevirtual #32                 // Method onChanged:()V
      40: aload_0
      41: areturn

  public com.google.rpc.DebugInfo$Builder addStackEntries(java.lang.String);
    Code:
       0: aload_1
       1: ifnonnull     12
       4: new           #38                 // class java/lang/NullPointerException
       7: dup
       8: invokespecial #39                 // Method java/lang/NullPointerException."<init>":()V
      11: athrow
      12: aload_0
      13: invokespecial #30                 // Method ensureStackEntriesIsMutable:()V
      16: aload_0
      17: getfield      #10                 // Field stackEntries_:Lcom/google/protobuf/LazyStringArrayList;
      20: aload_1
      21: invokevirtual #42                 // Method com/google/protobuf/LazyStringArrayList.add:(Ljava/lang/Object;)Z
      24: pop
      25: aload_0
      26: dup
      27: getfield      #15                 // Field bitField0_:I
      30: iconst_1
      31: ior
      32: putfield      #15                 // Field bitField0_:I
      35: aload_0
      36: invokevirtual #32                 // Method onChanged:()V
      39: aload_0
      40: areturn

  public com.google.rpc.DebugInfo$Builder addAllStackEntries(java.lang.Iterable<java.lang.String>);
    Code:
       0: aload_0
       1: invokespecial #30                 // Method ensureStackEntriesIsMutable:()V
       4: aload_1
       5: aload_0
       6: getfield      #10                 // Field stackEntries_:Lcom/google/protobuf/LazyStringArrayList;
       9: invokestatic  #53                 // Method com/google/protobuf/AbstractMessageLite$Builder.addAll:(Ljava/lang/Iterable;Ljava/util/List;)V
      12: aload_0
      13: dup
      14: getfield      #15                 // Field bitField0_:I
      17: iconst_1
      18: ior
      19: putfield      #15                 // Field bitField0_:I
      22: aload_0
      23: invokevirtual #32                 // Method onChanged:()V
      26: aload_0
      27: areturn

  public com.google.rpc.DebugInfo$Builder clearStackEntries();
    Code:
       0: aload_0
       1: invokestatic  #9                  // Method com/google/protobuf/LazyStringArrayList.emptyList:()Lcom/google/protobuf/LazyStringArrayList;
       4: putfield      #10                 // Field stackEntries_:Lcom/google/protobuf/LazyStringArrayList;
       7: aload_0
       8: aload_0
       9: getfield      #15                 // Field bitField0_:I
      12: bipush        -2
      14: iand
      15: putfield      #15                 // Field bitField0_:I
      18: aload_0
      19: invokevirtual #32                 // Method onChanged:()V
      22: aload_0
      23: areturn

  public com.google.rpc.DebugInfo$Builder addStackEntriesBytes(com.google.protobuf.ByteString);
    Code:
       0: aload_1
       1: ifnonnull     12
       4: new           #38                 // class java/lang/NullPointerException
       7: dup
       8: invokespecial #39                 // Method java/lang/NullPointerException."<init>":()V
      11: athrow
      12: aload_1
      13: invokestatic  #54                 // Method com/google/rpc/DebugInfo.access$500:(Lcom/google/protobuf/ByteString;)V
      16: aload_0
      17: invokespecial #30                 // Method ensureStackEntriesIsMutable:()V
      20: aload_0
      21: getfield      #10                 // Field stackEntries_:Lcom/google/protobuf/LazyStringArrayList;
      24: aload_1
      25: invokevirtual #55                 // Method com/google/protobuf/LazyStringArrayList.add:(Lcom/google/protobuf/ByteString;)V
      28: aload_0
      29: dup
      30: getfield      #15                 // Field bitField0_:I
      33: iconst_1
      34: ior
      35: putfield      #15                 // Field bitField0_:I
      38: aload_0
      39: invokevirtual #32                 // Method onChanged:()V
      42: aload_0
      43: areturn

  public java.lang.String getDetail();
    Code:
       0: aload_0
       1: getfield      #12                 // Field detail_:Ljava/lang/Object;
       4: astore_1
       5: aload_1
       6: instanceof    #56                 // class java/lang/String
       9: ifne          29
      12: aload_1
      13: checkcast     #57                 // class com/google/protobuf/ByteString
      16: astore_2
      17: aload_2
      18: invokevirtual #58                 // Method com/google/protobuf/ByteString.toStringUtf8:()Ljava/lang/String;
      21: astore_3
      22: aload_0
      23: aload_3
      24: putfield      #12                 // Field detail_:Ljava/lang/Object;
      27: aload_3
      28: areturn
      29: aload_1
      30: checkcast     #56                 // class java/lang/String
      33: areturn

  public com.google.protobuf.ByteString getDetailBytes();
    Code:
       0: aload_0
       1: getfield      #12                 // Field detail_:Ljava/lang/Object;
       4: astore_1
       5: aload_1
       6: instanceof    #56                 // class java/lang/String
       9: ifeq          27
      12: aload_1
      13: checkcast     #56                 // class java/lang/String
      16: invokestatic  #59                 // Method com/google/protobuf/ByteString.copyFromUtf8:(Ljava/lang/String;)Lcom/google/protobuf/ByteString;
      19: astore_2
      20: aload_0
      21: aload_2
      22: putfield      #12                 // Field detail_:Ljava/lang/Object;
      25: aload_2
      26: areturn
      27: aload_1
      28: checkcast     #57                 // class com/google/protobuf/ByteString
      31: areturn

  public com.google.rpc.DebugInfo$Builder setDetail(java.lang.String);
    Code:
       0: aload_1
       1: ifnonnull     12
       4: new           #38                 // class java/lang/NullPointerException
       7: dup
       8: invokespecial #39                 // Method java/lang/NullPointerException."<init>":()V
      11: athrow
      12: aload_0
      13: aload_1
      14: putfield      #12                 // Field detail_:Ljava/lang/Object;
      17: aload_0
      18: dup
      19: getfield      #15                 // Field bitField0_:I
      22: iconst_2
      23: ior
      24: putfield      #15                 // Field bitField0_:I
      27: aload_0
      28: invokevirtual #32                 // Method onChanged:()V
      31: aload_0
      32: areturn

  public com.google.rpc.DebugInfo$Builder clearDetail();
    Code:
       0: aload_0
       1: invokestatic  #16                 // Method com/google/rpc/DebugInfo.getDefaultInstance:()Lcom/google/rpc/DebugInfo;
       4: invokevirtual #33                 // Method com/google/rpc/DebugInfo.getDetail:()Ljava/lang/String;
       7: putfield      #12                 // Field detail_:Ljava/lang/Object;
      10: aload_0
      11: aload_0
      12: getfield      #15                 // Field bitField0_:I
      15: bipush        -3
      17: iand
      18: putfield      #15                 // Field bitField0_:I
      21: aload_0
      22: invokevirtual #32                 // Method onChanged:()V
      25: aload_0
      26: areturn

  public com.google.rpc.DebugInfo$Builder setDetailBytes(com.google.protobuf.ByteString);
    Code:
       0: aload_1
       1: ifnonnull     12
       4: new           #38                 // class java/lang/NullPointerException
       7: dup
       8: invokespecial #39                 // Method java/lang/NullPointerException."<init>":()V
      11: athrow
      12: aload_1
      13: invokestatic  #60                 // Method com/google/rpc/DebugInfo.access$600:(Lcom/google/protobuf/ByteString;)V
      16: aload_0
      17: aload_1
      18: putfield      #12                 // Field detail_:Ljava/lang/Object;
      21: aload_0
      22: dup
      23: getfield      #15                 // Field bitField0_:I
      26: iconst_2
      27: ior
      28: putfield      #15                 // Field bitField0_:I
      31: aload_0
      32: invokevirtual #32                 // Method onChanged:()V
      35: aload_0
      36: areturn

  public final com.google.rpc.DebugInfo$Builder setUnknownFields(com.google.protobuf.UnknownFieldSet);
    Code:
       0: aload_0
       1: aload_1
       2: invokespecial #61                 // Method com/google/protobuf/GeneratedMessageV3$Builder.setUnknownFields:(Lcom/google/protobuf/UnknownFieldSet;)Lcom/google/protobuf/GeneratedMessageV3$Builder;
       5: checkcast     #6                  // class com/google/rpc/DebugInfo$Builder
       8: areturn

  public final com.google.rpc.DebugInfo$Builder mergeUnknownFields(com.google.protobuf.UnknownFieldSet);
    Code:
       0: aload_0
       1: aload_1
       2: invokespecial #62                 // Method com/google/protobuf/GeneratedMessageV3$Builder.mergeUnknownFields:(Lcom/google/protobuf/UnknownFieldSet;)Lcom/google/protobuf/GeneratedMessageV3$Builder;
       5: checkcast     #6                  // class com/google/rpc/DebugInfo$Builder
       8: areturn

  public com.google.protobuf.GeneratedMessageV3$Builder mergeUnknownFields(com.google.protobuf.UnknownFieldSet);
    Code:
       0: aload_0
       1: aload_1
       2: invokevirtual #37                 // Method mergeUnknownFields:(Lcom/google/protobuf/UnknownFieldSet;)Lcom/google/rpc/DebugInfo$Builder;
       5: areturn

  public com.google.protobuf.GeneratedMessageV3$Builder setUnknownFields(com.google.protobuf.UnknownFieldSet);
    Code:
       0: aload_0
       1: aload_1
       2: invokevirtual #63                 // Method setUnknownFields:(Lcom/google/protobuf/UnknownFieldSet;)Lcom/google/rpc/DebugInfo$Builder;
       5: areturn

  public com.google.protobuf.GeneratedMessageV3$Builder clear();
    Code:
       0: aload_0
       1: invokevirtual #64                 // Method clear:()Lcom/google/rpc/DebugInfo$Builder;
       4: areturn

  public com.google.protobuf.AbstractMessage$Builder mergeUnknownFields(com.google.protobuf.UnknownFieldSet);
    Code:
       0: aload_0
       1: aload_1
       2: invokevirtual #37                 // Method mergeUnknownFields:(Lcom/google/protobuf/UnknownFieldSet;)Lcom/google/rpc/DebugInfo$Builder;
       5: areturn

  public com.google.protobuf.AbstractMessage$Builder mergeFrom(com.google.protobuf.CodedInputStream, com.google.protobuf.ExtensionRegistryLite) throws java.io.IOException;
    Code:
       0: aload_0
       1: aload_1
       2: aload_2
       3: invokevirtual #65                 // Method mergeFrom:(Lcom/google/protobuf/CodedInputStream;Lcom/google/protobuf/ExtensionRegistryLite;)Lcom/google/rpc/DebugInfo$Builder;
       6: areturn

  public com.google.protobuf.AbstractMessage$Builder mergeFrom(com.google.protobuf.Message);
    Code:
       0: aload_0
       1: aload_1
       2: invokevirtual #66                 // Method mergeFrom:(Lcom/google/protobuf/Message;)Lcom/google/rpc/DebugInfo$Builder;
       5: areturn

  public com.google.protobuf.AbstractMessage$Builder clear();
    Code:
       0: aload_0
       1: invokevirtual #64                 // Method clear:()Lcom/google/rpc/DebugInfo$Builder;
       4: areturn

  public com.google.protobuf.Message$Builder mergeUnknownFields(com.google.protobuf.UnknownFieldSet);
    Code:
       0: aload_0
       1: aload_1
       2: invokevirtual #37                 // Method mergeUnknownFields:(Lcom/google/protobuf/UnknownFieldSet;)Lcom/google/rpc/DebugInfo$Builder;
       5: areturn

  public com.google.protobuf.Message$Builder setUnknownFields(com.google.protobuf.UnknownFieldSet);
    Code:
       0: aload_0
       1: aload_1
       2: invokevirtual #63                 // Method setUnknownFields:(Lcom/google/protobuf/UnknownFieldSet;)Lcom/google/rpc/DebugInfo$Builder;
       5: areturn

  public com.google.protobuf.Message$Builder mergeFrom(com.google.protobuf.CodedInputStream, com.google.protobuf.ExtensionRegistryLite) throws java.io.IOException;
    Code:
       0: aload_0
       1: aload_1
       2: aload_2
       3: invokevirtual #65                 // Method mergeFrom:(Lcom/google/protobuf/CodedInputStream;Lcom/google/protobuf/ExtensionRegistryLite;)Lcom/google/rpc/DebugInfo$Builder;
       6: areturn

  public com.google.protobuf.Message buildPartial();
    Code:
       0: aload_0
       1: invokevirtual #17                 // Method buildPartial:()Lcom/google/rpc/DebugInfo;
       4: areturn

  public com.google.protobuf.Message build();
    Code:
       0: aload_0
       1: invokevirtual #67                 // Method build:()Lcom/google/rpc/DebugInfo;
       4: areturn

  public com.google.protobuf.Message$Builder mergeFrom(com.google.protobuf.Message);
    Code:
       0: aload_0
       1: aload_1
       2: invokevirtual #66                 // Method mergeFrom:(Lcom/google/protobuf/Message;)Lcom/google/rpc/DebugInfo$Builder;
       5: areturn

  public com.google.protobuf.Message$Builder clear();
    Code:
       0: aload_0
       1: invokevirtual #64                 // Method clear:()Lcom/google/rpc/DebugInfo$Builder;
       4: areturn

  public com.google.protobuf.MessageLite$Builder mergeFrom(com.google.protobuf.CodedInputStream, com.google.protobuf.ExtensionRegistryLite) throws java.io.IOException;
    Code:
       0: aload_0
       1: aload_1
       2: aload_2
       3: invokevirtual #65                 // Method mergeFrom:(Lcom/google/protobuf/CodedInputStream;Lcom/google/protobuf/ExtensionRegistryLite;)Lcom/google/rpc/DebugInfo$Builder;
       6: areturn

  public com.google.protobuf.MessageLite buildPartial();
    Code:
       0: aload_0
       1: invokevirtual #17                 // Method buildPartial:()Lcom/google/rpc/DebugInfo;
       4: areturn

  public com.google.protobuf.MessageLite build();
    Code:
       0: aload_0
       1: invokevirtual #67                 // Method build:()Lcom/google/rpc/DebugInfo;
       4: areturn

  public com.google.protobuf.MessageLite$Builder clear();
    Code:
       0: aload_0
       1: invokevirtual #64                 // Method clear:()Lcom/google/rpc/DebugInfo$Builder;
       4: areturn

  public com.google.protobuf.MessageLite getDefaultInstanceForType();
    Code:
       0: aload_0
       1: invokevirtual #68                 // Method getDefaultInstanceForType:()Lcom/google/rpc/DebugInfo;
       4: areturn

  public com.google.protobuf.Message getDefaultInstanceForType();
    Code:
       0: aload_0
       1: invokevirtual #68                 // Method getDefaultInstanceForType:()Lcom/google/rpc/DebugInfo;
       4: areturn

  public com.google.protobuf.AbstractMessageLite$Builder mergeFrom(com.google.protobuf.CodedInputStream, com.google.protobuf.ExtensionRegistryLite) throws java.io.IOException;
    Code:
       0: aload_0
       1: aload_1
       2: aload_2
       3: invokevirtual #65                 // Method mergeFrom:(Lcom/google/protobuf/CodedInputStream;Lcom/google/protobuf/ExtensionRegistryLite;)Lcom/google/rpc/DebugInfo$Builder;
       6: areturn

  public java.util.List getStackEntriesList();
    Code:
       0: aload_0
       1: invokevirtual #69                 // Method getStackEntriesList:()Lcom/google/protobuf/ProtocolStringList;
       4: areturn

  com.google.rpc.DebugInfo$Builder(com.google.rpc.DebugInfo$1);
    Code:
       0: aload_0
       1: invokespecial #2                  // Method "<init>":()V
       4: return

  com.google.rpc.DebugInfo$Builder(com.google.protobuf.GeneratedMessageV3$BuilderParent, com.google.rpc.DebugInfo$1);
    Code:
       0: aload_0
       1: aload_1
       2: invokespecial #1                  // Method "<init>":(Lcom/google/protobuf/GeneratedMessageV3$BuilderParent;)V
       5: return
}
