Compiled from "ErrorInfo.java"
public final class com.google.rpc.ErrorInfo extends com.google.protobuf.GeneratedMessageV3 implements com.google.rpc.ErrorInfoOrBuilder {
  private static final long serialVersionUID;

  public static final int REASON_FIELD_NUMBER;

  private volatile java.lang.Object reason_;

  public static final int DOMAIN_FIELD_NUMBER;

  private volatile java.lang.Object domain_;

  public static final int METADATA_FIELD_NUMBER;

  private com.google.protobuf.MapField<java.lang.String, java.lang.String> metadata_;

  private byte memoizedIsInitialized;

  private static final com.google.rpc.ErrorInfo DEFAULT_INSTANCE;

  private static final com.google.protobuf.Parser<com.google.rpc.ErrorInfo> PARSER;

  private com.google.rpc.ErrorInfo(com.google.protobuf.GeneratedMessageV3$Builder<?>);
    Code:
       0: aload_0
       1: aload_1
       2: invokespecial #7                  // Method com/google/protobuf/GeneratedMessageV3."<init>":(Lcom/google/protobuf/GeneratedMessageV3$Builder;)V
       5: aload_0
       6: ldc           #8                  // String
       8: putfield      #5                  // Field reason_:Ljava/lang/Object;
      11: aload_0
      12: ldc           #8                  // String
      14: putfield      #4                  // Field domain_:Ljava/lang/Object;
      17: aload_0
      18: iconst_m1
      19: putfield      #9                  // Field memoizedIsInitialized:B
      22: return

  private com.google.rpc.ErrorInfo();
    Code:
       0: aload_0
       1: invokespecial #10                 // Method com/google/protobuf/GeneratedMessageV3."<init>":()V
       4: aload_0
       5: ldc           #8                  // String
       7: putfield      #5                  // Field reason_:Ljava/lang/Object;
      10: aload_0
      11: ldc           #8                  // String
      13: putfield      #4                  // Field domain_:Ljava/lang/Object;
      16: aload_0
      17: iconst_m1
      18: putfield      #9                  // Field memoizedIsInitialized:B
      21: aload_0
      22: ldc           #8                  // String
      24: putfield      #5                  // Field reason_:Ljava/lang/Object;
      27: aload_0
      28: ldc           #8                  // String
      30: putfield      #4                  // Field domain_:Ljava/lang/Object;
      33: return

  protected java.lang.Object newInstance(com.google.protobuf.GeneratedMessageV3$UnusedPrivateParameter);
    Code:
       0: new           #11                 // class com/google/rpc/ErrorInfo
       3: dup
       4: invokespecial #12                 // Method "<init>":()V
       7: areturn

  public static final com.google.protobuf.Descriptors$Descriptor getDescriptor();
    Code:
       0: getstatic     #13                 // Field com/google/rpc/ErrorDetailsProto.internal_static_google_rpc_ErrorInfo_descriptor:Lcom/google/protobuf/Descriptors$Descriptor;
       3: areturn

  protected com.google.protobuf.MapField internalGetMapField(int);
    Code:
       0: iload_1
       1: lookupswitch  { // 1
                     3: 20
               default: 25
          }
      20: aload_0
      21: invokespecial #2                  // Method internalGetMetadata:()Lcom/google/protobuf/MapField;
      24: areturn
      25: new           #14                 // class java/lang/RuntimeException
      28: dup
      29: new           #15                 // class java/lang/StringBuilder
      32: dup
      33: invokespecial #16                 // Method java/lang/StringBuilder."<init>":()V
      36: ldc           #17                 // String Invalid map field number:
      38: invokevirtual #18                 // Method java/lang/StringBuilder.append:(Ljava/lang/String;)Ljava/lang/StringBuilder;
      41: iload_1
      42: invokevirtual #19                 // Method java/lang/StringBuilder.append:(I)Ljava/lang/StringBuilder;
      45: invokevirtual #20                 // Method java/lang/StringBuilder.toString:()Ljava/lang/String;
      48: invokespecial #21                 // Method java/lang/RuntimeException."<init>":(Ljava/lang/String;)V
      51: athrow

  protected com.google.protobuf.GeneratedMessageV3$FieldAccessorTable internalGetFieldAccessorTable();
    Code:
       0: getstatic     #22                 // Field com/google/rpc/ErrorDetailsProto.internal_static_google_rpc_ErrorInfo_fieldAccessorTable:Lcom/google/protobuf/GeneratedMessageV3$FieldAccessorTable;
       3: ldc           #11                 // class com/google/rpc/ErrorInfo
       5: ldc           #23                 // class com/google/rpc/ErrorInfo$Builder
       7: invokevirtual #24                 // Method com/google/protobuf/GeneratedMessageV3$FieldAccessorTable.ensureFieldAccessorsInitialized:(Ljava/lang/Class;Ljava/lang/Class;)Lcom/google/protobuf/GeneratedMessageV3$FieldAccessorTable;
      10: areturn

  public java.lang.String getReason();
    Code:
       0: aload_0
       1: getfield      #5                  // Field reason_:Ljava/lang/Object;
       4: astore_1
       5: aload_1
       6: instanceof    #25                 // class java/lang/String
       9: ifeq          17
      12: aload_1
      13: checkcast     #25                 // class java/lang/String
      16: areturn
      17: aload_1
      18: checkcast     #26                 // class com/google/protobuf/ByteString
      21: astore_2
      22: aload_2
      23: invokevirtual #27                 // Method com/google/protobuf/ByteString.toStringUtf8:()Ljava/lang/String;
      26: astore_3
      27: aload_0
      28: aload_3
      29: putfield      #5                  // Field reason_:Ljava/lang/Object;
      32: aload_3
      33: areturn

  public com.google.protobuf.ByteString getReasonBytes();
    Code:
       0: aload_0
       1: getfield      #5                  // Field reason_:Ljava/lang/Object;
       4: astore_1
       5: aload_1
       6: instanceof    #25                 // class java/lang/String
       9: ifeq          27
      12: aload_1
      13: checkcast     #25                 // class java/lang/String
      16: invokestatic  #28                 // Method com/google/protobuf/ByteString.copyFromUtf8:(Ljava/lang/String;)Lcom/google/protobuf/ByteString;
      19: astore_2
      20: aload_0
      21: aload_2
      22: putfield      #5                  // Field reason_:Ljava/lang/Object;
      25: aload_2
      26: areturn
      27: aload_1
      28: checkcast     #26                 // class com/google/protobuf/ByteString
      31: areturn

  public java.lang.String getDomain();
    Code:
       0: aload_0
       1: getfield      #4                  // Field domain_:Ljava/lang/Object;
       4: astore_1
       5: aload_1
       6: instanceof    #25                 // class java/lang/String
       9: ifeq          17
      12: aload_1
      13: checkcast     #25                 // class java/lang/String
      16: areturn
      17: aload_1
      18: checkcast     #26                 // class com/google/protobuf/ByteString
      21: astore_2
      22: aload_2
      23: invokevirtual #27                 // Method com/google/protobuf/ByteString.toStringUtf8:()Ljava/lang/String;
      26: astore_3
      27: aload_0
      28: aload_3
      29: putfield      #4                  // Field domain_:Ljava/lang/Object;
      32: aload_3
      33: areturn

  public com.google.protobuf.ByteString getDomainBytes();
    Code:
       0: aload_0
       1: getfield      #4                  // Field domain_:Ljava/lang/Object;
       4: astore_1
       5: aload_1
       6: instanceof    #25                 // class java/lang/String
       9: ifeq          27
      12: aload_1
      13: checkcast     #25                 // class java/lang/String
      16: invokestatic  #28                 // Method com/google/protobuf/ByteString.copyFromUtf8:(Ljava/lang/String;)Lcom/google/protobuf/ByteString;
      19: astore_2
      20: aload_0
      21: aload_2
      22: putfield      #4                  // Field domain_:Ljava/lang/Object;
      25: aload_2
      26: areturn
      27: aload_1
      28: checkcast     #26                 // class com/google/protobuf/ByteString
      31: areturn

  private com.google.protobuf.MapField<java.lang.String, java.lang.String> internalGetMetadata();
    Code:
       0: aload_0
       1: getfield      #3                  // Field metadata_:Lcom/google/protobuf/MapField;
       4: ifnonnull     14
       7: getstatic     #29                 // Field com/google/rpc/ErrorInfo$MetadataDefaultEntryHolder.defaultEntry:Lcom/google/protobuf/MapEntry;
      10: invokestatic  #30                 // Method com/google/protobuf/MapField.emptyMapField:(Lcom/google/protobuf/MapEntry;)Lcom/google/protobuf/MapField;
      13: areturn
      14: aload_0
      15: getfield      #3                  // Field metadata_:Lcom/google/protobuf/MapField;
      18: areturn

  public int getMetadataCount();
    Code:
       0: aload_0
       1: invokespecial #2                  // Method internalGetMetadata:()Lcom/google/protobuf/MapField;
       4: invokevirtual #31                 // Method com/google/protobuf/MapField.getMap:()Ljava/util/Map;
       7: invokeinterface #32,  1           // InterfaceMethod java/util/Map.size:()I
      12: ireturn

  public boolean containsMetadata(java.lang.String);
    Code:
       0: aload_1
       1: ifnonnull     14
       4: new           #33                 // class java/lang/NullPointerException
       7: dup
       8: ldc           #34                 // String map key
      10: invokespecial #35                 // Method java/lang/NullPointerException."<init>":(Ljava/lang/String;)V
      13: athrow
      14: aload_0
      15: invokespecial #2                  // Method internalGetMetadata:()Lcom/google/protobuf/MapField;
      18: invokevirtual #31                 // Method com/google/protobuf/MapField.getMap:()Ljava/util/Map;
      21: aload_1
      22: invokeinterface #36,  2           // InterfaceMethod java/util/Map.containsKey:(Ljava/lang/Object;)Z
      27: ireturn

  public java.util.Map<java.lang.String, java.lang.String> getMetadata();
    Code:
       0: aload_0
       1: invokevirtual #37                 // Method getMetadataMap:()Ljava/util/Map;
       4: areturn

  public java.util.Map<java.lang.String, java.lang.String> getMetadataMap();
    Code:
       0: aload_0
       1: invokespecial #2                  // Method internalGetMetadata:()Lcom/google/protobuf/MapField;
       4: invokevirtual #31                 // Method com/google/protobuf/MapField.getMap:()Ljava/util/Map;
       7: areturn

  public java.lang.String getMetadataOrDefault(java.lang.String, java.lang.String);
    Code:
       0: aload_1
       1: ifnonnull     14
       4: new           #33                 // class java/lang/NullPointerException
       7: dup
       8: ldc           #34                 // String map key
      10: invokespecial #35                 // Method java/lang/NullPointerException."<init>":(Ljava/lang/String;)V
      13: athrow
      14: aload_0
      15: invokespecial #2                  // Method internalGetMetadata:()Lcom/google/protobuf/MapField;
      18: invokevirtual #31                 // Method com/google/protobuf/MapField.getMap:()Ljava/util/Map;
      21: astore_3
      22: aload_3
      23: aload_1
      24: invokeinterface #36,  2           // InterfaceMethod java/util/Map.containsKey:(Ljava/lang/Object;)Z
      29: ifeq          45
      32: aload_3
      33: aload_1
      34: invokeinterface #38,  2           // InterfaceMethod java/util/Map.get:(Ljava/lang/Object;)Ljava/lang/Object;
      39: checkcast     #25                 // class java/lang/String
      42: goto          46
      45: aload_2
      46: areturn

  public java.lang.String getMetadataOrThrow(java.lang.String);
    Code:
       0: aload_1
       1: ifnonnull     14
       4: new           #33                 // class java/lang/NullPointerException
       7: dup
       8: ldc           #34                 // String map key
      10: invokespecial #35                 // Method java/lang/NullPointerException."<init>":(Ljava/lang/String;)V
      13: athrow
      14: aload_0
      15: invokespecial #2                  // Method internalGetMetadata:()Lcom/google/protobuf/MapField;
      18: invokevirtual #31                 // Method com/google/protobuf/MapField.getMap:()Ljava/util/Map;
      21: astore_2
      22: aload_2
      23: aload_1
      24: invokeinterface #36,  2           // InterfaceMethod java/util/Map.containsKey:(Ljava/lang/Object;)Z
      29: ifne          40
      32: new           #39                 // class java/lang/IllegalArgumentException
      35: dup
      36: invokespecial #40                 // Method java/lang/IllegalArgumentException."<init>":()V
      39: athrow
      40: aload_2
      41: aload_1
      42: invokeinterface #38,  2           // InterfaceMethod java/util/Map.get:(Ljava/lang/Object;)Ljava/lang/Object;
      47: checkcast     #25                 // class java/lang/String
      50: areturn

  public final boolean isInitialized();
    Code:
       0: aload_0
       1: getfield      #9                  // Field memoizedIsInitialized:B
       4: istore_1
       5: iload_1
       6: iconst_1
       7: if_icmpne     12
      10: iconst_1
      11: ireturn
      12: iload_1
      13: ifne          18
      16: iconst_0
      17: ireturn
      18: aload_0
      19: iconst_1
      20: putfield      #9                  // Field memoizedIsInitialized:B
      23: iconst_1
      24: ireturn

  public void writeTo(com.google.protobuf.CodedOutputStream) throws java.io.IOException;
    Code:
       0: aload_0
       1: getfield      #5                  // Field reason_:Ljava/lang/Object;
       4: invokestatic  #41                 // Method com/google/protobuf/GeneratedMessageV3.isStringEmpty:(Ljava/lang/Object;)Z
       7: ifne          19
      10: aload_1
      11: iconst_1
      12: aload_0
      13: getfield      #5                  // Field reason_:Ljava/lang/Object;
      16: invokestatic  #42                 // Method com/google/protobuf/GeneratedMessageV3.writeString:(Lcom/google/protobuf/CodedOutputStream;ILjava/lang/Object;)V
      19: aload_0
      20: getfield      #4                  // Field domain_:Ljava/lang/Object;
      23: invokestatic  #41                 // Method com/google/protobuf/GeneratedMessageV3.isStringEmpty:(Ljava/lang/Object;)Z
      26: ifne          38
      29: aload_1
      30: iconst_2
      31: aload_0
      32: getfield      #4                  // Field domain_:Ljava/lang/Object;
      35: invokestatic  #42                 // Method com/google/protobuf/GeneratedMessageV3.writeString:(Lcom/google/protobuf/CodedOutputStream;ILjava/lang/Object;)V
      38: aload_1
      39: aload_0
      40: invokespecial #2                  // Method internalGetMetadata:()Lcom/google/protobuf/MapField;
      43: getstatic     #29                 // Field com/google/rpc/ErrorInfo$MetadataDefaultEntryHolder.defaultEntry:Lcom/google/protobuf/MapEntry;
      46: iconst_3
      47: invokestatic  #43                 // Method com/google/protobuf/GeneratedMessageV3.serializeStringMapTo:(Lcom/google/protobuf/CodedOutputStream;Lcom/google/protobuf/MapField;Lcom/google/protobuf/MapEntry;I)V
      50: aload_0
      51: invokevirtual #44                 // Method getUnknownFields:()Lcom/google/protobuf/UnknownFieldSet;
      54: aload_1
      55: invokevirtual #45                 // Method com/google/protobuf/UnknownFieldSet.writeTo:(Lcom/google/protobuf/CodedOutputStream;)V
      58: return

  public int getSerializedSize();
    Code:
       0: aload_0
       1: getfield      #46                 // Field memoizedSize:I
       4: istore_1
       5: iload_1
       6: iconst_m1
       7: if_icmpeq     12
      10: iload_1
      11: ireturn
      12: iconst_0
      13: istore_1
      14: aload_0
      15: getfield      #5                  // Field reason_:Ljava/lang/Object;
      18: invokestatic  #41                 // Method com/google/protobuf/GeneratedMessageV3.isStringEmpty:(Ljava/lang/Object;)Z
      21: ifne          35
      24: iload_1
      25: iconst_1
      26: aload_0
      27: getfield      #5                  // Field reason_:Ljava/lang/Object;
      30: invokestatic  #47                 // Method com/google/protobuf/GeneratedMessageV3.computeStringSize:(ILjava/lang/Object;)I
      33: iadd
      34: istore_1
      35: aload_0
      36: getfield      #4                  // Field domain_:Ljava/lang/Object;
      39: invokestatic  #41                 // Method com/google/protobuf/GeneratedMessageV3.isStringEmpty:(Ljava/lang/Object;)Z
      42: ifne          56
      45: iload_1
      46: iconst_2
      47: aload_0
      48: getfield      #4                  // Field domain_:Ljava/lang/Object;
      51: invokestatic  #47                 // Method com/google/protobuf/GeneratedMessageV3.computeStringSize:(ILjava/lang/Object;)I
      54: iadd
      55: istore_1
      56: aload_0
      57: invokespecial #2                  // Method internalGetMetadata:()Lcom/google/protobuf/MapField;
      60: invokevirtual #31                 // Method com/google/protobuf/MapField.getMap:()Ljava/util/Map;
      63: invokeinterface #48,  1           // InterfaceMethod java/util/Map.entrySet:()Ljava/util/Set;
      68: invokeinterface #49,  1           // InterfaceMethod java/util/Set.iterator:()Ljava/util/Iterator;
      73: astore_2
      74: aload_2
      75: invokeinterface #50,  1           // InterfaceMethod java/util/Iterator.hasNext:()Z
      80: ifeq          134
      83: aload_2
      84: invokeinterface #51,  1           // InterfaceMethod java/util/Iterator.next:()Ljava/lang/Object;
      89: checkcast     #52                 // class java/util/Map$Entry
      92: astore_3
      93: getstatic     #29                 // Field com/google/rpc/ErrorInfo$MetadataDefaultEntryHolder.defaultEntry:Lcom/google/protobuf/MapEntry;
      96: invokevirtual #53                 // Method com/google/protobuf/MapEntry.newBuilderForType:()Lcom/google/protobuf/MapEntry$Builder;
      99: aload_3
     100: invokeinterface #54,  1           // InterfaceMethod java/util/Map$Entry.getKey:()Ljava/lang/Object;
     105: invokevirtual #55                 // Method com/google/protobuf/MapEntry$Builder.setKey:(Ljava/lang/Object;)Lcom/google/protobuf/MapEntry$Builder;
     108: aload_3
     109: invokeinterface #56,  1           // InterfaceMethod java/util/Map$Entry.getValue:()Ljava/lang/Object;
     114: invokevirtual #57                 // Method com/google/protobuf/MapEntry$Builder.setValue:(Ljava/lang/Object;)Lcom/google/protobuf/MapEntry$Builder;
     117: invokevirtual #58                 // Method com/google/protobuf/MapEntry$Builder.build:()Lcom/google/protobuf/MapEntry;
     120: astore        4
     122: iload_1
     123: iconst_3
     124: aload         4
     126: invokestatic  #59                 // Method com/google/protobuf/CodedOutputStream.computeMessageSize:(ILcom/google/protobuf/MessageLite;)I
     129: iadd
     130: istore_1
     131: goto          74
     134: iload_1
     135: aload_0
     136: invokevirtual #44                 // Method getUnknownFields:()Lcom/google/protobuf/UnknownFieldSet;
     139: invokevirtual #60                 // Method com/google/protobuf/UnknownFieldSet.getSerializedSize:()I
     142: iadd
     143: istore_1
     144: aload_0
     145: iload_1
     146: putfield      #46                 // Field memoizedSize:I
     149: iload_1
     150: ireturn

  public boolean equals(java.lang.Object);
    Code:
       0: aload_1
       1: aload_0
       2: if_acmpne     7
       5: iconst_1
       6: ireturn
       7: aload_1
       8: instanceof    #11                 // class com/google/rpc/ErrorInfo
      11: ifne          20
      14: aload_0
      15: aload_1
      16: invokespecial #61                 // Method com/google/protobuf/GeneratedMessageV3.equals:(Ljava/lang/Object;)Z
      19: ireturn
      20: aload_1
      21: checkcast     #11                 // class com/google/rpc/ErrorInfo
      24: astore_2
      25: aload_0
      26: invokevirtual #62                 // Method getReason:()Ljava/lang/String;
      29: aload_2
      30: invokevirtual #62                 // Method getReason:()Ljava/lang/String;
      33: invokevirtual #63                 // Method java/lang/String.equals:(Ljava/lang/Object;)Z
      36: ifne          41
      39: iconst_0
      40: ireturn
      41: aload_0
      42: invokevirtual #64                 // Method getDomain:()Ljava/lang/String;
      45: aload_2
      46: invokevirtual #64                 // Method getDomain:()Ljava/lang/String;
      49: invokevirtual #63                 // Method java/lang/String.equals:(Ljava/lang/Object;)Z
      52: ifne          57
      55: iconst_0
      56: ireturn
      57: aload_0
      58: invokespecial #2                  // Method internalGetMetadata:()Lcom/google/protobuf/MapField;
      61: aload_2
      62: invokespecial #2                  // Method internalGetMetadata:()Lcom/google/protobuf/MapField;
      65: invokevirtual #65                 // Method com/google/protobuf/MapField.equals:(Ljava/lang/Object;)Z
      68: ifne          73
      71: iconst_0
      72: ireturn
      73: aload_0
      74: invokevirtual #44                 // Method getUnknownFields:()Lcom/google/protobuf/UnknownFieldSet;
      77: aload_2
      78: invokevirtual #44                 // Method getUnknownFields:()Lcom/google/protobuf/UnknownFieldSet;
      81: invokevirtual #66                 // Method com/google/protobuf/UnknownFieldSet.equals:(Ljava/lang/Object;)Z
      84: ifne          89
      87: iconst_0
      88: ireturn
      89: iconst_1
      90: ireturn

  public int hashCode();
    Code:
       0: aload_0
       1: getfield      #67                 // Field memoizedHashCode:I
       4: ifeq          12
       7: aload_0
       8: getfield      #67                 // Field memoizedHashCode:I
      11: ireturn
      12: bipush        41
      14: istore_1
      15: bipush        19
      17: iload_1
      18: imul
      19: invokestatic  #68                 // Method getDescriptor:()Lcom/google/protobuf/Descriptors$Descriptor;
      22: invokevirtual #69                 // Method java/lang/Object.hashCode:()I
      25: iadd
      26: istore_1
      27: bipush        37
      29: iload_1
      30: imul
      31: iconst_1
      32: iadd
      33: istore_1
      34: bipush        53
      36: iload_1
      37: imul
      38: aload_0
      39: invokevirtual #62                 // Method getReason:()Ljava/lang/String;
      42: invokevirtual #70                 // Method java/lang/String.hashCode:()I
      45: iadd
      46: istore_1
      47: bipush        37
      49: iload_1
      50: imul
      51: iconst_2
      52: iadd
      53: istore_1
      54: bipush        53
      56: iload_1
      57: imul
      58: aload_0
      59: invokevirtual #64                 // Method getDomain:()Ljava/lang/String;
      62: invokevirtual #70                 // Method java/lang/String.hashCode:()I
      65: iadd
      66: istore_1
      67: aload_0
      68: invokespecial #2                  // Method internalGetMetadata:()Lcom/google/protobuf/MapField;
      71: invokevirtual #31                 // Method com/google/protobuf/MapField.getMap:()Ljava/util/Map;
      74: invokeinterface #71,  1           // InterfaceMethod java/util/Map.isEmpty:()Z
      79: ifne          102
      82: bipush        37
      84: iload_1
      85: imul
      86: iconst_3
      87: iadd
      88: istore_1
      89: bipush        53
      91: iload_1
      92: imul
      93: aload_0
      94: invokespecial #2                  // Method internalGetMetadata:()Lcom/google/protobuf/MapField;
      97: invokevirtual #72                 // Method com/google/protobuf/MapField.hashCode:()I
     100: iadd
     101: istore_1
     102: bipush        29
     104: iload_1
     105: imul
     106: aload_0
     107: invokevirtual #44                 // Method getUnknownFields:()Lcom/google/protobuf/UnknownFieldSet;
     110: invokevirtual #73                 // Method com/google/protobuf/UnknownFieldSet.hashCode:()I
     113: iadd
     114: istore_1
     115: aload_0
     116: iload_1
     117: putfield      #67                 // Field memoizedHashCode:I
     120: iload_1
     121: ireturn

  public static com.google.rpc.ErrorInfo parseFrom(java.nio.ByteBuffer) throws com.google.protobuf.InvalidProtocolBufferException;
    Code:
       0: getstatic     #74                 // Field PARSER:Lcom/google/protobuf/Parser;
       3: aload_0
       4: invokeinterface #75,  2           // InterfaceMethod com/google/protobuf/Parser.parseFrom:(Ljava/nio/ByteBuffer;)Ljava/lang/Object;
       9: checkcast     #11                 // class com/google/rpc/ErrorInfo
      12: areturn

  public static com.google.rpc.ErrorInfo parseFrom(java.nio.ByteBuffer, com.google.protobuf.ExtensionRegistryLite) throws com.google.protobuf.InvalidProtocolBufferException;
    Code:
       0: getstatic     #74                 // Field PARSER:Lcom/google/protobuf/Parser;
       3: aload_0
       4: aload_1
       5: invokeinterface #76,  3           // InterfaceMethod com/google/protobuf/Parser.parseFrom:(Ljava/nio/ByteBuffer;Lcom/google/protobuf/ExtensionRegistryLite;)Ljava/lang/Object;
      10: checkcast     #11                 // class com/google/rpc/ErrorInfo
      13: areturn

  public static com.google.rpc.ErrorInfo parseFrom(com.google.protobuf.ByteString) throws com.google.protobuf.InvalidProtocolBufferException;
    Code:
       0: getstatic     #74                 // Field PARSER:Lcom/google/protobuf/Parser;
       3: aload_0
       4: invokeinterface #77,  2           // InterfaceMethod com/google/protobuf/Parser.parseFrom:(Lcom/google/protobuf/ByteString;)Ljava/lang/Object;
       9: checkcast     #11                 // class com/google/rpc/ErrorInfo
      12: areturn

  public static com.google.rpc.ErrorInfo parseFrom(com.google.protobuf.ByteString, com.google.protobuf.ExtensionRegistryLite) throws com.google.protobuf.InvalidProtocolBufferException;
    Code:
       0: getstatic     #74                 // Field PARSER:Lcom/google/protobuf/Parser;
       3: aload_0
       4: aload_1
       5: invokeinterface #78,  3           // InterfaceMethod com/google/protobuf/Parser.parseFrom:(Lcom/google/protobuf/ByteString;Lcom/google/protobuf/ExtensionRegistryLite;)Ljava/lang/Object;
      10: checkcast     #11                 // class com/google/rpc/ErrorInfo
      13: areturn

  public static com.google.rpc.ErrorInfo parseFrom(byte[]) throws com.google.protobuf.InvalidProtocolBufferException;
    Code:
       0: getstatic     #74                 // Field PARSER:Lcom/google/protobuf/Parser;
       3: aload_0
       4: invokeinterface #79,  2           // InterfaceMethod com/google/protobuf/Parser.parseFrom:([B)Ljava/lang/Object;
       9: checkcast     #11                 // class com/google/rpc/ErrorInfo
      12: areturn

  public static com.google.rpc.ErrorInfo parseFrom(byte[], com.google.protobuf.ExtensionRegistryLite) throws com.google.protobuf.InvalidProtocolBufferException;
    Code:
       0: getstatic     #74                 // Field PARSER:Lcom/google/protobuf/Parser;
       3: aload_0
       4: aload_1
       5: invokeinterface #80,  3           // InterfaceMethod com/google/protobuf/Parser.parseFrom:([BLcom/google/protobuf/ExtensionRegistryLite;)Ljava/lang/Object;
      10: checkcast     #11                 // class com/google/rpc/ErrorInfo
      13: areturn

  public static com.google.rpc.ErrorInfo parseFrom(java.io.InputStream) throws java.io.IOException;
    Code:
       0: getstatic     #74                 // Field PARSER:Lcom/google/protobuf/Parser;
       3: aload_0
       4: invokestatic  #81                 // Method com/google/protobuf/GeneratedMessageV3.parseWithIOException:(Lcom/google/protobuf/Parser;Ljava/io/InputStream;)Lcom/google/protobuf/Message;
       7: checkcast     #11                 // class com/google/rpc/ErrorInfo
      10: areturn

  public static com.google.rpc.ErrorInfo parseFrom(java.io.InputStream, com.google.protobuf.ExtensionRegistryLite) throws java.io.IOException;
    Code:
       0: getstatic     #74                 // Field PARSER:Lcom/google/protobuf/Parser;
       3: aload_0
       4: aload_1
       5: invokestatic  #82                 // Method com/google/protobuf/GeneratedMessageV3.parseWithIOException:(Lcom/google/protobuf/Parser;Ljava/io/InputStream;Lcom/google/protobuf/ExtensionRegistryLite;)Lcom/google/protobuf/Message;
       8: checkcast     #11                 // class com/google/rpc/ErrorInfo
      11: areturn

  public static com.google.rpc.ErrorInfo parseDelimitedFrom(java.io.InputStream) throws java.io.IOException;
    Code:
       0: getstatic     #74                 // Field PARSER:Lcom/google/protobuf/Parser;
       3: aload_0
       4: invokestatic  #83                 // Method com/google/protobuf/GeneratedMessageV3.parseDelimitedWithIOException:(Lcom/google/protobuf/Parser;Ljava/io/InputStream;)Lcom/google/protobuf/Message;
       7: checkcast     #11                 // class com/google/rpc/ErrorInfo
      10: areturn

  public static com.google.rpc.ErrorInfo parseDelimitedFrom(java.io.InputStream, com.google.protobuf.ExtensionRegistryLite) throws java.io.IOException;
    Code:
       0: getstatic     #74                 // Field PARSER:Lcom/google/protobuf/Parser;
       3: aload_0
       4: aload_1
       5: invokestatic  #84                 // Method com/google/protobuf/GeneratedMessageV3.parseDelimitedWithIOException:(Lcom/google/protobuf/Parser;Ljava/io/InputStream;Lcom/google/protobuf/ExtensionRegistryLite;)Lcom/google/protobuf/Message;
       8: checkcast     #11                 // class com/google/rpc/ErrorInfo
      11: areturn

  public static com.google.rpc.ErrorInfo parseFrom(com.google.protobuf.CodedInputStream) throws java.io.IOException;
    Code:
       0: getstatic     #74                 // Field PARSER:Lcom/google/protobuf/Parser;
       3: aload_0
       4: invokestatic  #85                 // Method com/google/protobuf/GeneratedMessageV3.parseWithIOException:(Lcom/google/protobuf/Parser;Lcom/google/protobuf/CodedInputStream;)Lcom/google/protobuf/Message;
       7: checkcast     #11                 // class com/google/rpc/ErrorInfo
      10: areturn

  public static com.google.rpc.ErrorInfo parseFrom(com.google.protobuf.CodedInputStream, com.google.protobuf.ExtensionRegistryLite) throws java.io.IOException;
    Code:
       0: getstatic     #74                 // Field PARSER:Lcom/google/protobuf/Parser;
       3: aload_0
       4: aload_1
       5: invokestatic  #86                 // Method com/google/protobuf/GeneratedMessageV3.parseWithIOException:(Lcom/google/protobuf/Parser;Lcom/google/protobuf/CodedInputStream;Lcom/google/protobuf/ExtensionRegistryLite;)Lcom/google/protobuf/Message;
       8: checkcast     #11                 // class com/google/rpc/ErrorInfo
      11: areturn

  public com.google.rpc.ErrorInfo$Builder newBuilderForType();
    Code:
       0: invokestatic  #87                 // Method newBuilder:()Lcom/google/rpc/ErrorInfo$Builder;
       3: areturn

  public static com.google.rpc.ErrorInfo$Builder newBuilder();
    Code:
       0: getstatic     #88                 // Field DEFAULT_INSTANCE:Lcom/google/rpc/ErrorInfo;
       3: invokevirtual #89                 // Method toBuilder:()Lcom/google/rpc/ErrorInfo$Builder;
       6: areturn

  public static com.google.rpc.ErrorInfo$Builder newBuilder(com.google.rpc.ErrorInfo);
    Code:
       0: getstatic     #88                 // Field DEFAULT_INSTANCE:Lcom/google/rpc/ErrorInfo;
       3: invokevirtual #89                 // Method toBuilder:()Lcom/google/rpc/ErrorInfo$Builder;
       6: aload_0
       7: invokevirtual #90                 // Method com/google/rpc/ErrorInfo$Builder.mergeFrom:(Lcom/google/rpc/ErrorInfo;)Lcom/google/rpc/ErrorInfo$Builder;
      10: areturn

  public com.google.rpc.ErrorInfo$Builder toBuilder();
    Code:
       0: aload_0
       1: getstatic     #88                 // Field DEFAULT_INSTANCE:Lcom/google/rpc/ErrorInfo;
       4: if_acmpne     18
       7: new           #23                 // class com/google/rpc/ErrorInfo$Builder
      10: dup
      11: aconst_null
      12: invokespecial #91                 // Method com/google/rpc/ErrorInfo$Builder."<init>":(Lcom/google/rpc/ErrorInfo$1;)V
      15: goto          30
      18: new           #23                 // class com/google/rpc/ErrorInfo$Builder
      21: dup
      22: aconst_null
      23: invokespecial #91                 // Method com/google/rpc/ErrorInfo$Builder."<init>":(Lcom/google/rpc/ErrorInfo$1;)V
      26: aload_0
      27: invokevirtual #90                 // Method com/google/rpc/ErrorInfo$Builder.mergeFrom:(Lcom/google/rpc/ErrorInfo;)Lcom/google/rpc/ErrorInfo$Builder;
      30: areturn

  protected com.google.rpc.ErrorInfo$Builder newBuilderForType(com.google.protobuf.GeneratedMessageV3$BuilderParent);
    Code:
       0: new           #23                 // class com/google/rpc/ErrorInfo$Builder
       3: dup
       4: aload_1
       5: aconst_null
       6: invokespecial #92                 // Method com/google/rpc/ErrorInfo$Builder."<init>":(Lcom/google/protobuf/GeneratedMessageV3$BuilderParent;Lcom/google/rpc/ErrorInfo$1;)V
       9: astore_2
      10: aload_2
      11: areturn

  public static com.google.rpc.ErrorInfo getDefaultInstance();
    Code:
       0: getstatic     #88                 // Field DEFAULT_INSTANCE:Lcom/google/rpc/ErrorInfo;
       3: areturn

  public static com.google.protobuf.Parser<com.google.rpc.ErrorInfo> parser();
    Code:
       0: getstatic     #74                 // Field PARSER:Lcom/google/protobuf/Parser;
       3: areturn

  public com.google.protobuf.Parser<com.google.rpc.ErrorInfo> getParserForType();
    Code:
       0: getstatic     #74                 // Field PARSER:Lcom/google/protobuf/Parser;
       3: areturn

  public com.google.rpc.ErrorInfo getDefaultInstanceForType();
    Code:
       0: getstatic     #88                 // Field DEFAULT_INSTANCE:Lcom/google/rpc/ErrorInfo;
       3: areturn

  protected com.google.protobuf.Message$Builder newBuilderForType(com.google.protobuf.GeneratedMessageV3$BuilderParent);
    Code:
       0: aload_0
       1: aload_1
       2: invokevirtual #93                 // Method newBuilderForType:(Lcom/google/protobuf/GeneratedMessageV3$BuilderParent;)Lcom/google/rpc/ErrorInfo$Builder;
       5: areturn

  public com.google.protobuf.Message$Builder toBuilder();
    Code:
       0: aload_0
       1: invokevirtual #89                 // Method toBuilder:()Lcom/google/rpc/ErrorInfo$Builder;
       4: areturn

  public com.google.protobuf.Message$Builder newBuilderForType();
    Code:
       0: aload_0
       1: invokevirtual #94                 // Method newBuilderForType:()Lcom/google/rpc/ErrorInfo$Builder;
       4: areturn

  public com.google.protobuf.MessageLite$Builder toBuilder();
    Code:
       0: aload_0
       1: invokevirtual #89                 // Method toBuilder:()Lcom/google/rpc/ErrorInfo$Builder;
       4: areturn

  public com.google.protobuf.MessageLite$Builder newBuilderForType();
    Code:
       0: aload_0
       1: invokevirtual #94                 // Method newBuilderForType:()Lcom/google/rpc/ErrorInfo$Builder;
       4: areturn

  public com.google.protobuf.MessageLite getDefaultInstanceForType();
    Code:
       0: aload_0
       1: invokevirtual #95                 // Method getDefaultInstanceForType:()Lcom/google/rpc/ErrorInfo;
       4: areturn

  public com.google.protobuf.Message getDefaultInstanceForType();
    Code:
       0: aload_0
       1: invokevirtual #95                 // Method getDefaultInstanceForType:()Lcom/google/rpc/ErrorInfo;
       4: areturn

  com.google.rpc.ErrorInfo(com.google.protobuf.GeneratedMessageV3$Builder, com.google.rpc.ErrorInfo$1);
    Code:
       0: aload_0
       1: aload_1
       2: invokespecial #6                  // Method "<init>":(Lcom/google/protobuf/GeneratedMessageV3$Builder;)V
       5: return

  static java.lang.Object access$302(com.google.rpc.ErrorInfo, java.lang.Object);
    Code:
       0: aload_0
       1: aload_1
       2: dup_x1
       3: putfield      #5                  // Field reason_:Ljava/lang/Object;
       6: areturn

  static java.lang.Object access$402(com.google.rpc.ErrorInfo, java.lang.Object);
    Code:
       0: aload_0
       1: aload_1
       2: dup_x1
       3: putfield      #4                  // Field domain_:Ljava/lang/Object;
       6: areturn

  static com.google.protobuf.MapField access$502(com.google.rpc.ErrorInfo, com.google.protobuf.MapField);
    Code:
       0: aload_0
       1: aload_1
       2: dup_x1
       3: putfield      #3                  // Field metadata_:Lcom/google/protobuf/MapField;
       6: areturn

  static com.google.protobuf.MapField access$500(com.google.rpc.ErrorInfo);
    Code:
       0: aload_0
       1: getfield      #3                  // Field metadata_:Lcom/google/protobuf/MapField;
       4: areturn

  static java.lang.Object access$300(com.google.rpc.ErrorInfo);
    Code:
       0: aload_0
       1: getfield      #5                  // Field reason_:Ljava/lang/Object;
       4: areturn

  static java.lang.Object access$400(com.google.rpc.ErrorInfo);
    Code:
       0: aload_0
       1: getfield      #4                  // Field domain_:Ljava/lang/Object;
       4: areturn

  static com.google.protobuf.MapField access$600(com.google.rpc.ErrorInfo);
    Code:
       0: aload_0
       1: invokespecial #2                  // Method internalGetMetadata:()Lcom/google/protobuf/MapField;
       4: areturn

  static void access$700(com.google.protobuf.ByteString) throws java.lang.IllegalArgumentException;
    Code:
       0: aload_0
       1: invokestatic  #1                  // Method checkByteStringIsUtf8:(Lcom/google/protobuf/ByteString;)V
       4: return

  static void access$800(com.google.protobuf.ByteString) throws java.lang.IllegalArgumentException;
    Code:
       0: aload_0
       1: invokestatic  #1                  // Method checkByteStringIsUtf8:(Lcom/google/protobuf/ByteString;)V
       4: return

  static {};
    Code:
       0: new           #11                 // class com/google/rpc/ErrorInfo
       3: dup
       4: invokespecial #12                 // Method "<init>":()V
       7: putstatic     #88                 // Field DEFAULT_INSTANCE:Lcom/google/rpc/ErrorInfo;
      10: new           #96                 // class com/google/rpc/ErrorInfo$1
      13: dup
      14: invokespecial #97                 // Method com/google/rpc/ErrorInfo$1."<init>":()V
      17: putstatic     #74                 // Field PARSER:Lcom/google/protobuf/Parser;
      20: return
}
