Compiled from "Help.java"
public final class com.google.rpc.Help$Link$Builder extends com.google.protobuf.GeneratedMessageV3$Builder<com.google.rpc.Help$Link$Builder> implements com.google.rpc.Help$LinkOrBuilder {
  private int bitField0_;

  private java.lang.Object description_;

  private java.lang.Object url_;

  public static final com.google.protobuf.Descriptors$Descriptor getDescriptor();
    Code:
       0: getstatic     #3                  // Field com/google/rpc/ErrorDetailsProto.internal_static_google_rpc_Help_Link_descriptor:Lcom/google/protobuf/Descriptors$Descriptor;
       3: areturn

  protected com.google.protobuf.GeneratedMessageV3$FieldAccessorTable internalGetFieldAccessorTable();
    Code:
       0: getstatic     #4                  // Field com/google/rpc/ErrorDetailsProto.internal_static_google_rpc_Help_Link_fieldAccessorTable:Lcom/google/protobuf/GeneratedMessageV3$FieldAccessorTable;
       3: ldc           #5                  // class com/google/rpc/Help$Link
       5: ldc           #6                  // class com/google/rpc/Help$Link$Builder
       7: invokevirtual #7                  // Method com/google/protobuf/GeneratedMessageV3$FieldAccessorTable.ensureFieldAccessorsInitialized:(Ljava/lang/Class;Ljava/lang/Class;)Lcom/google/protobuf/GeneratedMessageV3$FieldAccessorTable;
      10: areturn

  private com.google.rpc.Help$Link$Builder();
    Code:
       0: aload_0
       1: invokespecial #8                  // Method com/google/protobuf/GeneratedMessageV3$Builder."<init>":()V
       4: aload_0
       5: ldc           #9                  // String
       7: putfield      #10                 // Field description_:Ljava/lang/Object;
      10: aload_0
      11: ldc           #9                  // String
      13: putfield      #11                 // Field url_:Ljava/lang/Object;
      16: return

  private com.google.rpc.Help$Link$Builder(com.google.protobuf.GeneratedMessageV3$BuilderParent);
    Code:
       0: aload_0
       1: aload_1
       2: invokespecial #12                 // Method com/google/protobuf/GeneratedMessageV3$Builder."<init>":(Lcom/google/protobuf/GeneratedMessageV3$BuilderParent;)V
       5: aload_0
       6: ldc           #9                  // String
       8: putfield      #10                 // Field description_:Ljava/lang/Object;
      11: aload_0
      12: ldc           #9                  // String
      14: putfield      #11                 // Field url_:Ljava/lang/Object;
      17: return

  public com.google.rpc.Help$Link$Builder clear();
    Code:
       0: aload_0
       1: invokespecial #13                 // Method com/google/protobuf/GeneratedMessageV3$Builder.clear:()Lcom/google/protobuf/GeneratedMessageV3$Builder;
       4: pop
       5: aload_0
       6: iconst_0
       7: putfield      #14                 // Field bitField0_:I
      10: aload_0
      11: ldc           #9                  // String
      13: putfield      #10                 // Field description_:Ljava/lang/Object;
      16: aload_0
      17: ldc           #9                  // String
      19: putfield      #11                 // Field url_:Ljava/lang/Object;
      22: aload_0
      23: areturn

  public com.google.protobuf.Descriptors$Descriptor getDescriptorForType();
    Code:
       0: getstatic     #3                  // Field com/google/rpc/ErrorDetailsProto.internal_static_google_rpc_Help_Link_descriptor:Lcom/google/protobuf/Descriptors$Descriptor;
       3: areturn

  public com.google.rpc.Help$Link getDefaultInstanceForType();
    Code:
       0: invokestatic  #15                 // Method com/google/rpc/Help$Link.getDefaultInstance:()Lcom/google/rpc/Help$Link;
       3: areturn

  public com.google.rpc.Help$Link build();
    Code:
       0: aload_0
       1: invokevirtual #16                 // Method buildPartial:()Lcom/google/rpc/Help$Link;
       4: astore_1
       5: aload_1
       6: invokevirtual #17                 // Method com/google/rpc/Help$Link.isInitialized:()Z
       9: ifne          17
      12: aload_1
      13: invokestatic  #18                 // Method newUninitializedMessageException:(Lcom/google/protobuf/Message;)Lcom/google/protobuf/UninitializedMessageException;
      16: athrow
      17: aload_1
      18: areturn

  public com.google.rpc.Help$Link buildPartial();
    Code:
       0: new           #5                  // class com/google/rpc/Help$Link
       3: dup
       4: aload_0
       5: aconst_null
       6: invokespecial #19                 // Method com/google/rpc/Help$Link."<init>":(Lcom/google/protobuf/GeneratedMessageV3$Builder;Lcom/google/rpc/Help$1;)V
       9: astore_1
      10: aload_0
      11: getfield      #14                 // Field bitField0_:I
      14: ifeq          22
      17: aload_0
      18: aload_1
      19: invokespecial #20                 // Method buildPartial0:(Lcom/google/rpc/Help$Link;)V
      22: aload_0
      23: invokevirtual #21                 // Method onBuilt:()V
      26: aload_1
      27: areturn

  private void buildPartial0(com.google.rpc.Help$Link);
    Code:
       0: aload_0
       1: getfield      #14                 // Field bitField0_:I
       4: istore_2
       5: iload_2
       6: iconst_1
       7: iand
       8: ifeq          20
      11: aload_1
      12: aload_0
      13: getfield      #10                 // Field description_:Ljava/lang/Object;
      16: invokestatic  #22                 // Method com/google/rpc/Help$Link.access$302:(Lcom/google/rpc/Help$Link;Ljava/lang/Object;)Ljava/lang/Object;
      19: pop
      20: iload_2
      21: iconst_2
      22: iand
      23: ifeq          35
      26: aload_1
      27: aload_0
      28: getfield      #11                 // Field url_:Ljava/lang/Object;
      31: invokestatic  #23                 // Method com/google/rpc/Help$Link.access$402:(Lcom/google/rpc/Help$Link;Ljava/lang/Object;)Ljava/lang/Object;
      34: pop
      35: return

  public com.google.rpc.Help$Link$Builder mergeFrom(com.google.protobuf.Message);
    Code:
       0: aload_1
       1: instanceof    #5                  // class com/google/rpc/Help$Link
       4: ifeq          16
       7: aload_0
       8: aload_1
       9: checkcast     #5                  // class com/google/rpc/Help$Link
      12: invokevirtual #24                 // Method mergeFrom:(Lcom/google/rpc/Help$Link;)Lcom/google/rpc/Help$Link$Builder;
      15: areturn
      16: aload_0
      17: aload_1
      18: invokespecial #25                 // Method com/google/protobuf/GeneratedMessageV3$Builder.mergeFrom:(Lcom/google/protobuf/Message;)Lcom/google/protobuf/AbstractMessage$Builder;
      21: pop
      22: aload_0
      23: areturn

  public com.google.rpc.Help$Link$Builder mergeFrom(com.google.rpc.Help$Link);
    Code:
       0: aload_1
       1: invokestatic  #15                 // Method com/google/rpc/Help$Link.getDefaultInstance:()Lcom/google/rpc/Help$Link;
       4: if_acmpne     9
       7: aload_0
       8: areturn
       9: aload_1
      10: invokevirtual #26                 // Method com/google/rpc/Help$Link.getDescription:()Ljava/lang/String;
      13: invokevirtual #27                 // Method java/lang/String.isEmpty:()Z
      16: ifne          41
      19: aload_0
      20: aload_1
      21: invokestatic  #28                 // Method com/google/rpc/Help$Link.access$300:(Lcom/google/rpc/Help$Link;)Ljava/lang/Object;
      24: putfield      #10                 // Field description_:Ljava/lang/Object;
      27: aload_0
      28: dup
      29: getfield      #14                 // Field bitField0_:I
      32: iconst_1
      33: ior
      34: putfield      #14                 // Field bitField0_:I
      37: aload_0
      38: invokevirtual #29                 // Method onChanged:()V
      41: aload_1
      42: invokevirtual #30                 // Method com/google/rpc/Help$Link.getUrl:()Ljava/lang/String;
      45: invokevirtual #27                 // Method java/lang/String.isEmpty:()Z
      48: ifne          73
      51: aload_0
      52: aload_1
      53: invokestatic  #31                 // Method com/google/rpc/Help$Link.access$400:(Lcom/google/rpc/Help$Link;)Ljava/lang/Object;
      56: putfield      #11                 // Field url_:Ljava/lang/Object;
      59: aload_0
      60: dup
      61: getfield      #14                 // Field bitField0_:I
      64: iconst_2
      65: ior
      66: putfield      #14                 // Field bitField0_:I
      69: aload_0
      70: invokevirtual #29                 // Method onChanged:()V
      73: aload_0
      74: aload_1
      75: invokevirtual #32                 // Method com/google/rpc/Help$Link.getUnknownFields:()Lcom/google/protobuf/UnknownFieldSet;
      78: invokevirtual #33                 // Method mergeUnknownFields:(Lcom/google/protobuf/UnknownFieldSet;)Lcom/google/rpc/Help$Link$Builder;
      81: pop
      82: aload_0
      83: invokevirtual #29                 // Method onChanged:()V
      86: aload_0
      87: areturn

  public final boolean isInitialized();
    Code:
       0: iconst_1
       1: ireturn

  public com.google.rpc.Help$Link$Builder mergeFrom(com.google.protobuf.CodedInputStream, com.google.protobuf.ExtensionRegistryLite) throws java.io.IOException;
    Code:
       0: aload_2
       1: ifnonnull     12
       4: new           #34                 // class java/lang/NullPointerException
       7: dup
       8: invokespecial #35                 // Method java/lang/NullPointerException."<init>":()V
      11: athrow
      12: iconst_0
      13: istore_3
      14: iload_3
      15: ifne          123
      18: aload_1
      19: invokevirtual #36                 // Method com/google/protobuf/CodedInputStream.readTag:()I
      22: istore        4
      24: iload         4
      26: lookupswitch  { // 3
                     0: 60
                    10: 65
                    18: 86
               default: 107
          }
      60: iconst_1
      61: istore_3
      62: goto          120
      65: aload_0
      66: aload_1
      67: invokevirtual #37                 // Method com/google/protobuf/CodedInputStream.readStringRequireUtf8:()Ljava/lang/String;
      70: putfield      #10                 // Field description_:Ljava/lang/Object;
      73: aload_0
      74: dup
      75: getfield      #14                 // Field bitField0_:I
      78: iconst_1
      79: ior
      80: putfield      #14                 // Field bitField0_:I
      83: goto          120
      86: aload_0
      87: aload_1
      88: invokevirtual #37                 // Method com/google/protobuf/CodedInputStream.readStringRequireUtf8:()Ljava/lang/String;
      91: putfield      #11                 // Field url_:Ljava/lang/Object;
      94: aload_0
      95: dup
      96: getfield      #14                 // Field bitField0_:I
      99: iconst_2
     100: ior
     101: putfield      #14                 // Field bitField0_:I
     104: goto          120
     107: aload_0
     108: aload_1
     109: aload_2
     110: iload         4
     112: invokespecial #38                 // Method com/google/protobuf/GeneratedMessageV3$Builder.parseUnknownField:(Lcom/google/protobuf/CodedInputStream;Lcom/google/protobuf/ExtensionRegistryLite;I)Z
     115: ifne          120
     118: iconst_1
     119: istore_3
     120: goto          14
     123: aload_0
     124: invokevirtual #29                 // Method onChanged:()V
     127: goto          145
     130: astore_3
     131: aload_3
     132: invokevirtual #40                 // Method com/google/protobuf/InvalidProtocolBufferException.unwrapIOException:()Ljava/io/IOException;
     135: athrow
     136: astore        5
     138: aload_0
     139: invokevirtual #29                 // Method onChanged:()V
     142: aload         5
     144: athrow
     145: aload_0
     146: areturn
    Exception table:
       from    to  target type
          12   123   130   Class com/google/protobuf/InvalidProtocolBufferException
          12   123   136   any
         130   138   136   any

  public java.lang.String getDescription();
    Code:
       0: aload_0
       1: getfield      #10                 // Field description_:Ljava/lang/Object;
       4: astore_1
       5: aload_1
       6: instanceof    #41                 // class java/lang/String
       9: ifne          29
      12: aload_1
      13: checkcast     #42                 // class com/google/protobuf/ByteString
      16: astore_2
      17: aload_2
      18: invokevirtual #43                 // Method com/google/protobuf/ByteString.toStringUtf8:()Ljava/lang/String;
      21: astore_3
      22: aload_0
      23: aload_3
      24: putfield      #10                 // Field description_:Ljava/lang/Object;
      27: aload_3
      28: areturn
      29: aload_1
      30: checkcast     #41                 // class java/lang/String
      33: areturn

  public com.google.protobuf.ByteString getDescriptionBytes();
    Code:
       0: aload_0
       1: getfield      #10                 // Field description_:Ljava/lang/Object;
       4: astore_1
       5: aload_1
       6: instanceof    #41                 // class java/lang/String
       9: ifeq          27
      12: aload_1
      13: checkcast     #41                 // class java/lang/String
      16: invokestatic  #44                 // Method com/google/protobuf/ByteString.copyFromUtf8:(Ljava/lang/String;)Lcom/google/protobuf/ByteString;
      19: astore_2
      20: aload_0
      21: aload_2
      22: putfield      #10                 // Field description_:Ljava/lang/Object;
      25: aload_2
      26: areturn
      27: aload_1
      28: checkcast     #42                 // class com/google/protobuf/ByteString
      31: areturn

  public com.google.rpc.Help$Link$Builder setDescription(java.lang.String);
    Code:
       0: aload_1
       1: ifnonnull     12
       4: new           #34                 // class java/lang/NullPointerException
       7: dup
       8: invokespecial #35                 // Method java/lang/NullPointerException."<init>":()V
      11: athrow
      12: aload_0
      13: aload_1
      14: putfield      #10                 // Field description_:Ljava/lang/Object;
      17: aload_0
      18: dup
      19: getfield      #14                 // Field bitField0_:I
      22: iconst_1
      23: ior
      24: putfield      #14                 // Field bitField0_:I
      27: aload_0
      28: invokevirtual #29                 // Method onChanged:()V
      31: aload_0
      32: areturn

  public com.google.rpc.Help$Link$Builder clearDescription();
    Code:
       0: aload_0
       1: invokestatic  #15                 // Method com/google/rpc/Help$Link.getDefaultInstance:()Lcom/google/rpc/Help$Link;
       4: invokevirtual #26                 // Method com/google/rpc/Help$Link.getDescription:()Ljava/lang/String;
       7: putfield      #10                 // Field description_:Ljava/lang/Object;
      10: aload_0
      11: aload_0
      12: getfield      #14                 // Field bitField0_:I
      15: bipush        -2
      17: iand
      18: putfield      #14                 // Field bitField0_:I
      21: aload_0
      22: invokevirtual #29                 // Method onChanged:()V
      25: aload_0
      26: areturn

  public com.google.rpc.Help$Link$Builder setDescriptionBytes(com.google.protobuf.ByteString);
    Code:
       0: aload_1
       1: ifnonnull     12
       4: new           #34                 // class java/lang/NullPointerException
       7: dup
       8: invokespecial #35                 // Method java/lang/NullPointerException."<init>":()V
      11: athrow
      12: aload_1
      13: invokestatic  #45                 // Method com/google/rpc/Help$Link.access$500:(Lcom/google/protobuf/ByteString;)V
      16: aload_0
      17: aload_1
      18: putfield      #10                 // Field description_:Ljava/lang/Object;
      21: aload_0
      22: dup
      23: getfield      #14                 // Field bitField0_:I
      26: iconst_1
      27: ior
      28: putfield      #14                 // Field bitField0_:I
      31: aload_0
      32: invokevirtual #29                 // Method onChanged:()V
      35: aload_0
      36: areturn

  public java.lang.String getUrl();
    Code:
       0: aload_0
       1: getfield      #11                 // Field url_:Ljava/lang/Object;
       4: astore_1
       5: aload_1
       6: instanceof    #41                 // class java/lang/String
       9: ifne          29
      12: aload_1
      13: checkcast     #42                 // class com/google/protobuf/ByteString
      16: astore_2
      17: aload_2
      18: invokevirtual #43                 // Method com/google/protobuf/ByteString.toStringUtf8:()Ljava/lang/String;
      21: astore_3
      22: aload_0
      23: aload_3
      24: putfield      #11                 // Field url_:Ljava/lang/Object;
      27: aload_3
      28: areturn
      29: aload_1
      30: checkcast     #41                 // class java/lang/String
      33: areturn

  public com.google.protobuf.ByteString getUrlBytes();
    Code:
       0: aload_0
       1: getfield      #11                 // Field url_:Ljava/lang/Object;
       4: astore_1
       5: aload_1
       6: instanceof    #41                 // class java/lang/String
       9: ifeq          27
      12: aload_1
      13: checkcast     #41                 // class java/lang/String
      16: invokestatic  #44                 // Method com/google/protobuf/ByteString.copyFromUtf8:(Ljava/lang/String;)Lcom/google/protobuf/ByteString;
      19: astore_2
      20: aload_0
      21: aload_2
      22: putfield      #11                 // Field url_:Ljava/lang/Object;
      25: aload_2
      26: areturn
      27: aload_1
      28: checkcast     #42                 // class com/google/protobuf/ByteString
      31: areturn

  public com.google.rpc.Help$Link$Builder setUrl(java.lang.String);
    Code:
       0: aload_1
       1: ifnonnull     12
       4: new           #34                 // class java/lang/NullPointerException
       7: dup
       8: invokespecial #35                 // Method java/lang/NullPointerException."<init>":()V
      11: athrow
      12: aload_0
      13: aload_1
      14: putfield      #11                 // Field url_:Ljava/lang/Object;
      17: aload_0
      18: dup
      19: getfield      #14                 // Field bitField0_:I
      22: iconst_2
      23: ior
      24: putfield      #14                 // Field bitField0_:I
      27: aload_0
      28: invokevirtual #29                 // Method onChanged:()V
      31: aload_0
      32: areturn

  public com.google.rpc.Help$Link$Builder clearUrl();
    Code:
       0: aload_0
       1: invokestatic  #15                 // Method com/google/rpc/Help$Link.getDefaultInstance:()Lcom/google/rpc/Help$Link;
       4: invokevirtual #30                 // Method com/google/rpc/Help$Link.getUrl:()Ljava/lang/String;
       7: putfield      #11                 // Field url_:Ljava/lang/Object;
      10: aload_0
      11: aload_0
      12: getfield      #14                 // Field bitField0_:I
      15: bipush        -3
      17: iand
      18: putfield      #14                 // Field bitField0_:I
      21: aload_0
      22: invokevirtual #29                 // Method onChanged:()V
      25: aload_0
      26: areturn

  public com.google.rpc.Help$Link$Builder setUrlBytes(com.google.protobuf.ByteString);
    Code:
       0: aload_1
       1: ifnonnull     12
       4: new           #34                 // class java/lang/NullPointerException
       7: dup
       8: invokespecial #35                 // Method java/lang/NullPointerException."<init>":()V
      11: athrow
      12: aload_1
      13: invokestatic  #46                 // Method com/google/rpc/Help$Link.access$600:(Lcom/google/protobuf/ByteString;)V
      16: aload_0
      17: aload_1
      18: putfield      #11                 // Field url_:Ljava/lang/Object;
      21: aload_0
      22: dup
      23: getfield      #14                 // Field bitField0_:I
      26: iconst_2
      27: ior
      28: putfield      #14                 // Field bitField0_:I
      31: aload_0
      32: invokevirtual #29                 // Method onChanged:()V
      35: aload_0
      36: areturn

  public final com.google.rpc.Help$Link$Builder setUnknownFields(com.google.protobuf.UnknownFieldSet);
    Code:
       0: aload_0
       1: aload_1
       2: invokespecial #47                 // Method com/google/protobuf/GeneratedMessageV3$Builder.setUnknownFields:(Lcom/google/protobuf/UnknownFieldSet;)Lcom/google/protobuf/GeneratedMessageV3$Builder;
       5: checkcast     #6                  // class com/google/rpc/Help$Link$Builder
       8: areturn

  public final com.google.rpc.Help$Link$Builder mergeUnknownFields(com.google.protobuf.UnknownFieldSet);
    Code:
       0: aload_0
       1: aload_1
       2: invokespecial #48                 // Method com/google/protobuf/GeneratedMessageV3$Builder.mergeUnknownFields:(Lcom/google/protobuf/UnknownFieldSet;)Lcom/google/protobuf/GeneratedMessageV3$Builder;
       5: checkcast     #6                  // class com/google/rpc/Help$Link$Builder
       8: areturn

  public com.google.protobuf.GeneratedMessageV3$Builder mergeUnknownFields(com.google.protobuf.UnknownFieldSet);
    Code:
       0: aload_0
       1: aload_1
       2: invokevirtual #33                 // Method mergeUnknownFields:(Lcom/google/protobuf/UnknownFieldSet;)Lcom/google/rpc/Help$Link$Builder;
       5: areturn

  public com.google.protobuf.GeneratedMessageV3$Builder setUnknownFields(com.google.protobuf.UnknownFieldSet);
    Code:
       0: aload_0
       1: aload_1
       2: invokevirtual #49                 // Method setUnknownFields:(Lcom/google/protobuf/UnknownFieldSet;)Lcom/google/rpc/Help$Link$Builder;
       5: areturn

  public com.google.protobuf.GeneratedMessageV3$Builder clear();
    Code:
       0: aload_0
       1: invokevirtual #50                 // Method clear:()Lcom/google/rpc/Help$Link$Builder;
       4: areturn

  public com.google.protobuf.AbstractMessage$Builder mergeUnknownFields(com.google.protobuf.UnknownFieldSet);
    Code:
       0: aload_0
       1: aload_1
       2: invokevirtual #33                 // Method mergeUnknownFields:(Lcom/google/protobuf/UnknownFieldSet;)Lcom/google/rpc/Help$Link$Builder;
       5: areturn

  public com.google.protobuf.AbstractMessage$Builder mergeFrom(com.google.protobuf.CodedInputStream, com.google.protobuf.ExtensionRegistryLite) throws java.io.IOException;
    Code:
       0: aload_0
       1: aload_1
       2: aload_2
       3: invokevirtual #51                 // Method mergeFrom:(Lcom/google/protobuf/CodedInputStream;Lcom/google/protobuf/ExtensionRegistryLite;)Lcom/google/rpc/Help$Link$Builder;
       6: areturn

  public com.google.protobuf.AbstractMessage$Builder mergeFrom(com.google.protobuf.Message);
    Code:
       0: aload_0
       1: aload_1
       2: invokevirtual #52                 // Method mergeFrom:(Lcom/google/protobuf/Message;)Lcom/google/rpc/Help$Link$Builder;
       5: areturn

  public com.google.protobuf.AbstractMessage$Builder clear();
    Code:
       0: aload_0
       1: invokevirtual #50                 // Method clear:()Lcom/google/rpc/Help$Link$Builder;
       4: areturn

  public com.google.protobuf.Message$Builder mergeUnknownFields(com.google.protobuf.UnknownFieldSet);
    Code:
       0: aload_0
       1: aload_1
       2: invokevirtual #33                 // Method mergeUnknownFields:(Lcom/google/protobuf/UnknownFieldSet;)Lcom/google/rpc/Help$Link$Builder;
       5: areturn

  public com.google.protobuf.Message$Builder setUnknownFields(com.google.protobuf.UnknownFieldSet);
    Code:
       0: aload_0
       1: aload_1
       2: invokevirtual #49                 // Method setUnknownFields:(Lcom/google/protobuf/UnknownFieldSet;)Lcom/google/rpc/Help$Link$Builder;
       5: areturn

  public com.google.protobuf.Message$Builder mergeFrom(com.google.protobuf.CodedInputStream, com.google.protobuf.ExtensionRegistryLite) throws java.io.IOException;
    Code:
       0: aload_0
       1: aload_1
       2: aload_2
       3: invokevirtual #51                 // Method mergeFrom:(Lcom/google/protobuf/CodedInputStream;Lcom/google/protobuf/ExtensionRegistryLite;)Lcom/google/rpc/Help$Link$Builder;
       6: areturn

  public com.google.protobuf.Message buildPartial();
    Code:
       0: aload_0
       1: invokevirtual #16                 // Method buildPartial:()Lcom/google/rpc/Help$Link;
       4: areturn

  public com.google.protobuf.Message build();
    Code:
       0: aload_0
       1: invokevirtual #53                 // Method build:()Lcom/google/rpc/Help$Link;
       4: areturn

  public com.google.protobuf.Message$Builder mergeFrom(com.google.protobuf.Message);
    Code:
       0: aload_0
       1: aload_1
       2: invokevirtual #52                 // Method mergeFrom:(Lcom/google/protobuf/Message;)Lcom/google/rpc/Help$Link$Builder;
       5: areturn

  public com.google.protobuf.Message$Builder clear();
    Code:
       0: aload_0
       1: invokevirtual #50                 // Method clear:()Lcom/google/rpc/Help$Link$Builder;
       4: areturn

  public com.google.protobuf.MessageLite$Builder mergeFrom(com.google.protobuf.CodedInputStream, com.google.protobuf.ExtensionRegistryLite) throws java.io.IOException;
    Code:
       0: aload_0
       1: aload_1
       2: aload_2
       3: invokevirtual #51                 // Method mergeFrom:(Lcom/google/protobuf/CodedInputStream;Lcom/google/protobuf/ExtensionRegistryLite;)Lcom/google/rpc/Help$Link$Builder;
       6: areturn

  public com.google.protobuf.MessageLite buildPartial();
    Code:
       0: aload_0
       1: invokevirtual #16                 // Method buildPartial:()Lcom/google/rpc/Help$Link;
       4: areturn

  public com.google.protobuf.MessageLite build();
    Code:
       0: aload_0
       1: invokevirtual #53                 // Method build:()Lcom/google/rpc/Help$Link;
       4: areturn

  public com.google.protobuf.MessageLite$Builder clear();
    Code:
       0: aload_0
       1: invokevirtual #50                 // Method clear:()Lcom/google/rpc/Help$Link$Builder;
       4: areturn

  public com.google.protobuf.MessageLite getDefaultInstanceForType();
    Code:
       0: aload_0
       1: invokevirtual #54                 // Method getDefaultInstanceForType:()Lcom/google/rpc/Help$Link;
       4: areturn

  public com.google.protobuf.Message getDefaultInstanceForType();
    Code:
       0: aload_0
       1: invokevirtual #54                 // Method getDefaultInstanceForType:()Lcom/google/rpc/Help$Link;
       4: areturn

  public com.google.protobuf.AbstractMessageLite$Builder mergeFrom(com.google.protobuf.CodedInputStream, com.google.protobuf.ExtensionRegistryLite) throws java.io.IOException;
    Code:
       0: aload_0
       1: aload_1
       2: aload_2
       3: invokevirtual #51                 // Method mergeFrom:(Lcom/google/protobuf/CodedInputStream;Lcom/google/protobuf/ExtensionRegistryLite;)Lcom/google/rpc/Help$Link$Builder;
       6: areturn

  com.google.rpc.Help$Link$Builder(com.google.rpc.Help$1);
    Code:
       0: aload_0
       1: invokespecial #2                  // Method "<init>":()V
       4: return

  com.google.rpc.Help$Link$Builder(com.google.protobuf.GeneratedMessageV3$BuilderParent, com.google.rpc.Help$1);
    Code:
       0: aload_0
       1: aload_1
       2: invokespecial #1                  // Method "<init>":(Lcom/google/protobuf/GeneratedMessageV3$BuilderParent;)V
       5: return
}
