Compiled from "PreconditionFailure.java"
public final class com.google.rpc.PreconditionFailure$Violation$Builder extends com.google.protobuf.GeneratedMessageV3$Builder<com.google.rpc.PreconditionFailure$Violation$Builder> implements com.google.rpc.PreconditionFailure$ViolationOrBuilder {
  private int bitField0_;

  private java.lang.Object type_;

  private java.lang.Object subject_;

  private java.lang.Object description_;

  public static final com.google.protobuf.Descriptors$Descriptor getDescriptor();
    Code:
       0: getstatic     #3                  // Field com/google/rpc/ErrorDetailsProto.internal_static_google_rpc_PreconditionFailure_Violation_descriptor:Lcom/google/protobuf/Descriptors$Descriptor;
       3: areturn

  protected com.google.protobuf.GeneratedMessageV3$FieldAccessorTable internalGetFieldAccessorTable();
    Code:
       0: getstatic     #4                  // Field com/google/rpc/ErrorDetailsProto.internal_static_google_rpc_PreconditionFailure_Violation_fieldAccessorTable:Lcom/google/protobuf/GeneratedMessageV3$FieldAccessorTable;
       3: ldc           #5                  // class com/google/rpc/PreconditionFailure$Violation
       5: ldc           #6                  // class com/google/rpc/PreconditionFailure$Violation$Builder
       7: invokevirtual #7                  // Method com/google/protobuf/GeneratedMessageV3$FieldAccessorTable.ensureFieldAccessorsInitialized:(Ljava/lang/Class;Ljava/lang/Class;)Lcom/google/protobuf/GeneratedMessageV3$FieldAccessorTable;
      10: areturn

  private com.google.rpc.PreconditionFailure$Violation$Builder();
    Code:
       0: aload_0
       1: invokespecial #8                  // Method com/google/protobuf/GeneratedMessageV3$Builder."<init>":()V
       4: aload_0
       5: ldc           #9                  // String
       7: putfield      #10                 // Field type_:Ljava/lang/Object;
      10: aload_0
      11: ldc           #9                  // String
      13: putfield      #11                 // Field subject_:Ljava/lang/Object;
      16: aload_0
      17: ldc           #9                  // String
      19: putfield      #12                 // Field description_:Ljava/lang/Object;
      22: return

  private com.google.rpc.PreconditionFailure$Violation$Builder(com.google.protobuf.GeneratedMessageV3$BuilderParent);
    Code:
       0: aload_0
       1: aload_1
       2: invokespecial #13                 // Method com/google/protobuf/GeneratedMessageV3$Builder."<init>":(Lcom/google/protobuf/GeneratedMessageV3$BuilderParent;)V
       5: aload_0
       6: ldc           #9                  // String
       8: putfield      #10                 // Field type_:Ljava/lang/Object;
      11: aload_0
      12: ldc           #9                  // String
      14: putfield      #11                 // Field subject_:Ljava/lang/Object;
      17: aload_0
      18: ldc           #9                  // String
      20: putfield      #12                 // Field description_:Ljava/lang/Object;
      23: return

  public com.google.rpc.PreconditionFailure$Violation$Builder clear();
    Code:
       0: aload_0
       1: invokespecial #14                 // Method com/google/protobuf/GeneratedMessageV3$Builder.clear:()Lcom/google/protobuf/GeneratedMessageV3$Builder;
       4: pop
       5: aload_0
       6: iconst_0
       7: putfield      #15                 // Field bitField0_:I
      10: aload_0
      11: ldc           #9                  // String
      13: putfield      #10                 // Field type_:Ljava/lang/Object;
      16: aload_0
      17: ldc           #9                  // String
      19: putfield      #11                 // Field subject_:Ljava/lang/Object;
      22: aload_0
      23: ldc           #9                  // String
      25: putfield      #12                 // Field description_:Ljava/lang/Object;
      28: aload_0
      29: areturn

  public com.google.protobuf.Descriptors$Descriptor getDescriptorForType();
    Code:
       0: getstatic     #3                  // Field com/google/rpc/ErrorDetailsProto.internal_static_google_rpc_PreconditionFailure_Violation_descriptor:Lcom/google/protobuf/Descriptors$Descriptor;
       3: areturn

  public com.google.rpc.PreconditionFailure$Violation getDefaultInstanceForType();
    Code:
       0: invokestatic  #16                 // Method com/google/rpc/PreconditionFailure$Violation.getDefaultInstance:()Lcom/google/rpc/PreconditionFailure$Violation;
       3: areturn

  public com.google.rpc.PreconditionFailure$Violation build();
    Code:
       0: aload_0
       1: invokevirtual #17                 // Method buildPartial:()Lcom/google/rpc/PreconditionFailure$Violation;
       4: astore_1
       5: aload_1
       6: invokevirtual #18                 // Method com/google/rpc/PreconditionFailure$Violation.isInitialized:()Z
       9: ifne          17
      12: aload_1
      13: invokestatic  #19                 // Method newUninitializedMessageException:(Lcom/google/protobuf/Message;)Lcom/google/protobuf/UninitializedMessageException;
      16: athrow
      17: aload_1
      18: areturn

  public com.google.rpc.PreconditionFailure$Violation buildPartial();
    Code:
       0: new           #5                  // class com/google/rpc/PreconditionFailure$Violation
       3: dup
       4: aload_0
       5: aconst_null
       6: invokespecial #20                 // Method com/google/rpc/PreconditionFailure$Violation."<init>":(Lcom/google/protobuf/GeneratedMessageV3$Builder;Lcom/google/rpc/PreconditionFailure$1;)V
       9: astore_1
      10: aload_0
      11: getfield      #15                 // Field bitField0_:I
      14: ifeq          22
      17: aload_0
      18: aload_1
      19: invokespecial #21                 // Method buildPartial0:(Lcom/google/rpc/PreconditionFailure$Violation;)V
      22: aload_0
      23: invokevirtual #22                 // Method onBuilt:()V
      26: aload_1
      27: areturn

  private void buildPartial0(com.google.rpc.PreconditionFailure$Violation);
    Code:
       0: aload_0
       1: getfield      #15                 // Field bitField0_:I
       4: istore_2
       5: iload_2
       6: iconst_1
       7: iand
       8: ifeq          20
      11: aload_1
      12: aload_0
      13: getfield      #10                 // Field type_:Ljava/lang/Object;
      16: invokestatic  #23                 // Method com/google/rpc/PreconditionFailure$Violation.access$302:(Lcom/google/rpc/PreconditionFailure$Violation;Ljava/lang/Object;)Ljava/lang/Object;
      19: pop
      20: iload_2
      21: iconst_2
      22: iand
      23: ifeq          35
      26: aload_1
      27: aload_0
      28: getfield      #11                 // Field subject_:Ljava/lang/Object;
      31: invokestatic  #24                 // Method com/google/rpc/PreconditionFailure$Violation.access$402:(Lcom/google/rpc/PreconditionFailure$Violation;Ljava/lang/Object;)Ljava/lang/Object;
      34: pop
      35: iload_2
      36: iconst_4
      37: iand
      38: ifeq          50
      41: aload_1
      42: aload_0
      43: getfield      #12                 // Field description_:Ljava/lang/Object;
      46: invokestatic  #25                 // Method com/google/rpc/PreconditionFailure$Violation.access$502:(Lcom/google/rpc/PreconditionFailure$Violation;Ljava/lang/Object;)Ljava/lang/Object;
      49: pop
      50: return

  public com.google.rpc.PreconditionFailure$Violation$Builder mergeFrom(com.google.protobuf.Message);
    Code:
       0: aload_1
       1: instanceof    #5                  // class com/google/rpc/PreconditionFailure$Violation
       4: ifeq          16
       7: aload_0
       8: aload_1
       9: checkcast     #5                  // class com/google/rpc/PreconditionFailure$Violation
      12: invokevirtual #26                 // Method mergeFrom:(Lcom/google/rpc/PreconditionFailure$Violation;)Lcom/google/rpc/PreconditionFailure$Violation$Builder;
      15: areturn
      16: aload_0
      17: aload_1
      18: invokespecial #27                 // Method com/google/protobuf/GeneratedMessageV3$Builder.mergeFrom:(Lcom/google/protobuf/Message;)Lcom/google/protobuf/AbstractMessage$Builder;
      21: pop
      22: aload_0
      23: areturn

  public com.google.rpc.PreconditionFailure$Violation$Builder mergeFrom(com.google.rpc.PreconditionFailure$Violation);
    Code:
       0: aload_1
       1: invokestatic  #16                 // Method com/google/rpc/PreconditionFailure$Violation.getDefaultInstance:()Lcom/google/rpc/PreconditionFailure$Violation;
       4: if_acmpne     9
       7: aload_0
       8: areturn
       9: aload_1
      10: invokevirtual #28                 // Method com/google/rpc/PreconditionFailure$Violation.getType:()Ljava/lang/String;
      13: invokevirtual #29                 // Method java/lang/String.isEmpty:()Z
      16: ifne          41
      19: aload_0
      20: aload_1
      21: invokestatic  #30                 // Method com/google/rpc/PreconditionFailure$Violation.access$300:(Lcom/google/rpc/PreconditionFailure$Violation;)Ljava/lang/Object;
      24: putfield      #10                 // Field type_:Ljava/lang/Object;
      27: aload_0
      28: dup
      29: getfield      #15                 // Field bitField0_:I
      32: iconst_1
      33: ior
      34: putfield      #15                 // Field bitField0_:I
      37: aload_0
      38: invokevirtual #31                 // Method onChanged:()V
      41: aload_1
      42: invokevirtual #32                 // Method com/google/rpc/PreconditionFailure$Violation.getSubject:()Ljava/lang/String;
      45: invokevirtual #29                 // Method java/lang/String.isEmpty:()Z
      48: ifne          73
      51: aload_0
      52: aload_1
      53: invokestatic  #33                 // Method com/google/rpc/PreconditionFailure$Violation.access$400:(Lcom/google/rpc/PreconditionFailure$Violation;)Ljava/lang/Object;
      56: putfield      #11                 // Field subject_:Ljava/lang/Object;
      59: aload_0
      60: dup
      61: getfield      #15                 // Field bitField0_:I
      64: iconst_2
      65: ior
      66: putfield      #15                 // Field bitField0_:I
      69: aload_0
      70: invokevirtual #31                 // Method onChanged:()V
      73: aload_1
      74: invokevirtual #34                 // Method com/google/rpc/PreconditionFailure$Violation.getDescription:()Ljava/lang/String;
      77: invokevirtual #29                 // Method java/lang/String.isEmpty:()Z
      80: ifne          105
      83: aload_0
      84: aload_1
      85: invokestatic  #35                 // Method com/google/rpc/PreconditionFailure$Violation.access$500:(Lcom/google/rpc/PreconditionFailure$Violation;)Ljava/lang/Object;
      88: putfield      #12                 // Field description_:Ljava/lang/Object;
      91: aload_0
      92: dup
      93: getfield      #15                 // Field bitField0_:I
      96: iconst_4
      97: ior
      98: putfield      #15                 // Field bitField0_:I
     101: aload_0
     102: invokevirtual #31                 // Method onChanged:()V
     105: aload_0
     106: aload_1
     107: invokevirtual #36                 // Method com/google/rpc/PreconditionFailure$Violation.getUnknownFields:()Lcom/google/protobuf/UnknownFieldSet;
     110: invokevirtual #37                 // Method mergeUnknownFields:(Lcom/google/protobuf/UnknownFieldSet;)Lcom/google/rpc/PreconditionFailure$Violation$Builder;
     113: pop
     114: aload_0
     115: invokevirtual #31                 // Method onChanged:()V
     118: aload_0
     119: areturn

  public final boolean isInitialized();
    Code:
       0: iconst_1
       1: ireturn

  public com.google.rpc.PreconditionFailure$Violation$Builder mergeFrom(com.google.protobuf.CodedInputStream, com.google.protobuf.ExtensionRegistryLite) throws java.io.IOException;
    Code:
       0: aload_2
       1: ifnonnull     12
       4: new           #38                 // class java/lang/NullPointerException
       7: dup
       8: invokespecial #39                 // Method java/lang/NullPointerException."<init>":()V
      11: athrow
      12: iconst_0
      13: istore_3
      14: iload_3
      15: ifne          152
      18: aload_1
      19: invokevirtual #40                 // Method com/google/protobuf/CodedInputStream.readTag:()I
      22: istore        4
      24: iload         4
      26: lookupswitch  { // 4
                     0: 68
                    10: 73
                    18: 94
                    26: 115
               default: 136
          }
      68: iconst_1
      69: istore_3
      70: goto          149
      73: aload_0
      74: aload_1
      75: invokevirtual #41                 // Method com/google/protobuf/CodedInputStream.readStringRequireUtf8:()Ljava/lang/String;
      78: putfield      #10                 // Field type_:Ljava/lang/Object;
      81: aload_0
      82: dup
      83: getfield      #15                 // Field bitField0_:I
      86: iconst_1
      87: ior
      88: putfield      #15                 // Field bitField0_:I
      91: goto          149
      94: aload_0
      95: aload_1
      96: invokevirtual #41                 // Method com/google/protobuf/CodedInputStream.readStringRequireUtf8:()Ljava/lang/String;
      99: putfield      #11                 // Field subject_:Ljava/lang/Object;
     102: aload_0
     103: dup
     104: getfield      #15                 // Field bitField0_:I
     107: iconst_2
     108: ior
     109: putfield      #15                 // Field bitField0_:I
     112: goto          149
     115: aload_0
     116: aload_1
     117: invokevirtual #41                 // Method com/google/protobuf/CodedInputStream.readStringRequireUtf8:()Ljava/lang/String;
     120: putfield      #12                 // Field description_:Ljava/lang/Object;
     123: aload_0
     124: dup
     125: getfield      #15                 // Field bitField0_:I
     128: iconst_4
     129: ior
     130: putfield      #15                 // Field bitField0_:I
     133: goto          149
     136: aload_0
     137: aload_1
     138: aload_2
     139: iload         4
     141: invokespecial #42                 // Method com/google/protobuf/GeneratedMessageV3$Builder.parseUnknownField:(Lcom/google/protobuf/CodedInputStream;Lcom/google/protobuf/ExtensionRegistryLite;I)Z
     144: ifne          149
     147: iconst_1
     148: istore_3
     149: goto          14
     152: aload_0
     153: invokevirtual #31                 // Method onChanged:()V
     156: goto          174
     159: astore_3
     160: aload_3
     161: invokevirtual #44                 // Method com/google/protobuf/InvalidProtocolBufferException.unwrapIOException:()Ljava/io/IOException;
     164: athrow
     165: astore        5
     167: aload_0
     168: invokevirtual #31                 // Method onChanged:()V
     171: aload         5
     173: athrow
     174: aload_0
     175: areturn
    Exception table:
       from    to  target type
          12   152   159   Class com/google/protobuf/InvalidProtocolBufferException
          12   152   165   any
         159   167   165   any

  public java.lang.String getType();
    Code:
       0: aload_0
       1: getfield      #10                 // Field type_:Ljava/lang/Object;
       4: astore_1
       5: aload_1
       6: instanceof    #45                 // class java/lang/String
       9: ifne          29
      12: aload_1
      13: checkcast     #46                 // class com/google/protobuf/ByteString
      16: astore_2
      17: aload_2
      18: invokevirtual #47                 // Method com/google/protobuf/ByteString.toStringUtf8:()Ljava/lang/String;
      21: astore_3
      22: aload_0
      23: aload_3
      24: putfield      #10                 // Field type_:Ljava/lang/Object;
      27: aload_3
      28: areturn
      29: aload_1
      30: checkcast     #45                 // class java/lang/String
      33: areturn

  public com.google.protobuf.ByteString getTypeBytes();
    Code:
       0: aload_0
       1: getfield      #10                 // Field type_:Ljava/lang/Object;
       4: astore_1
       5: aload_1
       6: instanceof    #45                 // class java/lang/String
       9: ifeq          27
      12: aload_1
      13: checkcast     #45                 // class java/lang/String
      16: invokestatic  #48                 // Method com/google/protobuf/ByteString.copyFromUtf8:(Ljava/lang/String;)Lcom/google/protobuf/ByteString;
      19: astore_2
      20: aload_0
      21: aload_2
      22: putfield      #10                 // Field type_:Ljava/lang/Object;
      25: aload_2
      26: areturn
      27: aload_1
      28: checkcast     #46                 // class com/google/protobuf/ByteString
      31: areturn

  public com.google.rpc.PreconditionFailure$Violation$Builder setType(java.lang.String);
    Code:
       0: aload_1
       1: ifnonnull     12
       4: new           #38                 // class java/lang/NullPointerException
       7: dup
       8: invokespecial #39                 // Method java/lang/NullPointerException."<init>":()V
      11: athrow
      12: aload_0
      13: aload_1
      14: putfield      #10                 // Field type_:Ljava/lang/Object;
      17: aload_0
      18: dup
      19: getfield      #15                 // Field bitField0_:I
      22: iconst_1
      23: ior
      24: putfield      #15                 // Field bitField0_:I
      27: aload_0
      28: invokevirtual #31                 // Method onChanged:()V
      31: aload_0
      32: areturn

  public com.google.rpc.PreconditionFailure$Violation$Builder clearType();
    Code:
       0: aload_0
       1: invokestatic  #16                 // Method com/google/rpc/PreconditionFailure$Violation.getDefaultInstance:()Lcom/google/rpc/PreconditionFailure$Violation;
       4: invokevirtual #28                 // Method com/google/rpc/PreconditionFailure$Violation.getType:()Ljava/lang/String;
       7: putfield      #10                 // Field type_:Ljava/lang/Object;
      10: aload_0
      11: aload_0
      12: getfield      #15                 // Field bitField0_:I
      15: bipush        -2
      17: iand
      18: putfield      #15                 // Field bitField0_:I
      21: aload_0
      22: invokevirtual #31                 // Method onChanged:()V
      25: aload_0
      26: areturn

  public com.google.rpc.PreconditionFailure$Violation$Builder setTypeBytes(com.google.protobuf.ByteString);
    Code:
       0: aload_1
       1: ifnonnull     12
       4: new           #38                 // class java/lang/NullPointerException
       7: dup
       8: invokespecial #39                 // Method java/lang/NullPointerException."<init>":()V
      11: athrow
      12: aload_1
      13: invokestatic  #49                 // Method com/google/rpc/PreconditionFailure$Violation.access$600:(Lcom/google/protobuf/ByteString;)V
      16: aload_0
      17: aload_1
      18: putfield      #10                 // Field type_:Ljava/lang/Object;
      21: aload_0
      22: dup
      23: getfield      #15                 // Field bitField0_:I
      26: iconst_1
      27: ior
      28: putfield      #15                 // Field bitField0_:I
      31: aload_0
      32: invokevirtual #31                 // Method onChanged:()V
      35: aload_0
      36: areturn

  public java.lang.String getSubject();
    Code:
       0: aload_0
       1: getfield      #11                 // Field subject_:Ljava/lang/Object;
       4: astore_1
       5: aload_1
       6: instanceof    #45                 // class java/lang/String
       9: ifne          29
      12: aload_1
      13: checkcast     #46                 // class com/google/protobuf/ByteString
      16: astore_2
      17: aload_2
      18: invokevirtual #47                 // Method com/google/protobuf/ByteString.toStringUtf8:()Ljava/lang/String;
      21: astore_3
      22: aload_0
      23: aload_3
      24: putfield      #11                 // Field subject_:Ljava/lang/Object;
      27: aload_3
      28: areturn
      29: aload_1
      30: checkcast     #45                 // class java/lang/String
      33: areturn

  public com.google.protobuf.ByteString getSubjectBytes();
    Code:
       0: aload_0
       1: getfield      #11                 // Field subject_:Ljava/lang/Object;
       4: astore_1
       5: aload_1
       6: instanceof    #45                 // class java/lang/String
       9: ifeq          27
      12: aload_1
      13: checkcast     #45                 // class java/lang/String
      16: invokestatic  #48                 // Method com/google/protobuf/ByteString.copyFromUtf8:(Ljava/lang/String;)Lcom/google/protobuf/ByteString;
      19: astore_2
      20: aload_0
      21: aload_2
      22: putfield      #11                 // Field subject_:Ljava/lang/Object;
      25: aload_2
      26: areturn
      27: aload_1
      28: checkcast     #46                 // class com/google/protobuf/ByteString
      31: areturn

  public com.google.rpc.PreconditionFailure$Violation$Builder setSubject(java.lang.String);
    Code:
       0: aload_1
       1: ifnonnull     12
       4: new           #38                 // class java/lang/NullPointerException
       7: dup
       8: invokespecial #39                 // Method java/lang/NullPointerException."<init>":()V
      11: athrow
      12: aload_0
      13: aload_1
      14: putfield      #11                 // Field subject_:Ljava/lang/Object;
      17: aload_0
      18: dup
      19: getfield      #15                 // Field bitField0_:I
      22: iconst_2
      23: ior
      24: putfield      #15                 // Field bitField0_:I
      27: aload_0
      28: invokevirtual #31                 // Method onChanged:()V
      31: aload_0
      32: areturn

  public com.google.rpc.PreconditionFailure$Violation$Builder clearSubject();
    Code:
       0: aload_0
       1: invokestatic  #16                 // Method com/google/rpc/PreconditionFailure$Violation.getDefaultInstance:()Lcom/google/rpc/PreconditionFailure$Violation;
       4: invokevirtual #32                 // Method com/google/rpc/PreconditionFailure$Violation.getSubject:()Ljava/lang/String;
       7: putfield      #11                 // Field subject_:Ljava/lang/Object;
      10: aload_0
      11: aload_0
      12: getfield      #15                 // Field bitField0_:I
      15: bipush        -3
      17: iand
      18: putfield      #15                 // Field bitField0_:I
      21: aload_0
      22: invokevirtual #31                 // Method onChanged:()V
      25: aload_0
      26: areturn

  public com.google.rpc.PreconditionFailure$Violation$Builder setSubjectBytes(com.google.protobuf.ByteString);
    Code:
       0: aload_1
       1: ifnonnull     12
       4: new           #38                 // class java/lang/NullPointerException
       7: dup
       8: invokespecial #39                 // Method java/lang/NullPointerException."<init>":()V
      11: athrow
      12: aload_1
      13: invokestatic  #50                 // Method com/google/rpc/PreconditionFailure$Violation.access$700:(Lcom/google/protobuf/ByteString;)V
      16: aload_0
      17: aload_1
      18: putfield      #11                 // Field subject_:Ljava/lang/Object;
      21: aload_0
      22: dup
      23: getfield      #15                 // Field bitField0_:I
      26: iconst_2
      27: ior
      28: putfield      #15                 // Field bitField0_:I
      31: aload_0
      32: invokevirtual #31                 // Method onChanged:()V
      35: aload_0
      36: areturn

  public java.lang.String getDescription();
    Code:
       0: aload_0
       1: getfield      #12                 // Field description_:Ljava/lang/Object;
       4: astore_1
       5: aload_1
       6: instanceof    #45                 // class java/lang/String
       9: ifne          29
      12: aload_1
      13: checkcast     #46                 // class com/google/protobuf/ByteString
      16: astore_2
      17: aload_2
      18: invokevirtual #47                 // Method com/google/protobuf/ByteString.toStringUtf8:()Ljava/lang/String;
      21: astore_3
      22: aload_0
      23: aload_3
      24: putfield      #12                 // Field description_:Ljava/lang/Object;
      27: aload_3
      28: areturn
      29: aload_1
      30: checkcast     #45                 // class java/lang/String
      33: areturn

  public com.google.protobuf.ByteString getDescriptionBytes();
    Code:
       0: aload_0
       1: getfield      #12                 // Field description_:Ljava/lang/Object;
       4: astore_1
       5: aload_1
       6: instanceof    #45                 // class java/lang/String
       9: ifeq          27
      12: aload_1
      13: checkcast     #45                 // class java/lang/String
      16: invokestatic  #48                 // Method com/google/protobuf/ByteString.copyFromUtf8:(Ljava/lang/String;)Lcom/google/protobuf/ByteString;
      19: astore_2
      20: aload_0
      21: aload_2
      22: putfield      #12                 // Field description_:Ljava/lang/Object;
      25: aload_2
      26: areturn
      27: aload_1
      28: checkcast     #46                 // class com/google/protobuf/ByteString
      31: areturn

  public com.google.rpc.PreconditionFailure$Violation$Builder setDescription(java.lang.String);
    Code:
       0: aload_1
       1: ifnonnull     12
       4: new           #38                 // class java/lang/NullPointerException
       7: dup
       8: invokespecial #39                 // Method java/lang/NullPointerException."<init>":()V
      11: athrow
      12: aload_0
      13: aload_1
      14: putfield      #12                 // Field description_:Ljava/lang/Object;
      17: aload_0
      18: dup
      19: getfield      #15                 // Field bitField0_:I
      22: iconst_4
      23: ior
      24: putfield      #15                 // Field bitField0_:I
      27: aload_0
      28: invokevirtual #31                 // Method onChanged:()V
      31: aload_0
      32: areturn

  public com.google.rpc.PreconditionFailure$Violation$Builder clearDescription();
    Code:
       0: aload_0
       1: invokestatic  #16                 // Method com/google/rpc/PreconditionFailure$Violation.getDefaultInstance:()Lcom/google/rpc/PreconditionFailure$Violation;
       4: invokevirtual #34                 // Method com/google/rpc/PreconditionFailure$Violation.getDescription:()Ljava/lang/String;
       7: putfield      #12                 // Field description_:Ljava/lang/Object;
      10: aload_0
      11: aload_0
      12: getfield      #15                 // Field bitField0_:I
      15: bipush        -5
      17: iand
      18: putfield      #15                 // Field bitField0_:I
      21: aload_0
      22: invokevirtual #31                 // Method onChanged:()V
      25: aload_0
      26: areturn

  public com.google.rpc.PreconditionFailure$Violation$Builder setDescriptionBytes(com.google.protobuf.ByteString);
    Code:
       0: aload_1
       1: ifnonnull     12
       4: new           #38                 // class java/lang/NullPointerException
       7: dup
       8: invokespecial #39                 // Method java/lang/NullPointerException."<init>":()V
      11: athrow
      12: aload_1
      13: invokestatic  #51                 // Method com/google/rpc/PreconditionFailure$Violation.access$800:(Lcom/google/protobuf/ByteString;)V
      16: aload_0
      17: aload_1
      18: putfield      #12                 // Field description_:Ljava/lang/Object;
      21: aload_0
      22: dup
      23: getfield      #15                 // Field bitField0_:I
      26: iconst_4
      27: ior
      28: putfield      #15                 // Field bitField0_:I
      31: aload_0
      32: invokevirtual #31                 // Method onChanged:()V
      35: aload_0
      36: areturn

  public final com.google.rpc.PreconditionFailure$Violation$Builder setUnknownFields(com.google.protobuf.UnknownFieldSet);
    Code:
       0: aload_0
       1: aload_1
       2: invokespecial #52                 // Method com/google/protobuf/GeneratedMessageV3$Builder.setUnknownFields:(Lcom/google/protobuf/UnknownFieldSet;)Lcom/google/protobuf/GeneratedMessageV3$Builder;
       5: checkcast     #6                  // class com/google/rpc/PreconditionFailure$Violation$Builder
       8: areturn

  public final com.google.rpc.PreconditionFailure$Violation$Builder mergeUnknownFields(com.google.protobuf.UnknownFieldSet);
    Code:
       0: aload_0
       1: aload_1
       2: invokespecial #53                 // Method com/google/protobuf/GeneratedMessageV3$Builder.mergeUnknownFields:(Lcom/google/protobuf/UnknownFieldSet;)Lcom/google/protobuf/GeneratedMessageV3$Builder;
       5: checkcast     #6                  // class com/google/rpc/PreconditionFailure$Violation$Builder
       8: areturn

  public com.google.protobuf.GeneratedMessageV3$Builder mergeUnknownFields(com.google.protobuf.UnknownFieldSet);
    Code:
       0: aload_0
       1: aload_1
       2: invokevirtual #37                 // Method mergeUnknownFields:(Lcom/google/protobuf/UnknownFieldSet;)Lcom/google/rpc/PreconditionFailure$Violation$Builder;
       5: areturn

  public com.google.protobuf.GeneratedMessageV3$Builder setUnknownFields(com.google.protobuf.UnknownFieldSet);
    Code:
       0: aload_0
       1: aload_1
       2: invokevirtual #54                 // Method setUnknownFields:(Lcom/google/protobuf/UnknownFieldSet;)Lcom/google/rpc/PreconditionFailure$Violation$Builder;
       5: areturn

  public com.google.protobuf.GeneratedMessageV3$Builder clear();
    Code:
       0: aload_0
       1: invokevirtual #55                 // Method clear:()Lcom/google/rpc/PreconditionFailure$Violation$Builder;
       4: areturn

  public com.google.protobuf.AbstractMessage$Builder mergeUnknownFields(com.google.protobuf.UnknownFieldSet);
    Code:
       0: aload_0
       1: aload_1
       2: invokevirtual #37                 // Method mergeUnknownFields:(Lcom/google/protobuf/UnknownFieldSet;)Lcom/google/rpc/PreconditionFailure$Violation$Builder;
       5: areturn

  public com.google.protobuf.AbstractMessage$Builder mergeFrom(com.google.protobuf.CodedInputStream, com.google.protobuf.ExtensionRegistryLite) throws java.io.IOException;
    Code:
       0: aload_0
       1: aload_1
       2: aload_2
       3: invokevirtual #56                 // Method mergeFrom:(Lcom/google/protobuf/CodedInputStream;Lcom/google/protobuf/ExtensionRegistryLite;)Lcom/google/rpc/PreconditionFailure$Violation$Builder;
       6: areturn

  public com.google.protobuf.AbstractMessage$Builder mergeFrom(com.google.protobuf.Message);
    Code:
       0: aload_0
       1: aload_1
       2: invokevirtual #57                 // Method mergeFrom:(Lcom/google/protobuf/Message;)Lcom/google/rpc/PreconditionFailure$Violation$Builder;
       5: areturn

  public com.google.protobuf.AbstractMessage$Builder clear();
    Code:
       0: aload_0
       1: invokevirtual #55                 // Method clear:()Lcom/google/rpc/PreconditionFailure$Violation$Builder;
       4: areturn

  public com.google.protobuf.Message$Builder mergeUnknownFields(com.google.protobuf.UnknownFieldSet);
    Code:
       0: aload_0
       1: aload_1
       2: invokevirtual #37                 // Method mergeUnknownFields:(Lcom/google/protobuf/UnknownFieldSet;)Lcom/google/rpc/PreconditionFailure$Violation$Builder;
       5: areturn

  public com.google.protobuf.Message$Builder setUnknownFields(com.google.protobuf.UnknownFieldSet);
    Code:
       0: aload_0
       1: aload_1
       2: invokevirtual #54                 // Method setUnknownFields:(Lcom/google/protobuf/UnknownFieldSet;)Lcom/google/rpc/PreconditionFailure$Violation$Builder;
       5: areturn

  public com.google.protobuf.Message$Builder mergeFrom(com.google.protobuf.CodedInputStream, com.google.protobuf.ExtensionRegistryLite) throws java.io.IOException;
    Code:
       0: aload_0
       1: aload_1
       2: aload_2
       3: invokevirtual #56                 // Method mergeFrom:(Lcom/google/protobuf/CodedInputStream;Lcom/google/protobuf/ExtensionRegistryLite;)Lcom/google/rpc/PreconditionFailure$Violation$Builder;
       6: areturn

  public com.google.protobuf.Message buildPartial();
    Code:
       0: aload_0
       1: invokevirtual #17                 // Method buildPartial:()Lcom/google/rpc/PreconditionFailure$Violation;
       4: areturn

  public com.google.protobuf.Message build();
    Code:
       0: aload_0
       1: invokevirtual #58                 // Method build:()Lcom/google/rpc/PreconditionFailure$Violation;
       4: areturn

  public com.google.protobuf.Message$Builder mergeFrom(com.google.protobuf.Message);
    Code:
       0: aload_0
       1: aload_1
       2: invokevirtual #57                 // Method mergeFrom:(Lcom/google/protobuf/Message;)Lcom/google/rpc/PreconditionFailure$Violation$Builder;
       5: areturn

  public com.google.protobuf.Message$Builder clear();
    Code:
       0: aload_0
       1: invokevirtual #55                 // Method clear:()Lcom/google/rpc/PreconditionFailure$Violation$Builder;
       4: areturn

  public com.google.protobuf.MessageLite$Builder mergeFrom(com.google.protobuf.CodedInputStream, com.google.protobuf.ExtensionRegistryLite) throws java.io.IOException;
    Code:
       0: aload_0
       1: aload_1
       2: aload_2
       3: invokevirtual #56                 // Method mergeFrom:(Lcom/google/protobuf/CodedInputStream;Lcom/google/protobuf/ExtensionRegistryLite;)Lcom/google/rpc/PreconditionFailure$Violation$Builder;
       6: areturn

  public com.google.protobuf.MessageLite buildPartial();
    Code:
       0: aload_0
       1: invokevirtual #17                 // Method buildPartial:()Lcom/google/rpc/PreconditionFailure$Violation;
       4: areturn

  public com.google.protobuf.MessageLite build();
    Code:
       0: aload_0
       1: invokevirtual #58                 // Method build:()Lcom/google/rpc/PreconditionFailure$Violation;
       4: areturn

  public com.google.protobuf.MessageLite$Builder clear();
    Code:
       0: aload_0
       1: invokevirtual #55                 // Method clear:()Lcom/google/rpc/PreconditionFailure$Violation$Builder;
       4: areturn

  public com.google.protobuf.MessageLite getDefaultInstanceForType();
    Code:
       0: aload_0
       1: invokevirtual #59                 // Method getDefaultInstanceForType:()Lcom/google/rpc/PreconditionFailure$Violation;
       4: areturn

  public com.google.protobuf.Message getDefaultInstanceForType();
    Code:
       0: aload_0
       1: invokevirtual #59                 // Method getDefaultInstanceForType:()Lcom/google/rpc/PreconditionFailure$Violation;
       4: areturn

  public com.google.protobuf.AbstractMessageLite$Builder mergeFrom(com.google.protobuf.CodedInputStream, com.google.protobuf.ExtensionRegistryLite) throws java.io.IOException;
    Code:
       0: aload_0
       1: aload_1
       2: aload_2
       3: invokevirtual #56                 // Method mergeFrom:(Lcom/google/protobuf/CodedInputStream;Lcom/google/protobuf/ExtensionRegistryLite;)Lcom/google/rpc/PreconditionFailure$Violation$Builder;
       6: areturn

  com.google.rpc.PreconditionFailure$Violation$Builder(com.google.rpc.PreconditionFailure$1);
    Code:
       0: aload_0
       1: invokespecial #2                  // Method "<init>":()V
       4: return

  com.google.rpc.PreconditionFailure$Violation$Builder(com.google.protobuf.GeneratedMessageV3$BuilderParent, com.google.rpc.PreconditionFailure$1);
    Code:
       0: aload_0
       1: aload_1
       2: invokespecial #1                  // Method "<init>":(Lcom/google/protobuf/GeneratedMessageV3$BuilderParent;)V
       5: return
}
