Compiled from "PreconditionFailure.java"
public final class com.google.rpc.PreconditionFailure$Violation extends com.google.protobuf.GeneratedMessageV3 implements com.google.rpc.PreconditionFailure$ViolationOrBuilder {
  private static final long serialVersionUID;

  public static final int TYPE_FIELD_NUMBER;

  private volatile java.lang.Object type_;

  public static final int SUBJECT_FIELD_NUMBER;

  private volatile java.lang.Object subject_;

  public static final int DESCRIPTION_FIELD_NUMBER;

  private volatile java.lang.Object description_;

  private byte memoizedIsInitialized;

  private static final com.google.rpc.PreconditionFailure$Violation DEFAULT_INSTANCE;

  private static final com.google.protobuf.Parser<com.google.rpc.PreconditionFailure$Violation> PARSER;

  private com.google.rpc.PreconditionFailure$Violation(com.google.protobuf.GeneratedMessageV3$Builder<?>);
    Code:
       0: aload_0
       1: aload_1
       2: invokespecial #6                  // Method com/google/protobuf/GeneratedMessageV3."<init>":(Lcom/google/protobuf/GeneratedMessageV3$Builder;)V
       5: aload_0
       6: ldc           #7                  // String
       8: putfield      #4                  // Field type_:Ljava/lang/Object;
      11: aload_0
      12: ldc           #7                  // String
      14: putfield      #3                  // Field subject_:Ljava/lang/Object;
      17: aload_0
      18: ldc           #7                  // String
      20: putfield      #2                  // Field description_:Ljava/lang/Object;
      23: aload_0
      24: iconst_m1
      25: putfield      #8                  // Field memoizedIsInitialized:B
      28: return

  private com.google.rpc.PreconditionFailure$Violation();
    Code:
       0: aload_0
       1: invokespecial #9                  // Method com/google/protobuf/GeneratedMessageV3."<init>":()V
       4: aload_0
       5: ldc           #7                  // String
       7: putfield      #4                  // Field type_:Ljava/lang/Object;
      10: aload_0
      11: ldc           #7                  // String
      13: putfield      #3                  // Field subject_:Ljava/lang/Object;
      16: aload_0
      17: ldc           #7                  // String
      19: putfield      #2                  // Field description_:Ljava/lang/Object;
      22: aload_0
      23: iconst_m1
      24: putfield      #8                  // Field memoizedIsInitialized:B
      27: aload_0
      28: ldc           #7                  // String
      30: putfield      #4                  // Field type_:Ljava/lang/Object;
      33: aload_0
      34: ldc           #7                  // String
      36: putfield      #3                  // Field subject_:Ljava/lang/Object;
      39: aload_0
      40: ldc           #7                  // String
      42: putfield      #2                  // Field description_:Ljava/lang/Object;
      45: return

  protected java.lang.Object newInstance(com.google.protobuf.GeneratedMessageV3$UnusedPrivateParameter);
    Code:
       0: new           #10                 // class com/google/rpc/PreconditionFailure$Violation
       3: dup
       4: invokespecial #11                 // Method "<init>":()V
       7: areturn

  public static final com.google.protobuf.Descriptors$Descriptor getDescriptor();
    Code:
       0: getstatic     #12                 // Field com/google/rpc/ErrorDetailsProto.internal_static_google_rpc_PreconditionFailure_Violation_descriptor:Lcom/google/protobuf/Descriptors$Descriptor;
       3: areturn

  protected com.google.protobuf.GeneratedMessageV3$FieldAccessorTable internalGetFieldAccessorTable();
    Code:
       0: getstatic     #13                 // Field com/google/rpc/ErrorDetailsProto.internal_static_google_rpc_PreconditionFailure_Violation_fieldAccessorTable:Lcom/google/protobuf/GeneratedMessageV3$FieldAccessorTable;
       3: ldc           #10                 // class com/google/rpc/PreconditionFailure$Violation
       5: ldc           #14                 // class com/google/rpc/PreconditionFailure$Violation$Builder
       7: invokevirtual #15                 // Method com/google/protobuf/GeneratedMessageV3$FieldAccessorTable.ensureFieldAccessorsInitialized:(Ljava/lang/Class;Ljava/lang/Class;)Lcom/google/protobuf/GeneratedMessageV3$FieldAccessorTable;
      10: areturn

  public java.lang.String getType();
    Code:
       0: aload_0
       1: getfield      #4                  // Field type_:Ljava/lang/Object;
       4: astore_1
       5: aload_1
       6: instanceof    #16                 // class java/lang/String
       9: ifeq          17
      12: aload_1
      13: checkcast     #16                 // class java/lang/String
      16: areturn
      17: aload_1
      18: checkcast     #17                 // class com/google/protobuf/ByteString
      21: astore_2
      22: aload_2
      23: invokevirtual #18                 // Method com/google/protobuf/ByteString.toStringUtf8:()Ljava/lang/String;
      26: astore_3
      27: aload_0
      28: aload_3
      29: putfield      #4                  // Field type_:Ljava/lang/Object;
      32: aload_3
      33: areturn

  public com.google.protobuf.ByteString getTypeBytes();
    Code:
       0: aload_0
       1: getfield      #4                  // Field type_:Ljava/lang/Object;
       4: astore_1
       5: aload_1
       6: instanceof    #16                 // class java/lang/String
       9: ifeq          27
      12: aload_1
      13: checkcast     #16                 // class java/lang/String
      16: invokestatic  #19                 // Method com/google/protobuf/ByteString.copyFromUtf8:(Ljava/lang/String;)Lcom/google/protobuf/ByteString;
      19: astore_2
      20: aload_0
      21: aload_2
      22: putfield      #4                  // Field type_:Ljava/lang/Object;
      25: aload_2
      26: areturn
      27: aload_1
      28: checkcast     #17                 // class com/google/protobuf/ByteString
      31: areturn

  public java.lang.String getSubject();
    Code:
       0: aload_0
       1: getfield      #3                  // Field subject_:Ljava/lang/Object;
       4: astore_1
       5: aload_1
       6: instanceof    #16                 // class java/lang/String
       9: ifeq          17
      12: aload_1
      13: checkcast     #16                 // class java/lang/String
      16: areturn
      17: aload_1
      18: checkcast     #17                 // class com/google/protobuf/ByteString
      21: astore_2
      22: aload_2
      23: invokevirtual #18                 // Method com/google/protobuf/ByteString.toStringUtf8:()Ljava/lang/String;
      26: astore_3
      27: aload_0
      28: aload_3
      29: putfield      #3                  // Field subject_:Ljava/lang/Object;
      32: aload_3
      33: areturn

  public com.google.protobuf.ByteString getSubjectBytes();
    Code:
       0: aload_0
       1: getfield      #3                  // Field subject_:Ljava/lang/Object;
       4: astore_1
       5: aload_1
       6: instanceof    #16                 // class java/lang/String
       9: ifeq          27
      12: aload_1
      13: checkcast     #16                 // class java/lang/String
      16: invokestatic  #19                 // Method com/google/protobuf/ByteString.copyFromUtf8:(Ljava/lang/String;)Lcom/google/protobuf/ByteString;
      19: astore_2
      20: aload_0
      21: aload_2
      22: putfield      #3                  // Field subject_:Ljava/lang/Object;
      25: aload_2
      26: areturn
      27: aload_1
      28: checkcast     #17                 // class com/google/protobuf/ByteString
      31: areturn

  public java.lang.String getDescription();
    Code:
       0: aload_0
       1: getfield      #2                  // Field description_:Ljava/lang/Object;
       4: astore_1
       5: aload_1
       6: instanceof    #16                 // class java/lang/String
       9: ifeq          17
      12: aload_1
      13: checkcast     #16                 // class java/lang/String
      16: areturn
      17: aload_1
      18: checkcast     #17                 // class com/google/protobuf/ByteString
      21: astore_2
      22: aload_2
      23: invokevirtual #18                 // Method com/google/protobuf/ByteString.toStringUtf8:()Ljava/lang/String;
      26: astore_3
      27: aload_0
      28: aload_3
      29: putfield      #2                  // Field description_:Ljava/lang/Object;
      32: aload_3
      33: areturn

  public com.google.protobuf.ByteString getDescriptionBytes();
    Code:
       0: aload_0
       1: getfield      #2                  // Field description_:Ljava/lang/Object;
       4: astore_1
       5: aload_1
       6: instanceof    #16                 // class java/lang/String
       9: ifeq          27
      12: aload_1
      13: checkcast     #16                 // class java/lang/String
      16: invokestatic  #19                 // Method com/google/protobuf/ByteString.copyFromUtf8:(Ljava/lang/String;)Lcom/google/protobuf/ByteString;
      19: astore_2
      20: aload_0
      21: aload_2
      22: putfield      #2                  // Field description_:Ljava/lang/Object;
      25: aload_2
      26: areturn
      27: aload_1
      28: checkcast     #17                 // class com/google/protobuf/ByteString
      31: areturn

  public final boolean isInitialized();
    Code:
       0: aload_0
       1: getfield      #8                  // Field memoizedIsInitialized:B
       4: istore_1
       5: iload_1
       6: iconst_1
       7: if_icmpne     12
      10: iconst_1
      11: ireturn
      12: iload_1
      13: ifne          18
      16: iconst_0
      17: ireturn
      18: aload_0
      19: iconst_1
      20: putfield      #8                  // Field memoizedIsInitialized:B
      23: iconst_1
      24: ireturn

  public void writeTo(com.google.protobuf.CodedOutputStream) throws java.io.IOException;
    Code:
       0: aload_0
       1: getfield      #4                  // Field type_:Ljava/lang/Object;
       4: invokestatic  #20                 // Method com/google/protobuf/GeneratedMessageV3.isStringEmpty:(Ljava/lang/Object;)Z
       7: ifne          19
      10: aload_1
      11: iconst_1
      12: aload_0
      13: getfield      #4                  // Field type_:Ljava/lang/Object;
      16: invokestatic  #21                 // Method com/google/protobuf/GeneratedMessageV3.writeString:(Lcom/google/protobuf/CodedOutputStream;ILjava/lang/Object;)V
      19: aload_0
      20: getfield      #3                  // Field subject_:Ljava/lang/Object;
      23: invokestatic  #20                 // Method com/google/protobuf/GeneratedMessageV3.isStringEmpty:(Ljava/lang/Object;)Z
      26: ifne          38
      29: aload_1
      30: iconst_2
      31: aload_0
      32: getfield      #3                  // Field subject_:Ljava/lang/Object;
      35: invokestatic  #21                 // Method com/google/protobuf/GeneratedMessageV3.writeString:(Lcom/google/protobuf/CodedOutputStream;ILjava/lang/Object;)V
      38: aload_0
      39: getfield      #2                  // Field description_:Ljava/lang/Object;
      42: invokestatic  #20                 // Method com/google/protobuf/GeneratedMessageV3.isStringEmpty:(Ljava/lang/Object;)Z
      45: ifne          57
      48: aload_1
      49: iconst_3
      50: aload_0
      51: getfield      #2                  // Field description_:Ljava/lang/Object;
      54: invokestatic  #21                 // Method com/google/protobuf/GeneratedMessageV3.writeString:(Lcom/google/protobuf/CodedOutputStream;ILjava/lang/Object;)V
      57: aload_0
      58: invokevirtual #22                 // Method getUnknownFields:()Lcom/google/protobuf/UnknownFieldSet;
      61: aload_1
      62: invokevirtual #23                 // Method com/google/protobuf/UnknownFieldSet.writeTo:(Lcom/google/protobuf/CodedOutputStream;)V
      65: return

  public int getSerializedSize();
    Code:
       0: aload_0
       1: getfield      #24                 // Field memoizedSize:I
       4: istore_1
       5: iload_1
       6: iconst_m1
       7: if_icmpeq     12
      10: iload_1
      11: ireturn
      12: iconst_0
      13: istore_1
      14: aload_0
      15: getfield      #4                  // Field type_:Ljava/lang/Object;
      18: invokestatic  #20                 // Method com/google/protobuf/GeneratedMessageV3.isStringEmpty:(Ljava/lang/Object;)Z
      21: ifne          35
      24: iload_1
      25: iconst_1
      26: aload_0
      27: getfield      #4                  // Field type_:Ljava/lang/Object;
      30: invokestatic  #25                 // Method com/google/protobuf/GeneratedMessageV3.computeStringSize:(ILjava/lang/Object;)I
      33: iadd
      34: istore_1
      35: aload_0
      36: getfield      #3                  // Field subject_:Ljava/lang/Object;
      39: invokestatic  #20                 // Method com/google/protobuf/GeneratedMessageV3.isStringEmpty:(Ljava/lang/Object;)Z
      42: ifne          56
      45: iload_1
      46: iconst_2
      47: aload_0
      48: getfield      #3                  // Field subject_:Ljava/lang/Object;
      51: invokestatic  #25                 // Method com/google/protobuf/GeneratedMessageV3.computeStringSize:(ILjava/lang/Object;)I
      54: iadd
      55: istore_1
      56: aload_0
      57: getfield      #2                  // Field description_:Ljava/lang/Object;
      60: invokestatic  #20                 // Method com/google/protobuf/GeneratedMessageV3.isStringEmpty:(Ljava/lang/Object;)Z
      63: ifne          77
      66: iload_1
      67: iconst_3
      68: aload_0
      69: getfield      #2                  // Field description_:Ljava/lang/Object;
      72: invokestatic  #25                 // Method com/google/protobuf/GeneratedMessageV3.computeStringSize:(ILjava/lang/Object;)I
      75: iadd
      76: istore_1
      77: iload_1
      78: aload_0
      79: invokevirtual #22                 // Method getUnknownFields:()Lcom/google/protobuf/UnknownFieldSet;
      82: invokevirtual #26                 // Method com/google/protobuf/UnknownFieldSet.getSerializedSize:()I
      85: iadd
      86: istore_1
      87: aload_0
      88: iload_1
      89: putfield      #24                 // Field memoizedSize:I
      92: iload_1
      93: ireturn

  public boolean equals(java.lang.Object);
    Code:
       0: aload_1
       1: aload_0
       2: if_acmpne     7
       5: iconst_1
       6: ireturn
       7: aload_1
       8: instanceof    #10                 // class com/google/rpc/PreconditionFailure$Violation
      11: ifne          20
      14: aload_0
      15: aload_1
      16: invokespecial #27                 // Method com/google/protobuf/GeneratedMessageV3.equals:(Ljava/lang/Object;)Z
      19: ireturn
      20: aload_1
      21: checkcast     #10                 // class com/google/rpc/PreconditionFailure$Violation
      24: astore_2
      25: aload_0
      26: invokevirtual #28                 // Method getType:()Ljava/lang/String;
      29: aload_2
      30: invokevirtual #28                 // Method getType:()Ljava/lang/String;
      33: invokevirtual #29                 // Method java/lang/String.equals:(Ljava/lang/Object;)Z
      36: ifne          41
      39: iconst_0
      40: ireturn
      41: aload_0
      42: invokevirtual #30                 // Method getSubject:()Ljava/lang/String;
      45: aload_2
      46: invokevirtual #30                 // Method getSubject:()Ljava/lang/String;
      49: invokevirtual #29                 // Method java/lang/String.equals:(Ljava/lang/Object;)Z
      52: ifne          57
      55: iconst_0
      56: ireturn
      57: aload_0
      58: invokevirtual #31                 // Method getDescription:()Ljava/lang/String;
      61: aload_2
      62: invokevirtual #31                 // Method getDescription:()Ljava/lang/String;
      65: invokevirtual #29                 // Method java/lang/String.equals:(Ljava/lang/Object;)Z
      68: ifne          73
      71: iconst_0
      72: ireturn
      73: aload_0
      74: invokevirtual #22                 // Method getUnknownFields:()Lcom/google/protobuf/UnknownFieldSet;
      77: aload_2
      78: invokevirtual #22                 // Method getUnknownFields:()Lcom/google/protobuf/UnknownFieldSet;
      81: invokevirtual #32                 // Method com/google/protobuf/UnknownFieldSet.equals:(Ljava/lang/Object;)Z
      84: ifne          89
      87: iconst_0
      88: ireturn
      89: iconst_1
      90: ireturn

  public int hashCode();
    Code:
       0: aload_0
       1: getfield      #33                 // Field memoizedHashCode:I
       4: ifeq          12
       7: aload_0
       8: getfield      #33                 // Field memoizedHashCode:I
      11: ireturn
      12: bipush        41
      14: istore_1
      15: bipush        19
      17: iload_1
      18: imul
      19: invokestatic  #34                 // Method getDescriptor:()Lcom/google/protobuf/Descriptors$Descriptor;
      22: invokevirtual #35                 // Method java/lang/Object.hashCode:()I
      25: iadd
      26: istore_1
      27: bipush        37
      29: iload_1
      30: imul
      31: iconst_1
      32: iadd
      33: istore_1
      34: bipush        53
      36: iload_1
      37: imul
      38: aload_0
      39: invokevirtual #28                 // Method getType:()Ljava/lang/String;
      42: invokevirtual #36                 // Method java/lang/String.hashCode:()I
      45: iadd
      46: istore_1
      47: bipush        37
      49: iload_1
      50: imul
      51: iconst_2
      52: iadd
      53: istore_1
      54: bipush        53
      56: iload_1
      57: imul
      58: aload_0
      59: invokevirtual #30                 // Method getSubject:()Ljava/lang/String;
      62: invokevirtual #36                 // Method java/lang/String.hashCode:()I
      65: iadd
      66: istore_1
      67: bipush        37
      69: iload_1
      70: imul
      71: iconst_3
      72: iadd
      73: istore_1
      74: bipush        53
      76: iload_1
      77: imul
      78: aload_0
      79: invokevirtual #31                 // Method getDescription:()Ljava/lang/String;
      82: invokevirtual #36                 // Method java/lang/String.hashCode:()I
      85: iadd
      86: istore_1
      87: bipush        29
      89: iload_1
      90: imul
      91: aload_0
      92: invokevirtual #22                 // Method getUnknownFields:()Lcom/google/protobuf/UnknownFieldSet;
      95: invokevirtual #37                 // Method com/google/protobuf/UnknownFieldSet.hashCode:()I
      98: iadd
      99: istore_1
     100: aload_0
     101: iload_1
     102: putfield      #33                 // Field memoizedHashCode:I
     105: iload_1
     106: ireturn

  public static com.google.rpc.PreconditionFailure$Violation parseFrom(java.nio.ByteBuffer) throws com.google.protobuf.InvalidProtocolBufferException;
    Code:
       0: getstatic     #38                 // Field PARSER:Lcom/google/protobuf/Parser;
       3: aload_0
       4: invokeinterface #39,  2           // InterfaceMethod com/google/protobuf/Parser.parseFrom:(Ljava/nio/ByteBuffer;)Ljava/lang/Object;
       9: checkcast     #10                 // class com/google/rpc/PreconditionFailure$Violation
      12: areturn

  public static com.google.rpc.PreconditionFailure$Violation parseFrom(java.nio.ByteBuffer, com.google.protobuf.ExtensionRegistryLite) throws com.google.protobuf.InvalidProtocolBufferException;
    Code:
       0: getstatic     #38                 // Field PARSER:Lcom/google/protobuf/Parser;
       3: aload_0
       4: aload_1
       5: invokeinterface #40,  3           // InterfaceMethod com/google/protobuf/Parser.parseFrom:(Ljava/nio/ByteBuffer;Lcom/google/protobuf/ExtensionRegistryLite;)Ljava/lang/Object;
      10: checkcast     #10                 // class com/google/rpc/PreconditionFailure$Violation
      13: areturn

  public static com.google.rpc.PreconditionFailure$Violation parseFrom(com.google.protobuf.ByteString) throws com.google.protobuf.InvalidProtocolBufferException;
    Code:
       0: getstatic     #38                 // Field PARSER:Lcom/google/protobuf/Parser;
       3: aload_0
       4: invokeinterface #41,  2           // InterfaceMethod com/google/protobuf/Parser.parseFrom:(Lcom/google/protobuf/ByteString;)Ljava/lang/Object;
       9: checkcast     #10                 // class com/google/rpc/PreconditionFailure$Violation
      12: areturn

  public static com.google.rpc.PreconditionFailure$Violation parseFrom(com.google.protobuf.ByteString, com.google.protobuf.ExtensionRegistryLite) throws com.google.protobuf.InvalidProtocolBufferException;
    Code:
       0: getstatic     #38                 // Field PARSER:Lcom/google/protobuf/Parser;
       3: aload_0
       4: aload_1
       5: invokeinterface #42,  3           // InterfaceMethod com/google/protobuf/Parser.parseFrom:(Lcom/google/protobuf/ByteString;Lcom/google/protobuf/ExtensionRegistryLite;)Ljava/lang/Object;
      10: checkcast     #10                 // class com/google/rpc/PreconditionFailure$Violation
      13: areturn

  public static com.google.rpc.PreconditionFailure$Violation parseFrom(byte[]) throws com.google.protobuf.InvalidProtocolBufferException;
    Code:
       0: getstatic     #38                 // Field PARSER:Lcom/google/protobuf/Parser;
       3: aload_0
       4: invokeinterface #43,  2           // InterfaceMethod com/google/protobuf/Parser.parseFrom:([B)Ljava/lang/Object;
       9: checkcast     #10                 // class com/google/rpc/PreconditionFailure$Violation
      12: areturn

  public static com.google.rpc.PreconditionFailure$Violation parseFrom(byte[], com.google.protobuf.ExtensionRegistryLite) throws com.google.protobuf.InvalidProtocolBufferException;
    Code:
       0: getstatic     #38                 // Field PARSER:Lcom/google/protobuf/Parser;
       3: aload_0
       4: aload_1
       5: invokeinterface #44,  3           // InterfaceMethod com/google/protobuf/Parser.parseFrom:([BLcom/google/protobuf/ExtensionRegistryLite;)Ljava/lang/Object;
      10: checkcast     #10                 // class com/google/rpc/PreconditionFailure$Violation
      13: areturn

  public static com.google.rpc.PreconditionFailure$Violation parseFrom(java.io.InputStream) throws java.io.IOException;
    Code:
       0: getstatic     #38                 // Field PARSER:Lcom/google/protobuf/Parser;
       3: aload_0
       4: invokestatic  #45                 // Method com/google/protobuf/GeneratedMessageV3.parseWithIOException:(Lcom/google/protobuf/Parser;Ljava/io/InputStream;)Lcom/google/protobuf/Message;
       7: checkcast     #10                 // class com/google/rpc/PreconditionFailure$Violation
      10: areturn

  public static com.google.rpc.PreconditionFailure$Violation parseFrom(java.io.InputStream, com.google.protobuf.ExtensionRegistryLite) throws java.io.IOException;
    Code:
       0: getstatic     #38                 // Field PARSER:Lcom/google/protobuf/Parser;
       3: aload_0
       4: aload_1
       5: invokestatic  #46                 // Method com/google/protobuf/GeneratedMessageV3.parseWithIOException:(Lcom/google/protobuf/Parser;Ljava/io/InputStream;Lcom/google/protobuf/ExtensionRegistryLite;)Lcom/google/protobuf/Message;
       8: checkcast     #10                 // class com/google/rpc/PreconditionFailure$Violation
      11: areturn

  public static com.google.rpc.PreconditionFailure$Violation parseDelimitedFrom(java.io.InputStream) throws java.io.IOException;
    Code:
       0: getstatic     #38                 // Field PARSER:Lcom/google/protobuf/Parser;
       3: aload_0
       4: invokestatic  #47                 // Method com/google/protobuf/GeneratedMessageV3.parseDelimitedWithIOException:(Lcom/google/protobuf/Parser;Ljava/io/InputStream;)Lcom/google/protobuf/Message;
       7: checkcast     #10                 // class com/google/rpc/PreconditionFailure$Violation
      10: areturn

  public static com.google.rpc.PreconditionFailure$Violation parseDelimitedFrom(java.io.InputStream, com.google.protobuf.ExtensionRegistryLite) throws java.io.IOException;
    Code:
       0: getstatic     #38                 // Field PARSER:Lcom/google/protobuf/Parser;
       3: aload_0
       4: aload_1
       5: invokestatic  #48                 // Method com/google/protobuf/GeneratedMessageV3.parseDelimitedWithIOException:(Lcom/google/protobuf/Parser;Ljava/io/InputStream;Lcom/google/protobuf/ExtensionRegistryLite;)Lcom/google/protobuf/Message;
       8: checkcast     #10                 // class com/google/rpc/PreconditionFailure$Violation
      11: areturn

  public static com.google.rpc.PreconditionFailure$Violation parseFrom(com.google.protobuf.CodedInputStream) throws java.io.IOException;
    Code:
       0: getstatic     #38                 // Field PARSER:Lcom/google/protobuf/Parser;
       3: aload_0
       4: invokestatic  #49                 // Method com/google/protobuf/GeneratedMessageV3.parseWithIOException:(Lcom/google/protobuf/Parser;Lcom/google/protobuf/CodedInputStream;)Lcom/google/protobuf/Message;
       7: checkcast     #10                 // class com/google/rpc/PreconditionFailure$Violation
      10: areturn

  public static com.google.rpc.PreconditionFailure$Violation parseFrom(com.google.protobuf.CodedInputStream, com.google.protobuf.ExtensionRegistryLite) throws java.io.IOException;
    Code:
       0: getstatic     #38                 // Field PARSER:Lcom/google/protobuf/Parser;
       3: aload_0
       4: aload_1
       5: invokestatic  #50                 // Method com/google/protobuf/GeneratedMessageV3.parseWithIOException:(Lcom/google/protobuf/Parser;Lcom/google/protobuf/CodedInputStream;Lcom/google/protobuf/ExtensionRegistryLite;)Lcom/google/protobuf/Message;
       8: checkcast     #10                 // class com/google/rpc/PreconditionFailure$Violation
      11: areturn

  public com.google.rpc.PreconditionFailure$Violation$Builder newBuilderForType();
    Code:
       0: invokestatic  #51                 // Method newBuilder:()Lcom/google/rpc/PreconditionFailure$Violation$Builder;
       3: areturn

  public static com.google.rpc.PreconditionFailure$Violation$Builder newBuilder();
    Code:
       0: getstatic     #52                 // Field DEFAULT_INSTANCE:Lcom/google/rpc/PreconditionFailure$Violation;
       3: invokevirtual #53                 // Method toBuilder:()Lcom/google/rpc/PreconditionFailure$Violation$Builder;
       6: areturn

  public static com.google.rpc.PreconditionFailure$Violation$Builder newBuilder(com.google.rpc.PreconditionFailure$Violation);
    Code:
       0: getstatic     #52                 // Field DEFAULT_INSTANCE:Lcom/google/rpc/PreconditionFailure$Violation;
       3: invokevirtual #53                 // Method toBuilder:()Lcom/google/rpc/PreconditionFailure$Violation$Builder;
       6: aload_0
       7: invokevirtual #54                 // Method com/google/rpc/PreconditionFailure$Violation$Builder.mergeFrom:(Lcom/google/rpc/PreconditionFailure$Violation;)Lcom/google/rpc/PreconditionFailure$Violation$Builder;
      10: areturn

  public com.google.rpc.PreconditionFailure$Violation$Builder toBuilder();
    Code:
       0: aload_0
       1: getstatic     #52                 // Field DEFAULT_INSTANCE:Lcom/google/rpc/PreconditionFailure$Violation;
       4: if_acmpne     18
       7: new           #14                 // class com/google/rpc/PreconditionFailure$Violation$Builder
      10: dup
      11: aconst_null
      12: invokespecial #55                 // Method com/google/rpc/PreconditionFailure$Violation$Builder."<init>":(Lcom/google/rpc/PreconditionFailure$1;)V
      15: goto          30
      18: new           #14                 // class com/google/rpc/PreconditionFailure$Violation$Builder
      21: dup
      22: aconst_null
      23: invokespecial #55                 // Method com/google/rpc/PreconditionFailure$Violation$Builder."<init>":(Lcom/google/rpc/PreconditionFailure$1;)V
      26: aload_0
      27: invokevirtual #54                 // Method com/google/rpc/PreconditionFailure$Violation$Builder.mergeFrom:(Lcom/google/rpc/PreconditionFailure$Violation;)Lcom/google/rpc/PreconditionFailure$Violation$Builder;
      30: areturn

  protected com.google.rpc.PreconditionFailure$Violation$Builder newBuilderForType(com.google.protobuf.GeneratedMessageV3$BuilderParent);
    Code:
       0: new           #14                 // class com/google/rpc/PreconditionFailure$Violation$Builder
       3: dup
       4: aload_1
       5: aconst_null
       6: invokespecial #56                 // Method com/google/rpc/PreconditionFailure$Violation$Builder."<init>":(Lcom/google/protobuf/GeneratedMessageV3$BuilderParent;Lcom/google/rpc/PreconditionFailure$1;)V
       9: astore_2
      10: aload_2
      11: areturn

  public static com.google.rpc.PreconditionFailure$Violation getDefaultInstance();
    Code:
       0: getstatic     #52                 // Field DEFAULT_INSTANCE:Lcom/google/rpc/PreconditionFailure$Violation;
       3: areturn

  public static com.google.protobuf.Parser<com.google.rpc.PreconditionFailure$Violation> parser();
    Code:
       0: getstatic     #38                 // Field PARSER:Lcom/google/protobuf/Parser;
       3: areturn

  public com.google.protobuf.Parser<com.google.rpc.PreconditionFailure$Violation> getParserForType();
    Code:
       0: getstatic     #38                 // Field PARSER:Lcom/google/protobuf/Parser;
       3: areturn

  public com.google.rpc.PreconditionFailure$Violation getDefaultInstanceForType();
    Code:
       0: getstatic     #52                 // Field DEFAULT_INSTANCE:Lcom/google/rpc/PreconditionFailure$Violation;
       3: areturn

  protected com.google.protobuf.Message$Builder newBuilderForType(com.google.protobuf.GeneratedMessageV3$BuilderParent);
    Code:
       0: aload_0
       1: aload_1
       2: invokevirtual #57                 // Method newBuilderForType:(Lcom/google/protobuf/GeneratedMessageV3$BuilderParent;)Lcom/google/rpc/PreconditionFailure$Violation$Builder;
       5: areturn

  public com.google.protobuf.Message$Builder toBuilder();
    Code:
       0: aload_0
       1: invokevirtual #53                 // Method toBuilder:()Lcom/google/rpc/PreconditionFailure$Violation$Builder;
       4: areturn

  public com.google.protobuf.Message$Builder newBuilderForType();
    Code:
       0: aload_0
       1: invokevirtual #58                 // Method newBuilderForType:()Lcom/google/rpc/PreconditionFailure$Violation$Builder;
       4: areturn

  public com.google.protobuf.MessageLite$Builder toBuilder();
    Code:
       0: aload_0
       1: invokevirtual #53                 // Method toBuilder:()Lcom/google/rpc/PreconditionFailure$Violation$Builder;
       4: areturn

  public com.google.protobuf.MessageLite$Builder newBuilderForType();
    Code:
       0: aload_0
       1: invokevirtual #58                 // Method newBuilderForType:()Lcom/google/rpc/PreconditionFailure$Violation$Builder;
       4: areturn

  public com.google.protobuf.MessageLite getDefaultInstanceForType();
    Code:
       0: aload_0
       1: invokevirtual #59                 // Method getDefaultInstanceForType:()Lcom/google/rpc/PreconditionFailure$Violation;
       4: areturn

  public com.google.protobuf.Message getDefaultInstanceForType();
    Code:
       0: aload_0
       1: invokevirtual #59                 // Method getDefaultInstanceForType:()Lcom/google/rpc/PreconditionFailure$Violation;
       4: areturn

  com.google.rpc.PreconditionFailure$Violation(com.google.protobuf.GeneratedMessageV3$Builder, com.google.rpc.PreconditionFailure$1);
    Code:
       0: aload_0
       1: aload_1
       2: invokespecial #5                  // Method "<init>":(Lcom/google/protobuf/GeneratedMessageV3$Builder;)V
       5: return

  static java.lang.Object access$302(com.google.rpc.PreconditionFailure$Violation, java.lang.Object);
    Code:
       0: aload_0
       1: aload_1
       2: dup_x1
       3: putfield      #4                  // Field type_:Ljava/lang/Object;
       6: areturn

  static java.lang.Object access$402(com.google.rpc.PreconditionFailure$Violation, java.lang.Object);
    Code:
       0: aload_0
       1: aload_1
       2: dup_x1
       3: putfield      #3                  // Field subject_:Ljava/lang/Object;
       6: areturn

  static java.lang.Object access$502(com.google.rpc.PreconditionFailure$Violation, java.lang.Object);
    Code:
       0: aload_0
       1: aload_1
       2: dup_x1
       3: putfield      #2                  // Field description_:Ljava/lang/Object;
       6: areturn

  static java.lang.Object access$300(com.google.rpc.PreconditionFailure$Violation);
    Code:
       0: aload_0
       1: getfield      #4                  // Field type_:Ljava/lang/Object;
       4: areturn

  static java.lang.Object access$400(com.google.rpc.PreconditionFailure$Violation);
    Code:
       0: aload_0
       1: getfield      #3                  // Field subject_:Ljava/lang/Object;
       4: areturn

  static java.lang.Object access$500(com.google.rpc.PreconditionFailure$Violation);
    Code:
       0: aload_0
       1: getfield      #2                  // Field description_:Ljava/lang/Object;
       4: areturn

  static void access$600(com.google.protobuf.ByteString) throws java.lang.IllegalArgumentException;
    Code:
       0: aload_0
       1: invokestatic  #1                  // Method checkByteStringIsUtf8:(Lcom/google/protobuf/ByteString;)V
       4: return

  static void access$700(com.google.protobuf.ByteString) throws java.lang.IllegalArgumentException;
    Code:
       0: aload_0
       1: invokestatic  #1                  // Method checkByteStringIsUtf8:(Lcom/google/protobuf/ByteString;)V
       4: return

  static void access$800(com.google.protobuf.ByteString) throws java.lang.IllegalArgumentException;
    Code:
       0: aload_0
       1: invokestatic  #1                  // Method checkByteStringIsUtf8:(Lcom/google/protobuf/ByteString;)V
       4: return

  static {};
    Code:
       0: new           #10                 // class com/google/rpc/PreconditionFailure$Violation
       3: dup
       4: invokespecial #11                 // Method "<init>":()V
       7: putstatic     #52                 // Field DEFAULT_INSTANCE:Lcom/google/rpc/PreconditionFailure$Violation;
      10: new           #60                 // class com/google/rpc/PreconditionFailure$Violation$1
      13: dup
      14: invokespecial #61                 // Method com/google/rpc/PreconditionFailure$Violation$1."<init>":()V
      17: putstatic     #38                 // Field PARSER:Lcom/google/protobuf/Parser;
      20: return
}
