Compiled from "RetryInfo.java"
public final class com.google.rpc.RetryInfo$Builder extends com.google.protobuf.GeneratedMessageV3$Builder<com.google.rpc.RetryInfo$Builder> implements com.google.rpc.RetryInfoOrBuilder {
  private int bitField0_;

  private com.google.protobuf.Duration retryDelay_;

  private com.google.protobuf.SingleFieldBuilderV3<com.google.protobuf.Duration, com.google.protobuf.Duration$Builder, com.google.protobuf.DurationOrBuilder> retryDelayBuilder_;

  public static final com.google.protobuf.Descriptors$Descriptor getDescriptor();
    Code:
       0: getstatic     #3                  // Field com/google/rpc/ErrorDetailsProto.internal_static_google_rpc_RetryInfo_descriptor:Lcom/google/protobuf/Descriptors$Descriptor;
       3: areturn

  protected com.google.protobuf.GeneratedMessageV3$FieldAccessorTable internalGetFieldAccessorTable();
    Code:
       0: getstatic     #4                  // Field com/google/rpc/ErrorDetailsProto.internal_static_google_rpc_RetryInfo_fieldAccessorTable:Lcom/google/protobuf/GeneratedMessageV3$FieldAccessorTable;
       3: ldc           #5                  // class com/google/rpc/RetryInfo
       5: ldc           #6                  // class com/google/rpc/RetryInfo$Builder
       7: invokevirtual #7                  // Method com/google/protobuf/GeneratedMessageV3$FieldAccessorTable.ensureFieldAccessorsInitialized:(Ljava/lang/Class;Ljava/lang/Class;)Lcom/google/protobuf/GeneratedMessageV3$FieldAccessorTable;
      10: areturn

  private com.google.rpc.RetryInfo$Builder();
    Code:
       0: aload_0
       1: invokespecial #8                  // Method com/google/protobuf/GeneratedMessageV3$Builder."<init>":()V
       4: return

  private com.google.rpc.RetryInfo$Builder(com.google.protobuf.GeneratedMessageV3$BuilderParent);
    Code:
       0: aload_0
       1: aload_1
       2: invokespecial #9                  // Method com/google/protobuf/GeneratedMessageV3$Builder."<init>":(Lcom/google/protobuf/GeneratedMessageV3$BuilderParent;)V
       5: return

  public com.google.rpc.RetryInfo$Builder clear();
    Code:
       0: aload_0
       1: invokespecial #10                 // Method com/google/protobuf/GeneratedMessageV3$Builder.clear:()Lcom/google/protobuf/GeneratedMessageV3$Builder;
       4: pop
       5: aload_0
       6: iconst_0
       7: putfield      #11                 // Field bitField0_:I
      10: aload_0
      11: aconst_null
      12: putfield      #12                 // Field retryDelay_:Lcom/google/protobuf/Duration;
      15: aload_0
      16: getfield      #13                 // Field retryDelayBuilder_:Lcom/google/protobuf/SingleFieldBuilderV3;
      19: ifnull        34
      22: aload_0
      23: getfield      #13                 // Field retryDelayBuilder_:Lcom/google/protobuf/SingleFieldBuilderV3;
      26: invokevirtual #14                 // Method com/google/protobuf/SingleFieldBuilderV3.dispose:()V
      29: aload_0
      30: aconst_null
      31: putfield      #13                 // Field retryDelayBuilder_:Lcom/google/protobuf/SingleFieldBuilderV3;
      34: aload_0
      35: areturn

  public com.google.protobuf.Descriptors$Descriptor getDescriptorForType();
    Code:
       0: getstatic     #3                  // Field com/google/rpc/ErrorDetailsProto.internal_static_google_rpc_RetryInfo_descriptor:Lcom/google/protobuf/Descriptors$Descriptor;
       3: areturn

  public com.google.rpc.RetryInfo getDefaultInstanceForType();
    Code:
       0: invokestatic  #15                 // Method com/google/rpc/RetryInfo.getDefaultInstance:()Lcom/google/rpc/RetryInfo;
       3: areturn

  public com.google.rpc.RetryInfo build();
    Code:
       0: aload_0
       1: invokevirtual #16                 // Method buildPartial:()Lcom/google/rpc/RetryInfo;
       4: astore_1
       5: aload_1
       6: invokevirtual #17                 // Method com/google/rpc/RetryInfo.isInitialized:()Z
       9: ifne          17
      12: aload_1
      13: invokestatic  #18                 // Method newUninitializedMessageException:(Lcom/google/protobuf/Message;)Lcom/google/protobuf/UninitializedMessageException;
      16: athrow
      17: aload_1
      18: areturn

  public com.google.rpc.RetryInfo buildPartial();
    Code:
       0: new           #5                  // class com/google/rpc/RetryInfo
       3: dup
       4: aload_0
       5: aconst_null
       6: invokespecial #19                 // Method com/google/rpc/RetryInfo."<init>":(Lcom/google/protobuf/GeneratedMessageV3$Builder;Lcom/google/rpc/RetryInfo$1;)V
       9: astore_1
      10: aload_0
      11: getfield      #11                 // Field bitField0_:I
      14: ifeq          22
      17: aload_0
      18: aload_1
      19: invokespecial #20                 // Method buildPartial0:(Lcom/google/rpc/RetryInfo;)V
      22: aload_0
      23: invokevirtual #21                 // Method onBuilt:()V
      26: aload_1
      27: areturn

  private void buildPartial0(com.google.rpc.RetryInfo);
    Code:
       0: aload_0
       1: getfield      #11                 // Field bitField0_:I
       4: istore_2
       5: iload_2
       6: iconst_1
       7: iand
       8: ifeq          40
      11: aload_1
      12: aload_0
      13: getfield      #13                 // Field retryDelayBuilder_:Lcom/google/protobuf/SingleFieldBuilderV3;
      16: ifnonnull     26
      19: aload_0
      20: getfield      #12                 // Field retryDelay_:Lcom/google/protobuf/Duration;
      23: goto          36
      26: aload_0
      27: getfield      #13                 // Field retryDelayBuilder_:Lcom/google/protobuf/SingleFieldBuilderV3;
      30: invokevirtual #22                 // Method com/google/protobuf/SingleFieldBuilderV3.build:()Lcom/google/protobuf/AbstractMessage;
      33: checkcast     #23                 // class com/google/protobuf/Duration
      36: invokestatic  #24                 // Method com/google/rpc/RetryInfo.access$302:(Lcom/google/rpc/RetryInfo;Lcom/google/protobuf/Duration;)Lcom/google/protobuf/Duration;
      39: pop
      40: return

  public com.google.rpc.RetryInfo$Builder mergeFrom(com.google.protobuf.Message);
    Code:
       0: aload_1
       1: instanceof    #5                  // class com/google/rpc/RetryInfo
       4: ifeq          16
       7: aload_0
       8: aload_1
       9: checkcast     #5                  // class com/google/rpc/RetryInfo
      12: invokevirtual #25                 // Method mergeFrom:(Lcom/google/rpc/RetryInfo;)Lcom/google/rpc/RetryInfo$Builder;
      15: areturn
      16: aload_0
      17: aload_1
      18: invokespecial #26                 // Method com/google/protobuf/GeneratedMessageV3$Builder.mergeFrom:(Lcom/google/protobuf/Message;)Lcom/google/protobuf/AbstractMessage$Builder;
      21: pop
      22: aload_0
      23: areturn

  public com.google.rpc.RetryInfo$Builder mergeFrom(com.google.rpc.RetryInfo);
    Code:
       0: aload_1
       1: invokestatic  #15                 // Method com/google/rpc/RetryInfo.getDefaultInstance:()Lcom/google/rpc/RetryInfo;
       4: if_acmpne     9
       7: aload_0
       8: areturn
       9: aload_1
      10: invokevirtual #27                 // Method com/google/rpc/RetryInfo.hasRetryDelay:()Z
      13: ifeq          25
      16: aload_0
      17: aload_1
      18: invokevirtual #28                 // Method com/google/rpc/RetryInfo.getRetryDelay:()Lcom/google/protobuf/Duration;
      21: invokevirtual #29                 // Method mergeRetryDelay:(Lcom/google/protobuf/Duration;)Lcom/google/rpc/RetryInfo$Builder;
      24: pop
      25: aload_0
      26: aload_1
      27: invokevirtual #30                 // Method com/google/rpc/RetryInfo.getUnknownFields:()Lcom/google/protobuf/UnknownFieldSet;
      30: invokevirtual #31                 // Method mergeUnknownFields:(Lcom/google/protobuf/UnknownFieldSet;)Lcom/google/rpc/RetryInfo$Builder;
      33: pop
      34: aload_0
      35: invokevirtual #32                 // Method onChanged:()V
      38: aload_0
      39: areturn

  public final boolean isInitialized();
    Code:
       0: iconst_1
       1: ireturn

  public com.google.rpc.RetryInfo$Builder mergeFrom(com.google.protobuf.CodedInputStream, com.google.protobuf.ExtensionRegistryLite) throws java.io.IOException;
    Code:
       0: aload_2
       1: ifnonnull     12
       4: new           #33                 // class java/lang/NullPointerException
       7: dup
       8: invokespecial #34                 // Method java/lang/NullPointerException."<init>":()V
      11: athrow
      12: iconst_0
      13: istore_3
      14: iload_3
      15: ifne          98
      18: aload_1
      19: invokevirtual #35                 // Method com/google/protobuf/CodedInputStream.readTag:()I
      22: istore        4
      24: iload         4
      26: lookupswitch  { // 2
                     0: 52
                    10: 57
               default: 82
          }
      52: iconst_1
      53: istore_3
      54: goto          95
      57: aload_1
      58: aload_0
      59: invokespecial #36                 // Method getRetryDelayFieldBuilder:()Lcom/google/protobuf/SingleFieldBuilderV3;
      62: invokevirtual #37                 // Method com/google/protobuf/SingleFieldBuilderV3.getBuilder:()Lcom/google/protobuf/AbstractMessage$Builder;
      65: aload_2
      66: invokevirtual #38                 // Method com/google/protobuf/CodedInputStream.readMessage:(Lcom/google/protobuf/MessageLite$Builder;Lcom/google/protobuf/ExtensionRegistryLite;)V
      69: aload_0
      70: dup
      71: getfield      #11                 // Field bitField0_:I
      74: iconst_1
      75: ior
      76: putfield      #11                 // Field bitField0_:I
      79: goto          95
      82: aload_0
      83: aload_1
      84: aload_2
      85: iload         4
      87: invokespecial #39                 // Method com/google/protobuf/GeneratedMessageV3$Builder.parseUnknownField:(Lcom/google/protobuf/CodedInputStream;Lcom/google/protobuf/ExtensionRegistryLite;I)Z
      90: ifne          95
      93: iconst_1
      94: istore_3
      95: goto          14
      98: aload_0
      99: invokevirtual #32                 // Method onChanged:()V
     102: goto          120
     105: astore_3
     106: aload_3
     107: invokevirtual #41                 // Method com/google/protobuf/InvalidProtocolBufferException.unwrapIOException:()Ljava/io/IOException;
     110: athrow
     111: astore        5
     113: aload_0
     114: invokevirtual #32                 // Method onChanged:()V
     117: aload         5
     119: athrow
     120: aload_0
     121: areturn
    Exception table:
       from    to  target type
          12    98   105   Class com/google/protobuf/InvalidProtocolBufferException
          12    98   111   any
         105   113   111   any

  public boolean hasRetryDelay();
    Code:
       0: aload_0
       1: getfield      #11                 // Field bitField0_:I
       4: iconst_1
       5: iand
       6: ifeq          13
       9: iconst_1
      10: goto          14
      13: iconst_0
      14: ireturn

  public com.google.protobuf.Duration getRetryDelay();
    Code:
       0: aload_0
       1: getfield      #13                 // Field retryDelayBuilder_:Lcom/google/protobuf/SingleFieldBuilderV3;
       4: ifnonnull     25
       7: aload_0
       8: getfield      #12                 // Field retryDelay_:Lcom/google/protobuf/Duration;
      11: ifnonnull     20
      14: invokestatic  #42                 // Method com/google/protobuf/Duration.getDefaultInstance:()Lcom/google/protobuf/Duration;
      17: goto          24
      20: aload_0
      21: getfield      #12                 // Field retryDelay_:Lcom/google/protobuf/Duration;
      24: areturn
      25: aload_0
      26: getfield      #13                 // Field retryDelayBuilder_:Lcom/google/protobuf/SingleFieldBuilderV3;
      29: invokevirtual #43                 // Method com/google/protobuf/SingleFieldBuilderV3.getMessage:()Lcom/google/protobuf/AbstractMessage;
      32: checkcast     #23                 // class com/google/protobuf/Duration
      35: areturn

  public com.google.rpc.RetryInfo$Builder setRetryDelay(com.google.protobuf.Duration);
    Code:
       0: aload_0
       1: getfield      #13                 // Field retryDelayBuilder_:Lcom/google/protobuf/SingleFieldBuilderV3;
       4: ifnonnull     27
       7: aload_1
       8: ifnonnull     19
      11: new           #33                 // class java/lang/NullPointerException
      14: dup
      15: invokespecial #34                 // Method java/lang/NullPointerException."<init>":()V
      18: athrow
      19: aload_0
      20: aload_1
      21: putfield      #12                 // Field retryDelay_:Lcom/google/protobuf/Duration;
      24: goto          36
      27: aload_0
      28: getfield      #13                 // Field retryDelayBuilder_:Lcom/google/protobuf/SingleFieldBuilderV3;
      31: aload_1
      32: invokevirtual #44                 // Method com/google/protobuf/SingleFieldBuilderV3.setMessage:(Lcom/google/protobuf/AbstractMessage;)Lcom/google/protobuf/SingleFieldBuilderV3;
      35: pop
      36: aload_0
      37: dup
      38: getfield      #11                 // Field bitField0_:I
      41: iconst_1
      42: ior
      43: putfield      #11                 // Field bitField0_:I
      46: aload_0
      47: invokevirtual #32                 // Method onChanged:()V
      50: aload_0
      51: areturn

  public com.google.rpc.RetryInfo$Builder setRetryDelay(com.google.protobuf.Duration$Builder);
    Code:
       0: aload_0
       1: getfield      #13                 // Field retryDelayBuilder_:Lcom/google/protobuf/SingleFieldBuilderV3;
       4: ifnonnull     18
       7: aload_0
       8: aload_1
       9: invokevirtual #45                 // Method com/google/protobuf/Duration$Builder.build:()Lcom/google/protobuf/Duration;
      12: putfield      #12                 // Field retryDelay_:Lcom/google/protobuf/Duration;
      15: goto          30
      18: aload_0
      19: getfield      #13                 // Field retryDelayBuilder_:Lcom/google/protobuf/SingleFieldBuilderV3;
      22: aload_1
      23: invokevirtual #45                 // Method com/google/protobuf/Duration$Builder.build:()Lcom/google/protobuf/Duration;
      26: invokevirtual #44                 // Method com/google/protobuf/SingleFieldBuilderV3.setMessage:(Lcom/google/protobuf/AbstractMessage;)Lcom/google/protobuf/SingleFieldBuilderV3;
      29: pop
      30: aload_0
      31: dup
      32: getfield      #11                 // Field bitField0_:I
      35: iconst_1
      36: ior
      37: putfield      #11                 // Field bitField0_:I
      40: aload_0
      41: invokevirtual #32                 // Method onChanged:()V
      44: aload_0
      45: areturn

  public com.google.rpc.RetryInfo$Builder mergeRetryDelay(com.google.protobuf.Duration);
    Code:
       0: aload_0
       1: getfield      #13                 // Field retryDelayBuilder_:Lcom/google/protobuf/SingleFieldBuilderV3;
       4: ifnonnull     53
       7: aload_0
       8: getfield      #11                 // Field bitField0_:I
      11: iconst_1
      12: iand
      13: ifeq          45
      16: aload_0
      17: getfield      #12                 // Field retryDelay_:Lcom/google/protobuf/Duration;
      20: ifnull        45
      23: aload_0
      24: getfield      #12                 // Field retryDelay_:Lcom/google/protobuf/Duration;
      27: invokestatic  #42                 // Method com/google/protobuf/Duration.getDefaultInstance:()Lcom/google/protobuf/Duration;
      30: if_acmpeq     45
      33: aload_0
      34: invokevirtual #46                 // Method getRetryDelayBuilder:()Lcom/google/protobuf/Duration$Builder;
      37: aload_1
      38: invokevirtual #47                 // Method com/google/protobuf/Duration$Builder.mergeFrom:(Lcom/google/protobuf/Duration;)Lcom/google/protobuf/Duration$Builder;
      41: pop
      42: goto          62
      45: aload_0
      46: aload_1
      47: putfield      #12                 // Field retryDelay_:Lcom/google/protobuf/Duration;
      50: goto          62
      53: aload_0
      54: getfield      #13                 // Field retryDelayBuilder_:Lcom/google/protobuf/SingleFieldBuilderV3;
      57: aload_1
      58: invokevirtual #48                 // Method com/google/protobuf/SingleFieldBuilderV3.mergeFrom:(Lcom/google/protobuf/AbstractMessage;)Lcom/google/protobuf/SingleFieldBuilderV3;
      61: pop
      62: aload_0
      63: dup
      64: getfield      #11                 // Field bitField0_:I
      67: iconst_1
      68: ior
      69: putfield      #11                 // Field bitField0_:I
      72: aload_0
      73: invokevirtual #32                 // Method onChanged:()V
      76: aload_0
      77: areturn

  public com.google.rpc.RetryInfo$Builder clearRetryDelay();
    Code:
       0: aload_0
       1: aload_0
       2: getfield      #11                 // Field bitField0_:I
       5: bipush        -2
       7: iand
       8: putfield      #11                 // Field bitField0_:I
      11: aload_0
      12: aconst_null
      13: putfield      #12                 // Field retryDelay_:Lcom/google/protobuf/Duration;
      16: aload_0
      17: getfield      #13                 // Field retryDelayBuilder_:Lcom/google/protobuf/SingleFieldBuilderV3;
      20: ifnull        35
      23: aload_0
      24: getfield      #13                 // Field retryDelayBuilder_:Lcom/google/protobuf/SingleFieldBuilderV3;
      27: invokevirtual #14                 // Method com/google/protobuf/SingleFieldBuilderV3.dispose:()V
      30: aload_0
      31: aconst_null
      32: putfield      #13                 // Field retryDelayBuilder_:Lcom/google/protobuf/SingleFieldBuilderV3;
      35: aload_0
      36: invokevirtual #32                 // Method onChanged:()V
      39: aload_0
      40: areturn

  public com.google.protobuf.Duration$Builder getRetryDelayBuilder();
    Code:
       0: aload_0
       1: dup
       2: getfield      #11                 // Field bitField0_:I
       5: iconst_1
       6: ior
       7: putfield      #11                 // Field bitField0_:I
      10: aload_0
      11: invokevirtual #32                 // Method onChanged:()V
      14: aload_0
      15: invokespecial #36                 // Method getRetryDelayFieldBuilder:()Lcom/google/protobuf/SingleFieldBuilderV3;
      18: invokevirtual #37                 // Method com/google/protobuf/SingleFieldBuilderV3.getBuilder:()Lcom/google/protobuf/AbstractMessage$Builder;
      21: checkcast     #49                 // class com/google/protobuf/Duration$Builder
      24: areturn

  public com.google.protobuf.DurationOrBuilder getRetryDelayOrBuilder();
    Code:
       0: aload_0
       1: getfield      #13                 // Field retryDelayBuilder_:Lcom/google/protobuf/SingleFieldBuilderV3;
       4: ifnull        18
       7: aload_0
       8: getfield      #13                 // Field retryDelayBuilder_:Lcom/google/protobuf/SingleFieldBuilderV3;
      11: invokevirtual #50                 // Method com/google/protobuf/SingleFieldBuilderV3.getMessageOrBuilder:()Lcom/google/protobuf/MessageOrBuilder;
      14: checkcast     #51                 // class com/google/protobuf/DurationOrBuilder
      17: areturn
      18: aload_0
      19: getfield      #12                 // Field retryDelay_:Lcom/google/protobuf/Duration;
      22: ifnonnull     31
      25: invokestatic  #42                 // Method com/google/protobuf/Duration.getDefaultInstance:()Lcom/google/protobuf/Duration;
      28: goto          35
      31: aload_0
      32: getfield      #12                 // Field retryDelay_:Lcom/google/protobuf/Duration;
      35: areturn

  private com.google.protobuf.SingleFieldBuilderV3<com.google.protobuf.Duration, com.google.protobuf.Duration$Builder, com.google.protobuf.DurationOrBuilder> getRetryDelayFieldBuilder();
    Code:
       0: aload_0
       1: getfield      #13                 // Field retryDelayBuilder_:Lcom/google/protobuf/SingleFieldBuilderV3;
       4: ifnonnull     35
       7: aload_0
       8: new           #52                 // class com/google/protobuf/SingleFieldBuilderV3
      11: dup
      12: aload_0
      13: invokevirtual #53                 // Method getRetryDelay:()Lcom/google/protobuf/Duration;
      16: aload_0
      17: invokevirtual #54                 // Method getParentForChildren:()Lcom/google/protobuf/GeneratedMessageV3$BuilderParent;
      20: aload_0
      21: invokevirtual #55                 // Method isClean:()Z
      24: invokespecial #56                 // Method com/google/protobuf/SingleFieldBuilderV3."<init>":(Lcom/google/protobuf/AbstractMessage;Lcom/google/protobuf/AbstractMessage$BuilderParent;Z)V
      27: putfield      #13                 // Field retryDelayBuilder_:Lcom/google/protobuf/SingleFieldBuilderV3;
      30: aload_0
      31: aconst_null
      32: putfield      #12                 // Field retryDelay_:Lcom/google/protobuf/Duration;
      35: aload_0
      36: getfield      #13                 // Field retryDelayBuilder_:Lcom/google/protobuf/SingleFieldBuilderV3;
      39: areturn

  public final com.google.rpc.RetryInfo$Builder setUnknownFields(com.google.protobuf.UnknownFieldSet);
    Code:
       0: aload_0
       1: aload_1
       2: invokespecial #57                 // Method com/google/protobuf/GeneratedMessageV3$Builder.setUnknownFields:(Lcom/google/protobuf/UnknownFieldSet;)Lcom/google/protobuf/GeneratedMessageV3$Builder;
       5: checkcast     #6                  // class com/google/rpc/RetryInfo$Builder
       8: areturn

  public final com.google.rpc.RetryInfo$Builder mergeUnknownFields(com.google.protobuf.UnknownFieldSet);
    Code:
       0: aload_0
       1: aload_1
       2: invokespecial #58                 // Method com/google/protobuf/GeneratedMessageV3$Builder.mergeUnknownFields:(Lcom/google/protobuf/UnknownFieldSet;)Lcom/google/protobuf/GeneratedMessageV3$Builder;
       5: checkcast     #6                  // class com/google/rpc/RetryInfo$Builder
       8: areturn

  public com.google.protobuf.GeneratedMessageV3$Builder mergeUnknownFields(com.google.protobuf.UnknownFieldSet);
    Code:
       0: aload_0
       1: aload_1
       2: invokevirtual #31                 // Method mergeUnknownFields:(Lcom/google/protobuf/UnknownFieldSet;)Lcom/google/rpc/RetryInfo$Builder;
       5: areturn

  public com.google.protobuf.GeneratedMessageV3$Builder setUnknownFields(com.google.protobuf.UnknownFieldSet);
    Code:
       0: aload_0
       1: aload_1
       2: invokevirtual #59                 // Method setUnknownFields:(Lcom/google/protobuf/UnknownFieldSet;)Lcom/google/rpc/RetryInfo$Builder;
       5: areturn

  public com.google.protobuf.GeneratedMessageV3$Builder clear();
    Code:
       0: aload_0
       1: invokevirtual #60                 // Method clear:()Lcom/google/rpc/RetryInfo$Builder;
       4: areturn

  public com.google.protobuf.AbstractMessage$Builder mergeUnknownFields(com.google.protobuf.UnknownFieldSet);
    Code:
       0: aload_0
       1: aload_1
       2: invokevirtual #31                 // Method mergeUnknownFields:(Lcom/google/protobuf/UnknownFieldSet;)Lcom/google/rpc/RetryInfo$Builder;
       5: areturn

  public com.google.protobuf.AbstractMessage$Builder mergeFrom(com.google.protobuf.CodedInputStream, com.google.protobuf.ExtensionRegistryLite) throws java.io.IOException;
    Code:
       0: aload_0
       1: aload_1
       2: aload_2
       3: invokevirtual #61                 // Method mergeFrom:(Lcom/google/protobuf/CodedInputStream;Lcom/google/protobuf/ExtensionRegistryLite;)Lcom/google/rpc/RetryInfo$Builder;
       6: areturn

  public com.google.protobuf.AbstractMessage$Builder mergeFrom(com.google.protobuf.Message);
    Code:
       0: aload_0
       1: aload_1
       2: invokevirtual #62                 // Method mergeFrom:(Lcom/google/protobuf/Message;)Lcom/google/rpc/RetryInfo$Builder;
       5: areturn

  public com.google.protobuf.AbstractMessage$Builder clear();
    Code:
       0: aload_0
       1: invokevirtual #60                 // Method clear:()Lcom/google/rpc/RetryInfo$Builder;
       4: areturn

  public com.google.protobuf.Message$Builder mergeUnknownFields(com.google.protobuf.UnknownFieldSet);
    Code:
       0: aload_0
       1: aload_1
       2: invokevirtual #31                 // Method mergeUnknownFields:(Lcom/google/protobuf/UnknownFieldSet;)Lcom/google/rpc/RetryInfo$Builder;
       5: areturn

  public com.google.protobuf.Message$Builder setUnknownFields(com.google.protobuf.UnknownFieldSet);
    Code:
       0: aload_0
       1: aload_1
       2: invokevirtual #59                 // Method setUnknownFields:(Lcom/google/protobuf/UnknownFieldSet;)Lcom/google/rpc/RetryInfo$Builder;
       5: areturn

  public com.google.protobuf.Message$Builder mergeFrom(com.google.protobuf.CodedInputStream, com.google.protobuf.ExtensionRegistryLite) throws java.io.IOException;
    Code:
       0: aload_0
       1: aload_1
       2: aload_2
       3: invokevirtual #61                 // Method mergeFrom:(Lcom/google/protobuf/CodedInputStream;Lcom/google/protobuf/ExtensionRegistryLite;)Lcom/google/rpc/RetryInfo$Builder;
       6: areturn

  public com.google.protobuf.Message buildPartial();
    Code:
       0: aload_0
       1: invokevirtual #16                 // Method buildPartial:()Lcom/google/rpc/RetryInfo;
       4: areturn

  public com.google.protobuf.Message build();
    Code:
       0: aload_0
       1: invokevirtual #63                 // Method build:()Lcom/google/rpc/RetryInfo;
       4: areturn

  public com.google.protobuf.Message$Builder mergeFrom(com.google.protobuf.Message);
    Code:
       0: aload_0
       1: aload_1
       2: invokevirtual #62                 // Method mergeFrom:(Lcom/google/protobuf/Message;)Lcom/google/rpc/RetryInfo$Builder;
       5: areturn

  public com.google.protobuf.Message$Builder clear();
    Code:
       0: aload_0
       1: invokevirtual #60                 // Method clear:()Lcom/google/rpc/RetryInfo$Builder;
       4: areturn

  public com.google.protobuf.MessageLite$Builder mergeFrom(com.google.protobuf.CodedInputStream, com.google.protobuf.ExtensionRegistryLite) throws java.io.IOException;
    Code:
       0: aload_0
       1: aload_1
       2: aload_2
       3: invokevirtual #61                 // Method mergeFrom:(Lcom/google/protobuf/CodedInputStream;Lcom/google/protobuf/ExtensionRegistryLite;)Lcom/google/rpc/RetryInfo$Builder;
       6: areturn

  public com.google.protobuf.MessageLite buildPartial();
    Code:
       0: aload_0
       1: invokevirtual #16                 // Method buildPartial:()Lcom/google/rpc/RetryInfo;
       4: areturn

  public com.google.protobuf.MessageLite build();
    Code:
       0: aload_0
       1: invokevirtual #63                 // Method build:()Lcom/google/rpc/RetryInfo;
       4: areturn

  public com.google.protobuf.MessageLite$Builder clear();
    Code:
       0: aload_0
       1: invokevirtual #60                 // Method clear:()Lcom/google/rpc/RetryInfo$Builder;
       4: areturn

  public com.google.protobuf.MessageLite getDefaultInstanceForType();
    Code:
       0: aload_0
       1: invokevirtual #64                 // Method getDefaultInstanceForType:()Lcom/google/rpc/RetryInfo;
       4: areturn

  public com.google.protobuf.Message getDefaultInstanceForType();
    Code:
       0: aload_0
       1: invokevirtual #64                 // Method getDefaultInstanceForType:()Lcom/google/rpc/RetryInfo;
       4: areturn

  public com.google.protobuf.AbstractMessageLite$Builder mergeFrom(com.google.protobuf.CodedInputStream, com.google.protobuf.ExtensionRegistryLite) throws java.io.IOException;
    Code:
       0: aload_0
       1: aload_1
       2: aload_2
       3: invokevirtual #61                 // Method mergeFrom:(Lcom/google/protobuf/CodedInputStream;Lcom/google/protobuf/ExtensionRegistryLite;)Lcom/google/rpc/RetryInfo$Builder;
       6: areturn

  com.google.rpc.RetryInfo$Builder(com.google.rpc.RetryInfo$1);
    Code:
       0: aload_0
       1: invokespecial #2                  // Method "<init>":()V
       4: return

  com.google.rpc.RetryInfo$Builder(com.google.protobuf.GeneratedMessageV3$BuilderParent, com.google.rpc.RetryInfo$1);
    Code:
       0: aload_0
       1: aload_1
       2: invokespecial #1                  // Method "<init>":(Lcom/google/protobuf/GeneratedMessageV3$BuilderParent;)V
       5: return
}
