Compiled from "RetryInfo.java"
public final class com.google.rpc.RetryInfo extends com.google.protobuf.GeneratedMessageV3 implements com.google.rpc.RetryInfoOrBuilder {
  private static final long serialVersionUID;

  public static final int RETRY_DELAY_FIELD_NUMBER;

  private com.google.protobuf.Duration retryDelay_;

  private byte memoizedIsInitialized;

  private static final com.google.rpc.RetryInfo DEFAULT_INSTANCE;

  private static final com.google.protobuf.Parser<com.google.rpc.RetryInfo> PARSER;

  private com.google.rpc.RetryInfo(com.google.protobuf.GeneratedMessageV3$Builder<?>);
    Code:
       0: aload_0
       1: aload_1
       2: invokespecial #3                  // Method com/google/protobuf/GeneratedMessageV3."<init>":(Lcom/google/protobuf/GeneratedMessageV3$Builder;)V
       5: aload_0
       6: iconst_m1
       7: putfield      #4                  // Field memoizedIsInitialized:B
      10: return

  private com.google.rpc.RetryInfo();
    Code:
       0: aload_0
       1: invokespecial #5                  // Method com/google/protobuf/GeneratedMessageV3."<init>":()V
       4: aload_0
       5: iconst_m1
       6: putfield      #4                  // Field memoizedIsInitialized:B
       9: return

  protected java.lang.Object newInstance(com.google.protobuf.GeneratedMessageV3$UnusedPrivateParameter);
    Code:
       0: new           #6                  // class com/google/rpc/RetryInfo
       3: dup
       4: invokespecial #7                  // Method "<init>":()V
       7: areturn

  public static final com.google.protobuf.Descriptors$Descriptor getDescriptor();
    Code:
       0: getstatic     #8                  // Field com/google/rpc/ErrorDetailsProto.internal_static_google_rpc_RetryInfo_descriptor:Lcom/google/protobuf/Descriptors$Descriptor;
       3: areturn

  protected com.google.protobuf.GeneratedMessageV3$FieldAccessorTable internalGetFieldAccessorTable();
    Code:
       0: getstatic     #9                  // Field com/google/rpc/ErrorDetailsProto.internal_static_google_rpc_RetryInfo_fieldAccessorTable:Lcom/google/protobuf/GeneratedMessageV3$FieldAccessorTable;
       3: ldc           #6                  // class com/google/rpc/RetryInfo
       5: ldc           #10                 // class com/google/rpc/RetryInfo$Builder
       7: invokevirtual #11                 // Method com/google/protobuf/GeneratedMessageV3$FieldAccessorTable.ensureFieldAccessorsInitialized:(Ljava/lang/Class;Ljava/lang/Class;)Lcom/google/protobuf/GeneratedMessageV3$FieldAccessorTable;
      10: areturn

  public boolean hasRetryDelay();
    Code:
       0: aload_0
       1: getfield      #1                  // Field retryDelay_:Lcom/google/protobuf/Duration;
       4: ifnull        11
       7: iconst_1
       8: goto          12
      11: iconst_0
      12: ireturn

  public com.google.protobuf.Duration getRetryDelay();
    Code:
       0: aload_0
       1: getfield      #1                  // Field retryDelay_:Lcom/google/protobuf/Duration;
       4: ifnonnull     13
       7: invokestatic  #12                 // Method com/google/protobuf/Duration.getDefaultInstance:()Lcom/google/protobuf/Duration;
      10: goto          17
      13: aload_0
      14: getfield      #1                  // Field retryDelay_:Lcom/google/protobuf/Duration;
      17: areturn

  public com.google.protobuf.DurationOrBuilder getRetryDelayOrBuilder();
    Code:
       0: aload_0
       1: getfield      #1                  // Field retryDelay_:Lcom/google/protobuf/Duration;
       4: ifnonnull     13
       7: invokestatic  #12                 // Method com/google/protobuf/Duration.getDefaultInstance:()Lcom/google/protobuf/Duration;
      10: goto          17
      13: aload_0
      14: getfield      #1                  // Field retryDelay_:Lcom/google/protobuf/Duration;
      17: areturn

  public final boolean isInitialized();
    Code:
       0: aload_0
       1: getfield      #4                  // Field memoizedIsInitialized:B
       4: istore_1
       5: iload_1
       6: iconst_1
       7: if_icmpne     12
      10: iconst_1
      11: ireturn
      12: iload_1
      13: ifne          18
      16: iconst_0
      17: ireturn
      18: aload_0
      19: iconst_1
      20: putfield      #4                  // Field memoizedIsInitialized:B
      23: iconst_1
      24: ireturn

  public void writeTo(com.google.protobuf.CodedOutputStream) throws java.io.IOException;
    Code:
       0: aload_0
       1: getfield      #1                  // Field retryDelay_:Lcom/google/protobuf/Duration;
       4: ifnull        16
       7: aload_1
       8: iconst_1
       9: aload_0
      10: invokevirtual #13                 // Method getRetryDelay:()Lcom/google/protobuf/Duration;
      13: invokevirtual #14                 // Method com/google/protobuf/CodedOutputStream.writeMessage:(ILcom/google/protobuf/MessageLite;)V
      16: aload_0
      17: invokevirtual #15                 // Method getUnknownFields:()Lcom/google/protobuf/UnknownFieldSet;
      20: aload_1
      21: invokevirtual #16                 // Method com/google/protobuf/UnknownFieldSet.writeTo:(Lcom/google/protobuf/CodedOutputStream;)V
      24: return

  public int getSerializedSize();
    Code:
       0: aload_0
       1: getfield      #17                 // Field memoizedSize:I
       4: istore_1
       5: iload_1
       6: iconst_m1
       7: if_icmpeq     12
      10: iload_1
      11: ireturn
      12: iconst_0
      13: istore_1
      14: aload_0
      15: getfield      #1                  // Field retryDelay_:Lcom/google/protobuf/Duration;
      18: ifnull        32
      21: iload_1
      22: iconst_1
      23: aload_0
      24: invokevirtual #13                 // Method getRetryDelay:()Lcom/google/protobuf/Duration;
      27: invokestatic  #18                 // Method com/google/protobuf/CodedOutputStream.computeMessageSize:(ILcom/google/protobuf/MessageLite;)I
      30: iadd
      31: istore_1
      32: iload_1
      33: aload_0
      34: invokevirtual #15                 // Method getUnknownFields:()Lcom/google/protobuf/UnknownFieldSet;
      37: invokevirtual #19                 // Method com/google/protobuf/UnknownFieldSet.getSerializedSize:()I
      40: iadd
      41: istore_1
      42: aload_0
      43: iload_1
      44: putfield      #17                 // Field memoizedSize:I
      47: iload_1
      48: ireturn

  public boolean equals(java.lang.Object);
    Code:
       0: aload_1
       1: aload_0
       2: if_acmpne     7
       5: iconst_1
       6: ireturn
       7: aload_1
       8: instanceof    #6                  // class com/google/rpc/RetryInfo
      11: ifne          20
      14: aload_0
      15: aload_1
      16: invokespecial #20                 // Method com/google/protobuf/GeneratedMessageV3.equals:(Ljava/lang/Object;)Z
      19: ireturn
      20: aload_1
      21: checkcast     #6                  // class com/google/rpc/RetryInfo
      24: astore_2
      25: aload_0
      26: invokevirtual #21                 // Method hasRetryDelay:()Z
      29: aload_2
      30: invokevirtual #21                 // Method hasRetryDelay:()Z
      33: if_icmpeq     38
      36: iconst_0
      37: ireturn
      38: aload_0
      39: invokevirtual #21                 // Method hasRetryDelay:()Z
      42: ifeq          61
      45: aload_0
      46: invokevirtual #13                 // Method getRetryDelay:()Lcom/google/protobuf/Duration;
      49: aload_2
      50: invokevirtual #13                 // Method getRetryDelay:()Lcom/google/protobuf/Duration;
      53: invokevirtual #22                 // Method com/google/protobuf/Duration.equals:(Ljava/lang/Object;)Z
      56: ifne          61
      59: iconst_0
      60: ireturn
      61: aload_0
      62: invokevirtual #15                 // Method getUnknownFields:()Lcom/google/protobuf/UnknownFieldSet;
      65: aload_2
      66: invokevirtual #15                 // Method getUnknownFields:()Lcom/google/protobuf/UnknownFieldSet;
      69: invokevirtual #23                 // Method com/google/protobuf/UnknownFieldSet.equals:(Ljava/lang/Object;)Z
      72: ifne          77
      75: iconst_0
      76: ireturn
      77: iconst_1
      78: ireturn

  public int hashCode();
    Code:
       0: aload_0
       1: getfield      #24                 // Field memoizedHashCode:I
       4: ifeq          12
       7: aload_0
       8: getfield      #24                 // Field memoizedHashCode:I
      11: ireturn
      12: bipush        41
      14: istore_1
      15: bipush        19
      17: iload_1
      18: imul
      19: invokestatic  #25                 // Method getDescriptor:()Lcom/google/protobuf/Descriptors$Descriptor;
      22: invokevirtual #26                 // Method java/lang/Object.hashCode:()I
      25: iadd
      26: istore_1
      27: aload_0
      28: invokevirtual #21                 // Method hasRetryDelay:()Z
      31: ifeq          54
      34: bipush        37
      36: iload_1
      37: imul
      38: iconst_1
      39: iadd
      40: istore_1
      41: bipush        53
      43: iload_1
      44: imul
      45: aload_0
      46: invokevirtual #13                 // Method getRetryDelay:()Lcom/google/protobuf/Duration;
      49: invokevirtual #27                 // Method com/google/protobuf/Duration.hashCode:()I
      52: iadd
      53: istore_1
      54: bipush        29
      56: iload_1
      57: imul
      58: aload_0
      59: invokevirtual #15                 // Method getUnknownFields:()Lcom/google/protobuf/UnknownFieldSet;
      62: invokevirtual #28                 // Method com/google/protobuf/UnknownFieldSet.hashCode:()I
      65: iadd
      66: istore_1
      67: aload_0
      68: iload_1
      69: putfield      #24                 // Field memoizedHashCode:I
      72: iload_1
      73: ireturn

  public static com.google.rpc.RetryInfo parseFrom(java.nio.ByteBuffer) throws com.google.protobuf.InvalidProtocolBufferException;
    Code:
       0: getstatic     #29                 // Field PARSER:Lcom/google/protobuf/Parser;
       3: aload_0
       4: invokeinterface #30,  2           // InterfaceMethod com/google/protobuf/Parser.parseFrom:(Ljava/nio/ByteBuffer;)Ljava/lang/Object;
       9: checkcast     #6                  // class com/google/rpc/RetryInfo
      12: areturn

  public static com.google.rpc.RetryInfo parseFrom(java.nio.ByteBuffer, com.google.protobuf.ExtensionRegistryLite) throws com.google.protobuf.InvalidProtocolBufferException;
    Code:
       0: getstatic     #29                 // Field PARSER:Lcom/google/protobuf/Parser;
       3: aload_0
       4: aload_1
       5: invokeinterface #31,  3           // InterfaceMethod com/google/protobuf/Parser.parseFrom:(Ljava/nio/ByteBuffer;Lcom/google/protobuf/ExtensionRegistryLite;)Ljava/lang/Object;
      10: checkcast     #6                  // class com/google/rpc/RetryInfo
      13: areturn

  public static com.google.rpc.RetryInfo parseFrom(com.google.protobuf.ByteString) throws com.google.protobuf.InvalidProtocolBufferException;
    Code:
       0: getstatic     #29                 // Field PARSER:Lcom/google/protobuf/Parser;
       3: aload_0
       4: invokeinterface #32,  2           // InterfaceMethod com/google/protobuf/Parser.parseFrom:(Lcom/google/protobuf/ByteString;)Ljava/lang/Object;
       9: checkcast     #6                  // class com/google/rpc/RetryInfo
      12: areturn

  public static com.google.rpc.RetryInfo parseFrom(com.google.protobuf.ByteString, com.google.protobuf.ExtensionRegistryLite) throws com.google.protobuf.InvalidProtocolBufferException;
    Code:
       0: getstatic     #29                 // Field PARSER:Lcom/google/protobuf/Parser;
       3: aload_0
       4: aload_1
       5: invokeinterface #33,  3           // InterfaceMethod com/google/protobuf/Parser.parseFrom:(Lcom/google/protobuf/ByteString;Lcom/google/protobuf/ExtensionRegistryLite;)Ljava/lang/Object;
      10: checkcast     #6                  // class com/google/rpc/RetryInfo
      13: areturn

  public static com.google.rpc.RetryInfo parseFrom(byte[]) throws com.google.protobuf.InvalidProtocolBufferException;
    Code:
       0: getstatic     #29                 // Field PARSER:Lcom/google/protobuf/Parser;
       3: aload_0
       4: invokeinterface #34,  2           // InterfaceMethod com/google/protobuf/Parser.parseFrom:([B)Ljava/lang/Object;
       9: checkcast     #6                  // class com/google/rpc/RetryInfo
      12: areturn

  public static com.google.rpc.RetryInfo parseFrom(byte[], com.google.protobuf.ExtensionRegistryLite) throws com.google.protobuf.InvalidProtocolBufferException;
    Code:
       0: getstatic     #29                 // Field PARSER:Lcom/google/protobuf/Parser;
       3: aload_0
       4: aload_1
       5: invokeinterface #35,  3           // InterfaceMethod com/google/protobuf/Parser.parseFrom:([BLcom/google/protobuf/ExtensionRegistryLite;)Ljava/lang/Object;
      10: checkcast     #6                  // class com/google/rpc/RetryInfo
      13: areturn

  public static com.google.rpc.RetryInfo parseFrom(java.io.InputStream) throws java.io.IOException;
    Code:
       0: getstatic     #29                 // Field PARSER:Lcom/google/protobuf/Parser;
       3: aload_0
       4: invokestatic  #36                 // Method com/google/protobuf/GeneratedMessageV3.parseWithIOException:(Lcom/google/protobuf/Parser;Ljava/io/InputStream;)Lcom/google/protobuf/Message;
       7: checkcast     #6                  // class com/google/rpc/RetryInfo
      10: areturn

  public static com.google.rpc.RetryInfo parseFrom(java.io.InputStream, com.google.protobuf.ExtensionRegistryLite) throws java.io.IOException;
    Code:
       0: getstatic     #29                 // Field PARSER:Lcom/google/protobuf/Parser;
       3: aload_0
       4: aload_1
       5: invokestatic  #37                 // Method com/google/protobuf/GeneratedMessageV3.parseWithIOException:(Lcom/google/protobuf/Parser;Ljava/io/InputStream;Lcom/google/protobuf/ExtensionRegistryLite;)Lcom/google/protobuf/Message;
       8: checkcast     #6                  // class com/google/rpc/RetryInfo
      11: areturn

  public static com.google.rpc.RetryInfo parseDelimitedFrom(java.io.InputStream) throws java.io.IOException;
    Code:
       0: getstatic     #29                 // Field PARSER:Lcom/google/protobuf/Parser;
       3: aload_0
       4: invokestatic  #38                 // Method com/google/protobuf/GeneratedMessageV3.parseDelimitedWithIOException:(Lcom/google/protobuf/Parser;Ljava/io/InputStream;)Lcom/google/protobuf/Message;
       7: checkcast     #6                  // class com/google/rpc/RetryInfo
      10: areturn

  public static com.google.rpc.RetryInfo parseDelimitedFrom(java.io.InputStream, com.google.protobuf.ExtensionRegistryLite) throws java.io.IOException;
    Code:
       0: getstatic     #29                 // Field PARSER:Lcom/google/protobuf/Parser;
       3: aload_0
       4: aload_1
       5: invokestatic  #39                 // Method com/google/protobuf/GeneratedMessageV3.parseDelimitedWithIOException:(Lcom/google/protobuf/Parser;Ljava/io/InputStream;Lcom/google/protobuf/ExtensionRegistryLite;)Lcom/google/protobuf/Message;
       8: checkcast     #6                  // class com/google/rpc/RetryInfo
      11: areturn

  public static com.google.rpc.RetryInfo parseFrom(com.google.protobuf.CodedInputStream) throws java.io.IOException;
    Code:
       0: getstatic     #29                 // Field PARSER:Lcom/google/protobuf/Parser;
       3: aload_0
       4: invokestatic  #40                 // Method com/google/protobuf/GeneratedMessageV3.parseWithIOException:(Lcom/google/protobuf/Parser;Lcom/google/protobuf/CodedInputStream;)Lcom/google/protobuf/Message;
       7: checkcast     #6                  // class com/google/rpc/RetryInfo
      10: areturn

  public static com.google.rpc.RetryInfo parseFrom(com.google.protobuf.CodedInputStream, com.google.protobuf.ExtensionRegistryLite) throws java.io.IOException;
    Code:
       0: getstatic     #29                 // Field PARSER:Lcom/google/protobuf/Parser;
       3: aload_0
       4: aload_1
       5: invokestatic  #41                 // Method com/google/protobuf/GeneratedMessageV3.parseWithIOException:(Lcom/google/protobuf/Parser;Lcom/google/protobuf/CodedInputStream;Lcom/google/protobuf/ExtensionRegistryLite;)Lcom/google/protobuf/Message;
       8: checkcast     #6                  // class com/google/rpc/RetryInfo
      11: areturn

  public com.google.rpc.RetryInfo$Builder newBuilderForType();
    Code:
       0: invokestatic  #42                 // Method newBuilder:()Lcom/google/rpc/RetryInfo$Builder;
       3: areturn

  public static com.google.rpc.RetryInfo$Builder newBuilder();
    Code:
       0: getstatic     #43                 // Field DEFAULT_INSTANCE:Lcom/google/rpc/RetryInfo;
       3: invokevirtual #44                 // Method toBuilder:()Lcom/google/rpc/RetryInfo$Builder;
       6: areturn

  public static com.google.rpc.RetryInfo$Builder newBuilder(com.google.rpc.RetryInfo);
    Code:
       0: getstatic     #43                 // Field DEFAULT_INSTANCE:Lcom/google/rpc/RetryInfo;
       3: invokevirtual #44                 // Method toBuilder:()Lcom/google/rpc/RetryInfo$Builder;
       6: aload_0
       7: invokevirtual #45                 // Method com/google/rpc/RetryInfo$Builder.mergeFrom:(Lcom/google/rpc/RetryInfo;)Lcom/google/rpc/RetryInfo$Builder;
      10: areturn

  public com.google.rpc.RetryInfo$Builder toBuilder();
    Code:
       0: aload_0
       1: getstatic     #43                 // Field DEFAULT_INSTANCE:Lcom/google/rpc/RetryInfo;
       4: if_acmpne     18
       7: new           #10                 // class com/google/rpc/RetryInfo$Builder
      10: dup
      11: aconst_null
      12: invokespecial #46                 // Method com/google/rpc/RetryInfo$Builder."<init>":(Lcom/google/rpc/RetryInfo$1;)V
      15: goto          30
      18: new           #10                 // class com/google/rpc/RetryInfo$Builder
      21: dup
      22: aconst_null
      23: invokespecial #46                 // Method com/google/rpc/RetryInfo$Builder."<init>":(Lcom/google/rpc/RetryInfo$1;)V
      26: aload_0
      27: invokevirtual #45                 // Method com/google/rpc/RetryInfo$Builder.mergeFrom:(Lcom/google/rpc/RetryInfo;)Lcom/google/rpc/RetryInfo$Builder;
      30: areturn

  protected com.google.rpc.RetryInfo$Builder newBuilderForType(com.google.protobuf.GeneratedMessageV3$BuilderParent);
    Code:
       0: new           #10                 // class com/google/rpc/RetryInfo$Builder
       3: dup
       4: aload_1
       5: aconst_null
       6: invokespecial #47                 // Method com/google/rpc/RetryInfo$Builder."<init>":(Lcom/google/protobuf/GeneratedMessageV3$BuilderParent;Lcom/google/rpc/RetryInfo$1;)V
       9: astore_2
      10: aload_2
      11: areturn

  public static com.google.rpc.RetryInfo getDefaultInstance();
    Code:
       0: getstatic     #43                 // Field DEFAULT_INSTANCE:Lcom/google/rpc/RetryInfo;
       3: areturn

  public static com.google.protobuf.Parser<com.google.rpc.RetryInfo> parser();
    Code:
       0: getstatic     #29                 // Field PARSER:Lcom/google/protobuf/Parser;
       3: areturn

  public com.google.protobuf.Parser<com.google.rpc.RetryInfo> getParserForType();
    Code:
       0: getstatic     #29                 // Field PARSER:Lcom/google/protobuf/Parser;
       3: areturn

  public com.google.rpc.RetryInfo getDefaultInstanceForType();
    Code:
       0: getstatic     #43                 // Field DEFAULT_INSTANCE:Lcom/google/rpc/RetryInfo;
       3: areturn

  protected com.google.protobuf.Message$Builder newBuilderForType(com.google.protobuf.GeneratedMessageV3$BuilderParent);
    Code:
       0: aload_0
       1: aload_1
       2: invokevirtual #48                 // Method newBuilderForType:(Lcom/google/protobuf/GeneratedMessageV3$BuilderParent;)Lcom/google/rpc/RetryInfo$Builder;
       5: areturn

  public com.google.protobuf.Message$Builder toBuilder();
    Code:
       0: aload_0
       1: invokevirtual #44                 // Method toBuilder:()Lcom/google/rpc/RetryInfo$Builder;
       4: areturn

  public com.google.protobuf.Message$Builder newBuilderForType();
    Code:
       0: aload_0
       1: invokevirtual #49                 // Method newBuilderForType:()Lcom/google/rpc/RetryInfo$Builder;
       4: areturn

  public com.google.protobuf.MessageLite$Builder toBuilder();
    Code:
       0: aload_0
       1: invokevirtual #44                 // Method toBuilder:()Lcom/google/rpc/RetryInfo$Builder;
       4: areturn

  public com.google.protobuf.MessageLite$Builder newBuilderForType();
    Code:
       0: aload_0
       1: invokevirtual #49                 // Method newBuilderForType:()Lcom/google/rpc/RetryInfo$Builder;
       4: areturn

  public com.google.protobuf.MessageLite getDefaultInstanceForType();
    Code:
       0: aload_0
       1: invokevirtual #50                 // Method getDefaultInstanceForType:()Lcom/google/rpc/RetryInfo;
       4: areturn

  public com.google.protobuf.Message getDefaultInstanceForType();
    Code:
       0: aload_0
       1: invokevirtual #50                 // Method getDefaultInstanceForType:()Lcom/google/rpc/RetryInfo;
       4: areturn

  com.google.rpc.RetryInfo(com.google.protobuf.GeneratedMessageV3$Builder, com.google.rpc.RetryInfo$1);
    Code:
       0: aload_0
       1: aload_1
       2: invokespecial #2                  // Method "<init>":(Lcom/google/protobuf/GeneratedMessageV3$Builder;)V
       5: return

  static com.google.protobuf.Duration access$302(com.google.rpc.RetryInfo, com.google.protobuf.Duration);
    Code:
       0: aload_0
       1: aload_1
       2: dup_x1
       3: putfield      #1                  // Field retryDelay_:Lcom/google/protobuf/Duration;
       6: areturn

  static {};
    Code:
       0: new           #6                  // class com/google/rpc/RetryInfo
       3: dup
       4: invokespecial #7                  // Method "<init>":()V
       7: putstatic     #43                 // Field DEFAULT_INSTANCE:Lcom/google/rpc/RetryInfo;
      10: new           #51                 // class com/google/rpc/RetryInfo$1
      13: dup
      14: invokespecial #52                 // Method com/google/rpc/RetryInfo$1."<init>":()V
      17: putstatic     #29                 // Field PARSER:Lcom/google/protobuf/Parser;
      20: return
}
