Compiled from "Status.java"
public final class com.google.rpc.Status extends com.google.protobuf.GeneratedMessageV3 implements com.google.rpc.StatusOrBuilder {
  private static final long serialVersionUID;

  public static final int CODE_FIELD_NUMBER;

  private int code_;

  public static final int MESSAGE_FIELD_NUMBER;

  private volatile java.lang.Object message_;

  public static final int DETAILS_FIELD_NUMBER;

  private java.util.List<com.google.protobuf.Any> details_;

  private byte memoizedIsInitialized;

  private static final com.google.rpc.Status DEFAULT_INSTANCE;

  private static final com.google.protobuf.Parser<com.google.rpc.Status> PARSER;

  private com.google.rpc.Status(com.google.protobuf.GeneratedMessageV3$Builder<?>);
    Code:
       0: aload_0
       1: aload_1
       2: invokespecial #7                  // Method com/google/protobuf/GeneratedMessageV3."<init>":(Lcom/google/protobuf/GeneratedMessageV3$Builder;)V
       5: aload_0
       6: iconst_0
       7: putfield      #4                  // Field code_:I
      10: aload_0
      11: ldc           #8                  // String
      13: putfield      #3                  // Field message_:Ljava/lang/Object;
      16: aload_0
      17: iconst_m1
      18: putfield      #9                  // Field memoizedIsInitialized:B
      21: return

  private com.google.rpc.Status();
    Code:
       0: aload_0
       1: invokespecial #10                 // Method com/google/protobuf/GeneratedMessageV3."<init>":()V
       4: aload_0
       5: iconst_0
       6: putfield      #4                  // Field code_:I
       9: aload_0
      10: ldc           #8                  // String
      12: putfield      #3                  // Field message_:Ljava/lang/Object;
      15: aload_0
      16: iconst_m1
      17: putfield      #9                  // Field memoizedIsInitialized:B
      20: aload_0
      21: ldc           #8                  // String
      23: putfield      #3                  // Field message_:Ljava/lang/Object;
      26: aload_0
      27: invokestatic  #11                 // Method java/util/Collections.emptyList:()Ljava/util/List;
      30: putfield      #5                  // Field details_:Ljava/util/List;
      33: return

  protected java.lang.Object newInstance(com.google.protobuf.GeneratedMessageV3$UnusedPrivateParameter);
    Code:
       0: new           #12                 // class com/google/rpc/Status
       3: dup
       4: invokespecial #13                 // Method "<init>":()V
       7: areturn

  public static final com.google.protobuf.Descriptors$Descriptor getDescriptor();
    Code:
       0: getstatic     #14                 // Field com/google/rpc/StatusProto.internal_static_google_rpc_Status_descriptor:Lcom/google/protobuf/Descriptors$Descriptor;
       3: areturn

  protected com.google.protobuf.GeneratedMessageV3$FieldAccessorTable internalGetFieldAccessorTable();
    Code:
       0: getstatic     #15                 // Field com/google/rpc/StatusProto.internal_static_google_rpc_Status_fieldAccessorTable:Lcom/google/protobuf/GeneratedMessageV3$FieldAccessorTable;
       3: ldc           #12                 // class com/google/rpc/Status
       5: ldc           #16                 // class com/google/rpc/Status$Builder
       7: invokevirtual #17                 // Method com/google/protobuf/GeneratedMessageV3$FieldAccessorTable.ensureFieldAccessorsInitialized:(Ljava/lang/Class;Ljava/lang/Class;)Lcom/google/protobuf/GeneratedMessageV3$FieldAccessorTable;
      10: areturn

  public int getCode();
    Code:
       0: aload_0
       1: getfield      #4                  // Field code_:I
       4: ireturn

  public java.lang.String getMessage();
    Code:
       0: aload_0
       1: getfield      #3                  // Field message_:Ljava/lang/Object;
       4: astore_1
       5: aload_1
       6: instanceof    #18                 // class java/lang/String
       9: ifeq          17
      12: aload_1
      13: checkcast     #18                 // class java/lang/String
      16: areturn
      17: aload_1
      18: checkcast     #19                 // class com/google/protobuf/ByteString
      21: astore_2
      22: aload_2
      23: invokevirtual #20                 // Method com/google/protobuf/ByteString.toStringUtf8:()Ljava/lang/String;
      26: astore_3
      27: aload_0
      28: aload_3
      29: putfield      #3                  // Field message_:Ljava/lang/Object;
      32: aload_3
      33: areturn

  public com.google.protobuf.ByteString getMessageBytes();
    Code:
       0: aload_0
       1: getfield      #3                  // Field message_:Ljava/lang/Object;
       4: astore_1
       5: aload_1
       6: instanceof    #18                 // class java/lang/String
       9: ifeq          27
      12: aload_1
      13: checkcast     #18                 // class java/lang/String
      16: invokestatic  #21                 // Method com/google/protobuf/ByteString.copyFromUtf8:(Ljava/lang/String;)Lcom/google/protobuf/ByteString;
      19: astore_2
      20: aload_0
      21: aload_2
      22: putfield      #3                  // Field message_:Ljava/lang/Object;
      25: aload_2
      26: areturn
      27: aload_1
      28: checkcast     #19                 // class com/google/protobuf/ByteString
      31: areturn

  public java.util.List<com.google.protobuf.Any> getDetailsList();
    Code:
       0: aload_0
       1: getfield      #5                  // Field details_:Ljava/util/List;
       4: areturn

  public java.util.List<? extends com.google.protobuf.AnyOrBuilder> getDetailsOrBuilderList();
    Code:
       0: aload_0
       1: getfield      #5                  // Field details_:Ljava/util/List;
       4: areturn

  public int getDetailsCount();
    Code:
       0: aload_0
       1: getfield      #5                  // Field details_:Ljava/util/List;
       4: invokeinterface #22,  1           // InterfaceMethod java/util/List.size:()I
       9: ireturn

  public com.google.protobuf.Any getDetails(int);
    Code:
       0: aload_0
       1: getfield      #5                  // Field details_:Ljava/util/List;
       4: iload_1
       5: invokeinterface #23,  2           // InterfaceMethod java/util/List.get:(I)Ljava/lang/Object;
      10: checkcast     #24                 // class com/google/protobuf/Any
      13: areturn

  public com.google.protobuf.AnyOrBuilder getDetailsOrBuilder(int);
    Code:
       0: aload_0
       1: getfield      #5                  // Field details_:Ljava/util/List;
       4: iload_1
       5: invokeinterface #23,  2           // InterfaceMethod java/util/List.get:(I)Ljava/lang/Object;
      10: checkcast     #25                 // class com/google/protobuf/AnyOrBuilder
      13: areturn

  public final boolean isInitialized();
    Code:
       0: aload_0
       1: getfield      #9                  // Field memoizedIsInitialized:B
       4: istore_1
       5: iload_1
       6: iconst_1
       7: if_icmpne     12
      10: iconst_1
      11: ireturn
      12: iload_1
      13: ifne          18
      16: iconst_0
      17: ireturn
      18: aload_0
      19: iconst_1
      20: putfield      #9                  // Field memoizedIsInitialized:B
      23: iconst_1
      24: ireturn

  public void writeTo(com.google.protobuf.CodedOutputStream) throws java.io.IOException;
    Code:
       0: aload_0
       1: getfield      #4                  // Field code_:I
       4: ifeq          16
       7: aload_1
       8: iconst_1
       9: aload_0
      10: getfield      #4                  // Field code_:I
      13: invokevirtual #26                 // Method com/google/protobuf/CodedOutputStream.writeInt32:(II)V
      16: aload_0
      17: getfield      #3                  // Field message_:Ljava/lang/Object;
      20: invokestatic  #27                 // Method com/google/protobuf/GeneratedMessageV3.isStringEmpty:(Ljava/lang/Object;)Z
      23: ifne          35
      26: aload_1
      27: iconst_2
      28: aload_0
      29: getfield      #3                  // Field message_:Ljava/lang/Object;
      32: invokestatic  #28                 // Method com/google/protobuf/GeneratedMessageV3.writeString:(Lcom/google/protobuf/CodedOutputStream;ILjava/lang/Object;)V
      35: iconst_0
      36: istore_2
      37: iload_2
      38: aload_0
      39: getfield      #5                  // Field details_:Ljava/util/List;
      42: invokeinterface #22,  1           // InterfaceMethod java/util/List.size:()I
      47: if_icmpge     74
      50: aload_1
      51: iconst_3
      52: aload_0
      53: getfield      #5                  // Field details_:Ljava/util/List;
      56: iload_2
      57: invokeinterface #23,  2           // InterfaceMethod java/util/List.get:(I)Ljava/lang/Object;
      62: checkcast     #29                 // class com/google/protobuf/MessageLite
      65: invokevirtual #30                 // Method com/google/protobuf/CodedOutputStream.writeMessage:(ILcom/google/protobuf/MessageLite;)V
      68: iinc          2, 1
      71: goto          37
      74: aload_0
      75: invokevirtual #31                 // Method getUnknownFields:()Lcom/google/protobuf/UnknownFieldSet;
      78: aload_1
      79: invokevirtual #32                 // Method com/google/protobuf/UnknownFieldSet.writeTo:(Lcom/google/protobuf/CodedOutputStream;)V
      82: return

  public int getSerializedSize();
    Code:
       0: aload_0
       1: getfield      #33                 // Field memoizedSize:I
       4: istore_1
       5: iload_1
       6: iconst_m1
       7: if_icmpeq     12
      10: iload_1
      11: ireturn
      12: iconst_0
      13: istore_1
      14: aload_0
      15: getfield      #4                  // Field code_:I
      18: ifeq          32
      21: iload_1
      22: iconst_1
      23: aload_0
      24: getfield      #4                  // Field code_:I
      27: invokestatic  #34                 // Method com/google/protobuf/CodedOutputStream.computeInt32Size:(II)I
      30: iadd
      31: istore_1
      32: aload_0
      33: getfield      #3                  // Field message_:Ljava/lang/Object;
      36: invokestatic  #27                 // Method com/google/protobuf/GeneratedMessageV3.isStringEmpty:(Ljava/lang/Object;)Z
      39: ifne          53
      42: iload_1
      43: iconst_2
      44: aload_0
      45: getfield      #3                  // Field message_:Ljava/lang/Object;
      48: invokestatic  #35                 // Method com/google/protobuf/GeneratedMessageV3.computeStringSize:(ILjava/lang/Object;)I
      51: iadd
      52: istore_1
      53: iconst_0
      54: istore_2
      55: iload_2
      56: aload_0
      57: getfield      #5                  // Field details_:Ljava/util/List;
      60: invokeinterface #22,  1           // InterfaceMethod java/util/List.size:()I
      65: if_icmpge     94
      68: iload_1
      69: iconst_3
      70: aload_0
      71: getfield      #5                  // Field details_:Ljava/util/List;
      74: iload_2
      75: invokeinterface #23,  2           // InterfaceMethod java/util/List.get:(I)Ljava/lang/Object;
      80: checkcast     #29                 // class com/google/protobuf/MessageLite
      83: invokestatic  #36                 // Method com/google/protobuf/CodedOutputStream.computeMessageSize:(ILcom/google/protobuf/MessageLite;)I
      86: iadd
      87: istore_1
      88: iinc          2, 1
      91: goto          55
      94: iload_1
      95: aload_0
      96: invokevirtual #31                 // Method getUnknownFields:()Lcom/google/protobuf/UnknownFieldSet;
      99: invokevirtual #37                 // Method com/google/protobuf/UnknownFieldSet.getSerializedSize:()I
     102: iadd
     103: istore_1
     104: aload_0
     105: iload_1
     106: putfield      #33                 // Field memoizedSize:I
     109: iload_1
     110: ireturn

  public boolean equals(java.lang.Object);
    Code:
       0: aload_1
       1: aload_0
       2: if_acmpne     7
       5: iconst_1
       6: ireturn
       7: aload_1
       8: instanceof    #12                 // class com/google/rpc/Status
      11: ifne          20
      14: aload_0
      15: aload_1
      16: invokespecial #38                 // Method com/google/protobuf/GeneratedMessageV3.equals:(Ljava/lang/Object;)Z
      19: ireturn
      20: aload_1
      21: checkcast     #12                 // class com/google/rpc/Status
      24: astore_2
      25: aload_0
      26: invokevirtual #39                 // Method getCode:()I
      29: aload_2
      30: invokevirtual #39                 // Method getCode:()I
      33: if_icmpeq     38
      36: iconst_0
      37: ireturn
      38: aload_0
      39: invokevirtual #40                 // Method getMessage:()Ljava/lang/String;
      42: aload_2
      43: invokevirtual #40                 // Method getMessage:()Ljava/lang/String;
      46: invokevirtual #41                 // Method java/lang/String.equals:(Ljava/lang/Object;)Z
      49: ifne          54
      52: iconst_0
      53: ireturn
      54: aload_0
      55: invokevirtual #42                 // Method getDetailsList:()Ljava/util/List;
      58: aload_2
      59: invokevirtual #42                 // Method getDetailsList:()Ljava/util/List;
      62: invokeinterface #43,  2           // InterfaceMethod java/util/List.equals:(Ljava/lang/Object;)Z
      67: ifne          72
      70: iconst_0
      71: ireturn
      72: aload_0
      73: invokevirtual #31                 // Method getUnknownFields:()Lcom/google/protobuf/UnknownFieldSet;
      76: aload_2
      77: invokevirtual #31                 // Method getUnknownFields:()Lcom/google/protobuf/UnknownFieldSet;
      80: invokevirtual #44                 // Method com/google/protobuf/UnknownFieldSet.equals:(Ljava/lang/Object;)Z
      83: ifne          88
      86: iconst_0
      87: ireturn
      88: iconst_1
      89: ireturn

  public int hashCode();
    Code:
       0: aload_0
       1: getfield      #45                 // Field memoizedHashCode:I
       4: ifeq          12
       7: aload_0
       8: getfield      #45                 // Field memoizedHashCode:I
      11: ireturn
      12: bipush        41
      14: istore_1
      15: bipush        19
      17: iload_1
      18: imul
      19: invokestatic  #46                 // Method getDescriptor:()Lcom/google/protobuf/Descriptors$Descriptor;
      22: invokevirtual #47                 // Method java/lang/Object.hashCode:()I
      25: iadd
      26: istore_1
      27: bipush        37
      29: iload_1
      30: imul
      31: iconst_1
      32: iadd
      33: istore_1
      34: bipush        53
      36: iload_1
      37: imul
      38: aload_0
      39: invokevirtual #39                 // Method getCode:()I
      42: iadd
      43: istore_1
      44: bipush        37
      46: iload_1
      47: imul
      48: iconst_2
      49: iadd
      50: istore_1
      51: bipush        53
      53: iload_1
      54: imul
      55: aload_0
      56: invokevirtual #40                 // Method getMessage:()Ljava/lang/String;
      59: invokevirtual #48                 // Method java/lang/String.hashCode:()I
      62: iadd
      63: istore_1
      64: aload_0
      65: invokevirtual #49                 // Method getDetailsCount:()I
      68: ifle          93
      71: bipush        37
      73: iload_1
      74: imul
      75: iconst_3
      76: iadd
      77: istore_1
      78: bipush        53
      80: iload_1
      81: imul
      82: aload_0
      83: invokevirtual #42                 // Method getDetailsList:()Ljava/util/List;
      86: invokeinterface #50,  1           // InterfaceMethod java/util/List.hashCode:()I
      91: iadd
      92: istore_1
      93: bipush        29
      95: iload_1
      96: imul
      97: aload_0
      98: invokevirtual #31                 // Method getUnknownFields:()Lcom/google/protobuf/UnknownFieldSet;
     101: invokevirtual #51                 // Method com/google/protobuf/UnknownFieldSet.hashCode:()I
     104: iadd
     105: istore_1
     106: aload_0
     107: iload_1
     108: putfield      #45                 // Field memoizedHashCode:I
     111: iload_1
     112: ireturn

  public static com.google.rpc.Status parseFrom(java.nio.ByteBuffer) throws com.google.protobuf.InvalidProtocolBufferException;
    Code:
       0: getstatic     #52                 // Field PARSER:Lcom/google/protobuf/Parser;
       3: aload_0
       4: invokeinterface #53,  2           // InterfaceMethod com/google/protobuf/Parser.parseFrom:(Ljava/nio/ByteBuffer;)Ljava/lang/Object;
       9: checkcast     #12                 // class com/google/rpc/Status
      12: areturn

  public static com.google.rpc.Status parseFrom(java.nio.ByteBuffer, com.google.protobuf.ExtensionRegistryLite) throws com.google.protobuf.InvalidProtocolBufferException;
    Code:
       0: getstatic     #52                 // Field PARSER:Lcom/google/protobuf/Parser;
       3: aload_0
       4: aload_1
       5: invokeinterface #54,  3           // InterfaceMethod com/google/protobuf/Parser.parseFrom:(Ljava/nio/ByteBuffer;Lcom/google/protobuf/ExtensionRegistryLite;)Ljava/lang/Object;
      10: checkcast     #12                 // class com/google/rpc/Status
      13: areturn

  public static com.google.rpc.Status parseFrom(com.google.protobuf.ByteString) throws com.google.protobuf.InvalidProtocolBufferException;
    Code:
       0: getstatic     #52                 // Field PARSER:Lcom/google/protobuf/Parser;
       3: aload_0
       4: invokeinterface #55,  2           // InterfaceMethod com/google/protobuf/Parser.parseFrom:(Lcom/google/protobuf/ByteString;)Ljava/lang/Object;
       9: checkcast     #12                 // class com/google/rpc/Status
      12: areturn

  public static com.google.rpc.Status parseFrom(com.google.protobuf.ByteString, com.google.protobuf.ExtensionRegistryLite) throws com.google.protobuf.InvalidProtocolBufferException;
    Code:
       0: getstatic     #52                 // Field PARSER:Lcom/google/protobuf/Parser;
       3: aload_0
       4: aload_1
       5: invokeinterface #56,  3           // InterfaceMethod com/google/protobuf/Parser.parseFrom:(Lcom/google/protobuf/ByteString;Lcom/google/protobuf/ExtensionRegistryLite;)Ljava/lang/Object;
      10: checkcast     #12                 // class com/google/rpc/Status
      13: areturn

  public static com.google.rpc.Status parseFrom(byte[]) throws com.google.protobuf.InvalidProtocolBufferException;
    Code:
       0: getstatic     #52                 // Field PARSER:Lcom/google/protobuf/Parser;
       3: aload_0
       4: invokeinterface #57,  2           // InterfaceMethod com/google/protobuf/Parser.parseFrom:([B)Ljava/lang/Object;
       9: checkcast     #12                 // class com/google/rpc/Status
      12: areturn

  public static com.google.rpc.Status parseFrom(byte[], com.google.protobuf.ExtensionRegistryLite) throws com.google.protobuf.InvalidProtocolBufferException;
    Code:
       0: getstatic     #52                 // Field PARSER:Lcom/google/protobuf/Parser;
       3: aload_0
       4: aload_1
       5: invokeinterface #58,  3           // InterfaceMethod com/google/protobuf/Parser.parseFrom:([BLcom/google/protobuf/ExtensionRegistryLite;)Ljava/lang/Object;
      10: checkcast     #12                 // class com/google/rpc/Status
      13: areturn

  public static com.google.rpc.Status parseFrom(java.io.InputStream) throws java.io.IOException;
    Code:
       0: getstatic     #52                 // Field PARSER:Lcom/google/protobuf/Parser;
       3: aload_0
       4: invokestatic  #59                 // Method com/google/protobuf/GeneratedMessageV3.parseWithIOException:(Lcom/google/protobuf/Parser;Ljava/io/InputStream;)Lcom/google/protobuf/Message;
       7: checkcast     #12                 // class com/google/rpc/Status
      10: areturn

  public static com.google.rpc.Status parseFrom(java.io.InputStream, com.google.protobuf.ExtensionRegistryLite) throws java.io.IOException;
    Code:
       0: getstatic     #52                 // Field PARSER:Lcom/google/protobuf/Parser;
       3: aload_0
       4: aload_1
       5: invokestatic  #60                 // Method com/google/protobuf/GeneratedMessageV3.parseWithIOException:(Lcom/google/protobuf/Parser;Ljava/io/InputStream;Lcom/google/protobuf/ExtensionRegistryLite;)Lcom/google/protobuf/Message;
       8: checkcast     #12                 // class com/google/rpc/Status
      11: areturn

  public static com.google.rpc.Status parseDelimitedFrom(java.io.InputStream) throws java.io.IOException;
    Code:
       0: getstatic     #52                 // Field PARSER:Lcom/google/protobuf/Parser;
       3: aload_0
       4: invokestatic  #61                 // Method com/google/protobuf/GeneratedMessageV3.parseDelimitedWithIOException:(Lcom/google/protobuf/Parser;Ljava/io/InputStream;)Lcom/google/protobuf/Message;
       7: checkcast     #12                 // class com/google/rpc/Status
      10: areturn

  public static com.google.rpc.Status parseDelimitedFrom(java.io.InputStream, com.google.protobuf.ExtensionRegistryLite) throws java.io.IOException;
    Code:
       0: getstatic     #52                 // Field PARSER:Lcom/google/protobuf/Parser;
       3: aload_0
       4: aload_1
       5: invokestatic  #62                 // Method com/google/protobuf/GeneratedMessageV3.parseDelimitedWithIOException:(Lcom/google/protobuf/Parser;Ljava/io/InputStream;Lcom/google/protobuf/ExtensionRegistryLite;)Lcom/google/protobuf/Message;
       8: checkcast     #12                 // class com/google/rpc/Status
      11: areturn

  public static com.google.rpc.Status parseFrom(com.google.protobuf.CodedInputStream) throws java.io.IOException;
    Code:
       0: getstatic     #52                 // Field PARSER:Lcom/google/protobuf/Parser;
       3: aload_0
       4: invokestatic  #63                 // Method com/google/protobuf/GeneratedMessageV3.parseWithIOException:(Lcom/google/protobuf/Parser;Lcom/google/protobuf/CodedInputStream;)Lcom/google/protobuf/Message;
       7: checkcast     #12                 // class com/google/rpc/Status
      10: areturn

  public static com.google.rpc.Status parseFrom(com.google.protobuf.CodedInputStream, com.google.protobuf.ExtensionRegistryLite) throws java.io.IOException;
    Code:
       0: getstatic     #52                 // Field PARSER:Lcom/google/protobuf/Parser;
       3: aload_0
       4: aload_1
       5: invokestatic  #64                 // Method com/google/protobuf/GeneratedMessageV3.parseWithIOException:(Lcom/google/protobuf/Parser;Lcom/google/protobuf/CodedInputStream;Lcom/google/protobuf/ExtensionRegistryLite;)Lcom/google/protobuf/Message;
       8: checkcast     #12                 // class com/google/rpc/Status
      11: areturn

  public com.google.rpc.Status$Builder newBuilderForType();
    Code:
       0: invokestatic  #65                 // Method newBuilder:()Lcom/google/rpc/Status$Builder;
       3: areturn

  public static com.google.rpc.Status$Builder newBuilder();
    Code:
       0: getstatic     #66                 // Field DEFAULT_INSTANCE:Lcom/google/rpc/Status;
       3: invokevirtual #67                 // Method toBuilder:()Lcom/google/rpc/Status$Builder;
       6: areturn

  public static com.google.rpc.Status$Builder newBuilder(com.google.rpc.Status);
    Code:
       0: getstatic     #66                 // Field DEFAULT_INSTANCE:Lcom/google/rpc/Status;
       3: invokevirtual #67                 // Method toBuilder:()Lcom/google/rpc/Status$Builder;
       6: aload_0
       7: invokevirtual #68                 // Method com/google/rpc/Status$Builder.mergeFrom:(Lcom/google/rpc/Status;)Lcom/google/rpc/Status$Builder;
      10: areturn

  public com.google.rpc.Status$Builder toBuilder();
    Code:
       0: aload_0
       1: getstatic     #66                 // Field DEFAULT_INSTANCE:Lcom/google/rpc/Status;
       4: if_acmpne     18
       7: new           #16                 // class com/google/rpc/Status$Builder
      10: dup
      11: aconst_null
      12: invokespecial #69                 // Method com/google/rpc/Status$Builder."<init>":(Lcom/google/rpc/Status$1;)V
      15: goto          30
      18: new           #16                 // class com/google/rpc/Status$Builder
      21: dup
      22: aconst_null
      23: invokespecial #69                 // Method com/google/rpc/Status$Builder."<init>":(Lcom/google/rpc/Status$1;)V
      26: aload_0
      27: invokevirtual #68                 // Method com/google/rpc/Status$Builder.mergeFrom:(Lcom/google/rpc/Status;)Lcom/google/rpc/Status$Builder;
      30: areturn

  protected com.google.rpc.Status$Builder newBuilderForType(com.google.protobuf.GeneratedMessageV3$BuilderParent);
    Code:
       0: new           #16                 // class com/google/rpc/Status$Builder
       3: dup
       4: aload_1
       5: aconst_null
       6: invokespecial #70                 // Method com/google/rpc/Status$Builder."<init>":(Lcom/google/protobuf/GeneratedMessageV3$BuilderParent;Lcom/google/rpc/Status$1;)V
       9: astore_2
      10: aload_2
      11: areturn

  public static com.google.rpc.Status getDefaultInstance();
    Code:
       0: getstatic     #66                 // Field DEFAULT_INSTANCE:Lcom/google/rpc/Status;
       3: areturn

  public static com.google.protobuf.Parser<com.google.rpc.Status> parser();
    Code:
       0: getstatic     #52                 // Field PARSER:Lcom/google/protobuf/Parser;
       3: areturn

  public com.google.protobuf.Parser<com.google.rpc.Status> getParserForType();
    Code:
       0: getstatic     #52                 // Field PARSER:Lcom/google/protobuf/Parser;
       3: areturn

  public com.google.rpc.Status getDefaultInstanceForType();
    Code:
       0: getstatic     #66                 // Field DEFAULT_INSTANCE:Lcom/google/rpc/Status;
       3: areturn

  protected com.google.protobuf.Message$Builder newBuilderForType(com.google.protobuf.GeneratedMessageV3$BuilderParent);
    Code:
       0: aload_0
       1: aload_1
       2: invokevirtual #71                 // Method newBuilderForType:(Lcom/google/protobuf/GeneratedMessageV3$BuilderParent;)Lcom/google/rpc/Status$Builder;
       5: areturn

  public com.google.protobuf.Message$Builder toBuilder();
    Code:
       0: aload_0
       1: invokevirtual #67                 // Method toBuilder:()Lcom/google/rpc/Status$Builder;
       4: areturn

  public com.google.protobuf.Message$Builder newBuilderForType();
    Code:
       0: aload_0
       1: invokevirtual #72                 // Method newBuilderForType:()Lcom/google/rpc/Status$Builder;
       4: areturn

  public com.google.protobuf.MessageLite$Builder toBuilder();
    Code:
       0: aload_0
       1: invokevirtual #67                 // Method toBuilder:()Lcom/google/rpc/Status$Builder;
       4: areturn

  public com.google.protobuf.MessageLite$Builder newBuilderForType();
    Code:
       0: aload_0
       1: invokevirtual #72                 // Method newBuilderForType:()Lcom/google/rpc/Status$Builder;
       4: areturn

  public com.google.protobuf.MessageLite getDefaultInstanceForType();
    Code:
       0: aload_0
       1: invokevirtual #73                 // Method getDefaultInstanceForType:()Lcom/google/rpc/Status;
       4: areturn

  public com.google.protobuf.Message getDefaultInstanceForType();
    Code:
       0: aload_0
       1: invokevirtual #73                 // Method getDefaultInstanceForType:()Lcom/google/rpc/Status;
       4: areturn

  com.google.rpc.Status(com.google.protobuf.GeneratedMessageV3$Builder, com.google.rpc.Status$1);
    Code:
       0: aload_0
       1: aload_1
       2: invokespecial #6                  // Method "<init>":(Lcom/google/protobuf/GeneratedMessageV3$Builder;)V
       5: return

  static java.util.List access$302(com.google.rpc.Status, java.util.List);
    Code:
       0: aload_0
       1: aload_1
       2: dup_x1
       3: putfield      #5                  // Field details_:Ljava/util/List;
       6: areturn

  static int access$402(com.google.rpc.Status, int);
    Code:
       0: aload_0
       1: iload_1
       2: dup_x1
       3: putfield      #4                  // Field code_:I
       6: ireturn

  static java.lang.Object access$502(com.google.rpc.Status, java.lang.Object);
    Code:
       0: aload_0
       1: aload_1
       2: dup_x1
       3: putfield      #3                  // Field message_:Ljava/lang/Object;
       6: areturn

  static java.lang.Object access$500(com.google.rpc.Status);
    Code:
       0: aload_0
       1: getfield      #3                  // Field message_:Ljava/lang/Object;
       4: areturn

  static java.util.List access$300(com.google.rpc.Status);
    Code:
       0: aload_0
       1: getfield      #5                  // Field details_:Ljava/util/List;
       4: areturn

  static boolean access$600();
    Code:
       0: getstatic     #2                  // Field alwaysUseFieldBuilders:Z
       3: ireturn

  static void access$700(com.google.protobuf.ByteString) throws java.lang.IllegalArgumentException;
    Code:
       0: aload_0
       1: invokestatic  #1                  // Method checkByteStringIsUtf8:(Lcom/google/protobuf/ByteString;)V
       4: return

  static {};
    Code:
       0: new           #12                 // class com/google/rpc/Status
       3: dup
       4: invokespecial #13                 // Method "<init>":()V
       7: putstatic     #66                 // Field DEFAULT_INSTANCE:Lcom/google/rpc/Status;
      10: new           #74                 // class com/google/rpc/Status$1
      13: dup
      14: invokespecial #75                 // Method com/google/rpc/Status$1."<init>":()V
      17: putstatic     #52                 // Field PARSER:Lcom/google/protobuf/Parser;
      20: return
}
