Compiled from "ConfigDataLocation.java"
public final class org.springframework.boot.context.config.ConfigDataLocation implements org.springframework.boot.origin.OriginProvider {
  public static final java.lang.String OPTIONAL_PREFIX;

  private final boolean optional;

  private final java.lang.String value;

  private final org.springframework.boot.origin.Origin origin;

  private org.springframework.boot.context.config.ConfigDataLocation(boolean, java.lang.String, org.springframework.boot.origin.Origin);
    Code:
       0: aload_0
       1: invokespecial #1                  // Method java/lang/Object."<init>":()V
       4: aload_0
       5: aload_2
       6: putfield      #7                  // Field value:Ljava/lang/String;
       9: aload_0
      10: iload_1
      11: putfield      #13                 // Field optional:Z
      14: aload_0
      15: aload_3
      16: putfield      #17                 // Field origin:Lorg/springframework/boot/origin/Origin;
      19: return

  public boolean isOptional();
    Code:
       0: aload_0
       1: getfield      #13                 // Field optional:Z
       4: ireturn

  public java.lang.String getValue();
    Code:
       0: aload_0
       1: getfield      #7                  // Field value:Ljava/lang/String;
       4: areturn

  public boolean hasPrefix(java.lang.String);
    Code:
       0: aload_0
       1: getfield      #7                  // Field value:Ljava/lang/String;
       4: aload_1
       5: invokevirtual #21                 // Method java/lang/String.startsWith:(Ljava/lang/String;)Z
       8: ireturn

  public java.lang.String getNonPrefixedValue(java.lang.String);
    Code:
       0: aload_0
       1: aload_1
       2: invokevirtual #27                 // Method hasPrefix:(Ljava/lang/String;)Z
       5: ifeq          20
       8: aload_0
       9: getfield      #7                  // Field value:Ljava/lang/String;
      12: aload_1
      13: invokevirtual #30                 // Method java/lang/String.length:()I
      16: invokevirtual #34                 // Method java/lang/String.substring:(I)Ljava/lang/String;
      19: areturn
      20: aload_0
      21: getfield      #7                  // Field value:Ljava/lang/String;
      24: areturn

  public org.springframework.boot.origin.Origin getOrigin();
    Code:
       0: aload_0
       1: getfield      #17                 // Field origin:Lorg/springframework/boot/origin/Origin;
       4: areturn

  public org.springframework.boot.context.config.ConfigDataLocation[] split();
    Code:
       0: aload_0
       1: ldc           #38                 // String ;
       3: invokevirtual #40                 // Method split:(Ljava/lang/String;)[Lorg/springframework/boot/context/config/ConfigDataLocation;
       6: areturn

  public org.springframework.boot.context.config.ConfigDataLocation[] split(java.lang.String);
    Code:
       0: aload_0
       1: invokevirtual #44                 // Method toString:()Ljava/lang/String;
       4: aload_1
       5: invokestatic  #48                 // Method org/springframework/util/StringUtils.delimitedListToStringArray:(Ljava/lang/String;Ljava/lang/String;)[Ljava/lang/String;
       8: astore_2
       9: aload_2
      10: arraylength
      11: anewarray     #8                  // class org/springframework/boot/context/config/ConfigDataLocation
      14: astore_3
      15: iconst_0
      16: istore        4
      18: iload         4
      20: aload_2
      21: arraylength
      22: if_icmpge     49
      25: aload_3
      26: iload         4
      28: aload_2
      29: iload         4
      31: aaload
      32: invokestatic  #54                 // Method of:(Ljava/lang/String;)Lorg/springframework/boot/context/config/ConfigDataLocation;
      35: aload_0
      36: invokevirtual #58                 // Method getOrigin:()Lorg/springframework/boot/origin/Origin;
      39: invokevirtual #62                 // Method withOrigin:(Lorg/springframework/boot/origin/Origin;)Lorg/springframework/boot/context/config/ConfigDataLocation;
      42: aastore
      43: iinc          4, 1
      46: goto          18
      49: aload_3
      50: areturn

  public boolean equals(java.lang.Object);
    Code:
       0: aload_0
       1: aload_1
       2: if_acmpne     7
       5: iconst_1
       6: ireturn
       7: aload_1
       8: ifnull        22
      11: aload_0
      12: invokevirtual #66                 // Method java/lang/Object.getClass:()Ljava/lang/Class;
      15: aload_1
      16: invokevirtual #66                 // Method java/lang/Object.getClass:()Ljava/lang/Class;
      19: if_acmpeq     24
      22: iconst_0
      23: ireturn
      24: aload_1
      25: checkcast     #8                  // class org/springframework/boot/context/config/ConfigDataLocation
      28: astore_2
      29: aload_0
      30: getfield      #7                  // Field value:Ljava/lang/String;
      33: aload_2
      34: getfield      #7                  // Field value:Ljava/lang/String;
      37: invokevirtual #70                 // Method java/lang/String.equals:(Ljava/lang/Object;)Z
      40: ireturn

  public int hashCode();
    Code:
       0: aload_0
       1: getfield      #7                  // Field value:Ljava/lang/String;
       4: invokevirtual #74                 // Method java/lang/String.hashCode:()I
       7: ireturn

  public java.lang.String toString();
    Code:
       0: aload_0
       1: getfield      #13                 // Field optional:Z
       4: ifne          14
       7: aload_0
       8: getfield      #7                  // Field value:Ljava/lang/String;
      11: goto          23
      14: aload_0
      15: getfield      #7                  // Field value:Ljava/lang/String;
      18: invokedynamic #77,  0             // InvokeDynamic #0:makeConcatWithConstants:(Ljava/lang/String;)Ljava/lang/String;
      23: areturn

  org.springframework.boot.context.config.ConfigDataLocation withOrigin(org.springframework.boot.origin.Origin);
    Code:
       0: new           #8                  // class org/springframework/boot/context/config/ConfigDataLocation
       3: dup
       4: aload_0
       5: getfield      #13                 // Field optional:Z
       8: aload_0
       9: getfield      #7                  // Field value:Ljava/lang/String;
      12: aload_1
      13: invokespecial #81                 // Method "<init>":(ZLjava/lang/String;Lorg/springframework/boot/origin/Origin;)V
      16: areturn

  public static org.springframework.boot.context.config.ConfigDataLocation of(java.lang.String);
    Code:
       0: aload_0
       1: ifnull        17
       4: aload_0
       5: ldc           #84                 // String optional:
       7: invokevirtual #21                 // Method java/lang/String.startsWith:(Ljava/lang/String;)Z
      10: ifeq          17
      13: iconst_1
      14: goto          18
      17: iconst_0
      18: istore_1
      19: iload_1
      20: ifne          27
      23: aload_0
      24: goto          36
      27: aload_0
      28: ldc           #84                 // String optional:
      30: invokevirtual #30                 // Method java/lang/String.length:()I
      33: invokevirtual #34                 // Method java/lang/String.substring:(I)Ljava/lang/String;
      36: astore_2
      37: aload_2
      38: invokestatic  #86                 // Method org/springframework/util/StringUtils.hasText:(Ljava/lang/String;)Z
      41: ifne          46
      44: aconst_null
      45: areturn
      46: new           #8                  // class org/springframework/boot/context/config/ConfigDataLocation
      49: dup
      50: iload_1
      51: aload_2
      52: aconst_null
      53: invokespecial #81                 // Method "<init>":(ZLjava/lang/String;Lorg/springframework/boot/origin/Origin;)V
      56: areturn
}
