Compiled from "ConfigDataEnvironmentContributor.java"
final class org.springframework.boot.context.config.ConfigDataEnvironmentContributor$Kind extends java.lang.Enum<org.springframework.boot.context.config.ConfigDataEnvironmentContributor$Kind> {
  public static final org.springframework.boot.context.config.ConfigDataEnvironmentContributor$Kind ROOT;

  public static final org.springframework.boot.context.config.ConfigDataEnvironmentContributor$Kind INITIAL_IMPORT;

  public static final org.springframework.boot.context.config.ConfigDataEnvironmentContributor$Kind EXISTING;

  public static final org.springframework.boot.context.config.ConfigDataEnvironmentContributor$Kind UNBOUND_IMPORT;

  public static final org.springframework.boot.context.config.ConfigDataEnvironmentContributor$Kind BOUND_IMPORT;

  public static final org.springframework.boot.context.config.ConfigDataEnvironmentContributor$Kind EMPTY_LOCATION;

  private static final org.springframework.boot.context.config.ConfigDataEnvironmentContributor$Kind[] $VALUES;

  public static org.springframework.boot.context.config.ConfigDataEnvironmentContributor$Kind[] values();
    Code:
       0: getstatic     #22                 // Field $VALUES:[Lorg/springframework/boot/context/config/ConfigDataEnvironmentContributor$Kind;
       3: invokevirtual #26                 // Method "[Lorg/springframework/boot/context/config/ConfigDataEnvironmentContributor$Kind;".clone:()Ljava/lang/Object;
       6: checkcast     #27                 // class "[Lorg/springframework/boot/context/config/ConfigDataEnvironmentContributor$Kind;"
       9: areturn

  public static org.springframework.boot.context.config.ConfigDataEnvironmentContributor$Kind valueOf(java.lang.String);
    Code:
       0: ldc           #1                  // class org/springframework/boot/context/config/ConfigDataEnvironmentContributor$Kind
       2: aload_0
       3: invokestatic  #31                 // Method java/lang/Enum.valueOf:(Ljava/lang/Class;Ljava/lang/String;)Ljava/lang/Enum;
       6: checkcast     #1                  // class org/springframework/boot/context/config/ConfigDataEnvironmentContributor$Kind
       9: areturn

  private org.springframework.boot.context.config.ConfigDataEnvironmentContributor$Kind();
    Code:
       0: aload_0
       1: aload_1
       2: iload_2
       3: invokespecial #37                 // Method java/lang/Enum."<init>":(Ljava/lang/String;I)V
       6: return

  private static org.springframework.boot.context.config.ConfigDataEnvironmentContributor$Kind[] $values();
    Code:
       0: bipush        6
       2: anewarray     #1                  // class org/springframework/boot/context/config/ConfigDataEnvironmentContributor$Kind
       5: dup
       6: iconst_0
       7: getstatic     #3                  // Field ROOT:Lorg/springframework/boot/context/config/ConfigDataEnvironmentContributor$Kind;
      10: aastore
      11: dup
      12: iconst_1
      13: getstatic     #7                  // Field INITIAL_IMPORT:Lorg/springframework/boot/context/config/ConfigDataEnvironmentContributor$Kind;
      16: aastore
      17: dup
      18: iconst_2
      19: getstatic     #10                 // Field EXISTING:Lorg/springframework/boot/context/config/ConfigDataEnvironmentContributor$Kind;
      22: aastore
      23: dup
      24: iconst_3
      25: getstatic     #13                 // Field UNBOUND_IMPORT:Lorg/springframework/boot/context/config/ConfigDataEnvironmentContributor$Kind;
      28: aastore
      29: dup
      30: iconst_4
      31: getstatic     #16                 // Field BOUND_IMPORT:Lorg/springframework/boot/context/config/ConfigDataEnvironmentContributor$Kind;
      34: aastore
      35: dup
      36: iconst_5
      37: getstatic     #19                 // Field EMPTY_LOCATION:Lorg/springframework/boot/context/config/ConfigDataEnvironmentContributor$Kind;
      40: aastore
      41: areturn

  static {};
    Code:
       0: new           #1                  // class org/springframework/boot/context/config/ConfigDataEnvironmentContributor$Kind
       3: dup
       4: ldc           #41                 // String ROOT
       6: iconst_0
       7: invokespecial #42                 // Method "<init>":(Ljava/lang/String;I)V
      10: putstatic     #3                  // Field ROOT:Lorg/springframework/boot/context/config/ConfigDataEnvironmentContributor$Kind;
      13: new           #1                  // class org/springframework/boot/context/config/ConfigDataEnvironmentContributor$Kind
      16: dup
      17: ldc           #43                 // String INITIAL_IMPORT
      19: iconst_1
      20: invokespecial #42                 // Method "<init>":(Ljava/lang/String;I)V
      23: putstatic     #7                  // Field INITIAL_IMPORT:Lorg/springframework/boot/context/config/ConfigDataEnvironmentContributor$Kind;
      26: new           #1                  // class org/springframework/boot/context/config/ConfigDataEnvironmentContributor$Kind
      29: dup
      30: ldc           #44                 // String EXISTING
      32: iconst_2
      33: invokespecial #42                 // Method "<init>":(Ljava/lang/String;I)V
      36: putstatic     #10                 // Field EXISTING:Lorg/springframework/boot/context/config/ConfigDataEnvironmentContributor$Kind;
      39: new           #1                  // class org/springframework/boot/context/config/ConfigDataEnvironmentContributor$Kind
      42: dup
      43: ldc           #45                 // String UNBOUND_IMPORT
      45: iconst_3
      46: invokespecial #42                 // Method "<init>":(Ljava/lang/String;I)V
      49: putstatic     #13                 // Field UNBOUND_IMPORT:Lorg/springframework/boot/context/config/ConfigDataEnvironmentContributor$Kind;
      52: new           #1                  // class org/springframework/boot/context/config/ConfigDataEnvironmentContributor$Kind
      55: dup
      56: ldc           #46                 // String BOUND_IMPORT
      58: iconst_4
      59: invokespecial #42                 // Method "<init>":(Ljava/lang/String;I)V
      62: putstatic     #16                 // Field BOUND_IMPORT:Lorg/springframework/boot/context/config/ConfigDataEnvironmentContributor$Kind;
      65: new           #1                  // class org/springframework/boot/context/config/ConfigDataEnvironmentContributor$Kind
      68: dup
      69: ldc           #47                 // String EMPTY_LOCATION
      71: iconst_5
      72: invokespecial #42                 // Method "<init>":(Ljava/lang/String;I)V
      75: putstatic     #19                 // Field EMPTY_LOCATION:Lorg/springframework/boot/context/config/ConfigDataEnvironmentContributor$Kind;
      78: invokestatic  #48                 // Method $values:()[Lorg/springframework/boot/context/config/ConfigDataEnvironmentContributor$Kind;
      81: putstatic     #22                 // Field $VALUES:[Lorg/springframework/boot/context/config/ConfigDataEnvironmentContributor$Kind;
      84: return
}
