Compiled from "ConfigTreeConfigDataResource.java"
public class org.springframework.boot.context.config.ConfigTreeConfigDataResource extends org.springframework.boot.context.config.ConfigDataResource {
  private final java.nio.file.Path path;

  org.springframework.boot.context.config.ConfigTreeConfigDataResource(java.lang.String);
    Code:
       0: aload_0
       1: invokespecial #1                  // Method org/springframework/boot/context/config/ConfigDataResource."<init>":()V
       4: aload_1
       5: ldc           #7                  // String Path must not be null
       7: invokestatic  #9                  // Method org/springframework/util/Assert.notNull:(Ljava/lang/Object;Ljava/lang/String;)V
      10: aload_0
      11: aload_1
      12: iconst_0
      13: anewarray     #15                 // class java/lang/String
      16: invokestatic  #17                 // Method java/nio/file/Paths.get:(Ljava/lang/String;[Ljava/lang/String;)Ljava/nio/file/Path;
      19: invokeinterface #23,  1           // InterfaceMethod java/nio/file/Path.toAbsolutePath:()Ljava/nio/file/Path;
      24: putfield      #29                 // Field path:Ljava/nio/file/Path;
      27: return

  org.springframework.boot.context.config.ConfigTreeConfigDataResource(java.nio.file.Path);
    Code:
       0: aload_0
       1: invokespecial #1                  // Method org/springframework/boot/context/config/ConfigDataResource."<init>":()V
       4: aload_1
       5: ldc           #7                  // String Path must not be null
       7: invokestatic  #9                  // Method org/springframework/util/Assert.notNull:(Ljava/lang/Object;Ljava/lang/String;)V
      10: aload_0
      11: aload_1
      12: invokeinterface #23,  1           // InterfaceMethod java/nio/file/Path.toAbsolutePath:()Ljava/nio/file/Path;
      17: putfield      #29                 // Field path:Ljava/nio/file/Path;
      20: return

  java.nio.file.Path getPath();
    Code:
       0: aload_0
       1: getfield      #29                 // Field path:Ljava/nio/file/Path;
       4: areturn

  public boolean equals(java.lang.Object);
    Code:
       0: aload_0
       1: aload_1
       2: if_acmpne     7
       5: iconst_1
       6: ireturn
       7: aload_1
       8: ifnull        22
      11: aload_0
      12: invokevirtual #35                 // Method java/lang/Object.getClass:()Ljava/lang/Class;
      15: aload_1
      16: invokevirtual #35                 // Method java/lang/Object.getClass:()Ljava/lang/Class;
      19: if_acmpeq     24
      22: iconst_0
      23: ireturn
      24: aload_1
      25: checkcast     #30                 // class org/springframework/boot/context/config/ConfigTreeConfigDataResource
      28: astore_2
      29: aload_0
      30: getfield      #29                 // Field path:Ljava/nio/file/Path;
      33: aload_2
      34: getfield      #29                 // Field path:Ljava/nio/file/Path;
      37: invokestatic  #41                 // Method java/util/Objects.equals:(Ljava/lang/Object;Ljava/lang/Object;)Z
      40: ireturn

  public int hashCode();
    Code:
       0: aload_0
       1: getfield      #29                 // Field path:Ljava/nio/file/Path;
       4: invokeinterface #47,  1           // InterfaceMethod java/nio/file/Path.hashCode:()I
       9: ireturn

  public java.lang.String toString();
    Code:
       0: aload_0
       1: getfield      #29                 // Field path:Ljava/nio/file/Path;
       4: invokedynamic #51,  0             // InvokeDynamic #0:makeConcatWithConstants:(Ljava/nio/file/Path;)Ljava/lang/String;
       9: areturn
}
