Compiled from "ConfigDataEnvironment.java"
class org.springframework.boot.context.config.ConfigDataEnvironment {
  static final java.lang.String LOCATION_PROPERTY;

  static final java.lang.String ADDITIONAL_LOCATION_PROPERTY;

  static final java.lang.String IMPORT_PROPERTY;

  static final java.lang.String ON_NOT_FOUND_PROPERTY;

  static final org.springframework.boot.context.config.ConfigDataLocation[] DEFAULT_SEARCH_LOCATIONS;

  private static final org.springframework.boot.context.config.ConfigDataLocation[] EMPTY_LOCATIONS;

  private static final org.springframework.boot.context.properties.bind.Bindable<org.springframework.boot.context.config.ConfigDataLocation[]> CONFIG_DATA_LOCATION_ARRAY;

  private static final org.springframework.boot.context.properties.bind.Bindable<java.util.List<java.lang.String>> STRING_LIST;

  private static final org.springframework.boot.context.config.ConfigDataEnvironmentContributors$BinderOption[] ALLOW_INACTIVE_BINDING;

  private static final org.springframework.boot.context.config.ConfigDataEnvironmentContributors$BinderOption[] DENY_INACTIVE_BINDING;

  private final org.springframework.boot.logging.DeferredLogFactory logFactory;

  private final org.apache.commons.logging.Log logger;

  private final org.springframework.boot.context.config.ConfigDataNotFoundAction notFoundAction;

  private final org.springframework.boot.ConfigurableBootstrapContext bootstrapContext;

  private final org.springframework.core.env.ConfigurableEnvironment environment;

  private final org.springframework.boot.context.config.ConfigDataLocationResolvers resolvers;

  private final java.util.Collection<java.lang.String> additionalProfiles;

  private final org.springframework.boot.context.config.ConfigDataEnvironmentUpdateListener environmentUpdateListener;

  private final org.springframework.boot.context.config.ConfigDataLoaders loaders;

  private final org.springframework.boot.context.config.ConfigDataEnvironmentContributors contributors;

  org.springframework.boot.context.config.ConfigDataEnvironment(org.springframework.boot.logging.DeferredLogFactory, org.springframework.boot.ConfigurableBootstrapContext, org.springframework.core.env.ConfigurableEnvironment, org.springframework.core.io.ResourceLoader, java.util.Collection<java.lang.String>, org.springframework.boot.context.config.ConfigDataEnvironmentUpdateListener);
    Code:
       0: aload_0
       1: invokespecial #1                  // Method java/lang/Object."<init>":()V
       4: aload_3
       5: invokestatic  #7                  // Method org/springframework/boot/context/properties/bind/Binder.get:(Lorg/springframework/core/env/Environment;)Lorg/springframework/boot/context/properties/bind/Binder;
       8: astore        7
      10: aload_0
      11: aload_1
      12: putfield      #13                 // Field logFactory:Lorg/springframework/boot/logging/DeferredLogFactory;
      15: aload_0
      16: aload_1
      17: aload_0
      18: invokevirtual #19                 // Method java/lang/Object.getClass:()Ljava/lang/Class;
      21: invokeinterface #23,  2           // InterfaceMethod org/springframework/boot/logging/DeferredLogFactory.getLog:(Ljava/lang/Class;)Lorg/apache/commons/logging/Log;
      26: putfield      #29                 // Field logger:Lorg/apache/commons/logging/Log;
      29: aload_0
      30: aload         7
      32: ldc           #33                 // String spring.config.on-not-found
      34: ldc           #35                 // class org/springframework/boot/context/config/ConfigDataNotFoundAction
      36: invokevirtual #37                 // Method org/springframework/boot/context/properties/bind/Binder.bind:(Ljava/lang/String;Ljava/lang/Class;)Lorg/springframework/boot/context/properties/bind/BindResult;
      39: getstatic     #41                 // Field org/springframework/boot/context/config/ConfigDataNotFoundAction.FAIL:Lorg/springframework/boot/context/config/ConfigDataNotFoundAction;
      42: invokevirtual #45                 // Method org/springframework/boot/context/properties/bind/BindResult.orElse:(Ljava/lang/Object;)Ljava/lang/Object;
      45: checkcast     #35                 // class org/springframework/boot/context/config/ConfigDataNotFoundAction
      48: putfield      #51                 // Field notFoundAction:Lorg/springframework/boot/context/config/ConfigDataNotFoundAction;
      51: aload_0
      52: aload_2
      53: putfield      #54                 // Field bootstrapContext:Lorg/springframework/boot/ConfigurableBootstrapContext;
      56: aload_0
      57: aload_3
      58: putfield      #58                 // Field environment:Lorg/springframework/core/env/ConfigurableEnvironment;
      61: aload_0
      62: aload_0
      63: aload_1
      64: aload_2
      65: aload         7
      67: aload         4
      69: invokevirtual #62                 // Method createConfigDataLocationResolvers:(Lorg/springframework/boot/logging/DeferredLogFactory;Lorg/springframework/boot/ConfigurableBootstrapContext;Lorg/springframework/boot/context/properties/bind/Binder;Lorg/springframework/core/io/ResourceLoader;)Lorg/springframework/boot/context/config/ConfigDataLocationResolvers;
      72: putfield      #66                 // Field resolvers:Lorg/springframework/boot/context/config/ConfigDataLocationResolvers;
      75: aload_0
      76: aload         5
      78: putfield      #70                 // Field additionalProfiles:Ljava/util/Collection;
      81: aload_0
      82: aload         6
      84: ifnull        92
      87: aload         6
      89: goto          95
      92: getstatic     #74                 // Field org/springframework/boot/context/config/ConfigDataEnvironmentUpdateListener.NONE:Lorg/springframework/boot/context/config/ConfigDataEnvironmentUpdateListener;
      95: putfield      #80                 // Field environmentUpdateListener:Lorg/springframework/boot/context/config/ConfigDataEnvironmentUpdateListener;
      98: aload_0
      99: new           #83                 // class org/springframework/boot/context/config/ConfigDataLoaders
     102: dup
     103: aload_1
     104: aload_2
     105: aload         4
     107: invokeinterface #85,  1           // InterfaceMethod org/springframework/core/io/ResourceLoader.getClassLoader:()Ljava/lang/ClassLoader;
     112: invokestatic  #91                 // Method org/springframework/core/io/support/SpringFactoriesLoader.forDefaultResourceLocation:(Ljava/lang/ClassLoader;)Lorg/springframework/core/io/support/SpringFactoriesLoader;
     115: invokespecial #97                 // Method org/springframework/boot/context/config/ConfigDataLoaders."<init>":(Lorg/springframework/boot/logging/DeferredLogFactory;Lorg/springframework/boot/ConfigurableBootstrapContext;Lorg/springframework/core/io/support/SpringFactoriesLoader;)V
     118: putfield      #100                // Field loaders:Lorg/springframework/boot/context/config/ConfigDataLoaders;
     121: aload_0
     122: aload_0
     123: aload         7
     125: invokevirtual #104                // Method createContributors:(Lorg/springframework/boot/context/properties/bind/Binder;)Lorg/springframework/boot/context/config/ConfigDataEnvironmentContributors;
     128: putfield      #108                // Field contributors:Lorg/springframework/boot/context/config/ConfigDataEnvironmentContributors;
     131: return

  protected org.springframework.boot.context.config.ConfigDataLocationResolvers createConfigDataLocationResolvers(org.springframework.boot.logging.DeferredLogFactory, org.springframework.boot.ConfigurableBootstrapContext, org.springframework.boot.context.properties.bind.Binder, org.springframework.core.io.ResourceLoader);
    Code:
       0: new           #112                // class org/springframework/boot/context/config/ConfigDataLocationResolvers
       3: dup
       4: aload_1
       5: aload_2
       6: aload_3
       7: aload         4
       9: aload         4
      11: invokeinterface #85,  1           // InterfaceMethod org/springframework/core/io/ResourceLoader.getClassLoader:()Ljava/lang/ClassLoader;
      16: invokestatic  #91                 // Method org/springframework/core/io/support/SpringFactoriesLoader.forDefaultResourceLocation:(Ljava/lang/ClassLoader;)Lorg/springframework/core/io/support/SpringFactoriesLoader;
      19: invokespecial #114                // Method org/springframework/boot/context/config/ConfigDataLocationResolvers."<init>":(Lorg/springframework/boot/logging/DeferredLogFactory;Lorg/springframework/boot/ConfigurableBootstrapContext;Lorg/springframework/boot/context/properties/bind/Binder;Lorg/springframework/core/io/ResourceLoader;Lorg/springframework/core/io/support/SpringFactoriesLoader;)V
      22: areturn

  private org.springframework.boot.context.config.ConfigDataEnvironmentContributors createContributors(org.springframework.boot.context.properties.bind.Binder);
    Code:
       0: aload_0
       1: getfield      #29                 // Field logger:Lorg/apache/commons/logging/Log;
       4: ldc           #117                // String Building config data environment contributors
       6: invokeinterface #119,  2          // InterfaceMethod org/apache/commons/logging/Log.trace:(Ljava/lang/Object;)V
      11: aload_0
      12: getfield      #58                 // Field environment:Lorg/springframework/core/env/ConfigurableEnvironment;
      15: invokeinterface #125,  1          // InterfaceMethod org/springframework/core/env/ConfigurableEnvironment.getPropertySources:()Lorg/springframework/core/env/MutablePropertySources;
      20: astore_2
      21: new           #131                // class java/util/ArrayList
      24: dup
      25: aload_2
      26: invokevirtual #133                // Method org/springframework/core/env/MutablePropertySources.size:()I
      29: bipush        10
      31: iadd
      32: invokespecial #139                // Method java/util/ArrayList."<init>":(I)V
      35: astore_3
      36: aconst_null
      37: astore        4
      39: aload_2
      40: invokevirtual #142                // Method org/springframework/core/env/MutablePropertySources.iterator:()Ljava/util/Iterator;
      43: astore        5
      45: aload         5
      47: invokeinterface #146,  1          // InterfaceMethod java/util/Iterator.hasNext:()Z
      52: ifeq          116
      55: aload         5
      57: invokeinterface #152,  1          // InterfaceMethod java/util/Iterator.next:()Ljava/lang/Object;
      62: checkcast     #156                // class org/springframework/core/env/PropertySource
      65: astore        6
      67: aload         6
      69: invokestatic  #158                // Method org/springframework/boot/DefaultPropertiesPropertySource.hasMatchingName:(Lorg/springframework/core/env/PropertySource;)Z
      72: ifeq          82
      75: aload         6
      77: astore        4
      79: goto          113
      82: aload_0
      83: getfield      #29                 // Field logger:Lorg/apache/commons/logging/Log;
      86: ldc           #164                // String Creating wrapped config data contributor for \'%s\'
      88: aload         6
      90: invokevirtual #166                // Method org/springframework/core/env/PropertySource.getName:()Ljava/lang/String;
      93: invokestatic  #170                // Method org/springframework/core/log/LogMessage.format:(Ljava/lang/String;Ljava/lang/Object;)Lorg/springframework/core/log/LogMessage;
      96: invokeinterface #119,  2          // InterfaceMethod org/apache/commons/logging/Log.trace:(Ljava/lang/Object;)V
     101: aload_3
     102: aload         6
     104: invokestatic  #176                // Method org/springframework/boot/context/config/ConfigDataEnvironmentContributor.ofExisting:(Lorg/springframework/core/env/PropertySource;)Lorg/springframework/boot/context/config/ConfigDataEnvironmentContributor;
     107: invokeinterface #182,  2          // InterfaceMethod java/util/List.add:(Ljava/lang/Object;)Z
     112: pop
     113: goto          45
     116: aload_3
     117: aload_0
     118: aload_1
     119: invokevirtual #188                // Method getInitialImportContributors:(Lorg/springframework/boot/context/properties/bind/Binder;)Ljava/util/List;
     122: invokeinterface #192,  2          // InterfaceMethod java/util/List.addAll:(Ljava/util/Collection;)Z
     127: pop
     128: aload         4
     130: ifnull        156
     133: aload_0
     134: getfield      #29                 // Field logger:Lorg/apache/commons/logging/Log;
     137: ldc           #196                // String Creating wrapped config data contributor for default property source
     139: invokeinterface #119,  2          // InterfaceMethod org/apache/commons/logging/Log.trace:(Ljava/lang/Object;)V
     144: aload_3
     145: aload         4
     147: invokestatic  #176                // Method org/springframework/boot/context/config/ConfigDataEnvironmentContributor.ofExisting:(Lorg/springframework/core/env/PropertySource;)Lorg/springframework/boot/context/config/ConfigDataEnvironmentContributor;
     150: invokeinterface #182,  2          // InterfaceMethod java/util/List.add:(Ljava/lang/Object;)Z
     155: pop
     156: aload_0
     157: aload_3
     158: invokevirtual #198                // Method createContributors:(Ljava/util/List;)Lorg/springframework/boot/context/config/ConfigDataEnvironmentContributors;
     161: areturn

  protected org.springframework.boot.context.config.ConfigDataEnvironmentContributors createContributors(java.util.List<org.springframework.boot.context.config.ConfigDataEnvironmentContributor>);
    Code:
       0: new           #201                // class org/springframework/boot/context/config/ConfigDataEnvironmentContributors
       3: dup
       4: aload_0
       5: getfield      #13                 // Field logFactory:Lorg/springframework/boot/logging/DeferredLogFactory;
       8: aload_0
       9: getfield      #54                 // Field bootstrapContext:Lorg/springframework/boot/ConfigurableBootstrapContext;
      12: aload_1
      13: invokespecial #203                // Method org/springframework/boot/context/config/ConfigDataEnvironmentContributors."<init>":(Lorg/springframework/boot/logging/DeferredLogFactory;Lorg/springframework/boot/ConfigurableBootstrapContext;Ljava/util/List;)V
      16: areturn

  org.springframework.boot.context.config.ConfigDataEnvironmentContributors getContributors();
    Code:
       0: aload_0
       1: getfield      #108                // Field contributors:Lorg/springframework/boot/context/config/ConfigDataEnvironmentContributors;
       4: areturn

  private java.util.List<org.springframework.boot.context.config.ConfigDataEnvironmentContributor> getInitialImportContributors(org.springframework.boot.context.properties.bind.Binder);
    Code:
       0: new           #131                // class java/util/ArrayList
       3: dup
       4: invokespecial #206                // Method java/util/ArrayList."<init>":()V
       7: astore_2
       8: aload_0
       9: aload_2
      10: aload_0
      11: aload_1
      12: ldc           #207                // String spring.config.import
      14: getstatic     #209                // Field EMPTY_LOCATIONS:[Lorg/springframework/boot/context/config/ConfigDataLocation;
      17: invokevirtual #213                // Method bindLocations:(Lorg/springframework/boot/context/properties/bind/Binder;Ljava/lang/String;[Lorg/springframework/boot/context/config/ConfigDataLocation;)[Lorg/springframework/boot/context/config/ConfigDataLocation;
      20: invokevirtual #217                // Method addInitialImportContributors:(Ljava/util/List;[Lorg/springframework/boot/context/config/ConfigDataLocation;)V
      23: aload_0
      24: aload_2
      25: aload_0
      26: aload_1
      27: ldc           #221                // String spring.config.additional-location
      29: getstatic     #209                // Field EMPTY_LOCATIONS:[Lorg/springframework/boot/context/config/ConfigDataLocation;
      32: invokevirtual #213                // Method bindLocations:(Lorg/springframework/boot/context/properties/bind/Binder;Ljava/lang/String;[Lorg/springframework/boot/context/config/ConfigDataLocation;)[Lorg/springframework/boot/context/config/ConfigDataLocation;
      35: invokevirtual #217                // Method addInitialImportContributors:(Ljava/util/List;[Lorg/springframework/boot/context/config/ConfigDataLocation;)V
      38: aload_0
      39: aload_2
      40: aload_0
      41: aload_1
      42: ldc           #223                // String spring.config.location
      44: getstatic     #225                // Field DEFAULT_SEARCH_LOCATIONS:[Lorg/springframework/boot/context/config/ConfigDataLocation;
      47: invokevirtual #213                // Method bindLocations:(Lorg/springframework/boot/context/properties/bind/Binder;Ljava/lang/String;[Lorg/springframework/boot/context/config/ConfigDataLocation;)[Lorg/springframework/boot/context/config/ConfigDataLocation;
      50: invokevirtual #217                // Method addInitialImportContributors:(Ljava/util/List;[Lorg/springframework/boot/context/config/ConfigDataLocation;)V
      53: aload_2
      54: areturn

  private org.springframework.boot.context.config.ConfigDataLocation[] bindLocations(org.springframework.boot.context.properties.bind.Binder, java.lang.String, org.springframework.boot.context.config.ConfigDataLocation[]);
    Code:
       0: aload_1
       1: aload_2
       2: getstatic     #228                // Field CONFIG_DATA_LOCATION_ARRAY:Lorg/springframework/boot/context/properties/bind/Bindable;
       5: invokevirtual #232                // Method org/springframework/boot/context/properties/bind/Binder.bind:(Ljava/lang/String;Lorg/springframework/boot/context/properties/bind/Bindable;)Lorg/springframework/boot/context/properties/bind/BindResult;
       8: aload_3
       9: invokevirtual #45                 // Method org/springframework/boot/context/properties/bind/BindResult.orElse:(Ljava/lang/Object;)Ljava/lang/Object;
      12: checkcast     #235                // class "[Lorg/springframework/boot/context/config/ConfigDataLocation;"
      15: areturn

  private void addInitialImportContributors(java.util.List<org.springframework.boot.context.config.ConfigDataEnvironmentContributor>, org.springframework.boot.context.config.ConfigDataLocation[]);
    Code:
       0: aload_2
       1: arraylength
       2: iconst_1
       3: isub
       4: istore_3
       5: iload_3
       6: iflt          29
       9: aload_1
      10: aload_0
      11: aload_2
      12: iload_3
      13: aaload
      14: invokevirtual #236                // Method createInitialImportContributor:(Lorg/springframework/boot/context/config/ConfigDataLocation;)Lorg/springframework/boot/context/config/ConfigDataEnvironmentContributor;
      17: invokeinterface #182,  2          // InterfaceMethod java/util/List.add:(Ljava/lang/Object;)Z
      22: pop
      23: iinc          3, -1
      26: goto          5
      29: return

  private org.springframework.boot.context.config.ConfigDataEnvironmentContributor createInitialImportContributor(org.springframework.boot.context.config.ConfigDataLocation);
    Code:
       0: aload_0
       1: getfield      #29                 // Field logger:Lorg/apache/commons/logging/Log;
       4: ldc           #240                // String Adding initial config data import from location \'%s\'
       6: aload_1
       7: invokestatic  #170                // Method org/springframework/core/log/LogMessage.format:(Ljava/lang/String;Ljava/lang/Object;)Lorg/springframework/core/log/LogMessage;
      10: invokeinterface #119,  2          // InterfaceMethod org/apache/commons/logging/Log.trace:(Ljava/lang/Object;)V
      15: aload_1
      16: invokestatic  #242                // Method org/springframework/boot/context/config/ConfigDataEnvironmentContributor.ofInitialImport:(Lorg/springframework/boot/context/config/ConfigDataLocation;)Lorg/springframework/boot/context/config/ConfigDataEnvironmentContributor;
      19: areturn

  void processAndApply();
    Code:
       0: new           #245                // class org/springframework/boot/context/config/ConfigDataImporter
       3: dup
       4: aload_0
       5: getfield      #13                 // Field logFactory:Lorg/springframework/boot/logging/DeferredLogFactory;
       8: aload_0
       9: getfield      #51                 // Field notFoundAction:Lorg/springframework/boot/context/config/ConfigDataNotFoundAction;
      12: aload_0
      13: getfield      #66                 // Field resolvers:Lorg/springframework/boot/context/config/ConfigDataLocationResolvers;
      16: aload_0
      17: getfield      #100                // Field loaders:Lorg/springframework/boot/context/config/ConfigDataLoaders;
      20: invokespecial #247                // Method org/springframework/boot/context/config/ConfigDataImporter."<init>":(Lorg/springframework/boot/logging/DeferredLogFactory;Lorg/springframework/boot/context/config/ConfigDataNotFoundAction;Lorg/springframework/boot/context/config/ConfigDataLocationResolvers;Lorg/springframework/boot/context/config/ConfigDataLoaders;)V
      23: astore_1
      24: aload_0
      25: aload_0
      26: getfield      #108                // Field contributors:Lorg/springframework/boot/context/config/ConfigDataEnvironmentContributors;
      29: aconst_null
      30: getstatic     #250                // Field DENY_INACTIVE_BINDING:[Lorg/springframework/boot/context/config/ConfigDataEnvironmentContributors$BinderOption;
      33: invokevirtual #254                // Method registerBootstrapBinder:(Lorg/springframework/boot/context/config/ConfigDataEnvironmentContributors;Lorg/springframework/boot/context/config/ConfigDataActivationContext;[Lorg/springframework/boot/context/config/ConfigDataEnvironmentContributors$BinderOption;)V
      36: aload_0
      37: aload_0
      38: getfield      #108                // Field contributors:Lorg/springframework/boot/context/config/ConfigDataEnvironmentContributors;
      41: aload_1
      42: invokevirtual #258                // Method processInitial:(Lorg/springframework/boot/context/config/ConfigDataEnvironmentContributors;Lorg/springframework/boot/context/config/ConfigDataImporter;)Lorg/springframework/boot/context/config/ConfigDataEnvironmentContributors;
      45: astore_2
      46: aload_0
      47: aload_2
      48: aconst_null
      49: iconst_1
      50: anewarray     #262                // class org/springframework/boot/context/config/ConfigDataEnvironmentContributors$BinderOption
      53: dup
      54: iconst_0
      55: getstatic     #264                // Field org/springframework/boot/context/config/ConfigDataEnvironmentContributors$BinderOption.FAIL_ON_BIND_TO_INACTIVE_SOURCE:Lorg/springframework/boot/context/config/ConfigDataEnvironmentContributors$BinderOption;
      58: aastore
      59: invokevirtual #268                // Method org/springframework/boot/context/config/ConfigDataEnvironmentContributors.getBinder:(Lorg/springframework/boot/context/config/ConfigDataActivationContext;[Lorg/springframework/boot/context/config/ConfigDataEnvironmentContributors$BinderOption;)Lorg/springframework/boot/context/properties/bind/Binder;
      62: invokevirtual #272                // Method createActivationContext:(Lorg/springframework/boot/context/properties/bind/Binder;)Lorg/springframework/boot/context/config/ConfigDataActivationContext;
      65: astore_3
      66: aload_0
      67: aload_2
      68: aload_1
      69: aload_3
      70: invokevirtual #276                // Method processWithoutProfiles:(Lorg/springframework/boot/context/config/ConfigDataEnvironmentContributors;Lorg/springframework/boot/context/config/ConfigDataImporter;Lorg/springframework/boot/context/config/ConfigDataActivationContext;)Lorg/springframework/boot/context/config/ConfigDataEnvironmentContributors;
      73: astore_2
      74: aload_0
      75: aload_2
      76: aload_3
      77: invokevirtual #280                // Method withProfiles:(Lorg/springframework/boot/context/config/ConfigDataEnvironmentContributors;Lorg/springframework/boot/context/config/ConfigDataActivationContext;)Lorg/springframework/boot/context/config/ConfigDataActivationContext;
      80: astore_3
      81: aload_0
      82: aload_2
      83: aload_1
      84: aload_3
      85: invokevirtual #284                // Method processWithProfiles:(Lorg/springframework/boot/context/config/ConfigDataEnvironmentContributors;Lorg/springframework/boot/context/config/ConfigDataImporter;Lorg/springframework/boot/context/config/ConfigDataActivationContext;)Lorg/springframework/boot/context/config/ConfigDataEnvironmentContributors;
      88: astore_2
      89: aload_0
      90: aload_2
      91: aload_3
      92: aload_1
      93: invokevirtual #287                // Method org/springframework/boot/context/config/ConfigDataImporter.getLoadedLocations:()Ljava/util/Set;
      96: aload_1
      97: invokevirtual #291                // Method org/springframework/boot/context/config/ConfigDataImporter.getOptionalLocations:()Ljava/util/Set;
     100: invokevirtual #294                // Method applyToEnvironment:(Lorg/springframework/boot/context/config/ConfigDataEnvironmentContributors;Lorg/springframework/boot/context/config/ConfigDataActivationContext;Ljava/util/Set;Ljava/util/Set;)V
     103: return

  private org.springframework.boot.context.config.ConfigDataEnvironmentContributors processInitial(org.springframework.boot.context.config.ConfigDataEnvironmentContributors, org.springframework.boot.context.config.ConfigDataImporter);
    Code:
       0: aload_0
       1: getfield      #29                 // Field logger:Lorg/apache/commons/logging/Log;
       4: ldc_w         #298                // String Processing initial config data environment contributors without activation context
       7: invokeinterface #119,  2          // InterfaceMethod org/apache/commons/logging/Log.trace:(Ljava/lang/Object;)V
      12: aload_1
      13: aload_2
      14: aconst_null
      15: invokevirtual #300                // Method org/springframework/boot/context/config/ConfigDataEnvironmentContributors.withProcessedImports:(Lorg/springframework/boot/context/config/ConfigDataImporter;Lorg/springframework/boot/context/config/ConfigDataActivationContext;)Lorg/springframework/boot/context/config/ConfigDataEnvironmentContributors;
      18: astore_1
      19: aload_0
      20: aload_1
      21: aconst_null
      22: getstatic     #250                // Field DENY_INACTIVE_BINDING:[Lorg/springframework/boot/context/config/ConfigDataEnvironmentContributors$BinderOption;
      25: invokevirtual #254                // Method registerBootstrapBinder:(Lorg/springframework/boot/context/config/ConfigDataEnvironmentContributors;Lorg/springframework/boot/context/config/ConfigDataActivationContext;[Lorg/springframework/boot/context/config/ConfigDataEnvironmentContributors$BinderOption;)V
      28: aload_1
      29: areturn

  private org.springframework.boot.context.config.ConfigDataActivationContext createActivationContext(org.springframework.boot.context.properties.bind.Binder);
    Code:
       0: aload_0
       1: getfield      #29                 // Field logger:Lorg/apache/commons/logging/Log;
       4: ldc_w         #304                // String Creating config data activation context from initial contributions
       7: invokeinterface #119,  2          // InterfaceMethod org/apache/commons/logging/Log.trace:(Ljava/lang/Object;)V
      12: new           #306                // class org/springframework/boot/context/config/ConfigDataActivationContext
      15: dup
      16: aload_0
      17: getfield      #58                 // Field environment:Lorg/springframework/core/env/ConfigurableEnvironment;
      20: aload_1
      21: invokespecial #308                // Method org/springframework/boot/context/config/ConfigDataActivationContext."<init>":(Lorg/springframework/core/env/Environment;Lorg/springframework/boot/context/properties/bind/Binder;)V
      24: areturn
      25: astore_2
      26: aload_2
      27: invokevirtual #313                // Method org/springframework/boot/context/properties/bind/BindException.getCause:()Ljava/lang/Throwable;
      30: astore        4
      32: aload         4
      34: instanceof    #317                // class org/springframework/boot/context/config/InactiveConfigDataAccessException
      37: ifeq          48
      40: aload         4
      42: checkcast     #317                // class org/springframework/boot/context/config/InactiveConfigDataAccessException
      45: astore_3
      46: aload_3
      47: athrow
      48: aload_2
      49: athrow
    Exception table:
       from    to  target type
          12    24    25   Class org/springframework/boot/context/properties/bind/BindException

  private org.springframework.boot.context.config.ConfigDataEnvironmentContributors processWithoutProfiles(org.springframework.boot.context.config.ConfigDataEnvironmentContributors, org.springframework.boot.context.config.ConfigDataImporter, org.springframework.boot.context.config.ConfigDataActivationContext);
    Code:
       0: aload_0
       1: getfield      #29                 // Field logger:Lorg/apache/commons/logging/Log;
       4: ldc_w         #319                // String Processing config data environment contributors with initial activation context
       7: invokeinterface #119,  2          // InterfaceMethod org/apache/commons/logging/Log.trace:(Ljava/lang/Object;)V
      12: aload_1
      13: aload_2
      14: aload_3
      15: invokevirtual #300                // Method org/springframework/boot/context/config/ConfigDataEnvironmentContributors.withProcessedImports:(Lorg/springframework/boot/context/config/ConfigDataImporter;Lorg/springframework/boot/context/config/ConfigDataActivationContext;)Lorg/springframework/boot/context/config/ConfigDataEnvironmentContributors;
      18: astore_1
      19: aload_0
      20: aload_1
      21: aload_3
      22: getstatic     #250                // Field DENY_INACTIVE_BINDING:[Lorg/springframework/boot/context/config/ConfigDataEnvironmentContributors$BinderOption;
      25: invokevirtual #254                // Method registerBootstrapBinder:(Lorg/springframework/boot/context/config/ConfigDataEnvironmentContributors;Lorg/springframework/boot/context/config/ConfigDataActivationContext;[Lorg/springframework/boot/context/config/ConfigDataEnvironmentContributors$BinderOption;)V
      28: aload_1
      29: areturn

  private org.springframework.boot.context.config.ConfigDataActivationContext withProfiles(org.springframework.boot.context.config.ConfigDataEnvironmentContributors, org.springframework.boot.context.config.ConfigDataActivationContext);
    Code:
       0: aload_0
       1: getfield      #29                 // Field logger:Lorg/apache/commons/logging/Log;
       4: ldc_w         #321                // String Deducing profiles from current config data environment contributors
       7: invokeinterface #119,  2          // InterfaceMethod org/apache/commons/logging/Log.trace:(Ljava/lang/Object;)V
      12: aload_1
      13: aload_2
      14: invokedynamic #323,  0            // InvokeDynamic #0:test:()Ljava/util/function/Predicate;
      19: iconst_1
      20: anewarray     #262                // class org/springframework/boot/context/config/ConfigDataEnvironmentContributors$BinderOption
      23: dup
      24: iconst_0
      25: getstatic     #264                // Field org/springframework/boot/context/config/ConfigDataEnvironmentContributors$BinderOption.FAIL_ON_BIND_TO_INACTIVE_SOURCE:Lorg/springframework/boot/context/config/ConfigDataEnvironmentContributors$BinderOption;
      28: aastore
      29: invokevirtual #327                // Method org/springframework/boot/context/config/ConfigDataEnvironmentContributors.getBinder:(Lorg/springframework/boot/context/config/ConfigDataActivationContext;Ljava/util/function/Predicate;[Lorg/springframework/boot/context/config/ConfigDataEnvironmentContributors$BinderOption;)Lorg/springframework/boot/context/properties/bind/Binder;
      32: astore_3
      33: new           #330                // class java/util/LinkedHashSet
      36: dup
      37: aload_0
      38: getfield      #70                 // Field additionalProfiles:Ljava/util/Collection;
      41: invokespecial #332                // Method java/util/LinkedHashSet."<init>":(Ljava/util/Collection;)V
      44: astore        4
      46: aload         4
      48: aload_0
      49: aload_1
      50: aload_2
      51: invokevirtual #335                // Method getIncludedProfiles:(Lorg/springframework/boot/context/config/ConfigDataEnvironmentContributors;Lorg/springframework/boot/context/config/ConfigDataActivationContext;)Ljava/util/Collection;
      54: invokeinterface #339,  2          // InterfaceMethod java/util/Set.addAll:(Ljava/util/Collection;)Z
      59: pop
      60: new           #342                // class org/springframework/boot/context/config/Profiles
      63: dup
      64: aload_0
      65: getfield      #58                 // Field environment:Lorg/springframework/core/env/ConfigurableEnvironment;
      68: aload_3
      69: aload         4
      71: invokespecial #344                // Method org/springframework/boot/context/config/Profiles."<init>":(Lorg/springframework/core/env/Environment;Lorg/springframework/boot/context/properties/bind/Binder;Ljava/util/Collection;)V
      74: astore        5
      76: aload_2
      77: aload         5
      79: invokevirtual #347                // Method org/springframework/boot/context/config/ConfigDataActivationContext.withProfiles:(Lorg/springframework/boot/context/config/Profiles;)Lorg/springframework/boot/context/config/ConfigDataActivationContext;
      82: areturn
      83: astore        4
      85: aload         4
      87: invokevirtual #313                // Method org/springframework/boot/context/properties/bind/BindException.getCause:()Ljava/lang/Throwable;
      90: astore        6
      92: aload         6
      94: instanceof    #317                // class org/springframework/boot/context/config/InactiveConfigDataAccessException
      97: ifeq          110
     100: aload         6
     102: checkcast     #317                // class org/springframework/boot/context/config/InactiveConfigDataAccessException
     105: astore        5
     107: aload         5
     109: athrow
     110: aload         4
     112: athrow
    Exception table:
       from    to  target type
          33    82    83   Class org/springframework/boot/context/properties/bind/BindException

  private java.util.Collection<? extends java.lang.String> getIncludedProfiles(org.springframework.boot.context.config.ConfigDataEnvironmentContributors, org.springframework.boot.context.config.ConfigDataActivationContext);
    Code:
       0: new           #350                // class org/springframework/boot/context/config/ConfigDataEnvironmentContributorPlaceholdersResolver
       3: dup
       4: aload_1
       5: aload_2
       6: aconst_null
       7: iconst_1
       8: invokespecial #352                // Method org/springframework/boot/context/config/ConfigDataEnvironmentContributorPlaceholdersResolver."<init>":(Ljava/lang/Iterable;Lorg/springframework/boot/context/config/ConfigDataActivationContext;Lorg/springframework/boot/context/config/ConfigDataEnvironmentContributor;Z)V
      11: astore_3
      12: new           #330                // class java/util/LinkedHashSet
      15: dup
      16: invokespecial #355                // Method java/util/LinkedHashSet."<init>":()V
      19: astore        4
      21: aload_1
      22: invokevirtual #356                // Method org/springframework/boot/context/config/ConfigDataEnvironmentContributors.iterator:()Ljava/util/Iterator;
      25: astore        5
      27: aload         5
      29: invokeinterface #146,  1          // InterfaceMethod java/util/Iterator.hasNext:()Z
      34: ifeq          114
      37: aload         5
      39: invokeinterface #152,  1          // InterfaceMethod java/util/Iterator.next:()Ljava/lang/Object;
      44: checkcast     #177                // class org/springframework/boot/context/config/ConfigDataEnvironmentContributor
      47: astore        6
      49: aload         6
      51: invokevirtual #357                // Method org/springframework/boot/context/config/ConfigDataEnvironmentContributor.getConfigurationPropertySource:()Lorg/springframework/boot/context/properties/source/ConfigurationPropertySource;
      54: astore        7
      56: aload         7
      58: ifnull        111
      61: aload         6
      63: getstatic     #361                // Field org/springframework/boot/context/config/ConfigData$Option.IGNORE_PROFILES:Lorg/springframework/boot/context/config/ConfigData$Option;
      66: invokevirtual #367                // Method org/springframework/boot/context/config/ConfigDataEnvironmentContributor.hasConfigDataOption:(Lorg/springframework/boot/context/config/ConfigData$Option;)Z
      69: ifne          111
      72: new           #8                  // class org/springframework/boot/context/properties/bind/Binder
      75: dup
      76: aload         7
      78: invokestatic  #371                // Method java/util/Collections.singleton:(Ljava/lang/Object;)Ljava/util/Set;
      81: aload_3
      82: invokespecial #377                // Method org/springframework/boot/context/properties/bind/Binder."<init>":(Ljava/lang/Iterable;Lorg/springframework/boot/context/properties/bind/PlaceholdersResolver;)V
      85: astore        8
      87: aload         8
      89: getstatic     #380                // Field org/springframework/boot/context/config/Profiles.INCLUDE_PROFILES:Lorg/springframework/boot/context/properties/source/ConfigurationPropertyName;
      92: getstatic     #384                // Field STRING_LIST:Lorg/springframework/boot/context/properties/bind/Bindable;
      95: invokevirtual #387                // Method org/springframework/boot/context/properties/bind/Binder.bind:(Lorg/springframework/boot/context/properties/source/ConfigurationPropertyName;Lorg/springframework/boot/context/properties/bind/Bindable;)Lorg/springframework/boot/context/properties/bind/BindResult;
      98: aload         6
     100: aload_2
     101: aload         4
     103: invokedynamic #390,  0            // InvokeDynamic #1:accept:(Lorg/springframework/boot/context/config/ConfigDataEnvironmentContributor;Lorg/springframework/boot/context/config/ConfigDataActivationContext;Ljava/util/Set;)Ljava/util/function/Consumer;
     108: invokevirtual #394                // Method org/springframework/boot/context/properties/bind/BindResult.ifBound:(Ljava/util/function/Consumer;)V
     111: goto          27
     114: aload         4
     116: areturn

  private org.springframework.boot.context.config.ConfigDataEnvironmentContributors processWithProfiles(org.springframework.boot.context.config.ConfigDataEnvironmentContributors, org.springframework.boot.context.config.ConfigDataImporter, org.springframework.boot.context.config.ConfigDataActivationContext);
    Code:
       0: aload_0
       1: getfield      #29                 // Field logger:Lorg/apache/commons/logging/Log;
       4: ldc_w         #398                // String Processing config data environment contributors with profile activation context
       7: invokeinterface #119,  2          // InterfaceMethod org/apache/commons/logging/Log.trace:(Ljava/lang/Object;)V
      12: aload_1
      13: aload_2
      14: aload_3
      15: invokevirtual #300                // Method org/springframework/boot/context/config/ConfigDataEnvironmentContributors.withProcessedImports:(Lorg/springframework/boot/context/config/ConfigDataImporter;Lorg/springframework/boot/context/config/ConfigDataActivationContext;)Lorg/springframework/boot/context/config/ConfigDataEnvironmentContributors;
      18: astore_1
      19: aload_0
      20: aload_1
      21: aload_3
      22: getstatic     #400                // Field ALLOW_INACTIVE_BINDING:[Lorg/springframework/boot/context/config/ConfigDataEnvironmentContributors$BinderOption;
      25: invokevirtual #254                // Method registerBootstrapBinder:(Lorg/springframework/boot/context/config/ConfigDataEnvironmentContributors;Lorg/springframework/boot/context/config/ConfigDataActivationContext;[Lorg/springframework/boot/context/config/ConfigDataEnvironmentContributors$BinderOption;)V
      28: aload_1
      29: areturn

  private void registerBootstrapBinder(org.springframework.boot.context.config.ConfigDataEnvironmentContributors, org.springframework.boot.context.config.ConfigDataActivationContext, org.springframework.boot.context.config.ConfigDataEnvironmentContributors$BinderOption...);
    Code:
       0: aload_0
       1: getfield      #54                 // Field bootstrapContext:Lorg/springframework/boot/ConfigurableBootstrapContext;
       4: ldc           #8                  // class org/springframework/boot/context/properties/bind/Binder
       6: aload_1
       7: aload_2
       8: aload_3
       9: invokedynamic #403,  0            // InvokeDynamic #2:get:(Lorg/springframework/boot/context/config/ConfigDataEnvironmentContributors;Lorg/springframework/boot/context/config/ConfigDataActivationContext;[Lorg/springframework/boot/context/config/ConfigDataEnvironmentContributors$BinderOption;)Ljava/util/function/Supplier;
      14: invokestatic  #406                // InterfaceMethod org/springframework/boot/BootstrapRegistry$InstanceSupplier.from:(Ljava/util/function/Supplier;)Lorg/springframework/boot/BootstrapRegistry$InstanceSupplier;
      17: getstatic     #412                // Field org/springframework/boot/BootstrapRegistry$Scope.PROTOTYPE:Lorg/springframework/boot/BootstrapRegistry$Scope;
      20: invokeinterface #418,  2          // InterfaceMethod org/springframework/boot/BootstrapRegistry$InstanceSupplier.withScope:(Lorg/springframework/boot/BootstrapRegistry$Scope;)Lorg/springframework/boot/BootstrapRegistry$InstanceSupplier;
      25: invokeinterface #422,  3          // InterfaceMethod org/springframework/boot/ConfigurableBootstrapContext.register:(Ljava/lang/Class;Lorg/springframework/boot/BootstrapRegistry$InstanceSupplier;)V
      30: return

  private void applyToEnvironment(org.springframework.boot.context.config.ConfigDataEnvironmentContributors, org.springframework.boot.context.config.ConfigDataActivationContext, java.util.Set<org.springframework.boot.context.config.ConfigDataLocation>, java.util.Set<org.springframework.boot.context.config.ConfigDataLocation>);
    Code:
       0: aload_0
       1: aload_1
       2: invokevirtual #428                // Method checkForInvalidProperties:(Lorg/springframework/boot/context/config/ConfigDataEnvironmentContributors;)V
       5: aload_0
       6: aload_1
       7: aload_2
       8: aload_3
       9: aload         4
      11: invokevirtual #432                // Method checkMandatoryLocations:(Lorg/springframework/boot/context/config/ConfigDataEnvironmentContributors;Lorg/springframework/boot/context/config/ConfigDataActivationContext;Ljava/util/Set;Ljava/util/Set;)V
      14: aload_0
      15: getfield      #58                 // Field environment:Lorg/springframework/core/env/ConfigurableEnvironment;
      18: invokeinterface #125,  1          // InterfaceMethod org/springframework/core/env/ConfigurableEnvironment.getPropertySources:()Lorg/springframework/core/env/MutablePropertySources;
      23: astore        5
      25: aload_0
      26: aload_1
      27: aload_2
      28: aload         5
      30: invokevirtual #435                // Method applyContributor:(Lorg/springframework/boot/context/config/ConfigDataEnvironmentContributors;Lorg/springframework/boot/context/config/ConfigDataActivationContext;Lorg/springframework/core/env/MutablePropertySources;)V
      33: aload         5
      35: invokestatic  #439                // Method org/springframework/boot/DefaultPropertiesPropertySource.moveToEnd:(Lorg/springframework/core/env/MutablePropertySources;)V
      38: aload_2
      39: invokevirtual #443                // Method org/springframework/boot/context/config/ConfigDataActivationContext.getProfiles:()Lorg/springframework/boot/context/config/Profiles;
      42: astore        6
      44: aload_0
      45: getfield      #29                 // Field logger:Lorg/apache/commons/logging/Log;
      48: ldc_w         #447                // String Setting default profiles: %s
      51: aload         6
      53: invokevirtual #449                // Method org/springframework/boot/context/config/Profiles.getDefault:()Ljava/util/List;
      56: invokestatic  #170                // Method org/springframework/core/log/LogMessage.format:(Ljava/lang/String;Ljava/lang/Object;)Lorg/springframework/core/log/LogMessage;
      59: invokeinterface #119,  2          // InterfaceMethod org/apache/commons/logging/Log.trace:(Ljava/lang/Object;)V
      64: aload_0
      65: getfield      #58                 // Field environment:Lorg/springframework/core/env/ConfigurableEnvironment;
      68: aload         6
      70: invokevirtual #449                // Method org/springframework/boot/context/config/Profiles.getDefault:()Ljava/util/List;
      73: invokestatic  #453                // Method org/springframework/util/StringUtils.toStringArray:(Ljava/util/Collection;)[Ljava/lang/String;
      76: invokeinterface #459,  2          // InterfaceMethod org/springframework/core/env/ConfigurableEnvironment.setDefaultProfiles:([Ljava/lang/String;)V
      81: aload_0
      82: getfield      #29                 // Field logger:Lorg/apache/commons/logging/Log;
      85: ldc_w         #463                // String Setting active profiles: %s
      88: aload         6
      90: invokevirtual #465                // Method org/springframework/boot/context/config/Profiles.getActive:()Ljava/util/List;
      93: invokestatic  #170                // Method org/springframework/core/log/LogMessage.format:(Ljava/lang/String;Ljava/lang/Object;)Lorg/springframework/core/log/LogMessage;
      96: invokeinterface #119,  2          // InterfaceMethod org/apache/commons/logging/Log.trace:(Ljava/lang/Object;)V
     101: aload_0
     102: getfield      #58                 // Field environment:Lorg/springframework/core/env/ConfigurableEnvironment;
     105: aload         6
     107: invokevirtual #465                // Method org/springframework/boot/context/config/Profiles.getActive:()Ljava/util/List;
     110: invokestatic  #453                // Method org/springframework/util/StringUtils.toStringArray:(Ljava/util/Collection;)[Ljava/lang/String;
     113: invokeinterface #468,  2          // InterfaceMethod org/springframework/core/env/ConfigurableEnvironment.setActiveProfiles:([Ljava/lang/String;)V
     118: aload_0
     119: getfield      #80                 // Field environmentUpdateListener:Lorg/springframework/boot/context/config/ConfigDataEnvironmentUpdateListener;
     122: aload         6
     124: invokeinterface #471,  2          // InterfaceMethod org/springframework/boot/context/config/ConfigDataEnvironmentUpdateListener.onSetProfiles:(Lorg/springframework/boot/context/config/Profiles;)V
     129: return

  private void applyContributor(org.springframework.boot.context.config.ConfigDataEnvironmentContributors, org.springframework.boot.context.config.ConfigDataActivationContext, org.springframework.core.env.MutablePropertySources);
    Code:
       0: aload_0
       1: getfield      #29                 // Field logger:Lorg/apache/commons/logging/Log;
       4: ldc_w         #475                // String Applying config data environment contributions
       7: invokeinterface #119,  2          // InterfaceMethod org/apache/commons/logging/Log.trace:(Ljava/lang/Object;)V
      12: aload_1
      13: invokevirtual #356                // Method org/springframework/boot/context/config/ConfigDataEnvironmentContributors.iterator:()Ljava/util/Iterator;
      16: astore        4
      18: aload         4
      20: invokeinterface #146,  1          // InterfaceMethod java/util/Iterator.hasNext:()Z
      25: ifeq          145
      28: aload         4
      30: invokeinterface #152,  1          // InterfaceMethod java/util/Iterator.next:()Ljava/lang/Object;
      35: checkcast     #177                // class org/springframework/boot/context/config/ConfigDataEnvironmentContributor
      38: astore        5
      40: aload         5
      42: invokevirtual #477                // Method org/springframework/boot/context/config/ConfigDataEnvironmentContributor.getPropertySource:()Lorg/springframework/core/env/PropertySource;
      45: astore        6
      47: aload         5
      49: invokevirtual #481                // Method org/springframework/boot/context/config/ConfigDataEnvironmentContributor.getKind:()Lorg/springframework/boot/context/config/ConfigDataEnvironmentContributor$Kind;
      52: getstatic     #485                // Field org/springframework/boot/context/config/ConfigDataEnvironmentContributor$Kind.BOUND_IMPORT:Lorg/springframework/boot/context/config/ConfigDataEnvironmentContributor$Kind;
      55: if_acmpne     142
      58: aload         6
      60: ifnull        142
      63: aload         5
      65: aload_2
      66: invokevirtual #491                // Method org/springframework/boot/context/config/ConfigDataEnvironmentContributor.isActive:(Lorg/springframework/boot/context/config/ConfigDataActivationContext;)Z
      69: ifne          95
      72: aload_0
      73: getfield      #29                 // Field logger:Lorg/apache/commons/logging/Log;
      76: ldc_w         #495                // String Skipping inactive property source \'%s\'
      79: aload         6
      81: invokevirtual #166                // Method org/springframework/core/env/PropertySource.getName:()Ljava/lang/String;
      84: invokestatic  #170                // Method org/springframework/core/log/LogMessage.format:(Ljava/lang/String;Ljava/lang/Object;)Lorg/springframework/core/log/LogMessage;
      87: invokeinterface #119,  2          // InterfaceMethod org/apache/commons/logging/Log.trace:(Ljava/lang/Object;)V
      92: goto          142
      95: aload_0
      96: getfield      #29                 // Field logger:Lorg/apache/commons/logging/Log;
      99: ldc_w         #497                // String Adding imported property source \'%s\'
     102: aload         6
     104: invokevirtual #166                // Method org/springframework/core/env/PropertySource.getName:()Ljava/lang/String;
     107: invokestatic  #170                // Method org/springframework/core/log/LogMessage.format:(Ljava/lang/String;Ljava/lang/Object;)Lorg/springframework/core/log/LogMessage;
     110: invokeinterface #119,  2          // InterfaceMethod org/apache/commons/logging/Log.trace:(Ljava/lang/Object;)V
     115: aload_3
     116: aload         6
     118: invokevirtual #499                // Method org/springframework/core/env/MutablePropertySources.addLast:(Lorg/springframework/core/env/PropertySource;)V
     121: aload_0
     122: getfield      #80                 // Field environmentUpdateListener:Lorg/springframework/boot/context/config/ConfigDataEnvironmentUpdateListener;
     125: aload         6
     127: aload         5
     129: invokevirtual #503                // Method org/springframework/boot/context/config/ConfigDataEnvironmentContributor.getLocation:()Lorg/springframework/boot/context/config/ConfigDataLocation;
     132: aload         5
     134: invokevirtual #507                // Method org/springframework/boot/context/config/ConfigDataEnvironmentContributor.getResource:()Lorg/springframework/boot/context/config/ConfigDataResource;
     137: invokeinterface #511,  4          // InterfaceMethod org/springframework/boot/context/config/ConfigDataEnvironmentUpdateListener.onPropertySourceAdded:(Lorg/springframework/core/env/PropertySource;Lorg/springframework/boot/context/config/ConfigDataLocation;Lorg/springframework/boot/context/config/ConfigDataResource;)V
     142: goto          18
     145: return

  private void checkForInvalidProperties(org.springframework.boot.context.config.ConfigDataEnvironmentContributors);
    Code:
       0: aload_1
       1: invokevirtual #356                // Method org/springframework/boot/context/config/ConfigDataEnvironmentContributors.iterator:()Ljava/util/Iterator;
       4: astore_2
       5: aload_2
       6: invokeinterface #146,  1          // InterfaceMethod java/util/Iterator.hasNext:()Z
      11: ifeq          31
      14: aload_2
      15: invokeinterface #152,  1          // InterfaceMethod java/util/Iterator.next:()Ljava/lang/Object;
      20: checkcast     #177                // class org/springframework/boot/context/config/ConfigDataEnvironmentContributor
      23: astore_3
      24: aload_3
      25: invokestatic  #515                // Method org/springframework/boot/context/config/InvalidConfigDataPropertyException.throwIfPropertyFound:(Lorg/springframework/boot/context/config/ConfigDataEnvironmentContributor;)V
      28: goto          5
      31: return

  private void checkMandatoryLocations(org.springframework.boot.context.config.ConfigDataEnvironmentContributors, org.springframework.boot.context.config.ConfigDataActivationContext, java.util.Set<org.springframework.boot.context.config.ConfigDataLocation>, java.util.Set<org.springframework.boot.context.config.ConfigDataLocation>);
    Code:
       0: new           #330                // class java/util/LinkedHashSet
       3: dup
       4: invokespecial #355                // Method java/util/LinkedHashSet."<init>":()V
       7: astore        5
       9: aload_1
      10: invokevirtual #356                // Method org/springframework/boot/context/config/ConfigDataEnvironmentContributors.iterator:()Ljava/util/Iterator;
      13: astore        6
      15: aload         6
      17: invokeinterface #146,  1          // InterfaceMethod java/util/Iterator.hasNext:()Z
      22: ifeq          63
      25: aload         6
      27: invokeinterface #152,  1          // InterfaceMethod java/util/Iterator.next:()Ljava/lang/Object;
      32: checkcast     #177                // class org/springframework/boot/context/config/ConfigDataEnvironmentContributor
      35: astore        7
      37: aload         7
      39: aload_2
      40: invokevirtual #491                // Method org/springframework/boot/context/config/ConfigDataEnvironmentContributor.isActive:(Lorg/springframework/boot/context/config/ConfigDataActivationContext;)Z
      43: ifeq          60
      46: aload         5
      48: aload_0
      49: aload         7
      51: invokevirtual #521                // Method getMandatoryImports:(Lorg/springframework/boot/context/config/ConfigDataEnvironmentContributor;)Ljava/util/Set;
      54: invokeinterface #339,  2          // InterfaceMethod java/util/Set.addAll:(Ljava/util/Collection;)Z
      59: pop
      60: goto          15
      63: aload_1
      64: invokevirtual #356                // Method org/springframework/boot/context/config/ConfigDataEnvironmentContributors.iterator:()Ljava/util/Iterator;
      67: astore        6
      69: aload         6
      71: invokeinterface #146,  1          // InterfaceMethod java/util/Iterator.hasNext:()Z
      76: ifeq          115
      79: aload         6
      81: invokeinterface #152,  1          // InterfaceMethod java/util/Iterator.next:()Ljava/lang/Object;
      86: checkcast     #177                // class org/springframework/boot/context/config/ConfigDataEnvironmentContributor
      89: astore        7
      91: aload         7
      93: invokevirtual #503                // Method org/springframework/boot/context/config/ConfigDataEnvironmentContributor.getLocation:()Lorg/springframework/boot/context/config/ConfigDataLocation;
      96: ifnull        112
      99: aload         5
     101: aload         7
     103: invokevirtual #503                // Method org/springframework/boot/context/config/ConfigDataEnvironmentContributor.getLocation:()Lorg/springframework/boot/context/config/ConfigDataLocation;
     106: invokeinterface #525,  2          // InterfaceMethod java/util/Set.remove:(Ljava/lang/Object;)Z
     111: pop
     112: goto          69
     115: aload         5
     117: aload_3
     118: invokeinterface #528,  2          // InterfaceMethod java/util/Set.removeAll:(Ljava/util/Collection;)Z
     123: pop
     124: aload         5
     126: aload         4
     128: invokeinterface #528,  2          // InterfaceMethod java/util/Set.removeAll:(Ljava/util/Collection;)Z
     133: pop
     134: aload         5
     136: invokeinterface #531,  1          // InterfaceMethod java/util/Set.isEmpty:()Z
     141: ifne          198
     144: aload         5
     146: invokeinterface #534,  1          // InterfaceMethod java/util/Set.iterator:()Ljava/util/Iterator;
     151: astore        6
     153: aload         6
     155: invokeinterface #146,  1          // InterfaceMethod java/util/Iterator.hasNext:()Z
     160: ifeq          198
     163: aload         6
     165: invokeinterface #152,  1          // InterfaceMethod java/util/Iterator.next:()Ljava/lang/Object;
     170: checkcast     #535                // class org/springframework/boot/context/config/ConfigDataLocation
     173: astore        7
     175: aload_0
     176: getfield      #51                 // Field notFoundAction:Lorg/springframework/boot/context/config/ConfigDataNotFoundAction;
     179: aload_0
     180: getfield      #29                 // Field logger:Lorg/apache/commons/logging/Log;
     183: new           #537                // class org/springframework/boot/context/config/ConfigDataLocationNotFoundException
     186: dup
     187: aload         7
     189: invokespecial #539                // Method org/springframework/boot/context/config/ConfigDataLocationNotFoundException."<init>":(Lorg/springframework/boot/context/config/ConfigDataLocation;)V
     192: invokevirtual #542                // Method org/springframework/boot/context/config/ConfigDataNotFoundAction.handle:(Lorg/apache/commons/logging/Log;Lorg/springframework/boot/context/config/ConfigDataNotFoundException;)V
     195: goto          153
     198: return

  private java.util.Set<org.springframework.boot.context.config.ConfigDataLocation> getMandatoryImports(org.springframework.boot.context.config.ConfigDataEnvironmentContributor);
    Code:
       0: aload_1
       1: invokevirtual #546                // Method org/springframework/boot/context/config/ConfigDataEnvironmentContributor.getImports:()Ljava/util/List;
       4: astore_2
       5: new           #330                // class java/util/LinkedHashSet
       8: dup
       9: aload_2
      10: invokeinterface #549,  1          // InterfaceMethod java/util/List.size:()I
      15: invokespecial #550                // Method java/util/LinkedHashSet."<init>":(I)V
      18: astore_3
      19: aload_2
      20: invokeinterface #551,  1          // InterfaceMethod java/util/List.iterator:()Ljava/util/Iterator;
      25: astore        4
      27: aload         4
      29: invokeinterface #146,  1          // InterfaceMethod java/util/Iterator.hasNext:()Z
      34: ifeq          69
      37: aload         4
      39: invokeinterface #152,  1          // InterfaceMethod java/util/Iterator.next:()Ljava/lang/Object;
      44: checkcast     #535                // class org/springframework/boot/context/config/ConfigDataLocation
      47: astore        5
      49: aload         5
      51: invokevirtual #552                // Method org/springframework/boot/context/config/ConfigDataLocation.isOptional:()Z
      54: ifne          66
      57: aload_3
      58: aload         5
      60: invokeinterface #555,  2          // InterfaceMethod java/util/Set.add:(Ljava/lang/Object;)Z
      65: pop
      66: goto          27
      69: aload_3
      70: areturn

  private static org.springframework.boot.context.properties.bind.Binder lambda$registerBootstrapBinder$2(org.springframework.boot.context.config.ConfigDataEnvironmentContributors, org.springframework.boot.context.config.ConfigDataActivationContext, org.springframework.boot.context.config.ConfigDataEnvironmentContributors$BinderOption[]);
    Code:
       0: aload_0
       1: aload_1
       2: aload_2
       3: invokevirtual #268                // Method org/springframework/boot/context/config/ConfigDataEnvironmentContributors.getBinder:(Lorg/springframework/boot/context/config/ConfigDataActivationContext;[Lorg/springframework/boot/context/config/ConfigDataEnvironmentContributors$BinderOption;)Lorg/springframework/boot/context/properties/bind/Binder;
       6: areturn

  private static void lambda$getIncludedProfiles$1(org.springframework.boot.context.config.ConfigDataEnvironmentContributor, org.springframework.boot.context.config.ConfigDataActivationContext, java.util.Set, java.util.List);
    Code:
       0: aload_0
       1: aload_1
       2: invokevirtual #491                // Method org/springframework/boot/context/config/ConfigDataEnvironmentContributor.isActive:(Lorg/springframework/boot/context/config/ConfigDataActivationContext;)Z
       5: ifne          28
       8: aload_0
       9: getstatic     #380                // Field org/springframework/boot/context/config/Profiles.INCLUDE_PROFILES:Lorg/springframework/boot/context/properties/source/ConfigurationPropertyName;
      12: invokestatic  #556                // Method org/springframework/boot/context/config/InactiveConfigDataAccessException.throwIfPropertyFound:(Lorg/springframework/boot/context/config/ConfigDataEnvironmentContributor;Lorg/springframework/boot/context/properties/source/ConfigurationPropertyName;)V
      15: aload_0
      16: getstatic     #380                // Field org/springframework/boot/context/config/Profiles.INCLUDE_PROFILES:Lorg/springframework/boot/context/properties/source/ConfigurationPropertyName;
      19: ldc_w         #559                // String [0]
      22: invokevirtual #561                // Method org/springframework/boot/context/properties/source/ConfigurationPropertyName.append:(Ljava/lang/String;)Lorg/springframework/boot/context/properties/source/ConfigurationPropertyName;
      25: invokestatic  #556                // Method org/springframework/boot/context/config/InactiveConfigDataAccessException.throwIfPropertyFound:(Lorg/springframework/boot/context/config/ConfigDataEnvironmentContributor;Lorg/springframework/boot/context/properties/source/ConfigurationPropertyName;)V
      28: aload_2
      29: aload_3
      30: invokeinterface #339,  2          // InterfaceMethod java/util/Set.addAll:(Ljava/util/Collection;)Z
      35: pop
      36: return

  private static boolean lambda$withProfiles$0(org.springframework.boot.context.config.ConfigDataEnvironmentContributor);
    Code:
       0: aload_0
       1: getstatic     #361                // Field org/springframework/boot/context/config/ConfigData$Option.IGNORE_PROFILES:Lorg/springframework/boot/context/config/ConfigData$Option;
       4: invokevirtual #367                // Method org/springframework/boot/context/config/ConfigDataEnvironmentContributor.hasConfigDataOption:(Lorg/springframework/boot/context/config/ConfigData$Option;)Z
       7: ifne          14
      10: iconst_1
      11: goto          15
      14: iconst_0
      15: ireturn

  static {};
    Code:
       0: new           #131                // class java/util/ArrayList
       3: dup
       4: invokespecial #206                // Method java/util/ArrayList."<init>":()V
       7: astore_0
       8: aload_0
       9: ldc_w         #567                // String optional:classpath:/;optional:classpath:/config/
      12: invokestatic  #569                // Method org/springframework/boot/context/config/ConfigDataLocation.of:(Ljava/lang/String;)Lorg/springframework/boot/context/config/ConfigDataLocation;
      15: invokeinterface #182,  2          // InterfaceMethod java/util/List.add:(Ljava/lang/Object;)Z
      20: pop
      21: aload_0
      22: ldc_w         #573                // String optional:file:./;optional:file:./config/;optional:file:./config/*/
      25: invokestatic  #569                // Method org/springframework/boot/context/config/ConfigDataLocation.of:(Ljava/lang/String;)Lorg/springframework/boot/context/config/ConfigDataLocation;
      28: invokeinterface #182,  2          // InterfaceMethod java/util/List.add:(Ljava/lang/Object;)Z
      33: pop
      34: aload_0
      35: iconst_0
      36: anewarray     #535                // class org/springframework/boot/context/config/ConfigDataLocation
      39: invokeinterface #575,  2          // InterfaceMethod java/util/List.toArray:([Ljava/lang/Object;)[Ljava/lang/Object;
      44: checkcast     #235                // class "[Lorg/springframework/boot/context/config/ConfigDataLocation;"
      47: putstatic     #225                // Field DEFAULT_SEARCH_LOCATIONS:[Lorg/springframework/boot/context/config/ConfigDataLocation;
      50: iconst_0
      51: anewarray     #535                // class org/springframework/boot/context/config/ConfigDataLocation
      54: putstatic     #209                // Field EMPTY_LOCATIONS:[Lorg/springframework/boot/context/config/ConfigDataLocation;
      57: ldc           #235                // class "[Lorg/springframework/boot/context/config/ConfigDataLocation;"
      59: invokestatic  #579                // Method org/springframework/boot/context/properties/bind/Bindable.of:(Ljava/lang/Class;)Lorg/springframework/boot/context/properties/bind/Bindable;
      62: putstatic     #228                // Field CONFIG_DATA_LOCATION_ARRAY:Lorg/springframework/boot/context/properties/bind/Bindable;
      65: ldc_w         #584                // class java/lang/String
      68: invokestatic  #586                // Method org/springframework/boot/context/properties/bind/Bindable.listOf:(Ljava/lang/Class;)Lorg/springframework/boot/context/properties/bind/Bindable;
      71: putstatic     #384                // Field STRING_LIST:Lorg/springframework/boot/context/properties/bind/Bindable;
      74: iconst_0
      75: anewarray     #262                // class org/springframework/boot/context/config/ConfigDataEnvironmentContributors$BinderOption
      78: putstatic     #400                // Field ALLOW_INACTIVE_BINDING:[Lorg/springframework/boot/context/config/ConfigDataEnvironmentContributors$BinderOption;
      81: iconst_1
      82: anewarray     #262                // class org/springframework/boot/context/config/ConfigDataEnvironmentContributors$BinderOption
      85: dup
      86: iconst_0
      87: getstatic     #264                // Field org/springframework/boot/context/config/ConfigDataEnvironmentContributors$BinderOption.FAIL_ON_BIND_TO_INACTIVE_SOURCE:Lorg/springframework/boot/context/config/ConfigDataEnvironmentContributors$BinderOption;
      90: aastore
      91: putstatic     #250                // Field DENY_INACTIVE_BINDING:[Lorg/springframework/boot/context/config/ConfigDataEnvironmentContributors$BinderOption;
      94: return
}
