Compiled from "ConfigDataEnvironmentContributor.java"
class org.springframework.boot.context.config.ConfigDataEnvironmentContributor implements java.lang.Iterable<org.springframework.boot.context.config.ConfigDataEnvironmentContributor> {
  private static final org.springframework.boot.context.config.ConfigData$Options EMPTY_LOCATION_OPTIONS;

  private final org.springframework.boot.context.config.ConfigDataLocation location;

  private final org.springframework.boot.context.config.ConfigDataResource resource;

  private final boolean fromProfileSpecificImport;

  private final org.springframework.core.env.PropertySource<?> propertySource;

  private final org.springframework.boot.context.properties.source.ConfigurationPropertySource configurationPropertySource;

  private final org.springframework.boot.context.config.ConfigDataProperties properties;

  private final org.springframework.boot.context.config.ConfigData$Options configDataOptions;

  private final java.util.Map<org.springframework.boot.context.config.ConfigDataEnvironmentContributor$ImportPhase, java.util.List<org.springframework.boot.context.config.ConfigDataEnvironmentContributor>> children;

  private final org.springframework.boot.context.config.ConfigDataEnvironmentContributor$Kind kind;

  org.springframework.boot.context.config.ConfigDataEnvironmentContributor(org.springframework.boot.context.config.ConfigDataEnvironmentContributor$Kind, org.springframework.boot.context.config.ConfigDataLocation, org.springframework.boot.context.config.ConfigDataResource, boolean, org.springframework.core.env.PropertySource<?>, org.springframework.boot.context.properties.source.ConfigurationPropertySource, org.springframework.boot.context.config.ConfigDataProperties, org.springframework.boot.context.config.ConfigData$Options, java.util.Map<org.springframework.boot.context.config.ConfigDataEnvironmentContributor$ImportPhase, java.util.List<org.springframework.boot.context.config.ConfigDataEnvironmentContributor>>);
    Code:
       0: aload_0
       1: invokespecial #1                  // Method java/lang/Object."<init>":()V
       4: aload_0
       5: aload_1
       6: putfield      #7                  // Field kind:Lorg/springframework/boot/context/config/ConfigDataEnvironmentContributor$Kind;
       9: aload_0
      10: aload_2
      11: putfield      #13                 // Field location:Lorg/springframework/boot/context/config/ConfigDataLocation;
      14: aload_0
      15: aload_3
      16: putfield      #17                 // Field resource:Lorg/springframework/boot/context/config/ConfigDataResource;
      19: aload_0
      20: iload         4
      22: putfield      #21                 // Field fromProfileSpecificImport:Z
      25: aload_0
      26: aload         7
      28: putfield      #25                 // Field properties:Lorg/springframework/boot/context/config/ConfigDataProperties;
      31: aload_0
      32: aload         5
      34: putfield      #29                 // Field propertySource:Lorg/springframework/core/env/PropertySource;
      37: aload_0
      38: aload         6
      40: putfield      #33                 // Field configurationPropertySource:Lorg/springframework/boot/context/properties/source/ConfigurationPropertySource;
      43: aload_0
      44: aload         8
      46: ifnull        54
      49: aload         8
      51: goto          57
      54: getstatic     #37                 // Field org/springframework/boot/context/config/ConfigData$Options.NONE:Lorg/springframework/boot/context/config/ConfigData$Options;
      57: putfield      #43                 // Field configDataOptions:Lorg/springframework/boot/context/config/ConfigData$Options;
      60: aload_0
      61: aload         9
      63: ifnull        71
      66: aload         9
      68: goto          74
      71: invokestatic  #46                 // Method java/util/Collections.emptyMap:()Ljava/util/Map;
      74: putfield      #52                 // Field children:Ljava/util/Map;
      77: return

  org.springframework.boot.context.config.ConfigDataEnvironmentContributor$Kind getKind();
    Code:
       0: aload_0
       1: getfield      #7                  // Field kind:Lorg/springframework/boot/context/config/ConfigDataEnvironmentContributor$Kind;
       4: areturn

  org.springframework.boot.context.config.ConfigDataLocation getLocation();
    Code:
       0: aload_0
       1: getfield      #13                 // Field location:Lorg/springframework/boot/context/config/ConfigDataLocation;
       4: areturn

  boolean isActive(org.springframework.boot.context.config.ConfigDataActivationContext);
    Code:
       0: aload_0
       1: getfield      #7                  // Field kind:Lorg/springframework/boot/context/config/ConfigDataEnvironmentContributor$Kind;
       4: getstatic     #56                 // Field org/springframework/boot/context/config/ConfigDataEnvironmentContributor$Kind.UNBOUND_IMPORT:Lorg/springframework/boot/context/config/ConfigDataEnvironmentContributor$Kind;
       7: if_acmpne     12
      10: iconst_0
      11: ireturn
      12: aload_0
      13: getfield      #25                 // Field properties:Lorg/springframework/boot/context/config/ConfigDataProperties;
      16: ifnull        30
      19: aload_0
      20: getfield      #25                 // Field properties:Lorg/springframework/boot/context/config/ConfigDataProperties;
      23: aload_1
      24: invokevirtual #61                 // Method org/springframework/boot/context/config/ConfigDataProperties.isActive:(Lorg/springframework/boot/context/config/ConfigDataActivationContext;)Z
      27: ifeq          34
      30: iconst_1
      31: goto          35
      34: iconst_0
      35: ireturn

  org.springframework.boot.context.config.ConfigDataResource getResource();
    Code:
       0: aload_0
       1: getfield      #17                 // Field resource:Lorg/springframework/boot/context/config/ConfigDataResource;
       4: areturn

  boolean isFromProfileSpecificImport();
    Code:
       0: aload_0
       1: getfield      #21                 // Field fromProfileSpecificImport:Z
       4: ireturn

  org.springframework.core.env.PropertySource<?> getPropertySource();
    Code:
       0: aload_0
       1: getfield      #29                 // Field propertySource:Lorg/springframework/core/env/PropertySource;
       4: areturn

  org.springframework.boot.context.properties.source.ConfigurationPropertySource getConfigurationPropertySource();
    Code:
       0: aload_0
       1: getfield      #33                 // Field configurationPropertySource:Lorg/springframework/boot/context/properties/source/ConfigurationPropertySource;
       4: areturn

  boolean hasConfigDataOption(org.springframework.boot.context.config.ConfigData$Option);
    Code:
       0: aload_0
       1: getfield      #43                 // Field configDataOptions:Lorg/springframework/boot/context/config/ConfigData$Options;
       4: aload_1
       5: invokevirtual #67                 // Method org/springframework/boot/context/config/ConfigData$Options.contains:(Lorg/springframework/boot/context/config/ConfigData$Option;)Z
       8: ireturn

  org.springframework.boot.context.config.ConfigDataEnvironmentContributor withoutConfigDataOption(org.springframework.boot.context.config.ConfigData$Option);
    Code:
       0: new           #8                  // class org/springframework/boot/context/config/ConfigDataEnvironmentContributor
       3: dup
       4: aload_0
       5: getfield      #7                  // Field kind:Lorg/springframework/boot/context/config/ConfigDataEnvironmentContributor$Kind;
       8: aload_0
       9: getfield      #13                 // Field location:Lorg/springframework/boot/context/config/ConfigDataLocation;
      12: aload_0
      13: getfield      #17                 // Field resource:Lorg/springframework/boot/context/config/ConfigDataResource;
      16: aload_0
      17: getfield      #21                 // Field fromProfileSpecificImport:Z
      20: aload_0
      21: getfield      #29                 // Field propertySource:Lorg/springframework/core/env/PropertySource;
      24: aload_0
      25: getfield      #33                 // Field configurationPropertySource:Lorg/springframework/boot/context/properties/source/ConfigurationPropertySource;
      28: aload_0
      29: getfield      #25                 // Field properties:Lorg/springframework/boot/context/config/ConfigDataProperties;
      32: aload_0
      33: getfield      #43                 // Field configDataOptions:Lorg/springframework/boot/context/config/ConfigData$Options;
      36: aload_1
      37: invokevirtual #71                 // Method org/springframework/boot/context/config/ConfigData$Options.without:(Lorg/springframework/boot/context/config/ConfigData$Option;)Lorg/springframework/boot/context/config/ConfigData$Options;
      40: aload_0
      41: getfield      #52                 // Field children:Ljava/util/Map;
      44: invokespecial #75                 // Method "<init>":(Lorg/springframework/boot/context/config/ConfigDataEnvironmentContributor$Kind;Lorg/springframework/boot/context/config/ConfigDataLocation;Lorg/springframework/boot/context/config/ConfigDataResource;ZLorg/springframework/core/env/PropertySource;Lorg/springframework/boot/context/properties/source/ConfigurationPropertySource;Lorg/springframework/boot/context/config/ConfigDataProperties;Lorg/springframework/boot/context/config/ConfigData$Options;Ljava/util/Map;)V
      47: areturn

  java.util.List<org.springframework.boot.context.config.ConfigDataLocation> getImports();
    Code:
       0: aload_0
       1: getfield      #25                 // Field properties:Lorg/springframework/boot/context/config/ConfigDataProperties;
       4: ifnull        17
       7: aload_0
       8: getfield      #25                 // Field properties:Lorg/springframework/boot/context/config/ConfigDataProperties;
      11: invokevirtual #78                 // Method org/springframework/boot/context/config/ConfigDataProperties.getImports:()Ljava/util/List;
      14: goto          20
      17: invokestatic  #82                 // Method java/util/Collections.emptyList:()Ljava/util/List;
      20: areturn

  boolean hasUnprocessedImports(org.springframework.boot.context.config.ConfigDataEnvironmentContributor$ImportPhase);
    Code:
       0: aload_0
       1: invokevirtual #85                 // Method getImports:()Ljava/util/List;
       4: invokeinterface #86,  1           // InterfaceMethod java/util/List.isEmpty:()Z
       9: ifeq          14
      12: iconst_0
      13: ireturn
      14: aload_0
      15: getfield      #52                 // Field children:Ljava/util/Map;
      18: aload_1
      19: invokeinterface #92,  2           // InterfaceMethod java/util/Map.containsKey:(Ljava/lang/Object;)Z
      24: ifne          31
      27: iconst_1
      28: goto          32
      31: iconst_0
      32: ireturn

  java.util.List<org.springframework.boot.context.config.ConfigDataEnvironmentContributor> getChildren(org.springframework.boot.context.config.ConfigDataEnvironmentContributor$ImportPhase);
    Code:
       0: aload_0
       1: getfield      #52                 // Field children:Ljava/util/Map;
       4: aload_1
       5: invokestatic  #82                 // Method java/util/Collections.emptyList:()Ljava/util/List;
       8: invokeinterface #98,  3           // InterfaceMethod java/util/Map.getOrDefault:(Ljava/lang/Object;Ljava/lang/Object;)Ljava/lang/Object;
      13: checkcast     #87                 // class java/util/List
      16: areturn

  java.util.stream.Stream<org.springframework.boot.context.config.ConfigDataEnvironmentContributor> stream();
    Code:
       0: aload_0
       1: invokevirtual #102                // Method spliterator:()Ljava/util/Spliterator;
       4: iconst_0
       5: invokestatic  #106                // Method java/util/stream/StreamSupport.stream:(Ljava/util/Spliterator;Z)Ljava/util/stream/Stream;
       8: areturn

  public java.util.Iterator<org.springframework.boot.context.config.ConfigDataEnvironmentContributor> iterator();
    Code:
       0: new           #112                // class org/springframework/boot/context/config/ConfigDataEnvironmentContributor$ContributorIterator
       3: dup
       4: aload_0
       5: invokespecial #114                // Method org/springframework/boot/context/config/ConfigDataEnvironmentContributor$ContributorIterator."<init>":(Lorg/springframework/boot/context/config/ConfigDataEnvironmentContributor;)V
       8: areturn

  org.springframework.boot.context.config.ConfigDataEnvironmentContributor withBoundProperties(java.lang.Iterable<org.springframework.boot.context.config.ConfigDataEnvironmentContributor>, org.springframework.boot.context.config.ConfigDataActivationContext);
    Code:
       0: aload_0
       1: invokevirtual #117                // Method getConfigurationPropertySource:()Lorg/springframework/boot/context/properties/source/ConfigurationPropertySource;
       4: invokestatic  #121                // Method java/util/Collections.singleton:(Ljava/lang/Object;)Ljava/util/Set;
       7: astore_3
       8: new           #125                // class org/springframework/boot/context/config/ConfigDataEnvironmentContributorPlaceholdersResolver
      11: dup
      12: aload_1
      13: aload_2
      14: aload_0
      15: iconst_1
      16: invokespecial #127                // Method org/springframework/boot/context/config/ConfigDataEnvironmentContributorPlaceholdersResolver."<init>":(Ljava/lang/Iterable;Lorg/springframework/boot/context/config/ConfigDataActivationContext;Lorg/springframework/boot/context/config/ConfigDataEnvironmentContributor;Z)V
      19: astore        4
      21: new           #130                // class org/springframework/boot/context/properties/bind/Binder
      24: dup
      25: aload_3
      26: aload         4
      28: aconst_null
      29: aconst_null
      30: aconst_null
      31: invokespecial #132                // Method org/springframework/boot/context/properties/bind/Binder."<init>":(Ljava/lang/Iterable;Lorg/springframework/boot/context/properties/bind/PlaceholdersResolver;Lorg/springframework/core/convert/ConversionService;Ljava/util/function/Consumer;Lorg/springframework/boot/context/properties/bind/BindHandler;)V
      34: astore        5
      36: aload         5
      38: invokestatic  #135                // Method org/springframework/boot/context/config/ConfigDataProperties.get:(Lorg/springframework/boot/context/properties/bind/Binder;)Lorg/springframework/boot/context/config/ConfigDataProperties;
      41: astore        6
      43: aload         6
      45: ifnull        68
      48: aload_0
      49: getfield      #43                 // Field configDataOptions:Lorg/springframework/boot/context/config/ConfigData$Options;
      52: getstatic     #139                // Field org/springframework/boot/context/config/ConfigData$Option.IGNORE_IMPORTS:Lorg/springframework/boot/context/config/ConfigData$Option;
      55: invokevirtual #67                 // Method org/springframework/boot/context/config/ConfigData$Options.contains:(Lorg/springframework/boot/context/config/ConfigData$Option;)Z
      58: ifeq          68
      61: aload         6
      63: invokevirtual #145                // Method org/springframework/boot/context/config/ConfigDataProperties.withoutImports:()Lorg/springframework/boot/context/config/ConfigDataProperties;
      66: astore        6
      68: new           #8                  // class org/springframework/boot/context/config/ConfigDataEnvironmentContributor
      71: dup
      72: getstatic     #149                // Field org/springframework/boot/context/config/ConfigDataEnvironmentContributor$Kind.BOUND_IMPORT:Lorg/springframework/boot/context/config/ConfigDataEnvironmentContributor$Kind;
      75: aload_0
      76: getfield      #13                 // Field location:Lorg/springframework/boot/context/config/ConfigDataLocation;
      79: aload_0
      80: getfield      #17                 // Field resource:Lorg/springframework/boot/context/config/ConfigDataResource;
      83: aload_0
      84: getfield      #21                 // Field fromProfileSpecificImport:Z
      87: aload_0
      88: getfield      #29                 // Field propertySource:Lorg/springframework/core/env/PropertySource;
      91: aload_0
      92: getfield      #33                 // Field configurationPropertySource:Lorg/springframework/boot/context/properties/source/ConfigurationPropertySource;
      95: aload         6
      97: aload_0
      98: getfield      #43                 // Field configDataOptions:Lorg/springframework/boot/context/config/ConfigData$Options;
     101: aconst_null
     102: invokespecial #75                 // Method "<init>":(Lorg/springframework/boot/context/config/ConfigDataEnvironmentContributor$Kind;Lorg/springframework/boot/context/config/ConfigDataLocation;Lorg/springframework/boot/context/config/ConfigDataResource;ZLorg/springframework/core/env/PropertySource;Lorg/springframework/boot/context/properties/source/ConfigurationPropertySource;Lorg/springframework/boot/context/config/ConfigDataProperties;Lorg/springframework/boot/context/config/ConfigData$Options;Ljava/util/Map;)V
     105: areturn

  org.springframework.boot.context.config.ConfigDataEnvironmentContributor withChildren(org.springframework.boot.context.config.ConfigDataEnvironmentContributor$ImportPhase, java.util.List<org.springframework.boot.context.config.ConfigDataEnvironmentContributor>);
    Code:
       0: new           #152                // class java/util/LinkedHashMap
       3: dup
       4: aload_0
       5: getfield      #52                 // Field children:Ljava/util/Map;
       8: invokespecial #154                // Method java/util/LinkedHashMap."<init>":(Ljava/util/Map;)V
      11: astore_3
      12: aload_3
      13: aload_1
      14: aload_2
      15: invokeinterface #157,  3          // InterfaceMethod java/util/Map.put:(Ljava/lang/Object;Ljava/lang/Object;)Ljava/lang/Object;
      20: pop
      21: aload_1
      22: getstatic     #160                // Field org/springframework/boot/context/config/ConfigDataEnvironmentContributor$ImportPhase.AFTER_PROFILE_ACTIVATION:Lorg/springframework/boot/context/config/ConfigDataEnvironmentContributor$ImportPhase;
      25: if_acmpne     33
      28: aload_0
      29: aload_3
      30: invokevirtual #166                // Method moveProfileSpecific:(Ljava/util/Map;)V
      33: new           #8                  // class org/springframework/boot/context/config/ConfigDataEnvironmentContributor
      36: dup
      37: aload_0
      38: getfield      #7                  // Field kind:Lorg/springframework/boot/context/config/ConfigDataEnvironmentContributor$Kind;
      41: aload_0
      42: getfield      #13                 // Field location:Lorg/springframework/boot/context/config/ConfigDataLocation;
      45: aload_0
      46: getfield      #17                 // Field resource:Lorg/springframework/boot/context/config/ConfigDataResource;
      49: aload_0
      50: getfield      #21                 // Field fromProfileSpecificImport:Z
      53: aload_0
      54: getfield      #29                 // Field propertySource:Lorg/springframework/core/env/PropertySource;
      57: aload_0
      58: getfield      #33                 // Field configurationPropertySource:Lorg/springframework/boot/context/properties/source/ConfigurationPropertySource;
      61: aload_0
      62: getfield      #25                 // Field properties:Lorg/springframework/boot/context/config/ConfigDataProperties;
      65: aload_0
      66: getfield      #43                 // Field configDataOptions:Lorg/springframework/boot/context/config/ConfigData$Options;
      69: aload_3
      70: invokespecial #75                 // Method "<init>":(Lorg/springframework/boot/context/config/ConfigDataEnvironmentContributor$Kind;Lorg/springframework/boot/context/config/ConfigDataLocation;Lorg/springframework/boot/context/config/ConfigDataResource;ZLorg/springframework/core/env/PropertySource;Lorg/springframework/boot/context/properties/source/ConfigurationPropertySource;Lorg/springframework/boot/context/config/ConfigDataProperties;Lorg/springframework/boot/context/config/ConfigData$Options;Ljava/util/Map;)V
      73: areturn

  private void moveProfileSpecific(java.util.Map<org.springframework.boot.context.config.ConfigDataEnvironmentContributor$ImportPhase, java.util.List<org.springframework.boot.context.config.ConfigDataEnvironmentContributor>>);
    Code:
       0: aload_1
       1: getstatic     #169                // Field org/springframework/boot/context/config/ConfigDataEnvironmentContributor$ImportPhase.BEFORE_PROFILE_ACTIVATION:Lorg/springframework/boot/context/config/ConfigDataEnvironmentContributor$ImportPhase;
       4: invokeinterface #172,  2          // InterfaceMethod java/util/Map.get:(Ljava/lang/Object;)Ljava/lang/Object;
       9: checkcast     #87                 // class java/util/List
      12: astore_2
      13: aload_0
      14: aload_2
      15: invokevirtual #175                // Method hasAnyProfileSpecificChildren:(Ljava/util/List;)Z
      18: ifne          22
      21: return
      22: new           #179                // class java/util/ArrayList
      25: dup
      26: aload_2
      27: invokeinterface #181,  1          // InterfaceMethod java/util/List.size:()I
      32: invokespecial #185                // Method java/util/ArrayList."<init>":(I)V
      35: astore_3
      36: new           #179                // class java/util/ArrayList
      39: dup
      40: invokespecial #188                // Method java/util/ArrayList."<init>":()V
      43: astore        4
      45: aload_2
      46: invokeinterface #189,  1          // InterfaceMethod java/util/List.iterator:()Ljava/util/Iterator;
      51: astore        5
      53: aload         5
      55: invokeinterface #193,  1          // InterfaceMethod java/util/Iterator.hasNext:()Z
      60: ifeq          93
      63: aload         5
      65: invokeinterface #198,  1          // InterfaceMethod java/util/Iterator.next:()Ljava/lang/Object;
      70: checkcast     #8                  // class org/springframework/boot/context/config/ConfigDataEnvironmentContributor
      73: astore        6
      75: aload_3
      76: aload_0
      77: aload         6
      79: aload         4
      81: invokevirtual #202                // Method moveProfileSpecificChildren:(Lorg/springframework/boot/context/config/ConfigDataEnvironmentContributor;Ljava/util/List;)Lorg/springframework/boot/context/config/ConfigDataEnvironmentContributor;
      84: invokeinterface #206,  2          // InterfaceMethod java/util/List.add:(Ljava/lang/Object;)Z
      89: pop
      90: goto          53
      93: aload         4
      95: aload_1
      96: getstatic     #160                // Field org/springframework/boot/context/config/ConfigDataEnvironmentContributor$ImportPhase.AFTER_PROFILE_ACTIVATION:Lorg/springframework/boot/context/config/ConfigDataEnvironmentContributor$ImportPhase;
      99: invokestatic  #82                 // Method java/util/Collections.emptyList:()Ljava/util/List;
     102: invokeinterface #98,  3           // InterfaceMethod java/util/Map.getOrDefault:(Ljava/lang/Object;Ljava/lang/Object;)Ljava/lang/Object;
     107: checkcast     #209                // class java/util/Collection
     110: invokeinterface #211,  2          // InterfaceMethod java/util/List.addAll:(Ljava/util/Collection;)Z
     115: pop
     116: aload_1
     117: getstatic     #169                // Field org/springframework/boot/context/config/ConfigDataEnvironmentContributor$ImportPhase.BEFORE_PROFILE_ACTIVATION:Lorg/springframework/boot/context/config/ConfigDataEnvironmentContributor$ImportPhase;
     120: aload_3
     121: invokeinterface #157,  3          // InterfaceMethod java/util/Map.put:(Ljava/lang/Object;Ljava/lang/Object;)Ljava/lang/Object;
     126: pop
     127: aload_1
     128: getstatic     #160                // Field org/springframework/boot/context/config/ConfigDataEnvironmentContributor$ImportPhase.AFTER_PROFILE_ACTIVATION:Lorg/springframework/boot/context/config/ConfigDataEnvironmentContributor$ImportPhase;
     131: aload         4
     133: invokeinterface #157,  3          // InterfaceMethod java/util/Map.put:(Ljava/lang/Object;Ljava/lang/Object;)Ljava/lang/Object;
     138: pop
     139: return

  private org.springframework.boot.context.config.ConfigDataEnvironmentContributor moveProfileSpecificChildren(org.springframework.boot.context.config.ConfigDataEnvironmentContributor, java.util.List<org.springframework.boot.context.config.ConfigDataEnvironmentContributor>);
    Code:
       0: invokestatic  #215                // Method org/springframework/boot/context/config/ConfigDataEnvironmentContributor$ImportPhase.values:()[Lorg/springframework/boot/context/config/ConfigDataEnvironmentContributor$ImportPhase;
       3: astore_3
       4: aload_3
       5: arraylength
       6: istore        4
       8: iconst_0
       9: istore        5
      11: iload         5
      13: iload         4
      15: if_icmpge     136
      18: aload_3
      19: iload         5
      21: aaload
      22: astore        6
      24: aload_1
      25: aload         6
      27: invokevirtual #219                // Method getChildren:(Lorg/springframework/boot/context/config/ConfigDataEnvironmentContributor$ImportPhase;)Ljava/util/List;
      30: astore        7
      32: new           #179                // class java/util/ArrayList
      35: dup
      36: aload         7
      38: invokeinterface #181,  1          // InterfaceMethod java/util/List.size:()I
      43: invokespecial #185                // Method java/util/ArrayList."<init>":(I)V
      46: astore        8
      48: aload         7
      50: invokeinterface #189,  1          // InterfaceMethod java/util/List.iterator:()Ljava/util/Iterator;
      55: astore        9
      57: aload         9
      59: invokeinterface #193,  1          // InterfaceMethod java/util/Iterator.hasNext:()Z
      64: ifeq          121
      67: aload         9
      69: invokeinterface #198,  1          // InterfaceMethod java/util/Iterator.next:()Ljava/lang/Object;
      74: checkcast     #8                  // class org/springframework/boot/context/config/ConfigDataEnvironmentContributor
      77: astore        10
      79: aload         10
      81: getstatic     #223                // Field org/springframework/boot/context/config/ConfigData$Option.PROFILE_SPECIFIC:Lorg/springframework/boot/context/config/ConfigData$Option;
      84: invokevirtual #226                // Method hasConfigDataOption:(Lorg/springframework/boot/context/config/ConfigData$Option;)Z
      87: ifeq          108
      90: aload_2
      91: aload         10
      93: getstatic     #223                // Field org/springframework/boot/context/config/ConfigData$Option.PROFILE_SPECIFIC:Lorg/springframework/boot/context/config/ConfigData$Option;
      96: invokevirtual #229                // Method withoutConfigDataOption:(Lorg/springframework/boot/context/config/ConfigData$Option;)Lorg/springframework/boot/context/config/ConfigDataEnvironmentContributor;
      99: invokeinterface #206,  2          // InterfaceMethod java/util/List.add:(Ljava/lang/Object;)Z
     104: pop
     105: goto          118
     108: aload         8
     110: aload         10
     112: invokeinterface #206,  2          // InterfaceMethod java/util/List.add:(Ljava/lang/Object;)Z
     117: pop
     118: goto          57
     121: aload_1
     122: aload         6
     124: aload         8
     126: invokevirtual #233                // Method withChildren:(Lorg/springframework/boot/context/config/ConfigDataEnvironmentContributor$ImportPhase;Ljava/util/List;)Lorg/springframework/boot/context/config/ConfigDataEnvironmentContributor;
     129: astore_1
     130: iinc          5, 1
     133: goto          11
     136: aload_1
     137: areturn

  private boolean hasAnyProfileSpecificChildren(java.util.List<org.springframework.boot.context.config.ConfigDataEnvironmentContributor>);
    Code:
       0: aload_1
       1: invokestatic  #237                // Method org/springframework/util/CollectionUtils.isEmpty:(Ljava/util/Collection;)Z
       4: ifeq          9
       7: iconst_0
       8: ireturn
       9: aload_1
      10: invokeinterface #189,  1          // InterfaceMethod java/util/List.iterator:()Ljava/util/Iterator;
      15: astore_2
      16: aload_2
      17: invokeinterface #193,  1          // InterfaceMethod java/util/Iterator.hasNext:()Z
      22: ifeq          97
      25: aload_2
      26: invokeinterface #198,  1          // InterfaceMethod java/util/Iterator.next:()Ljava/lang/Object;
      31: checkcast     #8                  // class org/springframework/boot/context/config/ConfigDataEnvironmentContributor
      34: astore_3
      35: invokestatic  #215                // Method org/springframework/boot/context/config/ConfigDataEnvironmentContributor$ImportPhase.values:()[Lorg/springframework/boot/context/config/ConfigDataEnvironmentContributor$ImportPhase;
      38: astore        4
      40: aload         4
      42: arraylength
      43: istore        5
      45: iconst_0
      46: istore        6
      48: iload         6
      50: iload         5
      52: if_icmpge     94
      55: aload         4
      57: iload         6
      59: aaload
      60: astore        7
      62: aload_3
      63: aload         7
      65: invokevirtual #219                // Method getChildren:(Lorg/springframework/boot/context/config/ConfigDataEnvironmentContributor$ImportPhase;)Ljava/util/List;
      68: invokeinterface #241,  1          // InterfaceMethod java/util/List.stream:()Ljava/util/stream/Stream;
      73: invokedynamic #244,  0            // InvokeDynamic #0:test:()Ljava/util/function/Predicate;
      78: invokeinterface #248,  2          // InterfaceMethod java/util/stream/Stream.anyMatch:(Ljava/util/function/Predicate;)Z
      83: ifeq          88
      86: iconst_1
      87: ireturn
      88: iinc          6, 1
      91: goto          48
      94: goto          16
      97: iconst_0
      98: ireturn

  org.springframework.boot.context.config.ConfigDataEnvironmentContributor withReplacement(org.springframework.boot.context.config.ConfigDataEnvironmentContributor, org.springframework.boot.context.config.ConfigDataEnvironmentContributor);
    Code:
       0: aload_0
       1: aload_1
       2: if_acmpne     7
       5: aload_2
       6: areturn
       7: new           #152                // class java/util/LinkedHashMap
      10: dup
      11: aload_0
      12: getfield      #52                 // Field children:Ljava/util/Map;
      15: invokeinterface #254,  1          // InterfaceMethod java/util/Map.size:()I
      20: invokespecial #255                // Method java/util/LinkedHashMap."<init>":(I)V
      23: astore_3
      24: aload_0
      25: getfield      #52                 // Field children:Ljava/util/Map;
      28: aload_1
      29: aload_2
      30: aload_3
      31: invokedynamic #256,  0            // InvokeDynamic #1:accept:(Lorg/springframework/boot/context/config/ConfigDataEnvironmentContributor;Lorg/springframework/boot/context/config/ConfigDataEnvironmentContributor;Ljava/util/Map;)Ljava/util/function/BiConsumer;
      36: invokeinterface #260,  2          // InterfaceMethod java/util/Map.forEach:(Ljava/util/function/BiConsumer;)V
      41: new           #8                  // class org/springframework/boot/context/config/ConfigDataEnvironmentContributor
      44: dup
      45: aload_0
      46: getfield      #7                  // Field kind:Lorg/springframework/boot/context/config/ConfigDataEnvironmentContributor$Kind;
      49: aload_0
      50: getfield      #13                 // Field location:Lorg/springframework/boot/context/config/ConfigDataLocation;
      53: aload_0
      54: getfield      #17                 // Field resource:Lorg/springframework/boot/context/config/ConfigDataResource;
      57: aload_0
      58: getfield      #21                 // Field fromProfileSpecificImport:Z
      61: aload_0
      62: getfield      #29                 // Field propertySource:Lorg/springframework/core/env/PropertySource;
      65: aload_0
      66: getfield      #33                 // Field configurationPropertySource:Lorg/springframework/boot/context/properties/source/ConfigurationPropertySource;
      69: aload_0
      70: getfield      #25                 // Field properties:Lorg/springframework/boot/context/config/ConfigDataProperties;
      73: aload_0
      74: getfield      #43                 // Field configDataOptions:Lorg/springframework/boot/context/config/ConfigData$Options;
      77: aload_3
      78: invokespecial #75                 // Method "<init>":(Lorg/springframework/boot/context/config/ConfigDataEnvironmentContributor$Kind;Lorg/springframework/boot/context/config/ConfigDataLocation;Lorg/springframework/boot/context/config/ConfigDataResource;ZLorg/springframework/core/env/PropertySource;Lorg/springframework/boot/context/properties/source/ConfigurationPropertySource;Lorg/springframework/boot/context/config/ConfigDataProperties;Lorg/springframework/boot/context/config/ConfigData$Options;Ljava/util/Map;)V
      81: areturn

  public java.lang.String toString();
    Code:
       0: new           #264                // class java/lang/StringBuilder
       3: dup
       4: invokespecial #266                // Method java/lang/StringBuilder."<init>":()V
       7: astore_1
       8: aload_0
       9: ldc_w         #267                // String
      12: aload_1
      13: invokevirtual #269                // Method buildToString:(Ljava/lang/String;Ljava/lang/StringBuilder;)V
      16: aload_1
      17: invokevirtual #273                // Method java/lang/StringBuilder.toString:()Ljava/lang/String;
      20: areturn

  private void buildToString(java.lang.String, java.lang.StringBuilder);
    Code:
       0: aload_2
       1: aload_1
       2: invokevirtual #277                // Method java/lang/StringBuilder.append:(Ljava/lang/String;)Ljava/lang/StringBuilder;
       5: pop
       6: aload_2
       7: aload_0
       8: getfield      #7                  // Field kind:Lorg/springframework/boot/context/config/ConfigDataEnvironmentContributor$Kind;
      11: invokevirtual #281                // Method java/lang/StringBuilder.append:(Ljava/lang/Object;)Ljava/lang/StringBuilder;
      14: pop
      15: aload_2
      16: ldc_w         #284                // String
      19: invokevirtual #277                // Method java/lang/StringBuilder.append:(Ljava/lang/String;)Ljava/lang/StringBuilder;
      22: pop
      23: aload_2
      24: aload_0
      25: getfield      #13                 // Field location:Lorg/springframework/boot/context/config/ConfigDataLocation;
      28: invokevirtual #281                // Method java/lang/StringBuilder.append:(Ljava/lang/Object;)Ljava/lang/StringBuilder;
      31: pop
      32: aload_2
      33: ldc_w         #284                // String
      36: invokevirtual #277                // Method java/lang/StringBuilder.append:(Ljava/lang/String;)Ljava/lang/StringBuilder;
      39: pop
      40: aload_2
      41: aload_0
      42: getfield      #17                 // Field resource:Lorg/springframework/boot/context/config/ConfigDataResource;
      45: invokevirtual #281                // Method java/lang/StringBuilder.append:(Ljava/lang/Object;)Ljava/lang/StringBuilder;
      48: pop
      49: aload_2
      50: ldc_w         #284                // String
      53: invokevirtual #277                // Method java/lang/StringBuilder.append:(Ljava/lang/String;)Ljava/lang/StringBuilder;
      56: pop
      57: aload_2
      58: aload_0
      59: getfield      #43                 // Field configDataOptions:Lorg/springframework/boot/context/config/ConfigData$Options;
      62: invokevirtual #281                // Method java/lang/StringBuilder.append:(Ljava/lang/Object;)Ljava/lang/StringBuilder;
      65: pop
      66: aload_2
      67: ldc_w         #286                // String \n
      70: invokevirtual #277                // Method java/lang/StringBuilder.append:(Ljava/lang/String;)Ljava/lang/StringBuilder;
      73: pop
      74: aload_0
      75: getfield      #52                 // Field children:Ljava/util/Map;
      78: getstatic     #169                // Field org/springframework/boot/context/config/ConfigDataEnvironmentContributor$ImportPhase.BEFORE_PROFILE_ACTIVATION:Lorg/springframework/boot/context/config/ConfigDataEnvironmentContributor$ImportPhase;
      81: invokestatic  #82                 // Method java/util/Collections.emptyList:()Ljava/util/List;
      84: invokeinterface #98,  3           // InterfaceMethod java/util/Map.getOrDefault:(Ljava/lang/Object;Ljava/lang/Object;)Ljava/lang/Object;
      89: checkcast     #87                 // class java/util/List
      92: invokeinterface #189,  1          // InterfaceMethod java/util/List.iterator:()Ljava/util/Iterator;
      97: astore_3
      98: aload_3
      99: invokeinterface #193,  1          // InterfaceMethod java/util/Iterator.hasNext:()Z
     104: ifeq          133
     107: aload_3
     108: invokeinterface #198,  1          // InterfaceMethod java/util/Iterator.next:()Ljava/lang/Object;
     113: checkcast     #8                  // class org/springframework/boot/context/config/ConfigDataEnvironmentContributor
     116: astore        4
     118: aload         4
     120: aload_1
     121: invokedynamic #288,  0            // InvokeDynamic #2:makeConcatWithConstants:(Ljava/lang/String;)Ljava/lang/String;
     126: aload_2
     127: invokevirtual #269                // Method buildToString:(Ljava/lang/String;Ljava/lang/StringBuilder;)V
     130: goto          98
     133: aload_0
     134: getfield      #52                 // Field children:Ljava/util/Map;
     137: getstatic     #160                // Field org/springframework/boot/context/config/ConfigDataEnvironmentContributor$ImportPhase.AFTER_PROFILE_ACTIVATION:Lorg/springframework/boot/context/config/ConfigDataEnvironmentContributor$ImportPhase;
     140: invokestatic  #82                 // Method java/util/Collections.emptyList:()Ljava/util/List;
     143: invokeinterface #98,  3           // InterfaceMethod java/util/Map.getOrDefault:(Ljava/lang/Object;Ljava/lang/Object;)Ljava/lang/Object;
     148: checkcast     #87                 // class java/util/List
     151: invokeinterface #189,  1          // InterfaceMethod java/util/List.iterator:()Ljava/util/Iterator;
     156: astore_3
     157: aload_3
     158: invokeinterface #193,  1          // InterfaceMethod java/util/Iterator.hasNext:()Z
     163: ifeq          192
     166: aload_3
     167: invokeinterface #198,  1          // InterfaceMethod java/util/Iterator.next:()Ljava/lang/Object;
     172: checkcast     #8                  // class org/springframework/boot/context/config/ConfigDataEnvironmentContributor
     175: astore        4
     177: aload         4
     179: aload_1
     180: invokedynamic #288,  0            // InvokeDynamic #2:makeConcatWithConstants:(Ljava/lang/String;)Ljava/lang/String;
     185: aload_2
     186: invokevirtual #269                // Method buildToString:(Ljava/lang/String;Ljava/lang/StringBuilder;)V
     189: goto          157
     192: return

  static org.springframework.boot.context.config.ConfigDataEnvironmentContributor of(java.util.List<org.springframework.boot.context.config.ConfigDataEnvironmentContributor>);
    Code:
       0: new           #152                // class java/util/LinkedHashMap
       3: dup
       4: invokespecial #292                // Method java/util/LinkedHashMap."<init>":()V
       7: astore_1
       8: aload_1
       9: getstatic     #169                // Field org/springframework/boot/context/config/ConfigDataEnvironmentContributor$ImportPhase.BEFORE_PROFILE_ACTIVATION:Lorg/springframework/boot/context/config/ConfigDataEnvironmentContributor$ImportPhase;
      12: aload_0
      13: invokestatic  #293                // Method java/util/Collections.unmodifiableList:(Ljava/util/List;)Ljava/util/List;
      16: invokeinterface #157,  3          // InterfaceMethod java/util/Map.put:(Ljava/lang/Object;Ljava/lang/Object;)Ljava/lang/Object;
      21: pop
      22: new           #8                  // class org/springframework/boot/context/config/ConfigDataEnvironmentContributor
      25: dup
      26: getstatic     #297                // Field org/springframework/boot/context/config/ConfigDataEnvironmentContributor$Kind.ROOT:Lorg/springframework/boot/context/config/ConfigDataEnvironmentContributor$Kind;
      29: aconst_null
      30: aconst_null
      31: iconst_0
      32: aconst_null
      33: aconst_null
      34: aconst_null
      35: aconst_null
      36: aload_1
      37: invokespecial #75                 // Method "<init>":(Lorg/springframework/boot/context/config/ConfigDataEnvironmentContributor$Kind;Lorg/springframework/boot/context/config/ConfigDataLocation;Lorg/springframework/boot/context/config/ConfigDataResource;ZLorg/springframework/core/env/PropertySource;Lorg/springframework/boot/context/properties/source/ConfigurationPropertySource;Lorg/springframework/boot/context/config/ConfigDataProperties;Lorg/springframework/boot/context/config/ConfigData$Options;Ljava/util/Map;)V
      40: areturn

  static org.springframework.boot.context.config.ConfigDataEnvironmentContributor ofInitialImport(org.springframework.boot.context.config.ConfigDataLocation);
    Code:
       0: aload_0
       1: invokestatic  #300                // Method java/util/Collections.singletonList:(Ljava/lang/Object;)Ljava/util/List;
       4: astore_1
       5: new           #62                 // class org/springframework/boot/context/config/ConfigDataProperties
       8: dup
       9: aload_1
      10: aconst_null
      11: invokespecial #304                // Method org/springframework/boot/context/config/ConfigDataProperties."<init>":(Ljava/util/List;Lorg/springframework/boot/context/config/ConfigDataProperties$Activate;)V
      14: astore_2
      15: new           #8                  // class org/springframework/boot/context/config/ConfigDataEnvironmentContributor
      18: dup
      19: getstatic     #307                // Field org/springframework/boot/context/config/ConfigDataEnvironmentContributor$Kind.INITIAL_IMPORT:Lorg/springframework/boot/context/config/ConfigDataEnvironmentContributor$Kind;
      22: aconst_null
      23: aconst_null
      24: iconst_0
      25: aconst_null
      26: aconst_null
      27: aload_2
      28: aconst_null
      29: aconst_null
      30: invokespecial #75                 // Method "<init>":(Lorg/springframework/boot/context/config/ConfigDataEnvironmentContributor$Kind;Lorg/springframework/boot/context/config/ConfigDataLocation;Lorg/springframework/boot/context/config/ConfigDataResource;ZLorg/springframework/core/env/PropertySource;Lorg/springframework/boot/context/properties/source/ConfigurationPropertySource;Lorg/springframework/boot/context/config/ConfigDataProperties;Lorg/springframework/boot/context/config/ConfigData$Options;Ljava/util/Map;)V
      33: areturn

  static org.springframework.boot.context.config.ConfigDataEnvironmentContributor ofExisting(org.springframework.core.env.PropertySource<?>);
    Code:
       0: new           #8                  // class org/springframework/boot/context/config/ConfigDataEnvironmentContributor
       3: dup
       4: getstatic     #310                // Field org/springframework/boot/context/config/ConfigDataEnvironmentContributor$Kind.EXISTING:Lorg/springframework/boot/context/config/ConfigDataEnvironmentContributor$Kind;
       7: aconst_null
       8: aconst_null
       9: iconst_0
      10: aload_0
      11: aload_0
      12: invokestatic  #313                // InterfaceMethod org/springframework/boot/context/properties/source/ConfigurationPropertySource.from:(Lorg/springframework/core/env/PropertySource;)Lorg/springframework/boot/context/properties/source/ConfigurationPropertySource;
      15: aconst_null
      16: aconst_null
      17: aconst_null
      18: invokespecial #75                 // Method "<init>":(Lorg/springframework/boot/context/config/ConfigDataEnvironmentContributor$Kind;Lorg/springframework/boot/context/config/ConfigDataLocation;Lorg/springframework/boot/context/config/ConfigDataResource;ZLorg/springframework/core/env/PropertySource;Lorg/springframework/boot/context/properties/source/ConfigurationPropertySource;Lorg/springframework/boot/context/config/ConfigDataProperties;Lorg/springframework/boot/context/config/ConfigData$Options;Ljava/util/Map;)V
      21: areturn

  static org.springframework.boot.context.config.ConfigDataEnvironmentContributor ofUnboundImport(org.springframework.boot.context.config.ConfigDataLocation, org.springframework.boot.context.config.ConfigDataResource, boolean, org.springframework.boot.context.config.ConfigData, int);
    Code:
       0: aload_3
       1: invokevirtual #319                // Method org/springframework/boot/context/config/ConfigData.getPropertySources:()Ljava/util/List;
       4: iload         4
       6: invokeinterface #324,  2          // InterfaceMethod java/util/List.get:(I)Ljava/lang/Object;
      11: checkcast     #327                // class org/springframework/core/env/PropertySource
      14: astore        5
      16: aload_3
      17: aload         5
      19: invokevirtual #329                // Method org/springframework/boot/context/config/ConfigData.getOptions:(Lorg/springframework/core/env/PropertySource;)Lorg/springframework/boot/context/config/ConfigData$Options;
      22: astore        6
      24: aload         5
      26: invokestatic  #313                // InterfaceMethod org/springframework/boot/context/properties/source/ConfigurationPropertySource.from:(Lorg/springframework/core/env/PropertySource;)Lorg/springframework/boot/context/properties/source/ConfigurationPropertySource;
      29: astore        7
      31: new           #8                  // class org/springframework/boot/context/config/ConfigDataEnvironmentContributor
      34: dup
      35: getstatic     #56                 // Field org/springframework/boot/context/config/ConfigDataEnvironmentContributor$Kind.UNBOUND_IMPORT:Lorg/springframework/boot/context/config/ConfigDataEnvironmentContributor$Kind;
      38: aload_0
      39: aload_1
      40: iload_2
      41: aload         5
      43: aload         7
      45: aconst_null
      46: aload         6
      48: aconst_null
      49: invokespecial #75                 // Method "<init>":(Lorg/springframework/boot/context/config/ConfigDataEnvironmentContributor$Kind;Lorg/springframework/boot/context/config/ConfigDataLocation;Lorg/springframework/boot/context/config/ConfigDataResource;ZLorg/springframework/core/env/PropertySource;Lorg/springframework/boot/context/properties/source/ConfigurationPropertySource;Lorg/springframework/boot/context/config/ConfigDataProperties;Lorg/springframework/boot/context/config/ConfigData$Options;Ljava/util/Map;)V
      52: areturn

  static org.springframework.boot.context.config.ConfigDataEnvironmentContributor ofEmptyLocation(org.springframework.boot.context.config.ConfigDataLocation, boolean);
    Code:
       0: new           #8                  // class org/springframework/boot/context/config/ConfigDataEnvironmentContributor
       3: dup
       4: getstatic     #333                // Field org/springframework/boot/context/config/ConfigDataEnvironmentContributor$Kind.EMPTY_LOCATION:Lorg/springframework/boot/context/config/ConfigDataEnvironmentContributor$Kind;
       7: aload_0
       8: aconst_null
       9: iload_1
      10: aconst_null
      11: aconst_null
      12: aconst_null
      13: getstatic     #336                // Field EMPTY_LOCATION_OPTIONS:Lorg/springframework/boot/context/config/ConfigData$Options;
      16: aconst_null
      17: invokespecial #75                 // Method "<init>":(Lorg/springframework/boot/context/config/ConfigDataEnvironmentContributor$Kind;Lorg/springframework/boot/context/config/ConfigDataLocation;Lorg/springframework/boot/context/config/ConfigDataResource;ZLorg/springframework/core/env/PropertySource;Lorg/springframework/boot/context/properties/source/ConfigurationPropertySource;Lorg/springframework/boot/context/config/ConfigDataProperties;Lorg/springframework/boot/context/config/ConfigData$Options;Ljava/util/Map;)V
      20: areturn

  private static void lambda$withReplacement$1(org.springframework.boot.context.config.ConfigDataEnvironmentContributor, org.springframework.boot.context.config.ConfigDataEnvironmentContributor, java.util.Map, org.springframework.boot.context.config.ConfigDataEnvironmentContributor$ImportPhase, java.util.List);
    Code:
       0: new           #179                // class java/util/ArrayList
       3: dup
       4: aload         4
       6: invokeinterface #181,  1          // InterfaceMethod java/util/List.size:()I
      11: invokespecial #185                // Method java/util/ArrayList."<init>":(I)V
      14: astore        5
      16: aload         4
      18: invokeinterface #189,  1          // InterfaceMethod java/util/List.iterator:()Ljava/util/Iterator;
      23: astore        6
      25: aload         6
      27: invokeinterface #193,  1          // InterfaceMethod java/util/Iterator.hasNext:()Z
      32: ifeq          65
      35: aload         6
      37: invokeinterface #198,  1          // InterfaceMethod java/util/Iterator.next:()Ljava/lang/Object;
      42: checkcast     #8                  // class org/springframework/boot/context/config/ConfigDataEnvironmentContributor
      45: astore        7
      47: aload         5
      49: aload         7
      51: aload_0
      52: aload_1
      53: invokevirtual #339                // Method withReplacement:(Lorg/springframework/boot/context/config/ConfigDataEnvironmentContributor;Lorg/springframework/boot/context/config/ConfigDataEnvironmentContributor;)Lorg/springframework/boot/context/config/ConfigDataEnvironmentContributor;
      56: invokeinterface #206,  2          // InterfaceMethod java/util/List.add:(Ljava/lang/Object;)Z
      61: pop
      62: goto          25
      65: aload_2
      66: aload_3
      67: aload         5
      69: invokestatic  #293                // Method java/util/Collections.unmodifiableList:(Ljava/util/List;)Ljava/util/List;
      72: invokeinterface #157,  3          // InterfaceMethod java/util/Map.put:(Ljava/lang/Object;Ljava/lang/Object;)Ljava/lang/Object;
      77: pop
      78: return

  private static boolean lambda$hasAnyProfileSpecificChildren$0(org.springframework.boot.context.config.ConfigDataEnvironmentContributor);
    Code:
       0: aload_0
       1: getstatic     #223                // Field org/springframework/boot/context/config/ConfigData$Option.PROFILE_SPECIFIC:Lorg/springframework/boot/context/config/ConfigData$Option;
       4: invokevirtual #226                // Method hasConfigDataOption:(Lorg/springframework/boot/context/config/ConfigData$Option;)Z
       7: ireturn

  static {};
    Code:
       0: iconst_1
       1: anewarray     #140                // class org/springframework/boot/context/config/ConfigData$Option
       4: dup
       5: iconst_0
       6: getstatic     #139                // Field org/springframework/boot/context/config/ConfigData$Option.IGNORE_IMPORTS:Lorg/springframework/boot/context/config/ConfigData$Option;
       9: aastore
      10: invokestatic  #343                // Method org/springframework/boot/context/config/ConfigData$Options.of:([Lorg/springframework/boot/context/config/ConfigData$Option;)Lorg/springframework/boot/context/config/ConfigData$Options;
      13: putstatic     #336                // Field EMPTY_LOCATION_OPTIONS:Lorg/springframework/boot/context/config/ConfigData$Options;
      16: return
}
