Compiled from "ConfigDataLocationBindHandler.java"
class org.springframework.boot.context.config.ConfigDataLocationBindHandler extends org.springframework.boot.context.properties.bind.AbstractBindHandler {
  org.springframework.boot.context.config.ConfigDataLocationBindHandler();
    Code:
       0: aload_0
       1: invokespecial #1                  // Method org/springframework/boot/context/properties/bind/AbstractBindHandler."<init>":()V
       4: return

  public java.lang.Object onSuccess(org.springframework.boot.context.properties.source.ConfigurationPropertyName, org.springframework.boot.context.properties.bind.Bindable<?>, org.springframework.boot.context.properties.bind.BindContext, java.lang.Object);
    Code:
       0: aload         4
       2: instanceof    #7                  // class org/springframework/boot/context/config/ConfigDataLocation
       5: ifeq          23
       8: aload         4
      10: checkcast     #7                  // class org/springframework/boot/context/config/ConfigDataLocation
      13: astore        5
      15: aload_0
      16: aload_3
      17: aload         5
      19: invokevirtual #9                  // Method withOrigin:(Lorg/springframework/boot/context/properties/bind/BindContext;Lorg/springframework/boot/context/config/ConfigDataLocation;)Lorg/springframework/boot/context/config/ConfigDataLocation;
      22: areturn
      23: aload         4
      25: instanceof    #15                 // class java/util/List
      28: ifeq          136
      31: aload         4
      33: checkcast     #15                 // class java/util/List
      36: invokeinterface #17,  1           // InterfaceMethod java/util/List.stream:()Ljava/util/stream/Stream;
      41: invokedynamic #21,  0             // InvokeDynamic #0:test:()Ljava/util/function/Predicate;
      46: invokeinterface #25,  2           // InterfaceMethod java/util/stream/Stream.filter:(Ljava/util/function/Predicate;)Ljava/util/stream/Stream;
      51: invokedynamic #31,  0             // InvokeDynamic #1:get:()Ljava/util/function/Supplier;
      56: invokestatic  #35                 // Method java/util/stream/Collectors.toCollection:(Ljava/util/function/Supplier;)Ljava/util/stream/Collector;
      59: invokeinterface #41,  2           // InterfaceMethod java/util/stream/Stream.collect:(Ljava/util/stream/Collector;)Ljava/lang/Object;
      64: checkcast     #15                 // class java/util/List
      67: astore        5
      69: iconst_0
      70: istore        6
      72: iload         6
      74: aload         5
      76: invokeinterface #45,  1           // InterfaceMethod java/util/List.size:()I
      81: if_icmpge     133
      84: aload         5
      86: iload         6
      88: invokeinterface #49,  2           // InterfaceMethod java/util/List.get:(I)Ljava/lang/Object;
      93: astore        7
      95: aload         7
      97: instanceof    #7                  // class org/springframework/boot/context/config/ConfigDataLocation
     100: ifeq          127
     103: aload         7
     105: checkcast     #7                  // class org/springframework/boot/context/config/ConfigDataLocation
     108: astore        8
     110: aload         5
     112: iload         6
     114: aload_0
     115: aload_3
     116: aload         8
     118: invokevirtual #9                  // Method withOrigin:(Lorg/springframework/boot/context/properties/bind/BindContext;Lorg/springframework/boot/context/config/ConfigDataLocation;)Lorg/springframework/boot/context/config/ConfigDataLocation;
     121: invokeinterface #52,  3           // InterfaceMethod java/util/List.set:(ILjava/lang/Object;)Ljava/lang/Object;
     126: pop
     127: iinc          6, 1
     130: goto          72
     133: aload         5
     135: areturn
     136: aload         4
     138: instanceof    #56                 // class "[Lorg/springframework/boot/context/config/ConfigDataLocation;"
     141: ifeq          216
     144: aload         4
     146: checkcast     #56                 // class "[Lorg/springframework/boot/context/config/ConfigDataLocation;"
     149: astore        5
     151: aload         5
     153: invokestatic  #58                 // Method java/util/Arrays.stream:([Ljava/lang/Object;)Ljava/util/stream/Stream;
     156: invokedynamic #63,  0             // InvokeDynamic #2:test:()Ljava/util/function/Predicate;
     161: invokeinterface #25,  2           // InterfaceMethod java/util/stream/Stream.filter:(Ljava/util/function/Predicate;)Ljava/util/stream/Stream;
     166: invokedynamic #64,  0             // InvokeDynamic #3:apply:()Ljava/util/function/IntFunction;
     171: invokeinterface #68,  2           // InterfaceMethod java/util/stream/Stream.toArray:(Ljava/util/function/IntFunction;)[Ljava/lang/Object;
     176: checkcast     #56                 // class "[Lorg/springframework/boot/context/config/ConfigDataLocation;"
     179: astore        6
     181: iconst_0
     182: istore        7
     184: iload         7
     186: aload         6
     188: arraylength
     189: if_icmpge     213
     192: aload         6
     194: iload         7
     196: aload_0
     197: aload_3
     198: aload         6
     200: iload         7
     202: aaload
     203: invokevirtual #9                  // Method withOrigin:(Lorg/springframework/boot/context/properties/bind/BindContext;Lorg/springframework/boot/context/config/ConfigDataLocation;)Lorg/springframework/boot/context/config/ConfigDataLocation;
     206: aastore
     207: iinc          7, 1
     210: goto          184
     213: aload         6
     215: areturn
     216: aload         4
     218: areturn

  private org.springframework.boot.context.config.ConfigDataLocation withOrigin(org.springframework.boot.context.properties.bind.BindContext, org.springframework.boot.context.config.ConfigDataLocation);
    Code:
       0: aload_2
       1: invokevirtual #72                 // Method org/springframework/boot/context/config/ConfigDataLocation.getOrigin:()Lorg/springframework/boot/origin/Origin;
       4: ifnull        9
       7: aload_2
       8: areturn
       9: aload_1
      10: invokeinterface #76,  1           // InterfaceMethod org/springframework/boot/context/properties/bind/BindContext.getConfigurationProperty:()Lorg/springframework/boot/context/properties/source/ConfigurationProperty;
      15: invokestatic  #82                 // InterfaceMethod org/springframework/boot/origin/Origin.from:(Ljava/lang/Object;)Lorg/springframework/boot/origin/Origin;
      18: astore_3
      19: aload_2
      20: aload_3
      21: invokevirtual #88                 // Method org/springframework/boot/context/config/ConfigDataLocation.withOrigin:(Lorg/springframework/boot/origin/Origin;)Lorg/springframework/boot/context/config/ConfigDataLocation;
      24: areturn

  private static org.springframework.boot.context.config.ConfigDataLocation[] lambda$onSuccess$0(int);
    Code:
       0: iload_0
       1: anewarray     #7                  // class org/springframework/boot/context/config/ConfigDataLocation
       4: areturn
}
