Compiled from "ConfigData.java"
public interface org.springframework.boot.context.config.ConfigData$PropertySourceOptions {
  public static final org.springframework.boot.context.config.ConfigData$PropertySourceOptions ALWAYS_NONE;

  public abstract org.springframework.boot.context.config.ConfigData$Options get(org.springframework.core.env.PropertySource<?>);

  public static org.springframework.boot.context.config.ConfigData$PropertySourceOptions always(org.springframework.boot.context.config.ConfigData$Option...);
    Code:
       0: aload_0
       1: invokestatic  #1                  // Method org/springframework/boot/context/config/ConfigData$Options.of:([Lorg/springframework/boot/context/config/ConfigData$Option;)Lorg/springframework/boot/context/config/ConfigData$Options;
       4: invokestatic  #7                  // InterfaceMethod always:(Lorg/springframework/boot/context/config/ConfigData$Options;)Lorg/springframework/boot/context/config/ConfigData$PropertySourceOptions;
       7: areturn

  public static org.springframework.boot.context.config.ConfigData$PropertySourceOptions always(org.springframework.boot.context.config.ConfigData$Options);
    Code:
       0: aload_0
       1: getstatic     #13                 // Field org/springframework/boot/context/config/ConfigData$Options.NONE:Lorg/springframework/boot/context/config/ConfigData$Options;
       4: if_acmpne     11
       7: getstatic     #17                 // Field ALWAYS_NONE:Lorg/springframework/boot/context/config/ConfigData$PropertySourceOptions;
      10: areturn
      11: new           #21                 // class org/springframework/boot/context/config/ConfigData$AlwaysPropertySourceOptions
      14: dup
      15: aload_0
      16: invokespecial #23                 // Method org/springframework/boot/context/config/ConfigData$AlwaysPropertySourceOptions."<init>":(Lorg/springframework/boot/context/config/ConfigData$Options;)V
      19: areturn

  static {};
    Code:
       0: new           #21                 // class org/springframework/boot/context/config/ConfigData$AlwaysPropertySourceOptions
       3: dup
       4: getstatic     #13                 // Field org/springframework/boot/context/config/ConfigData$Options.NONE:Lorg/springframework/boot/context/config/ConfigData$Options;
       7: invokespecial #23                 // Method org/springframework/boot/context/config/ConfigData$AlwaysPropertySourceOptions."<init>":(Lorg/springframework/boot/context/config/ConfigData$Options;)V
      10: putstatic     #17                 // Field ALWAYS_NONE:Lorg/springframework/boot/context/config/ConfigData$PropertySourceOptions;
      13: return
}
