Compiled from "ConfigDataLocationNotFoundException.java"
public class org.springframework.boot.context.config.ConfigDataLocationNotFoundException extends org.springframework.boot.context.config.ConfigDataNotFoundException {
  private final org.springframework.boot.context.config.ConfigDataLocation location;

  public org.springframework.boot.context.config.ConfigDataLocationNotFoundException(org.springframework.boot.context.config.ConfigDataLocation);
    Code:
       0: aload_0
       1: aload_1
       2: aconst_null
       3: invokespecial #1                  // Method "<init>":(Lorg/springframework/boot/context/config/ConfigDataLocation;Ljava/lang/Throwable;)V
       6: return

  public org.springframework.boot.context.config.ConfigDataLocationNotFoundException(org.springframework.boot.context.config.ConfigDataLocation, java.lang.Throwable);
    Code:
       0: aload_0
       1: aload_1
       2: aload_1
       3: invokestatic  #7                  // Method getMessage:(Lorg/springframework/boot/context/config/ConfigDataLocation;)Ljava/lang/String;
       6: aload_2
       7: invokespecial #11                 // Method "<init>":(Lorg/springframework/boot/context/config/ConfigDataLocation;Ljava/lang/String;Ljava/lang/Throwable;)V
      10: return

  public org.springframework.boot.context.config.ConfigDataLocationNotFoundException(org.springframework.boot.context.config.ConfigDataLocation, java.lang.String, java.lang.Throwable);
    Code:
       0: aload_0
       1: aload_2
       2: aload_3
       3: invokespecial #14                 // Method org/springframework/boot/context/config/ConfigDataNotFoundException."<init>":(Ljava/lang/String;Ljava/lang/Throwable;)V
       6: aload_1
       7: ldc           #19                 // String Location must not be null
       9: invokestatic  #21                 // Method org/springframework/util/Assert.notNull:(Ljava/lang/Object;Ljava/lang/String;)V
      12: aload_0
      13: aload_1
      14: putfield      #27                 // Field location:Lorg/springframework/boot/context/config/ConfigDataLocation;
      17: return

  public org.springframework.boot.context.config.ConfigDataLocation getLocation();
    Code:
       0: aload_0
       1: getfield      #27                 // Field location:Lorg/springframework/boot/context/config/ConfigDataLocation;
       4: areturn

  public org.springframework.boot.origin.Origin getOrigin();
    Code:
       0: aload_0
       1: getfield      #27                 // Field location:Lorg/springframework/boot/context/config/ConfigDataLocation;
       4: invokestatic  #31                 // InterfaceMethod org/springframework/boot/origin/Origin.from:(Ljava/lang/Object;)Lorg/springframework/boot/origin/Origin;
       7: areturn

  public java.lang.String getReferenceDescription();
    Code:
       0: aload_0
       1: getfield      #27                 // Field location:Lorg/springframework/boot/context/config/ConfigDataLocation;
       4: invokestatic  #37                 // Method getReferenceDescription:(Lorg/springframework/boot/context/config/ConfigDataLocation;)Ljava/lang/String;
       7: areturn

  private static java.lang.String getMessage(org.springframework.boot.context.config.ConfigDataLocation);
    Code:
       0: ldc           #40                 // String Config data %s cannot be found
       2: iconst_1
       3: anewarray     #42                 // class java/lang/Object
       6: dup
       7: iconst_0
       8: aload_0
       9: invokestatic  #37                 // Method getReferenceDescription:(Lorg/springframework/boot/context/config/ConfigDataLocation;)Ljava/lang/String;
      12: aastore
      13: invokestatic  #44                 // Method java/lang/String.format:(Ljava/lang/String;[Ljava/lang/Object;)Ljava/lang/String;
      16: areturn

  private static java.lang.String getReferenceDescription(org.springframework.boot.context.config.ConfigDataLocation);
    Code:
       0: ldc           #50                 // String location \'%s\'
       2: iconst_1
       3: anewarray     #42                 // class java/lang/Object
       6: dup
       7: iconst_0
       8: aload_0
       9: aastore
      10: invokestatic  #44                 // Method java/lang/String.format:(Ljava/lang/String;[Ljava/lang/Object;)Ljava/lang/String;
      13: areturn
}
