Compiled from "ConfigDataResource.java"
public abstract class org.springframework.boot.context.config.ConfigDataResource {
  private final boolean optional;

  public org.springframework.boot.context.config.ConfigDataResource();
    Code:
       0: aload_0
       1: iconst_0
       2: invokespecial #1                  // Method "<init>":(Z)V
       5: return

  protected org.springframework.boot.context.config.ConfigDataResource(boolean);
    Code:
       0: aload_0
       1: invokespecial #7                  // Method java/lang/Object."<init>":()V
       4: aload_0
       5: iload_1
       6: putfield      #12                 // Field optional:Z
       9: return

  boolean isOptional();
    Code:
       0: aload_0
       1: getfield      #12                 // Field optional:Z
       4: ireturn
}
