Compiled from "ConfigDataResourceNotFoundException.java"
public class org.springframework.boot.context.config.ConfigDataResourceNotFoundException extends org.springframework.boot.context.config.ConfigDataNotFoundException {
  private final org.springframework.boot.context.config.ConfigDataResource resource;

  private final org.springframework.boot.context.config.ConfigDataLocation location;

  public org.springframework.boot.context.config.ConfigDataResourceNotFoundException(org.springframework.boot.context.config.ConfigDataResource);
    Code:
       0: aload_0
       1: aload_1
       2: aconst_null
       3: invokespecial #1                  // Method "<init>":(Lorg/springframework/boot/context/config/ConfigDataResource;Ljava/lang/Throwable;)V
       6: return

  public org.springframework.boot.context.config.ConfigDataResourceNotFoundException(org.springframework.boot.context.config.ConfigDataResource, java.lang.Throwable);
    Code:
       0: aload_0
       1: aload_1
       2: aconst_null
       3: aload_2
       4: invokespecial #7                  // Method "<init>":(Lorg/springframework/boot/context/config/ConfigDataResource;Lorg/springframework/boot/context/config/ConfigDataLocation;Ljava/lang/Throwable;)V
       7: return

  private org.springframework.boot.context.config.ConfigDataResourceNotFoundException(org.springframework.boot.context.config.ConfigDataResource, org.springframework.boot.context.config.ConfigDataLocation, java.lang.Throwable);
    Code:
       0: aload_0
       1: aload_1
       2: aload_2
       3: invokestatic  #10                 // Method getMessage:(Lorg/springframework/boot/context/config/ConfigDataResource;Lorg/springframework/boot/context/config/ConfigDataLocation;)Ljava/lang/String;
       6: aload_3
       7: invokespecial #14                 // Method org/springframework/boot/context/config/ConfigDataNotFoundException."<init>":(Ljava/lang/String;Ljava/lang/Throwable;)V
      10: aload_1
      11: ldc           #19                 // String Resource must not be null
      13: invokestatic  #21                 // Method org/springframework/util/Assert.notNull:(Ljava/lang/Object;Ljava/lang/String;)V
      16: aload_0
      17: aload_1
      18: putfield      #27                 // Field resource:Lorg/springframework/boot/context/config/ConfigDataResource;
      21: aload_0
      22: aload_2
      23: putfield      #31                 // Field location:Lorg/springframework/boot/context/config/ConfigDataLocation;
      26: return

  public org.springframework.boot.context.config.ConfigDataResource getResource();
    Code:
       0: aload_0
       1: getfield      #27                 // Field resource:Lorg/springframework/boot/context/config/ConfigDataResource;
       4: areturn

  public org.springframework.boot.context.config.ConfigDataLocation getLocation();
    Code:
       0: aload_0
       1: getfield      #31                 // Field location:Lorg/springframework/boot/context/config/ConfigDataLocation;
       4: areturn

  public org.springframework.boot.origin.Origin getOrigin();
    Code:
       0: aload_0
       1: getfield      #31                 // Field location:Lorg/springframework/boot/context/config/ConfigDataLocation;
       4: invokestatic  #35                 // InterfaceMethod org/springframework/boot/origin/Origin.from:(Ljava/lang/Object;)Lorg/springframework/boot/origin/Origin;
       7: areturn

  public java.lang.String getReferenceDescription();
    Code:
       0: aload_0
       1: getfield      #27                 // Field resource:Lorg/springframework/boot/context/config/ConfigDataResource;
       4: aload_0
       5: getfield      #31                 // Field location:Lorg/springframework/boot/context/config/ConfigDataLocation;
       8: invokestatic  #41                 // Method getReferenceDescription:(Lorg/springframework/boot/context/config/ConfigDataResource;Lorg/springframework/boot/context/config/ConfigDataLocation;)Ljava/lang/String;
      11: areturn

  org.springframework.boot.context.config.ConfigDataResourceNotFoundException withLocation(org.springframework.boot.context.config.ConfigDataLocation);
    Code:
       0: new           #2                  // class org/springframework/boot/context/config/ConfigDataResourceNotFoundException
       3: dup
       4: aload_0
       5: getfield      #27                 // Field resource:Lorg/springframework/boot/context/config/ConfigDataResource;
       8: aload_1
       9: aload_0
      10: invokevirtual #44                 // Method getCause:()Ljava/lang/Throwable;
      13: invokespecial #7                  // Method "<init>":(Lorg/springframework/boot/context/config/ConfigDataResource;Lorg/springframework/boot/context/config/ConfigDataLocation;Ljava/lang/Throwable;)V
      16: areturn

  private static java.lang.String getMessage(org.springframework.boot.context.config.ConfigDataResource, org.springframework.boot.context.config.ConfigDataLocation);
    Code:
       0: ldc           #48                 // String Config data %s cannot be found
       2: iconst_1
       3: anewarray     #50                 // class java/lang/Object
       6: dup
       7: iconst_0
       8: aload_0
       9: aload_1
      10: invokestatic  #41                 // Method getReferenceDescription:(Lorg/springframework/boot/context/config/ConfigDataResource;Lorg/springframework/boot/context/config/ConfigDataLocation;)Ljava/lang/String;
      13: aastore
      14: invokestatic  #52                 // Method java/lang/String.format:(Ljava/lang/String;[Ljava/lang/Object;)Ljava/lang/String;
      17: areturn

  private static java.lang.String getReferenceDescription(org.springframework.boot.context.config.ConfigDataResource, org.springframework.boot.context.config.ConfigDataLocation);
    Code:
       0: ldc           #58                 // String resource \'%s\'
       2: iconst_1
       3: anewarray     #50                 // class java/lang/Object
       6: dup
       7: iconst_0
       8: aload_0
       9: aastore
      10: invokestatic  #52                 // Method java/lang/String.format:(Ljava/lang/String;[Ljava/lang/Object;)Ljava/lang/String;
      13: astore_2
      14: aload_1
      15: ifnull        38
      18: aload_2
      19: ldc           #60                 // String  via location \'%s\'
      21: iconst_1
      22: anewarray     #50                 // class java/lang/Object
      25: dup
      26: iconst_0
      27: aload_1
      28: aastore
      29: invokestatic  #52                 // Method java/lang/String.format:(Ljava/lang/String;[Ljava/lang/Object;)Ljava/lang/String;
      32: invokedynamic #62,  0             // InvokeDynamic #0:makeConcatWithConstants:(Ljava/lang/String;Ljava/lang/String;)Ljava/lang/String;
      37: astore_2
      38: aload_2
      39: areturn

  public static void throwIfDoesNotExist(org.springframework.boot.context.config.ConfigDataResource, java.nio.file.Path);
    Code:
       0: aload_0
       1: aload_1
       2: iconst_0
       3: anewarray     #66                 // class java/nio/file/LinkOption
       6: invokestatic  #68                 // Method java/nio/file/Files.exists:(Ljava/nio/file/Path;[Ljava/nio/file/LinkOption;)Z
       9: invokestatic  #74                 // Method throwIfDoesNotExist:(Lorg/springframework/boot/context/config/ConfigDataResource;Z)V
      12: return

  public static void throwIfDoesNotExist(org.springframework.boot.context.config.ConfigDataResource, java.io.File);
    Code:
       0: aload_0
       1: aload_1
       2: invokevirtual #78                 // Method java/io/File.exists:()Z
       5: invokestatic  #74                 // Method throwIfDoesNotExist:(Lorg/springframework/boot/context/config/ConfigDataResource;Z)V
       8: return

  public static void throwIfDoesNotExist(org.springframework.boot.context.config.ConfigDataResource, org.springframework.core.io.Resource);
    Code:
       0: aload_0
       1: aload_1
       2: invokeinterface #83,  1           // InterfaceMethod org/springframework/core/io/Resource.exists:()Z
       7: invokestatic  #74                 // Method throwIfDoesNotExist:(Lorg/springframework/boot/context/config/ConfigDataResource;Z)V
      10: return

  private static void throwIfDoesNotExist(org.springframework.boot.context.config.ConfigDataResource, boolean);
    Code:
       0: iload_1
       1: ifne          13
       4: new           #2                  // class org/springframework/boot/context/config/ConfigDataResourceNotFoundException
       7: dup
       8: aload_0
       9: invokespecial #86                 // Method "<init>":(Lorg/springframework/boot/context/config/ConfigDataResource;)V
      12: athrow
      13: return
}
