Compiled from "ConfigDataProperties.java"
class org.springframework.boot.context.config.ConfigDataProperties$Activate {
  private final org.springframework.boot.cloud.CloudPlatform onCloudPlatform;

  private final java.lang.String[] onProfile;

  org.springframework.boot.context.config.ConfigDataProperties$Activate(org.springframework.boot.cloud.CloudPlatform, java.lang.String[]);
    Code:
       0: aload_0
       1: invokespecial #1                  // Method java/lang/Object."<init>":()V
       4: aload_0
       5: aload_2
       6: putfield      #7                  // Field onProfile:[Ljava/lang/String;
       9: aload_0
      10: aload_1
      11: putfield      #13                 // Field onCloudPlatform:Lorg/springframework/boot/cloud/CloudPlatform;
      14: return

  boolean isActive(org.springframework.boot.context.config.ConfigDataActivationContext);
    Code:
       0: aload_1
       1: ifnonnull     6
       4: iconst_0
       5: ireturn
       6: iconst_1
       7: istore_2
       8: iload_2
       9: ifeq          27
      12: aload_0
      13: aload_1
      14: invokevirtual #17                 // Method org/springframework/boot/context/config/ConfigDataActivationContext.getCloudPlatform:()Lorg/springframework/boot/cloud/CloudPlatform;
      17: invokevirtual #23                 // Method isActive:(Lorg/springframework/boot/cloud/CloudPlatform;)Z
      20: ifeq          27
      23: iconst_1
      24: goto          28
      27: iconst_0
      28: istore_2
      29: iload_2
      30: ifeq          48
      33: aload_0
      34: aload_1
      35: invokevirtual #27                 // Method org/springframework/boot/context/config/ConfigDataActivationContext.getProfiles:()Lorg/springframework/boot/context/config/Profiles;
      38: invokevirtual #31                 // Method isActive:(Lorg/springframework/boot/context/config/Profiles;)Z
      41: ifeq          48
      44: iconst_1
      45: goto          49
      48: iconst_0
      49: istore_2
      50: iload_2
      51: ireturn

  private boolean isActive(org.springframework.boot.cloud.CloudPlatform);
    Code:
       0: aload_0
       1: getfield      #13                 // Field onCloudPlatform:Lorg/springframework/boot/cloud/CloudPlatform;
       4: ifnull        15
       7: aload_0
       8: getfield      #13                 // Field onCloudPlatform:Lorg/springframework/boot/cloud/CloudPlatform;
      11: aload_1
      12: if_acmpne     19
      15: iconst_1
      16: goto          20
      19: iconst_0
      20: ireturn

  private boolean isActive(org.springframework.boot.context.config.Profiles);
    Code:
       0: aload_0
       1: getfield      #7                  // Field onProfile:[Ljava/lang/String;
       4: invokestatic  #34                 // Method org/springframework/util/ObjectUtils.isEmpty:([Ljava/lang/Object;)Z
       7: ifne          32
      10: aload_1
      11: ifnull        36
      14: aload_0
      15: aload_1
      16: dup
      17: invokestatic  #40                 // Method java/util/Objects.requireNonNull:(Ljava/lang/Object;)Ljava/lang/Object;
      20: pop
      21: invokedynamic #46,  0             // InvokeDynamic #0:test:(Lorg/springframework/boot/context/config/Profiles;)Ljava/util/function/Predicate;
      26: invokevirtual #50                 // Method matchesActiveProfiles:(Ljava/util/function/Predicate;)Z
      29: ifeq          36
      32: iconst_1
      33: goto          37
      36: iconst_0
      37: ireturn

  private boolean matchesActiveProfiles(java.util.function.Predicate<java.lang.String>);
    Code:
       0: aload_0
       1: getfield      #7                  // Field onProfile:[Ljava/lang/String;
       4: invokestatic  #54                 // InterfaceMethod org/springframework/core/env/Profiles.of:([Ljava/lang/String;)Lorg/springframework/core/env/Profiles;
       7: aload_1
       8: invokeinterface #60,  2           // InterfaceMethod org/springframework/core/env/Profiles.matches:(Ljava/util/function/Predicate;)Z
      13: ireturn
}
