Compiled from "ConfigDataEnvironmentContributors.java"
class org.springframework.boot.context.config.ConfigDataEnvironmentContributors$InactiveSourceChecker implements org.springframework.boot.context.properties.bind.BindHandler {
  private final org.springframework.boot.context.config.ConfigDataActivationContext activationContext;

  final org.springframework.boot.context.config.ConfigDataEnvironmentContributors this$0;

  org.springframework.boot.context.config.ConfigDataEnvironmentContributors$InactiveSourceChecker(org.springframework.boot.context.config.ConfigDataEnvironmentContributors, org.springframework.boot.context.config.ConfigDataActivationContext);
    Code:
       0: aload_0
       1: aload_1
       2: putfield      #1                  // Field this$0:Lorg/springframework/boot/context/config/ConfigDataEnvironmentContributors;
       5: aload_0
       6: invokespecial #7                  // Method java/lang/Object."<init>":()V
       9: aload_0
      10: aload_2
      11: putfield      #13                 // Field activationContext:Lorg/springframework/boot/context/config/ConfigDataActivationContext;
      14: return

  public java.lang.Object onSuccess(org.springframework.boot.context.properties.source.ConfigurationPropertyName, org.springframework.boot.context.properties.bind.Bindable<?>, org.springframework.boot.context.properties.bind.BindContext, java.lang.Object);
    Code:
       0: aload_0
       1: getfield      #1                  // Field this$0:Lorg/springframework/boot/context/config/ConfigDataEnvironmentContributors;
       4: invokevirtual #17                 // Method org/springframework/boot/context/config/ConfigDataEnvironmentContributors.iterator:()Ljava/util/Iterator;
       7: astore        5
       9: aload         5
      11: invokeinterface #23,  1           // InterfaceMethod java/util/Iterator.hasNext:()Z
      16: ifeq          52
      19: aload         5
      21: invokeinterface #29,  1           // InterfaceMethod java/util/Iterator.next:()Ljava/lang/Object;
      26: checkcast     #33                 // class org/springframework/boot/context/config/ConfigDataEnvironmentContributor
      29: astore        6
      31: aload         6
      33: aload_0
      34: getfield      #13                 // Field activationContext:Lorg/springframework/boot/context/config/ConfigDataActivationContext;
      37: invokevirtual #35                 // Method org/springframework/boot/context/config/ConfigDataEnvironmentContributor.isActive:(Lorg/springframework/boot/context/config/ConfigDataActivationContext;)Z
      40: ifne          49
      43: aload         6
      45: aload_1
      46: invokestatic  #39                 // Method org/springframework/boot/context/config/InactiveConfigDataAccessException.throwIfPropertyFound:(Lorg/springframework/boot/context/config/ConfigDataEnvironmentContributor;Lorg/springframework/boot/context/properties/source/ConfigurationPropertyName;)V
      49: goto          9
      52: aload         4
      54: areturn
}
