Compiled from "ConfigDataLoaders.java"
class org.springframework.boot.context.config.ConfigDataLoaders {
  private final org.apache.commons.logging.Log logger;

  private final java.util.List<org.springframework.boot.context.config.ConfigDataLoader> loaders;

  private final java.util.List<java.lang.Class<?>> resourceTypes;

  org.springframework.boot.context.config.ConfigDataLoaders(org.springframework.boot.logging.DeferredLogFactory, org.springframework.boot.ConfigurableBootstrapContext, org.springframework.core.io.support.SpringFactoriesLoader);
    Code:
       0: aload_0
       1: invokespecial #1                  // Method java/lang/Object."<init>":()V
       4: aload_0
       5: aload_1
       6: aload_0
       7: invokevirtual #7                  // Method java/lang/Object.getClass:()Ljava/lang/Class;
      10: invokeinterface #11,  2           // InterfaceMethod org/springframework/boot/logging/DeferredLogFactory.getLog:(Ljava/lang/Class;)Lorg/apache/commons/logging/Log;
      15: putfield      #17                 // Field logger:Lorg/apache/commons/logging/Log;
      18: ldc           #12                 // class org/springframework/boot/logging/DeferredLogFactory
      20: aload_1
      21: invokestatic  #23                 // InterfaceMethod org/springframework/core/io/support/SpringFactoriesLoader$ArgumentResolver.of:(Ljava/lang/Class;Ljava/lang/Object;)Lorg/springframework/core/io/support/SpringFactoriesLoader$ArgumentResolver;
      24: astore        4
      26: aload         4
      28: ldc           #29                 // class org/springframework/boot/ConfigurableBootstrapContext
      30: aload_2
      31: invokeinterface #31,  3           // InterfaceMethod org/springframework/core/io/support/SpringFactoriesLoader$ArgumentResolver.and:(Ljava/lang/Class;Ljava/lang/Object;)Lorg/springframework/core/io/support/SpringFactoriesLoader$ArgumentResolver;
      36: astore        4
      38: aload         4
      40: ldc           #34                 // class org/springframework/boot/BootstrapContext
      42: aload_2
      43: invokeinterface #31,  3           // InterfaceMethod org/springframework/core/io/support/SpringFactoriesLoader$ArgumentResolver.and:(Ljava/lang/Class;Ljava/lang/Object;)Lorg/springframework/core/io/support/SpringFactoriesLoader$ArgumentResolver;
      48: astore        4
      50: aload         4
      52: ldc           #36                 // class org/springframework/boot/BootstrapRegistry
      54: aload_2
      55: invokeinterface #31,  3           // InterfaceMethod org/springframework/core/io/support/SpringFactoriesLoader$ArgumentResolver.and:(Ljava/lang/Class;Ljava/lang/Object;)Lorg/springframework/core/io/support/SpringFactoriesLoader$ArgumentResolver;
      60: astore        4
      62: aload         4
      64: ldc           #38                 // class org/apache/commons/logging/Log
      66: invokedynamic #40,  0             // InvokeDynamic #0:get:()Ljava/util/function/Supplier;
      71: invokeinterface #44,  3           // InterfaceMethod org/springframework/core/io/support/SpringFactoriesLoader$ArgumentResolver.andSupplied:(Ljava/lang/Class;Ljava/util/function/Supplier;)Lorg/springframework/core/io/support/SpringFactoriesLoader$ArgumentResolver;
      76: astore        4
      78: aload_0
      79: aload_3
      80: ldc           #48                 // class org/springframework/boot/context/config/ConfigDataLoader
      82: aload         4
      84: invokevirtual #50                 // Method org/springframework/core/io/support/SpringFactoriesLoader.load:(Ljava/lang/Class;Lorg/springframework/core/io/support/SpringFactoriesLoader$ArgumentResolver;)Ljava/util/List;
      87: putfield      #56                 // Field loaders:Ljava/util/List;
      90: aload_0
      91: aload_0
      92: aload_0
      93: getfield      #56                 // Field loaders:Ljava/util/List;
      96: invokevirtual #60                 // Method getResourceTypes:(Ljava/util/List;)Ljava/util/List;
      99: putfield      #64                 // Field resourceTypes:Ljava/util/List;
     102: return

  private java.util.List<java.lang.Class<?>> getResourceTypes(java.util.List<org.springframework.boot.context.config.ConfigDataLoader>);
    Code:
       0: new           #67                 // class java/util/ArrayList
       3: dup
       4: aload_1
       5: invokeinterface #69,  1           // InterfaceMethod java/util/List.size:()I
      10: invokespecial #75                 // Method java/util/ArrayList."<init>":(I)V
      13: astore_2
      14: aload_1
      15: invokeinterface #78,  1           // InterfaceMethod java/util/List.iterator:()Ljava/util/Iterator;
      20: astore_3
      21: aload_3
      22: invokeinterface #82,  1           // InterfaceMethod java/util/Iterator.hasNext:()Z
      27: ifeq          57
      30: aload_3
      31: invokeinterface #88,  1           // InterfaceMethod java/util/Iterator.next:()Ljava/lang/Object;
      36: checkcast     #48                 // class org/springframework/boot/context/config/ConfigDataLoader
      39: astore        4
      41: aload_2
      42: aload_0
      43: aload         4
      45: invokevirtual #92                 // Method getResourceType:(Lorg/springframework/boot/context/config/ConfigDataLoader;)Ljava/lang/Class;
      48: invokeinterface #96,  2           // InterfaceMethod java/util/List.add:(Ljava/lang/Object;)Z
      53: pop
      54: goto          21
      57: aload_2
      58: invokestatic  #100                // Method java/util/Collections.unmodifiableList:(Ljava/util/List;)Ljava/util/List;
      61: areturn

  private java.lang.Class<?> getResourceType(org.springframework.boot.context.config.ConfigDataLoader<?>);
    Code:
       0: aload_1
       1: invokevirtual #7                  // Method java/lang/Object.getClass:()Ljava/lang/Class;
       4: invokestatic  #105                // Method org/springframework/core/ResolvableType.forClass:(Ljava/lang/Class;)Lorg/springframework/core/ResolvableType;
       7: ldc           #48                 // class org/springframework/boot/context/config/ConfigDataLoader
       9: invokevirtual #111                // Method org/springframework/core/ResolvableType.as:(Ljava/lang/Class;)Lorg/springframework/core/ResolvableType;
      12: iconst_0
      13: newarray       int
      15: invokevirtual #114                // Method org/springframework/core/ResolvableType.resolveGeneric:([I)Ljava/lang/Class;
      18: areturn

  <R extends org.springframework.boot.context.config.ConfigDataResource> org.springframework.boot.context.config.ConfigData load(org.springframework.boot.context.config.ConfigDataLoaderContext, R) throws java.io.IOException;
    Code:
       0: aload_0
       1: aload_1
       2: aload_2
       3: invokevirtual #118                // Method getLoader:(Lorg/springframework/boot/context/config/ConfigDataLoaderContext;Lorg/springframework/boot/context/config/ConfigDataResource;)Lorg/springframework/boot/context/config/ConfigDataLoader;
       6: astore_3
       7: aload_0
       8: getfield      #17                 // Field logger:Lorg/apache/commons/logging/Log;
      11: aload_2
      12: aload_3
      13: invokedynamic #122,  0            // InvokeDynamic #1:get:(Lorg/springframework/boot/context/config/ConfigDataResource;Lorg/springframework/boot/context/config/ConfigDataLoader;)Ljava/util/function/Supplier;
      18: invokestatic  #125                // Method org/springframework/core/log/LogMessage.of:(Ljava/util/function/Supplier;)Lorg/springframework/core/log/LogMessage;
      21: invokeinterface #130,  2          // InterfaceMethod org/apache/commons/logging/Log.trace:(Ljava/lang/Object;)V
      26: aload_3
      27: aload_1
      28: aload_2
      29: invokeinterface #134,  3          // InterfaceMethod org/springframework/boot/context/config/ConfigDataLoader.load:(Lorg/springframework/boot/context/config/ConfigDataLoaderContext;Lorg/springframework/boot/context/config/ConfigDataResource;)Lorg/springframework/boot/context/config/ConfigData;
      34: areturn

  private <R extends org.springframework.boot.context.config.ConfigDataResource> org.springframework.boot.context.config.ConfigDataLoader<R> getLoader(org.springframework.boot.context.config.ConfigDataLoaderContext, R);
    Code:
       0: aconst_null
       1: astore_3
       2: iconst_0
       3: istore        4
       5: iload         4
       7: aload_0
       8: getfield      #56                 // Field loaders:Ljava/util/List;
      11: invokeinterface #69,  1           // InterfaceMethod java/util/List.size:()I
      16: if_icmpge     114
      19: aload_0
      20: getfield      #56                 // Field loaders:Ljava/util/List;
      23: iload         4
      25: invokeinterface #137,  2          // InterfaceMethod java/util/List.get:(I)Ljava/lang/Object;
      30: checkcast     #48                 // class org/springframework/boot/context/config/ConfigDataLoader
      33: astore        5
      35: aload_0
      36: getfield      #64                 // Field resourceTypes:Ljava/util/List;
      39: iload         4
      41: invokeinterface #137,  2          // InterfaceMethod java/util/List.get:(I)Ljava/lang/Object;
      46: checkcast     #140                // class java/lang/Class
      49: aload_2
      50: invokevirtual #142                // Method java/lang/Class.isInstance:(Ljava/lang/Object;)Z
      53: ifeq          108
      56: aload         5
      58: astore        6
      60: aload         6
      62: aload_1
      63: aload_2
      64: invokeinterface #145,  3          // InterfaceMethod org/springframework/boot/context/config/ConfigDataLoader.isLoadable:(Lorg/springframework/boot/context/config/ConfigDataLoaderContext;Lorg/springframework/boot/context/config/ConfigDataResource;)Z
      69: ifeq          108
      72: aload_3
      73: ifnull        105
      76: new           #149                // class java/lang/IllegalStateException
      79: dup
      80: aload_2
      81: aload         5
      83: invokevirtual #7                  // Method java/lang/Object.getClass:()Ljava/lang/Class;
      86: invokevirtual #151                // Method java/lang/Class.getName:()Ljava/lang/String;
      89: aload_3
      90: invokevirtual #7                  // Method java/lang/Object.getClass:()Ljava/lang/Class;
      93: invokevirtual #151                // Method java/lang/Class.getName:()Ljava/lang/String;
      96: invokedynamic #155,  0            // InvokeDynamic #2:makeConcatWithConstants:(Lorg/springframework/boot/context/config/ConfigDataResource;Ljava/lang/String;Ljava/lang/String;)Ljava/lang/String;
     101: invokespecial #159                // Method java/lang/IllegalStateException."<init>":(Ljava/lang/String;)V
     104: athrow
     105: aload         6
     107: astore_3
     108: iinc          4, 1
     111: goto          5
     114: aload_3
     115: ifnull        122
     118: iconst_1
     119: goto          123
     122: iconst_0
     123: aload_2
     124: invokedynamic #162,  0            // InvokeDynamic #3:get:(Lorg/springframework/boot/context/config/ConfigDataResource;)Ljava/util/function/Supplier;
     129: invokestatic  #165                // Method org/springframework/util/Assert.state:(ZLjava/util/function/Supplier;)V
     132: aload_3
     133: areturn

  private static java.lang.String lambda$getLoader$2(org.springframework.boot.context.config.ConfigDataResource);
    Code:
       0: aload_0
       1: invokedynamic #171,  0            // InvokeDynamic #4:makeConcatWithConstants:(Lorg/springframework/boot/context/config/ConfigDataResource;)Ljava/lang/String;
       6: areturn

  private static java.lang.CharSequence lambda$load$1(org.springframework.boot.context.config.ConfigDataResource, org.springframework.boot.context.config.ConfigDataLoader);
    Code:
       0: aload_0
       1: aload_1
       2: invokevirtual #7                  // Method java/lang/Object.getClass:()Ljava/lang/Class;
       5: invokevirtual #151                // Method java/lang/Class.getName:()Ljava/lang/String;
       8: invokedynamic #174,  0            // InvokeDynamic #5:makeConcatWithConstants:(Lorg/springframework/boot/context/config/ConfigDataResource;Ljava/lang/String;)Ljava/lang/String;
      13: areturn

  private static org.apache.commons.logging.Log lambda$new$0();
    Code:
       0: new           #177                // class java/lang/IllegalArgumentException
       3: dup
       4: ldc           #179                // String Log types cannot be injected, please use DeferredLogFactory
       6: invokespecial #181                // Method java/lang/IllegalArgumentException."<init>":(Ljava/lang/String;)V
       9: athrow
}
