Compiled from "ConfigDataEnvironmentContributors.java"
final class org.springframework.boot.context.config.ConfigDataEnvironmentContributors$BinderOption extends java.lang.Enum<org.springframework.boot.context.config.ConfigDataEnvironmentContributors$BinderOption> {
  public static final org.springframework.boot.context.config.ConfigDataEnvironmentContributors$BinderOption FAIL_ON_BIND_TO_INACTIVE_SOURCE;

  private static final org.springframework.boot.context.config.ConfigDataEnvironmentContributors$BinderOption[] $VALUES;

  public static org.springframework.boot.context.config.ConfigDataEnvironmentContributors$BinderOption[] values();
    Code:
       0: getstatic     #7                  // Field $VALUES:[Lorg/springframework/boot/context/config/ConfigDataEnvironmentContributors$BinderOption;
       3: invokevirtual #11                 // Method "[Lorg/springframework/boot/context/config/ConfigDataEnvironmentContributors$BinderOption;".clone:()Ljava/lang/Object;
       6: checkcast     #12                 // class "[Lorg/springframework/boot/context/config/ConfigDataEnvironmentContributors$BinderOption;"
       9: areturn

  public static org.springframework.boot.context.config.ConfigDataEnvironmentContributors$BinderOption valueOf(java.lang.String);
    Code:
       0: ldc           #1                  // class org/springframework/boot/context/config/ConfigDataEnvironmentContributors$BinderOption
       2: aload_0
       3: invokestatic  #16                 // Method java/lang/Enum.valueOf:(Ljava/lang/Class;Ljava/lang/String;)Ljava/lang/Enum;
       6: checkcast     #1                  // class org/springframework/boot/context/config/ConfigDataEnvironmentContributors$BinderOption
       9: areturn

  private org.springframework.boot.context.config.ConfigDataEnvironmentContributors$BinderOption();
    Code:
       0: aload_0
       1: aload_1
       2: iload_2
       3: invokespecial #22                 // Method java/lang/Enum."<init>":(Ljava/lang/String;I)V
       6: return

  private static org.springframework.boot.context.config.ConfigDataEnvironmentContributors$BinderOption[] $values();
    Code:
       0: iconst_1
       1: anewarray     #1                  // class org/springframework/boot/context/config/ConfigDataEnvironmentContributors$BinderOption
       4: dup
       5: iconst_0
       6: getstatic     #3                  // Field FAIL_ON_BIND_TO_INACTIVE_SOURCE:Lorg/springframework/boot/context/config/ConfigDataEnvironmentContributors$BinderOption;
       9: aastore
      10: areturn

  static {};
    Code:
       0: new           #1                  // class org/springframework/boot/context/config/ConfigDataEnvironmentContributors$BinderOption
       3: dup
       4: ldc           #26                 // String FAIL_ON_BIND_TO_INACTIVE_SOURCE
       6: iconst_0
       7: invokespecial #27                 // Method "<init>":(Ljava/lang/String;I)V
      10: putstatic     #3                  // Field FAIL_ON_BIND_TO_INACTIVE_SOURCE:Lorg/springframework/boot/context/config/ConfigDataEnvironmentContributors$BinderOption;
      13: invokestatic  #28                 // Method $values:()[Lorg/springframework/boot/context/config/ConfigDataEnvironmentContributors$BinderOption;
      16: putstatic     #7                  // Field $VALUES:[Lorg/springframework/boot/context/config/ConfigDataEnvironmentContributors$BinderOption;
      19: return
}
