Compiled from "ConfigDataLocationResolvers.java"
class org.springframework.boot.context.config.ConfigDataLocationResolvers {
  private final java.util.List<org.springframework.boot.context.config.ConfigDataLocationResolver<?>> resolvers;

  org.springframework.boot.context.config.ConfigDataLocationResolvers(org.springframework.boot.logging.DeferredLogFactory, org.springframework.boot.ConfigurableBootstrapContext, org.springframework.boot.context.properties.bind.Binder, org.springframework.core.io.ResourceLoader, org.springframework.core.io.support.SpringFactoriesLoader);
    Code:
       0: aload_0
       1: invokespecial #1                  // Method java/lang/Object."<init>":()V
       4: ldc           #7                  // class org/springframework/boot/logging/DeferredLogFactory
       6: aload_1
       7: invokestatic  #9                  // InterfaceMethod org/springframework/core/io/support/SpringFactoriesLoader$ArgumentResolver.of:(Ljava/lang/Class;Ljava/lang/Object;)Lorg/springframework/core/io/support/SpringFactoriesLoader$ArgumentResolver;
      10: astore        6
      12: aload         6
      14: ldc           #15                 // class org/springframework/boot/context/properties/bind/Binder
      16: aload_3
      17: invokeinterface #17,  3           // InterfaceMethod org/springframework/core/io/support/SpringFactoriesLoader$ArgumentResolver.and:(Ljava/lang/Class;Ljava/lang/Object;)Lorg/springframework/core/io/support/SpringFactoriesLoader$ArgumentResolver;
      22: astore        6
      24: aload         6
      26: ldc           #20                 // class org/springframework/core/io/ResourceLoader
      28: aload         4
      30: invokeinterface #17,  3           // InterfaceMethod org/springframework/core/io/support/SpringFactoriesLoader$ArgumentResolver.and:(Ljava/lang/Class;Ljava/lang/Object;)Lorg/springframework/core/io/support/SpringFactoriesLoader$ArgumentResolver;
      35: astore        6
      37: aload         6
      39: ldc           #22                 // class org/springframework/boot/ConfigurableBootstrapContext
      41: aload_2
      42: invokeinterface #17,  3           // InterfaceMethod org/springframework/core/io/support/SpringFactoriesLoader$ArgumentResolver.and:(Ljava/lang/Class;Ljava/lang/Object;)Lorg/springframework/core/io/support/SpringFactoriesLoader$ArgumentResolver;
      47: astore        6
      49: aload         6
      51: ldc           #24                 // class org/springframework/boot/BootstrapContext
      53: aload_2
      54: invokeinterface #17,  3           // InterfaceMethod org/springframework/core/io/support/SpringFactoriesLoader$ArgumentResolver.and:(Ljava/lang/Class;Ljava/lang/Object;)Lorg/springframework/core/io/support/SpringFactoriesLoader$ArgumentResolver;
      59: astore        6
      61: aload         6
      63: ldc           #26                 // class org/springframework/boot/BootstrapRegistry
      65: aload_2
      66: invokeinterface #17,  3           // InterfaceMethod org/springframework/core/io/support/SpringFactoriesLoader$ArgumentResolver.and:(Ljava/lang/Class;Ljava/lang/Object;)Lorg/springframework/core/io/support/SpringFactoriesLoader$ArgumentResolver;
      71: astore        6
      73: aload         6
      75: ldc           #28                 // class org/apache/commons/logging/Log
      77: invokedynamic #30,  0             // InvokeDynamic #0:get:()Ljava/util/function/Supplier;
      82: invokeinterface #34,  3           // InterfaceMethod org/springframework/core/io/support/SpringFactoriesLoader$ArgumentResolver.andSupplied:(Ljava/lang/Class;Ljava/util/function/Supplier;)Lorg/springframework/core/io/support/SpringFactoriesLoader$ArgumentResolver;
      87: astore        6
      89: aload_0
      90: aload_0
      91: aload         5
      93: ldc           #38                 // class org/springframework/boot/context/config/ConfigDataLocationResolver
      95: aload         6
      97: invokevirtual #40                 // Method org/springframework/core/io/support/SpringFactoriesLoader.load:(Ljava/lang/Class;Lorg/springframework/core/io/support/SpringFactoriesLoader$ArgumentResolver;)Ljava/util/List;
     100: invokevirtual #46                 // Method reorder:(Ljava/util/List;)Ljava/util/List;
     103: putfield      #52                 // Field resolvers:Ljava/util/List;
     106: return

  private java.util.List<org.springframework.boot.context.config.ConfigDataLocationResolver<?>> reorder(java.util.List<org.springframework.boot.context.config.ConfigDataLocationResolver>);
    Code:
       0: new           #56                 // class java/util/ArrayList
       3: dup
       4: aload_1
       5: invokeinterface #58,  1           // InterfaceMethod java/util/List.size:()I
      10: invokespecial #64                 // Method java/util/ArrayList."<init>":(I)V
      13: astore_2
      14: aconst_null
      15: astore_3
      16: aload_1
      17: invokeinterface #67,  1           // InterfaceMethod java/util/List.iterator:()Ljava/util/Iterator;
      22: astore        4
      24: aload         4
      26: invokeinterface #71,  1           // InterfaceMethod java/util/Iterator.hasNext:()Z
      31: ifeq          79
      34: aload         4
      36: invokeinterface #77,  1           // InterfaceMethod java/util/Iterator.next:()Ljava/lang/Object;
      41: checkcast     #38                 // class org/springframework/boot/context/config/ConfigDataLocationResolver
      44: astore        5
      46: aload         5
      48: instanceof    #81                 // class org/springframework/boot/context/config/StandardConfigDataLocationResolver
      51: ifeq          67
      54: aload         5
      56: checkcast     #81                 // class org/springframework/boot/context/config/StandardConfigDataLocationResolver
      59: astore        6
      61: aload         6
      63: astore_3
      64: goto          76
      67: aload_2
      68: aload         5
      70: invokeinterface #83,  2           // InterfaceMethod java/util/List.add:(Ljava/lang/Object;)Z
      75: pop
      76: goto          24
      79: aload_3
      80: ifnull        91
      83: aload_2
      84: aload_3
      85: invokeinterface #83,  2           // InterfaceMethod java/util/List.add:(Ljava/lang/Object;)Z
      90: pop
      91: aload_2
      92: invokestatic  #87                 // Method java/util/Collections.unmodifiableList:(Ljava/util/List;)Ljava/util/List;
      95: areturn

  java.util.List<org.springframework.boot.context.config.ConfigDataResolutionResult> resolve(org.springframework.boot.context.config.ConfigDataLocationResolverContext, org.springframework.boot.context.config.ConfigDataLocation, org.springframework.boot.context.config.Profiles);
    Code:
       0: aload_2
       1: ifnonnull     8
       4: invokestatic  #92                 // Method java/util/Collections.emptyList:()Ljava/util/List;
       7: areturn
       8: aload_0
       9: invokevirtual #96                 // Method getResolvers:()Ljava/util/List;
      12: invokeinterface #67,  1           // InterfaceMethod java/util/List.iterator:()Ljava/util/Iterator;
      17: astore        4
      19: aload         4
      21: invokeinterface #71,  1           // InterfaceMethod java/util/Iterator.hasNext:()Z
      26: ifeq          66
      29: aload         4
      31: invokeinterface #77,  1           // InterfaceMethod java/util/Iterator.next:()Ljava/lang/Object;
      36: checkcast     #38                 // class org/springframework/boot/context/config/ConfigDataLocationResolver
      39: astore        5
      41: aload         5
      43: aload_1
      44: aload_2
      45: invokeinterface #99,  3           // InterfaceMethod org/springframework/boot/context/config/ConfigDataLocationResolver.isResolvable:(Lorg/springframework/boot/context/config/ConfigDataLocationResolverContext;Lorg/springframework/boot/context/config/ConfigDataLocation;)Z
      50: ifeq          63
      53: aload_0
      54: aload         5
      56: aload_1
      57: aload_2
      58: aload_3
      59: invokevirtual #103                // Method resolve:(Lorg/springframework/boot/context/config/ConfigDataLocationResolver;Lorg/springframework/boot/context/config/ConfigDataLocationResolverContext;Lorg/springframework/boot/context/config/ConfigDataLocation;Lorg/springframework/boot/context/config/Profiles;)Ljava/util/List;
      62: areturn
      63: goto          19
      66: new           #107                // class org/springframework/boot/context/config/UnsupportedConfigDataLocationException
      69: dup
      70: aload_2
      71: invokespecial #109                // Method org/springframework/boot/context/config/UnsupportedConfigDataLocationException."<init>":(Lorg/springframework/boot/context/config/ConfigDataLocation;)V
      74: athrow

  private java.util.List<org.springframework.boot.context.config.ConfigDataResolutionResult> resolve(org.springframework.boot.context.config.ConfigDataLocationResolver<?>, org.springframework.boot.context.config.ConfigDataLocationResolverContext, org.springframework.boot.context.config.ConfigDataLocation, org.springframework.boot.context.config.Profiles);
    Code:
       0: aload_0
       1: aload_3
       2: iconst_0
       3: aload_1
       4: aload_2
       5: aload_3
       6: invokedynamic #112,  0            // InvokeDynamic #1:get:(Lorg/springframework/boot/context/config/ConfigDataLocationResolver;Lorg/springframework/boot/context/config/ConfigDataLocationResolverContext;Lorg/springframework/boot/context/config/ConfigDataLocation;)Ljava/util/function/Supplier;
      11: invokevirtual #115                // Method resolve:(Lorg/springframework/boot/context/config/ConfigDataLocation;ZLjava/util/function/Supplier;)Ljava/util/List;
      14: astore        5
      16: aload         4
      18: ifnonnull     24
      21: aload         5
      23: areturn
      24: aload_0
      25: aload_3
      26: iconst_1
      27: aload_1
      28: aload_2
      29: aload_3
      30: aload         4
      32: invokedynamic #118,  0            // InvokeDynamic #2:get:(Lorg/springframework/boot/context/config/ConfigDataLocationResolver;Lorg/springframework/boot/context/config/ConfigDataLocationResolverContext;Lorg/springframework/boot/context/config/ConfigDataLocation;Lorg/springframework/boot/context/config/Profiles;)Ljava/util/function/Supplier;
      37: invokevirtual #115                // Method resolve:(Lorg/springframework/boot/context/config/ConfigDataLocation;ZLjava/util/function/Supplier;)Ljava/util/List;
      40: astore        6
      42: aload_0
      43: aload         5
      45: aload         6
      47: invokevirtual #121                // Method merge:(Ljava/util/List;Ljava/util/List;)Ljava/util/List;
      50: areturn

  private java.util.List<org.springframework.boot.context.config.ConfigDataResolutionResult> resolve(org.springframework.boot.context.config.ConfigDataLocation, boolean, java.util.function.Supplier<java.util.List<? extends org.springframework.boot.context.config.ConfigDataResource>>);
    Code:
       0: aload_0
       1: aload_3
       2: invokeinterface #125,  1          // InterfaceMethod java/util/function/Supplier.get:()Ljava/lang/Object;
       7: checkcast     #59                 // class java/util/List
      10: invokevirtual #129                // Method nonNullList:(Ljava/util/List;)Ljava/util/List;
      13: astore        4
      15: new           #56                 // class java/util/ArrayList
      18: dup
      19: aload         4
      21: invokeinterface #58,  1           // InterfaceMethod java/util/List.size:()I
      26: invokespecial #64                 // Method java/util/ArrayList."<init>":(I)V
      29: astore        5
      31: aload         4
      33: invokeinterface #67,  1           // InterfaceMethod java/util/List.iterator:()Ljava/util/Iterator;
      38: astore        6
      40: aload         6
      42: invokeinterface #71,  1           // InterfaceMethod java/util/Iterator.hasNext:()Z
      47: ifeq          84
      50: aload         6
      52: invokeinterface #77,  1           // InterfaceMethod java/util/Iterator.next:()Ljava/lang/Object;
      57: checkcast     #132                // class org/springframework/boot/context/config/ConfigDataResource
      60: astore        7
      62: aload         5
      64: new           #134                // class org/springframework/boot/context/config/ConfigDataResolutionResult
      67: dup
      68: aload_1
      69: aload         7
      71: iload_2
      72: invokespecial #136                // Method org/springframework/boot/context/config/ConfigDataResolutionResult."<init>":(Lorg/springframework/boot/context/config/ConfigDataLocation;Lorg/springframework/boot/context/config/ConfigDataResource;Z)V
      75: invokeinterface #83,  2           // InterfaceMethod java/util/List.add:(Ljava/lang/Object;)Z
      80: pop
      81: goto          40
      84: aload         5
      86: areturn

  private <T> java.util.List<T> nonNullList(java.util.List<? extends T>);
    Code:
       0: aload_1
       1: ifnull        8
       4: aload_1
       5: goto          11
       8: invokestatic  #92                 // Method java/util/Collections.emptyList:()Ljava/util/List;
      11: areturn

  private <T> java.util.List<T> merge(java.util.List<T>, java.util.List<T>);
    Code:
       0: new           #56                 // class java/util/ArrayList
       3: dup
       4: aload_1
       5: invokeinterface #58,  1           // InterfaceMethod java/util/List.size:()I
      10: aload_2
      11: invokeinterface #58,  1           // InterfaceMethod java/util/List.size:()I
      16: iadd
      17: invokespecial #64                 // Method java/util/ArrayList."<init>":(I)V
      20: astore_3
      21: aload_3
      22: aload_1
      23: invokeinterface #139,  2          // InterfaceMethod java/util/List.addAll:(Ljava/util/Collection;)Z
      28: pop
      29: aload_3
      30: aload_2
      31: invokeinterface #139,  2          // InterfaceMethod java/util/List.addAll:(Ljava/util/Collection;)Z
      36: pop
      37: aload_3
      38: areturn

  java.util.List<org.springframework.boot.context.config.ConfigDataLocationResolver<?>> getResolvers();
    Code:
       0: aload_0
       1: getfield      #52                 // Field resolvers:Ljava/util/List;
       4: areturn

  private static java.util.List lambda$resolve$2(org.springframework.boot.context.config.ConfigDataLocationResolver, org.springframework.boot.context.config.ConfigDataLocationResolverContext, org.springframework.boot.context.config.ConfigDataLocation, org.springframework.boot.context.config.Profiles);
    Code:
       0: aload_0
       1: aload_1
       2: aload_2
       3: aload_3
       4: invokeinterface #143,  4          // InterfaceMethod org/springframework/boot/context/config/ConfigDataLocationResolver.resolveProfileSpecific:(Lorg/springframework/boot/context/config/ConfigDataLocationResolverContext;Lorg/springframework/boot/context/config/ConfigDataLocation;Lorg/springframework/boot/context/config/Profiles;)Ljava/util/List;
       9: areturn

  private static java.util.List lambda$resolve$1(org.springframework.boot.context.config.ConfigDataLocationResolver, org.springframework.boot.context.config.ConfigDataLocationResolverContext, org.springframework.boot.context.config.ConfigDataLocation);
    Code:
       0: aload_0
       1: aload_1
       2: aload_2
       3: invokeinterface #147,  3          // InterfaceMethod org/springframework/boot/context/config/ConfigDataLocationResolver.resolve:(Lorg/springframework/boot/context/config/ConfigDataLocationResolverContext;Lorg/springframework/boot/context/config/ConfigDataLocation;)Ljava/util/List;
       8: areturn

  private static org.apache.commons.logging.Log lambda$new$0();
    Code:
       0: new           #150                // class java/lang/IllegalArgumentException
       3: dup
       4: ldc           #152                // String Log types cannot be injected, please use DeferredLogFactory
       6: invokespecial #154                // Method java/lang/IllegalArgumentException."<init>":(Ljava/lang/String;)V
       9: athrow
}
