Compiled from "ConfigDataEnvironmentContributors.java"
class org.springframework.boot.context.config.ConfigDataEnvironmentContributors implements java.lang.Iterable<org.springframework.boot.context.config.ConfigDataEnvironmentContributor> {
  private static final java.util.function.Predicate<org.springframework.boot.context.config.ConfigDataEnvironmentContributor> NO_CONTRIBUTOR_FILTER;

  private final org.apache.commons.logging.Log logger;

  private final org.springframework.boot.context.config.ConfigDataEnvironmentContributor root;

  private final org.springframework.boot.ConfigurableBootstrapContext bootstrapContext;

  org.springframework.boot.context.config.ConfigDataEnvironmentContributors(org.springframework.boot.logging.DeferredLogFactory, org.springframework.boot.ConfigurableBootstrapContext, java.util.List<org.springframework.boot.context.config.ConfigDataEnvironmentContributor>);
    Code:
       0: aload_0
       1: invokespecial #1                  // Method java/lang/Object."<init>":()V
       4: aload_0
       5: aload_1
       6: aload_0
       7: invokevirtual #7                  // Method java/lang/Object.getClass:()Ljava/lang/Class;
      10: invokeinterface #11,  2           // InterfaceMethod org/springframework/boot/logging/DeferredLogFactory.getLog:(Ljava/lang/Class;)Lorg/apache/commons/logging/Log;
      15: putfield      #17                 // Field logger:Lorg/apache/commons/logging/Log;
      18: aload_0
      19: aload_2
      20: putfield      #23                 // Field bootstrapContext:Lorg/springframework/boot/ConfigurableBootstrapContext;
      23: aload_0
      24: aload_3
      25: invokestatic  #27                 // Method org/springframework/boot/context/config/ConfigDataEnvironmentContributor.of:(Ljava/util/List;)Lorg/springframework/boot/context/config/ConfigDataEnvironmentContributor;
      28: putfield      #33                 // Field root:Lorg/springframework/boot/context/config/ConfigDataEnvironmentContributor;
      31: return

  private org.springframework.boot.context.config.ConfigDataEnvironmentContributors(org.apache.commons.logging.Log, org.springframework.boot.ConfigurableBootstrapContext, org.springframework.boot.context.config.ConfigDataEnvironmentContributor);
    Code:
       0: aload_0
       1: invokespecial #1                  // Method java/lang/Object."<init>":()V
       4: aload_0
       5: aload_1
       6: putfield      #17                 // Field logger:Lorg/apache/commons/logging/Log;
       9: aload_0
      10: aload_2
      11: putfield      #23                 // Field bootstrapContext:Lorg/springframework/boot/ConfigurableBootstrapContext;
      14: aload_0
      15: aload_3
      16: putfield      #33                 // Field root:Lorg/springframework/boot/context/config/ConfigDataEnvironmentContributor;
      19: return

  org.springframework.boot.context.config.ConfigDataEnvironmentContributors withProcessedImports(org.springframework.boot.context.config.ConfigDataImporter, org.springframework.boot.context.config.ConfigDataActivationContext);
    Code:
       0: aload_2
       1: invokestatic  #37                 // Method org/springframework/boot/context/config/ConfigDataEnvironmentContributor$ImportPhase.get:(Lorg/springframework/boot/context/config/ConfigDataActivationContext;)Lorg/springframework/boot/context/config/ConfigDataEnvironmentContributor$ImportPhase;
       4: astore_3
       5: aload_0
       6: getfield      #17                 // Field logger:Lorg/apache/commons/logging/Log;
       9: ldc           #43                 // String Processing imports for phase %s. %s
      11: aload_3
      12: aload_2
      13: ifnull        20
      16: aload_2
      17: goto          22
      20: ldc           #45                 // String no activation context
      22: invokestatic  #47                 // Method org/springframework/core/log/LogMessage.format:(Ljava/lang/String;Ljava/lang/Object;Ljava/lang/Object;)Lorg/springframework/core/log/LogMessage;
      25: invokeinterface #53,  2           // InterfaceMethod org/apache/commons/logging/Log.trace:(Ljava/lang/Object;)V
      30: aload_0
      31: astore        4
      33: iconst_0
      34: istore        5
      36: aload_0
      37: aload         4
      39: aload_2
      40: aload_3
      41: invokevirtual #59                 // Method getNextToProcess:(Lorg/springframework/boot/context/config/ConfigDataEnvironmentContributors;Lorg/springframework/boot/context/config/ConfigDataActivationContext;Lorg/springframework/boot/context/config/ConfigDataEnvironmentContributor$ImportPhase;)Lorg/springframework/boot/context/config/ConfigDataEnvironmentContributor;
      44: astore        6
      46: aload         6
      48: ifnonnull     73
      51: aload_0
      52: getfield      #17                 // Field logger:Lorg/apache/commons/logging/Log;
      55: ldc           #63                 // String Processed imports for of %d contributors
      57: iload         5
      59: invokestatic  #65                 // Method java/lang/Integer.valueOf:(I)Ljava/lang/Integer;
      62: invokestatic  #71                 // Method org/springframework/core/log/LogMessage.format:(Ljava/lang/String;Ljava/lang/Object;)Lorg/springframework/core/log/LogMessage;
      65: invokeinterface #53,  2           // InterfaceMethod org/apache/commons/logging/Log.trace:(Ljava/lang/Object;)V
      70: aload         4
      72: areturn
      73: aload         6
      75: invokevirtual #74                 // Method org/springframework/boot/context/config/ConfigDataEnvironmentContributor.getKind:()Lorg/springframework/boot/context/config/ConfigDataEnvironmentContributor$Kind;
      78: getstatic     #78                 // Field org/springframework/boot/context/config/ConfigDataEnvironmentContributor$Kind.UNBOUND_IMPORT:Lorg/springframework/boot/context/config/ConfigDataEnvironmentContributor$Kind;
      81: if_acmpne     126
      84: aload         6
      86: aload         4
      88: aload_2
      89: invokevirtual #84                 // Method org/springframework/boot/context/config/ConfigDataEnvironmentContributor.withBoundProperties:(Ljava/lang/Iterable;Lorg/springframework/boot/context/config/ConfigDataActivationContext;)Lorg/springframework/boot/context/config/ConfigDataEnvironmentContributor;
      92: astore        7
      94: new           #18                 // class org/springframework/boot/context/config/ConfigDataEnvironmentContributors
      97: dup
      98: aload_0
      99: getfield      #17                 // Field logger:Lorg/apache/commons/logging/Log;
     102: aload_0
     103: getfield      #23                 // Field bootstrapContext:Lorg/springframework/boot/ConfigurableBootstrapContext;
     106: aload         4
     108: invokevirtual #88                 // Method getRoot:()Lorg/springframework/boot/context/config/ConfigDataEnvironmentContributor;
     111: aload         6
     113: aload         7
     115: invokevirtual #92                 // Method org/springframework/boot/context/config/ConfigDataEnvironmentContributor.withReplacement:(Lorg/springframework/boot/context/config/ConfigDataEnvironmentContributor;Lorg/springframework/boot/context/config/ConfigDataEnvironmentContributor;)Lorg/springframework/boot/context/config/ConfigDataEnvironmentContributor;
     118: invokespecial #96                 // Method "<init>":(Lorg/apache/commons/logging/Log;Lorg/springframework/boot/ConfigurableBootstrapContext;Lorg/springframework/boot/context/config/ConfigDataEnvironmentContributor;)V
     121: astore        4
     123: goto          36
     126: new           #99                 // class org/springframework/boot/context/config/ConfigDataEnvironmentContributors$ContributorConfigDataLocationResolverContext
     129: dup
     130: aload         4
     132: aload         6
     134: aload_2
     135: invokespecial #101                // Method org/springframework/boot/context/config/ConfigDataEnvironmentContributors$ContributorConfigDataLocationResolverContext."<init>":(Lorg/springframework/boot/context/config/ConfigDataEnvironmentContributors;Lorg/springframework/boot/context/config/ConfigDataEnvironmentContributor;Lorg/springframework/boot/context/config/ConfigDataActivationContext;)V
     138: astore        7
     140: new           #104                // class org/springframework/boot/context/config/ConfigDataEnvironmentContributors$ContributorDataLoaderContext
     143: dup
     144: aload_0
     145: invokespecial #106                // Method org/springframework/boot/context/config/ConfigDataEnvironmentContributors$ContributorDataLoaderContext."<init>":(Lorg/springframework/boot/context/config/ConfigDataEnvironmentContributors;)V
     148: astore        8
     150: aload         6
     152: invokevirtual #109                // Method org/springframework/boot/context/config/ConfigDataEnvironmentContributor.getImports:()Ljava/util/List;
     155: astore        9
     157: aload_0
     158: getfield      #17                 // Field logger:Lorg/apache/commons/logging/Log;
     161: ldc           #113                // String Processing imports %s
     163: aload         9
     165: invokestatic  #71                 // Method org/springframework/core/log/LogMessage.format:(Ljava/lang/String;Ljava/lang/Object;)Lorg/springframework/core/log/LogMessage;
     168: invokeinterface #53,  2           // InterfaceMethod org/apache/commons/logging/Log.trace:(Ljava/lang/Object;)V
     173: aload_1
     174: aload_2
     175: aload         7
     177: aload         8
     179: aload         9
     181: invokevirtual #115                // Method org/springframework/boot/context/config/ConfigDataImporter.resolveAndLoad:(Lorg/springframework/boot/context/config/ConfigDataActivationContext;Lorg/springframework/boot/context/config/ConfigDataLocationResolverContext;Lorg/springframework/boot/context/config/ConfigDataLoaderContext;Ljava/util/List;)Ljava/util/Map;
     184: astore        10
     186: aload_0
     187: getfield      #17                 // Field logger:Lorg/apache/commons/logging/Log;
     190: aload_0
     191: aload         10
     193: invokedynamic #121,  0            // InvokeDynamic #0:get:(Lorg/springframework/boot/context/config/ConfigDataEnvironmentContributors;Ljava/util/Map;)Ljava/util/function/Supplier;
     198: invokestatic  #124                // Method org/springframework/core/log/LogMessage.of:(Ljava/util/function/Supplier;)Lorg/springframework/core/log/LogMessage;
     201: invokeinterface #53,  2           // InterfaceMethod org/apache/commons/logging/Log.trace:(Ljava/lang/Object;)V
     206: aload         6
     208: aload_3
     209: aload_0
     210: aload         10
     212: invokevirtual #127                // Method asContributors:(Ljava/util/Map;)Ljava/util/List;
     215: invokevirtual #131                // Method org/springframework/boot/context/config/ConfigDataEnvironmentContributor.withChildren:(Lorg/springframework/boot/context/config/ConfigDataEnvironmentContributor$ImportPhase;Ljava/util/List;)Lorg/springframework/boot/context/config/ConfigDataEnvironmentContributor;
     218: astore        11
     220: new           #18                 // class org/springframework/boot/context/config/ConfigDataEnvironmentContributors
     223: dup
     224: aload_0
     225: getfield      #17                 // Field logger:Lorg/apache/commons/logging/Log;
     228: aload_0
     229: getfield      #23                 // Field bootstrapContext:Lorg/springframework/boot/ConfigurableBootstrapContext;
     232: aload         4
     234: invokevirtual #88                 // Method getRoot:()Lorg/springframework/boot/context/config/ConfigDataEnvironmentContributor;
     237: aload         6
     239: aload         11
     241: invokevirtual #92                 // Method org/springframework/boot/context/config/ConfigDataEnvironmentContributor.withReplacement:(Lorg/springframework/boot/context/config/ConfigDataEnvironmentContributor;Lorg/springframework/boot/context/config/ConfigDataEnvironmentContributor;)Lorg/springframework/boot/context/config/ConfigDataEnvironmentContributor;
     244: invokespecial #96                 // Method "<init>":(Lorg/apache/commons/logging/Log;Lorg/springframework/boot/ConfigurableBootstrapContext;Lorg/springframework/boot/context/config/ConfigDataEnvironmentContributor;)V
     247: astore        4
     249: iinc          5, 1
     252: goto          36

  private java.lang.CharSequence getImportedMessage(java.util.Set<org.springframework.boot.context.config.ConfigDataResolutionResult>);
    Code:
       0: aload_1
       1: invokeinterface #135,  1          // InterfaceMethod java/util/Set.isEmpty:()Z
       6: ifeq          12
       9: ldc           #141                // String Nothing imported
      11: areturn
      12: new           #143                // class java/lang/StringBuilder
      15: dup
      16: invokespecial #145                // Method java/lang/StringBuilder."<init>":()V
      19: astore_2
      20: aload_2
      21: aload_1
      22: invokeinterface #146,  1          // InterfaceMethod java/util/Set.size:()I
      27: aload_1
      28: invokeinterface #146,  1          // InterfaceMethod java/util/Set.size:()I
      33: iconst_1
      34: if_icmpeq     42
      37: ldc           #150                // String s
      39: goto          44
      42: ldc           #152                // String
      44: invokedynamic #154,  0            // InvokeDynamic #1:makeConcatWithConstants:(ILjava/lang/String;)Ljava/lang/String;
      49: invokevirtual #158                // Method java/lang/StringBuilder.append:(Ljava/lang/String;)Ljava/lang/StringBuilder;
      52: pop
      53: aload_2
      54: aload_1
      55: invokeinterface #162,  1          // InterfaceMethod java/util/Set.stream:()Ljava/util/stream/Stream;
      60: invokedynamic #166,  0            // InvokeDynamic #2:apply:()Ljava/util/function/Function;
      65: invokeinterface #170,  2          // InterfaceMethod java/util/stream/Stream.map:(Ljava/util/function/Function;)Ljava/util/stream/Stream;
      70: invokeinterface #176,  1          // InterfaceMethod java/util/stream/Stream.toList:()Ljava/util/List;
      75: invokevirtual #179                // Method java/lang/StringBuilder.append:(Ljava/lang/Object;)Ljava/lang/StringBuilder;
      78: pop
      79: aload_2
      80: areturn

  protected final org.springframework.boot.ConfigurableBootstrapContext getBootstrapContext();
    Code:
       0: aload_0
       1: getfield      #23                 // Field bootstrapContext:Lorg/springframework/boot/ConfigurableBootstrapContext;
       4: areturn

  private org.springframework.boot.context.config.ConfigDataEnvironmentContributor getNextToProcess(org.springframework.boot.context.config.ConfigDataEnvironmentContributors, org.springframework.boot.context.config.ConfigDataActivationContext, org.springframework.boot.context.config.ConfigDataEnvironmentContributor$ImportPhase);
    Code:
       0: aload_1
       1: invokevirtual #88                 // Method getRoot:()Lorg/springframework/boot/context/config/ConfigDataEnvironmentContributor;
       4: invokevirtual #182                // Method org/springframework/boot/context/config/ConfigDataEnvironmentContributor.iterator:()Ljava/util/Iterator;
       7: astore        4
       9: aload         4
      11: invokeinterface #186,  1          // InterfaceMethod java/util/Iterator.hasNext:()Z
      16: ifeq          59
      19: aload         4
      21: invokeinterface #191,  1          // InterfaceMethod java/util/Iterator.next:()Ljava/lang/Object;
      26: checkcast     #28                 // class org/springframework/boot/context/config/ConfigDataEnvironmentContributor
      29: astore        5
      31: aload         5
      33: invokevirtual #74                 // Method org/springframework/boot/context/config/ConfigDataEnvironmentContributor.getKind:()Lorg/springframework/boot/context/config/ConfigDataEnvironmentContributor$Kind;
      36: getstatic     #78                 // Field org/springframework/boot/context/config/ConfigDataEnvironmentContributor$Kind.UNBOUND_IMPORT:Lorg/springframework/boot/context/config/ConfigDataEnvironmentContributor$Kind;
      39: if_acmpeq     53
      42: aload_0
      43: aload_2
      44: aload_3
      45: aload         5
      47: invokevirtual #195                // Method isActiveWithUnprocessedImports:(Lorg/springframework/boot/context/config/ConfigDataActivationContext;Lorg/springframework/boot/context/config/ConfigDataEnvironmentContributor$ImportPhase;Lorg/springframework/boot/context/config/ConfigDataEnvironmentContributor;)Z
      50: ifeq          56
      53: aload         5
      55: areturn
      56: goto          9
      59: aconst_null
      60: areturn

  private boolean isActiveWithUnprocessedImports(org.springframework.boot.context.config.ConfigDataActivationContext, org.springframework.boot.context.config.ConfigDataEnvironmentContributor$ImportPhase, org.springframework.boot.context.config.ConfigDataEnvironmentContributor);
    Code:
       0: aload_3
       1: aload_1
       2: invokevirtual #199                // Method org/springframework/boot/context/config/ConfigDataEnvironmentContributor.isActive:(Lorg/springframework/boot/context/config/ConfigDataActivationContext;)Z
       5: ifeq          20
       8: aload_3
       9: aload_2
      10: invokevirtual #203                // Method org/springframework/boot/context/config/ConfigDataEnvironmentContributor.hasUnprocessedImports:(Lorg/springframework/boot/context/config/ConfigDataEnvironmentContributor$ImportPhase;)Z
      13: ifeq          20
      16: iconst_1
      17: goto          21
      20: iconst_0
      21: ireturn

  private java.util.List<org.springframework.boot.context.config.ConfigDataEnvironmentContributor> asContributors(java.util.Map<org.springframework.boot.context.config.ConfigDataResolutionResult, org.springframework.boot.context.config.ConfigData>);
    Code:
       0: new           #207                // class java/util/ArrayList
       3: dup
       4: aload_1
       5: invokeinterface #209,  1          // InterfaceMethod java/util/Map.size:()I
      10: iconst_5
      11: imul
      12: invokespecial #212                // Method java/util/ArrayList."<init>":(I)V
      15: astore_2
      16: aload_1
      17: aload_2
      18: invokedynamic #215,  0            // InvokeDynamic #3:accept:(Ljava/util/List;)Ljava/util/function/BiConsumer;
      23: invokeinterface #219,  2          // InterfaceMethod java/util/Map.forEach:(Ljava/util/function/BiConsumer;)V
      28: aload_2
      29: invokestatic  #223                // Method java/util/Collections.unmodifiableList:(Ljava/util/List;)Ljava/util/List;
      32: areturn

  org.springframework.boot.context.config.ConfigDataEnvironmentContributor getRoot();
    Code:
       0: aload_0
       1: getfield      #33                 // Field root:Lorg/springframework/boot/context/config/ConfigDataEnvironmentContributor;
       4: areturn

  org.springframework.boot.context.properties.bind.Binder getBinder(org.springframework.boot.context.config.ConfigDataActivationContext, org.springframework.boot.context.config.ConfigDataEnvironmentContributors$BinderOption...);
    Code:
       0: aload_0
       1: aload_1
       2: getstatic     #229                // Field NO_CONTRIBUTOR_FILTER:Ljava/util/function/Predicate;
       5: aload_2
       6: invokevirtual #233                // Method getBinder:(Lorg/springframework/boot/context/config/ConfigDataActivationContext;Ljava/util/function/Predicate;[Lorg/springframework/boot/context/config/ConfigDataEnvironmentContributors$BinderOption;)Lorg/springframework/boot/context/properties/bind/Binder;
       9: areturn

  org.springframework.boot.context.properties.bind.Binder getBinder(org.springframework.boot.context.config.ConfigDataActivationContext, java.util.function.Predicate<org.springframework.boot.context.config.ConfigDataEnvironmentContributor>, org.springframework.boot.context.config.ConfigDataEnvironmentContributors$BinderOption...);
    Code:
       0: aload_0
       1: aload_1
       2: aload_2
       3: aload_0
       4: aload_3
       5: invokevirtual #237                // Method asBinderOptionsSet:([Lorg/springframework/boot/context/config/ConfigDataEnvironmentContributors$BinderOption;)Ljava/util/Set;
       8: invokevirtual #241                // Method getBinder:(Lorg/springframework/boot/context/config/ConfigDataActivationContext;Ljava/util/function/Predicate;Ljava/util/Set;)Lorg/springframework/boot/context/properties/bind/Binder;
      11: areturn

  private java.util.Set<org.springframework.boot.context.config.ConfigDataEnvironmentContributors$BinderOption> asBinderOptionsSet(org.springframework.boot.context.config.ConfigDataEnvironmentContributors$BinderOption...);
    Code:
       0: aload_1
       1: invokestatic  #244                // Method org/springframework/util/ObjectUtils.isEmpty:([Ljava/lang/Object;)Z
       4: ifeq          15
       7: ldc           #249                // class org/springframework/boot/context/config/ConfigDataEnvironmentContributors$BinderOption
       9: invokestatic  #251                // Method java/util/EnumSet.noneOf:(Ljava/lang/Class;)Ljava/util/EnumSet;
      12: goto          22
      15: aload_1
      16: invokestatic  #257                // Method java/util/Arrays.asList:([Ljava/lang/Object;)Ljava/util/List;
      19: invokestatic  #263                // Method java/util/EnumSet.copyOf:(Ljava/util/Collection;)Ljava/util/EnumSet;
      22: areturn

  private org.springframework.boot.context.properties.bind.Binder getBinder(org.springframework.boot.context.config.ConfigDataActivationContext, java.util.function.Predicate<org.springframework.boot.context.config.ConfigDataEnvironmentContributor>, java.util.Set<org.springframework.boot.context.config.ConfigDataEnvironmentContributors$BinderOption>);
    Code:
       0: aload_3
       1: getstatic     #267                // Field org/springframework/boot/context/config/ConfigDataEnvironmentContributors$BinderOption.FAIL_ON_BIND_TO_INACTIVE_SOURCE:Lorg/springframework/boot/context/config/ConfigDataEnvironmentContributors$BinderOption;
       4: invokeinterface #271,  2          // InterfaceMethod java/util/Set.contains:(Ljava/lang/Object;)Z
       9: istore        4
      11: aload_0
      12: aload_2
      13: iload         4
      15: aload_1
      16: invokedynamic #275,  0            // InvokeDynamic #4:iterator:(Lorg/springframework/boot/context/config/ConfigDataEnvironmentContributors;Ljava/util/function/Predicate;ZLorg/springframework/boot/context/config/ConfigDataActivationContext;)Ljava/lang/Iterable;
      21: astore        5
      23: new           #278                // class org/springframework/boot/context/config/ConfigDataEnvironmentContributorPlaceholdersResolver
      26: dup
      27: aload_0
      28: getfield      #33                 // Field root:Lorg/springframework/boot/context/config/ConfigDataEnvironmentContributor;
      31: aload_1
      32: aconst_null
      33: iload         4
      35: invokespecial #280                // Method org/springframework/boot/context/config/ConfigDataEnvironmentContributorPlaceholdersResolver."<init>":(Ljava/lang/Iterable;Lorg/springframework/boot/context/config/ConfigDataActivationContext;Lorg/springframework/boot/context/config/ConfigDataEnvironmentContributor;Z)V
      38: astore        6
      40: iload         4
      42: ifne          49
      45: aconst_null
      46: goto          58
      49: new           #283                // class org/springframework/boot/context/config/ConfigDataEnvironmentContributors$InactiveSourceChecker
      52: dup
      53: aload_0
      54: aload_1
      55: invokespecial #285                // Method org/springframework/boot/context/config/ConfigDataEnvironmentContributors$InactiveSourceChecker."<init>":(Lorg/springframework/boot/context/config/ConfigDataEnvironmentContributors;Lorg/springframework/boot/context/config/ConfigDataActivationContext;)V
      58: astore        7
      60: new           #288                // class org/springframework/boot/context/properties/bind/Binder
      63: dup
      64: aload         5
      66: aload         6
      68: aconst_null
      69: aconst_null
      70: aload         7
      72: invokespecial #290                // Method org/springframework/boot/context/properties/bind/Binder."<init>":(Ljava/lang/Iterable;Lorg/springframework/boot/context/properties/bind/PlaceholdersResolver;Lorg/springframework/core/convert/ConversionService;Ljava/util/function/Consumer;Lorg/springframework/boot/context/properties/bind/BindHandler;)V
      75: areturn

  private java.util.Iterator<org.springframework.boot.context.properties.source.ConfigurationPropertySource> getBinderSources(java.util.function.Predicate<org.springframework.boot.context.config.ConfigDataEnvironmentContributor>);
    Code:
       0: aload_0
       1: getfield      #33                 // Field root:Lorg/springframework/boot/context/config/ConfigDataEnvironmentContributor;
       4: invokevirtual #293                // Method org/springframework/boot/context/config/ConfigDataEnvironmentContributor.stream:()Ljava/util/stream/Stream;
       7: aload_0
       8: invokedynamic #294,  0            // InvokeDynamic #5:test:(Lorg/springframework/boot/context/config/ConfigDataEnvironmentContributors;)Ljava/util/function/Predicate;
      13: invokeinterface #298,  2          // InterfaceMethod java/util/stream/Stream.filter:(Ljava/util/function/Predicate;)Ljava/util/stream/Stream;
      18: aload_1
      19: invokeinterface #298,  2          // InterfaceMethod java/util/stream/Stream.filter:(Ljava/util/function/Predicate;)Ljava/util/stream/Stream;
      24: invokedynamic #302,  0            // InvokeDynamic #6:apply:()Ljava/util/function/Function;
      29: invokeinterface #170,  2          // InterfaceMethod java/util/stream/Stream.map:(Ljava/util/function/Function;)Ljava/util/stream/Stream;
      34: invokeinterface #303,  1          // InterfaceMethod java/util/stream/Stream.iterator:()Ljava/util/Iterator;
      39: areturn

  private boolean hasConfigurationPropertySource(org.springframework.boot.context.config.ConfigDataEnvironmentContributor);
    Code:
       0: aload_1
       1: invokevirtual #304                // Method org/springframework/boot/context/config/ConfigDataEnvironmentContributor.getConfigurationPropertySource:()Lorg/springframework/boot/context/properties/source/ConfigurationPropertySource;
       4: ifnull        11
       7: iconst_1
       8: goto          12
      11: iconst_0
      12: ireturn

  public java.util.Iterator<org.springframework.boot.context.config.ConfigDataEnvironmentContributor> iterator();
    Code:
       0: aload_0
       1: getfield      #33                 // Field root:Lorg/springframework/boot/context/config/ConfigDataEnvironmentContributor;
       4: invokevirtual #182                // Method org/springframework/boot/context/config/ConfigDataEnvironmentContributor.iterator:()Ljava/util/Iterator;
       7: areturn

  private java.util.Iterator lambda$getBinder$4(java.util.function.Predicate, boolean, org.springframework.boot.context.config.ConfigDataActivationContext);
    Code:
       0: aload_0
       1: aload_1
       2: iload_2
       3: aload_3
       4: invokedynamic #308,  0            // InvokeDynamic #7:test:(ZLorg/springframework/boot/context/config/ConfigDataActivationContext;)Ljava/util/function/Predicate;
       9: invokeinterface #311,  2          // InterfaceMethod java/util/function/Predicate.and:(Ljava/util/function/Predicate;)Ljava/util/function/Predicate;
      14: invokevirtual #317                // Method getBinderSources:(Ljava/util/function/Predicate;)Ljava/util/Iterator;
      17: areturn

  private static boolean lambda$getBinder$3(boolean, org.springframework.boot.context.config.ConfigDataActivationContext, org.springframework.boot.context.config.ConfigDataEnvironmentContributor);
    Code:
       0: iload_0
       1: ifne          12
       4: aload_2
       5: aload_1
       6: invokevirtual #199                // Method org/springframework/boot/context/config/ConfigDataEnvironmentContributor.isActive:(Lorg/springframework/boot/context/config/ConfigDataActivationContext;)Z
       9: ifeq          16
      12: iconst_1
      13: goto          17
      16: iconst_0
      17: ireturn

  private static void lambda$asContributors$2(java.util.List, org.springframework.boot.context.config.ConfigDataResolutionResult, org.springframework.boot.context.config.ConfigData);
    Code:
       0: aload_1
       1: invokevirtual #321                // Method org/springframework/boot/context/config/ConfigDataResolutionResult.getLocation:()Lorg/springframework/boot/context/config/ConfigDataLocation;
       4: astore_3
       5: aload_1
       6: invokevirtual #327                // Method org/springframework/boot/context/config/ConfigDataResolutionResult.getResource:()Lorg/springframework/boot/context/config/ConfigDataResource;
       9: astore        4
      11: aload_1
      12: invokevirtual #331                // Method org/springframework/boot/context/config/ConfigDataResolutionResult.isProfileSpecific:()Z
      15: istore        5
      17: aload_2
      18: invokevirtual #334                // Method org/springframework/boot/context/config/ConfigData.getPropertySources:()Ljava/util/List;
      21: invokeinterface #339,  1          // InterfaceMethod java/util/List.isEmpty:()Z
      26: ifeq          45
      29: aload_0
      30: aload_3
      31: iload         5
      33: invokestatic  #342                // Method org/springframework/boot/context/config/ConfigDataEnvironmentContributor.ofEmptyLocation:(Lorg/springframework/boot/context/config/ConfigDataLocation;Z)Lorg/springframework/boot/context/config/ConfigDataEnvironmentContributor;
      36: invokeinterface #346,  2          // InterfaceMethod java/util/List.add:(Ljava/lang/Object;)Z
      41: pop
      42: goto          87
      45: aload_2
      46: invokevirtual #334                // Method org/springframework/boot/context/config/ConfigData.getPropertySources:()Ljava/util/List;
      49: invokeinterface #349,  1          // InterfaceMethod java/util/List.size:()I
      54: iconst_1
      55: isub
      56: istore        6
      58: iload         6
      60: iflt          87
      63: aload_0
      64: aload_3
      65: aload         4
      67: iload         5
      69: aload_2
      70: iload         6
      72: invokestatic  #350                // Method org/springframework/boot/context/config/ConfigDataEnvironmentContributor.ofUnboundImport:(Lorg/springframework/boot/context/config/ConfigDataLocation;Lorg/springframework/boot/context/config/ConfigDataResource;ZLorg/springframework/boot/context/config/ConfigData;I)Lorg/springframework/boot/context/config/ConfigDataEnvironmentContributor;
      75: invokeinterface #346,  2          // InterfaceMethod java/util/List.add:(Ljava/lang/Object;)Z
      80: pop
      81: iinc          6, -1
      84: goto          58
      87: return

  private java.lang.CharSequence lambda$withProcessedImports$1(java.util.Map);
    Code:
       0: aload_0
       1: aload_1
       2: invokeinterface #354,  1          // InterfaceMethod java/util/Map.keySet:()Ljava/util/Set;
       7: invokevirtual #358                // Method getImportedMessage:(Ljava/util/Set;)Ljava/lang/CharSequence;
      10: areturn

  private static boolean lambda$static$0(org.springframework.boot.context.config.ConfigDataEnvironmentContributor);
    Code:
       0: iconst_1
       1: ireturn

  static {};
    Code:
       0: invokedynamic #362,  0            // InvokeDynamic #8:test:()Ljava/util/function/Predicate;
       5: putstatic     #229                // Field NO_CONTRIBUTOR_FILTER:Ljava/util/function/Predicate;
       8: return
}
