Compiled from "ConfigDataEnvironmentContributor.java"
final class org.springframework.boot.context.config.ConfigDataEnvironmentContributor$ContributorIterator implements java.util.Iterator<org.springframework.boot.context.config.ConfigDataEnvironmentContributor> {
  private org.springframework.boot.context.config.ConfigDataEnvironmentContributor$ImportPhase phase;

  private java.util.Iterator<org.springframework.boot.context.config.ConfigDataEnvironmentContributor> children;

  private java.util.Iterator<org.springframework.boot.context.config.ConfigDataEnvironmentContributor> current;

  private org.springframework.boot.context.config.ConfigDataEnvironmentContributor next;

  final org.springframework.boot.context.config.ConfigDataEnvironmentContributor this$0;

  private org.springframework.boot.context.config.ConfigDataEnvironmentContributor$ContributorIterator(org.springframework.boot.context.config.ConfigDataEnvironmentContributor);
    Code:
       0: aload_0
       1: aload_1
       2: putfield      #1                  // Field this$0:Lorg/springframework/boot/context/config/ConfigDataEnvironmentContributor;
       5: aload_0
       6: invokespecial #7                  // Method java/lang/Object."<init>":()V
       9: aload_0
      10: getstatic     #13                 // Field org/springframework/boot/context/config/ConfigDataEnvironmentContributor$ImportPhase.AFTER_PROFILE_ACTIVATION:Lorg/springframework/boot/context/config/ConfigDataEnvironmentContributor$ImportPhase;
      13: putfield      #19                 // Field phase:Lorg/springframework/boot/context/config/ConfigDataEnvironmentContributor$ImportPhase;
      16: aload_0
      17: aload_1
      18: aload_0
      19: getfield      #19                 // Field phase:Lorg/springframework/boot/context/config/ConfigDataEnvironmentContributor$ImportPhase;
      22: invokevirtual #22                 // Method org/springframework/boot/context/config/ConfigDataEnvironmentContributor.getChildren:(Lorg/springframework/boot/context/config/ConfigDataEnvironmentContributor$ImportPhase;)Ljava/util/List;
      25: invokeinterface #28,  1           // InterfaceMethod java/util/List.iterator:()Ljava/util/Iterator;
      30: putfield      #34                 // Field children:Ljava/util/Iterator;
      33: aload_0
      34: invokestatic  #38                 // Method java/util/Collections.emptyIterator:()Ljava/util/Iterator;
      37: putfield      #43                 // Field current:Ljava/util/Iterator;
      40: return

  public boolean hasNext();
    Code:
       0: aload_0
       1: invokevirtual #46                 // Method fetchIfNecessary:()Lorg/springframework/boot/context/config/ConfigDataEnvironmentContributor;
       4: ifnull        11
       7: iconst_1
       8: goto          12
      11: iconst_0
      12: ireturn

  public org.springframework.boot.context.config.ConfigDataEnvironmentContributor next();
    Code:
       0: aload_0
       1: invokevirtual #46                 // Method fetchIfNecessary:()Lorg/springframework/boot/context/config/ConfigDataEnvironmentContributor;
       4: astore_1
       5: aload_1
       6: ifnonnull     17
       9: new           #50                 // class java/util/NoSuchElementException
      12: dup
      13: invokespecial #52                 // Method java/util/NoSuchElementException."<init>":()V
      16: athrow
      17: aload_0
      18: aconst_null
      19: putfield      #53                 // Field next:Lorg/springframework/boot/context/config/ConfigDataEnvironmentContributor;
      22: aload_1
      23: areturn

  private org.springframework.boot.context.config.ConfigDataEnvironmentContributor fetchIfNecessary();
    Code:
       0: aload_0
       1: getfield      #53                 // Field next:Lorg/springframework/boot/context/config/ConfigDataEnvironmentContributor;
       4: ifnull        12
       7: aload_0
       8: getfield      #53                 // Field next:Lorg/springframework/boot/context/config/ConfigDataEnvironmentContributor;
      11: areturn
      12: aload_0
      13: getfield      #43                 // Field current:Ljava/util/Iterator;
      16: invokeinterface #56,  1           // InterfaceMethod java/util/Iterator.hasNext:()Z
      21: ifeq          45
      24: aload_0
      25: aload_0
      26: getfield      #43                 // Field current:Ljava/util/Iterator;
      29: invokeinterface #62,  1           // InterfaceMethod java/util/Iterator.next:()Ljava/lang/Object;
      34: checkcast     #23                 // class org/springframework/boot/context/config/ConfigDataEnvironmentContributor
      37: putfield      #53                 // Field next:Lorg/springframework/boot/context/config/ConfigDataEnvironmentContributor;
      40: aload_0
      41: getfield      #53                 // Field next:Lorg/springframework/boot/context/config/ConfigDataEnvironmentContributor;
      44: areturn
      45: aload_0
      46: getfield      #34                 // Field children:Ljava/util/Iterator;
      49: invokeinterface #56,  1           // InterfaceMethod java/util/Iterator.hasNext:()Z
      54: ifeq          81
      57: aload_0
      58: aload_0
      59: getfield      #34                 // Field children:Ljava/util/Iterator;
      62: invokeinterface #62,  1           // InterfaceMethod java/util/Iterator.next:()Ljava/lang/Object;
      67: checkcast     #23                 // class org/springframework/boot/context/config/ConfigDataEnvironmentContributor
      70: invokevirtual #65                 // Method org/springframework/boot/context/config/ConfigDataEnvironmentContributor.iterator:()Ljava/util/Iterator;
      73: putfield      #43                 // Field current:Ljava/util/Iterator;
      76: aload_0
      77: invokevirtual #46                 // Method fetchIfNecessary:()Lorg/springframework/boot/context/config/ConfigDataEnvironmentContributor;
      80: areturn
      81: aload_0
      82: getfield      #19                 // Field phase:Lorg/springframework/boot/context/config/ConfigDataEnvironmentContributor$ImportPhase;
      85: getstatic     #13                 // Field org/springframework/boot/context/config/ConfigDataEnvironmentContributor$ImportPhase.AFTER_PROFILE_ACTIVATION:Lorg/springframework/boot/context/config/ConfigDataEnvironmentContributor$ImportPhase;
      88: if_acmpne     123
      91: aload_0
      92: getstatic     #66                 // Field org/springframework/boot/context/config/ConfigDataEnvironmentContributor$ImportPhase.BEFORE_PROFILE_ACTIVATION:Lorg/springframework/boot/context/config/ConfigDataEnvironmentContributor$ImportPhase;
      95: putfield      #19                 // Field phase:Lorg/springframework/boot/context/config/ConfigDataEnvironmentContributor$ImportPhase;
      98: aload_0
      99: aload_0
     100: getfield      #1                  // Field this$0:Lorg/springframework/boot/context/config/ConfigDataEnvironmentContributor;
     103: aload_0
     104: getfield      #19                 // Field phase:Lorg/springframework/boot/context/config/ConfigDataEnvironmentContributor$ImportPhase;
     107: invokevirtual #22                 // Method org/springframework/boot/context/config/ConfigDataEnvironmentContributor.getChildren:(Lorg/springframework/boot/context/config/ConfigDataEnvironmentContributor$ImportPhase;)Ljava/util/List;
     110: invokeinterface #28,  1           // InterfaceMethod java/util/List.iterator:()Ljava/util/Iterator;
     115: putfield      #34                 // Field children:Ljava/util/Iterator;
     118: aload_0
     119: invokevirtual #46                 // Method fetchIfNecessary:()Lorg/springframework/boot/context/config/ConfigDataEnvironmentContributor;
     122: areturn
     123: aload_0
     124: getfield      #19                 // Field phase:Lorg/springframework/boot/context/config/ConfigDataEnvironmentContributor$ImportPhase;
     127: getstatic     #66                 // Field org/springframework/boot/context/config/ConfigDataEnvironmentContributor$ImportPhase.BEFORE_PROFILE_ACTIVATION:Lorg/springframework/boot/context/config/ConfigDataEnvironmentContributor$ImportPhase;
     130: if_acmpne     151
     133: aload_0
     134: aconst_null
     135: putfield      #19                 // Field phase:Lorg/springframework/boot/context/config/ConfigDataEnvironmentContributor$ImportPhase;
     138: aload_0
     139: aload_0
     140: getfield      #1                  // Field this$0:Lorg/springframework/boot/context/config/ConfigDataEnvironmentContributor;
     143: putfield      #53                 // Field next:Lorg/springframework/boot/context/config/ConfigDataEnvironmentContributor;
     146: aload_0
     147: getfield      #53                 // Field next:Lorg/springframework/boot/context/config/ConfigDataEnvironmentContributor;
     150: areturn
     151: aconst_null
     152: areturn

  public java.lang.Object next();
    Code:
       0: aload_0
       1: invokevirtual #69                 // Method next:()Lorg/springframework/boot/context/config/ConfigDataEnvironmentContributor;
       4: areturn
}
