Compiled from "ConfigData.java"
public final class org.springframework.boot.context.config.ConfigData$Options {
  public static final org.springframework.boot.context.config.ConfigData$Options NONE;

  private final java.util.Set<org.springframework.boot.context.config.ConfigData$Option> options;

  private org.springframework.boot.context.config.ConfigData$Options(java.util.Set<org.springframework.boot.context.config.ConfigData$Option>);
    Code:
       0: aload_0
       1: invokespecial #1                  // Method java/lang/Object."<init>":()V
       4: aload_0
       5: aload_1
       6: invokestatic  #7                  // Method java/util/Collections.unmodifiableSet:(Ljava/util/Set;)Ljava/util/Set;
       9: putfield      #13                 // Field options:Ljava/util/Set;
      12: return

  java.util.Set<org.springframework.boot.context.config.ConfigData$Option> asSet();
    Code:
       0: aload_0
       1: getfield      #13                 // Field options:Ljava/util/Set;
       4: areturn

  public boolean contains(org.springframework.boot.context.config.ConfigData$Option);
    Code:
       0: aload_0
       1: getfield      #13                 // Field options:Ljava/util/Set;
       4: aload_1
       5: invokeinterface #19,  2           // InterfaceMethod java/util/Set.contains:(Ljava/lang/Object;)Z
      10: ireturn

  public boolean equals(java.lang.Object);
    Code:
       0: aload_0
       1: aload_1
       2: if_acmpne     7
       5: iconst_1
       6: ireturn
       7: aload_1
       8: ifnull        22
      11: aload_0
      12: invokevirtual #25                 // Method java/lang/Object.getClass:()Ljava/lang/Class;
      15: aload_1
      16: invokevirtual #25                 // Method java/lang/Object.getClass:()Ljava/lang/Class;
      19: if_acmpeq     24
      22: iconst_0
      23: ireturn
      24: aload_1
      25: checkcast     #14                 // class org/springframework/boot/context/config/ConfigData$Options
      28: astore_2
      29: aload_0
      30: getfield      #13                 // Field options:Ljava/util/Set;
      33: aload_2
      34: getfield      #13                 // Field options:Ljava/util/Set;
      37: invokeinterface #29,  2           // InterfaceMethod java/util/Set.equals:(Ljava/lang/Object;)Z
      42: ireturn

  public int hashCode();
    Code:
       0: aload_0
       1: getfield      #13                 // Field options:Ljava/util/Set;
       4: invokeinterface #32,  1           // InterfaceMethod java/util/Set.hashCode:()I
       9: ireturn

  public java.lang.String toString();
    Code:
       0: aload_0
       1: getfield      #13                 // Field options:Ljava/util/Set;
       4: invokevirtual #36                 // Method java/lang/Object.toString:()Ljava/lang/String;
       7: areturn

  public org.springframework.boot.context.config.ConfigData$Options without(org.springframework.boot.context.config.ConfigData$Option);
    Code:
       0: aload_0
       1: aload_1
       2: invokedynamic #40,  0             // InvokeDynamic #0:accept:(Lorg/springframework/boot/context/config/ConfigData$Option;)Ljava/util/function/Consumer;
       7: invokevirtual #44                 // Method copy:(Ljava/util/function/Consumer;)Lorg/springframework/boot/context/config/ConfigData$Options;
      10: areturn

  public org.springframework.boot.context.config.ConfigData$Options with(org.springframework.boot.context.config.ConfigData$Option);
    Code:
       0: aload_0
       1: aload_1
       2: invokedynamic #48,  0             // InvokeDynamic #1:accept:(Lorg/springframework/boot/context/config/ConfigData$Option;)Ljava/util/function/Consumer;
       7: invokevirtual #44                 // Method copy:(Ljava/util/function/Consumer;)Lorg/springframework/boot/context/config/ConfigData$Options;
      10: areturn

  private org.springframework.boot.context.config.ConfigData$Options copy(java.util.function.Consumer<java.util.EnumSet<org.springframework.boot.context.config.ConfigData$Option>>);
    Code:
       0: ldc           #49                 // class org/springframework/boot/context/config/ConfigData$Option
       2: invokestatic  #51                 // Method java/util/EnumSet.noneOf:(Ljava/lang/Class;)Ljava/util/EnumSet;
       5: astore_2
       6: aload_2
       7: aload_0
       8: getfield      #13                 // Field options:Ljava/util/Set;
      11: invokevirtual #57                 // Method java/util/EnumSet.addAll:(Ljava/util/Collection;)Z
      14: pop
      15: aload_1
      16: aload_2
      17: invokeinterface #61,  2           // InterfaceMethod java/util/function/Consumer.accept:(Ljava/lang/Object;)V
      22: new           #14                 // class org/springframework/boot/context/config/ConfigData$Options
      25: dup
      26: aload_2
      27: invokespecial #66                 // Method "<init>":(Ljava/util/Set;)V
      30: areturn

  public static org.springframework.boot.context.config.ConfigData$Options of(org.springframework.boot.context.config.ConfigData$Option...);
    Code:
       0: aload_0
       1: ldc           #69                 // String Options must not be null
       3: invokestatic  #71                 // Method org/springframework/util/Assert.notNull:(Ljava/lang/Object;Ljava/lang/String;)V
       6: aload_0
       7: arraylength
       8: ifne          15
      11: getstatic     #77                 // Field NONE:Lorg/springframework/boot/context/config/ConfigData$Options;
      14: areturn
      15: new           #14                 // class org/springframework/boot/context/config/ConfigData$Options
      18: dup
      19: aload_0
      20: invokestatic  #81                 // Method java/util/Arrays.asList:([Ljava/lang/Object;)Ljava/util/List;
      23: invokestatic  #87                 // Method java/util/EnumSet.copyOf:(Ljava/util/Collection;)Ljava/util/EnumSet;
      26: invokespecial #66                 // Method "<init>":(Ljava/util/Set;)V
      29: areturn

  private static void lambda$with$1(org.springframework.boot.context.config.ConfigData$Option, java.util.EnumSet);
    Code:
       0: aload_1
       1: aload_0
       2: invokevirtual #91                 // Method java/util/EnumSet.add:(Ljava/lang/Object;)Z
       5: pop
       6: return

  private static void lambda$without$0(org.springframework.boot.context.config.ConfigData$Option, java.util.EnumSet);
    Code:
       0: aload_1
       1: aload_0
       2: invokevirtual #94                 // Method java/util/EnumSet.remove:(Ljava/lang/Object;)Z
       5: pop
       6: return

  static {};
    Code:
       0: new           #14                 // class org/springframework/boot/context/config/ConfigData$Options
       3: dup
       4: invokestatic  #97                 // Method java/util/Collections.emptySet:()Ljava/util/Set;
       7: invokespecial #66                 // Method "<init>":(Ljava/util/Set;)V
      10: putstatic     #77                 // Field NONE:Lorg/springframework/boot/context/config/ConfigData$Options;
      13: return
}
