Compiled from "ConfigDataEnvironmentContributors.java"
class org.springframework.boot.context.config.ConfigDataEnvironmentContributors$ContributorConfigDataLocationResolverContext implements org.springframework.boot.context.config.ConfigDataLocationResolverContext {
  private final org.springframework.boot.context.config.ConfigDataEnvironmentContributors contributors;

  private final org.springframework.boot.context.config.ConfigDataEnvironmentContributor contributor;

  private final org.springframework.boot.context.config.ConfigDataActivationContext activationContext;

  private volatile org.springframework.boot.context.properties.bind.Binder binder;

  org.springframework.boot.context.config.ConfigDataEnvironmentContributors$ContributorConfigDataLocationResolverContext(org.springframework.boot.context.config.ConfigDataEnvironmentContributors, org.springframework.boot.context.config.ConfigDataEnvironmentContributor, org.springframework.boot.context.config.ConfigDataActivationContext);
    Code:
       0: aload_0
       1: invokespecial #1                  // Method java/lang/Object."<init>":()V
       4: aload_0
       5: aload_1
       6: putfield      #7                  // Field contributors:Lorg/springframework/boot/context/config/ConfigDataEnvironmentContributors;
       9: aload_0
      10: aload_2
      11: putfield      #13                 // Field contributor:Lorg/springframework/boot/context/config/ConfigDataEnvironmentContributor;
      14: aload_0
      15: aload_3
      16: putfield      #17                 // Field activationContext:Lorg/springframework/boot/context/config/ConfigDataActivationContext;
      19: return

  public org.springframework.boot.context.properties.bind.Binder getBinder();
    Code:
       0: aload_0
       1: getfield      #21                 // Field binder:Lorg/springframework/boot/context/properties/bind/Binder;
       4: astore_1
       5: aload_1
       6: ifnonnull     30
       9: aload_0
      10: getfield      #7                  // Field contributors:Lorg/springframework/boot/context/config/ConfigDataEnvironmentContributors;
      13: aload_0
      14: getfield      #17                 // Field activationContext:Lorg/springframework/boot/context/config/ConfigDataActivationContext;
      17: iconst_0
      18: anewarray     #25                 // class org/springframework/boot/context/config/ConfigDataEnvironmentContributors$BinderOption
      21: invokevirtual #27                 // Method org/springframework/boot/context/config/ConfigDataEnvironmentContributors.getBinder:(Lorg/springframework/boot/context/config/ConfigDataActivationContext;[Lorg/springframework/boot/context/config/ConfigDataEnvironmentContributors$BinderOption;)Lorg/springframework/boot/context/properties/bind/Binder;
      24: astore_1
      25: aload_0
      26: aload_1
      27: putfield      #21                 // Field binder:Lorg/springframework/boot/context/properties/bind/Binder;
      30: aload_1
      31: areturn

  public org.springframework.boot.context.config.ConfigDataResource getParent();
    Code:
       0: aload_0
       1: getfield      #13                 // Field contributor:Lorg/springframework/boot/context/config/ConfigDataEnvironmentContributor;
       4: invokevirtual #33                 // Method org/springframework/boot/context/config/ConfigDataEnvironmentContributor.getResource:()Lorg/springframework/boot/context/config/ConfigDataResource;
       7: areturn

  public org.springframework.boot.ConfigurableBootstrapContext getBootstrapContext();
    Code:
       0: aload_0
       1: getfield      #7                  // Field contributors:Lorg/springframework/boot/context/config/ConfigDataEnvironmentContributors;
       4: invokevirtual #39                 // Method org/springframework/boot/context/config/ConfigDataEnvironmentContributors.getBootstrapContext:()Lorg/springframework/boot/ConfigurableBootstrapContext;
       7: areturn
}
