Compiled from "ConfigDataActivationContext.java"
class org.springframework.boot.context.config.ConfigDataActivationContext {
  private final org.springframework.boot.cloud.CloudPlatform cloudPlatform;

  private final org.springframework.boot.context.config.Profiles profiles;

  org.springframework.boot.context.config.ConfigDataActivationContext(org.springframework.core.env.Environment, org.springframework.boot.context.properties.bind.Binder);
    Code:
       0: aload_0
       1: invokespecial #1                  // Method java/lang/Object."<init>":()V
       4: aload_0
       5: aload_0
       6: aload_1
       7: aload_2
       8: invokevirtual #7                  // Method deduceCloudPlatform:(Lorg/springframework/core/env/Environment;Lorg/springframework/boot/context/properties/bind/Binder;)Lorg/springframework/boot/cloud/CloudPlatform;
      11: putfield      #13                 // Field cloudPlatform:Lorg/springframework/boot/cloud/CloudPlatform;
      14: aload_0
      15: aconst_null
      16: putfield      #17                 // Field profiles:Lorg/springframework/boot/context/config/Profiles;
      19: return

  org.springframework.boot.context.config.ConfigDataActivationContext(org.springframework.boot.cloud.CloudPlatform, org.springframework.boot.context.config.Profiles);
    Code:
       0: aload_0
       1: invokespecial #1                  // Method java/lang/Object."<init>":()V
       4: aload_0
       5: aload_1
       6: putfield      #13                 // Field cloudPlatform:Lorg/springframework/boot/cloud/CloudPlatform;
       9: aload_0
      10: aload_2
      11: putfield      #17                 // Field profiles:Lorg/springframework/boot/context/config/Profiles;
      14: return

  private org.springframework.boot.cloud.CloudPlatform deduceCloudPlatform(org.springframework.core.env.Environment, org.springframework.boot.context.properties.bind.Binder);
    Code:
       0: invokestatic  #21                 // Method org/springframework/boot/cloud/CloudPlatform.values:()[Lorg/springframework/boot/cloud/CloudPlatform;
       3: astore_3
       4: aload_3
       5: arraylength
       6: istore        4
       8: iconst_0
       9: istore        5
      11: iload         5
      13: iload         4
      15: if_icmpge     42
      18: aload_3
      19: iload         5
      21: aaload
      22: astore        6
      24: aload         6
      26: aload_2
      27: invokevirtual #27                 // Method org/springframework/boot/cloud/CloudPlatform.isEnforced:(Lorg/springframework/boot/context/properties/bind/Binder;)Z
      30: ifeq          36
      33: aload         6
      35: areturn
      36: iinc          5, 1
      39: goto          11
      42: aload_1
      43: invokestatic  #31                 // Method org/springframework/boot/cloud/CloudPlatform.getActive:(Lorg/springframework/core/env/Environment;)Lorg/springframework/boot/cloud/CloudPlatform;
      46: areturn

  org.springframework.boot.context.config.ConfigDataActivationContext withProfiles(org.springframework.boot.context.config.Profiles);
    Code:
       0: new           #8                  // class org/springframework/boot/context/config/ConfigDataActivationContext
       3: dup
       4: aload_0
       5: getfield      #13                 // Field cloudPlatform:Lorg/springframework/boot/cloud/CloudPlatform;
       8: aload_1
       9: invokespecial #35                 // Method "<init>":(Lorg/springframework/boot/cloud/CloudPlatform;Lorg/springframework/boot/context/config/Profiles;)V
      12: areturn

  org.springframework.boot.cloud.CloudPlatform getCloudPlatform();
    Code:
       0: aload_0
       1: getfield      #13                 // Field cloudPlatform:Lorg/springframework/boot/cloud/CloudPlatform;
       4: areturn

  org.springframework.boot.context.config.Profiles getProfiles();
    Code:
       0: aload_0
       1: getfield      #17                 // Field profiles:Lorg/springframework/boot/context/config/Profiles;
       4: areturn

  public java.lang.String toString();
    Code:
       0: new           #38                 // class org/springframework/core/style/ToStringCreator
       3: dup
       4: aload_0
       5: invokespecial #40                 // Method org/springframework/core/style/ToStringCreator."<init>":(Ljava/lang/Object;)V
       8: astore_1
       9: aload_1
      10: ldc           #43                 // String cloudPlatform
      12: aload_0
      13: getfield      #13                 // Field cloudPlatform:Lorg/springframework/boot/cloud/CloudPlatform;
      16: invokevirtual #44                 // Method org/springframework/core/style/ToStringCreator.append:(Ljava/lang/String;Ljava/lang/Object;)Lorg/springframework/core/style/ToStringCreator;
      19: pop
      20: aload_1
      21: ldc           #48                 // String profiles
      23: aload_0
      24: getfield      #17                 // Field profiles:Lorg/springframework/boot/context/config/Profiles;
      27: invokevirtual #44                 // Method org/springframework/core/style/ToStringCreator.append:(Ljava/lang/String;Ljava/lang/Object;)Lorg/springframework/core/style/ToStringCreator;
      30: pop
      31: aload_1
      32: invokevirtual #49                 // Method org/springframework/core/style/ToStringCreator.toString:()Ljava/lang/String;
      35: areturn
}
