Compiled from "ConfigDataEnvironmentPostProcessor.java"
public class org.springframework.boot.context.config.ConfigDataEnvironmentPostProcessor implements org.springframework.boot.env.EnvironmentPostProcessor,org.springframework.core.Ordered {
  public static final int ORDER;

  public static final java.lang.String ON_LOCATION_NOT_FOUND_PROPERTY;

  private final org.springframework.boot.logging.DeferredLogFactory logFactory;

  private final org.apache.commons.logging.Log logger;

  private final org.springframework.boot.ConfigurableBootstrapContext bootstrapContext;

  private final org.springframework.boot.context.config.ConfigDataEnvironmentUpdateListener environmentUpdateListener;

  public org.springframework.boot.context.config.ConfigDataEnvironmentPostProcessor(org.springframework.boot.logging.DeferredLogFactory, org.springframework.boot.ConfigurableBootstrapContext);
    Code:
       0: aload_0
       1: aload_1
       2: aload_2
       3: aconst_null
       4: invokespecial #5                  // Method "<init>":(Lorg/springframework/boot/logging/DeferredLogFactory;Lorg/springframework/boot/ConfigurableBootstrapContext;Lorg/springframework/boot/context/config/ConfigDataEnvironmentUpdateListener;)V
       7: return

  private org.springframework.boot.context.config.ConfigDataEnvironmentPostProcessor(org.springframework.boot.logging.DeferredLogFactory, org.springframework.boot.ConfigurableBootstrapContext, org.springframework.boot.context.config.ConfigDataEnvironmentUpdateListener);
    Code:
       0: aload_0
       1: invokespecial #11                 // Method java/lang/Object."<init>":()V
       4: aload_0
       5: aload_1
       6: putfield      #16                 // Field logFactory:Lorg/springframework/boot/logging/DeferredLogFactory;
       9: aload_0
      10: aload_1
      11: aload_0
      12: invokevirtual #20                 // Method java/lang/Object.getClass:()Ljava/lang/Class;
      15: invokeinterface #24,  2           // InterfaceMethod org/springframework/boot/logging/DeferredLogFactory.getLog:(Ljava/lang/Class;)Lorg/apache/commons/logging/Log;
      20: putfield      #30                 // Field logger:Lorg/apache/commons/logging/Log;
      23: aload_0
      24: aload_2
      25: putfield      #34                 // Field bootstrapContext:Lorg/springframework/boot/ConfigurableBootstrapContext;
      28: aload_0
      29: aload_3
      30: putfield      #38                 // Field environmentUpdateListener:Lorg/springframework/boot/context/config/ConfigDataEnvironmentUpdateListener;
      33: return

  public int getOrder();
    Code:
       0: ldc           #42                 // int -2147483638
       2: ireturn

  public void postProcessEnvironment(org.springframework.core.env.ConfigurableEnvironment, org.springframework.boot.SpringApplication);
    Code:
       0: aload_0
       1: aload_1
       2: aload_2
       3: invokevirtual #43                 // Method org/springframework/boot/SpringApplication.getResourceLoader:()Lorg/springframework/core/io/ResourceLoader;
       6: aload_2
       7: invokevirtual #49                 // Method org/springframework/boot/SpringApplication.getAdditionalProfiles:()Ljava/util/Set;
      10: invokevirtual #53                 // Method postProcessEnvironment:(Lorg/springframework/core/env/ConfigurableEnvironment;Lorg/springframework/core/io/ResourceLoader;Ljava/util/Collection;)V
      13: return

  void postProcessEnvironment(org.springframework.core.env.ConfigurableEnvironment, org.springframework.core.io.ResourceLoader, java.util.Collection<java.lang.String>);
    Code:
       0: aload_0
       1: getfield      #30                 // Field logger:Lorg/apache/commons/logging/Log;
       4: ldc           #57                 // String Post-processing environment to add config data
       6: invokeinterface #59,  2           // InterfaceMethod org/apache/commons/logging/Log.trace:(Ljava/lang/Object;)V
      11: aload_2
      12: ifnull        19
      15: aload_2
      16: goto          26
      19: new           #65                 // class org/springframework/core/io/DefaultResourceLoader
      22: dup
      23: invokespecial #67                 // Method org/springframework/core/io/DefaultResourceLoader."<init>":()V
      26: astore_2
      27: aload_0
      28: aload_1
      29: aload_2
      30: aload_3
      31: invokevirtual #68                 // Method getConfigDataEnvironment:(Lorg/springframework/core/env/ConfigurableEnvironment;Lorg/springframework/core/io/ResourceLoader;Ljava/util/Collection;)Lorg/springframework/boot/context/config/ConfigDataEnvironment;
      34: invokevirtual #72                 // Method org/springframework/boot/context/config/ConfigDataEnvironment.processAndApply:()V
      37: return

  org.springframework.boot.context.config.ConfigDataEnvironment getConfigDataEnvironment(org.springframework.core.env.ConfigurableEnvironment, org.springframework.core.io.ResourceLoader, java.util.Collection<java.lang.String>);
    Code:
       0: new           #3                  // class org/springframework/boot/context/config/ConfigDataEnvironment
       3: dup
       4: aload_0
       5: getfield      #16                 // Field logFactory:Lorg/springframework/boot/logging/DeferredLogFactory;
       8: aload_0
       9: getfield      #34                 // Field bootstrapContext:Lorg/springframework/boot/ConfigurableBootstrapContext;
      12: aload_1
      13: aload_2
      14: aload_3
      15: aload_0
      16: getfield      #38                 // Field environmentUpdateListener:Lorg/springframework/boot/context/config/ConfigDataEnvironmentUpdateListener;
      19: invokespecial #75                 // Method org/springframework/boot/context/config/ConfigDataEnvironment."<init>":(Lorg/springframework/boot/logging/DeferredLogFactory;Lorg/springframework/boot/ConfigurableBootstrapContext;Lorg/springframework/core/env/ConfigurableEnvironment;Lorg/springframework/core/io/ResourceLoader;Ljava/util/Collection;Lorg/springframework/boot/context/config/ConfigDataEnvironmentUpdateListener;)V
      22: areturn

  public static void applyTo(org.springframework.core.env.ConfigurableEnvironment);
    Code:
       0: aload_0
       1: aconst_null
       2: aconst_null
       3: invokestatic  #78                 // Method java/util/Collections.emptyList:()Ljava/util/List;
       6: invokestatic  #84                 // Method applyTo:(Lorg/springframework/core/env/ConfigurableEnvironment;Lorg/springframework/core/io/ResourceLoader;Lorg/springframework/boot/ConfigurableBootstrapContext;Ljava/util/Collection;)V
       9: return

  public static void applyTo(org.springframework.core.env.ConfigurableEnvironment, org.springframework.core.io.ResourceLoader, org.springframework.boot.ConfigurableBootstrapContext, java.lang.String...);
    Code:
       0: aload_0
       1: aload_1
       2: aload_2
       3: aload_3
       4: invokestatic  #88                 // Method java/util/Arrays.asList:([Ljava/lang/Object;)Ljava/util/List;
       7: invokestatic  #84                 // Method applyTo:(Lorg/springframework/core/env/ConfigurableEnvironment;Lorg/springframework/core/io/ResourceLoader;Lorg/springframework/boot/ConfigurableBootstrapContext;Ljava/util/Collection;)V
      10: return

  public static void applyTo(org.springframework.core.env.ConfigurableEnvironment, org.springframework.core.io.ResourceLoader, org.springframework.boot.ConfigurableBootstrapContext, java.util.Collection<java.lang.String>);
    Code:
       0: invokedynamic #94,  0             // InvokeDynamic #0:getLog:()Lorg/springframework/boot/logging/DeferredLogFactory;
       5: astore        4
       7: aload_2
       8: ifnull        15
      11: aload_2
      12: goto          22
      15: new           #97                 // class org/springframework/boot/DefaultBootstrapContext
      18: dup
      19: invokespecial #99                 // Method org/springframework/boot/DefaultBootstrapContext."<init>":()V
      22: astore_2
      23: new           #6                  // class org/springframework/boot/context/config/ConfigDataEnvironmentPostProcessor
      26: dup
      27: aload         4
      29: aload_2
      30: invokespecial #100                // Method "<init>":(Lorg/springframework/boot/logging/DeferredLogFactory;Lorg/springframework/boot/ConfigurableBootstrapContext;)V
      33: astore        5
      35: aload         5
      37: aload_0
      38: aload_1
      39: aload_3
      40: invokevirtual #53                 // Method postProcessEnvironment:(Lorg/springframework/core/env/ConfigurableEnvironment;Lorg/springframework/core/io/ResourceLoader;Ljava/util/Collection;)V
      43: return

  public static void applyTo(org.springframework.core.env.ConfigurableEnvironment, org.springframework.core.io.ResourceLoader, org.springframework.boot.ConfigurableBootstrapContext, java.util.Collection<java.lang.String>, org.springframework.boot.context.config.ConfigDataEnvironmentUpdateListener);
    Code:
       0: invokedynamic #94,  0             // InvokeDynamic #0:getLog:()Lorg/springframework/boot/logging/DeferredLogFactory;
       5: astore        5
       7: aload_2
       8: ifnull        15
      11: aload_2
      12: goto          22
      15: new           #97                 // class org/springframework/boot/DefaultBootstrapContext
      18: dup
      19: invokespecial #99                 // Method org/springframework/boot/DefaultBootstrapContext."<init>":()V
      22: astore_2
      23: new           #6                  // class org/springframework/boot/context/config/ConfigDataEnvironmentPostProcessor
      26: dup
      27: aload         5
      29: aload_2
      30: aload         4
      32: invokespecial #5                  // Method "<init>":(Lorg/springframework/boot/logging/DeferredLogFactory;Lorg/springframework/boot/ConfigurableBootstrapContext;Lorg/springframework/boot/context/config/ConfigDataEnvironmentUpdateListener;)V
      35: astore        6
      37: aload         6
      39: aload_0
      40: aload_1
      41: aload_3
      42: invokevirtual #53                 // Method postProcessEnvironment:(Lorg/springframework/core/env/ConfigurableEnvironment;Lorg/springframework/core/io/ResourceLoader;Ljava/util/Collection;)V
      45: return
}
