Compiled from "ConfigData.java"
class org.springframework.boot.context.config.ConfigData$AlwaysPropertySourceOptions implements org.springframework.boot.context.config.ConfigData$PropertySourceOptions {
  private final org.springframework.boot.context.config.ConfigData$Options options;

  org.springframework.boot.context.config.ConfigData$AlwaysPropertySourceOptions(org.springframework.boot.context.config.ConfigData$Options);
    Code:
       0: aload_0
       1: invokespecial #1                  // Method java/lang/Object."<init>":()V
       4: aload_0
       5: aload_1
       6: putfield      #7                  // Field options:Lorg/springframework/boot/context/config/ConfigData$Options;
       9: return

  public org.springframework.boot.context.config.ConfigData$Options get(org.springframework.core.env.PropertySource<?>);
    Code:
       0: aload_0
       1: getfield      #7                  // Field options:Lorg/springframework/boot/context/config/ConfigData$Options;
       4: areturn
}
