Compiled from "ConfigTreeConfigDataLoader.java"
public class org.springframework.boot.context.config.ConfigTreeConfigDataLoader implements org.springframework.boot.context.config.ConfigDataLoader<org.springframework.boot.context.config.ConfigTreeConfigDataResource> {
  public org.springframework.boot.context.config.ConfigTreeConfigDataLoader();
    Code:
       0: aload_0
       1: invokespecial #1                  // Method java/lang/Object."<init>":()V
       4: return

  public org.springframework.boot.context.config.ConfigData load(org.springframework.boot.context.config.ConfigDataLoaderContext, org.springframework.boot.context.config.ConfigTreeConfigDataResource) throws java.io.IOException, org.springframework.boot.context.config.ConfigDataResourceNotFoundException;
    Code:
       0: aload_2
       1: invokevirtual #7                  // Method org/springframework/boot/context/config/ConfigTreeConfigDataResource.getPath:()Ljava/nio/file/Path;
       4: astore_3
       5: aload_2
       6: aload_3
       7: invokestatic  #13                 // Method org/springframework/boot/context/config/ConfigDataResourceNotFoundException.throwIfDoesNotExist:(Lorg/springframework/boot/context/config/ConfigDataResource;Ljava/nio/file/Path;)V
      10: aload_3
      11: invokedynamic #19,  0             // InvokeDynamic #0:makeConcatWithConstants:(Ljava/nio/file/Path;)Ljava/lang/String;
      16: astore        4
      18: new           #23                 // class org/springframework/boot/env/ConfigTreePropertySource
      21: dup
      22: aload         4
      24: aload_3
      25: iconst_1
      26: anewarray     #25                 // class org/springframework/boot/env/ConfigTreePropertySource$Option
      29: dup
      30: iconst_0
      31: getstatic     #27                 // Field org/springframework/boot/env/ConfigTreePropertySource$Option.AUTO_TRIM_TRAILING_NEW_LINE:Lorg/springframework/boot/env/ConfigTreePropertySource$Option;
      34: aastore
      35: invokespecial #31                 // Method org/springframework/boot/env/ConfigTreePropertySource."<init>":(Ljava/lang/String;Ljava/nio/file/Path;[Lorg/springframework/boot/env/ConfigTreePropertySource$Option;)V
      38: astore        5
      40: new           #34                 // class org/springframework/boot/context/config/ConfigData
      43: dup
      44: aload         5
      46: invokestatic  #36                 // Method java/util/Collections.singletonList:(Ljava/lang/Object;)Ljava/util/List;
      49: iconst_0
      50: anewarray     #42                 // class org/springframework/boot/context/config/ConfigData$Option
      53: invokespecial #44                 // Method org/springframework/boot/context/config/ConfigData."<init>":(Ljava/util/Collection;[Lorg/springframework/boot/context/config/ConfigData$Option;)V
      56: areturn

  public org.springframework.boot.context.config.ConfigData load(org.springframework.boot.context.config.ConfigDataLoaderContext, org.springframework.boot.context.config.ConfigDataResource) throws java.io.IOException, org.springframework.boot.context.config.ConfigDataResourceNotFoundException;
    Code:
       0: aload_0
       1: aload_1
       2: aload_2
       3: checkcast     #8                  // class org/springframework/boot/context/config/ConfigTreeConfigDataResource
       6: invokevirtual #47                 // Method load:(Lorg/springframework/boot/context/config/ConfigDataLoaderContext;Lorg/springframework/boot/context/config/ConfigTreeConfigDataResource;)Lorg/springframework/boot/context/config/ConfigData;
       9: areturn
}
