Compiled from "ConfigDataEnvironmentContributorPlaceholdersResolver.java"
class org.springframework.boot.context.config.ConfigDataEnvironmentContributorPlaceholdersResolver implements org.springframework.boot.context.properties.bind.PlaceholdersResolver {
  private final java.lang.Iterable<org.springframework.boot.context.config.ConfigDataEnvironmentContributor> contributors;

  private final org.springframework.boot.context.config.ConfigDataActivationContext activationContext;

  private final boolean failOnResolveFromInactiveContributor;

  private final org.springframework.util.PropertyPlaceholderHelper helper;

  private final org.springframework.boot.context.config.ConfigDataEnvironmentContributor activeContributor;

  org.springframework.boot.context.config.ConfigDataEnvironmentContributorPlaceholdersResolver(java.lang.Iterable<org.springframework.boot.context.config.ConfigDataEnvironmentContributor>, org.springframework.boot.context.config.ConfigDataActivationContext, org.springframework.boot.context.config.ConfigDataEnvironmentContributor, boolean);
    Code:
       0: aload_0
       1: invokespecial #1                  // Method java/lang/Object."<init>":()V
       4: aload_0
       5: aload_1
       6: putfield      #7                  // Field contributors:Ljava/lang/Iterable;
       9: aload_0
      10: aload_2
      11: putfield      #13                 // Field activationContext:Lorg/springframework/boot/context/config/ConfigDataActivationContext;
      14: aload_0
      15: aload_3
      16: putfield      #17                 // Field activeContributor:Lorg/springframework/boot/context/config/ConfigDataEnvironmentContributor;
      19: aload_0
      20: iload         4
      22: putfield      #21                 // Field failOnResolveFromInactiveContributor:Z
      25: aload_0
      26: new           #25                 // class org/springframework/util/PropertyPlaceholderHelper
      29: dup
      30: ldc           #29                 // String ${
      32: ldc           #31                 // String }
      34: ldc           #33                 // String :
      36: iconst_1
      37: invokespecial #35                 // Method org/springframework/util/PropertyPlaceholderHelper."<init>":(Ljava/lang/String;Ljava/lang/String;Ljava/lang/String;Z)V
      40: putfield      #38                 // Field helper:Lorg/springframework/util/PropertyPlaceholderHelper;
      43: return

  public java.lang.Object resolvePlaceholders(java.lang.Object);
    Code:
       0: aload_1
       1: instanceof    #42                 // class java/lang/String
       4: ifeq          27
       7: aload_1
       8: checkcast     #42                 // class java/lang/String
      11: astore_2
      12: aload_0
      13: getfield      #38                 // Field helper:Lorg/springframework/util/PropertyPlaceholderHelper;
      16: aload_2
      17: aload_0
      18: invokedynamic #44,  0             // InvokeDynamic #0:resolvePlaceholder:(Lorg/springframework/boot/context/config/ConfigDataEnvironmentContributorPlaceholdersResolver;)Lorg/springframework/util/PropertyPlaceholderHelper$PlaceholderResolver;
      23: invokevirtual #48                 // Method org/springframework/util/PropertyPlaceholderHelper.replacePlaceholders:(Ljava/lang/String;Lorg/springframework/util/PropertyPlaceholderHelper$PlaceholderResolver;)Ljava/lang/String;
      26: areturn
      27: aload_1
      28: areturn

  private java.lang.String resolvePlaceholder(java.lang.String);
    Code:
       0: aconst_null
       1: astore_2
       2: aload_0
       3: getfield      #7                  // Field contributors:Ljava/lang/Iterable;
       6: invokeinterface #52,  1           // InterfaceMethod java/lang/Iterable.iterator:()Ljava/util/Iterator;
      11: astore_3
      12: aload_3
      13: invokeinterface #58,  1           // InterfaceMethod java/util/Iterator.hasNext:()Z
      18: ifeq          124
      21: aload_3
      22: invokeinterface #64,  1           // InterfaceMethod java/util/Iterator.next:()Ljava/lang/Object;
      27: checkcast     #68                 // class org/springframework/boot/context/config/ConfigDataEnvironmentContributor
      30: astore        4
      32: aload         4
      34: invokevirtual #70                 // Method org/springframework/boot/context/config/ConfigDataEnvironmentContributor.getPropertySource:()Lorg/springframework/core/env/PropertySource;
      37: astore        5
      39: aload         5
      41: ifnull        53
      44: aload         5
      46: aload_1
      47: invokevirtual #74                 // Method org/springframework/core/env/PropertySource.getProperty:(Ljava/lang/String;)Ljava/lang/Object;
      50: goto          54
      53: aconst_null
      54: astore        6
      56: aload         6
      58: ifnull        110
      61: aload_0
      62: aload         4
      64: invokevirtual #80                 // Method isActive:(Lorg/springframework/boot/context/config/ConfigDataEnvironmentContributor;)Z
      67: ifne          110
      70: aload_0
      71: getfield      #21                 // Field failOnResolveFromInactiveContributor:Z
      74: ifeq          107
      77: aload         4
      79: invokevirtual #84                 // Method org/springframework/boot/context/config/ConfigDataEnvironmentContributor.getResource:()Lorg/springframework/boot/context/config/ConfigDataResource;
      82: astore        7
      84: aload         5
      86: aload_1
      87: invokestatic  #88                 // InterfaceMethod org/springframework/boot/origin/OriginLookup.getOrigin:(Ljava/lang/Object;Ljava/lang/Object;)Lorg/springframework/boot/origin/Origin;
      90: astore        8
      92: new           #94                 // class org/springframework/boot/context/config/InactiveConfigDataAccessException
      95: dup
      96: aload         5
      98: aload         7
     100: aload_1
     101: aload         8
     103: invokespecial #96                 // Method org/springframework/boot/context/config/InactiveConfigDataAccessException."<init>":(Lorg/springframework/core/env/PropertySource;Lorg/springframework/boot/context/config/ConfigDataResource;Ljava/lang/String;Lorg/springframework/boot/origin/Origin;)V
     106: athrow
     107: aconst_null
     108: astore        6
     110: aload_2
     111: ifnull        118
     114: aload_2
     115: goto          120
     118: aload         6
     120: astore_2
     121: goto          12
     124: aload_2
     125: ifnull        135
     128: aload_2
     129: invokestatic  #99                 // Method java/lang/String.valueOf:(Ljava/lang/Object;)Ljava/lang/String;
     132: goto          136
     135: aconst_null
     136: areturn

  private boolean isActive(org.springframework.boot.context.config.ConfigDataEnvironmentContributor);
    Code:
       0: aload_1
       1: aload_0
       2: getfield      #17                 // Field activeContributor:Lorg/springframework/boot/context/config/ConfigDataEnvironmentContributor;
       5: if_acmpne     10
       8: iconst_1
       9: ireturn
      10: aload_1
      11: invokevirtual #103                // Method org/springframework/boot/context/config/ConfigDataEnvironmentContributor.getKind:()Lorg/springframework/boot/context/config/ConfigDataEnvironmentContributor$Kind;
      14: getstatic     #107                // Field org/springframework/boot/context/config/ConfigDataEnvironmentContributor$Kind.UNBOUND_IMPORT:Lorg/springframework/boot/context/config/ConfigDataEnvironmentContributor$Kind;
      17: if_acmpeq     29
      20: aload_1
      21: aload_0
      22: getfield      #13                 // Field activationContext:Lorg/springframework/boot/context/config/ConfigDataActivationContext;
      25: invokevirtual #113                // Method org/springframework/boot/context/config/ConfigDataEnvironmentContributor.isActive:(Lorg/springframework/boot/context/config/ConfigDataActivationContext;)Z
      28: ireturn
      29: aload_1
      30: aload_0
      31: getfield      #7                  // Field contributors:Ljava/lang/Iterable;
      34: aload_0
      35: getfield      #13                 // Field activationContext:Lorg/springframework/boot/context/config/ConfigDataActivationContext;
      38: invokevirtual #116                // Method org/springframework/boot/context/config/ConfigDataEnvironmentContributor.withBoundProperties:(Ljava/lang/Iterable;Lorg/springframework/boot/context/config/ConfigDataActivationContext;)Lorg/springframework/boot/context/config/ConfigDataEnvironmentContributor;
      41: aload_0
      42: getfield      #13                 // Field activationContext:Lorg/springframework/boot/context/config/ConfigDataActivationContext;
      45: invokevirtual #113                // Method org/springframework/boot/context/config/ConfigDataEnvironmentContributor.isActive:(Lorg/springframework/boot/context/config/ConfigDataActivationContext;)Z
      48: ireturn
}
