Compiled from "ConfigDataNotFoundAction.java"
final class org.springframework.boot.context.config.ConfigDataNotFoundAction$2 extends org.springframework.boot.context.config.ConfigDataNotFoundAction {
  private org.springframework.boot.context.config.ConfigDataNotFoundAction$2(java.lang.String, int);
    Code:
       0: aload_0
       1: aload_1
       2: iload_2
       3: invokespecial #1                  // Method org/springframework/boot/context/config/ConfigDataNotFoundAction."<init>":(Ljava/lang/String;I)V
       6: return

  void handle(org.apache.commons.logging.Log, org.springframework.boot.context.config.ConfigDataNotFoundException);
    Code:
       0: aload_1
       1: ldc           #7                  // String Ignoring missing config data %s
       3: aload_2
       4: invokevirtual #9                  // Method org/springframework/boot/context/config/ConfigDataNotFoundException.getReferenceDescription:()Ljava/lang/String;
       7: invokestatic  #15                 // Method org/springframework/core/log/LogMessage.format:(Ljava/lang/String;Ljava/lang/Object;)Lorg/springframework/core/log/LogMessage;
      10: invokeinterface #21,  2           // InterfaceMethod org/apache/commons/logging/Log.trace:(Ljava/lang/Object;)V
      15: return
}
