Compiled from "ConfigDataNotFoundAction.java"
public abstract class org.springframework.boot.context.config.ConfigDataNotFoundAction extends java.lang.Enum<org.springframework.boot.context.config.ConfigDataNotFoundAction> {
  public static final org.springframework.boot.context.config.ConfigDataNotFoundAction FAIL;

  public static final org.springframework.boot.context.config.ConfigDataNotFoundAction IGNORE;

  private static final org.springframework.boot.context.config.ConfigDataNotFoundAction[] $VALUES;

  public static org.springframework.boot.context.config.ConfigDataNotFoundAction[] values();
    Code:
       0: getstatic     #10                 // Field $VALUES:[Lorg/springframework/boot/context/config/ConfigDataNotFoundAction;
       3: invokevirtual #14                 // Method "[Lorg/springframework/boot/context/config/ConfigDataNotFoundAction;".clone:()Ljava/lang/Object;
       6: checkcast     #15                 // class "[Lorg/springframework/boot/context/config/ConfigDataNotFoundAction;"
       9: areturn

  public static org.springframework.boot.context.config.ConfigDataNotFoundAction valueOf(java.lang.String);
    Code:
       0: ldc           #1                  // class org/springframework/boot/context/config/ConfigDataNotFoundAction
       2: aload_0
       3: invokestatic  #19                 // Method java/lang/Enum.valueOf:(Ljava/lang/Class;Ljava/lang/String;)Ljava/lang/Enum;
       6: checkcast     #1                  // class org/springframework/boot/context/config/ConfigDataNotFoundAction
       9: areturn

  private org.springframework.boot.context.config.ConfigDataNotFoundAction();
    Code:
       0: aload_0
       1: aload_1
       2: iload_2
       3: invokespecial #25                 // Method java/lang/Enum."<init>":(Ljava/lang/String;I)V
       6: return

  abstract void handle(org.apache.commons.logging.Log, org.springframework.boot.context.config.ConfigDataNotFoundException);

  private static org.springframework.boot.context.config.ConfigDataNotFoundAction[] $values();
    Code:
       0: iconst_2
       1: anewarray     #1                  // class org/springframework/boot/context/config/ConfigDataNotFoundAction
       4: dup
       5: iconst_0
       6: getstatic     #3                  // Field FAIL:Lorg/springframework/boot/context/config/ConfigDataNotFoundAction;
       9: aastore
      10: dup
      11: iconst_1
      12: getstatic     #7                  // Field IGNORE:Lorg/springframework/boot/context/config/ConfigDataNotFoundAction;
      15: aastore
      16: areturn

  static {};
    Code:
       0: new           #29                 // class org/springframework/boot/context/config/ConfigDataNotFoundAction$1
       3: dup
       4: ldc           #31                 // String FAIL
       6: iconst_0
       7: invokespecial #32                 // Method org/springframework/boot/context/config/ConfigDataNotFoundAction$1."<init>":(Ljava/lang/String;I)V
      10: putstatic     #3                  // Field FAIL:Lorg/springframework/boot/context/config/ConfigDataNotFoundAction;
      13: new           #33                 // class org/springframework/boot/context/config/ConfigDataNotFoundAction$2
      16: dup
      17: ldc           #35                 // String IGNORE
      19: iconst_1
      20: invokespecial #36                 // Method org/springframework/boot/context/config/ConfigDataNotFoundAction$2."<init>":(Ljava/lang/String;I)V
      23: putstatic     #7                  // Field IGNORE:Lorg/springframework/boot/context/config/ConfigDataNotFoundAction;
      26: invokestatic  #37                 // Method $values:()[Lorg/springframework/boot/context/config/ConfigDataNotFoundAction;
      29: putstatic     #10                 // Field $VALUES:[Lorg/springframework/boot/context/config/ConfigDataNotFoundAction;
      32: return
}
