Compiled from "ConfigDataEnvironmentContributor.java"
final class org.springframework.boot.context.config.ConfigDataEnvironmentContributor$ImportPhase extends java.lang.Enum<org.springframework.boot.context.config.ConfigDataEnvironmentContributor$ImportPhase> {
  public static final org.springframework.boot.context.config.ConfigDataEnvironmentContributor$ImportPhase BEFORE_PROFILE_ACTIVATION;

  public static final org.springframework.boot.context.config.ConfigDataEnvironmentContributor$ImportPhase AFTER_PROFILE_ACTIVATION;

  private static final org.springframework.boot.context.config.ConfigDataEnvironmentContributor$ImportPhase[] $VALUES;

  public static org.springframework.boot.context.config.ConfigDataEnvironmentContributor$ImportPhase[] values();
    Code:
       0: getstatic     #10                 // Field $VALUES:[Lorg/springframework/boot/context/config/ConfigDataEnvironmentContributor$ImportPhase;
       3: invokevirtual #14                 // Method "[Lorg/springframework/boot/context/config/ConfigDataEnvironmentContributor$ImportPhase;".clone:()Ljava/lang/Object;
       6: checkcast     #15                 // class "[Lorg/springframework/boot/context/config/ConfigDataEnvironmentContributor$ImportPhase;"
       9: areturn

  public static org.springframework.boot.context.config.ConfigDataEnvironmentContributor$ImportPhase valueOf(java.lang.String);
    Code:
       0: ldc           #1                  // class org/springframework/boot/context/config/ConfigDataEnvironmentContributor$ImportPhase
       2: aload_0
       3: invokestatic  #19                 // Method java/lang/Enum.valueOf:(Ljava/lang/Class;Ljava/lang/String;)Ljava/lang/Enum;
       6: checkcast     #1                  // class org/springframework/boot/context/config/ConfigDataEnvironmentContributor$ImportPhase
       9: areturn

  private org.springframework.boot.context.config.ConfigDataEnvironmentContributor$ImportPhase();
    Code:
       0: aload_0
       1: aload_1
       2: iload_2
       3: invokespecial #25                 // Method java/lang/Enum."<init>":(Ljava/lang/String;I)V
       6: return

  static org.springframework.boot.context.config.ConfigDataEnvironmentContributor$ImportPhase get(org.springframework.boot.context.config.ConfigDataActivationContext);
    Code:
       0: aload_0
       1: ifnull        15
       4: aload_0
       5: invokevirtual #29                 // Method org/springframework/boot/context/config/ConfigDataActivationContext.getProfiles:()Lorg/springframework/boot/context/config/Profiles;
       8: ifnull        15
      11: getstatic     #7                  // Field AFTER_PROFILE_ACTIVATION:Lorg/springframework/boot/context/config/ConfigDataEnvironmentContributor$ImportPhase;
      14: areturn
      15: getstatic     #3                  // Field BEFORE_PROFILE_ACTIVATION:Lorg/springframework/boot/context/config/ConfigDataEnvironmentContributor$ImportPhase;
      18: areturn

  private static org.springframework.boot.context.config.ConfigDataEnvironmentContributor$ImportPhase[] $values();
    Code:
       0: iconst_2
       1: anewarray     #1                  // class org/springframework/boot/context/config/ConfigDataEnvironmentContributor$ImportPhase
       4: dup
       5: iconst_0
       6: getstatic     #3                  // Field BEFORE_PROFILE_ACTIVATION:Lorg/springframework/boot/context/config/ConfigDataEnvironmentContributor$ImportPhase;
       9: aastore
      10: dup
      11: iconst_1
      12: getstatic     #7                  // Field AFTER_PROFILE_ACTIVATION:Lorg/springframework/boot/context/config/ConfigDataEnvironmentContributor$ImportPhase;
      15: aastore
      16: areturn

  static {};
    Code:
       0: new           #1                  // class org/springframework/boot/context/config/ConfigDataEnvironmentContributor$ImportPhase
       3: dup
       4: ldc           #35                 // String BEFORE_PROFILE_ACTIVATION
       6: iconst_0
       7: invokespecial #36                 // Method "<init>":(Ljava/lang/String;I)V
      10: putstatic     #3                  // Field BEFORE_PROFILE_ACTIVATION:Lorg/springframework/boot/context/config/ConfigDataEnvironmentContributor$ImportPhase;
      13: new           #1                  // class org/springframework/boot/context/config/ConfigDataEnvironmentContributor$ImportPhase
      16: dup
      17: ldc           #37                 // String AFTER_PROFILE_ACTIVATION
      19: iconst_1
      20: invokespecial #36                 // Method "<init>":(Ljava/lang/String;I)V
      23: putstatic     #7                  // Field AFTER_PROFILE_ACTIVATION:Lorg/springframework/boot/context/config/ConfigDataEnvironmentContributor$ImportPhase;
      26: invokestatic  #38                 // Method $values:()[Lorg/springframework/boot/context/config/ConfigDataEnvironmentContributor$ImportPhase;
      29: putstatic     #10                 // Field $VALUES:[Lorg/springframework/boot/context/config/ConfigDataEnvironmentContributor$ImportPhase;
      32: return
}
