Compiled from "ConfigDataImporter.java"
class org.springframework.boot.context.config.ConfigDataImporter {
  private final org.apache.commons.logging.Log logger;

  private final org.springframework.boot.context.config.ConfigDataLocationResolvers resolvers;

  private final org.springframework.boot.context.config.ConfigDataLoaders loaders;

  private final org.springframework.boot.context.config.ConfigDataNotFoundAction notFoundAction;

  private final java.util.Set<org.springframework.boot.context.config.ConfigDataResource> loaded;

  private final java.util.Set<org.springframework.boot.context.config.ConfigDataLocation> loadedLocations;

  private final java.util.Set<org.springframework.boot.context.config.ConfigDataLocation> optionalLocations;

  org.springframework.boot.context.config.ConfigDataImporter(org.springframework.boot.logging.DeferredLogFactory, org.springframework.boot.context.config.ConfigDataNotFoundAction, org.springframework.boot.context.config.ConfigDataLocationResolvers, org.springframework.boot.context.config.ConfigDataLoaders);
    Code:
       0: aload_0
       1: invokespecial #1                  // Method java/lang/Object."<init>":()V
       4: aload_0
       5: new           #7                  // class java/util/HashSet
       8: dup
       9: invokespecial #9                  // Method java/util/HashSet."<init>":()V
      12: putfield      #10                 // Field loaded:Ljava/util/Set;
      15: aload_0
      16: new           #7                  // class java/util/HashSet
      19: dup
      20: invokespecial #9                  // Method java/util/HashSet."<init>":()V
      23: putfield      #16                 // Field loadedLocations:Ljava/util/Set;
      26: aload_0
      27: new           #7                  // class java/util/HashSet
      30: dup
      31: invokespecial #9                  // Method java/util/HashSet."<init>":()V
      34: putfield      #19                 // Field optionalLocations:Ljava/util/Set;
      37: aload_0
      38: aload_1
      39: aload_0
      40: invokevirtual #22                 // Method java/lang/Object.getClass:()Ljava/lang/Class;
      43: invokeinterface #26,  2           // InterfaceMethod org/springframework/boot/logging/DeferredLogFactory.getLog:(Ljava/lang/Class;)Lorg/apache/commons/logging/Log;
      48: putfield      #32                 // Field logger:Lorg/apache/commons/logging/Log;
      51: aload_0
      52: aload_3
      53: putfield      #36                 // Field resolvers:Lorg/springframework/boot/context/config/ConfigDataLocationResolvers;
      56: aload_0
      57: aload         4
      59: putfield      #40                 // Field loaders:Lorg/springframework/boot/context/config/ConfigDataLoaders;
      62: aload_0
      63: aload_2
      64: putfield      #44                 // Field notFoundAction:Lorg/springframework/boot/context/config/ConfigDataNotFoundAction;
      67: return

  java.util.Map<org.springframework.boot.context.config.ConfigDataResolutionResult, org.springframework.boot.context.config.ConfigData> resolveAndLoad(org.springframework.boot.context.config.ConfigDataActivationContext, org.springframework.boot.context.config.ConfigDataLocationResolverContext, org.springframework.boot.context.config.ConfigDataLoaderContext, java.util.List<org.springframework.boot.context.config.ConfigDataLocation>);
    Code:
       0: aload_1
       1: ifnull        11
       4: aload_1
       5: invokevirtual #48                 // Method org/springframework/boot/context/config/ConfigDataActivationContext.getProfiles:()Lorg/springframework/boot/context/config/Profiles;
       8: goto          12
      11: aconst_null
      12: astore        5
      14: aload_0
      15: aload_2
      16: aload         5
      18: aload         4
      20: invokevirtual #54                 // Method resolve:(Lorg/springframework/boot/context/config/ConfigDataLocationResolverContext;Lorg/springframework/boot/context/config/Profiles;Ljava/util/List;)Ljava/util/List;
      23: astore        6
      25: aload_0
      26: aload_3
      27: aload         6
      29: invokevirtual #58                 // Method load:(Lorg/springframework/boot/context/config/ConfigDataLoaderContext;Ljava/util/List;)Ljava/util/Map;
      32: areturn
      33: astore        5
      35: new           #64                 // class java/lang/IllegalStateException
      38: dup
      39: aload         4
      41: invokedynamic #66,  0             // InvokeDynamic #0:makeConcatWithConstants:(Ljava/util/List;)Ljava/lang/String;
      46: aload         5
      48: invokespecial #70                 // Method java/lang/IllegalStateException."<init>":(Ljava/lang/String;Ljava/lang/Throwable;)V
      51: athrow
    Exception table:
       from    to  target type
           0    32    33   Class java/io/IOException

  private java.util.List<org.springframework.boot.context.config.ConfigDataResolutionResult> resolve(org.springframework.boot.context.config.ConfigDataLocationResolverContext, org.springframework.boot.context.config.Profiles, java.util.List<org.springframework.boot.context.config.ConfigDataLocation>);
    Code:
       0: new           #73                 // class java/util/ArrayList
       3: dup
       4: aload_3
       5: invokeinterface #75,  1           // InterfaceMethod java/util/List.size:()I
      10: invokespecial #81                 // Method java/util/ArrayList."<init>":(I)V
      13: astore        4
      15: aload_3
      16: invokeinterface #84,  1           // InterfaceMethod java/util/List.iterator:()Ljava/util/Iterator;
      21: astore        5
      23: aload         5
      25: invokeinterface #88,  1           // InterfaceMethod java/util/Iterator.hasNext:()Z
      30: ifeq          64
      33: aload         5
      35: invokeinterface #94,  1           // InterfaceMethod java/util/Iterator.next:()Ljava/lang/Object;
      40: checkcast     #98                 // class org/springframework/boot/context/config/ConfigDataLocation
      43: astore        6
      45: aload         4
      47: aload_0
      48: aload_1
      49: aload_2
      50: aload         6
      52: invokevirtual #100                // Method resolve:(Lorg/springframework/boot/context/config/ConfigDataLocationResolverContext;Lorg/springframework/boot/context/config/Profiles;Lorg/springframework/boot/context/config/ConfigDataLocation;)Ljava/util/List;
      55: invokeinterface #103,  2          // InterfaceMethod java/util/List.addAll:(Ljava/util/Collection;)Z
      60: pop
      61: goto          23
      64: aload         4
      66: invokestatic  #107                // Method java/util/Collections.unmodifiableList:(Ljava/util/List;)Ljava/util/List;
      69: areturn

  private java.util.List<org.springframework.boot.context.config.ConfigDataResolutionResult> resolve(org.springframework.boot.context.config.ConfigDataLocationResolverContext, org.springframework.boot.context.config.Profiles, org.springframework.boot.context.config.ConfigDataLocation);
    Code:
       0: aload_0
       1: getfield      #36                 // Field resolvers:Lorg/springframework/boot/context/config/ConfigDataLocationResolvers;
       4: aload_1
       5: aload_3
       6: aload_2
       7: invokevirtual #113                // Method org/springframework/boot/context/config/ConfigDataLocationResolvers.resolve:(Lorg/springframework/boot/context/config/ConfigDataLocationResolverContext;Lorg/springframework/boot/context/config/ConfigDataLocation;Lorg/springframework/boot/context/config/Profiles;)Ljava/util/List;
      10: areturn
      11: astore        4
      13: aload_0
      14: aload         4
      16: aload_3
      17: aconst_null
      18: invokevirtual #120                // Method handle:(Lorg/springframework/boot/context/config/ConfigDataNotFoundException;Lorg/springframework/boot/context/config/ConfigDataLocation;Lorg/springframework/boot/context/config/ConfigDataResource;)V
      21: invokestatic  #124                // Method java/util/Collections.emptyList:()Ljava/util/List;
      24: areturn
    Exception table:
       from    to  target type
           0    10    11   Class org/springframework/boot/context/config/ConfigDataNotFoundException

  private java.util.Map<org.springframework.boot.context.config.ConfigDataResolutionResult, org.springframework.boot.context.config.ConfigData> load(org.springframework.boot.context.config.ConfigDataLoaderContext, java.util.List<org.springframework.boot.context.config.ConfigDataResolutionResult>) throws java.io.IOException;
    Code:
       0: new           #128                // class java/util/LinkedHashMap
       3: dup
       4: invokespecial #130                // Method java/util/LinkedHashMap."<init>":()V
       7: astore_3
       8: aload_2
       9: invokeinterface #75,  1           // InterfaceMethod java/util/List.size:()I
      14: iconst_1
      15: isub
      16: istore        4
      18: iload         4
      20: iflt          226
      23: aload_2
      24: iload         4
      26: invokeinterface #131,  2          // InterfaceMethod java/util/List.get:(I)Ljava/lang/Object;
      31: checkcast     #135                // class org/springframework/boot/context/config/ConfigDataResolutionResult
      34: astore        5
      36: aload         5
      38: invokevirtual #137                // Method org/springframework/boot/context/config/ConfigDataResolutionResult.getLocation:()Lorg/springframework/boot/context/config/ConfigDataLocation;
      41: astore        6
      43: aload         5
      45: invokevirtual #141                // Method org/springframework/boot/context/config/ConfigDataResolutionResult.getResource:()Lorg/springframework/boot/context/config/ConfigDataResource;
      48: astore        7
      50: aload_0
      51: getfield      #32                 // Field logger:Lorg/apache/commons/logging/Log;
      54: ldc           #145                // String Considering resource %s from location %s
      56: aload         7
      58: aload         6
      60: invokestatic  #147                // Method org/springframework/core/log/LogMessage.format:(Ljava/lang/String;Ljava/lang/Object;Ljava/lang/Object;)Lorg/springframework/core/log/LogMessage;
      63: invokeinterface #153,  2          // InterfaceMethod org/apache/commons/logging/Log.trace:(Ljava/lang/Object;)V
      68: aload         7
      70: invokevirtual #159                // Method org/springframework/boot/context/config/ConfigDataResource.isOptional:()Z
      73: ifeq          88
      76: aload_0
      77: getfield      #19                 // Field optionalLocations:Ljava/util/Set;
      80: aload         6
      82: invokeinterface #164,  2          // InterfaceMethod java/util/Set.add:(Ljava/lang/Object;)Z
      87: pop
      88: aload_0
      89: getfield      #10                 // Field loaded:Ljava/util/Set;
      92: aload         7
      94: invokeinterface #170,  2          // InterfaceMethod java/util/Set.contains:(Ljava/lang/Object;)Z
      99: ifeq          135
     102: aload_0
     103: getfield      #32                 // Field logger:Lorg/apache/commons/logging/Log;
     106: ldc           #173                // String Already loaded resource %s ignoring location %s
     108: aload         7
     110: aload         6
     112: invokestatic  #147                // Method org/springframework/core/log/LogMessage.format:(Ljava/lang/String;Ljava/lang/Object;Ljava/lang/Object;)Lorg/springframework/core/log/LogMessage;
     115: invokeinterface #153,  2          // InterfaceMethod org/apache/commons/logging/Log.trace:(Ljava/lang/Object;)V
     120: aload_0
     121: getfield      #16                 // Field loadedLocations:Ljava/util/Set;
     124: aload         6
     126: invokeinterface #164,  2          // InterfaceMethod java/util/Set.add:(Ljava/lang/Object;)Z
     131: pop
     132: goto          220
     135: aload_0
     136: getfield      #40                 // Field loaders:Lorg/springframework/boot/context/config/ConfigDataLoaders;
     139: aload_1
     140: aload         7
     142: invokevirtual #175                // Method org/springframework/boot/context/config/ConfigDataLoaders.load:(Lorg/springframework/boot/context/config/ConfigDataLoaderContext;Lorg/springframework/boot/context/config/ConfigDataResource;)Lorg/springframework/boot/context/config/ConfigData;
     145: astore        8
     147: aload         8
     149: ifnull        205
     152: aload_0
     153: getfield      #32                 // Field logger:Lorg/apache/commons/logging/Log;
     156: ldc           #180                // String Loaded resource %s from location %s
     158: aload         7
     160: aload         6
     162: invokestatic  #147                // Method org/springframework/core/log/LogMessage.format:(Ljava/lang/String;Ljava/lang/Object;Ljava/lang/Object;)Lorg/springframework/core/log/LogMessage;
     165: invokeinterface #153,  2          // InterfaceMethod org/apache/commons/logging/Log.trace:(Ljava/lang/Object;)V
     170: aload_0
     171: getfield      #10                 // Field loaded:Ljava/util/Set;
     174: aload         7
     176: invokeinterface #164,  2          // InterfaceMethod java/util/Set.add:(Ljava/lang/Object;)Z
     181: pop
     182: aload_0
     183: getfield      #16                 // Field loadedLocations:Ljava/util/Set;
     186: aload         6
     188: invokeinterface #164,  2          // InterfaceMethod java/util/Set.add:(Ljava/lang/Object;)Z
     193: pop
     194: aload_3
     195: aload         5
     197: aload         8
     199: invokeinterface #182,  3          // InterfaceMethod java/util/Map.put:(Ljava/lang/Object;Ljava/lang/Object;)Ljava/lang/Object;
     204: pop
     205: goto          220
     208: astore        8
     210: aload_0
     211: aload         8
     213: aload         6
     215: aload         7
     217: invokevirtual #120                // Method handle:(Lorg/springframework/boot/context/config/ConfigDataNotFoundException;Lorg/springframework/boot/context/config/ConfigDataLocation;Lorg/springframework/boot/context/config/ConfigDataResource;)V
     220: iinc          4, -1
     223: goto          18
     226: aload_3
     227: invokestatic  #188                // Method java/util/Collections.unmodifiableMap:(Ljava/util/Map;)Ljava/util/Map;
     230: areturn
    Exception table:
       from    to  target type
         135   205   208   Class org/springframework/boot/context/config/ConfigDataNotFoundException

  private void handle(org.springframework.boot.context.config.ConfigDataNotFoundException, org.springframework.boot.context.config.ConfigDataLocation, org.springframework.boot.context.config.ConfigDataResource);
    Code:
       0: aload_1
       1: instanceof    #192                // class org/springframework/boot/context/config/ConfigDataResourceNotFoundException
       4: ifeq          20
       7: aload_1
       8: checkcast     #192                // class org/springframework/boot/context/config/ConfigDataResourceNotFoundException
      11: astore        4
      13: aload         4
      15: aload_2
      16: invokevirtual #194                // Method org/springframework/boot/context/config/ConfigDataResourceNotFoundException.withLocation:(Lorg/springframework/boot/context/config/ConfigDataLocation;)Lorg/springframework/boot/context/config/ConfigDataResourceNotFoundException;
      19: astore_1
      20: aload_0
      21: aload_2
      22: aload_3
      23: invokevirtual #198                // Method getNotFoundAction:(Lorg/springframework/boot/context/config/ConfigDataLocation;Lorg/springframework/boot/context/config/ConfigDataResource;)Lorg/springframework/boot/context/config/ConfigDataNotFoundAction;
      26: aload_0
      27: getfield      #32                 // Field logger:Lorg/apache/commons/logging/Log;
      30: aload_1
      31: invokevirtual #202                // Method org/springframework/boot/context/config/ConfigDataNotFoundAction.handle:(Lorg/apache/commons/logging/Log;Lorg/springframework/boot/context/config/ConfigDataNotFoundException;)V
      34: return

  private org.springframework.boot.context.config.ConfigDataNotFoundAction getNotFoundAction(org.springframework.boot.context.config.ConfigDataLocation, org.springframework.boot.context.config.ConfigDataResource);
    Code:
       0: aload_1
       1: invokevirtual #207                // Method org/springframework/boot/context/config/ConfigDataLocation.isOptional:()Z
       4: ifne          18
       7: aload_2
       8: ifnull        22
      11: aload_2
      12: invokevirtual #159                // Method org/springframework/boot/context/config/ConfigDataResource.isOptional:()Z
      15: ifeq          22
      18: getstatic     #208                // Field org/springframework/boot/context/config/ConfigDataNotFoundAction.IGNORE:Lorg/springframework/boot/context/config/ConfigDataNotFoundAction;
      21: areturn
      22: aload_0
      23: getfield      #44                 // Field notFoundAction:Lorg/springframework/boot/context/config/ConfigDataNotFoundAction;
      26: areturn

  java.util.Set<org.springframework.boot.context.config.ConfigDataLocation> getLoadedLocations();
    Code:
       0: aload_0
       1: getfield      #16                 // Field loadedLocations:Ljava/util/Set;
       4: areturn

  java.util.Set<org.springframework.boot.context.config.ConfigDataLocation> getOptionalLocations();
    Code:
       0: aload_0
       1: getfield      #19                 // Field optionalLocations:Ljava/util/Set;
       4: areturn
}
