Compiled from "ConfigDataResolutionResult.java"
class org.springframework.boot.context.config.ConfigDataResolutionResult {
  private final org.springframework.boot.context.config.ConfigDataLocation location;

  private final org.springframework.boot.context.config.ConfigDataResource resource;

  private final boolean profileSpecific;

  org.springframework.boot.context.config.ConfigDataResolutionResult(org.springframework.boot.context.config.ConfigDataLocation, org.springframework.boot.context.config.ConfigDataResource, boolean);
    Code:
       0: aload_0
       1: invokespecial #1                  // Method java/lang/Object."<init>":()V
       4: aload_0
       5: aload_1
       6: putfield      #7                  // Field location:Lorg/springframework/boot/context/config/ConfigDataLocation;
       9: aload_0
      10: aload_2
      11: putfield      #13                 // Field resource:Lorg/springframework/boot/context/config/ConfigDataResource;
      14: aload_0
      15: iload_3
      16: putfield      #17                 // Field profileSpecific:Z
      19: return

  org.springframework.boot.context.config.ConfigDataLocation getLocation();
    Code:
       0: aload_0
       1: getfield      #7                  // Field location:Lorg/springframework/boot/context/config/ConfigDataLocation;
       4: areturn

  org.springframework.boot.context.config.ConfigDataResource getResource();
    Code:
       0: aload_0
       1: getfield      #13                 // Field resource:Lorg/springframework/boot/context/config/ConfigDataResource;
       4: areturn

  boolean isProfileSpecific();
    Code:
       0: aload_0
       1: getfield      #17                 // Field profileSpecific:Z
       4: ireturn
}
