Compiled from "ConfigDataPropertiesRuntimeHints.java"
class org.springframework.boot.context.config.ConfigDataPropertiesRuntimeHints implements org.springframework.aot.hint.RuntimeHintsRegistrar {
  org.springframework.boot.context.config.ConfigDataPropertiesRuntimeHints();
    Code:
       0: aload_0
       1: invokespecial #1                  // Method java/lang/Object."<init>":()V
       4: return

  public void registerHints(org.springframework.aot.hint.RuntimeHints, java.lang.ClassLoader);
    Code:
       0: iconst_1
       1: anewarray     #7                  // class java/lang/Class
       4: dup
       5: iconst_0
       6: ldc           #9                  // class org/springframework/boot/context/config/ConfigDataProperties
       8: aastore
       9: invokestatic  #11                 // Method org/springframework/boot/context/properties/bind/BindableRuntimeHintsRegistrar.forTypes:([Ljava/lang/Class;)Lorg/springframework/boot/context/properties/bind/BindableRuntimeHintsRegistrar;
      12: aload_1
      13: invokevirtual #17                 // Method org/springframework/boot/context/properties/bind/BindableRuntimeHintsRegistrar.registerHints:(Lorg/springframework/aot/hint/RuntimeHints;)V
      16: aload_1
      17: invokevirtual #21                 // Method org/springframework/aot/hint/RuntimeHints.reflection:()Lorg/springframework/aot/hint/ReflectionHints;
      20: ldc           #27                 // class org/springframework/boot/context/config/ConfigDataLocation
      22: ldc           #29                 // String of
      24: iconst_1
      25: anewarray     #7                  // class java/lang/Class
      28: dup
      29: iconst_0
      30: ldc           #31                 // class java/lang/String
      32: aastore
      33: invokestatic  #33                 // Method org/springframework/util/ReflectionUtils.findMethod:(Ljava/lang/Class;Ljava/lang/String;[Ljava/lang/Class;)Ljava/lang/reflect/Method;
      36: getstatic     #39                 // Field org/springframework/aot/hint/ExecutableMode.INVOKE:Lorg/springframework/aot/hint/ExecutableMode;
      39: invokevirtual #45                 // Method org/springframework/aot/hint/ReflectionHints.registerMethod:(Ljava/lang/reflect/Method;Lorg/springframework/aot/hint/ExecutableMode;)Lorg/springframework/aot/hint/ReflectionHints;
      42: pop
      43: return
}
