Compiled from "ConfigDataEnvironmentContributors.java"
class org.springframework.boot.context.config.ConfigDataEnvironmentContributors$ContributorDataLoaderContext implements org.springframework.boot.context.config.ConfigDataLoaderContext {
  private final org.springframework.boot.context.config.ConfigDataEnvironmentContributors contributors;

  org.springframework.boot.context.config.ConfigDataEnvironmentContributors$ContributorDataLoaderContext(org.springframework.boot.context.config.ConfigDataEnvironmentContributors);
    Code:
       0: aload_0
       1: invokespecial #1                  // Method java/lang/Object."<init>":()V
       4: aload_0
       5: aload_1
       6: putfield      #7                  // Field contributors:Lorg/springframework/boot/context/config/ConfigDataEnvironmentContributors;
       9: return

  public org.springframework.boot.ConfigurableBootstrapContext getBootstrapContext();
    Code:
       0: aload_0
       1: getfield      #7                  // Field contributors:Lorg/springframework/boot/context/config/ConfigDataEnvironmentContributors;
       4: invokevirtual #13                 // Method org/springframework/boot/context/config/ConfigDataEnvironmentContributors.getBootstrapContext:()Lorg/springframework/boot/ConfigurableBootstrapContext;
       7: areturn
}
