Compiled from "ConfigDataProperties.java"
class org.springframework.boot.context.config.ConfigDataProperties {
  private static final org.springframework.boot.context.properties.source.ConfigurationPropertyName NAME;

  private static final org.springframework.boot.context.properties.bind.Bindable<org.springframework.boot.context.config.ConfigDataProperties> BINDABLE_PROPERTIES;

  private final java.util.List<org.springframework.boot.context.config.ConfigDataLocation> imports;

  private final org.springframework.boot.context.config.ConfigDataProperties$Activate activate;

  org.springframework.boot.context.config.ConfigDataProperties(java.util.List<org.springframework.boot.context.config.ConfigDataLocation>, org.springframework.boot.context.config.ConfigDataProperties$Activate);
    Code:
       0: aload_0
       1: invokespecial #1                  // Method java/lang/Object."<init>":()V
       4: aload_0
       5: aload_1
       6: ifnull        13
       9: aload_1
      10: goto          16
      13: invokestatic  #7                  // Method java/util/Collections.emptyList:()Ljava/util/List;
      16: putfield      #13                 // Field imports:Ljava/util/List;
      19: aload_0
      20: aload_2
      21: putfield      #19                 // Field activate:Lorg/springframework/boot/context/config/ConfigDataProperties$Activate;
      24: return

  java.util.List<org.springframework.boot.context.config.ConfigDataLocation> getImports();
    Code:
       0: aload_0
       1: getfield      #13                 // Field imports:Ljava/util/List;
       4: areturn

  boolean isActive(org.springframework.boot.context.config.ConfigDataActivationContext);
    Code:
       0: aload_0
       1: getfield      #19                 // Field activate:Lorg/springframework/boot/context/config/ConfigDataProperties$Activate;
       4: ifnull        18
       7: aload_0
       8: getfield      #19                 // Field activate:Lorg/springframework/boot/context/config/ConfigDataProperties$Activate;
      11: aload_1
      12: invokevirtual #23                 // Method org/springframework/boot/context/config/ConfigDataProperties$Activate.isActive:(Lorg/springframework/boot/context/config/ConfigDataActivationContext;)Z
      15: ifeq          22
      18: iconst_1
      19: goto          23
      22: iconst_0
      23: ireturn

  org.springframework.boot.context.config.ConfigDataProperties withoutImports();
    Code:
       0: new           #14                 // class org/springframework/boot/context/config/ConfigDataProperties
       3: dup
       4: aconst_null
       5: aload_0
       6: getfield      #19                 // Field activate:Lorg/springframework/boot/context/config/ConfigDataProperties$Activate;
       9: invokespecial #29                 // Method "<init>":(Ljava/util/List;Lorg/springframework/boot/context/config/ConfigDataProperties$Activate;)V
      12: areturn

  static org.springframework.boot.context.config.ConfigDataProperties get(org.springframework.boot.context.properties.bind.Binder);
    Code:
       0: aload_0
       1: getstatic     #32                 // Field NAME:Lorg/springframework/boot/context/properties/source/ConfigurationPropertyName;
       4: getstatic     #36                 // Field BINDABLE_PROPERTIES:Lorg/springframework/boot/context/properties/bind/Bindable;
       7: new           #40                 // class org/springframework/boot/context/config/ConfigDataLocationBindHandler
      10: dup
      11: invokespecial #42                 // Method org/springframework/boot/context/config/ConfigDataLocationBindHandler."<init>":()V
      14: invokevirtual #43                 // Method org/springframework/boot/context/properties/bind/Binder.bind:(Lorg/springframework/boot/context/properties/source/ConfigurationPropertyName;Lorg/springframework/boot/context/properties/bind/Bindable;Lorg/springframework/boot/context/properties/bind/BindHandler;)Lorg/springframework/boot/context/properties/bind/BindResult;
      17: aconst_null
      18: invokevirtual #49                 // Method org/springframework/boot/context/properties/bind/BindResult.orElse:(Ljava/lang/Object;)Ljava/lang/Object;
      21: checkcast     #14                 // class org/springframework/boot/context/config/ConfigDataProperties
      24: areturn

  static {};
    Code:
       0: ldc           #55                 // String spring.config
       2: invokestatic  #57                 // Method org/springframework/boot/context/properties/source/ConfigurationPropertyName.of:(Ljava/lang/CharSequence;)Lorg/springframework/boot/context/properties/source/ConfigurationPropertyName;
       5: putstatic     #32                 // Field NAME:Lorg/springframework/boot/context/properties/source/ConfigurationPropertyName;
       8: ldc           #14                 // class org/springframework/boot/context/config/ConfigDataProperties
      10: invokestatic  #63                 // Method org/springframework/boot/context/properties/bind/Bindable.of:(Ljava/lang/Class;)Lorg/springframework/boot/context/properties/bind/Bindable;
      13: putstatic     #36                 // Field BINDABLE_PROPERTIES:Lorg/springframework/boot/context/properties/bind/Bindable;
      16: return
}
