Compiled from "ConfigDataLocationRuntimeHints.java"
class org.springframework.boot.context.config.ConfigDataLocationRuntimeHints implements org.springframework.aot.hint.RuntimeHintsRegistrar {
  private static final org.apache.commons.logging.Log logger;

  org.springframework.boot.context.config.ConfigDataLocationRuntimeHints();
    Code:
       0: aload_0
       1: invokespecial #1                  // Method java/lang/Object."<init>":()V
       4: return

  public void registerHints(org.springframework.aot.hint.RuntimeHints, java.lang.ClassLoader);
    Code:
       0: aload_0
       1: aload_2
       2: invokevirtual #7                  // Method getFileNames:(Ljava/lang/ClassLoader;)Ljava/util/List;
       5: astore_3
       6: aload_0
       7: aload_2
       8: invokevirtual #13                 // Method getLocations:(Ljava/lang/ClassLoader;)Ljava/util/List;
      11: astore        4
      13: aload_0
      14: aload_2
      15: invokevirtual #16                 // Method getExtensions:(Ljava/lang/ClassLoader;)Ljava/util/List;
      18: astore        5
      20: getstatic     #19                 // Field logger:Lorg/apache/commons/logging/Log;
      23: invokeinterface #23,  1           // InterfaceMethod org/apache/commons/logging/Log.isDebugEnabled:()Z
      28: ifeq          49
      31: getstatic     #19                 // Field logger:Lorg/apache/commons/logging/Log;
      34: aload_3
      35: aload         5
      37: aload         4
      39: invokedynamic #29,  0             // InvokeDynamic #0:makeConcatWithConstants:(Ljava/util/List;Ljava/util/List;Ljava/util/List;)Ljava/lang/String;
      44: invokeinterface #33,  2           // InterfaceMethod org/apache/commons/logging/Log.debug:(Ljava/lang/Object;)V
      49: new           #37                 // class org/springframework/aot/hint/support/FilePatternResourceHintsRegistrar
      52: dup
      53: aload_3
      54: aload         4
      56: aload         5
      58: invokespecial #39                 // Method org/springframework/aot/hint/support/FilePatternResourceHintsRegistrar."<init>":(Ljava/util/List;Ljava/util/List;Ljava/util/List;)V
      61: aload_1
      62: invokevirtual #42                 // Method org/springframework/aot/hint/RuntimeHints.resources:()Lorg/springframework/aot/hint/ResourceHints;
      65: aload_2
      66: invokevirtual #48                 // Method org/springframework/aot/hint/support/FilePatternResourceHintsRegistrar.registerHints:(Lorg/springframework/aot/hint/ResourceHints;Ljava/lang/ClassLoader;)V
      69: return

  protected java.util.List<java.lang.String> getFileNames(java.lang.ClassLoader);
    Code:
       0: getstatic     #52                 // Field org/springframework/boot/context/config/StandardConfigDataLocationResolver.DEFAULT_CONFIG_NAMES:[Ljava/lang/String;
       3: invokestatic  #58                 // Method java/util/Arrays.asList:([Ljava/lang/Object;)Ljava/util/List;
       6: areturn

  protected java.util.List<java.lang.String> getLocations(java.lang.ClassLoader);
    Code:
       0: new           #64                 // class java/util/ArrayList
       3: dup
       4: invokespecial #66                 // Method java/util/ArrayList."<init>":()V
       7: astore_2
       8: getstatic     #67                 // Field org/springframework/boot/context/config/ConfigDataEnvironment.DEFAULT_SEARCH_LOCATIONS:[Lorg/springframework/boot/context/config/ConfigDataLocation;
      11: astore_3
      12: aload_3
      13: arraylength
      14: istore        4
      16: iconst_0
      17: istore        5
      19: iload         5
      21: iload         4
      23: if_icmpge     99
      26: aload_3
      27: iload         5
      29: aaload
      30: astore        6
      32: aload         6
      34: invokevirtual #73                 // Method org/springframework/boot/context/config/ConfigDataLocation.split:()[Lorg/springframework/boot/context/config/ConfigDataLocation;
      37: astore        7
      39: aload         7
      41: arraylength
      42: istore        8
      44: iconst_0
      45: istore        9
      47: iload         9
      49: iload         8
      51: if_icmpge     93
      54: aload         7
      56: iload         9
      58: aaload
      59: astore        10
      61: aload         10
      63: invokevirtual #79                 // Method org/springframework/boot/context/config/ConfigDataLocation.getValue:()Ljava/lang/String;
      66: astore        11
      68: aload         11
      70: ldc           #85                 // String classpath:
      72: invokevirtual #87                 // Method java/lang/String.startsWith:(Ljava/lang/String;)Z
      75: ifeq          87
      78: aload_2
      79: aload         11
      81: invokeinterface #93,  2           // InterfaceMethod java/util/List.add:(Ljava/lang/Object;)Z
      86: pop
      87: iinc          9, 1
      90: goto          47
      93: iinc          5, 1
      96: goto          19
      99: aload_2
     100: areturn

  protected java.util.List<java.lang.String> getExtensions(java.lang.ClassLoader);
    Code:
       0: new           #64                 // class java/util/ArrayList
       3: dup
       4: invokespecial #66                 // Method java/util/ArrayList."<init>":()V
       7: astore_2
       8: aload_0
       9: aload_1
      10: invokevirtual #99                 // Method getSpringFactoriesLoader:(Ljava/lang/ClassLoader;)Lorg/springframework/core/io/support/SpringFactoriesLoader;
      13: ldc           #103                // class org/springframework/boot/env/PropertySourceLoader
      15: invokevirtual #105                // Method org/springframework/core/io/support/SpringFactoriesLoader.load:(Ljava/lang/Class;)Ljava/util/List;
      18: astore_3
      19: aload_3
      20: invokeinterface #111,  1          // InterfaceMethod java/util/List.iterator:()Ljava/util/Iterator;
      25: astore        4
      27: aload         4
      29: invokeinterface #115,  1          // InterfaceMethod java/util/Iterator.hasNext:()Z
      34: ifeq          118
      37: aload         4
      39: invokeinterface #120,  1          // InterfaceMethod java/util/Iterator.next:()Ljava/lang/Object;
      44: checkcast     #103                // class org/springframework/boot/env/PropertySourceLoader
      47: astore        5
      49: aload         5
      51: invokeinterface #124,  1          // InterfaceMethod org/springframework/boot/env/PropertySourceLoader.getFileExtensions:()[Ljava/lang/String;
      56: astore        6
      58: aload         6
      60: arraylength
      61: istore        7
      63: iconst_0
      64: istore        8
      66: iload         8
      68: iload         7
      70: if_icmpge     115
      73: aload         6
      75: iload         8
      77: aaload
      78: astore        9
      80: aload         9
      82: invokedynamic #128,  0            // InvokeDynamic #1:makeConcatWithConstants:(Ljava/lang/String;)Ljava/lang/String;
      87: astore        10
      89: aload_2
      90: aload         10
      92: invokeinterface #131,  2          // InterfaceMethod java/util/List.contains:(Ljava/lang/Object;)Z
      97: ifne          109
     100: aload_2
     101: aload         10
     103: invokeinterface #93,  2           // InterfaceMethod java/util/List.add:(Ljava/lang/Object;)Z
     108: pop
     109: iinc          8, 1
     112: goto          66
     115: goto          27
     118: aload_2
     119: areturn

  protected org.springframework.core.io.support.SpringFactoriesLoader getSpringFactoriesLoader(java.lang.ClassLoader);
    Code:
       0: aload_1
       1: invokestatic  #134                // Method org/springframework/core/io/support/SpringFactoriesLoader.forDefaultResourceLocation:(Ljava/lang/ClassLoader;)Lorg/springframework/core/io/support/SpringFactoriesLoader;
       4: areturn

  static {};
    Code:
       0: ldc           #8                  // class org/springframework/boot/context/config/ConfigDataLocationRuntimeHints
       2: invokestatic  #137                // Method org/apache/commons/logging/LogFactory.getLog:(Ljava/lang/Class;)Lorg/apache/commons/logging/Log;
       5: putstatic     #19                 // Field logger:Lorg/apache/commons/logging/Log;
       8: return
}
