Compiled from "ConfigData.java"
public final class org.springframework.boot.context.config.ConfigData {
  private final java.util.List<org.springframework.core.env.PropertySource<?>> propertySources;

  private final org.springframework.boot.context.config.ConfigData$PropertySourceOptions propertySourceOptions;

  public static final org.springframework.boot.context.config.ConfigData EMPTY;

  public org.springframework.boot.context.config.ConfigData(java.util.Collection<? extends org.springframework.core.env.PropertySource<?>>, org.springframework.boot.context.config.ConfigData$Option...);
    Code:
       0: aload_0
       1: aload_1
       2: aload_2
       3: invokestatic  #1                  // Method org/springframework/boot/context/config/ConfigData$Options.of:([Lorg/springframework/boot/context/config/ConfigData$Option;)Lorg/springframework/boot/context/config/ConfigData$Options;
       6: invokestatic  #7                  // InterfaceMethod org/springframework/boot/context/config/ConfigData$PropertySourceOptions.always:(Lorg/springframework/boot/context/config/ConfigData$Options;)Lorg/springframework/boot/context/config/ConfigData$PropertySourceOptions;
       9: invokespecial #13                 // Method "<init>":(Ljava/util/Collection;Lorg/springframework/boot/context/config/ConfigData$PropertySourceOptions;)V
      12: return

  public org.springframework.boot.context.config.ConfigData(java.util.Collection<? extends org.springframework.core.env.PropertySource<?>>, org.springframework.boot.context.config.ConfigData$PropertySourceOptions);
    Code:
       0: aload_0
       1: invokespecial #19                 // Method java/lang/Object."<init>":()V
       4: aload_1
       5: ldc           #24                 // String PropertySources must not be null
       7: invokestatic  #26                 // Method org/springframework/util/Assert.notNull:(Ljava/lang/Object;Ljava/lang/String;)V
      10: aload_2
      11: ldc           #32                 // String PropertySourceOptions must not be null
      13: invokestatic  #26                 // Method org/springframework/util/Assert.notNull:(Ljava/lang/Object;Ljava/lang/String;)V
      16: aload_0
      17: new           #34                 // class java/util/ArrayList
      20: dup
      21: aload_1
      22: invokespecial #36                 // Method java/util/ArrayList."<init>":(Ljava/util/Collection;)V
      25: invokestatic  #39                 // Method java/util/Collections.unmodifiableList:(Ljava/util/List;)Ljava/util/List;
      28: putfield      #45                 // Field propertySources:Ljava/util/List;
      31: aload_0
      32: aload_2
      33: putfield      #49                 // Field propertySourceOptions:Lorg/springframework/boot/context/config/ConfigData$PropertySourceOptions;
      36: return

  public java.util.List<org.springframework.core.env.PropertySource<?>> getPropertySources();
    Code:
       0: aload_0
       1: getfield      #45                 // Field propertySources:Ljava/util/List;
       4: areturn

  public org.springframework.boot.context.config.ConfigData$Options getOptions(org.springframework.core.env.PropertySource<?>);
    Code:
       0: aload_0
       1: getfield      #49                 // Field propertySourceOptions:Lorg/springframework/boot/context/config/ConfigData$PropertySourceOptions;
       4: aload_1
       5: invokeinterface #53,  2           // InterfaceMethod org/springframework/boot/context/config/ConfigData$PropertySourceOptions.get:(Lorg/springframework/core/env/PropertySource;)Lorg/springframework/boot/context/config/ConfigData$Options;
      10: astore_2
      11: aload_2
      12: ifnull        19
      15: aload_2
      16: goto          22
      19: getstatic     #57                 // Field org/springframework/boot/context/config/ConfigData$Options.NONE:Lorg/springframework/boot/context/config/ConfigData$Options;
      22: areturn

  static {};
    Code:
       0: new           #14                 // class org/springframework/boot/context/config/ConfigData
       3: dup
       4: invokestatic  #61                 // Method java/util/Collections.emptySet:()Ljava/util/Set;
       7: iconst_0
       8: anewarray     #65                 // class org/springframework/boot/context/config/ConfigData$Option
      11: invokespecial #67                 // Method "<init>":(Ljava/util/Collection;[Lorg/springframework/boot/context/config/ConfigData$Option;)V
      14: putstatic     #70                 // Field EMPTY:Lorg/springframework/boot/context/config/ConfigData;
      17: return
}
