Compiled from "ConfigDataNotFoundFailureAnalyzer.java"
class org.springframework.boot.context.config.ConfigDataNotFoundFailureAnalyzer extends org.springframework.boot.diagnostics.AbstractFailureAnalyzer<org.springframework.boot.context.config.ConfigDataNotFoundException> {
  org.springframework.boot.context.config.ConfigDataNotFoundFailureAnalyzer();
    Code:
       0: aload_0
       1: invokespecial #1                  // Method org/springframework/boot/diagnostics/AbstractFailureAnalyzer."<init>":()V
       4: return

  protected org.springframework.boot.diagnostics.FailureAnalysis analyze(java.lang.Throwable, org.springframework.boot.context.config.ConfigDataNotFoundException);
    Code:
       0: aload_0
       1: aload_2
       2: invokevirtual #7                  // Method getLocation:(Lorg/springframework/boot/context/config/ConfigDataNotFoundException;)Lorg/springframework/boot/context/config/ConfigDataLocation;
       5: astore_3
       6: aload_3
       7: invokestatic  #13                 // InterfaceMethod org/springframework/boot/origin/Origin.from:(Ljava/lang/Object;)Lorg/springframework/boot/origin/Origin;
      10: astore        4
      12: ldc           #19                 // String Config data %s does not exist
      14: iconst_1
      15: anewarray     #21                 // class java/lang/Object
      18: dup
      19: iconst_0
      20: aload_2
      21: invokevirtual #23                 // Method org/springframework/boot/context/config/ConfigDataNotFoundException.getReferenceDescription:()Ljava/lang/String;
      24: aastore
      25: invokestatic  #29                 // Method java/lang/String.format:(Ljava/lang/String;[Ljava/lang/Object;)Ljava/lang/String;
      28: astore        5
      30: new           #35                 // class java/lang/StringBuilder
      33: dup
      34: ldc           #37                 // String Check that the value
      36: invokespecial #39                 // Method java/lang/StringBuilder."<init>":(Ljava/lang/String;)V
      39: astore        6
      41: aload_3
      42: ifnull        64
      45: aload         6
      47: ldc           #42                 // String \'%s\'
      49: iconst_1
      50: anewarray     #21                 // class java/lang/Object
      53: dup
      54: iconst_0
      55: aload_3
      56: aastore
      57: invokestatic  #29                 // Method java/lang/String.format:(Ljava/lang/String;[Ljava/lang/Object;)Ljava/lang/String;
      60: invokevirtual #44                 // Method java/lang/StringBuilder.append:(Ljava/lang/String;)Ljava/lang/StringBuilder;
      63: pop
      64: aload         4
      66: ifnull        89
      69: aload         6
      71: ldc           #48                 // String at %s
      73: iconst_1
      74: anewarray     #21                 // class java/lang/Object
      77: dup
      78: iconst_0
      79: aload         4
      81: aastore
      82: invokestatic  #29                 // Method java/lang/String.format:(Ljava/lang/String;[Ljava/lang/Object;)Ljava/lang/String;
      85: invokevirtual #44                 // Method java/lang/StringBuilder.append:(Ljava/lang/String;)Ljava/lang/StringBuilder;
      88: pop
      89: aload         6
      91: ldc           #50                 // String is correct
      93: invokevirtual #44                 // Method java/lang/StringBuilder.append:(Ljava/lang/String;)Ljava/lang/StringBuilder;
      96: pop
      97: aload_3
      98: ifnull        128
     101: aload_3
     102: invokevirtual #52                 // Method org/springframework/boot/context/config/ConfigDataLocation.isOptional:()Z
     105: ifne          128
     108: aload         6
     110: ldc           #58                 // String , or prefix it with \'%s\'
     112: iconst_1
     113: anewarray     #21                 // class java/lang/Object
     116: dup
     117: iconst_0
     118: ldc           #60                 // String optional:
     120: aastore
     121: invokestatic  #29                 // Method java/lang/String.format:(Ljava/lang/String;[Ljava/lang/Object;)Ljava/lang/String;
     124: invokevirtual #44                 // Method java/lang/StringBuilder.append:(Ljava/lang/String;)Ljava/lang/StringBuilder;
     127: pop
     128: new           #62                 // class org/springframework/boot/diagnostics/FailureAnalysis
     131: dup
     132: aload         5
     134: aload         6
     136: invokevirtual #64                 // Method java/lang/StringBuilder.toString:()Ljava/lang/String;
     139: aload_2
     140: invokespecial #67                 // Method org/springframework/boot/diagnostics/FailureAnalysis."<init>":(Ljava/lang/String;Ljava/lang/String;Ljava/lang/Throwable;)V
     143: areturn

  private org.springframework.boot.context.config.ConfigDataLocation getLocation(org.springframework.boot.context.config.ConfigDataNotFoundException);
    Code:
       0: aload_1
       1: instanceof    #70                 // class org/springframework/boot/context/config/ConfigDataLocationNotFoundException
       4: ifeq          17
       7: aload_1
       8: checkcast     #70                 // class org/springframework/boot/context/config/ConfigDataLocationNotFoundException
      11: astore_2
      12: aload_2
      13: invokevirtual #72                 // Method org/springframework/boot/context/config/ConfigDataLocationNotFoundException.getLocation:()Lorg/springframework/boot/context/config/ConfigDataLocation;
      16: areturn
      17: aload_1
      18: instanceof    #75                 // class org/springframework/boot/context/config/ConfigDataResourceNotFoundException
      21: ifeq          34
      24: aload_1
      25: checkcast     #75                 // class org/springframework/boot/context/config/ConfigDataResourceNotFoundException
      28: astore_2
      29: aload_2
      30: invokevirtual #77                 // Method org/springframework/boot/context/config/ConfigDataResourceNotFoundException.getLocation:()Lorg/springframework/boot/context/config/ConfigDataLocation;
      33: areturn
      34: aconst_null
      35: areturn

  protected org.springframework.boot.diagnostics.FailureAnalysis analyze(java.lang.Throwable, java.lang.Throwable);
    Code:
       0: aload_0
       1: aload_1
       2: aload_2
       3: checkcast     #24                 // class org/springframework/boot/context/config/ConfigDataNotFoundException
       6: invokevirtual #78                 // Method analyze:(Ljava/lang/Throwable;Lorg/springframework/boot/context/config/ConfigDataNotFoundException;)Lorg/springframework/boot/diagnostics/FailureAnalysis;
       9: areturn
}
