Compiled from "InactiveConfigDataAccessException.java"
public class org.springframework.boot.context.config.InactiveConfigDataAccessException extends org.springframework.boot.context.config.ConfigDataException {
  private final org.springframework.core.env.PropertySource<?> propertySource;

  private final org.springframework.boot.context.config.ConfigDataResource location;

  private final java.lang.String propertyName;

  private final org.springframework.boot.origin.Origin origin;

  org.springframework.boot.context.config.InactiveConfigDataAccessException(org.springframework.core.env.PropertySource<?>, org.springframework.boot.context.config.ConfigDataResource, java.lang.String, org.springframework.boot.origin.Origin);
    Code:
       0: aload_0
       1: aload_1
       2: aload_2
       3: aload_3
       4: aload         4
       6: invokestatic  #1                  // Method getMessage:(Lorg/springframework/core/env/PropertySource;Lorg/springframework/boot/context/config/ConfigDataResource;Ljava/lang/String;Lorg/springframework/boot/origin/Origin;)Ljava/lang/String;
       9: aconst_null
      10: invokespecial #7                  // Method org/springframework/boot/context/config/ConfigDataException."<init>":(Ljava/lang/String;Ljava/lang/Throwable;)V
      13: aload_0
      14: aload_1
      15: putfield      #13                 // Field propertySource:Lorg/springframework/core/env/PropertySource;
      18: aload_0
      19: aload_2
      20: putfield      #17                 // Field location:Lorg/springframework/boot/context/config/ConfigDataResource;
      23: aload_0
      24: aload_3
      25: putfield      #21                 // Field propertyName:Ljava/lang/String;
      28: aload_0
      29: aload         4
      31: putfield      #25                 // Field origin:Lorg/springframework/boot/origin/Origin;
      34: return

  private static java.lang.String getMessage(org.springframework.core.env.PropertySource<?>, org.springframework.boot.context.config.ConfigDataResource, java.lang.String, org.springframework.boot.origin.Origin);
    Code:
       0: new           #29                 // class java/lang/StringBuilder
       3: dup
       4: ldc           #31                 // String Inactive property source \'
       6: invokespecial #33                 // Method java/lang/StringBuilder."<init>":(Ljava/lang/String;)V
       9: astore        4
      11: aload         4
      13: aload_0
      14: invokevirtual #36                 // Method org/springframework/core/env/PropertySource.getName:()Ljava/lang/String;
      17: invokevirtual #42                 // Method java/lang/StringBuilder.append:(Ljava/lang/String;)Ljava/lang/StringBuilder;
      20: pop
      21: aload_1
      22: ifnull        40
      25: aload         4
      27: ldc           #46                 // String \' imported from location \'
      29: invokevirtual #42                 // Method java/lang/StringBuilder.append:(Ljava/lang/String;)Ljava/lang/StringBuilder;
      32: pop
      33: aload         4
      35: aload_1
      36: invokevirtual #48                 // Method java/lang/StringBuilder.append:(Ljava/lang/Object;)Ljava/lang/StringBuilder;
      39: pop
      40: aload         4
      42: ldc           #51                 // String \' cannot contain property \'
      44: invokevirtual #42                 // Method java/lang/StringBuilder.append:(Ljava/lang/String;)Ljava/lang/StringBuilder;
      47: pop
      48: aload         4
      50: aload_2
      51: invokevirtual #42                 // Method java/lang/StringBuilder.append:(Ljava/lang/String;)Ljava/lang/StringBuilder;
      54: pop
      55: aload         4
      57: ldc           #53                 // String \'
      59: invokevirtual #42                 // Method java/lang/StringBuilder.append:(Ljava/lang/String;)Ljava/lang/StringBuilder;
      62: pop
      63: aload_3
      64: ifnull        90
      67: aload         4
      69: ldc           #55                 // String  [origin:
      71: invokevirtual #42                 // Method java/lang/StringBuilder.append:(Ljava/lang/String;)Ljava/lang/StringBuilder;
      74: pop
      75: aload         4
      77: aload_3
      78: invokevirtual #48                 // Method java/lang/StringBuilder.append:(Ljava/lang/Object;)Ljava/lang/StringBuilder;
      81: pop
      82: aload         4
      84: ldc           #57                 // String ]
      86: invokevirtual #42                 // Method java/lang/StringBuilder.append:(Ljava/lang/String;)Ljava/lang/StringBuilder;
      89: pop
      90: aload         4
      92: invokevirtual #59                 // Method java/lang/StringBuilder.toString:()Ljava/lang/String;
      95: areturn

  public org.springframework.core.env.PropertySource<?> getPropertySource();
    Code:
       0: aload_0
       1: getfield      #13                 // Field propertySource:Lorg/springframework/core/env/PropertySource;
       4: areturn

  public org.springframework.boot.context.config.ConfigDataResource getLocation();
    Code:
       0: aload_0
       1: getfield      #17                 // Field location:Lorg/springframework/boot/context/config/ConfigDataResource;
       4: areturn

  public java.lang.String getPropertyName();
    Code:
       0: aload_0
       1: getfield      #21                 // Field propertyName:Ljava/lang/String;
       4: areturn

  public org.springframework.boot.origin.Origin getOrigin();
    Code:
       0: aload_0
       1: getfield      #25                 // Field origin:Lorg/springframework/boot/origin/Origin;
       4: areturn

  static void throwIfPropertyFound(org.springframework.boot.context.config.ConfigDataEnvironmentContributor, org.springframework.boot.context.properties.source.ConfigurationPropertyName);
    Code:
       0: aload_0
       1: invokevirtual #62                 // Method org/springframework/boot/context/config/ConfigDataEnvironmentContributor.getConfigurationPropertySource:()Lorg/springframework/boot/context/properties/source/ConfigurationPropertySource;
       4: astore_2
       5: aload_2
       6: ifnull        19
       9: aload_2
      10: aload_1
      11: invokeinterface #68,  2           // InterfaceMethod org/springframework/boot/context/properties/source/ConfigurationPropertySource.getConfigurationProperty:(Lorg/springframework/boot/context/properties/source/ConfigurationPropertyName;)Lorg/springframework/boot/context/properties/source/ConfigurationProperty;
      16: goto          20
      19: aconst_null
      20: astore_3
      21: aload_3
      22: ifnull        57
      25: aload_0
      26: invokevirtual #74                 // Method org/springframework/boot/context/config/ConfigDataEnvironmentContributor.getPropertySource:()Lorg/springframework/core/env/PropertySource;
      29: astore        4
      31: aload_0
      32: invokevirtual #78                 // Method org/springframework/boot/context/config/ConfigDataEnvironmentContributor.getResource:()Lorg/springframework/boot/context/config/ConfigDataResource;
      35: astore        5
      37: new           #2                  // class org/springframework/boot/context/config/InactiveConfigDataAccessException
      40: dup
      41: aload         4
      43: aload         5
      45: aload_1
      46: invokevirtual #82                 // Method org/springframework/boot/context/properties/source/ConfigurationPropertyName.toString:()Ljava/lang/String;
      49: aload_3
      50: invokevirtual #85                 // Method org/springframework/boot/context/properties/source/ConfigurationProperty.getOrigin:()Lorg/springframework/boot/origin/Origin;
      53: invokespecial #91                 // Method "<init>":(Lorg/springframework/core/env/PropertySource;Lorg/springframework/boot/context/config/ConfigDataResource;Ljava/lang/String;Lorg/springframework/boot/origin/Origin;)V
      56: athrow
      57: return
}
