Compiled from "InvalidConfigDataPropertyException.java"
public class org.springframework.boot.context.config.InvalidConfigDataPropertyException extends org.springframework.boot.context.config.ConfigDataException {
  private static final java.util.Map<org.springframework.boot.context.properties.source.ConfigurationPropertyName, org.springframework.boot.context.properties.source.ConfigurationPropertyName> ERRORS;

  private static final java.util.Set<org.springframework.boot.context.properties.source.ConfigurationPropertyName> PROFILE_SPECIFIC_ERRORS;

  private final org.springframework.boot.context.properties.source.ConfigurationProperty property;

  private final org.springframework.boot.context.properties.source.ConfigurationPropertyName replacement;

  private final org.springframework.boot.context.config.ConfigDataResource location;

  org.springframework.boot.context.config.InvalidConfigDataPropertyException(org.springframework.boot.context.properties.source.ConfigurationProperty, boolean, org.springframework.boot.context.properties.source.ConfigurationPropertyName, org.springframework.boot.context.config.ConfigDataResource);
    Code:
       0: aload_0
       1: aload_1
       2: iload_2
       3: aload_3
       4: aload         4
       6: invokestatic  #1                  // Method getMessage:(Lorg/springframework/boot/context/properties/source/ConfigurationProperty;ZLorg/springframework/boot/context/properties/source/ConfigurationPropertyName;Lorg/springframework/boot/context/config/ConfigDataResource;)Ljava/lang/String;
       9: aconst_null
      10: invokespecial #7                  // Method org/springframework/boot/context/config/ConfigDataException."<init>":(Ljava/lang/String;Ljava/lang/Throwable;)V
      13: aload_0
      14: aload_1
      15: putfield      #13                 // Field property:Lorg/springframework/boot/context/properties/source/ConfigurationProperty;
      18: aload_0
      19: aload_3
      20: putfield      #17                 // Field replacement:Lorg/springframework/boot/context/properties/source/ConfigurationPropertyName;
      23: aload_0
      24: aload         4
      26: putfield      #21                 // Field location:Lorg/springframework/boot/context/config/ConfigDataResource;
      29: return

  public org.springframework.boot.context.properties.source.ConfigurationProperty getProperty();
    Code:
       0: aload_0
       1: getfield      #13                 // Field property:Lorg/springframework/boot/context/properties/source/ConfigurationProperty;
       4: areturn

  public org.springframework.boot.context.config.ConfigDataResource getLocation();
    Code:
       0: aload_0
       1: getfield      #21                 // Field location:Lorg/springframework/boot/context/config/ConfigDataResource;
       4: areturn

  public org.springframework.boot.context.properties.source.ConfigurationPropertyName getReplacement();
    Code:
       0: aload_0
       1: getfield      #17                 // Field replacement:Lorg/springframework/boot/context/properties/source/ConfigurationPropertyName;
       4: areturn

  static void throwIfPropertyFound(org.springframework.boot.context.config.ConfigDataEnvironmentContributor);
    Code:
       0: aload_0
       1: invokevirtual #25                 // Method org/springframework/boot/context/config/ConfigDataEnvironmentContributor.getConfigurationPropertySource:()Lorg/springframework/boot/context/properties/source/ConfigurationPropertySource;
       4: astore_1
       5: aload_1
       6: ifnull        56
       9: getstatic     #31                 // Field ERRORS:Ljava/util/Map;
      12: aload_1
      13: aload_0
      14: invokedynamic #35,  0             // InvokeDynamic #0:accept:(Lorg/springframework/boot/context/properties/source/ConfigurationPropertySource;Lorg/springframework/boot/context/config/ConfigDataEnvironmentContributor;)Ljava/util/function/BiConsumer;
      19: invokeinterface #39,  2           // InterfaceMethod java/util/Map.forEach:(Ljava/util/function/BiConsumer;)V
      24: aload_0
      25: invokevirtual #45                 // Method org/springframework/boot/context/config/ConfigDataEnvironmentContributor.isFromProfileSpecificImport:()Z
      28: ifeq          56
      31: aload_0
      32: getstatic     #49                 // Field org/springframework/boot/context/config/ConfigData$Option.IGNORE_PROFILES:Lorg/springframework/boot/context/config/ConfigData$Option;
      35: invokevirtual #55                 // Method org/springframework/boot/context/config/ConfigDataEnvironmentContributor.hasConfigDataOption:(Lorg/springframework/boot/context/config/ConfigData$Option;)Z
      38: ifne          56
      41: getstatic     #59                 // Field PROFILE_SPECIFIC_ERRORS:Ljava/util/Set;
      44: aload_1
      45: aload_0
      46: invokedynamic #63,  0             // InvokeDynamic #1:accept:(Lorg/springframework/boot/context/properties/source/ConfigurationPropertySource;Lorg/springframework/boot/context/config/ConfigDataEnvironmentContributor;)Ljava/util/function/Consumer;
      51: invokeinterface #66,  2           // InterfaceMethod java/util/Set.forEach:(Ljava/util/function/Consumer;)V
      56: return

  private static java.lang.String getMessage(org.springframework.boot.context.properties.source.ConfigurationProperty, boolean, org.springframework.boot.context.properties.source.ConfigurationPropertyName, org.springframework.boot.context.config.ConfigDataResource);
    Code:
       0: new           #71                 // class java/lang/StringBuilder
       3: dup
       4: ldc           #73                 // String Property \'
       6: invokespecial #75                 // Method java/lang/StringBuilder."<init>":(Ljava/lang/String;)V
       9: astore        4
      11: aload         4
      13: aload_0
      14: invokevirtual #78                 // Method org/springframework/boot/context/properties/source/ConfigurationProperty.getName:()Lorg/springframework/boot/context/properties/source/ConfigurationPropertyName;
      17: invokevirtual #84                 // Method java/lang/StringBuilder.append:(Ljava/lang/Object;)Ljava/lang/StringBuilder;
      20: pop
      21: aload_3
      22: ifnull        40
      25: aload         4
      27: ldc           #88                 // String \' imported from location \'
      29: invokevirtual #90                 // Method java/lang/StringBuilder.append:(Ljava/lang/String;)Ljava/lang/StringBuilder;
      32: pop
      33: aload         4
      35: aload_3
      36: invokevirtual #84                 // Method java/lang/StringBuilder.append:(Ljava/lang/Object;)Ljava/lang/StringBuilder;
      39: pop
      40: aload         4
      42: ldc           #93                 // String \' is invalid
      44: invokevirtual #90                 // Method java/lang/StringBuilder.append:(Ljava/lang/String;)Ljava/lang/StringBuilder;
      47: pop
      48: iload_1
      49: ifeq          60
      52: aload         4
      54: ldc           #95                 // String  in a profile specific resource
      56: invokevirtual #90                 // Method java/lang/StringBuilder.append:(Ljava/lang/String;)Ljava/lang/StringBuilder;
      59: pop
      60: aload_2
      61: ifnull        87
      64: aload         4
      66: ldc           #97                 // String  and should be replaced with \'
      68: invokevirtual #90                 // Method java/lang/StringBuilder.append:(Ljava/lang/String;)Ljava/lang/StringBuilder;
      71: pop
      72: aload         4
      74: aload_2
      75: invokevirtual #84                 // Method java/lang/StringBuilder.append:(Ljava/lang/Object;)Ljava/lang/StringBuilder;
      78: pop
      79: aload         4
      81: ldc           #99                 // String \'
      83: invokevirtual #90                 // Method java/lang/StringBuilder.append:(Ljava/lang/String;)Ljava/lang/StringBuilder;
      86: pop
      87: aload_0
      88: invokevirtual #101                // Method org/springframework/boot/context/properties/source/ConfigurationProperty.getOrigin:()Lorg/springframework/boot/origin/Origin;
      91: ifnull        120
      94: aload         4
      96: ldc           #105                // String  [origin:
      98: invokevirtual #90                 // Method java/lang/StringBuilder.append:(Ljava/lang/String;)Ljava/lang/StringBuilder;
     101: pop
     102: aload         4
     104: aload_0
     105: invokevirtual #101                // Method org/springframework/boot/context/properties/source/ConfigurationProperty.getOrigin:()Lorg/springframework/boot/origin/Origin;
     108: invokevirtual #84                 // Method java/lang/StringBuilder.append:(Ljava/lang/Object;)Ljava/lang/StringBuilder;
     111: pop
     112: aload         4
     114: ldc           #107                // String ]
     116: invokevirtual #90                 // Method java/lang/StringBuilder.append:(Ljava/lang/String;)Ljava/lang/StringBuilder;
     119: pop
     120: aload         4
     122: invokevirtual #109                // Method java/lang/StringBuilder.toString:()Ljava/lang/String;
     125: areturn

  private static void lambda$throwIfPropertyFound$1(org.springframework.boot.context.properties.source.ConfigurationPropertySource, org.springframework.boot.context.config.ConfigDataEnvironmentContributor, org.springframework.boot.context.properties.source.ConfigurationPropertyName);
    Code:
       0: aload_0
       1: aload_2
       2: invokeinterface #113,  2          // InterfaceMethod org/springframework/boot/context/properties/source/ConfigurationPropertySource.getConfigurationProperty:(Lorg/springframework/boot/context/properties/source/ConfigurationPropertyName;)Lorg/springframework/boot/context/properties/source/ConfigurationProperty;
       7: astore_3
       8: aload_3
       9: ifnull        27
      12: new           #2                  // class org/springframework/boot/context/config/InvalidConfigDataPropertyException
      15: dup
      16: aload_3
      17: iconst_1
      18: aconst_null
      19: aload_1
      20: invokevirtual #119                // Method org/springframework/boot/context/config/ConfigDataEnvironmentContributor.getResource:()Lorg/springframework/boot/context/config/ConfigDataResource;
      23: invokespecial #123                // Method "<init>":(Lorg/springframework/boot/context/properties/source/ConfigurationProperty;ZLorg/springframework/boot/context/properties/source/ConfigurationPropertyName;Lorg/springframework/boot/context/config/ConfigDataResource;)V
      26: athrow
      27: return

  private static void lambda$throwIfPropertyFound$0(org.springframework.boot.context.properties.source.ConfigurationPropertySource, org.springframework.boot.context.config.ConfigDataEnvironmentContributor, org.springframework.boot.context.properties.source.ConfigurationPropertyName, org.springframework.boot.context.properties.source.ConfigurationPropertyName);
    Code:
       0: aload_0
       1: aload_2
       2: invokeinterface #113,  2          // InterfaceMethod org/springframework/boot/context/properties/source/ConfigurationPropertySource.getConfigurationProperty:(Lorg/springframework/boot/context/properties/source/ConfigurationPropertyName;)Lorg/springframework/boot/context/properties/source/ConfigurationProperty;
       7: astore        4
       9: aload         4
      11: ifnull        30
      14: new           #2                  // class org/springframework/boot/context/config/InvalidConfigDataPropertyException
      17: dup
      18: aload         4
      20: iconst_0
      21: aload_3
      22: aload_1
      23: invokevirtual #119                // Method org/springframework/boot/context/config/ConfigDataEnvironmentContributor.getResource:()Lorg/springframework/boot/context/config/ConfigDataResource;
      26: invokespecial #123                // Method "<init>":(Lorg/springframework/boot/context/properties/source/ConfigurationProperty;ZLorg/springframework/boot/context/properties/source/ConfigurationPropertyName;Lorg/springframework/boot/context/config/ConfigDataResource;)V
      29: athrow
      30: return

  static {};
    Code:
       0: new           #126                // class java/util/LinkedHashMap
       3: dup
       4: invokespecial #128                // Method java/util/LinkedHashMap."<init>":()V
       7: astore_0
       8: aload_0
       9: ldc           #131                // String spring.profiles
      11: invokestatic  #133                // Method org/springframework/boot/context/properties/source/ConfigurationPropertyName.of:(Ljava/lang/CharSequence;)Lorg/springframework/boot/context/properties/source/ConfigurationPropertyName;
      14: ldc           #139                // String spring.config.activate.on-profile
      16: invokestatic  #133                // Method org/springframework/boot/context/properties/source/ConfigurationPropertyName.of:(Ljava/lang/CharSequence;)Lorg/springframework/boot/context/properties/source/ConfigurationPropertyName;
      19: invokeinterface #141,  3          // InterfaceMethod java/util/Map.put:(Ljava/lang/Object;Ljava/lang/Object;)Ljava/lang/Object;
      24: pop
      25: aload_0
      26: ldc           #145                // String spring.profiles[0]
      28: invokestatic  #133                // Method org/springframework/boot/context/properties/source/ConfigurationPropertyName.of:(Ljava/lang/CharSequence;)Lorg/springframework/boot/context/properties/source/ConfigurationPropertyName;
      31: ldc           #139                // String spring.config.activate.on-profile
      33: invokestatic  #133                // Method org/springframework/boot/context/properties/source/ConfigurationPropertyName.of:(Ljava/lang/CharSequence;)Lorg/springframework/boot/context/properties/source/ConfigurationPropertyName;
      36: invokeinterface #141,  3          // InterfaceMethod java/util/Map.put:(Ljava/lang/Object;Ljava/lang/Object;)Ljava/lang/Object;
      41: pop
      42: aload_0
      43: invokestatic  #147                // Method java/util/Collections.unmodifiableMap:(Ljava/util/Map;)Ljava/util/Map;
      46: putstatic     #31                 // Field ERRORS:Ljava/util/Map;
      49: new           #153                // class java/util/LinkedHashSet
      52: dup
      53: invokespecial #155                // Method java/util/LinkedHashSet."<init>":()V
      56: astore_0
      57: aload_0
      58: getstatic     #156                // Field org/springframework/boot/context/config/Profiles.INCLUDE_PROFILES:Lorg/springframework/boot/context/properties/source/ConfigurationPropertyName;
      61: invokeinterface #161,  2          // InterfaceMethod java/util/Set.add:(Ljava/lang/Object;)Z
      66: pop
      67: aload_0
      68: getstatic     #156                // Field org/springframework/boot/context/config/Profiles.INCLUDE_PROFILES:Lorg/springframework/boot/context/properties/source/ConfigurationPropertyName;
      71: ldc           #165                // String [0]
      73: invokevirtual #167                // Method org/springframework/boot/context/properties/source/ConfigurationPropertyName.append:(Ljava/lang/String;)Lorg/springframework/boot/context/properties/source/ConfigurationPropertyName;
      76: invokeinterface #161,  2          // InterfaceMethod java/util/Set.add:(Ljava/lang/Object;)Z
      81: pop
      82: aload_0
      83: ldc           #172                // String spring.profiles.active
      85: invokestatic  #133                // Method org/springframework/boot/context/properties/source/ConfigurationPropertyName.of:(Ljava/lang/CharSequence;)Lorg/springframework/boot/context/properties/source/ConfigurationPropertyName;
      88: invokeinterface #161,  2          // InterfaceMethod java/util/Set.add:(Ljava/lang/Object;)Z
      93: pop
      94: aload_0
      95: ldc           #174                // String spring.profiles.active[0]
      97: invokestatic  #133                // Method org/springframework/boot/context/properties/source/ConfigurationPropertyName.of:(Ljava/lang/CharSequence;)Lorg/springframework/boot/context/properties/source/ConfigurationPropertyName;
     100: invokeinterface #161,  2          // InterfaceMethod java/util/Set.add:(Ljava/lang/Object;)Z
     105: pop
     106: aload_0
     107: ldc           #176                // String spring.profiles.default
     109: invokestatic  #133                // Method org/springframework/boot/context/properties/source/ConfigurationPropertyName.of:(Ljava/lang/CharSequence;)Lorg/springframework/boot/context/properties/source/ConfigurationPropertyName;
     112: invokeinterface #161,  2          // InterfaceMethod java/util/Set.add:(Ljava/lang/Object;)Z
     117: pop
     118: aload_0
     119: ldc           #178                // String spring.profiles.default[0]
     121: invokestatic  #133                // Method org/springframework/boot/context/properties/source/ConfigurationPropertyName.of:(Ljava/lang/CharSequence;)Lorg/springframework/boot/context/properties/source/ConfigurationPropertyName;
     124: invokeinterface #161,  2          // InterfaceMethod java/util/Set.add:(Ljava/lang/Object;)Z
     129: pop
     130: aload_0
     131: invokestatic  #180                // Method java/util/Collections.unmodifiableSet:(Ljava/util/Set;)Ljava/util/Set;
     134: putstatic     #59                 // Field PROFILE_SPECIFIC_ERRORS:Ljava/util/Set;
     137: return
}
