Compiled from "Profiles.java"
public class org.springframework.boot.context.config.Profiles implements java.lang.Iterable<java.lang.String> {
  public static final java.lang.String INCLUDE_PROFILES_PROPERTY_NAME;

  static final org.springframework.boot.context.properties.source.ConfigurationPropertyName INCLUDE_PROFILES;

  private static final org.springframework.boot.context.properties.bind.Bindable<org.springframework.util.MultiValueMap<java.lang.String, java.lang.String>> STRING_STRINGS_MAP;

  private static final org.springframework.boot.context.properties.bind.Bindable<java.util.Set<java.lang.String>> STRING_SET;

  private final org.springframework.util.MultiValueMap<java.lang.String, java.lang.String> groups;

  private final java.util.List<java.lang.String> activeProfiles;

  private final java.util.List<java.lang.String> defaultProfiles;

  org.springframework.boot.context.config.Profiles(org.springframework.core.env.Environment, org.springframework.boot.context.properties.bind.Binder, java.util.Collection<java.lang.String>);
    Code:
       0: aload_0
       1: invokespecial #1                  // Method java/lang/Object."<init>":()V
       4: aload_0
       5: aload_2
       6: ldc           #7                  // String spring.profiles.group
       8: getstatic     #9                  // Field STRING_STRINGS_MAP:Lorg/springframework/boot/context/properties/bind/Bindable;
      11: invokevirtual #15                 // Method org/springframework/boot/context/properties/bind/Binder.bind:(Ljava/lang/String;Lorg/springframework/boot/context/properties/bind/Bindable;)Lorg/springframework/boot/context/properties/bind/BindResult;
      14: invokedynamic #21,  0             // InvokeDynamic #0:get:()Ljava/util/function/Supplier;
      19: invokevirtual #25                 // Method org/springframework/boot/context/properties/bind/BindResult.orElseGet:(Ljava/util/function/Supplier;)Ljava/lang/Object;
      22: checkcast     #31                 // class org/springframework/util/MultiValueMap
      25: putfield      #33                 // Field groups:Lorg/springframework/util/MultiValueMap;
      28: aload_0
      29: aload_0
      30: aload_0
      31: aload_1
      32: aload_2
      33: aload_3
      34: invokevirtual #37                 // Method getActivatedProfiles:(Lorg/springframework/core/env/Environment;Lorg/springframework/boot/context/properties/bind/Binder;Ljava/util/Collection;)Ljava/util/List;
      37: invokevirtual #41                 // Method expandProfiles:(Ljava/util/List;)Ljava/util/List;
      40: putfield      #45                 // Field activeProfiles:Ljava/util/List;
      43: aload_0
      44: aload_0
      45: aload_0
      46: aload_1
      47: aload_2
      48: invokevirtual #49                 // Method getDefaultProfiles:(Lorg/springframework/core/env/Environment;Lorg/springframework/boot/context/properties/bind/Binder;)Ljava/util/List;
      51: invokevirtual #41                 // Method expandProfiles:(Ljava/util/List;)Ljava/util/List;
      54: putfield      #53                 // Field defaultProfiles:Ljava/util/List;
      57: return

  private java.util.List<java.lang.String> getActivatedProfiles(org.springframework.core.env.Environment, org.springframework.boot.context.properties.bind.Binder, java.util.Collection<java.lang.String>);
    Code:
       0: aload_0
       1: aload_0
       2: aload_1
       3: aload_2
       4: getstatic     #56                 // Field org/springframework/boot/context/config/Profiles$Type.ACTIVE:Lorg/springframework/boot/context/config/Profiles$Type;
       7: invokevirtual #62                 // Method getProfiles:(Lorg/springframework/core/env/Environment;Lorg/springframework/boot/context/properties/bind/Binder;Lorg/springframework/boot/context/config/Profiles$Type;)Ljava/util/Collection;
      10: aload_3
      11: invokevirtual #66                 // Method asUniqueItemList:(Ljava/util/Collection;Ljava/util/Collection;)Ljava/util/List;
      14: areturn

  private java.util.List<java.lang.String> getDefaultProfiles(org.springframework.core.env.Environment, org.springframework.boot.context.properties.bind.Binder);
    Code:
       0: aload_0
       1: aload_0
       2: aload_1
       3: aload_2
       4: getstatic     #70                 // Field org/springframework/boot/context/config/Profiles$Type.DEFAULT:Lorg/springframework/boot/context/config/Profiles$Type;
       7: invokevirtual #62                 // Method getProfiles:(Lorg/springframework/core/env/Environment;Lorg/springframework/boot/context/properties/bind/Binder;Lorg/springframework/boot/context/config/Profiles$Type;)Ljava/util/Collection;
      10: invokevirtual #73                 // Method asUniqueItemList:(Ljava/util/Collection;)Ljava/util/List;
      13: areturn

  private java.util.Collection<java.lang.String> getProfiles(org.springframework.core.env.Environment, org.springframework.boot.context.properties.bind.Binder, org.springframework.boot.context.config.Profiles$Type);
    Code:
       0: aload_1
       1: aload_3
       2: invokevirtual #76                 // Method org/springframework/boot/context/config/Profiles$Type.getName:()Ljava/lang/String;
       5: invokeinterface #80,  2           // InterfaceMethod org/springframework/core/env/Environment.getProperty:(Ljava/lang/String;)Ljava/lang/String;
      10: astore        4
      12: aload         4
      14: invokestatic  #86                 // Method org/springframework/util/StringUtils.hasLength:(Ljava/lang/String;)Z
      17: ifne          26
      20: invokestatic  #92                 // Method java/util/Collections.emptySet:()Ljava/util/Set;
      23: goto          34
      26: aload         4
      28: invokestatic  #98                 // Method org/springframework/util/StringUtils.trimAllWhitespace:(Ljava/lang/String;)Ljava/lang/String;
      31: invokestatic  #101                // Method org/springframework/util/StringUtils.commaDelimitedListToSet:(Ljava/lang/String;)Ljava/util/Set;
      34: astore        5
      36: new           #105                // class java/util/LinkedHashSet
      39: dup
      40: aload_3
      41: aload_1
      42: invokevirtual #107                // Method org/springframework/boot/context/config/Profiles$Type.get:(Lorg/springframework/core/env/Environment;)[Ljava/lang/String;
      45: invokestatic  #110                // Method java/util/Arrays.asList:([Ljava/lang/Object;)Ljava/util/List;
      48: invokespecial #116                // Method java/util/LinkedHashSet."<init>":(Ljava/util/Collection;)V
      51: astore        6
      53: aload_2
      54: aload_3
      55: invokevirtual #76                 // Method org/springframework/boot/context/config/Profiles$Type.getName:()Ljava/lang/String;
      58: getstatic     #119                // Field STRING_SET:Lorg/springframework/boot/context/properties/bind/Bindable;
      61: invokevirtual #15                 // Method org/springframework/boot/context/properties/bind/Binder.bind:(Ljava/lang/String;Lorg/springframework/boot/context/properties/bind/Bindable;)Lorg/springframework/boot/context/properties/bind/BindResult;
      64: astore        7
      66: aload_0
      67: aload_3
      68: aload         4
      70: aload         5
      72: aload         6
      74: invokevirtual #122                // Method hasProgrammaticallySetProfiles:(Lorg/springframework/boot/context/config/Profiles$Type;Ljava/lang/String;Ljava/util/Set;Ljava/util/Set;)Z
      77: ifeq          118
      80: aload_3
      81: invokevirtual #126                // Method org/springframework/boot/context/config/Profiles$Type.isMergeWithEnvironmentProfiles:()Z
      84: ifeq          95
      87: aload         7
      89: invokevirtual #130                // Method org/springframework/boot/context/properties/bind/BindResult.isBound:()Z
      92: ifne          98
      95: aload         6
      97: areturn
      98: aload         7
     100: aload_0
     101: aload         6
     103: invokedynamic #133,  0            // InvokeDynamic #1:apply:(Lorg/springframework/boot/context/config/Profiles;Ljava/util/Set;)Ljava/util/function/Function;
     108: invokevirtual #137                // Method org/springframework/boot/context/properties/bind/BindResult.map:(Ljava/util/function/Function;)Lorg/springframework/boot/context/properties/bind/BindResult;
     111: invokevirtual #141                // Method org/springframework/boot/context/properties/bind/BindResult.get:()Ljava/lang/Object;
     114: checkcast     #144                // class java/util/Collection
     117: areturn
     118: aload         7
     120: aload_3
     121: invokevirtual #146                // Method org/springframework/boot/context/config/Profiles$Type.getDefaultValue:()Ljava/util/Set;
     124: invokevirtual #149                // Method org/springframework/boot/context/properties/bind/BindResult.orElse:(Ljava/lang/Object;)Ljava/lang/Object;
     127: checkcast     #144                // class java/util/Collection
     130: areturn

  private boolean hasProgrammaticallySetProfiles(org.springframework.boot.context.config.Profiles$Type, java.lang.String, java.util.Set<java.lang.String>, java.util.Set<java.lang.String>);
    Code:
       0: aload_2
       1: invokestatic  #86                 // Method org/springframework/util/StringUtils.hasLength:(Ljava/lang/String;)Z
       4: ifne          27
       7: aload_1
       8: invokevirtual #146                // Method org/springframework/boot/context/config/Profiles$Type.getDefaultValue:()Ljava/util/Set;
      11: aload         4
      13: invokeinterface #153,  2          // InterfaceMethod java/util/Set.equals:(Ljava/lang/Object;)Z
      18: ifne          25
      21: iconst_1
      22: goto          26
      25: iconst_0
      26: ireturn
      27: aload_1
      28: invokevirtual #146                // Method org/springframework/boot/context/config/Profiles$Type.getDefaultValue:()Ljava/util/Set;
      31: aload         4
      33: invokeinterface #153,  2          // InterfaceMethod java/util/Set.equals:(Ljava/lang/Object;)Z
      38: ifeq          43
      41: iconst_0
      42: ireturn
      43: aload_3
      44: aload         4
      46: invokeinterface #153,  2          // InterfaceMethod java/util/Set.equals:(Ljava/lang/Object;)Z
      51: ifne          58
      54: iconst_1
      55: goto          59
      58: iconst_0
      59: ireturn

  private java.util.Set<java.lang.String> merge(java.util.Set<java.lang.String>, java.util.Set<java.lang.String>);
    Code:
       0: new           #105                // class java/util/LinkedHashSet
       3: dup
       4: aload_1
       5: invokespecial #116                // Method java/util/LinkedHashSet."<init>":(Ljava/util/Collection;)V
       8: astore_3
       9: aload_3
      10: aload_2
      11: invokeinterface #159,  2          // InterfaceMethod java/util/Set.addAll:(Ljava/util/Collection;)Z
      16: pop
      17: aload_3
      18: areturn

  private java.util.List<java.lang.String> expandProfiles(java.util.List<java.lang.String>);
    Code:
       0: new           #163                // class java/util/ArrayDeque
       3: dup
       4: invokespecial #165                // Method java/util/ArrayDeque."<init>":()V
       7: astore_2
       8: aload_0
       9: aload_1
      10: invokevirtual #166                // Method asReversedList:(Ljava/util/List;)Ljava/util/List;
      13: aload_2
      14: dup
      15: invokestatic  #169                // Method java/util/Objects.requireNonNull:(Ljava/lang/Object;)Ljava/lang/Object;
      18: pop
      19: invokedynamic #174,  0            // InvokeDynamic #2:accept:(Ljava/util/Deque;)Ljava/util/function/Consumer;
      24: invokeinterface #178,  2          // InterfaceMethod java/util/List.forEach:(Ljava/util/function/Consumer;)V
      29: new           #105                // class java/util/LinkedHashSet
      32: dup
      33: invokespecial #184                // Method java/util/LinkedHashSet."<init>":()V
      36: astore_3
      37: aload_2
      38: invokeinterface #185,  1          // InterfaceMethod java/util/Deque.isEmpty:()Z
      43: ifne          105
      46: aload_2
      47: invokeinterface #190,  1          // InterfaceMethod java/util/Deque.pop:()Ljava/lang/Object;
      52: checkcast     #193                // class java/lang/String
      55: astore        4
      57: aload_3
      58: aload         4
      60: invokeinterface #195,  2          // InterfaceMethod java/util/Set.add:(Ljava/lang/Object;)Z
      65: ifeq          102
      68: aload_0
      69: aload_0
      70: getfield      #33                 // Field groups:Lorg/springframework/util/MultiValueMap;
      73: aload         4
      75: invokeinterface #198,  2          // InterfaceMethod org/springframework/util/MultiValueMap.get:(Ljava/lang/Object;)Ljava/lang/Object;
      80: checkcast     #179                // class java/util/List
      83: invokevirtual #166                // Method asReversedList:(Ljava/util/List;)Ljava/util/List;
      86: aload_2
      87: dup
      88: invokestatic  #169                // Method java/util/Objects.requireNonNull:(Ljava/lang/Object;)Ljava/lang/Object;
      91: pop
      92: invokedynamic #174,  0            // InvokeDynamic #2:accept:(Ljava/util/Deque;)Ljava/util/function/Consumer;
      97: invokeinterface #178,  2          // InterfaceMethod java/util/List.forEach:(Ljava/util/function/Consumer;)V
     102: goto          37
     105: aload_0
     106: aload_3
     107: invokevirtual #73                 // Method asUniqueItemList:(Ljava/util/Collection;)Ljava/util/List;
     110: areturn

  private java.util.List<java.lang.String> asReversedList(java.util.List<java.lang.String>);
    Code:
       0: aload_1
       1: invokestatic  #200                // Method org/springframework/util/CollectionUtils.isEmpty:(Ljava/util/Collection;)Z
       4: ifeq          11
       7: invokestatic  #204                // Method java/util/Collections.emptyList:()Ljava/util/List;
      10: areturn
      11: new           #208                // class java/util/ArrayList
      14: dup
      15: aload_1
      16: invokespecial #210                // Method java/util/ArrayList."<init>":(Ljava/util/Collection;)V
      19: astore_2
      20: aload_2
      21: invokestatic  #211                // Method java/util/Collections.reverse:(Ljava/util/List;)V
      24: aload_2
      25: areturn

  private java.util.List<java.lang.String> asUniqueItemList(java.util.Collection<java.lang.String>);
    Code:
       0: aload_0
       1: aload_1
       2: aconst_null
       3: invokevirtual #66                 // Method asUniqueItemList:(Ljava/util/Collection;Ljava/util/Collection;)Ljava/util/List;
       6: areturn

  private java.util.List<java.lang.String> asUniqueItemList(java.util.Collection<java.lang.String>, java.util.Collection<java.lang.String>);
    Code:
       0: new           #105                // class java/util/LinkedHashSet
       3: dup
       4: invokespecial #184                // Method java/util/LinkedHashSet."<init>":()V
       7: astore_3
       8: aload_2
       9: invokestatic  #200                // Method org/springframework/util/CollectionUtils.isEmpty:(Ljava/util/Collection;)Z
      12: ifne          21
      15: aload_3
      16: aload_2
      17: invokevirtual #215                // Method java/util/LinkedHashSet.addAll:(Ljava/util/Collection;)Z
      20: pop
      21: aload_3
      22: aload_1
      23: invokevirtual #215                // Method java/util/LinkedHashSet.addAll:(Ljava/util/Collection;)Z
      26: pop
      27: new           #208                // class java/util/ArrayList
      30: dup
      31: aload_3
      32: invokespecial #210                // Method java/util/ArrayList."<init>":(Ljava/util/Collection;)V
      35: invokestatic  #216                // Method java/util/Collections.unmodifiableList:(Ljava/util/List;)Ljava/util/List;
      38: areturn

  public java.util.Iterator<java.lang.String> iterator();
    Code:
       0: aload_0
       1: invokevirtual #219                // Method getAccepted:()Ljava/util/List;
       4: invokeinterface #222,  1          // InterfaceMethod java/util/List.iterator:()Ljava/util/Iterator;
       9: areturn

  public java.util.List<java.lang.String> getActive();
    Code:
       0: aload_0
       1: getfield      #45                 // Field activeProfiles:Ljava/util/List;
       4: areturn

  public java.util.List<java.lang.String> getDefault();
    Code:
       0: aload_0
       1: getfield      #53                 // Field defaultProfiles:Ljava/util/List;
       4: areturn

  public java.util.List<java.lang.String> getAccepted();
    Code:
       0: aload_0
       1: getfield      #45                 // Field activeProfiles:Ljava/util/List;
       4: invokeinterface #226,  1          // InterfaceMethod java/util/List.isEmpty:()Z
       9: ifne          19
      12: aload_0
      13: getfield      #45                 // Field activeProfiles:Ljava/util/List;
      16: goto          23
      19: aload_0
      20: getfield      #53                 // Field defaultProfiles:Ljava/util/List;
      23: areturn

  public boolean isAccepted(java.lang.String);
    Code:
       0: aload_0
       1: invokevirtual #219                // Method getAccepted:()Ljava/util/List;
       4: aload_1
       5: invokeinterface #227,  2          // InterfaceMethod java/util/List.contains:(Ljava/lang/Object;)Z
      10: ireturn

  public java.lang.String toString();
    Code:
       0: new           #230                // class org/springframework/core/style/ToStringCreator
       3: dup
       4: aload_0
       5: invokespecial #232                // Method org/springframework/core/style/ToStringCreator."<init>":(Ljava/lang/Object;)V
       8: astore_1
       9: aload_1
      10: ldc           #235                // String active
      12: aload_0
      13: invokevirtual #237                // Method getActive:()Ljava/util/List;
      16: invokevirtual #240                // Method java/lang/Object.toString:()Ljava/lang/String;
      19: invokevirtual #243                // Method org/springframework/core/style/ToStringCreator.append:(Ljava/lang/String;Ljava/lang/Object;)Lorg/springframework/core/style/ToStringCreator;
      22: pop
      23: aload_1
      24: ldc           #247                // String default
      26: aload_0
      27: invokevirtual #249                // Method getDefault:()Ljava/util/List;
      30: invokevirtual #240                // Method java/lang/Object.toString:()Ljava/lang/String;
      33: invokevirtual #243                // Method org/springframework/core/style/ToStringCreator.append:(Ljava/lang/String;Ljava/lang/Object;)Lorg/springframework/core/style/ToStringCreator;
      36: pop
      37: aload_1
      38: ldc           #252                // String accepted
      40: aload_0
      41: invokevirtual #219                // Method getAccepted:()Ljava/util/List;
      44: invokevirtual #240                // Method java/lang/Object.toString:()Ljava/lang/String;
      47: invokevirtual #243                // Method org/springframework/core/style/ToStringCreator.append:(Ljava/lang/String;Ljava/lang/Object;)Lorg/springframework/core/style/ToStringCreator;
      50: pop
      51: aload_1
      52: invokevirtual #254                // Method org/springframework/core/style/ToStringCreator.toString:()Ljava/lang/String;
      55: areturn

  private java.util.Set lambda$getProfiles$0(java.util.Set, java.util.Set);
    Code:
       0: aload_0
       1: aload_1
       2: aload_2
       3: invokevirtual #255                // Method merge:(Ljava/util/Set;Ljava/util/Set;)Ljava/util/Set;
       6: areturn

  static {};
    Code:
       0: ldc_w         #259                // String spring.profiles.include
       3: invokestatic  #261                // Method org/springframework/boot/context/properties/source/ConfigurationPropertyName.of:(Ljava/lang/CharSequence;)Lorg/springframework/boot/context/properties/source/ConfigurationPropertyName;
       6: putstatic     #267                // Field INCLUDE_PROFILES:Lorg/springframework/boot/context/properties/source/ConfigurationPropertyName;
       9: ldc           #31                 // class org/springframework/util/MultiValueMap
      11: iconst_2
      12: anewarray     #271                // class java/lang/Class
      15: dup
      16: iconst_0
      17: ldc           #193                // class java/lang/String
      19: aastore
      20: dup
      21: iconst_1
      22: ldc           #193                // class java/lang/String
      24: aastore
      25: invokestatic  #273                // Method org/springframework/core/ResolvableType.forClassWithGenerics:(Ljava/lang/Class;[Ljava/lang/Class;)Lorg/springframework/core/ResolvableType;
      28: invokestatic  #279                // Method org/springframework/boot/context/properties/bind/Bindable.of:(Lorg/springframework/core/ResolvableType;)Lorg/springframework/boot/context/properties/bind/Bindable;
      31: putstatic     #9                  // Field STRING_STRINGS_MAP:Lorg/springframework/boot/context/properties/bind/Bindable;
      34: ldc           #193                // class java/lang/String
      36: invokestatic  #284                // Method org/springframework/boot/context/properties/bind/Bindable.setOf:(Ljava/lang/Class;)Lorg/springframework/boot/context/properties/bind/Bindable;
      39: putstatic     #119                // Field STRING_SET:Lorg/springframework/boot/context/properties/bind/Bindable;
      42: return
}
