Compiled from "Profiles.java"
final class org.springframework.boot.context.config.Profiles$Type extends java.lang.Enum<org.springframework.boot.context.config.Profiles$Type> {
  public static final org.springframework.boot.context.config.Profiles$Type ACTIVE;

  public static final org.springframework.boot.context.config.Profiles$Type DEFAULT;

  private final java.util.function.Function<org.springframework.core.env.Environment, java.lang.String[]> getter;

  private final boolean mergeWithEnvironmentProfiles;

  private final java.lang.String name;

  private final java.util.Set<java.lang.String> defaultValue;

  private static final org.springframework.boot.context.config.Profiles$Type[] $VALUES;

  public static org.springframework.boot.context.config.Profiles$Type[] values();
    Code:
       0: getstatic     #10                 // Field $VALUES:[Lorg/springframework/boot/context/config/Profiles$Type;
       3: invokevirtual #14                 // Method "[Lorg/springframework/boot/context/config/Profiles$Type;".clone:()Ljava/lang/Object;
       6: checkcast     #15                 // class "[Lorg/springframework/boot/context/config/Profiles$Type;"
       9: areturn

  public static org.springframework.boot.context.config.Profiles$Type valueOf(java.lang.String);
    Code:
       0: ldc           #1                  // class org/springframework/boot/context/config/Profiles$Type
       2: aload_0
       3: invokestatic  #19                 // Method java/lang/Enum.valueOf:(Ljava/lang/Class;Ljava/lang/String;)Ljava/lang/Enum;
       6: checkcast     #1                  // class org/springframework/boot/context/config/Profiles$Type
       9: areturn

  private org.springframework.boot.context.config.Profiles$Type(java.lang.String, java.util.function.Function<org.springframework.core.env.Environment, java.lang.String[]>, boolean, java.util.Set<java.lang.String>);
    Code:
       0: aload_0
       1: aload_1
       2: iload_2
       3: invokespecial #25                 // Method java/lang/Enum."<init>":(Ljava/lang/String;I)V
       6: aload_0
       7: aload_3
       8: putfield      #29                 // Field name:Ljava/lang/String;
      11: aload_0
      12: aload         4
      14: putfield      #33                 // Field getter:Ljava/util/function/Function;
      17: aload_0
      18: iload         5
      20: putfield      #37                 // Field mergeWithEnvironmentProfiles:Z
      23: aload_0
      24: aload         6
      26: putfield      #41                 // Field defaultValue:Ljava/util/Set;
      29: return

  java.lang.String getName();
    Code:
       0: aload_0
       1: getfield      #29                 // Field name:Ljava/lang/String;
       4: areturn

  java.lang.String[] get(org.springframework.core.env.Environment);
    Code:
       0: aload_0
       1: getfield      #33                 // Field getter:Ljava/util/function/Function;
       4: aload_1
       5: invokeinterface #45,  2           // InterfaceMethod java/util/function/Function.apply:(Ljava/lang/Object;)Ljava/lang/Object;
      10: checkcast     #51                 // class "[Ljava/lang/String;"
      13: areturn

  java.util.Set<java.lang.String> getDefaultValue();
    Code:
       0: aload_0
       1: getfield      #41                 // Field defaultValue:Ljava/util/Set;
       4: areturn

  boolean isMergeWithEnvironmentProfiles();
    Code:
       0: aload_0
       1: getfield      #37                 // Field mergeWithEnvironmentProfiles:Z
       4: ireturn

  private static org.springframework.boot.context.config.Profiles$Type[] $values();
    Code:
       0: iconst_2
       1: anewarray     #1                  // class org/springframework/boot/context/config/Profiles$Type
       4: dup
       5: iconst_0
       6: getstatic     #3                  // Field ACTIVE:Lorg/springframework/boot/context/config/Profiles$Type;
       9: aastore
      10: dup
      11: iconst_1
      12: getstatic     #7                  // Field DEFAULT:Lorg/springframework/boot/context/config/Profiles$Type;
      15: aastore
      16: areturn

  static {};
    Code:
       0: new           #1                  // class org/springframework/boot/context/config/Profiles$Type
       3: dup
       4: ldc           #53                 // String ACTIVE
       6: iconst_0
       7: ldc           #56                 // String spring.profiles.active
       9: invokedynamic #58,  0             // InvokeDynamic #0:apply:()Ljava/util/function/Function;
      14: iconst_1
      15: invokestatic  #61                 // Method java/util/Collections.emptySet:()Ljava/util/Set;
      18: invokespecial #67                 // Method "<init>":(Ljava/lang/String;ILjava/lang/String;Ljava/util/function/Function;ZLjava/util/Set;)V
      21: putstatic     #3                  // Field ACTIVE:Lorg/springframework/boot/context/config/Profiles$Type;
      24: new           #1                  // class org/springframework/boot/context/config/Profiles$Type
      27: dup
      28: ldc           #70                 // String DEFAULT
      30: iconst_1
      31: ldc           #71                 // String spring.profiles.default
      33: invokedynamic #73,  0             // InvokeDynamic #1:apply:()Ljava/util/function/Function;
      38: iconst_0
      39: ldc           #74                 // String default
      41: invokestatic  #76                 // Method java/util/Collections.singleton:(Ljava/lang/Object;)Ljava/util/Set;
      44: invokespecial #67                 // Method "<init>":(Ljava/lang/String;ILjava/lang/String;Ljava/util/function/Function;ZLjava/util/Set;)V
      47: putstatic     #7                  // Field DEFAULT:Lorg/springframework/boot/context/config/Profiles$Type;
      50: invokestatic  #80                 // Method $values:()[Lorg/springframework/boot/context/config/Profiles$Type;
      53: putstatic     #10                 // Field $VALUES:[Lorg/springframework/boot/context/config/Profiles$Type;
      56: return
}
