Compiled from "StandardConfigDataReference.java"
class org.springframework.boot.context.config.StandardConfigDataReference {
  private final org.springframework.boot.context.config.ConfigDataLocation configDataLocation;

  private final java.lang.String resourceLocation;

  private final java.lang.String directory;

  private final java.lang.String profile;

  private final org.springframework.boot.env.PropertySourceLoader propertySourceLoader;

  org.springframework.boot.context.config.StandardConfigDataReference(org.springframework.boot.context.config.ConfigDataLocation, java.lang.String, java.lang.String, java.lang.String, java.lang.String, org.springframework.boot.env.PropertySourceLoader);
    Code:
       0: aload_0
       1: invokespecial #1                  // Method java/lang/Object."<init>":()V
       4: aload_0
       5: aload_1
       6: putfield      #7                  // Field configDataLocation:Lorg/springframework/boot/context/config/ConfigDataLocation;
       9: aload         4
      11: invokestatic  #13                 // Method org/springframework/util/StringUtils.hasText:(Ljava/lang/String;)Z
      14: ifeq          27
      17: aload         4
      19: invokedynamic #19,  0             // InvokeDynamic #0:makeConcatWithConstants:(Ljava/lang/String;)Ljava/lang/String;
      24: goto          29
      27: ldc           #23                 // String
      29: astore        7
      31: aload_0
      32: aload_3
      33: aload         7
      35: aload         5
      37: ifnull        50
      40: aload         5
      42: invokedynamic #25,  0             // InvokeDynamic #1:makeConcatWithConstants:(Ljava/lang/String;)Ljava/lang/String;
      47: goto          52
      50: ldc           #23                 // String
      52: invokedynamic #26,  0             // InvokeDynamic #2:makeConcatWithConstants:(Ljava/lang/String;Ljava/lang/String;Ljava/lang/String;)Ljava/lang/String;
      57: putfield      #29                 // Field resourceLocation:Ljava/lang/String;
      60: aload_0
      61: aload_2
      62: putfield      #33                 // Field directory:Ljava/lang/String;
      65: aload_0
      66: aload         4
      68: putfield      #36                 // Field profile:Ljava/lang/String;
      71: aload_0
      72: aload         6
      74: putfield      #39                 // Field propertySourceLoader:Lorg/springframework/boot/env/PropertySourceLoader;
      77: return

  org.springframework.boot.context.config.ConfigDataLocation getConfigDataLocation();
    Code:
       0: aload_0
       1: getfield      #7                  // Field configDataLocation:Lorg/springframework/boot/context/config/ConfigDataLocation;
       4: areturn

  java.lang.String getResourceLocation();
    Code:
       0: aload_0
       1: getfield      #29                 // Field resourceLocation:Ljava/lang/String;
       4: areturn

  boolean isMandatoryDirectory();
    Code:
       0: aload_0
       1: getfield      #7                  // Field configDataLocation:Lorg/springframework/boot/context/config/ConfigDataLocation;
       4: invokevirtual #43                 // Method org/springframework/boot/context/config/ConfigDataLocation.isOptional:()Z
       7: ifne          21
      10: aload_0
      11: getfield      #33                 // Field directory:Ljava/lang/String;
      14: ifnull        21
      17: iconst_1
      18: goto          22
      21: iconst_0
      22: ireturn

  java.lang.String getDirectory();
    Code:
       0: aload_0
       1: getfield      #33                 // Field directory:Ljava/lang/String;
       4: areturn

  java.lang.String getProfile();
    Code:
       0: aload_0
       1: getfield      #36                 // Field profile:Ljava/lang/String;
       4: areturn

  boolean isSkippable();
    Code:
       0: aload_0
       1: getfield      #7                  // Field configDataLocation:Lorg/springframework/boot/context/config/ConfigDataLocation;
       4: invokevirtual #43                 // Method org/springframework/boot/context/config/ConfigDataLocation.isOptional:()Z
       7: ifne          24
      10: aload_0
      11: getfield      #33                 // Field directory:Ljava/lang/String;
      14: ifnonnull     24
      17: aload_0
      18: getfield      #36                 // Field profile:Ljava/lang/String;
      21: ifnull        28
      24: iconst_1
      25: goto          29
      28: iconst_0
      29: ireturn

  org.springframework.boot.env.PropertySourceLoader getPropertySourceLoader();
    Code:
       0: aload_0
       1: getfield      #39                 // Field propertySourceLoader:Lorg/springframework/boot/env/PropertySourceLoader;
       4: areturn

  public boolean equals(java.lang.Object);
    Code:
       0: aload_0
       1: aload_1
       2: if_acmpne     7
       5: iconst_1
       6: ireturn
       7: aload_1
       8: ifnull        22
      11: aload_0
      12: invokevirtual #49                 // Method java/lang/Object.getClass:()Ljava/lang/Class;
      15: aload_1
      16: invokevirtual #49                 // Method java/lang/Object.getClass:()Ljava/lang/Class;
      19: if_acmpeq     24
      22: iconst_0
      23: ireturn
      24: aload_1
      25: checkcast     #8                  // class org/springframework/boot/context/config/StandardConfigDataReference
      28: astore_2
      29: aload_0
      30: getfield      #29                 // Field resourceLocation:Ljava/lang/String;
      33: aload_2
      34: getfield      #29                 // Field resourceLocation:Ljava/lang/String;
      37: invokevirtual #53                 // Method java/lang/String.equals:(Ljava/lang/Object;)Z
      40: ireturn

  public int hashCode();
    Code:
       0: aload_0
       1: getfield      #29                 // Field resourceLocation:Ljava/lang/String;
       4: invokevirtual #59                 // Method java/lang/String.hashCode:()I
       7: ireturn

  public java.lang.String toString();
    Code:
       0: aload_0
       1: getfield      #29                 // Field resourceLocation:Ljava/lang/String;
       4: areturn
}
