Compiled from "StandardConfigDataResource.java"
public class org.springframework.boot.context.config.StandardConfigDataResource extends org.springframework.boot.context.config.ConfigDataResource {
  private final org.springframework.boot.context.config.StandardConfigDataReference reference;

  private final org.springframework.core.io.Resource resource;

  private final boolean emptyDirectory;

  org.springframework.boot.context.config.StandardConfigDataResource(org.springframework.boot.context.config.StandardConfigDataReference, org.springframework.core.io.Resource);
    Code:
       0: aload_0
       1: aload_1
       2: aload_2
       3: iconst_0
       4: invokespecial #1                  // Method "<init>":(Lorg/springframework/boot/context/config/StandardConfigDataReference;Lorg/springframework/core/io/Resource;Z)V
       7: return

  org.springframework.boot.context.config.StandardConfigDataResource(org.springframework.boot.context.config.StandardConfigDataReference, org.springframework.core.io.Resource, boolean);
    Code:
       0: aload_0
       1: invokespecial #7                  // Method org/springframework/boot/context/config/ConfigDataResource."<init>":()V
       4: aload_1
       5: ldc           #12                 // String Reference must not be null
       7: invokestatic  #14                 // Method org/springframework/util/Assert.notNull:(Ljava/lang/Object;Ljava/lang/String;)V
      10: aload_2
      11: ldc           #20                 // String Resource must not be null
      13: invokestatic  #14                 // Method org/springframework/util/Assert.notNull:(Ljava/lang/Object;Ljava/lang/String;)V
      16: aload_0
      17: aload_1
      18: putfield      #22                 // Field reference:Lorg/springframework/boot/context/config/StandardConfigDataReference;
      21: aload_0
      22: aload_2
      23: putfield      #26                 // Field resource:Lorg/springframework/core/io/Resource;
      26: aload_0
      27: iload_3
      28: putfield      #30                 // Field emptyDirectory:Z
      31: return

  org.springframework.boot.context.config.StandardConfigDataReference getReference();
    Code:
       0: aload_0
       1: getfield      #22                 // Field reference:Lorg/springframework/boot/context/config/StandardConfigDataReference;
       4: areturn

  public org.springframework.core.io.Resource getResource();
    Code:
       0: aload_0
       1: getfield      #26                 // Field resource:Lorg/springframework/core/io/Resource;
       4: areturn

  public java.lang.String getProfile();
    Code:
       0: aload_0
       1: getfield      #22                 // Field reference:Lorg/springframework/boot/context/config/StandardConfigDataReference;
       4: invokevirtual #34                 // Method org/springframework/boot/context/config/StandardConfigDataReference.getProfile:()Ljava/lang/String;
       7: areturn

  boolean isEmptyDirectory();
    Code:
       0: aload_0
       1: getfield      #30                 // Field emptyDirectory:Z
       4: ireturn

  public boolean equals(java.lang.Object);
    Code:
       0: aload_0
       1: aload_1
       2: if_acmpne     7
       5: iconst_1
       6: ireturn
       7: aload_1
       8: ifnull        22
      11: aload_0
      12: invokevirtual #40                 // Method java/lang/Object.getClass:()Ljava/lang/Class;
      15: aload_1
      16: invokevirtual #40                 // Method java/lang/Object.getClass:()Ljava/lang/Class;
      19: if_acmpeq     24
      22: iconst_0
      23: ireturn
      24: aload_1
      25: checkcast     #2                  // class org/springframework/boot/context/config/StandardConfigDataResource
      28: astore_2
      29: aload_0
      30: getfield      #30                 // Field emptyDirectory:Z
      33: aload_2
      34: getfield      #30                 // Field emptyDirectory:Z
      37: if_icmpne     59
      40: aload_0
      41: aload_0
      42: getfield      #26                 // Field resource:Lorg/springframework/core/io/Resource;
      45: aload_2
      46: getfield      #26                 // Field resource:Lorg/springframework/core/io/Resource;
      49: invokevirtual #46                 // Method isSameUnderlyingResource:(Lorg/springframework/core/io/Resource;Lorg/springframework/core/io/Resource;)Z
      52: ifeq          59
      55: iconst_1
      56: goto          60
      59: iconst_0
      60: ireturn

  private boolean isSameUnderlyingResource(org.springframework.core.io.Resource, org.springframework.core.io.Resource);
    Code:
       0: aload_1
       1: aload_2
       2: invokevirtual #50                 // Method java/lang/Object.equals:(Ljava/lang/Object;)Z
       5: ifne          25
       8: aload_0
       9: aload_0
      10: aload_1
      11: invokevirtual #54                 // Method getUnderlyingFile:(Lorg/springframework/core/io/Resource;)Ljava/io/File;
      14: aload_0
      15: aload_2
      16: invokevirtual #54                 // Method getUnderlyingFile:(Lorg/springframework/core/io/Resource;)Ljava/io/File;
      19: invokevirtual #58                 // Method isSameFile:(Ljava/io/File;Ljava/io/File;)Z
      22: ifeq          29
      25: iconst_1
      26: goto          30
      29: iconst_0
      30: ireturn

  private boolean isSameFile(java.io.File, java.io.File);
    Code:
       0: aload_1
       1: ifnull        20
       4: aload_2
       5: ifnull        20
       8: aload_1
       9: aload_2
      10: invokevirtual #62                 // Method java/io/File.equals:(Ljava/lang/Object;)Z
      13: ifeq          20
      16: iconst_1
      17: goto          21
      20: iconst_0
      21: ireturn

  public int hashCode();
    Code:
       0: aload_0
       1: aload_0
       2: getfield      #26                 // Field resource:Lorg/springframework/core/io/Resource;
       5: invokevirtual #54                 // Method getUnderlyingFile:(Lorg/springframework/core/io/Resource;)Ljava/io/File;
       8: astore_1
       9: aload_1
      10: ifnull        20
      13: aload_1
      14: invokevirtual #65                 // Method java/io/File.hashCode:()I
      17: goto          27
      20: aload_0
      21: getfield      #26                 // Field resource:Lorg/springframework/core/io/Resource;
      24: invokevirtual #69                 // Method java/lang/Object.hashCode:()I
      27: ireturn

  public java.lang.String toString();
    Code:
       0: aload_0
       1: getfield      #26                 // Field resource:Lorg/springframework/core/io/Resource;
       4: instanceof    #70                 // class org/springframework/core/io/FileSystemResource
       7: ifne          20
      10: aload_0
      11: getfield      #26                 // Field resource:Lorg/springframework/core/io/Resource;
      14: instanceof    #72                 // class org/springframework/core/io/FileUrlResource
      17: ifeq          39
      20: aload_0
      21: getfield      #26                 // Field resource:Lorg/springframework/core/io/Resource;
      24: invokeinterface #74,  1           // InterfaceMethod org/springframework/core/io/Resource.getFile:()Ljava/io/File;
      29: invokevirtual #80                 // Method java/io/File.toString:()Ljava/lang/String;
      32: invokedynamic #83,  0             // InvokeDynamic #0:makeConcatWithConstants:(Ljava/lang/String;)Ljava/lang/String;
      37: areturn
      38: astore_1
      39: aload_0
      40: getfield      #26                 // Field resource:Lorg/springframework/core/io/Resource;
      43: invokevirtual #89                 // Method java/lang/Object.toString:()Ljava/lang/String;
      46: areturn
    Exception table:
       from    to  target type
          20    37    38   Class java/io/IOException

  private java.io.File getUnderlyingFile(org.springframework.core.io.Resource);
    Code:
       0: aload_1
       1: instanceof    #90                 // class org/springframework/core/io/ClassPathResource
       4: ifne          21
       7: aload_1
       8: instanceof    #70                 // class org/springframework/core/io/FileSystemResource
      11: ifne          21
      14: aload_1
      15: instanceof    #72                 // class org/springframework/core/io/FileUrlResource
      18: ifeq          41
      21: aload_1
      22: invokeinterface #74,  1           // InterfaceMethod org/springframework/core/io/Resource.getFile:()Ljava/io/File;
      27: astore_2
      28: aload_2
      29: ifnull        39
      32: aload_2
      33: invokevirtual #92                 // Method java/io/File.getAbsoluteFile:()Ljava/io/File;
      36: goto          40
      39: aconst_null
      40: areturn
      41: goto          45
      44: astore_2
      45: aconst_null
      46: areturn
    Exception table:
       from    to  target type
           0    40    44   Class java/io/IOException
}
