Compiled from "StandardConfigDataLoader.java"
public class org.springframework.boot.context.config.StandardConfigDataLoader implements org.springframework.boot.context.config.ConfigDataLoader<org.springframework.boot.context.config.StandardConfigDataResource> {
  private static final org.springframework.boot.context.config.ConfigData$PropertySourceOptions PROFILE_SPECIFIC;

  private static final org.springframework.boot.context.config.ConfigData$PropertySourceOptions NON_PROFILE_SPECIFIC;

  public org.springframework.boot.context.config.StandardConfigDataLoader();
    Code:
       0: aload_0
       1: invokespecial #1                  // Method java/lang/Object."<init>":()V
       4: return

  public org.springframework.boot.context.config.ConfigData load(org.springframework.boot.context.config.ConfigDataLoaderContext, org.springframework.boot.context.config.StandardConfigDataResource) throws java.io.IOException, org.springframework.boot.context.config.ConfigDataNotFoundException;
    Code:
       0: aload_2
       1: invokevirtual #7                  // Method org/springframework/boot/context/config/StandardConfigDataResource.isEmptyDirectory:()Z
       4: ifeq          11
       7: getstatic     #13                 // Field org/springframework/boot/context/config/ConfigData.EMPTY:Lorg/springframework/boot/context/config/ConfigData;
      10: areturn
      11: aload_2
      12: aload_2
      13: invokevirtual #19                 // Method org/springframework/boot/context/config/StandardConfigDataResource.getResource:()Lorg/springframework/core/io/Resource;
      16: invokestatic  #23                 // Method org/springframework/boot/context/config/ConfigDataResourceNotFoundException.throwIfDoesNotExist:(Lorg/springframework/boot/context/config/ConfigDataResource;Lorg/springframework/core/io/Resource;)V
      19: aload_2
      20: invokevirtual #29                 // Method org/springframework/boot/context/config/StandardConfigDataResource.getReference:()Lorg/springframework/boot/context/config/StandardConfigDataReference;
      23: astore_3
      24: aload_2
      25: invokevirtual #19                 // Method org/springframework/boot/context/config/StandardConfigDataResource.getResource:()Lorg/springframework/core/io/Resource;
      28: aload_3
      29: invokevirtual #33                 // Method org/springframework/boot/context/config/StandardConfigDataReference.getConfigDataLocation:()Lorg/springframework/boot/context/config/ConfigDataLocation;
      32: invokestatic  #39                 // InterfaceMethod org/springframework/boot/origin/Origin.from:(Ljava/lang/Object;)Lorg/springframework/boot/origin/Origin;
      35: invokestatic  #45                 // Method org/springframework/boot/origin/OriginTrackedResource.of:(Lorg/springframework/core/io/Resource;Lorg/springframework/boot/origin/Origin;)Lorg/springframework/boot/origin/OriginTrackedResource;
      38: astore        4
      40: ldc           #51                 // String Config resource \'%s\' via location \'%s\'
      42: iconst_2
      43: anewarray     #2                  // class java/lang/Object
      46: dup
      47: iconst_0
      48: aload_2
      49: aastore
      50: dup
      51: iconst_1
      52: aload_3
      53: invokevirtual #33                 // Method org/springframework/boot/context/config/StandardConfigDataReference.getConfigDataLocation:()Lorg/springframework/boot/context/config/ConfigDataLocation;
      56: aastore
      57: invokestatic  #53                 // Method java/lang/String.format:(Ljava/lang/String;[Ljava/lang/Object;)Ljava/lang/String;
      60: astore        5
      62: aload_3
      63: invokevirtual #59                 // Method org/springframework/boot/context/config/StandardConfigDataReference.getPropertySourceLoader:()Lorg/springframework/boot/env/PropertySourceLoader;
      66: aload         5
      68: aload         4
      70: invokeinterface #63,  3           // InterfaceMethod org/springframework/boot/env/PropertySourceLoader.load:(Ljava/lang/String;Lorg/springframework/core/io/Resource;)Ljava/util/List;
      75: astore        6
      77: aload_2
      78: invokevirtual #69                 // Method org/springframework/boot/context/config/StandardConfigDataResource.getProfile:()Ljava/lang/String;
      81: ifnull        90
      84: getstatic     #73                 // Field PROFILE_SPECIFIC:Lorg/springframework/boot/context/config/ConfigData$PropertySourceOptions;
      87: goto          93
      90: getstatic     #79                 // Field NON_PROFILE_SPECIFIC:Lorg/springframework/boot/context/config/ConfigData$PropertySourceOptions;
      93: astore        7
      95: new           #14                 // class org/springframework/boot/context/config/ConfigData
      98: dup
      99: aload         6
     101: aload         7
     103: invokespecial #82                 // Method org/springframework/boot/context/config/ConfigData."<init>":(Ljava/util/Collection;Lorg/springframework/boot/context/config/ConfigData$PropertySourceOptions;)V
     106: areturn

  public org.springframework.boot.context.config.ConfigData load(org.springframework.boot.context.config.ConfigDataLoaderContext, org.springframework.boot.context.config.ConfigDataResource) throws java.io.IOException, org.springframework.boot.context.config.ConfigDataResourceNotFoundException;
    Code:
       0: aload_0
       1: aload_1
       2: aload_2
       3: checkcast     #8                  // class org/springframework/boot/context/config/StandardConfigDataResource
       6: invokevirtual #85                 // Method load:(Lorg/springframework/boot/context/config/ConfigDataLoaderContext;Lorg/springframework/boot/context/config/StandardConfigDataResource;)Lorg/springframework/boot/context/config/ConfigData;
       9: areturn

  static {};
    Code:
       0: iconst_1
       1: anewarray     #88                 // class org/springframework/boot/context/config/ConfigData$Option
       4: dup
       5: iconst_0
       6: getstatic     #90                 // Field org/springframework/boot/context/config/ConfigData$Option.PROFILE_SPECIFIC:Lorg/springframework/boot/context/config/ConfigData$Option;
       9: aastore
      10: invokestatic  #93                 // InterfaceMethod org/springframework/boot/context/config/ConfigData$PropertySourceOptions.always:([Lorg/springframework/boot/context/config/ConfigData$Option;)Lorg/springframework/boot/context/config/ConfigData$PropertySourceOptions;
      13: putstatic     #73                 // Field PROFILE_SPECIFIC:Lorg/springframework/boot/context/config/ConfigData$PropertySourceOptions;
      16: getstatic     #99                 // Field org/springframework/boot/context/config/ConfigData$PropertySourceOptions.ALWAYS_NONE:Lorg/springframework/boot/context/config/ConfigData$PropertySourceOptions;
      19: putstatic     #79                 // Field NON_PROFILE_SPECIFIC:Lorg/springframework/boot/context/config/ConfigData$PropertySourceOptions;
      22: return
}
