Compiled from "StandardConfigDataLocationResolver.java"
public class org.springframework.boot.context.config.StandardConfigDataLocationResolver implements org.springframework.boot.context.config.ConfigDataLocationResolver<org.springframework.boot.context.config.StandardConfigDataResource>, org.springframework.core.Ordered {
  private static final java.lang.String PREFIX;

  static final java.lang.String CONFIG_NAME_PROPERTY;

  static final java.lang.String[] DEFAULT_CONFIG_NAMES;

  private static final java.util.regex.Pattern URL_PREFIX;

  private static final java.util.regex.Pattern EXTENSION_HINT_PATTERN;

  private static final java.lang.String NO_PROFILE;

  private final org.apache.commons.logging.Log logger;

  private final java.util.List<org.springframework.boot.env.PropertySourceLoader> propertySourceLoaders;

  private final java.lang.String[] configNames;

  private final org.springframework.boot.context.config.LocationResourceLoader resourceLoader;

  public org.springframework.boot.context.config.StandardConfigDataLocationResolver(org.springframework.boot.logging.DeferredLogFactory, org.springframework.boot.context.properties.bind.Binder, org.springframework.core.io.ResourceLoader);
    Code:
       0: aload_0
       1: invokespecial #1                  // Method java/lang/Object."<init>":()V
       4: aload_0
       5: aload_1
       6: ldc           #7                  // class org/springframework/boot/context/config/StandardConfigDataLocationResolver
       8: invokeinterface #9,  2            // InterfaceMethod org/springframework/boot/logging/DeferredLogFactory.getLog:(Ljava/lang/Class;)Lorg/apache/commons/logging/Log;
      13: putfield      #15                 // Field logger:Lorg/apache/commons/logging/Log;
      16: aload_0
      17: ldc           #19                 // class org/springframework/boot/env/PropertySourceLoader
      19: aload_0
      20: invokevirtual #21                 // Method java/lang/Object.getClass:()Ljava/lang/Class;
      23: invokevirtual #25                 // Method java/lang/Class.getClassLoader:()Ljava/lang/ClassLoader;
      26: invokestatic  #31                 // Method org/springframework/core/io/support/SpringFactoriesLoader.loadFactories:(Ljava/lang/Class;Ljava/lang/ClassLoader;)Ljava/util/List;
      29: putfield      #37                 // Field propertySourceLoaders:Ljava/util/List;
      32: aload_0
      33: aload_0
      34: aload_2
      35: invokevirtual #41                 // Method getConfigNames:(Lorg/springframework/boot/context/properties/bind/Binder;)[Ljava/lang/String;
      38: putfield      #45                 // Field configNames:[Ljava/lang/String;
      41: aload_0
      42: new           #49                 // class org/springframework/boot/context/config/LocationResourceLoader
      45: dup
      46: aload_3
      47: invokespecial #51                 // Method org/springframework/boot/context/config/LocationResourceLoader."<init>":(Lorg/springframework/core/io/ResourceLoader;)V
      50: putfield      #54                 // Field resourceLoader:Lorg/springframework/boot/context/config/LocationResourceLoader;
      53: return

  private java.lang.String[] getConfigNames(org.springframework.boot.context.properties.bind.Binder);
    Code:
       0: aload_1
       1: ldc           #58                 // String spring.config.name
       3: ldc           #60                 // class "[Ljava/lang/String;"
       5: invokevirtual #61                 // Method org/springframework/boot/context/properties/bind/Binder.bind:(Ljava/lang/String;Ljava/lang/Class;)Lorg/springframework/boot/context/properties/bind/BindResult;
       8: getstatic     #67                 // Field DEFAULT_CONFIG_NAMES:[Ljava/lang/String;
      11: invokevirtual #70                 // Method org/springframework/boot/context/properties/bind/BindResult.orElse:(Ljava/lang/Object;)Ljava/lang/Object;
      14: checkcast     #60                 // class "[Ljava/lang/String;"
      17: astore_2
      18: aload_2
      19: astore_3
      20: aload_3
      21: arraylength
      22: istore        4
      24: iconst_0
      25: istore        5
      27: iload         5
      29: iload         4
      31: if_icmpge     52
      34: aload_3
      35: iload         5
      37: aaload
      38: astore        6
      40: aload_0
      41: aload         6
      43: invokevirtual #76                 // Method validateConfigName:(Ljava/lang/String;)V
      46: iinc          5, 1
      49: goto          27
      52: aload_2
      53: areturn

  private void validateConfigName(java.lang.String);
    Code:
       0: aload_1
       1: ldc           #80                 // String *
       3: invokevirtual #82                 // Method java/lang/String.contains:(Ljava/lang/CharSequence;)Z
       6: ifne          13
       9: iconst_1
      10: goto          14
      13: iconst_0
      14: aload_1
      15: invokedynamic #88,  0             // InvokeDynamic #0:get:(Ljava/lang/String;)Ljava/util/function/Supplier;
      20: invokestatic  #92                 // Method org/springframework/util/Assert.state:(ZLjava/util/function/Supplier;)V
      23: return

  public int getOrder();
    Code:
       0: ldc           #100                // int 2147483647
       2: ireturn

  public boolean isResolvable(org.springframework.boot.context.config.ConfigDataLocationResolverContext, org.springframework.boot.context.config.ConfigDataLocation);
    Code:
       0: iconst_1
       1: ireturn

  public java.util.List<org.springframework.boot.context.config.StandardConfigDataResource> resolve(org.springframework.boot.context.config.ConfigDataLocationResolverContext, org.springframework.boot.context.config.ConfigDataLocation) throws org.springframework.boot.context.config.ConfigDataNotFoundException;
    Code:
       0: aload_0
       1: aload_0
       2: aload_1
       3: aload_2
       4: invokevirtual #101                // Method org/springframework/boot/context/config/ConfigDataLocation.split:()[Lorg/springframework/boot/context/config/ConfigDataLocation;
       7: invokevirtual #107                // Method getReferences:(Lorg/springframework/boot/context/config/ConfigDataLocationResolverContext;[Lorg/springframework/boot/context/config/ConfigDataLocation;)Ljava/util/Set;
      10: invokevirtual #111                // Method resolve:(Ljava/util/Set;)Ljava/util/List;
      13: areturn

  private java.util.Set<org.springframework.boot.context.config.StandardConfigDataReference> getReferences(org.springframework.boot.context.config.ConfigDataLocationResolverContext, org.springframework.boot.context.config.ConfigDataLocation[]);
    Code:
       0: new           #115                // class java/util/LinkedHashSet
       3: dup
       4: invokespecial #117                // Method java/util/LinkedHashSet."<init>":()V
       7: astore_3
       8: aload_2
       9: astore        4
      11: aload         4
      13: arraylength
      14: istore        5
      16: iconst_0
      17: istore        6
      19: iload         6
      21: iload         5
      23: if_icmpge     53
      26: aload         4
      28: iload         6
      30: aaload
      31: astore        7
      33: aload_3
      34: aload_0
      35: aload_1
      36: aload         7
      38: invokevirtual #118                // Method getReferences:(Lorg/springframework/boot/context/config/ConfigDataLocationResolverContext;Lorg/springframework/boot/context/config/ConfigDataLocation;)Ljava/util/Set;
      41: invokeinterface #121,  2          // InterfaceMethod java/util/Set.addAll:(Ljava/util/Collection;)Z
      46: pop
      47: iinc          6, 1
      50: goto          19
      53: aload_3
      54: areturn

  private java.util.Set<org.springframework.boot.context.config.StandardConfigDataReference> getReferences(org.springframework.boot.context.config.ConfigDataLocationResolverContext, org.springframework.boot.context.config.ConfigDataLocation);
    Code:
       0: aload_0
       1: aload_1
       2: aload_2
       3: invokevirtual #127                // Method getResourceLocation:(Lorg/springframework/boot/context/config/ConfigDataLocationResolverContext;Lorg/springframework/boot/context/config/ConfigDataLocation;)Ljava/lang/String;
       6: astore_3
       7: aload_0
       8: aload_3
       9: invokevirtual #131                // Method isDirectory:(Ljava/lang/String;)Z
      12: ifeq          25
      15: aload_0
      16: aload_2
      17: aload_3
      18: getstatic     #135                // Field NO_PROFILE:Ljava/lang/String;
      21: invokevirtual #139                // Method getReferencesForDirectory:(Lorg/springframework/boot/context/config/ConfigDataLocation;Ljava/lang/String;Ljava/lang/String;)Ljava/util/Set;
      24: areturn
      25: aload_0
      26: aload_2
      27: aload_3
      28: getstatic     #135                // Field NO_PROFILE:Ljava/lang/String;
      31: invokevirtual #143                // Method getReferencesForFile:(Lorg/springframework/boot/context/config/ConfigDataLocation;Ljava/lang/String;Ljava/lang/String;)Ljava/util/Set;
      34: areturn
      35: astore        4
      37: new           #148                // class java/lang/IllegalStateException
      40: dup
      41: aload_2
      42: invokedynamic #150,  0            // InvokeDynamic #1:makeConcatWithConstants:(Lorg/springframework/boot/context/config/ConfigDataLocation;)Ljava/lang/String;
      47: aload         4
      49: invokespecial #154                // Method java/lang/IllegalStateException."<init>":(Ljava/lang/String;Ljava/lang/Throwable;)V
      52: athrow
    Exception table:
       from    to  target type
           7    24    35   Class java/lang/RuntimeException
          25    34    35   Class java/lang/RuntimeException

  public java.util.List<org.springframework.boot.context.config.StandardConfigDataResource> resolveProfileSpecific(org.springframework.boot.context.config.ConfigDataLocationResolverContext, org.springframework.boot.context.config.ConfigDataLocation, org.springframework.boot.context.config.Profiles);
    Code:
       0: aload_0
       1: aload_0
       2: aload_1
       3: aload_2
       4: invokevirtual #101                // Method org/springframework/boot/context/config/ConfigDataLocation.split:()[Lorg/springframework/boot/context/config/ConfigDataLocation;
       7: aload_3
       8: invokevirtual #157                // Method getProfileSpecificReferences:(Lorg/springframework/boot/context/config/ConfigDataLocationResolverContext;[Lorg/springframework/boot/context/config/ConfigDataLocation;Lorg/springframework/boot/context/config/Profiles;)Ljava/util/Set;
      11: invokevirtual #111                // Method resolve:(Ljava/util/Set;)Ljava/util/List;
      14: areturn

  private java.util.Set<org.springframework.boot.context.config.StandardConfigDataReference> getProfileSpecificReferences(org.springframework.boot.context.config.ConfigDataLocationResolverContext, org.springframework.boot.context.config.ConfigDataLocation[], org.springframework.boot.context.config.Profiles);
    Code:
       0: new           #115                // class java/util/LinkedHashSet
       3: dup
       4: invokespecial #117                // Method java/util/LinkedHashSet."<init>":()V
       7: astore        4
       9: aload_3
      10: invokevirtual #161                // Method org/springframework/boot/context/config/Profiles.iterator:()Ljava/util/Iterator;
      13: astore        5
      15: aload         5
      17: invokeinterface #167,  1          // InterfaceMethod java/util/Iterator.hasNext:()Z
      22: ifeq          98
      25: aload         5
      27: invokeinterface #173,  1          // InterfaceMethod java/util/Iterator.next:()Ljava/lang/Object;
      32: checkcast     #83                 // class java/lang/String
      35: astore        6
      37: aload_2
      38: astore        7
      40: aload         7
      42: arraylength
      43: istore        8
      45: iconst_0
      46: istore        9
      48: iload         9
      50: iload         8
      52: if_icmpge     95
      55: aload         7
      57: iload         9
      59: aaload
      60: astore        10
      62: aload_0
      63: aload_1
      64: aload         10
      66: invokevirtual #127                // Method getResourceLocation:(Lorg/springframework/boot/context/config/ConfigDataLocationResolverContext;Lorg/springframework/boot/context/config/ConfigDataLocation;)Ljava/lang/String;
      69: astore        11
      71: aload         4
      73: aload_0
      74: aload         10
      76: aload         11
      78: aload         6
      80: invokevirtual #177                // Method getReferences:(Lorg/springframework/boot/context/config/ConfigDataLocation;Ljava/lang/String;Ljava/lang/String;)Ljava/util/Set;
      83: invokeinterface #121,  2          // InterfaceMethod java/util/Set.addAll:(Ljava/util/Collection;)Z
      88: pop
      89: iinc          9, 1
      92: goto          48
      95: goto          15
      98: aload         4
     100: areturn

  private java.lang.String getResourceLocation(org.springframework.boot.context.config.ConfigDataLocationResolverContext, org.springframework.boot.context.config.ConfigDataLocation);
    Code:
       0: aload_2
       1: ldc           #179                // String resource:
       3: invokevirtual #181                // Method org/springframework/boot/context/config/ConfigDataLocation.getNonPrefixedValue:(Ljava/lang/String;)Ljava/lang/String;
       6: astore_3
       7: aload_3
       8: ldc           #185                // String /
      10: invokevirtual #187                // Method java/lang/String.startsWith:(Ljava/lang/String;)Z
      13: ifne          29
      16: getstatic     #190                // Field URL_PREFIX:Ljava/util/regex/Pattern;
      19: aload_3
      20: invokevirtual #194                // Method java/util/regex/Pattern.matcher:(Ljava/lang/CharSequence;)Ljava/util/regex/Matcher;
      23: invokevirtual #200                // Method java/util/regex/Matcher.matches:()Z
      26: ifeq          33
      29: iconst_1
      30: goto          34
      33: iconst_0
      34: istore        4
      36: iload         4
      38: ifeq          43
      41: aload_3
      42: areturn
      43: aload_1
      44: invokeinterface #205,  1          // InterfaceMethod org/springframework/boot/context/config/ConfigDataLocationResolverContext.getParent:()Lorg/springframework/boot/context/config/ConfigDataResource;
      49: astore        5
      51: aload         5
      53: instanceof    #211                // class org/springframework/boot/context/config/StandardConfigDataResource
      56: ifeq          102
      59: aload         5
      61: checkcast     #211                // class org/springframework/boot/context/config/StandardConfigDataResource
      64: astore        6
      66: aload         6
      68: invokevirtual #213                // Method org/springframework/boot/context/config/StandardConfigDataResource.getReference:()Lorg/springframework/boot/context/config/StandardConfigDataReference;
      71: invokevirtual #217                // Method org/springframework/boot/context/config/StandardConfigDataReference.getResourceLocation:()Ljava/lang/String;
      74: astore        7
      76: aload         7
      78: iconst_0
      79: aload         7
      81: ldc           #185                // String /
      83: invokevirtual #222                // Method java/lang/String.lastIndexOf:(Ljava/lang/String;)I
      86: iconst_1
      87: iadd
      88: invokevirtual #226                // Method java/lang/String.substring:(II)Ljava/lang/String;
      91: astore        8
      93: aload         8
      95: aload_3
      96: invokedynamic #230,  0            // InvokeDynamic #2:makeConcatWithConstants:(Ljava/lang/String;Ljava/lang/String;)Ljava/lang/String;
     101: areturn
     102: aload_3
     103: areturn

  private java.util.Set<org.springframework.boot.context.config.StandardConfigDataReference> getReferences(org.springframework.boot.context.config.ConfigDataLocation, java.lang.String, java.lang.String);
    Code:
       0: aload_0
       1: aload_2
       2: invokevirtual #131                // Method isDirectory:(Ljava/lang/String;)Z
       5: ifeq          16
       8: aload_0
       9: aload_1
      10: aload_2
      11: aload_3
      12: invokevirtual #139                // Method getReferencesForDirectory:(Lorg/springframework/boot/context/config/ConfigDataLocation;Ljava/lang/String;Ljava/lang/String;)Ljava/util/Set;
      15: areturn
      16: aload_0
      17: aload_1
      18: aload_2
      19: aload_3
      20: invokevirtual #143                // Method getReferencesForFile:(Lorg/springframework/boot/context/config/ConfigDataLocation;Ljava/lang/String;Ljava/lang/String;)Ljava/util/Set;
      23: areturn

  private java.util.Set<org.springframework.boot.context.config.StandardConfigDataReference> getReferencesForDirectory(org.springframework.boot.context.config.ConfigDataLocation, java.lang.String, java.lang.String);
    Code:
       0: new           #115                // class java/util/LinkedHashSet
       3: dup
       4: invokespecial #117                // Method java/util/LinkedHashSet."<init>":()V
       7: astore        4
       9: aload_0
      10: getfield      #45                 // Field configNames:[Ljava/lang/String;
      13: astore        5
      15: aload         5
      17: arraylength
      18: istore        6
      20: iconst_0
      21: istore        7
      23: iload         7
      25: iload         6
      27: if_icmpge     64
      30: aload         5
      32: iload         7
      34: aaload
      35: astore        8
      37: aload_0
      38: aload         8
      40: aload_1
      41: aload_2
      42: aload_3
      43: invokevirtual #233                // Method getReferencesForConfigName:(Ljava/lang/String;Lorg/springframework/boot/context/config/ConfigDataLocation;Ljava/lang/String;Ljava/lang/String;)Ljava/util/Deque;
      46: astore        9
      48: aload         4
      50: aload         9
      52: invokeinterface #121,  2          // InterfaceMethod java/util/Set.addAll:(Ljava/util/Collection;)Z
      57: pop
      58: iinc          7, 1
      61: goto          23
      64: aload         4
      66: areturn

  private java.util.Deque<org.springframework.boot.context.config.StandardConfigDataReference> getReferencesForConfigName(java.lang.String, org.springframework.boot.context.config.ConfigDataLocation, java.lang.String, java.lang.String);
    Code:
       0: new           #237                // class java/util/ArrayDeque
       3: dup
       4: invokespecial #239                // Method java/util/ArrayDeque."<init>":()V
       7: astore        5
       9: aload_0
      10: getfield      #37                 // Field propertySourceLoaders:Ljava/util/List;
      13: invokeinterface #240,  1          // InterfaceMethod java/util/List.iterator:()Ljava/util/Iterator;
      18: astore        6
      20: aload         6
      22: invokeinterface #167,  1          // InterfaceMethod java/util/Iterator.hasNext:()Z
      27: ifeq          127
      30: aload         6
      32: invokeinterface #173,  1          // InterfaceMethod java/util/Iterator.next:()Ljava/lang/Object;
      37: checkcast     #19                 // class org/springframework/boot/env/PropertySourceLoader
      40: astore        7
      42: aload         7
      44: invokeinterface #243,  1          // InterfaceMethod org/springframework/boot/env/PropertySourceLoader.getFileExtensions:()[Ljava/lang/String;
      49: astore        8
      51: aload         8
      53: arraylength
      54: istore        9
      56: iconst_0
      57: istore        10
      59: iload         10
      61: iload         9
      63: if_icmpge     124
      66: aload         8
      68: iload         10
      70: aaload
      71: astore        11
      73: new           #218                // class org/springframework/boot/context/config/StandardConfigDataReference
      76: dup
      77: aload_2
      78: aload_3
      79: aload_3
      80: aload_1
      81: invokedynamic #230,  0            // InvokeDynamic #2:makeConcatWithConstants:(Ljava/lang/String;Ljava/lang/String;)Ljava/lang/String;
      86: aload         4
      88: aload         11
      90: aload         7
      92: invokespecial #247                // Method org/springframework/boot/context/config/StandardConfigDataReference."<init>":(Lorg/springframework/boot/context/config/ConfigDataLocation;Ljava/lang/String;Ljava/lang/String;Ljava/lang/String;Ljava/lang/String;Lorg/springframework/boot/env/PropertySourceLoader;)V
      95: astore        12
      97: aload         5
      99: aload         12
     101: invokeinterface #250,  2          // InterfaceMethod java/util/Deque.contains:(Ljava/lang/Object;)Z
     106: ifne          118
     109: aload         5
     111: aload         12
     113: invokeinterface #255,  2          // InterfaceMethod java/util/Deque.addFirst:(Ljava/lang/Object;)V
     118: iinc          10, 1
     121: goto          59
     124: goto          20
     127: aload         5
     129: areturn

  private java.util.Set<org.springframework.boot.context.config.StandardConfigDataReference> getReferencesForFile(org.springframework.boot.context.config.ConfigDataLocation, java.lang.String, java.lang.String);
    Code:
       0: getstatic     #259                // Field EXTENSION_HINT_PATTERN:Ljava/util/regex/Pattern;
       3: aload_2
       4: invokevirtual #194                // Method java/util/regex/Pattern.matcher:(Ljava/lang/CharSequence;)Ljava/util/regex/Matcher;
       7: astore        4
       9: aload         4
      11: invokevirtual #200                // Method java/util/regex/Matcher.matches:()Z
      14: istore        5
      16: iload         5
      18: ifeq          39
      21: aload         4
      23: iconst_1
      24: invokevirtual #262                // Method java/util/regex/Matcher.group:(I)Ljava/lang/String;
      27: aload         4
      29: iconst_2
      30: invokevirtual #262                // Method java/util/regex/Matcher.group:(I)Ljava/lang/String;
      33: invokedynamic #230,  0            // InvokeDynamic #2:makeConcatWithConstants:(Ljava/lang/String;Ljava/lang/String;)Ljava/lang/String;
      38: astore_2
      39: aload_0
      40: getfield      #37                 // Field propertySourceLoaders:Ljava/util/List;
      43: invokeinterface #240,  1          // InterfaceMethod java/util/List.iterator:()Ljava/util/Iterator;
      48: astore        6
      50: aload         6
      52: invokeinterface #167,  1          // InterfaceMethod java/util/Iterator.hasNext:()Z
      57: ifeq          141
      60: aload         6
      62: invokeinterface #173,  1          // InterfaceMethod java/util/Iterator.next:()Ljava/lang/Object;
      67: checkcast     #19                 // class org/springframework/boot/env/PropertySourceLoader
      70: astore        7
      72: aload_0
      73: aload         7
      75: aload_2
      76: invokevirtual #266                // Method getLoadableFileExtension:(Lorg/springframework/boot/env/PropertySourceLoader;Ljava/lang/String;)Ljava/lang/String;
      79: astore        8
      81: aload         8
      83: ifnull        138
      86: aload_2
      87: iconst_0
      88: aload_2
      89: invokevirtual #270                // Method java/lang/String.length:()I
      92: aload         8
      94: invokevirtual #270                // Method java/lang/String.length:()I
      97: isub
      98: iconst_1
      99: isub
     100: invokevirtual #226                // Method java/lang/String.substring:(II)Ljava/lang/String;
     103: astore        9
     105: new           #218                // class org/springframework/boot/context/config/StandardConfigDataReference
     108: dup
     109: aload_1
     110: aconst_null
     111: aload         9
     113: aload_3
     114: iload         5
     116: ifne          124
     119: aload         8
     121: goto          125
     124: aconst_null
     125: aload         7
     127: invokespecial #247                // Method org/springframework/boot/context/config/StandardConfigDataReference."<init>":(Lorg/springframework/boot/context/config/ConfigDataLocation;Ljava/lang/String;Ljava/lang/String;Ljava/lang/String;Ljava/lang/String;Lorg/springframework/boot/env/PropertySourceLoader;)V
     130: astore        10
     132: aload         10
     134: invokestatic  #274                // Method java/util/Collections.singleton:(Ljava/lang/Object;)Ljava/util/Set;
     137: areturn
     138: goto          50
     141: new           #148                // class java/lang/IllegalStateException
     144: dup
     145: ldc_w         #280                // String File extension is not known to any PropertySourceLoader. If the location is meant to reference a directory, it must end in \'/\' or File.separator
     148: invokespecial #282                // Method java/lang/IllegalStateException."<init>":(Ljava/lang/String;)V
     151: athrow

  private java.lang.String getLoadableFileExtension(org.springframework.boot.env.PropertySourceLoader, java.lang.String);
    Code:
       0: aload_1
       1: invokeinterface #243,  1          // InterfaceMethod org/springframework/boot/env/PropertySourceLoader.getFileExtensions:()[Ljava/lang/String;
       6: astore_3
       7: aload_3
       8: arraylength
       9: istore        4
      11: iconst_0
      12: istore        5
      14: iload         5
      16: iload         4
      18: if_icmpge     45
      21: aload_3
      22: iload         5
      24: aaload
      25: astore        6
      27: aload_2
      28: aload         6
      30: invokestatic  #284                // Method org/springframework/util/StringUtils.endsWithIgnoreCase:(Ljava/lang/String;Ljava/lang/String;)Z
      33: ifeq          39
      36: aload         6
      38: areturn
      39: iinc          5, 1
      42: goto          14
      45: aconst_null
      46: areturn

  private boolean isDirectory(java.lang.String);
    Code:
       0: aload_1
       1: ldc           #185                // String /
       3: invokevirtual #290                // Method java/lang/String.endsWith:(Ljava/lang/String;)Z
       6: ifne          19
       9: aload_1
      10: getstatic     #293                // Field java/io/File.separator:Ljava/lang/String;
      13: invokevirtual #290                // Method java/lang/String.endsWith:(Ljava/lang/String;)Z
      16: ifeq          23
      19: iconst_1
      20: goto          24
      23: iconst_0
      24: ireturn

  private java.util.List<org.springframework.boot.context.config.StandardConfigDataResource> resolve(java.util.Set<org.springframework.boot.context.config.StandardConfigDataReference>);
    Code:
       0: new           #298                // class java/util/ArrayList
       3: dup
       4: invokespecial #300                // Method java/util/ArrayList."<init>":()V
       7: astore_2
       8: aload_1
       9: invokeinterface #301,  1          // InterfaceMethod java/util/Set.iterator:()Ljava/util/Iterator;
      14: astore_3
      15: aload_3
      16: invokeinterface #167,  1          // InterfaceMethod java/util/Iterator.hasNext:()Z
      21: ifeq          51
      24: aload_3
      25: invokeinterface #173,  1          // InterfaceMethod java/util/Iterator.next:()Ljava/lang/Object;
      30: checkcast     #218                // class org/springframework/boot/context/config/StandardConfigDataReference
      33: astore        4
      35: aload_2
      36: aload_0
      37: aload         4
      39: invokevirtual #302                // Method resolve:(Lorg/springframework/boot/context/config/StandardConfigDataReference;)Ljava/util/List;
      42: invokeinterface #305,  2          // InterfaceMethod java/util/List.addAll:(Ljava/util/Collection;)Z
      47: pop
      48: goto          15
      51: aload_2
      52: invokeinterface #306,  1          // InterfaceMethod java/util/List.isEmpty:()Z
      57: ifeq          72
      60: aload_2
      61: aload_0
      62: aload_1
      63: invokevirtual #309                // Method resolveEmptyDirectories:(Ljava/util/Set;)Ljava/util/Collection;
      66: invokeinterface #305,  2          // InterfaceMethod java/util/List.addAll:(Ljava/util/Collection;)Z
      71: pop
      72: aload_2
      73: areturn

  private java.util.Collection<org.springframework.boot.context.config.StandardConfigDataResource> resolveEmptyDirectories(java.util.Set<org.springframework.boot.context.config.StandardConfigDataReference>);
    Code:
       0: new           #115                // class java/util/LinkedHashSet
       3: dup
       4: invokespecial #117                // Method java/util/LinkedHashSet."<init>":()V
       7: astore_2
       8: aload_1
       9: invokeinterface #301,  1          // InterfaceMethod java/util/Set.iterator:()Ljava/util/Iterator;
      14: astore_3
      15: aload_3
      16: invokeinterface #167,  1          // InterfaceMethod java/util/Iterator.hasNext:()Z
      21: ifeq          59
      24: aload_3
      25: invokeinterface #173,  1          // InterfaceMethod java/util/Iterator.next:()Ljava/lang/Object;
      30: checkcast     #218                // class org/springframework/boot/context/config/StandardConfigDataReference
      33: astore        4
      35: aload         4
      37: invokevirtual #313                // Method org/springframework/boot/context/config/StandardConfigDataReference.getDirectory:()Ljava/lang/String;
      40: ifnull        56
      43: aload_2
      44: aload_0
      45: aload         4
      47: invokevirtual #316                // Method resolveEmptyDirectories:(Lorg/springframework/boot/context/config/StandardConfigDataReference;)Ljava/util/Set;
      50: invokeinterface #121,  2          // InterfaceMethod java/util/Set.addAll:(Ljava/util/Collection;)Z
      55: pop
      56: goto          15
      59: aload_2
      60: areturn

  private java.util.Set<org.springframework.boot.context.config.StandardConfigDataResource> resolveEmptyDirectories(org.springframework.boot.context.config.StandardConfigDataReference);
    Code:
       0: aload_0
       1: getfield      #54                 // Field resourceLoader:Lorg/springframework/boot/context/config/LocationResourceLoader;
       4: aload_1
       5: invokevirtual #217                // Method org/springframework/boot/context/config/StandardConfigDataReference.getResourceLocation:()Ljava/lang/String;
       8: invokevirtual #319                // Method org/springframework/boot/context/config/LocationResourceLoader.isPattern:(Ljava/lang/String;)Z
      11: ifne          20
      14: aload_0
      15: aload_1
      16: invokevirtual #322                // Method resolveNonPatternEmptyDirectories:(Lorg/springframework/boot/context/config/StandardConfigDataReference;)Ljava/util/Set;
      19: areturn
      20: aload_0
      21: aload_1
      22: invokevirtual #325                // Method resolvePatternEmptyDirectories:(Lorg/springframework/boot/context/config/StandardConfigDataReference;)Ljava/util/Set;
      25: areturn

  private java.util.Set<org.springframework.boot.context.config.StandardConfigDataResource> resolveNonPatternEmptyDirectories(org.springframework.boot.context.config.StandardConfigDataReference);
    Code:
       0: aload_0
       1: getfield      #54                 // Field resourceLoader:Lorg/springframework/boot/context/config/LocationResourceLoader;
       4: aload_1
       5: invokevirtual #313                // Method org/springframework/boot/context/config/StandardConfigDataReference.getDirectory:()Ljava/lang/String;
       8: invokevirtual #328                // Method org/springframework/boot/context/config/LocationResourceLoader.getResource:(Ljava/lang/String;)Lorg/springframework/core/io/Resource;
      11: astore_2
      12: aload_2
      13: instanceof    #332                // class org/springframework/core/io/ClassPathResource
      16: ifne          28
      19: aload_2
      20: invokeinterface #334,  1          // InterfaceMethod org/springframework/core/io/Resource.exists:()Z
      25: ifne          34
      28: invokestatic  #339                // Method java/util/Collections.emptySet:()Ljava/util/Set;
      31: goto          47
      34: new           #211                // class org/springframework/boot/context/config/StandardConfigDataResource
      37: dup
      38: aload_1
      39: aload_2
      40: iconst_1
      41: invokespecial #343                // Method org/springframework/boot/context/config/StandardConfigDataResource."<init>":(Lorg/springframework/boot/context/config/StandardConfigDataReference;Lorg/springframework/core/io/Resource;Z)V
      44: invokestatic  #274                // Method java/util/Collections.singleton:(Ljava/lang/Object;)Ljava/util/Set;
      47: areturn

  private java.util.Set<org.springframework.boot.context.config.StandardConfigDataResource> resolvePatternEmptyDirectories(org.springframework.boot.context.config.StandardConfigDataReference);
    Code:
       0: aload_0
       1: getfield      #54                 // Field resourceLoader:Lorg/springframework/boot/context/config/LocationResourceLoader;
       4: aload_1
       5: invokevirtual #313                // Method org/springframework/boot/context/config/StandardConfigDataReference.getDirectory:()Ljava/lang/String;
       8: getstatic     #346                // Field org/springframework/boot/context/config/LocationResourceLoader$ResourceType.DIRECTORY:Lorg/springframework/boot/context/config/LocationResourceLoader$ResourceType;
      11: invokevirtual #352                // Method org/springframework/boot/context/config/LocationResourceLoader.getResources:(Ljava/lang/String;Lorg/springframework/boot/context/config/LocationResourceLoader$ResourceType;)[Lorg/springframework/core/io/Resource;
      14: astore_2
      15: aload_1
      16: invokevirtual #356                // Method org/springframework/boot/context/config/StandardConfigDataReference.getConfigDataLocation:()Lorg/springframework/boot/context/config/ConfigDataLocation;
      19: astore_3
      20: aload_3
      21: invokevirtual #360                // Method org/springframework/boot/context/config/ConfigDataLocation.isOptional:()Z
      24: ifne          62
      27: aload_2
      28: invokestatic  #363                // Method org/springframework/util/ObjectUtils.isEmpty:([Ljava/lang/Object;)Z
      31: ifeq          62
      34: ldc_w         #368                // String Config data location \'%s\' contains no subdirectories
      37: iconst_1
      38: anewarray     #2                  // class java/lang/Object
      41: dup
      42: iconst_0
      43: aload_3
      44: aastore
      45: invokestatic  #370                // Method java/lang/String.format:(Ljava/lang/String;[Ljava/lang/Object;)Ljava/lang/String;
      48: astore        4
      50: new           #374                // class org/springframework/boot/context/config/ConfigDataLocationNotFoundException
      53: dup
      54: aload_3
      55: aload         4
      57: aconst_null
      58: invokespecial #376                // Method org/springframework/boot/context/config/ConfigDataLocationNotFoundException."<init>":(Lorg/springframework/boot/context/config/ConfigDataLocation;Ljava/lang/String;Ljava/lang/Throwable;)V
      61: athrow
      62: aload_2
      63: invokestatic  #379                // Method java/util/Arrays.stream:([Ljava/lang/Object;)Ljava/util/stream/Stream;
      66: invokedynamic #385,  0            // InvokeDynamic #3:test:()Ljava/util/function/Predicate;
      71: invokeinterface #389,  2          // InterfaceMethod java/util/stream/Stream.filter:(Ljava/util/function/Predicate;)Ljava/util/stream/Stream;
      76: aload_1
      77: invokedynamic #395,  0            // InvokeDynamic #4:apply:(Lorg/springframework/boot/context/config/StandardConfigDataReference;)Ljava/util/function/Function;
      82: invokeinterface #399,  2          // InterfaceMethod java/util/stream/Stream.map:(Ljava/util/function/Function;)Ljava/util/stream/Stream;
      87: invokedynamic #403,  0            // InvokeDynamic #5:get:()Ljava/util/function/Supplier;
      92: invokestatic  #406                // Method java/util/stream/Collectors.toCollection:(Ljava/util/function/Supplier;)Ljava/util/stream/Collector;
      95: invokeinterface #412,  2          // InterfaceMethod java/util/stream/Stream.collect:(Ljava/util/stream/Collector;)Ljava/lang/Object;
     100: checkcast     #122                // class java/util/Set
     103: areturn

  private java.util.List<org.springframework.boot.context.config.StandardConfigDataResource> resolve(org.springframework.boot.context.config.StandardConfigDataReference);
    Code:
       0: aload_0
       1: getfield      #54                 // Field resourceLoader:Lorg/springframework/boot/context/config/LocationResourceLoader;
       4: aload_1
       5: invokevirtual #217                // Method org/springframework/boot/context/config/StandardConfigDataReference.getResourceLocation:()Ljava/lang/String;
       8: invokevirtual #319                // Method org/springframework/boot/context/config/LocationResourceLoader.isPattern:(Ljava/lang/String;)Z
      11: ifne          20
      14: aload_0
      15: aload_1
      16: invokevirtual #416                // Method resolveNonPattern:(Lorg/springframework/boot/context/config/StandardConfigDataReference;)Ljava/util/List;
      19: areturn
      20: aload_0
      21: aload_1
      22: invokevirtual #419                // Method resolvePattern:(Lorg/springframework/boot/context/config/StandardConfigDataReference;)Ljava/util/List;
      25: areturn

  private java.util.List<org.springframework.boot.context.config.StandardConfigDataResource> resolveNonPattern(org.springframework.boot.context.config.StandardConfigDataReference);
    Code:
       0: aload_0
       1: getfield      #54                 // Field resourceLoader:Lorg/springframework/boot/context/config/LocationResourceLoader;
       4: aload_1
       5: invokevirtual #217                // Method org/springframework/boot/context/config/StandardConfigDataReference.getResourceLocation:()Ljava/lang/String;
       8: invokevirtual #328                // Method org/springframework/boot/context/config/LocationResourceLoader.getResource:(Ljava/lang/String;)Lorg/springframework/core/io/Resource;
      11: astore_2
      12: aload_2
      13: invokeinterface #334,  1          // InterfaceMethod org/springframework/core/io/Resource.exists:()Z
      18: ifne          37
      21: aload_1
      22: invokevirtual #422                // Method org/springframework/boot/context/config/StandardConfigDataReference.isSkippable:()Z
      25: ifeq          37
      28: aload_0
      29: aload_1
      30: invokevirtual #425                // Method logSkippingResource:(Lorg/springframework/boot/context/config/StandardConfigDataReference;)V
      33: invokestatic  #429                // Method java/util/Collections.emptyList:()Ljava/util/List;
      36: areturn
      37: aload_0
      38: aload_1
      39: aload_2
      40: invokevirtual #433                // Method createConfigResourceLocation:(Lorg/springframework/boot/context/config/StandardConfigDataReference;Lorg/springframework/core/io/Resource;)Lorg/springframework/boot/context/config/StandardConfigDataResource;
      43: invokestatic  #437                // Method java/util/Collections.singletonList:(Ljava/lang/Object;)Ljava/util/List;
      46: areturn

  private java.util.List<org.springframework.boot.context.config.StandardConfigDataResource> resolvePattern(org.springframework.boot.context.config.StandardConfigDataReference);
    Code:
       0: new           #298                // class java/util/ArrayList
       3: dup
       4: invokespecial #300                // Method java/util/ArrayList."<init>":()V
       7: astore_2
       8: aload_0
       9: getfield      #54                 // Field resourceLoader:Lorg/springframework/boot/context/config/LocationResourceLoader;
      12: aload_1
      13: invokevirtual #217                // Method org/springframework/boot/context/config/StandardConfigDataReference.getResourceLocation:()Ljava/lang/String;
      16: getstatic     #441                // Field org/springframework/boot/context/config/LocationResourceLoader$ResourceType.FILE:Lorg/springframework/boot/context/config/LocationResourceLoader$ResourceType;
      19: invokevirtual #352                // Method org/springframework/boot/context/config/LocationResourceLoader.getResources:(Ljava/lang/String;Lorg/springframework/boot/context/config/LocationResourceLoader$ResourceType;)[Lorg/springframework/core/io/Resource;
      22: astore_3
      23: aload_3
      24: arraylength
      25: istore        4
      27: iconst_0
      28: istore        5
      30: iload         5
      32: iload         4
      34: if_icmpge     88
      37: aload_3
      38: iload         5
      40: aaload
      41: astore        6
      43: aload         6
      45: invokeinterface #334,  1          // InterfaceMethod org/springframework/core/io/Resource.exists:()Z
      50: ifne          68
      53: aload_1
      54: invokevirtual #422                // Method org/springframework/boot/context/config/StandardConfigDataReference.isSkippable:()Z
      57: ifeq          68
      60: aload_0
      61: aload_1
      62: invokevirtual #425                // Method logSkippingResource:(Lorg/springframework/boot/context/config/StandardConfigDataReference;)V
      65: goto          82
      68: aload_2
      69: aload_0
      70: aload_1
      71: aload         6
      73: invokevirtual #433                // Method createConfigResourceLocation:(Lorg/springframework/boot/context/config/StandardConfigDataReference;Lorg/springframework/core/io/Resource;)Lorg/springframework/boot/context/config/StandardConfigDataResource;
      76: invokeinterface #444,  2          // InterfaceMethod java/util/List.add:(Ljava/lang/Object;)Z
      81: pop
      82: iinc          5, 1
      85: goto          30
      88: aload_2
      89: areturn

  private void logSkippingResource(org.springframework.boot.context.config.StandardConfigDataReference);
    Code:
       0: aload_0
       1: getfield      #15                 // Field logger:Lorg/apache/commons/logging/Log;
       4: ldc_w         #447                // String Skipping missing resource %s
       7: aload_1
       8: invokestatic  #449                // Method org/springframework/core/log/LogMessage.format:(Ljava/lang/String;Ljava/lang/Object;)Lorg/springframework/core/log/LogMessage;
      11: invokeinterface #454,  2          // InterfaceMethod org/apache/commons/logging/Log.trace:(Ljava/lang/Object;)V
      16: return

  private org.springframework.boot.context.config.StandardConfigDataResource createConfigResourceLocation(org.springframework.boot.context.config.StandardConfigDataReference, org.springframework.core.io.Resource);
    Code:
       0: new           #211                // class org/springframework/boot/context/config/StandardConfigDataResource
       3: dup
       4: aload_1
       5: aload_2
       6: invokespecial #459                // Method org/springframework/boot/context/config/StandardConfigDataResource."<init>":(Lorg/springframework/boot/context/config/StandardConfigDataReference;Lorg/springframework/core/io/Resource;)V
       9: areturn

  private static org.springframework.boot.context.config.StandardConfigDataResource lambda$resolvePatternEmptyDirectories$1(org.springframework.boot.context.config.StandardConfigDataReference, org.springframework.core.io.Resource);
    Code:
       0: new           #211                // class org/springframework/boot/context/config/StandardConfigDataResource
       3: dup
       4: aload_0
       5: aload_1
       6: iconst_1
       7: invokespecial #343                // Method org/springframework/boot/context/config/StandardConfigDataResource."<init>":(Lorg/springframework/boot/context/config/StandardConfigDataReference;Lorg/springframework/core/io/Resource;Z)V
      10: areturn

  private static java.lang.String lambda$validateConfigName$0(java.lang.String);
    Code:
       0: aload_0
       1: invokedynamic #462,  0            // InvokeDynamic #6:makeConcatWithConstants:(Ljava/lang/String;)Ljava/lang/String;
       6: areturn

  static {};
    Code:
       0: iconst_1
       1: anewarray     #83                 // class java/lang/String
       4: dup
       5: iconst_0
       6: ldc_w         #464                // String application
       9: aastore
      10: putstatic     #67                 // Field DEFAULT_CONFIG_NAMES:[Ljava/lang/String;
      13: ldc_w         #466                // String ^([a-zA-Z][a-zA-Z0-9*]*?:)(.*$)
      16: invokestatic  #468                // Method java/util/regex/Pattern.compile:(Ljava/lang/String;)Ljava/util/regex/Pattern;
      19: putstatic     #190                // Field URL_PREFIX:Ljava/util/regex/Pattern;
      22: ldc_w         #472                // String ^(.*)\\[(\\.\\w+)\\](?!\\[)$
      25: invokestatic  #468                // Method java/util/regex/Pattern.compile:(Ljava/lang/String;)Ljava/util/regex/Pattern;
      28: putstatic     #259                // Field EXTENSION_HINT_PATTERN:Ljava/util/regex/Pattern;
      31: aconst_null
      32: putstatic     #135                // Field NO_PROFILE:Ljava/lang/String;
      35: return
}
