Compiled from "UnsupportedConfigDataLocationException.java"
public class org.springframework.boot.context.config.UnsupportedConfigDataLocationException extends org.springframework.boot.context.config.ConfigDataException {
  private final org.springframework.boot.context.config.ConfigDataLocation location;

  org.springframework.boot.context.config.UnsupportedConfigDataLocationException(org.springframework.boot.context.config.ConfigDataLocation);
    Code:
       0: aload_0
       1: aload_1
       2: invokedynamic #1,  0              // InvokeDynamic #0:makeConcatWithConstants:(Lorg/springframework/boot/context/config/ConfigDataLocation;)Ljava/lang/String;
       7: aconst_null
       8: invokespecial #5                  // Method org/springframework/boot/context/config/ConfigDataException."<init>":(Ljava/lang/String;Ljava/lang/Throwable;)V
      11: aload_0
      12: aload_1
      13: putfield      #11                 // Field location:Lorg/springframework/boot/context/config/ConfigDataLocation;
      16: return

  public org.springframework.boot.context.config.ConfigDataLocation getLocation();
    Code:
       0: aload_0
       1: getfield      #11                 // Field location:Lorg/springframework/boot/context/config/ConfigDataLocation;
       4: areturn
}
