Compiled from "PrometheusMetricsReporterCmd.java"
public class org.apache.dubbo.metrics.prometheus.PrometheusMetricsReporterCmd implements org.apache.dubbo.qos.api.BaseCommand {
  private final org.apache.dubbo.common.logger.ErrorTypeAwareLogger logger;

  public org.apache.dubbo.rpc.model.FrameworkModel frameworkModel;

  public org.apache.dubbo.metrics.prometheus.PrometheusMetricsReporterCmd(org.apache.dubbo.rpc.model.FrameworkModel);
    Code:
       0: aload_0
       1: invokespecial #1                  // Method java/lang/Object."<init>":()V
       4: aload_0
       5: ldc           #2                  // class org/apache/dubbo/metrics/prometheus/PrometheusMetricsReporterCmd
       7: invokestatic  #3                  // Method org/apache/dubbo/common/logger/LoggerFactory.getErrorTypeAwareLogger:(Ljava/lang/Class;)Lorg/apache/dubbo/common/logger/ErrorTypeAwareLogger;
      10: putfield      #4                  // Field logger:Lorg/apache/dubbo/common/logger/ErrorTypeAwareLogger;
      13: aload_0
      14: aload_1
      15: putfield      #5                  // Field frameworkModel:Lorg/apache/dubbo/rpc/model/FrameworkModel;
      18: return

  public java.lang.String execute(org.apache.dubbo.qos.api.CommandContext, java.lang.String[]);
    Code:
       0: aload_0
       1: getfield      #5                  // Field frameworkModel:Lorg/apache/dubbo/rpc/model/FrameworkModel;
       4: invokevirtual #6                  // Method org/apache/dubbo/rpc/model/FrameworkModel.getApplicationModels:()Ljava/util/List;
       7: astore_3
       8: ldc           #7                  // String There is no application with data
      10: astore        4
      12: aload_0
      13: aload_2
      14: invokespecial #8                  // Method notSpecifyApplication:([Ljava/lang/String;)Z
      17: ifeq          32
      20: aload_0
      21: aload_3
      22: aload         4
      24: invokespecial #9                  // Method useFirst:(Ljava/util/List;Ljava/lang/String;)Ljava/lang/String;
      27: astore        4
      29: goto          42
      32: aload_0
      33: aload_2
      34: iconst_0
      35: aaload
      36: aload_3
      37: invokespecial #10                 // Method specifyApplication:(Ljava/lang/String;Ljava/util/List;)Ljava/lang/String;
      40: astore        4
      42: aload         4
      44: areturn

  private boolean notSpecifyApplication(java.lang.String[]);
    Code:
       0: aload_1
       1: ifnull        9
       4: aload_1
       5: arraylength
       6: ifne          13
       9: iconst_1
      10: goto          14
      13: iconst_0
      14: ireturn

  private java.lang.String useFirst(java.util.List<org.apache.dubbo.rpc.model.ApplicationModel>, java.lang.String);
    Code:
       0: aload_1
       1: invokeinterface #11,  1           // InterfaceMethod java/util/List.iterator:()Ljava/util/Iterator;
       6: astore_3
       7: aload_3
       8: invokeinterface #12,  1           // InterfaceMethod java/util/Iterator.hasNext:()Z
      13: ifeq          54
      16: aload_3
      17: invokeinterface #13,  1           // InterfaceMethod java/util/Iterator.next:()Ljava/lang/Object;
      22: checkcast     #14                 // class org/apache/dubbo/rpc/model/ApplicationModel
      25: astore        4
      27: aload_0
      28: aload         4
      30: invokespecial #15                 // Method getResponseByApplication:(Lorg/apache/dubbo/rpc/model/ApplicationModel;)Ljava/lang/String;
      33: astore        5
      35: aload         5
      37: invokestatic  #16                 // Method getLineNumber:(Ljava/lang/String;)J
      40: lconst_1
      41: lcmp
      42: ifle          51
      45: aload         5
      47: astore_2
      48: goto          54
      51: goto          7
      54: aload_2
      55: areturn

  private java.lang.String specifyApplication(java.lang.String, java.util.List<org.apache.dubbo.rpc.model.ApplicationModel>);
    Code:
       0: ldc           #17                 // String application_all
       2: aload_1
       3: invokevirtual #18                 // Method java/lang/String.equals:(Ljava/lang/Object;)Z
       6: ifeq          15
       9: aload_0
      10: aload_2
      11: invokespecial #19                 // Method allApplication:(Ljava/util/List;)Ljava/lang/String;
      14: areturn
      15: aload_0
      16: aload_1
      17: aload_2
      18: invokespecial #20                 // Method specifySingleApplication:(Ljava/lang/String;Ljava/util/List;)Ljava/lang/String;
      21: areturn

  private java.lang.String specifySingleApplication(java.lang.String, java.util.List<org.apache.dubbo.rpc.model.ApplicationModel>);
    Code:
       0: aload_2
       1: invokeinterface #21,  1           // InterfaceMethod java/util/List.stream:()Ljava/util/stream/Stream;
       6: aload_1
       7: invokedynamic #22,  0             // InvokeDynamic #0:test:(Ljava/lang/String;)Ljava/util/function/Predicate;
      12: invokeinterface #23,  2           // InterfaceMethod java/util/stream/Stream.filter:(Ljava/util/function/Predicate;)Ljava/util/stream/Stream;
      17: invokeinterface #24,  1           // InterfaceMethod java/util/stream/Stream.findFirst:()Ljava/util/Optional;
      22: astore_3
      23: aload_3
      24: invokevirtual #25                 // Method java/util/Optional.isPresent:()Z
      27: ifeq          42
      30: aload_0
      31: aload_3
      32: invokevirtual #26                 // Method java/util/Optional.get:()Ljava/lang/Object;
      35: checkcast     #14                 // class org/apache/dubbo/rpc/model/ApplicationModel
      38: invokespecial #15                 // Method getResponseByApplication:(Lorg/apache/dubbo/rpc/model/ApplicationModel;)Ljava/lang/String;
      41: areturn
      42: new           #27                 // class java/lang/StringBuilder
      45: dup
      46: invokespecial #28                 // Method java/lang/StringBuilder."<init>":()V
      49: ldc           #29                 // String Not exist application:
      51: invokevirtual #30                 // Method java/lang/StringBuilder.append:(Ljava/lang/String;)Ljava/lang/StringBuilder;
      54: aload_1
      55: invokevirtual #30                 // Method java/lang/StringBuilder.append:(Ljava/lang/String;)Ljava/lang/StringBuilder;
      58: invokevirtual #31                 // Method java/lang/StringBuilder.toString:()Ljava/lang/String;
      61: areturn

  private java.lang.String allApplication(java.util.List<org.apache.dubbo.rpc.model.ApplicationModel>);
    Code:
       0: new           #32                 // class java/util/HashMap
       3: dup
       4: invokespecial #33                 // Method java/util/HashMap."<init>":()V
       7: astore_2
       8: aload_1
       9: invokeinterface #11,  1           // InterfaceMethod java/util/List.iterator:()Ljava/util/Iterator;
      14: astore_3
      15: aload_3
      16: invokeinterface #12,  1           // InterfaceMethod java/util/Iterator.hasNext:()Z
      21: ifeq          56
      24: aload_3
      25: invokeinterface #13,  1           // InterfaceMethod java/util/Iterator.next:()Ljava/lang/Object;
      30: checkcast     #14                 // class org/apache/dubbo/rpc/model/ApplicationModel
      33: astore        4
      35: aload_2
      36: aload         4
      38: invokevirtual #34                 // Method org/apache/dubbo/rpc/model/ApplicationModel.getApplicationName:()Ljava/lang/String;
      41: aload_0
      42: aload         4
      44: invokespecial #15                 // Method getResponseByApplication:(Lorg/apache/dubbo/rpc/model/ApplicationModel;)Ljava/lang/String;
      47: invokeinterface #35,  3           // InterfaceMethod java/util/Map.put:(Ljava/lang/Object;Ljava/lang/Object;)Ljava/lang/Object;
      52: pop
      53: goto          15
      56: aload_2
      57: invokestatic  #36                 // Method org/apache/dubbo/common/utils/JsonUtils.toJson:(Ljava/lang/Object;)Ljava/lang/String;
      60: areturn

  public boolean logResult();
    Code:
       0: iconst_0
       1: ireturn

  private java.lang.String getResponseByApplication(org.apache.dubbo.rpc.model.ApplicationModel);
    Code:
       0: ldc           #37                 // String MetricsReporter not init
       2: astore_2
       3: aload_1
       4: invokevirtual #38                 // Method org/apache/dubbo/rpc/model/ApplicationModel.getBeanFactory:()Lorg/apache/dubbo/common/beans/factory/ScopeBeanFactory;
       7: ldc           #39                 // class org/apache/dubbo/metrics/report/MetricsReporter
       9: invokevirtual #40                 // Method org/apache/dubbo/common/beans/factory/ScopeBeanFactory.getBean:(Ljava/lang/Class;)Ljava/lang/Object;
      12: checkcast     #39                 // class org/apache/dubbo/metrics/report/MetricsReporter
      15: astore_3
      16: aload_3
      17: ifnull        103
      20: invokestatic  #41                 // Method java/lang/System.currentTimeMillis:()J
      23: lstore        4
      25: aload_0
      26: getfield      #4                  // Field logger:Lorg/apache/dubbo/common/logger/ErrorTypeAwareLogger;
      29: invokeinterface #42,  1           // InterfaceMethod org/apache/dubbo/common/logger/ErrorTypeAwareLogger.isDebugEnabled:()Z
      34: ifeq          48
      37: aload_0
      38: getfield      #4                  // Field logger:Lorg/apache/dubbo/common/logger/ErrorTypeAwareLogger;
      41: ldc           #43                 // String scrape begin
      43: invokeinterface #44,  2           // InterfaceMethod org/apache/dubbo/common/logger/ErrorTypeAwareLogger.debug:(Ljava/lang/String;)V
      48: aload_3
      49: invokeinterface #45,  1           // InterfaceMethod org/apache/dubbo/metrics/report/MetricsReporter.refreshData:()V
      54: aload_0
      55: getfield      #4                  // Field logger:Lorg/apache/dubbo/common/logger/ErrorTypeAwareLogger;
      58: invokeinterface #42,  1           // InterfaceMethod org/apache/dubbo/common/logger/ErrorTypeAwareLogger.isDebugEnabled:()Z
      63: ifeq          96
      66: aload_0
      67: getfield      #4                  // Field logger:Lorg/apache/dubbo/common/logger/ErrorTypeAwareLogger;
      70: ldc           #46                 // String scrape end,Elapsed Time£º%s
      72: iconst_1
      73: anewarray     #47                 // class java/lang/Object
      76: dup
      77: iconst_0
      78: invokestatic  #41                 // Method java/lang/System.currentTimeMillis:()J
      81: lload         4
      83: lsub
      84: invokestatic  #48                 // Method java/lang/Long.valueOf:(J)Ljava/lang/Long;
      87: aastore
      88: invokestatic  #49                 // Method java/lang/String.format:(Ljava/lang/String;[Ljava/lang/Object;)Ljava/lang/String;
      91: invokeinterface #44,  2           // InterfaceMethod org/apache/dubbo/common/logger/ErrorTypeAwareLogger.debug:(Ljava/lang/String;)V
      96: aload_3
      97: invokeinterface #50,  1           // InterfaceMethod org/apache/dubbo/metrics/report/MetricsReporter.getResponse:()Ljava/lang/String;
     102: astore_2
     103: aload_2
     104: areturn

  private static long getLineNumber(java.lang.String);
    Code:
       0: new           #51                 // class java/io/LineNumberReader
       3: dup
       4: new           #52                 // class java/io/CharArrayReader
       7: dup
       8: aload_0
       9: invokevirtual #53                 // Method java/lang/String.toCharArray:()[C
      12: invokespecial #54                 // Method java/io/CharArrayReader."<init>":([C)V
      15: invokespecial #55                 // Method java/io/LineNumberReader."<init>":(Ljava/io/Reader;)V
      18: astore_1
      19: aload_1
      20: ldc2_w        #57                 // long 9223372036854775807l
      23: invokevirtual #59                 // Method java/io/LineNumberReader.skip:(J)J
      26: pop2
      27: aload_1
      28: invokevirtual #60                 // Method java/io/LineNumberReader.close:()V
      31: goto          35
      34: astore_2
      35: aload_1
      36: invokevirtual #62                 // Method java/io/LineNumberReader.getLineNumber:()I
      39: i2l
      40: lreturn
    Exception table:
       from    to  target type
          19    31    34   Class java/io/IOException

  private static boolean lambda$specifySingleApplication$0(java.lang.String, org.apache.dubbo.rpc.model.ApplicationModel);
    Code:
       0: aload_0
       1: aload_1
       2: invokevirtual #34                 // Method org/apache/dubbo/rpc/model/ApplicationModel.getApplicationName:()Ljava/lang/String;
       5: invokevirtual #18                 // Method java/lang/String.equals:(Ljava/lang/Object;)Z
       8: ireturn
}
