Compiled from "PrometheusMetricsReporterFactory.java"
public class org.apache.dubbo.metrics.prometheus.PrometheusMetricsReporterFactory extends org.apache.dubbo.metrics.report.AbstractMetricsReporterFactory {
  private final org.apache.dubbo.common.logger.ErrorTypeAwareLogger logger;

  public org.apache.dubbo.metrics.prometheus.PrometheusMetricsReporterFactory(org.apache.dubbo.rpc.model.ApplicationModel);
    Code:
       0: aload_0
       1: aload_1
       2: invokespecial #2                  // Method org/apache/dubbo/metrics/report/AbstractMetricsReporterFactory."<init>":(Lorg/apache/dubbo/rpc/model/ApplicationModel;)V
       5: aload_0
       6: ldc           #3                  // class org/apache/dubbo/metrics/prometheus/PrometheusMetricsReporterFactory
       8: invokestatic  #4                  // Method org/apache/dubbo/common/logger/LoggerFactory.getErrorTypeAwareLogger:(Ljava/lang/Class;)Lorg/apache/dubbo/common/logger/ErrorTypeAwareLogger;
      11: putfield      #5                  // Field logger:Lorg/apache/dubbo/common/logger/ErrorTypeAwareLogger;
      14: return

  public org.apache.dubbo.metrics.report.MetricsReporter createMetricsReporter(org.apache.dubbo.common.URL);
    Code:
       0: new           #6                  // class org/apache/dubbo/metrics/prometheus/PrometheusMetricsReporter
       3: dup
       4: aload_1
       5: aload_0
       6: invokevirtual #7                  // Method getApplicationModel:()Lorg/apache/dubbo/rpc/model/ApplicationModel;
       9: invokespecial #8                  // Method org/apache/dubbo/metrics/prometheus/PrometheusMetricsReporter."<init>":(Lorg/apache/dubbo/common/URL;Lorg/apache/dubbo/rpc/model/ApplicationModel;)V
      12: areturn
      13: astore_2
      14: aload_2
      15: invokevirtual #10                 // Method java/lang/NoClassDefFoundError.getMessage:()Ljava/lang/String;
      18: astore_3
      19: aload_3
      20: invokestatic  #11                 // Method dependenciesNotFound:(Ljava/lang/String;)Z
      23: ifeq          88
      26: aload_0
      27: getfield      #5                  // Field logger:Lorg/apache/dubbo/common/logger/ErrorTypeAwareLogger;
      30: ldc           #12                 // String 99-0
      32: ldc           #13                 // String
      34: ldc           #13                 // String
      36: ldc           #14                 // String Failed to load class \"org.apache.dubbo.metrics.prometheus.PrometheusMetricsReporter\".
      38: aload_2
      39: invokeinterface #15,  6           // InterfaceMethod org/apache/dubbo/common/logger/ErrorTypeAwareLogger.error:(Ljava/lang/String;Ljava/lang/String;Ljava/lang/String;Ljava/lang/String;Ljava/lang/Throwable;)V
      44: aload_0
      45: getfield      #5                  // Field logger:Lorg/apache/dubbo/common/logger/ErrorTypeAwareLogger;
      48: ldc           #12                 // String 99-0
      50: ldc           #13                 // String
      52: ldc           #13                 // String
      54: ldc           #16                 // String Defaulting to no-operation (NOP) metricsReporter implementation
      56: aload_2
      57: invokeinterface #15,  6           // InterfaceMethod org/apache/dubbo/common/logger/ErrorTypeAwareLogger.error:(Ljava/lang/String;Ljava/lang/String;Ljava/lang/String;Ljava/lang/String;Ljava/lang/Throwable;)V
      62: aload_0
      63: getfield      #5                  // Field logger:Lorg/apache/dubbo/common/logger/ErrorTypeAwareLogger;
      66: ldc           #12                 // String 99-0
      68: ldc           #13                 // String
      70: ldc           #13                 // String
      72: ldc           #17                 // String Introduce the micrometer-core package to use the ability of metrics
      74: aload_2
      75: invokeinterface #15,  6           // InterfaceMethod org/apache/dubbo/common/logger/ErrorTypeAwareLogger.error:(Ljava/lang/String;Ljava/lang/String;Ljava/lang/String;Ljava/lang/String;Ljava/lang/Throwable;)V
      80: new           #18                 // class org/apache/dubbo/metrics/prometheus/NopPrometheusMetricsReporter
      83: dup
      84: invokespecial #19                 // Method org/apache/dubbo/metrics/prometheus/NopPrometheusMetricsReporter."<init>":()V
      87: areturn
      88: aload_0
      89: getfield      #5                  // Field logger:Lorg/apache/dubbo/common/logger/ErrorTypeAwareLogger;
      92: ldc           #12                 // String 99-0
      94: ldc           #13                 // String
      96: ldc           #13                 // String
      98: ldc           #20                 // String Failed to instantiate PrometheusMetricsReporter
     100: aload_2
     101: invokeinterface #15,  6           // InterfaceMethod org/apache/dubbo/common/logger/ErrorTypeAwareLogger.error:(Ljava/lang/String;Ljava/lang/String;Ljava/lang/String;Ljava/lang/String;Ljava/lang/Throwable;)V
     106: aload_2
     107: athrow
    Exception table:
       from    to  target type
           0    12    13   Class java/lang/NoClassDefFoundError

  private static boolean dependenciesNotFound(java.lang.String);
    Code:
       0: aload_0
       1: ifnonnull     6
       4: iconst_0
       5: ireturn
       6: aload_0
       7: ldc           #21                 // String io/micrometer/core/instrument/composite/CompositeMeterRegistry
       9: invokevirtual #22                 // Method java/lang/String.contains:(Ljava/lang/CharSequence;)Z
      12: ifeq          17
      15: iconst_1
      16: ireturn
      17: aload_0
      18: ldc           #23                 // String io.micrometer.core.instrument.composite.CompositeMeterRegistry
      20: invokevirtual #22                 // Method java/lang/String.contains:(Ljava/lang/CharSequence;)Z
      23: ireturn
}
