Compiled from "MockInvokersSelector.java"
public class org.apache.dubbo.rpc.cluster.router.mock.MockInvokersSelector<T> extends org.apache.dubbo.rpc.cluster.router.state.AbstractStateRouter<T> {
  public static final java.lang.String NAME;

  private volatile org.apache.dubbo.rpc.cluster.router.state.BitList<org.apache.dubbo.rpc.Invoker<T>> normalInvokers;

  private volatile org.apache.dubbo.rpc.cluster.router.state.BitList<org.apache.dubbo.rpc.Invoker<T>> mockedInvokers;

  public org.apache.dubbo.rpc.cluster.router.mock.MockInvokersSelector(org.apache.dubbo.common.URL);
    Code:
       0: aload_0
       1: aload_1
       2: invokespecial #2                  // Method org/apache/dubbo/rpc/cluster/router/state/AbstractStateRouter."<init>":(Lorg/apache/dubbo/common/URL;)V
       5: aload_0
       6: invokestatic  #3                  // Method org/apache/dubbo/rpc/cluster/router/state/BitList.emptyList:()Lorg/apache/dubbo/rpc/cluster/router/state/BitList;
       9: putfield      #4                  // Field normalInvokers:Lorg/apache/dubbo/rpc/cluster/router/state/BitList;
      12: aload_0
      13: invokestatic  #3                  // Method org/apache/dubbo/rpc/cluster/router/state/BitList.emptyList:()Lorg/apache/dubbo/rpc/cluster/router/state/BitList;
      16: putfield      #5                  // Field mockedInvokers:Lorg/apache/dubbo/rpc/cluster/router/state/BitList;
      19: return

  protected org.apache.dubbo.rpc.cluster.router.state.BitList<org.apache.dubbo.rpc.Invoker<T>> doRoute(org.apache.dubbo.rpc.cluster.router.state.BitList<org.apache.dubbo.rpc.Invoker<T>>, org.apache.dubbo.common.URL, org.apache.dubbo.rpc.Invocation, boolean, org.apache.dubbo.common.utils.Holder<org.apache.dubbo.rpc.cluster.router.RouterSnapshotNode<T>>, org.apache.dubbo.common.utils.Holder<java.lang.String>) throws org.apache.dubbo.rpc.RpcException;
    Code:
       0: aload_1
       1: invokestatic  #6                  // Method org/apache/dubbo/common/utils/CollectionUtils.isEmpty:(Ljava/util/Collection;)Z
       4: ifeq          21
       7: iload         4
       9: ifeq          19
      12: aload         6
      14: ldc           #7                  // String Empty invokers. Directly return.
      16: invokevirtual #8                  // Method org/apache/dubbo/common/utils/Holder.set:(Ljava/lang/Object;)V
      19: aload_1
      20: areturn
      21: aload_3
      22: invokeinterface #9,  1            // InterfaceMethod org/apache/dubbo/rpc/Invocation.getObjectAttachments:()Ljava/util/Map;
      27: ifnonnull     51
      30: iload         4
      32: ifeq          42
      35: aload         6
      37: ldc           #10                 // String ObjectAttachments from invocation are null. Return normal Invokers.
      39: invokevirtual #8                  // Method org/apache/dubbo/common/utils/Holder.set:(Ljava/lang/Object;)V
      42: aload_1
      43: aload_0
      44: getfield      #4                  // Field normalInvokers:Lorg/apache/dubbo/rpc/cluster/router/state/BitList;
      47: invokevirtual #11                 // Method org/apache/dubbo/rpc/cluster/router/state/BitList.and:(Lorg/apache/dubbo/rpc/cluster/router/state/BitList;)Lorg/apache/dubbo/rpc/cluster/router/state/BitList;
      50: areturn
      51: aload_3
      52: ldc           #12                 // String invocation.need.mock
      54: invokeinterface #13,  2           // InterfaceMethod org/apache/dubbo/rpc/Invocation.getObjectAttachmentWithoutConvert:(Ljava/lang/String;)Ljava/lang/Object;
      59: checkcast     #14                 // class java/lang/String
      62: astore        7
      64: aload         7
      66: ifnonnull     90
      69: iload         4
      71: ifeq          81
      74: aload         6
      76: ldc           #15                 // String invocation.need.mock not set. Return normal Invokers.
      78: invokevirtual #8                  // Method org/apache/dubbo/common/utils/Holder.set:(Ljava/lang/Object;)V
      81: aload_1
      82: aload_0
      83: getfield      #4                  // Field normalInvokers:Lorg/apache/dubbo/rpc/cluster/router/state/BitList;
      86: invokevirtual #11                 // Method org/apache/dubbo/rpc/cluster/router/state/BitList.and:(Lorg/apache/dubbo/rpc/cluster/router/state/BitList;)Lorg/apache/dubbo/rpc/cluster/router/state/BitList;
      89: areturn
      90: getstatic     #16                 // Field java/lang/Boolean.TRUE:Ljava/lang/Boolean;
      93: invokevirtual #17                 // Method java/lang/Boolean.toString:()Ljava/lang/String;
      96: aload         7
      98: invokevirtual #18                 // Method java/lang/String.equalsIgnoreCase:(Ljava/lang/String;)Z
     101: ifeq          125
     104: iload         4
     106: ifeq          116
     109: aload         6
     111: ldc           #19                 // String invocation.need.mock is true. Return mocked Invokers.
     113: invokevirtual #8                  // Method org/apache/dubbo/common/utils/Holder.set:(Ljava/lang/Object;)V
     116: aload_1
     117: aload_0
     118: getfield      #5                  // Field mockedInvokers:Lorg/apache/dubbo/rpc/cluster/router/state/BitList;
     121: invokevirtual #11                 // Method org/apache/dubbo/rpc/cluster/router/state/BitList.and:(Lorg/apache/dubbo/rpc/cluster/router/state/BitList;)Lorg/apache/dubbo/rpc/cluster/router/state/BitList;
     124: areturn
     125: iload         4
     127: ifeq          137
     130: aload         6
     132: ldc           #20                 // String Directly Return. Reason: invocation.need.mock is set but not match true
     134: invokevirtual #8                  // Method org/apache/dubbo/common/utils/Holder.set:(Ljava/lang/Object;)V
     137: aload_1
     138: areturn

  public void notify(org.apache.dubbo.rpc.cluster.router.state.BitList<org.apache.dubbo.rpc.Invoker<T>>);
    Code:
       0: aload_0
       1: aload_1
       2: invokespecial #21                 // Method cacheMockedInvokers:(Lorg/apache/dubbo/rpc/cluster/router/state/BitList;)V
       5: aload_0
       6: aload_1
       7: invokespecial #22                 // Method cacheNormalInvokers:(Lorg/apache/dubbo/rpc/cluster/router/state/BitList;)V
      10: return

  private void cacheMockedInvokers(org.apache.dubbo.rpc.cluster.router.state.BitList<org.apache.dubbo.rpc.Invoker<T>>);
    Code:
       0: aload_1
       1: invokevirtual #23                 // Method org/apache/dubbo/rpc/cluster/router/state/BitList.clone:()Lorg/apache/dubbo/rpc/cluster/router/state/BitList;
       4: astore_2
       5: aload_2
       6: invokedynamic #24,  0             // InvokeDynamic #0:test:()Ljava/util/function/Predicate;
      11: invokevirtual #25                 // Method org/apache/dubbo/rpc/cluster/router/state/BitList.removeIf:(Ljava/util/function/Predicate;)Z
      14: pop
      15: aload_0
      16: aload_2
      17: putfield      #5                  // Field mockedInvokers:Lorg/apache/dubbo/rpc/cluster/router/state/BitList;
      20: return

  private void cacheNormalInvokers(org.apache.dubbo.rpc.cluster.router.state.BitList<org.apache.dubbo.rpc.Invoker<T>>);
    Code:
       0: aload_1
       1: invokevirtual #23                 // Method org/apache/dubbo/rpc/cluster/router/state/BitList.clone:()Lorg/apache/dubbo/rpc/cluster/router/state/BitList;
       4: astore_2
       5: aload_2
       6: invokedynamic #26,  0             // InvokeDynamic #1:test:()Ljava/util/function/Predicate;
      11: invokevirtual #25                 // Method org/apache/dubbo/rpc/cluster/router/state/BitList.removeIf:(Ljava/util/function/Predicate;)Z
      14: pop
      15: aload_0
      16: aload_2
      17: putfield      #4                  // Field normalInvokers:Lorg/apache/dubbo/rpc/cluster/router/state/BitList;
      20: return

  protected java.lang.String doBuildSnapshot();
    Code:
       0: new           #27                 // class java/util/HashMap
       3: dup
       4: invokespecial #28                 // Method java/util/HashMap."<init>":()V
       7: astore_1
       8: aload_1
       9: ldc           #29                 // String Mocked
      11: aload_0
      12: getfield      #5                  // Field mockedInvokers:Lorg/apache/dubbo/rpc/cluster/router/state/BitList;
      15: invokeinterface #30,  3           // InterfaceMethod java/util/Map.put:(Ljava/lang/Object;Ljava/lang/Object;)Ljava/lang/Object;
      20: pop
      21: aload_1
      22: ldc           #31                 // String Normal
      24: aload_0
      25: getfield      #4                  // Field normalInvokers:Lorg/apache/dubbo/rpc/cluster/router/state/BitList;
      28: invokeinterface #30,  3           // InterfaceMethod java/util/Map.put:(Ljava/lang/Object;Ljava/lang/Object;)Ljava/lang/Object;
      33: pop
      34: new           #32                 // class org/apache/dubbo/rpc/cluster/router/state/RouterGroupingState
      37: dup
      38: aload_0
      39: invokevirtual #33                 // Method java/lang/Object.getClass:()Ljava/lang/Class;
      42: invokevirtual #34                 // Method java/lang/Class.getSimpleName:()Ljava/lang/String;
      45: aload_0
      46: getfield      #5                  // Field mockedInvokers:Lorg/apache/dubbo/rpc/cluster/router/state/BitList;
      49: invokevirtual #35                 // Method org/apache/dubbo/rpc/cluster/router/state/BitList.size:()I
      52: aload_0
      53: getfield      #4                  // Field normalInvokers:Lorg/apache/dubbo/rpc/cluster/router/state/BitList;
      56: invokevirtual #35                 // Method org/apache/dubbo/rpc/cluster/router/state/BitList.size:()I
      59: iadd
      60: aload_1
      61: invokespecial #36                 // Method org/apache/dubbo/rpc/cluster/router/state/RouterGroupingState."<init>":(Ljava/lang/String;ILjava/util/Map;)V
      64: invokevirtual #37                 // Method org/apache/dubbo/rpc/cluster/router/state/RouterGroupingState.toString:()Ljava/lang/String;
      67: areturn

  private static boolean lambda$cacheNormalInvokers$1(org.apache.dubbo.rpc.Invoker);
    Code:
       0: aload_0
       1: invokeinterface #38,  1           // InterfaceMethod org/apache/dubbo/rpc/Invoker.getUrl:()Lorg/apache/dubbo/common/URL;
       6: invokevirtual #39                 // Method org/apache/dubbo/common/URL.getProtocol:()Ljava/lang/String;
       9: ldc           #40                 // String mock
      11: invokevirtual #41                 // Method java/lang/String.equals:(Ljava/lang/Object;)Z
      14: ireturn

  private static boolean lambda$cacheMockedInvokers$0(org.apache.dubbo.rpc.Invoker);
    Code:
       0: aload_0
       1: invokeinterface #38,  1           // InterfaceMethod org/apache/dubbo/rpc/Invoker.getUrl:()Lorg/apache/dubbo/common/URL;
       6: invokevirtual #39                 // Method org/apache/dubbo/common/URL.getProtocol:()Ljava/lang/String;
       9: ldc           #40                 // String mock
      11: invokevirtual #41                 // Method java/lang/String.equals:(Ljava/lang/Object;)Z
      14: ifne          21
      17: iconst_1
      18: goto          22
      21: iconst_0
      22: ireturn
}
