Compiled from "NopMetricsReporterFactory.java"
public class org.apache.dubbo.metrics.report.nop.NopMetricsReporterFactory implements org.apache.dubbo.metrics.report.MetricsReporterFactory {
  public org.apache.dubbo.metrics.report.nop.NopMetricsReporterFactory();
    Code:
       0: aload_0
       1: invokespecial #1                  // Method java/lang/Object."<init>":()V
       4: return

  public org.apache.dubbo.metrics.report.MetricsReporter createMetricsReporter(org.apache.dubbo.common.URL);
    Code:
       0: new           #2                  // class org/apache/dubbo/metrics/report/nop/NopMetricsReporter
       3: dup
       4: aload_1
       5: invokespecial #3                  // Method org/apache/dubbo/metrics/report/nop/NopMetricsReporter."<init>":(Lorg/apache/dubbo/common/URL;)V
       8: areturn
}
