Compiled from "EncodedValue.java"
public class jadx.api.plugins.input.data.annotations.EncodedValue extends jadx.api.plugins.input.data.attributes.PinnedAttribute {
  public static final jadx.api.plugins.input.data.annotations.EncodedValue NULL;

  private final jadx.api.plugins.input.data.annotations.EncodedType type;

  private final java.lang.Object value;

  public jadx.api.plugins.input.data.annotations.EncodedValue(jadx.api.plugins.input.data.annotations.EncodedType, java.lang.Object);
    Code:
       0: aload_0
       1: invokespecial #1                  // Method jadx/api/plugins/input/data/attributes/PinnedAttribute."<init>":()V
       4: aload_0
       5: aload_1
       6: putfield      #2                  // Field type:Ljadx/api/plugins/input/data/annotations/EncodedType;
       9: aload_0
      10: aload_2
      11: putfield      #3                  // Field value:Ljava/lang/Object;
      14: return

  public jadx.api.plugins.input.data.annotations.EncodedType getType();
    Code:
       0: aload_0
       1: getfield      #2                  // Field type:Ljadx/api/plugins/input/data/annotations/EncodedType;
       4: areturn

  public java.lang.Object getValue();
    Code:
       0: aload_0
       1: getfield      #3                  // Field value:Ljava/lang/Object;
       4: areturn

  public boolean equals(java.lang.Object);
    Code:
       0: aload_0
       1: aload_1
       2: if_acmpne     7
       5: iconst_1
       6: ireturn
       7: aload_1
       8: ifnull        22
      11: aload_0
      12: invokevirtual #4                  // Method java/lang/Object.getClass:()Ljava/lang/Class;
      15: aload_1
      16: invokevirtual #4                  // Method java/lang/Object.getClass:()Ljava/lang/Class;
      19: if_acmpeq     24
      22: iconst_0
      23: ireturn
      24: aload_1
      25: checkcast     #5                  // class jadx/api/plugins/input/data/annotations/EncodedValue
      28: astore_2
      29: aload_0
      30: getfield      #2                  // Field type:Ljadx/api/plugins/input/data/annotations/EncodedType;
      33: aload_2
      34: invokevirtual #6                  // Method getType:()Ljadx/api/plugins/input/data/annotations/EncodedType;
      37: if_acmpne     58
      40: aload_0
      41: getfield      #3                  // Field value:Ljava/lang/Object;
      44: aload_2
      45: invokevirtual #7                  // Method getValue:()Ljava/lang/Object;
      48: invokestatic  #8                  // Method java/util/Objects.equals:(Ljava/lang/Object;Ljava/lang/Object;)Z
      51: ifeq          58
      54: iconst_1
      55: goto          59
      58: iconst_0
      59: ireturn

  public jadx.api.plugins.input.data.attributes.IJadxAttrType<? extends jadx.api.plugins.input.data.attributes.IJadxAttribute> getAttrType();
    Code:
       0: getstatic     #9                  // Field jadx/api/plugins/input/data/attributes/JadxAttrType.CONSTANT_VALUE:Ljadx/api/plugins/input/data/attributes/JadxAttrType;
       3: areturn

  public int hashCode();
    Code:
       0: iconst_2
       1: anewarray     #10                 // class java/lang/Object
       4: dup
       5: iconst_0
       6: aload_0
       7: invokevirtual #6                  // Method getType:()Ljadx/api/plugins/input/data/annotations/EncodedType;
      10: aastore
      11: dup
      12: iconst_1
      13: aload_0
      14: invokevirtual #7                  // Method getValue:()Ljava/lang/Object;
      17: aastore
      18: invokestatic  #11                 // Method java/util/Objects.hash:([Ljava/lang/Object;)I
      21: ireturn

  public java.lang.String toString();
    Code:
       0: getstatic     #12                 // Field jadx/api/plugins/input/data/annotations/EncodedValue$1.$SwitchMap$jadx$api$plugins$input$data$annotations$EncodedType:[I
       3: aload_0
       4: getfield      #2                  // Field type:Ljadx/api/plugins/input/data/annotations/EncodedType;
       7: invokevirtual #13                 // Method jadx/api/plugins/input/data/annotations/EncodedType.ordinal:()I
      10: iaload
      11: tableswitch   { // 1 to 3
                     1: 36
                     2: 39
                     3: 67
               default: 95
          }
      36: ldc           #14                 // String null
      38: areturn
      39: new           #15                 // class java/lang/StringBuilder
      42: dup
      43: invokespecial #16                 // Method java/lang/StringBuilder."<init>":()V
      46: ldc           #17                 // String [
      48: invokevirtual #18                 // Method java/lang/StringBuilder.append:(Ljava/lang/String;)Ljava/lang/StringBuilder;
      51: aload_0
      52: getfield      #3                  // Field value:Ljava/lang/Object;
      55: invokevirtual #19                 // Method java/lang/StringBuilder.append:(Ljava/lang/Object;)Ljava/lang/StringBuilder;
      58: ldc           #20                 // String ]
      60: invokevirtual #18                 // Method java/lang/StringBuilder.append:(Ljava/lang/String;)Ljava/lang/StringBuilder;
      63: invokevirtual #21                 // Method java/lang/StringBuilder.toString:()Ljava/lang/String;
      66: areturn
      67: new           #15                 // class java/lang/StringBuilder
      70: dup
      71: invokespecial #16                 // Method java/lang/StringBuilder."<init>":()V
      74: ldc           #22                 // String {STRING: \"
      76: invokevirtual #18                 // Method java/lang/StringBuilder.append:(Ljava/lang/String;)Ljava/lang/StringBuilder;
      79: aload_0
      80: getfield      #3                  // Field value:Ljava/lang/Object;
      83: invokevirtual #19                 // Method java/lang/StringBuilder.append:(Ljava/lang/Object;)Ljava/lang/StringBuilder;
      86: ldc           #23                 // String \"}
      88: invokevirtual #18                 // Method java/lang/StringBuilder.append:(Ljava/lang/String;)Ljava/lang/StringBuilder;
      91: invokevirtual #21                 // Method java/lang/StringBuilder.toString:()Ljava/lang/String;
      94: areturn
      95: new           #15                 // class java/lang/StringBuilder
      98: dup
      99: invokespecial #16                 // Method java/lang/StringBuilder."<init>":()V
     102: ldc           #24                 // String {
     104: invokevirtual #18                 // Method java/lang/StringBuilder.append:(Ljava/lang/String;)Ljava/lang/StringBuilder;
     107: aload_0
     108: getfield      #2                  // Field type:Ljadx/api/plugins/input/data/annotations/EncodedType;
     111: invokevirtual #25                 // Method jadx/api/plugins/input/data/annotations/EncodedType.toString:()Ljava/lang/String;
     114: bipush        8
     116: invokevirtual #26                 // Method java/lang/String.substring:(I)Ljava/lang/String;
     119: invokevirtual #18                 // Method java/lang/StringBuilder.append:(Ljava/lang/String;)Ljava/lang/StringBuilder;
     122: ldc           #27                 // String :
     124: invokevirtual #18                 // Method java/lang/StringBuilder.append:(Ljava/lang/String;)Ljava/lang/StringBuilder;
     127: aload_0
     128: getfield      #3                  // Field value:Ljava/lang/Object;
     131: invokevirtual #19                 // Method java/lang/StringBuilder.append:(Ljava/lang/Object;)Ljava/lang/StringBuilder;
     134: bipush        125
     136: invokevirtual #28                 // Method java/lang/StringBuilder.append:(C)Ljava/lang/StringBuilder;
     139: invokevirtual #21                 // Method java/lang/StringBuilder.toString:()Ljava/lang/String;
     142: areturn

  static {};
    Code:
       0: new           #5                  // class jadx/api/plugins/input/data/annotations/EncodedValue
       3: dup
       4: getstatic     #29                 // Field jadx/api/plugins/input/data/annotations/EncodedType.ENCODED_NULL:Ljadx/api/plugins/input/data/annotations/EncodedType;
       7: aconst_null
       8: invokespecial #30                 // Method "<init>":(Ljadx/api/plugins/input/data/annotations/EncodedType;Ljava/lang/Object;)V
      11: putstatic     #31                 // Field NULL:Ljadx/api/plugins/input/data/annotations/EncodedValue;
      14: return
}
