Compiled from "EncodedType.java"
public final class jadx.api.plugins.input.data.annotations.EncodedType extends java.lang.Enum<jadx.api.plugins.input.data.annotations.EncodedType> {
  public static final jadx.api.plugins.input.data.annotations.EncodedType ENCODED_NULL;

  public static final jadx.api.plugins.input.data.annotations.EncodedType ENCODED_BOOLEAN;

  public static final jadx.api.plugins.input.data.annotations.EncodedType ENCODED_BYTE;

  public static final jadx.api.plugins.input.data.annotations.EncodedType ENCODED_SHORT;

  public static final jadx.api.plugins.input.data.annotations.EncodedType ENCODED_CHAR;

  public static final jadx.api.plugins.input.data.annotations.EncodedType ENCODED_INT;

  public static final jadx.api.plugins.input.data.annotations.EncodedType ENCODED_LONG;

  public static final jadx.api.plugins.input.data.annotations.EncodedType ENCODED_FLOAT;

  public static final jadx.api.plugins.input.data.annotations.EncodedType ENCODED_DOUBLE;

  public static final jadx.api.plugins.input.data.annotations.EncodedType ENCODED_STRING;

  public static final jadx.api.plugins.input.data.annotations.EncodedType ENCODED_TYPE;

  public static final jadx.api.plugins.input.data.annotations.EncodedType ENCODED_ENUM;

  public static final jadx.api.plugins.input.data.annotations.EncodedType ENCODED_FIELD;

  public static final jadx.api.plugins.input.data.annotations.EncodedType ENCODED_METHOD;

  public static final jadx.api.plugins.input.data.annotations.EncodedType ENCODED_METHOD_TYPE;

  public static final jadx.api.plugins.input.data.annotations.EncodedType ENCODED_METHOD_HANDLE;

  public static final jadx.api.plugins.input.data.annotations.EncodedType ENCODED_ARRAY;

  public static final jadx.api.plugins.input.data.annotations.EncodedType ENCODED_ANNOTATION;

  private static final jadx.api.plugins.input.data.annotations.EncodedType[] $VALUES;

  public static jadx.api.plugins.input.data.annotations.EncodedType[] values();
    Code:
       0: getstatic     #1                  // Field $VALUES:[Ljadx/api/plugins/input/data/annotations/EncodedType;
       3: invokevirtual #2                  // Method "[Ljadx/api/plugins/input/data/annotations/EncodedType;".clone:()Ljava/lang/Object;
       6: checkcast     #3                  // class "[Ljadx/api/plugins/input/data/annotations/EncodedType;"
       9: areturn

  public static jadx.api.plugins.input.data.annotations.EncodedType valueOf(java.lang.String);
    Code:
       0: ldc           #4                  // class jadx/api/plugins/input/data/annotations/EncodedType
       2: aload_0
       3: invokestatic  #5                  // Method java/lang/Enum.valueOf:(Ljava/lang/Class;Ljava/lang/String;)Ljava/lang/Enum;
       6: checkcast     #4                  // class jadx/api/plugins/input/data/annotations/EncodedType
       9: areturn

  private jadx.api.plugins.input.data.annotations.EncodedType();
    Code:
       0: aload_0
       1: aload_1
       2: iload_2
       3: invokespecial #6                  // Method java/lang/Enum."<init>":(Ljava/lang/String;I)V
       6: return

  static {};
    Code:
       0: new           #4                  // class jadx/api/plugins/input/data/annotations/EncodedType
       3: dup
       4: ldc           #7                  // String ENCODED_NULL
       6: iconst_0
       7: invokespecial #8                  // Method "<init>":(Ljava/lang/String;I)V
      10: putstatic     #9                  // Field ENCODED_NULL:Ljadx/api/plugins/input/data/annotations/EncodedType;
      13: new           #4                  // class jadx/api/plugins/input/data/annotations/EncodedType
      16: dup
      17: ldc           #10                 // String ENCODED_BOOLEAN
      19: iconst_1
      20: invokespecial #8                  // Method "<init>":(Ljava/lang/String;I)V
      23: putstatic     #11                 // Field ENCODED_BOOLEAN:Ljadx/api/plugins/input/data/annotations/EncodedType;
      26: new           #4                  // class jadx/api/plugins/input/data/annotations/EncodedType
      29: dup
      30: ldc           #12                 // String ENCODED_BYTE
      32: iconst_2
      33: invokespecial #8                  // Method "<init>":(Ljava/lang/String;I)V
      36: putstatic     #13                 // Field ENCODED_BYTE:Ljadx/api/plugins/input/data/annotations/EncodedType;
      39: new           #4                  // class jadx/api/plugins/input/data/annotations/EncodedType
      42: dup
      43: ldc           #14                 // String ENCODED_SHORT
      45: iconst_3
      46: invokespecial #8                  // Method "<init>":(Ljava/lang/String;I)V
      49: putstatic     #15                 // Field ENCODED_SHORT:Ljadx/api/plugins/input/data/annotations/EncodedType;
      52: new           #4                  // class jadx/api/plugins/input/data/annotations/EncodedType
      55: dup
      56: ldc           #16                 // String ENCODED_CHAR
      58: iconst_4
      59: invokespecial #8                  // Method "<init>":(Ljava/lang/String;I)V
      62: putstatic     #17                 // Field ENCODED_CHAR:Ljadx/api/plugins/input/data/annotations/EncodedType;
      65: new           #4                  // class jadx/api/plugins/input/data/annotations/EncodedType
      68: dup
      69: ldc           #18                 // String ENCODED_INT
      71: iconst_5
      72: invokespecial #8                  // Method "<init>":(Ljava/lang/String;I)V
      75: putstatic     #19                 // Field ENCODED_INT:Ljadx/api/plugins/input/data/annotations/EncodedType;
      78: new           #4                  // class jadx/api/plugins/input/data/annotations/EncodedType
      81: dup
      82: ldc           #20                 // String ENCODED_LONG
      84: bipush        6
      86: invokespecial #8                  // Method "<init>":(Ljava/lang/String;I)V
      89: putstatic     #21                 // Field ENCODED_LONG:Ljadx/api/plugins/input/data/annotations/EncodedType;
      92: new           #4                  // class jadx/api/plugins/input/data/annotations/EncodedType
      95: dup
      96: ldc           #22                 // String ENCODED_FLOAT
      98: bipush        7
     100: invokespecial #8                  // Method "<init>":(Ljava/lang/String;I)V
     103: putstatic     #23                 // Field ENCODED_FLOAT:Ljadx/api/plugins/input/data/annotations/EncodedType;
     106: new           #4                  // class jadx/api/plugins/input/data/annotations/EncodedType
     109: dup
     110: ldc           #24                 // String ENCODED_DOUBLE
     112: bipush        8
     114: invokespecial #8                  // Method "<init>":(Ljava/lang/String;I)V
     117: putstatic     #25                 // Field ENCODED_DOUBLE:Ljadx/api/plugins/input/data/annotations/EncodedType;
     120: new           #4                  // class jadx/api/plugins/input/data/annotations/EncodedType
     123: dup
     124: ldc           #26                 // String ENCODED_STRING
     126: bipush        9
     128: invokespecial #8                  // Method "<init>":(Ljava/lang/String;I)V
     131: putstatic     #27                 // Field ENCODED_STRING:Ljadx/api/plugins/input/data/annotations/EncodedType;
     134: new           #4                  // class jadx/api/plugins/input/data/annotations/EncodedType
     137: dup
     138: ldc           #28                 // String ENCODED_TYPE
     140: bipush        10
     142: invokespecial #8                  // Method "<init>":(Ljava/lang/String;I)V
     145: putstatic     #29                 // Field ENCODED_TYPE:Ljadx/api/plugins/input/data/annotations/EncodedType;
     148: new           #4                  // class jadx/api/plugins/input/data/annotations/EncodedType
     151: dup
     152: ldc           #30                 // String ENCODED_ENUM
     154: bipush        11
     156: invokespecial #8                  // Method "<init>":(Ljava/lang/String;I)V
     159: putstatic     #31                 // Field ENCODED_ENUM:Ljadx/api/plugins/input/data/annotations/EncodedType;
     162: new           #4                  // class jadx/api/plugins/input/data/annotations/EncodedType
     165: dup
     166: ldc           #32                 // String ENCODED_FIELD
     168: bipush        12
     170: invokespecial #8                  // Method "<init>":(Ljava/lang/String;I)V
     173: putstatic     #33                 // Field ENCODED_FIELD:Ljadx/api/plugins/input/data/annotations/EncodedType;
     176: new           #4                  // class jadx/api/plugins/input/data/annotations/EncodedType
     179: dup
     180: ldc           #34                 // String ENCODED_METHOD
     182: bipush        13
     184: invokespecial #8                  // Method "<init>":(Ljava/lang/String;I)V
     187: putstatic     #35                 // Field ENCODED_METHOD:Ljadx/api/plugins/input/data/annotations/EncodedType;
     190: new           #4                  // class jadx/api/plugins/input/data/annotations/EncodedType
     193: dup
     194: ldc           #36                 // String ENCODED_METHOD_TYPE
     196: bipush        14
     198: invokespecial #8                  // Method "<init>":(Ljava/lang/String;I)V
     201: putstatic     #37                 // Field ENCODED_METHOD_TYPE:Ljadx/api/plugins/input/data/annotations/EncodedType;
     204: new           #4                  // class jadx/api/plugins/input/data/annotations/EncodedType
     207: dup
     208: ldc           #38                 // String ENCODED_METHOD_HANDLE
     210: bipush        15
     212: invokespecial #8                  // Method "<init>":(Ljava/lang/String;I)V
     215: putstatic     #39                 // Field ENCODED_METHOD_HANDLE:Ljadx/api/plugins/input/data/annotations/EncodedType;
     218: new           #4                  // class jadx/api/plugins/input/data/annotations/EncodedType
     221: dup
     222: ldc           #40                 // String ENCODED_ARRAY
     224: bipush        16
     226: invokespecial #8                  // Method "<init>":(Ljava/lang/String;I)V
     229: putstatic     #41                 // Field ENCODED_ARRAY:Ljadx/api/plugins/input/data/annotations/EncodedType;
     232: new           #4                  // class jadx/api/plugins/input/data/annotations/EncodedType
     235: dup
     236: ldc           #42                 // String ENCODED_ANNOTATION
     238: bipush        17
     240: invokespecial #8                  // Method "<init>":(Ljava/lang/String;I)V
     243: putstatic     #43                 // Field ENCODED_ANNOTATION:Ljadx/api/plugins/input/data/annotations/EncodedType;
     246: bipush        18
     248: anewarray     #4                  // class jadx/api/plugins/input/data/annotations/EncodedType
     251: dup
     252: iconst_0
     253: getstatic     #9                  // Field ENCODED_NULL:Ljadx/api/plugins/input/data/annotations/EncodedType;
     256: aastore
     257: dup
     258: iconst_1
     259: getstatic     #11                 // Field ENCODED_BOOLEAN:Ljadx/api/plugins/input/data/annotations/EncodedType;
     262: aastore
     263: dup
     264: iconst_2
     265: getstatic     #13                 // Field ENCODED_BYTE:Ljadx/api/plugins/input/data/annotations/EncodedType;
     268: aastore
     269: dup
     270: iconst_3
     271: getstatic     #15                 // Field ENCODED_SHORT:Ljadx/api/plugins/input/data/annotations/EncodedType;
     274: aastore
     275: dup
     276: iconst_4
     277: getstatic     #17                 // Field ENCODED_CHAR:Ljadx/api/plugins/input/data/annotations/EncodedType;
     280: aastore
     281: dup
     282: iconst_5
     283: getstatic     #19                 // Field ENCODED_INT:Ljadx/api/plugins/input/data/annotations/EncodedType;
     286: aastore
     287: dup
     288: bipush        6
     290: getstatic     #21                 // Field ENCODED_LONG:Ljadx/api/plugins/input/data/annotations/EncodedType;
     293: aastore
     294: dup
     295: bipush        7
     297: getstatic     #23                 // Field ENCODED_FLOAT:Ljadx/api/plugins/input/data/annotations/EncodedType;
     300: aastore
     301: dup
     302: bipush        8
     304: getstatic     #25                 // Field ENCODED_DOUBLE:Ljadx/api/plugins/input/data/annotations/EncodedType;
     307: aastore
     308: dup
     309: bipush        9
     311: getstatic     #27                 // Field ENCODED_STRING:Ljadx/api/plugins/input/data/annotations/EncodedType;
     314: aastore
     315: dup
     316: bipush        10
     318: getstatic     #29                 // Field ENCODED_TYPE:Ljadx/api/plugins/input/data/annotations/EncodedType;
     321: aastore
     322: dup
     323: bipush        11
     325: getstatic     #31                 // Field ENCODED_ENUM:Ljadx/api/plugins/input/data/annotations/EncodedType;
     328: aastore
     329: dup
     330: bipush        12
     332: getstatic     #33                 // Field ENCODED_FIELD:Ljadx/api/plugins/input/data/annotations/EncodedType;
     335: aastore
     336: dup
     337: bipush        13
     339: getstatic     #35                 // Field ENCODED_METHOD:Ljadx/api/plugins/input/data/annotations/EncodedType;
     342: aastore
     343: dup
     344: bipush        14
     346: getstatic     #37                 // Field ENCODED_METHOD_TYPE:Ljadx/api/plugins/input/data/annotations/EncodedType;
     349: aastore
     350: dup
     351: bipush        15
     353: getstatic     #39                 // Field ENCODED_METHOD_HANDLE:Ljadx/api/plugins/input/data/annotations/EncodedType;
     356: aastore
     357: dup
     358: bipush        16
     360: getstatic     #41                 // Field ENCODED_ARRAY:Ljadx/api/plugins/input/data/annotations/EncodedType;
     363: aastore
     364: dup
     365: bipush        17
     367: getstatic     #43                 // Field ENCODED_ANNOTATION:Ljadx/api/plugins/input/data/annotations/EncodedType;
     370: aastore
     371: putstatic     #1                  // Field $VALUES:[Ljadx/api/plugins/input/data/annotations/EncodedType;
     374: return
}
