Compiled from "JadxAnnotation.java"
public class jadx.api.plugins.input.data.annotations.JadxAnnotation implements jadx.api.plugins.input.data.annotations.IAnnotation {
  private final jadx.api.plugins.input.data.annotations.AnnotationVisibility visibility;

  private final java.lang.String type;

  private final java.util.Map<java.lang.String, jadx.api.plugins.input.data.annotations.EncodedValue> values;

  public jadx.api.plugins.input.data.annotations.JadxAnnotation(jadx.api.plugins.input.data.annotations.AnnotationVisibility, java.lang.String, java.util.Map<java.lang.String, jadx.api.plugins.input.data.annotations.EncodedValue>);
    Code:
       0: aload_0
       1: invokespecial #1                  // Method java/lang/Object."<init>":()V
       4: aload_0
       5: aload_1
       6: putfield      #2                  // Field visibility:Ljadx/api/plugins/input/data/annotations/AnnotationVisibility;
       9: aload_0
      10: aload_2
      11: putfield      #3                  // Field type:Ljava/lang/String;
      14: aload_0
      15: aload_3
      16: putfield      #4                  // Field values:Ljava/util/Map;
      19: return

  public java.lang.String getAnnotationClass();
    Code:
       0: aload_0
       1: getfield      #3                  // Field type:Ljava/lang/String;
       4: areturn

  public jadx.api.plugins.input.data.annotations.AnnotationVisibility getVisibility();
    Code:
       0: aload_0
       1: getfield      #2                  // Field visibility:Ljadx/api/plugins/input/data/annotations/AnnotationVisibility;
       4: areturn

  public java.util.Map<java.lang.String, jadx.api.plugins.input.data.annotations.EncodedValue> getValues();
    Code:
       0: aload_0
       1: getfield      #4                  // Field values:Ljava/util/Map;
       4: areturn

  public java.lang.String toString();
    Code:
       0: new           #5                  // class java/lang/StringBuilder
       3: dup
       4: invokespecial #6                  // Method java/lang/StringBuilder."<init>":()V
       7: ldc           #7                  // String Annotation{
       9: invokevirtual #8                  // Method java/lang/StringBuilder.append:(Ljava/lang/String;)Ljava/lang/StringBuilder;
      12: aload_0
      13: getfield      #2                  // Field visibility:Ljadx/api/plugins/input/data/annotations/AnnotationVisibility;
      16: invokevirtual #9                  // Method java/lang/StringBuilder.append:(Ljava/lang/Object;)Ljava/lang/StringBuilder;
      19: ldc           #10                 // String , type=
      21: invokevirtual #8                  // Method java/lang/StringBuilder.append:(Ljava/lang/String;)Ljava/lang/StringBuilder;
      24: aload_0
      25: getfield      #3                  // Field type:Ljava/lang/String;
      28: invokevirtual #8                  // Method java/lang/StringBuilder.append:(Ljava/lang/String;)Ljava/lang/StringBuilder;
      31: ldc           #11                 // String , values=
      33: invokevirtual #8                  // Method java/lang/StringBuilder.append:(Ljava/lang/String;)Ljava/lang/StringBuilder;
      36: aload_0
      37: getfield      #4                  // Field values:Ljava/util/Map;
      40: invokevirtual #9                  // Method java/lang/StringBuilder.append:(Ljava/lang/Object;)Ljava/lang/StringBuilder;
      43: bipush        125
      45: invokevirtual #12                 // Method java/lang/StringBuilder.append:(C)Ljava/lang/StringBuilder;
      48: invokevirtual #13                 // Method java/lang/StringBuilder.toString:()Ljava/lang/String;
      51: areturn
}
