Compiled from "CodecAdapter.java"
public class org.apache.dubbo.remoting.transport.codec.CodecAdapter implements org.apache.dubbo.remoting.Codec2 {
  private org.apache.dubbo.remoting.Codec codec;

  public org.apache.dubbo.remoting.transport.codec.CodecAdapter(org.apache.dubbo.remoting.Codec);
    Code:
       0: aload_0
       1: invokespecial #1                  // Method java/lang/Object."<init>":()V
       4: aload_1
       5: ldc           #2                  // String codec == null
       7: invokestatic  #3                  // Method org/apache/dubbo/common/utils/Assert.notNull:(Ljava/lang/Object;Ljava/lang/String;)V
      10: aload_0
      11: aload_1
      12: putfield      #4                  // Field codec:Lorg/apache/dubbo/remoting/Codec;
      15: return

  public void encode(org.apache.dubbo.remoting.Channel, org.apache.dubbo.remoting.buffer.ChannelBuffer, java.lang.Object) throws java.io.IOException;
    Code:
       0: new           #5                  // class org/apache/dubbo/common/io/UnsafeByteArrayOutputStream
       3: dup
       4: sipush        1024
       7: invokespecial #6                  // Method org/apache/dubbo/common/io/UnsafeByteArrayOutputStream."<init>":(I)V
      10: astore        4
      12: aload_0
      13: getfield      #4                  // Field codec:Lorg/apache/dubbo/remoting/Codec;
      16: aload_1
      17: aload         4
      19: aload_3
      20: invokeinterface #7,  4            // InterfaceMethod org/apache/dubbo/remoting/Codec.encode:(Lorg/apache/dubbo/remoting/Channel;Ljava/io/OutputStream;Ljava/lang/Object;)V
      25: aload_2
      26: aload         4
      28: invokevirtual #8                  // Method org/apache/dubbo/common/io/UnsafeByteArrayOutputStream.toByteArray:()[B
      31: invokeinterface #9,  2            // InterfaceMethod org/apache/dubbo/remoting/buffer/ChannelBuffer.writeBytes:([B)V
      36: return

  public java.lang.Object decode(org.apache.dubbo.remoting.Channel, org.apache.dubbo.remoting.buffer.ChannelBuffer) throws java.io.IOException;
    Code:
       0: aload_2
       1: invokeinterface #10,  1           // InterfaceMethod org/apache/dubbo/remoting/buffer/ChannelBuffer.readableBytes:()I
       6: newarray       byte
       8: astore_3
       9: aload_2
      10: invokeinterface #11,  1           // InterfaceMethod org/apache/dubbo/remoting/buffer/ChannelBuffer.readerIndex:()I
      15: istore        4
      17: aload_2
      18: aload_3
      19: invokeinterface #12,  2           // InterfaceMethod org/apache/dubbo/remoting/buffer/ChannelBuffer.readBytes:([B)V
      24: new           #13                 // class org/apache/dubbo/common/io/UnsafeByteArrayInputStream
      27: dup
      28: aload_3
      29: invokespecial #14                 // Method org/apache/dubbo/common/io/UnsafeByteArrayInputStream."<init>":([B)V
      32: astore        5
      34: aload_0
      35: getfield      #4                  // Field codec:Lorg/apache/dubbo/remoting/Codec;
      38: aload_1
      39: aload         5
      41: invokeinterface #15,  3           // InterfaceMethod org/apache/dubbo/remoting/Codec.decode:(Lorg/apache/dubbo/remoting/Channel;Ljava/io/InputStream;)Ljava/lang/Object;
      46: astore        6
      48: aload_2
      49: iload         4
      51: aload         5
      53: invokevirtual #16                 // Method org/apache/dubbo/common/io/UnsafeByteArrayInputStream.position:()I
      56: iadd
      57: invokeinterface #17,  2           // InterfaceMethod org/apache/dubbo/remoting/buffer/ChannelBuffer.readerIndex:(I)V
      62: aload         6
      64: getstatic     #18                 // Field org/apache/dubbo/remoting/Codec.NEED_MORE_INPUT:Ljava/lang/Object;
      67: if_acmpne     76
      70: getstatic     #19                 // Field org/apache/dubbo/remoting/Codec2$DecodeResult.NEED_MORE_INPUT:Lorg/apache/dubbo/remoting/Codec2$DecodeResult;
      73: goto          78
      76: aload         6
      78: areturn

  public org.apache.dubbo.remoting.Codec getCodec();
    Code:
       0: aload_0
       1: getfield      #4                  // Field codec:Lorg/apache/dubbo/remoting/Codec;
       4: areturn
}
