Compiled from "TransportCodec.java"
public class org.apache.dubbo.remoting.transport.codec.TransportCodec extends org.apache.dubbo.remoting.transport.AbstractCodec {
  public org.apache.dubbo.remoting.transport.codec.TransportCodec();
    Code:
       0: aload_0
       1: invokespecial #1                  // Method org/apache/dubbo/remoting/transport/AbstractCodec."<init>":()V
       4: return

  public void encode(org.apache.dubbo.remoting.Channel, org.apache.dubbo.remoting.buffer.ChannelBuffer, java.lang.Object) throws java.io.IOException;
    Code:
       0: new           #2                  // class org/apache/dubbo/remoting/buffer/ChannelBufferOutputStream
       3: dup
       4: aload_2
       5: invokespecial #3                  // Method org/apache/dubbo/remoting/buffer/ChannelBufferOutputStream."<init>":(Lorg/apache/dubbo/remoting/buffer/ChannelBuffer;)V
       8: astore        4
      10: aload_0
      11: aload_1
      12: invokevirtual #4                  // Method getSerialization:(Lorg/apache/dubbo/remoting/Channel;)Lorg/apache/dubbo/common/serialize/Serialization;
      15: aload_1
      16: invokeinterface #5,  1            // InterfaceMethod org/apache/dubbo/remoting/Channel.getUrl:()Lorg/apache/dubbo/common/URL;
      21: aload         4
      23: invokeinterface #6,  3            // InterfaceMethod org/apache/dubbo/common/serialize/Serialization.serialize:(Lorg/apache/dubbo/common/URL;Ljava/io/OutputStream;)Lorg/apache/dubbo/common/serialize/ObjectOutput;
      28: astore        5
      30: aload_0
      31: aload_1
      32: aload         5
      34: aload_3
      35: invokevirtual #7                  // Method encodeData:(Lorg/apache/dubbo/remoting/Channel;Lorg/apache/dubbo/common/serialize/ObjectOutput;Ljava/lang/Object;)V
      38: aload         5
      40: invokeinterface #8,  1            // InterfaceMethod org/apache/dubbo/common/serialize/ObjectOutput.flushBuffer:()V
      45: aload         5
      47: instanceof    #9                  // class org/apache/dubbo/common/serialize/Cleanable
      50: ifeq          63
      53: aload         5
      55: checkcast     #9                  // class org/apache/dubbo/common/serialize/Cleanable
      58: invokeinterface #10,  1           // InterfaceMethod org/apache/dubbo/common/serialize/Cleanable.cleanup:()V
      63: return

  public java.lang.Object decode(org.apache.dubbo.remoting.Channel, org.apache.dubbo.remoting.buffer.ChannelBuffer) throws java.io.IOException;
    Code:
       0: new           #11                 // class org/apache/dubbo/remoting/buffer/ChannelBufferInputStream
       3: dup
       4: aload_2
       5: invokespecial #12                 // Method org/apache/dubbo/remoting/buffer/ChannelBufferInputStream."<init>":(Lorg/apache/dubbo/remoting/buffer/ChannelBuffer;)V
       8: astore_3
       9: aload_0
      10: aload_1
      11: invokevirtual #4                  // Method getSerialization:(Lorg/apache/dubbo/remoting/Channel;)Lorg/apache/dubbo/common/serialize/Serialization;
      14: aload_1
      15: invokeinterface #5,  1            // InterfaceMethod org/apache/dubbo/remoting/Channel.getUrl:()Lorg/apache/dubbo/common/URL;
      20: aload_3
      21: invokeinterface #13,  3           // InterfaceMethod org/apache/dubbo/common/serialize/Serialization.deserialize:(Lorg/apache/dubbo/common/URL;Ljava/io/InputStream;)Lorg/apache/dubbo/common/serialize/ObjectInput;
      26: astore        4
      28: aload_0
      29: aload_1
      30: aload         4
      32: invokevirtual #14                 // Method decodeData:(Lorg/apache/dubbo/remoting/Channel;Lorg/apache/dubbo/common/serialize/ObjectInput;)Ljava/lang/Object;
      35: astore        5
      37: aload         4
      39: instanceof    #9                  // class org/apache/dubbo/common/serialize/Cleanable
      42: ifeq          55
      45: aload         4
      47: checkcast     #9                  // class org/apache/dubbo/common/serialize/Cleanable
      50: invokeinterface #10,  1           // InterfaceMethod org/apache/dubbo/common/serialize/Cleanable.cleanup:()V
      55: aload         5
      57: areturn

  protected void encodeData(org.apache.dubbo.remoting.Channel, org.apache.dubbo.common.serialize.ObjectOutput, java.lang.Object) throws java.io.IOException;
    Code:
       0: aload_0
       1: aload_2
       2: aload_3
       3: invokevirtual #15                 // Method encodeData:(Lorg/apache/dubbo/common/serialize/ObjectOutput;Ljava/lang/Object;)V
       6: return

  protected java.lang.Object decodeData(org.apache.dubbo.remoting.Channel, org.apache.dubbo.common.serialize.ObjectInput) throws java.io.IOException;
    Code:
       0: aload_0
       1: aload_2
       2: invokevirtual #16                 // Method decodeData:(Lorg/apache/dubbo/common/serialize/ObjectInput;)Ljava/lang/Object;
       5: areturn

  protected void encodeData(org.apache.dubbo.common.serialize.ObjectOutput, java.lang.Object) throws java.io.IOException;
    Code:
       0: aload_1
       1: aload_2
       2: invokeinterface #17,  2           // InterfaceMethod org/apache/dubbo/common/serialize/ObjectOutput.writeObject:(Ljava/lang/Object;)V
       7: return

  protected java.lang.Object decodeData(org.apache.dubbo.common.serialize.ObjectInput) throws java.io.IOException;
    Code:
       0: aload_1
       1: invokeinterface #18,  1           // InterfaceMethod org/apache/dubbo/common/serialize/ObjectInput.readObject:()Ljava/lang/Object;
       6: areturn
       7: astore_2
       8: new           #20                 // class java/io/IOException
      11: dup
      12: new           #21                 // class java/lang/StringBuilder
      15: dup
      16: invokespecial #22                 // Method java/lang/StringBuilder."<init>":()V
      19: ldc           #23                 // String ClassNotFoundException:
      21: invokevirtual #24                 // Method java/lang/StringBuilder.append:(Ljava/lang/String;)Ljava/lang/StringBuilder;
      24: aload_2
      25: invokestatic  #25                 // Method org/apache/dubbo/common/utils/StringUtils.toString:(Ljava/lang/Throwable;)Ljava/lang/String;
      28: invokevirtual #24                 // Method java/lang/StringBuilder.append:(Ljava/lang/String;)Ljava/lang/StringBuilder;
      31: invokevirtual #26                 // Method java/lang/StringBuilder.toString:()Ljava/lang/String;
      34: invokespecial #27                 // Method java/io/IOException."<init>":(Ljava/lang/String;)V
      37: athrow
    Exception table:
       from    to  target type
           0     6     7   Class java/lang/ClassNotFoundException
}
