Compiled from "ConnectionFactoryBuilder.java"
final class org.springframework.boot.r2dbc.ConnectionFactoryBuilder$PoolingAwareOptionsCapableWrapper extends org.springframework.boot.r2dbc.ConnectionFactoryBuilder$OptionsCapableWrapper {
  private final io.r2dbc.pool.PoolingConnectionFactoryProvider poolingProvider;

  org.springframework.boot.r2dbc.ConnectionFactoryBuilder$PoolingAwareOptionsCapableWrapper();
    Code:
       0: aload_0
       1: invokespecial #3                  // Method org/springframework/boot/r2dbc/ConnectionFactoryBuilder$OptionsCapableWrapper."<init>":()V
       4: aload_0
       5: new           #9                  // class io/r2dbc/pool/PoolingConnectionFactoryProvider
       8: dup
       9: invokespecial #11                 // Method io/r2dbc/pool/PoolingConnectionFactoryProvider."<init>":()V
      12: putfield      #12                 // Field poolingProvider:Lio/r2dbc/pool/PoolingConnectionFactoryProvider;
      15: return

  io.r2dbc.spi.ConnectionFactory buildAndWrap(io.r2dbc.spi.ConnectionFactoryOptions);
    Code:
       0: aload_0
       1: getfield      #12                 // Field poolingProvider:Lio/r2dbc/pool/PoolingConnectionFactoryProvider;
       4: aload_1
       5: invokevirtual #18                 // Method io/r2dbc/pool/PoolingConnectionFactoryProvider.supports:(Lio/r2dbc/spi/ConnectionFactoryOptions;)Z
       8: ifne          17
      11: aload_0
      12: aload_1
      13: invokespecial #22                 // Method org/springframework/boot/r2dbc/ConnectionFactoryBuilder$OptionsCapableWrapper.buildAndWrap:(Lio/r2dbc/spi/ConnectionFactoryOptions;)Lio/r2dbc/spi/ConnectionFactory;
      16: areturn
      17: aload_0
      18: aload_1
      19: invokevirtual #26                 // Method delegateFactoryOptions:(Lio/r2dbc/spi/ConnectionFactoryOptions;)Lio/r2dbc/spi/ConnectionFactoryOptions;
      22: astore_2
      23: aload_0
      24: aload_2
      25: invokespecial #22                 // Method org/springframework/boot/r2dbc/ConnectionFactoryBuilder$OptionsCapableWrapper.buildAndWrap:(Lio/r2dbc/spi/ConnectionFactoryOptions;)Lio/r2dbc/spi/ConnectionFactory;
      28: astore_3
      29: aload_0
      30: aload_2
      31: aload_3
      32: invokevirtual #30                 // Method connectionPoolConfiguration:(Lio/r2dbc/spi/ConnectionFactoryOptions;Lio/r2dbc/spi/ConnectionFactory;)Lio/r2dbc/pool/ConnectionPoolConfiguration;
      35: astore        4
      37: new           #34                 // class io/r2dbc/pool/ConnectionPool
      40: dup
      41: aload         4
      43: invokespecial #36                 // Method io/r2dbc/pool/ConnectionPool."<init>":(Lio/r2dbc/pool/ConnectionPoolConfiguration;)V
      46: areturn

  private io.r2dbc.spi.ConnectionFactoryOptions delegateFactoryOptions(io.r2dbc.spi.ConnectionFactoryOptions);
    Code:
       0: aload_0
       1: aload_1
       2: getstatic     #39                 // Field io/r2dbc/spi/ConnectionFactoryOptions.PROTOCOL:Lio/r2dbc/spi/Option;
       5: invokevirtual #45                 // Method io/r2dbc/spi/ConnectionFactoryOptions.getRequiredValue:(Lio/r2dbc/spi/Option;)Ljava/lang/Object;
       8: invokevirtual #49                 // Method toString:(Ljava/lang/Object;)Ljava/lang/String;
      11: astore_2
      12: aload_2
      13: invokevirtual #53                 // Method java/lang/String.trim:()Ljava/lang/String;
      16: invokevirtual #59                 // Method java/lang/String.length:()I
      19: ifne          43
      22: new           #63                 // class java/lang/IllegalArgumentException
      25: dup
      26: ldc           #65                 // String Protocol %s is not valid.
      28: iconst_1
      29: anewarray     #67                 // class java/lang/Object
      32: dup
      33: iconst_0
      34: aload_2
      35: aastore
      36: invokestatic  #69                 // Method java/lang/String.format:(Ljava/lang/String;[Ljava/lang/Object;)Ljava/lang/String;
      39: invokespecial #73                 // Method java/lang/IllegalArgumentException."<init>":(Ljava/lang/String;)V
      42: athrow
      43: aload_2
      44: ldc           #76                 // String :
      46: iconst_2
      47: invokevirtual #78                 // Method java/lang/String.split:(Ljava/lang/String;I)[Ljava/lang/String;
      50: astore_3
      51: aload_3
      52: iconst_0
      53: aaload
      54: astore        4
      56: aload_3
      57: arraylength
      58: iconst_2
      59: if_icmpeq     67
      62: ldc           #82                 // String
      64: goto          70
      67: aload_3
      68: iconst_1
      69: aaload
      70: astore        5
      72: invokestatic  #84                 // Method io/r2dbc/spi/ConnectionFactoryOptions.builder:()Lio/r2dbc/spi/ConnectionFactoryOptions$Builder;
      75: aload_1
      76: invokevirtual #88                 // Method io/r2dbc/spi/ConnectionFactoryOptions$Builder.from:(Lio/r2dbc/spi/ConnectionFactoryOptions;)Lio/r2dbc/spi/ConnectionFactoryOptions$Builder;
      79: getstatic     #94                 // Field io/r2dbc/spi/ConnectionFactoryOptions.DRIVER:Lio/r2dbc/spi/Option;
      82: aload         4
      84: invokevirtual #97                 // Method io/r2dbc/spi/ConnectionFactoryOptions$Builder.option:(Lio/r2dbc/spi/Option;Ljava/lang/Object;)Lio/r2dbc/spi/ConnectionFactoryOptions$Builder;
      87: getstatic     #39                 // Field io/r2dbc/spi/ConnectionFactoryOptions.PROTOCOL:Lio/r2dbc/spi/Option;
      90: aload         5
      92: invokevirtual #97                 // Method io/r2dbc/spi/ConnectionFactoryOptions$Builder.option:(Lio/r2dbc/spi/Option;Ljava/lang/Object;)Lio/r2dbc/spi/ConnectionFactoryOptions$Builder;
      95: invokevirtual #101                // Method io/r2dbc/spi/ConnectionFactoryOptions$Builder.build:()Lio/r2dbc/spi/ConnectionFactoryOptions;
      98: areturn

  io.r2dbc.pool.ConnectionPoolConfiguration connectionPoolConfiguration(io.r2dbc.spi.ConnectionFactoryOptions, io.r2dbc.spi.ConnectionFactory);
    Code:
       0: aload_2
       1: invokestatic  #105                // Method io/r2dbc/pool/ConnectionPoolConfiguration.builder:(Lio/r2dbc/spi/ConnectionFactory;)Lio/r2dbc/pool/ConnectionPoolConfiguration$Builder;
       4: astore_3
       5: invokestatic  #110                // Method org/springframework/boot/context/properties/PropertyMapper.get:()Lorg/springframework/boot/context/properties/PropertyMapper;
       8: invokevirtual #116                // Method org/springframework/boot/context/properties/PropertyMapper.alwaysApplyingWhenNonNull:()Lorg/springframework/boot/context/properties/PropertyMapper;
      11: astore        4
      13: aload         4
      15: aload_1
      16: getstatic     #119                // Field io/r2dbc/pool/PoolingConnectionFactoryProvider.BACKGROUND_EVICTION_INTERVAL:Lio/r2dbc/spi/Option;
      19: invokevirtual #122                // Method io/r2dbc/spi/ConnectionFactoryOptions.getValue:(Lio/r2dbc/spi/Option;)Ljava/lang/Object;
      22: invokevirtual #125                // Method org/springframework/boot/context/properties/PropertyMapper.from:(Ljava/lang/Object;)Lorg/springframework/boot/context/properties/PropertyMapper$Source;
      25: aload_0
      26: invokedynamic #128,  0            // InvokeDynamic #0:apply:(Lorg/springframework/boot/r2dbc/ConnectionFactoryBuilder$PoolingAwareOptionsCapableWrapper;)Ljava/util/function/Function;
      31: invokevirtual #132                // Method org/springframework/boot/context/properties/PropertyMapper$Source.as:(Ljava/util/function/Function;)Lorg/springframework/boot/context/properties/PropertyMapper$Source;
      34: aload_3
      35: dup
      36: invokestatic  #138                // Method java/util/Objects.requireNonNull:(Ljava/lang/Object;)Ljava/lang/Object;
      39: pop
      40: invokedynamic #144,  0            // InvokeDynamic #1:accept:(Lio/r2dbc/pool/ConnectionPoolConfiguration$Builder;)Ljava/util/function/Consumer;
      45: invokevirtual #148                // Method org/springframework/boot/context/properties/PropertyMapper$Source.to:(Ljava/util/function/Consumer;)V
      48: aload         4
      50: aload_1
      51: getstatic     #152                // Field io/r2dbc/pool/PoolingConnectionFactoryProvider.INITIAL_SIZE:Lio/r2dbc/spi/Option;
      54: invokevirtual #122                // Method io/r2dbc/spi/ConnectionFactoryOptions.getValue:(Lio/r2dbc/spi/Option;)Ljava/lang/Object;
      57: invokevirtual #125                // Method org/springframework/boot/context/properties/PropertyMapper.from:(Ljava/lang/Object;)Lorg/springframework/boot/context/properties/PropertyMapper$Source;
      60: aload_0
      61: invokedynamic #155,  0            // InvokeDynamic #2:apply:(Lorg/springframework/boot/r2dbc/ConnectionFactoryBuilder$PoolingAwareOptionsCapableWrapper;)Ljava/util/function/Function;
      66: invokevirtual #132                // Method org/springframework/boot/context/properties/PropertyMapper$Source.as:(Ljava/util/function/Function;)Lorg/springframework/boot/context/properties/PropertyMapper$Source;
      69: aload_3
      70: dup
      71: invokestatic  #138                // Method java/util/Objects.requireNonNull:(Ljava/lang/Object;)Ljava/lang/Object;
      74: pop
      75: invokedynamic #156,  0            // InvokeDynamic #3:accept:(Lio/r2dbc/pool/ConnectionPoolConfiguration$Builder;)Ljava/util/function/Consumer;
      80: invokevirtual #148                // Method org/springframework/boot/context/properties/PropertyMapper$Source.to:(Ljava/util/function/Consumer;)V
      83: aload         4
      85: aload_1
      86: getstatic     #157                // Field io/r2dbc/pool/PoolingConnectionFactoryProvider.MAX_SIZE:Lio/r2dbc/spi/Option;
      89: invokevirtual #122                // Method io/r2dbc/spi/ConnectionFactoryOptions.getValue:(Lio/r2dbc/spi/Option;)Ljava/lang/Object;
      92: invokevirtual #125                // Method org/springframework/boot/context/properties/PropertyMapper.from:(Ljava/lang/Object;)Lorg/springframework/boot/context/properties/PropertyMapper$Source;
      95: aload_0
      96: invokedynamic #155,  0            // InvokeDynamic #2:apply:(Lorg/springframework/boot/r2dbc/ConnectionFactoryBuilder$PoolingAwareOptionsCapableWrapper;)Ljava/util/function/Function;
     101: invokevirtual #132                // Method org/springframework/boot/context/properties/PropertyMapper$Source.as:(Ljava/util/function/Function;)Lorg/springframework/boot/context/properties/PropertyMapper$Source;
     104: aload_3
     105: dup
     106: invokestatic  #138                // Method java/util/Objects.requireNonNull:(Ljava/lang/Object;)Ljava/lang/Object;
     109: pop
     110: invokedynamic #160,  0            // InvokeDynamic #4:accept:(Lio/r2dbc/pool/ConnectionPoolConfiguration$Builder;)Ljava/util/function/Consumer;
     115: invokevirtual #148                // Method org/springframework/boot/context/properties/PropertyMapper$Source.to:(Ljava/util/function/Consumer;)V
     118: aload         4
     120: aload_1
     121: getstatic     #161                // Field io/r2dbc/pool/PoolingConnectionFactoryProvider.ACQUIRE_RETRY:Lio/r2dbc/spi/Option;
     124: invokevirtual #122                // Method io/r2dbc/spi/ConnectionFactoryOptions.getValue:(Lio/r2dbc/spi/Option;)Ljava/lang/Object;
     127: invokevirtual #125                // Method org/springframework/boot/context/properties/PropertyMapper.from:(Ljava/lang/Object;)Lorg/springframework/boot/context/properties/PropertyMapper$Source;
     130: aload_0
     131: invokedynamic #155,  0            // InvokeDynamic #2:apply:(Lorg/springframework/boot/r2dbc/ConnectionFactoryBuilder$PoolingAwareOptionsCapableWrapper;)Ljava/util/function/Function;
     136: invokevirtual #132                // Method org/springframework/boot/context/properties/PropertyMapper$Source.as:(Ljava/util/function/Function;)Lorg/springframework/boot/context/properties/PropertyMapper$Source;
     139: aload_3
     140: dup
     141: invokestatic  #138                // Method java/util/Objects.requireNonNull:(Ljava/lang/Object;)Ljava/lang/Object;
     144: pop
     145: invokedynamic #164,  0            // InvokeDynamic #5:accept:(Lio/r2dbc/pool/ConnectionPoolConfiguration$Builder;)Ljava/util/function/Consumer;
     150: invokevirtual #148                // Method org/springframework/boot/context/properties/PropertyMapper$Source.to:(Ljava/util/function/Consumer;)V
     153: aload         4
     155: aload_1
     156: getstatic     #165                // Field io/r2dbc/pool/PoolingConnectionFactoryProvider.MAX_LIFE_TIME:Lio/r2dbc/spi/Option;
     159: invokevirtual #122                // Method io/r2dbc/spi/ConnectionFactoryOptions.getValue:(Lio/r2dbc/spi/Option;)Ljava/lang/Object;
     162: invokevirtual #125                // Method org/springframework/boot/context/properties/PropertyMapper.from:(Ljava/lang/Object;)Lorg/springframework/boot/context/properties/PropertyMapper$Source;
     165: aload_0
     166: invokedynamic #128,  0            // InvokeDynamic #0:apply:(Lorg/springframework/boot/r2dbc/ConnectionFactoryBuilder$PoolingAwareOptionsCapableWrapper;)Ljava/util/function/Function;
     171: invokevirtual #132                // Method org/springframework/boot/context/properties/PropertyMapper$Source.as:(Ljava/util/function/Function;)Lorg/springframework/boot/context/properties/PropertyMapper$Source;
     174: aload_3
     175: dup
     176: invokestatic  #138                // Method java/util/Objects.requireNonNull:(Ljava/lang/Object;)Ljava/lang/Object;
     179: pop
     180: invokedynamic #168,  0            // InvokeDynamic #6:accept:(Lio/r2dbc/pool/ConnectionPoolConfiguration$Builder;)Ljava/util/function/Consumer;
     185: invokevirtual #148                // Method org/springframework/boot/context/properties/PropertyMapper$Source.to:(Ljava/util/function/Consumer;)V
     188: aload         4
     190: aload_1
     191: getstatic     #169                // Field io/r2dbc/pool/PoolingConnectionFactoryProvider.MAX_ACQUIRE_TIME:Lio/r2dbc/spi/Option;
     194: invokevirtual #122                // Method io/r2dbc/spi/ConnectionFactoryOptions.getValue:(Lio/r2dbc/spi/Option;)Ljava/lang/Object;
     197: invokevirtual #125                // Method org/springframework/boot/context/properties/PropertyMapper.from:(Ljava/lang/Object;)Lorg/springframework/boot/context/properties/PropertyMapper$Source;
     200: aload_0
     201: invokedynamic #128,  0            // InvokeDynamic #0:apply:(Lorg/springframework/boot/r2dbc/ConnectionFactoryBuilder$PoolingAwareOptionsCapableWrapper;)Ljava/util/function/Function;
     206: invokevirtual #132                // Method org/springframework/boot/context/properties/PropertyMapper$Source.as:(Ljava/util/function/Function;)Lorg/springframework/boot/context/properties/PropertyMapper$Source;
     209: aload_3
     210: dup
     211: invokestatic  #138                // Method java/util/Objects.requireNonNull:(Ljava/lang/Object;)Ljava/lang/Object;
     214: pop
     215: invokedynamic #172,  0            // InvokeDynamic #7:accept:(Lio/r2dbc/pool/ConnectionPoolConfiguration$Builder;)Ljava/util/function/Consumer;
     220: invokevirtual #148                // Method org/springframework/boot/context/properties/PropertyMapper$Source.to:(Ljava/util/function/Consumer;)V
     223: aload         4
     225: aload_1
     226: getstatic     #173                // Field io/r2dbc/pool/PoolingConnectionFactoryProvider.MAX_IDLE_TIME:Lio/r2dbc/spi/Option;
     229: invokevirtual #122                // Method io/r2dbc/spi/ConnectionFactoryOptions.getValue:(Lio/r2dbc/spi/Option;)Ljava/lang/Object;
     232: invokevirtual #125                // Method org/springframework/boot/context/properties/PropertyMapper.from:(Ljava/lang/Object;)Lorg/springframework/boot/context/properties/PropertyMapper$Source;
     235: aload_0
     236: invokedynamic #128,  0            // InvokeDynamic #0:apply:(Lorg/springframework/boot/r2dbc/ConnectionFactoryBuilder$PoolingAwareOptionsCapableWrapper;)Ljava/util/function/Function;
     241: invokevirtual #132                // Method org/springframework/boot/context/properties/PropertyMapper$Source.as:(Ljava/util/function/Function;)Lorg/springframework/boot/context/properties/PropertyMapper$Source;
     244: aload_3
     245: dup
     246: invokestatic  #138                // Method java/util/Objects.requireNonNull:(Ljava/lang/Object;)Ljava/lang/Object;
     249: pop
     250: invokedynamic #176,  0            // InvokeDynamic #8:accept:(Lio/r2dbc/pool/ConnectionPoolConfiguration$Builder;)Ljava/util/function/Consumer;
     255: invokevirtual #148                // Method org/springframework/boot/context/properties/PropertyMapper$Source.to:(Ljava/util/function/Consumer;)V
     258: aload         4
     260: aload_1
     261: getstatic     #177                // Field io/r2dbc/pool/PoolingConnectionFactoryProvider.MAX_CREATE_CONNECTION_TIME:Lio/r2dbc/spi/Option;
     264: invokevirtual #122                // Method io/r2dbc/spi/ConnectionFactoryOptions.getValue:(Lio/r2dbc/spi/Option;)Ljava/lang/Object;
     267: invokevirtual #125                // Method org/springframework/boot/context/properties/PropertyMapper.from:(Ljava/lang/Object;)Lorg/springframework/boot/context/properties/PropertyMapper$Source;
     270: aload_0
     271: invokedynamic #128,  0            // InvokeDynamic #0:apply:(Lorg/springframework/boot/r2dbc/ConnectionFactoryBuilder$PoolingAwareOptionsCapableWrapper;)Ljava/util/function/Function;
     276: invokevirtual #132                // Method org/springframework/boot/context/properties/PropertyMapper$Source.as:(Ljava/util/function/Function;)Lorg/springframework/boot/context/properties/PropertyMapper$Source;
     279: aload_3
     280: dup
     281: invokestatic  #138                // Method java/util/Objects.requireNonNull:(Ljava/lang/Object;)Ljava/lang/Object;
     284: pop
     285: invokedynamic #180,  0            // InvokeDynamic #9:accept:(Lio/r2dbc/pool/ConnectionPoolConfiguration$Builder;)Ljava/util/function/Consumer;
     290: invokevirtual #148                // Method org/springframework/boot/context/properties/PropertyMapper$Source.to:(Ljava/util/function/Consumer;)V
     293: aload         4
     295: aload_1
     296: getstatic     #181                // Field io/r2dbc/pool/PoolingConnectionFactoryProvider.MAX_VALIDATION_TIME:Lio/r2dbc/spi/Option;
     299: invokevirtual #122                // Method io/r2dbc/spi/ConnectionFactoryOptions.getValue:(Lio/r2dbc/spi/Option;)Ljava/lang/Object;
     302: invokevirtual #125                // Method org/springframework/boot/context/properties/PropertyMapper.from:(Ljava/lang/Object;)Lorg/springframework/boot/context/properties/PropertyMapper$Source;
     305: aload_0
     306: invokedynamic #128,  0            // InvokeDynamic #0:apply:(Lorg/springframework/boot/r2dbc/ConnectionFactoryBuilder$PoolingAwareOptionsCapableWrapper;)Ljava/util/function/Function;
     311: invokevirtual #132                // Method org/springframework/boot/context/properties/PropertyMapper$Source.as:(Ljava/util/function/Function;)Lorg/springframework/boot/context/properties/PropertyMapper$Source;
     314: aload_3
     315: dup
     316: invokestatic  #138                // Method java/util/Objects.requireNonNull:(Ljava/lang/Object;)Ljava/lang/Object;
     319: pop
     320: invokedynamic #184,  0            // InvokeDynamic #10:accept:(Lio/r2dbc/pool/ConnectionPoolConfiguration$Builder;)Ljava/util/function/Consumer;
     325: invokevirtual #148                // Method org/springframework/boot/context/properties/PropertyMapper$Source.to:(Ljava/util/function/Consumer;)V
     328: aload         4
     330: aload_1
     331: getstatic     #185                // Field io/r2dbc/pool/PoolingConnectionFactoryProvider.MIN_IDLE:Lio/r2dbc/spi/Option;
     334: invokevirtual #122                // Method io/r2dbc/spi/ConnectionFactoryOptions.getValue:(Lio/r2dbc/spi/Option;)Ljava/lang/Object;
     337: invokevirtual #125                // Method org/springframework/boot/context/properties/PropertyMapper.from:(Ljava/lang/Object;)Lorg/springframework/boot/context/properties/PropertyMapper$Source;
     340: aload_0
     341: invokedynamic #155,  0            // InvokeDynamic #2:apply:(Lorg/springframework/boot/r2dbc/ConnectionFactoryBuilder$PoolingAwareOptionsCapableWrapper;)Ljava/util/function/Function;
     346: invokevirtual #132                // Method org/springframework/boot/context/properties/PropertyMapper$Source.as:(Ljava/util/function/Function;)Lorg/springframework/boot/context/properties/PropertyMapper$Source;
     349: aload_3
     350: dup
     351: invokestatic  #138                // Method java/util/Objects.requireNonNull:(Ljava/lang/Object;)Ljava/lang/Object;
     354: pop
     355: invokedynamic #188,  0            // InvokeDynamic #11:accept:(Lio/r2dbc/pool/ConnectionPoolConfiguration$Builder;)Ljava/util/function/Consumer;
     360: invokevirtual #148                // Method org/springframework/boot/context/properties/PropertyMapper$Source.to:(Ljava/util/function/Consumer;)V
     363: aload         4
     365: aload_1
     366: getstatic     #189                // Field io/r2dbc/pool/PoolingConnectionFactoryProvider.POOL_NAME:Lio/r2dbc/spi/Option;
     369: invokevirtual #122                // Method io/r2dbc/spi/ConnectionFactoryOptions.getValue:(Lio/r2dbc/spi/Option;)Ljava/lang/Object;
     372: invokevirtual #125                // Method org/springframework/boot/context/properties/PropertyMapper.from:(Ljava/lang/Object;)Lorg/springframework/boot/context/properties/PropertyMapper$Source;
     375: aload_0
     376: invokedynamic #192,  0            // InvokeDynamic #12:apply:(Lorg/springframework/boot/r2dbc/ConnectionFactoryBuilder$PoolingAwareOptionsCapableWrapper;)Ljava/util/function/Function;
     381: invokevirtual #132                // Method org/springframework/boot/context/properties/PropertyMapper$Source.as:(Ljava/util/function/Function;)Lorg/springframework/boot/context/properties/PropertyMapper$Source;
     384: aload_3
     385: dup
     386: invokestatic  #138                // Method java/util/Objects.requireNonNull:(Ljava/lang/Object;)Ljava/lang/Object;
     389: pop
     390: invokedynamic #193,  0            // InvokeDynamic #13:accept:(Lio/r2dbc/pool/ConnectionPoolConfiguration$Builder;)Ljava/util/function/Consumer;
     395: invokevirtual #148                // Method org/springframework/boot/context/properties/PropertyMapper$Source.to:(Ljava/util/function/Consumer;)V
     398: aload         4
     400: aload_1
     401: getstatic     #194                // Field io/r2dbc/pool/PoolingConnectionFactoryProvider.PRE_RELEASE:Lio/r2dbc/spi/Option;
     404: invokevirtual #122                // Method io/r2dbc/spi/ConnectionFactoryOptions.getValue:(Lio/r2dbc/spi/Option;)Ljava/lang/Object;
     407: invokevirtual #125                // Method org/springframework/boot/context/properties/PropertyMapper.from:(Ljava/lang/Object;)Lorg/springframework/boot/context/properties/PropertyMapper$Source;
     410: aload_3
     411: invokedynamic #197,  0            // InvokeDynamic #14:accept:(Lio/r2dbc/pool/ConnectionPoolConfiguration$Builder;)Ljava/util/function/Consumer;
     416: invokevirtual #148                // Method org/springframework/boot/context/properties/PropertyMapper$Source.to:(Ljava/util/function/Consumer;)V
     419: aload         4
     421: aload_1
     422: getstatic     #198                // Field io/r2dbc/pool/PoolingConnectionFactoryProvider.POST_ALLOCATE:Lio/r2dbc/spi/Option;
     425: invokevirtual #122                // Method io/r2dbc/spi/ConnectionFactoryOptions.getValue:(Lio/r2dbc/spi/Option;)Ljava/lang/Object;
     428: invokevirtual #125                // Method org/springframework/boot/context/properties/PropertyMapper.from:(Ljava/lang/Object;)Lorg/springframework/boot/context/properties/PropertyMapper$Source;
     431: aload_3
     432: invokedynamic #201,  0            // InvokeDynamic #15:accept:(Lio/r2dbc/pool/ConnectionPoolConfiguration$Builder;)Ljava/util/function/Consumer;
     437: invokevirtual #148                // Method org/springframework/boot/context/properties/PropertyMapper$Source.to:(Ljava/util/function/Consumer;)V
     440: aload         4
     442: aload_1
     443: getstatic     #202                // Field io/r2dbc/pool/PoolingConnectionFactoryProvider.REGISTER_JMX:Lio/r2dbc/spi/Option;
     446: invokevirtual #122                // Method io/r2dbc/spi/ConnectionFactoryOptions.getValue:(Lio/r2dbc/spi/Option;)Ljava/lang/Object;
     449: invokevirtual #125                // Method org/springframework/boot/context/properties/PropertyMapper.from:(Ljava/lang/Object;)Lorg/springframework/boot/context/properties/PropertyMapper$Source;
     452: aload_0
     453: invokedynamic #205,  0            // InvokeDynamic #16:apply:(Lorg/springframework/boot/r2dbc/ConnectionFactoryBuilder$PoolingAwareOptionsCapableWrapper;)Ljava/util/function/Function;
     458: invokevirtual #132                // Method org/springframework/boot/context/properties/PropertyMapper$Source.as:(Ljava/util/function/Function;)Lorg/springframework/boot/context/properties/PropertyMapper$Source;
     461: aload_3
     462: dup
     463: invokestatic  #138                // Method java/util/Objects.requireNonNull:(Ljava/lang/Object;)Ljava/lang/Object;
     466: pop
     467: invokedynamic #206,  0            // InvokeDynamic #17:accept:(Lio/r2dbc/pool/ConnectionPoolConfiguration$Builder;)Ljava/util/function/Consumer;
     472: invokevirtual #148                // Method org/springframework/boot/context/properties/PropertyMapper$Source.to:(Ljava/util/function/Consumer;)V
     475: aload         4
     477: aload_1
     478: getstatic     #207                // Field io/r2dbc/pool/PoolingConnectionFactoryProvider.VALIDATION_QUERY:Lio/r2dbc/spi/Option;
     481: invokevirtual #122                // Method io/r2dbc/spi/ConnectionFactoryOptions.getValue:(Lio/r2dbc/spi/Option;)Ljava/lang/Object;
     484: invokevirtual #125                // Method org/springframework/boot/context/properties/PropertyMapper.from:(Ljava/lang/Object;)Lorg/springframework/boot/context/properties/PropertyMapper$Source;
     487: aload_0
     488: invokedynamic #192,  0            // InvokeDynamic #12:apply:(Lorg/springframework/boot/r2dbc/ConnectionFactoryBuilder$PoolingAwareOptionsCapableWrapper;)Ljava/util/function/Function;
     493: invokevirtual #132                // Method org/springframework/boot/context/properties/PropertyMapper$Source.as:(Ljava/util/function/Function;)Lorg/springframework/boot/context/properties/PropertyMapper$Source;
     496: aload_3
     497: dup
     498: invokestatic  #138                // Method java/util/Objects.requireNonNull:(Ljava/lang/Object;)Ljava/lang/Object;
     501: pop
     502: invokedynamic #210,  0            // InvokeDynamic #18:accept:(Lio/r2dbc/pool/ConnectionPoolConfiguration$Builder;)Ljava/util/function/Consumer;
     507: invokevirtual #148                // Method org/springframework/boot/context/properties/PropertyMapper$Source.to:(Ljava/util/function/Consumer;)V
     510: aload         4
     512: aload_1
     513: getstatic     #211                // Field io/r2dbc/pool/PoolingConnectionFactoryProvider.VALIDATION_DEPTH:Lio/r2dbc/spi/Option;
     516: invokevirtual #122                // Method io/r2dbc/spi/ConnectionFactoryOptions.getValue:(Lio/r2dbc/spi/Option;)Ljava/lang/Object;
     519: invokevirtual #125                // Method org/springframework/boot/context/properties/PropertyMapper.from:(Ljava/lang/Object;)Lorg/springframework/boot/context/properties/PropertyMapper$Source;
     522: aload_0
     523: invokedynamic #214,  0            // InvokeDynamic #19:apply:(Lorg/springframework/boot/r2dbc/ConnectionFactoryBuilder$PoolingAwareOptionsCapableWrapper;)Ljava/util/function/Function;
     528: invokevirtual #132                // Method org/springframework/boot/context/properties/PropertyMapper$Source.as:(Ljava/util/function/Function;)Lorg/springframework/boot/context/properties/PropertyMapper$Source;
     531: aload_3
     532: dup
     533: invokestatic  #138                // Method java/util/Objects.requireNonNull:(Ljava/lang/Object;)Ljava/lang/Object;
     536: pop
     537: invokedynamic #215,  0            // InvokeDynamic #20:accept:(Lio/r2dbc/pool/ConnectionPoolConfiguration$Builder;)Ljava/util/function/Consumer;
     542: invokevirtual #148                // Method org/springframework/boot/context/properties/PropertyMapper$Source.to:(Ljava/util/function/Consumer;)V
     545: aload_3
     546: invokevirtual #216                // Method io/r2dbc/pool/ConnectionPoolConfiguration$Builder.build:()Lio/r2dbc/pool/ConnectionPoolConfiguration;
     549: areturn

  private java.lang.String toString(java.lang.Object);
    Code:
       0: aload_0
       1: ldc           #54                 // class java/lang/String
       3: aload_1
       4: invokedynamic #221,  0            // InvokeDynamic #21:apply:()Ljava/util/function/Function;
       9: invokevirtual #224                // Method toType:(Ljava/lang/Class;Ljava/lang/Object;Ljava/util/function/Function;)Ljava/lang/Object;
      12: checkcast     #54                 // class java/lang/String
      15: areturn

  private java.lang.Integer toInteger(java.lang.Object);
    Code:
       0: aload_0
       1: ldc           #228                // class java/lang/Integer
       3: aload_1
       4: invokedynamic #230,  0            // InvokeDynamic #22:apply:()Ljava/util/function/Function;
       9: invokevirtual #224                // Method toType:(Ljava/lang/Class;Ljava/lang/Object;Ljava/util/function/Function;)Ljava/lang/Object;
      12: checkcast     #228                // class java/lang/Integer
      15: areturn

  private java.time.Duration toDuration(java.lang.Object);
    Code:
       0: aload_0
       1: ldc           #231                // class java/time/Duration
       3: aload_1
       4: invokedynamic #233,  0            // InvokeDynamic #23:apply:()Ljava/util/function/Function;
       9: invokevirtual #224                // Method toType:(Ljava/lang/Class;Ljava/lang/Object;Ljava/util/function/Function;)Ljava/lang/Object;
      12: checkcast     #231                // class java/time/Duration
      15: areturn

  private java.lang.Boolean toBoolean(java.lang.Object);
    Code:
       0: aload_0
       1: ldc           #234                // class java/lang/Boolean
       3: aload_1
       4: invokedynamic #236,  0            // InvokeDynamic #24:apply:()Ljava/util/function/Function;
       9: invokevirtual #224                // Method toType:(Ljava/lang/Class;Ljava/lang/Object;Ljava/util/function/Function;)Ljava/lang/Object;
      12: checkcast     #234                // class java/lang/Boolean
      15: areturn

  private io.r2dbc.spi.ValidationDepth toValidationDepth(java.lang.Object);
    Code:
       0: aload_0
       1: ldc           #237                // class io/r2dbc/spi/ValidationDepth
       3: aload_1
       4: invokedynamic #239,  0            // InvokeDynamic #25:apply:()Ljava/util/function/Function;
       9: invokevirtual #224                // Method toType:(Ljava/lang/Class;Ljava/lang/Object;Ljava/util/function/Function;)Ljava/lang/Object;
      12: checkcast     #237                // class io/r2dbc/spi/ValidationDepth
      15: areturn

  private <T> T toType(java.lang.Class<T>, java.lang.Object, java.util.function.Function<java.lang.String, T>);
    Code:
       0: aload_1
       1: aload_2
       2: invokevirtual #240                // Method java/lang/Class.isInstance:(Ljava/lang/Object;)Z
       5: ifeq          14
       8: aload_1
       9: aload_2
      10: invokevirtual #246                // Method java/lang/Class.cast:(Ljava/lang/Object;)Ljava/lang/Object;
      13: areturn
      14: aload_2
      15: instanceof    #54                 // class java/lang/String
      18: ifeq          36
      21: aload_2
      22: checkcast     #54                 // class java/lang/String
      25: astore        4
      27: aload_3
      28: aload         4
      30: invokeinterface #249,  2          // InterfaceMethod java/util/function/Function.apply:(Ljava/lang/Object;)Ljava/lang/Object;
      35: areturn
      36: new           #63                 // class java/lang/IllegalArgumentException
      39: dup
      40: aload_2
      41: aload_1
      42: invokevirtual #253                // Method java/lang/Class.getName:()Ljava/lang/String;
      45: invokedynamic #256,  0            // InvokeDynamic #26:makeConcatWithConstants:(Ljava/lang/Object;Ljava/lang/String;)Ljava/lang/String;
      50: invokespecial #73                 // Method java/lang/IllegalArgumentException."<init>":(Ljava/lang/String;)V
      53: athrow

  private static io.r2dbc.spi.ValidationDepth lambda$toValidationDepth$2(java.lang.String);
    Code:
       0: aload_0
       1: getstatic     #260                // Field java/util/Locale.ENGLISH:Ljava/util/Locale;
       4: invokevirtual #266                // Method java/lang/String.toUpperCase:(Ljava/util/Locale;)Ljava/lang/String;
       7: invokestatic  #270                // Method io/r2dbc/spi/ValidationDepth.valueOf:(Ljava/lang/String;)Lio/r2dbc/spi/ValidationDepth;
      10: areturn

  private static void lambda$connectionPoolConfiguration$1(io.r2dbc.pool.ConnectionPoolConfiguration$Builder, java.lang.Object);
    Code:
       0: aload_0
       1: aload_1
       2: checkcast     #250                // class java/util/function/Function
       5: invokevirtual #274                // Method io/r2dbc/pool/ConnectionPoolConfiguration$Builder.postAllocate:(Ljava/util/function/Function;)Lio/r2dbc/pool/ConnectionPoolConfiguration$Builder;
       8: pop
       9: return

  private static void lambda$connectionPoolConfiguration$0(io.r2dbc.pool.ConnectionPoolConfiguration$Builder, java.lang.Object);
    Code:
       0: aload_0
       1: aload_1
       2: checkcast     #250                // class java/util/function/Function
       5: invokevirtual #278                // Method io/r2dbc/pool/ConnectionPoolConfiguration$Builder.preRelease:(Ljava/util/function/Function;)Lio/r2dbc/pool/ConnectionPoolConfiguration$Builder;
       8: pop
       9: return
}
