Compiled from "ConnectionFactoryBuilder.java"
class org.springframework.boot.r2dbc.ConnectionFactoryBuilder$OptionsCapableWrapper {
  private org.springframework.boot.r2dbc.ConnectionFactoryBuilder$OptionsCapableWrapper();
    Code:
       0: aload_0
       1: invokespecial #1                  // Method java/lang/Object."<init>":()V
       4: return

  io.r2dbc.spi.ConnectionFactory buildAndWrap(io.r2dbc.spi.ConnectionFactoryOptions);
    Code:
       0: aload_1
       1: invokestatic  #7                  // Method io/r2dbc/spi/ConnectionFactories.get:(Lio/r2dbc/spi/ConnectionFactoryOptions;)Lio/r2dbc/spi/ConnectionFactory;
       4: astore_2
       5: new           #13                 // class org/springframework/boot/r2dbc/OptionsCapableConnectionFactory
       8: dup
       9: aload_1
      10: aload_2
      11: invokespecial #15                 // Method org/springframework/boot/r2dbc/OptionsCapableConnectionFactory."<init>":(Lio/r2dbc/spi/ConnectionFactoryOptions;Lio/r2dbc/spi/ConnectionFactory;)V
      14: areturn
}
