Compiled from "ConnectionFactoryBuilder.java"
public final class org.springframework.boot.r2dbc.ConnectionFactoryBuilder {
  private static final org.springframework.boot.r2dbc.ConnectionFactoryBuilder$OptionsCapableWrapper optionsCapableWrapper;

  private static final java.lang.String COLON;

  private final io.r2dbc.spi.ConnectionFactoryOptions$Builder optionsBuilder;

  private org.springframework.boot.r2dbc.ConnectionFactoryBuilder(io.r2dbc.spi.ConnectionFactoryOptions$Builder);
    Code:
       0: aload_0
       1: invokespecial #1                  // Method java/lang/Object."<init>":()V
       4: aload_0
       5: aload_1
       6: putfield      #7                  // Field optionsBuilder:Lio/r2dbc/spi/ConnectionFactoryOptions$Builder;
       9: return

  public static org.springframework.boot.r2dbc.ConnectionFactoryBuilder withUrl(java.lang.String);
    Code:
       0: aload_0
       1: invokedynamic #13,  0             // InvokeDynamic #0:get:()Ljava/util/function/Supplier;
       6: invokestatic  #17                 // Method org/springframework/util/Assert.hasText:(Ljava/lang/String;Ljava/util/function/Supplier;)V
       9: aload_0
      10: invokestatic  #23                 // Method io/r2dbc/spi/ConnectionFactoryOptions.parse:(Ljava/lang/CharSequence;)Lio/r2dbc/spi/ConnectionFactoryOptions;
      13: invokevirtual #29                 // Method io/r2dbc/spi/ConnectionFactoryOptions.mutate:()Lio/r2dbc/spi/ConnectionFactoryOptions$Builder;
      16: invokestatic  #33                 // Method withOptions:(Lio/r2dbc/spi/ConnectionFactoryOptions$Builder;)Lorg/springframework/boot/r2dbc/ConnectionFactoryBuilder;
      19: areturn

  public static org.springframework.boot.r2dbc.ConnectionFactoryBuilder withOptions(io.r2dbc.spi.ConnectionFactoryOptions$Builder);
    Code:
       0: new           #8                  // class org/springframework/boot/r2dbc/ConnectionFactoryBuilder
       3: dup
       4: aload_0
       5: invokespecial #37                 // Method "<init>":(Lio/r2dbc/spi/ConnectionFactoryOptions$Builder;)V
       8: areturn

  public static org.springframework.boot.r2dbc.ConnectionFactoryBuilder derivedFrom(io.r2dbc.spi.ConnectionFactory);
    Code:
       0: aload_0
       1: invokestatic  #40                 // Method extractOptionsIfPossible:(Lio/r2dbc/spi/ConnectionFactory;)Lio/r2dbc/spi/ConnectionFactoryOptions;
       4: astore_1
       5: aload_1
       6: ifnonnull     23
       9: new           #44                 // class java/lang/IllegalArgumentException
      12: dup
      13: aload_0
      14: invokedynamic #46,  0             // InvokeDynamic #1:makeConcatWithConstants:(Lio/r2dbc/spi/ConnectionFactory;)Ljava/lang/String;
      19: invokespecial #50                 // Method java/lang/IllegalArgumentException."<init>":(Ljava/lang/String;)V
      22: athrow
      23: aload_1
      24: invokevirtual #29                 // Method io/r2dbc/spi/ConnectionFactoryOptions.mutate:()Lio/r2dbc/spi/ConnectionFactoryOptions$Builder;
      27: invokestatic  #33                 // Method withOptions:(Lio/r2dbc/spi/ConnectionFactoryOptions$Builder;)Lorg/springframework/boot/r2dbc/ConnectionFactoryBuilder;
      30: areturn

  private static io.r2dbc.spi.ConnectionFactoryOptions extractOptionsIfPossible(io.r2dbc.spi.ConnectionFactory);
    Code:
       0: aload_0
       1: invokestatic  #53                 // Method org/springframework/boot/r2dbc/OptionsCapableConnectionFactory.unwrapFrom:(Lio/r2dbc/spi/ConnectionFactory;)Lorg/springframework/boot/r2dbc/OptionsCapableConnectionFactory;
       4: astore_1
       5: aload_1
       6: ifnull        14
       9: aload_1
      10: invokevirtual #59                 // Method org/springframework/boot/r2dbc/OptionsCapableConnectionFactory.getOptions:()Lio/r2dbc/spi/ConnectionFactoryOptions;
      13: areturn
      14: aconst_null
      15: areturn

  public org.springframework.boot.r2dbc.ConnectionFactoryBuilder configure(java.util.function.Consumer<io.r2dbc.spi.ConnectionFactoryOptions$Builder>);
    Code:
       0: aload_1
       1: aload_0
       2: getfield      #7                  // Field optionsBuilder:Lio/r2dbc/spi/ConnectionFactoryOptions$Builder;
       5: invokeinterface #63,  2           // InterfaceMethod java/util/function/Consumer.accept:(Ljava/lang/Object;)V
      10: aload_0
      11: areturn

  public org.springframework.boot.r2dbc.ConnectionFactoryBuilder username(java.lang.String);
    Code:
       0: aload_0
       1: aload_1
       2: invokedynamic #69,  0             // InvokeDynamic #2:accept:(Ljava/lang/String;)Ljava/util/function/Consumer;
       7: invokevirtual #72                 // Method configure:(Ljava/util/function/Consumer;)Lorg/springframework/boot/r2dbc/ConnectionFactoryBuilder;
      10: areturn

  public org.springframework.boot.r2dbc.ConnectionFactoryBuilder password(java.lang.CharSequence);
    Code:
       0: aload_0
       1: aload_1
       2: invokedynamic #76,  0             // InvokeDynamic #3:accept:(Ljava/lang/CharSequence;)Ljava/util/function/Consumer;
       7: invokevirtual #72                 // Method configure:(Ljava/util/function/Consumer;)Lorg/springframework/boot/r2dbc/ConnectionFactoryBuilder;
      10: areturn

  public org.springframework.boot.r2dbc.ConnectionFactoryBuilder hostname(java.lang.String);
    Code:
       0: aload_0
       1: aload_1
       2: invokedynamic #79,  0             // InvokeDynamic #4:accept:(Ljava/lang/String;)Ljava/util/function/Consumer;
       7: invokevirtual #72                 // Method configure:(Ljava/util/function/Consumer;)Lorg/springframework/boot/r2dbc/ConnectionFactoryBuilder;
      10: areturn

  public org.springframework.boot.r2dbc.ConnectionFactoryBuilder port(int);
    Code:
       0: aload_0
       1: iload_1
       2: invokedynamic #80,  0             // InvokeDynamic #5:accept:(I)Ljava/util/function/Consumer;
       7: invokevirtual #72                 // Method configure:(Ljava/util/function/Consumer;)Lorg/springframework/boot/r2dbc/ConnectionFactoryBuilder;
      10: areturn

  public org.springframework.boot.r2dbc.ConnectionFactoryBuilder database(java.lang.String);
    Code:
       0: aload_0
       1: aload_1
       2: invokedynamic #83,  0             // InvokeDynamic #6:accept:(Ljava/lang/String;)Ljava/util/function/Consumer;
       7: invokevirtual #72                 // Method configure:(Ljava/util/function/Consumer;)Lorg/springframework/boot/r2dbc/ConnectionFactoryBuilder;
      10: areturn

  public io.r2dbc.spi.ConnectionFactory build();
    Code:
       0: aload_0
       1: invokevirtual #84                 // Method buildOptions:()Lio/r2dbc/spi/ConnectionFactoryOptions;
       4: astore_1
       5: getstatic     #87                 // Field optionsCapableWrapper:Lorg/springframework/boot/r2dbc/ConnectionFactoryBuilder$OptionsCapableWrapper;
       8: aload_1
       9: invokevirtual #91                 // Method org/springframework/boot/r2dbc/ConnectionFactoryBuilder$OptionsCapableWrapper.buildAndWrap:(Lio/r2dbc/spi/ConnectionFactoryOptions;)Lio/r2dbc/spi/ConnectionFactory;
      12: areturn

  public io.r2dbc.spi.ConnectionFactoryOptions buildOptions();
    Code:
       0: aload_0
       1: getfield      #7                  // Field optionsBuilder:Lio/r2dbc/spi/ConnectionFactoryOptions$Builder;
       4: invokevirtual #97                 // Method io/r2dbc/spi/ConnectionFactoryOptions$Builder.build:()Lio/r2dbc/spi/ConnectionFactoryOptions;
       7: areturn

  private static void lambda$database$5(java.lang.String, io.r2dbc.spi.ConnectionFactoryOptions$Builder);
    Code:
       0: aload_1
       1: getstatic     #102                // Field io/r2dbc/spi/ConnectionFactoryOptions.DATABASE:Lio/r2dbc/spi/Option;
       4: aload_0
       5: invokevirtual #106                // Method io/r2dbc/spi/ConnectionFactoryOptions$Builder.option:(Lio/r2dbc/spi/Option;Ljava/lang/Object;)Lio/r2dbc/spi/ConnectionFactoryOptions$Builder;
       8: pop
       9: return

  private static void lambda$port$4(int, io.r2dbc.spi.ConnectionFactoryOptions$Builder);
    Code:
       0: aload_1
       1: getstatic     #110                // Field io/r2dbc/spi/ConnectionFactoryOptions.PORT:Lio/r2dbc/spi/Option;
       4: iload_0
       5: invokestatic  #113                // Method java/lang/Integer.valueOf:(I)Ljava/lang/Integer;
       8: invokevirtual #106                // Method io/r2dbc/spi/ConnectionFactoryOptions$Builder.option:(Lio/r2dbc/spi/Option;Ljava/lang/Object;)Lio/r2dbc/spi/ConnectionFactoryOptions$Builder;
      11: pop
      12: return

  private static void lambda$hostname$3(java.lang.String, io.r2dbc.spi.ConnectionFactoryOptions$Builder);
    Code:
       0: aload_1
       1: getstatic     #119                // Field io/r2dbc/spi/ConnectionFactoryOptions.HOST:Lio/r2dbc/spi/Option;
       4: aload_0
       5: invokevirtual #106                // Method io/r2dbc/spi/ConnectionFactoryOptions$Builder.option:(Lio/r2dbc/spi/Option;Ljava/lang/Object;)Lio/r2dbc/spi/ConnectionFactoryOptions$Builder;
       8: pop
       9: return

  private static void lambda$password$2(java.lang.CharSequence, io.r2dbc.spi.ConnectionFactoryOptions$Builder);
    Code:
       0: aload_1
       1: getstatic     #122                // Field io/r2dbc/spi/ConnectionFactoryOptions.PASSWORD:Lio/r2dbc/spi/Option;
       4: aload_0
       5: invokevirtual #106                // Method io/r2dbc/spi/ConnectionFactoryOptions$Builder.option:(Lio/r2dbc/spi/Option;Ljava/lang/Object;)Lio/r2dbc/spi/ConnectionFactoryOptions$Builder;
       8: pop
       9: return

  private static void lambda$username$1(java.lang.String, io.r2dbc.spi.ConnectionFactoryOptions$Builder);
    Code:
       0: aload_1
       1: getstatic     #125                // Field io/r2dbc/spi/ConnectionFactoryOptions.USER:Lio/r2dbc/spi/Option;
       4: aload_0
       5: invokevirtual #106                // Method io/r2dbc/spi/ConnectionFactoryOptions$Builder.option:(Lio/r2dbc/spi/Option;Ljava/lang/Object;)Lio/r2dbc/spi/ConnectionFactoryOptions$Builder;
       8: pop
       9: return

  private static java.lang.String lambda$withUrl$0();
    Code:
       0: ldc           #128                // String Url must not be null
       2: areturn

  static {};
    Code:
       0: ldc           #130                // String io.r2dbc.pool.ConnectionPool
       2: ldc           #8                  // class org/springframework/boot/r2dbc/ConnectionFactoryBuilder
       4: invokevirtual #132                // Method java/lang/Class.getClassLoader:()Ljava/lang/ClassLoader;
       7: invokestatic  #138                // Method org/springframework/util/ClassUtils.isPresent:(Ljava/lang/String;Ljava/lang/ClassLoader;)Z
      10: ifeq          26
      13: new           #144                // class org/springframework/boot/r2dbc/ConnectionFactoryBuilder$PoolingAwareOptionsCapableWrapper
      16: dup
      17: invokespecial #146                // Method org/springframework/boot/r2dbc/ConnectionFactoryBuilder$PoolingAwareOptionsCapableWrapper."<init>":()V
      20: putstatic     #87                 // Field optionsCapableWrapper:Lorg/springframework/boot/r2dbc/ConnectionFactoryBuilder$OptionsCapableWrapper;
      23: goto          36
      26: new           #92                 // class org/springframework/boot/r2dbc/ConnectionFactoryBuilder$OptionsCapableWrapper
      29: dup
      30: invokespecial #147                // Method org/springframework/boot/r2dbc/ConnectionFactoryBuilder$OptionsCapableWrapper."<init>":()V
      33: putstatic     #87                 // Field optionsCapableWrapper:Lorg/springframework/boot/r2dbc/ConnectionFactoryBuilder$OptionsCapableWrapper;
      36: return
}
