Compiled from "EmbeddedDatabaseConnection.java"
public final class org.springframework.boot.r2dbc.EmbeddedDatabaseConnection extends java.lang.Enum<org.springframework.boot.r2dbc.EmbeddedDatabaseConnection> {
  public static final org.springframework.boot.r2dbc.EmbeddedDatabaseConnection NONE;

  public static final org.springframework.boot.r2dbc.EmbeddedDatabaseConnection H2;

  private final java.lang.String driverClassName;

  private final java.lang.String url;

  private final java.util.function.Predicate<io.r2dbc.spi.ConnectionFactoryOptions> embedded;

  private static final org.springframework.boot.r2dbc.EmbeddedDatabaseConnection[] $VALUES;

  public static org.springframework.boot.r2dbc.EmbeddedDatabaseConnection[] values();
    Code:
       0: getstatic     #10                 // Field $VALUES:[Lorg/springframework/boot/r2dbc/EmbeddedDatabaseConnection;
       3: invokevirtual #14                 // Method "[Lorg/springframework/boot/r2dbc/EmbeddedDatabaseConnection;".clone:()Ljava/lang/Object;
       6: checkcast     #15                 // class "[Lorg/springframework/boot/r2dbc/EmbeddedDatabaseConnection;"
       9: areturn

  public static org.springframework.boot.r2dbc.EmbeddedDatabaseConnection valueOf(java.lang.String);
    Code:
       0: ldc           #1                  // class org/springframework/boot/r2dbc/EmbeddedDatabaseConnection
       2: aload_0
       3: invokestatic  #19                 // Method java/lang/Enum.valueOf:(Ljava/lang/Class;Ljava/lang/String;)Ljava/lang/Enum;
       6: checkcast     #1                  // class org/springframework/boot/r2dbc/EmbeddedDatabaseConnection
       9: areturn

  private org.springframework.boot.r2dbc.EmbeddedDatabaseConnection(java.lang.String, java.lang.String, java.util.function.Predicate<io.r2dbc.spi.ConnectionFactoryOptions>);
    Code:
       0: aload_0
       1: aload_1
       2: iload_2
       3: invokespecial #25                 // Method java/lang/Enum."<init>":(Ljava/lang/String;I)V
       6: aload_0
       7: aload_3
       8: putfield      #29                 // Field driverClassName:Ljava/lang/String;
      11: aload_0
      12: aload         4
      14: putfield      #33                 // Field url:Ljava/lang/String;
      17: aload_0
      18: aload         5
      20: putfield      #36                 // Field embedded:Ljava/util/function/Predicate;
      23: return

  public java.lang.String getDriverClassName();
    Code:
       0: aload_0
       1: getfield      #29                 // Field driverClassName:Ljava/lang/String;
       4: areturn

  public java.lang.String getUrl(java.lang.String);
    Code:
       0: aload_1
       1: ldc           #40                 // String DatabaseName must not be empty
       3: invokestatic  #42                 // Method org/springframework/util/Assert.hasText:(Ljava/lang/String;Ljava/lang/String;)V
       6: aload_0
       7: getfield      #33                 // Field url:Ljava/lang/String;
      10: ifnull        31
      13: aload_0
      14: getfield      #33                 // Field url:Ljava/lang/String;
      17: iconst_1
      18: anewarray     #48                 // class java/lang/Object
      21: dup
      22: iconst_0
      23: aload_1
      24: aastore
      25: invokestatic  #50                 // Method java/lang/String.format:(Ljava/lang/String;[Ljava/lang/Object;)Ljava/lang/String;
      28: goto          32
      31: aconst_null
      32: areturn

  public static org.springframework.boot.r2dbc.EmbeddedDatabaseConnection get(java.lang.ClassLoader);
    Code:
       0: invokestatic  #56                 // Method values:()[Lorg/springframework/boot/r2dbc/EmbeddedDatabaseConnection;
       3: astore_1
       4: aload_1
       5: arraylength
       6: istore_2
       7: iconst_0
       8: istore_3
       9: iload_3
      10: iload_2
      11: if_icmpge     48
      14: aload_1
      15: iload_3
      16: aaload
      17: astore        4
      19: aload         4
      21: getstatic     #3                  // Field NONE:Lorg/springframework/boot/r2dbc/EmbeddedDatabaseConnection;
      24: if_acmpeq     42
      27: aload         4
      29: invokevirtual #60                 // Method getDriverClassName:()Ljava/lang/String;
      32: aload_0
      33: invokestatic  #64                 // Method org/springframework/util/ClassUtils.isPresent:(Ljava/lang/String;Ljava/lang/ClassLoader;)Z
      36: ifeq          42
      39: aload         4
      41: areturn
      42: iinc          3, 1
      45: goto          9
      48: getstatic     #3                  // Field NONE:Lorg/springframework/boot/r2dbc/EmbeddedDatabaseConnection;
      51: areturn

  public static boolean isEmbedded(io.r2dbc.spi.ConnectionFactory);
    Code:
       0: aload_0
       1: invokestatic  #70                 // Method org/springframework/boot/r2dbc/OptionsCapableConnectionFactory.unwrapFrom:(Lio/r2dbc/spi/ConnectionFactory;)Lorg/springframework/boot/r2dbc/OptionsCapableConnectionFactory;
       4: astore_1
       5: aload_1
       6: invokedynamic #76,  0             // InvokeDynamic #0:get:()Ljava/util/function/Supplier;
      11: invokestatic  #80                 // Method org/springframework/util/Assert.notNull:(Ljava/lang/Object;Ljava/util/function/Supplier;)V
      14: aload_1
      15: invokevirtual #84                 // Method org/springframework/boot/r2dbc/OptionsCapableConnectionFactory.getOptions:()Lio/r2dbc/spi/ConnectionFactoryOptions;
      18: astore_2
      19: invokestatic  #56                 // Method values:()[Lorg/springframework/boot/r2dbc/EmbeddedDatabaseConnection;
      22: astore_3
      23: aload_3
      24: arraylength
      25: istore        4
      27: iconst_0
      28: istore        5
      30: iload         5
      32: iload         4
      34: if_icmpge     65
      37: aload_3
      38: iload         5
      40: aaload
      41: astore        6
      43: aload         6
      45: getfield      #36                 // Field embedded:Ljava/util/function/Predicate;
      48: aload_2
      49: invokeinterface #88,  2           // InterfaceMethod java/util/function/Predicate.test:(Ljava/lang/Object;)Z
      54: ifeq          59
      57: iconst_1
      58: ireturn
      59: iinc          5, 1
      62: goto          30
      65: iconst_0
      66: ireturn

  private static java.lang.String lambda$isEmbedded$2();
    Code:
       0: ldc           #94                 // class org/springframework/boot/r2dbc/ConnectionFactoryBuilder
       2: invokevirtual #96                 // Method java/lang/Class.getName:()Ljava/lang/String;
       5: invokedynamic #101,  0            // InvokeDynamic #1:makeConcatWithConstants:(Ljava/lang/String;)Ljava/lang/String;
      10: areturn

  private static boolean lambda$static$1(io.r2dbc.spi.ConnectionFactoryOptions);
    Code:
       0: aload_0
       1: getstatic     #105                // Field io/r2dbc/spi/ConnectionFactoryOptions.DRIVER:Lio/r2dbc/spi/Option;
       4: invokevirtual #111                // Method io/r2dbc/spi/ConnectionFactoryOptions.getValue:(Lio/r2dbc/spi/Option;)Ljava/lang/Object;
       7: ldc           #115                // String h2
       9: invokevirtual #117                // Method java/lang/Object.equals:(Ljava/lang/Object;)Z
      12: ifeq          34
      15: aload_0
      16: getstatic     #120                // Field io/r2dbc/spi/ConnectionFactoryOptions.PROTOCOL:Lio/r2dbc/spi/Option;
      19: invokevirtual #111                // Method io/r2dbc/spi/ConnectionFactoryOptions.getValue:(Lio/r2dbc/spi/Option;)Ljava/lang/Object;
      22: ldc           #123                // String mem
      24: invokevirtual #117                // Method java/lang/Object.equals:(Ljava/lang/Object;)Z
      27: ifeq          34
      30: iconst_1
      31: goto          35
      34: iconst_0
      35: ireturn

  private static boolean lambda$static$0(io.r2dbc.spi.ConnectionFactoryOptions);
    Code:
       0: iconst_0
       1: ireturn

  private static org.springframework.boot.r2dbc.EmbeddedDatabaseConnection[] $values();
    Code:
       0: iconst_2
       1: anewarray     #1                  // class org/springframework/boot/r2dbc/EmbeddedDatabaseConnection
       4: dup
       5: iconst_0
       6: getstatic     #3                  // Field NONE:Lorg/springframework/boot/r2dbc/EmbeddedDatabaseConnection;
       9: aastore
      10: dup
      11: iconst_1
      12: getstatic     #7                  // Field H2:Lorg/springframework/boot/r2dbc/EmbeddedDatabaseConnection;
      15: aastore
      16: areturn

  static {};
    Code:
       0: new           #1                  // class org/springframework/boot/r2dbc/EmbeddedDatabaseConnection
       3: dup
       4: ldc           #125                // String NONE
       6: iconst_0
       7: aconst_null
       8: aconst_null
       9: invokedynamic #126,  0            // InvokeDynamic #2:test:()Ljava/util/function/Predicate;
      14: invokespecial #129                // Method "<init>":(Ljava/lang/String;ILjava/lang/String;Ljava/lang/String;Ljava/util/function/Predicate;)V
      17: putstatic     #3                  // Field NONE:Lorg/springframework/boot/r2dbc/EmbeddedDatabaseConnection;
      20: new           #1                  // class org/springframework/boot/r2dbc/EmbeddedDatabaseConnection
      23: dup
      24: ldc           #132                // String H2
      26: iconst_1
      27: ldc           #133                // String io.r2dbc.h2.H2ConnectionFactoryProvider
      29: ldc           #135                // String r2dbc:h2:mem:///%s?options=DB_CLOSE_DELAY=-1;DB_CLOSE_ON_EXIT=FALSE
      31: invokedynamic #137,  0            // InvokeDynamic #3:test:()Ljava/util/function/Predicate;
      36: invokespecial #129                // Method "<init>":(Ljava/lang/String;ILjava/lang/String;Ljava/lang/String;Ljava/util/function/Predicate;)V
      39: putstatic     #7                  // Field H2:Lorg/springframework/boot/r2dbc/EmbeddedDatabaseConnection;
      42: invokestatic  #138                // Method $values:()[Lorg/springframework/boot/r2dbc/EmbeddedDatabaseConnection;
      45: putstatic     #10                 // Field $VALUES:[Lorg/springframework/boot/r2dbc/EmbeddedDatabaseConnection;
      48: return
}
