Compiled from "OptionsCapableConnectionFactory.java"
public class org.springframework.boot.r2dbc.OptionsCapableConnectionFactory implements io.r2dbc.spi.Wrapped<io.r2dbc.spi.ConnectionFactory>, io.r2dbc.spi.ConnectionFactory {
  private final io.r2dbc.spi.ConnectionFactoryOptions options;

  private final io.r2dbc.spi.ConnectionFactory delegate;

  public org.springframework.boot.r2dbc.OptionsCapableConnectionFactory(io.r2dbc.spi.ConnectionFactoryOptions, io.r2dbc.spi.ConnectionFactory);
    Code:
       0: aload_0
       1: invokespecial #1                  // Method java/lang/Object."<init>":()V
       4: aload_0
       5: aload_1
       6: putfield      #7                  // Field options:Lio/r2dbc/spi/ConnectionFactoryOptions;
       9: aload_0
      10: aload_2
      11: putfield      #13                 // Field delegate:Lio/r2dbc/spi/ConnectionFactory;
      14: return

  public io.r2dbc.spi.ConnectionFactoryOptions getOptions();
    Code:
       0: aload_0
       1: getfield      #7                  // Field options:Lio/r2dbc/spi/ConnectionFactoryOptions;
       4: areturn

  public org.reactivestreams.Publisher<? extends io.r2dbc.spi.Connection> create();
    Code:
       0: aload_0
       1: getfield      #13                 // Field delegate:Lio/r2dbc/spi/ConnectionFactory;
       4: invokeinterface #17,  1           // InterfaceMethod io/r2dbc/spi/ConnectionFactory.create:()Lorg/reactivestreams/Publisher;
       9: areturn

  public io.r2dbc.spi.ConnectionFactoryMetadata getMetadata();
    Code:
       0: aload_0
       1: getfield      #13                 // Field delegate:Lio/r2dbc/spi/ConnectionFactory;
       4: invokeinterface #23,  1           // InterfaceMethod io/r2dbc/spi/ConnectionFactory.getMetadata:()Lio/r2dbc/spi/ConnectionFactoryMetadata;
       9: areturn

  public io.r2dbc.spi.ConnectionFactory unwrap();
    Code:
       0: aload_0
       1: getfield      #13                 // Field delegate:Lio/r2dbc/spi/ConnectionFactory;
       4: areturn

  public static org.springframework.boot.r2dbc.OptionsCapableConnectionFactory unwrapFrom(io.r2dbc.spi.ConnectionFactory);
    Code:
       0: aload_0
       1: instanceof    #8                  // class org/springframework/boot/r2dbc/OptionsCapableConnectionFactory
       4: ifeq          12
       7: aload_0
       8: checkcast     #8                  // class org/springframework/boot/r2dbc/OptionsCapableConnectionFactory
      11: areturn
      12: aload_0
      13: instanceof    #27                 // class io/r2dbc/spi/Wrapped
      16: ifeq          44
      19: aload_0
      20: checkcast     #27                 // class io/r2dbc/spi/Wrapped
      23: invokeinterface #29,  1           // InterfaceMethod io/r2dbc/spi/Wrapped.unwrap:()Ljava/lang/Object;
      28: astore_1
      29: aload_1
      30: instanceof    #18                 // class io/r2dbc/spi/ConnectionFactory
      33: ifeq          44
      36: aload_1
      37: checkcast     #18                 // class io/r2dbc/spi/ConnectionFactory
      40: invokestatic  #33                 // Method unwrapFrom:(Lio/r2dbc/spi/ConnectionFactory;)Lorg/springframework/boot/r2dbc/OptionsCapableConnectionFactory;
      43: areturn
      44: aconst_null
      45: areturn

  public java.lang.Object unwrap();
    Code:
       0: aload_0
       1: invokevirtual #37                 // Method unwrap:()Lio/r2dbc/spi/ConnectionFactory;
       4: areturn
}
