Compiled from "ReferenceBean.java"
class org.apache.dubbo.config.spring.ReferenceBean$DubboReferenceLazyInitTargetSource extends org.springframework.aop.target.AbstractLazyCreationTargetSource {
  final org.apache.dubbo.config.spring.ReferenceBean this$0;

  private org.apache.dubbo.config.spring.ReferenceBean$DubboReferenceLazyInitTargetSource(org.apache.dubbo.config.spring.ReferenceBean);
    Code:
       0: aload_0
       1: aload_1
       2: putfield      #2                  // Field this$0:Lorg/apache/dubbo/config/spring/ReferenceBean;
       5: aload_0
       6: invokespecial #3                  // Method org/springframework/aop/target/AbstractLazyCreationTargetSource."<init>":()V
       9: return

  protected java.lang.Object createObject() throws java.lang.Exception;
    Code:
       0: aload_0
       1: getfield      #2                  // Field this$0:Lorg/apache/dubbo/config/spring/ReferenceBean;
       4: invokestatic  #4                  // Method org/apache/dubbo/config/spring/ReferenceBean.access$100:(Lorg/apache/dubbo/config/spring/ReferenceBean;)Ljava/lang/Object;
       7: areturn

  public synchronized java.lang.Class<?> getTargetClass();
    Code:
       0: aload_0
       1: getfield      #2                  // Field this$0:Lorg/apache/dubbo/config/spring/ReferenceBean;
       4: invokevirtual #5                  // Method org/apache/dubbo/config/spring/ReferenceBean.getInterfaceClass:()Ljava/lang/Class;
       7: areturn

  org.apache.dubbo.config.spring.ReferenceBean$DubboReferenceLazyInitTargetSource(org.apache.dubbo.config.spring.ReferenceBean, org.apache.dubbo.config.spring.ReferenceBean$1);
    Code:
       0: aload_0
       1: aload_1
       2: invokespecial #1                  // Method "<init>":(Lorg/apache/dubbo/config/spring/ReferenceBean;)V
       5: return
}
