Compiled from "ScheduledCompletableFuture.java"
public class org.apache.dubbo.common.threadpool.concurrent.ScheduledCompletableFuture {
  public org.apache.dubbo.common.threadpool.concurrent.ScheduledCompletableFuture();
    Code:
       0: aload_0
       1: invokespecial #1                  // Method java/lang/Object."<init>":()V
       4: return

  public static <T> java.util.concurrent.CompletableFuture<T> schedule(java.util.concurrent.ScheduledExecutorService, java.util.function.Supplier<T>, long, java.util.concurrent.TimeUnit);
    Code:
       0: new           #2                  // class java/util/concurrent/CompletableFuture
       3: dup
       4: invokespecial #3                  // Method java/util/concurrent/CompletableFuture."<init>":()V
       7: astore        5
       9: aload_0
      10: aload         5
      12: aload_1
      13: invokedynamic #4,  0              // InvokeDynamic #0:call:(Ljava/util/concurrent/CompletableFuture;Ljava/util/function/Supplier;)Ljava/util/concurrent/Callable;
      18: lload_2
      19: aload         4
      21: invokeinterface #5,  5            // InterfaceMethod java/util/concurrent/ScheduledExecutorService.schedule:(Ljava/util/concurrent/Callable;JLjava/util/concurrent/TimeUnit;)Ljava/util/concurrent/ScheduledFuture;
      26: pop
      27: aload         5
      29: areturn

  public static <T> java.util.concurrent.CompletableFuture<T> submit(java.util.concurrent.ScheduledExecutorService, java.util.function.Supplier<T>);
    Code:
       0: new           #2                  // class java/util/concurrent/CompletableFuture
       3: dup
       4: invokespecial #3                  // Method java/util/concurrent/CompletableFuture."<init>":()V
       7: astore_2
       8: aload_0
       9: aload_2
      10: aload_1
      11: invokedynamic #6,  0              // InvokeDynamic #1:call:(Ljava/util/concurrent/CompletableFuture;Ljava/util/function/Supplier;)Ljava/util/concurrent/Callable;
      16: invokeinterface #7,  2            // InterfaceMethod java/util/concurrent/ScheduledExecutorService.submit:(Ljava/util/concurrent/Callable;)Ljava/util/concurrent/Future;
      21: pop
      22: aload_2
      23: areturn

  private static java.lang.Boolean lambda$submit$1(java.util.concurrent.CompletableFuture, java.util.function.Supplier) throws java.lang.Exception;
    Code:
       0: aload_0
       1: aload_1
       2: invokeinterface #8,  1            // InterfaceMethod java/util/function/Supplier.get:()Ljava/lang/Object;
       7: invokevirtual #9                  // Method java/util/concurrent/CompletableFuture.complete:(Ljava/lang/Object;)Z
      10: invokestatic  #10                 // Method java/lang/Boolean.valueOf:(Z)Ljava/lang/Boolean;
      13: areturn
      14: astore_2
      15: aload_0
      16: aload_2
      17: invokevirtual #12                 // Method java/util/concurrent/CompletableFuture.completeExceptionally:(Ljava/lang/Throwable;)Z
      20: invokestatic  #10                 // Method java/lang/Boolean.valueOf:(Z)Ljava/lang/Boolean;
      23: areturn
    Exception table:
       from    to  target type
           0    13    14   Class java/lang/Throwable

  private static java.lang.Boolean lambda$schedule$0(java.util.concurrent.CompletableFuture, java.util.function.Supplier) throws java.lang.Exception;
    Code:
       0: aload_0
       1: aload_1
       2: invokeinterface #8,  1            // InterfaceMethod java/util/function/Supplier.get:()Ljava/lang/Object;
       7: invokevirtual #9                  // Method java/util/concurrent/CompletableFuture.complete:(Ljava/lang/Object;)Z
      10: invokestatic  #10                 // Method java/lang/Boolean.valueOf:(Z)Ljava/lang/Boolean;
      13: areturn
      14: astore_2
      15: aload_0
      16: aload_2
      17: invokevirtual #12                 // Method java/util/concurrent/CompletableFuture.completeExceptionally:(Ljava/lang/Throwable;)Z
      20: invokestatic  #10                 // Method java/lang/Boolean.valueOf:(Z)Ljava/lang/Boolean;
      23: areturn
    Exception table:
       from    to  target type
           0    13    14   Class java/lang/Throwable
}
