Compiled from "RetryServiceInstancesChangedEvent.java"
public class org.apache.dubbo.registry.client.event.RetryServiceInstancesChangedEvent extends org.apache.dubbo.registry.client.event.ServiceInstancesChangedEvent {
  private volatile long failureRecordTime;

  public org.apache.dubbo.registry.client.event.RetryServiceInstancesChangedEvent(java.lang.String);
    Code:
       0: aload_0
       1: aload_1
       2: invokestatic  #1                  // Method java/util/Collections.emptyList:()Ljava/util/List;
       5: invokespecial #2                  // Method org/apache/dubbo/registry/client/event/ServiceInstancesChangedEvent."<init>":(Ljava/lang/String;Ljava/util/List;)V
       8: aload_0
       9: invokestatic  #3                  // Method java/lang/System.currentTimeMillis:()J
      12: putfield      #4                  // Field failureRecordTime:J
      15: return

  public long getFailureRecordTime();
    Code:
       0: aload_0
       1: getfield      #4                  // Field failureRecordTime:J
       4: lreturn
}
