Compiled from "ServiceInstancesChangedEvent.java"
public class org.apache.dubbo.registry.client.event.ServiceInstancesChangedEvent {
  private final java.lang.String serviceName;

  private final java.util.List<org.apache.dubbo.registry.client.ServiceInstance> serviceInstances;

  public org.apache.dubbo.registry.client.event.ServiceInstancesChangedEvent(java.lang.String, java.util.List<org.apache.dubbo.registry.client.ServiceInstance>);
    Code:
       0: aload_0
       1: invokespecial #1                  // Method java/lang/Object."<init>":()V
       4: aload_0
       5: aload_1
       6: putfield      #2                  // Field serviceName:Ljava/lang/String;
       9: aload_0
      10: aload_2
      11: invokestatic  #3                  // Method java/util/Collections.unmodifiableList:(Ljava/util/List;)Ljava/util/List;
      14: putfield      #4                  // Field serviceInstances:Ljava/util/List;
      17: return

  protected org.apache.dubbo.registry.client.event.ServiceInstancesChangedEvent();
    Code:
       0: aload_0
       1: invokespecial #1                  // Method java/lang/Object."<init>":()V
       4: aload_0
       5: invokestatic  #5                  // Method java/util/Collections.emptyList:()Ljava/util/List;
       8: putfield      #4                  // Field serviceInstances:Ljava/util/List;
      11: aload_0
      12: ldc           #6                  // String
      14: putfield      #2                  // Field serviceName:Ljava/lang/String;
      17: return

  public java.lang.String getServiceName();
    Code:
       0: aload_0
       1: getfield      #2                  // Field serviceName:Ljava/lang/String;
       4: areturn

  public java.util.List<org.apache.dubbo.registry.client.ServiceInstance> getServiceInstances();
    Code:
       0: aload_0
       1: getfield      #4                  // Field serviceInstances:Ljava/util/List;
       4: areturn
}
