Compiled from "DubboWireProtocol.java"
public class org.apache.dubbo.rpc.protocol.dubbo.pu.DubboWireProtocol extends org.apache.dubbo.remoting.api.AbstractWireProtocol {
  public org.apache.dubbo.rpc.protocol.dubbo.pu.DubboWireProtocol();
    Code:
       0: aload_0
       1: new           #1                  // class org/apache/dubbo/rpc/protocol/dubbo/pu/DubboDetector
       4: dup
       5: invokespecial #2                  // Method org/apache/dubbo/rpc/protocol/dubbo/pu/DubboDetector."<init>":()V
       8: invokespecial #3                  // Method org/apache/dubbo/remoting/api/AbstractWireProtocol."<init>":(Lorg/apache/dubbo/remoting/api/ProtocolDetector;)V
      11: return

  public void configServerProtocolHandler(org.apache.dubbo.common.URL, org.apache.dubbo.remoting.api.pu.ChannelOperator);
    Code:
       0: new           #4                  // class java/util/ArrayList
       3: dup
       4: invokespecial #5                  // Method java/util/ArrayList."<init>":()V
       7: astore_3
       8: aload_2
       9: aload_3
      10: invokeinterface #6,  2            // InterfaceMethod org/apache/dubbo/remoting/api/pu/ChannelOperator.configChannelHandler:(Ljava/util/List;)V
      15: return
}
