Compiled from "DefaultFilterChainBuilder.java"
public class org.apache.dubbo.rpc.cluster.filter.DefaultFilterChainBuilder implements org.apache.dubbo.rpc.cluster.filter.FilterChainBuilder {
  public org.apache.dubbo.rpc.cluster.filter.DefaultFilterChainBuilder();
    Code:
       0: aload_0
       1: invokespecial #1                  // Method java/lang/Object."<init>":()V
       4: return

  public <T> org.apache.dubbo.rpc.Invoker<T> buildInvokerChain(org.apache.dubbo.rpc.Invoker<T>, java.lang.String, java.lang.String);
    Code:
       0: aload_1
       1: astore        4
       3: aload_1
       4: invokeinterface #2,  1            // InterfaceMethod org/apache/dubbo/rpc/Invoker.getUrl:()Lorg/apache/dubbo/common/URL;
       9: astore        5
      11: aload_0
      12: aload         5
      14: invokespecial #3                  // Method getModuleModelsFromUrl:(Lorg/apache/dubbo/common/URL;)Ljava/util/List;
      17: astore        6
      19: aload         6
      21: ifnull        63
      24: aload         6
      26: invokeinterface #4,  1            // InterfaceMethod java/util/List.size:()I
      31: iconst_1
      32: if_icmpne     63
      35: ldc           #5                  // class org/apache/dubbo/rpc/Filter
      37: aload         6
      39: iconst_0
      40: invokeinterface #6,  2            // InterfaceMethod java/util/List.get:(I)Ljava/lang/Object;
      45: checkcast     #7                  // class org/apache/dubbo/rpc/model/ScopeModel
      48: invokestatic  #8                  // Method org/apache/dubbo/rpc/model/ScopeModelUtil.getExtensionLoader:(Ljava/lang/Class;Lorg/apache/dubbo/rpc/model/ScopeModel;)Lorg/apache/dubbo/common/extension/ExtensionLoader;
      51: aload         5
      53: aload_2
      54: aload_3
      55: invokevirtual #9                  // Method org/apache/dubbo/common/extension/ExtensionLoader.getActivateExtension:(Lorg/apache/dubbo/common/URL;Ljava/lang/String;Ljava/lang/String;)Ljava/util/List;
      58: astore        7
      60: goto          198
      63: aload         6
      65: ifnull        183
      68: aload         6
      70: invokeinterface #4,  1            // InterfaceMethod java/util/List.size:()I
      75: iconst_1
      76: if_icmple     183
      79: new           #10                 // class java/util/ArrayList
      82: dup
      83: invokespecial #11                 // Method java/util/ArrayList."<init>":()V
      86: astore        7
      88: new           #10                 // class java/util/ArrayList
      91: dup
      92: invokespecial #11                 // Method java/util/ArrayList."<init>":()V
      95: astore        8
      97: aload         6
      99: invokeinterface #12,  1           // InterfaceMethod java/util/List.iterator:()Ljava/util/Iterator;
     104: astore        9
     106: aload         9
     108: invokeinterface #13,  1           // InterfaceMethod java/util/Iterator.hasNext:()Z
     113: ifeq          170
     116: aload         9
     118: invokeinterface #14,  1           // InterfaceMethod java/util/Iterator.next:()Ljava/lang/Object;
     123: checkcast     #15                 // class org/apache/dubbo/rpc/model/ModuleModel
     126: astore        10
     128: ldc           #5                  // class org/apache/dubbo/rpc/Filter
     130: aload         10
     132: invokestatic  #8                  // Method org/apache/dubbo/rpc/model/ScopeModelUtil.getExtensionLoader:(Ljava/lang/Class;Lorg/apache/dubbo/rpc/model/ScopeModel;)Lorg/apache/dubbo/common/extension/ExtensionLoader;
     135: aload         5
     137: aload_2
     138: aload_3
     139: invokevirtual #9                  // Method org/apache/dubbo/common/extension/ExtensionLoader.getActivateExtension:(Lorg/apache/dubbo/common/URL;Ljava/lang/String;Ljava/lang/String;)Ljava/util/List;
     142: astore        11
     144: aload         7
     146: aload         11
     148: invokeinterface #16,  2           // InterfaceMethod java/util/List.addAll:(Ljava/util/Collection;)Z
     153: pop
     154: aload         8
     156: aload         10
     158: invokevirtual #17                 // Method org/apache/dubbo/rpc/model/ModuleModel.getExtensionDirector:()Lorg/apache/dubbo/common/extension/ExtensionDirector;
     161: invokeinterface #18,  2           // InterfaceMethod java/util/List.add:(Ljava/lang/Object;)Z
     166: pop
     167: goto          106
     170: aload_0
     171: aload         7
     173: aload         8
     175: invokespecial #19                 // Method sortingAndDeduplication:(Ljava/util/List;Ljava/util/List;)Ljava/util/List;
     178: astore        7
     180: goto          198
     183: ldc           #5                  // class org/apache/dubbo/rpc/Filter
     185: aconst_null
     186: invokestatic  #8                  // Method org/apache/dubbo/rpc/model/ScopeModelUtil.getExtensionLoader:(Ljava/lang/Class;Lorg/apache/dubbo/rpc/model/ScopeModel;)Lorg/apache/dubbo/common/extension/ExtensionLoader;
     189: aload         5
     191: aload_2
     192: aload_3
     193: invokevirtual #9                  // Method org/apache/dubbo/common/extension/ExtensionLoader.getActivateExtension:(Lorg/apache/dubbo/common/URL;Ljava/lang/String;Ljava/lang/String;)Ljava/util/List;
     196: astore        7
     198: aload         7
     200: invokestatic  #20                 // Method org/apache/dubbo/common/utils/CollectionUtils.isEmpty:(Ljava/util/Collection;)Z
     203: ifne          272
     206: aload         7
     208: invokeinterface #4,  1            // InterfaceMethod java/util/List.size:()I
     213: iconst_1
     214: isub
     215: istore        8
     217: iload         8
     219: iflt          260
     222: aload         7
     224: iload         8
     226: invokeinterface #6,  2            // InterfaceMethod java/util/List.get:(I)Ljava/lang/Object;
     231: checkcast     #5                  // class org/apache/dubbo/rpc/Filter
     234: astore        9
     236: aload         4
     238: astore        10
     240: new           #21                 // class org/apache/dubbo/rpc/cluster/filter/FilterChainBuilder$CopyOfFilterChainNode
     243: dup
     244: aload_1
     245: aload         10
     247: aload         9
     249: invokespecial #22                 // Method org/apache/dubbo/rpc/cluster/filter/FilterChainBuilder$CopyOfFilterChainNode."<init>":(Lorg/apache/dubbo/rpc/Invoker;Lorg/apache/dubbo/rpc/Invoker;Lorg/apache/dubbo/rpc/BaseFilter;)V
     252: astore        4
     254: iinc          8, -1
     257: goto          217
     260: new           #23                 // class org/apache/dubbo/rpc/cluster/filter/FilterChainBuilder$CallbackRegistrationInvoker
     263: dup
     264: aload         4
     266: aload         7
     268: invokespecial #24                 // Method org/apache/dubbo/rpc/cluster/filter/FilterChainBuilder$CallbackRegistrationInvoker."<init>":(Lorg/apache/dubbo/rpc/Invoker;Ljava/util/List;)V
     271: areturn
     272: aload         4
     274: areturn

  public <T> org.apache.dubbo.rpc.cluster.ClusterInvoker<T> buildClusterInvokerChain(org.apache.dubbo.rpc.cluster.ClusterInvoker<T>, java.lang.String, java.lang.String);
    Code:
       0: aload_1
       1: astore        4
       3: aload_1
       4: invokeinterface #25,  1           // InterfaceMethod org/apache/dubbo/rpc/cluster/ClusterInvoker.getUrl:()Lorg/apache/dubbo/common/URL;
       9: astore        5
      11: aload_0
      12: aload         5
      14: invokespecial #3                  // Method getModuleModelsFromUrl:(Lorg/apache/dubbo/common/URL;)Ljava/util/List;
      17: astore        6
      19: aload         6
      21: ifnull        63
      24: aload         6
      26: invokeinterface #4,  1            // InterfaceMethod java/util/List.size:()I
      31: iconst_1
      32: if_icmpne     63
      35: ldc           #26                 // class org/apache/dubbo/rpc/cluster/filter/ClusterFilter
      37: aload         6
      39: iconst_0
      40: invokeinterface #6,  2            // InterfaceMethod java/util/List.get:(I)Ljava/lang/Object;
      45: checkcast     #7                  // class org/apache/dubbo/rpc/model/ScopeModel
      48: invokestatic  #8                  // Method org/apache/dubbo/rpc/model/ScopeModelUtil.getExtensionLoader:(Ljava/lang/Class;Lorg/apache/dubbo/rpc/model/ScopeModel;)Lorg/apache/dubbo/common/extension/ExtensionLoader;
      51: aload         5
      53: aload_2
      54: aload_3
      55: invokevirtual #9                  // Method org/apache/dubbo/common/extension/ExtensionLoader.getActivateExtension:(Lorg/apache/dubbo/common/URL;Ljava/lang/String;Ljava/lang/String;)Ljava/util/List;
      58: astore        7
      60: goto          198
      63: aload         6
      65: ifnull        183
      68: aload         6
      70: invokeinterface #4,  1            // InterfaceMethod java/util/List.size:()I
      75: iconst_1
      76: if_icmple     183
      79: new           #10                 // class java/util/ArrayList
      82: dup
      83: invokespecial #11                 // Method java/util/ArrayList."<init>":()V
      86: astore        7
      88: new           #10                 // class java/util/ArrayList
      91: dup
      92: invokespecial #11                 // Method java/util/ArrayList."<init>":()V
      95: astore        8
      97: aload         6
      99: invokeinterface #12,  1           // InterfaceMethod java/util/List.iterator:()Ljava/util/Iterator;
     104: astore        9
     106: aload         9
     108: invokeinterface #13,  1           // InterfaceMethod java/util/Iterator.hasNext:()Z
     113: ifeq          170
     116: aload         9
     118: invokeinterface #14,  1           // InterfaceMethod java/util/Iterator.next:()Ljava/lang/Object;
     123: checkcast     #15                 // class org/apache/dubbo/rpc/model/ModuleModel
     126: astore        10
     128: ldc           #26                 // class org/apache/dubbo/rpc/cluster/filter/ClusterFilter
     130: aload         10
     132: invokestatic  #8                  // Method org/apache/dubbo/rpc/model/ScopeModelUtil.getExtensionLoader:(Ljava/lang/Class;Lorg/apache/dubbo/rpc/model/ScopeModel;)Lorg/apache/dubbo/common/extension/ExtensionLoader;
     135: aload         5
     137: aload_2
     138: aload_3
     139: invokevirtual #9                  // Method org/apache/dubbo/common/extension/ExtensionLoader.getActivateExtension:(Lorg/apache/dubbo/common/URL;Ljava/lang/String;Ljava/lang/String;)Ljava/util/List;
     142: astore        11
     144: aload         7
     146: aload         11
     148: invokeinterface #16,  2           // InterfaceMethod java/util/List.addAll:(Ljava/util/Collection;)Z
     153: pop
     154: aload         8
     156: aload         10
     158: invokevirtual #17                 // Method org/apache/dubbo/rpc/model/ModuleModel.getExtensionDirector:()Lorg/apache/dubbo/common/extension/ExtensionDirector;
     161: invokeinterface #18,  2           // InterfaceMethod java/util/List.add:(Ljava/lang/Object;)Z
     166: pop
     167: goto          106
     170: aload_0
     171: aload         7
     173: aload         8
     175: invokespecial #19                 // Method sortingAndDeduplication:(Ljava/util/List;Ljava/util/List;)Ljava/util/List;
     178: astore        7
     180: goto          198
     183: ldc           #26                 // class org/apache/dubbo/rpc/cluster/filter/ClusterFilter
     185: aconst_null
     186: invokestatic  #8                  // Method org/apache/dubbo/rpc/model/ScopeModelUtil.getExtensionLoader:(Ljava/lang/Class;Lorg/apache/dubbo/rpc/model/ScopeModel;)Lorg/apache/dubbo/common/extension/ExtensionLoader;
     189: aload         5
     191: aload_2
     192: aload_3
     193: invokevirtual #9                  // Method org/apache/dubbo/common/extension/ExtensionLoader.getActivateExtension:(Lorg/apache/dubbo/common/URL;Ljava/lang/String;Ljava/lang/String;)Ljava/util/List;
     196: astore        7
     198: aload         7
     200: invokestatic  #20                 // Method org/apache/dubbo/common/utils/CollectionUtils.isEmpty:(Ljava/util/Collection;)Z
     203: ifne          273
     206: aload         7
     208: invokeinterface #4,  1            // InterfaceMethod java/util/List.size:()I
     213: iconst_1
     214: isub
     215: istore        8
     217: iload         8
     219: iflt          260
     222: aload         7
     224: iload         8
     226: invokeinterface #6,  2            // InterfaceMethod java/util/List.get:(I)Ljava/lang/Object;
     231: checkcast     #26                 // class org/apache/dubbo/rpc/cluster/filter/ClusterFilter
     234: astore        9
     236: aload         4
     238: astore        10
     240: new           #27                 // class org/apache/dubbo/rpc/cluster/filter/FilterChainBuilder$CopyOfClusterFilterChainNode
     243: dup
     244: aload_1
     245: aload         10
     247: aload         9
     249: invokespecial #28                 // Method org/apache/dubbo/rpc/cluster/filter/FilterChainBuilder$CopyOfClusterFilterChainNode."<init>":(Lorg/apache/dubbo/rpc/cluster/ClusterInvoker;Lorg/apache/dubbo/rpc/Invoker;Lorg/apache/dubbo/rpc/BaseFilter;)V
     252: astore        4
     254: iinc          8, -1
     257: goto          217
     260: new           #29                 // class org/apache/dubbo/rpc/cluster/filter/FilterChainBuilder$ClusterCallbackRegistrationInvoker
     263: dup
     264: aload_1
     265: aload         4
     267: aload         7
     269: invokespecial #30                 // Method org/apache/dubbo/rpc/cluster/filter/FilterChainBuilder$ClusterCallbackRegistrationInvoker."<init>":(Lorg/apache/dubbo/rpc/cluster/ClusterInvoker;Lorg/apache/dubbo/rpc/Invoker;Ljava/util/List;)V
     272: areturn
     273: aload         4
     275: areturn

  private <T> java.util.List<T> sortingAndDeduplication(java.util.List<T>, java.util.List<org.apache.dubbo.common.extension.ExtensionDirector>);
    Code:
       0: new           #31                 // class java/util/TreeMap
       3: dup
       4: new           #32                 // class org/apache/dubbo/common/extension/support/ActivateComparator
       7: dup
       8: aload_2
       9: invokespecial #33                 // Method org/apache/dubbo/common/extension/support/ActivateComparator."<init>":(Ljava/util/List;)V
      12: invokespecial #34                 // Method java/util/TreeMap."<init>":(Ljava/util/Comparator;)V
      15: astore_3
      16: aload_1
      17: invokeinterface #12,  1           // InterfaceMethod java/util/List.iterator:()Ljava/util/Iterator;
      22: astore        4
      24: aload         4
      26: invokeinterface #13,  1           // InterfaceMethod java/util/Iterator.hasNext:()Z
      31: ifeq          60
      34: aload         4
      36: invokeinterface #14,  1           // InterfaceMethod java/util/Iterator.next:()Ljava/lang/Object;
      41: astore        5
      43: aload_3
      44: aload         5
      46: invokevirtual #35                 // Method java/lang/Object.getClass:()Ljava/lang/Class;
      49: aload         5
      51: invokeinterface #36,  3           // InterfaceMethod java/util/Map.putIfAbsent:(Ljava/lang/Object;Ljava/lang/Object;)Ljava/lang/Object;
      56: pop
      57: goto          24
      60: new           #10                 // class java/util/ArrayList
      63: dup
      64: aload_3
      65: invokeinterface #37,  1           // InterfaceMethod java/util/Map.values:()Ljava/util/Collection;
      70: invokespecial #38                 // Method java/util/ArrayList."<init>":(Ljava/util/Collection;)V
      73: areturn

  private java.util.List<org.apache.dubbo.rpc.model.ModuleModel> getModuleModelsFromUrl(org.apache.dubbo.common.URL);
    Code:
       0: aconst_null
       1: astore_2
       2: aload_1
       3: invokevirtual #39                 // Method org/apache/dubbo/common/URL.getScopeModel:()Lorg/apache/dubbo/rpc/model/ScopeModel;
       6: astore_3
       7: aload_3
       8: instanceof    #40                 // class org/apache/dubbo/rpc/model/ApplicationModel
      11: ifeq          25
      14: aload_3
      15: checkcast     #40                 // class org/apache/dubbo/rpc/model/ApplicationModel
      18: invokevirtual #41                 // Method org/apache/dubbo/rpc/model/ApplicationModel.getPubModuleModels:()Ljava/util/List;
      21: astore_2
      22: goto          51
      25: aload_3
      26: instanceof    #15                 // class org/apache/dubbo/rpc/model/ModuleModel
      29: ifeq          51
      32: new           #10                 // class java/util/ArrayList
      35: dup
      36: invokespecial #11                 // Method java/util/ArrayList."<init>":()V
      39: astore_2
      40: aload_2
      41: aload_3
      42: checkcast     #15                 // class org/apache/dubbo/rpc/model/ModuleModel
      45: invokeinterface #18,  2           // InterfaceMethod java/util/List.add:(Ljava/lang/Object;)Z
      50: pop
      51: aload_2
      52: areturn
}
