Compiled from "FilterChainBuilder.java"
public class org.apache.dubbo.rpc.cluster.filter.FilterChainBuilder$CallbackRegistrationInvoker<T, FILTER extends org.apache.dubbo.rpc.BaseFilter> implements org.apache.dubbo.rpc.Invoker<T> {
  private static final org.apache.dubbo.common.logger.ErrorTypeAwareLogger LOGGER;

  final org.apache.dubbo.rpc.Invoker<T> filterInvoker;

  final java.util.List<FILTER> filters;

  public org.apache.dubbo.rpc.cluster.filter.FilterChainBuilder$CallbackRegistrationInvoker(org.apache.dubbo.rpc.Invoker<T>, java.util.List<FILTER>);
    Code:
       0: aload_0
       1: invokespecial #2                  // Method java/lang/Object."<init>":()V
       4: aload_0
       5: aload_1
       6: putfield      #3                  // Field filterInvoker:Lorg/apache/dubbo/rpc/Invoker;
       9: aload_0
      10: aload_2
      11: putfield      #4                  // Field filters:Ljava/util/List;
      14: return

  public org.apache.dubbo.rpc.Result invoke(org.apache.dubbo.rpc.Invocation) throws org.apache.dubbo.rpc.RpcException;
    Code:
       0: aload_0
       1: getfield      #3                  // Field filterInvoker:Lorg/apache/dubbo/rpc/Invoker;
       4: aload_1
       5: invokeinterface #5,  2            // InterfaceMethod org/apache/dubbo/rpc/Invoker.invoke:(Lorg/apache/dubbo/rpc/Invocation;)Lorg/apache/dubbo/rpc/Result;
      10: astore_2
      11: aload_2
      12: aload_0
      13: aload_1
      14: invokedynamic #6,  0              // InvokeDynamic #0:accept:(Lorg/apache/dubbo/rpc/cluster/filter/FilterChainBuilder$CallbackRegistrationInvoker;Lorg/apache/dubbo/rpc/Invocation;)Ljava/util/function/BiConsumer;
      19: invokeinterface #7,  2            // InterfaceMethod org/apache/dubbo/rpc/Result.whenCompleteWithContext:(Ljava/util/function/BiConsumer;)Lorg/apache/dubbo/rpc/Result;
      24: pop
      25: aload_2
      26: areturn

  public org.apache.dubbo.rpc.Invoker<T> getFilterInvoker();
    Code:
       0: aload_0
       1: getfield      #3                  // Field filterInvoker:Lorg/apache/dubbo/rpc/Invoker;
       4: areturn

  public java.lang.Class<T> getInterface();
    Code:
       0: aload_0
       1: getfield      #3                  // Field filterInvoker:Lorg/apache/dubbo/rpc/Invoker;
       4: invokeinterface #8,  1            // InterfaceMethod org/apache/dubbo/rpc/Invoker.getInterface:()Ljava/lang/Class;
       9: areturn

  public org.apache.dubbo.common.URL getUrl();
    Code:
       0: aload_0
       1: getfield      #3                  // Field filterInvoker:Lorg/apache/dubbo/rpc/Invoker;
       4: invokeinterface #9,  1            // InterfaceMethod org/apache/dubbo/rpc/Invoker.getUrl:()Lorg/apache/dubbo/common/URL;
       9: areturn

  public boolean isAvailable();
    Code:
       0: aload_0
       1: getfield      #3                  // Field filterInvoker:Lorg/apache/dubbo/rpc/Invoker;
       4: invokeinterface #10,  1           // InterfaceMethod org/apache/dubbo/rpc/Invoker.isAvailable:()Z
       9: ireturn

  public void destroy();
    Code:
       0: aload_0
       1: getfield      #3                  // Field filterInvoker:Lorg/apache/dubbo/rpc/Invoker;
       4: invokeinterface #11,  1           // InterfaceMethod org/apache/dubbo/rpc/Invoker.destroy:()V
       9: return

  private void lambda$invoke$1(org.apache.dubbo.rpc.Invocation, org.apache.dubbo.rpc.Result, java.lang.Throwable);
    Code:
       0: aconst_null
       1: astore        4
       3: aload_0
       4: getfield      #4                  // Field filters:Ljava/util/List;
       7: invokeinterface #12,  1           // InterfaceMethod java/util/List.size:()I
      12: iconst_1
      13: isub
      14: istore        5
      16: iload         5
      18: iflt          291
      21: aload_0
      22: getfield      #4                  // Field filters:Ljava/util/List;
      25: iload         5
      27: invokeinterface #13,  2           // InterfaceMethod java/util/List.get:(I)Ljava/lang/Object;
      32: checkcast     #14                 // class org/apache/dubbo/rpc/BaseFilter
      35: astore        6
      37: aload_1
      38: invokestatic  #15                 // Method org/apache/dubbo/rpc/InvocationProfilerUtils.releaseDetailProfiler:(Lorg/apache/dubbo/rpc/Invocation;)V
      41: aload         6
      43: instanceof    #16                 // class org/apache/dubbo/rpc/ListenableFilter
      46: ifeq          125
      49: aload         6
      51: checkcast     #16                 // class org/apache/dubbo/rpc/ListenableFilter
      54: astore        7
      56: aload         7
      58: aload_1
      59: invokevirtual #17                 // Method org/apache/dubbo/rpc/ListenableFilter.listener:(Lorg/apache/dubbo/rpc/Invocation;)Lorg/apache/dubbo/rpc/BaseFilter$Listener;
      62: astore        8
      64: aload         8
      66: ifnull        102
      69: aload_3
      70: ifnonnull     89
      73: aload         8
      75: aload_2
      76: aload_0
      77: getfield      #3                  // Field filterInvoker:Lorg/apache/dubbo/rpc/Invoker;
      80: aload_1
      81: invokeinterface #18,  4           // InterfaceMethod org/apache/dubbo/rpc/BaseFilter$Listener.onResponse:(Lorg/apache/dubbo/rpc/Result;Lorg/apache/dubbo/rpc/Invoker;Lorg/apache/dubbo/rpc/Invocation;)V
      86: goto          102
      89: aload         8
      91: aload_3
      92: aload_0
      93: getfield      #3                  // Field filterInvoker:Lorg/apache/dubbo/rpc/Invoker;
      96: aload_1
      97: invokeinterface #19,  4           // InterfaceMethod org/apache/dubbo/rpc/BaseFilter$Listener.onError:(Ljava/lang/Throwable;Lorg/apache/dubbo/rpc/Invoker;Lorg/apache/dubbo/rpc/Invocation;)V
     102: aload         7
     104: aload_1
     105: invokevirtual #20                 // Method org/apache/dubbo/rpc/ListenableFilter.removeListener:(Lorg/apache/dubbo/rpc/Invocation;)V
     108: goto          122
     111: astore        9
     113: aload         7
     115: aload_1
     116: invokevirtual #20                 // Method org/apache/dubbo/rpc/ListenableFilter.removeListener:(Lorg/apache/dubbo/rpc/Invocation;)V
     119: aload         9
     121: athrow
     122: goto          173
     125: aload         6
     127: instanceof    #21                 // class org/apache/dubbo/rpc/BaseFilter$Listener
     130: ifeq          173
     133: aload         6
     135: checkcast     #21                 // class org/apache/dubbo/rpc/BaseFilter$Listener
     138: astore        7
     140: aload_3
     141: ifnonnull     160
     144: aload         7
     146: aload_2
     147: aload_0
     148: getfield      #3                  // Field filterInvoker:Lorg/apache/dubbo/rpc/Invoker;
     151: aload_1
     152: invokeinterface #18,  4           // InterfaceMethod org/apache/dubbo/rpc/BaseFilter$Listener.onResponse:(Lorg/apache/dubbo/rpc/Result;Lorg/apache/dubbo/rpc/Invoker;Lorg/apache/dubbo/rpc/Invocation;)V
     157: goto          173
     160: aload         7
     162: aload_3
     163: aload_0
     164: getfield      #3                  // Field filterInvoker:Lorg/apache/dubbo/rpc/Invoker;
     167: aload_1
     168: invokeinterface #19,  4           // InterfaceMethod org/apache/dubbo/rpc/BaseFilter$Listener.onError:(Ljava/lang/Throwable;Lorg/apache/dubbo/rpc/Invoker;Lorg/apache/dubbo/rpc/Invocation;)V
     173: goto          285
     176: astore        7
     178: getstatic     #23                 // Field LOGGER:Lorg/apache/dubbo/common/logger/ErrorTypeAwareLogger;
     181: ldc           #24                 // String 2-19
     183: ldc           #25                 // String the custom filter is abnormal
     185: ldc           #26                 // String
     187: ldc           #27                 // String Exception occurred while executing the %s filter named %s.
     189: iconst_2
     190: anewarray     #28                 // class java/lang/Object
     193: dup
     194: iconst_0
     195: iload         5
     197: invokestatic  #29                 // Method java/lang/Integer.valueOf:(I)Ljava/lang/Integer;
     200: aastore
     201: dup
     202: iconst_1
     203: aload         6
     205: invokevirtual #30                 // Method java/lang/Object.getClass:()Ljava/lang/Class;
     208: invokevirtual #31                 // Method java/lang/Class.getSimpleName:()Ljava/lang/String;
     211: aastore
     212: invokestatic  #32                 // Method java/lang/String.format:(Ljava/lang/String;[Ljava/lang/Object;)Ljava/lang/String;
     215: invokeinterface #33,  5           // InterfaceMethod org/apache/dubbo/common/logger/ErrorTypeAwareLogger.error:(Ljava/lang/String;Ljava/lang/String;Ljava/lang/String;Ljava/lang/String;)V
     220: getstatic     #23                 // Field LOGGER:Lorg/apache/dubbo/common/logger/ErrorTypeAwareLogger;
     223: invokeinterface #34,  1           // InterfaceMethod org/apache/dubbo/common/logger/ErrorTypeAwareLogger.isDebugEnabled:()Z
     228: ifeq          278
     231: getstatic     #23                 // Field LOGGER:Lorg/apache/dubbo/common/logger/ErrorTypeAwareLogger;
     234: ldc           #35                 // String Whole filter list is: %s
     236: iconst_1
     237: anewarray     #28                 // class java/lang/Object
     240: dup
     241: iconst_0
     242: aload_0
     243: getfield      #4                  // Field filters:Ljava/util/List;
     246: invokeinterface #36,  1           // InterfaceMethod java/util/List.stream:()Ljava/util/stream/Stream;
     251: invokedynamic #37,  0             // InvokeDynamic #1:apply:()Ljava/util/function/Function;
     256: invokeinterface #38,  2           // InterfaceMethod java/util/stream/Stream.map:(Ljava/util/function/Function;)Ljava/util/stream/Stream;
     261: invokestatic  #39                 // Method java/util/stream/Collectors.toList:()Ljava/util/stream/Collector;
     264: invokeinterface #40,  2           // InterfaceMethod java/util/stream/Stream.collect:(Ljava/util/stream/Collector;)Ljava/lang/Object;
     269: aastore
     270: invokestatic  #32                 // Method java/lang/String.format:(Ljava/lang/String;[Ljava/lang/Object;)Ljava/lang/String;
     273: invokeinterface #41,  2           // InterfaceMethod org/apache/dubbo/common/logger/ErrorTypeAwareLogger.debug:(Ljava/lang/String;)V
     278: aload         7
     280: astore        4
     282: aload         7
     284: astore_3
     285: iinc          5, -1
     288: goto          16
     291: aload         4
     293: ifnull        299
     296: aload         4
     298: athrow
     299: return
    Exception table:
       from    to  target type
          64   102   111   any
         111   113   111   any
          37   173   176   Class java/lang/RuntimeException

  private static java.lang.String lambda$null$0(org.apache.dubbo.rpc.BaseFilter);
    Code:
       0: aload_0
       1: invokevirtual #30                 // Method java/lang/Object.getClass:()Ljava/lang/Class;
       4: invokevirtual #31                 // Method java/lang/Class.getSimpleName:()Ljava/lang/String;
       7: areturn

  static {};
    Code:
       0: ldc           #42                 // class org/apache/dubbo/rpc/cluster/filter/FilterChainBuilder$CallbackRegistrationInvoker
       2: invokestatic  #43                 // Method org/apache/dubbo/common/logger/LoggerFactory.getErrorTypeAwareLogger:(Ljava/lang/Class;)Lorg/apache/dubbo/common/logger/ErrorTypeAwareLogger;
       5: putstatic     #23                 // Field LOGGER:Lorg/apache/dubbo/common/logger/ErrorTypeAwareLogger;
       8: return
}
