Compiled from "FilterChainBuilder.java"
public class org.apache.dubbo.rpc.cluster.filter.FilterChainBuilder$ClusterFilterChainNode<T, TYPE extends org.apache.dubbo.rpc.cluster.ClusterInvoker<T>, FILTER extends org.apache.dubbo.rpc.BaseFilter> extends org.apache.dubbo.rpc.cluster.filter.FilterChainBuilder$FilterChainNode<T, TYPE, FILTER> implements org.apache.dubbo.rpc.cluster.ClusterInvoker<T> {
  public org.apache.dubbo.rpc.cluster.filter.FilterChainBuilder$ClusterFilterChainNode(TYPE, org.apache.dubbo.rpc.Invoker<T>, FILTER);
    Code:
       0: aload_0
       1: aload_1
       2: aload_2
       3: aload_3
       4: invokespecial #1                  // Method org/apache/dubbo/rpc/cluster/filter/FilterChainBuilder$FilterChainNode."<init>":(Lorg/apache/dubbo/rpc/Invoker;Lorg/apache/dubbo/rpc/Invoker;Lorg/apache/dubbo/rpc/BaseFilter;)V
       7: return

  public org.apache.dubbo.common.URL getRegistryUrl();
    Code:
       0: aload_0
       1: invokevirtual #2                  // Method getOriginalInvoker:()Lorg/apache/dubbo/rpc/Invoker;
       4: checkcast     #3                  // class org/apache/dubbo/rpc/cluster/ClusterInvoker
       7: invokeinterface #4,  1            // InterfaceMethod org/apache/dubbo/rpc/cluster/ClusterInvoker.getRegistryUrl:()Lorg/apache/dubbo/common/URL;
      12: areturn

  public org.apache.dubbo.rpc.cluster.Directory<T> getDirectory();
    Code:
       0: aload_0
       1: invokevirtual #2                  // Method getOriginalInvoker:()Lorg/apache/dubbo/rpc/Invoker;
       4: checkcast     #3                  // class org/apache/dubbo/rpc/cluster/ClusterInvoker
       7: invokeinterface #5,  1            // InterfaceMethod org/apache/dubbo/rpc/cluster/ClusterInvoker.getDirectory:()Lorg/apache/dubbo/rpc/cluster/Directory;
      12: areturn

  public boolean isDestroyed();
    Code:
       0: aload_0
       1: invokevirtual #2                  // Method getOriginalInvoker:()Lorg/apache/dubbo/rpc/Invoker;
       4: checkcast     #3                  // class org/apache/dubbo/rpc/cluster/ClusterInvoker
       7: invokeinterface #6,  1            // InterfaceMethod org/apache/dubbo/rpc/cluster/ClusterInvoker.isDestroyed:()Z
      12: ireturn
}
