Compiled from "FilterChainBuilder.java"
public class org.apache.dubbo.rpc.cluster.filter.FilterChainBuilder$ClusterCallbackRegistrationInvoker<T, FILTER extends org.apache.dubbo.rpc.BaseFilter> extends org.apache.dubbo.rpc.cluster.filter.FilterChainBuilder$CallbackRegistrationInvoker<T, FILTER> implements org.apache.dubbo.rpc.cluster.ClusterInvoker<T> {
  private org.apache.dubbo.rpc.cluster.ClusterInvoker<T> originalInvoker;

  public org.apache.dubbo.rpc.cluster.filter.FilterChainBuilder$ClusterCallbackRegistrationInvoker(org.apache.dubbo.rpc.cluster.ClusterInvoker<T>, org.apache.dubbo.rpc.Invoker<T>, java.util.List<FILTER>);
    Code:
       0: aload_0
       1: aload_2
       2: aload_3
       3: invokespecial #1                  // Method org/apache/dubbo/rpc/cluster/filter/FilterChainBuilder$CallbackRegistrationInvoker."<init>":(Lorg/apache/dubbo/rpc/Invoker;Ljava/util/List;)V
       6: aload_0
       7: aload_1
       8: putfield      #2                  // Field originalInvoker:Lorg/apache/dubbo/rpc/cluster/ClusterInvoker;
      11: return

  public org.apache.dubbo.rpc.cluster.ClusterInvoker<T> getOriginalInvoker();
    Code:
       0: aload_0
       1: getfield      #2                  // Field originalInvoker:Lorg/apache/dubbo/rpc/cluster/ClusterInvoker;
       4: areturn

  public org.apache.dubbo.common.URL getRegistryUrl();
    Code:
       0: aload_0
       1: invokevirtual #3                  // Method getOriginalInvoker:()Lorg/apache/dubbo/rpc/cluster/ClusterInvoker;
       4: invokeinterface #4,  1            // InterfaceMethod org/apache/dubbo/rpc/cluster/ClusterInvoker.getRegistryUrl:()Lorg/apache/dubbo/common/URL;
       9: areturn

  public org.apache.dubbo.rpc.cluster.Directory<T> getDirectory();
    Code:
       0: aload_0
       1: invokevirtual #3                  // Method getOriginalInvoker:()Lorg/apache/dubbo/rpc/cluster/ClusterInvoker;
       4: invokeinterface #5,  1            // InterfaceMethod org/apache/dubbo/rpc/cluster/ClusterInvoker.getDirectory:()Lorg/apache/dubbo/rpc/cluster/Directory;
       9: areturn

  public boolean isDestroyed();
    Code:
       0: aload_0
       1: invokevirtual #3                  // Method getOriginalInvoker:()Lorg/apache/dubbo/rpc/cluster/ClusterInvoker;
       4: invokeinterface #6,  1            // InterfaceMethod org/apache/dubbo/rpc/cluster/ClusterInvoker.isDestroyed:()Z
       9: ireturn
}
