Compiled from "AdaptiveCompiler.java"
public class org.apache.dubbo.common.compiler.support.AdaptiveCompiler implements org.apache.dubbo.common.compiler.Compiler,org.apache.dubbo.rpc.model.ScopeModelAware {
  private org.apache.dubbo.rpc.model.FrameworkModel frameworkModel;

  private static volatile java.lang.String DEFAULT_COMPILER;

  public org.apache.dubbo.common.compiler.support.AdaptiveCompiler();
    Code:
       0: aload_0
       1: invokespecial #1                  // Method java/lang/Object."<init>":()V
       4: return

  public void setFrameworkModel(org.apache.dubbo.rpc.model.FrameworkModel);
    Code:
       0: aload_0
       1: aload_1
       2: putfield      #2                  // Field frameworkModel:Lorg/apache/dubbo/rpc/model/FrameworkModel;
       5: return

  public static void setDefaultCompiler(java.lang.String);
    Code:
       0: aload_0
       1: putstatic     #3                  // Field DEFAULT_COMPILER:Ljava/lang/String;
       4: return

  public java.lang.Class<?> compile(java.lang.Class<?>, java.lang.String, java.lang.ClassLoader);
    Code:
       0: aload_0
       1: getfield      #2                  // Field frameworkModel:Lorg/apache/dubbo/rpc/model/FrameworkModel;
       4: ldc           #4                  // class org/apache/dubbo/common/compiler/Compiler
       6: invokevirtual #5                  // Method org/apache/dubbo/rpc/model/FrameworkModel.getExtensionLoader:(Ljava/lang/Class;)Lorg/apache/dubbo/common/extension/ExtensionLoader;
       9: astore        5
      11: getstatic     #3                  // Field DEFAULT_COMPILER:Ljava/lang/String;
      14: astore        6
      16: aload         6
      18: ifnull        44
      21: aload         6
      23: invokevirtual #6                  // Method java/lang/String.length:()I
      26: ifle          44
      29: aload         5
      31: aload         6
      33: invokevirtual #7                  // Method org/apache/dubbo/common/extension/ExtensionLoader.getExtension:(Ljava/lang/String;)Ljava/lang/Object;
      36: checkcast     #4                  // class org/apache/dubbo/common/compiler/Compiler
      39: astore        4
      41: goto          54
      44: aload         5
      46: invokevirtual #8                  // Method org/apache/dubbo/common/extension/ExtensionLoader.getDefaultExtension:()Ljava/lang/Object;
      49: checkcast     #4                  // class org/apache/dubbo/common/compiler/Compiler
      52: astore        4
      54: aload         4
      56: aload_1
      57: aload_2
      58: aload_3
      59: invokeinterface #9,  4            // InterfaceMethod org/apache/dubbo/common/compiler/Compiler.compile:(Ljava/lang/Class;Ljava/lang/String;Ljava/lang/ClassLoader;)Ljava/lang/Class;
      64: areturn
}
