Compiled from "CtClassBuilder.java"
public class org.apache.dubbo.common.compiler.support.CtClassBuilder {
  private java.lang.String className;

  private java.lang.String superClassName;

  private final java.util.List<java.lang.String> imports;

  private final java.util.Map<java.lang.String, java.lang.String> fullNames;

  private final java.util.List<java.lang.String> ifaces;

  private final java.util.List<java.lang.String> constructors;

  private final java.util.List<java.lang.String> fields;

  private final java.util.List<java.lang.String> methods;

  public org.apache.dubbo.common.compiler.support.CtClassBuilder();
    Code:
       0: aload_0
       1: invokespecial #1                  // Method java/lang/Object."<init>":()V
       4: aload_0
       5: ldc           #2                  // String java.lang.Object
       7: putfield      #3                  // Field superClassName:Ljava/lang/String;
      10: aload_0
      11: new           #4                  // class java/util/ArrayList
      14: dup
      15: invokespecial #5                  // Method java/util/ArrayList."<init>":()V
      18: putfield      #6                  // Field imports:Ljava/util/List;
      21: aload_0
      22: new           #7                  // class java/util/HashMap
      25: dup
      26: invokespecial #8                  // Method java/util/HashMap."<init>":()V
      29: putfield      #9                  // Field fullNames:Ljava/util/Map;
      32: aload_0
      33: new           #4                  // class java/util/ArrayList
      36: dup
      37: invokespecial #5                  // Method java/util/ArrayList."<init>":()V
      40: putfield      #10                 // Field ifaces:Ljava/util/List;
      43: aload_0
      44: new           #4                  // class java/util/ArrayList
      47: dup
      48: invokespecial #5                  // Method java/util/ArrayList."<init>":()V
      51: putfield      #11                 // Field constructors:Ljava/util/List;
      54: aload_0
      55: new           #4                  // class java/util/ArrayList
      58: dup
      59: invokespecial #5                  // Method java/util/ArrayList."<init>":()V
      62: putfield      #12                 // Field fields:Ljava/util/List;
      65: aload_0
      66: new           #4                  // class java/util/ArrayList
      69: dup
      70: invokespecial #5                  // Method java/util/ArrayList."<init>":()V
      73: putfield      #13                 // Field methods:Ljava/util/List;
      76: return

  public java.lang.String getClassName();
    Code:
       0: aload_0
       1: getfield      #14                 // Field className:Ljava/lang/String;
       4: areturn

  public void setClassName(java.lang.String);
    Code:
       0: aload_0
       1: aload_1
       2: putfield      #14                 // Field className:Ljava/lang/String;
       5: return

  public java.lang.String getSuperClassName();
    Code:
       0: aload_0
       1: getfield      #3                  // Field superClassName:Ljava/lang/String;
       4: areturn

  public void setSuperClassName(java.lang.String);
    Code:
       0: aload_0
       1: aload_0
       2: aload_1
       3: invokevirtual #15                 // Method getQualifiedClassName:(Ljava/lang/String;)Ljava/lang/String;
       6: putfield      #3                  // Field superClassName:Ljava/lang/String;
       9: return

  public java.util.List<java.lang.String> getImports();
    Code:
       0: aload_0
       1: getfield      #6                  // Field imports:Ljava/util/List;
       4: areturn

  public void addImports(java.lang.String);
    Code:
       0: aload_1
       1: bipush        46
       3: invokevirtual #16                 // Method java/lang/String.lastIndexOf:(I)I
       6: istore_2
       7: iload_2
       8: ifle          56
      11: aload_1
      12: iconst_0
      13: iload_2
      14: invokevirtual #17                 // Method java/lang/String.substring:(II)Ljava/lang/String;
      17: astore_3
      18: aload_0
      19: getfield      #6                  // Field imports:Ljava/util/List;
      22: aload_3
      23: invokeinterface #18,  2           // InterfaceMethod java/util/List.add:(Ljava/lang/Object;)Z
      28: pop
      29: aload_1
      30: ldc           #19                 // String .*
      32: invokevirtual #20                 // Method java/lang/String.endsWith:(Ljava/lang/String;)Z
      35: ifne          56
      38: aload_0
      39: getfield      #9                  // Field fullNames:Ljava/util/Map;
      42: aload_1
      43: iload_2
      44: iconst_1
      45: iadd
      46: invokevirtual #21                 // Method java/lang/String.substring:(I)Ljava/lang/String;
      49: aload_1
      50: invokeinterface #22,  3           // InterfaceMethod java/util/Map.put:(Ljava/lang/Object;Ljava/lang/Object;)Ljava/lang/Object;
      55: pop
      56: return

  public java.util.List<java.lang.String> getInterfaces();
    Code:
       0: aload_0
       1: getfield      #10                 // Field ifaces:Ljava/util/List;
       4: areturn

  public void addInterface(java.lang.String);
    Code:
       0: aload_0
       1: getfield      #10                 // Field ifaces:Ljava/util/List;
       4: aload_0
       5: aload_1
       6: invokevirtual #15                 // Method getQualifiedClassName:(Ljava/lang/String;)Ljava/lang/String;
       9: invokeinterface #18,  2           // InterfaceMethod java/util/List.add:(Ljava/lang/Object;)Z
      14: pop
      15: return

  public java.util.List<java.lang.String> getConstructors();
    Code:
       0: aload_0
       1: getfield      #11                 // Field constructors:Ljava/util/List;
       4: areturn

  public void addConstructor(java.lang.String);
    Code:
       0: aload_0
       1: getfield      #11                 // Field constructors:Ljava/util/List;
       4: aload_1
       5: invokeinterface #18,  2           // InterfaceMethod java/util/List.add:(Ljava/lang/Object;)Z
      10: pop
      11: return

  public java.util.List<java.lang.String> getFields();
    Code:
       0: aload_0
       1: getfield      #12                 // Field fields:Ljava/util/List;
       4: areturn

  public void addField(java.lang.String);
    Code:
       0: aload_0
       1: getfield      #12                 // Field fields:Ljava/util/List;
       4: aload_1
       5: invokeinterface #18,  2           // InterfaceMethod java/util/List.add:(Ljava/lang/Object;)Z
      10: pop
      11: return

  public java.util.List<java.lang.String> getMethods();
    Code:
       0: aload_0
       1: getfield      #13                 // Field methods:Ljava/util/List;
       4: areturn

  public void addMethod(java.lang.String);
    Code:
       0: aload_0
       1: getfield      #13                 // Field methods:Ljava/util/List;
       4: aload_1
       5: invokeinterface #18,  2           // InterfaceMethod java/util/List.add:(Ljava/lang/Object;)Z
      10: pop
      11: return

  protected java.lang.String getQualifiedClassName(java.lang.String);
    Code:
       0: aload_1
       1: ldc           #23                 // String .
       3: invokevirtual #24                 // Method java/lang/String.contains:(Ljava/lang/CharSequence;)Z
       6: ifeq          11
       9: aload_1
      10: areturn
      11: aload_0
      12: getfield      #9                  // Field fullNames:Ljava/util/Map;
      15: aload_1
      16: invokeinterface #25,  2           // InterfaceMethod java/util/Map.containsKey:(Ljava/lang/Object;)Z
      21: ifeq          38
      24: aload_0
      25: getfield      #9                  // Field fullNames:Ljava/util/Map;
      28: aload_1
      29: invokeinterface #26,  2           // InterfaceMethod java/util/Map.get:(Ljava/lang/Object;)Ljava/lang/Object;
      34: checkcast     #27                 // class java/lang/String
      37: areturn
      38: aload_0
      39: getfield      #6                  // Field imports:Ljava/util/List;
      42: iconst_0
      43: anewarray     #27                 // class java/lang/String
      46: invokeinterface #28,  2           // InterfaceMethod java/util/List.toArray:([Ljava/lang/Object;)[Ljava/lang/Object;
      51: checkcast     #29                 // class "[Ljava/lang/String;"
      54: aload_1
      55: invokestatic  #30                 // Method org/apache/dubbo/common/compiler/support/ClassUtils.forName:([Ljava/lang/String;Ljava/lang/String;)Ljava/lang/Class;
      58: invokevirtual #31                 // Method java/lang/Class.getName:()Ljava/lang/String;
      61: areturn

  public javassist.CtClass build(java.lang.ClassLoader) throws javassist.NotFoundException, javassist.CannotCompileException;
    Code:
       0: new           #32                 // class javassist/ClassPool
       3: dup
       4: iconst_1
       5: invokespecial #33                 // Method javassist/ClassPool."<init>":(Z)V
       8: astore_2
       9: aload_2
      10: new           #34                 // class javassist/LoaderClassPath
      13: dup
      14: aload_1
      15: invokespecial #35                 // Method javassist/LoaderClassPath."<init>":(Ljava/lang/ClassLoader;)V
      18: invokevirtual #36                 // Method javassist/ClassPool.insertClassPath:(Ljavassist/ClassPath;)Ljavassist/ClassPath;
      21: pop
      22: aload_2
      23: new           #37                 // class org/apache/dubbo/common/bytecode/DubboLoaderClassPath
      26: dup
      27: invokespecial #38                 // Method org/apache/dubbo/common/bytecode/DubboLoaderClassPath."<init>":()V
      30: invokevirtual #36                 // Method javassist/ClassPool.insertClassPath:(Ljavassist/ClassPath;)Ljavassist/ClassPath;
      33: pop
      34: aload_2
      35: aload_0
      36: getfield      #14                 // Field className:Ljava/lang/String;
      39: aload_2
      40: aload_0
      41: getfield      #3                  // Field superClassName:Ljava/lang/String;
      44: invokevirtual #39                 // Method javassist/ClassPool.get:(Ljava/lang/String;)Ljavassist/CtClass;
      47: invokevirtual #40                 // Method javassist/ClassPool.makeClass:(Ljava/lang/String;Ljavassist/CtClass;)Ljavassist/CtClass;
      50: astore_3
      51: aload_0
      52: getfield      #6                  // Field imports:Ljava/util/List;
      55: aload_2
      56: dup
      57: invokevirtual #41                 // Method java/lang/Object.getClass:()Ljava/lang/Class;
      60: pop
      61: invokedynamic #42,  0             // InvokeDynamic #0:accept:(Ljavassist/ClassPool;)Ljava/util/function/Consumer;
      66: invokeinterface #43,  2           // InterfaceMethod java/util/List.forEach:(Ljava/util/function/Consumer;)V
      71: aload_0
      72: getfield      #10                 // Field ifaces:Ljava/util/List;
      75: invokeinterface #44,  1           // InterfaceMethod java/util/List.iterator:()Ljava/util/Iterator;
      80: astore        4
      82: aload         4
      84: invokeinterface #45,  1           // InterfaceMethod java/util/Iterator.hasNext:()Z
      89: ifeq          117
      92: aload         4
      94: invokeinterface #46,  1           // InterfaceMethod java/util/Iterator.next:()Ljava/lang/Object;
      99: checkcast     #27                 // class java/lang/String
     102: astore        5
     104: aload_3
     105: aload_2
     106: aload         5
     108: invokevirtual #39                 // Method javassist/ClassPool.get:(Ljava/lang/String;)Ljavassist/CtClass;
     111: invokevirtual #47                 // Method javassist/CtClass.addInterface:(Ljavassist/CtClass;)V
     114: goto          82
     117: aload_0
     118: getfield      #11                 // Field constructors:Ljava/util/List;
     121: invokeinterface #44,  1           // InterfaceMethod java/util/List.iterator:()Ljava/util/Iterator;
     126: astore        4
     128: aload         4
     130: invokeinterface #45,  1           // InterfaceMethod java/util/Iterator.hasNext:()Z
     135: ifeq          163
     138: aload         4
     140: invokeinterface #46,  1           // InterfaceMethod java/util/Iterator.next:()Ljava/lang/Object;
     145: checkcast     #27                 // class java/lang/String
     148: astore        5
     150: aload_3
     151: aload         5
     153: aload_3
     154: invokestatic  #48                 // Method javassist/CtNewConstructor.make:(Ljava/lang/String;Ljavassist/CtClass;)Ljavassist/CtConstructor;
     157: invokevirtual #49                 // Method javassist/CtClass.addConstructor:(Ljavassist/CtConstructor;)V
     160: goto          128
     163: aload_0
     164: getfield      #12                 // Field fields:Ljava/util/List;
     167: invokeinterface #44,  1           // InterfaceMethod java/util/List.iterator:()Ljava/util/Iterator;
     172: astore        4
     174: aload         4
     176: invokeinterface #45,  1           // InterfaceMethod java/util/Iterator.hasNext:()Z
     181: ifeq          209
     184: aload         4
     186: invokeinterface #46,  1           // InterfaceMethod java/util/Iterator.next:()Ljava/lang/Object;
     191: checkcast     #27                 // class java/lang/String
     194: astore        5
     196: aload_3
     197: aload         5
     199: aload_3
     200: invokestatic  #50                 // Method javassist/CtField.make:(Ljava/lang/String;Ljavassist/CtClass;)Ljavassist/CtField;
     203: invokevirtual #51                 // Method javassist/CtClass.addField:(Ljavassist/CtField;)V
     206: goto          174
     209: aload_0
     210: getfield      #13                 // Field methods:Ljava/util/List;
     213: invokeinterface #44,  1           // InterfaceMethod java/util/List.iterator:()Ljava/util/Iterator;
     218: astore        4
     220: aload         4
     222: invokeinterface #45,  1           // InterfaceMethod java/util/Iterator.hasNext:()Z
     227: ifeq          255
     230: aload         4
     232: invokeinterface #46,  1           // InterfaceMethod java/util/Iterator.next:()Ljava/lang/Object;
     237: checkcast     #27                 // class java/lang/String
     240: astore        5
     242: aload_3
     243: aload         5
     245: aload_3
     246: invokestatic  #52                 // Method javassist/CtNewMethod.make:(Ljava/lang/String;Ljavassist/CtClass;)Ljavassist/CtMethod;
     249: invokevirtual #53                 // Method javassist/CtClass.addMethod:(Ljavassist/CtMethod;)V
     252: goto          220
     255: aload_3
     256: areturn
}
