Compiled from "JavassistCompiler.java"
public class org.apache.dubbo.common.compiler.support.JavassistCompiler extends org.apache.dubbo.common.compiler.support.AbstractCompiler {
  private static final java.util.regex.Pattern IMPORT_PATTERN;

  private static final java.util.regex.Pattern EXTENDS_PATTERN;

  private static final java.util.regex.Pattern IMPLEMENTS_PATTERN;

  private static final java.util.regex.Pattern METHODS_PATTERN;

  private static final java.util.regex.Pattern FIELD_PATTERN;

  public org.apache.dubbo.common.compiler.support.JavassistCompiler();
    Code:
       0: aload_0
       1: invokespecial #1                  // Method org/apache/dubbo/common/compiler/support/AbstractCompiler."<init>":()V
       4: return

  public java.lang.Class<?> doCompile(java.lang.Class<?>, java.lang.ClassLoader, java.lang.String, java.lang.String) throws java.lang.Throwable;
    Code:
       0: new           #2                  // class org/apache/dubbo/common/compiler/support/CtClassBuilder
       3: dup
       4: invokespecial #3                  // Method org/apache/dubbo/common/compiler/support/CtClassBuilder."<init>":()V
       7: astore        5
       9: aload         5
      11: aload_3
      12: invokevirtual #4                  // Method org/apache/dubbo/common/compiler/support/CtClassBuilder.setClassName:(Ljava/lang/String;)V
      15: getstatic     #5                  // Field IMPORT_PATTERN:Ljava/util/regex/Pattern;
      18: aload         4
      20: invokevirtual #6                  // Method java/util/regex/Pattern.matcher:(Ljava/lang/CharSequence;)Ljava/util/regex/Matcher;
      23: astore        6
      25: aload         6
      27: invokevirtual #7                  // Method java/util/regex/Matcher.find:()Z
      30: ifeq          50
      33: aload         5
      35: aload         6
      37: iconst_1
      38: invokevirtual #8                  // Method java/util/regex/Matcher.group:(I)Ljava/lang/String;
      41: invokevirtual #9                  // Method java/lang/String.trim:()Ljava/lang/String;
      44: invokevirtual #10                 // Method org/apache/dubbo/common/compiler/support/CtClassBuilder.addImports:(Ljava/lang/String;)V
      47: goto          25
      50: getstatic     #11                 // Field EXTENDS_PATTERN:Ljava/util/regex/Pattern;
      53: aload         4
      55: invokevirtual #6                  // Method java/util/regex/Pattern.matcher:(Ljava/lang/CharSequence;)Ljava/util/regex/Matcher;
      58: astore        6
      60: aload         6
      62: invokevirtual #7                  // Method java/util/regex/Matcher.find:()Z
      65: ifeq          82
      68: aload         5
      70: aload         6
      72: iconst_1
      73: invokevirtual #8                  // Method java/util/regex/Matcher.group:(I)Ljava/lang/String;
      76: invokevirtual #9                  // Method java/lang/String.trim:()Ljava/lang/String;
      79: invokevirtual #12                 // Method org/apache/dubbo/common/compiler/support/CtClassBuilder.setSuperClassName:(Ljava/lang/String;)V
      82: getstatic     #13                 // Field IMPLEMENTS_PATTERN:Ljava/util/regex/Pattern;
      85: aload         4
      87: invokevirtual #6                  // Method java/util/regex/Pattern.matcher:(Ljava/lang/CharSequence;)Ljava/util/regex/Matcher;
      90: astore        6
      92: aload         6
      94: invokevirtual #7                  // Method java/util/regex/Matcher.find:()Z
      97: ifeq          133
     100: aload         6
     102: iconst_1
     103: invokevirtual #8                  // Method java/util/regex/Matcher.group:(I)Ljava/lang/String;
     106: invokevirtual #9                  // Method java/lang/String.trim:()Ljava/lang/String;
     109: ldc           #14                 // String \\,
     111: invokevirtual #15                 // Method java/lang/String.split:(Ljava/lang/String;)[Ljava/lang/String;
     114: astore        7
     116: aload         7
     118: invokestatic  #16                 // Method java/util/Arrays.stream:([Ljava/lang/Object;)Ljava/util/stream/Stream;
     121: aload         5
     123: invokedynamic #17,  0             // InvokeDynamic #0:accept:(Lorg/apache/dubbo/common/compiler/support/CtClassBuilder;)Ljava/util/function/Consumer;
     128: invokeinterface #18,  2           // InterfaceMethod java/util/stream/Stream.forEach:(Ljava/util/function/Consumer;)V
     133: aload         4
     135: aload         4
     137: bipush        123
     139: invokevirtual #19                 // Method java/lang/String.indexOf:(I)I
     142: iconst_1
     143: iadd
     144: aload         4
     146: invokevirtual #20                 // Method java/lang/String.length:()I
     149: iconst_1
     150: isub
     151: invokevirtual #21                 // Method java/lang/String.substring:(II)Ljava/lang/String;
     154: astore        7
     156: getstatic     #22                 // Field METHODS_PATTERN:Ljava/util/regex/Pattern;
     159: aload         7
     161: invokevirtual #23                 // Method java/util/regex/Pattern.split:(Ljava/lang/CharSequence;)[Ljava/lang/String;
     164: astore        8
     166: aload_3
     167: invokestatic  #24                 // Method org/apache/dubbo/common/compiler/support/ClassUtils.getSimpleClassName:(Ljava/lang/String;)Ljava/lang/String;
     170: astore        9
     172: aload         8
     174: invokestatic  #16                 // Method java/util/Arrays.stream:([Ljava/lang/Object;)Ljava/util/stream/Stream;
     177: invokedynamic #25,  0             // InvokeDynamic #1:apply:()Ljava/util/function/Function;
     182: invokeinterface #26,  2           // InterfaceMethod java/util/stream/Stream.map:(Ljava/util/function/Function;)Ljava/util/stream/Stream;
     187: invokedynamic #27,  0             // InvokeDynamic #2:test:()Ljava/util/function/Predicate;
     192: invokeinterface #28,  2           // InterfaceMethod java/util/stream/Stream.filter:(Ljava/util/function/Predicate;)Ljava/util/stream/Stream;
     197: aload         9
     199: aload         5
     201: invokedynamic #29,  0             // InvokeDynamic #3:accept:(Ljava/lang/String;Lorg/apache/dubbo/common/compiler/support/CtClassBuilder;)Ljava/util/function/Consumer;
     206: invokeinterface #18,  2           // InterfaceMethod java/util/stream/Stream.forEach:(Ljava/util/function/Consumer;)V
     211: aload         5
     213: aload_2
     214: invokevirtual #30                 // Method org/apache/dubbo/common/compiler/support/CtClassBuilder.build:(Ljava/lang/ClassLoader;)Ljavassist/CtClass;
     217: astore        10
     219: aload         10
     221: invokevirtual #31                 // Method javassist/CtClass.getClassPool:()Ljavassist/ClassPool;
     224: astore        11
     226: aload_2
     227: ifnonnull     236
     230: aload         11
     232: invokevirtual #32                 // Method javassist/ClassPool.getClassLoader:()Ljava/lang/ClassLoader;
     235: astore_2
     236: aload         11
     238: new           #33                 // class javassist/LoaderClassPath
     241: dup
     242: aload_2
     243: invokespecial #34                 // Method javassist/LoaderClassPath."<init>":(Ljava/lang/ClassLoader;)V
     246: invokevirtual #35                 // Method javassist/ClassPool.insertClassPath:(Ljavassist/ClassPath;)Ljavassist/ClassPath;
     249: pop
     250: aload         11
     252: new           #36                 // class org/apache/dubbo/common/bytecode/DubboLoaderClassPath
     255: dup
     256: invokespecial #37                 // Method org/apache/dubbo/common/bytecode/DubboLoaderClassPath."<init>":()V
     259: invokevirtual #35                 // Method javassist/ClassPool.insertClassPath:(Ljavassist/ClassPath;)Ljavassist/ClassPath;
     262: pop
     263: aload         11
     265: aload         10
     267: aload_1
     268: aload_2
     269: ldc           #38                 // class org/apache/dubbo/common/compiler/support/JavassistCompiler
     271: invokevirtual #39                 // Method java/lang/Class.getProtectionDomain:()Ljava/security/ProtectionDomain;
     274: invokevirtual #40                 // Method javassist/ClassPool.toClass:(Ljavassist/CtClass;Ljava/lang/Class;Ljava/lang/ClassLoader;Ljava/security/ProtectionDomain;)Ljava/lang/Class;
     277: areturn
     278: astore        12
     280: aload         12
     282: instanceof    #42                 // class javassist/CannotCompileException
     285: ifne          302
     288: aload         11
     290: aload         10
     292: aload_2
     293: ldc           #38                 // class org/apache/dubbo/common/compiler/support/JavassistCompiler
     295: invokevirtual #39                 // Method java/lang/Class.getProtectionDomain:()Ljava/security/ProtectionDomain;
     298: invokevirtual #43                 // Method javassist/ClassPool.toClass:(Ljavassist/CtClass;Ljava/lang/ClassLoader;Ljava/security/ProtectionDomain;)Ljava/lang/Class;
     301: areturn
     302: aload         12
     304: athrow
    Exception table:
       from    to  target type
         263   277   278   Class java/lang/Throwable

  private static void lambda$doCompile$2(java.lang.String, org.apache.dubbo.common.compiler.support.CtClassBuilder, java.lang.String);
    Code:
       0: aload_2
       1: aload_0
       2: invokevirtual #44                 // Method java/lang/String.startsWith:(Ljava/lang/String;)Z
       5: ifeq          34
       8: aload_1
       9: new           #45                 // class java/lang/StringBuilder
      12: dup
      13: invokespecial #46                 // Method java/lang/StringBuilder."<init>":()V
      16: ldc           #47                 // String public
      18: invokevirtual #48                 // Method java/lang/StringBuilder.append:(Ljava/lang/String;)Ljava/lang/StringBuilder;
      21: aload_2
      22: invokevirtual #48                 // Method java/lang/StringBuilder.append:(Ljava/lang/String;)Ljava/lang/StringBuilder;
      25: invokevirtual #49                 // Method java/lang/StringBuilder.toString:()Ljava/lang/String;
      28: invokevirtual #50                 // Method org/apache/dubbo/common/compiler/support/CtClassBuilder.addConstructor:(Ljava/lang/String;)V
      31: goto          96
      34: getstatic     #51                 // Field FIELD_PATTERN:Ljava/util/regex/Pattern;
      37: aload_2
      38: invokevirtual #6                  // Method java/util/regex/Pattern.matcher:(Ljava/lang/CharSequence;)Ljava/util/regex/Matcher;
      41: invokevirtual #52                 // Method java/util/regex/Matcher.matches:()Z
      44: ifeq          73
      47: aload_1
      48: new           #45                 // class java/lang/StringBuilder
      51: dup
      52: invokespecial #46                 // Method java/lang/StringBuilder."<init>":()V
      55: ldc           #53                 // String private
      57: invokevirtual #48                 // Method java/lang/StringBuilder.append:(Ljava/lang/String;)Ljava/lang/StringBuilder;
      60: aload_2
      61: invokevirtual #48                 // Method java/lang/StringBuilder.append:(Ljava/lang/String;)Ljava/lang/StringBuilder;
      64: invokevirtual #49                 // Method java/lang/StringBuilder.toString:()Ljava/lang/String;
      67: invokevirtual #54                 // Method org/apache/dubbo/common/compiler/support/CtClassBuilder.addField:(Ljava/lang/String;)V
      70: goto          96
      73: aload_1
      74: new           #45                 // class java/lang/StringBuilder
      77: dup
      78: invokespecial #46                 // Method java/lang/StringBuilder."<init>":()V
      81: ldc           #47                 // String public
      83: invokevirtual #48                 // Method java/lang/StringBuilder.append:(Ljava/lang/String;)Ljava/lang/StringBuilder;
      86: aload_2
      87: invokevirtual #48                 // Method java/lang/StringBuilder.append:(Ljava/lang/String;)Ljava/lang/StringBuilder;
      90: invokevirtual #49                 // Method java/lang/StringBuilder.toString:()Ljava/lang/String;
      93: invokevirtual #55                 // Method org/apache/dubbo/common/compiler/support/CtClassBuilder.addMethod:(Ljava/lang/String;)V
      96: return

  private static boolean lambda$doCompile$1(java.lang.String);
    Code:
       0: aload_0
       1: invokevirtual #56                 // Method java/lang/String.isEmpty:()Z
       4: ifne          11
       7: iconst_1
       8: goto          12
      11: iconst_0
      12: ireturn

  private static void lambda$doCompile$0(org.apache.dubbo.common.compiler.support.CtClassBuilder, java.lang.String);
    Code:
       0: aload_0
       1: aload_1
       2: invokevirtual #9                  // Method java/lang/String.trim:()Ljava/lang/String;
       5: invokevirtual #57                 // Method org/apache/dubbo/common/compiler/support/CtClassBuilder.addInterface:(Ljava/lang/String;)V
       8: return

  static {};
    Code:
       0: ldc           #58                 // String import\\s+([\\w\\.\\*]+);\n
       2: invokestatic  #59                 // Method java/util/regex/Pattern.compile:(Ljava/lang/String;)Ljava/util/regex/Pattern;
       5: putstatic     #5                  // Field IMPORT_PATTERN:Ljava/util/regex/Pattern;
       8: ldc           #60                 // String \\s+extends\\s+([\\w\\.]+)[^\\{]*\\{\n
      10: invokestatic  #59                 // Method java/util/regex/Pattern.compile:(Ljava/lang/String;)Ljava/util/regex/Pattern;
      13: putstatic     #11                 // Field EXTENDS_PATTERN:Ljava/util/regex/Pattern;
      16: ldc           #61                 // String \\s+implements\\s+([\\w\\.]+)\\s*\\{\n
      18: invokestatic  #59                 // Method java/util/regex/Pattern.compile:(Ljava/lang/String;)Ljava/util/regex/Pattern;
      21: putstatic     #13                 // Field IMPLEMENTS_PATTERN:Ljava/util/regex/Pattern;
      24: ldc           #62                 // String \n(private|public|protected)\\s+
      26: invokestatic  #59                 // Method java/util/regex/Pattern.compile:(Ljava/lang/String;)Ljava/util/regex/Pattern;
      29: putstatic     #22                 // Field METHODS_PATTERN:Ljava/util/regex/Pattern;
      32: ldc           #63                 // String [^\n]+=[^\n]+;
      34: invokestatic  #59                 // Method java/util/regex/Pattern.compile:(Ljava/lang/String;)Ljava/util/regex/Pattern;
      37: putstatic     #51                 // Field FIELD_PATTERN:Ljava/util/regex/Pattern;
      40: return
}
