Compiled from "JdkCompiler.java"
final class org.apache.dubbo.common.compiler.support.JdkCompiler$ClassLoaderImpl extends java.lang.ClassLoader {
  private final java.util.Map<java.lang.String, javax.tools.JavaFileObject> classes;

  org.apache.dubbo.common.compiler.support.JdkCompiler$ClassLoaderImpl(java.lang.ClassLoader);
    Code:
       0: aload_0
       1: aload_1
       2: invokespecial #1                  // Method java/lang/ClassLoader."<init>":(Ljava/lang/ClassLoader;)V
       5: aload_0
       6: new           #2                  // class java/util/HashMap
       9: dup
      10: invokespecial #3                  // Method java/util/HashMap."<init>":()V
      13: putfield      #4                  // Field classes:Ljava/util/Map;
      16: return

  java.util.Collection<javax.tools.JavaFileObject> files();
    Code:
       0: aload_0
       1: getfield      #4                  // Field classes:Ljava/util/Map;
       4: invokeinterface #5,  1            // InterfaceMethod java/util/Map.values:()Ljava/util/Collection;
       9: invokestatic  #6                  // Method java/util/Collections.unmodifiableCollection:(Ljava/util/Collection;)Ljava/util/Collection;
      12: areturn

  protected java.lang.Class<?> findClass(java.lang.String) throws java.lang.ClassNotFoundException;
    Code:
       0: aload_0
       1: getfield      #4                  // Field classes:Ljava/util/Map;
       4: aload_1
       5: invokeinterface #7,  2            // InterfaceMethod java/util/Map.get:(Ljava/lang/Object;)Ljava/lang/Object;
      10: checkcast     #8                  // class javax/tools/JavaFileObject
      13: astore_2
      14: aload_2
      15: ifnull        36
      18: aload_2
      19: checkcast     #9                  // class org/apache/dubbo/common/compiler/support/JdkCompiler$JavaFileObjectImpl
      22: invokevirtual #10                 // Method org/apache/dubbo/common/compiler/support/JdkCompiler$JavaFileObjectImpl.getByteCode:()[B
      25: astore_3
      26: aload_0
      27: aload_1
      28: aload_3
      29: iconst_0
      30: aload_3
      31: arraylength
      32: invokevirtual #11                 // Method defineClass:(Ljava/lang/String;[BII)Ljava/lang/Class;
      35: areturn
      36: aload_1
      37: aload_0
      38: invokevirtual #12                 // Method java/lang/Object.getClass:()Ljava/lang/Class;
      41: invokestatic  #13                 // Method org/apache/dubbo/common/utils/ClassUtils.forNameWithCallerClassLoader:(Ljava/lang/String;Ljava/lang/Class;)Ljava/lang/Class;
      44: areturn
      45: astore_3
      46: aload_0
      47: aload_1
      48: invokespecial #15                 // Method java/lang/ClassLoader.findClass:(Ljava/lang/String;)Ljava/lang/Class;
      51: areturn
    Exception table:
       from    to  target type
          36    44    45   Class java/lang/ClassNotFoundException

  void add(java.lang.String, javax.tools.JavaFileObject);
    Code:
       0: aload_0
       1: getfield      #4                  // Field classes:Ljava/util/Map;
       4: aload_1
       5: aload_2
       6: invokeinterface #16,  3           // InterfaceMethod java/util/Map.put:(Ljava/lang/Object;Ljava/lang/Object;)Ljava/lang/Object;
      11: pop
      12: return

  protected synchronized java.lang.Class<?> loadClass(java.lang.String, boolean) throws java.lang.ClassNotFoundException;
    Code:
       0: aload_0
       1: aload_1
       2: iload_2
       3: invokespecial #17                 // Method java/lang/ClassLoader.loadClass:(Ljava/lang/String;Z)Ljava/lang/Class;
       6: areturn

  public java.io.InputStream getResourceAsStream(java.lang.String);
    Code:
       0: aload_1
       1: ldc           #19                 // String .class
       3: invokevirtual #20                 // Method java/lang/String.endsWith:(Ljava/lang/String;)Z
       6: ifeq          62
       9: aload_1
      10: iconst_0
      11: aload_1
      12: invokevirtual #21                 // Method java/lang/String.length:()I
      15: ldc           #19                 // String .class
      17: invokevirtual #21                 // Method java/lang/String.length:()I
      20: isub
      21: invokevirtual #22                 // Method java/lang/String.substring:(II)Ljava/lang/String;
      24: bipush        47
      26: bipush        46
      28: invokevirtual #23                 // Method java/lang/String.replace:(CC)Ljava/lang/String;
      31: astore_2
      32: aload_0
      33: getfield      #4                  // Field classes:Ljava/util/Map;
      36: aload_2
      37: invokeinterface #7,  2            // InterfaceMethod java/util/Map.get:(Ljava/lang/Object;)Ljava/lang/Object;
      42: checkcast     #9                  // class org/apache/dubbo/common/compiler/support/JdkCompiler$JavaFileObjectImpl
      45: astore_3
      46: aload_3
      47: ifnull        62
      50: new           #24                 // class java/io/ByteArrayInputStream
      53: dup
      54: aload_3
      55: invokevirtual #10                 // Method org/apache/dubbo/common/compiler/support/JdkCompiler$JavaFileObjectImpl.getByteCode:()[B
      58: invokespecial #25                 // Method java/io/ByteArrayInputStream."<init>":([B)V
      61: areturn
      62: aload_0
      63: aload_1
      64: invokespecial #26                 // Method java/lang/ClassLoader.getResourceAsStream:(Ljava/lang/String;)Ljava/io/InputStream;
      67: areturn
}
