Compiled from "JdkCompiler.java"
final class org.apache.dubbo.common.compiler.support.JdkCompiler$JavaFileObjectImpl extends javax.tools.SimpleJavaFileObject {
  private final java.lang.CharSequence source;

  private java.io.ByteArrayOutputStream bytecode;

  public org.apache.dubbo.common.compiler.support.JdkCompiler$JavaFileObjectImpl(java.lang.String, java.lang.CharSequence);
    Code:
       0: aload_0
       1: new           #1                  // class java/lang/StringBuilder
       4: dup
       5: invokespecial #2                  // Method java/lang/StringBuilder."<init>":()V
       8: aload_1
       9: invokevirtual #3                  // Method java/lang/StringBuilder.append:(Ljava/lang/String;)Ljava/lang/StringBuilder;
      12: ldc           #5                  // String .java
      14: invokevirtual #3                  // Method java/lang/StringBuilder.append:(Ljava/lang/String;)Ljava/lang/StringBuilder;
      17: invokevirtual #6                  // Method java/lang/StringBuilder.toString:()Ljava/lang/String;
      20: invokestatic  #7                  // Method org/apache/dubbo/common/compiler/support/ClassUtils.toURI:(Ljava/lang/String;)Ljava/net/URI;
      23: getstatic     #8                  // Field javax/tools/JavaFileObject$Kind.SOURCE:Ljavax/tools/JavaFileObject$Kind;
      26: invokespecial #9                  // Method javax/tools/SimpleJavaFileObject."<init>":(Ljava/net/URI;Ljavax/tools/JavaFileObject$Kind;)V
      29: aload_0
      30: aload_2
      31: putfield      #10                 // Field source:Ljava/lang/CharSequence;
      34: return

  org.apache.dubbo.common.compiler.support.JdkCompiler$JavaFileObjectImpl(java.lang.String, javax.tools.JavaFileObject$Kind);
    Code:
       0: aload_0
       1: aload_1
       2: invokestatic  #7                  // Method org/apache/dubbo/common/compiler/support/ClassUtils.toURI:(Ljava/lang/String;)Ljava/net/URI;
       5: aload_2
       6: invokespecial #9                  // Method javax/tools/SimpleJavaFileObject."<init>":(Ljava/net/URI;Ljavax/tools/JavaFileObject$Kind;)V
       9: aload_0
      10: aconst_null
      11: putfield      #10                 // Field source:Ljava/lang/CharSequence;
      14: return

  public org.apache.dubbo.common.compiler.support.JdkCompiler$JavaFileObjectImpl(java.net.URI, javax.tools.JavaFileObject$Kind);
    Code:
       0: aload_0
       1: aload_1
       2: aload_2
       3: invokespecial #9                  // Method javax/tools/SimpleJavaFileObject."<init>":(Ljava/net/URI;Ljavax/tools/JavaFileObject$Kind;)V
       6: aload_0
       7: aconst_null
       8: putfield      #10                 // Field source:Ljava/lang/CharSequence;
      11: return

  public java.lang.CharSequence getCharContent(boolean) throws java.lang.UnsupportedOperationException;
    Code:
       0: aload_0
       1: getfield      #10                 // Field source:Ljava/lang/CharSequence;
       4: ifnonnull     17
       7: new           #11                 // class java/lang/UnsupportedOperationException
      10: dup
      11: ldc           #12                 // String source == null
      13: invokespecial #13                 // Method java/lang/UnsupportedOperationException."<init>":(Ljava/lang/String;)V
      16: athrow
      17: aload_0
      18: getfield      #10                 // Field source:Ljava/lang/CharSequence;
      21: areturn

  public java.io.InputStream openInputStream();
    Code:
       0: new           #14                 // class java/io/ByteArrayInputStream
       3: dup
       4: aload_0
       5: invokevirtual #15                 // Method getByteCode:()[B
       8: invokespecial #16                 // Method java/io/ByteArrayInputStream."<init>":([B)V
      11: areturn

  public java.io.OutputStream openOutputStream();
    Code:
       0: aload_0
       1: new           #17                 // class java/io/ByteArrayOutputStream
       4: dup
       5: invokespecial #18                 // Method java/io/ByteArrayOutputStream."<init>":()V
       8: dup_x1
       9: putfield      #19                 // Field bytecode:Ljava/io/ByteArrayOutputStream;
      12: areturn

  public byte[] getByteCode();
    Code:
       0: aload_0
       1: getfield      #19                 // Field bytecode:Ljava/io/ByteArrayOutputStream;
       4: invokevirtual #20                 // Method java/io/ByteArrayOutputStream.toByteArray:()[B
       7: areturn
}
