Compiled from "JdkCompiler.java"
class org.apache.dubbo.common.compiler.support.JdkCompiler$1 implements java.security.PrivilegedAction<org.apache.dubbo.common.compiler.support.JdkCompiler$ClassLoaderImpl> {
  final java.lang.ClassLoader val$loader;

  final org.apache.dubbo.common.compiler.support.JdkCompiler this$0;

  org.apache.dubbo.common.compiler.support.JdkCompiler$1(org.apache.dubbo.common.compiler.support.JdkCompiler, java.lang.ClassLoader);
    Code:
       0: aload_0
       1: aload_1
       2: putfield      #1                  // Field this$0:Lorg/apache/dubbo/common/compiler/support/JdkCompiler;
       5: aload_0
       6: aload_2
       7: putfield      #2                  // Field val$loader:Ljava/lang/ClassLoader;
      10: aload_0
      11: invokespecial #3                  // Method java/lang/Object."<init>":()V
      14: return

  public org.apache.dubbo.common.compiler.support.JdkCompiler$ClassLoaderImpl run();
    Code:
       0: new           #4                  // class org/apache/dubbo/common/compiler/support/JdkCompiler$ClassLoaderImpl
       3: dup
       4: aload_0
       5: getfield      #2                  // Field val$loader:Ljava/lang/ClassLoader;
       8: invokespecial #5                  // Method org/apache/dubbo/common/compiler/support/JdkCompiler$ClassLoaderImpl."<init>":(Ljava/lang/ClassLoader;)V
      11: areturn

  public java.lang.Object run();
    Code:
       0: aload_0
       1: invokevirtual #6                  // Method run:()Lorg/apache/dubbo/common/compiler/support/JdkCompiler$ClassLoaderImpl;
       4: areturn
}
