Compiled from "JdkCompiler.java"
final class org.apache.dubbo.common.compiler.support.JdkCompiler$JavaFileManagerImpl extends javax.tools.ForwardingJavaFileManager<javax.tools.JavaFileManager> {
  private final org.apache.dubbo.common.compiler.support.JdkCompiler$ClassLoaderImpl classLoader;

  private final java.util.Map<java.net.URI, javax.tools.JavaFileObject> fileObjects;

  public org.apache.dubbo.common.compiler.support.JdkCompiler$JavaFileManagerImpl(javax.tools.JavaFileManager, org.apache.dubbo.common.compiler.support.JdkCompiler$ClassLoaderImpl);
    Code:
       0: aload_0
       1: aload_1
       2: invokespecial #1                  // Method javax/tools/ForwardingJavaFileManager."<init>":(Ljavax/tools/JavaFileManager;)V
       5: aload_0
       6: new           #2                  // class java/util/HashMap
       9: dup
      10: invokespecial #3                  // Method java/util/HashMap."<init>":()V
      13: putfield      #4                  // Field fileObjects:Ljava/util/Map;
      16: aload_0
      17: aload_2
      18: putfield      #5                  // Field classLoader:Lorg/apache/dubbo/common/compiler/support/JdkCompiler$ClassLoaderImpl;
      21: return

  public javax.tools.FileObject getFileForInput(javax.tools.JavaFileManager$Location, java.lang.String, java.lang.String) throws java.io.IOException;
    Code:
       0: aload_0
       1: getfield      #4                  // Field fileObjects:Ljava/util/Map;
       4: aload_0
       5: aload_1
       6: aload_2
       7: aload_3
       8: invokespecial #6                  // Method uri:(Ljavax/tools/JavaFileManager$Location;Ljava/lang/String;Ljava/lang/String;)Ljava/net/URI;
      11: invokeinterface #7,  2            // InterfaceMethod java/util/Map.get:(Ljava/lang/Object;)Ljava/lang/Object;
      16: checkcast     #8                  // class javax/tools/FileObject
      19: astore        4
      21: aload         4
      23: ifnull        29
      26: aload         4
      28: areturn
      29: aload_0
      30: aload_1
      31: aload_2
      32: aload_3
      33: invokespecial #9                  // Method javax/tools/ForwardingJavaFileManager.getFileForInput:(Ljavax/tools/JavaFileManager$Location;Ljava/lang/String;Ljava/lang/String;)Ljavax/tools/FileObject;
      36: areturn

  public void putFileForInput(javax.tools.StandardLocation, java.lang.String, java.lang.String, javax.tools.JavaFileObject);
    Code:
       0: aload_0
       1: getfield      #4                  // Field fileObjects:Ljava/util/Map;
       4: aload_0
       5: aload_1
       6: aload_2
       7: aload_3
       8: invokespecial #6                  // Method uri:(Ljavax/tools/JavaFileManager$Location;Ljava/lang/String;Ljava/lang/String;)Ljava/net/URI;
      11: aload         4
      13: invokeinterface #10,  3           // InterfaceMethod java/util/Map.put:(Ljava/lang/Object;Ljava/lang/Object;)Ljava/lang/Object;
      18: pop
      19: return

  private java.net.URI uri(javax.tools.JavaFileManager$Location, java.lang.String, java.lang.String);
    Code:
       0: new           #11                 // class java/lang/StringBuilder
       3: dup
       4: invokespecial #12                 // Method java/lang/StringBuilder."<init>":()V
       7: aload_1
       8: invokeinterface #13,  1           // InterfaceMethod javax/tools/JavaFileManager$Location.getName:()Ljava/lang/String;
      13: invokevirtual #14                 // Method java/lang/StringBuilder.append:(Ljava/lang/String;)Ljava/lang/StringBuilder;
      16: bipush        47
      18: invokevirtual #15                 // Method java/lang/StringBuilder.append:(C)Ljava/lang/StringBuilder;
      21: aload_2
      22: invokevirtual #14                 // Method java/lang/StringBuilder.append:(Ljava/lang/String;)Ljava/lang/StringBuilder;
      25: bipush        47
      27: invokevirtual #15                 // Method java/lang/StringBuilder.append:(C)Ljava/lang/StringBuilder;
      30: aload_3
      31: invokevirtual #14                 // Method java/lang/StringBuilder.append:(Ljava/lang/String;)Ljava/lang/StringBuilder;
      34: invokevirtual #16                 // Method java/lang/StringBuilder.toString:()Ljava/lang/String;
      37: invokestatic  #17                 // Method org/apache/dubbo/common/compiler/support/ClassUtils.toURI:(Ljava/lang/String;)Ljava/net/URI;
      40: areturn

  public javax.tools.JavaFileObject getJavaFileForOutput(javax.tools.JavaFileManager$Location, java.lang.String, javax.tools.JavaFileObject$Kind, javax.tools.FileObject) throws java.io.IOException;
    Code:
       0: new           #18                 // class org/apache/dubbo/common/compiler/support/JdkCompiler$JavaFileObjectImpl
       3: dup
       4: aload_2
       5: aload_3
       6: invokespecial #19                 // Method org/apache/dubbo/common/compiler/support/JdkCompiler$JavaFileObjectImpl."<init>":(Ljava/lang/String;Ljavax/tools/JavaFileObject$Kind;)V
       9: astore        5
      11: aload_0
      12: getfield      #5                  // Field classLoader:Lorg/apache/dubbo/common/compiler/support/JdkCompiler$ClassLoaderImpl;
      15: aload_2
      16: aload         5
      18: invokevirtual #20                 // Method org/apache/dubbo/common/compiler/support/JdkCompiler$ClassLoaderImpl.add:(Ljava/lang/String;Ljavax/tools/JavaFileObject;)V
      21: aload         5
      23: areturn

  public java.lang.ClassLoader getClassLoader(javax.tools.JavaFileManager$Location);
    Code:
       0: aload_0
       1: getfield      #5                  // Field classLoader:Lorg/apache/dubbo/common/compiler/support/JdkCompiler$ClassLoaderImpl;
       4: areturn

  public java.lang.String inferBinaryName(javax.tools.JavaFileManager$Location, javax.tools.JavaFileObject);
    Code:
       0: aload_2
       1: instanceof    #18                 // class org/apache/dubbo/common/compiler/support/JdkCompiler$JavaFileObjectImpl
       4: ifeq          14
       7: aload_2
       8: invokeinterface #21,  1           // InterfaceMethod javax/tools/JavaFileObject.getName:()Ljava/lang/String;
      13: areturn
      14: aload_0
      15: aload_1
      16: aload_2
      17: invokespecial #22                 // Method javax/tools/ForwardingJavaFileManager.inferBinaryName:(Ljavax/tools/JavaFileManager$Location;Ljavax/tools/JavaFileObject;)Ljava/lang/String;
      20: areturn

  public java.lang.Iterable<javax.tools.JavaFileObject> list(javax.tools.JavaFileManager$Location, java.lang.String, java.util.Set<javax.tools.JavaFileObject$Kind>, boolean) throws java.io.IOException;
    Code:
       0: aload_0
       1: aload_1
       2: aload_2
       3: aload_3
       4: iload         4
       6: invokespecial #23                 // Method javax/tools/ForwardingJavaFileManager.list:(Ljavax/tools/JavaFileManager$Location;Ljava/lang/String;Ljava/util/Set;Z)Ljava/lang/Iterable;
       9: astore        5
      11: invokestatic  #24                 // Method java/lang/Thread.currentThread:()Ljava/lang/Thread;
      14: invokevirtual #25                 // Method java/lang/Thread.getContextClassLoader:()Ljava/lang/ClassLoader;
      17: astore        6
      19: new           #26                 // class java/util/ArrayList
      22: dup
      23: invokespecial #27                 // Method java/util/ArrayList."<init>":()V
      26: astore        7
      28: aload_1
      29: getstatic     #28                 // Field javax/tools/StandardLocation.CLASS_PATH:Ljavax/tools/StandardLocation;
      32: if_acmpne     139
      35: aload_3
      36: getstatic     #29                 // Field javax/tools/JavaFileObject$Kind.CLASS:Ljavax/tools/JavaFileObject$Kind;
      39: invokeinterface #30,  2           // InterfaceMethod java/util/Set.contains:(Ljava/lang/Object;)Z
      44: ifeq          139
      47: aload_0
      48: getfield      #4                  // Field fileObjects:Ljava/util/Map;
      51: invokeinterface #31,  1           // InterfaceMethod java/util/Map.values:()Ljava/util/Collection;
      56: invokeinterface #32,  1           // InterfaceMethod java/util/Collection.iterator:()Ljava/util/Iterator;
      61: astore        8
      63: aload         8
      65: invokeinterface #33,  1           // InterfaceMethod java/util/Iterator.hasNext:()Z
      70: ifeq          123
      73: aload         8
      75: invokeinterface #34,  1           // InterfaceMethod java/util/Iterator.next:()Ljava/lang/Object;
      80: checkcast     #35                 // class javax/tools/JavaFileObject
      83: astore        9
      85: aload         9
      87: invokeinterface #36,  1           // InterfaceMethod javax/tools/JavaFileObject.getKind:()Ljavax/tools/JavaFileObject$Kind;
      92: getstatic     #29                 // Field javax/tools/JavaFileObject$Kind.CLASS:Ljavax/tools/JavaFileObject$Kind;
      95: if_acmpne     120
      98: aload         9
     100: invokeinterface #21,  1           // InterfaceMethod javax/tools/JavaFileObject.getName:()Ljava/lang/String;
     105: aload_2
     106: invokevirtual #37                 // Method java/lang/String.startsWith:(Ljava/lang/String;)Z
     109: ifeq          120
     112: aload         7
     114: aload         9
     116: invokevirtual #38                 // Method java/util/ArrayList.add:(Ljava/lang/Object;)Z
     119: pop
     120: goto          63
     123: aload         7
     125: aload_0
     126: getfield      #5                  // Field classLoader:Lorg/apache/dubbo/common/compiler/support/JdkCompiler$ClassLoaderImpl;
     129: invokevirtual #39                 // Method org/apache/dubbo/common/compiler/support/JdkCompiler$ClassLoaderImpl.files:()Ljava/util/Collection;
     132: invokevirtual #40                 // Method java/util/ArrayList.addAll:(Ljava/util/Collection;)Z
     135: pop
     136: goto          234
     139: aload_1
     140: getstatic     #41                 // Field javax/tools/StandardLocation.SOURCE_PATH:Ljavax/tools/StandardLocation;
     143: if_acmpne     234
     146: aload_3
     147: getstatic     #42                 // Field javax/tools/JavaFileObject$Kind.SOURCE:Ljavax/tools/JavaFileObject$Kind;
     150: invokeinterface #30,  2           // InterfaceMethod java/util/Set.contains:(Ljava/lang/Object;)Z
     155: ifeq          234
     158: aload_0
     159: getfield      #4                  // Field fileObjects:Ljava/util/Map;
     162: invokeinterface #31,  1           // InterfaceMethod java/util/Map.values:()Ljava/util/Collection;
     167: invokeinterface #32,  1           // InterfaceMethod java/util/Collection.iterator:()Ljava/util/Iterator;
     172: astore        8
     174: aload         8
     176: invokeinterface #33,  1           // InterfaceMethod java/util/Iterator.hasNext:()Z
     181: ifeq          234
     184: aload         8
     186: invokeinterface #34,  1           // InterfaceMethod java/util/Iterator.next:()Ljava/lang/Object;
     191: checkcast     #35                 // class javax/tools/JavaFileObject
     194: astore        9
     196: aload         9
     198: invokeinterface #36,  1           // InterfaceMethod javax/tools/JavaFileObject.getKind:()Ljavax/tools/JavaFileObject$Kind;
     203: getstatic     #42                 // Field javax/tools/JavaFileObject$Kind.SOURCE:Ljavax/tools/JavaFileObject$Kind;
     206: if_acmpne     231
     209: aload         9
     211: invokeinterface #21,  1           // InterfaceMethod javax/tools/JavaFileObject.getName:()Ljava/lang/String;
     216: aload_2
     217: invokevirtual #37                 // Method java/lang/String.startsWith:(Ljava/lang/String;)Z
     220: ifeq          231
     223: aload         7
     225: aload         9
     227: invokevirtual #38                 // Method java/util/ArrayList.add:(Ljava/lang/Object;)Z
     230: pop
     231: goto          174
     234: aload         5
     236: invokeinterface #43,  1           // InterfaceMethod java/lang/Iterable.iterator:()Ljava/util/Iterator;
     241: astore        8
     243: aload         8
     245: invokeinterface #33,  1           // InterfaceMethod java/util/Iterator.hasNext:()Z
     250: ifeq          276
     253: aload         8
     255: invokeinterface #34,  1           // InterfaceMethod java/util/Iterator.next:()Ljava/lang/Object;
     260: checkcast     #35                 // class javax/tools/JavaFileObject
     263: astore        9
     265: aload         7
     267: aload         9
     269: invokevirtual #38                 // Method java/util/ArrayList.add:(Ljava/lang/Object;)Z
     272: pop
     273: goto          243
     276: aload         7
     278: areturn
}
