Compiled from "Log4jLogger.java"
public class org.apache.dubbo.common.logger.log4j.Log4jLogger implements org.apache.dubbo.common.logger.Logger {
  private static final java.lang.String FQCN;

  private final org.apache.log4j.Logger logger;

  public org.apache.dubbo.common.logger.log4j.Log4jLogger(org.apache.log4j.Logger);
    Code:
       0: aload_0
       1: invokespecial #1                  // Method java/lang/Object."<init>":()V
       4: aload_0
       5: aload_1
       6: putfield      #2                  // Field logger:Lorg/apache/log4j/Logger;
       9: return

  public void trace(java.lang.String);
    Code:
       0: aload_0
       1: getfield      #2                  // Field logger:Lorg/apache/log4j/Logger;
       4: getstatic     #3                  // Field FQCN:Ljava/lang/String;
       7: getstatic     #4                  // Field org/apache/log4j/Level.TRACE:Lorg/apache/log4j/Level;
      10: aload_1
      11: aconst_null
      12: invokevirtual #5                  // Method org/apache/log4j/Logger.log:(Ljava/lang/String;Lorg/apache/log4j/Priority;Ljava/lang/Object;Ljava/lang/Throwable;)V
      15: return

  public void trace(java.lang.Throwable);
    Code:
       0: aload_0
       1: getfield      #2                  // Field logger:Lorg/apache/log4j/Logger;
       4: getstatic     #3                  // Field FQCN:Ljava/lang/String;
       7: getstatic     #4                  // Field org/apache/log4j/Level.TRACE:Lorg/apache/log4j/Level;
      10: aload_1
      11: ifnonnull     18
      14: aconst_null
      15: goto          22
      18: aload_1
      19: invokevirtual #6                  // Method java/lang/Throwable.getMessage:()Ljava/lang/String;
      22: aload_1
      23: invokevirtual #5                  // Method org/apache/log4j/Logger.log:(Ljava/lang/String;Lorg/apache/log4j/Priority;Ljava/lang/Object;Ljava/lang/Throwable;)V
      26: return

  public void trace(java.lang.String, java.lang.Throwable);
    Code:
       0: aload_0
       1: getfield      #2                  // Field logger:Lorg/apache/log4j/Logger;
       4: getstatic     #3                  // Field FQCN:Ljava/lang/String;
       7: getstatic     #4                  // Field org/apache/log4j/Level.TRACE:Lorg/apache/log4j/Level;
      10: aload_1
      11: aload_2
      12: invokevirtual #5                  // Method org/apache/log4j/Logger.log:(Ljava/lang/String;Lorg/apache/log4j/Priority;Ljava/lang/Object;Ljava/lang/Throwable;)V
      15: return

  public void debug(java.lang.String);
    Code:
       0: aload_0
       1: getfield      #2                  // Field logger:Lorg/apache/log4j/Logger;
       4: getstatic     #3                  // Field FQCN:Ljava/lang/String;
       7: getstatic     #7                  // Field org/apache/log4j/Level.DEBUG:Lorg/apache/log4j/Level;
      10: aload_1
      11: aconst_null
      12: invokevirtual #5                  // Method org/apache/log4j/Logger.log:(Ljava/lang/String;Lorg/apache/log4j/Priority;Ljava/lang/Object;Ljava/lang/Throwable;)V
      15: return

  public void debug(java.lang.Throwable);
    Code:
       0: aload_0
       1: getfield      #2                  // Field logger:Lorg/apache/log4j/Logger;
       4: getstatic     #3                  // Field FQCN:Ljava/lang/String;
       7: getstatic     #7                  // Field org/apache/log4j/Level.DEBUG:Lorg/apache/log4j/Level;
      10: aload_1
      11: ifnonnull     18
      14: aconst_null
      15: goto          22
      18: aload_1
      19: invokevirtual #6                  // Method java/lang/Throwable.getMessage:()Ljava/lang/String;
      22: aload_1
      23: invokevirtual #5                  // Method org/apache/log4j/Logger.log:(Ljava/lang/String;Lorg/apache/log4j/Priority;Ljava/lang/Object;Ljava/lang/Throwable;)V
      26: return

  public void debug(java.lang.String, java.lang.Throwable);
    Code:
       0: aload_0
       1: getfield      #2                  // Field logger:Lorg/apache/log4j/Logger;
       4: getstatic     #3                  // Field FQCN:Ljava/lang/String;
       7: getstatic     #7                  // Field org/apache/log4j/Level.DEBUG:Lorg/apache/log4j/Level;
      10: aload_1
      11: aload_2
      12: invokevirtual #5                  // Method org/apache/log4j/Logger.log:(Ljava/lang/String;Lorg/apache/log4j/Priority;Ljava/lang/Object;Ljava/lang/Throwable;)V
      15: return

  public void info(java.lang.String);
    Code:
       0: aload_0
       1: getfield      #2                  // Field logger:Lorg/apache/log4j/Logger;
       4: getstatic     #3                  // Field FQCN:Ljava/lang/String;
       7: getstatic     #8                  // Field org/apache/log4j/Level.INFO:Lorg/apache/log4j/Level;
      10: aload_1
      11: aconst_null
      12: invokevirtual #5                  // Method org/apache/log4j/Logger.log:(Ljava/lang/String;Lorg/apache/log4j/Priority;Ljava/lang/Object;Ljava/lang/Throwable;)V
      15: return

  public void info(java.lang.Throwable);
    Code:
       0: aload_0
       1: getfield      #2                  // Field logger:Lorg/apache/log4j/Logger;
       4: getstatic     #3                  // Field FQCN:Ljava/lang/String;
       7: getstatic     #8                  // Field org/apache/log4j/Level.INFO:Lorg/apache/log4j/Level;
      10: aload_1
      11: ifnonnull     18
      14: aconst_null
      15: goto          22
      18: aload_1
      19: invokevirtual #6                  // Method java/lang/Throwable.getMessage:()Ljava/lang/String;
      22: aload_1
      23: invokevirtual #5                  // Method org/apache/log4j/Logger.log:(Ljava/lang/String;Lorg/apache/log4j/Priority;Ljava/lang/Object;Ljava/lang/Throwable;)V
      26: return

  public void info(java.lang.String, java.lang.Throwable);
    Code:
       0: aload_0
       1: getfield      #2                  // Field logger:Lorg/apache/log4j/Logger;
       4: getstatic     #3                  // Field FQCN:Ljava/lang/String;
       7: getstatic     #8                  // Field org/apache/log4j/Level.INFO:Lorg/apache/log4j/Level;
      10: aload_1
      11: aload_2
      12: invokevirtual #5                  // Method org/apache/log4j/Logger.log:(Ljava/lang/String;Lorg/apache/log4j/Priority;Ljava/lang/Object;Ljava/lang/Throwable;)V
      15: return

  public void warn(java.lang.String);
    Code:
       0: aload_0
       1: getfield      #2                  // Field logger:Lorg/apache/log4j/Logger;
       4: getstatic     #3                  // Field FQCN:Ljava/lang/String;
       7: getstatic     #9                  // Field org/apache/log4j/Level.WARN:Lorg/apache/log4j/Level;
      10: aload_1
      11: aconst_null
      12: invokevirtual #5                  // Method org/apache/log4j/Logger.log:(Ljava/lang/String;Lorg/apache/log4j/Priority;Ljava/lang/Object;Ljava/lang/Throwable;)V
      15: return

  public void warn(java.lang.Throwable);
    Code:
       0: aload_0
       1: getfield      #2                  // Field logger:Lorg/apache/log4j/Logger;
       4: getstatic     #3                  // Field FQCN:Ljava/lang/String;
       7: getstatic     #9                  // Field org/apache/log4j/Level.WARN:Lorg/apache/log4j/Level;
      10: aload_1
      11: ifnonnull     18
      14: aconst_null
      15: goto          22
      18: aload_1
      19: invokevirtual #6                  // Method java/lang/Throwable.getMessage:()Ljava/lang/String;
      22: aload_1
      23: invokevirtual #5                  // Method org/apache/log4j/Logger.log:(Ljava/lang/String;Lorg/apache/log4j/Priority;Ljava/lang/Object;Ljava/lang/Throwable;)V
      26: return

  public void warn(java.lang.String, java.lang.Throwable);
    Code:
       0: aload_0
       1: getfield      #2                  // Field logger:Lorg/apache/log4j/Logger;
       4: getstatic     #3                  // Field FQCN:Ljava/lang/String;
       7: getstatic     #9                  // Field org/apache/log4j/Level.WARN:Lorg/apache/log4j/Level;
      10: aload_1
      11: aload_2
      12: invokevirtual #5                  // Method org/apache/log4j/Logger.log:(Ljava/lang/String;Lorg/apache/log4j/Priority;Ljava/lang/Object;Ljava/lang/Throwable;)V
      15: return

  public void error(java.lang.String);
    Code:
       0: aload_0
       1: getfield      #2                  // Field logger:Lorg/apache/log4j/Logger;
       4: getstatic     #3                  // Field FQCN:Ljava/lang/String;
       7: getstatic     #10                 // Field org/apache/log4j/Level.ERROR:Lorg/apache/log4j/Level;
      10: aload_1
      11: aconst_null
      12: invokevirtual #5                  // Method org/apache/log4j/Logger.log:(Ljava/lang/String;Lorg/apache/log4j/Priority;Ljava/lang/Object;Ljava/lang/Throwable;)V
      15: return

  public void error(java.lang.Throwable);
    Code:
       0: aload_0
       1: getfield      #2                  // Field logger:Lorg/apache/log4j/Logger;
       4: getstatic     #3                  // Field FQCN:Ljava/lang/String;
       7: getstatic     #10                 // Field org/apache/log4j/Level.ERROR:Lorg/apache/log4j/Level;
      10: aload_1
      11: ifnonnull     18
      14: aconst_null
      15: goto          22
      18: aload_1
      19: invokevirtual #6                  // Method java/lang/Throwable.getMessage:()Ljava/lang/String;
      22: aload_1
      23: invokevirtual #5                  // Method org/apache/log4j/Logger.log:(Ljava/lang/String;Lorg/apache/log4j/Priority;Ljava/lang/Object;Ljava/lang/Throwable;)V
      26: return

  public void error(java.lang.String, java.lang.Throwable);
    Code:
       0: aload_0
       1: getfield      #2                  // Field logger:Lorg/apache/log4j/Logger;
       4: getstatic     #3                  // Field FQCN:Ljava/lang/String;
       7: getstatic     #10                 // Field org/apache/log4j/Level.ERROR:Lorg/apache/log4j/Level;
      10: aload_1
      11: aload_2
      12: invokevirtual #5                  // Method org/apache/log4j/Logger.log:(Ljava/lang/String;Lorg/apache/log4j/Priority;Ljava/lang/Object;Ljava/lang/Throwable;)V
      15: return

  public boolean isTraceEnabled();
    Code:
       0: aload_0
       1: getfield      #2                  // Field logger:Lorg/apache/log4j/Logger;
       4: invokevirtual #11                 // Method org/apache/log4j/Logger.isTraceEnabled:()Z
       7: ireturn

  public boolean isDebugEnabled();
    Code:
       0: aload_0
       1: getfield      #2                  // Field logger:Lorg/apache/log4j/Logger;
       4: invokevirtual #12                 // Method org/apache/log4j/Logger.isDebugEnabled:()Z
       7: ireturn

  public boolean isInfoEnabled();
    Code:
       0: aload_0
       1: getfield      #2                  // Field logger:Lorg/apache/log4j/Logger;
       4: invokevirtual #13                 // Method org/apache/log4j/Logger.isInfoEnabled:()Z
       7: ireturn

  public boolean isWarnEnabled();
    Code:
       0: aload_0
       1: getfield      #2                  // Field logger:Lorg/apache/log4j/Logger;
       4: getstatic     #9                  // Field org/apache/log4j/Level.WARN:Lorg/apache/log4j/Level;
       7: invokevirtual #14                 // Method org/apache/log4j/Logger.isEnabledFor:(Lorg/apache/log4j/Priority;)Z
      10: ireturn

  public boolean isErrorEnabled();
    Code:
       0: aload_0
       1: getfield      #2                  // Field logger:Lorg/apache/log4j/Logger;
       4: getstatic     #10                 // Field org/apache/log4j/Level.ERROR:Lorg/apache/log4j/Level;
       7: invokevirtual #14                 // Method org/apache/log4j/Logger.isEnabledFor:(Lorg/apache/log4j/Priority;)Z
      10: ireturn

  public org.apache.log4j.Logger getLogger();
    Code:
       0: aload_0
       1: getfield      #2                  // Field logger:Lorg/apache/log4j/Logger;
       4: areturn

  static {};
    Code:
       0: ldc           #15                 // class org/apache/dubbo/common/logger/support/FailsafeLogger
       2: invokevirtual #16                 // Method java/lang/Class.getName:()Ljava/lang/String;
       5: putstatic     #3                  // Field FQCN:Ljava/lang/String;
       8: return
}
