Compiled from "Log4jLoggerAdapter.java"
public class org.apache.dubbo.common.logger.log4j.Log4jLoggerAdapter implements org.apache.dubbo.common.logger.LoggerAdapter {
  public static final java.lang.String NAME;

  private java.io.File file;

  public org.apache.dubbo.common.logger.log4j.Log4jLoggerAdapter();
    Code:
       0: aload_0
       1: invokespecial #1                  // Method java/lang/Object."<init>":()V
       4: invokestatic  #2                  // Method org/apache/log4j/LogManager.getRootLogger:()Lorg/apache/log4j/Logger;
       7: astore_1
       8: aload_1
       9: ifnull        79
      12: aload_1
      13: invokevirtual #3                  // Method org/apache/log4j/Logger.getAllAppenders:()Ljava/util/Enumeration;
      16: astore_2
      17: aload_2
      18: ifnull        79
      21: aload_2
      22: invokeinterface #4,  1            // InterfaceMethod java/util/Enumeration.hasMoreElements:()Z
      27: ifeq          79
      30: aload_2
      31: invokeinterface #5,  1            // InterfaceMethod java/util/Enumeration.nextElement:()Ljava/lang/Object;
      36: checkcast     #6                  // class org/apache/log4j/Appender
      39: astore_3
      40: aload_3
      41: instanceof    #7                  // class org/apache/log4j/FileAppender
      44: ifeq          76
      47: aload_3
      48: checkcast     #7                  // class org/apache/log4j/FileAppender
      51: astore        4
      53: aload         4
      55: invokevirtual #8                  // Method org/apache/log4j/FileAppender.getFile:()Ljava/lang/String;
      58: astore        5
      60: aload_0
      61: new           #9                  // class java/io/File
      64: dup
      65: aload         5
      67: invokespecial #10                 // Method java/io/File."<init>":(Ljava/lang/String;)V
      70: putfield      #11                 // Field file:Ljava/io/File;
      73: goto          79
      76: goto          21
      79: goto          83
      82: astore_1
      83: return
    Exception table:
       from    to  target type
           4    79    82   Class java/lang/Exception

  private static org.apache.log4j.Level toLog4jLevel(org.apache.dubbo.common.logger.Level);
    Code:
       0: aload_0
       1: getstatic     #13                 // Field org/apache/dubbo/common/logger/Level.ALL:Lorg/apache/dubbo/common/logger/Level;
       4: if_acmpne     11
       7: getstatic     #14                 // Field org/apache/log4j/Level.ALL:Lorg/apache/log4j/Level;
      10: areturn
      11: aload_0
      12: getstatic     #15                 // Field org/apache/dubbo/common/logger/Level.TRACE:Lorg/apache/dubbo/common/logger/Level;
      15: if_acmpne     22
      18: getstatic     #16                 // Field org/apache/log4j/Level.TRACE:Lorg/apache/log4j/Level;
      21: areturn
      22: aload_0
      23: getstatic     #17                 // Field org/apache/dubbo/common/logger/Level.DEBUG:Lorg/apache/dubbo/common/logger/Level;
      26: if_acmpne     33
      29: getstatic     #18                 // Field org/apache/log4j/Level.DEBUG:Lorg/apache/log4j/Level;
      32: areturn
      33: aload_0
      34: getstatic     #19                 // Field org/apache/dubbo/common/logger/Level.INFO:Lorg/apache/dubbo/common/logger/Level;
      37: if_acmpne     44
      40: getstatic     #20                 // Field org/apache/log4j/Level.INFO:Lorg/apache/log4j/Level;
      43: areturn
      44: aload_0
      45: getstatic     #21                 // Field org/apache/dubbo/common/logger/Level.WARN:Lorg/apache/dubbo/common/logger/Level;
      48: if_acmpne     55
      51: getstatic     #22                 // Field org/apache/log4j/Level.WARN:Lorg/apache/log4j/Level;
      54: areturn
      55: aload_0
      56: getstatic     #23                 // Field org/apache/dubbo/common/logger/Level.ERROR:Lorg/apache/dubbo/common/logger/Level;
      59: if_acmpne     66
      62: getstatic     #24                 // Field org/apache/log4j/Level.ERROR:Lorg/apache/log4j/Level;
      65: areturn
      66: getstatic     #25                 // Field org/apache/log4j/Level.OFF:Lorg/apache/log4j/Level;
      69: areturn

  private static org.apache.dubbo.common.logger.Level fromLog4jLevel(org.apache.log4j.Level);
    Code:
       0: aload_0
       1: getstatic     #14                 // Field org/apache/log4j/Level.ALL:Lorg/apache/log4j/Level;
       4: if_acmpne     11
       7: getstatic     #13                 // Field org/apache/dubbo/common/logger/Level.ALL:Lorg/apache/dubbo/common/logger/Level;
      10: areturn
      11: aload_0
      12: getstatic     #16                 // Field org/apache/log4j/Level.TRACE:Lorg/apache/log4j/Level;
      15: if_acmpne     22
      18: getstatic     #15                 // Field org/apache/dubbo/common/logger/Level.TRACE:Lorg/apache/dubbo/common/logger/Level;
      21: areturn
      22: aload_0
      23: getstatic     #18                 // Field org/apache/log4j/Level.DEBUG:Lorg/apache/log4j/Level;
      26: if_acmpne     33
      29: getstatic     #17                 // Field org/apache/dubbo/common/logger/Level.DEBUG:Lorg/apache/dubbo/common/logger/Level;
      32: areturn
      33: aload_0
      34: getstatic     #20                 // Field org/apache/log4j/Level.INFO:Lorg/apache/log4j/Level;
      37: if_acmpne     44
      40: getstatic     #19                 // Field org/apache/dubbo/common/logger/Level.INFO:Lorg/apache/dubbo/common/logger/Level;
      43: areturn
      44: aload_0
      45: getstatic     #22                 // Field org/apache/log4j/Level.WARN:Lorg/apache/log4j/Level;
      48: if_acmpne     55
      51: getstatic     #21                 // Field org/apache/dubbo/common/logger/Level.WARN:Lorg/apache/dubbo/common/logger/Level;
      54: areturn
      55: aload_0
      56: getstatic     #24                 // Field org/apache/log4j/Level.ERROR:Lorg/apache/log4j/Level;
      59: if_acmpne     66
      62: getstatic     #23                 // Field org/apache/dubbo/common/logger/Level.ERROR:Lorg/apache/dubbo/common/logger/Level;
      65: areturn
      66: getstatic     #26                 // Field org/apache/dubbo/common/logger/Level.OFF:Lorg/apache/dubbo/common/logger/Level;
      69: areturn

  public org.apache.dubbo.common.logger.Logger getLogger(java.lang.Class<?>);
    Code:
       0: new           #27                 // class org/apache/dubbo/common/logger/log4j/Log4jLogger
       3: dup
       4: aload_1
       5: invokestatic  #28                 // Method org/apache/log4j/LogManager.getLogger:(Ljava/lang/Class;)Lorg/apache/log4j/Logger;
       8: invokespecial #29                 // Method org/apache/dubbo/common/logger/log4j/Log4jLogger."<init>":(Lorg/apache/log4j/Logger;)V
      11: areturn

  public org.apache.dubbo.common.logger.Logger getLogger(java.lang.String);
    Code:
       0: new           #27                 // class org/apache/dubbo/common/logger/log4j/Log4jLogger
       3: dup
       4: aload_1
       5: invokestatic  #30                 // Method org/apache/log4j/LogManager.getLogger:(Ljava/lang/String;)Lorg/apache/log4j/Logger;
       8: invokespecial #29                 // Method org/apache/dubbo/common/logger/log4j/Log4jLogger."<init>":(Lorg/apache/log4j/Logger;)V
      11: areturn

  public org.apache.dubbo.common.logger.Level getLevel();
    Code:
       0: invokestatic  #2                  // Method org/apache/log4j/LogManager.getRootLogger:()Lorg/apache/log4j/Logger;
       3: invokevirtual #31                 // Method org/apache/log4j/Logger.getLevel:()Lorg/apache/log4j/Level;
       6: invokestatic  #32                 // Method fromLog4jLevel:(Lorg/apache/log4j/Level;)Lorg/apache/dubbo/common/logger/Level;
       9: areturn

  public void setLevel(org.apache.dubbo.common.logger.Level);
    Code:
       0: invokestatic  #2                  // Method org/apache/log4j/LogManager.getRootLogger:()Lorg/apache/log4j/Logger;
       3: aload_1
       4: invokestatic  #33                 // Method toLog4jLevel:(Lorg/apache/dubbo/common/logger/Level;)Lorg/apache/log4j/Level;
       7: invokevirtual #34                 // Method org/apache/log4j/Logger.setLevel:(Lorg/apache/log4j/Level;)V
      10: return

  public java.io.File getFile();
    Code:
       0: aload_0
       1: getfield      #11                 // Field file:Ljava/io/File;
       4: areturn

  public void setFile(java.io.File);
    Code:
       0: return

  public boolean isConfigured();
    Code:
       0: iconst_0
       1: istore_1
       2: invokestatic  #2                  // Method org/apache/log4j/LogManager.getRootLogger:()Lorg/apache/log4j/Logger;
       5: astore_2
       6: aload_2
       7: ifnull        82
      10: aload_2
      11: invokevirtual #3                  // Method org/apache/log4j/Logger.getAllAppenders:()Ljava/util/Enumeration;
      14: astore_3
      15: aload_3
      16: ifnull        82
      19: aload_3
      20: invokeinterface #4,  1            // InterfaceMethod java/util/Enumeration.hasMoreElements:()Z
      25: ifeq          82
      28: iconst_1
      29: istore_1
      30: aload_3
      31: invokeinterface #5,  1            // InterfaceMethod java/util/Enumeration.nextElement:()Ljava/lang/Object;
      36: checkcast     #6                  // class org/apache/log4j/Appender
      39: astore        4
      41: aload         4
      43: instanceof    #7                  // class org/apache/log4j/FileAppender
      46: ifeq          79
      49: aload         4
      51: checkcast     #7                  // class org/apache/log4j/FileAppender
      54: astore        5
      56: aload         5
      58: invokevirtual #8                  // Method org/apache/log4j/FileAppender.getFile:()Ljava/lang/String;
      61: astore        6
      63: aload_0
      64: new           #9                  // class java/io/File
      67: dup
      68: aload         6
      70: invokespecial #10                 // Method java/io/File."<init>":(Ljava/lang/String;)V
      73: putfield      #11                 // Field file:Ljava/io/File;
      76: goto          82
      79: goto          19
      82: goto          86
      85: astore_2
      86: iload_1
      87: ireturn
    Exception table:
       from    to  target type
           2    82    85   Class java/lang/Exception
}
