Compiled from "LiquibaseChangelogMissingFailureAnalyzer.java"
class org.springframework.boot.liquibase.LiquibaseChangelogMissingFailureAnalyzer extends org.springframework.boot.diagnostics.AbstractFailureAnalyzer<liquibase.exception.ChangeLogParseException> {
  private static final java.lang.String MESSAGE_SUFFIX;

  org.springframework.boot.liquibase.LiquibaseChangelogMissingFailureAnalyzer();
    Code:
       0: aload_0
       1: invokespecial #1                  // Method org/springframework/boot/diagnostics/AbstractFailureAnalyzer."<init>":()V
       4: return

  protected org.springframework.boot.diagnostics.FailureAnalysis analyze(java.lang.Throwable, liquibase.exception.ChangeLogParseException);
    Code:
       0: aload_2
       1: invokevirtual #7                  // Method liquibase/exception/ChangeLogParseException.getMessage:()Ljava/lang/String;
       4: ldc           #15                 // String  does not exist
       6: invokevirtual #17                 // Method java/lang/String.endsWith:(Ljava/lang/String;)Z
       9: ifeq          34
      12: aload_0
      13: aload_2
      14: invokevirtual #23                 // Method extractChangelogPath:(Lliquibase/exception/ChangeLogParseException;)Ljava/lang/String;
      17: astore_3
      18: new           #27                 // class org/springframework/boot/diagnostics/FailureAnalysis
      21: dup
      22: aload_0
      23: aload_3
      24: invokevirtual #29                 // Method getDescription:(Ljava/lang/String;)Ljava/lang/String;
      27: ldc           #33                 // String Make sure a Liquibase changelog is present at the configured path.
      29: aload_2
      30: invokespecial #35                 // Method org/springframework/boot/diagnostics/FailureAnalysis."<init>":(Ljava/lang/String;Ljava/lang/String;Ljava/lang/Throwable;)V
      33: areturn
      34: aconst_null
      35: areturn

  private java.lang.String extractChangelogPath(liquibase.exception.ChangeLogParseException);
    Code:
       0: aload_1
       1: invokevirtual #7                  // Method liquibase/exception/ChangeLogParseException.getMessage:()Ljava/lang/String;
       4: iconst_0
       5: aload_1
       6: invokevirtual #7                  // Method liquibase/exception/ChangeLogParseException.getMessage:()Ljava/lang/String;
       9: invokevirtual #38                 // Method java/lang/String.length:()I
      12: ldc           #15                 // String  does not exist
      14: invokevirtual #38                 // Method java/lang/String.length:()I
      17: isub
      18: invokevirtual #42                 // Method java/lang/String.substring:(II)Ljava/lang/String;
      21: areturn

  private java.lang.String getDescription(java.lang.String);
    Code:
       0: aload_1
       1: invokedynamic #46,  0             // InvokeDynamic #0:makeConcatWithConstants:(Ljava/lang/String;)Ljava/lang/String;
       6: areturn

  protected org.springframework.boot.diagnostics.FailureAnalysis analyze(java.lang.Throwable, java.lang.Throwable);
    Code:
       0: aload_0
       1: aload_1
       2: aload_2
       3: checkcast     #8                  // class liquibase/exception/ChangeLogParseException
       6: invokevirtual #49                 // Method analyze:(Ljava/lang/Throwable;Lliquibase/exception/ChangeLogParseException;)Lorg/springframework/boot/diagnostics/FailureAnalysis;
       9: areturn
}
