Compiled from "JavassistProxyFactory.java"
class org.apache.dubbo.rpc.proxy.javassist.JavassistProxyFactory$1 extends org.apache.dubbo.rpc.proxy.AbstractProxyInvoker<T> {
  final org.apache.dubbo.common.bytecode.Wrapper val$wrapper;

  final org.apache.dubbo.rpc.proxy.javassist.JavassistProxyFactory this$0;

  org.apache.dubbo.rpc.proxy.javassist.JavassistProxyFactory$1(org.apache.dubbo.rpc.proxy.javassist.JavassistProxyFactory, java.lang.Object, java.lang.Class, org.apache.dubbo.common.URL, org.apache.dubbo.common.bytecode.Wrapper);
    Code:
       0: aload_0
       1: aload_1
       2: putfield      #1                  // Field this$0:Lorg/apache/dubbo/rpc/proxy/javassist/JavassistProxyFactory;
       5: aload_0
       6: aload         5
       8: putfield      #2                  // Field val$wrapper:Lorg/apache/dubbo/common/bytecode/Wrapper;
      11: aload_0
      12: aload_2
      13: aload_3
      14: aload         4
      16: invokespecial #3                  // Method org/apache/dubbo/rpc/proxy/AbstractProxyInvoker."<init>":(Ljava/lang/Object;Ljava/lang/Class;Lorg/apache/dubbo/common/URL;)V
      19: return

  protected java.lang.Object doInvoke(T, java.lang.String, java.lang.Class<?>[], java.lang.Object[]) throws java.lang.Throwable;
    Code:
       0: aload_0
       1: getfield      #2                  // Field val$wrapper:Lorg/apache/dubbo/common/bytecode/Wrapper;
       4: aload_1
       5: aload_2
       6: aload_3
       7: aload         4
       9: invokevirtual #4                  // Method org/apache/dubbo/common/bytecode/Wrapper.invokeMethod:(Ljava/lang/Object;Ljava/lang/String;[Ljava/lang/Class;[Ljava/lang/Object;)Ljava/lang/Object;
      12: areturn
}
