Compiled from "JavassistProxyFactory.java"
public class org.apache.dubbo.rpc.proxy.javassist.JavassistProxyFactory extends org.apache.dubbo.rpc.proxy.AbstractProxyFactory {
  private static final org.apache.dubbo.common.logger.ErrorTypeAwareLogger logger;

  private final org.apache.dubbo.rpc.proxy.jdk.JdkProxyFactory jdkProxyFactory;

  public org.apache.dubbo.rpc.proxy.javassist.JavassistProxyFactory();
    Code:
       0: aload_0
       1: invokespecial #2                  // Method org/apache/dubbo/rpc/proxy/AbstractProxyFactory."<init>":()V
       4: aload_0
       5: new           #3                  // class org/apache/dubbo/rpc/proxy/jdk/JdkProxyFactory
       8: dup
       9: invokespecial #4                  // Method org/apache/dubbo/rpc/proxy/jdk/JdkProxyFactory."<init>":()V
      12: putfield      #5                  // Field jdkProxyFactory:Lorg/apache/dubbo/rpc/proxy/jdk/JdkProxyFactory;
      15: return

  public <T> T getProxy(org.apache.dubbo.rpc.Invoker<T>, java.lang.Class<?>[]);
    Code:
       0: aload_2
       1: invokestatic  #6                  // Method org/apache/dubbo/common/bytecode/Proxy.getProxy:([Ljava/lang/Class;)Lorg/apache/dubbo/common/bytecode/Proxy;
       4: new           #7                  // class org/apache/dubbo/rpc/proxy/InvokerInvocationHandler
       7: dup
       8: aload_1
       9: invokespecial #8                  // Method org/apache/dubbo/rpc/proxy/InvokerInvocationHandler."<init>":(Lorg/apache/dubbo/rpc/Invoker;)V
      12: invokevirtual #9                  // Method org/apache/dubbo/common/bytecode/Proxy.newInstance:(Ljava/lang/reflect/InvocationHandler;)Ljava/lang/Object;
      15: areturn
      16: astore_3
      17: aload_0
      18: getfield      #5                  // Field jdkProxyFactory:Lorg/apache/dubbo/rpc/proxy/jdk/JdkProxyFactory;
      21: aload_1
      22: aload_2
      23: invokevirtual #11                 // Method org/apache/dubbo/rpc/proxy/jdk/JdkProxyFactory.getProxy:(Lorg/apache/dubbo/rpc/Invoker;[Ljava/lang/Class;)Ljava/lang/Object;
      26: astore        4
      28: getstatic     #12                 // Field logger:Lorg/apache/dubbo/common/logger/ErrorTypeAwareLogger;
      31: ldc           #13                 // String 3-8
      33: ldc           #14                 // String
      35: ldc           #14                 // String
      37: new           #15                 // class java/lang/StringBuilder
      40: dup
      41: invokespecial #16                 // Method java/lang/StringBuilder."<init>":()V
      44: ldc           #17                 // String Failed to generate proxy by Javassist failed. Fallback to use JDK proxy success. Interfaces:
      46: invokevirtual #18                 // Method java/lang/StringBuilder.append:(Ljava/lang/String;)Ljava/lang/StringBuilder;
      49: aload_2
      50: invokestatic  #19                 // Method java/util/Arrays.toString:([Ljava/lang/Object;)Ljava/lang/String;
      53: invokevirtual #18                 // Method java/lang/StringBuilder.append:(Ljava/lang/String;)Ljava/lang/StringBuilder;
      56: invokevirtual #20                 // Method java/lang/StringBuilder.toString:()Ljava/lang/String;
      59: aload_3
      60: invokeinterface #21,  6           // InterfaceMethod org/apache/dubbo/common/logger/ErrorTypeAwareLogger.error:(Ljava/lang/String;Ljava/lang/String;Ljava/lang/String;Ljava/lang/String;Ljava/lang/Throwable;)V
      65: aload         4
      67: areturn
      68: astore        4
      70: getstatic     #12                 // Field logger:Lorg/apache/dubbo/common/logger/ErrorTypeAwareLogger;
      73: ldc           #13                 // String 3-8
      75: ldc           #14                 // String
      77: ldc           #14                 // String
      79: new           #15                 // class java/lang/StringBuilder
      82: dup
      83: invokespecial #16                 // Method java/lang/StringBuilder."<init>":()V
      86: ldc           #22                 // String Failed to generate proxy by Javassist failed. Fallback to use JDK proxy is also failed. Interfaces:
      88: invokevirtual #18                 // Method java/lang/StringBuilder.append:(Ljava/lang/String;)Ljava/lang/StringBuilder;
      91: aload_2
      92: invokestatic  #19                 // Method java/util/Arrays.toString:([Ljava/lang/Object;)Ljava/lang/String;
      95: invokevirtual #18                 // Method java/lang/StringBuilder.append:(Ljava/lang/String;)Ljava/lang/StringBuilder;
      98: ldc           #23                 // String  Javassist Error.
     100: invokevirtual #18                 // Method java/lang/StringBuilder.append:(Ljava/lang/String;)Ljava/lang/StringBuilder;
     103: invokevirtual #20                 // Method java/lang/StringBuilder.toString:()Ljava/lang/String;
     106: aload_3
     107: invokeinterface #21,  6           // InterfaceMethod org/apache/dubbo/common/logger/ErrorTypeAwareLogger.error:(Ljava/lang/String;Ljava/lang/String;Ljava/lang/String;Ljava/lang/String;Ljava/lang/Throwable;)V
     112: getstatic     #12                 // Field logger:Lorg/apache/dubbo/common/logger/ErrorTypeAwareLogger;
     115: ldc           #13                 // String 3-8
     117: ldc           #14                 // String
     119: ldc           #14                 // String
     121: new           #15                 // class java/lang/StringBuilder
     124: dup
     125: invokespecial #16                 // Method java/lang/StringBuilder."<init>":()V
     128: ldc           #22                 // String Failed to generate proxy by Javassist failed. Fallback to use JDK proxy is also failed. Interfaces:
     130: invokevirtual #18                 // Method java/lang/StringBuilder.append:(Ljava/lang/String;)Ljava/lang/StringBuilder;
     133: aload_2
     134: invokestatic  #19                 // Method java/util/Arrays.toString:([Ljava/lang/Object;)Ljava/lang/String;
     137: invokevirtual #18                 // Method java/lang/StringBuilder.append:(Ljava/lang/String;)Ljava/lang/StringBuilder;
     140: ldc           #24                 // String  JDK Error.
     142: invokevirtual #18                 // Method java/lang/StringBuilder.append:(Ljava/lang/String;)Ljava/lang/StringBuilder;
     145: invokevirtual #20                 // Method java/lang/StringBuilder.toString:()Ljava/lang/String;
     148: aload         4
     150: invokeinterface #21,  6           // InterfaceMethod org/apache/dubbo/common/logger/ErrorTypeAwareLogger.error:(Ljava/lang/String;Ljava/lang/String;Ljava/lang/String;Ljava/lang/String;Ljava/lang/Throwable;)V
     155: aload_3
     156: athrow
    Exception table:
       from    to  target type
           0    15    16   Class java/lang/Throwable
          17    67    68   Class java/lang/Throwable

  public <T> org.apache.dubbo.rpc.Invoker<T> getInvoker(T, java.lang.Class<T>, org.apache.dubbo.common.URL);
    Code:
       0: aload_1
       1: invokevirtual #25                 // Method java/lang/Object.getClass:()Ljava/lang/Class;
       4: invokevirtual #26                 // Method java/lang/Class.getName:()Ljava/lang/String;
       7: bipush        36
       9: invokevirtual #27                 // Method java/lang/String.indexOf:(I)I
      12: ifge          22
      15: aload_1
      16: invokevirtual #25                 // Method java/lang/Object.getClass:()Ljava/lang/Class;
      19: goto          23
      22: aload_2
      23: invokestatic  #28                 // Method org/apache/dubbo/common/bytecode/Wrapper.getWrapper:(Ljava/lang/Class;)Lorg/apache/dubbo/common/bytecode/Wrapper;
      26: astore        4
      28: new           #29                 // class org/apache/dubbo/rpc/proxy/javassist/JavassistProxyFactory$1
      31: dup
      32: aload_0
      33: aload_1
      34: aload_2
      35: aload_3
      36: aload         4
      38: invokespecial #30                 // Method org/apache/dubbo/rpc/proxy/javassist/JavassistProxyFactory$1."<init>":(Lorg/apache/dubbo/rpc/proxy/javassist/JavassistProxyFactory;Ljava/lang/Object;Ljava/lang/Class;Lorg/apache/dubbo/common/URL;Lorg/apache/dubbo/common/bytecode/Wrapper;)V
      41: areturn
      42: astore        4
      44: aload_0
      45: getfield      #5                  // Field jdkProxyFactory:Lorg/apache/dubbo/rpc/proxy/jdk/JdkProxyFactory;
      48: aload_1
      49: aload_2
      50: aload_3
      51: invokevirtual #31                 // Method org/apache/dubbo/rpc/proxy/jdk/JdkProxyFactory.getInvoker:(Ljava/lang/Object;Ljava/lang/Class;Lorg/apache/dubbo/common/URL;)Lorg/apache/dubbo/rpc/Invoker;
      54: astore        5
      56: getstatic     #12                 // Field logger:Lorg/apache/dubbo/common/logger/ErrorTypeAwareLogger;
      59: ldc           #13                 // String 3-8
      61: ldc           #14                 // String
      63: ldc           #14                 // String
      65: new           #15                 // class java/lang/StringBuilder
      68: dup
      69: invokespecial #16                 // Method java/lang/StringBuilder."<init>":()V
      72: ldc           #32                 // String Failed to generate invoker by Javassist failed. Fallback to use JDK proxy success. Interfaces:
      74: invokevirtual #18                 // Method java/lang/StringBuilder.append:(Ljava/lang/String;)Ljava/lang/StringBuilder;
      77: aload_2
      78: invokevirtual #33                 // Method java/lang/StringBuilder.append:(Ljava/lang/Object;)Ljava/lang/StringBuilder;
      81: invokevirtual #20                 // Method java/lang/StringBuilder.toString:()Ljava/lang/String;
      84: aload         4
      86: invokeinterface #21,  6           // InterfaceMethod org/apache/dubbo/common/logger/ErrorTypeAwareLogger.error:(Ljava/lang/String;Ljava/lang/String;Ljava/lang/String;Ljava/lang/String;Ljava/lang/Throwable;)V
      91: aload         5
      93: areturn
      94: astore        5
      96: getstatic     #12                 // Field logger:Lorg/apache/dubbo/common/logger/ErrorTypeAwareLogger;
      99: ldc           #13                 // String 3-8
     101: ldc           #14                 // String
     103: ldc           #14                 // String
     105: new           #15                 // class java/lang/StringBuilder
     108: dup
     109: invokespecial #16                 // Method java/lang/StringBuilder."<init>":()V
     112: ldc           #34                 // String Failed to generate invoker by Javassist failed. Fallback to use JDK proxy is also failed. Interfaces:
     114: invokevirtual #18                 // Method java/lang/StringBuilder.append:(Ljava/lang/String;)Ljava/lang/StringBuilder;
     117: aload_2
     118: invokevirtual #33                 // Method java/lang/StringBuilder.append:(Ljava/lang/Object;)Ljava/lang/StringBuilder;
     121: ldc           #23                 // String  Javassist Error.
     123: invokevirtual #18                 // Method java/lang/StringBuilder.append:(Ljava/lang/String;)Ljava/lang/StringBuilder;
     126: invokevirtual #20                 // Method java/lang/StringBuilder.toString:()Ljava/lang/String;
     129: aload         4
     131: invokeinterface #21,  6           // InterfaceMethod org/apache/dubbo/common/logger/ErrorTypeAwareLogger.error:(Ljava/lang/String;Ljava/lang/String;Ljava/lang/String;Ljava/lang/String;Ljava/lang/Throwable;)V
     136: getstatic     #12                 // Field logger:Lorg/apache/dubbo/common/logger/ErrorTypeAwareLogger;
     139: ldc           #13                 // String 3-8
     141: ldc           #14                 // String
     143: ldc           #14                 // String
     145: new           #15                 // class java/lang/StringBuilder
     148: dup
     149: invokespecial #16                 // Method java/lang/StringBuilder."<init>":()V
     152: ldc           #34                 // String Failed to generate invoker by Javassist failed. Fallback to use JDK proxy is also failed. Interfaces:
     154: invokevirtual #18                 // Method java/lang/StringBuilder.append:(Ljava/lang/String;)Ljava/lang/StringBuilder;
     157: aload_2
     158: invokevirtual #33                 // Method java/lang/StringBuilder.append:(Ljava/lang/Object;)Ljava/lang/StringBuilder;
     161: ldc           #24                 // String  JDK Error.
     163: invokevirtual #18                 // Method java/lang/StringBuilder.append:(Ljava/lang/String;)Ljava/lang/StringBuilder;
     166: invokevirtual #20                 // Method java/lang/StringBuilder.toString:()Ljava/lang/String;
     169: aload         5
     171: invokeinterface #21,  6           // InterfaceMethod org/apache/dubbo/common/logger/ErrorTypeAwareLogger.error:(Ljava/lang/String;Ljava/lang/String;Ljava/lang/String;Ljava/lang/String;Ljava/lang/Throwable;)V
     176: aload         4
     178: athrow
    Exception table:
       from    to  target type
           0    41    42   Class java/lang/Throwable
          44    93    94   Class java/lang/Throwable

  static {};
    Code:
       0: ldc           #35                 // class org/apache/dubbo/rpc/proxy/javassist/JavassistProxyFactory
       2: invokestatic  #36                 // Method org/apache/dubbo/common/logger/LoggerFactory.getErrorTypeAwareLogger:(Ljava/lang/Class;)Lorg/apache/dubbo/common/logger/ErrorTypeAwareLogger;
       5: putstatic     #12                 // Field logger:Lorg/apache/dubbo/common/logger/ErrorTypeAwareLogger;
       8: return
}
