Compiled from "BlockingFlowableLatest.java"
public final class io.reactivex.rxjava3.internal.operators.flowable.BlockingFlowableLatest<T> implements java.lang.Iterable<T> {
  final org.reactivestreams.Publisher<? extends T> source;

  public io.reactivex.rxjava3.internal.operators.flowable.BlockingFlowableLatest(org.reactivestreams.Publisher<? extends T>);
    Code:
       0: aload_0
       1: invokespecial #1                  // Method java/lang/Object."<init>":()V
       4: aload_0
       5: aload_1
       6: putfield      #2                  // Field source:Lorg/reactivestreams/Publisher;
       9: return

  public java.util.Iterator<T> iterator();
    Code:
       0: new           #3                  // class io/reactivex/rxjava3/internal/operators/flowable/BlockingFlowableLatest$LatestSubscriberIterator
       3: dup
       4: invokespecial #4                  // Method io/reactivex/rxjava3/internal/operators/flowable/BlockingFlowableLatest$LatestSubscriberIterator."<init>":()V
       7: astore_1
       8: aload_0
       9: getfield      #2                  // Field source:Lorg/reactivestreams/Publisher;
      12: invokestatic  #5                  // Method io/reactivex/rxjava3/core/Flowable.fromPublisher:(Lorg/reactivestreams/Publisher;)Lio/reactivex/rxjava3/core/Flowable;
      15: invokevirtual #6                  // Method io/reactivex/rxjava3/core/Flowable.materialize:()Lio/reactivex/rxjava3/core/Flowable;
      18: aload_1
      19: invokevirtual #7                  // Method io/reactivex/rxjava3/core/Flowable.subscribe:(Lio/reactivex/rxjava3/core/FlowableSubscriber;)V
      22: aload_1
      23: areturn
}
