Compiled from "BlockingFlowableMostRecent.java"
public final class io.reactivex.rxjava3.internal.operators.flowable.BlockingFlowableMostRecent<T> implements java.lang.Iterable<T> {
  final io.reactivex.rxjava3.core.Flowable<T> source;

  final T initialValue;

  public io.reactivex.rxjava3.internal.operators.flowable.BlockingFlowableMostRecent(io.reactivex.rxjava3.core.Flowable<T>, T);
    Code:
       0: aload_0
       1: invokespecial #1                  // Method java/lang/Object."<init>":()V
       4: aload_0
       5: aload_1
       6: putfield      #2                  // Field source:Lio/reactivex/rxjava3/core/Flowable;
       9: aload_0
      10: aload_2
      11: putfield      #3                  // Field initialValue:Ljava/lang/Object;
      14: return

  public java.util.Iterator<T> iterator();
    Code:
       0: new           #4                  // class io/reactivex/rxjava3/internal/operators/flowable/BlockingFlowableMostRecent$MostRecentSubscriber
       3: dup
       4: aload_0
       5: getfield      #3                  // Field initialValue:Ljava/lang/Object;
       8: invokespecial #5                  // Method io/reactivex/rxjava3/internal/operators/flowable/BlockingFlowableMostRecent$MostRecentSubscriber."<init>":(Ljava/lang/Object;)V
      11: astore_1
      12: aload_0
      13: getfield      #2                  // Field source:Lio/reactivex/rxjava3/core/Flowable;
      16: aload_1
      17: invokevirtual #6                  // Method io/reactivex/rxjava3/core/Flowable.subscribe:(Lio/reactivex/rxjava3/core/FlowableSubscriber;)V
      20: aload_1
      21: invokevirtual #7                  // Method io/reactivex/rxjava3/internal/operators/flowable/BlockingFlowableMostRecent$MostRecentSubscriber.getIterable:()Lio/reactivex/rxjava3/internal/operators/flowable/BlockingFlowableMostRecent$MostRecentSubscriber$Iterator;
      24: areturn
}
