Compiled from "BlockingFlowableNext.java"
public final class io.reactivex.rxjava3.internal.operators.flowable.BlockingFlowableNext<T> implements java.lang.Iterable<T> {
  final org.reactivestreams.Publisher<? extends T> source;

  public io.reactivex.rxjava3.internal.operators.flowable.BlockingFlowableNext(org.reactivestreams.Publisher<? extends T>);
    Code:
       0: aload_0
       1: invokespecial #1                  // Method java/lang/Object."<init>":()V
       4: aload_0
       5: aload_1
       6: putfield      #2                  // Field source:Lorg/reactivestreams/Publisher;
       9: return

  public java.util.Iterator<T> iterator();
    Code:
       0: new           #3                  // class io/reactivex/rxjava3/internal/operators/flowable/BlockingFlowableNext$NextSubscriber
       3: dup
       4: invokespecial #4                  // Method io/reactivex/rxjava3/internal/operators/flowable/BlockingFlowableNext$NextSubscriber."<init>":()V
       7: astore_1
       8: new           #5                  // class io/reactivex/rxjava3/internal/operators/flowable/BlockingFlowableNext$NextIterator
      11: dup
      12: aload_0
      13: getfield      #2                  // Field source:Lorg/reactivestreams/Publisher;
      16: aload_1
      17: invokespecial #6                  // Method io/reactivex/rxjava3/internal/operators/flowable/BlockingFlowableNext$NextIterator."<init>":(Lorg/reactivestreams/Publisher;Lio/reactivex/rxjava3/internal/operators/flowable/BlockingFlowableNext$NextSubscriber;)V
      20: areturn
}
