Compiled from "BlockingFlowableMostRecent.java"
final class io.reactivex.rxjava3.internal.operators.flowable.BlockingFlowableMostRecent$MostRecentSubscriber$Iterator implements java.util.Iterator<T> {
  private java.lang.Object buf;

  final io.reactivex.rxjava3.internal.operators.flowable.BlockingFlowableMostRecent$MostRecentSubscriber this$0;

  io.reactivex.rxjava3.internal.operators.flowable.BlockingFlowableMostRecent$MostRecentSubscriber$Iterator(io.reactivex.rxjava3.internal.operators.flowable.BlockingFlowableMostRecent$MostRecentSubscriber);
    Code:
       0: aload_0
       1: aload_1
       2: putfield      #1                  // Field this$0:Lio/reactivex/rxjava3/internal/operators/flowable/BlockingFlowableMostRecent$MostRecentSubscriber;
       5: aload_0
       6: invokespecial #2                  // Method java/lang/Object."<init>":()V
       9: return

  public boolean hasNext();
    Code:
       0: aload_0
       1: aload_0
       2: getfield      #1                  // Field this$0:Lio/reactivex/rxjava3/internal/operators/flowable/BlockingFlowableMostRecent$MostRecentSubscriber;
       5: getfield      #3                  // Field io/reactivex/rxjava3/internal/operators/flowable/BlockingFlowableMostRecent$MostRecentSubscriber.value:Ljava/lang/Object;
       8: putfield      #4                  // Field buf:Ljava/lang/Object;
      11: aload_0
      12: getfield      #4                  // Field buf:Ljava/lang/Object;
      15: invokestatic  #5                  // Method io/reactivex/rxjava3/internal/util/NotificationLite.isComplete:(Ljava/lang/Object;)Z
      18: ifne          25
      21: iconst_1
      22: goto          26
      25: iconst_0
      26: ireturn

  public T next();
    Code:
       0: aload_0
       1: getfield      #4                  // Field buf:Ljava/lang/Object;
       4: ifnonnull     18
       7: aload_0
       8: aload_0
       9: getfield      #1                  // Field this$0:Lio/reactivex/rxjava3/internal/operators/flowable/BlockingFlowableMostRecent$MostRecentSubscriber;
      12: getfield      #3                  // Field io/reactivex/rxjava3/internal/operators/flowable/BlockingFlowableMostRecent$MostRecentSubscriber.value:Ljava/lang/Object;
      15: putfield      #4                  // Field buf:Ljava/lang/Object;
      18: aload_0
      19: getfield      #4                  // Field buf:Ljava/lang/Object;
      22: invokestatic  #5                  // Method io/reactivex/rxjava3/internal/util/NotificationLite.isComplete:(Ljava/lang/Object;)Z
      25: ifeq          36
      28: new           #6                  // class java/util/NoSuchElementException
      31: dup
      32: invokespecial #7                  // Method java/util/NoSuchElementException."<init>":()V
      35: athrow
      36: aload_0
      37: getfield      #4                  // Field buf:Ljava/lang/Object;
      40: invokestatic  #8                  // Method io/reactivex/rxjava3/internal/util/NotificationLite.isError:(Ljava/lang/Object;)Z
      43: ifeq          57
      46: aload_0
      47: getfield      #4                  // Field buf:Ljava/lang/Object;
      50: invokestatic  #9                  // Method io/reactivex/rxjava3/internal/util/NotificationLite.getError:(Ljava/lang/Object;)Ljava/lang/Throwable;
      53: invokestatic  #10                 // Method io/reactivex/rxjava3/internal/util/ExceptionHelper.wrapOrThrow:(Ljava/lang/Throwable;)Ljava/lang/RuntimeException;
      56: athrow
      57: aload_0
      58: getfield      #4                  // Field buf:Ljava/lang/Object;
      61: invokestatic  #11                 // Method io/reactivex/rxjava3/internal/util/NotificationLite.getValue:(Ljava/lang/Object;)Ljava/lang/Object;
      64: astore_1
      65: aload_0
      66: aconst_null
      67: putfield      #4                  // Field buf:Ljava/lang/Object;
      70: aload_1
      71: areturn
      72: astore_2
      73: aload_0
      74: aconst_null
      75: putfield      #4                  // Field buf:Ljava/lang/Object;
      78: aload_2
      79: athrow
    Exception table:
       from    to  target type
           0    65    72   any

  public void remove();
    Code:
       0: new           #12                 // class java/lang/UnsupportedOperationException
       3: dup
       4: ldc           #13                 // String Read only iterator
       6: invokespecial #14                 // Method java/lang/UnsupportedOperationException."<init>":(Ljava/lang/String;)V
       9: athrow
}
