Compiled from "BlockingFlowableNext.java"
final class io.reactivex.rxjava3.internal.operators.flowable.BlockingFlowableNext$NextIterator<T> implements java.util.Iterator<T> {
  private final io.reactivex.rxjava3.internal.operators.flowable.BlockingFlowableNext$NextSubscriber<T> subscriber;

  private final org.reactivestreams.Publisher<? extends T> items;

  private T next;

  private boolean hasNext;

  private boolean isNextConsumed;

  private java.lang.Throwable error;

  private boolean started;

  io.reactivex.rxjava3.internal.operators.flowable.BlockingFlowableNext$NextIterator(org.reactivestreams.Publisher<? extends T>, io.reactivex.rxjava3.internal.operators.flowable.BlockingFlowableNext$NextSubscriber<T>);
    Code:
       0: aload_0
       1: invokespecial #1                  // Method java/lang/Object."<init>":()V
       4: aload_0
       5: iconst_1
       6: putfield      #2                  // Field hasNext:Z
       9: aload_0
      10: iconst_1
      11: putfield      #3                  // Field isNextConsumed:Z
      14: aload_0
      15: aload_1
      16: putfield      #4                  // Field items:Lorg/reactivestreams/Publisher;
      19: aload_0
      20: aload_2
      21: putfield      #5                  // Field subscriber:Lio/reactivex/rxjava3/internal/operators/flowable/BlockingFlowableNext$NextSubscriber;
      24: return

  public boolean hasNext();
    Code:
       0: aload_0
       1: getfield      #6                  // Field error:Ljava/lang/Throwable;
       4: ifnull        15
       7: aload_0
       8: getfield      #6                  // Field error:Ljava/lang/Throwable;
      11: invokestatic  #7                  // Method io/reactivex/rxjava3/internal/util/ExceptionHelper.wrapOrThrow:(Ljava/lang/Throwable;)Ljava/lang/RuntimeException;
      14: athrow
      15: aload_0
      16: getfield      #2                  // Field hasNext:Z
      19: ifne          24
      22: iconst_0
      23: ireturn
      24: aload_0
      25: getfield      #3                  // Field isNextConsumed:Z
      28: ifeq          38
      31: aload_0
      32: invokespecial #8                  // Method moveToNext:()Z
      35: ifeq          42
      38: iconst_1
      39: goto          43
      42: iconst_0
      43: ireturn

  private boolean moveToNext();
    Code:
       0: aload_0
       1: getfield      #9                  // Field started:Z
       4: ifne          36
       7: aload_0
       8: iconst_1
       9: putfield      #9                  // Field started:Z
      12: aload_0
      13: getfield      #5                  // Field subscriber:Lio/reactivex/rxjava3/internal/operators/flowable/BlockingFlowableNext$NextSubscriber;
      16: invokevirtual #10                 // Method io/reactivex/rxjava3/internal/operators/flowable/BlockingFlowableNext$NextSubscriber.setWaiting:()V
      19: aload_0
      20: getfield      #4                  // Field items:Lorg/reactivestreams/Publisher;
      23: invokestatic  #11                 // Method io/reactivex/rxjava3/core/Flowable.fromPublisher:(Lorg/reactivestreams/Publisher;)Lio/reactivex/rxjava3/core/Flowable;
      26: invokevirtual #12                 // Method io/reactivex/rxjava3/core/Flowable.materialize:()Lio/reactivex/rxjava3/core/Flowable;
      29: aload_0
      30: getfield      #5                  // Field subscriber:Lio/reactivex/rxjava3/internal/operators/flowable/BlockingFlowableNext$NextSubscriber;
      33: invokevirtual #13                 // Method io/reactivex/rxjava3/core/Flowable.subscribe:(Lio/reactivex/rxjava3/core/FlowableSubscriber;)V
      36: aload_0
      37: getfield      #5                  // Field subscriber:Lio/reactivex/rxjava3/internal/operators/flowable/BlockingFlowableNext$NextSubscriber;
      40: invokevirtual #14                 // Method io/reactivex/rxjava3/internal/operators/flowable/BlockingFlowableNext$NextSubscriber.takeNext:()Lio/reactivex/rxjava3/core/Notification;
      43: astore_1
      44: aload_1
      45: invokevirtual #15                 // Method io/reactivex/rxjava3/core/Notification.isOnNext:()Z
      48: ifeq          66
      51: aload_0
      52: iconst_0
      53: putfield      #3                  // Field isNextConsumed:Z
      56: aload_0
      57: aload_1
      58: invokevirtual #16                 // Method io/reactivex/rxjava3/core/Notification.getValue:()Ljava/lang/Object;
      61: putfield      #17                 // Field next:Ljava/lang/Object;
      64: iconst_1
      65: ireturn
      66: aload_0
      67: iconst_0
      68: putfield      #2                  // Field hasNext:Z
      71: aload_1
      72: invokevirtual #18                 // Method io/reactivex/rxjava3/core/Notification.isOnComplete:()Z
      75: ifeq          80
      78: iconst_0
      79: ireturn
      80: aload_0
      81: aload_1
      82: invokevirtual #19                 // Method io/reactivex/rxjava3/core/Notification.getError:()Ljava/lang/Throwable;
      85: putfield      #6                  // Field error:Ljava/lang/Throwable;
      88: aload_0
      89: getfield      #6                  // Field error:Ljava/lang/Throwable;
      92: invokestatic  #7                  // Method io/reactivex/rxjava3/internal/util/ExceptionHelper.wrapOrThrow:(Ljava/lang/Throwable;)Ljava/lang/RuntimeException;
      95: athrow
      96: astore_1
      97: aload_0
      98: getfield      #5                  // Field subscriber:Lio/reactivex/rxjava3/internal/operators/flowable/BlockingFlowableNext$NextSubscriber;
     101: invokevirtual #21                 // Method io/reactivex/rxjava3/internal/operators/flowable/BlockingFlowableNext$NextSubscriber.dispose:()V
     104: aload_0
     105: aload_1
     106: putfield      #6                  // Field error:Ljava/lang/Throwable;
     109: aload_1
     110: invokestatic  #7                  // Method io/reactivex/rxjava3/internal/util/ExceptionHelper.wrapOrThrow:(Ljava/lang/Throwable;)Ljava/lang/RuntimeException;
     113: athrow
    Exception table:
       from    to  target type
           0    65    96   Class java/lang/InterruptedException
          66    79    96   Class java/lang/InterruptedException
          80    96    96   Class java/lang/InterruptedException

  public T next();
    Code:
       0: aload_0
       1: getfield      #6                  // Field error:Ljava/lang/Throwable;
       4: ifnull        15
       7: aload_0
       8: getfield      #6                  // Field error:Ljava/lang/Throwable;
      11: invokestatic  #7                  // Method io/reactivex/rxjava3/internal/util/ExceptionHelper.wrapOrThrow:(Ljava/lang/Throwable;)Ljava/lang/RuntimeException;
      14: athrow
      15: aload_0
      16: invokevirtual #22                 // Method hasNext:()Z
      19: ifeq          32
      22: aload_0
      23: iconst_1
      24: putfield      #3                  // Field isNextConsumed:Z
      27: aload_0
      28: getfield      #17                 // Field next:Ljava/lang/Object;
      31: areturn
      32: new           #23                 // class java/util/NoSuchElementException
      35: dup
      36: ldc           #24                 // String No more elements
      38: invokespecial #25                 // Method java/util/NoSuchElementException."<init>":(Ljava/lang/String;)V
      41: athrow

  public void remove();
    Code:
       0: new           #26                 // class java/lang/UnsupportedOperationException
       3: dup
       4: ldc           #27                 // String Read only iterator
       6: invokespecial #28                 // Method java/lang/UnsupportedOperationException."<init>":(Ljava/lang/String;)V
       9: athrow
}
