Compiled from "FlowableDematerialize.java"
final class io.reactivex.rxjava3.internal.operators.flowable.FlowableDematerialize$DematerializeSubscriber<T, R> implements io.reactivex.rxjava3.core.FlowableSubscriber<T>, org.reactivestreams.Subscription {
  final org.reactivestreams.Subscriber<? super R> downstream;

  final io.reactivex.rxjava3.functions.Function<? super T, ? extends io.reactivex.rxjava3.core.Notification<R>> selector;

  boolean done;

  org.reactivestreams.Subscription upstream;

  io.reactivex.rxjava3.internal.operators.flowable.FlowableDematerialize$DematerializeSubscriber(org.reactivestreams.Subscriber<? super R>, io.reactivex.rxjava3.functions.Function<? super T, ? extends io.reactivex.rxjava3.core.Notification<R>>);
    Code:
       0: aload_0
       1: invokespecial #1                  // Method java/lang/Object."<init>":()V
       4: aload_0
       5: aload_1
       6: putfield      #2                  // Field downstream:Lorg/reactivestreams/Subscriber;
       9: aload_0
      10: aload_2
      11: putfield      #3                  // Field selector:Lio/reactivex/rxjava3/functions/Function;
      14: return

  public void onSubscribe(org.reactivestreams.Subscription);
    Code:
       0: aload_0
       1: getfield      #4                  // Field upstream:Lorg/reactivestreams/Subscription;
       4: aload_1
       5: invokestatic  #5                  // Method io/reactivex/rxjava3/internal/subscriptions/SubscriptionHelper.validate:(Lorg/reactivestreams/Subscription;Lorg/reactivestreams/Subscription;)Z
       8: ifeq          26
      11: aload_0
      12: aload_1
      13: putfield      #4                  // Field upstream:Lorg/reactivestreams/Subscription;
      16: aload_0
      17: getfield      #2                  // Field downstream:Lorg/reactivestreams/Subscriber;
      20: aload_0
      21: invokeinterface #6,  2            // InterfaceMethod org/reactivestreams/Subscriber.onSubscribe:(Lorg/reactivestreams/Subscription;)V
      26: return

  public void onNext(T);
    Code:
       0: aload_0
       1: getfield      #7                  // Field done:Z
       4: ifeq          34
       7: aload_1
       8: instanceof    #8                  // class io/reactivex/rxjava3/core/Notification
      11: ifeq          33
      14: aload_1
      15: checkcast     #8                  // class io/reactivex/rxjava3/core/Notification
      18: astore_2
      19: aload_2
      20: invokevirtual #9                  // Method io/reactivex/rxjava3/core/Notification.isOnError:()Z
      23: ifeq          33
      26: aload_2
      27: invokevirtual #10                 // Method io/reactivex/rxjava3/core/Notification.getError:()Ljava/lang/Throwable;
      30: invokestatic  #11                 // Method io/reactivex/rxjava3/plugins/RxJavaPlugins.onError:(Ljava/lang/Throwable;)V
      33: return
      34: aload_0
      35: getfield      #3                  // Field selector:Lio/reactivex/rxjava3/functions/Function;
      38: aload_1
      39: invokeinterface #12,  2           // InterfaceMethod io/reactivex/rxjava3/functions/Function.apply:(Ljava/lang/Object;)Ljava/lang/Object;
      44: ldc           #13                 // String The selector returned a null Notification
      46: invokestatic  #14                 // Method java/util/Objects.requireNonNull:(Ljava/lang/Object;Ljava/lang/String;)Ljava/lang/Object;
      49: checkcast     #8                  // class io/reactivex/rxjava3/core/Notification
      52: astore_2
      53: goto          76
      56: astore_3
      57: aload_3
      58: invokestatic  #16                 // Method io/reactivex/rxjava3/exceptions/Exceptions.throwIfFatal:(Ljava/lang/Throwable;)V
      61: aload_0
      62: getfield      #4                  // Field upstream:Lorg/reactivestreams/Subscription;
      65: invokeinterface #17,  1           // InterfaceMethod org/reactivestreams/Subscription.cancel:()V
      70: aload_0
      71: aload_3
      72: invokevirtual #18                 // Method onError:(Ljava/lang/Throwable;)V
      75: return
      76: aload_2
      77: invokevirtual #9                  // Method io/reactivex/rxjava3/core/Notification.isOnError:()Z
      80: ifeq          103
      83: aload_0
      84: getfield      #4                  // Field upstream:Lorg/reactivestreams/Subscription;
      87: invokeinterface #17,  1           // InterfaceMethod org/reactivestreams/Subscription.cancel:()V
      92: aload_0
      93: aload_2
      94: invokevirtual #10                 // Method io/reactivex/rxjava3/core/Notification.getError:()Ljava/lang/Throwable;
      97: invokevirtual #18                 // Method onError:(Ljava/lang/Throwable;)V
     100: goto          139
     103: aload_2
     104: invokevirtual #19                 // Method io/reactivex/rxjava3/core/Notification.isOnComplete:()Z
     107: ifeq          126
     110: aload_0
     111: getfield      #4                  // Field upstream:Lorg/reactivestreams/Subscription;
     114: invokeinterface #17,  1           // InterfaceMethod org/reactivestreams/Subscription.cancel:()V
     119: aload_0
     120: invokevirtual #20                 // Method onComplete:()V
     123: goto          139
     126: aload_0
     127: getfield      #2                  // Field downstream:Lorg/reactivestreams/Subscriber;
     130: aload_2
     131: invokevirtual #21                 // Method io/reactivex/rxjava3/core/Notification.getValue:()Ljava/lang/Object;
     134: invokeinterface #22,  2           // InterfaceMethod org/reactivestreams/Subscriber.onNext:(Ljava/lang/Object;)V
     139: return
    Exception table:
       from    to  target type
          34    53    56   Class java/lang/Throwable

  public void onError(java.lang.Throwable);
    Code:
       0: aload_0
       1: getfield      #7                  // Field done:Z
       4: ifeq          12
       7: aload_1
       8: invokestatic  #11                 // Method io/reactivex/rxjava3/plugins/RxJavaPlugins.onError:(Ljava/lang/Throwable;)V
      11: return
      12: aload_0
      13: iconst_1
      14: putfield      #7                  // Field done:Z
      17: aload_0
      18: getfield      #2                  // Field downstream:Lorg/reactivestreams/Subscriber;
      21: aload_1
      22: invokeinterface #23,  2           // InterfaceMethod org/reactivestreams/Subscriber.onError:(Ljava/lang/Throwable;)V
      27: return

  public void onComplete();
    Code:
       0: aload_0
       1: getfield      #7                  // Field done:Z
       4: ifeq          8
       7: return
       8: aload_0
       9: iconst_1
      10: putfield      #7                  // Field done:Z
      13: aload_0
      14: getfield      #2                  // Field downstream:Lorg/reactivestreams/Subscriber;
      17: invokeinterface #24,  1           // InterfaceMethod org/reactivestreams/Subscriber.onComplete:()V
      22: return

  public void request(long);
    Code:
       0: aload_0
       1: getfield      #4                  // Field upstream:Lorg/reactivestreams/Subscription;
       4: lload_1
       5: invokeinterface #25,  3           // InterfaceMethod org/reactivestreams/Subscription.request:(J)V
      10: return

  public void cancel();
    Code:
       0: aload_0
       1: getfield      #4                  // Field upstream:Lorg/reactivestreams/Subscription;
       4: invokeinterface #17,  1           // InterfaceMethod org/reactivestreams/Subscription.cancel:()V
       9: return
}
