Compiled from "FlowableDefer.java"
public final class io.reactivex.rxjava3.internal.operators.flowable.FlowableDefer<T> extends io.reactivex.rxjava3.core.Flowable<T> {
  final io.reactivex.rxjava3.functions.Supplier<? extends org.reactivestreams.Publisher<? extends T>> supplier;

  public io.reactivex.rxjava3.internal.operators.flowable.FlowableDefer(io.reactivex.rxjava3.functions.Supplier<? extends org.reactivestreams.Publisher<? extends T>>);
    Code:
       0: aload_0
       1: invokespecial #1                  // Method io/reactivex/rxjava3/core/Flowable."<init>":()V
       4: aload_0
       5: aload_1
       6: putfield      #2                  // Field supplier:Lio/reactivex/rxjava3/functions/Supplier;
       9: return

  public void subscribeActual(org.reactivestreams.Subscriber<? super T>);
    Code:
       0: aload_0
       1: getfield      #2                  // Field supplier:Lio/reactivex/rxjava3/functions/Supplier;
       4: invokeinterface #3,  1            // InterfaceMethod io/reactivex/rxjava3/functions/Supplier.get:()Ljava/lang/Object;
       9: ldc           #4                  // String The publisher supplied is null
      11: invokestatic  #5                  // Method java/util/Objects.requireNonNull:(Ljava/lang/Object;Ljava/lang/String;)Ljava/lang/Object;
      14: checkcast     #6                  // class org/reactivestreams/Publisher
      17: astore_2
      18: goto          32
      21: astore_3
      22: aload_3
      23: invokestatic  #8                  // Method io/reactivex/rxjava3/exceptions/Exceptions.throwIfFatal:(Ljava/lang/Throwable;)V
      26: aload_3
      27: aload_1
      28: invokestatic  #9                  // Method io/reactivex/rxjava3/internal/subscriptions/EmptySubscription.error:(Ljava/lang/Throwable;Lorg/reactivestreams/Subscriber;)V
      31: return
      32: aload_2
      33: aload_1
      34: invokeinterface #10,  2           // InterfaceMethod org/reactivestreams/Publisher.subscribe:(Lorg/reactivestreams/Subscriber;)V
      39: return
    Exception table:
       from    to  target type
           0    18    21   Class java/lang/Throwable
}
