Compiled from "FlowableFlatMapCompletableCompletable.java"
final class io.reactivex.rxjava3.internal.operators.flowable.FlowableFlatMapCompletableCompletable$FlatMapCompletableMainSubscriber$InnerObserver extends java.util.concurrent.atomic.AtomicReference<io.reactivex.rxjava3.disposables.Disposable> implements io.reactivex.rxjava3.core.CompletableObserver, io.reactivex.rxjava3.disposables.Disposable {
  private static final long serialVersionUID;

  final io.reactivex.rxjava3.internal.operators.flowable.FlowableFlatMapCompletableCompletable$FlatMapCompletableMainSubscriber this$0;

  io.reactivex.rxjava3.internal.operators.flowable.FlowableFlatMapCompletableCompletable$FlatMapCompletableMainSubscriber$InnerObserver(io.reactivex.rxjava3.internal.operators.flowable.FlowableFlatMapCompletableCompletable$FlatMapCompletableMainSubscriber);
    Code:
       0: aload_0
       1: aload_1
       2: putfield      #1                  // Field this$0:Lio/reactivex/rxjava3/internal/operators/flowable/FlowableFlatMapCompletableCompletable$FlatMapCompletableMainSubscriber;
       5: aload_0
       6: invokespecial #2                  // Method java/util/concurrent/atomic/AtomicReference."<init>":()V
       9: return

  public void onSubscribe(io.reactivex.rxjava3.disposables.Disposable);
    Code:
       0: aload_0
       1: aload_1
       2: invokestatic  #3                  // Method io/reactivex/rxjava3/internal/disposables/DisposableHelper.setOnce:(Ljava/util/concurrent/atomic/AtomicReference;Lio/reactivex/rxjava3/disposables/Disposable;)Z
       5: pop
       6: return

  public void onComplete();
    Code:
       0: aload_0
       1: getfield      #1                  // Field this$0:Lio/reactivex/rxjava3/internal/operators/flowable/FlowableFlatMapCompletableCompletable$FlatMapCompletableMainSubscriber;
       4: aload_0
       5: invokevirtual #4                  // Method io/reactivex/rxjava3/internal/operators/flowable/FlowableFlatMapCompletableCompletable$FlatMapCompletableMainSubscriber.innerComplete:(Lio/reactivex/rxjava3/internal/operators/flowable/FlowableFlatMapCompletableCompletable$FlatMapCompletableMainSubscriber$InnerObserver;)V
       8: return

  public void onError(java.lang.Throwable);
    Code:
       0: aload_0
       1: getfield      #1                  // Field this$0:Lio/reactivex/rxjava3/internal/operators/flowable/FlowableFlatMapCompletableCompletable$FlatMapCompletableMainSubscriber;
       4: aload_0
       5: aload_1
       6: invokevirtual #5                  // Method io/reactivex/rxjava3/internal/operators/flowable/FlowableFlatMapCompletableCompletable$FlatMapCompletableMainSubscriber.innerError:(Lio/reactivex/rxjava3/internal/operators/flowable/FlowableFlatMapCompletableCompletable$FlatMapCompletableMainSubscriber$InnerObserver;Ljava/lang/Throwable;)V
       9: return

  public void dispose();
    Code:
       0: aload_0
       1: invokestatic  #6                  // Method io/reactivex/rxjava3/internal/disposables/DisposableHelper.dispose:(Ljava/util/concurrent/atomic/AtomicReference;)Z
       4: pop
       5: return

  public boolean isDisposed();
    Code:
       0: aload_0
       1: invokevirtual #7                  // Method get:()Ljava/lang/Object;
       4: checkcast     #8                  // class io/reactivex/rxjava3/disposables/Disposable
       7: invokestatic  #9                  // Method io/reactivex/rxjava3/internal/disposables/DisposableHelper.isDisposed:(Lio/reactivex/rxjava3/disposables/Disposable;)Z
      10: ireturn
}
