Compiled from "FlowableConcatWithMaybe.java"
final class io.reactivex.rxjava3.internal.operators.flowable.FlowableConcatWithMaybe$ConcatWithSubscriber<T> extends io.reactivex.rxjava3.internal.subscribers.SinglePostCompleteSubscriber<T, T> implements io.reactivex.rxjava3.core.MaybeObserver<T> {
  private static final long serialVersionUID;

  final java.util.concurrent.atomic.AtomicReference<io.reactivex.rxjava3.disposables.Disposable> otherDisposable;

  io.reactivex.rxjava3.core.MaybeSource<? extends T> other;

  boolean inMaybe;

  io.reactivex.rxjava3.internal.operators.flowable.FlowableConcatWithMaybe$ConcatWithSubscriber(org.reactivestreams.Subscriber<? super T>, io.reactivex.rxjava3.core.MaybeSource<? extends T>);
    Code:
       0: aload_0
       1: aload_1
       2: invokespecial #1                  // Method io/reactivex/rxjava3/internal/subscribers/SinglePostCompleteSubscriber."<init>":(Lorg/reactivestreams/Subscriber;)V
       5: aload_0
       6: aload_2
       7: putfield      #2                  // Field other:Lio/reactivex/rxjava3/core/MaybeSource;
      10: aload_0
      11: new           #3                  // class java/util/concurrent/atomic/AtomicReference
      14: dup
      15: invokespecial #4                  // Method java/util/concurrent/atomic/AtomicReference."<init>":()V
      18: putfield      #5                  // Field otherDisposable:Ljava/util/concurrent/atomic/AtomicReference;
      21: return

  public void onSubscribe(io.reactivex.rxjava3.disposables.Disposable);
    Code:
       0: aload_0
       1: getfield      #5                  // Field otherDisposable:Ljava/util/concurrent/atomic/AtomicReference;
       4: aload_1
       5: invokestatic  #6                  // Method io/reactivex/rxjava3/internal/disposables/DisposableHelper.setOnce:(Ljava/util/concurrent/atomic/AtomicReference;Lio/reactivex/rxjava3/disposables/Disposable;)Z
       8: pop
       9: return

  public void onNext(T);
    Code:
       0: aload_0
       1: dup
       2: getfield      #7                  // Field produced:J
       5: lconst_1
       6: ladd
       7: putfield      #7                  // Field produced:J
      10: aload_0
      11: getfield      #8                  // Field downstream:Lorg/reactivestreams/Subscriber;
      14: aload_1
      15: invokeinterface #9,  2            // InterfaceMethod org/reactivestreams/Subscriber.onNext:(Ljava/lang/Object;)V
      20: return

  public void onError(java.lang.Throwable);
    Code:
       0: aload_0
       1: getfield      #8                  // Field downstream:Lorg/reactivestreams/Subscriber;
       4: aload_1
       5: invokeinterface #10,  2           // InterfaceMethod org/reactivestreams/Subscriber.onError:(Ljava/lang/Throwable;)V
      10: return

  public void onSuccess(T);
    Code:
       0: aload_0
       1: aload_1
       2: invokevirtual #11                 // Method complete:(Ljava/lang/Object;)V
       5: return

  public void onComplete();
    Code:
       0: aload_0
       1: getfield      #12                 // Field inMaybe:Z
       4: ifeq          19
       7: aload_0
       8: getfield      #8                  // Field downstream:Lorg/reactivestreams/Subscriber;
      11: invokeinterface #13,  1           // InterfaceMethod org/reactivestreams/Subscriber.onComplete:()V
      16: goto          48
      19: aload_0
      20: iconst_1
      21: putfield      #12                 // Field inMaybe:Z
      24: aload_0
      25: getstatic     #14                 // Field io/reactivex/rxjava3/internal/subscriptions/SubscriptionHelper.CANCELLED:Lio/reactivex/rxjava3/internal/subscriptions/SubscriptionHelper;
      28: putfield      #15                 // Field upstream:Lorg/reactivestreams/Subscription;
      31: aload_0
      32: getfield      #2                  // Field other:Lio/reactivex/rxjava3/core/MaybeSource;
      35: astore_1
      36: aload_0
      37: aconst_null
      38: putfield      #2                  // Field other:Lio/reactivex/rxjava3/core/MaybeSource;
      41: aload_1
      42: aload_0
      43: invokeinterface #16,  2           // InterfaceMethod io/reactivex/rxjava3/core/MaybeSource.subscribe:(Lio/reactivex/rxjava3/core/MaybeObserver;)V
      48: return

  public void cancel();
    Code:
       0: aload_0
       1: invokespecial #17                 // Method io/reactivex/rxjava3/internal/subscribers/SinglePostCompleteSubscriber.cancel:()V
       4: aload_0
       5: getfield      #5                  // Field otherDisposable:Ljava/util/concurrent/atomic/AtomicReference;
       8: invokestatic  #18                 // Method io/reactivex/rxjava3/internal/disposables/DisposableHelper.dispose:(Ljava/util/concurrent/atomic/AtomicReference;)Z
      11: pop
      12: return
}
