Compiled from "FlowableDematerialize.java"
public final class io.reactivex.rxjava3.internal.operators.flowable.FlowableDematerialize<T, R> extends io.reactivex.rxjava3.internal.operators.flowable.AbstractFlowableWithUpstream<T, R> {
  final io.reactivex.rxjava3.functions.Function<? super T, ? extends io.reactivex.rxjava3.core.Notification<R>> selector;

  public io.reactivex.rxjava3.internal.operators.flowable.FlowableDematerialize(io.reactivex.rxjava3.core.Flowable<T>, io.reactivex.rxjava3.functions.Function<? super T, ? extends io.reactivex.rxjava3.core.Notification<R>>);
    Code:
       0: aload_0
       1: aload_1
       2: invokespecial #1                  // Method io/reactivex/rxjava3/internal/operators/flowable/AbstractFlowableWithUpstream."<init>":(Lio/reactivex/rxjava3/core/Flowable;)V
       5: aload_0
       6: aload_2
       7: putfield      #2                  // Field selector:Lio/reactivex/rxjava3/functions/Function;
      10: return

  protected void subscribeActual(org.reactivestreams.Subscriber<? super R>);
    Code:
       0: aload_0
       1: getfield      #3                  // Field source:Lio/reactivex/rxjava3/core/Flowable;
       4: new           #4                  // class io/reactivex/rxjava3/internal/operators/flowable/FlowableDematerialize$DematerializeSubscriber
       7: dup
       8: aload_1
       9: aload_0
      10: getfield      #2                  // Field selector:Lio/reactivex/rxjava3/functions/Function;
      13: invokespecial #5                  // Method io/reactivex/rxjava3/internal/operators/flowable/FlowableDematerialize$DematerializeSubscriber."<init>":(Lorg/reactivestreams/Subscriber;Lio/reactivex/rxjava3/functions/Function;)V
      16: invokevirtual #6                  // Method io/reactivex/rxjava3/core/Flowable.subscribe:(Lio/reactivex/rxjava3/core/FlowableSubscriber;)V
      19: return
}
