Compiled from "FlowableUsing.java"
final class io.reactivex.rxjava3.internal.operators.flowable.FlowableUsing$UsingSubscriber<T, D> extends java.util.concurrent.atomic.AtomicBoolean implements io.reactivex.rxjava3.core.FlowableSubscriber<T>, org.reactivestreams.Subscription {
  private static final long serialVersionUID;

  final org.reactivestreams.Subscriber<? super T> downstream;

  final D resource;

  final io.reactivex.rxjava3.functions.Consumer<? super D> disposer;

  final boolean eager;

  org.reactivestreams.Subscription upstream;

  io.reactivex.rxjava3.internal.operators.flowable.FlowableUsing$UsingSubscriber(org.reactivestreams.Subscriber<? super T>, D, io.reactivex.rxjava3.functions.Consumer<? super D>, boolean);
    Code:
       0: aload_0
       1: invokespecial #1                  // Method java/util/concurrent/atomic/AtomicBoolean."<init>":()V
       4: aload_0
       5: aload_1
       6: putfield      #2                  // Field downstream:Lorg/reactivestreams/Subscriber;
       9: aload_0
      10: aload_2
      11: putfield      #3                  // Field resource:Ljava/lang/Object;
      14: aload_0
      15: aload_3
      16: putfield      #4                  // Field disposer:Lio/reactivex/rxjava3/functions/Consumer;
      19: aload_0
      20: iload         4
      22: putfield      #5                  // Field eager:Z
      25: return

  public void onSubscribe(org.reactivestreams.Subscription);
    Code:
       0: aload_0
       1: getfield      #6                  // Field upstream:Lorg/reactivestreams/Subscription;
       4: aload_1
       5: invokestatic  #7                  // Method io/reactivex/rxjava3/internal/subscriptions/SubscriptionHelper.validate:(Lorg/reactivestreams/Subscription;Lorg/reactivestreams/Subscription;)Z
       8: ifeq          26
      11: aload_0
      12: aload_1
      13: putfield      #6                  // Field upstream:Lorg/reactivestreams/Subscription;
      16: aload_0
      17: getfield      #2                  // Field downstream:Lorg/reactivestreams/Subscriber;
      20: aload_0
      21: invokeinterface #8,  2            // InterfaceMethod org/reactivestreams/Subscriber.onSubscribe:(Lorg/reactivestreams/Subscription;)V
      26: return

  public void onNext(T);
    Code:
       0: aload_0
       1: getfield      #2                  // Field downstream:Lorg/reactivestreams/Subscriber;
       4: aload_1
       5: invokeinterface #9,  2            // InterfaceMethod org/reactivestreams/Subscriber.onNext:(Ljava/lang/Object;)V
      10: return

  public void onError(java.lang.Throwable);
    Code:
       0: aload_0
       1: getfield      #5                  // Field eager:Z
       4: ifeq          89
       7: aconst_null
       8: astore_2
       9: aload_0
      10: iconst_0
      11: iconst_1
      12: invokevirtual #10                 // Method compareAndSet:(ZZ)Z
      15: ifeq          41
      18: aload_0
      19: getfield      #4                  // Field disposer:Lio/reactivex/rxjava3/functions/Consumer;
      22: aload_0
      23: getfield      #3                  // Field resource:Ljava/lang/Object;
      26: invokeinterface #11,  2           // InterfaceMethod io/reactivex/rxjava3/functions/Consumer.accept:(Ljava/lang/Object;)V
      31: goto          41
      34: astore_3
      35: aload_3
      36: invokestatic  #13                 // Method io/reactivex/rxjava3/exceptions/Exceptions.throwIfFatal:(Ljava/lang/Throwable;)V
      39: aload_3
      40: astore_2
      41: aload_2
      42: ifnull        76
      45: aload_0
      46: getfield      #2                  // Field downstream:Lorg/reactivestreams/Subscriber;
      49: new           #14                 // class io/reactivex/rxjava3/exceptions/CompositeException
      52: dup
      53: iconst_2
      54: anewarray     #15                 // class java/lang/Throwable
      57: dup
      58: iconst_0
      59: aload_1
      60: aastore
      61: dup
      62: iconst_1
      63: aload_2
      64: aastore
      65: invokespecial #16                 // Method io/reactivex/rxjava3/exceptions/CompositeException."<init>":([Ljava/lang/Throwable;)V
      68: invokeinterface #17,  2           // InterfaceMethod org/reactivestreams/Subscriber.onError:(Ljava/lang/Throwable;)V
      73: goto          86
      76: aload_0
      77: getfield      #2                  // Field downstream:Lorg/reactivestreams/Subscriber;
      80: aload_1
      81: invokeinterface #17,  2           // InterfaceMethod org/reactivestreams/Subscriber.onError:(Ljava/lang/Throwable;)V
      86: goto          103
      89: aload_0
      90: getfield      #2                  // Field downstream:Lorg/reactivestreams/Subscriber;
      93: aload_1
      94: invokeinterface #17,  2           // InterfaceMethod org/reactivestreams/Subscriber.onError:(Ljava/lang/Throwable;)V
      99: aload_0
     100: invokevirtual #18                 // Method disposeResource:()V
     103: return
    Exception table:
       from    to  target type
          18    31    34   Class java/lang/Throwable

  public void onComplete();
    Code:
       0: aload_0
       1: getfield      #5                  // Field eager:Z
       4: ifeq          60
       7: aload_0
       8: iconst_0
       9: iconst_1
      10: invokevirtual #10                 // Method compareAndSet:(ZZ)Z
      13: ifeq          48
      16: aload_0
      17: getfield      #4                  // Field disposer:Lio/reactivex/rxjava3/functions/Consumer;
      20: aload_0
      21: getfield      #3                  // Field resource:Ljava/lang/Object;
      24: invokeinterface #11,  2           // InterfaceMethod io/reactivex/rxjava3/functions/Consumer.accept:(Ljava/lang/Object;)V
      29: goto          48
      32: astore_1
      33: aload_1
      34: invokestatic  #13                 // Method io/reactivex/rxjava3/exceptions/Exceptions.throwIfFatal:(Ljava/lang/Throwable;)V
      37: aload_0
      38: getfield      #2                  // Field downstream:Lorg/reactivestreams/Subscriber;
      41: aload_1
      42: invokeinterface #17,  2           // InterfaceMethod org/reactivestreams/Subscriber.onError:(Ljava/lang/Throwable;)V
      47: return
      48: aload_0
      49: getfield      #2                  // Field downstream:Lorg/reactivestreams/Subscriber;
      52: invokeinterface #19,  1           // InterfaceMethod org/reactivestreams/Subscriber.onComplete:()V
      57: goto          73
      60: aload_0
      61: getfield      #2                  // Field downstream:Lorg/reactivestreams/Subscriber;
      64: invokeinterface #19,  1           // InterfaceMethod org/reactivestreams/Subscriber.onComplete:()V
      69: aload_0
      70: invokevirtual #18                 // Method disposeResource:()V
      73: return
    Exception table:
       from    to  target type
          16    29    32   Class java/lang/Throwable

  public void request(long);
    Code:
       0: aload_0
       1: getfield      #6                  // Field upstream:Lorg/reactivestreams/Subscription;
       4: lload_1
       5: invokeinterface #20,  3           // InterfaceMethod org/reactivestreams/Subscription.request:(J)V
      10: return

  public void cancel();
    Code:
       0: aload_0
       1: getfield      #5                  // Field eager:Z
       4: ifeq          30
       7: aload_0
       8: invokevirtual #18                 // Method disposeResource:()V
      11: aload_0
      12: getfield      #6                  // Field upstream:Lorg/reactivestreams/Subscription;
      15: invokeinterface #21,  1           // InterfaceMethod org/reactivestreams/Subscription.cancel:()V
      20: aload_0
      21: getstatic     #22                 // Field io/reactivex/rxjava3/internal/subscriptions/SubscriptionHelper.CANCELLED:Lio/reactivex/rxjava3/internal/subscriptions/SubscriptionHelper;
      24: putfield      #6                  // Field upstream:Lorg/reactivestreams/Subscription;
      27: goto          50
      30: aload_0
      31: getfield      #6                  // Field upstream:Lorg/reactivestreams/Subscription;
      34: invokeinterface #21,  1           // InterfaceMethod org/reactivestreams/Subscription.cancel:()V
      39: aload_0
      40: getstatic     #22                 // Field io/reactivex/rxjava3/internal/subscriptions/SubscriptionHelper.CANCELLED:Lio/reactivex/rxjava3/internal/subscriptions/SubscriptionHelper;
      43: putfield      #6                  // Field upstream:Lorg/reactivestreams/Subscription;
      46: aload_0
      47: invokevirtual #18                 // Method disposeResource:()V
      50: return

  void disposeResource();
    Code:
       0: aload_0
       1: iconst_0
       2: iconst_1
       3: invokevirtual #10                 // Method compareAndSet:(ZZ)Z
       6: ifeq          34
       9: aload_0
      10: getfield      #4                  // Field disposer:Lio/reactivex/rxjava3/functions/Consumer;
      13: aload_0
      14: getfield      #3                  // Field resource:Ljava/lang/Object;
      17: invokeinterface #11,  2           // InterfaceMethod io/reactivex/rxjava3/functions/Consumer.accept:(Ljava/lang/Object;)V
      22: goto          34
      25: astore_1
      26: aload_1
      27: invokestatic  #13                 // Method io/reactivex/rxjava3/exceptions/Exceptions.throwIfFatal:(Ljava/lang/Throwable;)V
      30: aload_1
      31: invokestatic  #23                 // Method io/reactivex/rxjava3/plugins/RxJavaPlugins.onError:(Ljava/lang/Throwable;)V
      34: return
    Exception table:
       from    to  target type
           9    22    25   Class java/lang/Throwable
}
