Compiled from "FlowableBufferTimed.java"
public final class io.reactivex.rxjava3.internal.operators.flowable.FlowableBufferTimed<T, U extends java.util.Collection<? super T>> extends io.reactivex.rxjava3.internal.operators.flowable.AbstractFlowableWithUpstream<T, U> {
  final long timespan;

  final long timeskip;

  final java.util.concurrent.TimeUnit unit;

  final io.reactivex.rxjava3.core.Scheduler scheduler;

  final io.reactivex.rxjava3.functions.Supplier<U> bufferSupplier;

  final int maxSize;

  final boolean restartTimerOnMaxSize;

  public io.reactivex.rxjava3.internal.operators.flowable.FlowableBufferTimed(io.reactivex.rxjava3.core.Flowable<T>, long, long, java.util.concurrent.TimeUnit, io.reactivex.rxjava3.core.Scheduler, io.reactivex.rxjava3.functions.Supplier<U>, int, boolean);
    Code:
       0: aload_0
       1: aload_1
       2: invokespecial #1                  // Method io/reactivex/rxjava3/internal/operators/flowable/AbstractFlowableWithUpstream."<init>":(Lio/reactivex/rxjava3/core/Flowable;)V
       5: aload_0
       6: lload_2
       7: putfield      #2                  // Field timespan:J
      10: aload_0
      11: lload         4
      13: putfield      #3                  // Field timeskip:J
      16: aload_0
      17: aload         6
      19: putfield      #4                  // Field unit:Ljava/util/concurrent/TimeUnit;
      22: aload_0
      23: aload         7
      25: putfield      #5                  // Field scheduler:Lio/reactivex/rxjava3/core/Scheduler;
      28: aload_0
      29: aload         8
      31: putfield      #6                  // Field bufferSupplier:Lio/reactivex/rxjava3/functions/Supplier;
      34: aload_0
      35: iload         9
      37: putfield      #7                  // Field maxSize:I
      40: aload_0
      41: iload         10
      43: putfield      #8                  // Field restartTimerOnMaxSize:Z
      46: return

  protected void subscribeActual(org.reactivestreams.Subscriber<? super U>);
    Code:
       0: aload_0
       1: getfield      #2                  // Field timespan:J
       4: aload_0
       5: getfield      #3                  // Field timeskip:J
       8: lcmp
       9: ifne          60
      12: aload_0
      13: getfield      #7                  // Field maxSize:I
      16: ldc           #10                 // int 2147483647
      18: if_icmpne     60
      21: aload_0
      22: getfield      #11                 // Field source:Lio/reactivex/rxjava3/core/Flowable;
      25: new           #12                 // class io/reactivex/rxjava3/internal/operators/flowable/FlowableBufferTimed$BufferExactUnboundedSubscriber
      28: dup
      29: new           #13                 // class io/reactivex/rxjava3/subscribers/SerializedSubscriber
      32: dup
      33: aload_1
      34: invokespecial #14                 // Method io/reactivex/rxjava3/subscribers/SerializedSubscriber."<init>":(Lorg/reactivestreams/Subscriber;)V
      37: aload_0
      38: getfield      #6                  // Field bufferSupplier:Lio/reactivex/rxjava3/functions/Supplier;
      41: aload_0
      42: getfield      #2                  // Field timespan:J
      45: aload_0
      46: getfield      #4                  // Field unit:Ljava/util/concurrent/TimeUnit;
      49: aload_0
      50: getfield      #5                  // Field scheduler:Lio/reactivex/rxjava3/core/Scheduler;
      53: invokespecial #15                 // Method io/reactivex/rxjava3/internal/operators/flowable/FlowableBufferTimed$BufferExactUnboundedSubscriber."<init>":(Lorg/reactivestreams/Subscriber;Lio/reactivex/rxjava3/functions/Supplier;JLjava/util/concurrent/TimeUnit;Lio/reactivex/rxjava3/core/Scheduler;)V
      56: invokevirtual #16                 // Method io/reactivex/rxjava3/core/Flowable.subscribe:(Lio/reactivex/rxjava3/core/FlowableSubscriber;)V
      59: return
      60: aload_0
      61: getfield      #5                  // Field scheduler:Lio/reactivex/rxjava3/core/Scheduler;
      64: invokevirtual #17                 // Method io/reactivex/rxjava3/core/Scheduler.createWorker:()Lio/reactivex/rxjava3/core/Scheduler$Worker;
      67: astore_2
      68: aload_0
      69: getfield      #2                  // Field timespan:J
      72: aload_0
      73: getfield      #3                  // Field timeskip:J
      76: lcmp
      77: ifne          124
      80: aload_0
      81: getfield      #11                 // Field source:Lio/reactivex/rxjava3/core/Flowable;
      84: new           #18                 // class io/reactivex/rxjava3/internal/operators/flowable/FlowableBufferTimed$BufferExactBoundedSubscriber
      87: dup
      88: new           #13                 // class io/reactivex/rxjava3/subscribers/SerializedSubscriber
      91: dup
      92: aload_1
      93: invokespecial #14                 // Method io/reactivex/rxjava3/subscribers/SerializedSubscriber."<init>":(Lorg/reactivestreams/Subscriber;)V
      96: aload_0
      97: getfield      #6                  // Field bufferSupplier:Lio/reactivex/rxjava3/functions/Supplier;
     100: aload_0
     101: getfield      #2                  // Field timespan:J
     104: aload_0
     105: getfield      #4                  // Field unit:Ljava/util/concurrent/TimeUnit;
     108: aload_0
     109: getfield      #7                  // Field maxSize:I
     112: aload_0
     113: getfield      #8                  // Field restartTimerOnMaxSize:Z
     116: aload_2
     117: invokespecial #19                 // Method io/reactivex/rxjava3/internal/operators/flowable/FlowableBufferTimed$BufferExactBoundedSubscriber."<init>":(Lorg/reactivestreams/Subscriber;Lio/reactivex/rxjava3/functions/Supplier;JLjava/util/concurrent/TimeUnit;IZLio/reactivex/rxjava3/core/Scheduler$Worker;)V
     120: invokevirtual #16                 // Method io/reactivex/rxjava3/core/Flowable.subscribe:(Lio/reactivex/rxjava3/core/FlowableSubscriber;)V
     123: return
     124: aload_0
     125: getfield      #11                 // Field source:Lio/reactivex/rxjava3/core/Flowable;
     128: new           #20                 // class io/reactivex/rxjava3/internal/operators/flowable/FlowableBufferTimed$BufferSkipBoundedSubscriber
     131: dup
     132: new           #13                 // class io/reactivex/rxjava3/subscribers/SerializedSubscriber
     135: dup
     136: aload_1
     137: invokespecial #14                 // Method io/reactivex/rxjava3/subscribers/SerializedSubscriber."<init>":(Lorg/reactivestreams/Subscriber;)V
     140: aload_0
     141: getfield      #6                  // Field bufferSupplier:Lio/reactivex/rxjava3/functions/Supplier;
     144: aload_0
     145: getfield      #2                  // Field timespan:J
     148: aload_0
     149: getfield      #3                  // Field timeskip:J
     152: aload_0
     153: getfield      #4                  // Field unit:Ljava/util/concurrent/TimeUnit;
     156: aload_2
     157: invokespecial #21                 // Method io/reactivex/rxjava3/internal/operators/flowable/FlowableBufferTimed$BufferSkipBoundedSubscriber."<init>":(Lorg/reactivestreams/Subscriber;Lio/reactivex/rxjava3/functions/Supplier;JJLjava/util/concurrent/TimeUnit;Lio/reactivex/rxjava3/core/Scheduler$Worker;)V
     160: invokevirtual #16                 // Method io/reactivex/rxjava3/core/Flowable.subscribe:(Lio/reactivex/rxjava3/core/FlowableSubscriber;)V
     163: return
}
