Compiled from "FlowableTimeInterval.java"
final class io.reactivex.rxjava3.internal.operators.flowable.FlowableTimeInterval$TimeIntervalSubscriber<T> implements io.reactivex.rxjava3.core.FlowableSubscriber<T>, org.reactivestreams.Subscription {
  final org.reactivestreams.Subscriber<? super io.reactivex.rxjava3.schedulers.Timed<T>> downstream;

  final java.util.concurrent.TimeUnit unit;

  final io.reactivex.rxjava3.core.Scheduler scheduler;

  org.reactivestreams.Subscription upstream;

  long lastTime;

  io.reactivex.rxjava3.internal.operators.flowable.FlowableTimeInterval$TimeIntervalSubscriber(org.reactivestreams.Subscriber<? super io.reactivex.rxjava3.schedulers.Timed<T>>, java.util.concurrent.TimeUnit, io.reactivex.rxjava3.core.Scheduler);
    Code:
       0: aload_0
       1: invokespecial #1                  // Method java/lang/Object."<init>":()V
       4: aload_0
       5: aload_1
       6: putfield      #2                  // Field downstream:Lorg/reactivestreams/Subscriber;
       9: aload_0
      10: aload_3
      11: putfield      #3                  // Field scheduler:Lio/reactivex/rxjava3/core/Scheduler;
      14: aload_0
      15: aload_2
      16: putfield      #4                  // Field unit:Ljava/util/concurrent/TimeUnit;
      19: return

  public void onSubscribe(org.reactivestreams.Subscription);
    Code:
       0: aload_0
       1: getfield      #5                  // Field upstream:Lorg/reactivestreams/Subscription;
       4: aload_1
       5: invokestatic  #6                  // Method io/reactivex/rxjava3/internal/subscriptions/SubscriptionHelper.validate:(Lorg/reactivestreams/Subscription;Lorg/reactivestreams/Subscription;)Z
       8: ifeq          41
      11: aload_0
      12: aload_0
      13: getfield      #3                  // Field scheduler:Lio/reactivex/rxjava3/core/Scheduler;
      16: aload_0
      17: getfield      #4                  // Field unit:Ljava/util/concurrent/TimeUnit;
      20: invokevirtual #7                  // Method io/reactivex/rxjava3/core/Scheduler.now:(Ljava/util/concurrent/TimeUnit;)J
      23: putfield      #8                  // Field lastTime:J
      26: aload_0
      27: aload_1
      28: putfield      #5                  // Field upstream:Lorg/reactivestreams/Subscription;
      31: aload_0
      32: getfield      #2                  // Field downstream:Lorg/reactivestreams/Subscriber;
      35: aload_0
      36: invokeinterface #9,  2            // InterfaceMethod org/reactivestreams/Subscriber.onSubscribe:(Lorg/reactivestreams/Subscription;)V
      41: return

  public void onNext(T);
    Code:
       0: aload_0
       1: getfield      #3                  // Field scheduler:Lio/reactivex/rxjava3/core/Scheduler;
       4: aload_0
       5: getfield      #4                  // Field unit:Ljava/util/concurrent/TimeUnit;
       8: invokevirtual #7                  // Method io/reactivex/rxjava3/core/Scheduler.now:(Ljava/util/concurrent/TimeUnit;)J
      11: lstore_2
      12: aload_0
      13: getfield      #8                  // Field lastTime:J
      16: lstore        4
      18: aload_0
      19: lload_2
      20: putfield      #8                  // Field lastTime:J
      23: lload_2
      24: lload         4
      26: lsub
      27: lstore        6
      29: aload_0
      30: getfield      #2                  // Field downstream:Lorg/reactivestreams/Subscriber;
      33: new           #10                 // class io/reactivex/rxjava3/schedulers/Timed
      36: dup
      37: aload_1
      38: lload         6
      40: aload_0
      41: getfield      #4                  // Field unit:Ljava/util/concurrent/TimeUnit;
      44: invokespecial #11                 // Method io/reactivex/rxjava3/schedulers/Timed."<init>":(Ljava/lang/Object;JLjava/util/concurrent/TimeUnit;)V
      47: invokeinterface #12,  2           // InterfaceMethod org/reactivestreams/Subscriber.onNext:(Ljava/lang/Object;)V
      52: return

  public void onError(java.lang.Throwable);
    Code:
       0: aload_0
       1: getfield      #2                  // Field downstream:Lorg/reactivestreams/Subscriber;
       4: aload_1
       5: invokeinterface #13,  2           // InterfaceMethod org/reactivestreams/Subscriber.onError:(Ljava/lang/Throwable;)V
      10: return

  public void onComplete();
    Code:
       0: aload_0
       1: getfield      #2                  // Field downstream:Lorg/reactivestreams/Subscriber;
       4: invokeinterface #14,  1           // InterfaceMethod org/reactivestreams/Subscriber.onComplete:()V
       9: return

  public void request(long);
    Code:
       0: aload_0
       1: getfield      #5                  // Field upstream:Lorg/reactivestreams/Subscription;
       4: lload_1
       5: invokeinterface #15,  3           // InterfaceMethod org/reactivestreams/Subscription.request:(J)V
      10: return

  public void cancel();
    Code:
       0: aload_0
       1: getfield      #5                  // Field upstream:Lorg/reactivestreams/Subscription;
       4: invokeinterface #16,  1           // InterfaceMethod org/reactivestreams/Subscription.cancel:()V
       9: return
}
