Compiled from "FlowableSingleSingle.java"
final class io.reactivex.rxjava3.internal.operators.flowable.FlowableSingleSingle$SingleElementSubscriber<T> implements io.reactivex.rxjava3.core.FlowableSubscriber<T>, io.reactivex.rxjava3.disposables.Disposable {
  final io.reactivex.rxjava3.core.SingleObserver<? super T> downstream;

  final T defaultValue;

  org.reactivestreams.Subscription upstream;

  boolean done;

  T value;

  io.reactivex.rxjava3.internal.operators.flowable.FlowableSingleSingle$SingleElementSubscriber(io.reactivex.rxjava3.core.SingleObserver<? super T>, T);
    Code:
       0: aload_0
       1: invokespecial #1                  // Method java/lang/Object."<init>":()V
       4: aload_0
       5: aload_1
       6: putfield      #2                  // Field downstream:Lio/reactivex/rxjava3/core/SingleObserver;
       9: aload_0
      10: aload_2
      11: putfield      #3                  // Field defaultValue:Ljava/lang/Object;
      14: return

  public void onSubscribe(org.reactivestreams.Subscription);
    Code:
       0: aload_0
       1: getfield      #4                  // Field upstream:Lorg/reactivestreams/Subscription;
       4: aload_1
       5: invokestatic  #5                  // Method io/reactivex/rxjava3/internal/subscriptions/SubscriptionHelper.validate:(Lorg/reactivestreams/Subscription;Lorg/reactivestreams/Subscription;)Z
       8: ifeq          35
      11: aload_0
      12: aload_1
      13: putfield      #4                  // Field upstream:Lorg/reactivestreams/Subscription;
      16: aload_0
      17: getfield      #2                  // Field downstream:Lio/reactivex/rxjava3/core/SingleObserver;
      20: aload_0
      21: invokeinterface #6,  2            // InterfaceMethod io/reactivex/rxjava3/core/SingleObserver.onSubscribe:(Lio/reactivex/rxjava3/disposables/Disposable;)V
      26: aload_1
      27: ldc2_w        #8                  // long 9223372036854775807l
      30: invokeinterface #10,  3           // InterfaceMethod org/reactivestreams/Subscription.request:(J)V
      35: return

  public void onNext(T);
    Code:
       0: aload_0
       1: getfield      #11                 // Field done:Z
       4: ifeq          8
       7: return
       8: aload_0
       9: getfield      #12                 // Field value:Ljava/lang/Object;
      12: ifnull        55
      15: aload_0
      16: iconst_1
      17: putfield      #11                 // Field done:Z
      20: aload_0
      21: getfield      #4                  // Field upstream:Lorg/reactivestreams/Subscription;
      24: invokeinterface #13,  1           // InterfaceMethod org/reactivestreams/Subscription.cancel:()V
      29: aload_0
      30: getstatic     #14                 // Field io/reactivex/rxjava3/internal/subscriptions/SubscriptionHelper.CANCELLED:Lio/reactivex/rxjava3/internal/subscriptions/SubscriptionHelper;
      33: putfield      #4                  // Field upstream:Lorg/reactivestreams/Subscription;
      36: aload_0
      37: getfield      #2                  // Field downstream:Lio/reactivex/rxjava3/core/SingleObserver;
      40: new           #15                 // class java/lang/IllegalArgumentException
      43: dup
      44: ldc           #16                 // String Sequence contains more than one element!
      46: invokespecial #17                 // Method java/lang/IllegalArgumentException."<init>":(Ljava/lang/String;)V
      49: invokeinterface #18,  2           // InterfaceMethod io/reactivex/rxjava3/core/SingleObserver.onError:(Ljava/lang/Throwable;)V
      54: return
      55: aload_0
      56: aload_1
      57: putfield      #12                 // Field value:Ljava/lang/Object;
      60: return

  public void onError(java.lang.Throwable);
    Code:
       0: aload_0
       1: getfield      #11                 // Field done:Z
       4: ifeq          12
       7: aload_1
       8: invokestatic  #19                 // Method io/reactivex/rxjava3/plugins/RxJavaPlugins.onError:(Ljava/lang/Throwable;)V
      11: return
      12: aload_0
      13: iconst_1
      14: putfield      #11                 // Field done:Z
      17: aload_0
      18: getstatic     #14                 // Field io/reactivex/rxjava3/internal/subscriptions/SubscriptionHelper.CANCELLED:Lio/reactivex/rxjava3/internal/subscriptions/SubscriptionHelper;
      21: putfield      #4                  // Field upstream:Lorg/reactivestreams/Subscription;
      24: aload_0
      25: getfield      #2                  // Field downstream:Lio/reactivex/rxjava3/core/SingleObserver;
      28: aload_1
      29: invokeinterface #18,  2           // InterfaceMethod io/reactivex/rxjava3/core/SingleObserver.onError:(Ljava/lang/Throwable;)V
      34: return

  public void onComplete();
    Code:
       0: aload_0
       1: getfield      #11                 // Field done:Z
       4: ifeq          8
       7: return
       8: aload_0
       9: iconst_1
      10: putfield      #11                 // Field done:Z
      13: aload_0
      14: getstatic     #14                 // Field io/reactivex/rxjava3/internal/subscriptions/SubscriptionHelper.CANCELLED:Lio/reactivex/rxjava3/internal/subscriptions/SubscriptionHelper;
      17: putfield      #4                  // Field upstream:Lorg/reactivestreams/Subscription;
      20: aload_0
      21: getfield      #12                 // Field value:Ljava/lang/Object;
      24: astore_1
      25: aload_0
      26: aconst_null
      27: putfield      #12                 // Field value:Ljava/lang/Object;
      30: aload_1
      31: ifnonnull     39
      34: aload_0
      35: getfield      #3                  // Field defaultValue:Ljava/lang/Object;
      38: astore_1
      39: aload_1
      40: ifnull        56
      43: aload_0
      44: getfield      #2                  // Field downstream:Lio/reactivex/rxjava3/core/SingleObserver;
      47: aload_1
      48: invokeinterface #20,  2           // InterfaceMethod io/reactivex/rxjava3/core/SingleObserver.onSuccess:(Ljava/lang/Object;)V
      53: goto          72
      56: aload_0
      57: getfield      #2                  // Field downstream:Lio/reactivex/rxjava3/core/SingleObserver;
      60: new           #21                 // class java/util/NoSuchElementException
      63: dup
      64: invokespecial #22                 // Method java/util/NoSuchElementException."<init>":()V
      67: invokeinterface #18,  2           // InterfaceMethod io/reactivex/rxjava3/core/SingleObserver.onError:(Ljava/lang/Throwable;)V
      72: return

  public void dispose();
    Code:
       0: aload_0
       1: getfield      #4                  // Field upstream:Lorg/reactivestreams/Subscription;
       4: invokeinterface #13,  1           // InterfaceMethod org/reactivestreams/Subscription.cancel:()V
       9: aload_0
      10: getstatic     #14                 // Field io/reactivex/rxjava3/internal/subscriptions/SubscriptionHelper.CANCELLED:Lio/reactivex/rxjava3/internal/subscriptions/SubscriptionHelper;
      13: putfield      #4                  // Field upstream:Lorg/reactivestreams/Subscription;
      16: return

  public boolean isDisposed();
    Code:
       0: aload_0
       1: getfield      #4                  // Field upstream:Lorg/reactivestreams/Subscription;
       4: getstatic     #14                 // Field io/reactivex/rxjava3/internal/subscriptions/SubscriptionHelper.CANCELLED:Lio/reactivex/rxjava3/internal/subscriptions/SubscriptionHelper;
       7: if_acmpne     14
      10: iconst_1
      11: goto          15
      14: iconst_0
      15: ireturn
}
