Compiled from "FlowableFromFuture.java"
public final class io.reactivex.rxjava3.internal.operators.flowable.FlowableFromFuture<T> extends io.reactivex.rxjava3.core.Flowable<T> {
  final java.util.concurrent.Future<? extends T> future;

  final long timeout;

  final java.util.concurrent.TimeUnit unit;

  public io.reactivex.rxjava3.internal.operators.flowable.FlowableFromFuture(java.util.concurrent.Future<? extends T>, long, java.util.concurrent.TimeUnit);
    Code:
       0: aload_0
       1: invokespecial #1                  // Method io/reactivex/rxjava3/core/Flowable."<init>":()V
       4: aload_0
       5: aload_1
       6: putfield      #2                  // Field future:Ljava/util/concurrent/Future;
       9: aload_0
      10: lload_2
      11: putfield      #3                  // Field timeout:J
      14: aload_0
      15: aload         4
      17: putfield      #4                  // Field unit:Ljava/util/concurrent/TimeUnit;
      20: return

  public void subscribeActual(org.reactivestreams.Subscriber<? super T>);
    Code:
       0: new           #5                  // class io/reactivex/rxjava3/internal/subscriptions/DeferredScalarSubscription
       3: dup
       4: aload_1
       5: invokespecial #6                  // Method io/reactivex/rxjava3/internal/subscriptions/DeferredScalarSubscription."<init>":(Lorg/reactivestreams/Subscriber;)V
       8: astore_2
       9: aload_1
      10: aload_2
      11: invokeinterface #7,  2            // InterfaceMethod org/reactivestreams/Subscriber.onSubscribe:(Lorg/reactivestreams/Subscription;)V
      16: aload_0
      17: getfield      #4                  // Field unit:Ljava/util/concurrent/TimeUnit;
      20: ifnull        43
      23: aload_0
      24: getfield      #2                  // Field future:Ljava/util/concurrent/Future;
      27: aload_0
      28: getfield      #3                  // Field timeout:J
      31: aload_0
      32: getfield      #4                  // Field unit:Ljava/util/concurrent/TimeUnit;
      35: invokeinterface #8,  4            // InterfaceMethod java/util/concurrent/Future.get:(JLjava/util/concurrent/TimeUnit;)Ljava/lang/Object;
      40: goto          52
      43: aload_0
      44: getfield      #2                  // Field future:Ljava/util/concurrent/Future;
      47: invokeinterface #9,  1            // InterfaceMethod java/util/concurrent/Future.get:()Ljava/lang/Object;
      52: astore_3
      53: goto          79
      56: astore        4
      58: aload         4
      60: invokestatic  #11                 // Method io/reactivex/rxjava3/exceptions/Exceptions.throwIfFatal:(Ljava/lang/Throwable;)V
      63: aload_2
      64: invokevirtual #12                 // Method io/reactivex/rxjava3/internal/subscriptions/DeferredScalarSubscription.isCancelled:()Z
      67: ifne          78
      70: aload_1
      71: aload         4
      73: invokeinterface #13,  2           // InterfaceMethod org/reactivestreams/Subscriber.onError:(Ljava/lang/Throwable;)V
      78: return
      79: aload_3
      80: ifnonnull     97
      83: aload_1
      84: ldc           #14                 // String The future returned a null value.
      86: invokestatic  #15                 // Method io/reactivex/rxjava3/internal/util/ExceptionHelper.createNullPointerException:(Ljava/lang/String;)Ljava/lang/NullPointerException;
      89: invokeinterface #13,  2           // InterfaceMethod org/reactivestreams/Subscriber.onError:(Ljava/lang/Throwable;)V
      94: goto          102
      97: aload_2
      98: aload_3
      99: invokevirtual #16                 // Method io/reactivex/rxjava3/internal/subscriptions/DeferredScalarSubscription.complete:(Ljava/lang/Object;)V
     102: return
    Exception table:
       from    to  target type
          16    53    56   Class java/lang/Throwable
}
