Compiled from "FlowableReplay.java"
final class io.reactivex.rxjava3.internal.operators.flowable.FlowableReplay$ReplayPublisher<T> implements org.reactivestreams.Publisher<T> {
  private final java.util.concurrent.atomic.AtomicReference<io.reactivex.rxjava3.internal.operators.flowable.FlowableReplay$ReplaySubscriber<T>> curr;

  private final io.reactivex.rxjava3.functions.Supplier<? extends io.reactivex.rxjava3.internal.operators.flowable.FlowableReplay$ReplayBuffer<T>> bufferFactory;

  io.reactivex.rxjava3.internal.operators.flowable.FlowableReplay$ReplayPublisher(java.util.concurrent.atomic.AtomicReference<io.reactivex.rxjava3.internal.operators.flowable.FlowableReplay$ReplaySubscriber<T>>, io.reactivex.rxjava3.functions.Supplier<? extends io.reactivex.rxjava3.internal.operators.flowable.FlowableReplay$ReplayBuffer<T>>);
    Code:
       0: aload_0
       1: invokespecial #1                  // Method java/lang/Object."<init>":()V
       4: aload_0
       5: aload_1
       6: putfield      #2                  // Field curr:Ljava/util/concurrent/atomic/AtomicReference;
       9: aload_0
      10: aload_2
      11: putfield      #3                  // Field bufferFactory:Lio/reactivex/rxjava3/functions/Supplier;
      14: return

  public void subscribe(org.reactivestreams.Subscriber<? super T>);
    Code:
       0: aload_0
       1: getfield      #2                  // Field curr:Ljava/util/concurrent/atomic/AtomicReference;
       4: invokevirtual #4                  // Method java/util/concurrent/atomic/AtomicReference.get:()Ljava/lang/Object;
       7: checkcast     #5                  // class io/reactivex/rxjava3/internal/operators/flowable/FlowableReplay$ReplaySubscriber
      10: astore_2
      11: aload_2
      12: ifnonnull     78
      15: aload_0
      16: getfield      #3                  // Field bufferFactory:Lio/reactivex/rxjava3/functions/Supplier;
      19: invokeinterface #6,  1            // InterfaceMethod io/reactivex/rxjava3/functions/Supplier.get:()Ljava/lang/Object;
      24: checkcast     #7                  // class io/reactivex/rxjava3/internal/operators/flowable/FlowableReplay$ReplayBuffer
      27: astore_3
      28: goto          45
      31: astore        4
      33: aload         4
      35: invokestatic  #9                  // Method io/reactivex/rxjava3/exceptions/Exceptions.throwIfFatal:(Ljava/lang/Throwable;)V
      38: aload         4
      40: aload_1
      41: invokestatic  #10                 // Method io/reactivex/rxjava3/internal/subscriptions/EmptySubscription.error:(Ljava/lang/Throwable;Lorg/reactivestreams/Subscriber;)V
      44: return
      45: new           #5                  // class io/reactivex/rxjava3/internal/operators/flowable/FlowableReplay$ReplaySubscriber
      48: dup
      49: aload_3
      50: aload_0
      51: getfield      #2                  // Field curr:Ljava/util/concurrent/atomic/AtomicReference;
      54: invokespecial #11                 // Method io/reactivex/rxjava3/internal/operators/flowable/FlowableReplay$ReplaySubscriber."<init>":(Lio/reactivex/rxjava3/internal/operators/flowable/FlowableReplay$ReplayBuffer;Ljava/util/concurrent/atomic/AtomicReference;)V
      57: astore        4
      59: aload_0
      60: getfield      #2                  // Field curr:Ljava/util/concurrent/atomic/AtomicReference;
      63: aconst_null
      64: aload         4
      66: invokevirtual #12                 // Method java/util/concurrent/atomic/AtomicReference.compareAndSet:(Ljava/lang/Object;Ljava/lang/Object;)Z
      69: ifne          75
      72: goto          0
      75: aload         4
      77: astore_2
      78: new           #13                 // class io/reactivex/rxjava3/internal/operators/flowable/FlowableReplay$InnerSubscription
      81: dup
      82: aload_2
      83: aload_1
      84: invokespecial #14                 // Method io/reactivex/rxjava3/internal/operators/flowable/FlowableReplay$InnerSubscription."<init>":(Lio/reactivex/rxjava3/internal/operators/flowable/FlowableReplay$ReplaySubscriber;Lorg/reactivestreams/Subscriber;)V
      87: astore_3
      88: aload_1
      89: aload_3
      90: invokeinterface #15,  2           // InterfaceMethod org/reactivestreams/Subscriber.onSubscribe:(Lorg/reactivestreams/Subscription;)V
      95: aload_2
      96: aload_3
      97: invokevirtual #16                 // Method io/reactivex/rxjava3/internal/operators/flowable/FlowableReplay$ReplaySubscriber.add:(Lio/reactivex/rxjava3/internal/operators/flowable/FlowableReplay$InnerSubscription;)Z
     100: pop
     101: aload_3
     102: invokevirtual #17                 // Method io/reactivex/rxjava3/internal/operators/flowable/FlowableReplay$InnerSubscription.isDisposed:()Z
     105: ifeq          114
     108: aload_2
     109: aload_3
     110: invokevirtual #18                 // Method io/reactivex/rxjava3/internal/operators/flowable/FlowableReplay$ReplaySubscriber.remove:(Lio/reactivex/rxjava3/internal/operators/flowable/FlowableReplay$InnerSubscription;)V
     113: return
     114: aload_2
     115: invokevirtual #19                 // Method io/reactivex/rxjava3/internal/operators/flowable/FlowableReplay$ReplaySubscriber.manageRequests:()V
     118: aload_2
     119: getfield      #20                 // Field io/reactivex/rxjava3/internal/operators/flowable/FlowableReplay$ReplaySubscriber.buffer:Lio/reactivex/rxjava3/internal/operators/flowable/FlowableReplay$ReplayBuffer;
     122: aload_3
     123: invokeinterface #21,  2           // InterfaceMethod io/reactivex/rxjava3/internal/operators/flowable/FlowableReplay$ReplayBuffer.replay:(Lio/reactivex/rxjava3/internal/operators/flowable/FlowableReplay$InnerSubscription;)V
     128: goto          131
     131: return
    Exception table:
       from    to  target type
          15    28    31   Class java/lang/Throwable
}
