Compiled from "FlowableFromObservable.java"
public final class io.reactivex.rxjava3.internal.operators.flowable.FlowableFromObservable<T> extends io.reactivex.rxjava3.core.Flowable<T> {
  private final io.reactivex.rxjava3.core.ObservableSource<T> upstream;

  public io.reactivex.rxjava3.internal.operators.flowable.FlowableFromObservable(io.reactivex.rxjava3.core.ObservableSource<T>);
    Code:
       0: aload_0
       1: invokespecial #1                  // Method io/reactivex/rxjava3/core/Flowable."<init>":()V
       4: aload_0
       5: aload_1
       6: putfield      #2                  // Field upstream:Lio/reactivex/rxjava3/core/ObservableSource;
       9: return

  protected void subscribeActual(org.reactivestreams.Subscriber<? super T>);
    Code:
       0: aload_0
       1: getfield      #2                  // Field upstream:Lio/reactivex/rxjava3/core/ObservableSource;
       4: new           #3                  // class io/reactivex/rxjava3/internal/operators/flowable/FlowableFromObservable$SubscriberObserver
       7: dup
       8: aload_1
       9: invokespecial #4                  // Method io/reactivex/rxjava3/internal/operators/flowable/FlowableFromObservable$SubscriberObserver."<init>":(Lorg/reactivestreams/Subscriber;)V
      12: invokeinterface #5,  2            // InterfaceMethod io/reactivex/rxjava3/core/ObservableSource.subscribe:(Lio/reactivex/rxjava3/core/Observer;)V
      17: return
}
