Compiled from "FlowableSamplePublisher.java"
public final class io.reactivex.rxjava3.internal.operators.flowable.FlowableSamplePublisher<T> extends io.reactivex.rxjava3.core.Flowable<T> {
  final org.reactivestreams.Publisher<T> source;

  final org.reactivestreams.Publisher<?> other;

  final boolean emitLast;

  public io.reactivex.rxjava3.internal.operators.flowable.FlowableSamplePublisher(org.reactivestreams.Publisher<T>, org.reactivestreams.Publisher<?>, boolean);
    Code:
       0: aload_0
       1: invokespecial #1                  // Method io/reactivex/rxjava3/core/Flowable."<init>":()V
       4: aload_0
       5: aload_1
       6: putfield      #2                  // Field source:Lorg/reactivestreams/Publisher;
       9: aload_0
      10: aload_2
      11: putfield      #3                  // Field other:Lorg/reactivestreams/Publisher;
      14: aload_0
      15: iload_3
      16: putfield      #4                  // Field emitLast:Z
      19: return

  protected void subscribeActual(org.reactivestreams.Subscriber<? super T>);
    Code:
       0: new           #5                  // class io/reactivex/rxjava3/subscribers/SerializedSubscriber
       3: dup
       4: aload_1
       5: invokespecial #6                  // Method io/reactivex/rxjava3/subscribers/SerializedSubscriber."<init>":(Lorg/reactivestreams/Subscriber;)V
       8: astore_2
       9: aload_0
      10: getfield      #4                  // Field emitLast:Z
      13: ifeq          40
      16: aload_0
      17: getfield      #2                  // Field source:Lorg/reactivestreams/Publisher;
      20: new           #7                  // class io/reactivex/rxjava3/internal/operators/flowable/FlowableSamplePublisher$SampleMainEmitLast
      23: dup
      24: aload_2
      25: aload_0
      26: getfield      #3                  // Field other:Lorg/reactivestreams/Publisher;
      29: invokespecial #8                  // Method io/reactivex/rxjava3/internal/operators/flowable/FlowableSamplePublisher$SampleMainEmitLast."<init>":(Lorg/reactivestreams/Subscriber;Lorg/reactivestreams/Publisher;)V
      32: invokeinterface #9,  2            // InterfaceMethod org/reactivestreams/Publisher.subscribe:(Lorg/reactivestreams/Subscriber;)V
      37: goto          61
      40: aload_0
      41: getfield      #2                  // Field source:Lorg/reactivestreams/Publisher;
      44: new           #10                 // class io/reactivex/rxjava3/internal/operators/flowable/FlowableSamplePublisher$SampleMainNoLast
      47: dup
      48: aload_2
      49: aload_0
      50: getfield      #3                  // Field other:Lorg/reactivestreams/Publisher;
      53: invokespecial #11                 // Method io/reactivex/rxjava3/internal/operators/flowable/FlowableSamplePublisher$SampleMainNoLast."<init>":(Lorg/reactivestreams/Subscriber;Lorg/reactivestreams/Publisher;)V
      56: invokeinterface #9,  2            // InterfaceMethod org/reactivestreams/Publisher.subscribe:(Lorg/reactivestreams/Subscriber;)V
      61: return
}
