Compiled from "FlowableCreate.java"
final class io.reactivex.rxjava3.internal.operators.flowable.FlowableCreate$ErrorAsyncEmitter<T> extends io.reactivex.rxjava3.internal.operators.flowable.FlowableCreate$NoOverflowBaseAsyncEmitter<T> {
  private static final long serialVersionUID;

  io.reactivex.rxjava3.internal.operators.flowable.FlowableCreate$ErrorAsyncEmitter(org.reactivestreams.Subscriber<? super T>);
    Code:
       0: aload_0
       1: aload_1
       2: invokespecial #1                  // Method io/reactivex/rxjava3/internal/operators/flowable/FlowableCreate$NoOverflowBaseAsyncEmitter."<init>":(Lorg/reactivestreams/Subscriber;)V
       5: return

  void onOverflow();
    Code:
       0: aload_0
       1: new           #2                  // class io/reactivex/rxjava3/exceptions/MissingBackpressureException
       4: dup
       5: ldc           #3                  // String create: Could not emit value due to lack of requests
       7: invokespecial #4                  // Method io/reactivex/rxjava3/exceptions/MissingBackpressureException."<init>":(Ljava/lang/String;)V
      10: invokevirtual #5                  // Method onError:(Ljava/lang/Throwable;)V
      13: return
}
