Compiled from "FlowableReplay.java"
final class io.reactivex.rxjava3.internal.operators.flowable.FlowableReplay$DefaultUnboundedFactory implements io.reactivex.rxjava3.functions.Supplier<java.lang.Object> {
  io.reactivex.rxjava3.internal.operators.flowable.FlowableReplay$DefaultUnboundedFactory();
    Code:
       0: aload_0
       1: invokespecial #1                  // Method java/lang/Object."<init>":()V
       4: return

  public java.lang.Object get();
    Code:
       0: new           #2                  // class io/reactivex/rxjava3/internal/operators/flowable/FlowableReplay$UnboundedReplayBuffer
       3: dup
       4: bipush        16
       6: invokespecial #3                  // Method io/reactivex/rxjava3/internal/operators/flowable/FlowableReplay$UnboundedReplayBuffer."<init>":(I)V
       9: areturn
}
