Compiled from "FlowableFlattenIterable.java"
public final class io.reactivex.rxjava3.internal.operators.flowable.FlowableFlattenIterable<T, R> extends io.reactivex.rxjava3.internal.operators.flowable.AbstractFlowableWithUpstream<T, R> {
  final io.reactivex.rxjava3.functions.Function<? super T, ? extends java.lang.Iterable<? extends R>> mapper;

  final int prefetch;

  public io.reactivex.rxjava3.internal.operators.flowable.FlowableFlattenIterable(io.reactivex.rxjava3.core.Flowable<T>, io.reactivex.rxjava3.functions.Function<? super T, ? extends java.lang.Iterable<? extends R>>, int);
    Code:
       0: aload_0
       1: aload_1
       2: invokespecial #1                  // Method io/reactivex/rxjava3/internal/operators/flowable/AbstractFlowableWithUpstream."<init>":(Lio/reactivex/rxjava3/core/Flowable;)V
       5: aload_0
       6: aload_2
       7: putfield      #2                  // Field mapper:Lio/reactivex/rxjava3/functions/Function;
      10: aload_0
      11: iload_3
      12: putfield      #3                  // Field prefetch:I
      15: return

  public void subscribeActual(org.reactivestreams.Subscriber<? super R>);
    Code:
       0: aload_0
       1: getfield      #4                  // Field source:Lio/reactivex/rxjava3/core/Flowable;
       4: instanceof    #5                  // class io/reactivex/rxjava3/functions/Supplier
       7: ifeq          92
      10: aload_0
      11: getfield      #4                  // Field source:Lio/reactivex/rxjava3/core/Flowable;
      14: checkcast     #5                  // class io/reactivex/rxjava3/functions/Supplier
      17: invokeinterface #6,  1            // InterfaceMethod io/reactivex/rxjava3/functions/Supplier.get:()Ljava/lang/Object;
      22: astore_2
      23: goto          37
      26: astore_3
      27: aload_3
      28: invokestatic  #8                  // Method io/reactivex/rxjava3/exceptions/Exceptions.throwIfFatal:(Ljava/lang/Throwable;)V
      31: aload_3
      32: aload_1
      33: invokestatic  #9                  // Method io/reactivex/rxjava3/internal/subscriptions/EmptySubscription.error:(Ljava/lang/Throwable;Lorg/reactivestreams/Subscriber;)V
      36: return
      37: aload_2
      38: ifnonnull     46
      41: aload_1
      42: invokestatic  #10                 // Method io/reactivex/rxjava3/internal/subscriptions/EmptySubscription.complete:(Lorg/reactivestreams/Subscriber;)V
      45: return
      46: aload_0
      47: getfield      #2                  // Field mapper:Lio/reactivex/rxjava3/functions/Function;
      50: aload_2
      51: invokeinterface #11,  2           // InterfaceMethod io/reactivex/rxjava3/functions/Function.apply:(Ljava/lang/Object;)Ljava/lang/Object;
      56: checkcast     #12                 // class java/lang/Iterable
      59: astore        4
      61: aload         4
      63: invokeinterface #13,  1           // InterfaceMethod java/lang/Iterable.iterator:()Ljava/util/Iterator;
      68: astore_3
      69: goto          86
      72: astore        4
      74: aload         4
      76: invokestatic  #8                  // Method io/reactivex/rxjava3/exceptions/Exceptions.throwIfFatal:(Ljava/lang/Throwable;)V
      79: aload         4
      81: aload_1
      82: invokestatic  #9                  // Method io/reactivex/rxjava3/internal/subscriptions/EmptySubscription.error:(Ljava/lang/Throwable;Lorg/reactivestreams/Subscriber;)V
      85: return
      86: aload_1
      87: aload_3
      88: invokestatic  #14                 // Method io/reactivex/rxjava3/internal/operators/flowable/FlowableFromIterable.subscribe:(Lorg/reactivestreams/Subscriber;Ljava/util/Iterator;)V
      91: return
      92: aload_0
      93: getfield      #4                  // Field source:Lio/reactivex/rxjava3/core/Flowable;
      96: new           #15                 // class io/reactivex/rxjava3/internal/operators/flowable/FlowableFlattenIterable$FlattenIterableSubscriber
      99: dup
     100: aload_1
     101: aload_0
     102: getfield      #2                  // Field mapper:Lio/reactivex/rxjava3/functions/Function;
     105: aload_0
     106: getfield      #3                  // Field prefetch:I
     109: invokespecial #16                 // Method io/reactivex/rxjava3/internal/operators/flowable/FlowableFlattenIterable$FlattenIterableSubscriber."<init>":(Lorg/reactivestreams/Subscriber;Lio/reactivex/rxjava3/functions/Function;I)V
     112: invokevirtual #17                 // Method io/reactivex/rxjava3/core/Flowable.subscribe:(Lio/reactivex/rxjava3/core/FlowableSubscriber;)V
     115: return
    Exception table:
       from    to  target type
          10    23    26   Class java/lang/Throwable
          46    69    72   Class java/lang/Throwable

  public static <T, R> org.reactivestreams.Subscriber<T> subscribe(org.reactivestreams.Subscriber<? super R>, io.reactivex.rxjava3.functions.Function<? super T, ? extends java.lang.Iterable<? extends R>>, int);
    Code:
       0: new           #15                 // class io/reactivex/rxjava3/internal/operators/flowable/FlowableFlattenIterable$FlattenIterableSubscriber
       3: dup
       4: aload_0
       5: aload_1
       6: iload_2
       7: invokespecial #16                 // Method io/reactivex/rxjava3/internal/operators/flowable/FlowableFlattenIterable$FlattenIterableSubscriber."<init>":(Lorg/reactivestreams/Subscriber;Lio/reactivex/rxjava3/functions/Function;I)V
      10: areturn
}
