Compiled from "FlowableDebounce.java"
final class io.reactivex.rxjava3.internal.operators.flowable.FlowableDebounce$DebounceSubscriber$DebounceInnerSubscriber<T, U> extends io.reactivex.rxjava3.subscribers.DisposableSubscriber<U> {
  final io.reactivex.rxjava3.internal.operators.flowable.FlowableDebounce$DebounceSubscriber<T, U> parent;

  final long index;

  final T value;

  boolean done;

  final java.util.concurrent.atomic.AtomicBoolean once;

  io.reactivex.rxjava3.internal.operators.flowable.FlowableDebounce$DebounceSubscriber$DebounceInnerSubscriber(io.reactivex.rxjava3.internal.operators.flowable.FlowableDebounce$DebounceSubscriber<T, U>, long, T);
    Code:
       0: aload_0
       1: invokespecial #1                  // Method io/reactivex/rxjava3/subscribers/DisposableSubscriber."<init>":()V
       4: aload_0
       5: new           #2                  // class java/util/concurrent/atomic/AtomicBoolean
       8: dup
       9: invokespecial #3                  // Method java/util/concurrent/atomic/AtomicBoolean."<init>":()V
      12: putfield      #4                  // Field once:Ljava/util/concurrent/atomic/AtomicBoolean;
      15: aload_0
      16: aload_1
      17: putfield      #5                  // Field parent:Lio/reactivex/rxjava3/internal/operators/flowable/FlowableDebounce$DebounceSubscriber;
      20: aload_0
      21: lload_2
      22: putfield      #6                  // Field index:J
      25: aload_0
      26: aload         4
      28: putfield      #7                  // Field value:Ljava/lang/Object;
      31: return

  public void onNext(U);
    Code:
       0: aload_0
       1: getfield      #8                  // Field done:Z
       4: ifeq          8
       7: return
       8: aload_0
       9: iconst_1
      10: putfield      #8                  // Field done:Z
      13: aload_0
      14: invokevirtual #9                  // Method cancel:()V
      17: aload_0
      18: invokevirtual #10                 // Method emit:()V
      21: return

  void emit();
    Code:
       0: aload_0
       1: getfield      #4                  // Field once:Ljava/util/concurrent/atomic/AtomicBoolean;
       4: iconst_0
       5: iconst_1
       6: invokevirtual #11                 // Method java/util/concurrent/atomic/AtomicBoolean.compareAndSet:(ZZ)Z
       9: ifeq          27
      12: aload_0
      13: getfield      #5                  // Field parent:Lio/reactivex/rxjava3/internal/operators/flowable/FlowableDebounce$DebounceSubscriber;
      16: aload_0
      17: getfield      #6                  // Field index:J
      20: aload_0
      21: getfield      #7                  // Field value:Ljava/lang/Object;
      24: invokevirtual #12                 // Method io/reactivex/rxjava3/internal/operators/flowable/FlowableDebounce$DebounceSubscriber.emit:(JLjava/lang/Object;)V
      27: return

  public void onError(java.lang.Throwable);
    Code:
       0: aload_0
       1: getfield      #8                  // Field done:Z
       4: ifeq          12
       7: aload_1
       8: invokestatic  #13                 // Method io/reactivex/rxjava3/plugins/RxJavaPlugins.onError:(Ljava/lang/Throwable;)V
      11: return
      12: aload_0
      13: iconst_1
      14: putfield      #8                  // Field done:Z
      17: aload_0
      18: getfield      #5                  // Field parent:Lio/reactivex/rxjava3/internal/operators/flowable/FlowableDebounce$DebounceSubscriber;
      21: aload_1
      22: invokevirtual #14                 // Method io/reactivex/rxjava3/internal/operators/flowable/FlowableDebounce$DebounceSubscriber.onError:(Ljava/lang/Throwable;)V
      25: return

  public void onComplete();
    Code:
       0: aload_0
       1: getfield      #8                  // Field done:Z
       4: ifeq          8
       7: return
       8: aload_0
       9: iconst_1
      10: putfield      #8                  // Field done:Z
      13: aload_0
      14: invokevirtual #10                 // Method emit:()V
      17: return
}
