Compiled from "FlowableTimeoutTimed.java"
public final class io.reactivex.rxjava3.internal.operators.flowable.FlowableTimeoutTimed<T> extends io.reactivex.rxjava3.internal.operators.flowable.AbstractFlowableWithUpstream<T, T> {
  final long timeout;

  final java.util.concurrent.TimeUnit unit;

  final io.reactivex.rxjava3.core.Scheduler scheduler;

  final org.reactivestreams.Publisher<? extends T> other;

  public io.reactivex.rxjava3.internal.operators.flowable.FlowableTimeoutTimed(io.reactivex.rxjava3.core.Flowable<T>, long, java.util.concurrent.TimeUnit, io.reactivex.rxjava3.core.Scheduler, org.reactivestreams.Publisher<? extends T>);
    Code:
       0: aload_0
       1: aload_1
       2: invokespecial #1                  // Method io/reactivex/rxjava3/internal/operators/flowable/AbstractFlowableWithUpstream."<init>":(Lio/reactivex/rxjava3/core/Flowable;)V
       5: aload_0
       6: lload_2
       7: putfield      #2                  // Field timeout:J
      10: aload_0
      11: aload         4
      13: putfield      #3                  // Field unit:Ljava/util/concurrent/TimeUnit;
      16: aload_0
      17: aload         5
      19: putfield      #4                  // Field scheduler:Lio/reactivex/rxjava3/core/Scheduler;
      22: aload_0
      23: aload         6
      25: putfield      #5                  // Field other:Lorg/reactivestreams/Publisher;
      28: return

  protected void subscribeActual(org.reactivestreams.Subscriber<? super T>);
    Code:
       0: aload_0
       1: getfield      #5                  // Field other:Lorg/reactivestreams/Publisher;
       4: ifnonnull     54
       7: new           #6                  // class io/reactivex/rxjava3/internal/operators/flowable/FlowableTimeoutTimed$TimeoutSubscriber
      10: dup
      11: aload_1
      12: aload_0
      13: getfield      #2                  // Field timeout:J
      16: aload_0
      17: getfield      #3                  // Field unit:Ljava/util/concurrent/TimeUnit;
      20: aload_0
      21: getfield      #4                  // Field scheduler:Lio/reactivex/rxjava3/core/Scheduler;
      24: invokevirtual #7                  // Method io/reactivex/rxjava3/core/Scheduler.createWorker:()Lio/reactivex/rxjava3/core/Scheduler$Worker;
      27: invokespecial #8                  // Method io/reactivex/rxjava3/internal/operators/flowable/FlowableTimeoutTimed$TimeoutSubscriber."<init>":(Lorg/reactivestreams/Subscriber;JLjava/util/concurrent/TimeUnit;Lio/reactivex/rxjava3/core/Scheduler$Worker;)V
      30: astore_2
      31: aload_1
      32: aload_2
      33: invokeinterface #9,  2            // InterfaceMethod org/reactivestreams/Subscriber.onSubscribe:(Lorg/reactivestreams/Subscription;)V
      38: aload_2
      39: lconst_0
      40: invokevirtual #10                 // Method io/reactivex/rxjava3/internal/operators/flowable/FlowableTimeoutTimed$TimeoutSubscriber.startTimeout:(J)V
      43: aload_0
      44: getfield      #11                 // Field source:Lio/reactivex/rxjava3/core/Flowable;
      47: aload_2
      48: invokevirtual #12                 // Method io/reactivex/rxjava3/core/Flowable.subscribe:(Lio/reactivex/rxjava3/core/FlowableSubscriber;)V
      51: goto          102
      54: new           #13                 // class io/reactivex/rxjava3/internal/operators/flowable/FlowableTimeoutTimed$TimeoutFallbackSubscriber
      57: dup
      58: aload_1
      59: aload_0
      60: getfield      #2                  // Field timeout:J
      63: aload_0
      64: getfield      #3                  // Field unit:Ljava/util/concurrent/TimeUnit;
      67: aload_0
      68: getfield      #4                  // Field scheduler:Lio/reactivex/rxjava3/core/Scheduler;
      71: invokevirtual #7                  // Method io/reactivex/rxjava3/core/Scheduler.createWorker:()Lio/reactivex/rxjava3/core/Scheduler$Worker;
      74: aload_0
      75: getfield      #5                  // Field other:Lorg/reactivestreams/Publisher;
      78: invokespecial #14                 // Method io/reactivex/rxjava3/internal/operators/flowable/FlowableTimeoutTimed$TimeoutFallbackSubscriber."<init>":(Lorg/reactivestreams/Subscriber;JLjava/util/concurrent/TimeUnit;Lio/reactivex/rxjava3/core/Scheduler$Worker;Lorg/reactivestreams/Publisher;)V
      81: astore_2
      82: aload_1
      83: aload_2
      84: invokeinterface #9,  2            // InterfaceMethod org/reactivestreams/Subscriber.onSubscribe:(Lorg/reactivestreams/Subscription;)V
      89: aload_2
      90: lconst_0
      91: invokevirtual #15                 // Method io/reactivex/rxjava3/internal/operators/flowable/FlowableTimeoutTimed$TimeoutFallbackSubscriber.startTimeout:(J)V
      94: aload_0
      95: getfield      #11                 // Field source:Lio/reactivex/rxjava3/core/Flowable;
      98: aload_2
      99: invokevirtual #12                 // Method io/reactivex/rxjava3/core/Flowable.subscribe:(Lio/reactivex/rxjava3/core/FlowableSubscriber;)V
     102: return
}
