Compiled from "FlowableTimeInterval.java"
public final class io.reactivex.rxjava3.internal.operators.flowable.FlowableTimeInterval<T> extends io.reactivex.rxjava3.internal.operators.flowable.AbstractFlowableWithUpstream<T, io.reactivex.rxjava3.schedulers.Timed<T>> {
  final io.reactivex.rxjava3.core.Scheduler scheduler;

  final java.util.concurrent.TimeUnit unit;

  public io.reactivex.rxjava3.internal.operators.flowable.FlowableTimeInterval(io.reactivex.rxjava3.core.Flowable<T>, java.util.concurrent.TimeUnit, io.reactivex.rxjava3.core.Scheduler);
    Code:
       0: aload_0
       1: aload_1
       2: invokespecial #1                  // Method io/reactivex/rxjava3/internal/operators/flowable/AbstractFlowableWithUpstream."<init>":(Lio/reactivex/rxjava3/core/Flowable;)V
       5: aload_0
       6: aload_3
       7: putfield      #2                  // Field scheduler:Lio/reactivex/rxjava3/core/Scheduler;
      10: aload_0
      11: aload_2
      12: putfield      #3                  // Field unit:Ljava/util/concurrent/TimeUnit;
      15: return

  protected void subscribeActual(org.reactivestreams.Subscriber<? super io.reactivex.rxjava3.schedulers.Timed<T>>);
    Code:
       0: aload_0
       1: getfield      #4                  // Field source:Lio/reactivex/rxjava3/core/Flowable;
       4: new           #5                  // class io/reactivex/rxjava3/internal/operators/flowable/FlowableTimeInterval$TimeIntervalSubscriber
       7: dup
       8: aload_1
       9: aload_0
      10: getfield      #3                  // Field unit:Ljava/util/concurrent/TimeUnit;
      13: aload_0
      14: getfield      #2                  // Field scheduler:Lio/reactivex/rxjava3/core/Scheduler;
      17: invokespecial #6                  // Method io/reactivex/rxjava3/internal/operators/flowable/FlowableTimeInterval$TimeIntervalSubscriber."<init>":(Lorg/reactivestreams/Subscriber;Ljava/util/concurrent/TimeUnit;Lio/reactivex/rxjava3/core/Scheduler;)V
      20: invokevirtual #7                  // Method io/reactivex/rxjava3/core/Flowable.subscribe:(Lio/reactivex/rxjava3/core/FlowableSubscriber;)V
      23: return
}
