Compiled from "FlowableSubscribeOn.java"
final class io.reactivex.rxjava3.internal.operators.flowable.FlowableSubscribeOn$SubscribeOnSubscriber$Request implements java.lang.Runnable {
  final org.reactivestreams.Subscription upstream;

  final long n;

  io.reactivex.rxjava3.internal.operators.flowable.FlowableSubscribeOn$SubscribeOnSubscriber$Request(org.reactivestreams.Subscription, long);
    Code:
       0: aload_0
       1: invokespecial #1                  // Method java/lang/Object."<init>":()V
       4: aload_0
       5: aload_1
       6: putfield      #2                  // Field upstream:Lorg/reactivestreams/Subscription;
       9: aload_0
      10: lload_2
      11: putfield      #3                  // Field n:J
      14: return

  public void run();
    Code:
       0: aload_0
       1: getfield      #2                  // Field upstream:Lorg/reactivestreams/Subscription;
       4: aload_0
       5: getfield      #3                  // Field n:J
       8: invokeinterface #4,  3            // InterfaceMethod org/reactivestreams/Subscription.request:(J)V
      13: return
}
