Compiled from "FlowableBufferBoundary.java"
public final class io.reactivex.rxjava3.internal.operators.flowable.FlowableBufferBoundary<T, U extends java.util.Collection<? super T>, Open, Close> extends io.reactivex.rxjava3.internal.operators.flowable.AbstractFlowableWithUpstream<T, U> {
  final io.reactivex.rxjava3.functions.Supplier<U> bufferSupplier;

  final org.reactivestreams.Publisher<? extends Open> bufferOpen;

  final io.reactivex.rxjava3.functions.Function<? super Open, ? extends org.reactivestreams.Publisher<? extends Close>> bufferClose;

  public io.reactivex.rxjava3.internal.operators.flowable.FlowableBufferBoundary(io.reactivex.rxjava3.core.Flowable<T>, org.reactivestreams.Publisher<? extends Open>, io.reactivex.rxjava3.functions.Function<? super Open, ? extends org.reactivestreams.Publisher<? extends Close>>, io.reactivex.rxjava3.functions.Supplier<U>);
    Code:
       0: aload_0
       1: aload_1
       2: invokespecial #1                  // Method io/reactivex/rxjava3/internal/operators/flowable/AbstractFlowableWithUpstream."<init>":(Lio/reactivex/rxjava3/core/Flowable;)V
       5: aload_0
       6: aload_2
       7: putfield      #2                  // Field bufferOpen:Lorg/reactivestreams/Publisher;
      10: aload_0
      11: aload_3
      12: putfield      #3                  // Field bufferClose:Lio/reactivex/rxjava3/functions/Function;
      15: aload_0
      16: aload         4
      18: putfield      #4                  // Field bufferSupplier:Lio/reactivex/rxjava3/functions/Supplier;
      21: return

  protected void subscribeActual(org.reactivestreams.Subscriber<? super U>);
    Code:
       0: new           #5                  // class io/reactivex/rxjava3/internal/operators/flowable/FlowableBufferBoundary$BufferBoundarySubscriber
       3: dup
       4: aload_1
       5: aload_0
       6: getfield      #2                  // Field bufferOpen:Lorg/reactivestreams/Publisher;
       9: aload_0
      10: getfield      #3                  // Field bufferClose:Lio/reactivex/rxjava3/functions/Function;
      13: aload_0
      14: getfield      #4                  // Field bufferSupplier:Lio/reactivex/rxjava3/functions/Supplier;
      17: invokespecial #6                  // Method io/reactivex/rxjava3/internal/operators/flowable/FlowableBufferBoundary$BufferBoundarySubscriber."<init>":(Lorg/reactivestreams/Subscriber;Lorg/reactivestreams/Publisher;Lio/reactivex/rxjava3/functions/Function;Lio/reactivex/rxjava3/functions/Supplier;)V
      20: astore_2
      21: aload_1
      22: aload_2
      23: invokeinterface #7,  2            // InterfaceMethod org/reactivestreams/Subscriber.onSubscribe:(Lorg/reactivestreams/Subscription;)V
      28: aload_0
      29: getfield      #8                  // Field source:Lio/reactivex/rxjava3/core/Flowable;
      32: aload_2
      33: invokevirtual #9                  // Method io/reactivex/rxjava3/core/Flowable.subscribe:(Lio/reactivex/rxjava3/core/FlowableSubscriber;)V
      36: return
}
