Compiled from "FlowableFlatMapCompletable.java"
public final class io.reactivex.rxjava3.internal.operators.flowable.FlowableFlatMapCompletable<T> extends io.reactivex.rxjava3.internal.operators.flowable.AbstractFlowableWithUpstream<T, T> {
  final io.reactivex.rxjava3.functions.Function<? super T, ? extends io.reactivex.rxjava3.core.CompletableSource> mapper;

  final int maxConcurrency;

  final boolean delayErrors;

  public io.reactivex.rxjava3.internal.operators.flowable.FlowableFlatMapCompletable(io.reactivex.rxjava3.core.Flowable<T>, io.reactivex.rxjava3.functions.Function<? super T, ? extends io.reactivex.rxjava3.core.CompletableSource>, boolean, int);
    Code:
       0: aload_0
       1: aload_1
       2: invokespecial #1                  // Method io/reactivex/rxjava3/internal/operators/flowable/AbstractFlowableWithUpstream."<init>":(Lio/reactivex/rxjava3/core/Flowable;)V
       5: aload_0
       6: aload_2
       7: putfield      #2                  // Field mapper:Lio/reactivex/rxjava3/functions/Function;
      10: aload_0
      11: iload_3
      12: putfield      #3                  // Field delayErrors:Z
      15: aload_0
      16: iload         4
      18: putfield      #4                  // Field maxConcurrency:I
      21: return

  protected void subscribeActual(org.reactivestreams.Subscriber<? super T>);
    Code:
       0: aload_0
       1: getfield      #5                  // Field source:Lio/reactivex/rxjava3/core/Flowable;
       4: new           #6                  // class io/reactivex/rxjava3/internal/operators/flowable/FlowableFlatMapCompletable$FlatMapCompletableMainSubscriber
       7: dup
       8: aload_1
       9: aload_0
      10: getfield      #2                  // Field mapper:Lio/reactivex/rxjava3/functions/Function;
      13: aload_0
      14: getfield      #3                  // Field delayErrors:Z
      17: aload_0
      18: getfield      #4                  // Field maxConcurrency:I
      21: invokespecial #7                  // Method io/reactivex/rxjava3/internal/operators/flowable/FlowableFlatMapCompletable$FlatMapCompletableMainSubscriber."<init>":(Lorg/reactivestreams/Subscriber;Lio/reactivex/rxjava3/functions/Function;ZI)V
      24: invokevirtual #8                  // Method io/reactivex/rxjava3/core/Flowable.subscribe:(Lio/reactivex/rxjava3/core/FlowableSubscriber;)V
      27: return
}
