Compiled from "FlowableCache.java"
final class io.reactivex.rxjava3.internal.operators.flowable.FlowableCache$Node<T> {
  final T[] values;

  volatile io.reactivex.rxjava3.internal.operators.flowable.FlowableCache$Node<T> next;

  io.reactivex.rxjava3.internal.operators.flowable.FlowableCache$Node(int);
    Code:
       0: aload_0
       1: invokespecial #1                  // Method java/lang/Object."<init>":()V
       4: aload_0
       5: iload_1
       6: anewarray     #2                  // class java/lang/Object
       9: checkcast     #3                  // class "[Ljava/lang/Object;"
      12: putfield      #4                  // Field values:[Ljava/lang/Object;
      15: return
}
