Compiled from "FlowableRepeatWhen.java"
final class io.reactivex.rxjava3.internal.operators.flowable.FlowableRepeatWhen$RepeatWhenSubscriber<T> extends io.reactivex.rxjava3.internal.operators.flowable.FlowableRepeatWhen$WhenSourceSubscriber<T, java.lang.Object> {
  private static final long serialVersionUID;

  io.reactivex.rxjava3.internal.operators.flowable.FlowableRepeatWhen$RepeatWhenSubscriber(org.reactivestreams.Subscriber<? super T>, io.reactivex.rxjava3.processors.FlowableProcessor<java.lang.Object>, org.reactivestreams.Subscription);
    Code:
       0: aload_0
       1: aload_1
       2: aload_2
       3: aload_3
       4: invokespecial #1                  // Method io/reactivex/rxjava3/internal/operators/flowable/FlowableRepeatWhen$WhenSourceSubscriber."<init>":(Lorg/reactivestreams/Subscriber;Lio/reactivex/rxjava3/processors/FlowableProcessor;Lorg/reactivestreams/Subscription;)V
       7: return

  public void onError(java.lang.Throwable);
    Code:
       0: aload_0
       1: getfield      #2                  // Field receiver:Lorg/reactivestreams/Subscription;
       4: invokeinterface #3,  1            // InterfaceMethod org/reactivestreams/Subscription.cancel:()V
       9: aload_0
      10: getfield      #4                  // Field downstream:Lorg/reactivestreams/Subscriber;
      13: aload_1
      14: invokeinterface #5,  2            // InterfaceMethod org/reactivestreams/Subscriber.onError:(Ljava/lang/Throwable;)V
      19: return

  public void onComplete();
    Code:
       0: aload_0
       1: iconst_0
       2: invokestatic  #6                  // Method java/lang/Integer.valueOf:(I)Ljava/lang/Integer;
       5: invokevirtual #7                  // Method again:(Ljava/lang/Object;)V
       8: return
}
