Compiled from "FlowableTimeout.java"
public final class io.reactivex.rxjava3.internal.operators.flowable.FlowableTimeout<T, U, V> extends io.reactivex.rxjava3.internal.operators.flowable.AbstractFlowableWithUpstream<T, T> {
  final org.reactivestreams.Publisher<U> firstTimeoutIndicator;

  final io.reactivex.rxjava3.functions.Function<? super T, ? extends org.reactivestreams.Publisher<V>> itemTimeoutIndicator;

  final org.reactivestreams.Publisher<? extends T> other;

  public io.reactivex.rxjava3.internal.operators.flowable.FlowableTimeout(io.reactivex.rxjava3.core.Flowable<T>, org.reactivestreams.Publisher<U>, io.reactivex.rxjava3.functions.Function<? super T, ? extends org.reactivestreams.Publisher<V>>, org.reactivestreams.Publisher<? extends T>);
    Code:
       0: aload_0
       1: aload_1
       2: invokespecial #1                  // Method io/reactivex/rxjava3/internal/operators/flowable/AbstractFlowableWithUpstream."<init>":(Lio/reactivex/rxjava3/core/Flowable;)V
       5: aload_0
       6: aload_2
       7: putfield      #2                  // Field firstTimeoutIndicator:Lorg/reactivestreams/Publisher;
      10: aload_0
      11: aload_3
      12: putfield      #3                  // Field itemTimeoutIndicator:Lio/reactivex/rxjava3/functions/Function;
      15: aload_0
      16: aload         4
      18: putfield      #4                  // Field other:Lorg/reactivestreams/Publisher;
      21: return

  protected void subscribeActual(org.reactivestreams.Subscriber<? super T>);
    Code:
       0: aload_0
       1: getfield      #4                  // Field other:Lorg/reactivestreams/Publisher;
       4: ifnonnull     46
       7: new           #5                  // class io/reactivex/rxjava3/internal/operators/flowable/FlowableTimeout$TimeoutSubscriber
      10: dup
      11: aload_1
      12: aload_0
      13: getfield      #3                  // Field itemTimeoutIndicator:Lio/reactivex/rxjava3/functions/Function;
      16: invokespecial #6                  // Method io/reactivex/rxjava3/internal/operators/flowable/FlowableTimeout$TimeoutSubscriber."<init>":(Lorg/reactivestreams/Subscriber;Lio/reactivex/rxjava3/functions/Function;)V
      19: astore_2
      20: aload_1
      21: aload_2
      22: invokeinterface #7,  2            // InterfaceMethod org/reactivestreams/Subscriber.onSubscribe:(Lorg/reactivestreams/Subscription;)V
      27: aload_2
      28: aload_0
      29: getfield      #2                  // Field firstTimeoutIndicator:Lorg/reactivestreams/Publisher;
      32: invokevirtual #8                  // Method io/reactivex/rxjava3/internal/operators/flowable/FlowableTimeout$TimeoutSubscriber.startFirstTimeout:(Lorg/reactivestreams/Publisher;)V
      35: aload_0
      36: getfield      #9                  // Field source:Lio/reactivex/rxjava3/core/Flowable;
      39: aload_2
      40: invokevirtual #10                 // Method io/reactivex/rxjava3/core/Flowable.subscribe:(Lio/reactivex/rxjava3/core/FlowableSubscriber;)V
      43: goto          86
      46: new           #11                 // class io/reactivex/rxjava3/internal/operators/flowable/FlowableTimeout$TimeoutFallbackSubscriber
      49: dup
      50: aload_1
      51: aload_0
      52: getfield      #3                  // Field itemTimeoutIndicator:Lio/reactivex/rxjava3/functions/Function;
      55: aload_0
      56: getfield      #4                  // Field other:Lorg/reactivestreams/Publisher;
      59: invokespecial #12                 // Method io/reactivex/rxjava3/internal/operators/flowable/FlowableTimeout$TimeoutFallbackSubscriber."<init>":(Lorg/reactivestreams/Subscriber;Lio/reactivex/rxjava3/functions/Function;Lorg/reactivestreams/Publisher;)V
      62: astore_2
      63: aload_1
      64: aload_2
      65: invokeinterface #7,  2            // InterfaceMethod org/reactivestreams/Subscriber.onSubscribe:(Lorg/reactivestreams/Subscription;)V
      70: aload_2
      71: aload_0
      72: getfield      #2                  // Field firstTimeoutIndicator:Lorg/reactivestreams/Publisher;
      75: invokevirtual #13                 // Method io/reactivex/rxjava3/internal/operators/flowable/FlowableTimeout$TimeoutFallbackSubscriber.startFirstTimeout:(Lorg/reactivestreams/Publisher;)V
      78: aload_0
      79: getfield      #9                  // Field source:Lio/reactivex/rxjava3/core/Flowable;
      82: aload_2
      83: invokevirtual #10                 // Method io/reactivex/rxjava3/core/Flowable.subscribe:(Lio/reactivex/rxjava3/core/FlowableSubscriber;)V
      86: return
}
