Compiled from "FlowableOnBackpressureReduceWith.java"
final class io.reactivex.rxjava3.internal.operators.flowable.FlowableOnBackpressureReduceWith$BackpressureReduceWithSubscriber<T, R> extends io.reactivex.rxjava3.internal.operators.flowable.AbstractBackpressureThrottlingSubscriber<T, R> {
  private static final long serialVersionUID;

  final io.reactivex.rxjava3.functions.BiFunction<R, ? super T, R> reducer;

  final io.reactivex.rxjava3.functions.Supplier<R> supplier;

  io.reactivex.rxjava3.internal.operators.flowable.FlowableOnBackpressureReduceWith$BackpressureReduceWithSubscriber(org.reactivestreams.Subscriber<? super R>, io.reactivex.rxjava3.functions.Supplier<R>, io.reactivex.rxjava3.functions.BiFunction<R, ? super T, R>);
    Code:
       0: aload_0
       1: aload_1
       2: invokespecial #1                  // Method io/reactivex/rxjava3/internal/operators/flowable/AbstractBackpressureThrottlingSubscriber."<init>":(Lorg/reactivestreams/Subscriber;)V
       5: aload_0
       6: aload_3
       7: putfield      #2                  // Field reducer:Lio/reactivex/rxjava3/functions/BiFunction;
      10: aload_0
      11: aload_2
      12: putfield      #3                  // Field supplier:Lio/reactivex/rxjava3/functions/Supplier;
      15: return

  public void onNext(T);
    Code:
       0: aload_0
       1: getfield      #4                  // Field current:Ljava/util/concurrent/atomic/AtomicReference;
       4: invokevirtual #5                  // Method java/util/concurrent/atomic/AtomicReference.get:()Ljava/lang/Object;
       7: astore_2
       8: aload_2
       9: ifnull        21
      12: aload_0
      13: getfield      #4                  // Field current:Ljava/util/concurrent/atomic/AtomicReference;
      16: aconst_null
      17: invokevirtual #6                  // Method java/util/concurrent/atomic/AtomicReference.getAndSet:(Ljava/lang/Object;)Ljava/lang/Object;
      20: astore_2
      21: aload_2
      22: ifnonnull     64
      25: aload_0
      26: getfield      #4                  // Field current:Ljava/util/concurrent/atomic/AtomicReference;
      29: aload_0
      30: getfield      #2                  // Field reducer:Lio/reactivex/rxjava3/functions/BiFunction;
      33: aload_0
      34: getfield      #3                  // Field supplier:Lio/reactivex/rxjava3/functions/Supplier;
      37: invokeinterface #7,  1            // InterfaceMethod io/reactivex/rxjava3/functions/Supplier.get:()Ljava/lang/Object;
      42: ldc           #8                  // String The supplier returned a null value
      44: invokestatic  #9                  // Method java/util/Objects.requireNonNull:(Ljava/lang/Object;Ljava/lang/String;)Ljava/lang/Object;
      47: aload_1
      48: invokeinterface #10,  3           // InterfaceMethod io/reactivex/rxjava3/functions/BiFunction.apply:(Ljava/lang/Object;Ljava/lang/Object;)Ljava/lang/Object;
      53: ldc           #11                 // String The reducer returned a null value
      55: invokestatic  #9                  // Method java/util/Objects.requireNonNull:(Ljava/lang/Object;Ljava/lang/String;)Ljava/lang/Object;
      58: invokevirtual #12                 // Method java/util/concurrent/atomic/AtomicReference.lazySet:(Ljava/lang/Object;)V
      61: goto          87
      64: aload_0
      65: getfield      #4                  // Field current:Ljava/util/concurrent/atomic/AtomicReference;
      68: aload_0
      69: getfield      #2                  // Field reducer:Lio/reactivex/rxjava3/functions/BiFunction;
      72: aload_2
      73: aload_1
      74: invokeinterface #10,  3           // InterfaceMethod io/reactivex/rxjava3/functions/BiFunction.apply:(Ljava/lang/Object;Ljava/lang/Object;)Ljava/lang/Object;
      79: ldc           #11                 // String The reducer returned a null value
      81: invokestatic  #9                  // Method java/util/Objects.requireNonNull:(Ljava/lang/Object;Ljava/lang/String;)Ljava/lang/Object;
      84: invokevirtual #12                 // Method java/util/concurrent/atomic/AtomicReference.lazySet:(Ljava/lang/Object;)V
      87: goto          110
      90: astore_3
      91: aload_3
      92: invokestatic  #14                 // Method io/reactivex/rxjava3/exceptions/Exceptions.throwIfFatal:(Ljava/lang/Throwable;)V
      95: aload_0
      96: getfield      #15                 // Field upstream:Lorg/reactivestreams/Subscription;
      99: invokeinterface #16,  1           // InterfaceMethod org/reactivestreams/Subscription.cancel:()V
     104: aload_0
     105: aload_3
     106: invokevirtual #17                 // Method onError:(Ljava/lang/Throwable;)V
     109: return
     110: aload_0
     111: invokevirtual #18                 // Method drain:()V
     114: return
    Exception table:
       from    to  target type
          21    87    90   Class java/lang/Throwable
}
