Compiled from "FlowableReduce.java"
final class io.reactivex.rxjava3.internal.operators.flowable.FlowableReduce$ReduceSubscriber<T> extends io.reactivex.rxjava3.internal.subscriptions.DeferredScalarSubscription<T> implements io.reactivex.rxjava3.core.FlowableSubscriber<T> {
  private static final long serialVersionUID;

  final io.reactivex.rxjava3.functions.BiFunction<T, T, T> reducer;

  org.reactivestreams.Subscription upstream;

  io.reactivex.rxjava3.internal.operators.flowable.FlowableReduce$ReduceSubscriber(org.reactivestreams.Subscriber<? super T>, io.reactivex.rxjava3.functions.BiFunction<T, T, T>);
    Code:
       0: aload_0
       1: aload_1
       2: invokespecial #1                  // Method io/reactivex/rxjava3/internal/subscriptions/DeferredScalarSubscription."<init>":(Lorg/reactivestreams/Subscriber;)V
       5: aload_0
       6: aload_2
       7: putfield      #2                  // Field reducer:Lio/reactivex/rxjava3/functions/BiFunction;
      10: return

  public void onSubscribe(org.reactivestreams.Subscription);
    Code:
       0: aload_0
       1: getfield      #3                  // Field upstream:Lorg/reactivestreams/Subscription;
       4: aload_1
       5: invokestatic  #4                  // Method io/reactivex/rxjava3/internal/subscriptions/SubscriptionHelper.validate:(Lorg/reactivestreams/Subscription;Lorg/reactivestreams/Subscription;)Z
       8: ifeq          35
      11: aload_0
      12: aload_1
      13: putfield      #3                  // Field upstream:Lorg/reactivestreams/Subscription;
      16: aload_0
      17: getfield      #5                  // Field downstream:Lorg/reactivestreams/Subscriber;
      20: aload_0
      21: invokeinterface #6,  2            // InterfaceMethod org/reactivestreams/Subscriber.onSubscribe:(Lorg/reactivestreams/Subscription;)V
      26: aload_1
      27: ldc2_w        #8                  // long 9223372036854775807l
      30: invokeinterface #10,  3           // InterfaceMethod org/reactivestreams/Subscription.request:(J)V
      35: return

  public void onNext(T);
    Code:
       0: aload_0
       1: getfield      #3                  // Field upstream:Lorg/reactivestreams/Subscription;
       4: getstatic     #11                 // Field io/reactivex/rxjava3/internal/subscriptions/SubscriptionHelper.CANCELLED:Lio/reactivex/rxjava3/internal/subscriptions/SubscriptionHelper;
       7: if_acmpne     11
      10: return
      11: aload_0
      12: getfield      #12                 // Field value:Ljava/lang/Object;
      15: astore_2
      16: aload_2
      17: ifnonnull     28
      20: aload_0
      21: aload_1
      22: putfield      #12                 // Field value:Ljava/lang/Object;
      25: goto          70
      28: aload_0
      29: aload_0
      30: getfield      #2                  // Field reducer:Lio/reactivex/rxjava3/functions/BiFunction;
      33: aload_2
      34: aload_1
      35: invokeinterface #13,  3           // InterfaceMethod io/reactivex/rxjava3/functions/BiFunction.apply:(Ljava/lang/Object;Ljava/lang/Object;)Ljava/lang/Object;
      40: ldc           #14                 // String The reducer returned a null value
      42: invokestatic  #15                 // Method java/util/Objects.requireNonNull:(Ljava/lang/Object;Ljava/lang/String;)Ljava/lang/Object;
      45: putfield      #12                 // Field value:Ljava/lang/Object;
      48: goto          70
      51: astore_3
      52: aload_3
      53: invokestatic  #17                 // Method io/reactivex/rxjava3/exceptions/Exceptions.throwIfFatal:(Ljava/lang/Throwable;)V
      56: aload_0
      57: getfield      #3                  // Field upstream:Lorg/reactivestreams/Subscription;
      60: invokeinterface #18,  1           // InterfaceMethod org/reactivestreams/Subscription.cancel:()V
      65: aload_0
      66: aload_3
      67: invokevirtual #19                 // Method onError:(Ljava/lang/Throwable;)V
      70: return
    Exception table:
       from    to  target type
          28    48    51   Class java/lang/Throwable

  public void onError(java.lang.Throwable);
    Code:
       0: aload_0
       1: getfield      #3                  // Field upstream:Lorg/reactivestreams/Subscription;
       4: getstatic     #11                 // Field io/reactivex/rxjava3/internal/subscriptions/SubscriptionHelper.CANCELLED:Lio/reactivex/rxjava3/internal/subscriptions/SubscriptionHelper;
       7: if_acmpne     15
      10: aload_1
      11: invokestatic  #20                 // Method io/reactivex/rxjava3/plugins/RxJavaPlugins.onError:(Ljava/lang/Throwable;)V
      14: return
      15: aload_0
      16: getstatic     #11                 // Field io/reactivex/rxjava3/internal/subscriptions/SubscriptionHelper.CANCELLED:Lio/reactivex/rxjava3/internal/subscriptions/SubscriptionHelper;
      19: putfield      #3                  // Field upstream:Lorg/reactivestreams/Subscription;
      22: aload_0
      23: getfield      #5                  // Field downstream:Lorg/reactivestreams/Subscriber;
      26: aload_1
      27: invokeinterface #21,  2           // InterfaceMethod org/reactivestreams/Subscriber.onError:(Ljava/lang/Throwable;)V
      32: return

  public void onComplete();
    Code:
       0: aload_0
       1: getfield      #3                  // Field upstream:Lorg/reactivestreams/Subscription;
       4: getstatic     #11                 // Field io/reactivex/rxjava3/internal/subscriptions/SubscriptionHelper.CANCELLED:Lio/reactivex/rxjava3/internal/subscriptions/SubscriptionHelper;
       7: if_acmpne     11
      10: return
      11: aload_0
      12: getstatic     #11                 // Field io/reactivex/rxjava3/internal/subscriptions/SubscriptionHelper.CANCELLED:Lio/reactivex/rxjava3/internal/subscriptions/SubscriptionHelper;
      15: putfield      #3                  // Field upstream:Lorg/reactivestreams/Subscription;
      18: aload_0
      19: getfield      #12                 // Field value:Ljava/lang/Object;
      22: astore_1
      23: aload_1
      24: ifnull        35
      27: aload_0
      28: aload_1
      29: invokevirtual #22                 // Method complete:(Ljava/lang/Object;)V
      32: goto          44
      35: aload_0
      36: getfield      #5                  // Field downstream:Lorg/reactivestreams/Subscriber;
      39: invokeinterface #23,  1           // InterfaceMethod org/reactivestreams/Subscriber.onComplete:()V
      44: return

  public void cancel();
    Code:
       0: aload_0
       1: invokespecial #24                 // Method io/reactivex/rxjava3/internal/subscriptions/DeferredScalarSubscription.cancel:()V
       4: aload_0
       5: getfield      #3                  // Field upstream:Lorg/reactivestreams/Subscription;
       8: invokeinterface #18,  1           // InterfaceMethod org/reactivestreams/Subscription.cancel:()V
      13: aload_0
      14: getstatic     #11                 // Field io/reactivex/rxjava3/internal/subscriptions/SubscriptionHelper.CANCELLED:Lio/reactivex/rxjava3/internal/subscriptions/SubscriptionHelper;
      17: putfield      #3                  // Field upstream:Lorg/reactivestreams/Subscription;
      20: return
}
