Compiled from "FlowableZipIterable.java"
final class io.reactivex.rxjava3.internal.operators.flowable.FlowableZipIterable$ZipIterableSubscriber<T, U, V> implements io.reactivex.rxjava3.core.FlowableSubscriber<T>, org.reactivestreams.Subscription {
  final org.reactivestreams.Subscriber<? super V> downstream;

  final java.util.Iterator<U> iterator;

  final io.reactivex.rxjava3.functions.BiFunction<? super T, ? super U, ? extends V> zipper;

  org.reactivestreams.Subscription upstream;

  boolean done;

  io.reactivex.rxjava3.internal.operators.flowable.FlowableZipIterable$ZipIterableSubscriber(org.reactivestreams.Subscriber<? super V>, java.util.Iterator<U>, io.reactivex.rxjava3.functions.BiFunction<? super T, ? super U, ? extends V>);
    Code:
       0: aload_0
       1: invokespecial #1                  // Method java/lang/Object."<init>":()V
       4: aload_0
       5: aload_1
       6: putfield      #2                  // Field downstream:Lorg/reactivestreams/Subscriber;
       9: aload_0
      10: aload_2
      11: putfield      #3                  // Field iterator:Ljava/util/Iterator;
      14: aload_0
      15: aload_3
      16: putfield      #4                  // Field zipper:Lio/reactivex/rxjava3/functions/BiFunction;
      19: return

  public void onSubscribe(org.reactivestreams.Subscription);
    Code:
       0: aload_0
       1: getfield      #5                  // Field upstream:Lorg/reactivestreams/Subscription;
       4: aload_1
       5: invokestatic  #6                  // Method io/reactivex/rxjava3/internal/subscriptions/SubscriptionHelper.validate:(Lorg/reactivestreams/Subscription;Lorg/reactivestreams/Subscription;)Z
       8: ifeq          26
      11: aload_0
      12: aload_1
      13: putfield      #5                  // Field upstream:Lorg/reactivestreams/Subscription;
      16: aload_0
      17: getfield      #2                  // Field downstream:Lorg/reactivestreams/Subscriber;
      20: aload_0
      21: invokeinterface #7,  2            // InterfaceMethod org/reactivestreams/Subscriber.onSubscribe:(Lorg/reactivestreams/Subscription;)V
      26: return

  public void onNext(T);
    Code:
       0: aload_0
       1: getfield      #8                  // Field done:Z
       4: ifeq          8
       7: return
       8: aload_0
       9: getfield      #3                  // Field iterator:Ljava/util/Iterator;
      12: invokeinterface #9,  1            // InterfaceMethod java/util/Iterator.next:()Ljava/lang/Object;
      17: ldc           #10                 // String The iterator returned a null value
      19: invokestatic  #11                 // Method java/util/Objects.requireNonNull:(Ljava/lang/Object;Ljava/lang/String;)Ljava/lang/Object;
      22: astore_2
      23: goto          33
      26: astore_3
      27: aload_0
      28: aload_3
      29: invokevirtual #13                 // Method fail:(Ljava/lang/Throwable;)V
      32: return
      33: aload_0
      34: getfield      #4                  // Field zipper:Lio/reactivex/rxjava3/functions/BiFunction;
      37: aload_1
      38: aload_2
      39: invokeinterface #14,  3           // InterfaceMethod io/reactivex/rxjava3/functions/BiFunction.apply:(Ljava/lang/Object;Ljava/lang/Object;)Ljava/lang/Object;
      44: ldc           #15                 // String The zipper function returned a null value
      46: invokestatic  #11                 // Method java/util/Objects.requireNonNull:(Ljava/lang/Object;Ljava/lang/String;)Ljava/lang/Object;
      49: astore_3
      50: goto          62
      53: astore        4
      55: aload_0
      56: aload         4
      58: invokevirtual #13                 // Method fail:(Ljava/lang/Throwable;)V
      61: return
      62: aload_0
      63: getfield      #2                  // Field downstream:Lorg/reactivestreams/Subscriber;
      66: aload_3
      67: invokeinterface #16,  2           // InterfaceMethod org/reactivestreams/Subscriber.onNext:(Ljava/lang/Object;)V
      72: aload_0
      73: getfield      #3                  // Field iterator:Ljava/util/Iterator;
      76: invokeinterface #17,  1           // InterfaceMethod java/util/Iterator.hasNext:()Z
      81: istore        4
      83: goto          95
      86: astore        5
      88: aload_0
      89: aload         5
      91: invokevirtual #13                 // Method fail:(Ljava/lang/Throwable;)V
      94: return
      95: iload         4
      97: ifne          123
     100: aload_0
     101: iconst_1
     102: putfield      #8                  // Field done:Z
     105: aload_0
     106: getfield      #5                  // Field upstream:Lorg/reactivestreams/Subscription;
     109: invokeinterface #18,  1           // InterfaceMethod org/reactivestreams/Subscription.cancel:()V
     114: aload_0
     115: getfield      #2                  // Field downstream:Lorg/reactivestreams/Subscriber;
     118: invokeinterface #19,  1           // InterfaceMethod org/reactivestreams/Subscriber.onComplete:()V
     123: return
    Exception table:
       from    to  target type
           8    23    26   Class java/lang/Throwable
          33    50    53   Class java/lang/Throwable
          72    83    86   Class java/lang/Throwable

  void fail(java.lang.Throwable);
    Code:
       0: aload_1
       1: invokestatic  #20                 // Method io/reactivex/rxjava3/exceptions/Exceptions.throwIfFatal:(Ljava/lang/Throwable;)V
       4: aload_0
       5: iconst_1
       6: putfield      #8                  // Field done:Z
       9: aload_0
      10: getfield      #5                  // Field upstream:Lorg/reactivestreams/Subscription;
      13: invokeinterface #18,  1           // InterfaceMethod org/reactivestreams/Subscription.cancel:()V
      18: aload_0
      19: getfield      #2                  // Field downstream:Lorg/reactivestreams/Subscriber;
      22: aload_1
      23: invokeinterface #21,  2           // InterfaceMethod org/reactivestreams/Subscriber.onError:(Ljava/lang/Throwable;)V
      28: return

  public void onError(java.lang.Throwable);
    Code:
       0: aload_0
       1: getfield      #8                  // Field done:Z
       4: ifeq          12
       7: aload_1
       8: invokestatic  #22                 // Method io/reactivex/rxjava3/plugins/RxJavaPlugins.onError:(Ljava/lang/Throwable;)V
      11: return
      12: aload_0
      13: iconst_1
      14: putfield      #8                  // Field done:Z
      17: aload_0
      18: getfield      #2                  // Field downstream:Lorg/reactivestreams/Subscriber;
      21: aload_1
      22: invokeinterface #21,  2           // InterfaceMethod org/reactivestreams/Subscriber.onError:(Ljava/lang/Throwable;)V
      27: return

  public void onComplete();
    Code:
       0: aload_0
       1: getfield      #8                  // Field done:Z
       4: ifeq          8
       7: return
       8: aload_0
       9: iconst_1
      10: putfield      #8                  // Field done:Z
      13: aload_0
      14: getfield      #2                  // Field downstream:Lorg/reactivestreams/Subscriber;
      17: invokeinterface #19,  1           // InterfaceMethod org/reactivestreams/Subscriber.onComplete:()V
      22: return

  public void request(long);
    Code:
       0: aload_0
       1: getfield      #5                  // Field upstream:Lorg/reactivestreams/Subscription;
       4: lload_1
       5: invokeinterface #23,  3           // InterfaceMethod org/reactivestreams/Subscription.request:(J)V
      10: return

  public void cancel();
    Code:
       0: aload_0
       1: getfield      #5                  // Field upstream:Lorg/reactivestreams/Subscription;
       4: invokeinterface #18,  1           // InterfaceMethod org/reactivestreams/Subscription.cancel:()V
       9: return
}
