Compiled from "FlowableWindow.java"
public final class io.reactivex.rxjava3.internal.operators.flowable.FlowableWindow<T> extends io.reactivex.rxjava3.internal.operators.flowable.AbstractFlowableWithUpstream<T, io.reactivex.rxjava3.core.Flowable<T>> {
  final long size;

  final long skip;

  final int bufferSize;

  public io.reactivex.rxjava3.internal.operators.flowable.FlowableWindow(io.reactivex.rxjava3.core.Flowable<T>, long, long, int);
    Code:
       0: aload_0
       1: aload_1
       2: invokespecial #1                  // Method io/reactivex/rxjava3/internal/operators/flowable/AbstractFlowableWithUpstream."<init>":(Lio/reactivex/rxjava3/core/Flowable;)V
       5: aload_0
       6: lload_2
       7: putfield      #2                  // Field size:J
      10: aload_0
      11: lload         4
      13: putfield      #3                  // Field skip:J
      16: aload_0
      17: iload         6
      19: putfield      #4                  // Field bufferSize:I
      22: return

  public void subscribeActual(org.reactivestreams.Subscriber<? super io.reactivex.rxjava3.core.Flowable<T>>);
    Code:
       0: aload_0
       1: getfield      #3                  // Field skip:J
       4: aload_0
       5: getfield      #2                  // Field size:J
       8: lcmp
       9: ifne          38
      12: aload_0
      13: getfield      #5                  // Field source:Lio/reactivex/rxjava3/core/Flowable;
      16: new           #6                  // class io/reactivex/rxjava3/internal/operators/flowable/FlowableWindow$WindowExactSubscriber
      19: dup
      20: aload_1
      21: aload_0
      22: getfield      #2                  // Field size:J
      25: aload_0
      26: getfield      #4                  // Field bufferSize:I
      29: invokespecial #7                  // Method io/reactivex/rxjava3/internal/operators/flowable/FlowableWindow$WindowExactSubscriber."<init>":(Lorg/reactivestreams/Subscriber;JI)V
      32: invokevirtual #8                  // Method io/reactivex/rxjava3/core/Flowable.subscribe:(Lio/reactivex/rxjava3/core/FlowableSubscriber;)V
      35: goto          107
      38: aload_0
      39: getfield      #3                  // Field skip:J
      42: aload_0
      43: getfield      #2                  // Field size:J
      46: lcmp
      47: ifle          80
      50: aload_0
      51: getfield      #5                  // Field source:Lio/reactivex/rxjava3/core/Flowable;
      54: new           #9                  // class io/reactivex/rxjava3/internal/operators/flowable/FlowableWindow$WindowSkipSubscriber
      57: dup
      58: aload_1
      59: aload_0
      60: getfield      #2                  // Field size:J
      63: aload_0
      64: getfield      #3                  // Field skip:J
      67: aload_0
      68: getfield      #4                  // Field bufferSize:I
      71: invokespecial #10                 // Method io/reactivex/rxjava3/internal/operators/flowable/FlowableWindow$WindowSkipSubscriber."<init>":(Lorg/reactivestreams/Subscriber;JJI)V
      74: invokevirtual #8                  // Method io/reactivex/rxjava3/core/Flowable.subscribe:(Lio/reactivex/rxjava3/core/FlowableSubscriber;)V
      77: goto          107
      80: aload_0
      81: getfield      #5                  // Field source:Lio/reactivex/rxjava3/core/Flowable;
      84: new           #11                 // class io/reactivex/rxjava3/internal/operators/flowable/FlowableWindow$WindowOverlapSubscriber
      87: dup
      88: aload_1
      89: aload_0
      90: getfield      #2                  // Field size:J
      93: aload_0
      94: getfield      #3                  // Field skip:J
      97: aload_0
      98: getfield      #4                  // Field bufferSize:I
     101: invokespecial #12                 // Method io/reactivex/rxjava3/internal/operators/flowable/FlowableWindow$WindowOverlapSubscriber."<init>":(Lorg/reactivestreams/Subscriber;JJI)V
     104: invokevirtual #8                  // Method io/reactivex/rxjava3/core/Flowable.subscribe:(Lio/reactivex/rxjava3/core/FlowableSubscriber;)V
     107: return
}
