Compiled from "FlowableRefCount.java"
final class io.reactivex.rxjava3.internal.operators.flowable.FlowableRefCount$RefCountSubscriber<T> extends java.util.concurrent.atomic.AtomicBoolean implements io.reactivex.rxjava3.core.FlowableSubscriber<T>, org.reactivestreams.Subscription {
  private static final long serialVersionUID;

  final org.reactivestreams.Subscriber<? super T> downstream;

  final io.reactivex.rxjava3.internal.operators.flowable.FlowableRefCount<T> parent;

  final io.reactivex.rxjava3.internal.operators.flowable.FlowableRefCount$RefConnection connection;

  org.reactivestreams.Subscription upstream;

  io.reactivex.rxjava3.internal.operators.flowable.FlowableRefCount$RefCountSubscriber(org.reactivestreams.Subscriber<? super T>, io.reactivex.rxjava3.internal.operators.flowable.FlowableRefCount<T>, io.reactivex.rxjava3.internal.operators.flowable.FlowableRefCount$RefConnection);
    Code:
       0: aload_0
       1: invokespecial #1                  // Method java/util/concurrent/atomic/AtomicBoolean."<init>":()V
       4: aload_0
       5: aload_1
       6: putfield      #2                  // Field downstream:Lorg/reactivestreams/Subscriber;
       9: aload_0
      10: aload_2
      11: putfield      #3                  // Field parent:Lio/reactivex/rxjava3/internal/operators/flowable/FlowableRefCount;
      14: aload_0
      15: aload_3
      16: putfield      #4                  // Field connection:Lio/reactivex/rxjava3/internal/operators/flowable/FlowableRefCount$RefConnection;
      19: return

  public void onNext(T);
    Code:
       0: aload_0
       1: getfield      #2                  // Field downstream:Lorg/reactivestreams/Subscriber;
       4: aload_1
       5: invokeinterface #5,  2            // InterfaceMethod org/reactivestreams/Subscriber.onNext:(Ljava/lang/Object;)V
      10: return

  public void onError(java.lang.Throwable);
    Code:
       0: aload_0
       1: iconst_0
       2: iconst_1
       3: invokevirtual #6                  // Method compareAndSet:(ZZ)Z
       6: ifeq          33
       9: aload_0
      10: getfield      #3                  // Field parent:Lio/reactivex/rxjava3/internal/operators/flowable/FlowableRefCount;
      13: aload_0
      14: getfield      #4                  // Field connection:Lio/reactivex/rxjava3/internal/operators/flowable/FlowableRefCount$RefConnection;
      17: invokevirtual #7                  // Method io/reactivex/rxjava3/internal/operators/flowable/FlowableRefCount.terminated:(Lio/reactivex/rxjava3/internal/operators/flowable/FlowableRefCount$RefConnection;)V
      20: aload_0
      21: getfield      #2                  // Field downstream:Lorg/reactivestreams/Subscriber;
      24: aload_1
      25: invokeinterface #8,  2            // InterfaceMethod org/reactivestreams/Subscriber.onError:(Ljava/lang/Throwable;)V
      30: goto          37
      33: aload_1
      34: invokestatic  #9                  // Method io/reactivex/rxjava3/plugins/RxJavaPlugins.onError:(Ljava/lang/Throwable;)V
      37: return

  public void onComplete();
    Code:
       0: aload_0
       1: iconst_0
       2: iconst_1
       3: invokevirtual #6                  // Method compareAndSet:(ZZ)Z
       6: ifeq          29
       9: aload_0
      10: getfield      #3                  // Field parent:Lio/reactivex/rxjava3/internal/operators/flowable/FlowableRefCount;
      13: aload_0
      14: getfield      #4                  // Field connection:Lio/reactivex/rxjava3/internal/operators/flowable/FlowableRefCount$RefConnection;
      17: invokevirtual #7                  // Method io/reactivex/rxjava3/internal/operators/flowable/FlowableRefCount.terminated:(Lio/reactivex/rxjava3/internal/operators/flowable/FlowableRefCount$RefConnection;)V
      20: aload_0
      21: getfield      #2                  // Field downstream:Lorg/reactivestreams/Subscriber;
      24: invokeinterface #10,  1           // InterfaceMethod org/reactivestreams/Subscriber.onComplete:()V
      29: return

  public void request(long);
    Code:
       0: aload_0
       1: getfield      #11                 // Field upstream:Lorg/reactivestreams/Subscription;
       4: lload_1
       5: invokeinterface #12,  3           // InterfaceMethod org/reactivestreams/Subscription.request:(J)V
      10: return

  public void cancel();
    Code:
       0: aload_0
       1: getfield      #11                 // Field upstream:Lorg/reactivestreams/Subscription;
       4: invokeinterface #13,  1           // InterfaceMethod org/reactivestreams/Subscription.cancel:()V
       9: aload_0
      10: iconst_0
      11: iconst_1
      12: invokevirtual #6                  // Method compareAndSet:(ZZ)Z
      15: ifeq          29
      18: aload_0
      19: getfield      #3                  // Field parent:Lio/reactivex/rxjava3/internal/operators/flowable/FlowableRefCount;
      22: aload_0
      23: getfield      #4                  // Field connection:Lio/reactivex/rxjava3/internal/operators/flowable/FlowableRefCount$RefConnection;
      26: invokevirtual #14                 // Method io/reactivex/rxjava3/internal/operators/flowable/FlowableRefCount.cancel:(Lio/reactivex/rxjava3/internal/operators/flowable/FlowableRefCount$RefConnection;)V
      29: return

  public void onSubscribe(org.reactivestreams.Subscription);
    Code:
       0: aload_0
       1: getfield      #11                 // Field upstream:Lorg/reactivestreams/Subscription;
       4: aload_1
       5: invokestatic  #15                 // Method io/reactivex/rxjava3/internal/subscriptions/SubscriptionHelper.validate:(Lorg/reactivestreams/Subscription;Lorg/reactivestreams/Subscription;)Z
       8: ifeq          26
      11: aload_0
      12: aload_1
      13: putfield      #11                 // Field upstream:Lorg/reactivestreams/Subscription;
      16: aload_0
      17: getfield      #2                  // Field downstream:Lorg/reactivestreams/Subscriber;
      20: aload_0
      21: invokeinterface #16,  2           // InterfaceMethod org/reactivestreams/Subscriber.onSubscribe:(Lorg/reactivestreams/Subscription;)V
      26: return
}
