Compiled from "FlowableOnBackpressureDrop.java"
public final class io.reactivex.rxjava3.internal.operators.flowable.FlowableOnBackpressureDrop<T> extends io.reactivex.rxjava3.internal.operators.flowable.AbstractFlowableWithUpstream<T, T> implements io.reactivex.rxjava3.functions.Consumer<T> {
  final io.reactivex.rxjava3.functions.Consumer<? super T> onDrop;

  public io.reactivex.rxjava3.internal.operators.flowable.FlowableOnBackpressureDrop(io.reactivex.rxjava3.core.Flowable<T>);
    Code:
       0: aload_0
       1: aload_1
       2: invokespecial #1                  // Method io/reactivex/rxjava3/internal/operators/flowable/AbstractFlowableWithUpstream."<init>":(Lio/reactivex/rxjava3/core/Flowable;)V
       5: aload_0
       6: aload_0
       7: putfield      #2                  // Field onDrop:Lio/reactivex/rxjava3/functions/Consumer;
      10: return

  public io.reactivex.rxjava3.internal.operators.flowable.FlowableOnBackpressureDrop(io.reactivex.rxjava3.core.Flowable<T>, io.reactivex.rxjava3.functions.Consumer<? super T>);
    Code:
       0: aload_0
       1: aload_1
       2: invokespecial #1                  // Method io/reactivex/rxjava3/internal/operators/flowable/AbstractFlowableWithUpstream."<init>":(Lio/reactivex/rxjava3/core/Flowable;)V
       5: aload_0
       6: aload_2
       7: putfield      #2                  // Field onDrop:Lio/reactivex/rxjava3/functions/Consumer;
      10: return

  public void accept(T);
    Code:
       0: return

  protected void subscribeActual(org.reactivestreams.Subscriber<? super T>);
    Code:
       0: aload_0
       1: getfield      #3                  // Field source:Lio/reactivex/rxjava3/core/Flowable;
       4: new           #4                  // class io/reactivex/rxjava3/internal/operators/flowable/FlowableOnBackpressureDrop$BackpressureDropSubscriber
       7: dup
       8: aload_1
       9: aload_0
      10: getfield      #2                  // Field onDrop:Lio/reactivex/rxjava3/functions/Consumer;
      13: invokespecial #5                  // Method io/reactivex/rxjava3/internal/operators/flowable/FlowableOnBackpressureDrop$BackpressureDropSubscriber."<init>":(Lorg/reactivestreams/Subscriber;Lio/reactivex/rxjava3/functions/Consumer;)V
      16: invokevirtual #6                  // Method io/reactivex/rxjava3/core/Flowable.subscribe:(Lio/reactivex/rxjava3/core/FlowableSubscriber;)V
      19: return
}
