Compiled from "FlowableSampleTimed.java"
public final class io.reactivex.rxjava3.internal.operators.flowable.FlowableSampleTimed<T> extends io.reactivex.rxjava3.internal.operators.flowable.AbstractFlowableWithUpstream<T, T> {
  final long period;

  final java.util.concurrent.TimeUnit unit;

  final io.reactivex.rxjava3.core.Scheduler scheduler;

  final boolean emitLast;

  final io.reactivex.rxjava3.functions.Consumer<? super T> onDropped;

  public io.reactivex.rxjava3.internal.operators.flowable.FlowableSampleTimed(io.reactivex.rxjava3.core.Flowable<T>, long, java.util.concurrent.TimeUnit, io.reactivex.rxjava3.core.Scheduler, boolean, io.reactivex.rxjava3.functions.Consumer<? super T>);
    Code:
       0: aload_0
       1: aload_1
       2: invokespecial #1                  // Method io/reactivex/rxjava3/internal/operators/flowable/AbstractFlowableWithUpstream."<init>":(Lio/reactivex/rxjava3/core/Flowable;)V
       5: aload_0
       6: lload_2
       7: putfield      #2                  // Field period:J
      10: aload_0
      11: aload         4
      13: putfield      #3                  // Field unit:Ljava/util/concurrent/TimeUnit;
      16: aload_0
      17: aload         5
      19: putfield      #4                  // Field scheduler:Lio/reactivex/rxjava3/core/Scheduler;
      22: aload_0
      23: iload         6
      25: putfield      #5                  // Field emitLast:Z
      28: aload_0
      29: aload         7
      31: putfield      #6                  // Field onDropped:Lio/reactivex/rxjava3/functions/Consumer;
      34: return

  protected void subscribeActual(org.reactivestreams.Subscriber<? super T>);
    Code:
       0: new           #7                  // class io/reactivex/rxjava3/subscribers/SerializedSubscriber
       3: dup
       4: aload_1
       5: invokespecial #8                  // Method io/reactivex/rxjava3/subscribers/SerializedSubscriber."<init>":(Lorg/reactivestreams/Subscriber;)V
       8: astore_2
       9: aload_0
      10: getfield      #5                  // Field emitLast:Z
      13: ifeq          50
      16: aload_0
      17: getfield      #9                  // Field source:Lio/reactivex/rxjava3/core/Flowable;
      20: new           #10                 // class io/reactivex/rxjava3/internal/operators/flowable/FlowableSampleTimed$SampleTimedEmitLast
      23: dup
      24: aload_2
      25: aload_0
      26: getfield      #2                  // Field period:J
      29: aload_0
      30: getfield      #3                  // Field unit:Ljava/util/concurrent/TimeUnit;
      33: aload_0
      34: getfield      #4                  // Field scheduler:Lio/reactivex/rxjava3/core/Scheduler;
      37: aload_0
      38: getfield      #6                  // Field onDropped:Lio/reactivex/rxjava3/functions/Consumer;
      41: invokespecial #11                 // Method io/reactivex/rxjava3/internal/operators/flowable/FlowableSampleTimed$SampleTimedEmitLast."<init>":(Lorg/reactivestreams/Subscriber;JLjava/util/concurrent/TimeUnit;Lio/reactivex/rxjava3/core/Scheduler;Lio/reactivex/rxjava3/functions/Consumer;)V
      44: invokevirtual #12                 // Method io/reactivex/rxjava3/core/Flowable.subscribe:(Lio/reactivex/rxjava3/core/FlowableSubscriber;)V
      47: goto          81
      50: aload_0
      51: getfield      #9                  // Field source:Lio/reactivex/rxjava3/core/Flowable;
      54: new           #13                 // class io/reactivex/rxjava3/internal/operators/flowable/FlowableSampleTimed$SampleTimedNoLast
      57: dup
      58: aload_2
      59: aload_0
      60: getfield      #2                  // Field period:J
      63: aload_0
      64: getfield      #3                  // Field unit:Ljava/util/concurrent/TimeUnit;
      67: aload_0
      68: getfield      #4                  // Field scheduler:Lio/reactivex/rxjava3/core/Scheduler;
      71: aload_0
      72: getfield      #6                  // Field onDropped:Lio/reactivex/rxjava3/functions/Consumer;
      75: invokespecial #14                 // Method io/reactivex/rxjava3/internal/operators/flowable/FlowableSampleTimed$SampleTimedNoLast."<init>":(Lorg/reactivestreams/Subscriber;JLjava/util/concurrent/TimeUnit;Lio/reactivex/rxjava3/core/Scheduler;Lio/reactivex/rxjava3/functions/Consumer;)V
      78: invokevirtual #12                 // Method io/reactivex/rxjava3/core/Flowable.subscribe:(Lio/reactivex/rxjava3/core/FlowableSubscriber;)V
      81: return
}
