Compiled from "FlowableInternalHelper.java"
public final class io.reactivex.rxjava3.internal.operators.flowable.FlowableInternalHelper$RequestMax extends java.lang.Enum<io.reactivex.rxjava3.internal.operators.flowable.FlowableInternalHelper$RequestMax> implements io.reactivex.rxjava3.functions.Consumer<org.reactivestreams.Subscription> {
  public static final io.reactivex.rxjava3.internal.operators.flowable.FlowableInternalHelper$RequestMax INSTANCE;

  private static final io.reactivex.rxjava3.internal.operators.flowable.FlowableInternalHelper$RequestMax[] $VALUES;

  public static io.reactivex.rxjava3.internal.operators.flowable.FlowableInternalHelper$RequestMax[] values();
    Code:
       0: getstatic     #1                  // Field $VALUES:[Lio/reactivex/rxjava3/internal/operators/flowable/FlowableInternalHelper$RequestMax;
       3: invokevirtual #2                  // Method "[Lio/reactivex/rxjava3/internal/operators/flowable/FlowableInternalHelper$RequestMax;".clone:()Ljava/lang/Object;
       6: checkcast     #3                  // class "[Lio/reactivex/rxjava3/internal/operators/flowable/FlowableInternalHelper$RequestMax;"
       9: areturn

  public static io.reactivex.rxjava3.internal.operators.flowable.FlowableInternalHelper$RequestMax valueOf(java.lang.String);
    Code:
       0: ldc           #4                  // class io/reactivex/rxjava3/internal/operators/flowable/FlowableInternalHelper$RequestMax
       2: aload_0
       3: invokestatic  #5                  // Method java/lang/Enum.valueOf:(Ljava/lang/Class;Ljava/lang/String;)Ljava/lang/Enum;
       6: checkcast     #4                  // class io/reactivex/rxjava3/internal/operators/flowable/FlowableInternalHelper$RequestMax
       9: areturn

  private io.reactivex.rxjava3.internal.operators.flowable.FlowableInternalHelper$RequestMax();
    Code:
       0: aload_0
       1: aload_1
       2: iload_2
       3: invokespecial #6                  // Method java/lang/Enum."<init>":(Ljava/lang/String;I)V
       6: return

  public void accept(org.reactivestreams.Subscription);
    Code:
       0: aload_1
       1: ldc2_w        #8                  // long 9223372036854775807l
       4: invokeinterface #10,  3           // InterfaceMethod org/reactivestreams/Subscription.request:(J)V
       9: return

  public void accept(java.lang.Object) throws java.lang.Throwable;
    Code:
       0: aload_0
       1: aload_1
       2: checkcast     #11                 // class org/reactivestreams/Subscription
       5: invokevirtual #12                 // Method accept:(Lorg/reactivestreams/Subscription;)V
       8: return

  static {};
    Code:
       0: new           #4                  // class io/reactivex/rxjava3/internal/operators/flowable/FlowableInternalHelper$RequestMax
       3: dup
       4: ldc           #13                 // String INSTANCE
       6: iconst_0
       7: invokespecial #14                 // Method "<init>":(Ljava/lang/String;I)V
      10: putstatic     #15                 // Field INSTANCE:Lio/reactivex/rxjava3/internal/operators/flowable/FlowableInternalHelper$RequestMax;
      13: iconst_1
      14: anewarray     #4                  // class io/reactivex/rxjava3/internal/operators/flowable/FlowableInternalHelper$RequestMax
      17: dup
      18: iconst_0
      19: getstatic     #15                 // Field INSTANCE:Lio/reactivex/rxjava3/internal/operators/flowable/FlowableInternalHelper$RequestMax;
      22: aastore
      23: putstatic     #1                  // Field $VALUES:[Lio/reactivex/rxjava3/internal/operators/flowable/FlowableInternalHelper$RequestMax;
      26: return
}
