Compiled from "FlowableRetryPredicate.java"
final class io.reactivex.rxjava3.internal.operators.flowable.FlowableRetryPredicate$RetrySubscriber<T> extends java.util.concurrent.atomic.AtomicInteger implements io.reactivex.rxjava3.core.FlowableSubscriber<T> {
  private static final long serialVersionUID;

  final org.reactivestreams.Subscriber<? super T> downstream;

  final io.reactivex.rxjava3.internal.subscriptions.SubscriptionArbiter sa;

  final org.reactivestreams.Publisher<? extends T> source;

  final io.reactivex.rxjava3.functions.Predicate<? super java.lang.Throwable> predicate;

  long remaining;

  long produced;

  io.reactivex.rxjava3.internal.operators.flowable.FlowableRetryPredicate$RetrySubscriber(org.reactivestreams.Subscriber<? super T>, long, io.reactivex.rxjava3.functions.Predicate<? super java.lang.Throwable>, io.reactivex.rxjava3.internal.subscriptions.SubscriptionArbiter, org.reactivestreams.Publisher<? extends T>);
    Code:
       0: aload_0
       1: invokespecial #1                  // Method java/util/concurrent/atomic/AtomicInteger."<init>":()V
       4: aload_0
       5: aload_1
       6: putfield      #2                  // Field downstream:Lorg/reactivestreams/Subscriber;
       9: aload_0
      10: aload         5
      12: putfield      #3                  // Field sa:Lio/reactivex/rxjava3/internal/subscriptions/SubscriptionArbiter;
      15: aload_0
      16: aload         6
      18: putfield      #4                  // Field source:Lorg/reactivestreams/Publisher;
      21: aload_0
      22: aload         4
      24: putfield      #5                  // Field predicate:Lio/reactivex/rxjava3/functions/Predicate;
      27: aload_0
      28: lload_2
      29: putfield      #6                  // Field remaining:J
      32: return

  public void onSubscribe(org.reactivestreams.Subscription);
    Code:
       0: aload_0
       1: getfield      #3                  // Field sa:Lio/reactivex/rxjava3/internal/subscriptions/SubscriptionArbiter;
       4: aload_1
       5: invokevirtual #7                  // Method io/reactivex/rxjava3/internal/subscriptions/SubscriptionArbiter.setSubscription:(Lorg/reactivestreams/Subscription;)V
       8: return

  public void onNext(T);
    Code:
       0: aload_0
       1: dup
       2: getfield      #8                  // Field produced:J
       5: lconst_1
       6: ladd
       7: putfield      #8                  // Field produced:J
      10: aload_0
      11: getfield      #2                  // Field downstream:Lorg/reactivestreams/Subscriber;
      14: aload_1
      15: invokeinterface #9,  2            // InterfaceMethod org/reactivestreams/Subscriber.onNext:(Ljava/lang/Object;)V
      20: return

  public void onError(java.lang.Throwable);
    Code:
       0: aload_0
       1: getfield      #6                  // Field remaining:J
       4: lstore_2
       5: lload_2
       6: ldc2_w        #11                 // long 9223372036854775807l
       9: lcmp
      10: ifeq          20
      13: aload_0
      14: lload_2
      15: lconst_1
      16: lsub
      17: putfield      #6                  // Field remaining:J
      20: lload_2
      21: lconst_0
      22: lcmp
      23: ifne          39
      26: aload_0
      27: getfield      #2                  // Field downstream:Lorg/reactivestreams/Subscriber;
      30: aload_1
      31: invokeinterface #13,  2           // InterfaceMethod org/reactivestreams/Subscriber.onError:(Ljava/lang/Throwable;)V
      36: goto          111
      39: aload_0
      40: getfield      #5                  // Field predicate:Lio/reactivex/rxjava3/functions/Predicate;
      43: aload_1
      44: invokeinterface #14,  2           // InterfaceMethod io/reactivex/rxjava3/functions/Predicate.test:(Ljava/lang/Object;)Z
      49: istore        4
      51: goto          91
      54: astore        5
      56: aload         5
      58: invokestatic  #16                 // Method io/reactivex/rxjava3/exceptions/Exceptions.throwIfFatal:(Ljava/lang/Throwable;)V
      61: aload_0
      62: getfield      #2                  // Field downstream:Lorg/reactivestreams/Subscriber;
      65: new           #17                 // class io/reactivex/rxjava3/exceptions/CompositeException
      68: dup
      69: iconst_2
      70: anewarray     #18                 // class java/lang/Throwable
      73: dup
      74: iconst_0
      75: aload_1
      76: aastore
      77: dup
      78: iconst_1
      79: aload         5
      81: aastore
      82: invokespecial #19                 // Method io/reactivex/rxjava3/exceptions/CompositeException."<init>":([Ljava/lang/Throwable;)V
      85: invokeinterface #13,  2           // InterfaceMethod org/reactivestreams/Subscriber.onError:(Ljava/lang/Throwable;)V
      90: return
      91: iload         4
      93: ifne          107
      96: aload_0
      97: getfield      #2                  // Field downstream:Lorg/reactivestreams/Subscriber;
     100: aload_1
     101: invokeinterface #13,  2           // InterfaceMethod org/reactivestreams/Subscriber.onError:(Ljava/lang/Throwable;)V
     106: return
     107: aload_0
     108: invokevirtual #20                 // Method subscribeNext:()V
     111: return
    Exception table:
       from    to  target type
          39    51    54   Class java/lang/Throwable

  public void onComplete();
    Code:
       0: aload_0
       1: getfield      #2                  // Field downstream:Lorg/reactivestreams/Subscriber;
       4: invokeinterface #21,  1           // InterfaceMethod org/reactivestreams/Subscriber.onComplete:()V
       9: return

  void subscribeNext();
    Code:
       0: aload_0
       1: invokevirtual #22                 // Method getAndIncrement:()I
       4: ifne          71
       7: iconst_1
       8: istore_1
       9: aload_0
      10: getfield      #3                  // Field sa:Lio/reactivex/rxjava3/internal/subscriptions/SubscriptionArbiter;
      13: invokevirtual #23                 // Method io/reactivex/rxjava3/internal/subscriptions/SubscriptionArbiter.isCancelled:()Z
      16: ifeq          20
      19: return
      20: aload_0
      21: getfield      #8                  // Field produced:J
      24: lstore_2
      25: lload_2
      26: lconst_0
      27: lcmp
      28: ifeq          44
      31: aload_0
      32: lconst_0
      33: putfield      #8                  // Field produced:J
      36: aload_0
      37: getfield      #3                  // Field sa:Lio/reactivex/rxjava3/internal/subscriptions/SubscriptionArbiter;
      40: lload_2
      41: invokevirtual #24                 // Method io/reactivex/rxjava3/internal/subscriptions/SubscriptionArbiter.produced:(J)V
      44: aload_0
      45: getfield      #4                  // Field source:Lorg/reactivestreams/Publisher;
      48: aload_0
      49: invokeinterface #25,  2           // InterfaceMethod org/reactivestreams/Publisher.subscribe:(Lorg/reactivestreams/Subscriber;)V
      54: aload_0
      55: iload_1
      56: ineg
      57: invokevirtual #26                 // Method addAndGet:(I)I
      60: istore_1
      61: iload_1
      62: ifne          68
      65: goto          71
      68: goto          9
      71: return
}
