Compiled from "FlowableOnBackpressureBufferStrategy.java"
class io.reactivex.rxjava3.internal.operators.flowable.FlowableOnBackpressureBufferStrategy$1 {
  static final int[] $SwitchMap$io$reactivex$rxjava3$core$BackpressureOverflowStrategy;

  static {};
    Code:
       0: invokestatic  #1                  // Method io/reactivex/rxjava3/core/BackpressureOverflowStrategy.values:()[Lio/reactivex/rxjava3/core/BackpressureOverflowStrategy;
       3: arraylength
       4: newarray       int
       6: putstatic     #2                  // Field $SwitchMap$io$reactivex$rxjava3$core$BackpressureOverflowStrategy:[I
       9: getstatic     #2                  // Field $SwitchMap$io$reactivex$rxjava3$core$BackpressureOverflowStrategy:[I
      12: getstatic     #3                  // Field io/reactivex/rxjava3/core/BackpressureOverflowStrategy.DROP_LATEST:Lio/reactivex/rxjava3/core/BackpressureOverflowStrategy;
      15: invokevirtual #4                  // Method io/reactivex/rxjava3/core/BackpressureOverflowStrategy.ordinal:()I
      18: iconst_1
      19: iastore
      20: goto          24
      23: astore_0
      24: getstatic     #2                  // Field $SwitchMap$io$reactivex$rxjava3$core$BackpressureOverflowStrategy:[I
      27: getstatic     #6                  // Field io/reactivex/rxjava3/core/BackpressureOverflowStrategy.DROP_OLDEST:Lio/reactivex/rxjava3/core/BackpressureOverflowStrategy;
      30: invokevirtual #4                  // Method io/reactivex/rxjava3/core/BackpressureOverflowStrategy.ordinal:()I
      33: iconst_2
      34: iastore
      35: goto          39
      38: astore_0
      39: return
    Exception table:
       from    to  target type
           9    20    23   Class java/lang/NoSuchFieldError
          24    35    38   Class java/lang/NoSuchFieldError
}
