Compiled from "FlowableRetryWhen.java"
final class io.reactivex.rxjava3.internal.operators.flowable.FlowableRetryWhen$RetryWhenSubscriber<T> extends io.reactivex.rxjava3.internal.operators.flowable.FlowableRepeatWhen$WhenSourceSubscriber<T, java.lang.Throwable> {
  private static final long serialVersionUID;

  io.reactivex.rxjava3.internal.operators.flowable.FlowableRetryWhen$RetryWhenSubscriber(org.reactivestreams.Subscriber<? super T>, io.reactivex.rxjava3.processors.FlowableProcessor<java.lang.Throwable>, org.reactivestreams.Subscription);
    Code:
       0: aload_0
       1: aload_1
       2: aload_2
       3: aload_3
       4: invokespecial #1                  // Method io/reactivex/rxjava3/internal/operators/flowable/FlowableRepeatWhen$WhenSourceSubscriber."<init>":(Lorg/reactivestreams/Subscriber;Lio/reactivex/rxjava3/processors/FlowableProcessor;Lorg/reactivestreams/Subscription;)V
       7: return

  public void onError(java.lang.Throwable);
    Code:
       0: aload_0
       1: aload_1
       2: invokevirtual #2                  // Method again:(Ljava/lang/Object;)V
       5: return

  public void onComplete();
    Code:
       0: aload_0
       1: getfield      #3                  // Field receiver:Lorg/reactivestreams/Subscription;
       4: invokeinterface #4,  1            // InterfaceMethod org/reactivestreams/Subscription.cancel:()V
       9: aload_0
      10: getfield      #5                  // Field downstream:Lorg/reactivestreams/Subscriber;
      13: invokeinterface #6,  1            // InterfaceMethod org/reactivestreams/Subscriber.onComplete:()V
      18: return
}
