Compiled from "FlowableDetach.java"
final class io.reactivex.rxjava3.internal.operators.flowable.FlowableDetach$DetachSubscriber<T> implements io.reactivex.rxjava3.core.FlowableSubscriber<T>, org.reactivestreams.Subscription {
  org.reactivestreams.Subscriber<? super T> downstream;

  org.reactivestreams.Subscription upstream;

  io.reactivex.rxjava3.internal.operators.flowable.FlowableDetach$DetachSubscriber(org.reactivestreams.Subscriber<? super T>);
    Code:
       0: aload_0
       1: invokespecial #1                  // Method java/lang/Object."<init>":()V
       4: aload_0
       5: aload_1
       6: putfield      #2                  // Field downstream:Lorg/reactivestreams/Subscriber;
       9: return

  public void request(long);
    Code:
       0: aload_0
       1: getfield      #3                  // Field upstream:Lorg/reactivestreams/Subscription;
       4: lload_1
       5: invokeinterface #4,  3            // InterfaceMethod org/reactivestreams/Subscription.request:(J)V
      10: return

  public void cancel();
    Code:
       0: aload_0
       1: getfield      #3                  // Field upstream:Lorg/reactivestreams/Subscription;
       4: astore_1
       5: aload_0
       6: getstatic     #5                  // Field io/reactivex/rxjava3/internal/util/EmptyComponent.INSTANCE:Lio/reactivex/rxjava3/internal/util/EmptyComponent;
       9: putfield      #3                  // Field upstream:Lorg/reactivestreams/Subscription;
      12: aload_0
      13: invokestatic  #6                  // Method io/reactivex/rxjava3/internal/util/EmptyComponent.asSubscriber:()Lorg/reactivestreams/Subscriber;
      16: putfield      #2                  // Field downstream:Lorg/reactivestreams/Subscriber;
      19: aload_1
      20: invokeinterface #7,  1            // InterfaceMethod org/reactivestreams/Subscription.cancel:()V
      25: return

  public void onSubscribe(org.reactivestreams.Subscription);
    Code:
       0: aload_0
       1: getfield      #3                  // Field upstream:Lorg/reactivestreams/Subscription;
       4: aload_1
       5: invokestatic  #8                  // Method io/reactivex/rxjava3/internal/subscriptions/SubscriptionHelper.validate:(Lorg/reactivestreams/Subscription;Lorg/reactivestreams/Subscription;)Z
       8: ifeq          26
      11: aload_0
      12: aload_1
      13: putfield      #3                  // Field upstream:Lorg/reactivestreams/Subscription;
      16: aload_0
      17: getfield      #2                  // Field downstream:Lorg/reactivestreams/Subscriber;
      20: aload_0
      21: invokeinterface #9,  2            // InterfaceMethod org/reactivestreams/Subscriber.onSubscribe:(Lorg/reactivestreams/Subscription;)V
      26: return

  public void onNext(T);
    Code:
       0: aload_0
       1: getfield      #2                  // Field downstream:Lorg/reactivestreams/Subscriber;
       4: aload_1
       5: invokeinterface #10,  2           // InterfaceMethod org/reactivestreams/Subscriber.onNext:(Ljava/lang/Object;)V
      10: return

  public void onError(java.lang.Throwable);
    Code:
       0: aload_0
       1: getfield      #2                  // Field downstream:Lorg/reactivestreams/Subscriber;
       4: astore_2
       5: aload_0
       6: getstatic     #5                  // Field io/reactivex/rxjava3/internal/util/EmptyComponent.INSTANCE:Lio/reactivex/rxjava3/internal/util/EmptyComponent;
       9: putfield      #3                  // Field upstream:Lorg/reactivestreams/Subscription;
      12: aload_0
      13: invokestatic  #6                  // Method io/reactivex/rxjava3/internal/util/EmptyComponent.asSubscriber:()Lorg/reactivestreams/Subscriber;
      16: putfield      #2                  // Field downstream:Lorg/reactivestreams/Subscriber;
      19: aload_2
      20: aload_1
      21: invokeinterface #11,  2           // InterfaceMethod org/reactivestreams/Subscriber.onError:(Ljava/lang/Throwable;)V
      26: return

  public void onComplete();
    Code:
       0: aload_0
       1: getfield      #2                  // Field downstream:Lorg/reactivestreams/Subscriber;
       4: astore_1
       5: aload_0
       6: getstatic     #5                  // Field io/reactivex/rxjava3/internal/util/EmptyComponent.INSTANCE:Lio/reactivex/rxjava3/internal/util/EmptyComponent;
       9: putfield      #3                  // Field upstream:Lorg/reactivestreams/Subscription;
      12: aload_0
      13: invokestatic  #6                  // Method io/reactivex/rxjava3/internal/util/EmptyComponent.asSubscriber:()Lorg/reactivestreams/Subscriber;
      16: putfield      #2                  // Field downstream:Lorg/reactivestreams/Subscriber;
      19: aload_1
      20: invokeinterface #12,  1           // InterfaceMethod org/reactivestreams/Subscriber.onComplete:()V
      25: return
}
