Compiled from "FlowableInternalHelper.java"
final class io.reactivex.rxjava3.internal.operators.flowable.FlowableInternalHelper$SubscriberOnNext<T> implements io.reactivex.rxjava3.functions.Consumer<T> {
  final org.reactivestreams.Subscriber<T> subscriber;

  io.reactivex.rxjava3.internal.operators.flowable.FlowableInternalHelper$SubscriberOnNext(org.reactivestreams.Subscriber<T>);
    Code:
       0: aload_0
       1: invokespecial #1                  // Method java/lang/Object."<init>":()V
       4: aload_0
       5: aload_1
       6: putfield      #2                  // Field subscriber:Lorg/reactivestreams/Subscriber;
       9: return

  public void accept(T);
    Code:
       0: aload_0
       1: getfield      #2                  // Field subscriber:Lorg/reactivestreams/Subscriber;
       4: aload_1
       5: invokeinterface #3,  2            // InterfaceMethod org/reactivestreams/Subscriber.onNext:(Ljava/lang/Object;)V
      10: return
}
