Compiled from "FlowableGroupJoin.java"
public final class io.reactivex.rxjava3.internal.operators.flowable.FlowableGroupJoin<TLeft, TRight, TLeftEnd, TRightEnd, R> extends io.reactivex.rxjava3.internal.operators.flowable.AbstractFlowableWithUpstream<TLeft, R> {
  final org.reactivestreams.Publisher<? extends TRight> other;

  final io.reactivex.rxjava3.functions.Function<? super TLeft, ? extends org.reactivestreams.Publisher<TLeftEnd>> leftEnd;

  final io.reactivex.rxjava3.functions.Function<? super TRight, ? extends org.reactivestreams.Publisher<TRightEnd>> rightEnd;

  final io.reactivex.rxjava3.functions.BiFunction<? super TLeft, ? super io.reactivex.rxjava3.core.Flowable<TRight>, ? extends R> resultSelector;

  public io.reactivex.rxjava3.internal.operators.flowable.FlowableGroupJoin(io.reactivex.rxjava3.core.Flowable<TLeft>, org.reactivestreams.Publisher<? extends TRight>, io.reactivex.rxjava3.functions.Function<? super TLeft, ? extends org.reactivestreams.Publisher<TLeftEnd>>, io.reactivex.rxjava3.functions.Function<? super TRight, ? extends org.reactivestreams.Publisher<TRightEnd>>, io.reactivex.rxjava3.functions.BiFunction<? super TLeft, ? super io.reactivex.rxjava3.core.Flowable<TRight>, ? extends R>);
    Code:
       0: aload_0
       1: aload_1
       2: invokespecial #1                  // Method io/reactivex/rxjava3/internal/operators/flowable/AbstractFlowableWithUpstream."<init>":(Lio/reactivex/rxjava3/core/Flowable;)V
       5: aload_0
       6: aload_2
       7: putfield      #2                  // Field other:Lorg/reactivestreams/Publisher;
      10: aload_0
      11: aload_3
      12: putfield      #3                  // Field leftEnd:Lio/reactivex/rxjava3/functions/Function;
      15: aload_0
      16: aload         4
      18: putfield      #4                  // Field rightEnd:Lio/reactivex/rxjava3/functions/Function;
      21: aload_0
      22: aload         5
      24: putfield      #5                  // Field resultSelector:Lio/reactivex/rxjava3/functions/BiFunction;
      27: return

  protected void subscribeActual(org.reactivestreams.Subscriber<? super R>);
    Code:
       0: new           #6                  // class io/reactivex/rxjava3/internal/operators/flowable/FlowableGroupJoin$GroupJoinSubscription
       3: dup
       4: aload_1
       5: aload_0
       6: getfield      #3                  // Field leftEnd:Lio/reactivex/rxjava3/functions/Function;
       9: aload_0
      10: getfield      #4                  // Field rightEnd:Lio/reactivex/rxjava3/functions/Function;
      13: aload_0
      14: getfield      #5                  // Field resultSelector:Lio/reactivex/rxjava3/functions/BiFunction;
      17: invokespecial #7                  // Method io/reactivex/rxjava3/internal/operators/flowable/FlowableGroupJoin$GroupJoinSubscription."<init>":(Lorg/reactivestreams/Subscriber;Lio/reactivex/rxjava3/functions/Function;Lio/reactivex/rxjava3/functions/Function;Lio/reactivex/rxjava3/functions/BiFunction;)V
      20: astore_2
      21: aload_1
      22: aload_2
      23: invokeinterface #8,  2            // InterfaceMethod org/reactivestreams/Subscriber.onSubscribe:(Lorg/reactivestreams/Subscription;)V
      28: new           #9                  // class io/reactivex/rxjava3/internal/operators/flowable/FlowableGroupJoin$LeftRightSubscriber
      31: dup
      32: aload_2
      33: iconst_1
      34: invokespecial #10                 // Method io/reactivex/rxjava3/internal/operators/flowable/FlowableGroupJoin$LeftRightSubscriber."<init>":(Lio/reactivex/rxjava3/internal/operators/flowable/FlowableGroupJoin$JoinSupport;Z)V
      37: astore_3
      38: aload_2
      39: getfield      #11                 // Field io/reactivex/rxjava3/internal/operators/flowable/FlowableGroupJoin$GroupJoinSubscription.disposables:Lio/reactivex/rxjava3/disposables/CompositeDisposable;
      42: aload_3
      43: invokevirtual #12                 // Method io/reactivex/rxjava3/disposables/CompositeDisposable.add:(Lio/reactivex/rxjava3/disposables/Disposable;)Z
      46: pop
      47: new           #9                  // class io/reactivex/rxjava3/internal/operators/flowable/FlowableGroupJoin$LeftRightSubscriber
      50: dup
      51: aload_2
      52: iconst_0
      53: invokespecial #10                 // Method io/reactivex/rxjava3/internal/operators/flowable/FlowableGroupJoin$LeftRightSubscriber."<init>":(Lio/reactivex/rxjava3/internal/operators/flowable/FlowableGroupJoin$JoinSupport;Z)V
      56: astore        4
      58: aload_2
      59: getfield      #11                 // Field io/reactivex/rxjava3/internal/operators/flowable/FlowableGroupJoin$GroupJoinSubscription.disposables:Lio/reactivex/rxjava3/disposables/CompositeDisposable;
      62: aload         4
      64: invokevirtual #12                 // Method io/reactivex/rxjava3/disposables/CompositeDisposable.add:(Lio/reactivex/rxjava3/disposables/Disposable;)Z
      67: pop
      68: aload_0
      69: getfield      #13                 // Field source:Lio/reactivex/rxjava3/core/Flowable;
      72: aload_3
      73: invokevirtual #14                 // Method io/reactivex/rxjava3/core/Flowable.subscribe:(Lio/reactivex/rxjava3/core/FlowableSubscriber;)V
      76: aload_0
      77: getfield      #2                  // Field other:Lorg/reactivestreams/Publisher;
      80: aload         4
      82: invokeinterface #15,  2           // InterfaceMethod org/reactivestreams/Publisher.subscribe:(Lorg/reactivestreams/Subscriber;)V
      87: return
}
