Compiled from "FlowableSkipUntil.java"
final class io.reactivex.rxjava3.internal.operators.flowable.FlowableSkipUntil$SkipUntilMainSubscriber<T> extends java.util.concurrent.atomic.AtomicInteger implements io.reactivex.rxjava3.operators.ConditionalSubscriber<T>, org.reactivestreams.Subscription {
  private static final long serialVersionUID;

  final org.reactivestreams.Subscriber<? super T> downstream;

  final java.util.concurrent.atomic.AtomicReference<org.reactivestreams.Subscription> upstream;

  final java.util.concurrent.atomic.AtomicLong requested;

  final io.reactivex.rxjava3.internal.operators.flowable.FlowableSkipUntil$SkipUntilMainSubscriber<T>.OtherSubscriber other;

  final io.reactivex.rxjava3.internal.util.AtomicThrowable error;

  volatile boolean gate;

  io.reactivex.rxjava3.internal.operators.flowable.FlowableSkipUntil$SkipUntilMainSubscriber(org.reactivestreams.Subscriber<? super T>);
    Code:
       0: aload_0
       1: invokespecial #1                  // Method java/util/concurrent/atomic/AtomicInteger."<init>":()V
       4: aload_0
       5: aload_1
       6: putfield      #2                  // Field downstream:Lorg/reactivestreams/Subscriber;
       9: aload_0
      10: new           #3                  // class java/util/concurrent/atomic/AtomicReference
      13: dup
      14: invokespecial #4                  // Method java/util/concurrent/atomic/AtomicReference."<init>":()V
      17: putfield      #5                  // Field upstream:Ljava/util/concurrent/atomic/AtomicReference;
      20: aload_0
      21: new           #6                  // class java/util/concurrent/atomic/AtomicLong
      24: dup
      25: invokespecial #7                  // Method java/util/concurrent/atomic/AtomicLong."<init>":()V
      28: putfield      #8                  // Field requested:Ljava/util/concurrent/atomic/AtomicLong;
      31: aload_0
      32: new           #9                  // class io/reactivex/rxjava3/internal/operators/flowable/FlowableSkipUntil$SkipUntilMainSubscriber$OtherSubscriber
      35: dup
      36: aload_0
      37: invokespecial #10                 // Method io/reactivex/rxjava3/internal/operators/flowable/FlowableSkipUntil$SkipUntilMainSubscriber$OtherSubscriber."<init>":(Lio/reactivex/rxjava3/internal/operators/flowable/FlowableSkipUntil$SkipUntilMainSubscriber;)V
      40: putfield      #11                 // Field other:Lio/reactivex/rxjava3/internal/operators/flowable/FlowableSkipUntil$SkipUntilMainSubscriber$OtherSubscriber;
      43: aload_0
      44: new           #12                 // class io/reactivex/rxjava3/internal/util/AtomicThrowable
      47: dup
      48: invokespecial #13                 // Method io/reactivex/rxjava3/internal/util/AtomicThrowable."<init>":()V
      51: putfield      #14                 // Field error:Lio/reactivex/rxjava3/internal/util/AtomicThrowable;
      54: return

  public void onSubscribe(org.reactivestreams.Subscription);
    Code:
       0: aload_0
       1: getfield      #5                  // Field upstream:Ljava/util/concurrent/atomic/AtomicReference;
       4: aload_0
       5: getfield      #8                  // Field requested:Ljava/util/concurrent/atomic/AtomicLong;
       8: aload_1
       9: invokestatic  #15                 // Method io/reactivex/rxjava3/internal/subscriptions/SubscriptionHelper.deferredSetOnce:(Ljava/util/concurrent/atomic/AtomicReference;Ljava/util/concurrent/atomic/AtomicLong;Lorg/reactivestreams/Subscription;)Z
      12: pop
      13: return

  public void onNext(T);
    Code:
       0: aload_0
       1: aload_1
       2: invokevirtual #16                 // Method tryOnNext:(Ljava/lang/Object;)Z
       5: ifne          24
       8: aload_0
       9: getfield      #5                  // Field upstream:Ljava/util/concurrent/atomic/AtomicReference;
      12: invokevirtual #17                 // Method java/util/concurrent/atomic/AtomicReference.get:()Ljava/lang/Object;
      15: checkcast     #18                 // class org/reactivestreams/Subscription
      18: lconst_1
      19: invokeinterface #19,  3           // InterfaceMethod org/reactivestreams/Subscription.request:(J)V
      24: return

  public boolean tryOnNext(T);
    Code:
       0: aload_0
       1: getfield      #20                 // Field gate:Z
       4: ifeq          23
       7: aload_0
       8: getfield      #2                  // Field downstream:Lorg/reactivestreams/Subscriber;
      11: aload_1
      12: aload_0
      13: aload_0
      14: getfield      #14                 // Field error:Lio/reactivex/rxjava3/internal/util/AtomicThrowable;
      17: invokestatic  #21                 // Method io/reactivex/rxjava3/internal/util/HalfSerializer.onNext:(Lorg/reactivestreams/Subscriber;Ljava/lang/Object;Ljava/util/concurrent/atomic/AtomicInteger;Lio/reactivex/rxjava3/internal/util/AtomicThrowable;)Z
      20: pop
      21: iconst_1
      22: ireturn
      23: iconst_0
      24: ireturn

  public void onError(java.lang.Throwable);
    Code:
       0: aload_0
       1: getfield      #11                 // Field other:Lio/reactivex/rxjava3/internal/operators/flowable/FlowableSkipUntil$SkipUntilMainSubscriber$OtherSubscriber;
       4: invokestatic  #22                 // Method io/reactivex/rxjava3/internal/subscriptions/SubscriptionHelper.cancel:(Ljava/util/concurrent/atomic/AtomicReference;)Z
       7: pop
       8: aload_0
       9: getfield      #2                  // Field downstream:Lorg/reactivestreams/Subscriber;
      12: aload_1
      13: aload_0
      14: aload_0
      15: getfield      #14                 // Field error:Lio/reactivex/rxjava3/internal/util/AtomicThrowable;
      18: invokestatic  #23                 // Method io/reactivex/rxjava3/internal/util/HalfSerializer.onError:(Lorg/reactivestreams/Subscriber;Ljava/lang/Throwable;Ljava/util/concurrent/atomic/AtomicInteger;Lio/reactivex/rxjava3/internal/util/AtomicThrowable;)V
      21: return

  public void onComplete();
    Code:
       0: aload_0
       1: getfield      #11                 // Field other:Lio/reactivex/rxjava3/internal/operators/flowable/FlowableSkipUntil$SkipUntilMainSubscriber$OtherSubscriber;
       4: invokestatic  #22                 // Method io/reactivex/rxjava3/internal/subscriptions/SubscriptionHelper.cancel:(Ljava/util/concurrent/atomic/AtomicReference;)Z
       7: pop
       8: aload_0
       9: getfield      #2                  // Field downstream:Lorg/reactivestreams/Subscriber;
      12: aload_0
      13: aload_0
      14: getfield      #14                 // Field error:Lio/reactivex/rxjava3/internal/util/AtomicThrowable;
      17: invokestatic  #24                 // Method io/reactivex/rxjava3/internal/util/HalfSerializer.onComplete:(Lorg/reactivestreams/Subscriber;Ljava/util/concurrent/atomic/AtomicInteger;Lio/reactivex/rxjava3/internal/util/AtomicThrowable;)V
      20: return

  public void request(long);
    Code:
       0: aload_0
       1: getfield      #5                  // Field upstream:Ljava/util/concurrent/atomic/AtomicReference;
       4: aload_0
       5: getfield      #8                  // Field requested:Ljava/util/concurrent/atomic/AtomicLong;
       8: lload_1
       9: invokestatic  #25                 // Method io/reactivex/rxjava3/internal/subscriptions/SubscriptionHelper.deferredRequest:(Ljava/util/concurrent/atomic/AtomicReference;Ljava/util/concurrent/atomic/AtomicLong;J)V
      12: return

  public void cancel();
    Code:
       0: aload_0
       1: getfield      #5                  // Field upstream:Ljava/util/concurrent/atomic/AtomicReference;
       4: invokestatic  #22                 // Method io/reactivex/rxjava3/internal/subscriptions/SubscriptionHelper.cancel:(Ljava/util/concurrent/atomic/AtomicReference;)Z
       7: pop
       8: aload_0
       9: getfield      #11                 // Field other:Lio/reactivex/rxjava3/internal/operators/flowable/FlowableSkipUntil$SkipUntilMainSubscriber$OtherSubscriber;
      12: invokestatic  #22                 // Method io/reactivex/rxjava3/internal/subscriptions/SubscriptionHelper.cancel:(Ljava/util/concurrent/atomic/AtomicReference;)Z
      15: pop
      16: return
}
