Compiled from "FlowableFromIterable.java"
public final class io.reactivex.rxjava3.internal.operators.flowable.FlowableFromIterable<T> extends io.reactivex.rxjava3.core.Flowable<T> {
  final java.lang.Iterable<? extends T> source;

  public io.reactivex.rxjava3.internal.operators.flowable.FlowableFromIterable(java.lang.Iterable<? extends T>);
    Code:
       0: aload_0
       1: invokespecial #1                  // Method io/reactivex/rxjava3/core/Flowable."<init>":()V
       4: aload_0
       5: aload_1
       6: putfield      #2                  // Field source:Ljava/lang/Iterable;
       9: return

  public void subscribeActual(org.reactivestreams.Subscriber<? super T>);
    Code:
       0: aload_0
       1: getfield      #2                  // Field source:Ljava/lang/Iterable;
       4: invokeinterface #3,  1            // InterfaceMethod java/lang/Iterable.iterator:()Ljava/util/Iterator;
       9: astore_2
      10: goto          24
      13: astore_3
      14: aload_3
      15: invokestatic  #5                  // Method io/reactivex/rxjava3/exceptions/Exceptions.throwIfFatal:(Ljava/lang/Throwable;)V
      18: aload_3
      19: aload_1
      20: invokestatic  #6                  // Method io/reactivex/rxjava3/internal/subscriptions/EmptySubscription.error:(Ljava/lang/Throwable;Lorg/reactivestreams/Subscriber;)V
      23: return
      24: aload_1
      25: aload_2
      26: invokestatic  #7                  // Method subscribe:(Lorg/reactivestreams/Subscriber;Ljava/util/Iterator;)V
      29: return
    Exception table:
       from    to  target type
           0    10    13   Class java/lang/Throwable

  public static <T> void subscribe(org.reactivestreams.Subscriber<? super T>, java.util.Iterator<? extends T>);
    Code:
       0: aload_1
       1: invokeinterface #8,  1            // InterfaceMethod java/util/Iterator.hasNext:()Z
       6: istore_2
       7: goto          21
      10: astore_3
      11: aload_3
      12: invokestatic  #5                  // Method io/reactivex/rxjava3/exceptions/Exceptions.throwIfFatal:(Ljava/lang/Throwable;)V
      15: aload_3
      16: aload_0
      17: invokestatic  #6                  // Method io/reactivex/rxjava3/internal/subscriptions/EmptySubscription.error:(Ljava/lang/Throwable;Lorg/reactivestreams/Subscriber;)V
      20: return
      21: iload_2
      22: ifne          30
      25: aload_0
      26: invokestatic  #9                  // Method io/reactivex/rxjava3/internal/subscriptions/EmptySubscription.complete:(Lorg/reactivestreams/Subscriber;)V
      29: return
      30: aload_0
      31: instanceof    #10                 // class io/reactivex/rxjava3/operators/ConditionalSubscriber
      34: ifeq          58
      37: aload_0
      38: new           #11                 // class io/reactivex/rxjava3/internal/operators/flowable/FlowableFromIterable$IteratorConditionalSubscription
      41: dup
      42: aload_0
      43: checkcast     #10                 // class io/reactivex/rxjava3/operators/ConditionalSubscriber
      46: aload_1
      47: invokespecial #12                 // Method io/reactivex/rxjava3/internal/operators/flowable/FlowableFromIterable$IteratorConditionalSubscription."<init>":(Lio/reactivex/rxjava3/operators/ConditionalSubscriber;Ljava/util/Iterator;)V
      50: invokeinterface #13,  2           // InterfaceMethod org/reactivestreams/Subscriber.onSubscribe:(Lorg/reactivestreams/Subscription;)V
      55: goto          73
      58: aload_0
      59: new           #14                 // class io/reactivex/rxjava3/internal/operators/flowable/FlowableFromIterable$IteratorSubscription
      62: dup
      63: aload_0
      64: aload_1
      65: invokespecial #15                 // Method io/reactivex/rxjava3/internal/operators/flowable/FlowableFromIterable$IteratorSubscription."<init>":(Lorg/reactivestreams/Subscriber;Ljava/util/Iterator;)V
      68: invokeinterface #13,  2           // InterfaceMethod org/reactivestreams/Subscriber.onSubscribe:(Lorg/reactivestreams/Subscription;)V
      73: return
    Exception table:
       from    to  target type
           0     7    10   Class java/lang/Throwable
}
