Compiled from "FlowableCreate.java"
public final class io.reactivex.rxjava3.internal.operators.flowable.FlowableCreate<T> extends io.reactivex.rxjava3.core.Flowable<T> {
  final io.reactivex.rxjava3.core.FlowableOnSubscribe<T> source;

  final io.reactivex.rxjava3.core.BackpressureStrategy backpressure;

  public io.reactivex.rxjava3.internal.operators.flowable.FlowableCreate(io.reactivex.rxjava3.core.FlowableOnSubscribe<T>, io.reactivex.rxjava3.core.BackpressureStrategy);
    Code:
       0: aload_0
       1: invokespecial #1                  // Method io/reactivex/rxjava3/core/Flowable."<init>":()V
       4: aload_0
       5: aload_1
       6: putfield      #2                  // Field source:Lio/reactivex/rxjava3/core/FlowableOnSubscribe;
       9: aload_0
      10: aload_2
      11: putfield      #3                  // Field backpressure:Lio/reactivex/rxjava3/core/BackpressureStrategy;
      14: return

  public void subscribeActual(org.reactivestreams.Subscriber<? super T>);
    Code:
       0: getstatic     #4                  // Field io/reactivex/rxjava3/internal/operators/flowable/FlowableCreate$1.$SwitchMap$io$reactivex$rxjava3$core$BackpressureStrategy:[I
       3: aload_0
       4: getfield      #3                  // Field backpressure:Lio/reactivex/rxjava3/core/BackpressureStrategy;
       7: invokevirtual #5                  // Method io/reactivex/rxjava3/core/BackpressureStrategy.ordinal:()I
      10: iaload
      11: tableswitch   { // 1 to 4
                     1: 40
                     2: 52
                     3: 64
                     4: 76
               default: 88
          }
      40: new           #6                  // class io/reactivex/rxjava3/internal/operators/flowable/FlowableCreate$MissingEmitter
      43: dup
      44: aload_1
      45: invokespecial #7                  // Method io/reactivex/rxjava3/internal/operators/flowable/FlowableCreate$MissingEmitter."<init>":(Lorg/reactivestreams/Subscriber;)V
      48: astore_2
      49: goto          100
      52: new           #8                  // class io/reactivex/rxjava3/internal/operators/flowable/FlowableCreate$ErrorAsyncEmitter
      55: dup
      56: aload_1
      57: invokespecial #9                  // Method io/reactivex/rxjava3/internal/operators/flowable/FlowableCreate$ErrorAsyncEmitter."<init>":(Lorg/reactivestreams/Subscriber;)V
      60: astore_2
      61: goto          100
      64: new           #10                 // class io/reactivex/rxjava3/internal/operators/flowable/FlowableCreate$DropAsyncEmitter
      67: dup
      68: aload_1
      69: invokespecial #11                 // Method io/reactivex/rxjava3/internal/operators/flowable/FlowableCreate$DropAsyncEmitter."<init>":(Lorg/reactivestreams/Subscriber;)V
      72: astore_2
      73: goto          100
      76: new           #12                 // class io/reactivex/rxjava3/internal/operators/flowable/FlowableCreate$LatestAsyncEmitter
      79: dup
      80: aload_1
      81: invokespecial #13                 // Method io/reactivex/rxjava3/internal/operators/flowable/FlowableCreate$LatestAsyncEmitter."<init>":(Lorg/reactivestreams/Subscriber;)V
      84: astore_2
      85: goto          100
      88: new           #14                 // class io/reactivex/rxjava3/internal/operators/flowable/FlowableCreate$BufferAsyncEmitter
      91: dup
      92: aload_1
      93: invokestatic  #15                 // Method bufferSize:()I
      96: invokespecial #16                 // Method io/reactivex/rxjava3/internal/operators/flowable/FlowableCreate$BufferAsyncEmitter."<init>":(Lorg/reactivestreams/Subscriber;I)V
      99: astore_2
     100: aload_1
     101: aload_2
     102: invokeinterface #17,  2           // InterfaceMethod org/reactivestreams/Subscriber.onSubscribe:(Lorg/reactivestreams/Subscription;)V
     107: aload_0
     108: getfield      #2                  // Field source:Lio/reactivex/rxjava3/core/FlowableOnSubscribe;
     111: aload_2
     112: invokeinterface #18,  2           // InterfaceMethod io/reactivex/rxjava3/core/FlowableOnSubscribe.subscribe:(Lio/reactivex/rxjava3/core/FlowableEmitter;)V
     117: goto          130
     120: astore_3
     121: aload_3
     122: invokestatic  #20                 // Method io/reactivex/rxjava3/exceptions/Exceptions.throwIfFatal:(Ljava/lang/Throwable;)V
     125: aload_2
     126: aload_3
     127: invokevirtual #21                 // Method io/reactivex/rxjava3/internal/operators/flowable/FlowableCreate$BaseEmitter.onError:(Ljava/lang/Throwable;)V
     130: return
    Exception table:
       from    to  target type
         107   117   120   Class java/lang/Throwable
}
