Compiled from "FlowableReplay.java"
final class io.reactivex.rxjava3.internal.operators.flowable.FlowableReplay$ScheduledReplayBufferSupplier<T> implements io.reactivex.rxjava3.functions.Supplier<io.reactivex.rxjava3.internal.operators.flowable.FlowableReplay$ReplayBuffer<T>> {
  private final int bufferSize;

  private final long maxAge;

  private final java.util.concurrent.TimeUnit unit;

  private final io.reactivex.rxjava3.core.Scheduler scheduler;

  final boolean eagerTruncate;

  io.reactivex.rxjava3.internal.operators.flowable.FlowableReplay$ScheduledReplayBufferSupplier(int, long, java.util.concurrent.TimeUnit, io.reactivex.rxjava3.core.Scheduler, boolean);
    Code:
       0: aload_0
       1: invokespecial #1                  // Method java/lang/Object."<init>":()V
       4: aload_0
       5: iload_1
       6: putfield      #2                  // Field bufferSize:I
       9: aload_0
      10: lload_2
      11: putfield      #3                  // Field maxAge:J
      14: aload_0
      15: aload         4
      17: putfield      #4                  // Field unit:Ljava/util/concurrent/TimeUnit;
      20: aload_0
      21: aload         5
      23: putfield      #5                  // Field scheduler:Lio/reactivex/rxjava3/core/Scheduler;
      26: aload_0
      27: iload         6
      29: putfield      #6                  // Field eagerTruncate:Z
      32: return

  public io.reactivex.rxjava3.internal.operators.flowable.FlowableReplay$ReplayBuffer<T> get();
    Code:
       0: new           #7                  // class io/reactivex/rxjava3/internal/operators/flowable/FlowableReplay$SizeAndTimeBoundReplayBuffer
       3: dup
       4: aload_0
       5: getfield      #2                  // Field bufferSize:I
       8: aload_0
       9: getfield      #3                  // Field maxAge:J
      12: aload_0
      13: getfield      #4                  // Field unit:Ljava/util/concurrent/TimeUnit;
      16: aload_0
      17: getfield      #5                  // Field scheduler:Lio/reactivex/rxjava3/core/Scheduler;
      20: aload_0
      21: getfield      #6                  // Field eagerTruncate:Z
      24: invokespecial #8                  // Method io/reactivex/rxjava3/internal/operators/flowable/FlowableReplay$SizeAndTimeBoundReplayBuffer."<init>":(IJLjava/util/concurrent/TimeUnit;Lio/reactivex/rxjava3/core/Scheduler;Z)V
      27: areturn

  public java.lang.Object get() throws java.lang.Throwable;
    Code:
       0: aload_0
       1: invokevirtual #9                  // Method get:()Lio/reactivex/rxjava3/internal/operators/flowable/FlowableReplay$ReplayBuffer;
       4: areturn
}
