Compiled from "FlowableDelaySubscriptionOther.java"
public final class io.reactivex.rxjava3.internal.operators.flowable.FlowableDelaySubscriptionOther<T, U> extends io.reactivex.rxjava3.core.Flowable<T> {
  final org.reactivestreams.Publisher<? extends T> main;

  final org.reactivestreams.Publisher<U> other;

  public io.reactivex.rxjava3.internal.operators.flowable.FlowableDelaySubscriptionOther(org.reactivestreams.Publisher<? extends T>, org.reactivestreams.Publisher<U>);
    Code:
       0: aload_0
       1: invokespecial #1                  // Method io/reactivex/rxjava3/core/Flowable."<init>":()V
       4: aload_0
       5: aload_1
       6: putfield      #2                  // Field main:Lorg/reactivestreams/Publisher;
       9: aload_0
      10: aload_2
      11: putfield      #3                  // Field other:Lorg/reactivestreams/Publisher;
      14: return

  public void subscribeActual(org.reactivestreams.Subscriber<? super T>);
    Code:
       0: new           #4                  // class io/reactivex/rxjava3/internal/operators/flowable/FlowableDelaySubscriptionOther$MainSubscriber
       3: dup
       4: aload_1
       5: aload_0
       6: getfield      #2                  // Field main:Lorg/reactivestreams/Publisher;
       9: invokespecial #5                  // Method io/reactivex/rxjava3/internal/operators/flowable/FlowableDelaySubscriptionOther$MainSubscriber."<init>":(Lorg/reactivestreams/Subscriber;Lorg/reactivestreams/Publisher;)V
      12: astore_2
      13: aload_1
      14: aload_2
      15: invokeinterface #6,  2            // InterfaceMethod org/reactivestreams/Subscriber.onSubscribe:(Lorg/reactivestreams/Subscription;)V
      20: aload_0
      21: getfield      #3                  // Field other:Lorg/reactivestreams/Publisher;
      24: aload_2
      25: getfield      #7                  // Field io/reactivex/rxjava3/internal/operators/flowable/FlowableDelaySubscriptionOther$MainSubscriber.other:Lio/reactivex/rxjava3/internal/operators/flowable/FlowableDelaySubscriptionOther$MainSubscriber$OtherSubscriber;
      28: invokeinterface #8,  2            // InterfaceMethod org/reactivestreams/Publisher.subscribe:(Lorg/reactivestreams/Subscriber;)V
      33: return
}
