Compiled from "FlowablePublishMulticast.java"
public final class io.reactivex.rxjava3.internal.operators.flowable.FlowablePublishMulticast<T, R> extends io.reactivex.rxjava3.internal.operators.flowable.AbstractFlowableWithUpstream<T, R> {
  final io.reactivex.rxjava3.functions.Function<? super io.reactivex.rxjava3.core.Flowable<T>, ? extends org.reactivestreams.Publisher<? extends R>> selector;

  final int prefetch;

  final boolean delayError;

  public io.reactivex.rxjava3.internal.operators.flowable.FlowablePublishMulticast(io.reactivex.rxjava3.core.Flowable<T>, io.reactivex.rxjava3.functions.Function<? super io.reactivex.rxjava3.core.Flowable<T>, ? extends org.reactivestreams.Publisher<? extends R>>, int, boolean);
    Code:
       0: aload_0
       1: aload_1
       2: invokespecial #1                  // Method io/reactivex/rxjava3/internal/operators/flowable/AbstractFlowableWithUpstream."<init>":(Lio/reactivex/rxjava3/core/Flowable;)V
       5: aload_0
       6: aload_2
       7: putfield      #2                  // Field selector:Lio/reactivex/rxjava3/functions/Function;
      10: aload_0
      11: iload_3
      12: putfield      #3                  // Field prefetch:I
      15: aload_0
      16: iload         4
      18: putfield      #4                  // Field delayError:Z
      21: return

  protected void subscribeActual(org.reactivestreams.Subscriber<? super R>);
    Code:
       0: new           #5                  // class io/reactivex/rxjava3/internal/operators/flowable/FlowablePublishMulticast$MulticastProcessor
       3: dup
       4: aload_0
       5: getfield      #3                  // Field prefetch:I
       8: aload_0
       9: getfield      #4                  // Field delayError:Z
      12: invokespecial #6                  // Method io/reactivex/rxjava3/internal/operators/flowable/FlowablePublishMulticast$MulticastProcessor."<init>":(IZ)V
      15: astore_2
      16: aload_0
      17: getfield      #2                  // Field selector:Lio/reactivex/rxjava3/functions/Function;
      20: aload_2
      21: invokeinterface #7,  2            // InterfaceMethod io/reactivex/rxjava3/functions/Function.apply:(Ljava/lang/Object;)Ljava/lang/Object;
      26: ldc           #8                  // String selector returned a null Publisher
      28: invokestatic  #9                  // Method java/util/Objects.requireNonNull:(Ljava/lang/Object;Ljava/lang/String;)Ljava/lang/Object;
      31: checkcast     #10                 // class org/reactivestreams/Publisher
      34: astore_3
      35: goto          52
      38: astore        4
      40: aload         4
      42: invokestatic  #12                 // Method io/reactivex/rxjava3/exceptions/Exceptions.throwIfFatal:(Ljava/lang/Throwable;)V
      45: aload         4
      47: aload_1
      48: invokestatic  #13                 // Method io/reactivex/rxjava3/internal/subscriptions/EmptySubscription.error:(Ljava/lang/Throwable;Lorg/reactivestreams/Subscriber;)V
      51: return
      52: new           #14                 // class io/reactivex/rxjava3/internal/operators/flowable/FlowablePublishMulticast$OutputCanceller
      55: dup
      56: aload_1
      57: aload_2
      58: invokespecial #15                 // Method io/reactivex/rxjava3/internal/operators/flowable/FlowablePublishMulticast$OutputCanceller."<init>":(Lorg/reactivestreams/Subscriber;Lio/reactivex/rxjava3/internal/operators/flowable/FlowablePublishMulticast$MulticastProcessor;)V
      61: astore        4
      63: aload_3
      64: aload         4
      66: invokeinterface #16,  2           // InterfaceMethod org/reactivestreams/Publisher.subscribe:(Lorg/reactivestreams/Subscriber;)V
      71: aload_0
      72: getfield      #17                 // Field source:Lio/reactivex/rxjava3/core/Flowable;
      75: aload_2
      76: invokevirtual #18                 // Method io/reactivex/rxjava3/core/Flowable.subscribe:(Lio/reactivex/rxjava3/core/FlowableSubscriber;)V
      79: return
    Exception table:
       from    to  target type
          16    35    38   Class java/lang/Throwable
}
