Compiled from "FlowableTake.java"
final class io.reactivex.rxjava3.internal.operators.flowable.FlowableTake$TakeSubscriber<T> extends java.util.concurrent.atomic.AtomicLong implements io.reactivex.rxjava3.core.FlowableSubscriber<T>, org.reactivestreams.Subscription {
  private static final long serialVersionUID;

  final org.reactivestreams.Subscriber<? super T> downstream;

  long remaining;

  org.reactivestreams.Subscription upstream;

  io.reactivex.rxjava3.internal.operators.flowable.FlowableTake$TakeSubscriber(org.reactivestreams.Subscriber<? super T>, long);
    Code:
       0: aload_0
       1: invokespecial #1                  // Method java/util/concurrent/atomic/AtomicLong."<init>":()V
       4: aload_0
       5: aload_1
       6: putfield      #2                  // Field downstream:Lorg/reactivestreams/Subscriber;
       9: aload_0
      10: lload_2
      11: putfield      #3                  // Field remaining:J
      14: aload_0
      15: lload_2
      16: invokevirtual #4                  // Method lazySet:(J)V
      19: return

  public void onSubscribe(org.reactivestreams.Subscription);
    Code:
       0: aload_0
       1: getfield      #5                  // Field upstream:Lorg/reactivestreams/Subscription;
       4: aload_1
       5: invokestatic  #6                  // Method io/reactivex/rxjava3/internal/subscriptions/SubscriptionHelper.validate:(Lorg/reactivestreams/Subscription;Lorg/reactivestreams/Subscription;)Z
       8: ifeq          51
      11: aload_0
      12: getfield      #3                  // Field remaining:J
      15: lconst_0
      16: lcmp
      17: ifne          36
      20: aload_1
      21: invokeinterface #7,  1            // InterfaceMethod org/reactivestreams/Subscription.cancel:()V
      26: aload_0
      27: getfield      #2                  // Field downstream:Lorg/reactivestreams/Subscriber;
      30: invokestatic  #8                  // Method io/reactivex/rxjava3/internal/subscriptions/EmptySubscription.complete:(Lorg/reactivestreams/Subscriber;)V
      33: goto          51
      36: aload_0
      37: aload_1
      38: putfield      #5                  // Field upstream:Lorg/reactivestreams/Subscription;
      41: aload_0
      42: getfield      #2                  // Field downstream:Lorg/reactivestreams/Subscriber;
      45: aload_0
      46: invokeinterface #9,  2            // InterfaceMethod org/reactivestreams/Subscriber.onSubscribe:(Lorg/reactivestreams/Subscription;)V
      51: return

  public void onNext(T);
    Code:
       0: aload_0
       1: getfield      #3                  // Field remaining:J
       4: lstore_2
       5: lload_2
       6: lconst_0
       7: lcmp
       8: ifle          54
      11: aload_0
      12: lload_2
      13: lconst_1
      14: lsub
      15: dup2
      16: lstore_2
      17: putfield      #3                  // Field remaining:J
      20: aload_0
      21: getfield      #2                  // Field downstream:Lorg/reactivestreams/Subscriber;
      24: aload_1
      25: invokeinterface #10,  2           // InterfaceMethod org/reactivestreams/Subscriber.onNext:(Ljava/lang/Object;)V
      30: lload_2
      31: lconst_0
      32: lcmp
      33: ifne          54
      36: aload_0
      37: getfield      #5                  // Field upstream:Lorg/reactivestreams/Subscription;
      40: invokeinterface #7,  1            // InterfaceMethod org/reactivestreams/Subscription.cancel:()V
      45: aload_0
      46: getfield      #2                  // Field downstream:Lorg/reactivestreams/Subscriber;
      49: invokeinterface #11,  1           // InterfaceMethod org/reactivestreams/Subscriber.onComplete:()V
      54: return

  public void onError(java.lang.Throwable);
    Code:
       0: aload_0
       1: getfield      #3                  // Field remaining:J
       4: lconst_0
       5: lcmp
       6: ifle          27
       9: aload_0
      10: lconst_0
      11: putfield      #3                  // Field remaining:J
      14: aload_0
      15: getfield      #2                  // Field downstream:Lorg/reactivestreams/Subscriber;
      18: aload_1
      19: invokeinterface #12,  2           // InterfaceMethod org/reactivestreams/Subscriber.onError:(Ljava/lang/Throwable;)V
      24: goto          31
      27: aload_1
      28: invokestatic  #13                 // Method io/reactivex/rxjava3/plugins/RxJavaPlugins.onError:(Ljava/lang/Throwable;)V
      31: return

  public void onComplete();
    Code:
       0: aload_0
       1: getfield      #3                  // Field remaining:J
       4: lconst_0
       5: lcmp
       6: ifle          23
       9: aload_0
      10: lconst_0
      11: putfield      #3                  // Field remaining:J
      14: aload_0
      15: getfield      #2                  // Field downstream:Lorg/reactivestreams/Subscriber;
      18: invokeinterface #11,  1           // InterfaceMethod org/reactivestreams/Subscriber.onComplete:()V
      23: return

  public void request(long);
    Code:
       0: lload_1
       1: invokestatic  #14                 // Method io/reactivex/rxjava3/internal/subscriptions/SubscriptionHelper.validate:(J)Z
       4: ifeq          61
       7: aload_0
       8: invokevirtual #15                 // Method get:()J
      11: lstore_3
      12: lload_3
      13: lconst_0
      14: lcmp
      15: ifne          21
      18: goto          61
      21: lload_3
      22: lload_1
      23: invokestatic  #16                 // Method java/lang/Math.min:(JJ)J
      26: lstore        5
      28: lload_3
      29: lload         5
      31: lsub
      32: lstore        7
      34: aload_0
      35: lload_3
      36: lload         7
      38: invokevirtual #17                 // Method compareAndSet:(JJ)Z
      41: ifeq          58
      44: aload_0
      45: getfield      #5                  // Field upstream:Lorg/reactivestreams/Subscription;
      48: lload         5
      50: invokeinterface #18,  3           // InterfaceMethod org/reactivestreams/Subscription.request:(J)V
      55: goto          61
      58: goto          7
      61: return

  public void cancel();
    Code:
       0: aload_0
       1: getfield      #5                  // Field upstream:Lorg/reactivestreams/Subscription;
       4: invokeinterface #7,  1            // InterfaceMethod org/reactivestreams/Subscription.cancel:()V
       9: return
}
