Compiled from "FlowableWindowTimed.java"
abstract class io.reactivex.rxjava3.internal.operators.flowable.FlowableWindowTimed$AbstractWindowSubscriber<T> extends java.util.concurrent.atomic.AtomicInteger implements io.reactivex.rxjava3.core.FlowableSubscriber<T>, org.reactivestreams.Subscription {
  private static final long serialVersionUID;

  final org.reactivestreams.Subscriber<? super io.reactivex.rxjava3.core.Flowable<T>> downstream;

  final io.reactivex.rxjava3.operators.SimplePlainQueue<java.lang.Object> queue;

  final long timespan;

  final java.util.concurrent.TimeUnit unit;

  final int bufferSize;

  final java.util.concurrent.atomic.AtomicLong requested;

  long emitted;

  volatile boolean done;

  java.lang.Throwable error;

  org.reactivestreams.Subscription upstream;

  final java.util.concurrent.atomic.AtomicBoolean downstreamCancelled;

  volatile boolean upstreamCancelled;

  final java.util.concurrent.atomic.AtomicInteger windowCount;

  io.reactivex.rxjava3.internal.operators.flowable.FlowableWindowTimed$AbstractWindowSubscriber(org.reactivestreams.Subscriber<? super io.reactivex.rxjava3.core.Flowable<T>>, long, java.util.concurrent.TimeUnit, int);
    Code:
       0: aload_0
       1: invokespecial #1                  // Method java/util/concurrent/atomic/AtomicInteger."<init>":()V
       4: aload_0
       5: aload_1
       6: putfield      #2                  // Field downstream:Lorg/reactivestreams/Subscriber;
       9: aload_0
      10: new           #3                  // class io/reactivex/rxjava3/internal/queue/MpscLinkedQueue
      13: dup
      14: invokespecial #4                  // Method io/reactivex/rxjava3/internal/queue/MpscLinkedQueue."<init>":()V
      17: putfield      #5                  // Field queue:Lio/reactivex/rxjava3/operators/SimplePlainQueue;
      20: aload_0
      21: lload_2
      22: putfield      #6                  // Field timespan:J
      25: aload_0
      26: aload         4
      28: putfield      #7                  // Field unit:Ljava/util/concurrent/TimeUnit;
      31: aload_0
      32: iload         5
      34: putfield      #8                  // Field bufferSize:I
      37: aload_0
      38: new           #9                  // class java/util/concurrent/atomic/AtomicLong
      41: dup
      42: invokespecial #10                 // Method java/util/concurrent/atomic/AtomicLong."<init>":()V
      45: putfield      #11                 // Field requested:Ljava/util/concurrent/atomic/AtomicLong;
      48: aload_0
      49: new           #12                 // class java/util/concurrent/atomic/AtomicBoolean
      52: dup
      53: invokespecial #13                 // Method java/util/concurrent/atomic/AtomicBoolean."<init>":()V
      56: putfield      #14                 // Field downstreamCancelled:Ljava/util/concurrent/atomic/AtomicBoolean;
      59: aload_0
      60: new           #15                 // class java/util/concurrent/atomic/AtomicInteger
      63: dup
      64: iconst_1
      65: invokespecial #16                 // Method java/util/concurrent/atomic/AtomicInteger."<init>":(I)V
      68: putfield      #17                 // Field windowCount:Ljava/util/concurrent/atomic/AtomicInteger;
      71: return

  public final void onSubscribe(org.reactivestreams.Subscription);
    Code:
       0: aload_0
       1: getfield      #18                 // Field upstream:Lorg/reactivestreams/Subscription;
       4: aload_1
       5: invokestatic  #19                 // Method io/reactivex/rxjava3/internal/subscriptions/SubscriptionHelper.validate:(Lorg/reactivestreams/Subscription;Lorg/reactivestreams/Subscription;)Z
       8: ifeq          30
      11: aload_0
      12: aload_1
      13: putfield      #18                 // Field upstream:Lorg/reactivestreams/Subscription;
      16: aload_0
      17: getfield      #2                  // Field downstream:Lorg/reactivestreams/Subscriber;
      20: aload_0
      21: invokeinterface #20,  2           // InterfaceMethod org/reactivestreams/Subscriber.onSubscribe:(Lorg/reactivestreams/Subscription;)V
      26: aload_0
      27: invokevirtual #21                 // Method createFirstWindow:()V
      30: return

  abstract void createFirstWindow();

  public final void onNext(T);
    Code:
       0: aload_0
       1: getfield      #5                  // Field queue:Lio/reactivex/rxjava3/operators/SimplePlainQueue;
       4: aload_1
       5: invokeinterface #22,  2           // InterfaceMethod io/reactivex/rxjava3/operators/SimplePlainQueue.offer:(Ljava/lang/Object;)Z
      10: pop
      11: aload_0
      12: invokevirtual #23                 // Method drain:()V
      15: return

  public final void onError(java.lang.Throwable);
    Code:
       0: aload_0
       1: aload_1
       2: putfield      #24                 // Field error:Ljava/lang/Throwable;
       5: aload_0
       6: iconst_1
       7: putfield      #25                 // Field done:Z
      10: aload_0
      11: invokevirtual #23                 // Method drain:()V
      14: return

  public final void onComplete();
    Code:
       0: aload_0
       1: iconst_1
       2: putfield      #25                 // Field done:Z
       5: aload_0
       6: invokevirtual #23                 // Method drain:()V
       9: return

  public final void request(long);
    Code:
       0: lload_1
       1: invokestatic  #26                 // Method io/reactivex/rxjava3/internal/subscriptions/SubscriptionHelper.validate:(J)Z
       4: ifeq          16
       7: aload_0
       8: getfield      #11                 // Field requested:Ljava/util/concurrent/atomic/AtomicLong;
      11: lload_1
      12: invokestatic  #27                 // Method io/reactivex/rxjava3/internal/util/BackpressureHelper.add:(Ljava/util/concurrent/atomic/AtomicLong;J)J
      15: pop2
      16: return

  public final void cancel();
    Code:
       0: aload_0
       1: getfield      #14                 // Field downstreamCancelled:Ljava/util/concurrent/atomic/AtomicBoolean;
       4: iconst_0
       5: iconst_1
       6: invokevirtual #28                 // Method java/util/concurrent/atomic/AtomicBoolean.compareAndSet:(ZZ)Z
       9: ifeq          16
      12: aload_0
      13: invokevirtual #29                 // Method windowDone:()V
      16: return

  final void windowDone();
    Code:
       0: aload_0
       1: getfield      #17                 // Field windowCount:Ljava/util/concurrent/atomic/AtomicInteger;
       4: invokevirtual #30                 // Method java/util/concurrent/atomic/AtomicInteger.decrementAndGet:()I
       7: ifne          32
      10: aload_0
      11: invokevirtual #31                 // Method cleanupResources:()V
      14: aload_0
      15: getfield      #18                 // Field upstream:Lorg/reactivestreams/Subscription;
      18: invokeinterface #32,  1           // InterfaceMethod org/reactivestreams/Subscription.cancel:()V
      23: aload_0
      24: iconst_1
      25: putfield      #33                 // Field upstreamCancelled:Z
      28: aload_0
      29: invokevirtual #23                 // Method drain:()V
      32: return

  abstract void cleanupResources();

  abstract void drain();
}
