Compiled from "FlowableFromSupplier.java"
public final class io.reactivex.rxjava3.internal.operators.flowable.FlowableFromSupplier<T> extends io.reactivex.rxjava3.core.Flowable<T> implements io.reactivex.rxjava3.functions.Supplier<T> {
  final io.reactivex.rxjava3.functions.Supplier<? extends T> supplier;

  public io.reactivex.rxjava3.internal.operators.flowable.FlowableFromSupplier(io.reactivex.rxjava3.functions.Supplier<? extends T>);
    Code:
       0: aload_0
       1: invokespecial #1                  // Method io/reactivex/rxjava3/core/Flowable."<init>":()V
       4: aload_0
       5: aload_1
       6: putfield      #2                  // Field supplier:Lio/reactivex/rxjava3/functions/Supplier;
       9: return

  public void subscribeActual(org.reactivestreams.Subscriber<? super T>);
    Code:
       0: new           #3                  // class io/reactivex/rxjava3/internal/subscriptions/DeferredScalarSubscription
       3: dup
       4: aload_1
       5: invokespecial #4                  // Method io/reactivex/rxjava3/internal/subscriptions/DeferredScalarSubscription."<init>":(Lorg/reactivestreams/Subscriber;)V
       8: astore_2
       9: aload_1
      10: aload_2
      11: invokeinterface #5,  2            // InterfaceMethod org/reactivestreams/Subscriber.onSubscribe:(Lorg/reactivestreams/Subscription;)V
      16: aload_0
      17: getfield      #2                  // Field supplier:Lio/reactivex/rxjava3/functions/Supplier;
      20: invokeinterface #6,  1            // InterfaceMethod io/reactivex/rxjava3/functions/Supplier.get:()Ljava/lang/Object;
      25: ldc           #7                  // String The supplier returned a null value
      27: invokestatic  #8                  // Method java/util/Objects.requireNonNull:(Ljava/lang/Object;Ljava/lang/String;)Ljava/lang/Object;
      30: astore_3
      31: goto          65
      34: astore        4
      36: aload         4
      38: invokestatic  #10                 // Method io/reactivex/rxjava3/exceptions/Exceptions.throwIfFatal:(Ljava/lang/Throwable;)V
      41: aload_2
      42: invokevirtual #11                 // Method io/reactivex/rxjava3/internal/subscriptions/DeferredScalarSubscription.isCancelled:()Z
      45: ifeq          56
      48: aload         4
      50: invokestatic  #12                 // Method io/reactivex/rxjava3/plugins/RxJavaPlugins.onError:(Ljava/lang/Throwable;)V
      53: goto          64
      56: aload_1
      57: aload         4
      59: invokeinterface #13,  2           // InterfaceMethod org/reactivestreams/Subscriber.onError:(Ljava/lang/Throwable;)V
      64: return
      65: aload_2
      66: aload_3
      67: invokevirtual #14                 // Method io/reactivex/rxjava3/internal/subscriptions/DeferredScalarSubscription.complete:(Ljava/lang/Object;)V
      70: return
    Exception table:
       from    to  target type
          16    31    34   Class java/lang/Throwable

  public T get() throws java.lang.Throwable;
    Code:
       0: aload_0
       1: getfield      #2                  // Field supplier:Lio/reactivex/rxjava3/functions/Supplier;
       4: invokeinterface #6,  1            // InterfaceMethod io/reactivex/rxjava3/functions/Supplier.get:()Ljava/lang/Object;
       9: ldc           #7                  // String The supplier returned a null value
      11: invokestatic  #8                  // Method java/util/Objects.requireNonNull:(Ljava/lang/Object;Ljava/lang/String;)Ljava/lang/Object;
      14: areturn
}
