Compiled from "FlowableBlockingSubscribe.java"
public final class io.reactivex.rxjava3.internal.operators.flowable.FlowableBlockingSubscribe {
  private io.reactivex.rxjava3.internal.operators.flowable.FlowableBlockingSubscribe();
    Code:
       0: aload_0
       1: invokespecial #1                  // Method java/lang/Object."<init>":()V
       4: new           #2                  // class java/lang/IllegalStateException
       7: dup
       8: ldc           #3                  // String No instances!
      10: invokespecial #4                  // Method java/lang/IllegalStateException."<init>":(Ljava/lang/String;)V
      13: athrow

  public static <T> void subscribe(org.reactivestreams.Publisher<? extends T>, org.reactivestreams.Subscriber<? super T>);
    Code:
       0: new           #5                  // class java/util/concurrent/LinkedBlockingQueue
       3: dup
       4: invokespecial #6                  // Method java/util/concurrent/LinkedBlockingQueue."<init>":()V
       7: astore_2
       8: new           #7                  // class io/reactivex/rxjava3/internal/subscribers/BlockingSubscriber
      11: dup
      12: aload_2
      13: invokespecial #8                  // Method io/reactivex/rxjava3/internal/subscribers/BlockingSubscriber."<init>":(Ljava/util/Queue;)V
      16: astore_3
      17: aload_0
      18: aload_3
      19: invokeinterface #9,  2            // InterfaceMethod org/reactivestreams/Publisher.subscribe:(Lorg/reactivestreams/Subscriber;)V
      24: aload_3
      25: invokevirtual #10                 // Method io/reactivex/rxjava3/internal/subscribers/BlockingSubscriber.isCancelled:()Z
      28: ifeq          34
      31: goto          101
      34: aload_2
      35: invokeinterface #11,  1           // InterfaceMethod java/util/concurrent/BlockingQueue.poll:()Ljava/lang/Object;
      40: astore        4
      42: aload         4
      44: ifnonnull     68
      47: aload_3
      48: invokevirtual #10                 // Method io/reactivex/rxjava3/internal/subscribers/BlockingSubscriber.isCancelled:()Z
      51: ifeq          57
      54: goto          101
      57: invokestatic  #12                 // Method io/reactivex/rxjava3/internal/util/BlockingHelper.verifyNonBlocking:()V
      60: aload_2
      61: invokeinterface #13,  1           // InterfaceMethod java/util/concurrent/BlockingQueue.take:()Ljava/lang/Object;
      66: astore        4
      68: aload_3
      69: invokevirtual #10                 // Method io/reactivex/rxjava3/internal/subscribers/BlockingSubscriber.isCancelled:()Z
      72: ifeq          78
      75: goto          101
      78: aload         4
      80: getstatic     #14                 // Field io/reactivex/rxjava3/internal/subscribers/BlockingSubscriber.TERMINATED:Ljava/lang/Object;
      83: if_acmpeq     101
      86: aload         4
      88: aload_1
      89: invokestatic  #15                 // Method io/reactivex/rxjava3/internal/util/NotificationLite.acceptFull:(Ljava/lang/Object;Lorg/reactivestreams/Subscriber;)Z
      92: ifeq          98
      95: goto          101
      98: goto          24
     101: goto          118
     104: astore        4
     106: aload_3
     107: invokevirtual #17                 // Method io/reactivex/rxjava3/internal/subscribers/BlockingSubscriber.cancel:()V
     110: aload_1
     111: aload         4
     113: invokeinterface #18,  2           // InterfaceMethod org/reactivestreams/Subscriber.onError:(Ljava/lang/Throwable;)V
     118: return
    Exception table:
       from    to  target type
          24   101   104   Class java/lang/InterruptedException

  public static <T> void subscribe(org.reactivestreams.Publisher<? extends T>);
    Code:
       0: new           #19                 // class io/reactivex/rxjava3/internal/util/BlockingIgnoringReceiver
       3: dup
       4: invokespecial #20                 // Method io/reactivex/rxjava3/internal/util/BlockingIgnoringReceiver."<init>":()V
       7: astore_1
       8: new           #21                 // class io/reactivex/rxjava3/internal/subscribers/LambdaSubscriber
      11: dup
      12: invokestatic  #22                 // Method io/reactivex/rxjava3/internal/functions/Functions.emptyConsumer:()Lio/reactivex/rxjava3/functions/Consumer;
      15: aload_1
      16: aload_1
      17: getstatic     #23                 // Field io/reactivex/rxjava3/internal/functions/Functions.REQUEST_MAX:Lio/reactivex/rxjava3/functions/Consumer;
      20: invokespecial #24                 // Method io/reactivex/rxjava3/internal/subscribers/LambdaSubscriber."<init>":(Lio/reactivex/rxjava3/functions/Consumer;Lio/reactivex/rxjava3/functions/Consumer;Lio/reactivex/rxjava3/functions/Action;Lio/reactivex/rxjava3/functions/Consumer;)V
      23: astore_2
      24: aload_0
      25: aload_2
      26: invokeinterface #9,  2            // InterfaceMethod org/reactivestreams/Publisher.subscribe:(Lorg/reactivestreams/Subscriber;)V
      31: aload_1
      32: aload_2
      33: invokestatic  #25                 // Method io/reactivex/rxjava3/internal/util/BlockingHelper.awaitForComplete:(Ljava/util/concurrent/CountDownLatch;Lio/reactivex/rxjava3/disposables/Disposable;)V
      36: aload_1
      37: getfield      #26                 // Field io/reactivex/rxjava3/internal/util/BlockingIgnoringReceiver.error:Ljava/lang/Throwable;
      40: astore_3
      41: aload_3
      42: ifnull        50
      45: aload_3
      46: invokestatic  #27                 // Method io/reactivex/rxjava3/internal/util/ExceptionHelper.wrapOrThrow:(Ljava/lang/Throwable;)Ljava/lang/RuntimeException;
      49: athrow
      50: return

  public static <T> void subscribe(org.reactivestreams.Publisher<? extends T>, io.reactivex.rxjava3.functions.Consumer<? super T>, io.reactivex.rxjava3.functions.Consumer<? super java.lang.Throwable>, io.reactivex.rxjava3.functions.Action);
    Code:
       0: aload_1
       1: ldc           #28                 // String onNext is null
       3: invokestatic  #29                 // Method java/util/Objects.requireNonNull:(Ljava/lang/Object;Ljava/lang/String;)Ljava/lang/Object;
       6: pop
       7: aload_2
       8: ldc           #30                 // String onError is null
      10: invokestatic  #29                 // Method java/util/Objects.requireNonNull:(Ljava/lang/Object;Ljava/lang/String;)Ljava/lang/Object;
      13: pop
      14: aload_3
      15: ldc           #31                 // String onComplete is null
      17: invokestatic  #29                 // Method java/util/Objects.requireNonNull:(Ljava/lang/Object;Ljava/lang/String;)Ljava/lang/Object;
      20: pop
      21: aload_0
      22: new           #21                 // class io/reactivex/rxjava3/internal/subscribers/LambdaSubscriber
      25: dup
      26: aload_1
      27: aload_2
      28: aload_3
      29: getstatic     #23                 // Field io/reactivex/rxjava3/internal/functions/Functions.REQUEST_MAX:Lio/reactivex/rxjava3/functions/Consumer;
      32: invokespecial #24                 // Method io/reactivex/rxjava3/internal/subscribers/LambdaSubscriber."<init>":(Lio/reactivex/rxjava3/functions/Consumer;Lio/reactivex/rxjava3/functions/Consumer;Lio/reactivex/rxjava3/functions/Action;Lio/reactivex/rxjava3/functions/Consumer;)V
      35: invokestatic  #32                 // Method subscribe:(Lorg/reactivestreams/Publisher;Lorg/reactivestreams/Subscriber;)V
      38: return

  public static <T> void subscribe(org.reactivestreams.Publisher<? extends T>, io.reactivex.rxjava3.functions.Consumer<? super T>, io.reactivex.rxjava3.functions.Consumer<? super java.lang.Throwable>, io.reactivex.rxjava3.functions.Action, int);
    Code:
       0: aload_1
       1: ldc           #28                 // String onNext is null
       3: invokestatic  #29                 // Method java/util/Objects.requireNonNull:(Ljava/lang/Object;Ljava/lang/String;)Ljava/lang/Object;
       6: pop
       7: aload_2
       8: ldc           #30                 // String onError is null
      10: invokestatic  #29                 // Method java/util/Objects.requireNonNull:(Ljava/lang/Object;Ljava/lang/String;)Ljava/lang/Object;
      13: pop
      14: aload_3
      15: ldc           #31                 // String onComplete is null
      17: invokestatic  #29                 // Method java/util/Objects.requireNonNull:(Ljava/lang/Object;Ljava/lang/String;)Ljava/lang/Object;
      20: pop
      21: iload         4
      23: ldc           #33                 // String number > 0 required
      25: invokestatic  #34                 // Method io/reactivex/rxjava3/internal/functions/ObjectHelper.verifyPositive:(ILjava/lang/String;)I
      28: pop
      29: aload_0
      30: new           #35                 // class io/reactivex/rxjava3/internal/subscribers/BoundedSubscriber
      33: dup
      34: aload_1
      35: aload_2
      36: aload_3
      37: iload         4
      39: invokestatic  #36                 // Method io/reactivex/rxjava3/internal/functions/Functions.boundedConsumer:(I)Lio/reactivex/rxjava3/functions/Consumer;
      42: iload         4
      44: invokespecial #37                 // Method io/reactivex/rxjava3/internal/subscribers/BoundedSubscriber."<init>":(Lio/reactivex/rxjava3/functions/Consumer;Lio/reactivex/rxjava3/functions/Consumer;Lio/reactivex/rxjava3/functions/Action;Lio/reactivex/rxjava3/functions/Consumer;I)V
      47: invokestatic  #32                 // Method subscribe:(Lorg/reactivestreams/Publisher;Lorg/reactivestreams/Subscriber;)V
      50: return
}
