Compiled from "FlowableDoOnEach.java"
final class io.reactivex.rxjava3.internal.operators.flowable.FlowableDoOnEach$DoOnEachSubscriber<T> extends io.reactivex.rxjava3.internal.subscribers.BasicFuseableSubscriber<T, T> {
  final io.reactivex.rxjava3.functions.Consumer<? super T> onNext;

  final io.reactivex.rxjava3.functions.Consumer<? super java.lang.Throwable> onError;

  final io.reactivex.rxjava3.functions.Action onComplete;

  final io.reactivex.rxjava3.functions.Action onAfterTerminate;

  io.reactivex.rxjava3.internal.operators.flowable.FlowableDoOnEach$DoOnEachSubscriber(org.reactivestreams.Subscriber<? super T>, io.reactivex.rxjava3.functions.Consumer<? super T>, io.reactivex.rxjava3.functions.Consumer<? super java.lang.Throwable>, io.reactivex.rxjava3.functions.Action, io.reactivex.rxjava3.functions.Action);
    Code:
       0: aload_0
       1: aload_1
       2: invokespecial #1                  // Method io/reactivex/rxjava3/internal/subscribers/BasicFuseableSubscriber."<init>":(Lorg/reactivestreams/Subscriber;)V
       5: aload_0
       6: aload_2
       7: putfield      #2                  // Field onNext:Lio/reactivex/rxjava3/functions/Consumer;
      10: aload_0
      11: aload_3
      12: putfield      #3                  // Field onError:Lio/reactivex/rxjava3/functions/Consumer;
      15: aload_0
      16: aload         4
      18: putfield      #4                  // Field onComplete:Lio/reactivex/rxjava3/functions/Action;
      21: aload_0
      22: aload         5
      24: putfield      #5                  // Field onAfterTerminate:Lio/reactivex/rxjava3/functions/Action;
      27: return

  public void onNext(T);
    Code:
       0: aload_0
       1: getfield      #6                  // Field done:Z
       4: ifeq          8
       7: return
       8: aload_0
       9: getfield      #7                  // Field sourceMode:I
      12: ifeq          26
      15: aload_0
      16: getfield      #8                  // Field downstream:Lorg/reactivestreams/Subscriber;
      19: aconst_null
      20: invokeinterface #9,  2            // InterfaceMethod org/reactivestreams/Subscriber.onNext:(Ljava/lang/Object;)V
      25: return
      26: aload_0
      27: getfield      #2                  // Field onNext:Lio/reactivex/rxjava3/functions/Consumer;
      30: aload_1
      31: invokeinterface #10,  2           // InterfaceMethod io/reactivex/rxjava3/functions/Consumer.accept:(Ljava/lang/Object;)V
      36: goto          46
      39: astore_2
      40: aload_0
      41: aload_2
      42: invokevirtual #12                 // Method fail:(Ljava/lang/Throwable;)V
      45: return
      46: aload_0
      47: getfield      #8                  // Field downstream:Lorg/reactivestreams/Subscriber;
      50: aload_1
      51: invokeinterface #9,  2            // InterfaceMethod org/reactivestreams/Subscriber.onNext:(Ljava/lang/Object;)V
      56: return
    Exception table:
       from    to  target type
          26    36    39   Class java/lang/Throwable

  public void onError(java.lang.Throwable);
    Code:
       0: aload_0
       1: getfield      #6                  // Field done:Z
       4: ifeq          12
       7: aload_1
       8: invokestatic  #13                 // Method io/reactivex/rxjava3/plugins/RxJavaPlugins.onError:(Ljava/lang/Throwable;)V
      11: return
      12: aload_0
      13: iconst_1
      14: putfield      #6                  // Field done:Z
      17: iconst_1
      18: istore_2
      19: aload_0
      20: getfield      #3                  // Field onError:Lio/reactivex/rxjava3/functions/Consumer;
      23: aload_1
      24: invokeinterface #10,  2           // InterfaceMethod io/reactivex/rxjava3/functions/Consumer.accept:(Ljava/lang/Object;)V
      29: goto          67
      32: astore_3
      33: aload_3
      34: invokestatic  #14                 // Method io/reactivex/rxjava3/exceptions/Exceptions.throwIfFatal:(Ljava/lang/Throwable;)V
      37: aload_0
      38: getfield      #8                  // Field downstream:Lorg/reactivestreams/Subscriber;
      41: new           #15                 // class io/reactivex/rxjava3/exceptions/CompositeException
      44: dup
      45: iconst_2
      46: anewarray     #16                 // class java/lang/Throwable
      49: dup
      50: iconst_0
      51: aload_1
      52: aastore
      53: dup
      54: iconst_1
      55: aload_3
      56: aastore
      57: invokespecial #17                 // Method io/reactivex/rxjava3/exceptions/CompositeException."<init>":([Ljava/lang/Throwable;)V
      60: invokeinterface #18,  2           // InterfaceMethod org/reactivestreams/Subscriber.onError:(Ljava/lang/Throwable;)V
      65: iconst_0
      66: istore_2
      67: iload_2
      68: ifeq          81
      71: aload_0
      72: getfield      #8                  // Field downstream:Lorg/reactivestreams/Subscriber;
      75: aload_1
      76: invokeinterface #18,  2           // InterfaceMethod org/reactivestreams/Subscriber.onError:(Ljava/lang/Throwable;)V
      81: aload_0
      82: getfield      #5                  // Field onAfterTerminate:Lio/reactivex/rxjava3/functions/Action;
      85: invokeinterface #19,  1           // InterfaceMethod io/reactivex/rxjava3/functions/Action.run:()V
      90: goto          102
      93: astore_3
      94: aload_3
      95: invokestatic  #14                 // Method io/reactivex/rxjava3/exceptions/Exceptions.throwIfFatal:(Ljava/lang/Throwable;)V
      98: aload_3
      99: invokestatic  #13                 // Method io/reactivex/rxjava3/plugins/RxJavaPlugins.onError:(Ljava/lang/Throwable;)V
     102: return
    Exception table:
       from    to  target type
          19    29    32   Class java/lang/Throwable
          81    90    93   Class java/lang/Throwable

  public void onComplete();
    Code:
       0: aload_0
       1: getfield      #6                  // Field done:Z
       4: ifeq          8
       7: return
       8: aload_0
       9: getfield      #4                  // Field onComplete:Lio/reactivex/rxjava3/functions/Action;
      12: invokeinterface #19,  1           // InterfaceMethod io/reactivex/rxjava3/functions/Action.run:()V
      17: goto          27
      20: astore_1
      21: aload_0
      22: aload_1
      23: invokevirtual #12                 // Method fail:(Ljava/lang/Throwable;)V
      26: return
      27: aload_0
      28: iconst_1
      29: putfield      #6                  // Field done:Z
      32: aload_0
      33: getfield      #8                  // Field downstream:Lorg/reactivestreams/Subscriber;
      36: invokeinterface #20,  1           // InterfaceMethod org/reactivestreams/Subscriber.onComplete:()V
      41: aload_0
      42: getfield      #5                  // Field onAfterTerminate:Lio/reactivex/rxjava3/functions/Action;
      45: invokeinterface #19,  1           // InterfaceMethod io/reactivex/rxjava3/functions/Action.run:()V
      50: goto          62
      53: astore_1
      54: aload_1
      55: invokestatic  #14                 // Method io/reactivex/rxjava3/exceptions/Exceptions.throwIfFatal:(Ljava/lang/Throwable;)V
      58: aload_1
      59: invokestatic  #13                 // Method io/reactivex/rxjava3/plugins/RxJavaPlugins.onError:(Ljava/lang/Throwable;)V
      62: return
    Exception table:
       from    to  target type
           8    17    20   Class java/lang/Throwable
          41    50    53   Class java/lang/Throwable

  public int requestFusion(int);
    Code:
       0: aload_0
       1: iload_1
       2: invokevirtual #21                 // Method transitiveBoundaryFusion:(I)I
       5: ireturn

  public T poll() throws java.lang.Throwable;
    Code:
       0: aload_0
       1: getfield      #22                 // Field qs:Lio/reactivex/rxjava3/operators/QueueSubscription;
       4: invokeinterface #23,  1           // InterfaceMethod io/reactivex/rxjava3/operators/QueueSubscription.poll:()Ljava/lang/Object;
       9: astore_1
      10: goto          61
      13: astore_2
      14: aload_2
      15: invokestatic  #14                 // Method io/reactivex/rxjava3/exceptions/Exceptions.throwIfFatal:(Ljava/lang/Throwable;)V
      18: aload_0
      19: getfield      #3                  // Field onError:Lio/reactivex/rxjava3/functions/Consumer;
      22: aload_2
      23: invokeinterface #10,  2           // InterfaceMethod io/reactivex/rxjava3/functions/Consumer.accept:(Ljava/lang/Object;)V
      28: goto          56
      31: astore_3
      32: aload_3
      33: invokestatic  #14                 // Method io/reactivex/rxjava3/exceptions/Exceptions.throwIfFatal:(Ljava/lang/Throwable;)V
      36: new           #15                 // class io/reactivex/rxjava3/exceptions/CompositeException
      39: dup
      40: iconst_2
      41: anewarray     #16                 // class java/lang/Throwable
      44: dup
      45: iconst_0
      46: aload_2
      47: aastore
      48: dup
      49: iconst_1
      50: aload_3
      51: aastore
      52: invokespecial #17                 // Method io/reactivex/rxjava3/exceptions/CompositeException."<init>":([Ljava/lang/Throwable;)V
      55: athrow
      56: aload_2
      57: invokestatic  #24                 // Method io/reactivex/rxjava3/internal/util/ExceptionHelper.throwIfThrowable:(Ljava/lang/Throwable;)Ljava/lang/Exception;
      60: athrow
      61: aload_1
      62: ifnull        155
      65: aload_0
      66: getfield      #2                  // Field onNext:Lio/reactivex/rxjava3/functions/Consumer;
      69: aload_1
      70: invokeinterface #10,  2           // InterfaceMethod io/reactivex/rxjava3/functions/Consumer.accept:(Ljava/lang/Object;)V
      75: goto          126
      78: astore_2
      79: aload_2
      80: invokestatic  #14                 // Method io/reactivex/rxjava3/exceptions/Exceptions.throwIfFatal:(Ljava/lang/Throwable;)V
      83: aload_0
      84: getfield      #3                  // Field onError:Lio/reactivex/rxjava3/functions/Consumer;
      87: aload_2
      88: invokeinterface #10,  2           // InterfaceMethod io/reactivex/rxjava3/functions/Consumer.accept:(Ljava/lang/Object;)V
      93: goto          121
      96: astore_3
      97: aload_3
      98: invokestatic  #14                 // Method io/reactivex/rxjava3/exceptions/Exceptions.throwIfFatal:(Ljava/lang/Throwable;)V
     101: new           #15                 // class io/reactivex/rxjava3/exceptions/CompositeException
     104: dup
     105: iconst_2
     106: anewarray     #16                 // class java/lang/Throwable
     109: dup
     110: iconst_0
     111: aload_2
     112: aastore
     113: dup
     114: iconst_1
     115: aload_3
     116: aastore
     117: invokespecial #17                 // Method io/reactivex/rxjava3/exceptions/CompositeException."<init>":([Ljava/lang/Throwable;)V
     120: athrow
     121: aload_2
     122: invokestatic  #24                 // Method io/reactivex/rxjava3/internal/util/ExceptionHelper.throwIfThrowable:(Ljava/lang/Throwable;)Ljava/lang/Exception;
     125: athrow
     126: aload_0
     127: getfield      #5                  // Field onAfterTerminate:Lio/reactivex/rxjava3/functions/Action;
     130: invokeinterface #19,  1           // InterfaceMethod io/reactivex/rxjava3/functions/Action.run:()V
     135: goto          152
     138: astore        4
     140: aload_0
     141: getfield      #5                  // Field onAfterTerminate:Lio/reactivex/rxjava3/functions/Action;
     144: invokeinterface #19,  1           // InterfaceMethod io/reactivex/rxjava3/functions/Action.run:()V
     149: aload         4
     151: athrow
     152: goto          181
     155: aload_0
     156: getfield      #7                  // Field sourceMode:I
     159: iconst_1
     160: if_icmpne     181
     163: aload_0
     164: getfield      #4                  // Field onComplete:Lio/reactivex/rxjava3/functions/Action;
     167: invokeinterface #19,  1           // InterfaceMethod io/reactivex/rxjava3/functions/Action.run:()V
     172: aload_0
     173: getfield      #5                  // Field onAfterTerminate:Lio/reactivex/rxjava3/functions/Action;
     176: invokeinterface #19,  1           // InterfaceMethod io/reactivex/rxjava3/functions/Action.run:()V
     181: aload_1
     182: areturn
    Exception table:
       from    to  target type
           0    10    13   Class java/lang/Throwable
          18    28    31   Class java/lang/Throwable
          65    75    78   Class java/lang/Throwable
          83    93    96   Class java/lang/Throwable
          65   126   138   any
         138   140   138   any
}
