Compiled from "FlowableScanSeed.java"
public final class io.reactivex.rxjava3.internal.operators.flowable.FlowableScanSeed<T, R> extends io.reactivex.rxjava3.internal.operators.flowable.AbstractFlowableWithUpstream<T, R> {
  final io.reactivex.rxjava3.functions.BiFunction<R, ? super T, R> accumulator;

  final io.reactivex.rxjava3.functions.Supplier<R> seedSupplier;

  public io.reactivex.rxjava3.internal.operators.flowable.FlowableScanSeed(io.reactivex.rxjava3.core.Flowable<T>, io.reactivex.rxjava3.functions.Supplier<R>, io.reactivex.rxjava3.functions.BiFunction<R, ? super T, R>);
    Code:
       0: aload_0
       1: aload_1
       2: invokespecial #1                  // Method io/reactivex/rxjava3/internal/operators/flowable/AbstractFlowableWithUpstream."<init>":(Lio/reactivex/rxjava3/core/Flowable;)V
       5: aload_0
       6: aload_3
       7: putfield      #2                  // Field accumulator:Lio/reactivex/rxjava3/functions/BiFunction;
      10: aload_0
      11: aload_2
      12: putfield      #3                  // Field seedSupplier:Lio/reactivex/rxjava3/functions/Supplier;
      15: return

  protected void subscribeActual(org.reactivestreams.Subscriber<? super R>);
    Code:
       0: aload_0
       1: getfield      #3                  // Field seedSupplier:Lio/reactivex/rxjava3/functions/Supplier;
       4: invokeinterface #4,  1            // InterfaceMethod io/reactivex/rxjava3/functions/Supplier.get:()Ljava/lang/Object;
       9: ldc           #5                  // String The seed supplied is null
      11: invokestatic  #6                  // Method java/util/Objects.requireNonNull:(Ljava/lang/Object;Ljava/lang/String;)Ljava/lang/Object;
      14: astore_2
      15: goto          29
      18: astore_3
      19: aload_3
      20: invokestatic  #8                  // Method io/reactivex/rxjava3/exceptions/Exceptions.throwIfFatal:(Ljava/lang/Throwable;)V
      23: aload_3
      24: aload_1
      25: invokestatic  #9                  // Method io/reactivex/rxjava3/internal/subscriptions/EmptySubscription.error:(Ljava/lang/Throwable;Lorg/reactivestreams/Subscriber;)V
      28: return
      29: aload_0
      30: getfield      #10                 // Field source:Lio/reactivex/rxjava3/core/Flowable;
      33: new           #11                 // class io/reactivex/rxjava3/internal/operators/flowable/FlowableScanSeed$ScanSeedSubscriber
      36: dup
      37: aload_1
      38: aload_0
      39: getfield      #2                  // Field accumulator:Lio/reactivex/rxjava3/functions/BiFunction;
      42: aload_2
      43: invokestatic  #12                 // Method bufferSize:()I
      46: invokespecial #13                 // Method io/reactivex/rxjava3/internal/operators/flowable/FlowableScanSeed$ScanSeedSubscriber."<init>":(Lorg/reactivestreams/Subscriber;Lio/reactivex/rxjava3/functions/BiFunction;Ljava/lang/Object;I)V
      49: invokevirtual #14                 // Method io/reactivex/rxjava3/core/Flowable.subscribe:(Lio/reactivex/rxjava3/core/FlowableSubscriber;)V
      52: return
    Exception table:
       from    to  target type
           0    15    18   Class java/lang/Throwable
}
