Compiled from "FlowableFromPublisher.java"
public final class io.reactivex.rxjava3.internal.operators.flowable.FlowableFromPublisher<T> extends io.reactivex.rxjava3.core.Flowable<T> {
  final org.reactivestreams.Publisher<? extends T> publisher;

  public io.reactivex.rxjava3.internal.operators.flowable.FlowableFromPublisher(org.reactivestreams.Publisher<? extends T>);
    Code:
       0: aload_0
       1: invokespecial #1                  // Method io/reactivex/rxjava3/core/Flowable."<init>":()V
       4: aload_0
       5: aload_1
       6: putfield      #2                  // Field publisher:Lorg/reactivestreams/Publisher;
       9: return

  protected void subscribeActual(org.reactivestreams.Subscriber<? super T>);
    Code:
       0: aload_0
       1: getfield      #2                  // Field publisher:Lorg/reactivestreams/Publisher;
       4: aload_1
       5: invokeinterface #3,  2            // InterfaceMethod org/reactivestreams/Publisher.subscribe:(Lorg/reactivestreams/Subscriber;)V
      10: return
}
