Compiled from "FlowableEmpty.java"
public final class io.reactivex.rxjava3.internal.operators.flowable.FlowableEmpty extends io.reactivex.rxjava3.core.Flowable<java.lang.Object> implements io.reactivex.rxjava3.operators.ScalarSupplier<java.lang.Object> {
  public static final io.reactivex.rxjava3.core.Flowable<java.lang.Object> INSTANCE;

  private io.reactivex.rxjava3.internal.operators.flowable.FlowableEmpty();
    Code:
       0: aload_0
       1: invokespecial #1                  // Method io/reactivex/rxjava3/core/Flowable."<init>":()V
       4: return

  public void subscribeActual(org.reactivestreams.Subscriber<? super java.lang.Object>);
    Code:
       0: aload_1
       1: invokestatic  #2                  // Method io/reactivex/rxjava3/internal/subscriptions/EmptySubscription.complete:(Lorg/reactivestreams/Subscriber;)V
       4: return

  public java.lang.Object get();
    Code:
       0: aconst_null
       1: areturn

  static {};
    Code:
       0: new           #3                  // class io/reactivex/rxjava3/internal/operators/flowable/FlowableEmpty
       3: dup
       4: invokespecial #4                  // Method "<init>":()V
       7: putstatic     #5                  // Field INSTANCE:Lio/reactivex/rxjava3/core/Flowable;
      10: return
}
