Compiled from "FlowableUsing.java"
public final class io.reactivex.rxjava3.internal.operators.flowable.FlowableUsing<T, D> extends io.reactivex.rxjava3.core.Flowable<T> {
  final io.reactivex.rxjava3.functions.Supplier<? extends D> resourceSupplier;

  final io.reactivex.rxjava3.functions.Function<? super D, ? extends org.reactivestreams.Publisher<? extends T>> sourceSupplier;

  final io.reactivex.rxjava3.functions.Consumer<? super D> disposer;

  final boolean eager;

  public io.reactivex.rxjava3.internal.operators.flowable.FlowableUsing(io.reactivex.rxjava3.functions.Supplier<? extends D>, io.reactivex.rxjava3.functions.Function<? super D, ? extends org.reactivestreams.Publisher<? extends T>>, io.reactivex.rxjava3.functions.Consumer<? super D>, boolean);
    Code:
       0: aload_0
       1: invokespecial #1                  // Method io/reactivex/rxjava3/core/Flowable."<init>":()V
       4: aload_0
       5: aload_1
       6: putfield      #2                  // Field resourceSupplier:Lio/reactivex/rxjava3/functions/Supplier;
       9: aload_0
      10: aload_2
      11: putfield      #3                  // Field sourceSupplier:Lio/reactivex/rxjava3/functions/Function;
      14: aload_0
      15: aload_3
      16: putfield      #4                  // Field disposer:Lio/reactivex/rxjava3/functions/Consumer;
      19: aload_0
      20: iload         4
      22: putfield      #5                  // Field eager:Z
      25: return

  public void subscribeActual(org.reactivestreams.Subscriber<? super T>);
    Code:
       0: aload_0
       1: getfield      #2                  // Field resourceSupplier:Lio/reactivex/rxjava3/functions/Supplier;
       4: invokeinterface #6,  1            // InterfaceMethod io/reactivex/rxjava3/functions/Supplier.get:()Ljava/lang/Object;
       9: astore_2
      10: goto          24
      13: astore_3
      14: aload_3
      15: invokestatic  #8                  // Method io/reactivex/rxjava3/exceptions/Exceptions.throwIfFatal:(Ljava/lang/Throwable;)V
      18: aload_3
      19: aload_1
      20: invokestatic  #9                  // Method io/reactivex/rxjava3/internal/subscriptions/EmptySubscription.error:(Ljava/lang/Throwable;Lorg/reactivestreams/Subscriber;)V
      23: return
      24: aload_0
      25: getfield      #3                  // Field sourceSupplier:Lio/reactivex/rxjava3/functions/Function;
      28: aload_2
      29: invokeinterface #10,  2           // InterfaceMethod io/reactivex/rxjava3/functions/Function.apply:(Ljava/lang/Object;)Ljava/lang/Object;
      34: ldc           #11                 // String The sourceSupplier returned a null Publisher
      36: invokestatic  #12                 // Method java/util/Objects.requireNonNull:(Ljava/lang/Object;Ljava/lang/String;)Ljava/lang/Object;
      39: checkcast     #13                 // class org/reactivestreams/Publisher
      42: astore_3
      43: goto          106
      46: astore        4
      48: aload         4
      50: invokestatic  #8                  // Method io/reactivex/rxjava3/exceptions/Exceptions.throwIfFatal:(Ljava/lang/Throwable;)V
      53: aload_0
      54: getfield      #4                  // Field disposer:Lio/reactivex/rxjava3/functions/Consumer;
      57: aload_2
      58: invokeinterface #14,  2           // InterfaceMethod io/reactivex/rxjava3/functions/Consumer.accept:(Ljava/lang/Object;)V
      63: goto          99
      66: astore        5
      68: aload         5
      70: invokestatic  #8                  // Method io/reactivex/rxjava3/exceptions/Exceptions.throwIfFatal:(Ljava/lang/Throwable;)V
      73: new           #15                 // class io/reactivex/rxjava3/exceptions/CompositeException
      76: dup
      77: iconst_2
      78: anewarray     #16                 // class java/lang/Throwable
      81: dup
      82: iconst_0
      83: aload         4
      85: aastore
      86: dup
      87: iconst_1
      88: aload         5
      90: aastore
      91: invokespecial #17                 // Method io/reactivex/rxjava3/exceptions/CompositeException."<init>":([Ljava/lang/Throwable;)V
      94: aload_1
      95: invokestatic  #9                  // Method io/reactivex/rxjava3/internal/subscriptions/EmptySubscription.error:(Ljava/lang/Throwable;Lorg/reactivestreams/Subscriber;)V
      98: return
      99: aload         4
     101: aload_1
     102: invokestatic  #9                  // Method io/reactivex/rxjava3/internal/subscriptions/EmptySubscription.error:(Ljava/lang/Throwable;Lorg/reactivestreams/Subscriber;)V
     105: return
     106: new           #18                 // class io/reactivex/rxjava3/internal/operators/flowable/FlowableUsing$UsingSubscriber
     109: dup
     110: aload_1
     111: aload_2
     112: aload_0
     113: getfield      #4                  // Field disposer:Lio/reactivex/rxjava3/functions/Consumer;
     116: aload_0
     117: getfield      #5                  // Field eager:Z
     120: invokespecial #19                 // Method io/reactivex/rxjava3/internal/operators/flowable/FlowableUsing$UsingSubscriber."<init>":(Lorg/reactivestreams/Subscriber;Ljava/lang/Object;Lio/reactivex/rxjava3/functions/Consumer;Z)V
     123: astore        4
     125: aload_3
     126: aload         4
     128: invokeinterface #20,  2           // InterfaceMethod org/reactivestreams/Publisher.subscribe:(Lorg/reactivestreams/Subscriber;)V
     133: return
    Exception table:
       from    to  target type
           0    10    13   Class java/lang/Throwable
          24    43    46   Class java/lang/Throwable
          53    63    66   Class java/lang/Throwable
}
