Compiled from "FlowableRange.java"
public final class io.reactivex.rxjava3.internal.operators.flowable.FlowableRange extends io.reactivex.rxjava3.core.Flowable<java.lang.Integer> {
  final int start;

  final int end;

  public io.reactivex.rxjava3.internal.operators.flowable.FlowableRange(int, int);
    Code:
       0: aload_0
       1: invokespecial #1                  // Method io/reactivex/rxjava3/core/Flowable."<init>":()V
       4: aload_0
       5: iload_1
       6: putfield      #2                  // Field start:I
       9: aload_0
      10: iload_1
      11: iload_2
      12: iadd
      13: putfield      #3                  // Field end:I
      16: return

  public void subscribeActual(org.reactivestreams.Subscriber<? super java.lang.Integer>);
    Code:
       0: aload_1
       1: instanceof    #4                  // class io/reactivex/rxjava3/operators/ConditionalSubscriber
       4: ifeq          35
       7: aload_1
       8: new           #5                  // class io/reactivex/rxjava3/internal/operators/flowable/FlowableRange$RangeConditionalSubscription
      11: dup
      12: aload_1
      13: checkcast     #4                  // class io/reactivex/rxjava3/operators/ConditionalSubscriber
      16: aload_0
      17: getfield      #2                  // Field start:I
      20: aload_0
      21: getfield      #3                  // Field end:I
      24: invokespecial #6                  // Method io/reactivex/rxjava3/internal/operators/flowable/FlowableRange$RangeConditionalSubscription."<init>":(Lio/reactivex/rxjava3/operators/ConditionalSubscriber;II)V
      27: invokeinterface #7,  2            // InterfaceMethod org/reactivestreams/Subscriber.onSubscribe:(Lorg/reactivestreams/Subscription;)V
      32: goto          57
      35: aload_1
      36: new           #8                  // class io/reactivex/rxjava3/internal/operators/flowable/FlowableRange$RangeSubscription
      39: dup
      40: aload_1
      41: aload_0
      42: getfield      #2                  // Field start:I
      45: aload_0
      46: getfield      #3                  // Field end:I
      49: invokespecial #9                  // Method io/reactivex/rxjava3/internal/operators/flowable/FlowableRange$RangeSubscription."<init>":(Lorg/reactivestreams/Subscriber;II)V
      52: invokeinterface #7,  2            // InterfaceMethod org/reactivestreams/Subscriber.onSubscribe:(Lorg/reactivestreams/Subscription;)V
      57: return
}
