Compiled from "FlowableTakeLastTimed.java"
public final class io.reactivex.rxjava3.internal.operators.flowable.FlowableTakeLastTimed<T> extends io.reactivex.rxjava3.internal.operators.flowable.AbstractFlowableWithUpstream<T, T> {
  final long count;

  final long time;

  final java.util.concurrent.TimeUnit unit;

  final io.reactivex.rxjava3.core.Scheduler scheduler;

  final int bufferSize;

  final boolean delayError;

  public io.reactivex.rxjava3.internal.operators.flowable.FlowableTakeLastTimed(io.reactivex.rxjava3.core.Flowable<T>, long, long, java.util.concurrent.TimeUnit, io.reactivex.rxjava3.core.Scheduler, int, boolean);
    Code:
       0: aload_0
       1: aload_1
       2: invokespecial #1                  // Method io/reactivex/rxjava3/internal/operators/flowable/AbstractFlowableWithUpstream."<init>":(Lio/reactivex/rxjava3/core/Flowable;)V
       5: aload_0
       6: lload_2
       7: putfield      #2                  // Field count:J
      10: aload_0
      11: lload         4
      13: putfield      #3                  // Field time:J
      16: aload_0
      17: aload         6
      19: putfield      #4                  // Field unit:Ljava/util/concurrent/TimeUnit;
      22: aload_0
      23: aload         7
      25: putfield      #5                  // Field scheduler:Lio/reactivex/rxjava3/core/Scheduler;
      28: aload_0
      29: iload         8
      31: putfield      #6                  // Field bufferSize:I
      34: aload_0
      35: iload         9
      37: putfield      #7                  // Field delayError:Z
      40: return

  protected void subscribeActual(org.reactivestreams.Subscriber<? super T>);
    Code:
       0: aload_0
       1: getfield      #8                  // Field source:Lio/reactivex/rxjava3/core/Flowable;
       4: new           #9                  // class io/reactivex/rxjava3/internal/operators/flowable/FlowableTakeLastTimed$TakeLastTimedSubscriber
       7: dup
       8: aload_1
       9: aload_0
      10: getfield      #2                  // Field count:J
      13: aload_0
      14: getfield      #3                  // Field time:J
      17: aload_0
      18: getfield      #4                  // Field unit:Ljava/util/concurrent/TimeUnit;
      21: aload_0
      22: getfield      #5                  // Field scheduler:Lio/reactivex/rxjava3/core/Scheduler;
      25: aload_0
      26: getfield      #6                  // Field bufferSize:I
      29: aload_0
      30: getfield      #7                  // Field delayError:Z
      33: invokespecial #10                 // Method io/reactivex/rxjava3/internal/operators/flowable/FlowableTakeLastTimed$TakeLastTimedSubscriber."<init>":(Lorg/reactivestreams/Subscriber;JJLjava/util/concurrent/TimeUnit;Lio/reactivex/rxjava3/core/Scheduler;IZ)V
      36: invokevirtual #11                 // Method io/reactivex/rxjava3/core/Flowable.subscribe:(Lio/reactivex/rxjava3/core/FlowableSubscriber;)V
      39: return
}
