Compiled from "FlowableOnBackpressureError.java"
public final class io.reactivex.rxjava3.internal.operators.flowable.FlowableOnBackpressureError<T> extends io.reactivex.rxjava3.internal.operators.flowable.AbstractFlowableWithUpstream<T, T> {
  public io.reactivex.rxjava3.internal.operators.flowable.FlowableOnBackpressureError(io.reactivex.rxjava3.core.Flowable<T>);
    Code:
       0: aload_0
       1: aload_1
       2: invokespecial #1                  // Method io/reactivex/rxjava3/internal/operators/flowable/AbstractFlowableWithUpstream."<init>":(Lio/reactivex/rxjava3/core/Flowable;)V
       5: return

  protected void subscribeActual(org.reactivestreams.Subscriber<? super T>);
    Code:
       0: aload_0
       1: getfield      #2                  // Field source:Lio/reactivex/rxjava3/core/Flowable;
       4: new           #3                  // class io/reactivex/rxjava3/internal/operators/flowable/FlowableOnBackpressureError$BackpressureErrorSubscriber
       7: dup
       8: aload_1
       9: invokespecial #4                  // Method io/reactivex/rxjava3/internal/operators/flowable/FlowableOnBackpressureError$BackpressureErrorSubscriber."<init>":(Lorg/reactivestreams/Subscriber;)V
      12: invokevirtual #5                  // Method io/reactivex/rxjava3/core/Flowable.subscribe:(Lio/reactivex/rxjava3/core/FlowableSubscriber;)V
      15: return
}
