Compiled from "FlowableOnBackpressureLatest.java"
final class io.reactivex.rxjava3.internal.operators.flowable.FlowableOnBackpressureLatest$BackpressureLatestSubscriber<T> extends io.reactivex.rxjava3.internal.operators.flowable.AbstractBackpressureThrottlingSubscriber<T, T> {
  private static final long serialVersionUID;

  io.reactivex.rxjava3.internal.operators.flowable.FlowableOnBackpressureLatest$BackpressureLatestSubscriber(org.reactivestreams.Subscriber<? super T>);
    Code:
       0: aload_0
       1: aload_1
       2: invokespecial #1                  // Method io/reactivex/rxjava3/internal/operators/flowable/AbstractBackpressureThrottlingSubscriber."<init>":(Lorg/reactivestreams/Subscriber;)V
       5: return

  public void onNext(T);
    Code:
       0: aload_0
       1: getfield      #2                  // Field current:Ljava/util/concurrent/atomic/AtomicReference;
       4: aload_1
       5: invokevirtual #3                  // Method java/util/concurrent/atomic/AtomicReference.lazySet:(Ljava/lang/Object;)V
       8: aload_0
       9: invokevirtual #4                  // Method drain:()V
      12: return
}
