Compiled from "FlowableSkip.java"
public final class io.reactivex.rxjava3.internal.operators.flowable.FlowableSkip<T> extends io.reactivex.rxjava3.internal.operators.flowable.AbstractFlowableWithUpstream<T, T> {
  final long n;

  public io.reactivex.rxjava3.internal.operators.flowable.FlowableSkip(io.reactivex.rxjava3.core.Flowable<T>, long);
    Code:
       0: aload_0
       1: aload_1
       2: invokespecial #1                  // Method io/reactivex/rxjava3/internal/operators/flowable/AbstractFlowableWithUpstream."<init>":(Lio/reactivex/rxjava3/core/Flowable;)V
       5: aload_0
       6: lload_2
       7: putfield      #2                  // Field n:J
      10: return

  protected void subscribeActual(org.reactivestreams.Subscriber<? super T>);
    Code:
       0: aload_0
       1: getfield      #3                  // Field source:Lio/reactivex/rxjava3/core/Flowable;
       4: new           #4                  // class io/reactivex/rxjava3/internal/operators/flowable/FlowableSkip$SkipSubscriber
       7: dup
       8: aload_1
       9: aload_0
      10: getfield      #2                  // Field n:J
      13: invokespecial #5                  // Method io/reactivex/rxjava3/internal/operators/flowable/FlowableSkip$SkipSubscriber."<init>":(Lorg/reactivestreams/Subscriber;J)V
      16: invokevirtual #6                  // Method io/reactivex/rxjava3/core/Flowable.subscribe:(Lio/reactivex/rxjava3/core/FlowableSubscriber;)V
      19: return
}
