Compiled from "FlowableCombineLatest.java"
final class io.reactivex.rxjava3.internal.operators.flowable.FlowableCombineLatest$CombineLatestInnerSubscriber<T> extends java.util.concurrent.atomic.AtomicReference<org.reactivestreams.Subscription> implements io.reactivex.rxjava3.core.FlowableSubscriber<T> {
  private static final long serialVersionUID;

  final io.reactivex.rxjava3.internal.operators.flowable.FlowableCombineLatest$CombineLatestCoordinator<T, ?> parent;

  final int index;

  final int prefetch;

  final int limit;

  int produced;

  io.reactivex.rxjava3.internal.operators.flowable.FlowableCombineLatest$CombineLatestInnerSubscriber(io.reactivex.rxjava3.internal.operators.flowable.FlowableCombineLatest$CombineLatestCoordinator<T, ?>, int, int);
    Code:
       0: aload_0
       1: invokespecial #1                  // Method java/util/concurrent/atomic/AtomicReference."<init>":()V
       4: aload_0
       5: aload_1
       6: putfield      #2                  // Field parent:Lio/reactivex/rxjava3/internal/operators/flowable/FlowableCombineLatest$CombineLatestCoordinator;
       9: aload_0
      10: iload_2
      11: putfield      #3                  // Field index:I
      14: aload_0
      15: iload_3
      16: putfield      #4                  // Field prefetch:I
      19: aload_0
      20: iload_3
      21: iload_3
      22: iconst_2
      23: ishr
      24: isub
      25: putfield      #5                  // Field limit:I
      28: return

  public void onSubscribe(org.reactivestreams.Subscription);
    Code:
       0: aload_0
       1: aload_1
       2: aload_0
       3: getfield      #4                  // Field prefetch:I
       6: i2l
       7: invokestatic  #6                  // Method io/reactivex/rxjava3/internal/subscriptions/SubscriptionHelper.setOnce:(Ljava/util/concurrent/atomic/AtomicReference;Lorg/reactivestreams/Subscription;J)Z
      10: pop
      11: return

  public void onNext(T);
    Code:
       0: aload_0
       1: getfield      #2                  // Field parent:Lio/reactivex/rxjava3/internal/operators/flowable/FlowableCombineLatest$CombineLatestCoordinator;
       4: aload_0
       5: getfield      #3                  // Field index:I
       8: aload_1
       9: invokevirtual #7                  // Method io/reactivex/rxjava3/internal/operators/flowable/FlowableCombineLatest$CombineLatestCoordinator.innerValue:(ILjava/lang/Object;)V
      12: return

  public void onError(java.lang.Throwable);
    Code:
       0: aload_0
       1: getfield      #2                  // Field parent:Lio/reactivex/rxjava3/internal/operators/flowable/FlowableCombineLatest$CombineLatestCoordinator;
       4: aload_0
       5: getfield      #3                  // Field index:I
       8: aload_1
       9: invokevirtual #8                  // Method io/reactivex/rxjava3/internal/operators/flowable/FlowableCombineLatest$CombineLatestCoordinator.innerError:(ILjava/lang/Throwable;)V
      12: return

  public void onComplete();
    Code:
       0: aload_0
       1: getfield      #2                  // Field parent:Lio/reactivex/rxjava3/internal/operators/flowable/FlowableCombineLatest$CombineLatestCoordinator;
       4: aload_0
       5: getfield      #3                  // Field index:I
       8: invokevirtual #9                  // Method io/reactivex/rxjava3/internal/operators/flowable/FlowableCombineLatest$CombineLatestCoordinator.innerComplete:(I)V
      11: return

  public void cancel();
    Code:
       0: aload_0
       1: invokestatic  #10                 // Method io/reactivex/rxjava3/internal/subscriptions/SubscriptionHelper.cancel:(Ljava/util/concurrent/atomic/AtomicReference;)Z
       4: pop
       5: return

  public void requestOne();
    Code:
       0: aload_0
       1: getfield      #11                 // Field produced:I
       4: iconst_1
       5: iadd
       6: istore_1
       7: iload_1
       8: aload_0
       9: getfield      #5                  // Field limit:I
      12: if_icmpne     37
      15: aload_0
      16: iconst_0
      17: putfield      #11                 // Field produced:I
      20: aload_0
      21: invokevirtual #12                 // Method get:()Ljava/lang/Object;
      24: checkcast     #13                 // class org/reactivestreams/Subscription
      27: iload_1
      28: i2l
      29: invokeinterface #14,  3           // InterfaceMethod org/reactivestreams/Subscription.request:(J)V
      34: goto          42
      37: aload_0
      38: iload_1
      39: putfield      #11                 // Field produced:I
      42: return
}
