Compiled from "FlowableFlattenIterable.java"
final class io.reactivex.rxjava3.internal.operators.flowable.FlowableFlattenIterable$FlattenIterableSubscriber<T, R> extends io.reactivex.rxjava3.internal.subscriptions.BasicIntQueueSubscription<R> implements io.reactivex.rxjava3.core.FlowableSubscriber<T> {
  private static final long serialVersionUID;

  final org.reactivestreams.Subscriber<? super R> downstream;

  final io.reactivex.rxjava3.functions.Function<? super T, ? extends java.lang.Iterable<? extends R>> mapper;

  final int prefetch;

  final int limit;

  final java.util.concurrent.atomic.AtomicLong requested;

  org.reactivestreams.Subscription upstream;

  io.reactivex.rxjava3.operators.SimpleQueue<T> queue;

  volatile boolean done;

  volatile boolean cancelled;

  final java.util.concurrent.atomic.AtomicReference<java.lang.Throwable> error;

  java.util.Iterator<? extends R> current;

  int consumed;

  int fusionMode;

  io.reactivex.rxjava3.internal.operators.flowable.FlowableFlattenIterable$FlattenIterableSubscriber(org.reactivestreams.Subscriber<? super R>, io.reactivex.rxjava3.functions.Function<? super T, ? extends java.lang.Iterable<? extends R>>, int);
    Code:
       0: aload_0
       1: invokespecial #1                  // Method io/reactivex/rxjava3/internal/subscriptions/BasicIntQueueSubscription."<init>":()V
       4: aload_0
       5: aload_1
       6: putfield      #2                  // Field downstream:Lorg/reactivestreams/Subscriber;
       9: aload_0
      10: aload_2
      11: putfield      #3                  // Field mapper:Lio/reactivex/rxjava3/functions/Function;
      14: aload_0
      15: iload_3
      16: putfield      #4                  // Field prefetch:I
      19: aload_0
      20: iload_3
      21: iload_3
      22: iconst_2
      23: ishr
      24: isub
      25: putfield      #5                  // Field limit:I
      28: aload_0
      29: new           #6                  // class java/util/concurrent/atomic/AtomicReference
      32: dup
      33: invokespecial #7                  // Method java/util/concurrent/atomic/AtomicReference."<init>":()V
      36: putfield      #8                  // Field error:Ljava/util/concurrent/atomic/AtomicReference;
      39: aload_0
      40: new           #9                  // class java/util/concurrent/atomic/AtomicLong
      43: dup
      44: invokespecial #10                 // Method java/util/concurrent/atomic/AtomicLong."<init>":()V
      47: putfield      #11                 // Field requested:Ljava/util/concurrent/atomic/AtomicLong;
      50: return

  public void onSubscribe(org.reactivestreams.Subscription);
    Code:
       0: aload_0
       1: getfield      #12                 // Field upstream:Lorg/reactivestreams/Subscription;
       4: aload_1
       5: invokestatic  #13                 // Method io/reactivex/rxjava3/internal/subscriptions/SubscriptionHelper.validate:(Lorg/reactivestreams/Subscription;Lorg/reactivestreams/Subscription;)Z
       8: ifeq          140
      11: aload_0
      12: aload_1
      13: putfield      #12                 // Field upstream:Lorg/reactivestreams/Subscription;
      16: aload_1
      17: instanceof    #14                 // class io/reactivex/rxjava3/operators/QueueSubscription
      20: ifeq          104
      23: aload_1
      24: checkcast     #14                 // class io/reactivex/rxjava3/operators/QueueSubscription
      27: astore_2
      28: aload_2
      29: iconst_3
      30: invokeinterface #16,  2           // InterfaceMethod io/reactivex/rxjava3/operators/QueueSubscription.requestFusion:(I)I
      35: istore_3
      36: iload_3
      37: iconst_1
      38: if_icmpne     67
      41: aload_0
      42: iload_3
      43: putfield      #17                 // Field fusionMode:I
      46: aload_0
      47: aload_2
      48: putfield      #18                 // Field queue:Lio/reactivex/rxjava3/operators/SimpleQueue;
      51: aload_0
      52: iconst_1
      53: putfield      #19                 // Field done:Z
      56: aload_0
      57: getfield      #2                  // Field downstream:Lorg/reactivestreams/Subscriber;
      60: aload_0
      61: invokeinterface #20,  2           // InterfaceMethod org/reactivestreams/Subscriber.onSubscribe:(Lorg/reactivestreams/Subscription;)V
      66: return
      67: iload_3
      68: iconst_2
      69: if_icmpne     104
      72: aload_0
      73: iload_3
      74: putfield      #17                 // Field fusionMode:I
      77: aload_0
      78: aload_2
      79: putfield      #18                 // Field queue:Lio/reactivex/rxjava3/operators/SimpleQueue;
      82: aload_0
      83: getfield      #2                  // Field downstream:Lorg/reactivestreams/Subscriber;
      86: aload_0
      87: invokeinterface #20,  2           // InterfaceMethod org/reactivestreams/Subscriber.onSubscribe:(Lorg/reactivestreams/Subscription;)V
      92: aload_1
      93: aload_0
      94: getfield      #4                  // Field prefetch:I
      97: i2l
      98: invokeinterface #21,  3           // InterfaceMethod org/reactivestreams/Subscription.request:(J)V
     103: return
     104: aload_0
     105: new           #22                 // class io/reactivex/rxjava3/operators/SpscArrayQueue
     108: dup
     109: aload_0
     110: getfield      #4                  // Field prefetch:I
     113: invokespecial #23                 // Method io/reactivex/rxjava3/operators/SpscArrayQueue."<init>":(I)V
     116: putfield      #18                 // Field queue:Lio/reactivex/rxjava3/operators/SimpleQueue;
     119: aload_0
     120: getfield      #2                  // Field downstream:Lorg/reactivestreams/Subscriber;
     123: aload_0
     124: invokeinterface #20,  2           // InterfaceMethod org/reactivestreams/Subscriber.onSubscribe:(Lorg/reactivestreams/Subscription;)V
     129: aload_1
     130: aload_0
     131: getfield      #4                  // Field prefetch:I
     134: i2l
     135: invokeinterface #21,  3           // InterfaceMethod org/reactivestreams/Subscription.request:(J)V
     140: return

  public void onNext(T);
    Code:
       0: aload_0
       1: getfield      #19                 // Field done:Z
       4: ifeq          8
       7: return
       8: aload_0
       9: getfield      #17                 // Field fusionMode:I
      12: ifne          40
      15: aload_0
      16: getfield      #18                 // Field queue:Lio/reactivex/rxjava3/operators/SimpleQueue;
      19: aload_1
      20: invokeinterface #24,  2           // InterfaceMethod io/reactivex/rxjava3/operators/SimpleQueue.offer:(Ljava/lang/Object;)Z
      25: ifne          40
      28: aload_0
      29: new           #25                 // class io/reactivex/rxjava3/exceptions/QueueOverflowException
      32: dup
      33: invokespecial #26                 // Method io/reactivex/rxjava3/exceptions/QueueOverflowException."<init>":()V
      36: invokevirtual #27                 // Method onError:(Ljava/lang/Throwable;)V
      39: return
      40: aload_0
      41: invokevirtual #28                 // Method drain:()V
      44: return

  public void onError(java.lang.Throwable);
    Code:
       0: aload_0
       1: getfield      #19                 // Field done:Z
       4: ifne          30
       7: aload_0
       8: getfield      #8                  // Field error:Ljava/util/concurrent/atomic/AtomicReference;
      11: aload_1
      12: invokestatic  #29                 // Method io/reactivex/rxjava3/internal/util/ExceptionHelper.addThrowable:(Ljava/util/concurrent/atomic/AtomicReference;Ljava/lang/Throwable;)Z
      15: ifeq          30
      18: aload_0
      19: iconst_1
      20: putfield      #19                 // Field done:Z
      23: aload_0
      24: invokevirtual #28                 // Method drain:()V
      27: goto          34
      30: aload_1
      31: invokestatic  #30                 // Method io/reactivex/rxjava3/plugins/RxJavaPlugins.onError:(Ljava/lang/Throwable;)V
      34: return

  public void onComplete();
    Code:
       0: aload_0
       1: getfield      #19                 // Field done:Z
       4: ifeq          8
       7: return
       8: aload_0
       9: iconst_1
      10: putfield      #19                 // Field done:Z
      13: aload_0
      14: invokevirtual #28                 // Method drain:()V
      17: return

  public void request(long);
    Code:
       0: lload_1
       1: invokestatic  #31                 // Method io/reactivex/rxjava3/internal/subscriptions/SubscriptionHelper.validate:(J)Z
       4: ifeq          20
       7: aload_0
       8: getfield      #11                 // Field requested:Ljava/util/concurrent/atomic/AtomicLong;
      11: lload_1
      12: invokestatic  #32                 // Method io/reactivex/rxjava3/internal/util/BackpressureHelper.add:(Ljava/util/concurrent/atomic/AtomicLong;J)J
      15: pop2
      16: aload_0
      17: invokevirtual #28                 // Method drain:()V
      20: return

  public void cancel();
    Code:
       0: aload_0
       1: getfield      #33                 // Field cancelled:Z
       4: ifne          37
       7: aload_0
       8: iconst_1
       9: putfield      #33                 // Field cancelled:Z
      12: aload_0
      13: getfield      #12                 // Field upstream:Lorg/reactivestreams/Subscription;
      16: invokeinterface #34,  1           // InterfaceMethod org/reactivestreams/Subscription.cancel:()V
      21: aload_0
      22: invokevirtual #35                 // Method getAndIncrement:()I
      25: ifne          37
      28: aload_0
      29: getfield      #18                 // Field queue:Lio/reactivex/rxjava3/operators/SimpleQueue;
      32: invokeinterface #36,  1           // InterfaceMethod io/reactivex/rxjava3/operators/SimpleQueue.clear:()V
      37: return

  void drain();
    Code:
       0: aload_0
       1: invokevirtual #35                 // Method getAndIncrement:()I
       4: ifeq          8
       7: return
       8: aload_0
       9: getfield      #2                  // Field downstream:Lorg/reactivestreams/Subscriber;
      12: astore_1
      13: aload_0
      14: getfield      #18                 // Field queue:Lio/reactivex/rxjava3/operators/SimpleQueue;
      17: astore_2
      18: aload_0
      19: getfield      #17                 // Field fusionMode:I
      22: iconst_1
      23: if_icmpeq     30
      26: iconst_1
      27: goto          31
      30: iconst_0
      31: istore_3
      32: iconst_1
      33: istore        4
      35: aload_0
      36: getfield      #37                 // Field current:Ljava/util/Iterator;
      39: astore        5
      41: aload         5
      43: ifnonnull     252
      46: aload_0
      47: getfield      #19                 // Field done:Z
      50: istore        6
      52: aload_2
      53: invokeinterface #38,  1           // InterfaceMethod io/reactivex/rxjava3/operators/SimpleQueue.poll:()Ljava/lang/Object;
      58: astore        7
      60: goto          118
      63: astore        8
      65: aload         8
      67: invokestatic  #40                 // Method io/reactivex/rxjava3/exceptions/Exceptions.throwIfFatal:(Ljava/lang/Throwable;)V
      70: aload_0
      71: getfield      #12                 // Field upstream:Lorg/reactivestreams/Subscription;
      74: invokeinterface #34,  1           // InterfaceMethod org/reactivestreams/Subscription.cancel:()V
      79: aload_0
      80: getfield      #8                  // Field error:Ljava/util/concurrent/atomic/AtomicReference;
      83: aload         8
      85: invokestatic  #29                 // Method io/reactivex/rxjava3/internal/util/ExceptionHelper.addThrowable:(Ljava/util/concurrent/atomic/AtomicReference;Ljava/lang/Throwable;)Z
      88: pop
      89: aload_0
      90: getfield      #8                  // Field error:Ljava/util/concurrent/atomic/AtomicReference;
      93: invokestatic  #41                 // Method io/reactivex/rxjava3/internal/util/ExceptionHelper.terminate:(Ljava/util/concurrent/atomic/AtomicReference;)Ljava/lang/Throwable;
      96: astore        8
      98: aload_0
      99: aconst_null
     100: putfield      #37                 // Field current:Ljava/util/Iterator;
     103: aload_2
     104: invokeinterface #36,  1           // InterfaceMethod io/reactivex/rxjava3/operators/SimpleQueue.clear:()V
     109: aload_1
     110: aload         8
     112: invokeinterface #42,  2           // InterfaceMethod org/reactivestreams/Subscriber.onError:(Ljava/lang/Throwable;)V
     117: return
     118: aload         7
     120: ifnonnull     127
     123: iconst_1
     124: goto          128
     127: iconst_0
     128: istore        8
     130: aload_0
     131: iload         6
     133: iload         8
     135: aload_1
     136: aload_2
     137: invokevirtual #43                 // Method checkTerminated:(ZZLorg/reactivestreams/Subscriber;Lio/reactivex/rxjava3/operators/SimpleQueue;)Z
     140: ifeq          144
     143: return
     144: aload         7
     146: ifnull        252
     149: aload_0
     150: getfield      #3                  // Field mapper:Lio/reactivex/rxjava3/functions/Function;
     153: aload         7
     155: invokeinterface #44,  2           // InterfaceMethod io/reactivex/rxjava3/functions/Function.apply:(Ljava/lang/Object;)Ljava/lang/Object;
     160: checkcast     #45                 // class java/lang/Iterable
     163: astore        9
     165: aload         9
     167: invokeinterface #46,  1           // InterfaceMethod java/lang/Iterable.iterator:()Ljava/util/Iterator;
     172: astore        5
     174: aload         5
     176: invokeinterface #47,  1           // InterfaceMethod java/util/Iterator.hasNext:()Z
     181: istore        10
     183: goto          230
     186: astore        11
     188: aload         11
     190: invokestatic  #40                 // Method io/reactivex/rxjava3/exceptions/Exceptions.throwIfFatal:(Ljava/lang/Throwable;)V
     193: aload_0
     194: getfield      #12                 // Field upstream:Lorg/reactivestreams/Subscription;
     197: invokeinterface #34,  1           // InterfaceMethod org/reactivestreams/Subscription.cancel:()V
     202: aload_0
     203: getfield      #8                  // Field error:Ljava/util/concurrent/atomic/AtomicReference;
     206: aload         11
     208: invokestatic  #29                 // Method io/reactivex/rxjava3/internal/util/ExceptionHelper.addThrowable:(Ljava/util/concurrent/atomic/AtomicReference;Ljava/lang/Throwable;)Z
     211: pop
     212: aload_0
     213: getfield      #8                  // Field error:Ljava/util/concurrent/atomic/AtomicReference;
     216: invokestatic  #41                 // Method io/reactivex/rxjava3/internal/util/ExceptionHelper.terminate:(Ljava/util/concurrent/atomic/AtomicReference;)Ljava/lang/Throwable;
     219: astore        11
     221: aload_1
     222: aload         11
     224: invokeinterface #42,  2           // InterfaceMethod org/reactivestreams/Subscriber.onError:(Ljava/lang/Throwable;)V
     229: return
     230: iload         10
     232: ifne          246
     235: aconst_null
     236: astore        5
     238: aload_0
     239: iload_3
     240: invokevirtual #48                 // Method consumedOne:(Z)V
     243: goto          41
     246: aload_0
     247: aload         5
     249: putfield      #37                 // Field current:Ljava/util/Iterator;
     252: aload         5
     254: ifnull        556
     257: aload_0
     258: getfield      #11                 // Field requested:Ljava/util/concurrent/atomic/AtomicLong;
     261: invokevirtual #49                 // Method java/util/concurrent/atomic/AtomicLong.get:()J
     264: lstore        6
     266: lconst_0
     267: lstore        8
     269: lload         8
     271: lload         6
     273: lcmp
     274: ifeq          472
     277: aload_0
     278: aload_0
     279: getfield      #19                 // Field done:Z
     282: iconst_0
     283: aload_1
     284: aload_2
     285: invokevirtual #43                 // Method checkTerminated:(ZZLorg/reactivestreams/Subscriber;Lio/reactivex/rxjava3/operators/SimpleQueue;)Z
     288: ifeq          292
     291: return
     292: aload         5
     294: invokeinterface #50,  1           // InterfaceMethod java/util/Iterator.next:()Ljava/lang/Object;
     299: ldc           #51                 // String The iterator returned a null value
     301: invokestatic  #52                 // Method java/util/Objects.requireNonNull:(Ljava/lang/Object;Ljava/lang/String;)Ljava/lang/Object;
     304: astore        10
     306: goto          358
     309: astore        11
     311: aload         11
     313: invokestatic  #40                 // Method io/reactivex/rxjava3/exceptions/Exceptions.throwIfFatal:(Ljava/lang/Throwable;)V
     316: aload_0
     317: aconst_null
     318: putfield      #37                 // Field current:Ljava/util/Iterator;
     321: aload_0
     322: getfield      #12                 // Field upstream:Lorg/reactivestreams/Subscription;
     325: invokeinterface #34,  1           // InterfaceMethod org/reactivestreams/Subscription.cancel:()V
     330: aload_0
     331: getfield      #8                  // Field error:Ljava/util/concurrent/atomic/AtomicReference;
     334: aload         11
     336: invokestatic  #29                 // Method io/reactivex/rxjava3/internal/util/ExceptionHelper.addThrowable:(Ljava/util/concurrent/atomic/AtomicReference;Ljava/lang/Throwable;)Z
     339: pop
     340: aload_0
     341: getfield      #8                  // Field error:Ljava/util/concurrent/atomic/AtomicReference;
     344: invokestatic  #41                 // Method io/reactivex/rxjava3/internal/util/ExceptionHelper.terminate:(Ljava/util/concurrent/atomic/AtomicReference;)Ljava/lang/Throwable;
     347: astore        11
     349: aload_1
     350: aload         11
     352: invokeinterface #42,  2           // InterfaceMethod org/reactivestreams/Subscriber.onError:(Ljava/lang/Throwable;)V
     357: return
     358: aload_1
     359: aload         10
     361: invokeinterface #53,  2           // InterfaceMethod org/reactivestreams/Subscriber.onNext:(Ljava/lang/Object;)V
     366: aload_0
     367: aload_0
     368: getfield      #19                 // Field done:Z
     371: iconst_0
     372: aload_1
     373: aload_2
     374: invokevirtual #43                 // Method checkTerminated:(ZZLorg/reactivestreams/Subscriber;Lio/reactivex/rxjava3/operators/SimpleQueue;)Z
     377: ifeq          381
     380: return
     381: lload         8
     383: lconst_1
     384: ladd
     385: lstore        8
     387: aload         5
     389: invokeinterface #47,  1           // InterfaceMethod java/util/Iterator.hasNext:()Z
     394: istore        11
     396: goto          448
     399: astore        12
     401: aload         12
     403: invokestatic  #40                 // Method io/reactivex/rxjava3/exceptions/Exceptions.throwIfFatal:(Ljava/lang/Throwable;)V
     406: aload_0
     407: aconst_null
     408: putfield      #37                 // Field current:Ljava/util/Iterator;
     411: aload_0
     412: getfield      #12                 // Field upstream:Lorg/reactivestreams/Subscription;
     415: invokeinterface #34,  1           // InterfaceMethod org/reactivestreams/Subscription.cancel:()V
     420: aload_0
     421: getfield      #8                  // Field error:Ljava/util/concurrent/atomic/AtomicReference;
     424: aload         12
     426: invokestatic  #29                 // Method io/reactivex/rxjava3/internal/util/ExceptionHelper.addThrowable:(Ljava/util/concurrent/atomic/AtomicReference;Ljava/lang/Throwable;)Z
     429: pop
     430: aload_0
     431: getfield      #8                  // Field error:Ljava/util/concurrent/atomic/AtomicReference;
     434: invokestatic  #41                 // Method io/reactivex/rxjava3/internal/util/ExceptionHelper.terminate:(Ljava/util/concurrent/atomic/AtomicReference;)Ljava/lang/Throwable;
     437: astore        12
     439: aload_1
     440: aload         12
     442: invokeinterface #42,  2           // InterfaceMethod org/reactivestreams/Subscriber.onError:(Ljava/lang/Throwable;)V
     447: return
     448: iload         11
     450: ifne          469
     453: aload_0
     454: iload_3
     455: invokevirtual #48                 // Method consumedOne:(Z)V
     458: aconst_null
     459: astore        5
     461: aload_0
     462: aconst_null
     463: putfield      #37                 // Field current:Ljava/util/Iterator;
     466: goto          472
     469: goto          269
     472: lload         8
     474: lload         6
     476: lcmp
     477: ifne          521
     480: aload_0
     481: getfield      #19                 // Field done:Z
     484: istore        10
     486: aload_2
     487: invokeinterface #54,  1           // InterfaceMethod io/reactivex/rxjava3/operators/SimpleQueue.isEmpty:()Z
     492: ifeq          504
     495: aload         5
     497: ifnonnull     504
     500: iconst_1
     501: goto          505
     504: iconst_0
     505: istore        11
     507: aload_0
     508: iload         10
     510: iload         11
     512: aload_1
     513: aload_2
     514: invokevirtual #43                 // Method checkTerminated:(ZZLorg/reactivestreams/Subscriber;Lio/reactivex/rxjava3/operators/SimpleQueue;)Z
     517: ifeq          521
     520: return
     521: lload         8
     523: lconst_0
     524: lcmp
     525: ifeq          548
     528: lload         6
     530: ldc2_w        #56                 // long 9223372036854775807l
     533: lcmp
     534: ifeq          548
     537: aload_0
     538: getfield      #11                 // Field requested:Ljava/util/concurrent/atomic/AtomicLong;
     541: lload         8
     543: lneg
     544: invokevirtual #58                 // Method java/util/concurrent/atomic/AtomicLong.addAndGet:(J)J
     547: pop2
     548: aload         5
     550: ifnonnull     556
     553: goto          41
     556: aload_0
     557: iload         4
     559: ineg
     560: invokevirtual #59                 // Method addAndGet:(I)I
     563: istore        4
     565: iload         4
     567: ifne          41
     570: goto          573
     573: return
    Exception table:
       from    to  target type
          52    60    63   Class java/lang/Throwable
         149   183   186   Class java/lang/Throwable
         292   306   309   Class java/lang/Throwable
         387   396   399   Class java/lang/Throwable

  void consumedOne(boolean);
    Code:
       0: iload_1
       1: ifeq          43
       4: aload_0
       5: getfield      #60                 // Field consumed:I
       8: iconst_1
       9: iadd
      10: istore_2
      11: iload_2
      12: aload_0
      13: getfield      #5                  // Field limit:I
      16: if_icmpne     38
      19: aload_0
      20: iconst_0
      21: putfield      #60                 // Field consumed:I
      24: aload_0
      25: getfield      #12                 // Field upstream:Lorg/reactivestreams/Subscription;
      28: iload_2
      29: i2l
      30: invokeinterface #21,  3           // InterfaceMethod org/reactivestreams/Subscription.request:(J)V
      35: goto          43
      38: aload_0
      39: iload_2
      40: putfield      #60                 // Field consumed:I
      43: return

  boolean checkTerminated(boolean, boolean, org.reactivestreams.Subscriber<?>, io.reactivex.rxjava3.operators.SimpleQueue<?>);
    Code:
       0: aload_0
       1: getfield      #33                 // Field cancelled:Z
       4: ifeq          21
       7: aload_0
       8: aconst_null
       9: putfield      #37                 // Field current:Ljava/util/Iterator;
      12: aload         4
      14: invokeinterface #36,  1           // InterfaceMethod io/reactivex/rxjava3/operators/SimpleQueue.clear:()V
      19: iconst_1
      20: ireturn
      21: iload_1
      22: ifeq          85
      25: aload_0
      26: getfield      #8                  // Field error:Ljava/util/concurrent/atomic/AtomicReference;
      29: invokevirtual #61                 // Method java/util/concurrent/atomic/AtomicReference.get:()Ljava/lang/Object;
      32: checkcast     #39                 // class java/lang/Throwable
      35: astore        5
      37: aload         5
      39: ifnull        73
      42: aload_0
      43: getfield      #8                  // Field error:Ljava/util/concurrent/atomic/AtomicReference;
      46: invokestatic  #41                 // Method io/reactivex/rxjava3/internal/util/ExceptionHelper.terminate:(Ljava/util/concurrent/atomic/AtomicReference;)Ljava/lang/Throwable;
      49: astore        5
      51: aload_0
      52: aconst_null
      53: putfield      #37                 // Field current:Ljava/util/Iterator;
      56: aload         4
      58: invokeinterface #36,  1           // InterfaceMethod io/reactivex/rxjava3/operators/SimpleQueue.clear:()V
      63: aload_3
      64: aload         5
      66: invokeinterface #42,  2           // InterfaceMethod org/reactivestreams/Subscriber.onError:(Ljava/lang/Throwable;)V
      71: iconst_1
      72: ireturn
      73: iload_2
      74: ifeq          85
      77: aload_3
      78: invokeinterface #62,  1           // InterfaceMethod org/reactivestreams/Subscriber.onComplete:()V
      83: iconst_1
      84: ireturn
      85: iconst_0
      86: ireturn

  public void clear();
    Code:
       0: aload_0
       1: aconst_null
       2: putfield      #37                 // Field current:Ljava/util/Iterator;
       5: aload_0
       6: getfield      #18                 // Field queue:Lio/reactivex/rxjava3/operators/SimpleQueue;
       9: invokeinterface #36,  1           // InterfaceMethod io/reactivex/rxjava3/operators/SimpleQueue.clear:()V
      14: return

  public boolean isEmpty();
    Code:
       0: aload_0
       1: getfield      #37                 // Field current:Ljava/util/Iterator;
       4: ifnonnull     23
       7: aload_0
       8: getfield      #18                 // Field queue:Lio/reactivex/rxjava3/operators/SimpleQueue;
      11: invokeinterface #54,  1           // InterfaceMethod io/reactivex/rxjava3/operators/SimpleQueue.isEmpty:()Z
      16: ifeq          23
      19: iconst_1
      20: goto          24
      23: iconst_0
      24: ireturn

  public R poll() throws java.lang.Throwable;
    Code:
       0: aload_0
       1: getfield      #37                 // Field current:Ljava/util/Iterator;
       4: astore_1
       5: aload_1
       6: ifnonnull     63
       9: aload_0
      10: getfield      #18                 // Field queue:Lio/reactivex/rxjava3/operators/SimpleQueue;
      13: invokeinterface #38,  1           // InterfaceMethod io/reactivex/rxjava3/operators/SimpleQueue.poll:()Ljava/lang/Object;
      18: astore_2
      19: aload_2
      20: ifnonnull     25
      23: aconst_null
      24: areturn
      25: aload_0
      26: getfield      #3                  // Field mapper:Lio/reactivex/rxjava3/functions/Function;
      29: aload_2
      30: invokeinterface #44,  2           // InterfaceMethod io/reactivex/rxjava3/functions/Function.apply:(Ljava/lang/Object;)Ljava/lang/Object;
      35: checkcast     #45                 // class java/lang/Iterable
      38: invokeinterface #46,  1           // InterfaceMethod java/lang/Iterable.iterator:()Ljava/util/Iterator;
      43: astore_1
      44: aload_1
      45: invokeinterface #47,  1           // InterfaceMethod java/util/Iterator.hasNext:()Z
      50: ifne          58
      53: aconst_null
      54: astore_1
      55: goto          5
      58: aload_0
      59: aload_1
      60: putfield      #37                 // Field current:Ljava/util/Iterator;
      63: aload_1
      64: invokeinterface #50,  1           // InterfaceMethod java/util/Iterator.next:()Ljava/lang/Object;
      69: ldc           #51                 // String The iterator returned a null value
      71: invokestatic  #52                 // Method java/util/Objects.requireNonNull:(Ljava/lang/Object;Ljava/lang/String;)Ljava/lang/Object;
      74: astore_2
      75: aload_1
      76: invokeinterface #47,  1           // InterfaceMethod java/util/Iterator.hasNext:()Z
      81: ifne          89
      84: aload_0
      85: aconst_null
      86: putfield      #37                 // Field current:Ljava/util/Iterator;
      89: aload_2
      90: areturn

  public int requestFusion(int);
    Code:
       0: iload_1
       1: iconst_1
       2: iand
       3: ifeq          16
       6: aload_0
       7: getfield      #17                 // Field fusionMode:I
      10: iconst_1
      11: if_icmpne     16
      14: iconst_1
      15: ireturn
      16: iconst_0
      17: ireturn
}
