Compiled from "FlowableFromArray.java"
public final class io.reactivex.rxjava3.internal.operators.flowable.FlowableFromArray<T> extends io.reactivex.rxjava3.core.Flowable<T> {
  final T[] array;

  public io.reactivex.rxjava3.internal.operators.flowable.FlowableFromArray(T[]);
    Code:
       0: aload_0
       1: invokespecial #1                  // Method io/reactivex/rxjava3/core/Flowable."<init>":()V
       4: aload_0
       5: aload_1
       6: putfield      #2                  // Field array:[Ljava/lang/Object;
       9: return

  public void subscribeActual(org.reactivestreams.Subscriber<? super T>);
    Code:
       0: aload_1
       1: instanceof    #3                  // class io/reactivex/rxjava3/operators/ConditionalSubscriber
       4: ifeq          31
       7: aload_1
       8: new           #4                  // class io/reactivex/rxjava3/internal/operators/flowable/FlowableFromArray$ArrayConditionalSubscription
      11: dup
      12: aload_1
      13: checkcast     #3                  // class io/reactivex/rxjava3/operators/ConditionalSubscriber
      16: aload_0
      17: getfield      #2                  // Field array:[Ljava/lang/Object;
      20: invokespecial #5                  // Method io/reactivex/rxjava3/internal/operators/flowable/FlowableFromArray$ArrayConditionalSubscription."<init>":(Lio/reactivex/rxjava3/operators/ConditionalSubscriber;[Ljava/lang/Object;)V
      23: invokeinterface #6,  2            // InterfaceMethod org/reactivestreams/Subscriber.onSubscribe:(Lorg/reactivestreams/Subscription;)V
      28: goto          49
      31: aload_1
      32: new           #7                  // class io/reactivex/rxjava3/internal/operators/flowable/FlowableFromArray$ArraySubscription
      35: dup
      36: aload_1
      37: aload_0
      38: getfield      #2                  // Field array:[Ljava/lang/Object;
      41: invokespecial #8                  // Method io/reactivex/rxjava3/internal/operators/flowable/FlowableFromArray$ArraySubscription."<init>":(Lorg/reactivestreams/Subscriber;[Ljava/lang/Object;)V
      44: invokeinterface #6,  2            // InterfaceMethod org/reactivestreams/Subscriber.onSubscribe:(Lorg/reactivestreams/Subscription;)V
      49: return
}
