Compiled from "FlowableJust.java"
public final class io.reactivex.rxjava3.internal.operators.flowable.FlowableJust<T> extends io.reactivex.rxjava3.core.Flowable<T> implements io.reactivex.rxjava3.operators.ScalarSupplier<T> {
  private final T value;

  public io.reactivex.rxjava3.internal.operators.flowable.FlowableJust(T);
    Code:
       0: aload_0
       1: invokespecial #1                  // Method io/reactivex/rxjava3/core/Flowable."<init>":()V
       4: aload_0
       5: aload_1
       6: putfield      #2                  // Field value:Ljava/lang/Object;
       9: return

  protected void subscribeActual(org.reactivestreams.Subscriber<? super T>);
    Code:
       0: aload_1
       1: new           #3                  // class io/reactivex/rxjava3/internal/subscriptions/ScalarSubscription
       4: dup
       5: aload_1
       6: aload_0
       7: getfield      #2                  // Field value:Ljava/lang/Object;
      10: invokespecial #4                  // Method io/reactivex/rxjava3/internal/subscriptions/ScalarSubscription."<init>":(Lorg/reactivestreams/Subscriber;Ljava/lang/Object;)V
      13: invokeinterface #5,  2            // InterfaceMethod org/reactivestreams/Subscriber.onSubscribe:(Lorg/reactivestreams/Subscription;)V
      18: return

  public T get();
    Code:
       0: aload_0
       1: getfield      #2                  // Field value:Ljava/lang/Object;
       4: areturn
}
