Compiled from "FlowableDebounce.java"
public final class io.reactivex.rxjava3.internal.operators.flowable.FlowableDebounce<T, U> extends io.reactivex.rxjava3.internal.operators.flowable.AbstractFlowableWithUpstream<T, T> {
  final io.reactivex.rxjava3.functions.Function<? super T, ? extends org.reactivestreams.Publisher<U>> debounceSelector;

  public io.reactivex.rxjava3.internal.operators.flowable.FlowableDebounce(io.reactivex.rxjava3.core.Flowable<T>, io.reactivex.rxjava3.functions.Function<? super T, ? extends org.reactivestreams.Publisher<U>>);
    Code:
       0: aload_0
       1: aload_1
       2: invokespecial #1                  // Method io/reactivex/rxjava3/internal/operators/flowable/AbstractFlowableWithUpstream."<init>":(Lio/reactivex/rxjava3/core/Flowable;)V
       5: aload_0
       6: aload_2
       7: putfield      #2                  // Field debounceSelector:Lio/reactivex/rxjava3/functions/Function;
      10: return

  protected void subscribeActual(org.reactivestreams.Subscriber<? super T>);
    Code:
       0: aload_0
       1: getfield      #3                  // Field source:Lio/reactivex/rxjava3/core/Flowable;
       4: new           #4                  // class io/reactivex/rxjava3/internal/operators/flowable/FlowableDebounce$DebounceSubscriber
       7: dup
       8: new           #5                  // class io/reactivex/rxjava3/subscribers/SerializedSubscriber
      11: dup
      12: aload_1
      13: invokespecial #6                  // Method io/reactivex/rxjava3/subscribers/SerializedSubscriber."<init>":(Lorg/reactivestreams/Subscriber;)V
      16: aload_0
      17: getfield      #2                  // Field debounceSelector:Lio/reactivex/rxjava3/functions/Function;
      20: invokespecial #7                  // Method io/reactivex/rxjava3/internal/operators/flowable/FlowableDebounce$DebounceSubscriber."<init>":(Lorg/reactivestreams/Subscriber;Lio/reactivex/rxjava3/functions/Function;)V
      23: invokevirtual #8                  // Method io/reactivex/rxjava3/core/Flowable.subscribe:(Lio/reactivex/rxjava3/core/FlowableSubscriber;)V
      26: return
}
