Compiled from "FlowableSamplePublisher.java"
final class io.reactivex.rxjava3.internal.operators.flowable.FlowableSamplePublisher$SampleMainNoLast<T> extends io.reactivex.rxjava3.internal.operators.flowable.FlowableSamplePublisher$SamplePublisherSubscriber<T> {
  private static final long serialVersionUID;

  io.reactivex.rxjava3.internal.operators.flowable.FlowableSamplePublisher$SampleMainNoLast(org.reactivestreams.Subscriber<? super T>, org.reactivestreams.Publisher<?>);
    Code:
       0: aload_0
       1: aload_1
       2: aload_2
       3: invokespecial #1                  // Method io/reactivex/rxjava3/internal/operators/flowable/FlowableSamplePublisher$SamplePublisherSubscriber."<init>":(Lorg/reactivestreams/Subscriber;Lorg/reactivestreams/Publisher;)V
       6: return

  void completion();
    Code:
       0: aload_0
       1: getfield      #2                  // Field downstream:Lorg/reactivestreams/Subscriber;
       4: invokeinterface #3,  1            // InterfaceMethod org/reactivestreams/Subscriber.onComplete:()V
       9: return

  void run();
    Code:
       0: aload_0
       1: invokevirtual #4                  // Method emit:()V
       4: return
}
