Compiled from "FlowableDistinct.java"
final class io.reactivex.rxjava3.internal.operators.flowable.FlowableDistinct$DistinctSubscriber<T, K> extends io.reactivex.rxjava3.internal.subscribers.BasicFuseableSubscriber<T, T> {
  final java.util.Collection<? super K> collection;

  final io.reactivex.rxjava3.functions.Function<? super T, K> keySelector;

  io.reactivex.rxjava3.internal.operators.flowable.FlowableDistinct$DistinctSubscriber(org.reactivestreams.Subscriber<? super T>, io.reactivex.rxjava3.functions.Function<? super T, K>, java.util.Collection<? super K>);
    Code:
       0: aload_0
       1: aload_1
       2: invokespecial #1                  // Method io/reactivex/rxjava3/internal/subscribers/BasicFuseableSubscriber."<init>":(Lorg/reactivestreams/Subscriber;)V
       5: aload_0
       6: aload_2
       7: putfield      #2                  // Field keySelector:Lio/reactivex/rxjava3/functions/Function;
      10: aload_0
      11: aload_3
      12: putfield      #3                  // Field collection:Ljava/util/Collection;
      15: return

  public void onNext(T);
    Code:
       0: aload_0
       1: getfield      #4                  // Field done:Z
       4: ifeq          8
       7: return
       8: aload_0
       9: getfield      #5                  // Field sourceMode:I
      12: ifne          84
      15: aload_0
      16: getfield      #2                  // Field keySelector:Lio/reactivex/rxjava3/functions/Function;
      19: aload_1
      20: invokeinterface #6,  2            // InterfaceMethod io/reactivex/rxjava3/functions/Function.apply:(Ljava/lang/Object;)Ljava/lang/Object;
      25: ldc           #7                  // String The keySelector returned a null key
      27: invokestatic  #8                  // Method java/util/Objects.requireNonNull:(Ljava/lang/Object;Ljava/lang/String;)Ljava/lang/Object;
      30: astore_2
      31: aload_0
      32: getfield      #3                  // Field collection:Ljava/util/Collection;
      35: aload_2
      36: invokeinterface #9,  2            // InterfaceMethod java/util/Collection.add:(Ljava/lang/Object;)Z
      41: istore_3
      42: goto          54
      45: astore        4
      47: aload_0
      48: aload         4
      50: invokevirtual #11                 // Method fail:(Ljava/lang/Throwable;)V
      53: return
      54: iload_3
      55: ifeq          71
      58: aload_0
      59: getfield      #12                 // Field downstream:Lorg/reactivestreams/Subscriber;
      62: aload_1
      63: invokeinterface #13,  2           // InterfaceMethod org/reactivestreams/Subscriber.onNext:(Ljava/lang/Object;)V
      68: goto          81
      71: aload_0
      72: getfield      #14                 // Field upstream:Lorg/reactivestreams/Subscription;
      75: lconst_1
      76: invokeinterface #15,  3           // InterfaceMethod org/reactivestreams/Subscription.request:(J)V
      81: goto          94
      84: aload_0
      85: getfield      #12                 // Field downstream:Lorg/reactivestreams/Subscriber;
      88: aconst_null
      89: invokeinterface #13,  2           // InterfaceMethod org/reactivestreams/Subscriber.onNext:(Ljava/lang/Object;)V
      94: return
    Exception table:
       from    to  target type
          15    42    45   Class java/lang/Throwable

  public void onError(java.lang.Throwable);
    Code:
       0: aload_0
       1: getfield      #4                  // Field done:Z
       4: ifeq          14
       7: aload_1
       8: invokestatic  #16                 // Method io/reactivex/rxjava3/plugins/RxJavaPlugins.onError:(Ljava/lang/Throwable;)V
      11: goto          38
      14: aload_0
      15: iconst_1
      16: putfield      #4                  // Field done:Z
      19: aload_0
      20: getfield      #3                  // Field collection:Ljava/util/Collection;
      23: invokeinterface #17,  1           // InterfaceMethod java/util/Collection.clear:()V
      28: aload_0
      29: getfield      #12                 // Field downstream:Lorg/reactivestreams/Subscriber;
      32: aload_1
      33: invokeinterface #18,  2           // InterfaceMethod org/reactivestreams/Subscriber.onError:(Ljava/lang/Throwable;)V
      38: return

  public void onComplete();
    Code:
       0: aload_0
       1: getfield      #4                  // Field done:Z
       4: ifne          30
       7: aload_0
       8: iconst_1
       9: putfield      #4                  // Field done:Z
      12: aload_0
      13: getfield      #3                  // Field collection:Ljava/util/Collection;
      16: invokeinterface #17,  1           // InterfaceMethod java/util/Collection.clear:()V
      21: aload_0
      22: getfield      #12                 // Field downstream:Lorg/reactivestreams/Subscriber;
      25: invokeinterface #19,  1           // InterfaceMethod org/reactivestreams/Subscriber.onComplete:()V
      30: return

  public int requestFusion(int);
    Code:
       0: aload_0
       1: iload_1
       2: invokevirtual #20                 // Method transitiveBoundaryFusion:(I)I
       5: ireturn

  public T poll() throws java.lang.Throwable;
    Code:
       0: aload_0
       1: getfield      #21                 // Field qs:Lio/reactivex/rxjava3/operators/QueueSubscription;
       4: invokeinterface #22,  1           // InterfaceMethod io/reactivex/rxjava3/operators/QueueSubscription.poll:()Ljava/lang/Object;
       9: astore_1
      10: aload_1
      11: ifnull        41
      14: aload_0
      15: getfield      #3                  // Field collection:Ljava/util/Collection;
      18: aload_0
      19: getfield      #2                  // Field keySelector:Lio/reactivex/rxjava3/functions/Function;
      22: aload_1
      23: invokeinterface #6,  2            // InterfaceMethod io/reactivex/rxjava3/functions/Function.apply:(Ljava/lang/Object;)Ljava/lang/Object;
      28: ldc           #7                  // String The keySelector returned a null key
      30: invokestatic  #8                  // Method java/util/Objects.requireNonNull:(Ljava/lang/Object;Ljava/lang/String;)Ljava/lang/Object;
      33: invokeinterface #9,  2            // InterfaceMethod java/util/Collection.add:(Ljava/lang/Object;)Z
      38: ifeq          43
      41: aload_1
      42: areturn
      43: aload_0
      44: getfield      #5                  // Field sourceMode:I
      47: iconst_2
      48: if_icmpne     61
      51: aload_0
      52: getfield      #14                 // Field upstream:Lorg/reactivestreams/Subscription;
      55: lconst_1
      56: invokeinterface #15,  3           // InterfaceMethod org/reactivestreams/Subscription.request:(J)V
      61: goto          0

  public void clear();
    Code:
       0: aload_0
       1: getfield      #3                  // Field collection:Ljava/util/Collection;
       4: invokeinterface #17,  1           // InterfaceMethod java/util/Collection.clear:()V
       9: aload_0
      10: invokespecial #24                 // Method io/reactivex/rxjava3/internal/subscribers/BasicFuseableSubscriber.clear:()V
      13: return
}
