Compiled from "FlowableToList.java"
final class io.reactivex.rxjava3.internal.operators.flowable.FlowableToList$ToListSubscriber<T, U extends java.util.Collection<? super T>> extends io.reactivex.rxjava3.internal.subscriptions.DeferredScalarSubscription<U> implements io.reactivex.rxjava3.core.FlowableSubscriber<T> {
  private static final long serialVersionUID;

  org.reactivestreams.Subscription upstream;

  io.reactivex.rxjava3.internal.operators.flowable.FlowableToList$ToListSubscriber(org.reactivestreams.Subscriber<? super U>, U);
    Code:
       0: aload_0
       1: aload_1
       2: invokespecial #1                  // Method io/reactivex/rxjava3/internal/subscriptions/DeferredScalarSubscription."<init>":(Lorg/reactivestreams/Subscriber;)V
       5: aload_0
       6: aload_2
       7: putfield      #2                  // Field value:Ljava/lang/Object;
      10: return

  public void onSubscribe(org.reactivestreams.Subscription);
    Code:
       0: aload_0
       1: getfield      #3                  // Field upstream:Lorg/reactivestreams/Subscription;
       4: aload_1
       5: invokestatic  #4                  // Method io/reactivex/rxjava3/internal/subscriptions/SubscriptionHelper.validate:(Lorg/reactivestreams/Subscription;Lorg/reactivestreams/Subscription;)Z
       8: ifeq          35
      11: aload_0
      12: aload_1
      13: putfield      #3                  // Field upstream:Lorg/reactivestreams/Subscription;
      16: aload_0
      17: getfield      #5                  // Field downstream:Lorg/reactivestreams/Subscriber;
      20: aload_0
      21: invokeinterface #6,  2            // InterfaceMethod org/reactivestreams/Subscriber.onSubscribe:(Lorg/reactivestreams/Subscription;)V
      26: aload_1
      27: ldc2_w        #8                  // long 9223372036854775807l
      30: invokeinterface #10,  3           // InterfaceMethod org/reactivestreams/Subscription.request:(J)V
      35: return

  public void onNext(T);
    Code:
       0: aload_0
       1: getfield      #2                  // Field value:Ljava/lang/Object;
       4: checkcast     #11                 // class java/util/Collection
       7: astore_2
       8: aload_2
       9: ifnull        20
      12: aload_2
      13: aload_1
      14: invokeinterface #12,  2           // InterfaceMethod java/util/Collection.add:(Ljava/lang/Object;)Z
      19: pop
      20: return

  public void onError(java.lang.Throwable);
    Code:
       0: aload_0
       1: aconst_null
       2: putfield      #2                  // Field value:Ljava/lang/Object;
       5: aload_0
       6: getfield      #5                  // Field downstream:Lorg/reactivestreams/Subscriber;
       9: aload_1
      10: invokeinterface #13,  2           // InterfaceMethod org/reactivestreams/Subscriber.onError:(Ljava/lang/Throwable;)V
      15: return

  public void onComplete();
    Code:
       0: aload_0
       1: aload_0
       2: getfield      #2                  // Field value:Ljava/lang/Object;
       5: invokevirtual #14                 // Method complete:(Ljava/lang/Object;)V
       8: return

  public void cancel();
    Code:
       0: aload_0
       1: invokespecial #15                 // Method io/reactivex/rxjava3/internal/subscriptions/DeferredScalarSubscription.cancel:()V
       4: aload_0
       5: getfield      #3                  // Field upstream:Lorg/reactivestreams/Subscription;
       8: invokeinterface #16,  1           // InterfaceMethod org/reactivestreams/Subscription.cancel:()V
      13: return
}
