Compiled from "FlowableWindowBoundarySelector.java"
final class io.reactivex.rxjava3.internal.operators.flowable.FlowableWindowBoundarySelector$WindowBoundaryMainSubscriber$WindowStartSubscriber<B> extends java.util.concurrent.atomic.AtomicReference<org.reactivestreams.Subscription> implements io.reactivex.rxjava3.core.FlowableSubscriber<B> {
  private static final long serialVersionUID;

  final io.reactivex.rxjava3.internal.operators.flowable.FlowableWindowBoundarySelector$WindowBoundaryMainSubscriber<?, B, ?> parent;

  io.reactivex.rxjava3.internal.operators.flowable.FlowableWindowBoundarySelector$WindowBoundaryMainSubscriber$WindowStartSubscriber(io.reactivex.rxjava3.internal.operators.flowable.FlowableWindowBoundarySelector$WindowBoundaryMainSubscriber<?, B, ?>);
    Code:
       0: aload_0
       1: invokespecial #1                  // Method java/util/concurrent/atomic/AtomicReference."<init>":()V
       4: aload_0
       5: aload_1
       6: putfield      #2                  // Field parent:Lio/reactivex/rxjava3/internal/operators/flowable/FlowableWindowBoundarySelector$WindowBoundaryMainSubscriber;
       9: return

  public void onSubscribe(org.reactivestreams.Subscription);
    Code:
       0: aload_0
       1: aload_1
       2: invokestatic  #3                  // Method io/reactivex/rxjava3/internal/subscriptions/SubscriptionHelper.setOnce:(Ljava/util/concurrent/atomic/AtomicReference;Lorg/reactivestreams/Subscription;)Z
       5: ifeq          17
       8: aload_1
       9: ldc2_w        #5                  // long 9223372036854775807l
      12: invokeinterface #7,  3            // InterfaceMethod org/reactivestreams/Subscription.request:(J)V
      17: return

  public void onNext(B);
    Code:
       0: aload_0
       1: getfield      #2                  // Field parent:Lio/reactivex/rxjava3/internal/operators/flowable/FlowableWindowBoundarySelector$WindowBoundaryMainSubscriber;
       4: aload_1
       5: invokevirtual #8                  // Method io/reactivex/rxjava3/internal/operators/flowable/FlowableWindowBoundarySelector$WindowBoundaryMainSubscriber.open:(Ljava/lang/Object;)V
       8: return

  public void onError(java.lang.Throwable);
    Code:
       0: aload_0
       1: getfield      #2                  // Field parent:Lio/reactivex/rxjava3/internal/operators/flowable/FlowableWindowBoundarySelector$WindowBoundaryMainSubscriber;
       4: aload_1
       5: invokevirtual #9                  // Method io/reactivex/rxjava3/internal/operators/flowable/FlowableWindowBoundarySelector$WindowBoundaryMainSubscriber.openError:(Ljava/lang/Throwable;)V
       8: return

  public void onComplete();
    Code:
       0: aload_0
       1: getfield      #2                  // Field parent:Lio/reactivex/rxjava3/internal/operators/flowable/FlowableWindowBoundarySelector$WindowBoundaryMainSubscriber;
       4: invokevirtual #10                 // Method io/reactivex/rxjava3/internal/operators/flowable/FlowableWindowBoundarySelector$WindowBoundaryMainSubscriber.openComplete:()V
       7: return

  void cancel();
    Code:
       0: aload_0
       1: invokestatic  #11                 // Method io/reactivex/rxjava3/internal/subscriptions/SubscriptionHelper.cancel:(Ljava/util/concurrent/atomic/AtomicReference;)Z
       4: pop
       5: return
}
