Compiled from "FlowableWithLatestFrom.java"
final class io.reactivex.rxjava3.internal.operators.flowable.FlowableWithLatestFrom$FlowableWithLatestSubscriber implements io.reactivex.rxjava3.core.FlowableSubscriber<U> {
  private final io.reactivex.rxjava3.internal.operators.flowable.FlowableWithLatestFrom$WithLatestFromSubscriber<T, U, R> wlf;

  final io.reactivex.rxjava3.internal.operators.flowable.FlowableWithLatestFrom this$0;

  io.reactivex.rxjava3.internal.operators.flowable.FlowableWithLatestFrom$FlowableWithLatestSubscriber(io.reactivex.rxjava3.internal.operators.flowable.FlowableWithLatestFrom$WithLatestFromSubscriber<T, U, R>);
    Code:
       0: aload_0
       1: aload_1
       2: putfield      #1                  // Field this$0:Lio/reactivex/rxjava3/internal/operators/flowable/FlowableWithLatestFrom;
       5: aload_0
       6: invokespecial #2                  // Method java/lang/Object."<init>":()V
       9: aload_0
      10: aload_2
      11: putfield      #3                  // Field wlf:Lio/reactivex/rxjava3/internal/operators/flowable/FlowableWithLatestFrom$WithLatestFromSubscriber;
      14: return

  public void onSubscribe(org.reactivestreams.Subscription);
    Code:
       0: aload_0
       1: getfield      #3                  // Field wlf:Lio/reactivex/rxjava3/internal/operators/flowable/FlowableWithLatestFrom$WithLatestFromSubscriber;
       4: aload_1
       5: invokevirtual #4                  // Method io/reactivex/rxjava3/internal/operators/flowable/FlowableWithLatestFrom$WithLatestFromSubscriber.setOther:(Lorg/reactivestreams/Subscription;)Z
       8: ifeq          20
      11: aload_1
      12: ldc2_w        #6                  // long 9223372036854775807l
      15: invokeinterface #8,  3            // InterfaceMethod org/reactivestreams/Subscription.request:(J)V
      20: return

  public void onNext(U);
    Code:
       0: aload_0
       1: getfield      #3                  // Field wlf:Lio/reactivex/rxjava3/internal/operators/flowable/FlowableWithLatestFrom$WithLatestFromSubscriber;
       4: aload_1
       5: invokevirtual #9                  // Method io/reactivex/rxjava3/internal/operators/flowable/FlowableWithLatestFrom$WithLatestFromSubscriber.lazySet:(Ljava/lang/Object;)V
       8: return

  public void onError(java.lang.Throwable);
    Code:
       0: aload_0
       1: getfield      #3                  // Field wlf:Lio/reactivex/rxjava3/internal/operators/flowable/FlowableWithLatestFrom$WithLatestFromSubscriber;
       4: aload_1
       5: invokevirtual #10                 // Method io/reactivex/rxjava3/internal/operators/flowable/FlowableWithLatestFrom$WithLatestFromSubscriber.otherError:(Ljava/lang/Throwable;)V
       8: return

  public void onComplete();
    Code:
       0: return
}
