Compiled from "FlowableWindowBoundarySelector.java"
public final class io.reactivex.rxjava3.internal.operators.flowable.FlowableWindowBoundarySelector<T, B, V> extends io.reactivex.rxjava3.internal.operators.flowable.AbstractFlowableWithUpstream<T, io.reactivex.rxjava3.core.Flowable<T>> {
  final org.reactivestreams.Publisher<B> open;

  final io.reactivex.rxjava3.functions.Function<? super B, ? extends org.reactivestreams.Publisher<V>> closingIndicator;

  final int bufferSize;

  public io.reactivex.rxjava3.internal.operators.flowable.FlowableWindowBoundarySelector(io.reactivex.rxjava3.core.Flowable<T>, org.reactivestreams.Publisher<B>, io.reactivex.rxjava3.functions.Function<? super B, ? extends org.reactivestreams.Publisher<V>>, int);
    Code:
       0: aload_0
       1: aload_1
       2: invokespecial #1                  // Method io/reactivex/rxjava3/internal/operators/flowable/AbstractFlowableWithUpstream."<init>":(Lio/reactivex/rxjava3/core/Flowable;)V
       5: aload_0
       6: aload_2
       7: putfield      #2                  // Field open:Lorg/reactivestreams/Publisher;
      10: aload_0
      11: aload_3
      12: putfield      #3                  // Field closingIndicator:Lio/reactivex/rxjava3/functions/Function;
      15: aload_0
      16: iload         4
      18: putfield      #4                  // Field bufferSize:I
      21: return

  protected void subscribeActual(org.reactivestreams.Subscriber<? super io.reactivex.rxjava3.core.Flowable<T>>);
    Code:
       0: aload_0
       1: getfield      #5                  // Field source:Lio/reactivex/rxjava3/core/Flowable;
       4: new           #6                  // class io/reactivex/rxjava3/internal/operators/flowable/FlowableWindowBoundarySelector$WindowBoundaryMainSubscriber
       7: dup
       8: aload_1
       9: aload_0
      10: getfield      #2                  // Field open:Lorg/reactivestreams/Publisher;
      13: aload_0
      14: getfield      #3                  // Field closingIndicator:Lio/reactivex/rxjava3/functions/Function;
      17: aload_0
      18: getfield      #4                  // Field bufferSize:I
      21: invokespecial #7                  // Method io/reactivex/rxjava3/internal/operators/flowable/FlowableWindowBoundarySelector$WindowBoundaryMainSubscriber."<init>":(Lorg/reactivestreams/Subscriber;Lorg/reactivestreams/Publisher;Lio/reactivex/rxjava3/functions/Function;I)V
      24: invokevirtual #8                  // Method io/reactivex/rxjava3/core/Flowable.subscribe:(Lio/reactivex/rxjava3/core/FlowableSubscriber;)V
      27: return
}
