Compiled from "FlowableFlatMapCompletable.java"
final class io.reactivex.rxjava3.internal.operators.flowable.FlowableFlatMapCompletable$FlatMapCompletableMainSubscriber<T> extends io.reactivex.rxjava3.internal.subscriptions.BasicIntQueueSubscription<T> implements io.reactivex.rxjava3.core.FlowableSubscriber<T> {
  private static final long serialVersionUID;

  final org.reactivestreams.Subscriber<? super T> downstream;

  final io.reactivex.rxjava3.internal.util.AtomicThrowable errors;

  final io.reactivex.rxjava3.functions.Function<? super T, ? extends io.reactivex.rxjava3.core.CompletableSource> mapper;

  final boolean delayErrors;

  final io.reactivex.rxjava3.disposables.CompositeDisposable set;

  final int maxConcurrency;

  org.reactivestreams.Subscription upstream;

  volatile boolean cancelled;

  io.reactivex.rxjava3.internal.operators.flowable.FlowableFlatMapCompletable$FlatMapCompletableMainSubscriber(org.reactivestreams.Subscriber<? super T>, io.reactivex.rxjava3.functions.Function<? super T, ? extends io.reactivex.rxjava3.core.CompletableSource>, boolean, int);
    Code:
       0: aload_0
       1: invokespecial #1                  // Method io/reactivex/rxjava3/internal/subscriptions/BasicIntQueueSubscription."<init>":()V
       4: aload_0
       5: aload_1
       6: putfield      #2                  // Field downstream:Lorg/reactivestreams/Subscriber;
       9: aload_0
      10: aload_2
      11: putfield      #3                  // Field mapper:Lio/reactivex/rxjava3/functions/Function;
      14: aload_0
      15: iload_3
      16: putfield      #4                  // Field delayErrors:Z
      19: aload_0
      20: new           #5                  // class io/reactivex/rxjava3/internal/util/AtomicThrowable
      23: dup
      24: invokespecial #6                  // Method io/reactivex/rxjava3/internal/util/AtomicThrowable."<init>":()V
      27: putfield      #7                  // Field errors:Lio/reactivex/rxjava3/internal/util/AtomicThrowable;
      30: aload_0
      31: new           #8                  // class io/reactivex/rxjava3/disposables/CompositeDisposable
      34: dup
      35: invokespecial #9                  // Method io/reactivex/rxjava3/disposables/CompositeDisposable."<init>":()V
      38: putfield      #10                 // Field set:Lio/reactivex/rxjava3/disposables/CompositeDisposable;
      41: aload_0
      42: iload         4
      44: putfield      #11                 // Field maxConcurrency:I
      47: aload_0
      48: iconst_1
      49: invokevirtual #12                 // Method lazySet:(I)V
      52: return

  public void onSubscribe(org.reactivestreams.Subscription);
    Code:
       0: aload_0
       1: getfield      #13                 // Field upstream:Lorg/reactivestreams/Subscription;
       4: aload_1
       5: invokestatic  #14                 // Method io/reactivex/rxjava3/internal/subscriptions/SubscriptionHelper.validate:(Lorg/reactivestreams/Subscription;Lorg/reactivestreams/Subscription;)Z
       8: ifeq          57
      11: aload_0
      12: aload_1
      13: putfield      #13                 // Field upstream:Lorg/reactivestreams/Subscription;
      16: aload_0
      17: getfield      #2                  // Field downstream:Lorg/reactivestreams/Subscriber;
      20: aload_0
      21: invokeinterface #15,  2           // InterfaceMethod org/reactivestreams/Subscriber.onSubscribe:(Lorg/reactivestreams/Subscription;)V
      26: aload_0
      27: getfield      #11                 // Field maxConcurrency:I
      30: istore_2
      31: iload_2
      32: ldc           #17                 // int 2147483647
      34: if_icmpne     49
      37: aload_1
      38: ldc2_w        #19                 // long 9223372036854775807l
      41: invokeinterface #21,  3           // InterfaceMethod org/reactivestreams/Subscription.request:(J)V
      46: goto          57
      49: aload_1
      50: iload_2
      51: i2l
      52: invokeinterface #21,  3           // InterfaceMethod org/reactivestreams/Subscription.request:(J)V
      57: return

  public void onNext(T);
    Code:
       0: aload_0
       1: getfield      #3                  // Field mapper:Lio/reactivex/rxjava3/functions/Function;
       4: aload_1
       5: invokeinterface #22,  2           // InterfaceMethod io/reactivex/rxjava3/functions/Function.apply:(Ljava/lang/Object;)Ljava/lang/Object;
      10: ldc           #23                 // String The mapper returned a null CompletableSource
      12: invokestatic  #24                 // Method java/util/Objects.requireNonNull:(Ljava/lang/Object;Ljava/lang/String;)Ljava/lang/Object;
      15: checkcast     #25                 // class io/reactivex/rxjava3/core/CompletableSource
      18: astore_2
      19: goto          42
      22: astore_3
      23: aload_3
      24: invokestatic  #27                 // Method io/reactivex/rxjava3/exceptions/Exceptions.throwIfFatal:(Ljava/lang/Throwable;)V
      27: aload_0
      28: getfield      #13                 // Field upstream:Lorg/reactivestreams/Subscription;
      31: invokeinterface #28,  1           // InterfaceMethod org/reactivestreams/Subscription.cancel:()V
      36: aload_0
      37: aload_3
      38: invokevirtual #29                 // Method onError:(Ljava/lang/Throwable;)V
      41: return
      42: aload_0
      43: invokevirtual #30                 // Method getAndIncrement:()I
      46: pop
      47: new           #31                 // class io/reactivex/rxjava3/internal/operators/flowable/FlowableFlatMapCompletable$FlatMapCompletableMainSubscriber$InnerConsumer
      50: dup
      51: aload_0
      52: invokespecial #32                 // Method io/reactivex/rxjava3/internal/operators/flowable/FlowableFlatMapCompletable$FlatMapCompletableMainSubscriber$InnerConsumer."<init>":(Lio/reactivex/rxjava3/internal/operators/flowable/FlowableFlatMapCompletable$FlatMapCompletableMainSubscriber;)V
      55: astore_3
      56: aload_0
      57: getfield      #33                 // Field cancelled:Z
      60: ifne          81
      63: aload_0
      64: getfield      #10                 // Field set:Lio/reactivex/rxjava3/disposables/CompositeDisposable;
      67: aload_3
      68: invokevirtual #34                 // Method io/reactivex/rxjava3/disposables/CompositeDisposable.add:(Lio/reactivex/rxjava3/disposables/Disposable;)Z
      71: ifeq          81
      74: aload_2
      75: aload_3
      76: invokeinterface #35,  2           // InterfaceMethod io/reactivex/rxjava3/core/CompletableSource.subscribe:(Lio/reactivex/rxjava3/core/CompletableObserver;)V
      81: return
    Exception table:
       from    to  target type
           0    19    22   Class java/lang/Throwable

  public void onError(java.lang.Throwable);
    Code:
       0: aload_0
       1: getfield      #7                  // Field errors:Lio/reactivex/rxjava3/internal/util/AtomicThrowable;
       4: aload_1
       5: invokevirtual #36                 // Method io/reactivex/rxjava3/internal/util/AtomicThrowable.tryAddThrowableOrReport:(Ljava/lang/Throwable;)Z
       8: ifeq          93
      11: aload_0
      12: getfield      #4                  // Field delayErrors:Z
      15: ifeq          61
      18: aload_0
      19: invokevirtual #37                 // Method decrementAndGet:()I
      22: ifne          39
      25: aload_0
      26: getfield      #7                  // Field errors:Lio/reactivex/rxjava3/internal/util/AtomicThrowable;
      29: aload_0
      30: getfield      #2                  // Field downstream:Lorg/reactivestreams/Subscriber;
      33: invokevirtual #38                 // Method io/reactivex/rxjava3/internal/util/AtomicThrowable.tryTerminateConsumer:(Lorg/reactivestreams/Subscriber;)V
      36: goto          93
      39: aload_0
      40: getfield      #11                 // Field maxConcurrency:I
      43: ldc           #17                 // int 2147483647
      45: if_icmpeq     93
      48: aload_0
      49: getfield      #13                 // Field upstream:Lorg/reactivestreams/Subscription;
      52: lconst_1
      53: invokeinterface #21,  3           // InterfaceMethod org/reactivestreams/Subscription.request:(J)V
      58: goto          93
      61: aload_0
      62: iconst_1
      63: putfield      #33                 // Field cancelled:Z
      66: aload_0
      67: getfield      #13                 // Field upstream:Lorg/reactivestreams/Subscription;
      70: invokeinterface #28,  1           // InterfaceMethod org/reactivestreams/Subscription.cancel:()V
      75: aload_0
      76: getfield      #10                 // Field set:Lio/reactivex/rxjava3/disposables/CompositeDisposable;
      79: invokevirtual #39                 // Method io/reactivex/rxjava3/disposables/CompositeDisposable.dispose:()V
      82: aload_0
      83: getfield      #7                  // Field errors:Lio/reactivex/rxjava3/internal/util/AtomicThrowable;
      86: aload_0
      87: getfield      #2                  // Field downstream:Lorg/reactivestreams/Subscriber;
      90: invokevirtual #38                 // Method io/reactivex/rxjava3/internal/util/AtomicThrowable.tryTerminateConsumer:(Lorg/reactivestreams/Subscriber;)V
      93: return

  public void onComplete();
    Code:
       0: aload_0
       1: invokevirtual #37                 // Method decrementAndGet:()I
       4: ifne          21
       7: aload_0
       8: getfield      #7                  // Field errors:Lio/reactivex/rxjava3/internal/util/AtomicThrowable;
      11: aload_0
      12: getfield      #2                  // Field downstream:Lorg/reactivestreams/Subscriber;
      15: invokevirtual #38                 // Method io/reactivex/rxjava3/internal/util/AtomicThrowable.tryTerminateConsumer:(Lorg/reactivestreams/Subscriber;)V
      18: goto          40
      21: aload_0
      22: getfield      #11                 // Field maxConcurrency:I
      25: ldc           #17                 // int 2147483647
      27: if_icmpeq     40
      30: aload_0
      31: getfield      #13                 // Field upstream:Lorg/reactivestreams/Subscription;
      34: lconst_1
      35: invokeinterface #21,  3           // InterfaceMethod org/reactivestreams/Subscription.request:(J)V
      40: return

  public void cancel();
    Code:
       0: aload_0
       1: iconst_1
       2: putfield      #33                 // Field cancelled:Z
       5: aload_0
       6: getfield      #13                 // Field upstream:Lorg/reactivestreams/Subscription;
       9: invokeinterface #28,  1           // InterfaceMethod org/reactivestreams/Subscription.cancel:()V
      14: aload_0
      15: getfield      #10                 // Field set:Lio/reactivex/rxjava3/disposables/CompositeDisposable;
      18: invokevirtual #39                 // Method io/reactivex/rxjava3/disposables/CompositeDisposable.dispose:()V
      21: aload_0
      22: getfield      #7                  // Field errors:Lio/reactivex/rxjava3/internal/util/AtomicThrowable;
      25: invokevirtual #40                 // Method io/reactivex/rxjava3/internal/util/AtomicThrowable.tryTerminateAndReport:()V
      28: return

  public void request(long);
    Code:
       0: return

  public T poll();
    Code:
       0: aconst_null
       1: areturn

  public boolean isEmpty();
    Code:
       0: iconst_1
       1: ireturn

  public void clear();
    Code:
       0: return

  public int requestFusion(int);
    Code:
       0: iload_1
       1: iconst_2
       2: iand
       3: ireturn

  void innerComplete(io.reactivex.rxjava3.internal.operators.flowable.FlowableFlatMapCompletable$FlatMapCompletableMainSubscriber<T>.InnerConsumer);
    Code:
       0: aload_0
       1: getfield      #10                 // Field set:Lio/reactivex/rxjava3/disposables/CompositeDisposable;
       4: aload_1
       5: invokevirtual #42                 // Method io/reactivex/rxjava3/disposables/CompositeDisposable.delete:(Lio/reactivex/rxjava3/disposables/Disposable;)Z
       8: pop
       9: aload_0
      10: invokevirtual #43                 // Method onComplete:()V
      13: return

  void innerError(io.reactivex.rxjava3.internal.operators.flowable.FlowableFlatMapCompletable$FlatMapCompletableMainSubscriber<T>.InnerConsumer, java.lang.Throwable);
    Code:
       0: aload_0
       1: getfield      #10                 // Field set:Lio/reactivex/rxjava3/disposables/CompositeDisposable;
       4: aload_1
       5: invokevirtual #42                 // Method io/reactivex/rxjava3/disposables/CompositeDisposable.delete:(Lio/reactivex/rxjava3/disposables/Disposable;)Z
       8: pop
       9: aload_0
      10: aload_2
      11: invokevirtual #29                 // Method onError:(Ljava/lang/Throwable;)V
      14: return
}
