Compiled from "FlowableScalarXMap.java"
public final class io.reactivex.rxjava3.internal.operators.flowable.FlowableScalarXMap {
  private io.reactivex.rxjava3.internal.operators.flowable.FlowableScalarXMap();
    Code:
       0: aload_0
       1: invokespecial #1                  // Method java/lang/Object."<init>":()V
       4: new           #2                  // class java/lang/IllegalStateException
       7: dup
       8: ldc           #3                  // String No instances!
      10: invokespecial #4                  // Method java/lang/IllegalStateException."<init>":(Ljava/lang/String;)V
      13: athrow

  public static <T, R> boolean tryScalarXMapSubscribe(org.reactivestreams.Publisher<T>, org.reactivestreams.Subscriber<? super R>, io.reactivex.rxjava3.functions.Function<? super T, ? extends org.reactivestreams.Publisher<? extends R>>);
    Code:
       0: aload_0
       1: instanceof    #5                  // class io/reactivex/rxjava3/functions/Supplier
       4: ifeq          158
       7: aload_0
       8: checkcast     #5                  // class io/reactivex/rxjava3/functions/Supplier
      11: invokeinterface #6,  1            // InterfaceMethod io/reactivex/rxjava3/functions/Supplier.get:()Ljava/lang/Object;
      16: astore_3
      17: goto          35
      20: astore        4
      22: aload         4
      24: invokestatic  #8                  // Method io/reactivex/rxjava3/exceptions/Exceptions.throwIfFatal:(Ljava/lang/Throwable;)V
      27: aload         4
      29: aload_1
      30: invokestatic  #9                  // Method io/reactivex/rxjava3/internal/subscriptions/EmptySubscription.error:(Ljava/lang/Throwable;Lorg/reactivestreams/Subscriber;)V
      33: iconst_1
      34: ireturn
      35: aload_3
      36: ifnonnull     45
      39: aload_1
      40: invokestatic  #10                 // Method io/reactivex/rxjava3/internal/subscriptions/EmptySubscription.complete:(Lorg/reactivestreams/Subscriber;)V
      43: iconst_1
      44: ireturn
      45: aload_2
      46: aload_3
      47: invokeinterface #11,  2           // InterfaceMethod io/reactivex/rxjava3/functions/Function.apply:(Ljava/lang/Object;)Ljava/lang/Object;
      52: ldc           #12                 // String The mapper returned a null Publisher
      54: invokestatic  #13                 // Method java/util/Objects.requireNonNull:(Ljava/lang/Object;Ljava/lang/String;)Ljava/lang/Object;
      57: checkcast     #14                 // class org/reactivestreams/Publisher
      60: astore        4
      62: goto          80
      65: astore        5
      67: aload         5
      69: invokestatic  #8                  // Method io/reactivex/rxjava3/exceptions/Exceptions.throwIfFatal:(Ljava/lang/Throwable;)V
      72: aload         5
      74: aload_1
      75: invokestatic  #9                  // Method io/reactivex/rxjava3/internal/subscriptions/EmptySubscription.error:(Ljava/lang/Throwable;Lorg/reactivestreams/Subscriber;)V
      78: iconst_1
      79: ireturn
      80: aload         4
      82: instanceof    #5                  // class io/reactivex/rxjava3/functions/Supplier
      85: ifeq          148
      88: aload         4
      90: checkcast     #5                  // class io/reactivex/rxjava3/functions/Supplier
      93: invokeinterface #6,  1            // InterfaceMethod io/reactivex/rxjava3/functions/Supplier.get:()Ljava/lang/Object;
      98: astore        5
     100: goto          118
     103: astore        6
     105: aload         6
     107: invokestatic  #8                  // Method io/reactivex/rxjava3/exceptions/Exceptions.throwIfFatal:(Ljava/lang/Throwable;)V
     110: aload         6
     112: aload_1
     113: invokestatic  #9                  // Method io/reactivex/rxjava3/internal/subscriptions/EmptySubscription.error:(Ljava/lang/Throwable;Lorg/reactivestreams/Subscriber;)V
     116: iconst_1
     117: ireturn
     118: aload         5
     120: ifnonnull     129
     123: aload_1
     124: invokestatic  #10                 // Method io/reactivex/rxjava3/internal/subscriptions/EmptySubscription.complete:(Lorg/reactivestreams/Subscriber;)V
     127: iconst_1
     128: ireturn
     129: aload_1
     130: new           #15                 // class io/reactivex/rxjava3/internal/subscriptions/ScalarSubscription
     133: dup
     134: aload_1
     135: aload         5
     137: invokespecial #16                 // Method io/reactivex/rxjava3/internal/subscriptions/ScalarSubscription."<init>":(Lorg/reactivestreams/Subscriber;Ljava/lang/Object;)V
     140: invokeinterface #17,  2           // InterfaceMethod org/reactivestreams/Subscriber.onSubscribe:(Lorg/reactivestreams/Subscription;)V
     145: goto          156
     148: aload         4
     150: aload_1
     151: invokeinterface #18,  2           // InterfaceMethod org/reactivestreams/Publisher.subscribe:(Lorg/reactivestreams/Subscriber;)V
     156: iconst_1
     157: ireturn
     158: iconst_0
     159: ireturn
    Exception table:
       from    to  target type
           7    17    20   Class java/lang/Throwable
          45    62    65   Class java/lang/Throwable
          88   100   103   Class java/lang/Throwable

  public static <T, U> io.reactivex.rxjava3.core.Flowable<U> scalarXMap(T, io.reactivex.rxjava3.functions.Function<? super T, ? extends org.reactivestreams.Publisher<? extends U>>);
    Code:
       0: new           #19                 // class io/reactivex/rxjava3/internal/operators/flowable/FlowableScalarXMap$ScalarXMapFlowable
       3: dup
       4: aload_0
       5: aload_1
       6: invokespecial #20                 // Method io/reactivex/rxjava3/internal/operators/flowable/FlowableScalarXMap$ScalarXMapFlowable."<init>":(Ljava/lang/Object;Lio/reactivex/rxjava3/functions/Function;)V
       9: invokestatic  #21                 // Method io/reactivex/rxjava3/plugins/RxJavaPlugins.onAssembly:(Lio/reactivex/rxjava3/core/Flowable;)Lio/reactivex/rxjava3/core/Flowable;
      12: areturn
}
