Compiled from "FlowableDebounceTimed.java"
public final class io.reactivex.rxjava3.internal.operators.flowable.FlowableDebounceTimed<T> extends io.reactivex.rxjava3.internal.operators.flowable.AbstractFlowableWithUpstream<T, T> {
  final long timeout;

  final java.util.concurrent.TimeUnit unit;

  final io.reactivex.rxjava3.core.Scheduler scheduler;

  final io.reactivex.rxjava3.functions.Consumer<? super T> onDropped;

  public io.reactivex.rxjava3.internal.operators.flowable.FlowableDebounceTimed(io.reactivex.rxjava3.core.Flowable<T>, long, java.util.concurrent.TimeUnit, io.reactivex.rxjava3.core.Scheduler, io.reactivex.rxjava3.functions.Consumer<? super T>);
    Code:
       0: aload_0
       1: aload_1
       2: invokespecial #1                  // Method io/reactivex/rxjava3/internal/operators/flowable/AbstractFlowableWithUpstream."<init>":(Lio/reactivex/rxjava3/core/Flowable;)V
       5: aload_0
       6: lload_2
       7: putfield      #2                  // Field timeout:J
      10: aload_0
      11: aload         4
      13: putfield      #3                  // Field unit:Ljava/util/concurrent/TimeUnit;
      16: aload_0
      17: aload         5
      19: putfield      #4                  // Field scheduler:Lio/reactivex/rxjava3/core/Scheduler;
      22: aload_0
      23: aload         6
      25: putfield      #5                  // Field onDropped:Lio/reactivex/rxjava3/functions/Consumer;
      28: return

  protected void subscribeActual(org.reactivestreams.Subscriber<? super T>);
    Code:
       0: aload_0
       1: getfield      #6                  // Field source:Lio/reactivex/rxjava3/core/Flowable;
       4: new           #7                  // class io/reactivex/rxjava3/internal/operators/flowable/FlowableDebounceTimed$DebounceTimedSubscriber
       7: dup
       8: new           #8                  // class io/reactivex/rxjava3/subscribers/SerializedSubscriber
      11: dup
      12: aload_1
      13: invokespecial #9                  // Method io/reactivex/rxjava3/subscribers/SerializedSubscriber."<init>":(Lorg/reactivestreams/Subscriber;)V
      16: aload_0
      17: getfield      #2                  // Field timeout:J
      20: aload_0
      21: getfield      #3                  // Field unit:Ljava/util/concurrent/TimeUnit;
      24: aload_0
      25: getfield      #4                  // Field scheduler:Lio/reactivex/rxjava3/core/Scheduler;
      28: invokevirtual #10                 // Method io/reactivex/rxjava3/core/Scheduler.createWorker:()Lio/reactivex/rxjava3/core/Scheduler$Worker;
      31: aload_0
      32: getfield      #5                  // Field onDropped:Lio/reactivex/rxjava3/functions/Consumer;
      35: invokespecial #11                 // Method io/reactivex/rxjava3/internal/operators/flowable/FlowableDebounceTimed$DebounceTimedSubscriber."<init>":(Lorg/reactivestreams/Subscriber;JLjava/util/concurrent/TimeUnit;Lio/reactivex/rxjava3/core/Scheduler$Worker;Lio/reactivex/rxjava3/functions/Consumer;)V
      38: invokevirtual #12                 // Method io/reactivex/rxjava3/core/Flowable.subscribe:(Lio/reactivex/rxjava3/core/FlowableSubscriber;)V
      41: return
}
