Compiled from "FlowableConcatArray.java"
public final class io.reactivex.rxjava3.internal.operators.flowable.FlowableConcatArray<T> extends io.reactivex.rxjava3.core.Flowable<T> {
  final org.reactivestreams.Publisher<? extends T>[] sources;

  final boolean delayError;

  public io.reactivex.rxjava3.internal.operators.flowable.FlowableConcatArray(org.reactivestreams.Publisher<? extends T>[], boolean);
    Code:
       0: aload_0
       1: invokespecial #1                  // Method io/reactivex/rxjava3/core/Flowable."<init>":()V
       4: aload_0
       5: aload_1
       6: putfield      #2                  // Field sources:[Lorg/reactivestreams/Publisher;
       9: aload_0
      10: iload_2
      11: putfield      #3                  // Field delayError:Z
      14: return

  protected void subscribeActual(org.reactivestreams.Subscriber<? super T>);
    Code:
       0: new           #4                  // class io/reactivex/rxjava3/internal/operators/flowable/FlowableConcatArray$ConcatArraySubscriber
       3: dup
       4: aload_0
       5: getfield      #2                  // Field sources:[Lorg/reactivestreams/Publisher;
       8: aload_0
       9: getfield      #3                  // Field delayError:Z
      12: aload_1
      13: invokespecial #5                  // Method io/reactivex/rxjava3/internal/operators/flowable/FlowableConcatArray$ConcatArraySubscriber."<init>":([Lorg/reactivestreams/Publisher;ZLorg/reactivestreams/Subscriber;)V
      16: astore_2
      17: aload_1
      18: aload_2
      19: invokeinterface #6,  2            // InterfaceMethod org/reactivestreams/Subscriber.onSubscribe:(Lorg/reactivestreams/Subscription;)V
      24: aload_2
      25: invokevirtual #7                  // Method io/reactivex/rxjava3/internal/operators/flowable/FlowableConcatArray$ConcatArraySubscriber.onComplete:()V
      28: return
}
