Compiled from "FlowableWindowBoundarySelector.java"
final class io.reactivex.rxjava3.internal.operators.flowable.FlowableWindowBoundarySelector$WindowBoundaryMainSubscriber$WindowEndSubscriberIntercept<T, V> extends io.reactivex.rxjava3.core.Flowable<T> implements io.reactivex.rxjava3.core.FlowableSubscriber<V>, io.reactivex.rxjava3.disposables.Disposable {
  final io.reactivex.rxjava3.internal.operators.flowable.FlowableWindowBoundarySelector$WindowBoundaryMainSubscriber<T, ?, V> parent;

  final io.reactivex.rxjava3.processors.UnicastProcessor<T> window;

  final java.util.concurrent.atomic.AtomicReference<org.reactivestreams.Subscription> upstream;

  final java.util.concurrent.atomic.AtomicBoolean once;

  io.reactivex.rxjava3.internal.operators.flowable.FlowableWindowBoundarySelector$WindowBoundaryMainSubscriber$WindowEndSubscriberIntercept(io.reactivex.rxjava3.internal.operators.flowable.FlowableWindowBoundarySelector$WindowBoundaryMainSubscriber<T, ?, V>, io.reactivex.rxjava3.processors.UnicastProcessor<T>);
    Code:
       0: aload_0
       1: invokespecial #1                  // Method io/reactivex/rxjava3/core/Flowable."<init>":()V
       4: aload_0
       5: aload_1
       6: putfield      #2                  // Field parent:Lio/reactivex/rxjava3/internal/operators/flowable/FlowableWindowBoundarySelector$WindowBoundaryMainSubscriber;
       9: aload_0
      10: aload_2
      11: putfield      #3                  // Field window:Lio/reactivex/rxjava3/processors/UnicastProcessor;
      14: aload_0
      15: new           #4                  // class java/util/concurrent/atomic/AtomicReference
      18: dup
      19: invokespecial #5                  // Method java/util/concurrent/atomic/AtomicReference."<init>":()V
      22: putfield      #6                  // Field upstream:Ljava/util/concurrent/atomic/AtomicReference;
      25: aload_0
      26: new           #7                  // class java/util/concurrent/atomic/AtomicBoolean
      29: dup
      30: invokespecial #8                  // Method java/util/concurrent/atomic/AtomicBoolean."<init>":()V
      33: putfield      #9                  // Field once:Ljava/util/concurrent/atomic/AtomicBoolean;
      36: return

  public void onSubscribe(org.reactivestreams.Subscription);
    Code:
       0: aload_0
       1: getfield      #6                  // Field upstream:Ljava/util/concurrent/atomic/AtomicReference;
       4: aload_1
       5: invokestatic  #10                 // Method io/reactivex/rxjava3/internal/subscriptions/SubscriptionHelper.setOnce:(Ljava/util/concurrent/atomic/AtomicReference;Lorg/reactivestreams/Subscription;)Z
       8: ifeq          20
      11: aload_1
      12: ldc2_w        #12                 // long 9223372036854775807l
      15: invokeinterface #14,  3           // InterfaceMethod org/reactivestreams/Subscription.request:(J)V
      20: return

  public void onNext(V);
    Code:
       0: aload_0
       1: getfield      #6                  // Field upstream:Ljava/util/concurrent/atomic/AtomicReference;
       4: invokestatic  #15                 // Method io/reactivex/rxjava3/internal/subscriptions/SubscriptionHelper.cancel:(Ljava/util/concurrent/atomic/AtomicReference;)Z
       7: ifeq          18
      10: aload_0
      11: getfield      #2                  // Field parent:Lio/reactivex/rxjava3/internal/operators/flowable/FlowableWindowBoundarySelector$WindowBoundaryMainSubscriber;
      14: aload_0
      15: invokevirtual #16                 // Method io/reactivex/rxjava3/internal/operators/flowable/FlowableWindowBoundarySelector$WindowBoundaryMainSubscriber.close:(Lio/reactivex/rxjava3/internal/operators/flowable/FlowableWindowBoundarySelector$WindowBoundaryMainSubscriber$WindowEndSubscriberIntercept;)V
      18: return

  public void onError(java.lang.Throwable);
    Code:
       0: aload_0
       1: invokevirtual #17                 // Method isDisposed:()Z
       4: ifeq          14
       7: aload_1
       8: invokestatic  #18                 // Method io/reactivex/rxjava3/plugins/RxJavaPlugins.onError:(Ljava/lang/Throwable;)V
      11: goto          22
      14: aload_0
      15: getfield      #2                  // Field parent:Lio/reactivex/rxjava3/internal/operators/flowable/FlowableWindowBoundarySelector$WindowBoundaryMainSubscriber;
      18: aload_1
      19: invokevirtual #19                 // Method io/reactivex/rxjava3/internal/operators/flowable/FlowableWindowBoundarySelector$WindowBoundaryMainSubscriber.closeError:(Ljava/lang/Throwable;)V
      22: return

  public void onComplete();
    Code:
       0: aload_0
       1: getfield      #2                  // Field parent:Lio/reactivex/rxjava3/internal/operators/flowable/FlowableWindowBoundarySelector$WindowBoundaryMainSubscriber;
       4: aload_0
       5: invokevirtual #16                 // Method io/reactivex/rxjava3/internal/operators/flowable/FlowableWindowBoundarySelector$WindowBoundaryMainSubscriber.close:(Lio/reactivex/rxjava3/internal/operators/flowable/FlowableWindowBoundarySelector$WindowBoundaryMainSubscriber$WindowEndSubscriberIntercept;)V
       8: return

  public void dispose();
    Code:
       0: aload_0
       1: getfield      #6                  // Field upstream:Ljava/util/concurrent/atomic/AtomicReference;
       4: invokestatic  #15                 // Method io/reactivex/rxjava3/internal/subscriptions/SubscriptionHelper.cancel:(Ljava/util/concurrent/atomic/AtomicReference;)Z
       7: pop
       8: return

  public boolean isDisposed();
    Code:
       0: aload_0
       1: getfield      #6                  // Field upstream:Ljava/util/concurrent/atomic/AtomicReference;
       4: invokevirtual #20                 // Method java/util/concurrent/atomic/AtomicReference.get:()Ljava/lang/Object;
       7: getstatic     #21                 // Field io/reactivex/rxjava3/internal/subscriptions/SubscriptionHelper.CANCELLED:Lio/reactivex/rxjava3/internal/subscriptions/SubscriptionHelper;
      10: if_acmpne     17
      13: iconst_1
      14: goto          18
      17: iconst_0
      18: ireturn

  protected void subscribeActual(org.reactivestreams.Subscriber<? super T>);
    Code:
       0: aload_0
       1: getfield      #3                  // Field window:Lio/reactivex/rxjava3/processors/UnicastProcessor;
       4: aload_1
       5: invokevirtual #22                 // Method io/reactivex/rxjava3/processors/UnicastProcessor.subscribe:(Lorg/reactivestreams/Subscriber;)V
       8: aload_0
       9: getfield      #9                  // Field once:Ljava/util/concurrent/atomic/AtomicBoolean;
      12: iconst_1
      13: invokevirtual #23                 // Method java/util/concurrent/atomic/AtomicBoolean.set:(Z)V
      16: return

  boolean tryAbandon();
    Code:
       0: aload_0
       1: getfield      #9                  // Field once:Ljava/util/concurrent/atomic/AtomicBoolean;
       4: invokevirtual #24                 // Method java/util/concurrent/atomic/AtomicBoolean.get:()Z
       7: ifne          26
      10: aload_0
      11: getfield      #9                  // Field once:Ljava/util/concurrent/atomic/AtomicBoolean;
      14: iconst_0
      15: iconst_1
      16: invokevirtual #25                 // Method java/util/concurrent/atomic/AtomicBoolean.compareAndSet:(ZZ)Z
      19: ifeq          26
      22: iconst_1
      23: goto          27
      26: iconst_0
      27: ireturn
}
