Compiled from "FlowableCombineLatest.java"
public final class io.reactivex.rxjava3.internal.operators.flowable.FlowableCombineLatest<T, R> extends io.reactivex.rxjava3.core.Flowable<R> {
  final org.reactivestreams.Publisher<? extends T>[] array;

  final java.lang.Iterable<? extends org.reactivestreams.Publisher<? extends T>> iterable;

  final io.reactivex.rxjava3.functions.Function<? super java.lang.Object[], ? extends R> combiner;

  final int bufferSize;

  final boolean delayErrors;

  public io.reactivex.rxjava3.internal.operators.flowable.FlowableCombineLatest(org.reactivestreams.Publisher<? extends T>[], io.reactivex.rxjava3.functions.Function<? super java.lang.Object[], ? extends R>, int, boolean);
    Code:
       0: aload_0
       1: invokespecial #1                  // Method io/reactivex/rxjava3/core/Flowable."<init>":()V
       4: aload_0
       5: aload_1
       6: putfield      #2                  // Field array:[Lorg/reactivestreams/Publisher;
       9: aload_0
      10: aconst_null
      11: putfield      #3                  // Field iterable:Ljava/lang/Iterable;
      14: aload_0
      15: aload_2
      16: putfield      #4                  // Field combiner:Lio/reactivex/rxjava3/functions/Function;
      19: aload_0
      20: iload_3
      21: putfield      #5                  // Field bufferSize:I
      24: aload_0
      25: iload         4
      27: putfield      #6                  // Field delayErrors:Z
      30: return

  public io.reactivex.rxjava3.internal.operators.flowable.FlowableCombineLatest(java.lang.Iterable<? extends org.reactivestreams.Publisher<? extends T>>, io.reactivex.rxjava3.functions.Function<? super java.lang.Object[], ? extends R>, int, boolean);
    Code:
       0: aload_0
       1: invokespecial #1                  // Method io/reactivex/rxjava3/core/Flowable."<init>":()V
       4: aload_0
       5: aconst_null
       6: putfield      #2                  // Field array:[Lorg/reactivestreams/Publisher;
       9: aload_0
      10: aload_1
      11: putfield      #3                  // Field iterable:Ljava/lang/Iterable;
      14: aload_0
      15: aload_2
      16: putfield      #4                  // Field combiner:Lio/reactivex/rxjava3/functions/Function;
      19: aload_0
      20: iload_3
      21: putfield      #5                  // Field bufferSize:I
      24: aload_0
      25: iload         4
      27: putfield      #6                  // Field delayErrors:Z
      30: return

  public void subscribeActual(org.reactivestreams.Subscriber<? super R>);
    Code:
       0: aload_0
       1: getfield      #2                  // Field array:[Lorg/reactivestreams/Publisher;
       4: astore_2
       5: aload_2
       6: ifnonnull     114
       9: iconst_0
      10: istore_3
      11: bipush        8
      13: anewarray     #7                  // class org/reactivestreams/Publisher
      16: astore_2
      17: aload_0
      18: getfield      #3                  // Field iterable:Ljava/lang/Iterable;
      21: invokeinterface #8,  1            // InterfaceMethod java/lang/Iterable.iterator:()Ljava/util/Iterator;
      26: astore        4
      28: aload         4
      30: invokeinterface #9,  1            // InterfaceMethod java/util/Iterator.hasNext:()Z
      35: ifeq          97
      38: aload         4
      40: invokeinterface #10,  1           // InterfaceMethod java/util/Iterator.next:()Ljava/lang/Object;
      45: checkcast     #7                  // class org/reactivestreams/Publisher
      48: astore        5
      50: iload_3
      51: aload_2
      52: arraylength
      53: if_icmpne     78
      56: iload_3
      57: iload_3
      58: iconst_2
      59: ishr
      60: iadd
      61: anewarray     #7                  // class org/reactivestreams/Publisher
      64: astore        6
      66: aload_2
      67: iconst_0
      68: aload         6
      70: iconst_0
      71: iload_3
      72: invokestatic  #11                 // Method java/lang/System.arraycopy:(Ljava/lang/Object;ILjava/lang/Object;II)V
      75: aload         6
      77: astore_2
      78: aload_2
      79: iload_3
      80: iinc          3, 1
      83: aload         5
      85: ldc           #12                 // String The Iterator returned a null Publisher
      87: invokestatic  #13                 // Method java/util/Objects.requireNonNull:(Ljava/lang/Object;Ljava/lang/String;)Ljava/lang/Object;
      90: checkcast     #7                  // class org/reactivestreams/Publisher
      93: aastore
      94: goto          28
      97: goto          117
     100: astore        4
     102: aload         4
     104: invokestatic  #15                 // Method io/reactivex/rxjava3/exceptions/Exceptions.throwIfFatal:(Ljava/lang/Throwable;)V
     107: aload         4
     109: aload_1
     110: invokestatic  #16                 // Method io/reactivex/rxjava3/internal/subscriptions/EmptySubscription.error:(Ljava/lang/Throwable;Lorg/reactivestreams/Subscriber;)V
     113: return
     114: aload_2
     115: arraylength
     116: istore_3
     117: iload_3
     118: ifne          126
     121: aload_1
     122: invokestatic  #17                 // Method io/reactivex/rxjava3/internal/subscriptions/EmptySubscription.complete:(Lorg/reactivestreams/Subscriber;)V
     125: return
     126: iload_3
     127: iconst_1
     128: if_icmpne     156
     131: aload_2
     132: iconst_0
     133: aaload
     134: new           #18                 // class io/reactivex/rxjava3/internal/operators/flowable/FlowableMap$MapSubscriber
     137: dup
     138: aload_1
     139: new           #19                 // class io/reactivex/rxjava3/internal/operators/flowable/FlowableCombineLatest$SingletonArrayFunc
     142: dup
     143: aload_0
     144: invokespecial #20                 // Method io/reactivex/rxjava3/internal/operators/flowable/FlowableCombineLatest$SingletonArrayFunc."<init>":(Lio/reactivex/rxjava3/internal/operators/flowable/FlowableCombineLatest;)V
     147: invokespecial #21                 // Method io/reactivex/rxjava3/internal/operators/flowable/FlowableMap$MapSubscriber."<init>":(Lorg/reactivestreams/Subscriber;Lio/reactivex/rxjava3/functions/Function;)V
     150: invokeinterface #22,  2           // InterfaceMethod org/reactivestreams/Publisher.subscribe:(Lorg/reactivestreams/Subscriber;)V
     155: return
     156: new           #23                 // class io/reactivex/rxjava3/internal/operators/flowable/FlowableCombineLatest$CombineLatestCoordinator
     159: dup
     160: aload_1
     161: aload_0
     162: getfield      #4                  // Field combiner:Lio/reactivex/rxjava3/functions/Function;
     165: iload_3
     166: aload_0
     167: getfield      #5                  // Field bufferSize:I
     170: aload_0
     171: getfield      #6                  // Field delayErrors:Z
     174: invokespecial #24                 // Method io/reactivex/rxjava3/internal/operators/flowable/FlowableCombineLatest$CombineLatestCoordinator."<init>":(Lorg/reactivestreams/Subscriber;Lio/reactivex/rxjava3/functions/Function;IIZ)V
     177: astore        4
     179: aload_1
     180: aload         4
     182: invokeinterface #25,  2           // InterfaceMethod org/reactivestreams/Subscriber.onSubscribe:(Lorg/reactivestreams/Subscription;)V
     187: aload         4
     189: aload_2
     190: iload_3
     191: invokevirtual #26                 // Method io/reactivex/rxjava3/internal/operators/flowable/FlowableCombineLatest$CombineLatestCoordinator.subscribe:([Lorg/reactivestreams/Publisher;I)V
     194: return
    Exception table:
       from    to  target type
          17    97   100   Class java/lang/Throwable
}
