Compiled from "FlowableDoFinally.java"
final class io.reactivex.rxjava3.internal.operators.flowable.FlowableDoFinally$DoFinallySubscriber<T> extends io.reactivex.rxjava3.internal.subscriptions.BasicIntQueueSubscription<T> implements io.reactivex.rxjava3.core.FlowableSubscriber<T> {
  private static final long serialVersionUID;

  final org.reactivestreams.Subscriber<? super T> downstream;

  final io.reactivex.rxjava3.functions.Action onFinally;

  org.reactivestreams.Subscription upstream;

  io.reactivex.rxjava3.operators.QueueSubscription<T> qs;

  boolean syncFused;

  io.reactivex.rxjava3.internal.operators.flowable.FlowableDoFinally$DoFinallySubscriber(org.reactivestreams.Subscriber<? super T>, io.reactivex.rxjava3.functions.Action);
    Code:
       0: aload_0
       1: invokespecial #1                  // Method io/reactivex/rxjava3/internal/subscriptions/BasicIntQueueSubscription."<init>":()V
       4: aload_0
       5: aload_1
       6: putfield      #2                  // Field downstream:Lorg/reactivestreams/Subscriber;
       9: aload_0
      10: aload_2
      11: putfield      #3                  // Field onFinally:Lio/reactivex/rxjava3/functions/Action;
      14: return

  public void onSubscribe(org.reactivestreams.Subscription);
    Code:
       0: aload_0
       1: getfield      #4                  // Field upstream:Lorg/reactivestreams/Subscription;
       4: aload_1
       5: invokestatic  #5                  // Method io/reactivex/rxjava3/internal/subscriptions/SubscriptionHelper.validate:(Lorg/reactivestreams/Subscription;Lorg/reactivestreams/Subscription;)Z
       8: ifeq          41
      11: aload_0
      12: aload_1
      13: putfield      #4                  // Field upstream:Lorg/reactivestreams/Subscription;
      16: aload_1
      17: instanceof    #6                  // class io/reactivex/rxjava3/operators/QueueSubscription
      20: ifeq          31
      23: aload_0
      24: aload_1
      25: checkcast     #6                  // class io/reactivex/rxjava3/operators/QueueSubscription
      28: putfield      #7                  // Field qs:Lio/reactivex/rxjava3/operators/QueueSubscription;
      31: aload_0
      32: getfield      #2                  // Field downstream:Lorg/reactivestreams/Subscriber;
      35: aload_0
      36: invokeinterface #8,  2            // InterfaceMethod org/reactivestreams/Subscriber.onSubscribe:(Lorg/reactivestreams/Subscription;)V
      41: return

  public void onNext(T);
    Code:
       0: aload_0
       1: getfield      #2                  // Field downstream:Lorg/reactivestreams/Subscriber;
       4: aload_1
       5: invokeinterface #9,  2            // InterfaceMethod org/reactivestreams/Subscriber.onNext:(Ljava/lang/Object;)V
      10: return

  public void onError(java.lang.Throwable);
    Code:
       0: aload_0
       1: getfield      #2                  // Field downstream:Lorg/reactivestreams/Subscriber;
       4: aload_1
       5: invokeinterface #10,  2           // InterfaceMethod org/reactivestreams/Subscriber.onError:(Ljava/lang/Throwable;)V
      10: aload_0
      11: invokevirtual #11                 // Method runFinally:()V
      14: return

  public void onComplete();
    Code:
       0: aload_0
       1: getfield      #2                  // Field downstream:Lorg/reactivestreams/Subscriber;
       4: invokeinterface #12,  1           // InterfaceMethod org/reactivestreams/Subscriber.onComplete:()V
       9: aload_0
      10: invokevirtual #11                 // Method runFinally:()V
      13: return

  public void cancel();
    Code:
       0: aload_0
       1: getfield      #4                  // Field upstream:Lorg/reactivestreams/Subscription;
       4: invokeinterface #13,  1           // InterfaceMethod org/reactivestreams/Subscription.cancel:()V
       9: aload_0
      10: invokevirtual #11                 // Method runFinally:()V
      13: return

  public void request(long);
    Code:
       0: aload_0
       1: getfield      #4                  // Field upstream:Lorg/reactivestreams/Subscription;
       4: lload_1
       5: invokeinterface #14,  3           // InterfaceMethod org/reactivestreams/Subscription.request:(J)V
      10: return

  public int requestFusion(int);
    Code:
       0: aload_0
       1: getfield      #7                  // Field qs:Lio/reactivex/rxjava3/operators/QueueSubscription;
       4: astore_2
       5: aload_2
       6: ifnull        43
       9: iload_1
      10: iconst_4
      11: iand
      12: ifne          43
      15: aload_2
      16: iload_1
      17: invokeinterface #16,  2           // InterfaceMethod io/reactivex/rxjava3/operators/QueueSubscription.requestFusion:(I)I
      22: istore_3
      23: iload_3
      24: ifeq          41
      27: aload_0
      28: iload_3
      29: iconst_1
      30: if_icmpne     37
      33: iconst_1
      34: goto          38
      37: iconst_0
      38: putfield      #17                 // Field syncFused:Z
      41: iload_3
      42: ireturn
      43: iconst_0
      44: ireturn

  public void clear();
    Code:
       0: aload_0
       1: getfield      #7                  // Field qs:Lio/reactivex/rxjava3/operators/QueueSubscription;
       4: invokeinterface #18,  1           // InterfaceMethod io/reactivex/rxjava3/operators/QueueSubscription.clear:()V
       9: return

  public boolean isEmpty();
    Code:
       0: aload_0
       1: getfield      #7                  // Field qs:Lio/reactivex/rxjava3/operators/QueueSubscription;
       4: invokeinterface #19,  1           // InterfaceMethod io/reactivex/rxjava3/operators/QueueSubscription.isEmpty:()Z
       9: ireturn

  public T poll() throws java.lang.Throwable;
    Code:
       0: aload_0
       1: getfield      #7                  // Field qs:Lio/reactivex/rxjava3/operators/QueueSubscription;
       4: invokeinterface #20,  1           // InterfaceMethod io/reactivex/rxjava3/operators/QueueSubscription.poll:()Ljava/lang/Object;
       9: astore_1
      10: aload_1
      11: ifnonnull     25
      14: aload_0
      15: getfield      #17                 // Field syncFused:Z
      18: ifeq          25
      21: aload_0
      22: invokevirtual #11                 // Method runFinally:()V
      25: aload_1
      26: areturn

  void runFinally();
    Code:
       0: aload_0
       1: iconst_0
       2: iconst_1
       3: invokevirtual #21                 // Method compareAndSet:(II)Z
       6: ifeq          30
       9: aload_0
      10: getfield      #3                  // Field onFinally:Lio/reactivex/rxjava3/functions/Action;
      13: invokeinterface #22,  1           // InterfaceMethod io/reactivex/rxjava3/functions/Action.run:()V
      18: goto          30
      21: astore_1
      22: aload_1
      23: invokestatic  #24                 // Method io/reactivex/rxjava3/exceptions/Exceptions.throwIfFatal:(Ljava/lang/Throwable;)V
      26: aload_1
      27: invokestatic  #25                 // Method io/reactivex/rxjava3/plugins/RxJavaPlugins.onError:(Ljava/lang/Throwable;)V
      30: return
    Exception table:
       from    to  target type
           9    18    21   Class java/lang/Throwable
}
