Compiled from "FlowableSamplePublisher.java"
final class io.reactivex.rxjava3.internal.operators.flowable.FlowableSamplePublisher$SamplerSubscriber<T> implements io.reactivex.rxjava3.core.FlowableSubscriber<java.lang.Object> {
  final io.reactivex.rxjava3.internal.operators.flowable.FlowableSamplePublisher$SamplePublisherSubscriber<T> parent;

  io.reactivex.rxjava3.internal.operators.flowable.FlowableSamplePublisher$SamplerSubscriber(io.reactivex.rxjava3.internal.operators.flowable.FlowableSamplePublisher$SamplePublisherSubscriber<T>);
    Code:
       0: aload_0
       1: invokespecial #1                  // Method java/lang/Object."<init>":()V
       4: aload_0
       5: aload_1
       6: putfield      #2                  // Field parent:Lio/reactivex/rxjava3/internal/operators/flowable/FlowableSamplePublisher$SamplePublisherSubscriber;
       9: return

  public void onSubscribe(org.reactivestreams.Subscription);
    Code:
       0: aload_0
       1: getfield      #2                  // Field parent:Lio/reactivex/rxjava3/internal/operators/flowable/FlowableSamplePublisher$SamplePublisherSubscriber;
       4: aload_1
       5: invokevirtual #3                  // Method io/reactivex/rxjava3/internal/operators/flowable/FlowableSamplePublisher$SamplePublisherSubscriber.setOther:(Lorg/reactivestreams/Subscription;)V
       8: return

  public void onNext(java.lang.Object);
    Code:
       0: aload_0
       1: getfield      #2                  // Field parent:Lio/reactivex/rxjava3/internal/operators/flowable/FlowableSamplePublisher$SamplePublisherSubscriber;
       4: invokevirtual #4                  // Method io/reactivex/rxjava3/internal/operators/flowable/FlowableSamplePublisher$SamplePublisherSubscriber.run:()V
       7: return

  public void onError(java.lang.Throwable);
    Code:
       0: aload_0
       1: getfield      #2                  // Field parent:Lio/reactivex/rxjava3/internal/operators/flowable/FlowableSamplePublisher$SamplePublisherSubscriber;
       4: aload_1
       5: invokevirtual #5                  // Method io/reactivex/rxjava3/internal/operators/flowable/FlowableSamplePublisher$SamplePublisherSubscriber.error:(Ljava/lang/Throwable;)V
       8: return

  public void onComplete();
    Code:
       0: aload_0
       1: getfield      #2                  // Field parent:Lio/reactivex/rxjava3/internal/operators/flowable/FlowableSamplePublisher$SamplePublisherSubscriber;
       4: invokevirtual #6                  // Method io/reactivex/rxjava3/internal/operators/flowable/FlowableSamplePublisher$SamplePublisherSubscriber.complete:()V
       7: return
}
