Compiled from "FlowableMap.java"
final class io.reactivex.rxjava3.internal.operators.flowable.FlowableMap$MapConditionalSubscriber<T, U> extends io.reactivex.rxjava3.internal.subscribers.BasicFuseableConditionalSubscriber<T, U> {
  final io.reactivex.rxjava3.functions.Function<? super T, ? extends U> mapper;

  io.reactivex.rxjava3.internal.operators.flowable.FlowableMap$MapConditionalSubscriber(io.reactivex.rxjava3.operators.ConditionalSubscriber<? super U>, io.reactivex.rxjava3.functions.Function<? super T, ? extends U>);
    Code:
       0: aload_0
       1: aload_1
       2: invokespecial #1                  // Method io/reactivex/rxjava3/internal/subscribers/BasicFuseableConditionalSubscriber."<init>":(Lio/reactivex/rxjava3/operators/ConditionalSubscriber;)V
       5: aload_0
       6: aload_2
       7: putfield      #2                  // Field mapper:Lio/reactivex/rxjava3/functions/Function;
      10: return

  public void onNext(T);
    Code:
       0: aload_0
       1: getfield      #3                  // Field done:Z
       4: ifeq          8
       7: return
       8: aload_0
       9: getfield      #4                  // Field sourceMode:I
      12: ifeq          26
      15: aload_0
      16: getfield      #5                  // Field downstream:Lio/reactivex/rxjava3/operators/ConditionalSubscriber;
      19: aconst_null
      20: invokeinterface #6,  2            // InterfaceMethod io/reactivex/rxjava3/operators/ConditionalSubscriber.onNext:(Ljava/lang/Object;)V
      25: return
      26: aload_0
      27: getfield      #2                  // Field mapper:Lio/reactivex/rxjava3/functions/Function;
      30: aload_1
      31: invokeinterface #7,  2            // InterfaceMethod io/reactivex/rxjava3/functions/Function.apply:(Ljava/lang/Object;)Ljava/lang/Object;
      36: ldc           #8                  // String The mapper function returned a null value.
      38: invokestatic  #9                  // Method java/util/Objects.requireNonNull:(Ljava/lang/Object;Ljava/lang/String;)Ljava/lang/Object;
      41: astore_2
      42: goto          52
      45: astore_3
      46: aload_0
      47: aload_3
      48: invokevirtual #11                 // Method fail:(Ljava/lang/Throwable;)V
      51: return
      52: aload_0
      53: getfield      #5                  // Field downstream:Lio/reactivex/rxjava3/operators/ConditionalSubscriber;
      56: aload_2
      57: invokeinterface #6,  2            // InterfaceMethod io/reactivex/rxjava3/operators/ConditionalSubscriber.onNext:(Ljava/lang/Object;)V
      62: return
    Exception table:
       from    to  target type
          26    42    45   Class java/lang/Throwable

  public boolean tryOnNext(T);
    Code:
       0: aload_0
       1: getfield      #3                  // Field done:Z
       4: ifeq          9
       7: iconst_1
       8: ireturn
       9: aload_0
      10: getfield      #4                  // Field sourceMode:I
      13: ifeq          29
      16: aload_0
      17: getfield      #5                  // Field downstream:Lio/reactivex/rxjava3/operators/ConditionalSubscriber;
      20: aconst_null
      21: invokeinterface #12,  2           // InterfaceMethod io/reactivex/rxjava3/operators/ConditionalSubscriber.tryOnNext:(Ljava/lang/Object;)Z
      26: pop
      27: iconst_1
      28: ireturn
      29: aload_0
      30: getfield      #2                  // Field mapper:Lio/reactivex/rxjava3/functions/Function;
      33: aload_1
      34: invokeinterface #7,  2            // InterfaceMethod io/reactivex/rxjava3/functions/Function.apply:(Ljava/lang/Object;)Ljava/lang/Object;
      39: ldc           #8                  // String The mapper function returned a null value.
      41: invokestatic  #9                  // Method java/util/Objects.requireNonNull:(Ljava/lang/Object;Ljava/lang/String;)Ljava/lang/Object;
      44: astore_2
      45: goto          56
      48: astore_3
      49: aload_0
      50: aload_3
      51: invokevirtual #11                 // Method fail:(Ljava/lang/Throwable;)V
      54: iconst_1
      55: ireturn
      56: aload_0
      57: getfield      #5                  // Field downstream:Lio/reactivex/rxjava3/operators/ConditionalSubscriber;
      60: aload_2
      61: invokeinterface #12,  2           // InterfaceMethod io/reactivex/rxjava3/operators/ConditionalSubscriber.tryOnNext:(Ljava/lang/Object;)Z
      66: ireturn
    Exception table:
       from    to  target type
          29    45    48   Class java/lang/Throwable

  public int requestFusion(int);
    Code:
       0: aload_0
       1: iload_1
       2: invokevirtual #13                 // Method transitiveBoundaryFusion:(I)I
       5: ireturn

  public U poll() throws java.lang.Throwable;
    Code:
       0: aload_0
       1: getfield      #14                 // Field qs:Lio/reactivex/rxjava3/operators/QueueSubscription;
       4: invokeinterface #15,  1           // InterfaceMethod io/reactivex/rxjava3/operators/QueueSubscription.poll:()Ljava/lang/Object;
       9: astore_1
      10: aload_1
      11: ifnull        32
      14: aload_0
      15: getfield      #2                  // Field mapper:Lio/reactivex/rxjava3/functions/Function;
      18: aload_1
      19: invokeinterface #7,  2            // InterfaceMethod io/reactivex/rxjava3/functions/Function.apply:(Ljava/lang/Object;)Ljava/lang/Object;
      24: ldc           #8                  // String The mapper function returned a null value.
      26: invokestatic  #9                  // Method java/util/Objects.requireNonNull:(Ljava/lang/Object;Ljava/lang/String;)Ljava/lang/Object;
      29: goto          33
      32: aconst_null
      33: areturn
}
