Compiled from "FlowableRepeat.java"
public final class io.reactivex.rxjava3.internal.operators.flowable.FlowableRepeat<T> extends io.reactivex.rxjava3.internal.operators.flowable.AbstractFlowableWithUpstream<T, T> {
  final long count;

  public io.reactivex.rxjava3.internal.operators.flowable.FlowableRepeat(io.reactivex.rxjava3.core.Flowable<T>, long);
    Code:
       0: aload_0
       1: aload_1
       2: invokespecial #1                  // Method io/reactivex/rxjava3/internal/operators/flowable/AbstractFlowableWithUpstream."<init>":(Lio/reactivex/rxjava3/core/Flowable;)V
       5: aload_0
       6: lload_2
       7: putfield      #2                  // Field count:J
      10: return

  public void subscribeActual(org.reactivestreams.Subscriber<? super T>);
    Code:
       0: new           #3                  // class io/reactivex/rxjava3/internal/subscriptions/SubscriptionArbiter
       3: dup
       4: iconst_0
       5: invokespecial #4                  // Method io/reactivex/rxjava3/internal/subscriptions/SubscriptionArbiter."<init>":(Z)V
       8: astore_2
       9: aload_1
      10: aload_2
      11: invokeinterface #5,  2            // InterfaceMethod org/reactivestreams/Subscriber.onSubscribe:(Lorg/reactivestreams/Subscription;)V
      16: new           #6                  // class io/reactivex/rxjava3/internal/operators/flowable/FlowableRepeat$RepeatSubscriber
      19: dup
      20: aload_1
      21: aload_0
      22: getfield      #2                  // Field count:J
      25: ldc2_w        #8                  // long 9223372036854775807l
      28: lcmp
      29: ifeq          41
      32: aload_0
      33: getfield      #2                  // Field count:J
      36: lconst_1
      37: lsub
      38: goto          44
      41: ldc2_w        #8                  // long 9223372036854775807l
      44: aload_2
      45: aload_0
      46: getfield      #10                 // Field source:Lio/reactivex/rxjava3/core/Flowable;
      49: invokespecial #11                 // Method io/reactivex/rxjava3/internal/operators/flowable/FlowableRepeat$RepeatSubscriber."<init>":(Lorg/reactivestreams/Subscriber;JLio/reactivex/rxjava3/internal/subscriptions/SubscriptionArbiter;Lorg/reactivestreams/Publisher;)V
      52: astore_3
      53: aload_3
      54: invokevirtual #12                 // Method io/reactivex/rxjava3/internal/operators/flowable/FlowableRepeat$RepeatSubscriber.subscribeNext:()V
      57: return
}
