Compiled from "FlowableSwitchIfEmpty.java"
public final class io.reactivex.rxjava3.internal.operators.flowable.FlowableSwitchIfEmpty<T> extends io.reactivex.rxjava3.internal.operators.flowable.AbstractFlowableWithUpstream<T, T> {
  final org.reactivestreams.Publisher<? extends T> other;

  public io.reactivex.rxjava3.internal.operators.flowable.FlowableSwitchIfEmpty(io.reactivex.rxjava3.core.Flowable<T>, org.reactivestreams.Publisher<? extends T>);
    Code:
       0: aload_0
       1: aload_1
       2: invokespecial #1                  // Method io/reactivex/rxjava3/internal/operators/flowable/AbstractFlowableWithUpstream."<init>":(Lio/reactivex/rxjava3/core/Flowable;)V
       5: aload_0
       6: aload_2
       7: putfield      #2                  // Field other:Lorg/reactivestreams/Publisher;
      10: return

  protected void subscribeActual(org.reactivestreams.Subscriber<? super T>);
    Code:
       0: new           #3                  // class io/reactivex/rxjava3/internal/operators/flowable/FlowableSwitchIfEmpty$SwitchIfEmptySubscriber
       3: dup
       4: aload_1
       5: aload_0
       6: getfield      #2                  // Field other:Lorg/reactivestreams/Publisher;
       9: invokespecial #4                  // Method io/reactivex/rxjava3/internal/operators/flowable/FlowableSwitchIfEmpty$SwitchIfEmptySubscriber."<init>":(Lorg/reactivestreams/Subscriber;Lorg/reactivestreams/Publisher;)V
      12: astore_2
      13: aload_1
      14: aload_2
      15: getfield      #5                  // Field io/reactivex/rxjava3/internal/operators/flowable/FlowableSwitchIfEmpty$SwitchIfEmptySubscriber.arbiter:Lio/reactivex/rxjava3/internal/subscriptions/SubscriptionArbiter;
      18: invokeinterface #6,  2            // InterfaceMethod org/reactivestreams/Subscriber.onSubscribe:(Lorg/reactivestreams/Subscription;)V
      23: aload_0
      24: getfield      #7                  // Field source:Lio/reactivex/rxjava3/core/Flowable;
      27: aload_2
      28: invokevirtual #8                  // Method io/reactivex/rxjava3/core/Flowable.subscribe:(Lio/reactivex/rxjava3/core/FlowableSubscriber;)V
      31: return
}
