Compiled from "FlowableMapPublisher.java"
public final class io.reactivex.rxjava3.internal.operators.flowable.FlowableMapPublisher<T, U> extends io.reactivex.rxjava3.core.Flowable<U> {
  final org.reactivestreams.Publisher<T> source;

  final io.reactivex.rxjava3.functions.Function<? super T, ? extends U> mapper;

  public io.reactivex.rxjava3.internal.operators.flowable.FlowableMapPublisher(org.reactivestreams.Publisher<T>, io.reactivex.rxjava3.functions.Function<? super T, ? extends U>);
    Code:
       0: aload_0
       1: invokespecial #1                  // Method io/reactivex/rxjava3/core/Flowable."<init>":()V
       4: aload_0
       5: aload_1
       6: putfield      #2                  // Field source:Lorg/reactivestreams/Publisher;
       9: aload_0
      10: aload_2
      11: putfield      #3                  // Field mapper:Lio/reactivex/rxjava3/functions/Function;
      14: return

  protected void subscribeActual(org.reactivestreams.Subscriber<? super U>);
    Code:
       0: aload_0
       1: getfield      #2                  // Field source:Lorg/reactivestreams/Publisher;
       4: new           #4                  // class io/reactivex/rxjava3/internal/operators/flowable/FlowableMap$MapSubscriber
       7: dup
       8: aload_1
       9: aload_0
      10: getfield      #3                  // Field mapper:Lio/reactivex/rxjava3/functions/Function;
      13: invokespecial #5                  // Method io/reactivex/rxjava3/internal/operators/flowable/FlowableMap$MapSubscriber."<init>":(Lorg/reactivestreams/Subscriber;Lio/reactivex/rxjava3/functions/Function;)V
      16: invokeinterface #6,  2            // InterfaceMethod org/reactivestreams/Publisher.subscribe:(Lorg/reactivestreams/Subscriber;)V
      21: return
}
