Compiled from "FlowableConcatMapScheduler.java"
public final class io.reactivex.rxjava3.internal.operators.flowable.FlowableConcatMapScheduler<T, R> extends io.reactivex.rxjava3.internal.operators.flowable.AbstractFlowableWithUpstream<T, R> {
  final io.reactivex.rxjava3.functions.Function<? super T, ? extends org.reactivestreams.Publisher<? extends R>> mapper;

  final int prefetch;

  final io.reactivex.rxjava3.internal.util.ErrorMode errorMode;

  final io.reactivex.rxjava3.core.Scheduler scheduler;

  public io.reactivex.rxjava3.internal.operators.flowable.FlowableConcatMapScheduler(io.reactivex.rxjava3.core.Flowable<T>, io.reactivex.rxjava3.functions.Function<? super T, ? extends org.reactivestreams.Publisher<? extends R>>, int, io.reactivex.rxjava3.internal.util.ErrorMode, io.reactivex.rxjava3.core.Scheduler);
    Code:
       0: aload_0
       1: aload_1
       2: invokespecial #1                  // Method io/reactivex/rxjava3/internal/operators/flowable/AbstractFlowableWithUpstream."<init>":(Lio/reactivex/rxjava3/core/Flowable;)V
       5: aload_0
       6: aload_2
       7: putfield      #2                  // Field mapper:Lio/reactivex/rxjava3/functions/Function;
      10: aload_0
      11: iload_3
      12: putfield      #3                  // Field prefetch:I
      15: aload_0
      16: aload         4
      18: putfield      #4                  // Field errorMode:Lio/reactivex/rxjava3/internal/util/ErrorMode;
      21: aload_0
      22: aload         5
      24: putfield      #5                  // Field scheduler:Lio/reactivex/rxjava3/core/Scheduler;
      27: return

  protected void subscribeActual(org.reactivestreams.Subscriber<? super R>);
    Code:
       0: getstatic     #6                  // Field io/reactivex/rxjava3/internal/operators/flowable/FlowableConcatMapScheduler$1.$SwitchMap$io$reactivex$rxjava3$internal$util$ErrorMode:[I
       3: aload_0
       4: getfield      #4                  // Field errorMode:Lio/reactivex/rxjava3/internal/util/ErrorMode;
       7: invokevirtual #7                  // Method io/reactivex/rxjava3/internal/util/ErrorMode.ordinal:()I
      10: iaload
      11: lookupswitch  { // 2
                     1: 36
                     2: 70
               default: 104
          }
      36: aload_0
      37: getfield      #8                  // Field source:Lio/reactivex/rxjava3/core/Flowable;
      40: new           #9                  // class io/reactivex/rxjava3/internal/operators/flowable/FlowableConcatMapScheduler$ConcatMapDelayed
      43: dup
      44: aload_1
      45: aload_0
      46: getfield      #2                  // Field mapper:Lio/reactivex/rxjava3/functions/Function;
      49: aload_0
      50: getfield      #3                  // Field prefetch:I
      53: iconst_0
      54: aload_0
      55: getfield      #5                  // Field scheduler:Lio/reactivex/rxjava3/core/Scheduler;
      58: invokevirtual #10                 // Method io/reactivex/rxjava3/core/Scheduler.createWorker:()Lio/reactivex/rxjava3/core/Scheduler$Worker;
      61: invokespecial #11                 // Method io/reactivex/rxjava3/internal/operators/flowable/FlowableConcatMapScheduler$ConcatMapDelayed."<init>":(Lorg/reactivestreams/Subscriber;Lio/reactivex/rxjava3/functions/Function;IZLio/reactivex/rxjava3/core/Scheduler$Worker;)V
      64: invokevirtual #12                 // Method io/reactivex/rxjava3/core/Flowable.subscribe:(Lio/reactivex/rxjava3/core/FlowableSubscriber;)V
      67: goto          134
      70: aload_0
      71: getfield      #8                  // Field source:Lio/reactivex/rxjava3/core/Flowable;
      74: new           #9                  // class io/reactivex/rxjava3/internal/operators/flowable/FlowableConcatMapScheduler$ConcatMapDelayed
      77: dup
      78: aload_1
      79: aload_0
      80: getfield      #2                  // Field mapper:Lio/reactivex/rxjava3/functions/Function;
      83: aload_0
      84: getfield      #3                  // Field prefetch:I
      87: iconst_1
      88: aload_0
      89: getfield      #5                  // Field scheduler:Lio/reactivex/rxjava3/core/Scheduler;
      92: invokevirtual #10                 // Method io/reactivex/rxjava3/core/Scheduler.createWorker:()Lio/reactivex/rxjava3/core/Scheduler$Worker;
      95: invokespecial #11                 // Method io/reactivex/rxjava3/internal/operators/flowable/FlowableConcatMapScheduler$ConcatMapDelayed."<init>":(Lorg/reactivestreams/Subscriber;Lio/reactivex/rxjava3/functions/Function;IZLio/reactivex/rxjava3/core/Scheduler$Worker;)V
      98: invokevirtual #12                 // Method io/reactivex/rxjava3/core/Flowable.subscribe:(Lio/reactivex/rxjava3/core/FlowableSubscriber;)V
     101: goto          134
     104: aload_0
     105: getfield      #8                  // Field source:Lio/reactivex/rxjava3/core/Flowable;
     108: new           #13                 // class io/reactivex/rxjava3/internal/operators/flowable/FlowableConcatMapScheduler$ConcatMapImmediate
     111: dup
     112: aload_1
     113: aload_0
     114: getfield      #2                  // Field mapper:Lio/reactivex/rxjava3/functions/Function;
     117: aload_0
     118: getfield      #3                  // Field prefetch:I
     121: aload_0
     122: getfield      #5                  // Field scheduler:Lio/reactivex/rxjava3/core/Scheduler;
     125: invokevirtual #10                 // Method io/reactivex/rxjava3/core/Scheduler.createWorker:()Lio/reactivex/rxjava3/core/Scheduler$Worker;
     128: invokespecial #14                 // Method io/reactivex/rxjava3/internal/operators/flowable/FlowableConcatMapScheduler$ConcatMapImmediate."<init>":(Lorg/reactivestreams/Subscriber;Lio/reactivex/rxjava3/functions/Function;ILio/reactivex/rxjava3/core/Scheduler$Worker;)V
     131: invokevirtual #12                 // Method io/reactivex/rxjava3/core/Flowable.subscribe:(Lio/reactivex/rxjava3/core/FlowableSubscriber;)V
     134: return
}
