Compiled from "FlowableCreate.java"
abstract class io.reactivex.rxjava3.internal.operators.flowable.FlowableCreate$BaseEmitter<T> extends java.util.concurrent.atomic.AtomicLong implements io.reactivex.rxjava3.core.FlowableEmitter<T>, org.reactivestreams.Subscription {
  private static final long serialVersionUID;

  final org.reactivestreams.Subscriber<? super T> downstream;

  final io.reactivex.rxjava3.internal.disposables.SequentialDisposable serial;

  io.reactivex.rxjava3.internal.operators.flowable.FlowableCreate$BaseEmitter(org.reactivestreams.Subscriber<? super T>);
    Code:
       0: aload_0
       1: invokespecial #1                  // Method java/util/concurrent/atomic/AtomicLong."<init>":()V
       4: aload_0
       5: aload_1
       6: putfield      #2                  // Field downstream:Lorg/reactivestreams/Subscriber;
       9: aload_0
      10: new           #3                  // class io/reactivex/rxjava3/internal/disposables/SequentialDisposable
      13: dup
      14: invokespecial #4                  // Method io/reactivex/rxjava3/internal/disposables/SequentialDisposable."<init>":()V
      17: putfield      #5                  // Field serial:Lio/reactivex/rxjava3/internal/disposables/SequentialDisposable;
      20: return

  public void onComplete();
    Code:
       0: aload_0
       1: invokevirtual #6                  // Method completeDownstream:()V
       4: return

  protected void completeDownstream();
    Code:
       0: aload_0
       1: invokevirtual #7                  // Method isCancelled:()Z
       4: ifeq          8
       7: return
       8: aload_0
       9: getfield      #2                  // Field downstream:Lorg/reactivestreams/Subscriber;
      12: invokeinterface #8,  1            // InterfaceMethod org/reactivestreams/Subscriber.onComplete:()V
      17: aload_0
      18: getfield      #5                  // Field serial:Lio/reactivex/rxjava3/internal/disposables/SequentialDisposable;
      21: invokevirtual #9                  // Method io/reactivex/rxjava3/internal/disposables/SequentialDisposable.dispose:()V
      24: goto          37
      27: astore_1
      28: aload_0
      29: getfield      #5                  // Field serial:Lio/reactivex/rxjava3/internal/disposables/SequentialDisposable;
      32: invokevirtual #9                  // Method io/reactivex/rxjava3/internal/disposables/SequentialDisposable.dispose:()V
      35: aload_1
      36: athrow
      37: return
    Exception table:
       from    to  target type
           8    17    27   any

  public final void onError(java.lang.Throwable);
    Code:
       0: aload_1
       1: ifnonnull     10
       4: ldc           #10                 // String onError called with a null Throwable.
       6: invokestatic  #11                 // Method io/reactivex/rxjava3/internal/util/ExceptionHelper.createNullPointerException:(Ljava/lang/String;)Ljava/lang/NullPointerException;
       9: astore_1
      10: aload_0
      11: aload_1
      12: invokevirtual #12                 // Method signalError:(Ljava/lang/Throwable;)Z
      15: ifne          22
      18: aload_1
      19: invokestatic  #13                 // Method io/reactivex/rxjava3/plugins/RxJavaPlugins.onError:(Ljava/lang/Throwable;)V
      22: return

  public final boolean tryOnError(java.lang.Throwable);
    Code:
       0: aload_1
       1: ifnonnull     10
       4: ldc           #14                 // String tryOnError called with a null Throwable.
       6: invokestatic  #11                 // Method io/reactivex/rxjava3/internal/util/ExceptionHelper.createNullPointerException:(Ljava/lang/String;)Ljava/lang/NullPointerException;
       9: astore_1
      10: aload_0
      11: aload_1
      12: invokevirtual #12                 // Method signalError:(Ljava/lang/Throwable;)Z
      15: ireturn

  public boolean signalError(java.lang.Throwable);
    Code:
       0: aload_0
       1: aload_1
       2: invokevirtual #15                 // Method errorDownstream:(Ljava/lang/Throwable;)Z
       5: ireturn

  protected boolean errorDownstream(java.lang.Throwable);
    Code:
       0: aload_0
       1: invokevirtual #7                  // Method isCancelled:()Z
       4: ifeq          9
       7: iconst_0
       8: ireturn
       9: aload_0
      10: getfield      #2                  // Field downstream:Lorg/reactivestreams/Subscriber;
      13: aload_1
      14: invokeinterface #16,  2           // InterfaceMethod org/reactivestreams/Subscriber.onError:(Ljava/lang/Throwable;)V
      19: aload_0
      20: getfield      #5                  // Field serial:Lio/reactivex/rxjava3/internal/disposables/SequentialDisposable;
      23: invokevirtual #9                  // Method io/reactivex/rxjava3/internal/disposables/SequentialDisposable.dispose:()V
      26: goto          39
      29: astore_2
      30: aload_0
      31: getfield      #5                  // Field serial:Lio/reactivex/rxjava3/internal/disposables/SequentialDisposable;
      34: invokevirtual #9                  // Method io/reactivex/rxjava3/internal/disposables/SequentialDisposable.dispose:()V
      37: aload_2
      38: athrow
      39: iconst_1
      40: ireturn
    Exception table:
       from    to  target type
           9    19    29   any

  public final void cancel();
    Code:
       0: aload_0
       1: getfield      #5                  // Field serial:Lio/reactivex/rxjava3/internal/disposables/SequentialDisposable;
       4: invokevirtual #9                  // Method io/reactivex/rxjava3/internal/disposables/SequentialDisposable.dispose:()V
       7: aload_0
       8: invokevirtual #17                 // Method onUnsubscribed:()V
      11: return

  void onUnsubscribed();
    Code:
       0: return

  public final boolean isCancelled();
    Code:
       0: aload_0
       1: getfield      #5                  // Field serial:Lio/reactivex/rxjava3/internal/disposables/SequentialDisposable;
       4: invokevirtual #18                 // Method io/reactivex/rxjava3/internal/disposables/SequentialDisposable.isDisposed:()Z
       7: ireturn

  public final void request(long);
    Code:
       0: lload_1
       1: invokestatic  #19                 // Method io/reactivex/rxjava3/internal/subscriptions/SubscriptionHelper.validate:(J)Z
       4: ifeq          17
       7: aload_0
       8: lload_1
       9: invokestatic  #20                 // Method io/reactivex/rxjava3/internal/util/BackpressureHelper.add:(Ljava/util/concurrent/atomic/AtomicLong;J)J
      12: pop2
      13: aload_0
      14: invokevirtual #21                 // Method onRequested:()V
      17: return

  void onRequested();
    Code:
       0: return

  public final void setDisposable(io.reactivex.rxjava3.disposables.Disposable);
    Code:
       0: aload_0
       1: getfield      #5                  // Field serial:Lio/reactivex/rxjava3/internal/disposables/SequentialDisposable;
       4: aload_1
       5: invokevirtual #22                 // Method io/reactivex/rxjava3/internal/disposables/SequentialDisposable.update:(Lio/reactivex/rxjava3/disposables/Disposable;)Z
       8: pop
       9: return

  public final void setCancellable(io.reactivex.rxjava3.functions.Cancellable);
    Code:
       0: aload_0
       1: new           #23                 // class io/reactivex/rxjava3/internal/disposables/CancellableDisposable
       4: dup
       5: aload_1
       6: invokespecial #24                 // Method io/reactivex/rxjava3/internal/disposables/CancellableDisposable."<init>":(Lio/reactivex/rxjava3/functions/Cancellable;)V
       9: invokevirtual #25                 // Method setDisposable:(Lio/reactivex/rxjava3/disposables/Disposable;)V
      12: return

  public final long requested();
    Code:
       0: aload_0
       1: invokevirtual #26                 // Method get:()J
       4: lreturn

  public final io.reactivex.rxjava3.core.FlowableEmitter<T> serialize();
    Code:
       0: new           #27                 // class io/reactivex/rxjava3/internal/operators/flowable/FlowableCreate$SerializedEmitter
       3: dup
       4: aload_0
       5: invokespecial #28                 // Method io/reactivex/rxjava3/internal/operators/flowable/FlowableCreate$SerializedEmitter."<init>":(Lio/reactivex/rxjava3/internal/operators/flowable/FlowableCreate$BaseEmitter;)V
       8: areturn

  public java.lang.String toString();
    Code:
       0: ldc           #29                 // String %s{%s}
       2: iconst_2
       3: anewarray     #30                 // class java/lang/Object
       6: dup
       7: iconst_0
       8: aload_0
       9: invokevirtual #31                 // Method java/lang/Object.getClass:()Ljava/lang/Class;
      12: invokevirtual #32                 // Method java/lang/Class.getSimpleName:()Ljava/lang/String;
      15: aastore
      16: dup
      17: iconst_1
      18: aload_0
      19: invokespecial #33                 // Method java/util/concurrent/atomic/AtomicLong.toString:()Ljava/lang/String;
      22: aastore
      23: invokestatic  #34                 // Method java/lang/String.format:(Ljava/lang/String;[Ljava/lang/Object;)Ljava/lang/String;
      26: areturn
}
