Compiled from "FlowableSampleTimed.java"
final class io.reactivex.rxjava3.internal.operators.flowable.FlowableSampleTimed$SampleTimedNoLast<T> extends io.reactivex.rxjava3.internal.operators.flowable.FlowableSampleTimed$SampleTimedSubscriber<T> {
  private static final long serialVersionUID;

  io.reactivex.rxjava3.internal.operators.flowable.FlowableSampleTimed$SampleTimedNoLast(org.reactivestreams.Subscriber<? super T>, long, java.util.concurrent.TimeUnit, io.reactivex.rxjava3.core.Scheduler, io.reactivex.rxjava3.functions.Consumer<? super T>);
    Code:
       0: aload_0
       1: aload_1
       2: lload_2
       3: aload         4
       5: aload         5
       7: aload         6
       9: invokespecial #1                  // Method io/reactivex/rxjava3/internal/operators/flowable/FlowableSampleTimed$SampleTimedSubscriber."<init>":(Lorg/reactivestreams/Subscriber;JLjava/util/concurrent/TimeUnit;Lio/reactivex/rxjava3/core/Scheduler;Lio/reactivex/rxjava3/functions/Consumer;)V
      12: return

  void complete();
    Code:
       0: aload_0
       1: getfield      #2                  // Field downstream:Lorg/reactivestreams/Subscriber;
       4: invokeinterface #3,  1            // InterfaceMethod org/reactivestreams/Subscriber.onComplete:()V
       9: return

  public void run();
    Code:
       0: aload_0
       1: invokevirtual #4                  // Method emit:()V
       4: return
}
