Compiled from "FlowableLastSingle.java"
public final class io.reactivex.rxjava3.internal.operators.flowable.FlowableLastSingle<T> extends io.reactivex.rxjava3.core.Single<T> {
  final org.reactivestreams.Publisher<T> source;

  final T defaultItem;

  public io.reactivex.rxjava3.internal.operators.flowable.FlowableLastSingle(org.reactivestreams.Publisher<T>, T);
    Code:
       0: aload_0
       1: invokespecial #1                  // Method io/reactivex/rxjava3/core/Single."<init>":()V
       4: aload_0
       5: aload_1
       6: putfield      #2                  // Field source:Lorg/reactivestreams/Publisher;
       9: aload_0
      10: aload_2
      11: putfield      #3                  // Field defaultItem:Ljava/lang/Object;
      14: return

  protected void subscribeActual(io.reactivex.rxjava3.core.SingleObserver<? super T>);
    Code:
       0: aload_0
       1: getfield      #2                  // Field source:Lorg/reactivestreams/Publisher;
       4: new           #4                  // class io/reactivex/rxjava3/internal/operators/flowable/FlowableLastSingle$LastSubscriber
       7: dup
       8: aload_1
       9: aload_0
      10: getfield      #3                  // Field defaultItem:Ljava/lang/Object;
      13: invokespecial #5                  // Method io/reactivex/rxjava3/internal/operators/flowable/FlowableLastSingle$LastSubscriber."<init>":(Lio/reactivex/rxjava3/core/SingleObserver;Ljava/lang/Object;)V
      16: invokeinterface #6,  2            // InterfaceMethod org/reactivestreams/Publisher.subscribe:(Lorg/reactivestreams/Subscriber;)V
      21: return
}
