Compiled from "FlowableFromObservable.java"
final class io.reactivex.rxjava3.internal.operators.flowable.FlowableFromObservable$SubscriberObserver<T> implements io.reactivex.rxjava3.core.Observer<T>, org.reactivestreams.Subscription {
  final org.reactivestreams.Subscriber<? super T> downstream;

  io.reactivex.rxjava3.disposables.Disposable upstream;

  io.reactivex.rxjava3.internal.operators.flowable.FlowableFromObservable$SubscriberObserver(org.reactivestreams.Subscriber<? super T>);
    Code:
       0: aload_0
       1: invokespecial #1                  // Method java/lang/Object."<init>":()V
       4: aload_0
       5: aload_1
       6: putfield      #2                  // Field downstream:Lorg/reactivestreams/Subscriber;
       9: return

  public void onComplete();
    Code:
       0: aload_0
       1: getfield      #2                  // Field downstream:Lorg/reactivestreams/Subscriber;
       4: invokeinterface #3,  1            // InterfaceMethod org/reactivestreams/Subscriber.onComplete:()V
       9: return

  public void onError(java.lang.Throwable);
    Code:
       0: aload_0
       1: getfield      #2                  // Field downstream:Lorg/reactivestreams/Subscriber;
       4: aload_1
       5: invokeinterface #4,  2            // InterfaceMethod org/reactivestreams/Subscriber.onError:(Ljava/lang/Throwable;)V
      10: return

  public void onNext(T);
    Code:
       0: aload_0
       1: getfield      #2                  // Field downstream:Lorg/reactivestreams/Subscriber;
       4: aload_1
       5: invokeinterface #5,  2            // InterfaceMethod org/reactivestreams/Subscriber.onNext:(Ljava/lang/Object;)V
      10: return

  public void onSubscribe(io.reactivex.rxjava3.disposables.Disposable);
    Code:
       0: aload_0
       1: aload_1
       2: putfield      #6                  // Field upstream:Lio/reactivex/rxjava3/disposables/Disposable;
       5: aload_0
       6: getfield      #2                  // Field downstream:Lorg/reactivestreams/Subscriber;
       9: aload_0
      10: invokeinterface #7,  2            // InterfaceMethod org/reactivestreams/Subscriber.onSubscribe:(Lorg/reactivestreams/Subscription;)V
      15: return

  public void cancel();
    Code:
       0: aload_0
       1: getfield      #6                  // Field upstream:Lio/reactivex/rxjava3/disposables/Disposable;
       4: invokeinterface #8,  1            // InterfaceMethod io/reactivex/rxjava3/disposables/Disposable.dispose:()V
       9: return

  public void request(long);
    Code:
       0: return
}
