Compiled from "FlowableRangeLong.java"
abstract class io.reactivex.rxjava3.internal.operators.flowable.FlowableRangeLong$BaseRangeSubscription extends io.reactivex.rxjava3.internal.subscriptions.BasicQueueSubscription<java.lang.Long> {
  private static final long serialVersionUID;

  final long end;

  long index;

  volatile boolean cancelled;

  io.reactivex.rxjava3.internal.operators.flowable.FlowableRangeLong$BaseRangeSubscription(long, long);
    Code:
       0: aload_0
       1: invokespecial #1                  // Method io/reactivex/rxjava3/internal/subscriptions/BasicQueueSubscription."<init>":()V
       4: aload_0
       5: lload_1
       6: putfield      #2                  // Field index:J
       9: aload_0
      10: lload_3
      11: putfield      #3                  // Field end:J
      14: return

  public final int requestFusion(int);
    Code:
       0: iload_1
       1: iconst_1
       2: iand
       3: ireturn

  public final java.lang.Long poll();
    Code:
       0: aload_0
       1: getfield      #2                  // Field index:J
       4: lstore_1
       5: lload_1
       6: aload_0
       7: getfield      #3                  // Field end:J
      10: lcmp
      11: ifne          16
      14: aconst_null
      15: areturn
      16: aload_0
      17: lload_1
      18: lconst_1
      19: ladd
      20: putfield      #2                  // Field index:J
      23: lload_1
      24: invokestatic  #5                  // Method java/lang/Long.valueOf:(J)Ljava/lang/Long;
      27: areturn

  public final boolean isEmpty();
    Code:
       0: aload_0
       1: getfield      #2                  // Field index:J
       4: aload_0
       5: getfield      #3                  // Field end:J
       8: lcmp
       9: ifne          16
      12: iconst_1
      13: goto          17
      16: iconst_0
      17: ireturn

  public final void clear();
    Code:
       0: aload_0
       1: aload_0
       2: getfield      #3                  // Field end:J
       5: putfield      #2                  // Field index:J
       8: return

  public final void request(long);
    Code:
       0: lload_1
       1: invokestatic  #6                  // Method io/reactivex/rxjava3/internal/subscriptions/SubscriptionHelper.validate:(J)Z
       4: ifeq          37
       7: aload_0
       8: lload_1
       9: invokestatic  #7                  // Method io/reactivex/rxjava3/internal/util/BackpressureHelper.add:(Ljava/util/concurrent/atomic/AtomicLong;J)J
      12: lconst_0
      13: lcmp
      14: ifne          37
      17: lload_1
      18: ldc2_w        #9                  // long 9223372036854775807l
      21: lcmp
      22: ifne          32
      25: aload_0
      26: invokevirtual #11                 // Method fastPath:()V
      29: goto          37
      32: aload_0
      33: lload_1
      34: invokevirtual #12                 // Method slowPath:(J)V
      37: return

  public final void cancel();
    Code:
       0: aload_0
       1: iconst_1
       2: putfield      #13                 // Field cancelled:Z
       5: return

  abstract void fastPath();

  abstract void slowPath(long);

  public java.lang.Object poll() throws java.lang.Throwable;
    Code:
       0: aload_0
       1: invokevirtual #14                 // Method poll:()Ljava/lang/Long;
       4: areturn
}
