Compiled from "FlowableBufferExactBoundary.java"
public final class io.reactivex.rxjava3.internal.operators.flowable.FlowableBufferExactBoundary<T, U extends java.util.Collection<? super T>, B> extends io.reactivex.rxjava3.internal.operators.flowable.AbstractFlowableWithUpstream<T, U> {
  final org.reactivestreams.Publisher<B> boundary;

  final io.reactivex.rxjava3.functions.Supplier<U> bufferSupplier;

  public io.reactivex.rxjava3.internal.operators.flowable.FlowableBufferExactBoundary(io.reactivex.rxjava3.core.Flowable<T>, org.reactivestreams.Publisher<B>, io.reactivex.rxjava3.functions.Supplier<U>);
    Code:
       0: aload_0
       1: aload_1
       2: invokespecial #1                  // Method io/reactivex/rxjava3/internal/operators/flowable/AbstractFlowableWithUpstream."<init>":(Lio/reactivex/rxjava3/core/Flowable;)V
       5: aload_0
       6: aload_2
       7: putfield      #2                  // Field boundary:Lorg/reactivestreams/Publisher;
      10: aload_0
      11: aload_3
      12: putfield      #3                  // Field bufferSupplier:Lio/reactivex/rxjava3/functions/Supplier;
      15: return

  protected void subscribeActual(org.reactivestreams.Subscriber<? super U>);
    Code:
       0: aload_0
       1: getfield      #4                  // Field source:Lio/reactivex/rxjava3/core/Flowable;
       4: new           #5                  // class io/reactivex/rxjava3/internal/operators/flowable/FlowableBufferExactBoundary$BufferExactBoundarySubscriber
       7: dup
       8: new           #6                  // class io/reactivex/rxjava3/subscribers/SerializedSubscriber
      11: dup
      12: aload_1
      13: invokespecial #7                  // Method io/reactivex/rxjava3/subscribers/SerializedSubscriber."<init>":(Lorg/reactivestreams/Subscriber;)V
      16: aload_0
      17: getfield      #3                  // Field bufferSupplier:Lio/reactivex/rxjava3/functions/Supplier;
      20: aload_0
      21: getfield      #2                  // Field boundary:Lorg/reactivestreams/Publisher;
      24: invokespecial #8                  // Method io/reactivex/rxjava3/internal/operators/flowable/FlowableBufferExactBoundary$BufferExactBoundarySubscriber."<init>":(Lorg/reactivestreams/Subscriber;Lio/reactivex/rxjava3/functions/Supplier;Lorg/reactivestreams/Publisher;)V
      27: invokevirtual #9                  // Method io/reactivex/rxjava3/core/Flowable.subscribe:(Lio/reactivex/rxjava3/core/FlowableSubscriber;)V
      30: return
}
