Compiled from "FlowableInternalHelper.java"
final class io.reactivex.rxjava3.internal.operators.flowable.FlowableInternalHelper$FlatMapIntoIterable<T, U> implements io.reactivex.rxjava3.functions.Function<T, org.reactivestreams.Publisher<U>> {
  private final io.reactivex.rxjava3.functions.Function<? super T, ? extends java.lang.Iterable<? extends U>> mapper;

  io.reactivex.rxjava3.internal.operators.flowable.FlowableInternalHelper$FlatMapIntoIterable(io.reactivex.rxjava3.functions.Function<? super T, ? extends java.lang.Iterable<? extends U>>);
    Code:
       0: aload_0
       1: invokespecial #1                  // Method java/lang/Object."<init>":()V
       4: aload_0
       5: aload_1
       6: putfield      #2                  // Field mapper:Lio/reactivex/rxjava3/functions/Function;
       9: return

  public org.reactivestreams.Publisher<U> apply(T) throws java.lang.Throwable;
    Code:
       0: new           #3                  // class io/reactivex/rxjava3/internal/operators/flowable/FlowableFromIterable
       3: dup
       4: aload_0
       5: getfield      #2                  // Field mapper:Lio/reactivex/rxjava3/functions/Function;
       8: aload_1
       9: invokeinterface #4,  2            // InterfaceMethod io/reactivex/rxjava3/functions/Function.apply:(Ljava/lang/Object;)Ljava/lang/Object;
      14: ldc           #5                  // String The mapper returned a null Iterable
      16: invokestatic  #6                  // Method java/util/Objects.requireNonNull:(Ljava/lang/Object;Ljava/lang/String;)Ljava/lang/Object;
      19: checkcast     #7                  // class java/lang/Iterable
      22: invokespecial #8                  // Method io/reactivex/rxjava3/internal/operators/flowable/FlowableFromIterable."<init>":(Ljava/lang/Iterable;)V
      25: areturn

  public java.lang.Object apply(java.lang.Object) throws java.lang.Throwable;
    Code:
       0: aload_0
       1: aload_1
       2: invokevirtual #9                  // Method apply:(Ljava/lang/Object;)Lorg/reactivestreams/Publisher;
       5: areturn
}
