Compiled from "FlowableAmb.java"
final class io.reactivex.rxjava3.internal.operators.flowable.FlowableAmb$AmbCoordinator<T> implements org.reactivestreams.Subscription {
  final org.reactivestreams.Subscriber<? super T> downstream;

  final io.reactivex.rxjava3.internal.operators.flowable.FlowableAmb$AmbInnerSubscriber<T>[] subscribers;

  final java.util.concurrent.atomic.AtomicInteger winner;

  io.reactivex.rxjava3.internal.operators.flowable.FlowableAmb$AmbCoordinator(org.reactivestreams.Subscriber<? super T>, int);
    Code:
       0: aload_0
       1: invokespecial #1                  // Method java/lang/Object."<init>":()V
       4: aload_0
       5: new           #2                  // class java/util/concurrent/atomic/AtomicInteger
       8: dup
       9: invokespecial #3                  // Method java/util/concurrent/atomic/AtomicInteger."<init>":()V
      12: putfield      #4                  // Field winner:Ljava/util/concurrent/atomic/AtomicInteger;
      15: aload_0
      16: aload_1
      17: putfield      #5                  // Field downstream:Lorg/reactivestreams/Subscriber;
      20: aload_0
      21: iload_2
      22: anewarray     #6                  // class io/reactivex/rxjava3/internal/operators/flowable/FlowableAmb$AmbInnerSubscriber
      25: putfield      #7                  // Field subscribers:[Lio/reactivex/rxjava3/internal/operators/flowable/FlowableAmb$AmbInnerSubscriber;
      28: return

  public void subscribe(org.reactivestreams.Publisher<? extends T>[]);
    Code:
       0: aload_0
       1: getfield      #7                  // Field subscribers:[Lio/reactivex/rxjava3/internal/operators/flowable/FlowableAmb$AmbInnerSubscriber;
       4: astore_2
       5: aload_2
       6: arraylength
       7: istore_3
       8: iconst_0
       9: istore        4
      11: iload         4
      13: iload_3
      14: if_icmpge     43
      17: aload_2
      18: iload         4
      20: new           #6                  // class io/reactivex/rxjava3/internal/operators/flowable/FlowableAmb$AmbInnerSubscriber
      23: dup
      24: aload_0
      25: iload         4
      27: iconst_1
      28: iadd
      29: aload_0
      30: getfield      #5                  // Field downstream:Lorg/reactivestreams/Subscriber;
      33: invokespecial #8                  // Method io/reactivex/rxjava3/internal/operators/flowable/FlowableAmb$AmbInnerSubscriber."<init>":(Lio/reactivex/rxjava3/internal/operators/flowable/FlowableAmb$AmbCoordinator;ILorg/reactivestreams/Subscriber;)V
      36: aastore
      37: iinc          4, 1
      40: goto          11
      43: aload_0
      44: getfield      #4                  // Field winner:Ljava/util/concurrent/atomic/AtomicInteger;
      47: iconst_0
      48: invokevirtual #9                  // Method java/util/concurrent/atomic/AtomicInteger.lazySet:(I)V
      51: aload_0
      52: getfield      #5                  // Field downstream:Lorg/reactivestreams/Subscriber;
      55: aload_0
      56: invokeinterface #10,  2           // InterfaceMethod org/reactivestreams/Subscriber.onSubscribe:(Lorg/reactivestreams/Subscription;)V
      61: iconst_0
      62: istore        4
      64: iload         4
      66: iload_3
      67: if_icmpge     100
      70: aload_0
      71: getfield      #4                  // Field winner:Ljava/util/concurrent/atomic/AtomicInteger;
      74: invokevirtual #11                 // Method java/util/concurrent/atomic/AtomicInteger.get:()I
      77: ifeq          81
      80: return
      81: aload_1
      82: iload         4
      84: aaload
      85: aload_2
      86: iload         4
      88: aaload
      89: invokeinterface #12,  2           // InterfaceMethod org/reactivestreams/Publisher.subscribe:(Lorg/reactivestreams/Subscriber;)V
      94: iinc          4, 1
      97: goto          64
     100: return

  public void request(long);
    Code:
       0: lload_1
       1: invokestatic  #13                 // Method io/reactivex/rxjava3/internal/subscriptions/SubscriptionHelper.validate:(J)Z
       4: ifeq          78
       7: aload_0
       8: getfield      #4                  // Field winner:Ljava/util/concurrent/atomic/AtomicInteger;
      11: invokevirtual #11                 // Method java/util/concurrent/atomic/AtomicInteger.get:()I
      14: istore_3
      15: iload_3
      16: ifle          34
      19: aload_0
      20: getfield      #7                  // Field subscribers:[Lio/reactivex/rxjava3/internal/operators/flowable/FlowableAmb$AmbInnerSubscriber;
      23: iload_3
      24: iconst_1
      25: isub
      26: aaload
      27: lload_1
      28: invokevirtual #14                 // Method io/reactivex/rxjava3/internal/operators/flowable/FlowableAmb$AmbInnerSubscriber.request:(J)V
      31: goto          78
      34: iload_3
      35: ifne          78
      38: aload_0
      39: getfield      #7                  // Field subscribers:[Lio/reactivex/rxjava3/internal/operators/flowable/FlowableAmb$AmbInnerSubscriber;
      42: astore        4
      44: aload         4
      46: arraylength
      47: istore        5
      49: iconst_0
      50: istore        6
      52: iload         6
      54: iload         5
      56: if_icmpge     78
      59: aload         4
      61: iload         6
      63: aaload
      64: astore        7
      66: aload         7
      68: lload_1
      69: invokevirtual #14                 // Method io/reactivex/rxjava3/internal/operators/flowable/FlowableAmb$AmbInnerSubscriber.request:(J)V
      72: iinc          6, 1
      75: goto          52
      78: return

  public boolean win(int);
    Code:
       0: aload_0
       1: getfield      #4                  // Field winner:Ljava/util/concurrent/atomic/AtomicInteger;
       4: invokevirtual #11                 // Method java/util/concurrent/atomic/AtomicInteger.get:()I
       7: istore_2
       8: iload_2
       9: ifne          66
      12: aload_0
      13: getfield      #4                  // Field winner:Ljava/util/concurrent/atomic/AtomicInteger;
      16: iconst_0
      17: iload_1
      18: invokevirtual #15                 // Method java/util/concurrent/atomic/AtomicInteger.compareAndSet:(II)Z
      21: ifeq          66
      24: aload_0
      25: getfield      #7                  // Field subscribers:[Lio/reactivex/rxjava3/internal/operators/flowable/FlowableAmb$AmbInnerSubscriber;
      28: astore_3
      29: aload_3
      30: arraylength
      31: istore        4
      33: iconst_0
      34: istore        5
      36: iload         5
      38: iload         4
      40: if_icmpge     64
      43: iload         5
      45: iconst_1
      46: iadd
      47: iload_1
      48: if_icmpeq     58
      51: aload_3
      52: iload         5
      54: aaload
      55: invokevirtual #16                 // Method io/reactivex/rxjava3/internal/operators/flowable/FlowableAmb$AmbInnerSubscriber.cancel:()V
      58: iinc          5, 1
      61: goto          36
      64: iconst_1
      65: ireturn
      66: iconst_0
      67: ireturn

  public void cancel();
    Code:
       0: aload_0
       1: getfield      #4                  // Field winner:Ljava/util/concurrent/atomic/AtomicInteger;
       4: invokevirtual #11                 // Method java/util/concurrent/atomic/AtomicInteger.get:()I
       7: iconst_m1
       8: if_icmpeq     50
      11: aload_0
      12: getfield      #4                  // Field winner:Ljava/util/concurrent/atomic/AtomicInteger;
      15: iconst_m1
      16: invokevirtual #9                  // Method java/util/concurrent/atomic/AtomicInteger.lazySet:(I)V
      19: aload_0
      20: getfield      #7                  // Field subscribers:[Lio/reactivex/rxjava3/internal/operators/flowable/FlowableAmb$AmbInnerSubscriber;
      23: astore_1
      24: aload_1
      25: arraylength
      26: istore_2
      27: iconst_0
      28: istore_3
      29: iload_3
      30: iload_2
      31: if_icmpge     50
      34: aload_1
      35: iload_3
      36: aaload
      37: astore        4
      39: aload         4
      41: invokevirtual #16                 // Method io/reactivex/rxjava3/internal/operators/flowable/FlowableAmb$AmbInnerSubscriber.cancel:()V
      44: iinc          3, 1
      47: goto          29
      50: return
}
