Compiled from "FlowableInternalHelper.java"
final class io.reactivex.rxjava3.internal.operators.flowable.FlowableInternalHelper$ItemDelayFunction<T, U> implements io.reactivex.rxjava3.functions.Function<T, org.reactivestreams.Publisher<T>> {
  final io.reactivex.rxjava3.functions.Function<? super T, ? extends org.reactivestreams.Publisher<U>> itemDelay;

  io.reactivex.rxjava3.internal.operators.flowable.FlowableInternalHelper$ItemDelayFunction(io.reactivex.rxjava3.functions.Function<? super T, ? extends org.reactivestreams.Publisher<U>>);
    Code:
       0: aload_0
       1: invokespecial #1                  // Method java/lang/Object."<init>":()V
       4: aload_0
       5: aload_1
       6: putfield      #2                  // Field itemDelay:Lio/reactivex/rxjava3/functions/Function;
       9: return

  public org.reactivestreams.Publisher<T> apply(T) throws java.lang.Throwable;
    Code:
       0: aload_0
       1: getfield      #2                  // Field itemDelay:Lio/reactivex/rxjava3/functions/Function;
       4: aload_1
       5: invokeinterface #3,  2            // InterfaceMethod io/reactivex/rxjava3/functions/Function.apply:(Ljava/lang/Object;)Ljava/lang/Object;
      10: ldc           #4                  // String The itemDelay returned a null Publisher
      12: invokestatic  #5                  // Method java/util/Objects.requireNonNull:(Ljava/lang/Object;Ljava/lang/String;)Ljava/lang/Object;
      15: checkcast     #6                  // class org/reactivestreams/Publisher
      18: astore_2
      19: new           #7                  // class io/reactivex/rxjava3/internal/operators/flowable/FlowableTakePublisher
      22: dup
      23: aload_2
      24: lconst_1
      25: invokespecial #8                  // Method io/reactivex/rxjava3/internal/operators/flowable/FlowableTakePublisher."<init>":(Lorg/reactivestreams/Publisher;J)V
      28: aload_1
      29: invokestatic  #9                  // Method io/reactivex/rxjava3/internal/functions/Functions.justFunction:(Ljava/lang/Object;)Lio/reactivex/rxjava3/functions/Function;
      32: invokevirtual #10                 // Method io/reactivex/rxjava3/internal/operators/flowable/FlowableTakePublisher.map:(Lio/reactivex/rxjava3/functions/Function;)Lio/reactivex/rxjava3/core/Flowable;
      35: aload_1
      36: invokevirtual #11                 // Method io/reactivex/rxjava3/core/Flowable.defaultIfEmpty:(Ljava/lang/Object;)Lio/reactivex/rxjava3/core/Flowable;
      39: areturn

  public java.lang.Object apply(java.lang.Object) throws java.lang.Throwable;
    Code:
       0: aload_0
       1: aload_1
       2: invokevirtual #12                 // Method apply:(Ljava/lang/Object;)Lorg/reactivestreams/Publisher;
       5: areturn
}
