Compiled from "FlowableThrottleLatest.java"
final class io.reactivex.rxjava3.internal.operators.flowable.FlowableThrottleLatest$ThrottleLatestSubscriber<T> extends java.util.concurrent.atomic.AtomicInteger implements io.reactivex.rxjava3.core.FlowableSubscriber<T>, org.reactivestreams.Subscription, java.lang.Runnable {
  private static final long serialVersionUID;

  final org.reactivestreams.Subscriber<? super T> downstream;

  final long timeout;

  final java.util.concurrent.TimeUnit unit;

  final io.reactivex.rxjava3.core.Scheduler$Worker worker;

  final boolean emitLast;

  final java.util.concurrent.atomic.AtomicReference<T> latest;

  final java.util.concurrent.atomic.AtomicLong requested;

  final io.reactivex.rxjava3.functions.Consumer<? super T> onDropped;

  org.reactivestreams.Subscription upstream;

  volatile boolean done;

  java.lang.Throwable error;

  volatile boolean cancelled;

  volatile boolean timerFired;

  long emitted;

  boolean timerRunning;

  io.reactivex.rxjava3.internal.operators.flowable.FlowableThrottleLatest$ThrottleLatestSubscriber(org.reactivestreams.Subscriber<? super T>, long, java.util.concurrent.TimeUnit, io.reactivex.rxjava3.core.Scheduler$Worker, boolean, io.reactivex.rxjava3.functions.Consumer<? super T>);
    Code:
       0: aload_0
       1: invokespecial #1                  // Method java/util/concurrent/atomic/AtomicInteger."<init>":()V
       4: aload_0
       5: aload_1
       6: putfield      #2                  // Field downstream:Lorg/reactivestreams/Subscriber;
       9: aload_0
      10: lload_2
      11: putfield      #3                  // Field timeout:J
      14: aload_0
      15: aload         4
      17: putfield      #4                  // Field unit:Ljava/util/concurrent/TimeUnit;
      20: aload_0
      21: aload         5
      23: putfield      #5                  // Field worker:Lio/reactivex/rxjava3/core/Scheduler$Worker;
      26: aload_0
      27: iload         6
      29: putfield      #6                  // Field emitLast:Z
      32: aload_0
      33: new           #7                  // class java/util/concurrent/atomic/AtomicReference
      36: dup
      37: invokespecial #8                  // Method java/util/concurrent/atomic/AtomicReference."<init>":()V
      40: putfield      #9                  // Field latest:Ljava/util/concurrent/atomic/AtomicReference;
      43: aload_0
      44: new           #10                 // class java/util/concurrent/atomic/AtomicLong
      47: dup
      48: invokespecial #11                 // Method java/util/concurrent/atomic/AtomicLong."<init>":()V
      51: putfield      #12                 // Field requested:Ljava/util/concurrent/atomic/AtomicLong;
      54: aload_0
      55: aload         7
      57: putfield      #13                 // Field onDropped:Lio/reactivex/rxjava3/functions/Consumer;
      60: return

  public void onSubscribe(org.reactivestreams.Subscription);
    Code:
       0: aload_0
       1: getfield      #14                 // Field upstream:Lorg/reactivestreams/Subscription;
       4: aload_1
       5: invokestatic  #15                 // Method io/reactivex/rxjava3/internal/subscriptions/SubscriptionHelper.validate:(Lorg/reactivestreams/Subscription;Lorg/reactivestreams/Subscription;)Z
       8: ifeq          35
      11: aload_0
      12: aload_1
      13: putfield      #14                 // Field upstream:Lorg/reactivestreams/Subscription;
      16: aload_0
      17: getfield      #2                  // Field downstream:Lorg/reactivestreams/Subscriber;
      20: aload_0
      21: invokeinterface #16,  2           // InterfaceMethod org/reactivestreams/Subscriber.onSubscribe:(Lorg/reactivestreams/Subscription;)V
      26: aload_1
      27: ldc2_w        #18                 // long 9223372036854775807l
      30: invokeinterface #20,  3           // InterfaceMethod org/reactivestreams/Subscription.request:(J)V
      35: return

  public void onNext(T);
    Code:
       0: aload_0
       1: getfield      #9                  // Field latest:Ljava/util/concurrent/atomic/AtomicReference;
       4: aload_1
       5: invokevirtual #21                 // Method java/util/concurrent/atomic/AtomicReference.getAndSet:(Ljava/lang/Object;)Ljava/lang/Object;
       8: astore_2
       9: aload_0
      10: getfield      #13                 // Field onDropped:Lio/reactivex/rxjava3/functions/Consumer;
      13: ifnull        57
      16: aload_2
      17: ifnull        57
      20: aload_0
      21: getfield      #13                 // Field onDropped:Lio/reactivex/rxjava3/functions/Consumer;
      24: aload_2
      25: invokeinterface #22,  2           // InterfaceMethod io/reactivex/rxjava3/functions/Consumer.accept:(Ljava/lang/Object;)V
      30: goto          57
      33: astore_3
      34: aload_3
      35: invokestatic  #24                 // Method io/reactivex/rxjava3/exceptions/Exceptions.throwIfFatal:(Ljava/lang/Throwable;)V
      38: aload_0
      39: getfield      #14                 // Field upstream:Lorg/reactivestreams/Subscription;
      42: invokeinterface #25,  1           // InterfaceMethod org/reactivestreams/Subscription.cancel:()V
      47: aload_0
      48: aload_3
      49: putfield      #26                 // Field error:Ljava/lang/Throwable;
      52: aload_0
      53: iconst_1
      54: putfield      #27                 // Field done:Z
      57: aload_0
      58: invokevirtual #28                 // Method drain:()V
      61: return
    Exception table:
       from    to  target type
          20    30    33   Class java/lang/Throwable

  public void onError(java.lang.Throwable);
    Code:
       0: aload_0
       1: aload_1
       2: putfield      #26                 // Field error:Ljava/lang/Throwable;
       5: aload_0
       6: iconst_1
       7: putfield      #27                 // Field done:Z
      10: aload_0
      11: invokevirtual #28                 // Method drain:()V
      14: return

  public void onComplete();
    Code:
       0: aload_0
       1: iconst_1
       2: putfield      #27                 // Field done:Z
       5: aload_0
       6: invokevirtual #28                 // Method drain:()V
       9: return

  public void request(long);
    Code:
       0: lload_1
       1: invokestatic  #29                 // Method io/reactivex/rxjava3/internal/subscriptions/SubscriptionHelper.validate:(J)Z
       4: ifeq          16
       7: aload_0
       8: getfield      #12                 // Field requested:Ljava/util/concurrent/atomic/AtomicLong;
      11: lload_1
      12: invokestatic  #30                 // Method io/reactivex/rxjava3/internal/util/BackpressureHelper.add:(Ljava/util/concurrent/atomic/AtomicLong;J)J
      15: pop2
      16: return

  public void cancel();
    Code:
       0: aload_0
       1: iconst_1
       2: putfield      #31                 // Field cancelled:Z
       5: aload_0
       6: getfield      #14                 // Field upstream:Lorg/reactivestreams/Subscription;
       9: invokeinterface #25,  1           // InterfaceMethod org/reactivestreams/Subscription.cancel:()V
      14: aload_0
      15: getfield      #5                  // Field worker:Lio/reactivex/rxjava3/core/Scheduler$Worker;
      18: invokevirtual #32                 // Method io/reactivex/rxjava3/core/Scheduler$Worker.dispose:()V
      21: aload_0
      22: invokevirtual #33                 // Method getAndIncrement:()I
      25: ifne          32
      28: aload_0
      29: invokevirtual #34                 // Method clear:()V
      32: return

  void clear();
    Code:
       0: aload_0
       1: getfield      #13                 // Field onDropped:Lio/reactivex/rxjava3/functions/Consumer;
       4: ifnull        45
       7: aload_0
       8: getfield      #9                  // Field latest:Ljava/util/concurrent/atomic/AtomicReference;
      11: aconst_null
      12: invokevirtual #21                 // Method java/util/concurrent/atomic/AtomicReference.getAndSet:(Ljava/lang/Object;)Ljava/lang/Object;
      15: astore_1
      16: aload_1
      17: ifnull        42
      20: aload_0
      21: getfield      #13                 // Field onDropped:Lio/reactivex/rxjava3/functions/Consumer;
      24: aload_1
      25: invokeinterface #22,  2           // InterfaceMethod io/reactivex/rxjava3/functions/Consumer.accept:(Ljava/lang/Object;)V
      30: goto          42
      33: astore_2
      34: aload_2
      35: invokestatic  #24                 // Method io/reactivex/rxjava3/exceptions/Exceptions.throwIfFatal:(Ljava/lang/Throwable;)V
      38: aload_2
      39: invokestatic  #35                 // Method io/reactivex/rxjava3/plugins/RxJavaPlugins.onError:(Ljava/lang/Throwable;)V
      42: goto          53
      45: aload_0
      46: getfield      #9                  // Field latest:Ljava/util/concurrent/atomic/AtomicReference;
      49: aconst_null
      50: invokevirtual #36                 // Method java/util/concurrent/atomic/AtomicReference.lazySet:(Ljava/lang/Object;)V
      53: return
    Exception table:
       from    to  target type
          20    30    33   Class java/lang/Throwable

  public void run();
    Code:
       0: aload_0
       1: iconst_1
       2: putfield      #37                 // Field timerFired:Z
       5: aload_0
       6: invokevirtual #28                 // Method drain:()V
       9: return

  void drain();
    Code:
       0: aload_0
       1: invokevirtual #33                 // Method getAndIncrement:()I
       4: ifeq          8
       7: return
       8: iconst_1
       9: istore_1
      10: aload_0
      11: getfield      #9                  // Field latest:Ljava/util/concurrent/atomic/AtomicReference;
      14: astore_2
      15: aload_0
      16: getfield      #12                 // Field requested:Ljava/util/concurrent/atomic/AtomicLong;
      19: astore_3
      20: aload_0
      21: getfield      #2                  // Field downstream:Lorg/reactivestreams/Subscriber;
      24: astore        4
      26: aload_0
      27: getfield      #31                 // Field cancelled:Z
      30: ifeq          38
      33: aload_0
      34: invokevirtual #34                 // Method clear:()V
      37: return
      38: aload_0
      39: getfield      #27                 // Field done:Z
      42: istore        5
      44: aload_0
      45: getfield      #26                 // Field error:Ljava/lang/Throwable;
      48: astore        6
      50: iload         5
      52: ifeq          148
      55: aload         6
      57: ifnull        148
      60: aload_0
      61: getfield      #13                 // Field onDropped:Lio/reactivex/rxjava3/functions/Consumer;
      64: ifnull        126
      67: aload_2
      68: aconst_null
      69: invokevirtual #21                 // Method java/util/concurrent/atomic/AtomicReference.getAndSet:(Ljava/lang/Object;)Ljava/lang/Object;
      72: astore        7
      74: aload         7
      76: ifnull        123
      79: aload_0
      80: getfield      #13                 // Field onDropped:Lio/reactivex/rxjava3/functions/Consumer;
      83: aload         7
      85: invokeinterface #22,  2           // InterfaceMethod io/reactivex/rxjava3/functions/Consumer.accept:(Ljava/lang/Object;)V
      90: goto          123
      93: astore        8
      95: aload         8
      97: invokestatic  #24                 // Method io/reactivex/rxjava3/exceptions/Exceptions.throwIfFatal:(Ljava/lang/Throwable;)V
     100: new           #38                 // class io/reactivex/rxjava3/exceptions/CompositeException
     103: dup
     104: iconst_2
     105: anewarray     #39                 // class java/lang/Throwable
     108: dup
     109: iconst_0
     110: aload         6
     112: aastore
     113: dup
     114: iconst_1
     115: aload         8
     117: aastore
     118: invokespecial #40                 // Method io/reactivex/rxjava3/exceptions/CompositeException."<init>":([Ljava/lang/Throwable;)V
     121: astore        6
     123: goto          131
     126: aload_2
     127: aconst_null
     128: invokevirtual #36                 // Method java/util/concurrent/atomic/AtomicReference.lazySet:(Ljava/lang/Object;)V
     131: aload         4
     133: aload         6
     135: invokeinterface #41,  2           // InterfaceMethod org/reactivestreams/Subscriber.onError:(Ljava/lang/Throwable;)V
     140: aload_0
     141: getfield      #5                  // Field worker:Lio/reactivex/rxjava3/core/Scheduler$Worker;
     144: invokevirtual #32                 // Method io/reactivex/rxjava3/core/Scheduler$Worker.dispose:()V
     147: return
     148: aload_2
     149: invokevirtual #42                 // Method java/util/concurrent/atomic/AtomicReference.get:()Ljava/lang/Object;
     152: astore        7
     154: aload         7
     156: ifnonnull     163
     159: iconst_1
     160: goto          164
     163: iconst_0
     164: istore        8
     166: iload         5
     168: ifeq          312
     171: iload         8
     173: ifne          297
     176: aload_2
     177: aconst_null
     178: invokevirtual #21                 // Method java/util/concurrent/atomic/AtomicReference.getAndSet:(Ljava/lang/Object;)Ljava/lang/Object;
     181: astore        7
     183: aload_0
     184: getfield      #6                  // Field emitLast:Z
     187: ifeq          242
     190: aload_0
     191: getfield      #43                 // Field emitted:J
     194: lstore        9
     196: lload         9
     198: aload_3
     199: invokevirtual #44                 // Method java/util/concurrent/atomic/AtomicLong.get:()J
     202: lcmp
     203: ifeq          233
     206: aload_0
     207: lload         9
     209: lconst_1
     210: ladd
     211: putfield      #43                 // Field emitted:J
     214: aload         4
     216: aload         7
     218: invokeinterface #45,  2           // InterfaceMethod org/reactivestreams/Subscriber.onNext:(Ljava/lang/Object;)V
     223: aload         4
     225: invokeinterface #46,  1           // InterfaceMethod org/reactivestreams/Subscriber.onComplete:()V
     230: goto          239
     233: aload_0
     234: aload         7
     236: invokevirtual #47                 // Method tryDropAndSignalMBE:(Ljava/lang/Object;)V
     239: goto          304
     242: aload_0
     243: getfield      #13                 // Field onDropped:Lio/reactivex/rxjava3/functions/Consumer;
     246: ifnull        287
     249: aload_0
     250: getfield      #13                 // Field onDropped:Lio/reactivex/rxjava3/functions/Consumer;
     253: aload         7
     255: invokeinterface #22,  2           // InterfaceMethod io/reactivex/rxjava3/functions/Consumer.accept:(Ljava/lang/Object;)V
     260: goto          287
     263: astore        9
     265: aload         9
     267: invokestatic  #24                 // Method io/reactivex/rxjava3/exceptions/Exceptions.throwIfFatal:(Ljava/lang/Throwable;)V
     270: aload         4
     272: aload         9
     274: invokeinterface #41,  2           // InterfaceMethod org/reactivestreams/Subscriber.onError:(Ljava/lang/Throwable;)V
     279: aload_0
     280: getfield      #5                  // Field worker:Lio/reactivex/rxjava3/core/Scheduler$Worker;
     283: invokevirtual #32                 // Method io/reactivex/rxjava3/core/Scheduler$Worker.dispose:()V
     286: return
     287: aload         4
     289: invokeinterface #46,  1           // InterfaceMethod org/reactivestreams/Subscriber.onComplete:()V
     294: goto          304
     297: aload         4
     299: invokeinterface #46,  1           // InterfaceMethod org/reactivestreams/Subscriber.onComplete:()V
     304: aload_0
     305: getfield      #5                  // Field worker:Lio/reactivex/rxjava3/core/Scheduler$Worker;
     308: invokevirtual #32                 // Method io/reactivex/rxjava3/core/Scheduler$Worker.dispose:()V
     311: return
     312: iload         8
     314: ifeq          337
     317: aload_0
     318: getfield      #37                 // Field timerFired:Z
     321: ifeq          447
     324: aload_0
     325: iconst_0
     326: putfield      #48                 // Field timerRunning:Z
     329: aload_0
     330: iconst_0
     331: putfield      #37                 // Field timerFired:Z
     334: goto          447
     337: aload_0
     338: getfield      #48                 // Field timerRunning:Z
     341: ifeq          351
     344: aload_0
     345: getfield      #37                 // Field timerFired:Z
     348: ifeq          447
     351: aload_2
     352: aconst_null
     353: invokevirtual #21                 // Method java/util/concurrent/atomic/AtomicReference.getAndSet:(Ljava/lang/Object;)Ljava/lang/Object;
     356: astore        7
     358: aload_0
     359: getfield      #43                 // Field emitted:J
     362: lstore        9
     364: lload         9
     366: aload_3
     367: invokevirtual #44                 // Method java/util/concurrent/atomic/AtomicLong.get:()J
     370: lcmp
     371: ifeq          394
     374: aload         4
     376: aload         7
     378: invokeinterface #45,  2           // InterfaceMethod org/reactivestreams/Subscriber.onNext:(Ljava/lang/Object;)V
     383: aload_0
     384: lload         9
     386: lconst_1
     387: ladd
     388: putfield      #43                 // Field emitted:J
     391: goto          417
     394: aload_0
     395: getfield      #14                 // Field upstream:Lorg/reactivestreams/Subscription;
     398: invokeinterface #25,  1           // InterfaceMethod org/reactivestreams/Subscription.cancel:()V
     403: aload_0
     404: aload         7
     406: invokevirtual #47                 // Method tryDropAndSignalMBE:(Ljava/lang/Object;)V
     409: aload_0
     410: getfield      #5                  // Field worker:Lio/reactivex/rxjava3/core/Scheduler$Worker;
     413: invokevirtual #32                 // Method io/reactivex/rxjava3/core/Scheduler$Worker.dispose:()V
     416: return
     417: aload_0
     418: iconst_0
     419: putfield      #37                 // Field timerFired:Z
     422: aload_0
     423: iconst_1
     424: putfield      #48                 // Field timerRunning:Z
     427: aload_0
     428: getfield      #5                  // Field worker:Lio/reactivex/rxjava3/core/Scheduler$Worker;
     431: aload_0
     432: aload_0
     433: getfield      #3                  // Field timeout:J
     436: aload_0
     437: getfield      #4                  // Field unit:Ljava/util/concurrent/TimeUnit;
     440: invokevirtual #49                 // Method io/reactivex/rxjava3/core/Scheduler$Worker.schedule:(Ljava/lang/Runnable;JLjava/util/concurrent/TimeUnit;)Lio/reactivex/rxjava3/disposables/Disposable;
     443: pop
     444: goto          26
     447: aload_0
     448: iload_1
     449: ineg
     450: invokevirtual #50                 // Method addAndGet:(I)I
     453: istore_1
     454: iload_1
     455: ifne          26
     458: goto          461
     461: return
    Exception table:
       from    to  target type
          79    90    93   Class java/lang/Throwable
         249   260   263   Class java/lang/Throwable

  void tryDropAndSignalMBE(T);
    Code:
       0: invokestatic  #51                 // Method io/reactivex/rxjava3/exceptions/MissingBackpressureException.createDefault:()Lio/reactivex/rxjava3/exceptions/MissingBackpressureException;
       3: astore_2
       4: aload_0
       5: getfield      #13                 // Field onDropped:Lio/reactivex/rxjava3/functions/Consumer;
       8: ifnull        49
      11: aload_0
      12: getfield      #13                 // Field onDropped:Lio/reactivex/rxjava3/functions/Consumer;
      15: aload_1
      16: invokeinterface #22,  2           // InterfaceMethod io/reactivex/rxjava3/functions/Consumer.accept:(Ljava/lang/Object;)V
      21: goto          49
      24: astore_3
      25: aload_3
      26: invokestatic  #24                 // Method io/reactivex/rxjava3/exceptions/Exceptions.throwIfFatal:(Ljava/lang/Throwable;)V
      29: new           #38                 // class io/reactivex/rxjava3/exceptions/CompositeException
      32: dup
      33: iconst_2
      34: anewarray     #39                 // class java/lang/Throwable
      37: dup
      38: iconst_0
      39: aload_2
      40: aastore
      41: dup
      42: iconst_1
      43: aload_3
      44: aastore
      45: invokespecial #40                 // Method io/reactivex/rxjava3/exceptions/CompositeException."<init>":([Ljava/lang/Throwable;)V
      48: astore_2
      49: aload_0
      50: getfield      #2                  // Field downstream:Lorg/reactivestreams/Subscriber;
      53: aload_2
      54: invokeinterface #41,  2           // InterfaceMethod org/reactivestreams/Subscriber.onError:(Ljava/lang/Throwable;)V
      59: return
    Exception table:
       from    to  target type
          11    21    24   Class java/lang/Throwable
}
