Compiled from "FlowableUnsubscribeOn.java"
final class io.reactivex.rxjava3.internal.operators.flowable.FlowableUnsubscribeOn$UnsubscribeSubscriber<T> extends java.util.concurrent.atomic.AtomicBoolean implements io.reactivex.rxjava3.core.FlowableSubscriber<T>, org.reactivestreams.Subscription {
  private static final long serialVersionUID;

  final org.reactivestreams.Subscriber<? super T> downstream;

  final io.reactivex.rxjava3.core.Scheduler scheduler;

  org.reactivestreams.Subscription upstream;

  io.reactivex.rxjava3.internal.operators.flowable.FlowableUnsubscribeOn$UnsubscribeSubscriber(org.reactivestreams.Subscriber<? super T>, io.reactivex.rxjava3.core.Scheduler);
    Code:
       0: aload_0
       1: invokespecial #1                  // Method java/util/concurrent/atomic/AtomicBoolean."<init>":()V
       4: aload_0
       5: aload_1
       6: putfield      #2                  // Field downstream:Lorg/reactivestreams/Subscriber;
       9: aload_0
      10: aload_2
      11: putfield      #3                  // Field scheduler:Lio/reactivex/rxjava3/core/Scheduler;
      14: return

  public void onSubscribe(org.reactivestreams.Subscription);
    Code:
       0: aload_0
       1: getfield      #4                  // Field upstream:Lorg/reactivestreams/Subscription;
       4: aload_1
       5: invokestatic  #5                  // Method io/reactivex/rxjava3/internal/subscriptions/SubscriptionHelper.validate:(Lorg/reactivestreams/Subscription;Lorg/reactivestreams/Subscription;)Z
       8: ifeq          26
      11: aload_0
      12: aload_1
      13: putfield      #4                  // Field upstream:Lorg/reactivestreams/Subscription;
      16: aload_0
      17: getfield      #2                  // Field downstream:Lorg/reactivestreams/Subscriber;
      20: aload_0
      21: invokeinterface #6,  2            // InterfaceMethod org/reactivestreams/Subscriber.onSubscribe:(Lorg/reactivestreams/Subscription;)V
      26: return

  public void onNext(T);
    Code:
       0: aload_0
       1: invokevirtual #7                  // Method get:()Z
       4: ifne          17
       7: aload_0
       8: getfield      #2                  // Field downstream:Lorg/reactivestreams/Subscriber;
      11: aload_1
      12: invokeinterface #8,  2            // InterfaceMethod org/reactivestreams/Subscriber.onNext:(Ljava/lang/Object;)V
      17: return

  public void onError(java.lang.Throwable);
    Code:
       0: aload_0
       1: invokevirtual #7                  // Method get:()Z
       4: ifeq          12
       7: aload_1
       8: invokestatic  #9                  // Method io/reactivex/rxjava3/plugins/RxJavaPlugins.onError:(Ljava/lang/Throwable;)V
      11: return
      12: aload_0
      13: getfield      #2                  // Field downstream:Lorg/reactivestreams/Subscriber;
      16: aload_1
      17: invokeinterface #10,  2           // InterfaceMethod org/reactivestreams/Subscriber.onError:(Ljava/lang/Throwable;)V
      22: return

  public void onComplete();
    Code:
       0: aload_0
       1: invokevirtual #7                  // Method get:()Z
       4: ifne          16
       7: aload_0
       8: getfield      #2                  // Field downstream:Lorg/reactivestreams/Subscriber;
      11: invokeinterface #11,  1           // InterfaceMethod org/reactivestreams/Subscriber.onComplete:()V
      16: return

  public void request(long);
    Code:
       0: aload_0
       1: getfield      #4                  // Field upstream:Lorg/reactivestreams/Subscription;
       4: lload_1
       5: invokeinterface #12,  3           // InterfaceMethod org/reactivestreams/Subscription.request:(J)V
      10: return

  public void cancel();
    Code:
       0: aload_0
       1: iconst_0
       2: iconst_1
       3: invokevirtual #13                 // Method compareAndSet:(ZZ)Z
       6: ifeq          25
       9: aload_0
      10: getfield      #3                  // Field scheduler:Lio/reactivex/rxjava3/core/Scheduler;
      13: new           #14                 // class io/reactivex/rxjava3/internal/operators/flowable/FlowableUnsubscribeOn$UnsubscribeSubscriber$Cancellation
      16: dup
      17: aload_0
      18: invokespecial #15                 // Method io/reactivex/rxjava3/internal/operators/flowable/FlowableUnsubscribeOn$UnsubscribeSubscriber$Cancellation."<init>":(Lio/reactivex/rxjava3/internal/operators/flowable/FlowableUnsubscribeOn$UnsubscribeSubscriber;)V
      21: invokevirtual #16                 // Method io/reactivex/rxjava3/core/Scheduler.scheduleDirect:(Ljava/lang/Runnable;)Lio/reactivex/rxjava3/disposables/Disposable;
      24: pop
      25: return
}
