Compiled from "FlowableReplay.java"
final class io.reactivex.rxjava3.internal.operators.flowable.FlowableReplay$UnboundedReplayBuffer<T> extends java.util.ArrayList<java.lang.Object> implements io.reactivex.rxjava3.internal.operators.flowable.FlowableReplay$ReplayBuffer<T> {
  private static final long serialVersionUID;

  volatile int size;

  io.reactivex.rxjava3.internal.operators.flowable.FlowableReplay$UnboundedReplayBuffer(int);
    Code:
       0: aload_0
       1: iload_1
       2: invokespecial #1                  // Method java/util/ArrayList."<init>":(I)V
       5: return

  public void next(T);
    Code:
       0: aload_0
       1: aload_1
       2: invokestatic  #2                  // Method io/reactivex/rxjava3/internal/util/NotificationLite.next:(Ljava/lang/Object;)Ljava/lang/Object;
       5: invokevirtual #3                  // Method add:(Ljava/lang/Object;)Z
       8: pop
       9: aload_0
      10: dup
      11: getfield      #4                  // Field size:I
      14: iconst_1
      15: iadd
      16: putfield      #4                  // Field size:I
      19: return

  public void error(java.lang.Throwable);
    Code:
       0: aload_0
       1: aload_1
       2: invokestatic  #5                  // Method io/reactivex/rxjava3/internal/util/NotificationLite.error:(Ljava/lang/Throwable;)Ljava/lang/Object;
       5: invokevirtual #3                  // Method add:(Ljava/lang/Object;)Z
       8: pop
       9: aload_0
      10: dup
      11: getfield      #4                  // Field size:I
      14: iconst_1
      15: iadd
      16: putfield      #4                  // Field size:I
      19: return

  public void complete();
    Code:
       0: aload_0
       1: invokestatic  #6                  // Method io/reactivex/rxjava3/internal/util/NotificationLite.complete:()Ljava/lang/Object;
       4: invokevirtual #3                  // Method add:(Ljava/lang/Object;)Z
       7: pop
       8: aload_0
       9: dup
      10: getfield      #4                  // Field size:I
      13: iconst_1
      14: iadd
      15: putfield      #4                  // Field size:I
      18: return

  public void replay(io.reactivex.rxjava3.internal.operators.flowable.FlowableReplay$InnerSubscription<T>);
    Code:
       0: aload_1
       1: dup
       2: astore_2
       3: monitorenter
       4: aload_1
       5: getfield      #7                  // Field io/reactivex/rxjava3/internal/operators/flowable/FlowableReplay$InnerSubscription.emitting:Z
       8: ifeq          19
      11: aload_1
      12: iconst_1
      13: putfield      #8                  // Field io/reactivex/rxjava3/internal/operators/flowable/FlowableReplay$InnerSubscription.missed:Z
      16: aload_2
      17: monitorexit
      18: return
      19: aload_1
      20: iconst_1
      21: putfield      #7                  // Field io/reactivex/rxjava3/internal/operators/flowable/FlowableReplay$InnerSubscription.emitting:Z
      24: aload_2
      25: monitorexit
      26: goto          34
      29: astore_3
      30: aload_2
      31: monitorexit
      32: aload_3
      33: athrow
      34: aload_1
      35: getfield      #9                  // Field io/reactivex/rxjava3/internal/operators/flowable/FlowableReplay$InnerSubscription.child:Lorg/reactivestreams/Subscriber;
      38: astore_2
      39: aload_1
      40: invokevirtual #10                 // Method io/reactivex/rxjava3/internal/operators/flowable/FlowableReplay$InnerSubscription.isDisposed:()Z
      43: ifeq          47
      46: return
      47: aload_0
      48: getfield      #4                  // Field size:I
      51: istore_3
      52: aload_1
      53: invokevirtual #11                 // Method io/reactivex/rxjava3/internal/operators/flowable/FlowableReplay$InnerSubscription.index:()Ljava/lang/Object;
      56: checkcast     #12                 // class java/lang/Integer
      59: astore        4
      61: aload         4
      63: ifnull        74
      66: aload         4
      68: invokevirtual #13                 // Method java/lang/Integer.intValue:()I
      71: goto          75
      74: iconst_0
      75: istore        5
      77: aload_1
      78: invokevirtual #14                 // Method io/reactivex/rxjava3/internal/operators/flowable/FlowableReplay$InnerSubscription.get:()J
      81: lstore        6
      83: lload         6
      85: lstore        8
      87: lconst_0
      88: lstore        10
      90: lload         6
      92: lconst_0
      93: lcmp
      94: ifeq          194
      97: iload         5
      99: iload_3
     100: if_icmpge     194
     103: aload_0
     104: iload         5
     106: invokevirtual #15                 // Method get:(I)Ljava/lang/Object;
     109: astore        12
     111: aload         12
     113: aload_2
     114: invokestatic  #16                 // Method io/reactivex/rxjava3/internal/util/NotificationLite.accept:(Ljava/lang/Object;Lorg/reactivestreams/Subscriber;)Z
     117: ifeq          121
     120: return
     121: goto          168
     124: astore        13
     126: aload         13
     128: invokestatic  #18                 // Method io/reactivex/rxjava3/exceptions/Exceptions.throwIfFatal:(Ljava/lang/Throwable;)V
     131: aload_1
     132: invokevirtual #19                 // Method io/reactivex/rxjava3/internal/operators/flowable/FlowableReplay$InnerSubscription.dispose:()V
     135: aload         12
     137: invokestatic  #20                 // Method io/reactivex/rxjava3/internal/util/NotificationLite.isError:(Ljava/lang/Object;)Z
     140: ifne          162
     143: aload         12
     145: invokestatic  #21                 // Method io/reactivex/rxjava3/internal/util/NotificationLite.isComplete:(Ljava/lang/Object;)Z
     148: ifne          162
     151: aload_2
     152: aload         13
     154: invokeinterface #22,  2           // InterfaceMethod org/reactivestreams/Subscriber.onError:(Ljava/lang/Throwable;)V
     159: goto          167
     162: aload         13
     164: invokestatic  #23                 // Method io/reactivex/rxjava3/plugins/RxJavaPlugins.onError:(Ljava/lang/Throwable;)V
     167: return
     168: aload_1
     169: invokevirtual #10                 // Method io/reactivex/rxjava3/internal/operators/flowable/FlowableReplay$InnerSubscription.isDisposed:()Z
     172: ifeq          176
     175: return
     176: iinc          5, 1
     179: lload         6
     181: lconst_1
     182: lsub
     183: lstore        6
     185: lload         10
     187: lconst_1
     188: ladd
     189: lstore        10
     191: goto          90
     194: lload         10
     196: lconst_0
     197: lcmp
     198: ifeq          226
     201: aload_1
     202: iload         5
     204: invokestatic  #24                 // Method java/lang/Integer.valueOf:(I)Ljava/lang/Integer;
     207: putfield      #25                 // Field io/reactivex/rxjava3/internal/operators/flowable/FlowableReplay$InnerSubscription.index:Ljava/lang/Object;
     210: lload         8
     212: ldc2_w        #27                 // long 9223372036854775807l
     215: lcmp
     216: ifeq          226
     219: aload_1
     220: lload         10
     222: invokevirtual #29                 // Method io/reactivex/rxjava3/internal/operators/flowable/FlowableReplay$InnerSubscription.produced:(J)J
     225: pop2
     226: aload_1
     227: dup
     228: astore        12
     230: monitorenter
     231: aload_1
     232: getfield      #8                  // Field io/reactivex/rxjava3/internal/operators/flowable/FlowableReplay$InnerSubscription.missed:Z
     235: ifne          247
     238: aload_1
     239: iconst_0
     240: putfield      #7                  // Field io/reactivex/rxjava3/internal/operators/flowable/FlowableReplay$InnerSubscription.emitting:Z
     243: aload         12
     245: monitorexit
     246: return
     247: aload_1
     248: iconst_0
     249: putfield      #8                  // Field io/reactivex/rxjava3/internal/operators/flowable/FlowableReplay$InnerSubscription.missed:Z
     252: aload         12
     254: monitorexit
     255: goto          266
     258: astore        14
     260: aload         12
     262: monitorexit
     263: aload         14
     265: athrow
     266: goto          39
    Exception table:
       from    to  target type
           4    18    29   any
          19    26    29   any
          29    32    29   any
         111   120   124   Class java/lang/Throwable
         231   246   258   any
         247   255   258   any
         258   263   258   any
}
