Compiled from "FlowableOnErrorNext.java"
public final class io.reactivex.rxjava3.internal.operators.flowable.FlowableOnErrorNext<T> extends io.reactivex.rxjava3.internal.operators.flowable.AbstractFlowableWithUpstream<T, T> {
  final io.reactivex.rxjava3.functions.Function<? super java.lang.Throwable, ? extends org.reactivestreams.Publisher<? extends T>> nextSupplier;

  public io.reactivex.rxjava3.internal.operators.flowable.FlowableOnErrorNext(io.reactivex.rxjava3.core.Flowable<T>, io.reactivex.rxjava3.functions.Function<? super java.lang.Throwable, ? extends org.reactivestreams.Publisher<? extends T>>);
    Code:
       0: aload_0
       1: aload_1
       2: invokespecial #1                  // Method io/reactivex/rxjava3/internal/operators/flowable/AbstractFlowableWithUpstream."<init>":(Lio/reactivex/rxjava3/core/Flowable;)V
       5: aload_0
       6: aload_2
       7: putfield      #2                  // Field nextSupplier:Lio/reactivex/rxjava3/functions/Function;
      10: return

  protected void subscribeActual(org.reactivestreams.Subscriber<? super T>);
    Code:
       0: new           #3                  // class io/reactivex/rxjava3/internal/operators/flowable/FlowableOnErrorNext$OnErrorNextSubscriber
       3: dup
       4: aload_1
       5: aload_0
       6: getfield      #2                  // Field nextSupplier:Lio/reactivex/rxjava3/functions/Function;
       9: invokespecial #4                  // Method io/reactivex/rxjava3/internal/operators/flowable/FlowableOnErrorNext$OnErrorNextSubscriber."<init>":(Lorg/reactivestreams/Subscriber;Lio/reactivex/rxjava3/functions/Function;)V
      12: astore_2
      13: aload_1
      14: aload_2
      15: invokeinterface #5,  2            // InterfaceMethod org/reactivestreams/Subscriber.onSubscribe:(Lorg/reactivestreams/Subscription;)V
      20: aload_0
      21: getfield      #6                  // Field source:Lio/reactivex/rxjava3/core/Flowable;
      24: aload_2
      25: invokevirtual #7                  // Method io/reactivex/rxjava3/core/Flowable.subscribe:(Lio/reactivex/rxjava3/core/FlowableSubscriber;)V
      28: return
}
