Compiled from "FlowableSkipUntil.java"
final class io.reactivex.rxjava3.internal.operators.flowable.FlowableSkipUntil$SkipUntilMainSubscriber$OtherSubscriber extends java.util.concurrent.atomic.AtomicReference<org.reactivestreams.Subscription> implements io.reactivex.rxjava3.core.FlowableSubscriber<java.lang.Object> {
  private static final long serialVersionUID;

  final io.reactivex.rxjava3.internal.operators.flowable.FlowableSkipUntil$SkipUntilMainSubscriber this$0;

  io.reactivex.rxjava3.internal.operators.flowable.FlowableSkipUntil$SkipUntilMainSubscriber$OtherSubscriber(io.reactivex.rxjava3.internal.operators.flowable.FlowableSkipUntil$SkipUntilMainSubscriber);
    Code:
       0: aload_0
       1: aload_1
       2: putfield      #1                  // Field this$0:Lio/reactivex/rxjava3/internal/operators/flowable/FlowableSkipUntil$SkipUntilMainSubscriber;
       5: aload_0
       6: invokespecial #2                  // Method java/util/concurrent/atomic/AtomicReference."<init>":()V
       9: return

  public void onSubscribe(org.reactivestreams.Subscription);
    Code:
       0: aload_0
       1: aload_1
       2: ldc2_w        #4                  // long 9223372036854775807l
       5: invokestatic  #6                  // Method io/reactivex/rxjava3/internal/subscriptions/SubscriptionHelper.setOnce:(Ljava/util/concurrent/atomic/AtomicReference;Lorg/reactivestreams/Subscription;J)Z
       8: pop
       9: return

  public void onNext(java.lang.Object);
    Code:
       0: aload_0
       1: getfield      #1                  // Field this$0:Lio/reactivex/rxjava3/internal/operators/flowable/FlowableSkipUntil$SkipUntilMainSubscriber;
       4: iconst_1
       5: putfield      #7                  // Field io/reactivex/rxjava3/internal/operators/flowable/FlowableSkipUntil$SkipUntilMainSubscriber.gate:Z
       8: aload_0
       9: invokevirtual #8                  // Method get:()Ljava/lang/Object;
      12: checkcast     #9                  // class org/reactivestreams/Subscription
      15: invokeinterface #10,  1           // InterfaceMethod org/reactivestreams/Subscription.cancel:()V
      20: return

  public void onError(java.lang.Throwable);
    Code:
       0: aload_0
       1: getfield      #1                  // Field this$0:Lio/reactivex/rxjava3/internal/operators/flowable/FlowableSkipUntil$SkipUntilMainSubscriber;
       4: getfield      #11                 // Field io/reactivex/rxjava3/internal/operators/flowable/FlowableSkipUntil$SkipUntilMainSubscriber.upstream:Ljava/util/concurrent/atomic/AtomicReference;
       7: invokestatic  #12                 // Method io/reactivex/rxjava3/internal/subscriptions/SubscriptionHelper.cancel:(Ljava/util/concurrent/atomic/AtomicReference;)Z
      10: pop
      11: aload_0
      12: getfield      #1                  // Field this$0:Lio/reactivex/rxjava3/internal/operators/flowable/FlowableSkipUntil$SkipUntilMainSubscriber;
      15: getfield      #13                 // Field io/reactivex/rxjava3/internal/operators/flowable/FlowableSkipUntil$SkipUntilMainSubscriber.downstream:Lorg/reactivestreams/Subscriber;
      18: aload_1
      19: aload_0
      20: getfield      #1                  // Field this$0:Lio/reactivex/rxjava3/internal/operators/flowable/FlowableSkipUntil$SkipUntilMainSubscriber;
      23: aload_0
      24: getfield      #1                  // Field this$0:Lio/reactivex/rxjava3/internal/operators/flowable/FlowableSkipUntil$SkipUntilMainSubscriber;
      27: getfield      #14                 // Field io/reactivex/rxjava3/internal/operators/flowable/FlowableSkipUntil$SkipUntilMainSubscriber.error:Lio/reactivex/rxjava3/internal/util/AtomicThrowable;
      30: invokestatic  #15                 // Method io/reactivex/rxjava3/internal/util/HalfSerializer.onError:(Lorg/reactivestreams/Subscriber;Ljava/lang/Throwable;Ljava/util/concurrent/atomic/AtomicInteger;Lio/reactivex/rxjava3/internal/util/AtomicThrowable;)V
      33: return

  public void onComplete();
    Code:
       0: aload_0
       1: getfield      #1                  // Field this$0:Lio/reactivex/rxjava3/internal/operators/flowable/FlowableSkipUntil$SkipUntilMainSubscriber;
       4: iconst_1
       5: putfield      #7                  // Field io/reactivex/rxjava3/internal/operators/flowable/FlowableSkipUntil$SkipUntilMainSubscriber.gate:Z
       8: return
}
