Compiled from "FlowableElementAtSingle.java"
public final class io.reactivex.rxjava3.internal.operators.flowable.FlowableElementAtSingle<T> extends io.reactivex.rxjava3.core.Single<T> implements io.reactivex.rxjava3.internal.fuseable.FuseToFlowable<T> {
  final io.reactivex.rxjava3.core.Flowable<T> source;

  final long index;

  final T defaultValue;

  public io.reactivex.rxjava3.internal.operators.flowable.FlowableElementAtSingle(io.reactivex.rxjava3.core.Flowable<T>, long, T);
    Code:
       0: aload_0
       1: invokespecial #1                  // Method io/reactivex/rxjava3/core/Single."<init>":()V
       4: aload_0
       5: aload_1
       6: putfield      #2                  // Field source:Lio/reactivex/rxjava3/core/Flowable;
       9: aload_0
      10: lload_2
      11: putfield      #3                  // Field index:J
      14: aload_0
      15: aload         4
      17: putfield      #4                  // Field defaultValue:Ljava/lang/Object;
      20: return

  protected void subscribeActual(io.reactivex.rxjava3.core.SingleObserver<? super T>);
    Code:
       0: aload_0
       1: getfield      #2                  // Field source:Lio/reactivex/rxjava3/core/Flowable;
       4: new           #5                  // class io/reactivex/rxjava3/internal/operators/flowable/FlowableElementAtSingle$ElementAtSubscriber
       7: dup
       8: aload_1
       9: aload_0
      10: getfield      #3                  // Field index:J
      13: aload_0
      14: getfield      #4                  // Field defaultValue:Ljava/lang/Object;
      17: invokespecial #6                  // Method io/reactivex/rxjava3/internal/operators/flowable/FlowableElementAtSingle$ElementAtSubscriber."<init>":(Lio/reactivex/rxjava3/core/SingleObserver;JLjava/lang/Object;)V
      20: invokevirtual #7                  // Method io/reactivex/rxjava3/core/Flowable.subscribe:(Lio/reactivex/rxjava3/core/FlowableSubscriber;)V
      23: return

  public io.reactivex.rxjava3.core.Flowable<T> fuseToFlowable();
    Code:
       0: new           #8                  // class io/reactivex/rxjava3/internal/operators/flowable/FlowableElementAt
       3: dup
       4: aload_0
       5: getfield      #2                  // Field source:Lio/reactivex/rxjava3/core/Flowable;
       8: aload_0
       9: getfield      #3                  // Field index:J
      12: aload_0
      13: getfield      #4                  // Field defaultValue:Ljava/lang/Object;
      16: iconst_1
      17: invokespecial #9                  // Method io/reactivex/rxjava3/internal/operators/flowable/FlowableElementAt."<init>":(Lio/reactivex/rxjava3/core/Flowable;JLjava/lang/Object;Z)V
      20: invokestatic  #10                 // Method io/reactivex/rxjava3/plugins/RxJavaPlugins.onAssembly:(Lio/reactivex/rxjava3/core/Flowable;)Lio/reactivex/rxjava3/core/Flowable;
      23: areturn
}
