Compiled from "FlowableFromCompletable.java"
public final class io.reactivex.rxjava3.internal.operators.flowable.FlowableFromCompletable$FromCompletableObserver<T> extends io.reactivex.rxjava3.internal.fuseable.AbstractEmptyQueueFuseable<T> implements io.reactivex.rxjava3.core.CompletableObserver {
  final org.reactivestreams.Subscriber<? super T> downstream;

  io.reactivex.rxjava3.disposables.Disposable upstream;

  public io.reactivex.rxjava3.internal.operators.flowable.FlowableFromCompletable$FromCompletableObserver(org.reactivestreams.Subscriber<? super T>);
    Code:
       0: aload_0
       1: invokespecial #1                  // Method io/reactivex/rxjava3/internal/fuseable/AbstractEmptyQueueFuseable."<init>":()V
       4: aload_0
       5: aload_1
       6: putfield      #2                  // Field downstream:Lorg/reactivestreams/Subscriber;
       9: return

  public void cancel();
    Code:
       0: aload_0
       1: getfield      #3                  // Field upstream:Lio/reactivex/rxjava3/disposables/Disposable;
       4: invokeinterface #4,  1            // InterfaceMethod io/reactivex/rxjava3/disposables/Disposable.dispose:()V
       9: aload_0
      10: getstatic     #5                  // Field io/reactivex/rxjava3/internal/disposables/DisposableHelper.DISPOSED:Lio/reactivex/rxjava3/internal/disposables/DisposableHelper;
      13: putfield      #3                  // Field upstream:Lio/reactivex/rxjava3/disposables/Disposable;
      16: return

  public void onSubscribe(io.reactivex.rxjava3.disposables.Disposable);
    Code:
       0: aload_0
       1: getfield      #3                  // Field upstream:Lio/reactivex/rxjava3/disposables/Disposable;
       4: aload_1
       5: invokestatic  #6                  // Method io/reactivex/rxjava3/internal/disposables/DisposableHelper.validate:(Lio/reactivex/rxjava3/disposables/Disposable;Lio/reactivex/rxjava3/disposables/Disposable;)Z
       8: ifeq          26
      11: aload_0
      12: aload_1
      13: putfield      #3                  // Field upstream:Lio/reactivex/rxjava3/disposables/Disposable;
      16: aload_0
      17: getfield      #2                  // Field downstream:Lorg/reactivestreams/Subscriber;
      20: aload_0
      21: invokeinterface #7,  2            // InterfaceMethod org/reactivestreams/Subscriber.onSubscribe:(Lorg/reactivestreams/Subscription;)V
      26: return

  public void onComplete();
    Code:
       0: aload_0
       1: getstatic     #5                  // Field io/reactivex/rxjava3/internal/disposables/DisposableHelper.DISPOSED:Lio/reactivex/rxjava3/internal/disposables/DisposableHelper;
       4: putfield      #3                  // Field upstream:Lio/reactivex/rxjava3/disposables/Disposable;
       7: aload_0
       8: getfield      #2                  // Field downstream:Lorg/reactivestreams/Subscriber;
      11: invokeinterface #8,  1            // InterfaceMethod org/reactivestreams/Subscriber.onComplete:()V
      16: return

  public void onError(java.lang.Throwable);
    Code:
       0: aload_0
       1: getstatic     #5                  // Field io/reactivex/rxjava3/internal/disposables/DisposableHelper.DISPOSED:Lio/reactivex/rxjava3/internal/disposables/DisposableHelper;
       4: putfield      #3                  // Field upstream:Lio/reactivex/rxjava3/disposables/Disposable;
       7: aload_0
       8: getfield      #2                  // Field downstream:Lorg/reactivestreams/Subscriber;
      11: aload_1
      12: invokeinterface #9,  2            // InterfaceMethod org/reactivestreams/Subscriber.onError:(Ljava/lang/Throwable;)V
      17: return
}
