Compiled from "FlowableScalarXMap.java"
final class io.reactivex.rxjava3.internal.operators.flowable.FlowableScalarXMap$ScalarXMapFlowable<T, R> extends io.reactivex.rxjava3.core.Flowable<R> {
  final T value;

  final io.reactivex.rxjava3.functions.Function<? super T, ? extends org.reactivestreams.Publisher<? extends R>> mapper;

  io.reactivex.rxjava3.internal.operators.flowable.FlowableScalarXMap$ScalarXMapFlowable(T, io.reactivex.rxjava3.functions.Function<? super T, ? extends org.reactivestreams.Publisher<? extends R>>);
    Code:
       0: aload_0
       1: invokespecial #1                  // Method io/reactivex/rxjava3/core/Flowable."<init>":()V
       4: aload_0
       5: aload_1
       6: putfield      #2                  // Field value:Ljava/lang/Object;
       9: aload_0
      10: aload_2
      11: putfield      #3                  // Field mapper:Lio/reactivex/rxjava3/functions/Function;
      14: return

  public void subscribeActual(org.reactivestreams.Subscriber<? super R>);
    Code:
       0: aload_0
       1: getfield      #3                  // Field mapper:Lio/reactivex/rxjava3/functions/Function;
       4: aload_0
       5: getfield      #2                  // Field value:Ljava/lang/Object;
       8: invokeinterface #4,  2            // InterfaceMethod io/reactivex/rxjava3/functions/Function.apply:(Ljava/lang/Object;)Ljava/lang/Object;
      13: ldc           #5                  // String The mapper returned a null Publisher
      15: invokestatic  #6                  // Method java/util/Objects.requireNonNull:(Ljava/lang/Object;Ljava/lang/String;)Ljava/lang/Object;
      18: checkcast     #7                  // class org/reactivestreams/Publisher
      21: astore_2
      22: goto          36
      25: astore_3
      26: aload_3
      27: invokestatic  #9                  // Method io/reactivex/rxjava3/exceptions/Exceptions.throwIfFatal:(Ljava/lang/Throwable;)V
      30: aload_3
      31: aload_1
      32: invokestatic  #10                 // Method io/reactivex/rxjava3/internal/subscriptions/EmptySubscription.error:(Ljava/lang/Throwable;Lorg/reactivestreams/Subscriber;)V
      35: return
      36: aload_2
      37: instanceof    #11                 // class io/reactivex/rxjava3/functions/Supplier
      40: ifeq          97
      43: aload_2
      44: checkcast     #11                 // class io/reactivex/rxjava3/functions/Supplier
      47: invokeinterface #12,  1           // InterfaceMethod io/reactivex/rxjava3/functions/Supplier.get:()Ljava/lang/Object;
      52: astore_3
      53: goto          70
      56: astore        4
      58: aload         4
      60: invokestatic  #9                  // Method io/reactivex/rxjava3/exceptions/Exceptions.throwIfFatal:(Ljava/lang/Throwable;)V
      63: aload         4
      65: aload_1
      66: invokestatic  #10                 // Method io/reactivex/rxjava3/internal/subscriptions/EmptySubscription.error:(Ljava/lang/Throwable;Lorg/reactivestreams/Subscriber;)V
      69: return
      70: aload_3
      71: ifnonnull     79
      74: aload_1
      75: invokestatic  #13                 // Method io/reactivex/rxjava3/internal/subscriptions/EmptySubscription.complete:(Lorg/reactivestreams/Subscriber;)V
      78: return
      79: aload_1
      80: new           #14                 // class io/reactivex/rxjava3/internal/subscriptions/ScalarSubscription
      83: dup
      84: aload_1
      85: aload_3
      86: invokespecial #15                 // Method io/reactivex/rxjava3/internal/subscriptions/ScalarSubscription."<init>":(Lorg/reactivestreams/Subscriber;Ljava/lang/Object;)V
      89: invokeinterface #16,  2           // InterfaceMethod org/reactivestreams/Subscriber.onSubscribe:(Lorg/reactivestreams/Subscription;)V
      94: goto          104
      97: aload_2
      98: aload_1
      99: invokeinterface #17,  2           // InterfaceMethod org/reactivestreams/Publisher.subscribe:(Lorg/reactivestreams/Subscriber;)V
     104: return
    Exception table:
       from    to  target type
           0    22    25   Class java/lang/Throwable
          43    53    56   Class java/lang/Throwable
}
