Compiled from "FlowableReplay.java"
final class io.reactivex.rxjava3.internal.operators.flowable.FlowableReplay$Node extends java.util.concurrent.atomic.AtomicReference<io.reactivex.rxjava3.internal.operators.flowable.FlowableReplay$Node> {
  private static final long serialVersionUID;

  final java.lang.Object value;

  final long index;

  io.reactivex.rxjava3.internal.operators.flowable.FlowableReplay$Node(java.lang.Object, long);
    Code:
       0: aload_0
       1: invokespecial #1                  // Method java/util/concurrent/atomic/AtomicReference."<init>":()V
       4: aload_0
       5: aload_1
       6: putfield      #2                  // Field value:Ljava/lang/Object;
       9: aload_0
      10: lload_2
      11: putfield      #3                  // Field index:J
      14: return
}
