Compiled from "FlowableSubscribeOn.java"
public final class io.reactivex.rxjava3.internal.operators.flowable.FlowableSubscribeOn<T> extends io.reactivex.rxjava3.internal.operators.flowable.AbstractFlowableWithUpstream<T, T> {
  final io.reactivex.rxjava3.core.Scheduler scheduler;

  final boolean nonScheduledRequests;

  public io.reactivex.rxjava3.internal.operators.flowable.FlowableSubscribeOn(io.reactivex.rxjava3.core.Flowable<T>, io.reactivex.rxjava3.core.Scheduler, boolean);
    Code:
       0: aload_0
       1: aload_1
       2: invokespecial #1                  // Method io/reactivex/rxjava3/internal/operators/flowable/AbstractFlowableWithUpstream."<init>":(Lio/reactivex/rxjava3/core/Flowable;)V
       5: aload_0
       6: aload_2
       7: putfield      #2                  // Field scheduler:Lio/reactivex/rxjava3/core/Scheduler;
      10: aload_0
      11: iload_3
      12: putfield      #3                  // Field nonScheduledRequests:Z
      15: return

  public void subscribeActual(org.reactivestreams.Subscriber<? super T>);
    Code:
       0: aload_0
       1: getfield      #2                  // Field scheduler:Lio/reactivex/rxjava3/core/Scheduler;
       4: invokevirtual #4                  // Method io/reactivex/rxjava3/core/Scheduler.createWorker:()Lio/reactivex/rxjava3/core/Scheduler$Worker;
       7: astore_2
       8: new           #5                  // class io/reactivex/rxjava3/internal/operators/flowable/FlowableSubscribeOn$SubscribeOnSubscriber
      11: dup
      12: aload_1
      13: aload_2
      14: aload_0
      15: getfield      #6                  // Field source:Lio/reactivex/rxjava3/core/Flowable;
      18: aload_0
      19: getfield      #3                  // Field nonScheduledRequests:Z
      22: invokespecial #7                  // Method io/reactivex/rxjava3/internal/operators/flowable/FlowableSubscribeOn$SubscribeOnSubscriber."<init>":(Lorg/reactivestreams/Subscriber;Lio/reactivex/rxjava3/core/Scheduler$Worker;Lorg/reactivestreams/Publisher;Z)V
      25: astore_3
      26: aload_1
      27: aload_3
      28: invokeinterface #8,  2            // InterfaceMethod org/reactivestreams/Subscriber.onSubscribe:(Lorg/reactivestreams/Subscription;)V
      33: aload_2
      34: aload_3
      35: invokevirtual #9                  // Method io/reactivex/rxjava3/core/Scheduler$Worker.schedule:(Ljava/lang/Runnable;)Lio/reactivex/rxjava3/disposables/Disposable;
      38: pop
      39: return
}
