Compiled from "FlowableInternalHelper.java"
final class io.reactivex.rxjava3.internal.operators.flowable.FlowableInternalHelper$SubscriberOnError<T> implements io.reactivex.rxjava3.functions.Consumer<java.lang.Throwable> {
  final org.reactivestreams.Subscriber<T> subscriber;

  io.reactivex.rxjava3.internal.operators.flowable.FlowableInternalHelper$SubscriberOnError(org.reactivestreams.Subscriber<T>);
    Code:
       0: aload_0
       1: invokespecial #1                  // Method java/lang/Object."<init>":()V
       4: aload_0
       5: aload_1
       6: putfield      #2                  // Field subscriber:Lorg/reactivestreams/Subscriber;
       9: return

  public void accept(java.lang.Throwable);
    Code:
       0: aload_0
       1: getfield      #2                  // Field subscriber:Lorg/reactivestreams/Subscriber;
       4: aload_1
       5: invokeinterface #3,  2            // InterfaceMethod org/reactivestreams/Subscriber.onError:(Ljava/lang/Throwable;)V
      10: return

  public void accept(java.lang.Object) throws java.lang.Throwable;
    Code:
       0: aload_0
       1: aload_1
       2: checkcast     #4                  // class java/lang/Throwable
       5: invokevirtual #5                  // Method accept:(Ljava/lang/Throwable;)V
       8: return
}
