Compiled from "FlowableConcatMap.java"
final class io.reactivex.rxjava3.internal.operators.flowable.FlowableConcatMap$ConcatMapInner<R> extends io.reactivex.rxjava3.internal.subscriptions.SubscriptionArbiter implements io.reactivex.rxjava3.core.FlowableSubscriber<R> {
  private static final long serialVersionUID;

  final io.reactivex.rxjava3.internal.operators.flowable.FlowableConcatMap$ConcatMapSupport<R> parent;

  long produced;

  io.reactivex.rxjava3.internal.operators.flowable.FlowableConcatMap$ConcatMapInner(io.reactivex.rxjava3.internal.operators.flowable.FlowableConcatMap$ConcatMapSupport<R>);
    Code:
       0: aload_0
       1: iconst_0
       2: invokespecial #1                  // Method io/reactivex/rxjava3/internal/subscriptions/SubscriptionArbiter."<init>":(Z)V
       5: aload_0
       6: aload_1
       7: putfield      #2                  // Field parent:Lio/reactivex/rxjava3/internal/operators/flowable/FlowableConcatMap$ConcatMapSupport;
      10: return

  public void onSubscribe(org.reactivestreams.Subscription);
    Code:
       0: aload_0
       1: aload_1
       2: invokevirtual #3                  // Method setSubscription:(Lorg/reactivestreams/Subscription;)V
       5: return

  public void onNext(R);
    Code:
       0: aload_0
       1: dup
       2: getfield      #4                  // Field produced:J
       5: lconst_1
       6: ladd
       7: putfield      #4                  // Field produced:J
      10: aload_0
      11: getfield      #2                  // Field parent:Lio/reactivex/rxjava3/internal/operators/flowable/FlowableConcatMap$ConcatMapSupport;
      14: aload_1
      15: invokeinterface #5,  2            // InterfaceMethod io/reactivex/rxjava3/internal/operators/flowable/FlowableConcatMap$ConcatMapSupport.innerNext:(Ljava/lang/Object;)V
      20: return

  public void onError(java.lang.Throwable);
    Code:
       0: aload_0
       1: getfield      #4                  // Field produced:J
       4: lstore_2
       5: lload_2
       6: lconst_0
       7: lcmp
       8: ifeq          21
      11: aload_0
      12: lconst_0
      13: putfield      #4                  // Field produced:J
      16: aload_0
      17: lload_2
      18: invokevirtual #6                  // Method produced:(J)V
      21: aload_0
      22: getfield      #2                  // Field parent:Lio/reactivex/rxjava3/internal/operators/flowable/FlowableConcatMap$ConcatMapSupport;
      25: aload_1
      26: invokeinterface #7,  2            // InterfaceMethod io/reactivex/rxjava3/internal/operators/flowable/FlowableConcatMap$ConcatMapSupport.innerError:(Ljava/lang/Throwable;)V
      31: return

  public void onComplete();
    Code:
       0: aload_0
       1: getfield      #4                  // Field produced:J
       4: lstore_1
       5: lload_1
       6: lconst_0
       7: lcmp
       8: ifeq          21
      11: aload_0
      12: lconst_0
      13: putfield      #4                  // Field produced:J
      16: aload_0
      17: lload_1
      18: invokevirtual #6                  // Method produced:(J)V
      21: aload_0
      22: getfield      #2                  // Field parent:Lio/reactivex/rxjava3/internal/operators/flowable/FlowableConcatMap$ConcatMapSupport;
      25: invokeinterface #8,  1            // InterfaceMethod io/reactivex/rxjava3/internal/operators/flowable/FlowableConcatMap$ConcatMapSupport.innerComplete:()V
      30: return
}
