Compiled from "FlowableReplay.java"
final class io.reactivex.rxjava3.internal.operators.flowable.FlowableReplay$InnerSubscription<T> extends java.util.concurrent.atomic.AtomicLong implements org.reactivestreams.Subscription, io.reactivex.rxjava3.disposables.Disposable {
  private static final long serialVersionUID;

  final io.reactivex.rxjava3.internal.operators.flowable.FlowableReplay$ReplaySubscriber<T> parent;

  final org.reactivestreams.Subscriber<? super T> child;

  java.lang.Object index;

  final java.util.concurrent.atomic.AtomicLong totalRequested;

  boolean emitting;

  boolean missed;

  static final long CANCELLED;

  io.reactivex.rxjava3.internal.operators.flowable.FlowableReplay$InnerSubscription(io.reactivex.rxjava3.internal.operators.flowable.FlowableReplay$ReplaySubscriber<T>, org.reactivestreams.Subscriber<? super T>);
    Code:
       0: aload_0
       1: invokespecial #2                  // Method java/util/concurrent/atomic/AtomicLong."<init>":()V
       4: aload_0
       5: aload_1
       6: putfield      #3                  // Field parent:Lio/reactivex/rxjava3/internal/operators/flowable/FlowableReplay$ReplaySubscriber;
       9: aload_0
      10: aload_2
      11: putfield      #4                  // Field child:Lorg/reactivestreams/Subscriber;
      14: aload_0
      15: new           #5                  // class java/util/concurrent/atomic/AtomicLong
      18: dup
      19: invokespecial #2                  // Method java/util/concurrent/atomic/AtomicLong."<init>":()V
      22: putfield      #6                  // Field totalRequested:Ljava/util/concurrent/atomic/AtomicLong;
      25: return

  public void request(long);
    Code:
       0: lload_1
       1: invokestatic  #7                  // Method io/reactivex/rxjava3/internal/subscriptions/SubscriptionHelper.validate:(J)Z
       4: ifeq          48
       7: aload_0
       8: lload_1
       9: invokestatic  #8                  // Method io/reactivex/rxjava3/internal/util/BackpressureHelper.addCancel:(Ljava/util/concurrent/atomic/AtomicLong;J)J
      12: ldc2_w        #10                 // long -9223372036854775808l
      15: lcmp
      16: ifeq          48
      19: aload_0
      20: getfield      #6                  // Field totalRequested:Ljava/util/concurrent/atomic/AtomicLong;
      23: lload_1
      24: invokestatic  #12                 // Method io/reactivex/rxjava3/internal/util/BackpressureHelper.add:(Ljava/util/concurrent/atomic/AtomicLong;J)J
      27: pop2
      28: aload_0
      29: getfield      #3                  // Field parent:Lio/reactivex/rxjava3/internal/operators/flowable/FlowableReplay$ReplaySubscriber;
      32: invokevirtual #13                 // Method io/reactivex/rxjava3/internal/operators/flowable/FlowableReplay$ReplaySubscriber.manageRequests:()V
      35: aload_0
      36: getfield      #3                  // Field parent:Lio/reactivex/rxjava3/internal/operators/flowable/FlowableReplay$ReplaySubscriber;
      39: getfield      #14                 // Field io/reactivex/rxjava3/internal/operators/flowable/FlowableReplay$ReplaySubscriber.buffer:Lio/reactivex/rxjava3/internal/operators/flowable/FlowableReplay$ReplayBuffer;
      42: aload_0
      43: invokeinterface #15,  2           // InterfaceMethod io/reactivex/rxjava3/internal/operators/flowable/FlowableReplay$ReplayBuffer.replay:(Lio/reactivex/rxjava3/internal/operators/flowable/FlowableReplay$InnerSubscription;)V
      48: return

  public long produced(long);
    Code:
       0: aload_0
       1: lload_1
       2: invokestatic  #16                 // Method io/reactivex/rxjava3/internal/util/BackpressureHelper.producedCancel:(Ljava/util/concurrent/atomic/AtomicLong;J)J
       5: lreturn

  public boolean isDisposed();
    Code:
       0: aload_0
       1: invokevirtual #17                 // Method get:()J
       4: ldc2_w        #10                 // long -9223372036854775808l
       7: lcmp
       8: ifne          15
      11: iconst_1
      12: goto          16
      15: iconst_0
      16: ireturn

  public void cancel();
    Code:
       0: aload_0
       1: invokevirtual #18                 // Method dispose:()V
       4: return

  public void dispose();
    Code:
       0: aload_0
       1: ldc2_w        #10                 // long -9223372036854775808l
       4: invokevirtual #19                 // Method getAndSet:(J)J
       7: ldc2_w        #10                 // long -9223372036854775808l
      10: lcmp
      11: ifeq          34
      14: aload_0
      15: getfield      #3                  // Field parent:Lio/reactivex/rxjava3/internal/operators/flowable/FlowableReplay$ReplaySubscriber;
      18: aload_0
      19: invokevirtual #20                 // Method io/reactivex/rxjava3/internal/operators/flowable/FlowableReplay$ReplaySubscriber.remove:(Lio/reactivex/rxjava3/internal/operators/flowable/FlowableReplay$InnerSubscription;)V
      22: aload_0
      23: getfield      #3                  // Field parent:Lio/reactivex/rxjava3/internal/operators/flowable/FlowableReplay$ReplaySubscriber;
      26: invokevirtual #13                 // Method io/reactivex/rxjava3/internal/operators/flowable/FlowableReplay$ReplaySubscriber.manageRequests:()V
      29: aload_0
      30: aconst_null
      31: putfield      #21                 // Field index:Ljava/lang/Object;
      34: return

  <U> U index();
    Code:
       0: aload_0
       1: getfield      #21                 // Field index:Ljava/lang/Object;
       4: areturn
}
