Compiled from "FlowableFromArray.java"
final class io.reactivex.rxjava3.internal.operators.flowable.FlowableFromArray$ArrayConditionalSubscription<T> extends io.reactivex.rxjava3.internal.operators.flowable.FlowableFromArray$BaseArraySubscription<T> {
  private static final long serialVersionUID;

  final io.reactivex.rxjava3.operators.ConditionalSubscriber<? super T> downstream;

  io.reactivex.rxjava3.internal.operators.flowable.FlowableFromArray$ArrayConditionalSubscription(io.reactivex.rxjava3.operators.ConditionalSubscriber<? super T>, T[]);
    Code:
       0: aload_0
       1: aload_2
       2: invokespecial #1                  // Method io/reactivex/rxjava3/internal/operators/flowable/FlowableFromArray$BaseArraySubscription."<init>":([Ljava/lang/Object;)V
       5: aload_0
       6: aload_1
       7: putfield      #2                  // Field downstream:Lio/reactivex/rxjava3/operators/ConditionalSubscriber;
      10: return

  void fastPath();
    Code:
       0: aload_0
       1: getfield      #3                  // Field array:[Ljava/lang/Object;
       4: astore_1
       5: aload_1
       6: arraylength
       7: istore_2
       8: aload_0
       9: getfield      #2                  // Field downstream:Lio/reactivex/rxjava3/operators/ConditionalSubscriber;
      12: astore_3
      13: aload_0
      14: getfield      #4                  // Field index:I
      17: istore        4
      19: iload         4
      21: iload_2
      22: if_icmpeq     98
      25: aload_0
      26: getfield      #5                  // Field cancelled:Z
      29: ifeq          33
      32: return
      33: aload_1
      34: iload         4
      36: aaload
      37: astore        5
      39: aload         5
      41: ifnonnull     83
      44: aload_3
      45: new           #6                  // class java/lang/NullPointerException
      48: dup
      49: new           #7                  // class java/lang/StringBuilder
      52: dup
      53: invokespecial #8                  // Method java/lang/StringBuilder."<init>":()V
      56: ldc           #9                  // String The element at index
      58: invokevirtual #10                 // Method java/lang/StringBuilder.append:(Ljava/lang/String;)Ljava/lang/StringBuilder;
      61: iload         4
      63: invokevirtual #11                 // Method java/lang/StringBuilder.append:(I)Ljava/lang/StringBuilder;
      66: ldc           #12                 // String  is null
      68: invokevirtual #10                 // Method java/lang/StringBuilder.append:(Ljava/lang/String;)Ljava/lang/StringBuilder;
      71: invokevirtual #13                 // Method java/lang/StringBuilder.toString:()Ljava/lang/String;
      74: invokespecial #14                 // Method java/lang/NullPointerException."<init>":(Ljava/lang/String;)V
      77: invokeinterface #15,  2           // InterfaceMethod io/reactivex/rxjava3/operators/ConditionalSubscriber.onError:(Ljava/lang/Throwable;)V
      82: return
      83: aload_3
      84: aload         5
      86: invokeinterface #16,  2           // InterfaceMethod io/reactivex/rxjava3/operators/ConditionalSubscriber.tryOnNext:(Ljava/lang/Object;)Z
      91: pop
      92: iinc          4, 1
      95: goto          19
      98: aload_0
      99: getfield      #5                  // Field cancelled:Z
     102: ifeq          106
     105: return
     106: aload_3
     107: invokeinterface #17,  1           // InterfaceMethod io/reactivex/rxjava3/operators/ConditionalSubscriber.onComplete:()V
     112: return

  void slowPath(long);
    Code:
       0: lconst_0
       1: lstore_3
       2: aload_0
       3: getfield      #3                  // Field array:[Ljava/lang/Object;
       6: astore        5
       8: aload         5
      10: arraylength
      11: istore        6
      13: aload_0
      14: getfield      #4                  // Field index:I
      17: istore        7
      19: aload_0
      20: getfield      #2                  // Field downstream:Lio/reactivex/rxjava3/operators/ConditionalSubscriber;
      23: astore        8
      25: lload_3
      26: lload_1
      27: lcmp
      28: ifeq          120
      31: iload         7
      33: iload         6
      35: if_icmpeq     120
      38: aload_0
      39: getfield      #5                  // Field cancelled:Z
      42: ifeq          46
      45: return
      46: aload         5
      48: iload         7
      50: aaload
      51: astore        9
      53: aload         9
      55: ifnonnull     98
      58: aload         8
      60: new           #6                  // class java/lang/NullPointerException
      63: dup
      64: new           #7                  // class java/lang/StringBuilder
      67: dup
      68: invokespecial #8                  // Method java/lang/StringBuilder."<init>":()V
      71: ldc           #9                  // String The element at index
      73: invokevirtual #10                 // Method java/lang/StringBuilder.append:(Ljava/lang/String;)Ljava/lang/StringBuilder;
      76: iload         7
      78: invokevirtual #11                 // Method java/lang/StringBuilder.append:(I)Ljava/lang/StringBuilder;
      81: ldc           #12                 // String  is null
      83: invokevirtual #10                 // Method java/lang/StringBuilder.append:(Ljava/lang/String;)Ljava/lang/StringBuilder;
      86: invokevirtual #13                 // Method java/lang/StringBuilder.toString:()Ljava/lang/String;
      89: invokespecial #14                 // Method java/lang/NullPointerException."<init>":(Ljava/lang/String;)V
      92: invokeinterface #15,  2           // InterfaceMethod io/reactivex/rxjava3/operators/ConditionalSubscriber.onError:(Ljava/lang/Throwable;)V
      97: return
      98: aload         8
     100: aload         9
     102: invokeinterface #16,  2           // InterfaceMethod io/reactivex/rxjava3/operators/ConditionalSubscriber.tryOnNext:(Ljava/lang/Object;)Z
     107: ifeq          114
     110: lload_3
     111: lconst_1
     112: ladd
     113: lstore_3
     114: iinc          7, 1
     117: goto          25
     120: iload         7
     122: iload         6
     124: if_icmpne     142
     127: aload_0
     128: getfield      #5                  // Field cancelled:Z
     131: ifne          141
     134: aload         8
     136: invokeinterface #17,  1           // InterfaceMethod io/reactivex/rxjava3/operators/ConditionalSubscriber.onComplete:()V
     141: return
     142: aload_0
     143: invokevirtual #18                 // Method get:()J
     146: lstore_1
     147: lload_3
     148: lload_1
     149: lcmp
     150: ifne          25
     153: aload_0
     154: iload         7
     156: putfield      #4                  // Field index:I
     159: aload_0
     160: lload_3
     161: lneg
     162: invokevirtual #19                 // Method addAndGet:(J)J
     165: lstore_1
     166: lload_1
     167: lconst_0
     168: lcmp
     169: ifne          173
     172: return
     173: lconst_0
     174: lstore_3
     175: goto          25
}
