Compiled from "FlowableObserveOn.java"
public final class io.reactivex.rxjava3.internal.operators.flowable.FlowableObserveOn<T> extends io.reactivex.rxjava3.internal.operators.flowable.AbstractFlowableWithUpstream<T, T> {
  final io.reactivex.rxjava3.core.Scheduler scheduler;

  final boolean delayError;

  final int prefetch;

  public io.reactivex.rxjava3.internal.operators.flowable.FlowableObserveOn(io.reactivex.rxjava3.core.Flowable<T>, io.reactivex.rxjava3.core.Scheduler, boolean, int);
    Code:
       0: aload_0
       1: aload_1
       2: invokespecial #1                  // Method io/reactivex/rxjava3/internal/operators/flowable/AbstractFlowableWithUpstream."<init>":(Lio/reactivex/rxjava3/core/Flowable;)V
       5: aload_0
       6: aload_2
       7: putfield      #2                  // Field scheduler:Lio/reactivex/rxjava3/core/Scheduler;
      10: aload_0
      11: iload_3
      12: putfield      #3                  // Field delayError:Z
      15: aload_0
      16: iload         4
      18: putfield      #4                  // Field prefetch:I
      21: return

  public void subscribeActual(org.reactivestreams.Subscriber<? super T>);
    Code:
       0: aload_0
       1: getfield      #2                  // Field scheduler:Lio/reactivex/rxjava3/core/Scheduler;
       4: invokevirtual #5                  // Method io/reactivex/rxjava3/core/Scheduler.createWorker:()Lio/reactivex/rxjava3/core/Scheduler$Worker;
       7: astore_2
       8: aload_1
       9: instanceof    #6                  // class io/reactivex/rxjava3/operators/ConditionalSubscriber
      12: ifeq          45
      15: aload_0
      16: getfield      #7                  // Field source:Lio/reactivex/rxjava3/core/Flowable;
      19: new           #8                  // class io/reactivex/rxjava3/internal/operators/flowable/FlowableObserveOn$ObserveOnConditionalSubscriber
      22: dup
      23: aload_1
      24: checkcast     #6                  // class io/reactivex/rxjava3/operators/ConditionalSubscriber
      27: aload_2
      28: aload_0
      29: getfield      #3                  // Field delayError:Z
      32: aload_0
      33: getfield      #4                  // Field prefetch:I
      36: invokespecial #9                  // Method io/reactivex/rxjava3/internal/operators/flowable/FlowableObserveOn$ObserveOnConditionalSubscriber."<init>":(Lio/reactivex/rxjava3/operators/ConditionalSubscriber;Lio/reactivex/rxjava3/core/Scheduler$Worker;ZI)V
      39: invokevirtual #10                 // Method io/reactivex/rxjava3/core/Flowable.subscribe:(Lio/reactivex/rxjava3/core/FlowableSubscriber;)V
      42: goto          69
      45: aload_0
      46: getfield      #7                  // Field source:Lio/reactivex/rxjava3/core/Flowable;
      49: new           #11                 // class io/reactivex/rxjava3/internal/operators/flowable/FlowableObserveOn$ObserveOnSubscriber
      52: dup
      53: aload_1
      54: aload_2
      55: aload_0
      56: getfield      #3                  // Field delayError:Z
      59: aload_0
      60: getfield      #4                  // Field prefetch:I
      63: invokespecial #12                 // Method io/reactivex/rxjava3/internal/operators/flowable/FlowableObserveOn$ObserveOnSubscriber."<init>":(Lorg/reactivestreams/Subscriber;Lio/reactivex/rxjava3/core/Scheduler$Worker;ZI)V
      66: invokevirtual #10                 // Method io/reactivex/rxjava3/core/Flowable.subscribe:(Lio/reactivex/rxjava3/core/FlowableSubscriber;)V
      69: return
}
