Compiled from "FlowableDelaySubscriptionOther.java"
final class io.reactivex.rxjava3.internal.operators.flowable.FlowableDelaySubscriptionOther$MainSubscriber$OtherSubscriber extends java.util.concurrent.atomic.AtomicReference<org.reactivestreams.Subscription> implements io.reactivex.rxjava3.core.FlowableSubscriber<java.lang.Object> {
  private static final long serialVersionUID;

  final io.reactivex.rxjava3.internal.operators.flowable.FlowableDelaySubscriptionOther$MainSubscriber this$0;

  io.reactivex.rxjava3.internal.operators.flowable.FlowableDelaySubscriptionOther$MainSubscriber$OtherSubscriber(io.reactivex.rxjava3.internal.operators.flowable.FlowableDelaySubscriptionOther$MainSubscriber);
    Code:
       0: aload_0
       1: aload_1
       2: putfield      #1                  // Field this$0:Lio/reactivex/rxjava3/internal/operators/flowable/FlowableDelaySubscriptionOther$MainSubscriber;
       5: aload_0
       6: invokespecial #2                  // Method java/util/concurrent/atomic/AtomicReference."<init>":()V
       9: return

  public void onSubscribe(org.reactivestreams.Subscription);
    Code:
       0: aload_0
       1: aload_1
       2: invokestatic  #3                  // Method io/reactivex/rxjava3/internal/subscriptions/SubscriptionHelper.setOnce:(Ljava/util/concurrent/atomic/AtomicReference;Lorg/reactivestreams/Subscription;)Z
       5: ifeq          17
       8: aload_1
       9: ldc2_w        #5                  // long 9223372036854775807l
      12: invokeinterface #7,  3            // InterfaceMethod org/reactivestreams/Subscription.request:(J)V
      17: return

  public void onNext(java.lang.Object);
    Code:
       0: aload_0
       1: invokevirtual #8                  // Method get:()Ljava/lang/Object;
       4: checkcast     #9                  // class org/reactivestreams/Subscription
       7: astore_2
       8: aload_2
       9: getstatic     #10                 // Field io/reactivex/rxjava3/internal/subscriptions/SubscriptionHelper.CANCELLED:Lio/reactivex/rxjava3/internal/subscriptions/SubscriptionHelper;
      12: if_acmpeq     35
      15: aload_0
      16: getstatic     #10                 // Field io/reactivex/rxjava3/internal/subscriptions/SubscriptionHelper.CANCELLED:Lio/reactivex/rxjava3/internal/subscriptions/SubscriptionHelper;
      19: invokevirtual #11                 // Method lazySet:(Ljava/lang/Object;)V
      22: aload_2
      23: invokeinterface #12,  1           // InterfaceMethod org/reactivestreams/Subscription.cancel:()V
      28: aload_0
      29: getfield      #1                  // Field this$0:Lio/reactivex/rxjava3/internal/operators/flowable/FlowableDelaySubscriptionOther$MainSubscriber;
      32: invokevirtual #13                 // Method io/reactivex/rxjava3/internal/operators/flowable/FlowableDelaySubscriptionOther$MainSubscriber.next:()V
      35: return

  public void onError(java.lang.Throwable);
    Code:
       0: aload_0
       1: invokevirtual #8                  // Method get:()Ljava/lang/Object;
       4: checkcast     #9                  // class org/reactivestreams/Subscription
       7: astore_2
       8: aload_2
       9: getstatic     #10                 // Field io/reactivex/rxjava3/internal/subscriptions/SubscriptionHelper.CANCELLED:Lio/reactivex/rxjava3/internal/subscriptions/SubscriptionHelper;
      12: if_acmpeq     31
      15: aload_0
      16: getfield      #1                  // Field this$0:Lio/reactivex/rxjava3/internal/operators/flowable/FlowableDelaySubscriptionOther$MainSubscriber;
      19: getfield      #14                 // Field io/reactivex/rxjava3/internal/operators/flowable/FlowableDelaySubscriptionOther$MainSubscriber.downstream:Lorg/reactivestreams/Subscriber;
      22: aload_1
      23: invokeinterface #15,  2           // InterfaceMethod org/reactivestreams/Subscriber.onError:(Ljava/lang/Throwable;)V
      28: goto          35
      31: aload_1
      32: invokestatic  #16                 // Method io/reactivex/rxjava3/plugins/RxJavaPlugins.onError:(Ljava/lang/Throwable;)V
      35: return

  public void onComplete();
    Code:
       0: aload_0
       1: invokevirtual #8                  // Method get:()Ljava/lang/Object;
       4: checkcast     #9                  // class org/reactivestreams/Subscription
       7: astore_1
       8: aload_1
       9: getstatic     #10                 // Field io/reactivex/rxjava3/internal/subscriptions/SubscriptionHelper.CANCELLED:Lio/reactivex/rxjava3/internal/subscriptions/SubscriptionHelper;
      12: if_acmpeq     22
      15: aload_0
      16: getfield      #1                  // Field this$0:Lio/reactivex/rxjava3/internal/operators/flowable/FlowableDelaySubscriptionOther$MainSubscriber;
      19: invokevirtual #13                 // Method io/reactivex/rxjava3/internal/operators/flowable/FlowableDelaySubscriptionOther$MainSubscriber.next:()V
      22: return
}
