Compiled from "FlowableTimeout.java"
final class io.reactivex.rxjava3.internal.operators.flowable.FlowableTimeout$TimeoutFallbackSubscriber<T> extends io.reactivex.rxjava3.internal.subscriptions.SubscriptionArbiter implements io.reactivex.rxjava3.core.FlowableSubscriber<T>, io.reactivex.rxjava3.internal.operators.flowable.FlowableTimeout$TimeoutSelectorSupport {
  private static final long serialVersionUID;

  final org.reactivestreams.Subscriber<? super T> downstream;

  final io.reactivex.rxjava3.functions.Function<? super T, ? extends org.reactivestreams.Publisher<?>> itemTimeoutIndicator;

  final io.reactivex.rxjava3.internal.disposables.SequentialDisposable task;

  final java.util.concurrent.atomic.AtomicReference<org.reactivestreams.Subscription> upstream;

  final java.util.concurrent.atomic.AtomicLong index;

  org.reactivestreams.Publisher<? extends T> fallback;

  long consumed;

  io.reactivex.rxjava3.internal.operators.flowable.FlowableTimeout$TimeoutFallbackSubscriber(org.reactivestreams.Subscriber<? super T>, io.reactivex.rxjava3.functions.Function<? super T, ? extends org.reactivestreams.Publisher<?>>, org.reactivestreams.Publisher<? extends T>);
    Code:
       0: aload_0
       1: iconst_1
       2: invokespecial #1                  // Method io/reactivex/rxjava3/internal/subscriptions/SubscriptionArbiter."<init>":(Z)V
       5: aload_0
       6: aload_1
       7: putfield      #2                  // Field downstream:Lorg/reactivestreams/Subscriber;
      10: aload_0
      11: aload_2
      12: putfield      #3                  // Field itemTimeoutIndicator:Lio/reactivex/rxjava3/functions/Function;
      15: aload_0
      16: new           #4                  // class io/reactivex/rxjava3/internal/disposables/SequentialDisposable
      19: dup
      20: invokespecial #5                  // Method io/reactivex/rxjava3/internal/disposables/SequentialDisposable."<init>":()V
      23: putfield      #6                  // Field task:Lio/reactivex/rxjava3/internal/disposables/SequentialDisposable;
      26: aload_0
      27: new           #7                  // class java/util/concurrent/atomic/AtomicReference
      30: dup
      31: invokespecial #8                  // Method java/util/concurrent/atomic/AtomicReference."<init>":()V
      34: putfield      #9                  // Field upstream:Ljava/util/concurrent/atomic/AtomicReference;
      37: aload_0
      38: aload_3
      39: putfield      #10                 // Field fallback:Lorg/reactivestreams/Publisher;
      42: aload_0
      43: new           #11                 // class java/util/concurrent/atomic/AtomicLong
      46: dup
      47: invokespecial #12                 // Method java/util/concurrent/atomic/AtomicLong."<init>":()V
      50: putfield      #13                 // Field index:Ljava/util/concurrent/atomic/AtomicLong;
      53: return

  public void onSubscribe(org.reactivestreams.Subscription);
    Code:
       0: aload_0
       1: getfield      #9                  // Field upstream:Ljava/util/concurrent/atomic/AtomicReference;
       4: aload_1
       5: invokestatic  #14                 // Method io/reactivex/rxjava3/internal/subscriptions/SubscriptionHelper.setOnce:(Ljava/util/concurrent/atomic/AtomicReference;Lorg/reactivestreams/Subscription;)Z
       8: ifeq          16
      11: aload_0
      12: aload_1
      13: invokevirtual #15                 // Method setSubscription:(Lorg/reactivestreams/Subscription;)V
      16: return

  public void onNext(T);
    Code:
       0: aload_0
       1: getfield      #13                 // Field index:Ljava/util/concurrent/atomic/AtomicLong;
       4: invokevirtual #16                 // Method java/util/concurrent/atomic/AtomicLong.get:()J
       7: lstore_2
       8: lload_2
       9: ldc2_w        #18                 // long 9223372036854775807l
      12: lcmp
      13: ifeq          30
      16: aload_0
      17: getfield      #13                 // Field index:Ljava/util/concurrent/atomic/AtomicLong;
      20: lload_2
      21: lload_2
      22: lconst_1
      23: ladd
      24: invokevirtual #20                 // Method java/util/concurrent/atomic/AtomicLong.compareAndSet:(JJ)Z
      27: ifne          31
      30: return
      31: aload_0
      32: getfield      #6                  // Field task:Lio/reactivex/rxjava3/internal/disposables/SequentialDisposable;
      35: invokevirtual #21                 // Method io/reactivex/rxjava3/internal/disposables/SequentialDisposable.get:()Ljava/lang/Object;
      38: checkcast     #22                 // class io/reactivex/rxjava3/disposables/Disposable
      41: astore        4
      43: aload         4
      45: ifnull        55
      48: aload         4
      50: invokeinterface #23,  1           // InterfaceMethod io/reactivex/rxjava3/disposables/Disposable.dispose:()V
      55: aload_0
      56: dup
      57: getfield      #24                 // Field consumed:J
      60: lconst_1
      61: ladd
      62: putfield      #24                 // Field consumed:J
      65: aload_0
      66: getfield      #2                  // Field downstream:Lorg/reactivestreams/Subscriber;
      69: aload_1
      70: invokeinterface #25,  2           // InterfaceMethod org/reactivestreams/Subscriber.onNext:(Ljava/lang/Object;)V
      75: aload_0
      76: getfield      #3                  // Field itemTimeoutIndicator:Lio/reactivex/rxjava3/functions/Function;
      79: aload_1
      80: invokeinterface #26,  2           // InterfaceMethod io/reactivex/rxjava3/functions/Function.apply:(Ljava/lang/Object;)Ljava/lang/Object;
      85: ldc           #27                 // String The itemTimeoutIndicator returned a null Publisher.
      87: invokestatic  #28                 // Method java/util/Objects.requireNonNull:(Ljava/lang/Object;Ljava/lang/String;)Ljava/lang/Object;
      90: checkcast     #29                 // class org/reactivestreams/Publisher
      93: astore        5
      95: goto          143
      98: astore        6
     100: aload         6
     102: invokestatic  #31                 // Method io/reactivex/rxjava3/exceptions/Exceptions.throwIfFatal:(Ljava/lang/Throwable;)V
     105: aload_0
     106: getfield      #9                  // Field upstream:Ljava/util/concurrent/atomic/AtomicReference;
     109: invokevirtual #32                 // Method java/util/concurrent/atomic/AtomicReference.get:()Ljava/lang/Object;
     112: checkcast     #33                 // class org/reactivestreams/Subscription
     115: invokeinterface #34,  1           // InterfaceMethod org/reactivestreams/Subscription.cancel:()V
     120: aload_0
     121: getfield      #13                 // Field index:Ljava/util/concurrent/atomic/AtomicLong;
     124: ldc2_w        #18                 // long 9223372036854775807l
     127: invokevirtual #35                 // Method java/util/concurrent/atomic/AtomicLong.getAndSet:(J)J
     130: pop2
     131: aload_0
     132: getfield      #2                  // Field downstream:Lorg/reactivestreams/Subscriber;
     135: aload         6
     137: invokeinterface #36,  2           // InterfaceMethod org/reactivestreams/Subscriber.onError:(Ljava/lang/Throwable;)V
     142: return
     143: new           #37                 // class io/reactivex/rxjava3/internal/operators/flowable/FlowableTimeout$TimeoutConsumer
     146: dup
     147: lload_2
     148: lconst_1
     149: ladd
     150: aload_0
     151: invokespecial #38                 // Method io/reactivex/rxjava3/internal/operators/flowable/FlowableTimeout$TimeoutConsumer."<init>":(JLio/reactivex/rxjava3/internal/operators/flowable/FlowableTimeout$TimeoutSelectorSupport;)V
     154: astore        6
     156: aload_0
     157: getfield      #6                  // Field task:Lio/reactivex/rxjava3/internal/disposables/SequentialDisposable;
     160: aload         6
     162: invokevirtual #39                 // Method io/reactivex/rxjava3/internal/disposables/SequentialDisposable.replace:(Lio/reactivex/rxjava3/disposables/Disposable;)Z
     165: ifeq          177
     168: aload         5
     170: aload         6
     172: invokeinterface #40,  2           // InterfaceMethod org/reactivestreams/Publisher.subscribe:(Lorg/reactivestreams/Subscriber;)V
     177: return
    Exception table:
       from    to  target type
          75    95    98   Class java/lang/Throwable

  void startFirstTimeout(org.reactivestreams.Publisher<?>);
    Code:
       0: aload_1
       1: ifnull        32
       4: new           #37                 // class io/reactivex/rxjava3/internal/operators/flowable/FlowableTimeout$TimeoutConsumer
       7: dup
       8: lconst_0
       9: aload_0
      10: invokespecial #38                 // Method io/reactivex/rxjava3/internal/operators/flowable/FlowableTimeout$TimeoutConsumer."<init>":(JLio/reactivex/rxjava3/internal/operators/flowable/FlowableTimeout$TimeoutSelectorSupport;)V
      13: astore_2
      14: aload_0
      15: getfield      #6                  // Field task:Lio/reactivex/rxjava3/internal/disposables/SequentialDisposable;
      18: aload_2
      19: invokevirtual #39                 // Method io/reactivex/rxjava3/internal/disposables/SequentialDisposable.replace:(Lio/reactivex/rxjava3/disposables/Disposable;)Z
      22: ifeq          32
      25: aload_1
      26: aload_2
      27: invokeinterface #40,  2           // InterfaceMethod org/reactivestreams/Publisher.subscribe:(Lorg/reactivestreams/Subscriber;)V
      32: return

  public void onError(java.lang.Throwable);
    Code:
       0: aload_0
       1: getfield      #13                 // Field index:Ljava/util/concurrent/atomic/AtomicLong;
       4: ldc2_w        #18                 // long 9223372036854775807l
       7: invokevirtual #35                 // Method java/util/concurrent/atomic/AtomicLong.getAndSet:(J)J
      10: ldc2_w        #18                 // long 9223372036854775807l
      13: lcmp
      14: ifeq          44
      17: aload_0
      18: getfield      #6                  // Field task:Lio/reactivex/rxjava3/internal/disposables/SequentialDisposable;
      21: invokevirtual #41                 // Method io/reactivex/rxjava3/internal/disposables/SequentialDisposable.dispose:()V
      24: aload_0
      25: getfield      #2                  // Field downstream:Lorg/reactivestreams/Subscriber;
      28: aload_1
      29: invokeinterface #36,  2           // InterfaceMethod org/reactivestreams/Subscriber.onError:(Ljava/lang/Throwable;)V
      34: aload_0
      35: getfield      #6                  // Field task:Lio/reactivex/rxjava3/internal/disposables/SequentialDisposable;
      38: invokevirtual #41                 // Method io/reactivex/rxjava3/internal/disposables/SequentialDisposable.dispose:()V
      41: goto          48
      44: aload_1
      45: invokestatic  #42                 // Method io/reactivex/rxjava3/plugins/RxJavaPlugins.onError:(Ljava/lang/Throwable;)V
      48: return

  public void onComplete();
    Code:
       0: aload_0
       1: getfield      #13                 // Field index:Ljava/util/concurrent/atomic/AtomicLong;
       4: ldc2_w        #18                 // long 9223372036854775807l
       7: invokevirtual #35                 // Method java/util/concurrent/atomic/AtomicLong.getAndSet:(J)J
      10: ldc2_w        #18                 // long 9223372036854775807l
      13: lcmp
      14: ifeq          40
      17: aload_0
      18: getfield      #6                  // Field task:Lio/reactivex/rxjava3/internal/disposables/SequentialDisposable;
      21: invokevirtual #41                 // Method io/reactivex/rxjava3/internal/disposables/SequentialDisposable.dispose:()V
      24: aload_0
      25: getfield      #2                  // Field downstream:Lorg/reactivestreams/Subscriber;
      28: invokeinterface #43,  1           // InterfaceMethod org/reactivestreams/Subscriber.onComplete:()V
      33: aload_0
      34: getfield      #6                  // Field task:Lio/reactivex/rxjava3/internal/disposables/SequentialDisposable;
      37: invokevirtual #41                 // Method io/reactivex/rxjava3/internal/disposables/SequentialDisposable.dispose:()V
      40: return

  public void onTimeout(long);
    Code:
       0: aload_0
       1: getfield      #13                 // Field index:Ljava/util/concurrent/atomic/AtomicLong;
       4: lload_1
       5: ldc2_w        #18                 // long 9223372036854775807l
       8: invokevirtual #20                 // Method java/util/concurrent/atomic/AtomicLong.compareAndSet:(JJ)Z
      11: ifeq          69
      14: aload_0
      15: getfield      #9                  // Field upstream:Ljava/util/concurrent/atomic/AtomicReference;
      18: invokestatic  #44                 // Method io/reactivex/rxjava3/internal/subscriptions/SubscriptionHelper.cancel:(Ljava/util/concurrent/atomic/AtomicReference;)Z
      21: pop
      22: aload_0
      23: getfield      #10                 // Field fallback:Lorg/reactivestreams/Publisher;
      26: astore_3
      27: aload_0
      28: aconst_null
      29: putfield      #10                 // Field fallback:Lorg/reactivestreams/Publisher;
      32: aload_0
      33: getfield      #24                 // Field consumed:J
      36: lstore        4
      38: lload         4
      40: lconst_0
      41: lcmp
      42: ifeq          51
      45: aload_0
      46: lload         4
      48: invokevirtual #45                 // Method produced:(J)V
      51: aload_3
      52: new           #46                 // class io/reactivex/rxjava3/internal/operators/flowable/FlowableTimeoutTimed$FallbackSubscriber
      55: dup
      56: aload_0
      57: getfield      #2                  // Field downstream:Lorg/reactivestreams/Subscriber;
      60: aload_0
      61: invokespecial #47                 // Method io/reactivex/rxjava3/internal/operators/flowable/FlowableTimeoutTimed$FallbackSubscriber."<init>":(Lorg/reactivestreams/Subscriber;Lio/reactivex/rxjava3/internal/subscriptions/SubscriptionArbiter;)V
      64: invokeinterface #40,  2           // InterfaceMethod org/reactivestreams/Publisher.subscribe:(Lorg/reactivestreams/Subscriber;)V
      69: return

  public void onTimeoutError(long, java.lang.Throwable);
    Code:
       0: aload_0
       1: getfield      #13                 // Field index:Ljava/util/concurrent/atomic/AtomicLong;
       4: lload_1
       5: ldc2_w        #18                 // long 9223372036854775807l
       8: invokevirtual #20                 // Method java/util/concurrent/atomic/AtomicLong.compareAndSet:(JJ)Z
      11: ifeq          35
      14: aload_0
      15: getfield      #9                  // Field upstream:Ljava/util/concurrent/atomic/AtomicReference;
      18: invokestatic  #44                 // Method io/reactivex/rxjava3/internal/subscriptions/SubscriptionHelper.cancel:(Ljava/util/concurrent/atomic/AtomicReference;)Z
      21: pop
      22: aload_0
      23: getfield      #2                  // Field downstream:Lorg/reactivestreams/Subscriber;
      26: aload_3
      27: invokeinterface #36,  2           // InterfaceMethod org/reactivestreams/Subscriber.onError:(Ljava/lang/Throwable;)V
      32: goto          39
      35: aload_3
      36: invokestatic  #42                 // Method io/reactivex/rxjava3/plugins/RxJavaPlugins.onError:(Ljava/lang/Throwable;)V
      39: return

  public void cancel();
    Code:
       0: aload_0
       1: invokespecial #48                 // Method io/reactivex/rxjava3/internal/subscriptions/SubscriptionArbiter.cancel:()V
       4: aload_0
       5: getfield      #6                  // Field task:Lio/reactivex/rxjava3/internal/disposables/SequentialDisposable;
       8: invokevirtual #41                 // Method io/reactivex/rxjava3/internal/disposables/SequentialDisposable.dispose:()V
      11: return
}
