Compiled from "FlowableWithLatestFrom.java"
final class io.reactivex.rxjava3.internal.operators.flowable.FlowableWithLatestFrom$WithLatestFromSubscriber<T, U, R> extends java.util.concurrent.atomic.AtomicReference<U> implements io.reactivex.rxjava3.operators.ConditionalSubscriber<T>, org.reactivestreams.Subscription {
  private static final long serialVersionUID;

  final org.reactivestreams.Subscriber<? super R> downstream;

  final io.reactivex.rxjava3.functions.BiFunction<? super T, ? super U, ? extends R> combiner;

  final java.util.concurrent.atomic.AtomicReference<org.reactivestreams.Subscription> upstream;

  final java.util.concurrent.atomic.AtomicLong requested;

  final java.util.concurrent.atomic.AtomicReference<org.reactivestreams.Subscription> other;

  io.reactivex.rxjava3.internal.operators.flowable.FlowableWithLatestFrom$WithLatestFromSubscriber(org.reactivestreams.Subscriber<? super R>, io.reactivex.rxjava3.functions.BiFunction<? super T, ? super U, ? extends R>);
    Code:
       0: aload_0
       1: invokespecial #1                  // Method java/util/concurrent/atomic/AtomicReference."<init>":()V
       4: aload_0
       5: new           #2                  // class java/util/concurrent/atomic/AtomicReference
       8: dup
       9: invokespecial #1                  // Method java/util/concurrent/atomic/AtomicReference."<init>":()V
      12: putfield      #3                  // Field upstream:Ljava/util/concurrent/atomic/AtomicReference;
      15: aload_0
      16: new           #4                  // class java/util/concurrent/atomic/AtomicLong
      19: dup
      20: invokespecial #5                  // Method java/util/concurrent/atomic/AtomicLong."<init>":()V
      23: putfield      #6                  // Field requested:Ljava/util/concurrent/atomic/AtomicLong;
      26: aload_0
      27: new           #2                  // class java/util/concurrent/atomic/AtomicReference
      30: dup
      31: invokespecial #1                  // Method java/util/concurrent/atomic/AtomicReference."<init>":()V
      34: putfield      #7                  // Field other:Ljava/util/concurrent/atomic/AtomicReference;
      37: aload_0
      38: aload_1
      39: putfield      #8                  // Field downstream:Lorg/reactivestreams/Subscriber;
      42: aload_0
      43: aload_2
      44: putfield      #9                  // Field combiner:Lio/reactivex/rxjava3/functions/BiFunction;
      47: return

  public void onSubscribe(org.reactivestreams.Subscription);
    Code:
       0: aload_0
       1: getfield      #3                  // Field upstream:Ljava/util/concurrent/atomic/AtomicReference;
       4: aload_0
       5: getfield      #6                  // Field requested:Ljava/util/concurrent/atomic/AtomicLong;
       8: aload_1
       9: invokestatic  #10                 // Method io/reactivex/rxjava3/internal/subscriptions/SubscriptionHelper.deferredSetOnce:(Ljava/util/concurrent/atomic/AtomicReference;Ljava/util/concurrent/atomic/AtomicLong;Lorg/reactivestreams/Subscription;)Z
      12: pop
      13: return

  public void onNext(T);
    Code:
       0: aload_0
       1: aload_1
       2: invokevirtual #11                 // Method tryOnNext:(Ljava/lang/Object;)Z
       5: ifne          24
       8: aload_0
       9: getfield      #3                  // Field upstream:Ljava/util/concurrent/atomic/AtomicReference;
      12: invokevirtual #12                 // Method java/util/concurrent/atomic/AtomicReference.get:()Ljava/lang/Object;
      15: checkcast     #13                 // class org/reactivestreams/Subscription
      18: lconst_1
      19: invokeinterface #14,  3           // InterfaceMethod org/reactivestreams/Subscription.request:(J)V
      24: return

  public boolean tryOnNext(T);
    Code:
       0: aload_0
       1: invokevirtual #15                 // Method get:()Ljava/lang/Object;
       4: astore_2
       5: aload_2
       6: ifnull        65
       9: aload_0
      10: getfield      #9                  // Field combiner:Lio/reactivex/rxjava3/functions/BiFunction;
      13: aload_1
      14: aload_2
      15: invokeinterface #16,  3           // InterfaceMethod io/reactivex/rxjava3/functions/BiFunction.apply:(Ljava/lang/Object;Ljava/lang/Object;)Ljava/lang/Object;
      20: ldc           #17                 // String The combiner returned a null value
      22: invokestatic  #18                 // Method java/util/Objects.requireNonNull:(Ljava/lang/Object;Ljava/lang/String;)Ljava/lang/Object;
      25: astore_3
      26: goto          53
      29: astore        4
      31: aload         4
      33: invokestatic  #20                 // Method io/reactivex/rxjava3/exceptions/Exceptions.throwIfFatal:(Ljava/lang/Throwable;)V
      36: aload_0
      37: invokevirtual #21                 // Method cancel:()V
      40: aload_0
      41: getfield      #8                  // Field downstream:Lorg/reactivestreams/Subscriber;
      44: aload         4
      46: invokeinterface #22,  2           // InterfaceMethod org/reactivestreams/Subscriber.onError:(Ljava/lang/Throwable;)V
      51: iconst_0
      52: ireturn
      53: aload_0
      54: getfield      #8                  // Field downstream:Lorg/reactivestreams/Subscriber;
      57: aload_3
      58: invokeinterface #23,  2           // InterfaceMethod org/reactivestreams/Subscriber.onNext:(Ljava/lang/Object;)V
      63: iconst_1
      64: ireturn
      65: iconst_0
      66: ireturn
    Exception table:
       from    to  target type
           9    26    29   Class java/lang/Throwable

  public void onError(java.lang.Throwable);
    Code:
       0: aload_0
       1: getfield      #7                  // Field other:Ljava/util/concurrent/atomic/AtomicReference;
       4: invokestatic  #24                 // Method io/reactivex/rxjava3/internal/subscriptions/SubscriptionHelper.cancel:(Ljava/util/concurrent/atomic/AtomicReference;)Z
       7: pop
       8: aload_0
       9: getfield      #8                  // Field downstream:Lorg/reactivestreams/Subscriber;
      12: aload_1
      13: invokeinterface #22,  2           // InterfaceMethod org/reactivestreams/Subscriber.onError:(Ljava/lang/Throwable;)V
      18: return

  public void onComplete();
    Code:
       0: aload_0
       1: getfield      #7                  // Field other:Ljava/util/concurrent/atomic/AtomicReference;
       4: invokestatic  #24                 // Method io/reactivex/rxjava3/internal/subscriptions/SubscriptionHelper.cancel:(Ljava/util/concurrent/atomic/AtomicReference;)Z
       7: pop
       8: aload_0
       9: getfield      #8                  // Field downstream:Lorg/reactivestreams/Subscriber;
      12: invokeinterface #25,  1           // InterfaceMethod org/reactivestreams/Subscriber.onComplete:()V
      17: return

  public void request(long);
    Code:
       0: aload_0
       1: getfield      #3                  // Field upstream:Ljava/util/concurrent/atomic/AtomicReference;
       4: aload_0
       5: getfield      #6                  // Field requested:Ljava/util/concurrent/atomic/AtomicLong;
       8: lload_1
       9: invokestatic  #26                 // Method io/reactivex/rxjava3/internal/subscriptions/SubscriptionHelper.deferredRequest:(Ljava/util/concurrent/atomic/AtomicReference;Ljava/util/concurrent/atomic/AtomicLong;J)V
      12: return

  public void cancel();
    Code:
       0: aload_0
       1: getfield      #3                  // Field upstream:Ljava/util/concurrent/atomic/AtomicReference;
       4: invokestatic  #24                 // Method io/reactivex/rxjava3/internal/subscriptions/SubscriptionHelper.cancel:(Ljava/util/concurrent/atomic/AtomicReference;)Z
       7: pop
       8: aload_0
       9: getfield      #7                  // Field other:Ljava/util/concurrent/atomic/AtomicReference;
      12: invokestatic  #24                 // Method io/reactivex/rxjava3/internal/subscriptions/SubscriptionHelper.cancel:(Ljava/util/concurrent/atomic/AtomicReference;)Z
      15: pop
      16: return

  public boolean setOther(org.reactivestreams.Subscription);
    Code:
       0: aload_0
       1: getfield      #7                  // Field other:Ljava/util/concurrent/atomic/AtomicReference;
       4: aload_1
       5: invokestatic  #27                 // Method io/reactivex/rxjava3/internal/subscriptions/SubscriptionHelper.setOnce:(Ljava/util/concurrent/atomic/AtomicReference;Lorg/reactivestreams/Subscription;)Z
       8: ireturn

  public void otherError(java.lang.Throwable);
    Code:
       0: aload_0
       1: getfield      #3                  // Field upstream:Ljava/util/concurrent/atomic/AtomicReference;
       4: invokestatic  #24                 // Method io/reactivex/rxjava3/internal/subscriptions/SubscriptionHelper.cancel:(Ljava/util/concurrent/atomic/AtomicReference;)Z
       7: pop
       8: aload_0
       9: getfield      #8                  // Field downstream:Lorg/reactivestreams/Subscriber;
      12: aload_1
      13: invokeinterface #22,  2           // InterfaceMethod org/reactivestreams/Subscriber.onError:(Ljava/lang/Throwable;)V
      18: return
}
