Compiled from "FlowableConcatMapEager.java"
final class io.reactivex.rxjava3.internal.operators.flowable.FlowableConcatMapEager$ConcatMapEagerDelayErrorSubscriber<T, R> extends java.util.concurrent.atomic.AtomicInteger implements io.reactivex.rxjava3.core.FlowableSubscriber<T>, org.reactivestreams.Subscription, io.reactivex.rxjava3.internal.subscribers.InnerQueuedSubscriberSupport<R> {
  private static final long serialVersionUID;

  final org.reactivestreams.Subscriber<? super R> downstream;

  final io.reactivex.rxjava3.functions.Function<? super T, ? extends org.reactivestreams.Publisher<? extends R>> mapper;

  final int maxConcurrency;

  final int prefetch;

  final io.reactivex.rxjava3.internal.util.ErrorMode errorMode;

  final io.reactivex.rxjava3.internal.util.AtomicThrowable errors;

  final java.util.concurrent.atomic.AtomicLong requested;

  final io.reactivex.rxjava3.operators.SpscLinkedArrayQueue<io.reactivex.rxjava3.internal.subscribers.InnerQueuedSubscriber<R>> subscribers;

  org.reactivestreams.Subscription upstream;

  volatile boolean cancelled;

  volatile boolean done;

  volatile io.reactivex.rxjava3.internal.subscribers.InnerQueuedSubscriber<R> current;

  io.reactivex.rxjava3.internal.operators.flowable.FlowableConcatMapEager$ConcatMapEagerDelayErrorSubscriber(org.reactivestreams.Subscriber<? super R>, io.reactivex.rxjava3.functions.Function<? super T, ? extends org.reactivestreams.Publisher<? extends R>>, int, int, io.reactivex.rxjava3.internal.util.ErrorMode);
    Code:
       0: aload_0
       1: invokespecial #1                  // Method java/util/concurrent/atomic/AtomicInteger."<init>":()V
       4: aload_0
       5: aload_1
       6: putfield      #2                  // Field downstream:Lorg/reactivestreams/Subscriber;
       9: aload_0
      10: aload_2
      11: putfield      #3                  // Field mapper:Lio/reactivex/rxjava3/functions/Function;
      14: aload_0
      15: iload_3
      16: putfield      #4                  // Field maxConcurrency:I
      19: aload_0
      20: iload         4
      22: putfield      #5                  // Field prefetch:I
      25: aload_0
      26: aload         5
      28: putfield      #6                  // Field errorMode:Lio/reactivex/rxjava3/internal/util/ErrorMode;
      31: aload_0
      32: new           #7                  // class io/reactivex/rxjava3/operators/SpscLinkedArrayQueue
      35: dup
      36: iload         4
      38: iload_3
      39: invokestatic  #8                  // Method java/lang/Math.min:(II)I
      42: invokespecial #9                  // Method io/reactivex/rxjava3/operators/SpscLinkedArrayQueue."<init>":(I)V
      45: putfield      #10                 // Field subscribers:Lio/reactivex/rxjava3/operators/SpscLinkedArrayQueue;
      48: aload_0
      49: new           #11                 // class io/reactivex/rxjava3/internal/util/AtomicThrowable
      52: dup
      53: invokespecial #12                 // Method io/reactivex/rxjava3/internal/util/AtomicThrowable."<init>":()V
      56: putfield      #13                 // Field errors:Lio/reactivex/rxjava3/internal/util/AtomicThrowable;
      59: aload_0
      60: new           #14                 // class java/util/concurrent/atomic/AtomicLong
      63: dup
      64: invokespecial #15                 // Method java/util/concurrent/atomic/AtomicLong."<init>":()V
      67: putfield      #16                 // Field requested:Ljava/util/concurrent/atomic/AtomicLong;
      70: return

  public void onSubscribe(org.reactivestreams.Subscription);
    Code:
       0: aload_0
       1: getfield      #17                 // Field upstream:Lorg/reactivestreams/Subscription;
       4: aload_1
       5: invokestatic  #18                 // Method io/reactivex/rxjava3/internal/subscriptions/SubscriptionHelper.validate:(Lorg/reactivestreams/Subscription;Lorg/reactivestreams/Subscription;)Z
       8: ifeq          52
      11: aload_0
      12: aload_1
      13: putfield      #17                 // Field upstream:Lorg/reactivestreams/Subscription;
      16: aload_0
      17: getfield      #2                  // Field downstream:Lorg/reactivestreams/Subscriber;
      20: aload_0
      21: invokeinterface #19,  2           // InterfaceMethod org/reactivestreams/Subscriber.onSubscribe:(Lorg/reactivestreams/Subscription;)V
      26: aload_1
      27: aload_0
      28: getfield      #4                  // Field maxConcurrency:I
      31: ldc           #21                 // int 2147483647
      33: if_icmpne     42
      36: ldc2_w        #23                 // long 9223372036854775807l
      39: goto          47
      42: aload_0
      43: getfield      #4                  // Field maxConcurrency:I
      46: i2l
      47: invokeinterface #25,  3           // InterfaceMethod org/reactivestreams/Subscription.request:(J)V
      52: return

  public void onNext(T);
    Code:
       0: aload_0
       1: getfield      #3                  // Field mapper:Lio/reactivex/rxjava3/functions/Function;
       4: aload_1
       5: invokeinterface #26,  2           // InterfaceMethod io/reactivex/rxjava3/functions/Function.apply:(Ljava/lang/Object;)Ljava/lang/Object;
      10: ldc           #27                 // String The mapper returned a null Publisher
      12: invokestatic  #28                 // Method java/util/Objects.requireNonNull:(Ljava/lang/Object;Ljava/lang/String;)Ljava/lang/Object;
      15: checkcast     #29                 // class org/reactivestreams/Publisher
      18: astore_2
      19: goto          42
      22: astore_3
      23: aload_3
      24: invokestatic  #31                 // Method io/reactivex/rxjava3/exceptions/Exceptions.throwIfFatal:(Ljava/lang/Throwable;)V
      27: aload_0
      28: getfield      #17                 // Field upstream:Lorg/reactivestreams/Subscription;
      31: invokeinterface #32,  1           // InterfaceMethod org/reactivestreams/Subscription.cancel:()V
      36: aload_0
      37: aload_3
      38: invokevirtual #33                 // Method onError:(Ljava/lang/Throwable;)V
      41: return
      42: new           #34                 // class io/reactivex/rxjava3/internal/subscribers/InnerQueuedSubscriber
      45: dup
      46: aload_0
      47: aload_0
      48: getfield      #5                  // Field prefetch:I
      51: invokespecial #35                 // Method io/reactivex/rxjava3/internal/subscribers/InnerQueuedSubscriber."<init>":(Lio/reactivex/rxjava3/internal/subscribers/InnerQueuedSubscriberSupport;I)V
      54: astore_3
      55: aload_0
      56: getfield      #36                 // Field cancelled:Z
      59: ifeq          63
      62: return
      63: aload_0
      64: getfield      #10                 // Field subscribers:Lio/reactivex/rxjava3/operators/SpscLinkedArrayQueue;
      67: aload_3
      68: invokevirtual #37                 // Method io/reactivex/rxjava3/operators/SpscLinkedArrayQueue.offer:(Ljava/lang/Object;)Z
      71: pop
      72: aload_2
      73: aload_3
      74: invokeinterface #38,  2           // InterfaceMethod org/reactivestreams/Publisher.subscribe:(Lorg/reactivestreams/Subscriber;)V
      79: aload_0
      80: getfield      #36                 // Field cancelled:Z
      83: ifeq          94
      86: aload_3
      87: invokevirtual #39                 // Method io/reactivex/rxjava3/internal/subscribers/InnerQueuedSubscriber.cancel:()V
      90: aload_0
      91: invokevirtual #40                 // Method drainAndCancel:()V
      94: return
    Exception table:
       from    to  target type
           0    19    22   Class java/lang/Throwable

  public void onError(java.lang.Throwable);
    Code:
       0: aload_0
       1: getfield      #13                 // Field errors:Lio/reactivex/rxjava3/internal/util/AtomicThrowable;
       4: aload_1
       5: invokevirtual #41                 // Method io/reactivex/rxjava3/internal/util/AtomicThrowable.tryAddThrowableOrReport:(Ljava/lang/Throwable;)Z
       8: ifeq          20
      11: aload_0
      12: iconst_1
      13: putfield      #42                 // Field done:Z
      16: aload_0
      17: invokevirtual #43                 // Method drain:()V
      20: return

  public void onComplete();
    Code:
       0: aload_0
       1: iconst_1
       2: putfield      #42                 // Field done:Z
       5: aload_0
       6: invokevirtual #43                 // Method drain:()V
       9: return

  public void cancel();
    Code:
       0: aload_0
       1: getfield      #36                 // Field cancelled:Z
       4: ifeq          8
       7: return
       8: aload_0
       9: iconst_1
      10: putfield      #36                 // Field cancelled:Z
      13: aload_0
      14: getfield      #17                 // Field upstream:Lorg/reactivestreams/Subscription;
      17: invokeinterface #32,  1           // InterfaceMethod org/reactivestreams/Subscription.cancel:()V
      22: aload_0
      23: getfield      #13                 // Field errors:Lio/reactivex/rxjava3/internal/util/AtomicThrowable;
      26: invokevirtual #44                 // Method io/reactivex/rxjava3/internal/util/AtomicThrowable.tryTerminateAndReport:()V
      29: aload_0
      30: invokevirtual #40                 // Method drainAndCancel:()V
      33: return

  void drainAndCancel();
    Code:
       0: aload_0
       1: invokevirtual #45                 // Method getAndIncrement:()I
       4: ifne          18
       7: aload_0
       8: invokevirtual #46                 // Method cancelAll:()V
      11: aload_0
      12: invokevirtual #47                 // Method decrementAndGet:()I
      15: ifne          7
      18: return

  void cancelAll();
    Code:
       0: aload_0
       1: getfield      #48                 // Field current:Lio/reactivex/rxjava3/internal/subscribers/InnerQueuedSubscriber;
       4: astore_1
       5: aload_0
       6: aconst_null
       7: putfield      #48                 // Field current:Lio/reactivex/rxjava3/internal/subscribers/InnerQueuedSubscriber;
      10: aload_1
      11: ifnull        18
      14: aload_1
      15: invokevirtual #39                 // Method io/reactivex/rxjava3/internal/subscribers/InnerQueuedSubscriber.cancel:()V
      18: aload_0
      19: getfield      #10                 // Field subscribers:Lio/reactivex/rxjava3/operators/SpscLinkedArrayQueue;
      22: invokevirtual #49                 // Method io/reactivex/rxjava3/operators/SpscLinkedArrayQueue.poll:()Ljava/lang/Object;
      25: checkcast     #34                 // class io/reactivex/rxjava3/internal/subscribers/InnerQueuedSubscriber
      28: dup
      29: astore_1
      30: ifnull        40
      33: aload_1
      34: invokevirtual #39                 // Method io/reactivex/rxjava3/internal/subscribers/InnerQueuedSubscriber.cancel:()V
      37: goto          18
      40: return

  public void request(long);
    Code:
       0: lload_1
       1: invokestatic  #50                 // Method io/reactivex/rxjava3/internal/subscriptions/SubscriptionHelper.validate:(J)Z
       4: ifeq          20
       7: aload_0
       8: getfield      #16                 // Field requested:Ljava/util/concurrent/atomic/AtomicLong;
      11: lload_1
      12: invokestatic  #51                 // Method io/reactivex/rxjava3/internal/util/BackpressureHelper.add:(Ljava/util/concurrent/atomic/AtomicLong;J)J
      15: pop2
      16: aload_0
      17: invokevirtual #43                 // Method drain:()V
      20: return

  public void innerNext(io.reactivex.rxjava3.internal.subscribers.InnerQueuedSubscriber<R>, R);
    Code:
       0: aload_1
       1: invokevirtual #52                 // Method io/reactivex/rxjava3/internal/subscribers/InnerQueuedSubscriber.queue:()Lio/reactivex/rxjava3/operators/SimpleQueue;
       4: aload_2
       5: invokeinterface #53,  2           // InterfaceMethod io/reactivex/rxjava3/operators/SimpleQueue.offer:(Ljava/lang/Object;)Z
      10: ifeq          20
      13: aload_0
      14: invokevirtual #43                 // Method drain:()V
      17: goto          32
      20: aload_1
      21: invokevirtual #39                 // Method io/reactivex/rxjava3/internal/subscribers/InnerQueuedSubscriber.cancel:()V
      24: aload_0
      25: aload_1
      26: invokestatic  #54                 // Method io/reactivex/rxjava3/exceptions/MissingBackpressureException.createDefault:()Lio/reactivex/rxjava3/exceptions/MissingBackpressureException;
      29: invokevirtual #55                 // Method innerError:(Lio/reactivex/rxjava3/internal/subscribers/InnerQueuedSubscriber;Ljava/lang/Throwable;)V
      32: return

  public void innerError(io.reactivex.rxjava3.internal.subscribers.InnerQueuedSubscriber<R>, java.lang.Throwable);
    Code:
       0: aload_0
       1: getfield      #13                 // Field errors:Lio/reactivex/rxjava3/internal/util/AtomicThrowable;
       4: aload_2
       5: invokevirtual #41                 // Method io/reactivex/rxjava3/internal/util/AtomicThrowable.tryAddThrowableOrReport:(Ljava/lang/Throwable;)Z
       8: ifeq          38
      11: aload_1
      12: invokevirtual #56                 // Method io/reactivex/rxjava3/internal/subscribers/InnerQueuedSubscriber.setDone:()V
      15: aload_0
      16: getfield      #6                  // Field errorMode:Lio/reactivex/rxjava3/internal/util/ErrorMode;
      19: getstatic     #57                 // Field io/reactivex/rxjava3/internal/util/ErrorMode.END:Lio/reactivex/rxjava3/internal/util/ErrorMode;
      22: if_acmpeq     34
      25: aload_0
      26: getfield      #17                 // Field upstream:Lorg/reactivestreams/Subscription;
      29: invokeinterface #32,  1           // InterfaceMethod org/reactivestreams/Subscription.cancel:()V
      34: aload_0
      35: invokevirtual #43                 // Method drain:()V
      38: return

  public void innerComplete(io.reactivex.rxjava3.internal.subscribers.InnerQueuedSubscriber<R>);
    Code:
       0: aload_1
       1: invokevirtual #56                 // Method io/reactivex/rxjava3/internal/subscribers/InnerQueuedSubscriber.setDone:()V
       4: aload_0
       5: invokevirtual #43                 // Method drain:()V
       8: return

  public void drain();
    Code:
       0: aload_0
       1: invokevirtual #45                 // Method getAndIncrement:()I
       4: ifeq          8
       7: return
       8: iconst_1
       9: istore_1
      10: aload_0
      11: getfield      #48                 // Field current:Lio/reactivex/rxjava3/internal/subscribers/InnerQueuedSubscriber;
      14: astore_2
      15: aload_0
      16: getfield      #2                  // Field downstream:Lorg/reactivestreams/Subscriber;
      19: astore_3
      20: aload_0
      21: getfield      #6                  // Field errorMode:Lio/reactivex/rxjava3/internal/util/ErrorMode;
      24: astore        4
      26: aload_0
      27: getfield      #16                 // Field requested:Ljava/util/concurrent/atomic/AtomicLong;
      30: invokevirtual #58                 // Method java/util/concurrent/atomic/AtomicLong.get:()J
      33: lstore        5
      35: lconst_0
      36: lstore        7
      38: aload_2
      39: ifnonnull     130
      42: aload         4
      44: getstatic     #57                 // Field io/reactivex/rxjava3/internal/util/ErrorMode.END:Lio/reactivex/rxjava3/internal/util/ErrorMode;
      47: if_acmpeq     83
      50: aload_0
      51: getfield      #13                 // Field errors:Lio/reactivex/rxjava3/internal/util/AtomicThrowable;
      54: invokevirtual #59                 // Method io/reactivex/rxjava3/internal/util/AtomicThrowable.get:()Ljava/lang/Object;
      57: checkcast     #30                 // class java/lang/Throwable
      60: astore        9
      62: aload         9
      64: ifnull        83
      67: aload_0
      68: invokevirtual #46                 // Method cancelAll:()V
      71: aload_0
      72: getfield      #13                 // Field errors:Lio/reactivex/rxjava3/internal/util/AtomicThrowable;
      75: aload_0
      76: getfield      #2                  // Field downstream:Lorg/reactivestreams/Subscriber;
      79: invokevirtual #60                 // Method io/reactivex/rxjava3/internal/util/AtomicThrowable.tryTerminateConsumer:(Lorg/reactivestreams/Subscriber;)V
      82: return
      83: aload_0
      84: getfield      #42                 // Field done:Z
      87: istore        9
      89: aload_0
      90: getfield      #10                 // Field subscribers:Lio/reactivex/rxjava3/operators/SpscLinkedArrayQueue;
      93: invokevirtual #49                 // Method io/reactivex/rxjava3/operators/SpscLinkedArrayQueue.poll:()Ljava/lang/Object;
      96: checkcast     #34                 // class io/reactivex/rxjava3/internal/subscribers/InnerQueuedSubscriber
      99: astore_2
     100: iload         9
     102: ifeq          121
     105: aload_2
     106: ifnonnull     121
     109: aload_0
     110: getfield      #13                 // Field errors:Lio/reactivex/rxjava3/internal/util/AtomicThrowable;
     113: aload_0
     114: getfield      #2                  // Field downstream:Lorg/reactivestreams/Subscriber;
     117: invokevirtual #60                 // Method io/reactivex/rxjava3/internal/util/AtomicThrowable.tryTerminateConsumer:(Lorg/reactivestreams/Subscriber;)V
     120: return
     121: aload_2
     122: ifnull        130
     125: aload_0
     126: aload_2
     127: putfield      #48                 // Field current:Lio/reactivex/rxjava3/internal/subscribers/InnerQueuedSubscriber;
     130: iconst_0
     131: istore        9
     133: aload_2
     134: ifnull        455
     137: aload_2
     138: invokevirtual #52                 // Method io/reactivex/rxjava3/internal/subscribers/InnerQueuedSubscriber.queue:()Lio/reactivex/rxjava3/operators/SimpleQueue;
     141: astore        10
     143: aload         10
     145: ifnull        455
     148: lload         7
     150: lload         5
     152: lcmp
     153: ifeq          340
     156: aload_0
     157: getfield      #36                 // Field cancelled:Z
     160: ifeq          168
     163: aload_0
     164: invokevirtual #46                 // Method cancelAll:()V
     167: return
     168: aload         4
     170: getstatic     #61                 // Field io/reactivex/rxjava3/internal/util/ErrorMode.IMMEDIATE:Lio/reactivex/rxjava3/internal/util/ErrorMode;
     173: if_acmpne     218
     176: aload_0
     177: getfield      #13                 // Field errors:Lio/reactivex/rxjava3/internal/util/AtomicThrowable;
     180: invokevirtual #59                 // Method io/reactivex/rxjava3/internal/util/AtomicThrowable.get:()Ljava/lang/Object;
     183: checkcast     #30                 // class java/lang/Throwable
     186: astore        11
     188: aload         11
     190: ifnull        218
     193: aload_0
     194: aconst_null
     195: putfield      #48                 // Field current:Lio/reactivex/rxjava3/internal/subscribers/InnerQueuedSubscriber;
     198: aload_2
     199: invokevirtual #39                 // Method io/reactivex/rxjava3/internal/subscribers/InnerQueuedSubscriber.cancel:()V
     202: aload_0
     203: invokevirtual #46                 // Method cancelAll:()V
     206: aload_0
     207: getfield      #13                 // Field errors:Lio/reactivex/rxjava3/internal/util/AtomicThrowable;
     210: aload_0
     211: getfield      #2                  // Field downstream:Lorg/reactivestreams/Subscriber;
     214: invokevirtual #60                 // Method io/reactivex/rxjava3/internal/util/AtomicThrowable.tryTerminateConsumer:(Lorg/reactivestreams/Subscriber;)V
     217: return
     218: aload_2
     219: invokevirtual #62                 // Method io/reactivex/rxjava3/internal/subscribers/InnerQueuedSubscriber.isDone:()Z
     222: istore        11
     224: aload         10
     226: invokeinterface #63,  1           // InterfaceMethod io/reactivex/rxjava3/operators/SimpleQueue.poll:()Ljava/lang/Object;
     231: astore        12
     233: goto          265
     236: astore        13
     238: aload         13
     240: invokestatic  #31                 // Method io/reactivex/rxjava3/exceptions/Exceptions.throwIfFatal:(Ljava/lang/Throwable;)V
     243: aload_0
     244: aconst_null
     245: putfield      #48                 // Field current:Lio/reactivex/rxjava3/internal/subscribers/InnerQueuedSubscriber;
     248: aload_2
     249: invokevirtual #39                 // Method io/reactivex/rxjava3/internal/subscribers/InnerQueuedSubscriber.cancel:()V
     252: aload_0
     253: invokevirtual #46                 // Method cancelAll:()V
     256: aload_3
     257: aload         13
     259: invokeinterface #64,  2           // InterfaceMethod org/reactivestreams/Subscriber.onError:(Ljava/lang/Throwable;)V
     264: return
     265: aload         12
     267: ifnonnull     274
     270: iconst_1
     271: goto          275
     274: iconst_0
     275: istore        13
     277: iload         11
     279: ifeq          310
     282: iload         13
     284: ifeq          310
     287: aconst_null
     288: astore_2
     289: aload_0
     290: aconst_null
     291: putfield      #48                 // Field current:Lio/reactivex/rxjava3/internal/subscribers/InnerQueuedSubscriber;
     294: aload_0
     295: getfield      #17                 // Field upstream:Lorg/reactivestreams/Subscription;
     298: lconst_1
     299: invokeinterface #25,  3           // InterfaceMethod org/reactivestreams/Subscription.request:(J)V
     304: iconst_1
     305: istore        9
     307: goto          340
     310: iload         13
     312: ifeq          318
     315: goto          340
     318: aload_3
     319: aload         12
     321: invokeinterface #65,  2           // InterfaceMethod org/reactivestreams/Subscriber.onNext:(Ljava/lang/Object;)V
     326: lload         7
     328: lconst_1
     329: ladd
     330: lstore        7
     332: aload_2
     333: lconst_1
     334: invokevirtual #66                 // Method io/reactivex/rxjava3/internal/subscribers/InnerQueuedSubscriber.request:(J)V
     337: goto          148
     340: lload         7
     342: lload         5
     344: lcmp
     345: ifne          455
     348: aload_0
     349: getfield      #36                 // Field cancelled:Z
     352: ifeq          360
     355: aload_0
     356: invokevirtual #46                 // Method cancelAll:()V
     359: return
     360: aload         4
     362: getstatic     #61                 // Field io/reactivex/rxjava3/internal/util/ErrorMode.IMMEDIATE:Lio/reactivex/rxjava3/internal/util/ErrorMode;
     365: if_acmpne     410
     368: aload_0
     369: getfield      #13                 // Field errors:Lio/reactivex/rxjava3/internal/util/AtomicThrowable;
     372: invokevirtual #59                 // Method io/reactivex/rxjava3/internal/util/AtomicThrowable.get:()Ljava/lang/Object;
     375: checkcast     #30                 // class java/lang/Throwable
     378: astore        11
     380: aload         11
     382: ifnull        410
     385: aload_0
     386: aconst_null
     387: putfield      #48                 // Field current:Lio/reactivex/rxjava3/internal/subscribers/InnerQueuedSubscriber;
     390: aload_2
     391: invokevirtual #39                 // Method io/reactivex/rxjava3/internal/subscribers/InnerQueuedSubscriber.cancel:()V
     394: aload_0
     395: invokevirtual #46                 // Method cancelAll:()V
     398: aload_0
     399: getfield      #13                 // Field errors:Lio/reactivex/rxjava3/internal/util/AtomicThrowable;
     402: aload_0
     403: getfield      #2                  // Field downstream:Lorg/reactivestreams/Subscriber;
     406: invokevirtual #60                 // Method io/reactivex/rxjava3/internal/util/AtomicThrowable.tryTerminateConsumer:(Lorg/reactivestreams/Subscriber;)V
     409: return
     410: aload_2
     411: invokevirtual #62                 // Method io/reactivex/rxjava3/internal/subscribers/InnerQueuedSubscriber.isDone:()Z
     414: istore        11
     416: aload         10
     418: invokeinterface #67,  1           // InterfaceMethod io/reactivex/rxjava3/operators/SimpleQueue.isEmpty:()Z
     423: istore        12
     425: iload         11
     427: ifeq          455
     430: iload         12
     432: ifeq          455
     435: aconst_null
     436: astore_2
     437: aload_0
     438: aconst_null
     439: putfield      #48                 // Field current:Lio/reactivex/rxjava3/internal/subscribers/InnerQueuedSubscriber;
     442: aload_0
     443: getfield      #17                 // Field upstream:Lorg/reactivestreams/Subscription;
     446: lconst_1
     447: invokeinterface #25,  3           // InterfaceMethod org/reactivestreams/Subscription.request:(J)V
     452: iconst_1
     453: istore        9
     455: lload         7
     457: lconst_0
     458: lcmp
     459: ifeq          482
     462: lload         5
     464: ldc2_w        #23                 // long 9223372036854775807l
     467: lcmp
     468: ifeq          482
     471: aload_0
     472: getfield      #16                 // Field requested:Ljava/util/concurrent/atomic/AtomicLong;
     475: lload         7
     477: lneg
     478: invokevirtual #68                 // Method java/util/concurrent/atomic/AtomicLong.addAndGet:(J)J
     481: pop2
     482: iload         9
     484: ifeq          490
     487: goto          26
     490: aload_0
     491: iload_1
     492: ineg
     493: invokevirtual #69                 // Method addAndGet:(I)I
     496: istore_1
     497: iload_1
     498: ifne          504
     501: goto          507
     504: goto          26
     507: return
    Exception table:
       from    to  target type
         224   233   236   Class java/lang/Throwable
}
