Compiled from "FlowableMergeWithMaybe.java"
public final class io.reactivex.rxjava3.internal.operators.flowable.FlowableMergeWithMaybe<T> extends io.reactivex.rxjava3.internal.operators.flowable.AbstractFlowableWithUpstream<T, T> {
  final io.reactivex.rxjava3.core.MaybeSource<? extends T> other;

  public io.reactivex.rxjava3.internal.operators.flowable.FlowableMergeWithMaybe(io.reactivex.rxjava3.core.Flowable<T>, io.reactivex.rxjava3.core.MaybeSource<? extends T>);
    Code:
       0: aload_0
       1: aload_1
       2: invokespecial #1                  // Method io/reactivex/rxjava3/internal/operators/flowable/AbstractFlowableWithUpstream."<init>":(Lio/reactivex/rxjava3/core/Flowable;)V
       5: aload_0
       6: aload_2
       7: putfield      #2                  // Field other:Lio/reactivex/rxjava3/core/MaybeSource;
      10: return

  protected void subscribeActual(org.reactivestreams.Subscriber<? super T>);
    Code:
       0: new           #3                  // class io/reactivex/rxjava3/internal/operators/flowable/FlowableMergeWithMaybe$MergeWithObserver
       3: dup
       4: aload_1
       5: invokespecial #4                  // Method io/reactivex/rxjava3/internal/operators/flowable/FlowableMergeWithMaybe$MergeWithObserver."<init>":(Lorg/reactivestreams/Subscriber;)V
       8: astore_2
       9: aload_1
      10: aload_2
      11: invokeinterface #5,  2            // InterfaceMethod org/reactivestreams/Subscriber.onSubscribe:(Lorg/reactivestreams/Subscription;)V
      16: aload_0
      17: getfield      #6                  // Field source:Lio/reactivex/rxjava3/core/Flowable;
      20: aload_2
      21: invokevirtual #7                  // Method io/reactivex/rxjava3/core/Flowable.subscribe:(Lio/reactivex/rxjava3/core/FlowableSubscriber;)V
      24: aload_0
      25: getfield      #2                  // Field other:Lio/reactivex/rxjava3/core/MaybeSource;
      28: aload_2
      29: getfield      #8                  // Field io/reactivex/rxjava3/internal/operators/flowable/FlowableMergeWithMaybe$MergeWithObserver.otherObserver:Lio/reactivex/rxjava3/internal/operators/flowable/FlowableMergeWithMaybe$MergeWithObserver$OtherObserver;
      32: invokeinterface #9,  2            // InterfaceMethod io/reactivex/rxjava3/core/MaybeSource.subscribe:(Lio/reactivex/rxjava3/core/MaybeObserver;)V
      37: return
}
