Compiled from "FlowableWindowBoundary.java"
final class io.reactivex.rxjava3.internal.operators.flowable.FlowableWindowBoundary$WindowBoundaryInnerSubscriber<T, B> extends io.reactivex.rxjava3.subscribers.DisposableSubscriber<B> {
  final io.reactivex.rxjava3.internal.operators.flowable.FlowableWindowBoundary$WindowBoundaryMainSubscriber<T, B> parent;

  boolean done;

  io.reactivex.rxjava3.internal.operators.flowable.FlowableWindowBoundary$WindowBoundaryInnerSubscriber(io.reactivex.rxjava3.internal.operators.flowable.FlowableWindowBoundary$WindowBoundaryMainSubscriber<T, B>);
    Code:
       0: aload_0
       1: invokespecial #1                  // Method io/reactivex/rxjava3/subscribers/DisposableSubscriber."<init>":()V
       4: aload_0
       5: aload_1
       6: putfield      #2                  // Field parent:Lio/reactivex/rxjava3/internal/operators/flowable/FlowableWindowBoundary$WindowBoundaryMainSubscriber;
       9: return

  public void onNext(B);
    Code:
       0: aload_0
       1: getfield      #3                  // Field done:Z
       4: ifeq          8
       7: return
       8: aload_0
       9: getfield      #2                  // Field parent:Lio/reactivex/rxjava3/internal/operators/flowable/FlowableWindowBoundary$WindowBoundaryMainSubscriber;
      12: invokevirtual #4                  // Method io/reactivex/rxjava3/internal/operators/flowable/FlowableWindowBoundary$WindowBoundaryMainSubscriber.innerNext:()V
      15: return

  public void onError(java.lang.Throwable);
    Code:
       0: aload_0
       1: getfield      #3                  // Field done:Z
       4: ifeq          12
       7: aload_1
       8: invokestatic  #5                  // Method io/reactivex/rxjava3/plugins/RxJavaPlugins.onError:(Ljava/lang/Throwable;)V
      11: return
      12: aload_0
      13: iconst_1
      14: putfield      #3                  // Field done:Z
      17: aload_0
      18: getfield      #2                  // Field parent:Lio/reactivex/rxjava3/internal/operators/flowable/FlowableWindowBoundary$WindowBoundaryMainSubscriber;
      21: aload_1
      22: invokevirtual #6                  // Method io/reactivex/rxjava3/internal/operators/flowable/FlowableWindowBoundary$WindowBoundaryMainSubscriber.innerError:(Ljava/lang/Throwable;)V
      25: return

  public void onComplete();
    Code:
       0: aload_0
       1: getfield      #3                  // Field done:Z
       4: ifeq          8
       7: return
       8: aload_0
       9: iconst_1
      10: putfield      #3                  // Field done:Z
      13: aload_0
      14: getfield      #2                  // Field parent:Lio/reactivex/rxjava3/internal/operators/flowable/FlowableWindowBoundary$WindowBoundaryMainSubscriber;
      17: invokevirtual #7                  // Method io/reactivex/rxjava3/internal/operators/flowable/FlowableWindowBoundary$WindowBoundaryMainSubscriber.innerComplete:()V
      20: return
}
