Compiled from "FlowableReplay.java"
final class io.reactivex.rxjava3.internal.operators.flowable.FlowableReplay$ReplayBufferSupplier<T> implements io.reactivex.rxjava3.functions.Supplier<io.reactivex.rxjava3.internal.operators.flowable.FlowableReplay$ReplayBuffer<T>> {
  final int bufferSize;

  final boolean eagerTruncate;

  io.reactivex.rxjava3.internal.operators.flowable.FlowableReplay$ReplayBufferSupplier(int, boolean);
    Code:
       0: aload_0
       1: invokespecial #1                  // Method java/lang/Object."<init>":()V
       4: aload_0
       5: iload_1
       6: putfield      #2                  // Field bufferSize:I
       9: aload_0
      10: iload_2
      11: putfield      #3                  // Field eagerTruncate:Z
      14: return

  public io.reactivex.rxjava3.internal.operators.flowable.FlowableReplay$ReplayBuffer<T> get();
    Code:
       0: new           #4                  // class io/reactivex/rxjava3/internal/operators/flowable/FlowableReplay$SizeBoundReplayBuffer
       3: dup
       4: aload_0
       5: getfield      #2                  // Field bufferSize:I
       8: aload_0
       9: getfield      #3                  // Field eagerTruncate:Z
      12: invokespecial #5                  // Method io/reactivex/rxjava3/internal/operators/flowable/FlowableReplay$SizeBoundReplayBuffer."<init>":(IZ)V
      15: areturn

  public java.lang.Object get() throws java.lang.Throwable;
    Code:
       0: aload_0
       1: invokevirtual #6                  // Method get:()Lio/reactivex/rxjava3/internal/operators/flowable/FlowableReplay$ReplayBuffer;
       4: areturn
}
