Compiled from "FlowableMaterialize.java"
final class io.reactivex.rxjava3.internal.operators.flowable.FlowableMaterialize$MaterializeSubscriber<T> extends io.reactivex.rxjava3.internal.subscribers.SinglePostCompleteSubscriber<T, io.reactivex.rxjava3.core.Notification<T>> {
  private static final long serialVersionUID;

  io.reactivex.rxjava3.internal.operators.flowable.FlowableMaterialize$MaterializeSubscriber(org.reactivestreams.Subscriber<? super io.reactivex.rxjava3.core.Notification<T>>);
    Code:
       0: aload_0
       1: aload_1
       2: invokespecial #1                  // Method io/reactivex/rxjava3/internal/subscribers/SinglePostCompleteSubscriber."<init>":(Lorg/reactivestreams/Subscriber;)V
       5: return

  public void onNext(T);
    Code:
       0: aload_0
       1: dup
       2: getfield      #2                  // Field produced:J
       5: lconst_1
       6: ladd
       7: putfield      #2                  // Field produced:J
      10: aload_0
      11: getfield      #3                  // Field downstream:Lorg/reactivestreams/Subscriber;
      14: aload_1
      15: invokestatic  #4                  // Method io/reactivex/rxjava3/core/Notification.createOnNext:(Ljava/lang/Object;)Lio/reactivex/rxjava3/core/Notification;
      18: invokeinterface #5,  2            // InterfaceMethod org/reactivestreams/Subscriber.onNext:(Ljava/lang/Object;)V
      23: return

  public void onError(java.lang.Throwable);
    Code:
       0: aload_0
       1: aload_1
       2: invokestatic  #6                  // Method io/reactivex/rxjava3/core/Notification.createOnError:(Ljava/lang/Throwable;)Lio/reactivex/rxjava3/core/Notification;
       5: invokevirtual #7                  // Method complete:(Ljava/lang/Object;)V
       8: return

  public void onComplete();
    Code:
       0: aload_0
       1: invokestatic  #8                  // Method io/reactivex/rxjava3/core/Notification.createOnComplete:()Lio/reactivex/rxjava3/core/Notification;
       4: invokevirtual #7                  // Method complete:(Ljava/lang/Object;)V
       7: return

  protected void onDrop(io.reactivex.rxjava3.core.Notification<T>);
    Code:
       0: aload_1
       1: invokevirtual #9                  // Method io/reactivex/rxjava3/core/Notification.isOnError:()Z
       4: ifeq          14
       7: aload_1
       8: invokevirtual #10                 // Method io/reactivex/rxjava3/core/Notification.getError:()Ljava/lang/Throwable;
      11: invokestatic  #11                 // Method io/reactivex/rxjava3/plugins/RxJavaPlugins.onError:(Ljava/lang/Throwable;)V
      14: return

  protected void onDrop(java.lang.Object);
    Code:
       0: aload_0
       1: aload_1
       2: checkcast     #12                 // class io/reactivex/rxjava3/core/Notification
       5: invokevirtual #13                 // Method onDrop:(Lio/reactivex/rxjava3/core/Notification;)V
       8: return
}
