Compiled from "FlowableTimeout.java"
final class io.reactivex.rxjava3.internal.operators.flowable.FlowableTimeout$TimeoutConsumer extends java.util.concurrent.atomic.AtomicReference<org.reactivestreams.Subscription> implements io.reactivex.rxjava3.core.FlowableSubscriber<java.lang.Object>, io.reactivex.rxjava3.disposables.Disposable {
  private static final long serialVersionUID;

  final io.reactivex.rxjava3.internal.operators.flowable.FlowableTimeout$TimeoutSelectorSupport parent;

  final long idx;

  io.reactivex.rxjava3.internal.operators.flowable.FlowableTimeout$TimeoutConsumer(long, io.reactivex.rxjava3.internal.operators.flowable.FlowableTimeout$TimeoutSelectorSupport);
    Code:
       0: aload_0
       1: invokespecial #1                  // Method java/util/concurrent/atomic/AtomicReference."<init>":()V
       4: aload_0
       5: lload_1
       6: putfield      #2                  // Field idx:J
       9: aload_0
      10: aload_3
      11: putfield      #3                  // Field parent:Lio/reactivex/rxjava3/internal/operators/flowable/FlowableTimeout$TimeoutSelectorSupport;
      14: return

  public void onSubscribe(org.reactivestreams.Subscription);
    Code:
       0: aload_0
       1: aload_1
       2: ldc2_w        #5                  // long 9223372036854775807l
       5: invokestatic  #7                  // Method io/reactivex/rxjava3/internal/subscriptions/SubscriptionHelper.setOnce:(Ljava/util/concurrent/atomic/AtomicReference;Lorg/reactivestreams/Subscription;J)Z
       8: pop
       9: return

  public void onNext(java.lang.Object);
    Code:
       0: aload_0
       1: invokevirtual #8                  // Method get:()Ljava/lang/Object;
       4: checkcast     #9                  // class org/reactivestreams/Subscription
       7: astore_2
       8: aload_2
       9: getstatic     #10                 // Field io/reactivex/rxjava3/internal/subscriptions/SubscriptionHelper.CANCELLED:Lio/reactivex/rxjava3/internal/subscriptions/SubscriptionHelper;
      12: if_acmpeq     41
      15: aload_2
      16: invokeinterface #11,  1           // InterfaceMethod org/reactivestreams/Subscription.cancel:()V
      21: aload_0
      22: getstatic     #10                 // Field io/reactivex/rxjava3/internal/subscriptions/SubscriptionHelper.CANCELLED:Lio/reactivex/rxjava3/internal/subscriptions/SubscriptionHelper;
      25: invokevirtual #12                 // Method lazySet:(Ljava/lang/Object;)V
      28: aload_0
      29: getfield      #3                  // Field parent:Lio/reactivex/rxjava3/internal/operators/flowable/FlowableTimeout$TimeoutSelectorSupport;
      32: aload_0
      33: getfield      #2                  // Field idx:J
      36: invokeinterface #13,  3           // InterfaceMethod io/reactivex/rxjava3/internal/operators/flowable/FlowableTimeout$TimeoutSelectorSupport.onTimeout:(J)V
      41: return

  public void onError(java.lang.Throwable);
    Code:
       0: aload_0
       1: invokevirtual #8                  // Method get:()Ljava/lang/Object;
       4: getstatic     #10                 // Field io/reactivex/rxjava3/internal/subscriptions/SubscriptionHelper.CANCELLED:Lio/reactivex/rxjava3/internal/subscriptions/SubscriptionHelper;
       7: if_acmpeq     34
      10: aload_0
      11: getstatic     #10                 // Field io/reactivex/rxjava3/internal/subscriptions/SubscriptionHelper.CANCELLED:Lio/reactivex/rxjava3/internal/subscriptions/SubscriptionHelper;
      14: invokevirtual #12                 // Method lazySet:(Ljava/lang/Object;)V
      17: aload_0
      18: getfield      #3                  // Field parent:Lio/reactivex/rxjava3/internal/operators/flowable/FlowableTimeout$TimeoutSelectorSupport;
      21: aload_0
      22: getfield      #2                  // Field idx:J
      25: aload_1
      26: invokeinterface #14,  4           // InterfaceMethod io/reactivex/rxjava3/internal/operators/flowable/FlowableTimeout$TimeoutSelectorSupport.onTimeoutError:(JLjava/lang/Throwable;)V
      31: goto          38
      34: aload_1
      35: invokestatic  #15                 // Method io/reactivex/rxjava3/plugins/RxJavaPlugins.onError:(Ljava/lang/Throwable;)V
      38: return

  public void onComplete();
    Code:
       0: aload_0
       1: invokevirtual #8                  // Method get:()Ljava/lang/Object;
       4: getstatic     #10                 // Field io/reactivex/rxjava3/internal/subscriptions/SubscriptionHelper.CANCELLED:Lio/reactivex/rxjava3/internal/subscriptions/SubscriptionHelper;
       7: if_acmpeq     30
      10: aload_0
      11: getstatic     #10                 // Field io/reactivex/rxjava3/internal/subscriptions/SubscriptionHelper.CANCELLED:Lio/reactivex/rxjava3/internal/subscriptions/SubscriptionHelper;
      14: invokevirtual #12                 // Method lazySet:(Ljava/lang/Object;)V
      17: aload_0
      18: getfield      #3                  // Field parent:Lio/reactivex/rxjava3/internal/operators/flowable/FlowableTimeout$TimeoutSelectorSupport;
      21: aload_0
      22: getfield      #2                  // Field idx:J
      25: invokeinterface #13,  3           // InterfaceMethod io/reactivex/rxjava3/internal/operators/flowable/FlowableTimeout$TimeoutSelectorSupport.onTimeout:(J)V
      30: return

  public void dispose();
    Code:
       0: aload_0
       1: invokestatic  #16                 // Method io/reactivex/rxjava3/internal/subscriptions/SubscriptionHelper.cancel:(Ljava/util/concurrent/atomic/AtomicReference;)Z
       4: pop
       5: return

  public boolean isDisposed();
    Code:
       0: aload_0
       1: invokevirtual #8                  // Method get:()Ljava/lang/Object;
       4: getstatic     #10                 // Field io/reactivex/rxjava3/internal/subscriptions/SubscriptionHelper.CANCELLED:Lio/reactivex/rxjava3/internal/subscriptions/SubscriptionHelper;
       7: if_acmpne     14
      10: iconst_1
      11: goto          15
      14: iconst_0
      15: ireturn
}
