Compiled from "FlowableFlatMapMaybePublisher.java"
public final class io.reactivex.rxjava3.internal.operators.flowable.FlowableFlatMapMaybePublisher<T, R> extends io.reactivex.rxjava3.core.Flowable<R> {
  final org.reactivestreams.Publisher<T> source;

  final io.reactivex.rxjava3.functions.Function<? super T, ? extends io.reactivex.rxjava3.core.MaybeSource<? extends R>> mapper;

  final boolean delayErrors;

  final int maxConcurrency;

  public io.reactivex.rxjava3.internal.operators.flowable.FlowableFlatMapMaybePublisher(org.reactivestreams.Publisher<T>, io.reactivex.rxjava3.functions.Function<? super T, ? extends io.reactivex.rxjava3.core.MaybeSource<? extends R>>, boolean, int);
    Code:
       0: aload_0
       1: invokespecial #1                  // Method io/reactivex/rxjava3/core/Flowable."<init>":()V
       4: aload_0
       5: aload_1
       6: putfield      #2                  // Field source:Lorg/reactivestreams/Publisher;
       9: aload_0
      10: aload_2
      11: putfield      #3                  // Field mapper:Lio/reactivex/rxjava3/functions/Function;
      14: aload_0
      15: iload_3
      16: putfield      #4                  // Field delayErrors:Z
      19: aload_0
      20: iload         4
      22: putfield      #5                  // Field maxConcurrency:I
      25: return

  protected void subscribeActual(org.reactivestreams.Subscriber<? super R>);
    Code:
       0: aload_0
       1: getfield      #2                  // Field source:Lorg/reactivestreams/Publisher;
       4: new           #6                  // class io/reactivex/rxjava3/internal/operators/flowable/FlowableFlatMapMaybe$FlatMapMaybeSubscriber
       7: dup
       8: aload_1
       9: aload_0
      10: getfield      #3                  // Field mapper:Lio/reactivex/rxjava3/functions/Function;
      13: aload_0
      14: getfield      #4                  // Field delayErrors:Z
      17: aload_0
      18: getfield      #5                  // Field maxConcurrency:I
      21: invokespecial #7                  // Method io/reactivex/rxjava3/internal/operators/flowable/FlowableFlatMapMaybe$FlatMapMaybeSubscriber."<init>":(Lorg/reactivestreams/Subscriber;Lio/reactivex/rxjava3/functions/Function;ZI)V
      24: invokeinterface #8,  2            // InterfaceMethod org/reactivestreams/Publisher.subscribe:(Lorg/reactivestreams/Subscriber;)V
      29: return
}
