Compiled from "FlowableWithLatestFromMany.java"
final class io.reactivex.rxjava3.internal.operators.flowable.FlowableWithLatestFromMany$WithLatestFromSubscriber<T, R> extends java.util.concurrent.atomic.AtomicInteger implements io.reactivex.rxjava3.operators.ConditionalSubscriber<T>, org.reactivestreams.Subscription {
  private static final long serialVersionUID;

  final org.reactivestreams.Subscriber<? super R> downstream;

  final io.reactivex.rxjava3.functions.Function<? super java.lang.Object[], R> combiner;

  final io.reactivex.rxjava3.internal.operators.flowable.FlowableWithLatestFromMany$WithLatestInnerSubscriber[] subscribers;

  final java.util.concurrent.atomic.AtomicReferenceArray<java.lang.Object> values;

  final java.util.concurrent.atomic.AtomicReference<org.reactivestreams.Subscription> upstream;

  final java.util.concurrent.atomic.AtomicLong requested;

  final io.reactivex.rxjava3.internal.util.AtomicThrowable error;

  volatile boolean done;

  io.reactivex.rxjava3.internal.operators.flowable.FlowableWithLatestFromMany$WithLatestFromSubscriber(org.reactivestreams.Subscriber<? super R>, io.reactivex.rxjava3.functions.Function<? super java.lang.Object[], R>, int);
    Code:
       0: aload_0
       1: invokespecial #1                  // Method java/util/concurrent/atomic/AtomicInteger."<init>":()V
       4: aload_0
       5: aload_1
       6: putfield      #2                  // Field downstream:Lorg/reactivestreams/Subscriber;
       9: aload_0
      10: aload_2
      11: putfield      #3                  // Field combiner:Lio/reactivex/rxjava3/functions/Function;
      14: iload_3
      15: anewarray     #4                  // class io/reactivex/rxjava3/internal/operators/flowable/FlowableWithLatestFromMany$WithLatestInnerSubscriber
      18: astore        4
      20: iconst_0
      21: istore        5
      23: iload         5
      25: iload_3
      26: if_icmpge     50
      29: aload         4
      31: iload         5
      33: new           #4                  // class io/reactivex/rxjava3/internal/operators/flowable/FlowableWithLatestFromMany$WithLatestInnerSubscriber
      36: dup
      37: aload_0
      38: iload         5
      40: invokespecial #5                  // Method io/reactivex/rxjava3/internal/operators/flowable/FlowableWithLatestFromMany$WithLatestInnerSubscriber."<init>":(Lio/reactivex/rxjava3/internal/operators/flowable/FlowableWithLatestFromMany$WithLatestFromSubscriber;I)V
      43: aastore
      44: iinc          5, 1
      47: goto          23
      50: aload_0
      51: aload         4
      53: putfield      #6                  // Field subscribers:[Lio/reactivex/rxjava3/internal/operators/flowable/FlowableWithLatestFromMany$WithLatestInnerSubscriber;
      56: aload_0
      57: new           #7                  // class java/util/concurrent/atomic/AtomicReferenceArray
      60: dup
      61: iload_3
      62: invokespecial #8                  // Method java/util/concurrent/atomic/AtomicReferenceArray."<init>":(I)V
      65: putfield      #9                  // Field values:Ljava/util/concurrent/atomic/AtomicReferenceArray;
      68: aload_0
      69: new           #10                 // class java/util/concurrent/atomic/AtomicReference
      72: dup
      73: invokespecial #11                 // Method java/util/concurrent/atomic/AtomicReference."<init>":()V
      76: putfield      #12                 // Field upstream:Ljava/util/concurrent/atomic/AtomicReference;
      79: aload_0
      80: new           #13                 // class java/util/concurrent/atomic/AtomicLong
      83: dup
      84: invokespecial #14                 // Method java/util/concurrent/atomic/AtomicLong."<init>":()V
      87: putfield      #15                 // Field requested:Ljava/util/concurrent/atomic/AtomicLong;
      90: aload_0
      91: new           #16                 // class io/reactivex/rxjava3/internal/util/AtomicThrowable
      94: dup
      95: invokespecial #17                 // Method io/reactivex/rxjava3/internal/util/AtomicThrowable."<init>":()V
      98: putfield      #18                 // Field error:Lio/reactivex/rxjava3/internal/util/AtomicThrowable;
     101: return

  void subscribe(org.reactivestreams.Publisher<?>[], int);
    Code:
       0: aload_0
       1: getfield      #6                  // Field subscribers:[Lio/reactivex/rxjava3/internal/operators/flowable/FlowableWithLatestFromMany$WithLatestInnerSubscriber;
       4: astore_3
       5: aload_0
       6: getfield      #12                 // Field upstream:Ljava/util/concurrent/atomic/AtomicReference;
       9: astore        4
      11: iconst_0
      12: istore        5
      14: iload         5
      16: iload_2
      17: if_icmpge     51
      20: aload         4
      22: invokevirtual #19                 // Method java/util/concurrent/atomic/AtomicReference.get:()Ljava/lang/Object;
      25: getstatic     #20                 // Field io/reactivex/rxjava3/internal/subscriptions/SubscriptionHelper.CANCELLED:Lio/reactivex/rxjava3/internal/subscriptions/SubscriptionHelper;
      28: if_acmpne     32
      31: return
      32: aload_1
      33: iload         5
      35: aaload
      36: aload_3
      37: iload         5
      39: aaload
      40: invokeinterface #21,  2           // InterfaceMethod org/reactivestreams/Publisher.subscribe:(Lorg/reactivestreams/Subscriber;)V
      45: iinc          5, 1
      48: goto          14
      51: return

  public void onSubscribe(org.reactivestreams.Subscription);
    Code:
       0: aload_0
       1: getfield      #12                 // Field upstream:Ljava/util/concurrent/atomic/AtomicReference;
       4: aload_0
       5: getfield      #15                 // Field requested:Ljava/util/concurrent/atomic/AtomicLong;
       8: aload_1
       9: invokestatic  #22                 // Method io/reactivex/rxjava3/internal/subscriptions/SubscriptionHelper.deferredSetOnce:(Ljava/util/concurrent/atomic/AtomicReference;Ljava/util/concurrent/atomic/AtomicLong;Lorg/reactivestreams/Subscription;)Z
      12: pop
      13: return

  public void onNext(T);
    Code:
       0: aload_0
       1: aload_1
       2: invokevirtual #23                 // Method tryOnNext:(Ljava/lang/Object;)Z
       5: ifne          31
       8: aload_0
       9: getfield      #24                 // Field done:Z
      12: ifne          31
      15: aload_0
      16: getfield      #12                 // Field upstream:Ljava/util/concurrent/atomic/AtomicReference;
      19: invokevirtual #19                 // Method java/util/concurrent/atomic/AtomicReference.get:()Ljava/lang/Object;
      22: checkcast     #25                 // class org/reactivestreams/Subscription
      25: lconst_1
      26: invokeinterface #26,  3           // InterfaceMethod org/reactivestreams/Subscription.request:(J)V
      31: return

  public boolean tryOnNext(T);
    Code:
       0: aload_0
       1: getfield      #24                 // Field done:Z
       4: ifeq          9
       7: iconst_0
       8: ireturn
       9: aload_0
      10: getfield      #9                  // Field values:Ljava/util/concurrent/atomic/AtomicReferenceArray;
      13: astore_2
      14: aload_2
      15: invokevirtual #27                 // Method java/util/concurrent/atomic/AtomicReferenceArray.length:()I
      18: istore_3
      19: iload_3
      20: iconst_1
      21: iadd
      22: anewarray     #28                 // class java/lang/Object
      25: astore        4
      27: aload         4
      29: iconst_0
      30: aload_1
      31: aastore
      32: iconst_0
      33: istore        5
      35: iload         5
      37: iload_3
      38: if_icmpge     71
      41: aload_2
      42: iload         5
      44: invokevirtual #29                 // Method java/util/concurrent/atomic/AtomicReferenceArray.get:(I)Ljava/lang/Object;
      47: astore        6
      49: aload         6
      51: ifnonnull     56
      54: iconst_0
      55: ireturn
      56: aload         4
      58: iload         5
      60: iconst_1
      61: iadd
      62: aload         6
      64: aastore
      65: iinc          5, 1
      68: goto          35
      71: aload_0
      72: getfield      #3                  // Field combiner:Lio/reactivex/rxjava3/functions/Function;
      75: aload         4
      77: invokeinterface #30,  2           // InterfaceMethod io/reactivex/rxjava3/functions/Function.apply:(Ljava/lang/Object;)Ljava/lang/Object;
      82: ldc           #31                 // String The combiner returned a null value
      84: invokestatic  #32                 // Method java/util/Objects.requireNonNull:(Ljava/lang/Object;Ljava/lang/String;)Ljava/lang/Object;
      87: astore        5
      89: goto          111
      92: astore        6
      94: aload         6
      96: invokestatic  #34                 // Method io/reactivex/rxjava3/exceptions/Exceptions.throwIfFatal:(Ljava/lang/Throwable;)V
      99: aload_0
     100: invokevirtual #35                 // Method cancel:()V
     103: aload_0
     104: aload         6
     106: invokevirtual #36                 // Method onError:(Ljava/lang/Throwable;)V
     109: iconst_0
     110: ireturn
     111: aload_0
     112: getfield      #2                  // Field downstream:Lorg/reactivestreams/Subscriber;
     115: aload         5
     117: aload_0
     118: aload_0
     119: getfield      #18                 // Field error:Lio/reactivex/rxjava3/internal/util/AtomicThrowable;
     122: invokestatic  #37                 // Method io/reactivex/rxjava3/internal/util/HalfSerializer.onNext:(Lorg/reactivestreams/Subscriber;Ljava/lang/Object;Ljava/util/concurrent/atomic/AtomicInteger;Lio/reactivex/rxjava3/internal/util/AtomicThrowable;)Z
     125: pop
     126: iconst_1
     127: ireturn
    Exception table:
       from    to  target type
          71    89    92   Class java/lang/Throwable

  public void onError(java.lang.Throwable);
    Code:
       0: aload_0
       1: getfield      #24                 // Field done:Z
       4: ifeq          12
       7: aload_1
       8: invokestatic  #38                 // Method io/reactivex/rxjava3/plugins/RxJavaPlugins.onError:(Ljava/lang/Throwable;)V
      11: return
      12: aload_0
      13: iconst_1
      14: putfield      #24                 // Field done:Z
      17: aload_0
      18: iconst_m1
      19: invokevirtual #39                 // Method cancelAllBut:(I)V
      22: aload_0
      23: getfield      #2                  // Field downstream:Lorg/reactivestreams/Subscriber;
      26: aload_1
      27: aload_0
      28: aload_0
      29: getfield      #18                 // Field error:Lio/reactivex/rxjava3/internal/util/AtomicThrowable;
      32: invokestatic  #40                 // Method io/reactivex/rxjava3/internal/util/HalfSerializer.onError:(Lorg/reactivestreams/Subscriber;Ljava/lang/Throwable;Ljava/util/concurrent/atomic/AtomicInteger;Lio/reactivex/rxjava3/internal/util/AtomicThrowable;)V
      35: return

  public void onComplete();
    Code:
       0: aload_0
       1: getfield      #24                 // Field done:Z
       4: ifne          29
       7: aload_0
       8: iconst_1
       9: putfield      #24                 // Field done:Z
      12: aload_0
      13: iconst_m1
      14: invokevirtual #39                 // Method cancelAllBut:(I)V
      17: aload_0
      18: getfield      #2                  // Field downstream:Lorg/reactivestreams/Subscriber;
      21: aload_0
      22: aload_0
      23: getfield      #18                 // Field error:Lio/reactivex/rxjava3/internal/util/AtomicThrowable;
      26: invokestatic  #41                 // Method io/reactivex/rxjava3/internal/util/HalfSerializer.onComplete:(Lorg/reactivestreams/Subscriber;Ljava/util/concurrent/atomic/AtomicInteger;Lio/reactivex/rxjava3/internal/util/AtomicThrowable;)V
      29: return

  public void request(long);
    Code:
       0: aload_0
       1: getfield      #12                 // Field upstream:Ljava/util/concurrent/atomic/AtomicReference;
       4: aload_0
       5: getfield      #15                 // Field requested:Ljava/util/concurrent/atomic/AtomicLong;
       8: lload_1
       9: invokestatic  #42                 // Method io/reactivex/rxjava3/internal/subscriptions/SubscriptionHelper.deferredRequest:(Ljava/util/concurrent/atomic/AtomicReference;Ljava/util/concurrent/atomic/AtomicLong;J)V
      12: return

  public void cancel();
    Code:
       0: aload_0
       1: getfield      #12                 // Field upstream:Ljava/util/concurrent/atomic/AtomicReference;
       4: invokestatic  #43                 // Method io/reactivex/rxjava3/internal/subscriptions/SubscriptionHelper.cancel:(Ljava/util/concurrent/atomic/AtomicReference;)Z
       7: pop
       8: aload_0
       9: getfield      #6                  // Field subscribers:[Lio/reactivex/rxjava3/internal/operators/flowable/FlowableWithLatestFromMany$WithLatestInnerSubscriber;
      12: astore_1
      13: aload_1
      14: arraylength
      15: istore_2
      16: iconst_0
      17: istore_3
      18: iload_3
      19: iload_2
      20: if_icmpge     39
      23: aload_1
      24: iload_3
      25: aaload
      26: astore        4
      28: aload         4
      30: invokevirtual #44                 // Method io/reactivex/rxjava3/internal/operators/flowable/FlowableWithLatestFromMany$WithLatestInnerSubscriber.dispose:()V
      33: iinc          3, 1
      36: goto          18
      39: return

  void innerNext(int, java.lang.Object);
    Code:
       0: aload_0
       1: getfield      #9                  // Field values:Ljava/util/concurrent/atomic/AtomicReferenceArray;
       4: iload_1
       5: aload_2
       6: invokevirtual #45                 // Method java/util/concurrent/atomic/AtomicReferenceArray.set:(ILjava/lang/Object;)V
       9: return

  void innerError(int, java.lang.Throwable);
    Code:
       0: aload_0
       1: iconst_1
       2: putfield      #24                 // Field done:Z
       5: aload_0
       6: getfield      #12                 // Field upstream:Ljava/util/concurrent/atomic/AtomicReference;
       9: invokestatic  #43                 // Method io/reactivex/rxjava3/internal/subscriptions/SubscriptionHelper.cancel:(Ljava/util/concurrent/atomic/AtomicReference;)Z
      12: pop
      13: aload_0
      14: iload_1
      15: invokevirtual #39                 // Method cancelAllBut:(I)V
      18: aload_0
      19: getfield      #2                  // Field downstream:Lorg/reactivestreams/Subscriber;
      22: aload_2
      23: aload_0
      24: aload_0
      25: getfield      #18                 // Field error:Lio/reactivex/rxjava3/internal/util/AtomicThrowable;
      28: invokestatic  #40                 // Method io/reactivex/rxjava3/internal/util/HalfSerializer.onError:(Lorg/reactivestreams/Subscriber;Ljava/lang/Throwable;Ljava/util/concurrent/atomic/AtomicInteger;Lio/reactivex/rxjava3/internal/util/AtomicThrowable;)V
      31: return

  void innerComplete(int, boolean);
    Code:
       0: iload_2
       1: ifne          34
       4: aload_0
       5: iconst_1
       6: putfield      #24                 // Field done:Z
       9: aload_0
      10: getfield      #12                 // Field upstream:Ljava/util/concurrent/atomic/AtomicReference;
      13: invokestatic  #43                 // Method io/reactivex/rxjava3/internal/subscriptions/SubscriptionHelper.cancel:(Ljava/util/concurrent/atomic/AtomicReference;)Z
      16: pop
      17: aload_0
      18: iload_1
      19: invokevirtual #39                 // Method cancelAllBut:(I)V
      22: aload_0
      23: getfield      #2                  // Field downstream:Lorg/reactivestreams/Subscriber;
      26: aload_0
      27: aload_0
      28: getfield      #18                 // Field error:Lio/reactivex/rxjava3/internal/util/AtomicThrowable;
      31: invokestatic  #41                 // Method io/reactivex/rxjava3/internal/util/HalfSerializer.onComplete:(Lorg/reactivestreams/Subscriber;Ljava/util/concurrent/atomic/AtomicInteger;Lio/reactivex/rxjava3/internal/util/AtomicThrowable;)V
      34: return

  void cancelAllBut(int);
    Code:
       0: aload_0
       1: getfield      #6                  // Field subscribers:[Lio/reactivex/rxjava3/internal/operators/flowable/FlowableWithLatestFromMany$WithLatestInnerSubscriber;
       4: astore_2
       5: iconst_0
       6: istore_3
       7: iload_3
       8: aload_2
       9: arraylength
      10: if_icmpge     30
      13: iload_3
      14: iload_1
      15: if_icmpeq     24
      18: aload_2
      19: iload_3
      20: aaload
      21: invokevirtual #44                 // Method io/reactivex/rxjava3/internal/operators/flowable/FlowableWithLatestFromMany$WithLatestInnerSubscriber.dispose:()V
      24: iinc          3, 1
      27: goto          7
      30: return
}
