Compiled from "FlowableMapNotification.java"
final class io.reactivex.rxjava3.internal.operators.flowable.FlowableMapNotification$MapNotificationSubscriber<T, R> extends io.reactivex.rxjava3.internal.subscribers.SinglePostCompleteSubscriber<T, R> {
  private static final long serialVersionUID;

  final io.reactivex.rxjava3.functions.Function<? super T, ? extends R> onNextMapper;

  final io.reactivex.rxjava3.functions.Function<? super java.lang.Throwable, ? extends R> onErrorMapper;

  final io.reactivex.rxjava3.functions.Supplier<? extends R> onCompleteSupplier;

  io.reactivex.rxjava3.internal.operators.flowable.FlowableMapNotification$MapNotificationSubscriber(org.reactivestreams.Subscriber<? super R>, io.reactivex.rxjava3.functions.Function<? super T, ? extends R>, io.reactivex.rxjava3.functions.Function<? super java.lang.Throwable, ? extends R>, io.reactivex.rxjava3.functions.Supplier<? extends R>);
    Code:
       0: aload_0
       1: aload_1
       2: invokespecial #1                  // Method io/reactivex/rxjava3/internal/subscribers/SinglePostCompleteSubscriber."<init>":(Lorg/reactivestreams/Subscriber;)V
       5: aload_0
       6: aload_2
       7: putfield      #2                  // Field onNextMapper:Lio/reactivex/rxjava3/functions/Function;
      10: aload_0
      11: aload_3
      12: putfield      #3                  // Field onErrorMapper:Lio/reactivex/rxjava3/functions/Function;
      15: aload_0
      16: aload         4
      18: putfield      #4                  // Field onCompleteSupplier:Lio/reactivex/rxjava3/functions/Supplier;
      21: return

  public void onNext(T);
    Code:
       0: aload_0
       1: getfield      #2                  // Field onNextMapper:Lio/reactivex/rxjava3/functions/Function;
       4: aload_1
       5: invokeinterface #5,  2            // InterfaceMethod io/reactivex/rxjava3/functions/Function.apply:(Ljava/lang/Object;)Ljava/lang/Object;
      10: ldc           #6                  // String The onNext publisher returned is null
      12: invokestatic  #7                  // Method java/util/Objects.requireNonNull:(Ljava/lang/Object;Ljava/lang/String;)Ljava/lang/Object;
      15: astore_2
      16: goto          35
      19: astore_3
      20: aload_3
      21: invokestatic  #9                  // Method io/reactivex/rxjava3/exceptions/Exceptions.throwIfFatal:(Ljava/lang/Throwable;)V
      24: aload_0
      25: getfield      #10                 // Field downstream:Lorg/reactivestreams/Subscriber;
      28: aload_3
      29: invokeinterface #11,  2           // InterfaceMethod org/reactivestreams/Subscriber.onError:(Ljava/lang/Throwable;)V
      34: return
      35: aload_0
      36: dup
      37: getfield      #12                 // Field produced:J
      40: lconst_1
      41: ladd
      42: putfield      #12                 // Field produced:J
      45: aload_0
      46: getfield      #10                 // Field downstream:Lorg/reactivestreams/Subscriber;
      49: aload_2
      50: invokeinterface #13,  2           // InterfaceMethod org/reactivestreams/Subscriber.onNext:(Ljava/lang/Object;)V
      55: return
    Exception table:
       from    to  target type
           0    16    19   Class java/lang/Throwable

  public void onError(java.lang.Throwable);
    Code:
       0: aload_0
       1: getfield      #3                  // Field onErrorMapper:Lio/reactivex/rxjava3/functions/Function;
       4: aload_1
       5: invokeinterface #5,  2            // InterfaceMethod io/reactivex/rxjava3/functions/Function.apply:(Ljava/lang/Object;)Ljava/lang/Object;
      10: ldc           #14                 // String The onError publisher returned is null
      12: invokestatic  #7                  // Method java/util/Objects.requireNonNull:(Ljava/lang/Object;Ljava/lang/String;)Ljava/lang/Object;
      15: astore_2
      16: goto          53
      19: astore_3
      20: aload_3
      21: invokestatic  #9                  // Method io/reactivex/rxjava3/exceptions/Exceptions.throwIfFatal:(Ljava/lang/Throwable;)V
      24: aload_0
      25: getfield      #10                 // Field downstream:Lorg/reactivestreams/Subscriber;
      28: new           #15                 // class io/reactivex/rxjava3/exceptions/CompositeException
      31: dup
      32: iconst_2
      33: anewarray     #16                 // class java/lang/Throwable
      36: dup
      37: iconst_0
      38: aload_1
      39: aastore
      40: dup
      41: iconst_1
      42: aload_3
      43: aastore
      44: invokespecial #17                 // Method io/reactivex/rxjava3/exceptions/CompositeException."<init>":([Ljava/lang/Throwable;)V
      47: invokeinterface #11,  2           // InterfaceMethod org/reactivestreams/Subscriber.onError:(Ljava/lang/Throwable;)V
      52: return
      53: aload_0
      54: aload_2
      55: invokevirtual #18                 // Method complete:(Ljava/lang/Object;)V
      58: return
    Exception table:
       from    to  target type
           0    16    19   Class java/lang/Throwable

  public void onComplete();
    Code:
       0: aload_0
       1: getfield      #4                  // Field onCompleteSupplier:Lio/reactivex/rxjava3/functions/Supplier;
       4: invokeinterface #19,  1           // InterfaceMethod io/reactivex/rxjava3/functions/Supplier.get:()Ljava/lang/Object;
       9: ldc           #20                 // String The onComplete publisher returned is null
      11: invokestatic  #7                  // Method java/util/Objects.requireNonNull:(Ljava/lang/Object;Ljava/lang/String;)Ljava/lang/Object;
      14: astore_1
      15: goto          34
      18: astore_2
      19: aload_2
      20: invokestatic  #9                  // Method io/reactivex/rxjava3/exceptions/Exceptions.throwIfFatal:(Ljava/lang/Throwable;)V
      23: aload_0
      24: getfield      #10                 // Field downstream:Lorg/reactivestreams/Subscriber;
      27: aload_2
      28: invokeinterface #11,  2           // InterfaceMethod org/reactivestreams/Subscriber.onError:(Ljava/lang/Throwable;)V
      33: return
      34: aload_0
      35: aload_1
      36: invokevirtual #18                 // Method complete:(Ljava/lang/Object;)V
      39: return
    Exception table:
       from    to  target type
           0    15    18   Class java/lang/Throwable
}
