Compiled from "FlowableOnBackpressureBuffer.java"
public final class io.reactivex.rxjava3.internal.operators.flowable.FlowableOnBackpressureBuffer<T> extends io.reactivex.rxjava3.internal.operators.flowable.AbstractFlowableWithUpstream<T, T> {
  final int bufferSize;

  final boolean unbounded;

  final boolean delayError;

  final io.reactivex.rxjava3.functions.Action onOverflow;

  public io.reactivex.rxjava3.internal.operators.flowable.FlowableOnBackpressureBuffer(io.reactivex.rxjava3.core.Flowable<T>, int, boolean, boolean, io.reactivex.rxjava3.functions.Action);
    Code:
       0: aload_0
       1: aload_1
       2: invokespecial #1                  // Method io/reactivex/rxjava3/internal/operators/flowable/AbstractFlowableWithUpstream."<init>":(Lio/reactivex/rxjava3/core/Flowable;)V
       5: aload_0
       6: iload_2
       7: putfield      #2                  // Field bufferSize:I
      10: aload_0
      11: iload_3
      12: putfield      #3                  // Field unbounded:Z
      15: aload_0
      16: iload         4
      18: putfield      #4                  // Field delayError:Z
      21: aload_0
      22: aload         5
      24: putfield      #5                  // Field onOverflow:Lio/reactivex/rxjava3/functions/Action;
      27: return

  protected void subscribeActual(org.reactivestreams.Subscriber<? super T>);
    Code:
       0: aload_0
       1: getfield      #6                  // Field source:Lio/reactivex/rxjava3/core/Flowable;
       4: new           #7                  // class io/reactivex/rxjava3/internal/operators/flowable/FlowableOnBackpressureBuffer$BackpressureBufferSubscriber
       7: dup
       8: aload_1
       9: aload_0
      10: getfield      #2                  // Field bufferSize:I
      13: aload_0
      14: getfield      #3                  // Field unbounded:Z
      17: aload_0
      18: getfield      #4                  // Field delayError:Z
      21: aload_0
      22: getfield      #5                  // Field onOverflow:Lio/reactivex/rxjava3/functions/Action;
      25: invokespecial #8                  // Method io/reactivex/rxjava3/internal/operators/flowable/FlowableOnBackpressureBuffer$BackpressureBufferSubscriber."<init>":(Lorg/reactivestreams/Subscriber;IZZLio/reactivex/rxjava3/functions/Action;)V
      28: invokevirtual #9                  // Method io/reactivex/rxjava3/core/Flowable.subscribe:(Lio/reactivex/rxjava3/core/FlowableSubscriber;)V
      31: return
}
