Compiled from "FlowableAllSingle.java"
final class io.reactivex.rxjava3.internal.operators.flowable.FlowableAllSingle$AllSubscriber<T> implements io.reactivex.rxjava3.core.FlowableSubscriber<T>, io.reactivex.rxjava3.disposables.Disposable {
  final io.reactivex.rxjava3.core.SingleObserver<? super java.lang.Boolean> downstream;

  final io.reactivex.rxjava3.functions.Predicate<? super T> predicate;

  org.reactivestreams.Subscription upstream;

  boolean done;

  io.reactivex.rxjava3.internal.operators.flowable.FlowableAllSingle$AllSubscriber(io.reactivex.rxjava3.core.SingleObserver<? super java.lang.Boolean>, io.reactivex.rxjava3.functions.Predicate<? super T>);
    Code:
       0: aload_0
       1: invokespecial #1                  // Method java/lang/Object."<init>":()V
       4: aload_0
       5: aload_1
       6: putfield      #2                  // Field downstream:Lio/reactivex/rxjava3/core/SingleObserver;
       9: aload_0
      10: aload_2
      11: putfield      #3                  // Field predicate:Lio/reactivex/rxjava3/functions/Predicate;
      14: return

  public void onSubscribe(org.reactivestreams.Subscription);
    Code:
       0: aload_0
       1: getfield      #4                  // Field upstream:Lorg/reactivestreams/Subscription;
       4: aload_1
       5: invokestatic  #5                  // Method io/reactivex/rxjava3/internal/subscriptions/SubscriptionHelper.validate:(Lorg/reactivestreams/Subscription;Lorg/reactivestreams/Subscription;)Z
       8: ifeq          35
      11: aload_0
      12: aload_1
      13: putfield      #4                  // Field upstream:Lorg/reactivestreams/Subscription;
      16: aload_0
      17: getfield      #2                  // Field downstream:Lio/reactivex/rxjava3/core/SingleObserver;
      20: aload_0
      21: invokeinterface #6,  2            // InterfaceMethod io/reactivex/rxjava3/core/SingleObserver.onSubscribe:(Lio/reactivex/rxjava3/disposables/Disposable;)V
      26: aload_1
      27: ldc2_w        #8                  // long 9223372036854775807l
      30: invokeinterface #10,  3           // InterfaceMethod org/reactivestreams/Subscription.request:(J)V
      35: return

  public void onNext(T);
    Code:
       0: aload_0
       1: getfield      #11                 // Field done:Z
       4: ifeq          8
       7: return
       8: aload_0
       9: getfield      #3                  // Field predicate:Lio/reactivex/rxjava3/functions/Predicate;
      12: aload_1
      13: invokeinterface #12,  2           // InterfaceMethod io/reactivex/rxjava3/functions/Predicate.test:(Ljava/lang/Object;)Z
      18: istore_2
      19: goto          49
      22: astore_3
      23: aload_3
      24: invokestatic  #14                 // Method io/reactivex/rxjava3/exceptions/Exceptions.throwIfFatal:(Ljava/lang/Throwable;)V
      27: aload_0
      28: getfield      #4                  // Field upstream:Lorg/reactivestreams/Subscription;
      31: invokeinterface #15,  1           // InterfaceMethod org/reactivestreams/Subscription.cancel:()V
      36: aload_0
      37: getstatic     #16                 // Field io/reactivex/rxjava3/internal/subscriptions/SubscriptionHelper.CANCELLED:Lio/reactivex/rxjava3/internal/subscriptions/SubscriptionHelper;
      40: putfield      #4                  // Field upstream:Lorg/reactivestreams/Subscription;
      43: aload_0
      44: aload_3
      45: invokevirtual #17                 // Method onError:(Ljava/lang/Throwable;)V
      48: return
      49: iload_2
      50: ifne          87
      53: aload_0
      54: iconst_1
      55: putfield      #11                 // Field done:Z
      58: aload_0
      59: getfield      #4                  // Field upstream:Lorg/reactivestreams/Subscription;
      62: invokeinterface #15,  1           // InterfaceMethod org/reactivestreams/Subscription.cancel:()V
      67: aload_0
      68: getstatic     #16                 // Field io/reactivex/rxjava3/internal/subscriptions/SubscriptionHelper.CANCELLED:Lio/reactivex/rxjava3/internal/subscriptions/SubscriptionHelper;
      71: putfield      #4                  // Field upstream:Lorg/reactivestreams/Subscription;
      74: aload_0
      75: getfield      #2                  // Field downstream:Lio/reactivex/rxjava3/core/SingleObserver;
      78: iconst_0
      79: invokestatic  #18                 // Method java/lang/Boolean.valueOf:(Z)Ljava/lang/Boolean;
      82: invokeinterface #19,  2           // InterfaceMethod io/reactivex/rxjava3/core/SingleObserver.onSuccess:(Ljava/lang/Object;)V
      87: return
    Exception table:
       from    to  target type
           8    19    22   Class java/lang/Throwable

  public void onError(java.lang.Throwable);
    Code:
       0: aload_0
       1: getfield      #11                 // Field done:Z
       4: ifeq          12
       7: aload_1
       8: invokestatic  #20                 // Method io/reactivex/rxjava3/plugins/RxJavaPlugins.onError:(Ljava/lang/Throwable;)V
      11: return
      12: aload_0
      13: iconst_1
      14: putfield      #11                 // Field done:Z
      17: aload_0
      18: getstatic     #16                 // Field io/reactivex/rxjava3/internal/subscriptions/SubscriptionHelper.CANCELLED:Lio/reactivex/rxjava3/internal/subscriptions/SubscriptionHelper;
      21: putfield      #4                  // Field upstream:Lorg/reactivestreams/Subscription;
      24: aload_0
      25: getfield      #2                  // Field downstream:Lio/reactivex/rxjava3/core/SingleObserver;
      28: aload_1
      29: invokeinterface #21,  2           // InterfaceMethod io/reactivex/rxjava3/core/SingleObserver.onError:(Ljava/lang/Throwable;)V
      34: return

  public void onComplete();
    Code:
       0: aload_0
       1: getfield      #11                 // Field done:Z
       4: ifeq          8
       7: return
       8: aload_0
       9: iconst_1
      10: putfield      #11                 // Field done:Z
      13: aload_0
      14: getstatic     #16                 // Field io/reactivex/rxjava3/internal/subscriptions/SubscriptionHelper.CANCELLED:Lio/reactivex/rxjava3/internal/subscriptions/SubscriptionHelper;
      17: putfield      #4                  // Field upstream:Lorg/reactivestreams/Subscription;
      20: aload_0
      21: getfield      #2                  // Field downstream:Lio/reactivex/rxjava3/core/SingleObserver;
      24: iconst_1
      25: invokestatic  #18                 // Method java/lang/Boolean.valueOf:(Z)Ljava/lang/Boolean;
      28: invokeinterface #19,  2           // InterfaceMethod io/reactivex/rxjava3/core/SingleObserver.onSuccess:(Ljava/lang/Object;)V
      33: return

  public void dispose();
    Code:
       0: aload_0
       1: getfield      #4                  // Field upstream:Lorg/reactivestreams/Subscription;
       4: invokeinterface #15,  1           // InterfaceMethod org/reactivestreams/Subscription.cancel:()V
       9: aload_0
      10: getstatic     #16                 // Field io/reactivex/rxjava3/internal/subscriptions/SubscriptionHelper.CANCELLED:Lio/reactivex/rxjava3/internal/subscriptions/SubscriptionHelper;
      13: putfield      #4                  // Field upstream:Lorg/reactivestreams/Subscription;
      16: return

  public boolean isDisposed();
    Code:
       0: aload_0
       1: getfield      #4                  // Field upstream:Lorg/reactivestreams/Subscription;
       4: getstatic     #16                 // Field io/reactivex/rxjava3/internal/subscriptions/SubscriptionHelper.CANCELLED:Lio/reactivex/rxjava3/internal/subscriptions/SubscriptionHelper;
       7: if_acmpne     14
      10: iconst_1
      11: goto          15
      14: iconst_0
      15: ireturn
}
