Compiled from "FlowableIgnoreElementsCompletable.java"
public final class io.reactivex.rxjava3.internal.operators.flowable.FlowableIgnoreElementsCompletable<T> extends io.reactivex.rxjava3.core.Completable implements io.reactivex.rxjava3.internal.fuseable.FuseToFlowable<T> {
  final io.reactivex.rxjava3.core.Flowable<T> source;

  public io.reactivex.rxjava3.internal.operators.flowable.FlowableIgnoreElementsCompletable(io.reactivex.rxjava3.core.Flowable<T>);
    Code:
       0: aload_0
       1: invokespecial #1                  // Method io/reactivex/rxjava3/core/Completable."<init>":()V
       4: aload_0
       5: aload_1
       6: putfield      #2                  // Field source:Lio/reactivex/rxjava3/core/Flowable;
       9: return

  protected void subscribeActual(io.reactivex.rxjava3.core.CompletableObserver);
    Code:
       0: aload_0
       1: getfield      #2                  // Field source:Lio/reactivex/rxjava3/core/Flowable;
       4: new           #3                  // class io/reactivex/rxjava3/internal/operators/flowable/FlowableIgnoreElementsCompletable$IgnoreElementsSubscriber
       7: dup
       8: aload_1
       9: invokespecial #4                  // Method io/reactivex/rxjava3/internal/operators/flowable/FlowableIgnoreElementsCompletable$IgnoreElementsSubscriber."<init>":(Lio/reactivex/rxjava3/core/CompletableObserver;)V
      12: invokevirtual #5                  // Method io/reactivex/rxjava3/core/Flowable.subscribe:(Lio/reactivex/rxjava3/core/FlowableSubscriber;)V
      15: return

  public io.reactivex.rxjava3.core.Flowable<T> fuseToFlowable();
    Code:
       0: new           #6                  // class io/reactivex/rxjava3/internal/operators/flowable/FlowableIgnoreElements
       3: dup
       4: aload_0
       5: getfield      #2                  // Field source:Lio/reactivex/rxjava3/core/Flowable;
       8: invokespecial #7                  // Method io/reactivex/rxjava3/internal/operators/flowable/FlowableIgnoreElements."<init>":(Lio/reactivex/rxjava3/core/Flowable;)V
      11: invokestatic  #8                  // Method io/reactivex/rxjava3/plugins/RxJavaPlugins.onAssembly:(Lio/reactivex/rxjava3/core/Flowable;)Lio/reactivex/rxjava3/core/Flowable;
      14: areturn
}
