Compiled from "FlowableInternalHelper.java"
public final class io.reactivex.rxjava3.internal.operators.flowable.FlowableInternalHelper {
  private io.reactivex.rxjava3.internal.operators.flowable.FlowableInternalHelper();
    Code:
       0: aload_0
       1: invokespecial #1                  // Method java/lang/Object."<init>":()V
       4: new           #2                  // class java/lang/IllegalStateException
       7: dup
       8: ldc           #3                  // String No instances!
      10: invokespecial #4                  // Method java/lang/IllegalStateException."<init>":(Ljava/lang/String;)V
      13: athrow

  public static <T, S> io.reactivex.rxjava3.functions.BiFunction<S, io.reactivex.rxjava3.core.Emitter<T>, S> simpleGenerator(io.reactivex.rxjava3.functions.Consumer<io.reactivex.rxjava3.core.Emitter<T>>);
    Code:
       0: new           #5                  // class io/reactivex/rxjava3/internal/operators/flowable/FlowableInternalHelper$SimpleGenerator
       3: dup
       4: aload_0
       5: invokespecial #6                  // Method io/reactivex/rxjava3/internal/operators/flowable/FlowableInternalHelper$SimpleGenerator."<init>":(Lio/reactivex/rxjava3/functions/Consumer;)V
       8: areturn

  public static <T, S> io.reactivex.rxjava3.functions.BiFunction<S, io.reactivex.rxjava3.core.Emitter<T>, S> simpleBiGenerator(io.reactivex.rxjava3.functions.BiConsumer<S, io.reactivex.rxjava3.core.Emitter<T>>);
    Code:
       0: new           #7                  // class io/reactivex/rxjava3/internal/operators/flowable/FlowableInternalHelper$SimpleBiGenerator
       3: dup
       4: aload_0
       5: invokespecial #8                  // Method io/reactivex/rxjava3/internal/operators/flowable/FlowableInternalHelper$SimpleBiGenerator."<init>":(Lio/reactivex/rxjava3/functions/BiConsumer;)V
       8: areturn

  public static <T, U> io.reactivex.rxjava3.functions.Function<T, org.reactivestreams.Publisher<T>> itemDelay(io.reactivex.rxjava3.functions.Function<? super T, ? extends org.reactivestreams.Publisher<U>>);
    Code:
       0: new           #9                  // class io/reactivex/rxjava3/internal/operators/flowable/FlowableInternalHelper$ItemDelayFunction
       3: dup
       4: aload_0
       5: invokespecial #10                 // Method io/reactivex/rxjava3/internal/operators/flowable/FlowableInternalHelper$ItemDelayFunction."<init>":(Lio/reactivex/rxjava3/functions/Function;)V
       8: areturn

  public static <T> io.reactivex.rxjava3.functions.Consumer<T> subscriberOnNext(org.reactivestreams.Subscriber<T>);
    Code:
       0: new           #11                 // class io/reactivex/rxjava3/internal/operators/flowable/FlowableInternalHelper$SubscriberOnNext
       3: dup
       4: aload_0
       5: invokespecial #12                 // Method io/reactivex/rxjava3/internal/operators/flowable/FlowableInternalHelper$SubscriberOnNext."<init>":(Lorg/reactivestreams/Subscriber;)V
       8: areturn

  public static <T> io.reactivex.rxjava3.functions.Consumer<java.lang.Throwable> subscriberOnError(org.reactivestreams.Subscriber<T>);
    Code:
       0: new           #13                 // class io/reactivex/rxjava3/internal/operators/flowable/FlowableInternalHelper$SubscriberOnError
       3: dup
       4: aload_0
       5: invokespecial #14                 // Method io/reactivex/rxjava3/internal/operators/flowable/FlowableInternalHelper$SubscriberOnError."<init>":(Lorg/reactivestreams/Subscriber;)V
       8: areturn

  public static <T> io.reactivex.rxjava3.functions.Action subscriberOnComplete(org.reactivestreams.Subscriber<T>);
    Code:
       0: new           #15                 // class io/reactivex/rxjava3/internal/operators/flowable/FlowableInternalHelper$SubscriberOnComplete
       3: dup
       4: aload_0
       5: invokespecial #16                 // Method io/reactivex/rxjava3/internal/operators/flowable/FlowableInternalHelper$SubscriberOnComplete."<init>":(Lorg/reactivestreams/Subscriber;)V
       8: areturn

  public static <T, U, R> io.reactivex.rxjava3.functions.Function<T, org.reactivestreams.Publisher<R>> flatMapWithCombiner(io.reactivex.rxjava3.functions.Function<? super T, ? extends org.reactivestreams.Publisher<? extends U>>, io.reactivex.rxjava3.functions.BiFunction<? super T, ? super U, ? extends R>);
    Code:
       0: new           #17                 // class io/reactivex/rxjava3/internal/operators/flowable/FlowableInternalHelper$FlatMapWithCombinerOuter
       3: dup
       4: aload_1
       5: aload_0
       6: invokespecial #18                 // Method io/reactivex/rxjava3/internal/operators/flowable/FlowableInternalHelper$FlatMapWithCombinerOuter."<init>":(Lio/reactivex/rxjava3/functions/BiFunction;Lio/reactivex/rxjava3/functions/Function;)V
       9: areturn

  public static <T, U> io.reactivex.rxjava3.functions.Function<T, org.reactivestreams.Publisher<U>> flatMapIntoIterable(io.reactivex.rxjava3.functions.Function<? super T, ? extends java.lang.Iterable<? extends U>>);
    Code:
       0: new           #19                 // class io/reactivex/rxjava3/internal/operators/flowable/FlowableInternalHelper$FlatMapIntoIterable
       3: dup
       4: aload_0
       5: invokespecial #20                 // Method io/reactivex/rxjava3/internal/operators/flowable/FlowableInternalHelper$FlatMapIntoIterable."<init>":(Lio/reactivex/rxjava3/functions/Function;)V
       8: areturn

  public static <T> io.reactivex.rxjava3.functions.Supplier<io.reactivex.rxjava3.flowables.ConnectableFlowable<T>> replaySupplier(io.reactivex.rxjava3.core.Flowable<T>);
    Code:
       0: new           #21                 // class io/reactivex/rxjava3/internal/operators/flowable/FlowableInternalHelper$ReplaySupplier
       3: dup
       4: aload_0
       5: invokespecial #22                 // Method io/reactivex/rxjava3/internal/operators/flowable/FlowableInternalHelper$ReplaySupplier."<init>":(Lio/reactivex/rxjava3/core/Flowable;)V
       8: areturn

  public static <T> io.reactivex.rxjava3.functions.Supplier<io.reactivex.rxjava3.flowables.ConnectableFlowable<T>> replaySupplier(io.reactivex.rxjava3.core.Flowable<T>, int, boolean);
    Code:
       0: new           #23                 // class io/reactivex/rxjava3/internal/operators/flowable/FlowableInternalHelper$BufferedReplaySupplier
       3: dup
       4: aload_0
       5: iload_1
       6: iload_2
       7: invokespecial #24                 // Method io/reactivex/rxjava3/internal/operators/flowable/FlowableInternalHelper$BufferedReplaySupplier."<init>":(Lio/reactivex/rxjava3/core/Flowable;IZ)V
      10: areturn

  public static <T> io.reactivex.rxjava3.functions.Supplier<io.reactivex.rxjava3.flowables.ConnectableFlowable<T>> replaySupplier(io.reactivex.rxjava3.core.Flowable<T>, int, long, java.util.concurrent.TimeUnit, io.reactivex.rxjava3.core.Scheduler, boolean);
    Code:
       0: new           #25                 // class io/reactivex/rxjava3/internal/operators/flowable/FlowableInternalHelper$BufferedTimedReplay
       3: dup
       4: aload_0
       5: iload_1
       6: lload_2
       7: aload         4
       9: aload         5
      11: iload         6
      13: invokespecial #26                 // Method io/reactivex/rxjava3/internal/operators/flowable/FlowableInternalHelper$BufferedTimedReplay."<init>":(Lio/reactivex/rxjava3/core/Flowable;IJLjava/util/concurrent/TimeUnit;Lio/reactivex/rxjava3/core/Scheduler;Z)V
      16: areturn

  public static <T> io.reactivex.rxjava3.functions.Supplier<io.reactivex.rxjava3.flowables.ConnectableFlowable<T>> replaySupplier(io.reactivex.rxjava3.core.Flowable<T>, long, java.util.concurrent.TimeUnit, io.reactivex.rxjava3.core.Scheduler, boolean);
    Code:
       0: new           #27                 // class io/reactivex/rxjava3/internal/operators/flowable/FlowableInternalHelper$TimedReplay
       3: dup
       4: aload_0
       5: lload_1
       6: aload_3
       7: aload         4
       9: iload         5
      11: invokespecial #28                 // Method io/reactivex/rxjava3/internal/operators/flowable/FlowableInternalHelper$TimedReplay."<init>":(Lio/reactivex/rxjava3/core/Flowable;JLjava/util/concurrent/TimeUnit;Lio/reactivex/rxjava3/core/Scheduler;Z)V
      14: areturn
}
