Compiled from "FlowableCombineLatest.java"
final class io.reactivex.rxjava3.internal.operators.flowable.FlowableCombineLatest$CombineLatestCoordinator<T, R> extends io.reactivex.rxjava3.internal.subscriptions.BasicIntQueueSubscription<R> {
  private static final long serialVersionUID;

  final org.reactivestreams.Subscriber<? super R> downstream;

  final io.reactivex.rxjava3.functions.Function<? super java.lang.Object[], ? extends R> combiner;

  final io.reactivex.rxjava3.internal.operators.flowable.FlowableCombineLatest$CombineLatestInnerSubscriber<T>[] subscribers;

  final io.reactivex.rxjava3.operators.SpscLinkedArrayQueue<java.lang.Object> queue;

  final java.lang.Object[] latest;

  final boolean delayErrors;

  boolean outputFused;

  int nonEmptySources;

  int completedSources;

  volatile boolean cancelled;

  final java.util.concurrent.atomic.AtomicLong requested;

  volatile boolean done;

  final io.reactivex.rxjava3.internal.util.AtomicThrowable error;

  io.reactivex.rxjava3.internal.operators.flowable.FlowableCombineLatest$CombineLatestCoordinator(org.reactivestreams.Subscriber<? super R>, io.reactivex.rxjava3.functions.Function<? super java.lang.Object[], ? extends R>, int, int, boolean);
    Code:
       0: aload_0
       1: invokespecial #1                  // Method io/reactivex/rxjava3/internal/subscriptions/BasicIntQueueSubscription."<init>":()V
       4: aload_0
       5: aload_1
       6: putfield      #2                  // Field downstream:Lorg/reactivestreams/Subscriber;
       9: aload_0
      10: aload_2
      11: putfield      #3                  // Field combiner:Lio/reactivex/rxjava3/functions/Function;
      14: iload_3
      15: anewarray     #4                  // class io/reactivex/rxjava3/internal/operators/flowable/FlowableCombineLatest$CombineLatestInnerSubscriber
      18: astore        6
      20: iconst_0
      21: istore        7
      23: iload         7
      25: iload_3
      26: if_icmpge     52
      29: aload         6
      31: iload         7
      33: new           #4                  // class io/reactivex/rxjava3/internal/operators/flowable/FlowableCombineLatest$CombineLatestInnerSubscriber
      36: dup
      37: aload_0
      38: iload         7
      40: iload         4
      42: invokespecial #5                  // Method io/reactivex/rxjava3/internal/operators/flowable/FlowableCombineLatest$CombineLatestInnerSubscriber."<init>":(Lio/reactivex/rxjava3/internal/operators/flowable/FlowableCombineLatest$CombineLatestCoordinator;II)V
      45: aastore
      46: iinc          7, 1
      49: goto          23
      52: aload_0
      53: aload         6
      55: putfield      #6                  // Field subscribers:[Lio/reactivex/rxjava3/internal/operators/flowable/FlowableCombineLatest$CombineLatestInnerSubscriber;
      58: aload_0
      59: iload_3
      60: anewarray     #7                  // class java/lang/Object
      63: putfield      #8                  // Field latest:[Ljava/lang/Object;
      66: aload_0
      67: new           #9                  // class io/reactivex/rxjava3/operators/SpscLinkedArrayQueue
      70: dup
      71: iload         4
      73: invokespecial #10                 // Method io/reactivex/rxjava3/operators/SpscLinkedArrayQueue."<init>":(I)V
      76: putfield      #11                 // Field queue:Lio/reactivex/rxjava3/operators/SpscLinkedArrayQueue;
      79: aload_0
      80: new           #12                 // class java/util/concurrent/atomic/AtomicLong
      83: dup
      84: invokespecial #13                 // Method java/util/concurrent/atomic/AtomicLong."<init>":()V
      87: putfield      #14                 // Field requested:Ljava/util/concurrent/atomic/AtomicLong;
      90: aload_0
      91: new           #15                 // class io/reactivex/rxjava3/internal/util/AtomicThrowable
      94: dup
      95: invokespecial #16                 // Method io/reactivex/rxjava3/internal/util/AtomicThrowable."<init>":()V
      98: putfield      #17                 // Field error:Lio/reactivex/rxjava3/internal/util/AtomicThrowable;
     101: aload_0
     102: iload         5
     104: putfield      #18                 // Field delayErrors:Z
     107: return

  public void request(long);
    Code:
       0: lload_1
       1: invokestatic  #19                 // Method io/reactivex/rxjava3/internal/subscriptions/SubscriptionHelper.validate:(J)Z
       4: ifeq          20
       7: aload_0
       8: getfield      #14                 // Field requested:Ljava/util/concurrent/atomic/AtomicLong;
      11: lload_1
      12: invokestatic  #20                 // Method io/reactivex/rxjava3/internal/util/BackpressureHelper.add:(Ljava/util/concurrent/atomic/AtomicLong;J)J
      15: pop2
      16: aload_0
      17: invokevirtual #21                 // Method drain:()V
      20: return

  public void cancel();
    Code:
       0: aload_0
       1: iconst_1
       2: putfield      #22                 // Field cancelled:Z
       5: aload_0
       6: invokevirtual #23                 // Method cancelAll:()V
       9: aload_0
      10: invokevirtual #21                 // Method drain:()V
      13: return

  void subscribe(org.reactivestreams.Publisher<? extends T>[], int);
    Code:
       0: aload_0
       1: getfield      #6                  // Field subscribers:[Lio/reactivex/rxjava3/internal/operators/flowable/FlowableCombineLatest$CombineLatestInnerSubscriber;
       4: astore_3
       5: iconst_0
       6: istore        4
       8: iload         4
      10: iload_2
      11: if_icmpge     48
      14: aload_0
      15: getfield      #24                 // Field done:Z
      18: ifne          28
      21: aload_0
      22: getfield      #22                 // Field cancelled:Z
      25: ifeq          29
      28: return
      29: aload_1
      30: iload         4
      32: aaload
      33: aload_3
      34: iload         4
      36: aaload
      37: invokeinterface #25,  2           // InterfaceMethod org/reactivestreams/Publisher.subscribe:(Lorg/reactivestreams/Subscriber;)V
      42: iinc          4, 1
      45: goto          8
      48: return

  void innerValue(int, T);
    Code:
       0: aload_0
       1: dup
       2: astore        4
       4: monitorenter
       5: aload_0
       6: getfield      #8                  // Field latest:[Ljava/lang/Object;
       9: astore        5
      11: aload_0
      12: getfield      #26                 // Field nonEmptySources:I
      15: istore        6
      17: aload         5
      19: iload_1
      20: aaload
      21: ifnonnull     33
      24: iinc          6, 1
      27: aload_0
      28: iload         6
      30: putfield      #26                 // Field nonEmptySources:I
      33: aload         5
      35: iload_1
      36: aload_2
      37: aastore
      38: aload         5
      40: arraylength
      41: iload         6
      43: if_icmpne     70
      46: aload_0
      47: getfield      #11                 // Field queue:Lio/reactivex/rxjava3/operators/SpscLinkedArrayQueue;
      50: aload_0
      51: getfield      #6                  // Field subscribers:[Lio/reactivex/rxjava3/internal/operators/flowable/FlowableCombineLatest$CombineLatestInnerSubscriber;
      54: iload_1
      55: aaload
      56: aload         5
      58: invokevirtual #27                 // Method "[Ljava/lang/Object;".clone:()Ljava/lang/Object;
      61: invokevirtual #28                 // Method io/reactivex/rxjava3/operators/SpscLinkedArrayQueue.offer:(Ljava/lang/Object;Ljava/lang/Object;)Z
      64: pop
      65: iconst_0
      66: istore_3
      67: goto          72
      70: iconst_1
      71: istore_3
      72: aload         4
      74: monitorexit
      75: goto          86
      78: astore        7
      80: aload         4
      82: monitorexit
      83: aload         7
      85: athrow
      86: iload_3
      87: ifeq          102
      90: aload_0
      91: getfield      #6                  // Field subscribers:[Lio/reactivex/rxjava3/internal/operators/flowable/FlowableCombineLatest$CombineLatestInnerSubscriber;
      94: iload_1
      95: aaload
      96: invokevirtual #29                 // Method io/reactivex/rxjava3/internal/operators/flowable/FlowableCombineLatest$CombineLatestInnerSubscriber.requestOne:()V
      99: goto          106
     102: aload_0
     103: invokevirtual #21                 // Method drain:()V
     106: return
    Exception table:
       from    to  target type
           5    75    78   any
          78    83    78   any

  void innerComplete(int);
    Code:
       0: aload_0
       1: dup
       2: astore_2
       3: monitorenter
       4: aload_0
       5: getfield      #8                  // Field latest:[Ljava/lang/Object;
       8: astore_3
       9: aload_3
      10: iload_1
      11: aaload
      12: ifnull        50
      15: aload_0
      16: getfield      #30                 // Field completedSources:I
      19: iconst_1
      20: iadd
      21: istore        4
      23: iload         4
      25: aload_3
      26: arraylength
      27: if_icmpne     38
      30: aload_0
      31: iconst_1
      32: putfield      #24                 // Field done:Z
      35: goto          47
      38: aload_0
      39: iload         4
      41: putfield      #30                 // Field completedSources:I
      44: aload_2
      45: monitorexit
      46: return
      47: goto          55
      50: aload_0
      51: iconst_1
      52: putfield      #24                 // Field done:Z
      55: aload_2
      56: monitorexit
      57: goto          67
      60: astore        5
      62: aload_2
      63: monitorexit
      64: aload         5
      66: athrow
      67: aload_0
      68: invokevirtual #21                 // Method drain:()V
      71: return
    Exception table:
       from    to  target type
           4    46    60   any
          47    57    60   any
          60    64    60   any

  void innerError(int, java.lang.Throwable);
    Code:
       0: aload_0
       1: getfield      #17                 // Field error:Lio/reactivex/rxjava3/internal/util/AtomicThrowable;
       4: aload_2
       5: invokestatic  #31                 // Method io/reactivex/rxjava3/internal/util/ExceptionHelper.addThrowable:(Ljava/util/concurrent/atomic/AtomicReference;Ljava/lang/Throwable;)Z
       8: ifeq          42
      11: aload_0
      12: getfield      #18                 // Field delayErrors:Z
      15: ifne          34
      18: aload_0
      19: invokevirtual #23                 // Method cancelAll:()V
      22: aload_0
      23: iconst_1
      24: putfield      #24                 // Field done:Z
      27: aload_0
      28: invokevirtual #21                 // Method drain:()V
      31: goto          46
      34: aload_0
      35: iload_1
      36: invokevirtual #32                 // Method innerComplete:(I)V
      39: goto          46
      42: aload_2
      43: invokestatic  #33                 // Method io/reactivex/rxjava3/plugins/RxJavaPlugins.onError:(Ljava/lang/Throwable;)V
      46: return

  void drainOutput();
    Code:
       0: aload_0
       1: getfield      #2                  // Field downstream:Lorg/reactivestreams/Subscriber;
       4: astore_1
       5: aload_0
       6: getfield      #11                 // Field queue:Lio/reactivex/rxjava3/operators/SpscLinkedArrayQueue;
       9: astore_2
      10: iconst_1
      11: istore_3
      12: aload_0
      13: getfield      #22                 // Field cancelled:Z
      16: ifeq          24
      19: aload_2
      20: invokevirtual #34                 // Method io/reactivex/rxjava3/operators/SpscLinkedArrayQueue.clear:()V
      23: return
      24: aload_0
      25: getfield      #17                 // Field error:Lio/reactivex/rxjava3/internal/util/AtomicThrowable;
      28: invokevirtual #35                 // Method io/reactivex/rxjava3/internal/util/AtomicThrowable.get:()Ljava/lang/Object;
      31: checkcast     #36                 // class java/lang/Throwable
      34: astore        4
      36: aload         4
      38: ifnull        54
      41: aload_2
      42: invokevirtual #34                 // Method io/reactivex/rxjava3/operators/SpscLinkedArrayQueue.clear:()V
      45: aload_1
      46: aload         4
      48: invokeinterface #37,  2           // InterfaceMethod org/reactivestreams/Subscriber.onError:(Ljava/lang/Throwable;)V
      53: return
      54: aload_0
      55: getfield      #24                 // Field done:Z
      58: istore        5
      60: aload_2
      61: invokevirtual #38                 // Method io/reactivex/rxjava3/operators/SpscLinkedArrayQueue.isEmpty:()Z
      64: istore        6
      66: iload         6
      68: ifne          78
      71: aload_1
      72: aconst_null
      73: invokeinterface #39,  2           // InterfaceMethod org/reactivestreams/Subscriber.onNext:(Ljava/lang/Object;)V
      78: iload         5
      80: ifeq          95
      83: iload         6
      85: ifeq          95
      88: aload_1
      89: invokeinterface #40,  1           // InterfaceMethod org/reactivestreams/Subscriber.onComplete:()V
      94: return
      95: aload_0
      96: iload_3
      97: ineg
      98: invokevirtual #41                 // Method addAndGet:(I)I
     101: istore_3
     102: iload_3
     103: ifne          109
     106: goto          112
     109: goto          12
     112: return

  void drainAsync();
    Code:
       0: aload_0
       1: getfield      #2                  // Field downstream:Lorg/reactivestreams/Subscriber;
       4: astore_1
       5: aload_0
       6: getfield      #11                 // Field queue:Lio/reactivex/rxjava3/operators/SpscLinkedArrayQueue;
       9: astore_2
      10: iconst_1
      11: istore_3
      12: aload_0
      13: getfield      #14                 // Field requested:Ljava/util/concurrent/atomic/AtomicLong;
      16: invokevirtual #42                 // Method java/util/concurrent/atomic/AtomicLong.get:()J
      19: lstore        4
      21: lconst_0
      22: lstore        6
      24: lload         6
      26: lload         4
      28: lcmp
      29: ifeq          175
      32: aload_0
      33: getfield      #24                 // Field done:Z
      36: istore        8
      38: aload_2
      39: invokevirtual #43                 // Method io/reactivex/rxjava3/operators/SpscLinkedArrayQueue.poll:()Ljava/lang/Object;
      42: astore        9
      44: aload         9
      46: ifnonnull     53
      49: iconst_1
      50: goto          54
      53: iconst_0
      54: istore        10
      56: aload_0
      57: iload         8
      59: iload         10
      61: aload_1
      62: aload_2
      63: invokevirtual #44                 // Method checkTerminated:(ZZLorg/reactivestreams/Subscriber;Lio/reactivex/rxjava3/operators/SpscLinkedArrayQueue;)Z
      66: ifeq          70
      69: return
      70: iload         10
      72: ifeq          78
      75: goto          175
      78: aload_2
      79: invokevirtual #43                 // Method io/reactivex/rxjava3/operators/SpscLinkedArrayQueue.poll:()Ljava/lang/Object;
      82: checkcast     #45                 // class "[Ljava/lang/Object;"
      85: checkcast     #45                 // class "[Ljava/lang/Object;"
      88: astore        11
      90: aload_0
      91: getfield      #3                  // Field combiner:Lio/reactivex/rxjava3/functions/Function;
      94: aload         11
      96: invokeinterface #46,  2           // InterfaceMethod io/reactivex/rxjava3/functions/Function.apply:(Ljava/lang/Object;)Ljava/lang/Object;
     101: ldc           #47                 // String The combiner returned a null value
     103: invokestatic  #48                 // Method java/util/Objects.requireNonNull:(Ljava/lang/Object;Ljava/lang/String;)Ljava/lang/Object;
     106: astore        12
     108: goto          150
     111: astore        13
     113: aload         13
     115: invokestatic  #49                 // Method io/reactivex/rxjava3/exceptions/Exceptions.throwIfFatal:(Ljava/lang/Throwable;)V
     118: aload_0
     119: invokevirtual #23                 // Method cancelAll:()V
     122: aload_0
     123: getfield      #17                 // Field error:Lio/reactivex/rxjava3/internal/util/AtomicThrowable;
     126: aload         13
     128: invokestatic  #31                 // Method io/reactivex/rxjava3/internal/util/ExceptionHelper.addThrowable:(Ljava/util/concurrent/atomic/AtomicReference;Ljava/lang/Throwable;)Z
     131: pop
     132: aload_0
     133: getfield      #17                 // Field error:Lio/reactivex/rxjava3/internal/util/AtomicThrowable;
     136: invokestatic  #50                 // Method io/reactivex/rxjava3/internal/util/ExceptionHelper.terminate:(Ljava/util/concurrent/atomic/AtomicReference;)Ljava/lang/Throwable;
     139: astore        13
     141: aload_1
     142: aload         13
     144: invokeinterface #37,  2           // InterfaceMethod org/reactivestreams/Subscriber.onError:(Ljava/lang/Throwable;)V
     149: return
     150: aload_1
     151: aload         12
     153: invokeinterface #39,  2           // InterfaceMethod org/reactivestreams/Subscriber.onNext:(Ljava/lang/Object;)V
     158: aload         9
     160: checkcast     #4                  // class io/reactivex/rxjava3/internal/operators/flowable/FlowableCombineLatest$CombineLatestInnerSubscriber
     163: invokevirtual #29                 // Method io/reactivex/rxjava3/internal/operators/flowable/FlowableCombineLatest$CombineLatestInnerSubscriber.requestOne:()V
     166: lload         6
     168: lconst_1
     169: ladd
     170: lstore        6
     172: goto          24
     175: lload         6
     177: lload         4
     179: lcmp
     180: ifne          201
     183: aload_0
     184: aload_0
     185: getfield      #24                 // Field done:Z
     188: aload_2
     189: invokevirtual #38                 // Method io/reactivex/rxjava3/operators/SpscLinkedArrayQueue.isEmpty:()Z
     192: aload_1
     193: aload_2
     194: invokevirtual #44                 // Method checkTerminated:(ZZLorg/reactivestreams/Subscriber;Lio/reactivex/rxjava3/operators/SpscLinkedArrayQueue;)Z
     197: ifeq          201
     200: return
     201: lload         6
     203: lconst_0
     204: lcmp
     205: ifeq          228
     208: lload         4
     210: ldc2_w        #52                 // long 9223372036854775807l
     213: lcmp
     214: ifeq          228
     217: aload_0
     218: getfield      #14                 // Field requested:Ljava/util/concurrent/atomic/AtomicLong;
     221: lload         6
     223: lneg
     224: invokevirtual #54                 // Method java/util/concurrent/atomic/AtomicLong.addAndGet:(J)J
     227: pop2
     228: aload_0
     229: iload_3
     230: ineg
     231: invokevirtual #41                 // Method addAndGet:(I)I
     234: istore_3
     235: iload_3
     236: ifne          242
     239: goto          245
     242: goto          12
     245: return
    Exception table:
       from    to  target type
          90   108   111   Class java/lang/Throwable

  void drain();
    Code:
       0: aload_0
       1: invokevirtual #55                 // Method getAndIncrement:()I
       4: ifeq          8
       7: return
       8: aload_0
       9: getfield      #56                 // Field outputFused:Z
      12: ifeq          22
      15: aload_0
      16: invokevirtual #57                 // Method drainOutput:()V
      19: goto          26
      22: aload_0
      23: invokevirtual #58                 // Method drainAsync:()V
      26: return

  boolean checkTerminated(boolean, boolean, org.reactivestreams.Subscriber<?>, io.reactivex.rxjava3.operators.SpscLinkedArrayQueue<?>);
    Code:
       0: aload_0
       1: getfield      #22                 // Field cancelled:Z
       4: ifeq          25
       7: aload_0
       8: invokevirtual #23                 // Method cancelAll:()V
      11: aload         4
      13: invokevirtual #34                 // Method io/reactivex/rxjava3/operators/SpscLinkedArrayQueue.clear:()V
      16: aload_0
      17: getfield      #17                 // Field error:Lio/reactivex/rxjava3/internal/util/AtomicThrowable;
      20: invokevirtual #59                 // Method io/reactivex/rxjava3/internal/util/AtomicThrowable.tryTerminateAndReport:()V
      23: iconst_1
      24: ireturn
      25: iload_1
      26: ifeq          111
      29: aload_0
      30: getfield      #18                 // Field delayErrors:Z
      33: ifeq          54
      36: iload_2
      37: ifeq          111
      40: aload_0
      41: invokevirtual #23                 // Method cancelAll:()V
      44: aload_0
      45: getfield      #17                 // Field error:Lio/reactivex/rxjava3/internal/util/AtomicThrowable;
      48: aload_3
      49: invokevirtual #60                 // Method io/reactivex/rxjava3/internal/util/AtomicThrowable.tryTerminateConsumer:(Lorg/reactivestreams/Subscriber;)V
      52: iconst_1
      53: ireturn
      54: aload_0
      55: getfield      #17                 // Field error:Lio/reactivex/rxjava3/internal/util/AtomicThrowable;
      58: invokestatic  #50                 // Method io/reactivex/rxjava3/internal/util/ExceptionHelper.terminate:(Ljava/util/concurrent/atomic/AtomicReference;)Ljava/lang/Throwable;
      61: astore        5
      63: aload         5
      65: ifnull        95
      68: aload         5
      70: getstatic     #61                 // Field io/reactivex/rxjava3/internal/util/ExceptionHelper.TERMINATED:Ljava/lang/Throwable;
      73: if_acmpeq     95
      76: aload_0
      77: invokevirtual #23                 // Method cancelAll:()V
      80: aload         4
      82: invokevirtual #34                 // Method io/reactivex/rxjava3/operators/SpscLinkedArrayQueue.clear:()V
      85: aload_3
      86: aload         5
      88: invokeinterface #37,  2           // InterfaceMethod org/reactivestreams/Subscriber.onError:(Ljava/lang/Throwable;)V
      93: iconst_1
      94: ireturn
      95: iload_2
      96: ifeq          111
      99: aload_0
     100: invokevirtual #23                 // Method cancelAll:()V
     103: aload_3
     104: invokeinterface #40,  1           // InterfaceMethod org/reactivestreams/Subscriber.onComplete:()V
     109: iconst_1
     110: ireturn
     111: iconst_0
     112: ireturn

  void cancelAll();
    Code:
       0: aload_0
       1: getfield      #6                  // Field subscribers:[Lio/reactivex/rxjava3/internal/operators/flowable/FlowableCombineLatest$CombineLatestInnerSubscriber;
       4: astore_1
       5: aload_1
       6: arraylength
       7: istore_2
       8: iconst_0
       9: istore_3
      10: iload_3
      11: iload_2
      12: if_icmpge     31
      15: aload_1
      16: iload_3
      17: aaload
      18: astore        4
      20: aload         4
      22: invokevirtual #62                 // Method io/reactivex/rxjava3/internal/operators/flowable/FlowableCombineLatest$CombineLatestInnerSubscriber.cancel:()V
      25: iinc          3, 1
      28: goto          10
      31: return

  public int requestFusion(int);
    Code:
       0: iload_1
       1: iconst_4
       2: iand
       3: ifeq          8
       6: iconst_0
       7: ireturn
       8: iload_1
       9: iconst_2
      10: iand
      11: istore_2
      12: aload_0
      13: iload_2
      14: ifeq          21
      17: iconst_1
      18: goto          22
      21: iconst_0
      22: putfield      #56                 // Field outputFused:Z
      25: iload_2
      26: ireturn

  public R poll() throws java.lang.Throwable;
    Code:
       0: aload_0
       1: getfield      #11                 // Field queue:Lio/reactivex/rxjava3/operators/SpscLinkedArrayQueue;
       4: invokevirtual #43                 // Method io/reactivex/rxjava3/operators/SpscLinkedArrayQueue.poll:()Ljava/lang/Object;
       7: astore_1
       8: aload_1
       9: ifnonnull     14
      12: aconst_null
      13: areturn
      14: aload_0
      15: getfield      #11                 // Field queue:Lio/reactivex/rxjava3/operators/SpscLinkedArrayQueue;
      18: invokevirtual #43                 // Method io/reactivex/rxjava3/operators/SpscLinkedArrayQueue.poll:()Ljava/lang/Object;
      21: checkcast     #45                 // class "[Ljava/lang/Object;"
      24: checkcast     #45                 // class "[Ljava/lang/Object;"
      27: astore_2
      28: aload_0
      29: getfield      #3                  // Field combiner:Lio/reactivex/rxjava3/functions/Function;
      32: aload_2
      33: invokeinterface #46,  2           // InterfaceMethod io/reactivex/rxjava3/functions/Function.apply:(Ljava/lang/Object;)Ljava/lang/Object;
      38: ldc           #47                 // String The combiner returned a null value
      40: invokestatic  #48                 // Method java/util/Objects.requireNonNull:(Ljava/lang/Object;Ljava/lang/String;)Ljava/lang/Object;
      43: astore_3
      44: aload_1
      45: checkcast     #4                  // class io/reactivex/rxjava3/internal/operators/flowable/FlowableCombineLatest$CombineLatestInnerSubscriber
      48: invokevirtual #29                 // Method io/reactivex/rxjava3/internal/operators/flowable/FlowableCombineLatest$CombineLatestInnerSubscriber.requestOne:()V
      51: aload_3
      52: areturn

  public void clear();
    Code:
       0: aload_0
       1: getfield      #11                 // Field queue:Lio/reactivex/rxjava3/operators/SpscLinkedArrayQueue;
       4: invokevirtual #34                 // Method io/reactivex/rxjava3/operators/SpscLinkedArrayQueue.clear:()V
       7: return

  public boolean isEmpty();
    Code:
       0: aload_0
       1: getfield      #11                 // Field queue:Lio/reactivex/rxjava3/operators/SpscLinkedArrayQueue;
       4: invokevirtual #38                 // Method io/reactivex/rxjava3/operators/SpscLinkedArrayQueue.isEmpty:()Z
       7: ireturn
}
