Compiled from "FlowableWithLatestFrom.java"
public final class io.reactivex.rxjava3.internal.operators.flowable.FlowableWithLatestFrom<T, U, R> extends io.reactivex.rxjava3.internal.operators.flowable.AbstractFlowableWithUpstream<T, R> {
  final io.reactivex.rxjava3.functions.BiFunction<? super T, ? super U, ? extends R> combiner;

  final org.reactivestreams.Publisher<? extends U> other;

  public io.reactivex.rxjava3.internal.operators.flowable.FlowableWithLatestFrom(io.reactivex.rxjava3.core.Flowable<T>, io.reactivex.rxjava3.functions.BiFunction<? super T, ? super U, ? extends R>, org.reactivestreams.Publisher<? extends U>);
    Code:
       0: aload_0
       1: aload_1
       2: invokespecial #1                  // Method io/reactivex/rxjava3/internal/operators/flowable/AbstractFlowableWithUpstream."<init>":(Lio/reactivex/rxjava3/core/Flowable;)V
       5: aload_0
       6: aload_2
       7: putfield      #2                  // Field combiner:Lio/reactivex/rxjava3/functions/BiFunction;
      10: aload_0
      11: aload_3
      12: putfield      #3                  // Field other:Lorg/reactivestreams/Publisher;
      15: return

  protected void subscribeActual(org.reactivestreams.Subscriber<? super R>);
    Code:
       0: new           #4                  // class io/reactivex/rxjava3/subscribers/SerializedSubscriber
       3: dup
       4: aload_1
       5: invokespecial #5                  // Method io/reactivex/rxjava3/subscribers/SerializedSubscriber."<init>":(Lorg/reactivestreams/Subscriber;)V
       8: astore_2
       9: new           #6                  // class io/reactivex/rxjava3/internal/operators/flowable/FlowableWithLatestFrom$WithLatestFromSubscriber
      12: dup
      13: aload_2
      14: aload_0
      15: getfield      #2                  // Field combiner:Lio/reactivex/rxjava3/functions/BiFunction;
      18: invokespecial #7                  // Method io/reactivex/rxjava3/internal/operators/flowable/FlowableWithLatestFrom$WithLatestFromSubscriber."<init>":(Lorg/reactivestreams/Subscriber;Lio/reactivex/rxjava3/functions/BiFunction;)V
      21: astore_3
      22: aload_2
      23: aload_3
      24: invokevirtual #8                  // Method io/reactivex/rxjava3/subscribers/SerializedSubscriber.onSubscribe:(Lorg/reactivestreams/Subscription;)V
      27: aload_0
      28: getfield      #3                  // Field other:Lorg/reactivestreams/Publisher;
      31: new           #9                  // class io/reactivex/rxjava3/internal/operators/flowable/FlowableWithLatestFrom$FlowableWithLatestSubscriber
      34: dup
      35: aload_0
      36: aload_3
      37: invokespecial #10                 // Method io/reactivex/rxjava3/internal/operators/flowable/FlowableWithLatestFrom$FlowableWithLatestSubscriber."<init>":(Lio/reactivex/rxjava3/internal/operators/flowable/FlowableWithLatestFrom;Lio/reactivex/rxjava3/internal/operators/flowable/FlowableWithLatestFrom$WithLatestFromSubscriber;)V
      40: invokeinterface #11,  2           // InterfaceMethod org/reactivestreams/Publisher.subscribe:(Lorg/reactivestreams/Subscriber;)V
      45: aload_0
      46: getfield      #12                 // Field source:Lio/reactivex/rxjava3/core/Flowable;
      49: aload_3
      50: invokevirtual #13                 // Method io/reactivex/rxjava3/core/Flowable.subscribe:(Lio/reactivex/rxjava3/core/FlowableSubscriber;)V
      53: return
}
