Compiled from "FlowableElementAt.java"
final class io.reactivex.rxjava3.internal.operators.flowable.FlowableElementAt$ElementAtSubscriber<T> extends io.reactivex.rxjava3.internal.subscriptions.DeferredScalarSubscription<T> implements io.reactivex.rxjava3.core.FlowableSubscriber<T> {
  private static final long serialVersionUID;

  final long index;

  final T defaultValue;

  final boolean errorOnFewer;

  org.reactivestreams.Subscription upstream;

  long count;

  boolean done;

  io.reactivex.rxjava3.internal.operators.flowable.FlowableElementAt$ElementAtSubscriber(org.reactivestreams.Subscriber<? super T>, long, T, boolean);
    Code:
       0: aload_0
       1: aload_1
       2: invokespecial #1                  // Method io/reactivex/rxjava3/internal/subscriptions/DeferredScalarSubscription."<init>":(Lorg/reactivestreams/Subscriber;)V
       5: aload_0
       6: lload_2
       7: putfield      #2                  // Field index:J
      10: aload_0
      11: aload         4
      13: putfield      #3                  // Field defaultValue:Ljava/lang/Object;
      16: aload_0
      17: iload         5
      19: putfield      #4                  // Field errorOnFewer:Z
      22: return

  public void onSubscribe(org.reactivestreams.Subscription);
    Code:
       0: aload_0
       1: getfield      #5                  // Field upstream:Lorg/reactivestreams/Subscription;
       4: aload_1
       5: invokestatic  #6                  // Method io/reactivex/rxjava3/internal/subscriptions/SubscriptionHelper.validate:(Lorg/reactivestreams/Subscription;Lorg/reactivestreams/Subscription;)Z
       8: ifeq          35
      11: aload_0
      12: aload_1
      13: putfield      #5                  // Field upstream:Lorg/reactivestreams/Subscription;
      16: aload_0
      17: getfield      #7                  // Field downstream:Lorg/reactivestreams/Subscriber;
      20: aload_0
      21: invokeinterface #8,  2            // InterfaceMethod org/reactivestreams/Subscriber.onSubscribe:(Lorg/reactivestreams/Subscription;)V
      26: aload_1
      27: ldc2_w        #10                 // long 9223372036854775807l
      30: invokeinterface #12,  3           // InterfaceMethod org/reactivestreams/Subscription.request:(J)V
      35: return

  public void onNext(T);
    Code:
       0: aload_0
       1: getfield      #13                 // Field done:Z
       4: ifeq          8
       7: return
       8: aload_0
       9: getfield      #14                 // Field count:J
      12: lstore_2
      13: lload_2
      14: aload_0
      15: getfield      #2                  // Field index:J
      18: lcmp
      19: ifne          42
      22: aload_0
      23: iconst_1
      24: putfield      #13                 // Field done:Z
      27: aload_0
      28: getfield      #5                  // Field upstream:Lorg/reactivestreams/Subscription;
      31: invokeinterface #15,  1           // InterfaceMethod org/reactivestreams/Subscription.cancel:()V
      36: aload_0
      37: aload_1
      38: invokevirtual #16                 // Method complete:(Ljava/lang/Object;)V
      41: return
      42: aload_0
      43: lload_2
      44: lconst_1
      45: ladd
      46: putfield      #14                 // Field count:J
      49: return

  public void onError(java.lang.Throwable);
    Code:
       0: aload_0
       1: getfield      #13                 // Field done:Z
       4: ifeq          12
       7: aload_1
       8: invokestatic  #17                 // Method io/reactivex/rxjava3/plugins/RxJavaPlugins.onError:(Ljava/lang/Throwable;)V
      11: return
      12: aload_0
      13: iconst_1
      14: putfield      #13                 // Field done:Z
      17: aload_0
      18: getfield      #7                  // Field downstream:Lorg/reactivestreams/Subscriber;
      21: aload_1
      22: invokeinterface #18,  2           // InterfaceMethod org/reactivestreams/Subscriber.onError:(Ljava/lang/Throwable;)V
      27: return

  public void onComplete();
    Code:
       0: aload_0
       1: getfield      #13                 // Field done:Z
       4: ifne          64
       7: aload_0
       8: iconst_1
       9: putfield      #13                 // Field done:Z
      12: aload_0
      13: getfield      #3                  // Field defaultValue:Ljava/lang/Object;
      16: astore_1
      17: aload_1
      18: ifnonnull     59
      21: aload_0
      22: getfield      #4                  // Field errorOnFewer:Z
      25: ifeq          47
      28: aload_0
      29: getfield      #7                  // Field downstream:Lorg/reactivestreams/Subscriber;
      32: new           #19                 // class java/util/NoSuchElementException
      35: dup
      36: invokespecial #20                 // Method java/util/NoSuchElementException."<init>":()V
      39: invokeinterface #18,  2           // InterfaceMethod org/reactivestreams/Subscriber.onError:(Ljava/lang/Throwable;)V
      44: goto          64
      47: aload_0
      48: getfield      #7                  // Field downstream:Lorg/reactivestreams/Subscriber;
      51: invokeinterface #21,  1           // InterfaceMethod org/reactivestreams/Subscriber.onComplete:()V
      56: goto          64
      59: aload_0
      60: aload_1
      61: invokevirtual #16                 // Method complete:(Ljava/lang/Object;)V
      64: return

  public void cancel();
    Code:
       0: aload_0
       1: invokespecial #22                 // Method io/reactivex/rxjava3/internal/subscriptions/DeferredScalarSubscription.cancel:()V
       4: aload_0
       5: getfield      #5                  // Field upstream:Lorg/reactivestreams/Subscription;
       8: invokeinterface #15,  1           // InterfaceMethod org/reactivestreams/Subscription.cancel:()V
      13: return
}
