Compiled from "FlowableAllSingle.java"
public final class io.reactivex.rxjava3.internal.operators.flowable.FlowableAllSingle<T> extends io.reactivex.rxjava3.core.Single<java.lang.Boolean> implements io.reactivex.rxjava3.internal.fuseable.FuseToFlowable<java.lang.Boolean> {
  final io.reactivex.rxjava3.core.Flowable<T> source;

  final io.reactivex.rxjava3.functions.Predicate<? super T> predicate;

  public io.reactivex.rxjava3.internal.operators.flowable.FlowableAllSingle(io.reactivex.rxjava3.core.Flowable<T>, io.reactivex.rxjava3.functions.Predicate<? super T>);
    Code:
       0: aload_0
       1: invokespecial #1                  // Method io/reactivex/rxjava3/core/Single."<init>":()V
       4: aload_0
       5: aload_1
       6: putfield      #2                  // Field source:Lio/reactivex/rxjava3/core/Flowable;
       9: aload_0
      10: aload_2
      11: putfield      #3                  // Field predicate:Lio/reactivex/rxjava3/functions/Predicate;
      14: return

  protected void subscribeActual(io.reactivex.rxjava3.core.SingleObserver<? super java.lang.Boolean>);
    Code:
       0: aload_0
       1: getfield      #2                  // Field source:Lio/reactivex/rxjava3/core/Flowable;
       4: new           #4                  // class io/reactivex/rxjava3/internal/operators/flowable/FlowableAllSingle$AllSubscriber
       7: dup
       8: aload_1
       9: aload_0
      10: getfield      #3                  // Field predicate:Lio/reactivex/rxjava3/functions/Predicate;
      13: invokespecial #5                  // Method io/reactivex/rxjava3/internal/operators/flowable/FlowableAllSingle$AllSubscriber."<init>":(Lio/reactivex/rxjava3/core/SingleObserver;Lio/reactivex/rxjava3/functions/Predicate;)V
      16: invokevirtual #6                  // Method io/reactivex/rxjava3/core/Flowable.subscribe:(Lio/reactivex/rxjava3/core/FlowableSubscriber;)V
      19: return

  public io.reactivex.rxjava3.core.Flowable<java.lang.Boolean> fuseToFlowable();
    Code:
       0: new           #7                  // class io/reactivex/rxjava3/internal/operators/flowable/FlowableAll
       3: dup
       4: aload_0
       5: getfield      #2                  // Field source:Lio/reactivex/rxjava3/core/Flowable;
       8: aload_0
       9: getfield      #3                  // Field predicate:Lio/reactivex/rxjava3/functions/Predicate;
      12: invokespecial #8                  // Method io/reactivex/rxjava3/internal/operators/flowable/FlowableAll."<init>":(Lio/reactivex/rxjava3/core/Flowable;Lio/reactivex/rxjava3/functions/Predicate;)V
      15: invokestatic  #9                  // Method io/reactivex/rxjava3/plugins/RxJavaPlugins.onAssembly:(Lio/reactivex/rxjava3/core/Flowable;)Lio/reactivex/rxjava3/core/Flowable;
      18: areturn
}
