Compiled from "FlowableIgnoreElements.java"
final class io.reactivex.rxjava3.internal.operators.flowable.FlowableIgnoreElements$IgnoreElementsSubscriber<T> implements io.reactivex.rxjava3.core.FlowableSubscriber<T>, io.reactivex.rxjava3.operators.QueueSubscription<T> {
  final org.reactivestreams.Subscriber<? super T> downstream;

  org.reactivestreams.Subscription upstream;

  io.reactivex.rxjava3.internal.operators.flowable.FlowableIgnoreElements$IgnoreElementsSubscriber(org.reactivestreams.Subscriber<? super T>);
    Code:
       0: aload_0
       1: invokespecial #1                  // Method java/lang/Object."<init>":()V
       4: aload_0
       5: aload_1
       6: putfield      #2                  // Field downstream:Lorg/reactivestreams/Subscriber;
       9: return

  public void onSubscribe(org.reactivestreams.Subscription);
    Code:
       0: aload_0
       1: getfield      #3                  // Field upstream:Lorg/reactivestreams/Subscription;
       4: aload_1
       5: invokestatic  #4                  // Method io/reactivex/rxjava3/internal/subscriptions/SubscriptionHelper.validate:(Lorg/reactivestreams/Subscription;Lorg/reactivestreams/Subscription;)Z
       8: ifeq          35
      11: aload_0
      12: aload_1
      13: putfield      #3                  // Field upstream:Lorg/reactivestreams/Subscription;
      16: aload_0
      17: getfield      #2                  // Field downstream:Lorg/reactivestreams/Subscriber;
      20: aload_0
      21: invokeinterface #5,  2            // InterfaceMethod org/reactivestreams/Subscriber.onSubscribe:(Lorg/reactivestreams/Subscription;)V
      26: aload_1
      27: ldc2_w        #7                  // long 9223372036854775807l
      30: invokeinterface #9,  3            // InterfaceMethod org/reactivestreams/Subscription.request:(J)V
      35: return

  public void onNext(T);
    Code:
       0: return

  public void onError(java.lang.Throwable);
    Code:
       0: aload_0
       1: getfield      #2                  // Field downstream:Lorg/reactivestreams/Subscriber;
       4: aload_1
       5: invokeinterface #10,  2           // InterfaceMethod org/reactivestreams/Subscriber.onError:(Ljava/lang/Throwable;)V
      10: return

  public void onComplete();
    Code:
       0: aload_0
       1: getfield      #2                  // Field downstream:Lorg/reactivestreams/Subscriber;
       4: invokeinterface #11,  1           // InterfaceMethod org/reactivestreams/Subscriber.onComplete:()V
       9: return

  public boolean offer(T);
    Code:
       0: new           #12                 // class java/lang/UnsupportedOperationException
       3: dup
       4: ldc           #13                 // String Should not be called!
       6: invokespecial #14                 // Method java/lang/UnsupportedOperationException."<init>":(Ljava/lang/String;)V
       9: athrow

  public boolean offer(T, T);
    Code:
       0: new           #12                 // class java/lang/UnsupportedOperationException
       3: dup
       4: ldc           #13                 // String Should not be called!
       6: invokespecial #14                 // Method java/lang/UnsupportedOperationException."<init>":(Ljava/lang/String;)V
       9: athrow

  public T poll();
    Code:
       0: aconst_null
       1: areturn

  public boolean isEmpty();
    Code:
       0: iconst_1
       1: ireturn

  public void clear();
    Code:
       0: return

  public void request(long);
    Code:
       0: return

  public void cancel();
    Code:
       0: aload_0
       1: getfield      #3                  // Field upstream:Lorg/reactivestreams/Subscription;
       4: invokeinterface #15,  1           // InterfaceMethod org/reactivestreams/Subscription.cancel:()V
       9: return

  public int requestFusion(int);
    Code:
       0: iload_1
       1: iconst_2
       2: iand
       3: ireturn
}
