Compiled from "FlowableBufferBoundary.java"
final class io.reactivex.rxjava3.internal.operators.flowable.FlowableBufferBoundary$BufferBoundarySubscriber$BufferOpenSubscriber<Open> extends java.util.concurrent.atomic.AtomicReference<org.reactivestreams.Subscription> implements io.reactivex.rxjava3.core.FlowableSubscriber<Open>, io.reactivex.rxjava3.disposables.Disposable {
  private static final long serialVersionUID;

  final io.reactivex.rxjava3.internal.operators.flowable.FlowableBufferBoundary$BufferBoundarySubscriber<?, ?, Open, ?> parent;

  io.reactivex.rxjava3.internal.operators.flowable.FlowableBufferBoundary$BufferBoundarySubscriber$BufferOpenSubscriber(io.reactivex.rxjava3.internal.operators.flowable.FlowableBufferBoundary$BufferBoundarySubscriber<?, ?, Open, ?>);
    Code:
       0: aload_0
       1: invokespecial #1                  // Method java/util/concurrent/atomic/AtomicReference."<init>":()V
       4: aload_0
       5: aload_1
       6: putfield      #2                  // Field parent:Lio/reactivex/rxjava3/internal/operators/flowable/FlowableBufferBoundary$BufferBoundarySubscriber;
       9: return

  public void onSubscribe(org.reactivestreams.Subscription);
    Code:
       0: aload_0
       1: aload_1
       2: ldc2_w        #4                  // long 9223372036854775807l
       5: invokestatic  #6                  // Method io/reactivex/rxjava3/internal/subscriptions/SubscriptionHelper.setOnce:(Ljava/util/concurrent/atomic/AtomicReference;Lorg/reactivestreams/Subscription;J)Z
       8: pop
       9: return

  public void onNext(Open);
    Code:
       0: aload_0
       1: getfield      #2                  // Field parent:Lio/reactivex/rxjava3/internal/operators/flowable/FlowableBufferBoundary$BufferBoundarySubscriber;
       4: aload_1
       5: invokevirtual #7                  // Method io/reactivex/rxjava3/internal/operators/flowable/FlowableBufferBoundary$BufferBoundarySubscriber.open:(Ljava/lang/Object;)V
       8: return

  public void onError(java.lang.Throwable);
    Code:
       0: aload_0
       1: getstatic     #8                  // Field io/reactivex/rxjava3/internal/subscriptions/SubscriptionHelper.CANCELLED:Lio/reactivex/rxjava3/internal/subscriptions/SubscriptionHelper;
       4: invokevirtual #9                  // Method lazySet:(Ljava/lang/Object;)V
       7: aload_0
       8: getfield      #2                  // Field parent:Lio/reactivex/rxjava3/internal/operators/flowable/FlowableBufferBoundary$BufferBoundarySubscriber;
      11: aload_0
      12: aload_1
      13: invokevirtual #10                 // Method io/reactivex/rxjava3/internal/operators/flowable/FlowableBufferBoundary$BufferBoundarySubscriber.boundaryError:(Lio/reactivex/rxjava3/disposables/Disposable;Ljava/lang/Throwable;)V
      16: return

  public void onComplete();
    Code:
       0: aload_0
       1: getstatic     #8                  // Field io/reactivex/rxjava3/internal/subscriptions/SubscriptionHelper.CANCELLED:Lio/reactivex/rxjava3/internal/subscriptions/SubscriptionHelper;
       4: invokevirtual #9                  // Method lazySet:(Ljava/lang/Object;)V
       7: aload_0
       8: getfield      #2                  // Field parent:Lio/reactivex/rxjava3/internal/operators/flowable/FlowableBufferBoundary$BufferBoundarySubscriber;
      11: aload_0
      12: invokevirtual #11                 // Method io/reactivex/rxjava3/internal/operators/flowable/FlowableBufferBoundary$BufferBoundarySubscriber.openComplete:(Lio/reactivex/rxjava3/internal/operators/flowable/FlowableBufferBoundary$BufferBoundarySubscriber$BufferOpenSubscriber;)V
      15: return

  public void dispose();
    Code:
       0: aload_0
       1: invokestatic  #12                 // Method io/reactivex/rxjava3/internal/subscriptions/SubscriptionHelper.cancel:(Ljava/util/concurrent/atomic/AtomicReference;)Z
       4: pop
       5: return

  public boolean isDisposed();
    Code:
       0: aload_0
       1: invokevirtual #13                 // Method get:()Ljava/lang/Object;
       4: getstatic     #8                  // Field io/reactivex/rxjava3/internal/subscriptions/SubscriptionHelper.CANCELLED:Lio/reactivex/rxjava3/internal/subscriptions/SubscriptionHelper;
       7: if_acmpne     14
      10: iconst_1
      11: goto          15
      14: iconst_0
      15: ireturn
}
