Compiled from "FlowableZip.java"
public final class io.reactivex.rxjava3.internal.operators.flowable.FlowableZip<T, R> extends io.reactivex.rxjava3.core.Flowable<R> {
  final org.reactivestreams.Publisher<? extends T>[] sources;

  final java.lang.Iterable<? extends org.reactivestreams.Publisher<? extends T>> sourcesIterable;

  final io.reactivex.rxjava3.functions.Function<? super java.lang.Object[], ? extends R> zipper;

  final int bufferSize;

  final boolean delayError;

  public io.reactivex.rxjava3.internal.operators.flowable.FlowableZip(org.reactivestreams.Publisher<? extends T>[], java.lang.Iterable<? extends org.reactivestreams.Publisher<? extends T>>, io.reactivex.rxjava3.functions.Function<? super java.lang.Object[], ? extends R>, int, boolean);
    Code:
       0: aload_0
       1: invokespecial #1                  // Method io/reactivex/rxjava3/core/Flowable."<init>":()V
       4: aload_0
       5: aload_1
       6: putfield      #2                  // Field sources:[Lorg/reactivestreams/Publisher;
       9: aload_0
      10: aload_2
      11: putfield      #3                  // Field sourcesIterable:Ljava/lang/Iterable;
      14: aload_0
      15: aload_3
      16: putfield      #4                  // Field zipper:Lio/reactivex/rxjava3/functions/Function;
      19: aload_0
      20: iload         4
      22: putfield      #5                  // Field bufferSize:I
      25: aload_0
      26: iload         5
      28: putfield      #6                  // Field delayError:Z
      31: return

  public void subscribeActual(org.reactivestreams.Subscriber<? super R>);
    Code:
       0: aload_0
       1: getfield      #2                  // Field sources:[Lorg/reactivestreams/Publisher;
       4: astore_2
       5: iconst_0
       6: istore_3
       7: aload_2
       8: ifnonnull     92
      11: bipush        8
      13: anewarray     #7                  // class org/reactivestreams/Publisher
      16: astore_2
      17: aload_0
      18: getfield      #3                  // Field sourcesIterable:Ljava/lang/Iterable;
      21: invokeinterface #8,  1            // InterfaceMethod java/lang/Iterable.iterator:()Ljava/util/Iterator;
      26: astore        4
      28: aload         4
      30: invokeinterface #9,  1            // InterfaceMethod java/util/Iterator.hasNext:()Z
      35: ifeq          89
      38: aload         4
      40: invokeinterface #10,  1           // InterfaceMethod java/util/Iterator.next:()Ljava/lang/Object;
      45: checkcast     #7                  // class org/reactivestreams/Publisher
      48: astore        5
      50: iload_3
      51: aload_2
      52: arraylength
      53: if_icmpne     78
      56: iload_3
      57: iload_3
      58: iconst_2
      59: ishr
      60: iadd
      61: anewarray     #7                  // class org/reactivestreams/Publisher
      64: astore        6
      66: aload_2
      67: iconst_0
      68: aload         6
      70: iconst_0
      71: iload_3
      72: invokestatic  #11                 // Method java/lang/System.arraycopy:(Ljava/lang/Object;ILjava/lang/Object;II)V
      75: aload         6
      77: astore_2
      78: aload_2
      79: iload_3
      80: iinc          3, 1
      83: aload         5
      85: aastore
      86: goto          28
      89: goto          95
      92: aload_2
      93: arraylength
      94: istore_3
      95: iload_3
      96: ifne          104
      99: aload_1
     100: invokestatic  #12                 // Method io/reactivex/rxjava3/internal/subscriptions/EmptySubscription.complete:(Lorg/reactivestreams/Subscriber;)V
     103: return
     104: new           #13                 // class io/reactivex/rxjava3/internal/operators/flowable/FlowableZip$ZipCoordinator
     107: dup
     108: aload_1
     109: aload_0
     110: getfield      #4                  // Field zipper:Lio/reactivex/rxjava3/functions/Function;
     113: iload_3
     114: aload_0
     115: getfield      #5                  // Field bufferSize:I
     118: aload_0
     119: getfield      #6                  // Field delayError:Z
     122: invokespecial #14                 // Method io/reactivex/rxjava3/internal/operators/flowable/FlowableZip$ZipCoordinator."<init>":(Lorg/reactivestreams/Subscriber;Lio/reactivex/rxjava3/functions/Function;IIZ)V
     125: astore        4
     127: aload_1
     128: aload         4
     130: invokeinterface #15,  2           // InterfaceMethod org/reactivestreams/Subscriber.onSubscribe:(Lorg/reactivestreams/Subscription;)V
     135: aload         4
     137: aload_2
     138: iload_3
     139: invokevirtual #16                 // Method io/reactivex/rxjava3/internal/operators/flowable/FlowableZip$ZipCoordinator.subscribe:([Lorg/reactivestreams/Publisher;I)V
     142: return
}
