Compiled from "FlowableDoAfterNext.java"
public final class io.reactivex.rxjava3.internal.operators.flowable.FlowableDoAfterNext<T> extends io.reactivex.rxjava3.internal.operators.flowable.AbstractFlowableWithUpstream<T, T> {
  final io.reactivex.rxjava3.functions.Consumer<? super T> onAfterNext;

  public io.reactivex.rxjava3.internal.operators.flowable.FlowableDoAfterNext(io.reactivex.rxjava3.core.Flowable<T>, io.reactivex.rxjava3.functions.Consumer<? super T>);
    Code:
       0: aload_0
       1: aload_1
       2: invokespecial #1                  // Method io/reactivex/rxjava3/internal/operators/flowable/AbstractFlowableWithUpstream."<init>":(Lio/reactivex/rxjava3/core/Flowable;)V
       5: aload_0
       6: aload_2
       7: putfield      #2                  // Field onAfterNext:Lio/reactivex/rxjava3/functions/Consumer;
      10: return

  protected void subscribeActual(org.reactivestreams.Subscriber<? super T>);
    Code:
       0: aload_1
       1: instanceof    #3                  // class io/reactivex/rxjava3/operators/ConditionalSubscriber
       4: ifeq          32
       7: aload_0
       8: getfield      #4                  // Field source:Lio/reactivex/rxjava3/core/Flowable;
      11: new           #5                  // class io/reactivex/rxjava3/internal/operators/flowable/FlowableDoAfterNext$DoAfterConditionalSubscriber
      14: dup
      15: aload_1
      16: checkcast     #3                  // class io/reactivex/rxjava3/operators/ConditionalSubscriber
      19: aload_0
      20: getfield      #2                  // Field onAfterNext:Lio/reactivex/rxjava3/functions/Consumer;
      23: invokespecial #6                  // Method io/reactivex/rxjava3/internal/operators/flowable/FlowableDoAfterNext$DoAfterConditionalSubscriber."<init>":(Lio/reactivex/rxjava3/operators/ConditionalSubscriber;Lio/reactivex/rxjava3/functions/Consumer;)V
      26: invokevirtual #7                  // Method io/reactivex/rxjava3/core/Flowable.subscribe:(Lio/reactivex/rxjava3/core/FlowableSubscriber;)V
      29: goto          51
      32: aload_0
      33: getfield      #4                  // Field source:Lio/reactivex/rxjava3/core/Flowable;
      36: new           #8                  // class io/reactivex/rxjava3/internal/operators/flowable/FlowableDoAfterNext$DoAfterSubscriber
      39: dup
      40: aload_1
      41: aload_0
      42: getfield      #2                  // Field onAfterNext:Lio/reactivex/rxjava3/functions/Consumer;
      45: invokespecial #9                  // Method io/reactivex/rxjava3/internal/operators/flowable/FlowableDoAfterNext$DoAfterSubscriber."<init>":(Lorg/reactivestreams/Subscriber;Lio/reactivex/rxjava3/functions/Consumer;)V
      48: invokevirtual #7                  // Method io/reactivex/rxjava3/core/Flowable.subscribe:(Lio/reactivex/rxjava3/core/FlowableSubscriber;)V
      51: return
}
