Compiled from "FlowableOnBackpressureReduceWith.java"
public final class io.reactivex.rxjava3.internal.operators.flowable.FlowableOnBackpressureReduceWith<T, R> extends io.reactivex.rxjava3.internal.operators.flowable.AbstractFlowableWithUpstream<T, R> {
  final io.reactivex.rxjava3.functions.BiFunction<R, ? super T, R> reducer;

  final io.reactivex.rxjava3.functions.Supplier<R> supplier;

  public io.reactivex.rxjava3.internal.operators.flowable.FlowableOnBackpressureReduceWith(io.reactivex.rxjava3.core.Flowable<T>, io.reactivex.rxjava3.functions.Supplier<R>, io.reactivex.rxjava3.functions.BiFunction<R, ? super T, R>);
    Code:
       0: aload_0
       1: aload_1
       2: invokespecial #1                  // Method io/reactivex/rxjava3/internal/operators/flowable/AbstractFlowableWithUpstream."<init>":(Lio/reactivex/rxjava3/core/Flowable;)V
       5: aload_0
       6: aload_3
       7: putfield      #2                  // Field reducer:Lio/reactivex/rxjava3/functions/BiFunction;
      10: aload_0
      11: aload_2
      12: putfield      #3                  // Field supplier:Lio/reactivex/rxjava3/functions/Supplier;
      15: return

  protected void subscribeActual(org.reactivestreams.Subscriber<? super R>);
    Code:
       0: aload_0
       1: getfield      #4                  // Field source:Lio/reactivex/rxjava3/core/Flowable;
       4: new           #5                  // class io/reactivex/rxjava3/internal/operators/flowable/FlowableOnBackpressureReduceWith$BackpressureReduceWithSubscriber
       7: dup
       8: aload_1
       9: aload_0
      10: getfield      #3                  // Field supplier:Lio/reactivex/rxjava3/functions/Supplier;
      13: aload_0
      14: getfield      #2                  // Field reducer:Lio/reactivex/rxjava3/functions/BiFunction;
      17: invokespecial #6                  // Method io/reactivex/rxjava3/internal/operators/flowable/FlowableOnBackpressureReduceWith$BackpressureReduceWithSubscriber."<init>":(Lorg/reactivestreams/Subscriber;Lio/reactivex/rxjava3/functions/Supplier;Lio/reactivex/rxjava3/functions/BiFunction;)V
      20: invokevirtual #7                  // Method io/reactivex/rxjava3/core/Flowable.subscribe:(Lio/reactivex/rxjava3/core/FlowableSubscriber;)V
      23: return
}
