Compiled from "FlowableOnErrorNext.java"
final class io.reactivex.rxjava3.internal.operators.flowable.FlowableOnErrorNext$OnErrorNextSubscriber<T> extends io.reactivex.rxjava3.internal.subscriptions.SubscriptionArbiter implements io.reactivex.rxjava3.core.FlowableSubscriber<T> {
  private static final long serialVersionUID;

  final org.reactivestreams.Subscriber<? super T> downstream;

  final io.reactivex.rxjava3.functions.Function<? super java.lang.Throwable, ? extends org.reactivestreams.Publisher<? extends T>> nextSupplier;

  boolean once;

  boolean done;

  long produced;

  io.reactivex.rxjava3.internal.operators.flowable.FlowableOnErrorNext$OnErrorNextSubscriber(org.reactivestreams.Subscriber<? super T>, io.reactivex.rxjava3.functions.Function<? super java.lang.Throwable, ? extends org.reactivestreams.Publisher<? extends T>>);
    Code:
       0: aload_0
       1: iconst_0
       2: invokespecial #1                  // Method io/reactivex/rxjava3/internal/subscriptions/SubscriptionArbiter."<init>":(Z)V
       5: aload_0
       6: aload_1
       7: putfield      #2                  // Field downstream:Lorg/reactivestreams/Subscriber;
      10: aload_0
      11: aload_2
      12: putfield      #3                  // Field nextSupplier:Lio/reactivex/rxjava3/functions/Function;
      15: return

  public void onSubscribe(org.reactivestreams.Subscription);
    Code:
       0: aload_0
       1: aload_1
       2: invokevirtual #4                  // Method setSubscription:(Lorg/reactivestreams/Subscription;)V
       5: return

  public void onNext(T);
    Code:
       0: aload_0
       1: getfield      #5                  // Field done:Z
       4: ifeq          8
       7: return
       8: aload_0
       9: getfield      #6                  // Field once:Z
      12: ifne          25
      15: aload_0
      16: dup
      17: getfield      #7                  // Field produced:J
      20: lconst_1
      21: ladd
      22: putfield      #7                  // Field produced:J
      25: aload_0
      26: getfield      #2                  // Field downstream:Lorg/reactivestreams/Subscriber;
      29: aload_1
      30: invokeinterface #8,  2            // InterfaceMethod org/reactivestreams/Subscriber.onNext:(Ljava/lang/Object;)V
      35: return

  public void onError(java.lang.Throwable);
    Code:
       0: aload_0
       1: getfield      #6                  // Field once:Z
       4: ifeq          30
       7: aload_0
       8: getfield      #5                  // Field done:Z
      11: ifeq          19
      14: aload_1
      15: invokestatic  #9                  // Method io/reactivex/rxjava3/plugins/RxJavaPlugins.onError:(Ljava/lang/Throwable;)V
      18: return
      19: aload_0
      20: getfield      #2                  // Field downstream:Lorg/reactivestreams/Subscriber;
      23: aload_1
      24: invokeinterface #10,  2           // InterfaceMethod org/reactivestreams/Subscriber.onError:(Ljava/lang/Throwable;)V
      29: return
      30: aload_0
      31: iconst_1
      32: putfield      #6                  // Field once:Z
      35: aload_0
      36: getfield      #3                  // Field nextSupplier:Lio/reactivex/rxjava3/functions/Function;
      39: aload_1
      40: invokeinterface #11,  2           // InterfaceMethod io/reactivex/rxjava3/functions/Function.apply:(Ljava/lang/Object;)Ljava/lang/Object;
      45: ldc           #12                 // String The nextSupplier returned a null Publisher
      47: invokestatic  #13                 // Method java/util/Objects.requireNonNull:(Ljava/lang/Object;Ljava/lang/String;)Ljava/lang/Object;
      50: checkcast     #14                 // class org/reactivestreams/Publisher
      53: astore_2
      54: goto          91
      57: astore_3
      58: aload_3
      59: invokestatic  #16                 // Method io/reactivex/rxjava3/exceptions/Exceptions.throwIfFatal:(Ljava/lang/Throwable;)V
      62: aload_0
      63: getfield      #2                  // Field downstream:Lorg/reactivestreams/Subscriber;
      66: new           #17                 // class io/reactivex/rxjava3/exceptions/CompositeException
      69: dup
      70: iconst_2
      71: anewarray     #18                 // class java/lang/Throwable
      74: dup
      75: iconst_0
      76: aload_1
      77: aastore
      78: dup
      79: iconst_1
      80: aload_3
      81: aastore
      82: invokespecial #19                 // Method io/reactivex/rxjava3/exceptions/CompositeException."<init>":([Ljava/lang/Throwable;)V
      85: invokeinterface #10,  2           // InterfaceMethod org/reactivestreams/Subscriber.onError:(Ljava/lang/Throwable;)V
      90: return
      91: aload_0
      92: getfield      #7                  // Field produced:J
      95: lstore_3
      96: lload_3
      97: lconst_0
      98: lcmp
      99: ifeq          107
     102: aload_0
     103: lload_3
     104: invokevirtual #20                 // Method produced:(J)V
     107: aload_2
     108: aload_0
     109: invokeinterface #21,  2           // InterfaceMethod org/reactivestreams/Publisher.subscribe:(Lorg/reactivestreams/Subscriber;)V
     114: return
    Exception table:
       from    to  target type
          35    54    57   Class java/lang/Throwable

  public void onComplete();
    Code:
       0: aload_0
       1: getfield      #5                  // Field done:Z
       4: ifeq          8
       7: return
       8: aload_0
       9: iconst_1
      10: putfield      #5                  // Field done:Z
      13: aload_0
      14: iconst_1
      15: putfield      #6                  // Field once:Z
      18: aload_0
      19: getfield      #2                  // Field downstream:Lorg/reactivestreams/Subscriber;
      22: invokeinterface #22,  1           // InterfaceMethod org/reactivestreams/Subscriber.onComplete:()V
      27: return
}
