Compiled from "FlowableWithLatestFromMany.java"
public final class io.reactivex.rxjava3.internal.operators.flowable.FlowableWithLatestFromMany<T, R> extends io.reactivex.rxjava3.internal.operators.flowable.AbstractFlowableWithUpstream<T, R> {
  final org.reactivestreams.Publisher<?>[] otherArray;

  final java.lang.Iterable<? extends org.reactivestreams.Publisher<?>> otherIterable;

  final io.reactivex.rxjava3.functions.Function<? super java.lang.Object[], R> combiner;

  public io.reactivex.rxjava3.internal.operators.flowable.FlowableWithLatestFromMany(io.reactivex.rxjava3.core.Flowable<T>, org.reactivestreams.Publisher<?>[], io.reactivex.rxjava3.functions.Function<? super java.lang.Object[], R>);
    Code:
       0: aload_0
       1: aload_1
       2: invokespecial #1                  // Method io/reactivex/rxjava3/internal/operators/flowable/AbstractFlowableWithUpstream."<init>":(Lio/reactivex/rxjava3/core/Flowable;)V
       5: aload_0
       6: aload_2
       7: putfield      #2                  // Field otherArray:[Lorg/reactivestreams/Publisher;
      10: aload_0
      11: aconst_null
      12: putfield      #3                  // Field otherIterable:Ljava/lang/Iterable;
      15: aload_0
      16: aload_3
      17: putfield      #4                  // Field combiner:Lio/reactivex/rxjava3/functions/Function;
      20: return

  public io.reactivex.rxjava3.internal.operators.flowable.FlowableWithLatestFromMany(io.reactivex.rxjava3.core.Flowable<T>, java.lang.Iterable<? extends org.reactivestreams.Publisher<?>>, io.reactivex.rxjava3.functions.Function<? super java.lang.Object[], R>);
    Code:
       0: aload_0
       1: aload_1
       2: invokespecial #1                  // Method io/reactivex/rxjava3/internal/operators/flowable/AbstractFlowableWithUpstream."<init>":(Lio/reactivex/rxjava3/core/Flowable;)V
       5: aload_0
       6: aconst_null
       7: putfield      #2                  // Field otherArray:[Lorg/reactivestreams/Publisher;
      10: aload_0
      11: aload_2
      12: putfield      #3                  // Field otherIterable:Ljava/lang/Iterable;
      15: aload_0
      16: aload_3
      17: putfield      #4                  // Field combiner:Lio/reactivex/rxjava3/functions/Function;
      20: return

  protected void subscribeActual(org.reactivestreams.Subscriber<? super R>);
    Code:
       0: aload_0
       1: getfield      #2                  // Field otherArray:[Lorg/reactivestreams/Publisher;
       4: astore_2
       5: iconst_0
       6: istore_3
       7: aload_2
       8: ifnonnull     97
      11: bipush        8
      13: anewarray     #5                  // class org/reactivestreams/Publisher
      16: astore_2
      17: aload_0
      18: getfield      #3                  // Field otherIterable:Ljava/lang/Iterable;
      21: invokeinterface #6,  1            // InterfaceMethod java/lang/Iterable.iterator:()Ljava/util/Iterator;
      26: astore        4
      28: aload         4
      30: invokeinterface #7,  1            // InterfaceMethod java/util/Iterator.hasNext:()Z
      35: ifeq          80
      38: aload         4
      40: invokeinterface #8,  1            // InterfaceMethod java/util/Iterator.next:()Ljava/lang/Object;
      45: checkcast     #5                  // class org/reactivestreams/Publisher
      48: astore        5
      50: iload_3
      51: aload_2
      52: arraylength
      53: if_icmpne     69
      56: aload_2
      57: iload_3
      58: iload_3
      59: iconst_1
      60: ishr
      61: iadd
      62: invokestatic  #9                  // Method java/util/Arrays.copyOf:([Ljava/lang/Object;I)[Ljava/lang/Object;
      65: checkcast     #10                 // class "[Lorg/reactivestreams/Publisher;"
      68: astore_2
      69: aload_2
      70: iload_3
      71: iinc          3, 1
      74: aload         5
      76: aastore
      77: goto          28
      80: goto          100
      83: astore        4
      85: aload         4
      87: invokestatic  #12                 // Method io/reactivex/rxjava3/exceptions/Exceptions.throwIfFatal:(Ljava/lang/Throwable;)V
      90: aload         4
      92: aload_1
      93: invokestatic  #13                 // Method io/reactivex/rxjava3/internal/subscriptions/EmptySubscription.error:(Ljava/lang/Throwable;Lorg/reactivestreams/Subscriber;)V
      96: return
      97: aload_2
      98: arraylength
      99: istore_3
     100: iload_3
     101: ifne          128
     104: new           #14                 // class io/reactivex/rxjava3/internal/operators/flowable/FlowableMap
     107: dup
     108: aload_0
     109: getfield      #15                 // Field source:Lio/reactivex/rxjava3/core/Flowable;
     112: new           #16                 // class io/reactivex/rxjava3/internal/operators/flowable/FlowableWithLatestFromMany$SingletonArrayFunc
     115: dup
     116: aload_0
     117: invokespecial #17                 // Method io/reactivex/rxjava3/internal/operators/flowable/FlowableWithLatestFromMany$SingletonArrayFunc."<init>":(Lio/reactivex/rxjava3/internal/operators/flowable/FlowableWithLatestFromMany;)V
     120: invokespecial #18                 // Method io/reactivex/rxjava3/internal/operators/flowable/FlowableMap."<init>":(Lio/reactivex/rxjava3/core/Flowable;Lio/reactivex/rxjava3/functions/Function;)V
     123: aload_1
     124: invokevirtual #19                 // Method io/reactivex/rxjava3/internal/operators/flowable/FlowableMap.subscribeActual:(Lorg/reactivestreams/Subscriber;)V
     127: return
     128: new           #20                 // class io/reactivex/rxjava3/internal/operators/flowable/FlowableWithLatestFromMany$WithLatestFromSubscriber
     131: dup
     132: aload_1
     133: aload_0
     134: getfield      #4                  // Field combiner:Lio/reactivex/rxjava3/functions/Function;
     137: iload_3
     138: invokespecial #21                 // Method io/reactivex/rxjava3/internal/operators/flowable/FlowableWithLatestFromMany$WithLatestFromSubscriber."<init>":(Lorg/reactivestreams/Subscriber;Lio/reactivex/rxjava3/functions/Function;I)V
     141: astore        4
     143: aload_1
     144: aload         4
     146: invokeinterface #22,  2           // InterfaceMethod org/reactivestreams/Subscriber.onSubscribe:(Lorg/reactivestreams/Subscription;)V
     151: aload         4
     153: aload_2
     154: iload_3
     155: invokevirtual #23                 // Method io/reactivex/rxjava3/internal/operators/flowable/FlowableWithLatestFromMany$WithLatestFromSubscriber.subscribe:([Lorg/reactivestreams/Publisher;I)V
     158: aload_0
     159: getfield      #15                 // Field source:Lio/reactivex/rxjava3/core/Flowable;
     162: aload         4
     164: invokevirtual #24                 // Method io/reactivex/rxjava3/core/Flowable.subscribe:(Lio/reactivex/rxjava3/core/FlowableSubscriber;)V
     167: return
    Exception table:
       from    to  target type
          17    80    83   Class java/lang/Throwable
}
