Compiled from "FlowableReplay.java"
final class io.reactivex.rxjava3.internal.operators.flowable.FlowableReplay$MulticastFlowable<R, U> extends io.reactivex.rxjava3.core.Flowable<R> {
  private final io.reactivex.rxjava3.functions.Supplier<? extends io.reactivex.rxjava3.flowables.ConnectableFlowable<U>> connectableFactory;

  private final io.reactivex.rxjava3.functions.Function<? super io.reactivex.rxjava3.core.Flowable<U>, ? extends org.reactivestreams.Publisher<R>> selector;

  io.reactivex.rxjava3.internal.operators.flowable.FlowableReplay$MulticastFlowable(io.reactivex.rxjava3.functions.Supplier<? extends io.reactivex.rxjava3.flowables.ConnectableFlowable<U>>, io.reactivex.rxjava3.functions.Function<? super io.reactivex.rxjava3.core.Flowable<U>, ? extends org.reactivestreams.Publisher<R>>);
    Code:
       0: aload_0
       1: invokespecial #1                  // Method io/reactivex/rxjava3/core/Flowable."<init>":()V
       4: aload_0
       5: aload_1
       6: putfield      #2                  // Field connectableFactory:Lio/reactivex/rxjava3/functions/Supplier;
       9: aload_0
      10: aload_2
      11: putfield      #3                  // Field selector:Lio/reactivex/rxjava3/functions/Function;
      14: return

  protected void subscribeActual(org.reactivestreams.Subscriber<? super R>);
    Code:
       0: aload_0
       1: getfield      #2                  // Field connectableFactory:Lio/reactivex/rxjava3/functions/Supplier;
       4: invokeinterface #4,  1            // InterfaceMethod io/reactivex/rxjava3/functions/Supplier.get:()Ljava/lang/Object;
       9: ldc           #5                  // String The connectableFactory returned a null ConnectableFlowable.
      11: invokestatic  #6                  // Method io/reactivex/rxjava3/internal/util/ExceptionHelper.nullCheck:(Ljava/lang/Object;Ljava/lang/String;)Ljava/lang/Object;
      14: checkcast     #7                  // class io/reactivex/rxjava3/flowables/ConnectableFlowable
      17: astore_2
      18: goto          32
      21: astore_3
      22: aload_3
      23: invokestatic  #9                  // Method io/reactivex/rxjava3/exceptions/Exceptions.throwIfFatal:(Ljava/lang/Throwable;)V
      26: aload_3
      27: aload_1
      28: invokestatic  #10                 // Method io/reactivex/rxjava3/internal/subscriptions/EmptySubscription.error:(Ljava/lang/Throwable;Lorg/reactivestreams/Subscriber;)V
      31: return
      32: aload_0
      33: getfield      #3                  // Field selector:Lio/reactivex/rxjava3/functions/Function;
      36: aload_2
      37: invokeinterface #11,  2           // InterfaceMethod io/reactivex/rxjava3/functions/Function.apply:(Ljava/lang/Object;)Ljava/lang/Object;
      42: ldc           #12                 // String The selector returned a null Publisher.
      44: invokestatic  #6                  // Method io/reactivex/rxjava3/internal/util/ExceptionHelper.nullCheck:(Ljava/lang/Object;Ljava/lang/String;)Ljava/lang/Object;
      47: checkcast     #13                 // class org/reactivestreams/Publisher
      50: astore_3
      51: goto          68
      54: astore        4
      56: aload         4
      58: invokestatic  #9                  // Method io/reactivex/rxjava3/exceptions/Exceptions.throwIfFatal:(Ljava/lang/Throwable;)V
      61: aload         4
      63: aload_1
      64: invokestatic  #10                 // Method io/reactivex/rxjava3/internal/subscriptions/EmptySubscription.error:(Ljava/lang/Throwable;Lorg/reactivestreams/Subscriber;)V
      67: return
      68: new           #14                 // class io/reactivex/rxjava3/internal/subscribers/SubscriberResourceWrapper
      71: dup
      72: aload_1
      73: invokespecial #15                 // Method io/reactivex/rxjava3/internal/subscribers/SubscriberResourceWrapper."<init>":(Lorg/reactivestreams/Subscriber;)V
      76: astore        4
      78: aload_3
      79: aload         4
      81: invokeinterface #16,  2           // InterfaceMethod org/reactivestreams/Publisher.subscribe:(Lorg/reactivestreams/Subscriber;)V
      86: aload_2
      87: new           #17                 // class io/reactivex/rxjava3/internal/operators/flowable/FlowableReplay$MulticastFlowable$DisposableConsumer
      90: dup
      91: aload_0
      92: aload         4
      94: invokespecial #18                 // Method io/reactivex/rxjava3/internal/operators/flowable/FlowableReplay$MulticastFlowable$DisposableConsumer."<init>":(Lio/reactivex/rxjava3/internal/operators/flowable/FlowableReplay$MulticastFlowable;Lio/reactivex/rxjava3/internal/subscribers/SubscriberResourceWrapper;)V
      97: invokevirtual #19                 // Method io/reactivex/rxjava3/flowables/ConnectableFlowable.connect:(Lio/reactivex/rxjava3/functions/Consumer;)V
     100: return
    Exception table:
       from    to  target type
           0    18    21   Class java/lang/Throwable
          32    51    54   Class java/lang/Throwable
}
