Compiled from "FlowableConcatWithCompletable.java"
final class io.reactivex.rxjava3.internal.operators.flowable.FlowableConcatWithCompletable$ConcatWithSubscriber<T> extends java.util.concurrent.atomic.AtomicReference<io.reactivex.rxjava3.disposables.Disposable> implements io.reactivex.rxjava3.core.FlowableSubscriber<T>, io.reactivex.rxjava3.core.CompletableObserver, org.reactivestreams.Subscription {
  private static final long serialVersionUID;

  final org.reactivestreams.Subscriber<? super T> downstream;

  org.reactivestreams.Subscription upstream;

  io.reactivex.rxjava3.core.CompletableSource other;

  boolean inCompletable;

  io.reactivex.rxjava3.internal.operators.flowable.FlowableConcatWithCompletable$ConcatWithSubscriber(org.reactivestreams.Subscriber<? super T>, io.reactivex.rxjava3.core.CompletableSource);
    Code:
       0: aload_0
       1: invokespecial #1                  // Method java/util/concurrent/atomic/AtomicReference."<init>":()V
       4: aload_0
       5: aload_1
       6: putfield      #2                  // Field downstream:Lorg/reactivestreams/Subscriber;
       9: aload_0
      10: aload_2
      11: putfield      #3                  // Field other:Lio/reactivex/rxjava3/core/CompletableSource;
      14: return

  public void onSubscribe(org.reactivestreams.Subscription);
    Code:
       0: aload_0
       1: getfield      #4                  // Field upstream:Lorg/reactivestreams/Subscription;
       4: aload_1
       5: invokestatic  #5                  // Method io/reactivex/rxjava3/internal/subscriptions/SubscriptionHelper.validate:(Lorg/reactivestreams/Subscription;Lorg/reactivestreams/Subscription;)Z
       8: ifeq          26
      11: aload_0
      12: aload_1
      13: putfield      #4                  // Field upstream:Lorg/reactivestreams/Subscription;
      16: aload_0
      17: getfield      #2                  // Field downstream:Lorg/reactivestreams/Subscriber;
      20: aload_0
      21: invokeinterface #6,  2            // InterfaceMethod org/reactivestreams/Subscriber.onSubscribe:(Lorg/reactivestreams/Subscription;)V
      26: return

  public void onSubscribe(io.reactivex.rxjava3.disposables.Disposable);
    Code:
       0: aload_0
       1: aload_1
       2: invokestatic  #7                  // Method io/reactivex/rxjava3/internal/disposables/DisposableHelper.setOnce:(Ljava/util/concurrent/atomic/AtomicReference;Lio/reactivex/rxjava3/disposables/Disposable;)Z
       5: pop
       6: return

  public void onNext(T);
    Code:
       0: aload_0
       1: getfield      #2                  // Field downstream:Lorg/reactivestreams/Subscriber;
       4: aload_1
       5: invokeinterface #8,  2            // InterfaceMethod org/reactivestreams/Subscriber.onNext:(Ljava/lang/Object;)V
      10: return

  public void onError(java.lang.Throwable);
    Code:
       0: aload_0
       1: getfield      #2                  // Field downstream:Lorg/reactivestreams/Subscriber;
       4: aload_1
       5: invokeinterface #9,  2            // InterfaceMethod org/reactivestreams/Subscriber.onError:(Ljava/lang/Throwable;)V
      10: return

  public void onComplete();
    Code:
       0: aload_0
       1: getfield      #10                 // Field inCompletable:Z
       4: ifeq          19
       7: aload_0
       8: getfield      #2                  // Field downstream:Lorg/reactivestreams/Subscriber;
      11: invokeinterface #11,  1           // InterfaceMethod org/reactivestreams/Subscriber.onComplete:()V
      16: goto          48
      19: aload_0
      20: iconst_1
      21: putfield      #10                 // Field inCompletable:Z
      24: aload_0
      25: getstatic     #12                 // Field io/reactivex/rxjava3/internal/subscriptions/SubscriptionHelper.CANCELLED:Lio/reactivex/rxjava3/internal/subscriptions/SubscriptionHelper;
      28: putfield      #4                  // Field upstream:Lorg/reactivestreams/Subscription;
      31: aload_0
      32: getfield      #3                  // Field other:Lio/reactivex/rxjava3/core/CompletableSource;
      35: astore_1
      36: aload_0
      37: aconst_null
      38: putfield      #3                  // Field other:Lio/reactivex/rxjava3/core/CompletableSource;
      41: aload_1
      42: aload_0
      43: invokeinterface #13,  2           // InterfaceMethod io/reactivex/rxjava3/core/CompletableSource.subscribe:(Lio/reactivex/rxjava3/core/CompletableObserver;)V
      48: return

  public void request(long);
    Code:
       0: aload_0
       1: getfield      #4                  // Field upstream:Lorg/reactivestreams/Subscription;
       4: lload_1
       5: invokeinterface #14,  3           // InterfaceMethod org/reactivestreams/Subscription.request:(J)V
      10: return

  public void cancel();
    Code:
       0: aload_0
       1: getfield      #4                  // Field upstream:Lorg/reactivestreams/Subscription;
       4: invokeinterface #15,  1           // InterfaceMethod org/reactivestreams/Subscription.cancel:()V
       9: aload_0
      10: invokestatic  #16                 // Method io/reactivex/rxjava3/internal/disposables/DisposableHelper.dispose:(Ljava/util/concurrent/atomic/AtomicReference;)Z
      13: pop
      14: return
}
