Compiled from "FlowableDoOnLifecycle.java"
public final class io.reactivex.rxjava3.internal.operators.flowable.FlowableDoOnLifecycle<T> extends io.reactivex.rxjava3.internal.operators.flowable.AbstractFlowableWithUpstream<T, T> {
  private final io.reactivex.rxjava3.functions.Consumer<? super org.reactivestreams.Subscription> onSubscribe;

  private final io.reactivex.rxjava3.functions.LongConsumer onRequest;

  private final io.reactivex.rxjava3.functions.Action onCancel;

  public io.reactivex.rxjava3.internal.operators.flowable.FlowableDoOnLifecycle(io.reactivex.rxjava3.core.Flowable<T>, io.reactivex.rxjava3.functions.Consumer<? super org.reactivestreams.Subscription>, io.reactivex.rxjava3.functions.LongConsumer, io.reactivex.rxjava3.functions.Action);
    Code:
       0: aload_0
       1: aload_1
       2: invokespecial #1                  // Method io/reactivex/rxjava3/internal/operators/flowable/AbstractFlowableWithUpstream."<init>":(Lio/reactivex/rxjava3/core/Flowable;)V
       5: aload_0
       6: aload_2
       7: putfield      #2                  // Field onSubscribe:Lio/reactivex/rxjava3/functions/Consumer;
      10: aload_0
      11: aload_3
      12: putfield      #3                  // Field onRequest:Lio/reactivex/rxjava3/functions/LongConsumer;
      15: aload_0
      16: aload         4
      18: putfield      #4                  // Field onCancel:Lio/reactivex/rxjava3/functions/Action;
      21: return

  protected void subscribeActual(org.reactivestreams.Subscriber<? super T>);
    Code:
       0: aload_0
       1: getfield      #5                  // Field source:Lio/reactivex/rxjava3/core/Flowable;
       4: new           #6                  // class io/reactivex/rxjava3/internal/operators/flowable/FlowableDoOnLifecycle$SubscriptionLambdaSubscriber
       7: dup
       8: aload_1
       9: aload_0
      10: getfield      #2                  // Field onSubscribe:Lio/reactivex/rxjava3/functions/Consumer;
      13: aload_0
      14: getfield      #3                  // Field onRequest:Lio/reactivex/rxjava3/functions/LongConsumer;
      17: aload_0
      18: getfield      #4                  // Field onCancel:Lio/reactivex/rxjava3/functions/Action;
      21: invokespecial #7                  // Method io/reactivex/rxjava3/internal/operators/flowable/FlowableDoOnLifecycle$SubscriptionLambdaSubscriber."<init>":(Lorg/reactivestreams/Subscriber;Lio/reactivex/rxjava3/functions/Consumer;Lio/reactivex/rxjava3/functions/LongConsumer;Lio/reactivex/rxjava3/functions/Action;)V
      24: invokevirtual #8                  // Method io/reactivex/rxjava3/core/Flowable.subscribe:(Lio/reactivex/rxjava3/core/FlowableSubscriber;)V
      27: return
}
