Compiled from "FlowableNever.java"
public final class io.reactivex.rxjava3.internal.operators.flowable.FlowableNever extends io.reactivex.rxjava3.core.Flowable<java.lang.Object> {
  public static final io.reactivex.rxjava3.core.Flowable<java.lang.Object> INSTANCE;

  private io.reactivex.rxjava3.internal.operators.flowable.FlowableNever();
    Code:
       0: aload_0
       1: invokespecial #1                  // Method io/reactivex/rxjava3/core/Flowable."<init>":()V
       4: return

  public void subscribeActual(org.reactivestreams.Subscriber<? super java.lang.Object>);
    Code:
       0: aload_1
       1: getstatic     #2                  // Field io/reactivex/rxjava3/internal/subscriptions/EmptySubscription.INSTANCE:Lio/reactivex/rxjava3/internal/subscriptions/EmptySubscription;
       4: invokeinterface #3,  2            // InterfaceMethod org/reactivestreams/Subscriber.onSubscribe:(Lorg/reactivestreams/Subscription;)V
       9: return

  static {};
    Code:
       0: new           #4                  // class io/reactivex/rxjava3/internal/operators/flowable/FlowableNever
       3: dup
       4: invokespecial #5                  // Method "<init>":()V
       7: putstatic     #6                  // Field INSTANCE:Lio/reactivex/rxjava3/core/Flowable;
      10: return
}
