Compiled from "FlowableSwitchMap.java"
public final class io.reactivex.rxjava3.internal.operators.flowable.FlowableSwitchMap<T, R> extends io.reactivex.rxjava3.internal.operators.flowable.AbstractFlowableWithUpstream<T, R> {
  final io.reactivex.rxjava3.functions.Function<? super T, ? extends org.reactivestreams.Publisher<? extends R>> mapper;

  final int bufferSize;

  final boolean delayErrors;

  public io.reactivex.rxjava3.internal.operators.flowable.FlowableSwitchMap(io.reactivex.rxjava3.core.Flowable<T>, io.reactivex.rxjava3.functions.Function<? super T, ? extends org.reactivestreams.Publisher<? extends R>>, int, boolean);
    Code:
       0: aload_0
       1: aload_1
       2: invokespecial #1                  // Method io/reactivex/rxjava3/internal/operators/flowable/AbstractFlowableWithUpstream."<init>":(Lio/reactivex/rxjava3/core/Flowable;)V
       5: aload_0
       6: aload_2
       7: putfield      #2                  // Field mapper:Lio/reactivex/rxjava3/functions/Function;
      10: aload_0
      11: iload_3
      12: putfield      #3                  // Field bufferSize:I
      15: aload_0
      16: iload         4
      18: putfield      #4                  // Field delayErrors:Z
      21: return

  protected void subscribeActual(org.reactivestreams.Subscriber<? super R>);
    Code:
       0: aload_0
       1: getfield      #5                  // Field source:Lio/reactivex/rxjava3/core/Flowable;
       4: aload_1
       5: aload_0
       6: getfield      #2                  // Field mapper:Lio/reactivex/rxjava3/functions/Function;
       9: invokestatic  #6                  // Method io/reactivex/rxjava3/internal/operators/flowable/FlowableScalarXMap.tryScalarXMapSubscribe:(Lorg/reactivestreams/Publisher;Lorg/reactivestreams/Subscriber;Lio/reactivex/rxjava3/functions/Function;)Z
      12: ifeq          16
      15: return
      16: aload_0
      17: getfield      #5                  // Field source:Lio/reactivex/rxjava3/core/Flowable;
      20: new           #7                  // class io/reactivex/rxjava3/internal/operators/flowable/FlowableSwitchMap$SwitchMapSubscriber
      23: dup
      24: aload_1
      25: aload_0
      26: getfield      #2                  // Field mapper:Lio/reactivex/rxjava3/functions/Function;
      29: aload_0
      30: getfield      #3                  // Field bufferSize:I
      33: aload_0
      34: getfield      #4                  // Field delayErrors:Z
      37: invokespecial #8                  // Method io/reactivex/rxjava3/internal/operators/flowable/FlowableSwitchMap$SwitchMapSubscriber."<init>":(Lorg/reactivestreams/Subscriber;Lio/reactivex/rxjava3/functions/Function;IZ)V
      40: invokevirtual #9                  // Method io/reactivex/rxjava3/core/Flowable.subscribe:(Lio/reactivex/rxjava3/core/FlowableSubscriber;)V
      43: return
}
