Compiled from "FlowableRetryPredicate.java"
public final class io.reactivex.rxjava3.internal.operators.flowable.FlowableRetryPredicate<T> extends io.reactivex.rxjava3.internal.operators.flowable.AbstractFlowableWithUpstream<T, T> {
  final io.reactivex.rxjava3.functions.Predicate<? super java.lang.Throwable> predicate;

  final long count;

  public io.reactivex.rxjava3.internal.operators.flowable.FlowableRetryPredicate(io.reactivex.rxjava3.core.Flowable<T>, long, io.reactivex.rxjava3.functions.Predicate<? super java.lang.Throwable>);
    Code:
       0: aload_0
       1: aload_1
       2: invokespecial #1                  // Method io/reactivex/rxjava3/internal/operators/flowable/AbstractFlowableWithUpstream."<init>":(Lio/reactivex/rxjava3/core/Flowable;)V
       5: aload_0
       6: aload         4
       8: putfield      #2                  // Field predicate:Lio/reactivex/rxjava3/functions/Predicate;
      11: aload_0
      12: lload_2
      13: putfield      #3                  // Field count:J
      16: return

  public void subscribeActual(org.reactivestreams.Subscriber<? super T>);
    Code:
       0: new           #4                  // class io/reactivex/rxjava3/internal/subscriptions/SubscriptionArbiter
       3: dup
       4: iconst_0
       5: invokespecial #5                  // Method io/reactivex/rxjava3/internal/subscriptions/SubscriptionArbiter."<init>":(Z)V
       8: astore_2
       9: aload_1
      10: aload_2
      11: invokeinterface #6,  2            // InterfaceMethod org/reactivestreams/Subscriber.onSubscribe:(Lorg/reactivestreams/Subscription;)V
      16: new           #7                  // class io/reactivex/rxjava3/internal/operators/flowable/FlowableRetryPredicate$RetrySubscriber
      19: dup
      20: aload_1
      21: aload_0
      22: getfield      #3                  // Field count:J
      25: aload_0
      26: getfield      #2                  // Field predicate:Lio/reactivex/rxjava3/functions/Predicate;
      29: aload_2
      30: aload_0
      31: getfield      #8                  // Field source:Lio/reactivex/rxjava3/core/Flowable;
      34: invokespecial #9                  // Method io/reactivex/rxjava3/internal/operators/flowable/FlowableRetryPredicate$RetrySubscriber."<init>":(Lorg/reactivestreams/Subscriber;JLio/reactivex/rxjava3/functions/Predicate;Lio/reactivex/rxjava3/internal/subscriptions/SubscriptionArbiter;Lorg/reactivestreams/Publisher;)V
      37: astore_3
      38: aload_3
      39: invokevirtual #10                 // Method io/reactivex/rxjava3/internal/operators/flowable/FlowableRetryPredicate$RetrySubscriber.subscribeNext:()V
      42: return
}
