Compiled from "FlowableAmb.java"
final class io.reactivex.rxjava3.internal.operators.flowable.FlowableAmb$AmbInnerSubscriber<T> extends java.util.concurrent.atomic.AtomicReference<org.reactivestreams.Subscription> implements io.reactivex.rxjava3.core.FlowableSubscriber<T>, org.reactivestreams.Subscription {
  private static final long serialVersionUID;

  final io.reactivex.rxjava3.internal.operators.flowable.FlowableAmb$AmbCoordinator<T> parent;

  final int index;

  final org.reactivestreams.Subscriber<? super T> downstream;

  boolean won;

  final java.util.concurrent.atomic.AtomicLong missedRequested;

  io.reactivex.rxjava3.internal.operators.flowable.FlowableAmb$AmbInnerSubscriber(io.reactivex.rxjava3.internal.operators.flowable.FlowableAmb$AmbCoordinator<T>, int, org.reactivestreams.Subscriber<? super T>);
    Code:
       0: aload_0
       1: invokespecial #1                  // Method java/util/concurrent/atomic/AtomicReference."<init>":()V
       4: aload_0
       5: new           #2                  // class java/util/concurrent/atomic/AtomicLong
       8: dup
       9: invokespecial #3                  // Method java/util/concurrent/atomic/AtomicLong."<init>":()V
      12: putfield      #4                  // Field missedRequested:Ljava/util/concurrent/atomic/AtomicLong;
      15: aload_0
      16: aload_1
      17: putfield      #5                  // Field parent:Lio/reactivex/rxjava3/internal/operators/flowable/FlowableAmb$AmbCoordinator;
      20: aload_0
      21: iload_2
      22: putfield      #6                  // Field index:I
      25: aload_0
      26: aload_3
      27: putfield      #7                  // Field downstream:Lorg/reactivestreams/Subscriber;
      30: return

  public void onSubscribe(org.reactivestreams.Subscription);
    Code:
       0: aload_0
       1: aload_0
       2: getfield      #4                  // Field missedRequested:Ljava/util/concurrent/atomic/AtomicLong;
       5: aload_1
       6: invokestatic  #8                  // Method io/reactivex/rxjava3/internal/subscriptions/SubscriptionHelper.deferredSetOnce:(Ljava/util/concurrent/atomic/AtomicReference;Ljava/util/concurrent/atomic/AtomicLong;Lorg/reactivestreams/Subscription;)Z
       9: pop
      10: return

  public void request(long);
    Code:
       0: aload_0
       1: aload_0
       2: getfield      #4                  // Field missedRequested:Ljava/util/concurrent/atomic/AtomicLong;
       5: lload_1
       6: invokestatic  #9                  // Method io/reactivex/rxjava3/internal/subscriptions/SubscriptionHelper.deferredRequest:(Ljava/util/concurrent/atomic/AtomicReference;Ljava/util/concurrent/atomic/AtomicLong;J)V
       9: return

  public void onNext(T);
    Code:
       0: aload_0
       1: getfield      #10                 // Field won:Z
       4: ifeq          20
       7: aload_0
       8: getfield      #7                  // Field downstream:Lorg/reactivestreams/Subscriber;
      11: aload_1
      12: invokeinterface #11,  2           // InterfaceMethod org/reactivestreams/Subscriber.onNext:(Ljava/lang/Object;)V
      17: goto          64
      20: aload_0
      21: getfield      #5                  // Field parent:Lio/reactivex/rxjava3/internal/operators/flowable/FlowableAmb$AmbCoordinator;
      24: aload_0
      25: getfield      #6                  // Field index:I
      28: invokevirtual #12                 // Method io/reactivex/rxjava3/internal/operators/flowable/FlowableAmb$AmbCoordinator.win:(I)Z
      31: ifeq          52
      34: aload_0
      35: iconst_1
      36: putfield      #10                 // Field won:Z
      39: aload_0
      40: getfield      #7                  // Field downstream:Lorg/reactivestreams/Subscriber;
      43: aload_1
      44: invokeinterface #11,  2           // InterfaceMethod org/reactivestreams/Subscriber.onNext:(Ljava/lang/Object;)V
      49: goto          64
      52: aload_0
      53: invokevirtual #13                 // Method get:()Ljava/lang/Object;
      56: checkcast     #14                 // class org/reactivestreams/Subscription
      59: invokeinterface #15,  1           // InterfaceMethod org/reactivestreams/Subscription.cancel:()V
      64: return

  public void onError(java.lang.Throwable);
    Code:
       0: aload_0
       1: getfield      #10                 // Field won:Z
       4: ifeq          20
       7: aload_0
       8: getfield      #7                  // Field downstream:Lorg/reactivestreams/Subscriber;
      11: aload_1
      12: invokeinterface #16,  2           // InterfaceMethod org/reactivestreams/Subscriber.onError:(Ljava/lang/Throwable;)V
      17: goto          68
      20: aload_0
      21: getfield      #5                  // Field parent:Lio/reactivex/rxjava3/internal/operators/flowable/FlowableAmb$AmbCoordinator;
      24: aload_0
      25: getfield      #6                  // Field index:I
      28: invokevirtual #12                 // Method io/reactivex/rxjava3/internal/operators/flowable/FlowableAmb$AmbCoordinator.win:(I)Z
      31: ifeq          52
      34: aload_0
      35: iconst_1
      36: putfield      #10                 // Field won:Z
      39: aload_0
      40: getfield      #7                  // Field downstream:Lorg/reactivestreams/Subscriber;
      43: aload_1
      44: invokeinterface #16,  2           // InterfaceMethod org/reactivestreams/Subscriber.onError:(Ljava/lang/Throwable;)V
      49: goto          68
      52: aload_0
      53: invokevirtual #13                 // Method get:()Ljava/lang/Object;
      56: checkcast     #14                 // class org/reactivestreams/Subscription
      59: invokeinterface #15,  1           // InterfaceMethod org/reactivestreams/Subscription.cancel:()V
      64: aload_1
      65: invokestatic  #17                 // Method io/reactivex/rxjava3/plugins/RxJavaPlugins.onError:(Ljava/lang/Throwable;)V
      68: return

  public void onComplete();
    Code:
       0: aload_0
       1: getfield      #10                 // Field won:Z
       4: ifeq          19
       7: aload_0
       8: getfield      #7                  // Field downstream:Lorg/reactivestreams/Subscriber;
      11: invokeinterface #18,  1           // InterfaceMethod org/reactivestreams/Subscriber.onComplete:()V
      16: goto          62
      19: aload_0
      20: getfield      #5                  // Field parent:Lio/reactivex/rxjava3/internal/operators/flowable/FlowableAmb$AmbCoordinator;
      23: aload_0
      24: getfield      #6                  // Field index:I
      27: invokevirtual #12                 // Method io/reactivex/rxjava3/internal/operators/flowable/FlowableAmb$AmbCoordinator.win:(I)Z
      30: ifeq          50
      33: aload_0
      34: iconst_1
      35: putfield      #10                 // Field won:Z
      38: aload_0
      39: getfield      #7                  // Field downstream:Lorg/reactivestreams/Subscriber;
      42: invokeinterface #18,  1           // InterfaceMethod org/reactivestreams/Subscriber.onComplete:()V
      47: goto          62
      50: aload_0
      51: invokevirtual #13                 // Method get:()Ljava/lang/Object;
      54: checkcast     #14                 // class org/reactivestreams/Subscription
      57: invokeinterface #15,  1           // InterfaceMethod org/reactivestreams/Subscription.cancel:()V
      62: return

  public void cancel();
    Code:
       0: aload_0
       1: invokestatic  #19                 // Method io/reactivex/rxjava3/internal/subscriptions/SubscriptionHelper.cancel:(Ljava/util/concurrent/atomic/AtomicReference;)Z
       4: pop
       5: return
}
