Compiled from "FlowableRangeLong.java"
public final class io.reactivex.rxjava3.internal.operators.flowable.FlowableRangeLong extends io.reactivex.rxjava3.core.Flowable<java.lang.Long> {
  final long start;

  final long end;

  public io.reactivex.rxjava3.internal.operators.flowable.FlowableRangeLong(long, long);
    Code:
       0: aload_0
       1: invokespecial #1                  // Method io/reactivex/rxjava3/core/Flowable."<init>":()V
       4: aload_0
       5: lload_1
       6: putfield      #2                  // Field start:J
       9: aload_0
      10: lload_1
      11: lload_3
      12: ladd
      13: putfield      #3                  // Field end:J
      16: return

  public void subscribeActual(org.reactivestreams.Subscriber<? super java.lang.Long>);
    Code:
       0: aload_1
       1: instanceof    #4                  // class io/reactivex/rxjava3/operators/ConditionalSubscriber
       4: ifeq          35
       7: aload_1
       8: new           #5                  // class io/reactivex/rxjava3/internal/operators/flowable/FlowableRangeLong$RangeConditionalSubscription
      11: dup
      12: aload_1
      13: checkcast     #4                  // class io/reactivex/rxjava3/operators/ConditionalSubscriber
      16: aload_0
      17: getfield      #2                  // Field start:J
      20: aload_0
      21: getfield      #3                  // Field end:J
      24: invokespecial #6                  // Method io/reactivex/rxjava3/internal/operators/flowable/FlowableRangeLong$RangeConditionalSubscription."<init>":(Lio/reactivex/rxjava3/operators/ConditionalSubscriber;JJ)V
      27: invokeinterface #7,  2            // InterfaceMethod org/reactivestreams/Subscriber.onSubscribe:(Lorg/reactivestreams/Subscription;)V
      32: goto          57
      35: aload_1
      36: new           #8                  // class io/reactivex/rxjava3/internal/operators/flowable/FlowableRangeLong$RangeSubscription
      39: dup
      40: aload_1
      41: aload_0
      42: getfield      #2                  // Field start:J
      45: aload_0
      46: getfield      #3                  // Field end:J
      49: invokespecial #9                  // Method io/reactivex/rxjava3/internal/operators/flowable/FlowableRangeLong$RangeSubscription."<init>":(Lorg/reactivestreams/Subscriber;JJ)V
      52: invokeinterface #7,  2            // InterfaceMethod org/reactivestreams/Subscriber.onSubscribe:(Lorg/reactivestreams/Subscription;)V
      57: return
}
