Compiled from "FlowableConcatMap.java"
class io.reactivex.rxjava3.internal.operators.flowable.FlowableConcatMap$1 {
  static final int[] $SwitchMap$io$reactivex$rxjava3$internal$util$ErrorMode;

  static {};
    Code:
       0: invokestatic  #1                  // Method io/reactivex/rxjava3/internal/util/ErrorMode.values:()[Lio/reactivex/rxjava3/internal/util/ErrorMode;
       3: arraylength
       4: newarray       int
       6: putstatic     #2                  // Field $SwitchMap$io$reactivex$rxjava3$internal$util$ErrorMode:[I
       9: getstatic     #2                  // Field $SwitchMap$io$reactivex$rxjava3$internal$util$ErrorMode:[I
      12: getstatic     #3                  // Field io/reactivex/rxjava3/internal/util/ErrorMode.BOUNDARY:Lio/reactivex/rxjava3/internal/util/ErrorMode;
      15: invokevirtual #4                  // Method io/reactivex/rxjava3/internal/util/ErrorMode.ordinal:()I
      18: iconst_1
      19: iastore
      20: goto          24
      23: astore_0
      24: getstatic     #2                  // Field $SwitchMap$io$reactivex$rxjava3$internal$util$ErrorMode:[I
      27: getstatic     #6                  // Field io/reactivex/rxjava3/internal/util/ErrorMode.END:Lio/reactivex/rxjava3/internal/util/ErrorMode;
      30: invokevirtual #4                  // Method io/reactivex/rxjava3/internal/util/ErrorMode.ordinal:()I
      33: iconst_2
      34: iastore
      35: goto          39
      38: astore_0
      39: return
    Exception table:
       from    to  target type
           9    20    23   Class java/lang/NoSuchFieldError
          24    35    38   Class java/lang/NoSuchFieldError
}
