Compiled from "FlowableReduceSeedSingle.java"
public final class io.reactivex.rxjava3.internal.operators.flowable.FlowableReduceSeedSingle<T, R> extends io.reactivex.rxjava3.core.Single<R> {
  final org.reactivestreams.Publisher<T> source;

  final R seed;

  final io.reactivex.rxjava3.functions.BiFunction<R, ? super T, R> reducer;

  public io.reactivex.rxjava3.internal.operators.flowable.FlowableReduceSeedSingle(org.reactivestreams.Publisher<T>, R, io.reactivex.rxjava3.functions.BiFunction<R, ? super T, R>);
    Code:
       0: aload_0
       1: invokespecial #1                  // Method io/reactivex/rxjava3/core/Single."<init>":()V
       4: aload_0
       5: aload_1
       6: putfield      #2                  // Field source:Lorg/reactivestreams/Publisher;
       9: aload_0
      10: aload_2
      11: putfield      #3                  // Field seed:Ljava/lang/Object;
      14: aload_0
      15: aload_3
      16: putfield      #4                  // Field reducer:Lio/reactivex/rxjava3/functions/BiFunction;
      19: return

  protected void subscribeActual(io.reactivex.rxjava3.core.SingleObserver<? super R>);
    Code:
       0: aload_0
       1: getfield      #2                  // Field source:Lorg/reactivestreams/Publisher;
       4: new           #5                  // class io/reactivex/rxjava3/internal/operators/flowable/FlowableReduceSeedSingle$ReduceSeedObserver
       7: dup
       8: aload_1
       9: aload_0
      10: getfield      #4                  // Field reducer:Lio/reactivex/rxjava3/functions/BiFunction;
      13: aload_0
      14: getfield      #3                  // Field seed:Ljava/lang/Object;
      17: invokespecial #6                  // Method io/reactivex/rxjava3/internal/operators/flowable/FlowableReduceSeedSingle$ReduceSeedObserver."<init>":(Lio/reactivex/rxjava3/core/SingleObserver;Lio/reactivex/rxjava3/functions/BiFunction;Ljava/lang/Object;)V
      20: invokeinterface #7,  2            // InterfaceMethod org/reactivestreams/Publisher.subscribe:(Lorg/reactivestreams/Subscriber;)V
      25: return
}
