Compiled from "FlowableDoAfterNext.java"
final class io.reactivex.rxjava3.internal.operators.flowable.FlowableDoAfterNext$DoAfterConditionalSubscriber<T> extends io.reactivex.rxjava3.internal.subscribers.BasicFuseableConditionalSubscriber<T, T> {
  final io.reactivex.rxjava3.functions.Consumer<? super T> onAfterNext;

  io.reactivex.rxjava3.internal.operators.flowable.FlowableDoAfterNext$DoAfterConditionalSubscriber(io.reactivex.rxjava3.operators.ConditionalSubscriber<? super T>, io.reactivex.rxjava3.functions.Consumer<? super T>);
    Code:
       0: aload_0
       1: aload_1
       2: invokespecial #1                  // Method io/reactivex/rxjava3/internal/subscribers/BasicFuseableConditionalSubscriber."<init>":(Lio/reactivex/rxjava3/operators/ConditionalSubscriber;)V
       5: aload_0
       6: aload_2
       7: putfield      #2                  // Field onAfterNext:Lio/reactivex/rxjava3/functions/Consumer;
      10: return

  public void onNext(T);
    Code:
       0: aload_0
       1: getfield      #3                  // Field downstream:Lio/reactivex/rxjava3/operators/ConditionalSubscriber;
       4: aload_1
       5: invokeinterface #4,  2            // InterfaceMethod io/reactivex/rxjava3/operators/ConditionalSubscriber.onNext:(Ljava/lang/Object;)V
      10: aload_0
      11: getfield      #5                  // Field sourceMode:I
      14: ifne          36
      17: aload_0
      18: getfield      #2                  // Field onAfterNext:Lio/reactivex/rxjava3/functions/Consumer;
      21: aload_1
      22: invokeinterface #6,  2            // InterfaceMethod io/reactivex/rxjava3/functions/Consumer.accept:(Ljava/lang/Object;)V
      27: goto          36
      30: astore_2
      31: aload_0
      32: aload_2
      33: invokevirtual #8                  // Method fail:(Ljava/lang/Throwable;)V
      36: return
    Exception table:
       from    to  target type
          17    27    30   Class java/lang/Throwable

  public boolean tryOnNext(T);
    Code:
       0: aload_0
       1: getfield      #3                  // Field downstream:Lio/reactivex/rxjava3/operators/ConditionalSubscriber;
       4: aload_1
       5: invokeinterface #9,  2            // InterfaceMethod io/reactivex/rxjava3/operators/ConditionalSubscriber.tryOnNext:(Ljava/lang/Object;)Z
      10: istore_2
      11: aload_0
      12: getfield      #2                  // Field onAfterNext:Lio/reactivex/rxjava3/functions/Consumer;
      15: aload_1
      16: invokeinterface #6,  2            // InterfaceMethod io/reactivex/rxjava3/functions/Consumer.accept:(Ljava/lang/Object;)V
      21: goto          30
      24: astore_3
      25: aload_0
      26: aload_3
      27: invokevirtual #8                  // Method fail:(Ljava/lang/Throwable;)V
      30: iload_2
      31: ireturn
    Exception table:
       from    to  target type
          11    21    24   Class java/lang/Throwable

  public int requestFusion(int);
    Code:
       0: aload_0
       1: iload_1
       2: invokevirtual #10                 // Method transitiveBoundaryFusion:(I)I
       5: ireturn

  public T poll() throws java.lang.Throwable;
    Code:
       0: aload_0
       1: getfield      #11                 // Field qs:Lio/reactivex/rxjava3/operators/QueueSubscription;
       4: invokeinterface #12,  1           // InterfaceMethod io/reactivex/rxjava3/operators/QueueSubscription.poll:()Ljava/lang/Object;
       9: astore_1
      10: aload_1
      11: ifnull        24
      14: aload_0
      15: getfield      #2                  // Field onAfterNext:Lio/reactivex/rxjava3/functions/Consumer;
      18: aload_1
      19: invokeinterface #6,  2            // InterfaceMethod io/reactivex/rxjava3/functions/Consumer.accept:(Ljava/lang/Object;)V
      24: aload_1
      25: areturn
}
