Compiled from "FlowableGenerate.java"
final class io.reactivex.rxjava3.internal.operators.flowable.FlowableGenerate$GeneratorSubscription<T, S> extends java.util.concurrent.atomic.AtomicLong implements io.reactivex.rxjava3.core.Emitter<T>, org.reactivestreams.Subscription {
  private static final long serialVersionUID;

  final org.reactivestreams.Subscriber<? super T> downstream;

  final io.reactivex.rxjava3.functions.BiFunction<S, ? super io.reactivex.rxjava3.core.Emitter<T>, S> generator;

  final io.reactivex.rxjava3.functions.Consumer<? super S> disposeState;

  S state;

  volatile boolean cancelled;

  boolean terminate;

  boolean hasNext;

  io.reactivex.rxjava3.internal.operators.flowable.FlowableGenerate$GeneratorSubscription(org.reactivestreams.Subscriber<? super T>, io.reactivex.rxjava3.functions.BiFunction<S, ? super io.reactivex.rxjava3.core.Emitter<T>, S>, io.reactivex.rxjava3.functions.Consumer<? super S>, S);
    Code:
       0: aload_0
       1: invokespecial #1                  // Method java/util/concurrent/atomic/AtomicLong."<init>":()V
       4: aload_0
       5: aload_1
       6: putfield      #2                  // Field downstream:Lorg/reactivestreams/Subscriber;
       9: aload_0
      10: aload_2
      11: putfield      #3                  // Field generator:Lio/reactivex/rxjava3/functions/BiFunction;
      14: aload_0
      15: aload_3
      16: putfield      #4                  // Field disposeState:Lio/reactivex/rxjava3/functions/Consumer;
      19: aload_0
      20: aload         4
      22: putfield      #5                  // Field state:Ljava/lang/Object;
      25: return

  public void request(long);
    Code:
       0: lload_1
       1: invokestatic  #6                  // Method io/reactivex/rxjava3/internal/subscriptions/SubscriptionHelper.validate:(J)Z
       4: ifne          8
       7: return
       8: aload_0
       9: lload_1
      10: invokestatic  #7                  // Method io/reactivex/rxjava3/internal/util/BackpressureHelper.add:(Ljava/util/concurrent/atomic/AtomicLong;J)J
      13: lconst_0
      14: lcmp
      15: ifeq          19
      18: return
      19: lconst_0
      20: lstore_3
      21: aload_0
      22: getfield      #5                  // Field state:Ljava/lang/Object;
      25: astore        5
      27: aload_0
      28: getfield      #3                  // Field generator:Lio/reactivex/rxjava3/functions/BiFunction;
      31: astore        6
      33: lload_3
      34: lload_1
      35: lcmp
      36: ifeq          139
      39: aload_0
      40: getfield      #8                  // Field cancelled:Z
      43: ifeq          58
      46: aload_0
      47: aconst_null
      48: putfield      #5                  // Field state:Ljava/lang/Object;
      51: aload_0
      52: aload         5
      54: invokespecial #9                  // Method dispose:(Ljava/lang/Object;)V
      57: return
      58: aload_0
      59: iconst_0
      60: putfield      #10                 // Field hasNext:Z
      63: aload         6
      65: aload         5
      67: aload_0
      68: invokeinterface #11,  3           // InterfaceMethod io/reactivex/rxjava3/functions/BiFunction.apply:(Ljava/lang/Object;Ljava/lang/Object;)Ljava/lang/Object;
      73: astore        5
      75: goto          108
      78: astore        7
      80: aload         7
      82: invokestatic  #13                 // Method io/reactivex/rxjava3/exceptions/Exceptions.throwIfFatal:(Ljava/lang/Throwable;)V
      85: aload_0
      86: iconst_1
      87: putfield      #8                  // Field cancelled:Z
      90: aload_0
      91: aconst_null
      92: putfield      #5                  // Field state:Ljava/lang/Object;
      95: aload_0
      96: aload         7
      98: invokevirtual #14                 // Method onError:(Ljava/lang/Throwable;)V
     101: aload_0
     102: aload         5
     104: invokespecial #9                  // Method dispose:(Ljava/lang/Object;)V
     107: return
     108: aload_0
     109: getfield      #15                 // Field terminate:Z
     112: ifeq          132
     115: aload_0
     116: iconst_1
     117: putfield      #8                  // Field cancelled:Z
     120: aload_0
     121: aconst_null
     122: putfield      #5                  // Field state:Ljava/lang/Object;
     125: aload_0
     126: aload         5
     128: invokespecial #9                  // Method dispose:(Ljava/lang/Object;)V
     131: return
     132: lload_3
     133: lconst_1
     134: ladd
     135: lstore_3
     136: goto          33
     139: aload_0
     140: invokevirtual #16                 // Method get:()J
     143: lstore_1
     144: lload_3
     145: lload_1
     146: lcmp
     147: ifne          33
     150: aload_0
     151: aload         5
     153: putfield      #5                  // Field state:Ljava/lang/Object;
     156: aload_0
     157: lload_3
     158: lneg
     159: invokevirtual #17                 // Method addAndGet:(J)J
     162: lstore_1
     163: lload_1
     164: lconst_0
     165: lcmp
     166: ifne          172
     169: goto          177
     172: lconst_0
     173: lstore_3
     174: goto          33
     177: return
    Exception table:
       from    to  target type
          63    75    78   Class java/lang/Throwable

  private void dispose(S);
    Code:
       0: aload_0
       1: getfield      #4                  // Field disposeState:Lio/reactivex/rxjava3/functions/Consumer;
       4: aload_1
       5: invokeinterface #18,  2           // InterfaceMethod io/reactivex/rxjava3/functions/Consumer.accept:(Ljava/lang/Object;)V
      10: goto          22
      13: astore_2
      14: aload_2
      15: invokestatic  #13                 // Method io/reactivex/rxjava3/exceptions/Exceptions.throwIfFatal:(Ljava/lang/Throwable;)V
      18: aload_2
      19: invokestatic  #19                 // Method io/reactivex/rxjava3/plugins/RxJavaPlugins.onError:(Ljava/lang/Throwable;)V
      22: return
    Exception table:
       from    to  target type
           0    10    13   Class java/lang/Throwable

  public void cancel();
    Code:
       0: aload_0
       1: getfield      #8                  // Field cancelled:Z
       4: ifne          37
       7: aload_0
       8: iconst_1
       9: putfield      #8                  // Field cancelled:Z
      12: aload_0
      13: lconst_1
      14: invokestatic  #7                  // Method io/reactivex/rxjava3/internal/util/BackpressureHelper.add:(Ljava/util/concurrent/atomic/AtomicLong;J)J
      17: lconst_0
      18: lcmp
      19: ifne          37
      22: aload_0
      23: getfield      #5                  // Field state:Ljava/lang/Object;
      26: astore_1
      27: aload_0
      28: aconst_null
      29: putfield      #5                  // Field state:Ljava/lang/Object;
      32: aload_0
      33: aload_1
      34: invokespecial #9                  // Method dispose:(Ljava/lang/Object;)V
      37: return

  public void onNext(T);
    Code:
       0: aload_0
       1: getfield      #15                 // Field terminate:Z
       4: ifne          61
       7: aload_0
       8: getfield      #10                 // Field hasNext:Z
      11: ifeq          30
      14: aload_0
      15: new           #20                 // class java/lang/IllegalStateException
      18: dup
      19: ldc           #21                 // String onNext already called in this generate turn
      21: invokespecial #22                 // Method java/lang/IllegalStateException."<init>":(Ljava/lang/String;)V
      24: invokevirtual #14                 // Method onError:(Ljava/lang/Throwable;)V
      27: goto          61
      30: aload_1
      31: ifnonnull     46
      34: aload_0
      35: ldc           #23                 // String onNext called with a null value.
      37: invokestatic  #24                 // Method io/reactivex/rxjava3/internal/util/ExceptionHelper.createNullPointerException:(Ljava/lang/String;)Ljava/lang/NullPointerException;
      40: invokevirtual #14                 // Method onError:(Ljava/lang/Throwable;)V
      43: goto          61
      46: aload_0
      47: iconst_1
      48: putfield      #10                 // Field hasNext:Z
      51: aload_0
      52: getfield      #2                  // Field downstream:Lorg/reactivestreams/Subscriber;
      55: aload_1
      56: invokeinterface #25,  2           // InterfaceMethod org/reactivestreams/Subscriber.onNext:(Ljava/lang/Object;)V
      61: return

  public void onError(java.lang.Throwable);
    Code:
       0: aload_0
       1: getfield      #15                 // Field terminate:Z
       4: ifeq          14
       7: aload_1
       8: invokestatic  #19                 // Method io/reactivex/rxjava3/plugins/RxJavaPlugins.onError:(Ljava/lang/Throwable;)V
      11: goto          39
      14: aload_1
      15: ifnonnull     24
      18: ldc           #26                 // String onError called with a null Throwable.
      20: invokestatic  #24                 // Method io/reactivex/rxjava3/internal/util/ExceptionHelper.createNullPointerException:(Ljava/lang/String;)Ljava/lang/NullPointerException;
      23: astore_1
      24: aload_0
      25: iconst_1
      26: putfield      #15                 // Field terminate:Z
      29: aload_0
      30: getfield      #2                  // Field downstream:Lorg/reactivestreams/Subscriber;
      33: aload_1
      34: invokeinterface #27,  2           // InterfaceMethod org/reactivestreams/Subscriber.onError:(Ljava/lang/Throwable;)V
      39: return

  public void onComplete();
    Code:
       0: aload_0
       1: getfield      #15                 // Field terminate:Z
       4: ifne          21
       7: aload_0
       8: iconst_1
       9: putfield      #15                 // Field terminate:Z
      12: aload_0
      13: getfield      #2                  // Field downstream:Lorg/reactivestreams/Subscriber;
      16: invokeinterface #28,  1           // InterfaceMethod org/reactivestreams/Subscriber.onComplete:()V
      21: return
}
