Compiled from "FlowableDoOnEach.java"
public final class io.reactivex.rxjava3.internal.operators.flowable.FlowableDoOnEach<T> extends io.reactivex.rxjava3.internal.operators.flowable.AbstractFlowableWithUpstream<T, T> {
  final io.reactivex.rxjava3.functions.Consumer<? super T> onNext;

  final io.reactivex.rxjava3.functions.Consumer<? super java.lang.Throwable> onError;

  final io.reactivex.rxjava3.functions.Action onComplete;

  final io.reactivex.rxjava3.functions.Action onAfterTerminate;

  public io.reactivex.rxjava3.internal.operators.flowable.FlowableDoOnEach(io.reactivex.rxjava3.core.Flowable<T>, io.reactivex.rxjava3.functions.Consumer<? super T>, io.reactivex.rxjava3.functions.Consumer<? super java.lang.Throwable>, io.reactivex.rxjava3.functions.Action, io.reactivex.rxjava3.functions.Action);
    Code:
       0: aload_0
       1: aload_1
       2: invokespecial #1                  // Method io/reactivex/rxjava3/internal/operators/flowable/AbstractFlowableWithUpstream."<init>":(Lio/reactivex/rxjava3/core/Flowable;)V
       5: aload_0
       6: aload_2
       7: putfield      #2                  // Field onNext:Lio/reactivex/rxjava3/functions/Consumer;
      10: aload_0
      11: aload_3
      12: putfield      #3                  // Field onError:Lio/reactivex/rxjava3/functions/Consumer;
      15: aload_0
      16: aload         4
      18: putfield      #4                  // Field onComplete:Lio/reactivex/rxjava3/functions/Action;
      21: aload_0
      22: aload         5
      24: putfield      #5                  // Field onAfterTerminate:Lio/reactivex/rxjava3/functions/Action;
      27: return

  protected void subscribeActual(org.reactivestreams.Subscriber<? super T>);
    Code:
       0: aload_1
       1: instanceof    #6                  // class io/reactivex/rxjava3/operators/ConditionalSubscriber
       4: ifeq          44
       7: aload_0
       8: getfield      #7                  // Field source:Lio/reactivex/rxjava3/core/Flowable;
      11: new           #8                  // class io/reactivex/rxjava3/internal/operators/flowable/FlowableDoOnEach$DoOnEachConditionalSubscriber
      14: dup
      15: aload_1
      16: checkcast     #6                  // class io/reactivex/rxjava3/operators/ConditionalSubscriber
      19: aload_0
      20: getfield      #2                  // Field onNext:Lio/reactivex/rxjava3/functions/Consumer;
      23: aload_0
      24: getfield      #3                  // Field onError:Lio/reactivex/rxjava3/functions/Consumer;
      27: aload_0
      28: getfield      #4                  // Field onComplete:Lio/reactivex/rxjava3/functions/Action;
      31: aload_0
      32: getfield      #5                  // Field onAfterTerminate:Lio/reactivex/rxjava3/functions/Action;
      35: invokespecial #9                  // Method io/reactivex/rxjava3/internal/operators/flowable/FlowableDoOnEach$DoOnEachConditionalSubscriber."<init>":(Lio/reactivex/rxjava3/operators/ConditionalSubscriber;Lio/reactivex/rxjava3/functions/Consumer;Lio/reactivex/rxjava3/functions/Consumer;Lio/reactivex/rxjava3/functions/Action;Lio/reactivex/rxjava3/functions/Action;)V
      38: invokevirtual #10                 // Method io/reactivex/rxjava3/core/Flowable.subscribe:(Lio/reactivex/rxjava3/core/FlowableSubscriber;)V
      41: goto          75
      44: aload_0
      45: getfield      #7                  // Field source:Lio/reactivex/rxjava3/core/Flowable;
      48: new           #11                 // class io/reactivex/rxjava3/internal/operators/flowable/FlowableDoOnEach$DoOnEachSubscriber
      51: dup
      52: aload_1
      53: aload_0
      54: getfield      #2                  // Field onNext:Lio/reactivex/rxjava3/functions/Consumer;
      57: aload_0
      58: getfield      #3                  // Field onError:Lio/reactivex/rxjava3/functions/Consumer;
      61: aload_0
      62: getfield      #4                  // Field onComplete:Lio/reactivex/rxjava3/functions/Action;
      65: aload_0
      66: getfield      #5                  // Field onAfterTerminate:Lio/reactivex/rxjava3/functions/Action;
      69: invokespecial #12                 // Method io/reactivex/rxjava3/internal/operators/flowable/FlowableDoOnEach$DoOnEachSubscriber."<init>":(Lorg/reactivestreams/Subscriber;Lio/reactivex/rxjava3/functions/Consumer;Lio/reactivex/rxjava3/functions/Consumer;Lio/reactivex/rxjava3/functions/Action;Lio/reactivex/rxjava3/functions/Action;)V
      72: invokevirtual #10                 // Method io/reactivex/rxjava3/core/Flowable.subscribe:(Lio/reactivex/rxjava3/core/FlowableSubscriber;)V
      75: return
}
