Compiled from "FlowableDebounce.java"
final class io.reactivex.rxjava3.internal.operators.flowable.FlowableDebounce$DebounceSubscriber<T, U> extends java.util.concurrent.atomic.AtomicLong implements io.reactivex.rxjava3.core.FlowableSubscriber<T>, org.reactivestreams.Subscription {
  private static final long serialVersionUID;

  final org.reactivestreams.Subscriber<? super T> downstream;

  final io.reactivex.rxjava3.functions.Function<? super T, ? extends org.reactivestreams.Publisher<U>> debounceSelector;

  org.reactivestreams.Subscription upstream;

  final java.util.concurrent.atomic.AtomicReference<io.reactivex.rxjava3.disposables.Disposable> debouncer;

  volatile long index;

  boolean done;

  io.reactivex.rxjava3.internal.operators.flowable.FlowableDebounce$DebounceSubscriber(org.reactivestreams.Subscriber<? super T>, io.reactivex.rxjava3.functions.Function<? super T, ? extends org.reactivestreams.Publisher<U>>);
    Code:
       0: aload_0
       1: invokespecial #1                  // Method java/util/concurrent/atomic/AtomicLong."<init>":()V
       4: aload_0
       5: new           #2                  // class java/util/concurrent/atomic/AtomicReference
       8: dup
       9: invokespecial #3                  // Method java/util/concurrent/atomic/AtomicReference."<init>":()V
      12: putfield      #4                  // Field debouncer:Ljava/util/concurrent/atomic/AtomicReference;
      15: aload_0
      16: aload_1
      17: putfield      #5                  // Field downstream:Lorg/reactivestreams/Subscriber;
      20: aload_0
      21: aload_2
      22: putfield      #6                  // Field debounceSelector:Lio/reactivex/rxjava3/functions/Function;
      25: return

  public void onSubscribe(org.reactivestreams.Subscription);
    Code:
       0: aload_0
       1: getfield      #7                  // Field upstream:Lorg/reactivestreams/Subscription;
       4: aload_1
       5: invokestatic  #8                  // Method io/reactivex/rxjava3/internal/subscriptions/SubscriptionHelper.validate:(Lorg/reactivestreams/Subscription;Lorg/reactivestreams/Subscription;)Z
       8: ifeq          35
      11: aload_0
      12: aload_1
      13: putfield      #7                  // Field upstream:Lorg/reactivestreams/Subscription;
      16: aload_0
      17: getfield      #5                  // Field downstream:Lorg/reactivestreams/Subscriber;
      20: aload_0
      21: invokeinterface #9,  2            // InterfaceMethod org/reactivestreams/Subscriber.onSubscribe:(Lorg/reactivestreams/Subscription;)V
      26: aload_1
      27: ldc2_w        #11                 // long 9223372036854775807l
      30: invokeinterface #13,  3           // InterfaceMethod org/reactivestreams/Subscription.request:(J)V
      35: return

  public void onNext(T);
    Code:
       0: aload_0
       1: getfield      #14                 // Field done:Z
       4: ifeq          8
       7: return
       8: aload_0
       9: getfield      #15                 // Field index:J
      12: lconst_1
      13: ladd
      14: lstore_2
      15: aload_0
      16: lload_2
      17: putfield      #15                 // Field index:J
      20: aload_0
      21: getfield      #4                  // Field debouncer:Ljava/util/concurrent/atomic/AtomicReference;
      24: invokevirtual #16                 // Method java/util/concurrent/atomic/AtomicReference.get:()Ljava/lang/Object;
      27: checkcast     #17                 // class io/reactivex/rxjava3/disposables/Disposable
      30: astore        4
      32: aload         4
      34: ifnull        44
      37: aload         4
      39: invokeinterface #18,  1           // InterfaceMethod io/reactivex/rxjava3/disposables/Disposable.dispose:()V
      44: aload_0
      45: getfield      #6                  // Field debounceSelector:Lio/reactivex/rxjava3/functions/Function;
      48: aload_1
      49: invokeinterface #19,  2           // InterfaceMethod io/reactivex/rxjava3/functions/Function.apply:(Ljava/lang/Object;)Ljava/lang/Object;
      54: ldc           #20                 // String The publisher supplied is null
      56: invokestatic  #21                 // Method java/util/Objects.requireNonNull:(Ljava/lang/Object;Ljava/lang/String;)Ljava/lang/Object;
      59: checkcast     #22                 // class org/reactivestreams/Publisher
      62: astore        5
      64: goto          90
      67: astore        6
      69: aload         6
      71: invokestatic  #24                 // Method io/reactivex/rxjava3/exceptions/Exceptions.throwIfFatal:(Ljava/lang/Throwable;)V
      74: aload_0
      75: invokevirtual #25                 // Method cancel:()V
      78: aload_0
      79: getfield      #5                  // Field downstream:Lorg/reactivestreams/Subscriber;
      82: aload         6
      84: invokeinterface #26,  2           // InterfaceMethod org/reactivestreams/Subscriber.onError:(Ljava/lang/Throwable;)V
      89: return
      90: new           #27                 // class io/reactivex/rxjava3/internal/operators/flowable/FlowableDebounce$DebounceSubscriber$DebounceInnerSubscriber
      93: dup
      94: aload_0
      95: lload_2
      96: aload_1
      97: invokespecial #28                 // Method io/reactivex/rxjava3/internal/operators/flowable/FlowableDebounce$DebounceSubscriber$DebounceInnerSubscriber."<init>":(Lio/reactivex/rxjava3/internal/operators/flowable/FlowableDebounce$DebounceSubscriber;JLjava/lang/Object;)V
     100: astore        6
     102: aload_0
     103: getfield      #4                  // Field debouncer:Ljava/util/concurrent/atomic/AtomicReference;
     106: aload         4
     108: aload         6
     110: invokevirtual #29                 // Method java/util/concurrent/atomic/AtomicReference.compareAndSet:(Ljava/lang/Object;Ljava/lang/Object;)Z
     113: ifeq          125
     116: aload         5
     118: aload         6
     120: invokeinterface #30,  2           // InterfaceMethod org/reactivestreams/Publisher.subscribe:(Lorg/reactivestreams/Subscriber;)V
     125: return
    Exception table:
       from    to  target type
          44    64    67   Class java/lang/Throwable

  public void onError(java.lang.Throwable);
    Code:
       0: aload_0
       1: getfield      #4                  // Field debouncer:Ljava/util/concurrent/atomic/AtomicReference;
       4: invokestatic  #31                 // Method io/reactivex/rxjava3/internal/disposables/DisposableHelper.dispose:(Ljava/util/concurrent/atomic/AtomicReference;)Z
       7: pop
       8: aload_0
       9: getfield      #5                  // Field downstream:Lorg/reactivestreams/Subscriber;
      12: aload_1
      13: invokeinterface #26,  2           // InterfaceMethod org/reactivestreams/Subscriber.onError:(Ljava/lang/Throwable;)V
      18: return

  public void onComplete();
    Code:
       0: aload_0
       1: getfield      #14                 // Field done:Z
       4: ifeq          8
       7: return
       8: aload_0
       9: iconst_1
      10: putfield      #14                 // Field done:Z
      13: aload_0
      14: getfield      #4                  // Field debouncer:Ljava/util/concurrent/atomic/AtomicReference;
      17: invokevirtual #16                 // Method java/util/concurrent/atomic/AtomicReference.get:()Ljava/lang/Object;
      20: checkcast     #17                 // class io/reactivex/rxjava3/disposables/Disposable
      23: astore_1
      24: aload_1
      25: invokestatic  #32                 // Method io/reactivex/rxjava3/internal/disposables/DisposableHelper.isDisposed:(Lio/reactivex/rxjava3/disposables/Disposable;)Z
      28: ifne          61
      31: aload_1
      32: checkcast     #27                 // class io/reactivex/rxjava3/internal/operators/flowable/FlowableDebounce$DebounceSubscriber$DebounceInnerSubscriber
      35: astore_2
      36: aload_2
      37: ifnull        44
      40: aload_2
      41: invokevirtual #33                 // Method io/reactivex/rxjava3/internal/operators/flowable/FlowableDebounce$DebounceSubscriber$DebounceInnerSubscriber.emit:()V
      44: aload_0
      45: getfield      #4                  // Field debouncer:Ljava/util/concurrent/atomic/AtomicReference;
      48: invokestatic  #31                 // Method io/reactivex/rxjava3/internal/disposables/DisposableHelper.dispose:(Ljava/util/concurrent/atomic/AtomicReference;)Z
      51: pop
      52: aload_0
      53: getfield      #5                  // Field downstream:Lorg/reactivestreams/Subscriber;
      56: invokeinterface #34,  1           // InterfaceMethod org/reactivestreams/Subscriber.onComplete:()V
      61: return

  public void request(long);
    Code:
       0: lload_1
       1: invokestatic  #35                 // Method io/reactivex/rxjava3/internal/subscriptions/SubscriptionHelper.validate:(J)Z
       4: ifeq          13
       7: aload_0
       8: lload_1
       9: invokestatic  #36                 // Method io/reactivex/rxjava3/internal/util/BackpressureHelper.add:(Ljava/util/concurrent/atomic/AtomicLong;J)J
      12: pop2
      13: return

  public void cancel();
    Code:
       0: aload_0
       1: getfield      #7                  // Field upstream:Lorg/reactivestreams/Subscription;
       4: invokeinterface #37,  1           // InterfaceMethod org/reactivestreams/Subscription.cancel:()V
       9: aload_0
      10: getfield      #4                  // Field debouncer:Ljava/util/concurrent/atomic/AtomicReference;
      13: invokestatic  #31                 // Method io/reactivex/rxjava3/internal/disposables/DisposableHelper.dispose:(Ljava/util/concurrent/atomic/AtomicReference;)Z
      16: pop
      17: return

  void emit(long, T);
    Code:
       0: lload_1
       1: aload_0
       2: getfield      #15                 // Field index:J
       5: lcmp
       6: ifne          57
       9: aload_0
      10: invokevirtual #38                 // Method get:()J
      13: lstore        4
      15: lload         4
      17: lconst_0
      18: lcmp
      19: ifeq          41
      22: aload_0
      23: getfield      #5                  // Field downstream:Lorg/reactivestreams/Subscriber;
      26: aload_3
      27: invokeinterface #39,  2           // InterfaceMethod org/reactivestreams/Subscriber.onNext:(Ljava/lang/Object;)V
      32: aload_0
      33: lconst_1
      34: invokestatic  #40                 // Method io/reactivex/rxjava3/internal/util/BackpressureHelper.produced:(Ljava/util/concurrent/atomic/AtomicLong;J)J
      37: pop2
      38: goto          57
      41: aload_0
      42: invokevirtual #25                 // Method cancel:()V
      45: aload_0
      46: getfield      #5                  // Field downstream:Lorg/reactivestreams/Subscriber;
      49: invokestatic  #41                 // Method io/reactivex/rxjava3/exceptions/MissingBackpressureException.createDefault:()Lio/reactivex/rxjava3/exceptions/MissingBackpressureException;
      52: invokeinterface #26,  2           // InterfaceMethod org/reactivestreams/Subscriber.onError:(Ljava/lang/Throwable;)V
      57: return
}
