Compiled from "FlowableDoAfterNext.java"
final class io.reactivex.rxjava3.internal.operators.flowable.FlowableDoAfterNext$DoAfterSubscriber<T> extends io.reactivex.rxjava3.internal.subscribers.BasicFuseableSubscriber<T, T> {
  final io.reactivex.rxjava3.functions.Consumer<? super T> onAfterNext;

  io.reactivex.rxjava3.internal.operators.flowable.FlowableDoAfterNext$DoAfterSubscriber(org.reactivestreams.Subscriber<? super T>, io.reactivex.rxjava3.functions.Consumer<? super T>);
    Code:
       0: aload_0
       1: aload_1
       2: invokespecial #1                  // Method io/reactivex/rxjava3/internal/subscribers/BasicFuseableSubscriber."<init>":(Lorg/reactivestreams/Subscriber;)V
       5: aload_0
       6: aload_2
       7: putfield      #2                  // Field onAfterNext:Lio/reactivex/rxjava3/functions/Consumer;
      10: return

  public void onNext(T);
    Code:
       0: aload_0
       1: getfield      #3                  // Field done:Z
       4: ifeq          8
       7: return
       8: aload_0
       9: getfield      #4                  // Field downstream:Lorg/reactivestreams/Subscriber;
      12: aload_1
      13: invokeinterface #5,  2            // InterfaceMethod org/reactivestreams/Subscriber.onNext:(Ljava/lang/Object;)V
      18: aload_0
      19: getfield      #6                  // Field sourceMode:I
      22: ifne          44
      25: aload_0
      26: getfield      #2                  // Field onAfterNext:Lio/reactivex/rxjava3/functions/Consumer;
      29: aload_1
      30: invokeinterface #7,  2            // InterfaceMethod io/reactivex/rxjava3/functions/Consumer.accept:(Ljava/lang/Object;)V
      35: goto          44
      38: astore_2
      39: aload_0
      40: aload_2
      41: invokevirtual #9                  // Method fail:(Ljava/lang/Throwable;)V
      44: return
    Exception table:
       from    to  target type
          25    35    38   Class java/lang/Throwable

  public int requestFusion(int);
    Code:
       0: aload_0
       1: iload_1
       2: invokevirtual #10                 // Method transitiveBoundaryFusion:(I)I
       5: ireturn

  public T poll() throws java.lang.Throwable;
    Code:
       0: aload_0
       1: getfield      #11                 // Field qs:Lio/reactivex/rxjava3/operators/QueueSubscription;
       4: invokeinterface #12,  1           // InterfaceMethod io/reactivex/rxjava3/operators/QueueSubscription.poll:()Ljava/lang/Object;
       9: astore_1
      10: aload_1
      11: ifnull        24
      14: aload_0
      15: getfield      #2                  // Field onAfterNext:Lio/reactivex/rxjava3/functions/Consumer;
      18: aload_1
      19: invokeinterface #7,  2            // InterfaceMethod io/reactivex/rxjava3/functions/Consumer.accept:(Ljava/lang/Object;)V
      24: aload_1
      25: areturn
}
