Compiled from "FlowableFromIterable.java"
final class io.reactivex.rxjava3.internal.operators.flowable.FlowableFromIterable$IteratorConditionalSubscription<T> extends io.reactivex.rxjava3.internal.operators.flowable.FlowableFromIterable$BaseRangeSubscription<T> {
  private static final long serialVersionUID;

  final io.reactivex.rxjava3.operators.ConditionalSubscriber<? super T> downstream;

  io.reactivex.rxjava3.internal.operators.flowable.FlowableFromIterable$IteratorConditionalSubscription(io.reactivex.rxjava3.operators.ConditionalSubscriber<? super T>, java.util.Iterator<? extends T>);
    Code:
       0: aload_0
       1: aload_2
       2: invokespecial #1                  // Method io/reactivex/rxjava3/internal/operators/flowable/FlowableFromIterable$BaseRangeSubscription."<init>":(Ljava/util/Iterator;)V
       5: aload_0
       6: aload_1
       7: putfield      #2                  // Field downstream:Lio/reactivex/rxjava3/operators/ConditionalSubscriber;
      10: return

  void fastPath();
    Code:
       0: aload_0
       1: getfield      #3                  // Field iterator:Ljava/util/Iterator;
       4: astore_1
       5: aload_0
       6: getfield      #2                  // Field downstream:Lio/reactivex/rxjava3/operators/ConditionalSubscriber;
       9: astore_2
      10: aload_0
      11: getfield      #4                  // Field cancelled:Z
      14: ifeq          18
      17: return
      18: aload_1
      19: invokeinterface #5,  1            // InterfaceMethod java/util/Iterator.next:()Ljava/lang/Object;
      24: astore_3
      25: goto          44
      28: astore        4
      30: aload         4
      32: invokestatic  #7                  // Method io/reactivex/rxjava3/exceptions/Exceptions.throwIfFatal:(Ljava/lang/Throwable;)V
      35: aload_2
      36: aload         4
      38: invokeinterface #8,  2            // InterfaceMethod io/reactivex/rxjava3/operators/ConditionalSubscriber.onError:(Ljava/lang/Throwable;)V
      43: return
      44: aload_0
      45: getfield      #4                  // Field cancelled:Z
      48: ifeq          52
      51: return
      52: aload_3
      53: ifnonnull     72
      56: aload_2
      57: new           #9                  // class java/lang/NullPointerException
      60: dup
      61: ldc           #10                 // String Iterator.next() returned a null value
      63: invokespecial #11                 // Method java/lang/NullPointerException."<init>":(Ljava/lang/String;)V
      66: invokeinterface #8,  2            // InterfaceMethod io/reactivex/rxjava3/operators/ConditionalSubscriber.onError:(Ljava/lang/Throwable;)V
      71: return
      72: aload_2
      73: aload_3
      74: invokeinterface #12,  2           // InterfaceMethod io/reactivex/rxjava3/operators/ConditionalSubscriber.tryOnNext:(Ljava/lang/Object;)Z
      79: pop
      80: aload_0
      81: getfield      #4                  // Field cancelled:Z
      84: ifeq          88
      87: return
      88: aload_1
      89: invokeinterface #13,  1           // InterfaceMethod java/util/Iterator.hasNext:()Z
      94: istore        4
      96: goto          115
      99: astore        5
     101: aload         5
     103: invokestatic  #7                  // Method io/reactivex/rxjava3/exceptions/Exceptions.throwIfFatal:(Ljava/lang/Throwable;)V
     106: aload_2
     107: aload         5
     109: invokeinterface #8,  2            // InterfaceMethod io/reactivex/rxjava3/operators/ConditionalSubscriber.onError:(Ljava/lang/Throwable;)V
     114: return
     115: iload         4
     117: ifne          134
     120: aload_0
     121: getfield      #4                  // Field cancelled:Z
     124: ifne          133
     127: aload_2
     128: invokeinterface #14,  1           // InterfaceMethod io/reactivex/rxjava3/operators/ConditionalSubscriber.onComplete:()V
     133: return
     134: goto          10
    Exception table:
       from    to  target type
          18    25    28   Class java/lang/Throwable
          88    96    99   Class java/lang/Throwable

  void slowPath(long);
    Code:
       0: lconst_0
       1: lstore_3
       2: aload_0
       3: getfield      #3                  // Field iterator:Ljava/util/Iterator;
       6: astore        5
       8: aload_0
       9: getfield      #2                  // Field downstream:Lio/reactivex/rxjava3/operators/ConditionalSubscriber;
      12: astore        6
      14: lload_3
      15: lload_1
      16: lcmp
      17: ifeq          167
      20: aload_0
      21: getfield      #4                  // Field cancelled:Z
      24: ifeq          28
      27: return
      28: aload         5
      30: invokeinterface #5,  1            // InterfaceMethod java/util/Iterator.next:()Ljava/lang/Object;
      35: astore        7
      37: goto          57
      40: astore        8
      42: aload         8
      44: invokestatic  #7                  // Method io/reactivex/rxjava3/exceptions/Exceptions.throwIfFatal:(Ljava/lang/Throwable;)V
      47: aload         6
      49: aload         8
      51: invokeinterface #8,  2            // InterfaceMethod io/reactivex/rxjava3/operators/ConditionalSubscriber.onError:(Ljava/lang/Throwable;)V
      56: return
      57: aload_0
      58: getfield      #4                  // Field cancelled:Z
      61: ifeq          65
      64: return
      65: aload         7
      67: ifnonnull     87
      70: aload         6
      72: new           #9                  // class java/lang/NullPointerException
      75: dup
      76: ldc           #10                 // String Iterator.next() returned a null value
      78: invokespecial #11                 // Method java/lang/NullPointerException."<init>":(Ljava/lang/String;)V
      81: invokeinterface #8,  2            // InterfaceMethod io/reactivex/rxjava3/operators/ConditionalSubscriber.onError:(Ljava/lang/Throwable;)V
      86: return
      87: aload         6
      89: aload         7
      91: invokeinterface #12,  2           // InterfaceMethod io/reactivex/rxjava3/operators/ConditionalSubscriber.tryOnNext:(Ljava/lang/Object;)Z
      96: istore        8
      98: aload_0
      99: getfield      #4                  // Field cancelled:Z
     102: ifeq          106
     105: return
     106: aload         5
     108: invokeinterface #13,  1           // InterfaceMethod java/util/Iterator.hasNext:()Z
     113: istore        9
     115: goto          135
     118: astore        10
     120: aload         10
     122: invokestatic  #7                  // Method io/reactivex/rxjava3/exceptions/Exceptions.throwIfFatal:(Ljava/lang/Throwable;)V
     125: aload         6
     127: aload         10
     129: invokeinterface #8,  2            // InterfaceMethod io/reactivex/rxjava3/operators/ConditionalSubscriber.onError:(Ljava/lang/Throwable;)V
     134: return
     135: iload         9
     137: ifne          155
     140: aload_0
     141: getfield      #4                  // Field cancelled:Z
     144: ifne          154
     147: aload         6
     149: invokeinterface #14,  1           // InterfaceMethod io/reactivex/rxjava3/operators/ConditionalSubscriber.onComplete:()V
     154: return
     155: iload         8
     157: ifeq          164
     160: lload_3
     161: lconst_1
     162: ladd
     163: lstore_3
     164: goto          14
     167: aload_0
     168: invokevirtual #15                 // Method get:()J
     171: lstore_1
     172: lload_3
     173: lload_1
     174: lcmp
     175: ifne          14
     178: aload_0
     179: lload_3
     180: lneg
     181: invokevirtual #16                 // Method addAndGet:(J)J
     184: lstore_1
     185: lload_1
     186: lconst_0
     187: lcmp
     188: ifne          192
     191: return
     192: lconst_0
     193: lstore_3
     194: goto          14
    Exception table:
       from    to  target type
          28    37    40   Class java/lang/Throwable
         106   115   118   Class java/lang/Throwable
}
