Compiled from "FlowableSingleSingle.java"
public final class io.reactivex.rxjava3.internal.operators.flowable.FlowableSingleSingle<T> extends io.reactivex.rxjava3.core.Single<T> implements io.reactivex.rxjava3.internal.fuseable.FuseToFlowable<T> {
  final io.reactivex.rxjava3.core.Flowable<T> source;

  final T defaultValue;

  public io.reactivex.rxjava3.internal.operators.flowable.FlowableSingleSingle(io.reactivex.rxjava3.core.Flowable<T>, T);
    Code:
       0: aload_0
       1: invokespecial #1                  // Method io/reactivex/rxjava3/core/Single."<init>":()V
       4: aload_0
       5: aload_1
       6: putfield      #2                  // Field source:Lio/reactivex/rxjava3/core/Flowable;
       9: aload_0
      10: aload_2
      11: putfield      #3                  // Field defaultValue:Ljava/lang/Object;
      14: return

  protected void subscribeActual(io.reactivex.rxjava3.core.SingleObserver<? super T>);
    Code:
       0: aload_0
       1: getfield      #2                  // Field source:Lio/reactivex/rxjava3/core/Flowable;
       4: new           #4                  // class io/reactivex/rxjava3/internal/operators/flowable/FlowableSingleSingle$SingleElementSubscriber
       7: dup
       8: aload_1
       9: aload_0
      10: getfield      #3                  // Field defaultValue:Ljava/lang/Object;
      13: invokespecial #5                  // Method io/reactivex/rxjava3/internal/operators/flowable/FlowableSingleSingle$SingleElementSubscriber."<init>":(Lio/reactivex/rxjava3/core/SingleObserver;Ljava/lang/Object;)V
      16: invokevirtual #6                  // Method io/reactivex/rxjava3/core/Flowable.subscribe:(Lio/reactivex/rxjava3/core/FlowableSubscriber;)V
      19: return

  public io.reactivex.rxjava3.core.Flowable<T> fuseToFlowable();
    Code:
       0: new           #7                  // class io/reactivex/rxjava3/internal/operators/flowable/FlowableSingle
       3: dup
       4: aload_0
       5: getfield      #2                  // Field source:Lio/reactivex/rxjava3/core/Flowable;
       8: aload_0
       9: getfield      #3                  // Field defaultValue:Ljava/lang/Object;
      12: iconst_1
      13: invokespecial #8                  // Method io/reactivex/rxjava3/internal/operators/flowable/FlowableSingle."<init>":(Lio/reactivex/rxjava3/core/Flowable;Ljava/lang/Object;Z)V
      16: invokestatic  #9                  // Method io/reactivex/rxjava3/plugins/RxJavaPlugins.onAssembly:(Lio/reactivex/rxjava3/core/Flowable;)Lio/reactivex/rxjava3/core/Flowable;
      19: areturn
}
