Compiled from "FlowableCreate.java"
abstract class io.reactivex.rxjava3.internal.operators.flowable.FlowableCreate$NoOverflowBaseAsyncEmitter<T> extends io.reactivex.rxjava3.internal.operators.flowable.FlowableCreate$BaseEmitter<T> {
  private static final long serialVersionUID;

  io.reactivex.rxjava3.internal.operators.flowable.FlowableCreate$NoOverflowBaseAsyncEmitter(org.reactivestreams.Subscriber<? super T>);
    Code:
       0: aload_0
       1: aload_1
       2: invokespecial #1                  // Method io/reactivex/rxjava3/internal/operators/flowable/FlowableCreate$BaseEmitter."<init>":(Lorg/reactivestreams/Subscriber;)V
       5: return

  public final void onNext(T);
    Code:
       0: aload_0
       1: invokevirtual #2                  // Method isCancelled:()Z
       4: ifeq          8
       7: return
       8: aload_1
       9: ifnonnull     22
      12: aload_0
      13: ldc           #3                  // String onNext called with a null value.
      15: invokestatic  #4                  // Method io/reactivex/rxjava3/internal/util/ExceptionHelper.createNullPointerException:(Ljava/lang/String;)Ljava/lang/NullPointerException;
      18: invokevirtual #5                  // Method onError:(Ljava/lang/Throwable;)V
      21: return
      22: aload_0
      23: invokevirtual #6                  // Method get:()J
      26: lconst_0
      27: lcmp
      28: ifeq          50
      31: aload_0
      32: getfield      #7                  // Field downstream:Lorg/reactivestreams/Subscriber;
      35: aload_1
      36: invokeinterface #8,  2            // InterfaceMethod org/reactivestreams/Subscriber.onNext:(Ljava/lang/Object;)V
      41: aload_0
      42: lconst_1
      43: invokestatic  #9                  // Method io/reactivex/rxjava3/internal/util/BackpressureHelper.produced:(Ljava/util/concurrent/atomic/AtomicLong;J)J
      46: pop2
      47: goto          54
      50: aload_0
      51: invokevirtual #10                 // Method onOverflow:()V
      54: return

  abstract void onOverflow();
}
