Compiled from "FlowableDelay.java"
public final class io.reactivex.rxjava3.internal.operators.flowable.FlowableDelay<T> extends io.reactivex.rxjava3.internal.operators.flowable.AbstractFlowableWithUpstream<T, T> {
  final long delay;

  final java.util.concurrent.TimeUnit unit;

  final io.reactivex.rxjava3.core.Scheduler scheduler;

  final boolean delayError;

  public io.reactivex.rxjava3.internal.operators.flowable.FlowableDelay(io.reactivex.rxjava3.core.Flowable<T>, long, java.util.concurrent.TimeUnit, io.reactivex.rxjava3.core.Scheduler, boolean);
    Code:
       0: aload_0
       1: aload_1
       2: invokespecial #1                  // Method io/reactivex/rxjava3/internal/operators/flowable/AbstractFlowableWithUpstream."<init>":(Lio/reactivex/rxjava3/core/Flowable;)V
       5: aload_0
       6: lload_2
       7: putfield      #2                  // Field delay:J
      10: aload_0
      11: aload         4
      13: putfield      #3                  // Field unit:Ljava/util/concurrent/TimeUnit;
      16: aload_0
      17: aload         5
      19: putfield      #4                  // Field scheduler:Lio/reactivex/rxjava3/core/Scheduler;
      22: aload_0
      23: iload         6
      25: putfield      #5                  // Field delayError:Z
      28: return

  protected void subscribeActual(org.reactivestreams.Subscriber<? super T>);
    Code:
       0: aload_0
       1: getfield      #5                  // Field delayError:Z
       4: ifeq          12
       7: aload_1
       8: astore_2
       9: goto          21
      12: new           #6                  // class io/reactivex/rxjava3/subscribers/SerializedSubscriber
      15: dup
      16: aload_1
      17: invokespecial #7                  // Method io/reactivex/rxjava3/subscribers/SerializedSubscriber."<init>":(Lorg/reactivestreams/Subscriber;)V
      20: astore_2
      21: aload_0
      22: getfield      #4                  // Field scheduler:Lio/reactivex/rxjava3/core/Scheduler;
      25: invokevirtual #8                  // Method io/reactivex/rxjava3/core/Scheduler.createWorker:()Lio/reactivex/rxjava3/core/Scheduler$Worker;
      28: astore_3
      29: aload_0
      30: getfield      #9                  // Field source:Lio/reactivex/rxjava3/core/Flowable;
      33: new           #10                 // class io/reactivex/rxjava3/internal/operators/flowable/FlowableDelay$DelaySubscriber
      36: dup
      37: aload_2
      38: aload_0
      39: getfield      #2                  // Field delay:J
      42: aload_0
      43: getfield      #3                  // Field unit:Ljava/util/concurrent/TimeUnit;
      46: aload_3
      47: aload_0
      48: getfield      #5                  // Field delayError:Z
      51: invokespecial #11                 // Method io/reactivex/rxjava3/internal/operators/flowable/FlowableDelay$DelaySubscriber."<init>":(Lorg/reactivestreams/Subscriber;JLjava/util/concurrent/TimeUnit;Lio/reactivex/rxjava3/core/Scheduler$Worker;Z)V
      54: invokevirtual #12                 // Method io/reactivex/rxjava3/core/Flowable.subscribe:(Lio/reactivex/rxjava3/core/FlowableSubscriber;)V
      57: return
}
