Compiled from "FlowableOnBackpressureBufferStrategy.java"
public final class io.reactivex.rxjava3.internal.operators.flowable.FlowableOnBackpressureBufferStrategy<T> extends io.reactivex.rxjava3.internal.operators.flowable.AbstractFlowableWithUpstream<T, T> {
  final long bufferSize;

  final io.reactivex.rxjava3.functions.Action onOverflow;

  final io.reactivex.rxjava3.core.BackpressureOverflowStrategy strategy;

  public io.reactivex.rxjava3.internal.operators.flowable.FlowableOnBackpressureBufferStrategy(io.reactivex.rxjava3.core.Flowable<T>, long, io.reactivex.rxjava3.functions.Action, io.reactivex.rxjava3.core.BackpressureOverflowStrategy);
    Code:
       0: aload_0
       1: aload_1
       2: invokespecial #1                  // Method io/reactivex/rxjava3/internal/operators/flowable/AbstractFlowableWithUpstream."<init>":(Lio/reactivex/rxjava3/core/Flowable;)V
       5: aload_0
       6: lload_2
       7: putfield      #2                  // Field bufferSize:J
      10: aload_0
      11: aload         4
      13: putfield      #3                  // Field onOverflow:Lio/reactivex/rxjava3/functions/Action;
      16: aload_0
      17: aload         5
      19: putfield      #4                  // Field strategy:Lio/reactivex/rxjava3/core/BackpressureOverflowStrategy;
      22: return

  protected void subscribeActual(org.reactivestreams.Subscriber<? super T>);
    Code:
       0: aload_0
       1: getfield      #5                  // Field source:Lio/reactivex/rxjava3/core/Flowable;
       4: new           #6                  // class io/reactivex/rxjava3/internal/operators/flowable/FlowableOnBackpressureBufferStrategy$OnBackpressureBufferStrategySubscriber
       7: dup
       8: aload_1
       9: aload_0
      10: getfield      #3                  // Field onOverflow:Lio/reactivex/rxjava3/functions/Action;
      13: aload_0
      14: getfield      #4                  // Field strategy:Lio/reactivex/rxjava3/core/BackpressureOverflowStrategy;
      17: aload_0
      18: getfield      #2                  // Field bufferSize:J
      21: invokespecial #7                  // Method io/reactivex/rxjava3/internal/operators/flowable/FlowableOnBackpressureBufferStrategy$OnBackpressureBufferStrategySubscriber."<init>":(Lorg/reactivestreams/Subscriber;Lio/reactivex/rxjava3/functions/Action;Lio/reactivex/rxjava3/core/BackpressureOverflowStrategy;J)V
      24: invokevirtual #8                  // Method io/reactivex/rxjava3/core/Flowable.subscribe:(Lio/reactivex/rxjava3/core/FlowableSubscriber;)V
      27: return
}
