Compiled from "FlowableUnsubscribeOn.java"
final class io.reactivex.rxjava3.internal.operators.flowable.FlowableUnsubscribeOn$UnsubscribeSubscriber$Cancellation implements java.lang.Runnable {
  final io.reactivex.rxjava3.internal.operators.flowable.FlowableUnsubscribeOn$UnsubscribeSubscriber this$0;

  io.reactivex.rxjava3.internal.operators.flowable.FlowableUnsubscribeOn$UnsubscribeSubscriber$Cancellation(io.reactivex.rxjava3.internal.operators.flowable.FlowableUnsubscribeOn$UnsubscribeSubscriber);
    Code:
       0: aload_0
       1: aload_1
       2: putfield      #1                  // Field this$0:Lio/reactivex/rxjava3/internal/operators/flowable/FlowableUnsubscribeOn$UnsubscribeSubscriber;
       5: aload_0
       6: invokespecial #2                  // Method java/lang/Object."<init>":()V
       9: return

  public void run();
    Code:
       0: aload_0
       1: getfield      #1                  // Field this$0:Lio/reactivex/rxjava3/internal/operators/flowable/FlowableUnsubscribeOn$UnsubscribeSubscriber;
       4: getfield      #3                  // Field io/reactivex/rxjava3/internal/operators/flowable/FlowableUnsubscribeOn$UnsubscribeSubscriber.upstream:Lorg/reactivestreams/Subscription;
       7: invokeinterface #4,  1            // InterfaceMethod org/reactivestreams/Subscription.cancel:()V
      12: return
}
