Compiled from "FlowableInternalHelper.java"
final class io.reactivex.rxjava3.internal.operators.flowable.FlowableInternalHelper$BufferedTimedReplay<T> implements io.reactivex.rxjava3.functions.Supplier<io.reactivex.rxjava3.flowables.ConnectableFlowable<T>> {
  final io.reactivex.rxjava3.core.Flowable<T> parent;

  final int bufferSize;

  final long time;

  final java.util.concurrent.TimeUnit unit;

  final io.reactivex.rxjava3.core.Scheduler scheduler;

  final boolean eagerTruncate;

  io.reactivex.rxjava3.internal.operators.flowable.FlowableInternalHelper$BufferedTimedReplay(io.reactivex.rxjava3.core.Flowable<T>, int, long, java.util.concurrent.TimeUnit, io.reactivex.rxjava3.core.Scheduler, boolean);
    Code:
       0: aload_0
       1: invokespecial #1                  // Method java/lang/Object."<init>":()V
       4: aload_0
       5: aload_1
       6: putfield      #2                  // Field parent:Lio/reactivex/rxjava3/core/Flowable;
       9: aload_0
      10: iload_2
      11: putfield      #3                  // Field bufferSize:I
      14: aload_0
      15: lload_3
      16: putfield      #4                  // Field time:J
      19: aload_0
      20: aload         5
      22: putfield      #5                  // Field unit:Ljava/util/concurrent/TimeUnit;
      25: aload_0
      26: aload         6
      28: putfield      #6                  // Field scheduler:Lio/reactivex/rxjava3/core/Scheduler;
      31: aload_0
      32: iload         7
      34: putfield      #7                  // Field eagerTruncate:Z
      37: return

  public io.reactivex.rxjava3.flowables.ConnectableFlowable<T> get();
    Code:
       0: aload_0
       1: getfield      #2                  // Field parent:Lio/reactivex/rxjava3/core/Flowable;
       4: aload_0
       5: getfield      #3                  // Field bufferSize:I
       8: aload_0
       9: getfield      #4                  // Field time:J
      12: aload_0
      13: getfield      #5                  // Field unit:Ljava/util/concurrent/TimeUnit;
      16: aload_0
      17: getfield      #6                  // Field scheduler:Lio/reactivex/rxjava3/core/Scheduler;
      20: aload_0
      21: getfield      #7                  // Field eagerTruncate:Z
      24: invokevirtual #8                  // Method io/reactivex/rxjava3/core/Flowable.replay:(IJLjava/util/concurrent/TimeUnit;Lio/reactivex/rxjava3/core/Scheduler;Z)Lio/reactivex/rxjava3/flowables/ConnectableFlowable;
      27: areturn

  public java.lang.Object get() throws java.lang.Throwable;
    Code:
       0: aload_0
       1: invokevirtual #9                  // Method get:()Lio/reactivex/rxjava3/flowables/ConnectableFlowable;
       4: areturn
}
