Compiled from "FlowableTakeLastTimed.java"
final class io.reactivex.rxjava3.internal.operators.flowable.FlowableTakeLastTimed$TakeLastTimedSubscriber<T> extends java.util.concurrent.atomic.AtomicInteger implements io.reactivex.rxjava3.core.FlowableSubscriber<T>, org.reactivestreams.Subscription {
  private static final long serialVersionUID;

  final org.reactivestreams.Subscriber<? super T> downstream;

  final long count;

  final long time;

  final java.util.concurrent.TimeUnit unit;

  final io.reactivex.rxjava3.core.Scheduler scheduler;

  final io.reactivex.rxjava3.operators.SpscLinkedArrayQueue<java.lang.Object> queue;

  final boolean delayError;

  org.reactivestreams.Subscription upstream;

  final java.util.concurrent.atomic.AtomicLong requested;

  volatile boolean cancelled;

  volatile boolean done;

  java.lang.Throwable error;

  io.reactivex.rxjava3.internal.operators.flowable.FlowableTakeLastTimed$TakeLastTimedSubscriber(org.reactivestreams.Subscriber<? super T>, long, long, java.util.concurrent.TimeUnit, io.reactivex.rxjava3.core.Scheduler, int, boolean);
    Code:
       0: aload_0
       1: invokespecial #1                  // Method java/util/concurrent/atomic/AtomicInteger."<init>":()V
       4: aload_0
       5: new           #2                  // class java/util/concurrent/atomic/AtomicLong
       8: dup
       9: invokespecial #3                  // Method java/util/concurrent/atomic/AtomicLong."<init>":()V
      12: putfield      #4                  // Field requested:Ljava/util/concurrent/atomic/AtomicLong;
      15: aload_0
      16: aload_1
      17: putfield      #5                  // Field downstream:Lorg/reactivestreams/Subscriber;
      20: aload_0
      21: lload_2
      22: putfield      #6                  // Field count:J
      25: aload_0
      26: lload         4
      28: putfield      #7                  // Field time:J
      31: aload_0
      32: aload         6
      34: putfield      #8                  // Field unit:Ljava/util/concurrent/TimeUnit;
      37: aload_0
      38: aload         7
      40: putfield      #9                  // Field scheduler:Lio/reactivex/rxjava3/core/Scheduler;
      43: aload_0
      44: new           #10                 // class io/reactivex/rxjava3/operators/SpscLinkedArrayQueue
      47: dup
      48: iload         8
      50: invokespecial #11                 // Method io/reactivex/rxjava3/operators/SpscLinkedArrayQueue."<init>":(I)V
      53: putfield      #12                 // Field queue:Lio/reactivex/rxjava3/operators/SpscLinkedArrayQueue;
      56: aload_0
      57: iload         9
      59: putfield      #13                 // Field delayError:Z
      62: return

  public void onSubscribe(org.reactivestreams.Subscription);
    Code:
       0: aload_0
       1: getfield      #14                 // Field upstream:Lorg/reactivestreams/Subscription;
       4: aload_1
       5: invokestatic  #15                 // Method io/reactivex/rxjava3/internal/subscriptions/SubscriptionHelper.validate:(Lorg/reactivestreams/Subscription;Lorg/reactivestreams/Subscription;)Z
       8: ifeq          35
      11: aload_0
      12: aload_1
      13: putfield      #14                 // Field upstream:Lorg/reactivestreams/Subscription;
      16: aload_0
      17: getfield      #5                  // Field downstream:Lorg/reactivestreams/Subscriber;
      20: aload_0
      21: invokeinterface #16,  2           // InterfaceMethod org/reactivestreams/Subscriber.onSubscribe:(Lorg/reactivestreams/Subscription;)V
      26: aload_1
      27: ldc2_w        #18                 // long 9223372036854775807l
      30: invokeinterface #20,  3           // InterfaceMethod org/reactivestreams/Subscription.request:(J)V
      35: return

  public void onNext(T);
    Code:
       0: aload_0
       1: getfield      #12                 // Field queue:Lio/reactivex/rxjava3/operators/SpscLinkedArrayQueue;
       4: astore_2
       5: aload_0
       6: getfield      #9                  // Field scheduler:Lio/reactivex/rxjava3/core/Scheduler;
       9: aload_0
      10: getfield      #8                  // Field unit:Ljava/util/concurrent/TimeUnit;
      13: invokevirtual #21                 // Method io/reactivex/rxjava3/core/Scheduler.now:(Ljava/util/concurrent/TimeUnit;)J
      16: lstore_3
      17: aload_2
      18: lload_3
      19: invokestatic  #22                 // Method java/lang/Long.valueOf:(J)Ljava/lang/Long;
      22: aload_1
      23: invokevirtual #23                 // Method io/reactivex/rxjava3/operators/SpscLinkedArrayQueue.offer:(Ljava/lang/Object;Ljava/lang/Object;)Z
      26: pop
      27: aload_0
      28: lload_3
      29: aload_2
      30: invokevirtual #24                 // Method trim:(JLio/reactivex/rxjava3/operators/SpscLinkedArrayQueue;)V
      33: return

  public void onError(java.lang.Throwable);
    Code:
       0: aload_0
       1: getfield      #13                 // Field delayError:Z
       4: ifeq          26
       7: aload_0
       8: aload_0
       9: getfield      #9                  // Field scheduler:Lio/reactivex/rxjava3/core/Scheduler;
      12: aload_0
      13: getfield      #8                  // Field unit:Ljava/util/concurrent/TimeUnit;
      16: invokevirtual #21                 // Method io/reactivex/rxjava3/core/Scheduler.now:(Ljava/util/concurrent/TimeUnit;)J
      19: aload_0
      20: getfield      #12                 // Field queue:Lio/reactivex/rxjava3/operators/SpscLinkedArrayQueue;
      23: invokevirtual #24                 // Method trim:(JLio/reactivex/rxjava3/operators/SpscLinkedArrayQueue;)V
      26: aload_0
      27: aload_1
      28: putfield      #25                 // Field error:Ljava/lang/Throwable;
      31: aload_0
      32: iconst_1
      33: putfield      #26                 // Field done:Z
      36: aload_0
      37: invokevirtual #27                 // Method drain:()V
      40: return

  public void onComplete();
    Code:
       0: aload_0
       1: aload_0
       2: getfield      #9                  // Field scheduler:Lio/reactivex/rxjava3/core/Scheduler;
       5: aload_0
       6: getfield      #8                  // Field unit:Ljava/util/concurrent/TimeUnit;
       9: invokevirtual #21                 // Method io/reactivex/rxjava3/core/Scheduler.now:(Ljava/util/concurrent/TimeUnit;)J
      12: aload_0
      13: getfield      #12                 // Field queue:Lio/reactivex/rxjava3/operators/SpscLinkedArrayQueue;
      16: invokevirtual #24                 // Method trim:(JLio/reactivex/rxjava3/operators/SpscLinkedArrayQueue;)V
      19: aload_0
      20: iconst_1
      21: putfield      #26                 // Field done:Z
      24: aload_0
      25: invokevirtual #27                 // Method drain:()V
      28: return

  void trim(long, io.reactivex.rxjava3.operators.SpscLinkedArrayQueue<java.lang.Object>);
    Code:
       0: aload_0
       1: getfield      #7                  // Field time:J
       4: lstore        4
       6: aload_0
       7: getfield      #6                  // Field count:J
      10: lstore        6
      12: lload         6
      14: ldc2_w        #18                 // long 9223372036854775807l
      17: lcmp
      18: ifne          25
      21: iconst_1
      22: goto          26
      25: iconst_0
      26: istore        8
      28: aload_3
      29: invokevirtual #28                 // Method io/reactivex/rxjava3/operators/SpscLinkedArrayQueue.isEmpty:()Z
      32: ifne          88
      35: aload_3
      36: invokevirtual #29                 // Method io/reactivex/rxjava3/operators/SpscLinkedArrayQueue.peek:()Ljava/lang/Object;
      39: checkcast     #17                 // class java/lang/Long
      42: invokevirtual #30                 // Method java/lang/Long.longValue:()J
      45: lstore        9
      47: lload         9
      49: lload_1
      50: lload         4
      52: lsub
      53: lcmp
      54: iflt          75
      57: iload         8
      59: ifne          88
      62: aload_3
      63: invokevirtual #31                 // Method io/reactivex/rxjava3/operators/SpscLinkedArrayQueue.size:()I
      66: iconst_1
      67: ishr
      68: i2l
      69: lload         6
      71: lcmp
      72: ifle          88
      75: aload_3
      76: invokevirtual #32                 // Method io/reactivex/rxjava3/operators/SpscLinkedArrayQueue.poll:()Ljava/lang/Object;
      79: pop
      80: aload_3
      81: invokevirtual #32                 // Method io/reactivex/rxjava3/operators/SpscLinkedArrayQueue.poll:()Ljava/lang/Object;
      84: pop
      85: goto          28
      88: return

  public void request(long);
    Code:
       0: lload_1
       1: invokestatic  #33                 // Method io/reactivex/rxjava3/internal/subscriptions/SubscriptionHelper.validate:(J)Z
       4: ifeq          20
       7: aload_0
       8: getfield      #4                  // Field requested:Ljava/util/concurrent/atomic/AtomicLong;
      11: lload_1
      12: invokestatic  #34                 // Method io/reactivex/rxjava3/internal/util/BackpressureHelper.add:(Ljava/util/concurrent/atomic/AtomicLong;J)J
      15: pop2
      16: aload_0
      17: invokevirtual #27                 // Method drain:()V
      20: return

  public void cancel();
    Code:
       0: aload_0
       1: getfield      #35                 // Field cancelled:Z
       4: ifne          35
       7: aload_0
       8: iconst_1
       9: putfield      #35                 // Field cancelled:Z
      12: aload_0
      13: getfield      #14                 // Field upstream:Lorg/reactivestreams/Subscription;
      16: invokeinterface #36,  1           // InterfaceMethod org/reactivestreams/Subscription.cancel:()V
      21: aload_0
      22: invokevirtual #37                 // Method getAndIncrement:()I
      25: ifne          35
      28: aload_0
      29: getfield      #12                 // Field queue:Lio/reactivex/rxjava3/operators/SpscLinkedArrayQueue;
      32: invokevirtual #38                 // Method io/reactivex/rxjava3/operators/SpscLinkedArrayQueue.clear:()V
      35: return

  void drain();
    Code:
       0: aload_0
       1: invokevirtual #37                 // Method getAndIncrement:()I
       4: ifeq          8
       7: return
       8: iconst_1
       9: istore_1
      10: aload_0
      11: getfield      #5                  // Field downstream:Lorg/reactivestreams/Subscriber;
      14: astore_2
      15: aload_0
      16: getfield      #12                 // Field queue:Lio/reactivex/rxjava3/operators/SpscLinkedArrayQueue;
      19: astore_3
      20: aload_0
      21: getfield      #13                 // Field delayError:Z
      24: istore        4
      26: aload_0
      27: getfield      #26                 // Field done:Z
      30: ifeq          151
      33: aload_3
      34: invokevirtual #28                 // Method io/reactivex/rxjava3/operators/SpscLinkedArrayQueue.isEmpty:()Z
      37: istore        5
      39: aload_0
      40: iload         5
      42: aload_2
      43: iload         4
      45: invokevirtual #39                 // Method checkTerminated:(ZLorg/reactivestreams/Subscriber;Z)Z
      48: ifeq          52
      51: return
      52: aload_0
      53: getfield      #4                  // Field requested:Ljava/util/concurrent/atomic/AtomicLong;
      56: invokevirtual #40                 // Method java/util/concurrent/atomic/AtomicLong.get:()J
      59: lstore        6
      61: lconst_0
      62: lstore        8
      64: aload_3
      65: invokevirtual #29                 // Method io/reactivex/rxjava3/operators/SpscLinkedArrayQueue.peek:()Ljava/lang/Object;
      68: astore        10
      70: aload         10
      72: ifnonnull     79
      75: iconst_1
      76: goto          80
      79: iconst_0
      80: istore        5
      82: aload_0
      83: iload         5
      85: aload_2
      86: iload         4
      88: invokevirtual #39                 // Method checkTerminated:(ZLorg/reactivestreams/Subscriber;Z)Z
      91: ifeq          95
      94: return
      95: lload         6
      97: lload         8
      99: lcmp
     100: ifne          106
     103: goto          134
     106: aload_3
     107: invokevirtual #32                 // Method io/reactivex/rxjava3/operators/SpscLinkedArrayQueue.poll:()Ljava/lang/Object;
     110: pop
     111: aload_3
     112: invokevirtual #32                 // Method io/reactivex/rxjava3/operators/SpscLinkedArrayQueue.poll:()Ljava/lang/Object;
     115: astore        11
     117: aload_2
     118: aload         11
     120: invokeinterface #41,  2           // InterfaceMethod org/reactivestreams/Subscriber.onNext:(Ljava/lang/Object;)V
     125: lload         8
     127: lconst_1
     128: ladd
     129: lstore        8
     131: goto          64
     134: lload         8
     136: lconst_0
     137: lcmp
     138: ifeq          151
     141: aload_0
     142: getfield      #4                  // Field requested:Ljava/util/concurrent/atomic/AtomicLong;
     145: lload         8
     147: invokestatic  #42                 // Method io/reactivex/rxjava3/internal/util/BackpressureHelper.produced:(Ljava/util/concurrent/atomic/AtomicLong;J)J
     150: pop2
     151: aload_0
     152: iload_1
     153: ineg
     154: invokevirtual #43                 // Method addAndGet:(I)I
     157: istore_1
     158: iload_1
     159: ifne          26
     162: goto          165
     165: return

  boolean checkTerminated(boolean, org.reactivestreams.Subscriber<? super T>, boolean);
    Code:
       0: aload_0
       1: getfield      #35                 // Field cancelled:Z
       4: ifeq          16
       7: aload_0
       8: getfield      #12                 // Field queue:Lio/reactivex/rxjava3/operators/SpscLinkedArrayQueue;
      11: invokevirtual #38                 // Method io/reactivex/rxjava3/operators/SpscLinkedArrayQueue.clear:()V
      14: iconst_1
      15: ireturn
      16: iload_3
      17: ifeq          54
      20: iload_1
      21: ifeq          94
      24: aload_0
      25: getfield      #25                 // Field error:Ljava/lang/Throwable;
      28: astore        4
      30: aload         4
      32: ifnull        46
      35: aload_2
      36: aload         4
      38: invokeinterface #44,  2           // InterfaceMethod org/reactivestreams/Subscriber.onError:(Ljava/lang/Throwable;)V
      43: goto          52
      46: aload_2
      47: invokeinterface #45,  1           // InterfaceMethod org/reactivestreams/Subscriber.onComplete:()V
      52: iconst_1
      53: ireturn
      54: aload_0
      55: getfield      #25                 // Field error:Ljava/lang/Throwable;
      58: astore        4
      60: aload         4
      62: ifnull        82
      65: aload_0
      66: getfield      #12                 // Field queue:Lio/reactivex/rxjava3/operators/SpscLinkedArrayQueue;
      69: invokevirtual #38                 // Method io/reactivex/rxjava3/operators/SpscLinkedArrayQueue.clear:()V
      72: aload_2
      73: aload         4
      75: invokeinterface #44,  2           // InterfaceMethod org/reactivestreams/Subscriber.onError:(Ljava/lang/Throwable;)V
      80: iconst_1
      81: ireturn
      82: iload_1
      83: ifeq          94
      86: aload_2
      87: invokeinterface #45,  1           // InterfaceMethod org/reactivestreams/Subscriber.onComplete:()V
      92: iconst_1
      93: ireturn
      94: iconst_0
      95: ireturn
}
