Compiled from "FlowableAmb.java"
public final class io.reactivex.rxjava3.internal.operators.flowable.FlowableAmb<T> extends io.reactivex.rxjava3.core.Flowable<T> {
  final org.reactivestreams.Publisher<? extends T>[] sources;

  final java.lang.Iterable<? extends org.reactivestreams.Publisher<? extends T>> sourcesIterable;

  public io.reactivex.rxjava3.internal.operators.flowable.FlowableAmb(org.reactivestreams.Publisher<? extends T>[], java.lang.Iterable<? extends org.reactivestreams.Publisher<? extends T>>);
    Code:
       0: aload_0
       1: invokespecial #1                  // Method io/reactivex/rxjava3/core/Flowable."<init>":()V
       4: aload_0
       5: aload_1
       6: putfield      #2                  // Field sources:[Lorg/reactivestreams/Publisher;
       9: aload_0
      10: aload_2
      11: putfield      #3                  // Field sourcesIterable:Ljava/lang/Iterable;
      14: return

  public void subscribeActual(org.reactivestreams.Subscriber<? super T>);
    Code:
       0: aload_0
       1: getfield      #2                  // Field sources:[Lorg/reactivestreams/Publisher;
       4: astore_2
       5: iconst_0
       6: istore_3
       7: aload_2
       8: ifnonnull     125
      11: bipush        8
      13: anewarray     #4                  // class org/reactivestreams/Publisher
      16: astore_2
      17: aload_0
      18: getfield      #3                  // Field sourcesIterable:Ljava/lang/Iterable;
      21: invokeinterface #5,  1            // InterfaceMethod java/lang/Iterable.iterator:()Ljava/util/Iterator;
      26: astore        4
      28: aload         4
      30: invokeinterface #6,  1            // InterfaceMethod java/util/Iterator.hasNext:()Z
      35: ifeq          108
      38: aload         4
      40: invokeinterface #7,  1            // InterfaceMethod java/util/Iterator.next:()Ljava/lang/Object;
      45: checkcast     #4                  // class org/reactivestreams/Publisher
      48: astore        5
      50: aload         5
      52: ifnonnull     69
      55: new           #8                  // class java/lang/NullPointerException
      58: dup
      59: ldc           #9                  // String One of the sources is null
      61: invokespecial #10                 // Method java/lang/NullPointerException."<init>":(Ljava/lang/String;)V
      64: aload_1
      65: invokestatic  #11                 // Method io/reactivex/rxjava3/internal/subscriptions/EmptySubscription.error:(Ljava/lang/Throwable;Lorg/reactivestreams/Subscriber;)V
      68: return
      69: iload_3
      70: aload_2
      71: arraylength
      72: if_icmpne     97
      75: iload_3
      76: iload_3
      77: iconst_2
      78: ishr
      79: iadd
      80: anewarray     #4                  // class org/reactivestreams/Publisher
      83: astore        6
      85: aload_2
      86: iconst_0
      87: aload         6
      89: iconst_0
      90: iload_3
      91: invokestatic  #12                 // Method java/lang/System.arraycopy:(Ljava/lang/Object;ILjava/lang/Object;II)V
      94: aload         6
      96: astore_2
      97: aload_2
      98: iload_3
      99: iinc          3, 1
     102: aload         5
     104: aastore
     105: goto          28
     108: goto          128
     111: astore        4
     113: aload         4
     115: invokestatic  #14                 // Method io/reactivex/rxjava3/exceptions/Exceptions.throwIfFatal:(Ljava/lang/Throwable;)V
     118: aload         4
     120: aload_1
     121: invokestatic  #11                 // Method io/reactivex/rxjava3/internal/subscriptions/EmptySubscription.error:(Ljava/lang/Throwable;Lorg/reactivestreams/Subscriber;)V
     124: return
     125: aload_2
     126: arraylength
     127: istore_3
     128: iload_3
     129: ifne          137
     132: aload_1
     133: invokestatic  #15                 // Method io/reactivex/rxjava3/internal/subscriptions/EmptySubscription.complete:(Lorg/reactivestreams/Subscriber;)V
     136: return
     137: iload_3
     138: iconst_1
     139: if_icmpne     152
     142: aload_2
     143: iconst_0
     144: aaload
     145: aload_1
     146: invokeinterface #16,  2           // InterfaceMethod org/reactivestreams/Publisher.subscribe:(Lorg/reactivestreams/Subscriber;)V
     151: return
     152: new           #17                 // class io/reactivex/rxjava3/internal/operators/flowable/FlowableAmb$AmbCoordinator
     155: dup
     156: aload_1
     157: iload_3
     158: invokespecial #18                 // Method io/reactivex/rxjava3/internal/operators/flowable/FlowableAmb$AmbCoordinator."<init>":(Lorg/reactivestreams/Subscriber;I)V
     161: astore        4
     163: aload         4
     165: aload_2
     166: invokevirtual #19                 // Method io/reactivex/rxjava3/internal/operators/flowable/FlowableAmb$AmbCoordinator.subscribe:([Lorg/reactivestreams/Publisher;)V
     169: return
    Exception table:
       from    to  target type
          17    68   111   Class java/lang/Throwable
          69   108   111   Class java/lang/Throwable
}
