Compiled from "FlowableLastMaybe.java"
public final class io.reactivex.rxjava3.internal.operators.flowable.FlowableLastMaybe<T> extends io.reactivex.rxjava3.core.Maybe<T> {
  final org.reactivestreams.Publisher<T> source;

  public io.reactivex.rxjava3.internal.operators.flowable.FlowableLastMaybe(org.reactivestreams.Publisher<T>);
    Code:
       0: aload_0
       1: invokespecial #1                  // Method io/reactivex/rxjava3/core/Maybe."<init>":()V
       4: aload_0
       5: aload_1
       6: putfield      #2                  // Field source:Lorg/reactivestreams/Publisher;
       9: return

  protected void subscribeActual(io.reactivex.rxjava3.core.MaybeObserver<? super T>);
    Code:
       0: aload_0
       1: getfield      #2                  // Field source:Lorg/reactivestreams/Publisher;
       4: new           #3                  // class io/reactivex/rxjava3/internal/operators/flowable/FlowableLastMaybe$LastSubscriber
       7: dup
       8: aload_1
       9: invokespecial #4                  // Method io/reactivex/rxjava3/internal/operators/flowable/FlowableLastMaybe$LastSubscriber."<init>":(Lio/reactivex/rxjava3/core/MaybeObserver;)V
      12: invokeinterface #5,  2            // InterfaceMethod org/reactivestreams/Publisher.subscribe:(Lorg/reactivestreams/Subscriber;)V
      17: return
}
