Compiled from "FlowableGroupBy.java"
final class io.reactivex.rxjava3.internal.operators.flowable.FlowableGroupBy$EvictionAction<K, V> implements io.reactivex.rxjava3.functions.Consumer<io.reactivex.rxjava3.internal.operators.flowable.FlowableGroupBy$GroupedUnicast<K, V>> {
  final java.util.Queue<io.reactivex.rxjava3.internal.operators.flowable.FlowableGroupBy$GroupedUnicast<K, V>> evictedGroups;

  io.reactivex.rxjava3.internal.operators.flowable.FlowableGroupBy$EvictionAction(java.util.Queue<io.reactivex.rxjava3.internal.operators.flowable.FlowableGroupBy$GroupedUnicast<K, V>>);
    Code:
       0: aload_0
       1: invokespecial #1                  // Method java/lang/Object."<init>":()V
       4: aload_0
       5: aload_1
       6: putfield      #2                  // Field evictedGroups:Ljava/util/Queue;
       9: return

  public void accept(io.reactivex.rxjava3.internal.operators.flowable.FlowableGroupBy$GroupedUnicast<K, V>);
    Code:
       0: aload_0
       1: getfield      #2                  // Field evictedGroups:Ljava/util/Queue;
       4: aload_1
       5: invokeinterface #3,  2            // InterfaceMethod java/util/Queue.offer:(Ljava/lang/Object;)Z
      10: pop
      11: return

  public void accept(java.lang.Object) throws java.lang.Throwable;
    Code:
       0: aload_0
       1: aload_1
       2: checkcast     #4                  // class io/reactivex/rxjava3/internal/operators/flowable/FlowableGroupBy$GroupedUnicast
       5: invokevirtual #5                  // Method accept:(Lio/reactivex/rxjava3/internal/operators/flowable/FlowableGroupBy$GroupedUnicast;)V
       8: return
}
