Compiled from "Instantiator.java"
class org.springframework.boot.util.Instantiator$TypeSupplier$2 implements org.springframework.boot.util.Instantiator$TypeSupplier {
  final java.lang.Class val$type;

  org.springframework.boot.util.Instantiator$TypeSupplier$2();
    Code:
       0: aload_0
       1: aload_1
       2: putfield      #1                  // Field val$type:Ljava/lang/Class;
       5: aload_0
       6: invokespecial #7                  // Method java/lang/Object."<init>":()V
       9: return

  public java.lang.String getName();
    Code:
       0: aload_0
       1: getfield      #1                  // Field val$type:Ljava/lang/Class;
       4: invokevirtual #13                 // Method java/lang/Class.getName:()Ljava/lang/String;
       7: areturn

  public java.lang.Class<?> get() throws java.lang.ClassNotFoundException;
    Code:
       0: aload_0
       1: getfield      #1                  // Field val$type:Ljava/lang/Class;
       4: areturn
}
