Compiled from "Instantiator.java"
class org.springframework.boot.util.Instantiator$1 implements org.springframework.boot.util.Instantiator$AvailableParameters {
  final java.util.Map val$result;

  final org.springframework.boot.util.Instantiator this$0;

  org.springframework.boot.util.Instantiator$1();
    Code:
       0: aload_0
       1: aload_1
       2: putfield      #1                  // Field this$0:Lorg/springframework/boot/util/Instantiator;
       5: aload_0
       6: aload_2
       7: putfield      #7                  // Field val$result:Ljava/util/Map;
      10: aload_0
      11: invokespecial #11                 // Method java/lang/Object."<init>":()V
      14: return

  public void add(java.lang.Class<?>, java.lang.Object);
    Code:
       0: aload_0
       1: getfield      #7                  // Field val$result:Ljava/util/Map;
       4: aload_1
       5: aload_2
       6: invokedynamic #17,  0             // InvokeDynamic #0:apply:(Ljava/lang/Object;)Ljava/util/function/Function;
      11: invokeinterface #21,  3           // InterfaceMethod java/util/Map.put:(Ljava/lang/Object;Ljava/lang/Object;)Ljava/lang/Object;
      16: pop
      17: return

  public void add(java.lang.Class<?>, java.util.function.Function<java.lang.Class<?>, java.lang.Object>);
    Code:
       0: aload_0
       1: getfield      #7                  // Field val$result:Ljava/util/Map;
       4: aload_1
       5: aload_2
       6: invokeinterface #21,  3           // InterfaceMethod java/util/Map.put:(Ljava/lang/Object;Ljava/lang/Object;)Ljava/lang/Object;
      11: pop
      12: return

  private static java.lang.Object lambda$add$0(java.lang.Object, java.lang.Class);
    Code:
       0: aload_0
       1: areturn
}
