Compiled from "Instantiator.java"
class org.springframework.boot.util.Instantiator$TypeSupplier$1 implements org.springframework.boot.util.Instantiator$TypeSupplier {
  final java.lang.String val$name;

  final java.lang.ClassLoader val$classLoader;

  org.springframework.boot.util.Instantiator$TypeSupplier$1();
    Code:
       0: aload_0
       1: aload_1
       2: putfield      #1                  // Field val$name:Ljava/lang/String;
       5: aload_0
       6: aload_2
       7: putfield      #7                  // Field val$classLoader:Ljava/lang/ClassLoader;
      10: aload_0
      11: invokespecial #11                 // Method java/lang/Object."<init>":()V
      14: return

  public java.lang.String getName();
    Code:
       0: aload_0
       1: getfield      #1                  // Field val$name:Ljava/lang/String;
       4: areturn

  public java.lang.Class<?> get() throws java.lang.ClassNotFoundException;
    Code:
       0: aload_0
       1: getfield      #1                  // Field val$name:Ljava/lang/String;
       4: aload_0
       5: getfield      #7                  // Field val$classLoader:Ljava/lang/ClassLoader;
       8: invokestatic  #17                 // Method org/springframework/util/ClassUtils.forName:(Ljava/lang/String;Ljava/lang/ClassLoader;)Ljava/lang/Class;
      11: areturn
}
