Compiled from "Instantiator.java"
interface org.springframework.boot.util.Instantiator$TypeSupplier {
  public abstract java.lang.String getName();

  public abstract java.lang.Class<?> get() throws java.lang.ClassNotFoundException;

  public static org.springframework.boot.util.Instantiator$TypeSupplier forName(java.lang.ClassLoader, java.lang.String);
    Code:
       0: new           #1                  // class org/springframework/boot/util/Instantiator$TypeSupplier$1
       3: dup
       4: aload_1
       5: aload_0
       6: invokespecial #3                  // Method org/springframework/boot/util/Instantiator$TypeSupplier$1."<init>":(Ljava/lang/String;Ljava/lang/ClassLoader;)V
       9: areturn

  public static org.springframework.boot.util.Instantiator$TypeSupplier forType(java.lang.Class<?>);
    Code:
       0: new           #7                  // class org/springframework/boot/util/Instantiator$TypeSupplier$2
       3: dup
       4: aload_0
       5: invokespecial #9                  // Method org/springframework/boot/util/Instantiator$TypeSupplier$2."<init>":(Ljava/lang/Class;)V
       8: areturn
}
