Compiled from "Instantiator.java"
public class org.springframework.boot.util.Instantiator<T> {
  private static final java.util.Comparator<java.lang.reflect.Constructor<?>> CONSTRUCTOR_COMPARATOR;

  private static final org.springframework.boot.util.Instantiator$FailureHandler throwingFailureHandler;

  private final java.lang.Class<?> type;

  private final java.util.Map<java.lang.Class<?>, java.util.function.Function<java.lang.Class<?>, java.lang.Object>> availableParameters;

  private final org.springframework.boot.util.Instantiator$FailureHandler failureHandler;

  public org.springframework.boot.util.Instantiator(java.lang.Class<?>, java.util.function.Consumer<org.springframework.boot.util.Instantiator$AvailableParameters>);
    Code:
       0: aload_0
       1: aload_1
       2: aload_2
       3: getstatic     #1                  // Field throwingFailureHandler:Lorg/springframework/boot/util/Instantiator$FailureHandler;
       6: invokespecial #7                  // Method "<init>":(Ljava/lang/Class;Ljava/util/function/Consumer;Lorg/springframework/boot/util/Instantiator$FailureHandler;)V
       9: return

  public org.springframework.boot.util.Instantiator(java.lang.Class<?>, java.util.function.Consumer<org.springframework.boot.util.Instantiator$AvailableParameters>, org.springframework.boot.util.Instantiator$FailureHandler);
    Code:
       0: aload_0
       1: invokespecial #11                 // Method java/lang/Object."<init>":()V
       4: aload_0
       5: aload_1
       6: putfield      #16                 // Field type:Ljava/lang/Class;
       9: aload_0
      10: aload_0
      11: aload_2
      12: invokevirtual #20                 // Method getAvailableParameters:(Ljava/util/function/Consumer;)Ljava/util/Map;
      15: putfield      #24                 // Field availableParameters:Ljava/util/Map;
      18: aload_0
      19: aload_3
      20: putfield      #28                 // Field failureHandler:Lorg/springframework/boot/util/Instantiator$FailureHandler;
      23: return

  private java.util.Map<java.lang.Class<?>, java.util.function.Function<java.lang.Class<?>, java.lang.Object>> getAvailableParameters(java.util.function.Consumer<org.springframework.boot.util.Instantiator$AvailableParameters>);
    Code:
       0: new           #31                 // class java/util/LinkedHashMap
       3: dup
       4: invokespecial #33                 // Method java/util/LinkedHashMap."<init>":()V
       7: astore_2
       8: aload_1
       9: new           #34                 // class org/springframework/boot/util/Instantiator$1
      12: dup
      13: aload_0
      14: aload_2
      15: invokespecial #36                 // Method org/springframework/boot/util/Instantiator$1."<init>":(Lorg/springframework/boot/util/Instantiator;Ljava/util/Map;)V
      18: invokeinterface #39,  2           // InterfaceMethod java/util/function/Consumer.accept:(Ljava/lang/Object;)V
      23: aload_2
      24: invokestatic  #45                 // Method java/util/Collections.unmodifiableMap:(Ljava/util/Map;)Ljava/util/Map;
      27: areturn

  public java.util.List<T> instantiate(java.util.Collection<java.lang.String>);
    Code:
       0: aload_0
       1: aconst_null
       2: checkcast     #51                 // class java/lang/ClassLoader
       5: aload_1
       6: invokevirtual #53                 // Method instantiate:(Ljava/lang/ClassLoader;Ljava/util/Collection;)Ljava/util/List;
       9: areturn

  public java.util.List<T> instantiate(java.lang.ClassLoader, java.util.Collection<java.lang.String>);
    Code:
       0: aload_2
       1: ldc           #57                 // String Names must not be null
       3: invokestatic  #59                 // Method org/springframework/util/Assert.notNull:(Ljava/lang/Object;Ljava/lang/String;)V
       6: aload_0
       7: aload_2
       8: invokeinterface #65,  1           // InterfaceMethod java/util/Collection.stream:()Ljava/util/stream/Stream;
      13: aload_1
      14: invokedynamic #71,  0             // InvokeDynamic #0:apply:(Ljava/lang/ClassLoader;)Ljava/util/function/Function;
      19: invokeinterface #75,  2           // InterfaceMethod java/util/stream/Stream.map:(Ljava/util/function/Function;)Ljava/util/stream/Stream;
      24: invokevirtual #81                 // Method instantiate:(Ljava/util/stream/Stream;)Ljava/util/List;
      27: areturn

  public java.util.List<T> instantiateTypes(java.util.Collection<java.lang.Class<?>>);
    Code:
       0: aload_1
       1: ldc           #84                 // String Types must not be null
       3: invokestatic  #59                 // Method org/springframework/util/Assert.notNull:(Ljava/lang/Object;Ljava/lang/String;)V
       6: aload_0
       7: aload_1
       8: invokeinterface #65,  1           // InterfaceMethod java/util/Collection.stream:()Ljava/util/stream/Stream;
      13: invokedynamic #86,  0             // InvokeDynamic #1:apply:()Ljava/util/function/Function;
      18: invokeinterface #75,  2           // InterfaceMethod java/util/stream/Stream.map:(Ljava/util/function/Function;)Ljava/util/stream/Stream;
      23: invokevirtual #81                 // Method instantiate:(Ljava/util/stream/Stream;)Ljava/util/List;
      26: areturn

  private java.util.List<T> instantiate(java.util.stream.Stream<org.springframework.boot.util.Instantiator$TypeSupplier>);
    Code:
       0: aload_1
       1: aload_0
       2: invokedynamic #89,  0             // InvokeDynamic #2:apply:(Lorg/springframework/boot/util/Instantiator;)Ljava/util/function/Function;
       7: invokeinterface #75,  2           // InterfaceMethod java/util/stream/Stream.map:(Ljava/util/function/Function;)Ljava/util/stream/Stream;
      12: invokedynamic #92,  0             // InvokeDynamic #3:get:()Ljava/util/function/Supplier;
      17: invokestatic  #96                 // Method java/util/stream/Collectors.toCollection:(Ljava/util/function/Supplier;)Ljava/util/stream/Collector;
      20: invokeinterface #102,  2          // InterfaceMethod java/util/stream/Stream.collect:(Ljava/util/stream/Collector;)Ljava/lang/Object;
      25: checkcast     #106                // class java/util/List
      28: astore_2
      29: aload_2
      30: invokestatic  #108                // Method org/springframework/core/annotation/AnnotationAwareOrderComparator.sort:(Ljava/util/List;)V
      33: aload_2
      34: invokestatic  #114                // Method java/util/Collections.unmodifiableList:(Ljava/util/List;)Ljava/util/List;
      37: areturn

  private T instantiate(org.springframework.boot.util.Instantiator$TypeSupplier);
    Code:
       0: aload_1
       1: invokeinterface #118,  1          // InterfaceMethod org/springframework/boot/util/Instantiator$TypeSupplier.get:()Ljava/lang/Class;
       6: astore_2
       7: aload_0
       8: getfield      #16                 // Field type:Ljava/lang/Class;
      11: aload_2
      12: invokestatic  #123                // Method org/springframework/util/Assert.isAssignable:(Ljava/lang/Class;Ljava/lang/Class;)V
      15: aload_0
      16: aload_2
      17: invokevirtual #127                // Method instantiate:(Ljava/lang/Class;)Ljava/lang/Object;
      20: areturn
      21: astore_2
      22: aload_0
      23: getfield      #28                 // Field failureHandler:Lorg/springframework/boot/util/Instantiator$FailureHandler;
      26: aload_0
      27: getfield      #16                 // Field type:Ljava/lang/Class;
      30: aload_1
      31: invokeinterface #132,  1          // InterfaceMethod org/springframework/boot/util/Instantiator$TypeSupplier.getName:()Ljava/lang/String;
      36: aload_2
      37: invokeinterface #136,  4          // InterfaceMethod org/springframework/boot/util/Instantiator$FailureHandler.handleFailure:(Ljava/lang/Class;Ljava/lang/String;Ljava/lang/Throwable;)V
      42: aconst_null
      43: areturn
    Exception table:
       from    to  target type
           0    20    21   Class java/lang/Throwable

  private T instantiate(java.lang.Class<?>) throws java.lang.Exception;
    Code:
       0: aload_1
       1: invokevirtual #142                // Method java/lang/Class.getDeclaredConstructors:()[Ljava/lang/reflect/Constructor;
       4: astore_2
       5: aload_2
       6: getstatic     #148                // Field CONSTRUCTOR_COMPARATOR:Ljava/util/Comparator;
       9: invokestatic  #152                // Method java/util/Arrays.sort:([Ljava/lang/Object;Ljava/util/Comparator;)V
      12: aload_2
      13: astore_3
      14: aload_3
      15: arraylength
      16: istore        4
      18: iconst_0
      19: istore        5
      21: iload         5
      23: iload         4
      25: if_icmpge     69
      28: aload_3
      29: iload         5
      31: aaload
      32: astore        6
      34: aload_0
      35: aload         6
      37: invokevirtual #157                // Method java/lang/reflect/Constructor.getParameterTypes:()[Ljava/lang/Class;
      40: invokevirtual #163                // Method getArgs:([Ljava/lang/Class;)[Ljava/lang/Object;
      43: astore        7
      45: aload         7
      47: ifnull        63
      50: aload         6
      52: invokestatic  #167                // Method org/springframework/util/ReflectionUtils.makeAccessible:(Ljava/lang/reflect/Constructor;)V
      55: aload         6
      57: aload         7
      59: invokevirtual #173                // Method java/lang/reflect/Constructor.newInstance:([Ljava/lang/Object;)Ljava/lang/Object;
      62: areturn
      63: iinc          5, 1
      66: goto          21
      69: new           #177                // class java/lang/IllegalAccessException
      72: dup
      73: aload_1
      74: invokevirtual #179                // Method java/lang/Class.getName:()Ljava/lang/String;
      77: invokedynamic #180,  0            // InvokeDynamic #4:makeConcatWithConstants:(Ljava/lang/String;)Ljava/lang/String;
      82: invokespecial #184                // Method java/lang/IllegalAccessException."<init>":(Ljava/lang/String;)V
      85: athrow

  private java.lang.Object[] getArgs(java.lang.Class<?>[]);
    Code:
       0: aload_1
       1: arraylength
       2: anewarray     #12                 // class java/lang/Object
       5: astore_2
       6: iconst_0
       7: istore_3
       8: iload_3
       9: aload_1
      10: arraylength
      11: if_icmpge     50
      14: aload_0
      15: aload_1
      16: iload_3
      17: aaload
      18: invokevirtual #187                // Method getAvailableParameter:(Ljava/lang/Class;)Ljava/util/function/Function;
      21: astore        4
      23: aload         4
      25: ifnonnull     30
      28: aconst_null
      29: areturn
      30: aload_2
      31: iload_3
      32: aload         4
      34: aload_0
      35: getfield      #16                 // Field type:Ljava/lang/Class;
      38: invokeinterface #191,  2          // InterfaceMethod java/util/function/Function.apply:(Ljava/lang/Object;)Ljava/lang/Object;
      43: aastore
      44: iinc          3, 1
      47: goto          8
      50: aload_2
      51: areturn

  private java.util.function.Function<java.lang.Class<?>, java.lang.Object> getAvailableParameter(java.lang.Class<?>);
    Code:
       0: aload_0
       1: getfield      #24                 // Field availableParameters:Ljava/util/Map;
       4: invokeinterface #196,  1          // InterfaceMethod java/util/Map.entrySet:()Ljava/util/Set;
       9: invokeinterface #202,  1          // InterfaceMethod java/util/Set.iterator:()Ljava/util/Iterator;
      14: astore_2
      15: aload_2
      16: invokeinterface #208,  1          // InterfaceMethod java/util/Iterator.hasNext:()Z
      21: ifeq          63
      24: aload_2
      25: invokeinterface #214,  1          // InterfaceMethod java/util/Iterator.next:()Ljava/lang/Object;
      30: checkcast     #218                // class java/util/Map$Entry
      33: astore_3
      34: aload_3
      35: invokeinterface #220,  1          // InterfaceMethod java/util/Map$Entry.getKey:()Ljava/lang/Object;
      40: checkcast     #143                // class java/lang/Class
      43: aload_1
      44: invokevirtual #223                // Method java/lang/Class.isAssignableFrom:(Ljava/lang/Class;)Z
      47: ifeq          60
      50: aload_3
      51: invokeinterface #227,  1          // InterfaceMethod java/util/Map$Entry.getValue:()Ljava/lang/Object;
      56: checkcast     #192                // class java/util/function/Function
      59: areturn
      60: goto          15
      63: aconst_null
      64: areturn

  private static org.springframework.boot.util.Instantiator$TypeSupplier lambda$instantiate$1(java.lang.ClassLoader, java.lang.String);
    Code:
       0: aload_0
       1: aload_1
       2: invokestatic  #230                // InterfaceMethod org/springframework/boot/util/Instantiator$TypeSupplier.forName:(Ljava/lang/ClassLoader;Ljava/lang/String;)Lorg/springframework/boot/util/Instantiator$TypeSupplier;
       5: areturn

  private static void lambda$static$0(java.lang.Class, java.lang.String, java.lang.Throwable);
    Code:
       0: new           #234                // class java/lang/IllegalArgumentException
       3: dup
       4: aload_1
       5: aload_0
       6: invokevirtual #179                // Method java/lang/Class.getName:()Ljava/lang/String;
       9: invokedynamic #236,  0            // InvokeDynamic #5:makeConcatWithConstants:(Ljava/lang/String;Ljava/lang/String;)Ljava/lang/String;
      14: aload_2
      15: invokespecial #239                // Method java/lang/IllegalArgumentException."<init>":(Ljava/lang/String;Ljava/lang/Throwable;)V
      18: athrow

  static {};
    Code:
       0: invokedynamic #242,  0            // InvokeDynamic #6:applyAsInt:()Ljava/util/function/ToIntFunction;
       5: invokestatic  #246                // InterfaceMethod java/util/Comparator.comparingInt:(Ljava/util/function/ToIntFunction;)Ljava/util/Comparator;
       8: invokeinterface #252,  1          // InterfaceMethod java/util/Comparator.reversed:()Ljava/util/Comparator;
      13: putstatic     #148                // Field CONSTRUCTOR_COMPARATOR:Ljava/util/Comparator;
      16: invokedynamic #256,  0            // InvokeDynamic #7:handleFailure:()Lorg/springframework/boot/util/Instantiator$FailureHandler;
      21: putstatic     #1                  // Field throwingFailureHandler:Lorg/springframework/boot/util/Instantiator$FailureHandler;
      24: return
}
