Compiled from "LambdaSafe.java"
public final class org.springframework.boot.util.LambdaSafe$Callbacks<C, A> extends org.springframework.boot.util.LambdaSafe$LambdaSafeCallback<C, A, org.springframework.boot.util.LambdaSafe$Callbacks<C, A>> {
  private final java.util.Collection<? extends C> callbackInstances;

  private org.springframework.boot.util.LambdaSafe$Callbacks(java.lang.Class<C>, java.util.Collection<? extends C>, A, java.lang.Object[]);
    Code:
       0: aload_0
       1: aload_1
       2: aload_3
       3: aload         4
       5: invokespecial #1                  // Method org/springframework/boot/util/LambdaSafe$LambdaSafeCallback."<init>":(Ljava/lang/Class;Ljava/lang/Object;[Ljava/lang/Object;)V
       8: aload_0
       9: aload_2
      10: putfield      #7                  // Field callbackInstances:Ljava/util/Collection;
      13: return

  public void invoke(java.util.function.Consumer<C>);
    Code:
       0: aload_0
       1: getfield      #7                  // Field callbackInstances:Ljava/util/Collection;
       4: aload_0
       5: aload_1
       6: invokedynamic #13,  0             // InvokeDynamic #0:accept:(Lorg/springframework/boot/util/LambdaSafe$Callbacks;Ljava/util/function/Consumer;)Ljava/util/function/Consumer;
      11: invokeinterface #17,  2           // InterfaceMethod java/util/Collection.forEach:(Ljava/util/function/Consumer;)V
      16: return

  public <R> java.util.stream.Stream<R> invokeAnd(java.util.function.Function<C, R>);
    Code:
       0: aload_0
       1: aload_1
       2: invokedynamic #23,  0             // InvokeDynamic #1:apply:(Lorg/springframework/boot/util/LambdaSafe$Callbacks;Ljava/util/function/Function;)Ljava/util/function/Function;
       7: astore_2
       8: aload_0
       9: getfield      #7                  // Field callbackInstances:Ljava/util/Collection;
      12: invokeinterface #27,  1           // InterfaceMethod java/util/Collection.stream:()Ljava/util/stream/Stream;
      17: aload_2
      18: invokeinterface #31,  2           // InterfaceMethod java/util/stream/Stream.map:(Ljava/util/function/Function;)Ljava/util/stream/Stream;
      23: invokedynamic #37,  0             // InvokeDynamic #2:test:()Ljava/util/function/Predicate;
      28: invokeinterface #41,  2           // InterfaceMethod java/util/stream/Stream.filter:(Ljava/util/function/Predicate;)Ljava/util/stream/Stream;
      33: invokedynamic #45,  0             // InvokeDynamic #3:apply:()Ljava/util/function/Function;
      38: invokeinterface #31,  2           // InterfaceMethod java/util/stream/Stream.map:(Ljava/util/function/Function;)Ljava/util/stream/Stream;
      43: areturn

  public org.springframework.boot.util.LambdaSafe$LambdaSafeCallback withLogger(org.apache.commons.logging.Log);
    Code:
       0: aload_0
       1: aload_1
       2: invokespecial #48                 // Method org/springframework/boot/util/LambdaSafe$LambdaSafeCallback.withLogger:(Lorg/apache/commons/logging/Log;)Lorg/springframework/boot/util/LambdaSafe$LambdaSafeCallback;
       5: areturn

  public org.springframework.boot.util.LambdaSafe$LambdaSafeCallback withLogger(java.lang.Class);
    Code:
       0: aload_0
       1: aload_1
       2: invokespecial #52                 // Method org/springframework/boot/util/LambdaSafe$LambdaSafeCallback.withLogger:(Ljava/lang/Class;)Lorg/springframework/boot/util/LambdaSafe$LambdaSafeCallback;
       5: areturn

  private org.springframework.boot.util.LambdaSafe$InvocationResult lambda$invokeAnd$3(java.util.function.Function, java.lang.Object);
    Code:
       0: aload_0
       1: aload_2
       2: aload_1
       3: aload_2
       4: invokedynamic #55,  0             // InvokeDynamic #4:get:(Ljava/util/function/Function;Ljava/lang/Object;)Ljava/util/function/Supplier;
       9: invokevirtual #59                 // Method invoke:(Ljava/lang/Object;Ljava/util/function/Supplier;)Lorg/springframework/boot/util/LambdaSafe$InvocationResult;
      12: areturn

  private static java.lang.Object lambda$invokeAnd$2(java.util.function.Function, java.lang.Object);
    Code:
       0: aload_0
       1: aload_1
       2: invokeinterface #63,  2           // InterfaceMethod java/util/function/Function.apply:(Ljava/lang/Object;)Ljava/lang/Object;
       7: areturn

  private void lambda$invoke$1(java.util.function.Consumer, java.lang.Object);
    Code:
       0: aload_0
       1: aload_2
       2: aload_1
       3: aload_2
       4: invokedynamic #68,  0             // InvokeDynamic #5:get:(Ljava/util/function/Consumer;Ljava/lang/Object;)Ljava/util/function/Supplier;
       9: invokevirtual #59                 // Method invoke:(Ljava/lang/Object;Ljava/util/function/Supplier;)Lorg/springframework/boot/util/LambdaSafe$InvocationResult;
      12: pop
      13: return

  private static java.lang.Object lambda$invoke$0(java.util.function.Consumer, java.lang.Object);
    Code:
       0: aload_0
       1: aload_1
       2: invokeinterface #71,  2           // InterfaceMethod java/util/function/Consumer.accept:(Ljava/lang/Object;)V
       7: aconst_null
       8: areturn
}
