Compiled from "LambdaSafe.java"
public final class org.springframework.boot.util.LambdaSafe$Callback<C, A> extends org.springframework.boot.util.LambdaSafe$LambdaSafeCallback<C, A, org.springframework.boot.util.LambdaSafe$Callback<C, A>> {
  private final C callbackInstance;

  private org.springframework.boot.util.LambdaSafe$Callback(java.lang.Class<C>, C, A, java.lang.Object[]);
    Code:
       0: aload_0
       1: aload_1
       2: aload_3
       3: aload         4
       5: invokespecial #1                  // Method org/springframework/boot/util/LambdaSafe$LambdaSafeCallback."<init>":(Ljava/lang/Class;Ljava/lang/Object;[Ljava/lang/Object;)V
       8: aload_0
       9: aload_2
      10: putfield      #7                  // Field callbackInstance:Ljava/lang/Object;
      13: return

  public void invoke(java.util.function.Consumer<C>);
    Code:
       0: aload_0
       1: aload_0
       2: getfield      #7                  // Field callbackInstance:Ljava/lang/Object;
       5: aload_0
       6: aload_1
       7: invokedynamic #13,  0             // InvokeDynamic #0:get:(Lorg/springframework/boot/util/LambdaSafe$Callback;Ljava/util/function/Consumer;)Ljava/util/function/Supplier;
      12: invokevirtual #17                 // Method invoke:(Ljava/lang/Object;Ljava/util/function/Supplier;)Lorg/springframework/boot/util/LambdaSafe$InvocationResult;
      15: pop
      16: return

  public <R> org.springframework.boot.util.LambdaSafe$InvocationResult<R> invokeAnd(java.util.function.Function<C, R>);
    Code:
       0: aload_0
       1: aload_0
       2: getfield      #7                  // Field callbackInstance:Ljava/lang/Object;
       5: aload_0
       6: aload_1
       7: invokedynamic #21,  0             // InvokeDynamic #1:get:(Lorg/springframework/boot/util/LambdaSafe$Callback;Ljava/util/function/Function;)Ljava/util/function/Supplier;
      12: invokevirtual #17                 // Method invoke:(Ljava/lang/Object;Ljava/util/function/Supplier;)Lorg/springframework/boot/util/LambdaSafe$InvocationResult;
      15: areturn

  public org.springframework.boot.util.LambdaSafe$LambdaSafeCallback withLogger(org.apache.commons.logging.Log);
    Code:
       0: aload_0
       1: aload_1
       2: invokespecial #24                 // Method org/springframework/boot/util/LambdaSafe$LambdaSafeCallback.withLogger:(Lorg/apache/commons/logging/Log;)Lorg/springframework/boot/util/LambdaSafe$LambdaSafeCallback;
       5: areturn

  public org.springframework.boot.util.LambdaSafe$LambdaSafeCallback withLogger(java.lang.Class);
    Code:
       0: aload_0
       1: aload_1
       2: invokespecial #28                 // Method org/springframework/boot/util/LambdaSafe$LambdaSafeCallback.withLogger:(Ljava/lang/Class;)Lorg/springframework/boot/util/LambdaSafe$LambdaSafeCallback;
       5: areturn

  private java.lang.Object lambda$invokeAnd$1(java.util.function.Function);
    Code:
       0: aload_1
       1: aload_0
       2: getfield      #7                  // Field callbackInstance:Ljava/lang/Object;
       5: invokeinterface #31,  2           // InterfaceMethod java/util/function/Function.apply:(Ljava/lang/Object;)Ljava/lang/Object;
      10: areturn

  private java.lang.Object lambda$invoke$0(java.util.function.Consumer);
    Code:
       0: aload_1
       1: aload_0
       2: getfield      #7                  // Field callbackInstance:Ljava/lang/Object;
       5: invokeinterface #37,  2           // InterfaceMethod java/util/function/Consumer.accept:(Ljava/lang/Object;)V
      10: aconst_null
      11: areturn
}
