Compiled from "ConditionRuleParser.java"
public class org.apache.dubbo.rpc.cluster.router.condition.config.model.ConditionRuleParser {
  public org.apache.dubbo.rpc.cluster.router.condition.config.model.ConditionRuleParser();
    Code:
       0: aload_0
       1: invokespecial #1                  // Method java/lang/Object."<init>":()V
       4: return

  public static org.apache.dubbo.rpc.cluster.router.condition.config.model.ConditionRouterRule parse(java.lang.String);
    Code:
       0: new           #2                  // class org/yaml/snakeyaml/Yaml
       3: dup
       4: new           #3                  // class org/yaml/snakeyaml/constructor/SafeConstructor
       7: dup
       8: new           #4                  // class org/yaml/snakeyaml/LoaderOptions
      11: dup
      12: invokespecial #5                  // Method org/yaml/snakeyaml/LoaderOptions."<init>":()V
      15: invokespecial #6                  // Method org/yaml/snakeyaml/constructor/SafeConstructor."<init>":(Lorg/yaml/snakeyaml/LoaderOptions;)V
      18: invokespecial #7                  // Method org/yaml/snakeyaml/Yaml."<init>":(Lorg/yaml/snakeyaml/constructor/BaseConstructor;)V
      21: astore_1
      22: aload_1
      23: aload_0
      24: invokevirtual #8                  // Method org/yaml/snakeyaml/Yaml.load:(Ljava/lang/String;)Ljava/lang/Object;
      27: checkcast     #9                  // class java/util/Map
      30: astore_2
      31: aload_2
      32: invokestatic  #10                 // Method org/apache/dubbo/rpc/cluster/router/condition/config/model/ConditionRouterRule.parseFromMap:(Ljava/util/Map;)Lorg/apache/dubbo/rpc/cluster/router/condition/config/model/ConditionRouterRule;
      35: astore_3
      36: aload_3
      37: aload_0
      38: invokevirtual #11                 // Method org/apache/dubbo/rpc/cluster/router/condition/config/model/ConditionRouterRule.setRawRule:(Ljava/lang/String;)V
      41: aload_3
      42: invokevirtual #12                 // Method org/apache/dubbo/rpc/cluster/router/condition/config/model/ConditionRouterRule.getConditions:()Ljava/util/List;
      45: invokestatic  #13                 // Method org/apache/dubbo/common/utils/CollectionUtils.isEmpty:(Ljava/util/Collection;)Z
      48: ifeq          56
      51: aload_3
      52: iconst_0
      53: invokevirtual #14                 // Method org/apache/dubbo/rpc/cluster/router/condition/config/model/ConditionRouterRule.setValid:(Z)V
      56: aload_3
      57: areturn
}
