Compiled from "ConditionRouterRule.java"
public class org.apache.dubbo.rpc.cluster.router.condition.config.model.ConditionRouterRule extends org.apache.dubbo.rpc.cluster.router.AbstractRouterRule {
  private java.util.List<java.lang.String> conditions;

  public static org.apache.dubbo.rpc.cluster.router.condition.config.model.ConditionRouterRule parseFromMap(java.util.Map<java.lang.String, java.lang.Object>);
    Code:
       0: new           #2                  // class org/apache/dubbo/rpc/cluster/router/condition/config/model/ConditionRouterRule
       3: dup
       4: invokespecial #3                  // Method "<init>":()V
       7: astore_1
       8: aload_1
       9: aload_0
      10: invokevirtual #4                  // Method parseFromMap0:(Ljava/util/Map;)V
      13: aload_0
      14: ldc           #5                  // String conditions
      16: invokeinterface #6,  2            // InterfaceMethod java/util/Map.get:(Ljava/lang/Object;)Ljava/lang/Object;
      21: astore_2
      22: aload_2
      23: ifnull        72
      26: ldc           #7                  // class java/util/List
      28: aload_2
      29: invokevirtual #8                  // Method java/lang/Object.getClass:()Ljava/lang/Class;
      32: invokevirtual #9                  // Method java/lang/Class.isAssignableFrom:(Ljava/lang/Class;)Z
      35: ifeq          72
      38: aload_1
      39: aload_2
      40: checkcast     #7                  // class java/util/List
      43: invokeinterface #10,  1           // InterfaceMethod java/util/List.stream:()Ljava/util/stream/Stream;
      48: invokedynamic #11,  0             // InvokeDynamic #0:apply:()Ljava/util/function/Function;
      53: invokeinterface #12,  2           // InterfaceMethod java/util/stream/Stream.map:(Ljava/util/function/Function;)Ljava/util/stream/Stream;
      58: invokestatic  #13                 // Method java/util/stream/Collectors.toList:()Ljava/util/stream/Collector;
      61: invokeinterface #14,  2           // InterfaceMethod java/util/stream/Stream.collect:(Ljava/util/stream/Collector;)Ljava/lang/Object;
      66: checkcast     #7                  // class java/util/List
      69: invokevirtual #15                 // Method setConditions:(Ljava/util/List;)V
      72: aload_1
      73: areturn

  public org.apache.dubbo.rpc.cluster.router.condition.config.model.ConditionRouterRule();
    Code:
       0: aload_0
       1: invokespecial #16                 // Method org/apache/dubbo/rpc/cluster/router/AbstractRouterRule."<init>":()V
       4: return

  public java.util.List<java.lang.String> getConditions();
    Code:
       0: aload_0
       1: getfield      #17                 // Field conditions:Ljava/util/List;
       4: areturn

  public void setConditions(java.util.List<java.lang.String>);
    Code:
       0: aload_0
       1: aload_1
       2: putfield      #17                 // Field conditions:Ljava/util/List;
       5: return
}
