Compiled from "AbstractNoAnnotatedParameterProcessor.java"
public abstract class org.apache.dubbo.metadata.rest.AbstractNoAnnotatedParameterProcessor implements org.apache.dubbo.metadata.rest.NoAnnotatedParameterRequestTagProcessor {
  public org.apache.dubbo.metadata.rest.AbstractNoAnnotatedParameterProcessor();
    Code:
       0: aload_0
       1: invokespecial #1                  // Method java/lang/Object."<init>":()V
       4: return

  public boolean process(java.lang.reflect.Parameter, int, org.apache.dubbo.metadata.rest.RestMethodMetadata);
    Code:
       0: aload_0
       1: invokevirtual #2                  // Method consumerContentType:()Lorg/apache/dubbo/metadata/rest/media/MediaType;
       4: astore        4
       6: aload_0
       7: aload_3
       8: aload         4
      10: aload_1
      11: invokevirtual #3                  // Method java/lang/reflect/Parameter.getType:()Ljava/lang/Class;
      14: invokespecial #4                  // Method contentTypeSupport:(Lorg/apache/dubbo/metadata/rest/RestMethodMetadata;Lorg/apache/dubbo/metadata/rest/media/MediaType;Ljava/lang/Class;)Z
      17: ifne          22
      20: iconst_0
      21: ireturn
      22: aload_0
      23: aload_3
      24: invokevirtual #5                  // Method isFormContentType:(Lorg/apache/dubbo/metadata/rest/RestMethodMetadata;)Z
      27: istore        5
      29: aload_0
      30: aload_1
      31: iload_2
      32: aload_3
      33: iload         5
      35: invokevirtual #6                  // Method addArgInfo:(Ljava/lang/reflect/Parameter;ILorg/apache/dubbo/metadata/rest/RestMethodMetadata;Z)V
      38: iconst_1
      39: ireturn

  private boolean contentTypeSupport(org.apache.dubbo.metadata.rest.RestMethodMetadata, org.apache.dubbo.metadata.rest.media.MediaType, java.lang.Class);
    Code:
       0: aload_2
       1: getstatic     #7                  // Field org/apache/dubbo/metadata/rest/media/MediaType.ALL_VALUE:Lorg/apache/dubbo/metadata/rest/media/MediaType;
       4: invokevirtual #8                  // Method org/apache/dubbo/metadata/rest/media/MediaType.equals:(Ljava/lang/Object;)Z
       7: ifeq          34
      10: ldc           #9                  // class java/lang/String
      12: aload_3
      13: if_acmpeq     32
      16: aload_3
      17: invokevirtual #10                 // Method java/lang/Class.isPrimitive:()Z
      20: ifne          32
      23: ldc           #11                 // class java/lang/Number
      25: aload_3
      26: invokevirtual #12                 // Method java/lang/Class.isAssignableFrom:(Ljava/lang/Class;)Z
      29: ifeq          34
      32: iconst_1
      33: ireturn
      34: aload_1
      35: invokevirtual #13                 // Method org/apache/dubbo/metadata/rest/RestMethodMetadata.getRequest:()Lorg/apache/dubbo/metadata/rest/RequestMetadata;
      38: invokevirtual #14                 // Method org/apache/dubbo/metadata/rest/RequestMetadata.getConsumes:()Ljava/util/Set;
      41: astore        4
      43: aload         4
      45: invokeinterface #15,  1           // InterfaceMethod java/util/Set.iterator:()Ljava/util/Iterator;
      50: astore        5
      52: aload         5
      54: invokeinterface #16,  1           // InterfaceMethod java/util/Iterator.hasNext:()Z
      59: ifeq          91
      62: aload         5
      64: invokeinterface #17,  1           // InterfaceMethod java/util/Iterator.next:()Ljava/lang/Object;
      69: checkcast     #9                  // class java/lang/String
      72: astore        6
      74: aload         6
      76: aload_2
      77: getfield      #18                 // Field org/apache/dubbo/metadata/rest/media/MediaType.value:Ljava/lang/String;
      80: invokevirtual #19                 // Method java/lang/String.contains:(Ljava/lang/CharSequence;)Z
      83: ifeq          88
      86: iconst_1
      87: ireturn
      88: goto          52
      91: iconst_0
      92: ireturn

  protected boolean isFormContentType(org.apache.dubbo.metadata.rest.RestMethodMetadata);
    Code:
       0: iconst_0
       1: ireturn

  protected void addArgInfo(java.lang.reflect.Parameter, int, org.apache.dubbo.metadata.rest.RestMethodMetadata, boolean);
    Code:
       0: iload_2
       1: aload_1
       2: invokestatic  #20                 // Method org/apache/dubbo/metadata/rest/ArgInfo.build:(ILjava/lang/reflect/Parameter;)Lorg/apache/dubbo/metadata/rest/ArgInfo;
       5: aload_0
       6: aload_3
       7: invokevirtual #21                 // Method defaultAnnotationClassName:(Lorg/apache/dubbo/metadata/rest/RestMethodMetadata;)Ljava/lang/String;
      10: invokestatic  #22                 // Method org/apache/dubbo/common/utils/ClassUtils.getClassLoader:()Ljava/lang/ClassLoader;
      13: invokestatic  #23                 // Method org/apache/dubbo/common/utils/ClassUtils.resolveClass:(Ljava/lang/String;Ljava/lang/ClassLoader;)Ljava/lang/Class;
      16: invokevirtual #24                 // Method org/apache/dubbo/metadata/rest/ArgInfo.setParamAnnotationType:(Ljava/lang/Class;)Lorg/apache/dubbo/metadata/rest/ArgInfo;
      19: aload_1
      20: invokevirtual #25                 // Method java/lang/reflect/Parameter.getName:()Ljava/lang/String;
      23: invokevirtual #26                 // Method org/apache/dubbo/metadata/rest/ArgInfo.setAnnotationNameAttribute:(Ljava/lang/String;)Lorg/apache/dubbo/metadata/rest/ArgInfo;
      26: iload         4
      28: invokevirtual #27                 // Method org/apache/dubbo/metadata/rest/ArgInfo.setFormContentType:(Z)Lorg/apache/dubbo/metadata/rest/ArgInfo;
      31: astore        5
      33: aload_3
      34: aload         5
      36: invokevirtual #28                 // Method org/apache/dubbo/metadata/rest/RestMethodMetadata.addArgInfo:(Lorg/apache/dubbo/metadata/rest/ArgInfo;)V
      39: return
}
