Compiled from "AbstractAnnotatedMethodParameterProcessor.java"
public abstract class org.apache.dubbo.metadata.rest.AbstractAnnotatedMethodParameterProcessor implements org.apache.dubbo.metadata.rest.AnnotatedMethodParameterProcessor {
  public org.apache.dubbo.metadata.rest.AbstractAnnotatedMethodParameterProcessor();
    Code:
       0: aload_0
       1: invokespecial #1                  // Method java/lang/Object."<init>":()V
       4: return

  public void process(java.lang.annotation.Annotation, java.lang.reflect.Parameter, int, java.lang.reflect.Method, java.lang.Class<?>, java.lang.Class<?>, org.apache.dubbo.metadata.rest.RestMethodMetadata);
    Code:
       0: aload_0
       1: aload_1
       2: aload_2
       3: iload_3
       4: invokevirtual #2                  // Method getAnnotationValue:(Ljava/lang/annotation/Annotation;Ljava/lang/reflect/Parameter;I)Ljava/lang/String;
       7: astore        8
       9: aload_0
      10: aload_1
      11: aload_2
      12: iload_3
      13: invokevirtual #3                  // Method getDefaultValue:(Ljava/lang/annotation/Annotation;Ljava/lang/reflect/Parameter;I)Ljava/lang/String;
      16: astore        9
      18: aload_0
      19: aload_2
      20: iload_3
      21: aload         7
      23: aload         8
      25: aload         9
      27: invokevirtual #4                  // Method addArgInfo:(Ljava/lang/reflect/Parameter;ILorg/apache/dubbo/metadata/rest/RestMethodMetadata;Ljava/lang/String;Ljava/lang/Object;)V
      30: aload_0
      31: aload         8
      33: aload         9
      35: aload_1
      36: aload_2
      37: iload_3
      38: aload         4
      40: aload         7
      42: invokevirtual #5                  // Method process:(Ljava/lang/String;Ljava/lang/String;Ljava/lang/annotation/Annotation;Ljava/lang/reflect/Parameter;ILjava/lang/reflect/Method;Lorg/apache/dubbo/metadata/rest/RestMethodMetadata;)V
      45: return

  protected void process(java.lang.String, java.lang.String, java.lang.annotation.Annotation, java.lang.reflect.Parameter, int, java.lang.reflect.Method, org.apache.dubbo.metadata.rest.RestMethodMetadata);
    Code:
       0: return

  public java.lang.Class getAnnotationClass();
    Code:
       0: aload_0
       1: invokevirtual #6                  // Method getAnnotationName:()Ljava/lang/String;
       4: invokestatic  #7                  // Method org/apache/dubbo/common/utils/ClassUtils.getClassLoader:()Ljava/lang/ClassLoader;
       7: invokestatic  #8                  // Method org/apache/dubbo/common/utils/ClassUtils.resolveClass:(Ljava/lang/String;Ljava/lang/ClassLoader;)Ljava/lang/Class;
      10: areturn

  protected void addArgInfo(java.lang.reflect.Parameter, int, org.apache.dubbo.metadata.rest.RestMethodMetadata, java.lang.String, java.lang.Object);
    Code:
       0: iload_2
       1: aload_1
       2: invokestatic  #9                  // Method org/apache/dubbo/metadata/rest/ArgInfo.build:(ILjava/lang/reflect/Parameter;)Lorg/apache/dubbo/metadata/rest/ArgInfo;
       5: aload_0
       6: invokevirtual #10                 // Method getAnnotationClass:()Ljava/lang/Class;
       9: invokevirtual #11                 // Method org/apache/dubbo/metadata/rest/ArgInfo.setParamAnnotationType:(Ljava/lang/Class;)Lorg/apache/dubbo/metadata/rest/ArgInfo;
      12: aload         4
      14: invokevirtual #12                 // Method org/apache/dubbo/metadata/rest/ArgInfo.setAnnotationNameAttribute:(Ljava/lang/String;)Lorg/apache/dubbo/metadata/rest/ArgInfo;
      17: aload         5
      19: invokevirtual #13                 // Method org/apache/dubbo/metadata/rest/ArgInfo.setDefaultValue:(Ljava/lang/Object;)Lorg/apache/dubbo/metadata/rest/ArgInfo;
      22: astore        6
      24: aload_3
      25: aload         6
      27: invokevirtual #14                 // Method org/apache/dubbo/metadata/rest/RestMethodMetadata.addArgInfo:(Lorg/apache/dubbo/metadata/rest/ArgInfo;)V
      30: return

  protected java.lang.String getAnnotationValue(java.lang.annotation.Annotation, java.lang.reflect.Parameter, int);
    Code:
       0: aload_1
       1: invokestatic  #15                 // InterfaceMethod org/apache/dubbo/common/utils/AnnotationUtils.getValue:(Ljava/lang/annotation/Annotation;)Ljava/lang/Object;
       4: checkcast     #16                 // class java/lang/String
       7: areturn

  protected java.lang.String getDefaultValue(java.lang.annotation.Annotation, java.lang.reflect.Parameter, int);
    Code:
       0: iload_3
       1: invokestatic  #17                 // InterfaceMethod org/apache/dubbo/metadata/rest/AnnotatedMethodParameterProcessor.buildDefaultValue:(I)Ljava/lang/String;
       4: areturn
}
