Compiled from "AbstractServiceRestMetadataResolver.java"
public abstract class org.apache.dubbo.metadata.rest.AbstractServiceRestMetadataResolver implements org.apache.dubbo.metadata.rest.ServiceRestMetadataResolver {
  private final java.util.Map<java.lang.String, java.util.List<org.apache.dubbo.metadata.rest.AnnotatedMethodParameterProcessor>> parameterProcessorsMap;

  private final java.util.Set<org.apache.dubbo.metadata.rest.NoAnnotatedParameterRequestTagProcessor> noAnnotatedParameterRequestTagProcessors;

  public org.apache.dubbo.metadata.rest.AbstractServiceRestMetadataResolver(org.apache.dubbo.rpc.model.ApplicationModel);
    Code:
       0: aload_0
       1: invokespecial #1                  // Method java/lang/Object."<init>":()V
       4: aload_0
       5: aload_1
       6: invokestatic  #2                  // Method loadAnnotatedMethodParameterProcessors:(Lorg/apache/dubbo/rpc/model/ApplicationModel;)Ljava/util/Map;
       9: putfield      #3                  // Field parameterProcessorsMap:Ljava/util/Map;
      12: aload_0
      13: aload_1
      14: invokestatic  #4                  // Method loadNoAnnotatedMethodParameterProcessors:(Lorg/apache/dubbo/rpc/model/ApplicationModel;)Ljava/util/Set;
      17: putfield      #5                  // Field noAnnotatedParameterRequestTagProcessors:Ljava/util/Set;
      20: return

  public final boolean supports(java.lang.Class<?>);
    Code:
       0: aload_0
       1: aload_1
       2: iconst_0
       3: invokevirtual #6                  // Method supports:(Ljava/lang/Class;Z)Z
       6: ireturn

  public final boolean supports(java.lang.Class<?>, boolean);
    Code:
       0: aload_1
       1: ifnonnull     6
       4: iconst_0
       5: ireturn
       6: aload_0
       7: aload_1
       8: invokevirtual #7                  // Method supports0:(Ljava/lang/Class;)Z
      11: ireturn

  protected final boolean isImplementedInterface(java.lang.Class<?>);
    Code:
       0: aload_1
       1: iconst_0
       2: anewarray     #8                  // class java/util/function/Predicate
       5: invokestatic  #9                  // Method org/apache/dubbo/common/utils/ClassUtils.getAllInterfaces:(Ljava/lang/Class;[Ljava/util/function/Predicate;)Ljava/util/Set;
       8: invokeinterface #10,  1           // InterfaceMethod java/util/Set.isEmpty:()Z
      13: ifne          20
      16: iconst_1
      17: goto          21
      20: iconst_0
      21: ireturn

  protected final boolean isServiceAnnotationPresent(java.lang.Class<?>);
    Code:
       0: aload_1
       1: iconst_3
       2: anewarray     #11                 // class java/lang/Class
       5: dup
       6: iconst_0
       7: ldc           #12                 // class org/apache/dubbo/config/annotation/DubboService
       9: aastore
      10: dup
      11: iconst_1
      12: ldc           #13                 // class org/apache/dubbo/config/annotation/Service
      14: aastore
      15: dup
      16: iconst_2
      17: ldc           #14                 // class com/alibaba/dubbo/config/annotation/Service
      19: aastore
      20: invokestatic  #15                 // InterfaceMethod org/apache/dubbo/common/utils/AnnotationUtils.isAnyAnnotationPresent:(Ljava/lang/Class;[Ljava/lang/Class;)Z
      23: ireturn

  protected abstract boolean supports0(java.lang.Class<?>);

  public final org.apache.dubbo.metadata.rest.ServiceRestMetadata resolve(java.lang.Class<?>);
    Code:
       0: new           #16                 // class org/apache/dubbo/metadata/rest/ServiceRestMetadata
       3: dup
       4: invokespecial #17                 // Method org/apache/dubbo/metadata/rest/ServiceRestMetadata."<init>":()V
       7: astore_2
       8: aload_0
       9: aload_2
      10: aload_1
      11: invokevirtual #18                 // Method processServiceRestMetadata:(Lorg/apache/dubbo/metadata/rest/ServiceRestMetadata;Ljava/lang/Class;)V
      14: aload_0
      15: aload_1
      16: aload_2
      17: invokevirtual #19                 // Method resolve:(Ljava/lang/Class;Lorg/apache/dubbo/metadata/rest/ServiceRestMetadata;)Lorg/apache/dubbo/metadata/rest/ServiceRestMetadata;
      20: areturn

  public final org.apache.dubbo.metadata.rest.ServiceRestMetadata resolve(java.lang.Class<?>, org.apache.dubbo.metadata.rest.ServiceRestMetadata);
    Code:
       0: aload_2
       1: aload_0
       2: invokevirtual #20                 // Method java/lang/Object.getClass:()Ljava/lang/Class;
       5: invokevirtual #21                 // Method org/apache/dubbo/metadata/rest/ServiceRestMetadata.setCodeStyle:(Ljava/lang/Class;)V
       8: aload_0
       9: aload_2
      10: aload_1
      11: invokevirtual #22                 // Method processAllRestMethodMetadata:(Lorg/apache/dubbo/metadata/rest/ServiceRestMetadata;Ljava/lang/Class;)V
      14: aload_2
      15: areturn

  protected void processServiceRestMetadata(org.apache.dubbo.metadata.rest.ServiceRestMetadata, java.lang.Class<?>);
    Code:
       0: new           #23                 // class org/apache/dubbo/common/utils/ServiceAnnotationResolver
       3: dup
       4: aload_2
       5: invokespecial #24                 // Method org/apache/dubbo/common/utils/ServiceAnnotationResolver."<init>":(Ljava/lang/Class;)V
       8: astore_3
       9: aload_1
      10: aload_3
      11: invokevirtual #25                 // Method org/apache/dubbo/common/utils/ServiceAnnotationResolver.resolveInterfaceClassName:()Ljava/lang/String;
      14: invokevirtual #26                 // Method org/apache/dubbo/metadata/rest/ServiceRestMetadata.setServiceInterface:(Ljava/lang/String;)V
      17: aload_1
      18: aload_3
      19: invokevirtual #27                 // Method org/apache/dubbo/common/utils/ServiceAnnotationResolver.resolveVersion:()Ljava/lang/String;
      22: invokevirtual #28                 // Method org/apache/dubbo/metadata/rest/ServiceRestMetadata.setVersion:(Ljava/lang/String;)V
      25: aload_1
      26: aload_3
      27: invokevirtual #29                 // Method org/apache/dubbo/common/utils/ServiceAnnotationResolver.resolveGroup:()Ljava/lang/String;
      30: invokevirtual #30                 // Method org/apache/dubbo/metadata/rest/ServiceRestMetadata.setGroup:(Ljava/lang/String;)V
      33: return

  protected void processAllRestMethodMetadata(org.apache.dubbo.metadata.rest.ServiceRestMetadata, java.lang.Class<?>);
    Code:
       0: aload_0
       1: aload_1
       2: aload_2
       3: invokevirtual #31                 // Method resolveServiceInterfaceClass:(Lorg/apache/dubbo/metadata/rest/ServiceRestMetadata;Ljava/lang/Class;)Ljava/lang/Class;
       6: astore_3
       7: aload_0
       8: aload_2
       9: aload_3
      10: invokevirtual #32                 // Method resolveServiceMethodsMap:(Ljava/lang/Class;Ljava/lang/Class;)Ljava/util/Map;
      13: astore        4
      15: aload         4
      17: invokeinterface #33,  1           // InterfaceMethod java/util/Map.entrySet:()Ljava/util/Set;
      22: invokeinterface #34,  1           // InterfaceMethod java/util/Set.iterator:()Ljava/util/Iterator;
      27: astore        5
      29: aload         5
      31: invokeinterface #35,  1           // InterfaceMethod java/util/Iterator.hasNext:()Z
      36: ifeq          122
      39: aload         5
      41: invokeinterface #36,  1           // InterfaceMethod java/util/Iterator.next:()Ljava/lang/Object;
      46: checkcast     #37                 // class java/util/Map$Entry
      49: astore        6
      51: aload         6
      53: invokeinterface #38,  1           // InterfaceMethod java/util/Map$Entry.getKey:()Ljava/lang/Object;
      58: checkcast     #39                 // class java/lang/reflect/Method
      61: astore        7
      63: aload_0
      64: aload         7
      66: aload_2
      67: aload_3
      68: aload_1
      69: dup
      70: invokevirtual #20                 // Method java/lang/Object.getClass:()Ljava/lang/Class;
      73: pop
      74: invokedynamic #40,  0             // InvokeDynamic #0:accept:(Lorg/apache/dubbo/metadata/rest/ServiceRestMetadata;)Ljava/util/function/Consumer;
      79: aload_1
      80: invokevirtual #41                 // Method processRestMethodMetadata:(Ljava/lang/reflect/Method;Ljava/lang/Class;Ljava/lang/Class;Ljava/util/function/Consumer;Lorg/apache/dubbo/metadata/rest/ServiceRestMetadata;)Z
      83: ifne          119
      86: aload         6
      88: invokeinterface #42,  1           // InterfaceMethod java/util/Map$Entry.getValue:()Ljava/lang/Object;
      93: checkcast     #39                 // class java/lang/reflect/Method
      96: astore        8
      98: aload_0
      99: aload         8
     101: aload_2
     102: aload_3
     103: aload_1
     104: dup
     105: invokevirtual #20                 // Method java/lang/Object.getClass:()Ljava/lang/Class;
     108: pop
     109: invokedynamic #40,  0             // InvokeDynamic #0:accept:(Lorg/apache/dubbo/metadata/rest/ServiceRestMetadata;)Ljava/util/function/Consumer;
     114: aload_1
     115: invokevirtual #41                 // Method processRestMethodMetadata:(Ljava/lang/reflect/Method;Ljava/lang/Class;Ljava/lang/Class;Ljava/util/function/Consumer;Lorg/apache/dubbo/metadata/rest/ServiceRestMetadata;)Z
     118: pop
     119: goto          29
     122: return

  protected java.util.Map<java.lang.reflect.Method, java.lang.reflect.Method> resolveServiceMethodsMap(java.lang.Class<?>, java.lang.Class<?>);
    Code:
       0: new           #43                 // class java/util/LinkedHashMap
       3: dup
       4: invokespecial #44                 // Method java/util/LinkedHashMap."<init>":()V
       7: astore_3
       8: new           #45                 // class java/util/ArrayList
      11: dup
      12: aload_2
      13: iconst_1
      14: anewarray     #8                  // class java/util/function/Predicate
      17: dup
      18: iconst_0
      19: ldc           #46                 // class java/lang/Object
      21: invokestatic  #47                 // InterfaceMethod org/apache/dubbo/common/utils/MethodUtils.excludedDeclaredClass:(Ljava/lang/Class;)Ljava/util/function/Predicate;
      24: aastore
      25: invokestatic  #48                 // InterfaceMethod org/apache/dubbo/common/utils/MethodUtils.getAllMethods:(Ljava/lang/Class;[Ljava/util/function/Predicate;)Ljava/util/List;
      28: invokespecial #49                 // Method java/util/ArrayList."<init>":(Ljava/util/Collection;)V
      31: astore        4
      33: aload_1
      34: aload_2
      35: invokevirtual #50                 // Method java/lang/Object.equals:(Ljava/lang/Object;)Z
      38: ifeq          53
      41: aload_0
      42: aload_3
      43: aload         4
      45: invokespecial #51                 // Method putServiceMethodToMap:(Ljava/util/Map;Ljava/util/List;)V
      48: aload_3
      49: invokestatic  #52                 // Method java/util/Collections.unmodifiableMap:(Ljava/util/Map;)Ljava/util/Map;
      52: areturn
      53: aload_1
      54: invokevirtual #53                 // Method java/lang/Class.isInterface:()Z
      57: ifeq          72
      60: aload_0
      61: aload_3
      62: aload         4
      64: invokespecial #51                 // Method putServiceMethodToMap:(Ljava/util/Map;Ljava/util/List;)V
      67: aload_3
      68: invokestatic  #52                 // Method java/util/Collections.unmodifiableMap:(Ljava/util/Map;)Ljava/util/Map;
      71: areturn
      72: new           #45                 // class java/util/ArrayList
      75: dup
      76: aload_1
      77: iconst_1
      78: anewarray     #8                  // class java/util/function/Predicate
      81: dup
      82: iconst_0
      83: ldc           #46                 // class java/lang/Object
      85: invokestatic  #47                 // InterfaceMethod org/apache/dubbo/common/utils/MethodUtils.excludedDeclaredClass:(Ljava/lang/Class;)Ljava/util/function/Predicate;
      88: aastore
      89: invokestatic  #48                 // InterfaceMethod org/apache/dubbo/common/utils/MethodUtils.getAllMethods:(Ljava/lang/Class;[Ljava/util/function/Predicate;)Ljava/util/List;
      92: invokespecial #49                 // Method java/util/ArrayList."<init>":(Ljava/util/Collection;)V
      95: astore        5
      97: aload         4
      99: getstatic     #54                 // Field org/apache/dubbo/common/utils/MethodComparator.INSTANCE:Lorg/apache/dubbo/common/utils/MethodComparator;
     102: invokestatic  #55                 // Method java/util/Collections.sort:(Ljava/util/List;Ljava/util/Comparator;)V
     105: aload         5
     107: getstatic     #54                 // Field org/apache/dubbo/common/utils/MethodComparator.INSTANCE:Lorg/apache/dubbo/common/utils/MethodComparator;
     110: invokestatic  #55                 // Method java/util/Collections.sort:(Ljava/util/List;Ljava/util/Comparator;)V
     113: aload         4
     115: invokeinterface #56,  1           // InterfaceMethod java/util/List.iterator:()Ljava/util/Iterator;
     120: astore        6
     122: aload         6
     124: invokeinterface #35,  1           // InterfaceMethod java/util/Iterator.hasNext:()Z
     129: ifeq          205
     132: aload         6
     134: invokeinterface #36,  1           // InterfaceMethod java/util/Iterator.next:()Ljava/lang/Object;
     139: checkcast     #39                 // class java/lang/reflect/Method
     142: astore        7
     144: aload         5
     146: invokeinterface #56,  1           // InterfaceMethod java/util/List.iterator:()Ljava/util/Iterator;
     151: astore        8
     153: aload         8
     155: invokeinterface #35,  1           // InterfaceMethod java/util/Iterator.hasNext:()Z
     160: ifeq          202
     163: aload         8
     165: invokeinterface #36,  1           // InterfaceMethod java/util/Iterator.next:()Ljava/lang/Object;
     170: checkcast     #39                 // class java/lang/reflect/Method
     173: astore        9
     175: aload         9
     177: aload         7
     179: invokestatic  #57                 // InterfaceMethod org/apache/dubbo/common/utils/MethodUtils.overrides:(Ljava/lang/reflect/Method;Ljava/lang/reflect/Method;)Z
     182: ifeq          199
     185: aload_3
     186: aload         9
     188: aload         7
     190: invokeinterface #58,  3           // InterfaceMethod java/util/Map.put:(Ljava/lang/Object;Ljava/lang/Object;)Ljava/lang/Object;
     195: pop
     196: goto          202
     199: goto          153
     202: goto          122
     205: aload_3
     206: invokestatic  #52                 // Method java/util/Collections.unmodifiableMap:(Ljava/util/Map;)Ljava/util/Map;
     209: areturn

  private void putServiceMethodToMap(java.util.Map<java.lang.reflect.Method, java.lang.reflect.Method>, java.util.List<java.lang.reflect.Method>);
    Code:
       0: aload_2
       1: invokeinterface #59,  1           // InterfaceMethod java/util/List.stream:()Ljava/util/stream/Stream;
       6: aload_1
       7: invokedynamic #60,  0             // InvokeDynamic #1:accept:(Ljava/util/Map;)Ljava/util/function/Consumer;
      12: invokeinterface #61,  2           // InterfaceMethod java/util/stream/Stream.forEach:(Ljava/util/function/Consumer;)V
      17: return

  protected java.lang.Class<?> resolveServiceInterfaceClass(org.apache.dubbo.metadata.rest.ServiceRestMetadata, java.lang.Class<?>);
    Code:
       0: aload_2
       1: invokevirtual #62                 // Method java/lang/Class.getClassLoader:()Ljava/lang/ClassLoader;
       4: aload_1
       5: invokedynamic #63,  0             // InvokeDynamic #2:apply:(Lorg/apache/dubbo/metadata/rest/ServiceRestMetadata;)Lorg/apache/dubbo/common/function/ThrowableFunction;
      10: invokestatic  #64                 // InterfaceMethod org/apache/dubbo/common/function/ThrowableFunction.execute:(Ljava/lang/Object;Lorg/apache/dubbo/common/function/ThrowableFunction;)Ljava/lang/Object;
      13: checkcast     #11                 // class java/lang/Class
      16: areturn

  protected boolean processRestMethodMetadata(java.lang.reflect.Method, java.lang.Class<?>, java.lang.Class<?>, java.util.function.Consumer<org.apache.dubbo.metadata.rest.RestMethodMetadata>, org.apache.dubbo.metadata.rest.ServiceRestMetadata);
    Code:
       0: aload_0
       1: aload_1
       2: aload_2
       3: aload_3
       4: invokevirtual #65                 // Method isRestCapableMethod:(Ljava/lang/reflect/Method;Ljava/lang/Class;Ljava/lang/Class;)Z
       7: ifne          12
      10: iconst_0
      11: ireturn
      12: aload_0
      13: aload_1
      14: aload_2
      15: aload_3
      16: invokevirtual #66                 // Method resolveRequestPath:(Ljava/lang/reflect/Method;Ljava/lang/Class;Ljava/lang/Class;)Ljava/lang/String;
      19: astore        6
      21: aload         6
      23: ifnonnull     28
      26: iconst_0
      27: ireturn
      28: aload_0
      29: aload_1
      30: aload_2
      31: aload_3
      32: invokevirtual #67                 // Method resolveRequestMethod:(Ljava/lang/reflect/Method;Ljava/lang/Class;Ljava/lang/Class;)Ljava/lang/String;
      35: astore        7
      37: aload         7
      39: ifnonnull     44
      42: iconst_0
      43: ireturn
      44: new           #68                 // class org/apache/dubbo/metadata/rest/RestMethodMetadata
      47: dup
      48: invokespecial #69                 // Method org/apache/dubbo/metadata/rest/RestMethodMetadata."<init>":()V
      51: astore        8
      53: aload         8
      55: aload_0
      56: invokevirtual #20                 // Method java/lang/Object.getClass:()Ljava/lang/Class;
      59: invokevirtual #70                 // Method org/apache/dubbo/metadata/rest/RestMethodMetadata.setCodeStyle:(Ljava/lang/Class;)V
      62: aload         8
      64: aload_1
      65: invokevirtual #71                 // Method org/apache/dubbo/metadata/rest/RestMethodMetadata.setReflectMethod:(Ljava/lang/reflect/Method;)V
      68: aload_0
      69: aload_1
      70: aload_2
      71: aload_3
      72: invokevirtual #72                 // Method resolveMethodDefinition:(Ljava/lang/reflect/Method;Ljava/lang/Class;Ljava/lang/Class;)Lorg/apache/dubbo/metadata/definition/model/MethodDefinition;
      75: astore        9
      77: aload         8
      79: aload         9
      81: invokevirtual #73                 // Method org/apache/dubbo/metadata/rest/RestMethodMetadata.setMethod:(Lorg/apache/dubbo/metadata/definition/model/MethodDefinition;)V
      84: new           #74                 // class java/util/LinkedHashSet
      87: dup
      88: invokespecial #75                 // Method java/util/LinkedHashSet."<init>":()V
      91: astore        10
      93: aload_0
      94: aload_1
      95: aload_2
      96: aload_3
      97: aload         10
      99: invokevirtual #76                 // Method processProduces:(Ljava/lang/reflect/Method;Ljava/lang/Class;Ljava/lang/Class;Ljava/util/Set;)V
     102: new           #74                 // class java/util/LinkedHashSet
     105: dup
     106: invokespecial #75                 // Method java/util/LinkedHashSet."<init>":()V
     109: astore        11
     111: aload_0
     112: aload_1
     113: aload_2
     114: aload_3
     115: aload         11
     117: invokevirtual #77                 // Method processConsumes:(Ljava/lang/reflect/Method;Ljava/lang/Class;Ljava/lang/Class;Ljava/util/Set;)V
     120: aload         8
     122: invokevirtual #78                 // Method org/apache/dubbo/metadata/rest/RestMethodMetadata.getRequest:()Lorg/apache/dubbo/metadata/rest/RequestMetadata;
     125: astore        12
     127: aload         12
     129: aload         6
     131: invokevirtual #79                 // Method org/apache/dubbo/metadata/rest/RequestMetadata.setPath:(Ljava/lang/String;)V
     134: aload         12
     136: aload         5
     138: invokevirtual #80                 // Method org/apache/dubbo/metadata/rest/ServiceRestMetadata.getContextPathFromUrl:()Ljava/lang/String;
     141: invokevirtual #81                 // Method org/apache/dubbo/metadata/rest/RequestMetadata.appendContextPathFromUrl:(Ljava/lang/String;)V
     144: aload         12
     146: aload         7
     148: invokevirtual #82                 // Method org/apache/dubbo/metadata/rest/RequestMetadata.setMethod:(Ljava/lang/String;)V
     151: aload         12
     153: aload         10
     155: invokevirtual #83                 // Method org/apache/dubbo/metadata/rest/RequestMetadata.setProduces:(Ljava/util/Set;)V
     158: aload         12
     160: aload         11
     162: invokevirtual #84                 // Method org/apache/dubbo/metadata/rest/RequestMetadata.setConsumes:(Ljava/util/Set;)V
     165: aload_0
     166: aload_1
     167: aload_2
     168: aload_3
     169: aload         8
     171: invokespecial #85                 // Method processAnnotatedMethodParameters:(Ljava/lang/reflect/Method;Ljava/lang/Class;Ljava/lang/Class;Lorg/apache/dubbo/metadata/rest/RestMethodMetadata;)V
     174: aload_0
     175: aload_1
     176: aload_2
     177: aload_3
     178: aload         8
     180: invokevirtual #86                 // Method postResolveRestMethodMetadata:(Ljava/lang/reflect/Method;Ljava/lang/Class;Ljava/lang/Class;Lorg/apache/dubbo/metadata/rest/RestMethodMetadata;)V
     183: aload         4
     185: aload         8
     187: invokeinterface #87,  2           // InterfaceMethod java/util/function/Consumer.accept:(Ljava/lang/Object;)V
     192: iconst_1
     193: ireturn

  protected abstract boolean isRestCapableMethod(java.lang.reflect.Method, java.lang.Class<?>, java.lang.Class<?>);

  protected abstract java.lang.String resolveRequestMethod(java.lang.reflect.Method, java.lang.Class<?>, java.lang.Class<?>);

  protected abstract java.lang.String resolveRequestPath(java.lang.reflect.Method, java.lang.Class<?>, java.lang.Class<?>);

  protected org.apache.dubbo.metadata.definition.model.MethodDefinition resolveMethodDefinition(java.lang.reflect.Method, java.lang.Class<?>, java.lang.Class<?>);
    Code:
       0: new           #88                 // class org/apache/dubbo/metadata/definition/MethodDefinitionBuilder
       3: dup
       4: invokespecial #89                 // Method org/apache/dubbo/metadata/definition/MethodDefinitionBuilder."<init>":()V
       7: astore        4
       9: aload         4
      11: aload_1
      12: invokevirtual #90                 // Method org/apache/dubbo/metadata/definition/MethodDefinitionBuilder.build:(Ljava/lang/reflect/Method;)Lorg/apache/dubbo/metadata/definition/model/MethodDefinition;
      15: areturn

  private void processAnnotatedMethodParameters(java.lang.reflect.Method, java.lang.Class<?>, java.lang.Class<?>, org.apache.dubbo.metadata.rest.RestMethodMetadata);
    Code:
       0: aload_1
       1: invokevirtual #91                 // Method java/lang/reflect/Method.getParameterCount:()I
       4: istore        5
       6: aload_1
       7: invokevirtual #92                 // Method java/lang/reflect/Method.getParameters:()[Ljava/lang/reflect/Parameter;
      10: astore        6
      12: iconst_0
      13: istore        7
      15: iload         7
      17: iload         5
      19: if_icmpge     63
      22: aload         6
      24: iload         7
      26: aaload
      27: astore        8
      29: aload         4
      31: iload         7
      33: invokestatic  #93                 // Method java/lang/Integer.valueOf:(I)Ljava/lang/Integer;
      36: aload         8
      38: invokevirtual #94                 // Method java/lang/reflect/Parameter.getName:()Ljava/lang/String;
      41: invokevirtual #95                 // Method org/apache/dubbo/metadata/rest/RestMethodMetadata.addIndexToName:(Ljava/lang/Integer;Ljava/lang/String;)V
      44: aload_0
      45: aload         8
      47: iload         7
      49: aload_1
      50: aload_2
      51: aload_3
      52: aload         4
      54: invokespecial #96                 // Method processAnnotatedMethodParameter:(Ljava/lang/reflect/Parameter;ILjava/lang/reflect/Method;Ljava/lang/Class;Ljava/lang/Class;Lorg/apache/dubbo/metadata/rest/RestMethodMetadata;)V
      57: iinc          7, 1
      60: goto          15
      63: return

  private void processAnnotatedMethodParameter(java.lang.reflect.Parameter, int, java.lang.reflect.Method, java.lang.Class<?>, java.lang.Class<?>, org.apache.dubbo.metadata.rest.RestMethodMetadata);
    Code:
       0: aload_1
       1: invokevirtual #97                 // Method java/lang/reflect/Parameter.getAnnotations:()[Ljava/lang/annotation/Annotation;
       4: astore        7
       6: aload         7
       8: ifnull        17
      11: aload         7
      13: arraylength
      14: ifne          68
      17: aload_0
      18: getfield      #5                  // Field noAnnotatedParameterRequestTagProcessors:Ljava/util/Set;
      21: invokeinterface #34,  1           // InterfaceMethod java/util/Set.iterator:()Ljava/util/Iterator;
      26: astore        8
      28: aload         8
      30: invokeinterface #35,  1           // InterfaceMethod java/util/Iterator.hasNext:()Z
      35: ifeq          68
      38: aload         8
      40: invokeinterface #36,  1           // InterfaceMethod java/util/Iterator.next:()Ljava/lang/Object;
      45: checkcast     #98                 // class org/apache/dubbo/metadata/rest/NoAnnotatedParameterRequestTagProcessor
      48: astore        9
      50: aload         9
      52: aload_1
      53: iload_2
      54: aload         6
      56: invokeinterface #99,  4           // InterfaceMethod org/apache/dubbo/metadata/rest/NoAnnotatedParameterRequestTagProcessor.process:(Ljava/lang/reflect/Parameter;ILorg/apache/dubbo/metadata/rest/RestMethodMetadata;)Z
      61: ifeq          65
      64: return
      65: goto          28
      68: aload         7
      70: astore        8
      72: aload         8
      74: arraylength
      75: istore        9
      77: iconst_0
      78: istore        10
      80: iload         10
      82: iload         9
      84: if_icmpge     150
      87: aload         8
      89: iload         10
      91: aaload
      92: astore        11
      94: aload         11
      96: invokeinterface #100,  1          // InterfaceMethod java/lang/annotation/Annotation.annotationType:()Ljava/lang/Class;
     101: invokevirtual #101                // Method java/lang/Class.getName:()Ljava/lang/String;
     104: astore        12
     106: aload_0
     107: getfield      #3                  // Field parameterProcessorsMap:Ljava/util/Map;
     110: aload         12
     112: invokestatic  #102                // Method java/util/Collections.emptyList:()Ljava/util/List;
     115: invokeinterface #103,  3          // InterfaceMethod java/util/Map.getOrDefault:(Ljava/lang/Object;Ljava/lang/Object;)Ljava/lang/Object;
     120: checkcast     #104                // class java/util/List
     123: aload         11
     125: aload_1
     126: iload_2
     127: aload_3
     128: aload         4
     130: aload         5
     132: aload         6
     134: invokedynamic #105,  0            // InvokeDynamic #3:accept:(Ljava/lang/annotation/Annotation;Ljava/lang/reflect/Parameter;ILjava/lang/reflect/Method;Ljava/lang/Class;Ljava/lang/Class;Lorg/apache/dubbo/metadata/rest/RestMethodMetadata;)Ljava/util/function/Consumer;
     139: invokeinterface #106,  2          // InterfaceMethod java/util/List.forEach:(Ljava/util/function/Consumer;)V
     144: iinc          10, 1
     147: goto          80
     150: return

  protected abstract void processProduces(java.lang.reflect.Method, java.lang.Class<?>, java.lang.Class<?>, java.util.Set<java.lang.String>);

  protected abstract void processConsumes(java.lang.reflect.Method, java.lang.Class<?>, java.lang.Class<?>, java.util.Set<java.lang.String>);

  protected void postResolveRestMethodMetadata(java.lang.reflect.Method, java.lang.Class<?>, java.lang.Class<?>, org.apache.dubbo.metadata.rest.RestMethodMetadata);
    Code:
       0: aload         4
       2: invokevirtual #78                 // Method org/apache/dubbo/metadata/rest/RestMethodMetadata.getRequest:()Lorg/apache/dubbo/metadata/rest/RequestMetadata;
       5: invokevirtual #107                // Method org/apache/dubbo/metadata/rest/RequestMetadata.getPath:()Ljava/lang/String;
       8: aload         4
      10: invokevirtual #108                // Method org/apache/dubbo/metadata/rest/RestMethodMetadata.getArgInfos:()Ljava/util/List;
      13: invokestatic  #109                // Method org/apache/dubbo/metadata/rest/PathUtil.setArgInfoSplitIndex:(Ljava/lang/String;Ljava/util/List;)V
      16: return

  private static java.util.Map<java.lang.String, java.util.List<org.apache.dubbo.metadata.rest.AnnotatedMethodParameterProcessor>> loadAnnotatedMethodParameterProcessors(org.apache.dubbo.rpc.model.ApplicationModel);
    Code:
       0: new           #43                 // class java/util/LinkedHashMap
       3: dup
       4: invokespecial #44                 // Method java/util/LinkedHashMap."<init>":()V
       7: astore_1
       8: aload_0
       9: ldc           #110                // class org/apache/dubbo/metadata/rest/AnnotatedMethodParameterProcessor
      11: invokevirtual #111                // Method org/apache/dubbo/rpc/model/ApplicationModel.getExtensionLoader:(Ljava/lang/Class;)Lorg/apache/dubbo/common/extension/ExtensionLoader;
      14: invokevirtual #112                // Method org/apache/dubbo/common/extension/ExtensionLoader.getSupportedExtensionInstances:()Ljava/util/Set;
      17: aload_1
      18: invokedynamic #113,  0            // InvokeDynamic #4:accept:(Ljava/util/Map;)Ljava/util/function/Consumer;
      23: invokeinterface #114,  2          // InterfaceMethod java/util/Set.forEach:(Ljava/util/function/Consumer;)V
      28: aload_1
      29: areturn

  private static java.util.Set<org.apache.dubbo.metadata.rest.NoAnnotatedParameterRequestTagProcessor> loadNoAnnotatedMethodParameterProcessors(org.apache.dubbo.rpc.model.ApplicationModel);
    Code:
       0: aload_0
       1: ldc           #98                 // class org/apache/dubbo/metadata/rest/NoAnnotatedParameterRequestTagProcessor
       3: invokevirtual #111                // Method org/apache/dubbo/rpc/model/ApplicationModel.getExtensionLoader:(Ljava/lang/Class;)Lorg/apache/dubbo/common/extension/ExtensionLoader;
       6: invokevirtual #112                // Method org/apache/dubbo/common/extension/ExtensionLoader.getSupportedExtensionInstances:()Ljava/util/Set;
       9: astore_1
      10: aload_1
      11: areturn

  private static void lambda$loadAnnotatedMethodParameterProcessors$4(java.util.Map, org.apache.dubbo.metadata.rest.AnnotatedMethodParameterProcessor);
    Code:
       0: aload_0
       1: aload_1
       2: invokeinterface #115,  1          // InterfaceMethod org/apache/dubbo/metadata/rest/AnnotatedMethodParameterProcessor.getAnnotationName:()Ljava/lang/String;
       7: invokedynamic #116,  0            // InvokeDynamic #5:apply:()Ljava/util/function/Function;
      12: invokeinterface #117,  3          // InterfaceMethod java/util/Map.computeIfAbsent:(Ljava/lang/Object;Ljava/util/function/Function;)Ljava/lang/Object;
      17: checkcast     #104                // class java/util/List
      20: astore_2
      21: aload_2
      22: aload_1
      23: invokeinterface #118,  2          // InterfaceMethod java/util/List.add:(Ljava/lang/Object;)Z
      28: pop
      29: return

  private static java.util.List lambda$null$3(java.lang.String);
    Code:
       0: new           #119                // class java/util/LinkedList
       3: dup
       4: invokespecial #120                // Method java/util/LinkedList."<init>":()V
       7: areturn

  private static void lambda$processAnnotatedMethodParameter$2(java.lang.annotation.Annotation, java.lang.reflect.Parameter, int, java.lang.reflect.Method, java.lang.Class, java.lang.Class, org.apache.dubbo.metadata.rest.RestMethodMetadata, org.apache.dubbo.metadata.rest.AnnotatedMethodParameterProcessor);
    Code:
       0: aload         7
       2: aload_0
       3: aload_1
       4: iload_2
       5: aload_3
       6: aload         4
       8: aload         5
      10: aload         6
      12: invokeinterface #121,  8          // InterfaceMethod org/apache/dubbo/metadata/rest/AnnotatedMethodParameterProcessor.process:(Ljava/lang/annotation/Annotation;Ljava/lang/reflect/Parameter;ILjava/lang/reflect/Method;Ljava/lang/Class;Ljava/lang/Class;Lorg/apache/dubbo/metadata/rest/RestMethodMetadata;)V
      17: return

  private static java.lang.Class lambda$resolveServiceInterfaceClass$1(org.apache.dubbo.metadata.rest.ServiceRestMetadata, java.lang.ClassLoader) throws java.lang.Throwable;
    Code:
       0: aload_0
       1: invokevirtual #122                // Method org/apache/dubbo/metadata/rest/ServiceRestMetadata.getServiceInterface:()Ljava/lang/String;
       4: astore_2
       5: aload_2
       6: aload_1
       7: invokestatic  #123                // Method org/apache/dubbo/common/utils/ClassUtils.forName:(Ljava/lang/String;Ljava/lang/ClassLoader;)Ljava/lang/Class;
      10: areturn

  private static void lambda$putServiceMethodToMap$0(java.util.Map, java.lang.reflect.Method);
    Code:
       0: aload_1
       1: invokestatic  #124                // InterfaceMethod org/apache/dubbo/common/utils/MemberUtils.isStatic:(Ljava/lang/reflect/Member;)Z
       4: ifne          21
       7: aload_1
       8: invokestatic  #125                // InterfaceMethod org/apache/dubbo/common/utils/MemberUtils.isPrivate:(Ljava/lang/reflect/Member;)Z
      11: ifne          21
      14: aload_1
      15: invokevirtual #126                // Method java/lang/reflect/Method.isDefault:()Z
      18: ifeq          22
      21: return
      22: aload_0
      23: aload_1
      24: aload_1
      25: invokeinterface #58,  3           // InterfaceMethod java/util/Map.put:(Ljava/lang/Object;Ljava/lang/Object;)Ljava/lang/Object;
      30: pop
      31: return
}
