Compiled from "AnnotatedMethodParameterProcessor.java"
public interface org.apache.dubbo.metadata.rest.AnnotatedMethodParameterProcessor extends org.apache.dubbo.common.lang.Prioritized {
  public abstract java.lang.String getAnnotationName();

  public abstract java.lang.Class getAnnotationClass();

  public abstract void process(java.lang.annotation.Annotation, java.lang.reflect.Parameter, int, java.lang.reflect.Method, java.lang.Class<?>, java.lang.Class<?>, org.apache.dubbo.metadata.rest.RestMethodMetadata);

  public static java.lang.String buildDefaultValue(int);
    Code:
       0: new           #1                  // class java/lang/StringBuilder
       3: dup
       4: invokespecial #2                  // Method java/lang/StringBuilder."<init>":()V
       7: ldc           #3                  // String {
       9: invokevirtual #4                  // Method java/lang/StringBuilder.append:(Ljava/lang/String;)Ljava/lang/StringBuilder;
      12: iload_0
      13: invokevirtual #5                  // Method java/lang/StringBuilder.append:(I)Ljava/lang/StringBuilder;
      16: ldc           #6                  // String }
      18: invokevirtual #4                  // Method java/lang/StringBuilder.append:(Ljava/lang/String;)Ljava/lang/StringBuilder;
      21: invokevirtual #7                  // Method java/lang/StringBuilder.toString:()Ljava/lang/String;
      24: areturn
}
