Compiled from "ArgInfo.java"
public class org.apache.dubbo.metadata.rest.ArgInfo {
  private int index;

  private java.lang.String annotationNameAttribute;

  private java.lang.Class paramAnnotationType;

  private java.lang.Class paramType;

  private java.lang.String paramName;

  private int urlSplitIndex;

  private java.lang.Object defaultValue;

  private boolean formContentType;

  public org.apache.dubbo.metadata.rest.ArgInfo(int, java.lang.String, java.lang.Class);
    Code:
       0: aload_0
       1: invokespecial #1                  // Method java/lang/Object."<init>":()V
       4: aload_0
       5: iload_1
       6: putfield      #2                  // Field index:I
       9: aload_0
      10: aload_2
      11: putfield      #3                  // Field paramName:Ljava/lang/String;
      14: aload_0
      15: aload_3
      16: putfield      #4                  // Field paramType:Ljava/lang/Class;
      19: return

  public org.apache.dubbo.metadata.rest.ArgInfo(int, java.lang.reflect.Parameter);
    Code:
       0: aload_0
       1: iload_1
       2: aload_2
       3: invokevirtual #5                  // Method java/lang/reflect/Parameter.getName:()Ljava/lang/String;
       6: aload_2
       7: invokevirtual #6                  // Method java/lang/reflect/Parameter.getType:()Ljava/lang/Class;
      10: invokespecial #7                  // Method "<init>":(ILjava/lang/String;Ljava/lang/Class;)V
      13: return

  public org.apache.dubbo.metadata.rest.ArgInfo();
    Code:
       0: aload_0
       1: invokespecial #1                  // Method java/lang/Object."<init>":()V
       4: return

  public int getIndex();
    Code:
       0: aload_0
       1: getfield      #2                  // Field index:I
       4: ireturn

  public org.apache.dubbo.metadata.rest.ArgInfo setIndex(int);
    Code:
       0: aload_0
       1: iload_1
       2: putfield      #2                  // Field index:I
       5: aload_0
       6: areturn

  public java.lang.String getAnnotationNameAttribute();
    Code:
       0: aload_0
       1: getfield      #8                  // Field annotationNameAttribute:Ljava/lang/String;
       4: ifnonnull     12
       7: aload_0
       8: getfield      #3                  // Field paramName:Ljava/lang/String;
      11: areturn
      12: aload_0
      13: getfield      #8                  // Field annotationNameAttribute:Ljava/lang/String;
      16: areturn

  public org.apache.dubbo.metadata.rest.ArgInfo setAnnotationNameAttribute(java.lang.String);
    Code:
       0: aload_0
       1: aload_1
       2: putfield      #8                  // Field annotationNameAttribute:Ljava/lang/String;
       5: aload_0
       6: areturn

  public java.lang.Class getParamAnnotationType();
    Code:
       0: aload_0
       1: getfield      #9                  // Field paramAnnotationType:Ljava/lang/Class;
       4: areturn

  public org.apache.dubbo.metadata.rest.ArgInfo setParamAnnotationType(java.lang.Class);
    Code:
       0: aload_0
       1: aload_1
       2: putfield      #9                  // Field paramAnnotationType:Ljava/lang/Class;
       5: aload_0
       6: areturn

  public java.lang.Class getParamType();
    Code:
       0: aload_0
       1: getfield      #4                  // Field paramType:Ljava/lang/Class;
       4: areturn

  public void setParamType(java.lang.Class);
    Code:
       0: aload_0
       1: aload_1
       2: putfield      #4                  // Field paramType:Ljava/lang/Class;
       5: return

  public int getUrlSplitIndex();
    Code:
       0: aload_0
       1: getfield      #10                 // Field urlSplitIndex:I
       4: ireturn

  public void setUrlSplitIndex(int);
    Code:
       0: aload_0
       1: iload_1
       2: putfield      #10                 // Field urlSplitIndex:I
       5: return

  public static org.apache.dubbo.metadata.rest.ArgInfo build();
    Code:
       0: new           #11                 // class org/apache/dubbo/metadata/rest/ArgInfo
       3: dup
       4: invokespecial #12                 // Method "<init>":()V
       7: areturn

  public static org.apache.dubbo.metadata.rest.ArgInfo build(int, java.lang.reflect.Parameter);
    Code:
       0: new           #11                 // class org/apache/dubbo/metadata/rest/ArgInfo
       3: dup
       4: iload_0
       5: aload_1
       6: invokespecial #13                 // Method "<init>":(ILjava/lang/reflect/Parameter;)V
       9: areturn

  public java.lang.String getParamName();
    Code:
       0: aload_0
       1: getfield      #3                  // Field paramName:Ljava/lang/String;
       4: areturn

  public org.apache.dubbo.metadata.rest.ArgInfo setParamName(java.lang.String);
    Code:
       0: aload_0
       1: aload_1
       2: putfield      #3                  // Field paramName:Ljava/lang/String;
       5: aload_0
       6: areturn

  public java.lang.Object getDefaultValue();
    Code:
       0: aload_0
       1: getfield      #14                 // Field defaultValue:Ljava/lang/Object;
       4: areturn

  public org.apache.dubbo.metadata.rest.ArgInfo setDefaultValue(java.lang.Object);
    Code:
       0: aload_0
       1: aload_1
       2: putfield      #14                 // Field defaultValue:Ljava/lang/Object;
       5: aload_0
       6: areturn

  public boolean isFormContentType();
    Code:
       0: aload_0
       1: getfield      #15                 // Field formContentType:Z
       4: ireturn

  public org.apache.dubbo.metadata.rest.ArgInfo setFormContentType(boolean);
    Code:
       0: aload_0
       1: iload_1
       2: putfield      #15                 // Field formContentType:Z
       5: aload_0
       6: areturn

  public java.lang.String toString();
    Code:
       0: new           #16                 // class java/lang/StringBuilder
       3: dup
       4: invokespecial #17                 // Method java/lang/StringBuilder."<init>":()V
       7: ldc           #18                 // String ArgInfo{index=
       9: invokevirtual #19                 // Method java/lang/StringBuilder.append:(Ljava/lang/String;)Ljava/lang/StringBuilder;
      12: aload_0
      13: getfield      #2                  // Field index:I
      16: invokevirtual #20                 // Method java/lang/StringBuilder.append:(I)Ljava/lang/StringBuilder;
      19: ldc           #21                 // String , annotationNameAttribute=\'
      21: invokevirtual #19                 // Method java/lang/StringBuilder.append:(Ljava/lang/String;)Ljava/lang/StringBuilder;
      24: aload_0
      25: getfield      #8                  // Field annotationNameAttribute:Ljava/lang/String;
      28: invokevirtual #19                 // Method java/lang/StringBuilder.append:(Ljava/lang/String;)Ljava/lang/StringBuilder;
      31: bipush        39
      33: invokevirtual #22                 // Method java/lang/StringBuilder.append:(C)Ljava/lang/StringBuilder;
      36: ldc           #23                 // String , paramAnnotationType=
      38: invokevirtual #19                 // Method java/lang/StringBuilder.append:(Ljava/lang/String;)Ljava/lang/StringBuilder;
      41: aload_0
      42: getfield      #9                  // Field paramAnnotationType:Ljava/lang/Class;
      45: invokevirtual #24                 // Method java/lang/StringBuilder.append:(Ljava/lang/Object;)Ljava/lang/StringBuilder;
      48: ldc           #25                 // String , paramType=
      50: invokevirtual #19                 // Method java/lang/StringBuilder.append:(Ljava/lang/String;)Ljava/lang/StringBuilder;
      53: aload_0
      54: getfield      #4                  // Field paramType:Ljava/lang/Class;
      57: invokevirtual #24                 // Method java/lang/StringBuilder.append:(Ljava/lang/Object;)Ljava/lang/StringBuilder;
      60: ldc           #26                 // String , paramName=\'
      62: invokevirtual #19                 // Method java/lang/StringBuilder.append:(Ljava/lang/String;)Ljava/lang/StringBuilder;
      65: aload_0
      66: getfield      #3                  // Field paramName:Ljava/lang/String;
      69: invokevirtual #19                 // Method java/lang/StringBuilder.append:(Ljava/lang/String;)Ljava/lang/StringBuilder;
      72: bipush        39
      74: invokevirtual #22                 // Method java/lang/StringBuilder.append:(C)Ljava/lang/StringBuilder;
      77: ldc           #27                 // String , urlSplitIndex=
      79: invokevirtual #19                 // Method java/lang/StringBuilder.append:(Ljava/lang/String;)Ljava/lang/StringBuilder;
      82: aload_0
      83: getfield      #10                 // Field urlSplitIndex:I
      86: invokevirtual #20                 // Method java/lang/StringBuilder.append:(I)Ljava/lang/StringBuilder;
      89: ldc           #28                 // String , defaultValue=
      91: invokevirtual #19                 // Method java/lang/StringBuilder.append:(Ljava/lang/String;)Ljava/lang/StringBuilder;
      94: aload_0
      95: getfield      #14                 // Field defaultValue:Ljava/lang/Object;
      98: invokevirtual #24                 // Method java/lang/StringBuilder.append:(Ljava/lang/Object;)Ljava/lang/StringBuilder;
     101: ldc           #29                 // String , formContentType=
     103: invokevirtual #19                 // Method java/lang/StringBuilder.append:(Ljava/lang/String;)Ljava/lang/StringBuilder;
     106: aload_0
     107: getfield      #15                 // Field formContentType:Z
     110: invokevirtual #30                 // Method java/lang/StringBuilder.append:(Z)Ljava/lang/StringBuilder;
     113: bipush        125
     115: invokevirtual #22                 // Method java/lang/StringBuilder.append:(C)Ljava/lang/StringBuilder;
     118: invokevirtual #31                 // Method java/lang/StringBuilder.toString:()Ljava/lang/String;
     121: areturn
}
