Compiled from "ClassPathServiceRestMetadataReader.java"
public class org.apache.dubbo.metadata.rest.ClassPathServiceRestMetadataReader implements org.apache.dubbo.metadata.rest.ServiceRestMetadataReader {
  private final java.lang.String serviceRestMetadataJsonResourcePath;

  public org.apache.dubbo.metadata.rest.ClassPathServiceRestMetadataReader();
    Code:
       0: aload_0
       1: ldc           #2                  // String META-INF/dubbo/service-rest-metadata.json
       3: invokespecial #3                  // Method "<init>":(Ljava/lang/String;)V
       6: return

  public org.apache.dubbo.metadata.rest.ClassPathServiceRestMetadataReader(java.lang.String);
    Code:
       0: aload_0
       1: invokespecial #4                  // Method java/lang/Object."<init>":()V
       4: aload_0
       5: aload_1
       6: putfield      #5                  // Field serviceRestMetadataJsonResourcePath:Ljava/lang/String;
       9: return

  public java.util.List<org.apache.dubbo.metadata.rest.ServiceRestMetadata> read();
    Code:
       0: new           #6                  // class java/util/LinkedList
       3: dup
       4: invokespecial #7                  // Method java/util/LinkedList."<init>":()V
       7: astore_1
       8: aload_0
       9: invokevirtual #8                  // Method java/lang/Object.getClass:()Ljava/lang/Class;
      12: invokevirtual #9                  // Method java/lang/Class.getClassLoader:()Ljava/lang/ClassLoader;
      15: astore_2
      16: aload_0
      17: aload_2
      18: aload_1
      19: invokedynamic #10,  0             // InvokeDynamic #0:execute:(Lorg/apache/dubbo/metadata/rest/ClassPathServiceRestMetadataReader;Ljava/lang/ClassLoader;Ljava/util/List;)Lorg/apache/dubbo/common/function/ThrowableAction;
      24: invokestatic  #11                 // InterfaceMethod org/apache/dubbo/common/function/ThrowableAction.execute:(Lorg/apache/dubbo/common/function/ThrowableAction;)V
      27: aload_1
      28: invokestatic  #12                 // Method java/util/Collections.unmodifiableList:(Ljava/util/List;)Ljava/util/List;
      31: areturn

  private void lambda$read$0(java.lang.ClassLoader, java.util.List) throws java.lang.Throwable;
    Code:
       0: aload_1
       1: aload_0
       2: getfield      #5                  // Field serviceRestMetadataJsonResourcePath:Ljava/lang/String;
       5: invokevirtual #13                 // Method java/lang/ClassLoader.getResources:(Ljava/lang/String;)Ljava/util/Enumeration;
       8: astore_3
       9: aload_3
      10: invokeinterface #14,  1           // InterfaceMethod java/util/Enumeration.hasMoreElements:()Z
      15: ifeq          62
      18: aload_3
      19: invokeinterface #15,  1           // InterfaceMethod java/util/Enumeration.nextElement:()Ljava/lang/Object;
      24: checkcast     #16                 // class java/net/URL
      27: astore        4
      29: aload         4
      31: invokevirtual #17                 // Method java/net/URL.openStream:()Ljava/io/InputStream;
      34: astore        5
      36: aload         5
      38: ldc           #18                 // String UTF-8
      40: invokestatic  #19                 // Method org/apache/dubbo/common/utils/IOUtils.read:(Ljava/io/InputStream;Ljava/lang/String;)Ljava/lang/String;
      43: astore        6
      45: aload_2
      46: aload         6
      48: ldc           #20                 // class org/apache/dubbo/metadata/rest/ServiceRestMetadata
      50: invokestatic  #21                 // Method org/apache/dubbo/common/utils/JsonUtils.toJavaList:(Ljava/lang/String;Ljava/lang/Class;)Ljava/util/List;
      53: invokeinterface #22,  2           // InterfaceMethod java/util/List.addAll:(Ljava/util/Collection;)Z
      58: pop
      59: goto          9
      62: return
}
