Compiled from "DefaultServiceRestMetadataResolver.java"
public class org.apache.dubbo.metadata.rest.DefaultServiceRestMetadataResolver extends org.apache.dubbo.metadata.rest.AbstractServiceRestMetadataResolver {
  public org.apache.dubbo.metadata.rest.DefaultServiceRestMetadataResolver(org.apache.dubbo.rpc.model.ApplicationModel);
    Code:
       0: aload_0
       1: aload_1
       2: invokespecial #1                  // Method org/apache/dubbo/metadata/rest/AbstractServiceRestMetadataResolver."<init>":(Lorg/apache/dubbo/rpc/model/ApplicationModel;)V
       5: return

  protected boolean supports0(java.lang.Class<?>);
    Code:
       0: iconst_0
       1: ireturn

  protected boolean isRestCapableMethod(java.lang.reflect.Method, java.lang.Class<?>, java.lang.Class<?>);
    Code:
       0: iconst_0
       1: ireturn

  protected java.lang.String resolveRequestMethod(java.lang.reflect.Method, java.lang.Class<?>, java.lang.Class<?>);
    Code:
       0: aconst_null
       1: areturn

  protected java.lang.String resolveRequestPath(java.lang.reflect.Method, java.lang.Class<?>, java.lang.Class<?>);
    Code:
       0: aconst_null
       1: areturn

  protected void processProduces(java.lang.reflect.Method, java.lang.Class<?>, java.lang.Class<?>, java.util.Set<java.lang.String>);
    Code:
       0: return

  protected void processConsumes(java.lang.reflect.Method, java.lang.Class<?>, java.lang.Class<?>, java.util.Set<java.lang.String>);
    Code:
       0: return
}
