Compiled from "ParamType.java"
public final class org.apache.dubbo.metadata.rest.ParamType extends java.lang.Enum<org.apache.dubbo.metadata.rest.ParamType> {
  public static final org.apache.dubbo.metadata.rest.ParamType HEADER;

  public static final org.apache.dubbo.metadata.rest.ParamType PARAM;

  public static final org.apache.dubbo.metadata.rest.ParamType BODY;

  public static final org.apache.dubbo.metadata.rest.ParamType PATH;

  public static final org.apache.dubbo.metadata.rest.ParamType FORM;

  public static final org.apache.dubbo.metadata.rest.ParamType PROVIDER_BODY;

  public static final org.apache.dubbo.metadata.rest.ParamType EMPTY;

  private java.util.List<java.lang.Class> annotationClasses;

  private static final org.apache.dubbo.metadata.rest.ParamType[] $VALUES;

  public static org.apache.dubbo.metadata.rest.ParamType[] values();
    Code:
       0: getstatic     #1                  // Field $VALUES:[Lorg/apache/dubbo/metadata/rest/ParamType;
       3: invokevirtual #2                  // Method "[Lorg/apache/dubbo/metadata/rest/ParamType;".clone:()Ljava/lang/Object;
       6: checkcast     #3                  // class "[Lorg/apache/dubbo/metadata/rest/ParamType;"
       9: areturn

  public static org.apache.dubbo.metadata.rest.ParamType valueOf(java.lang.String);
    Code:
       0: ldc           #4                  // class org/apache/dubbo/metadata/rest/ParamType
       2: aload_0
       3: invokestatic  #5                  // Method java/lang/Enum.valueOf:(Ljava/lang/Class;Ljava/lang/String;)Ljava/lang/Enum;
       6: checkcast     #4                  // class org/apache/dubbo/metadata/rest/ParamType
       9: areturn

  private org.apache.dubbo.metadata.rest.ParamType(java.util.List<java.lang.Class>);
    Code:
       0: aload_0
       1: aload_1
       2: iload_2
       3: invokespecial #6                  // Method java/lang/Enum."<init>":(Ljava/lang/String;I)V
       6: aload_0
       7: aload_3
       8: putfield      #7                  // Field annotationClasses:Ljava/util/List;
      11: return

  public boolean supportAnno(java.lang.Class);
    Code:
       0: aload_1
       1: ifnonnull     6
       4: iconst_0
       5: ireturn
       6: aload_0
       7: getfield      #7                  // Field annotationClasses:Ljava/util/List;
      10: aload_1
      11: invokeinterface #8,  2            // InterfaceMethod java/util/List.contains:(Ljava/lang/Object;)Z
      16: ireturn

  private static java.util.List<java.lang.Class> addSupportTypes(java.lang.Class...);
    Code:
       0: new           #9                  // class java/util/ArrayList
       3: dup
       4: invokespecial #10                 // Method java/util/ArrayList."<init>":()V
       7: astore_1
       8: aload_0
       9: astore_2
      10: aload_2
      11: arraylength
      12: istore_3
      13: iconst_0
      14: istore        4
      16: iload         4
      18: iload_3
      19: if_icmpge     49
      22: aload_2
      23: iload         4
      25: aaload
      26: astore        5
      28: aload         5
      30: ifnonnull     36
      33: goto          43
      36: aload_1
      37: aload         5
      39: invokevirtual #11                 // Method java/util/ArrayList.add:(Ljava/lang/Object;)Z
      42: pop
      43: iinc          4, 1
      46: goto          16
      49: aload_1
      50: areturn

  static {};
    Code:
       0: new           #4                  // class org/apache/dubbo/metadata/rest/ParamType
       3: dup
       4: ldc           #12                 // String HEADER
       6: iconst_0
       7: iconst_2
       8: anewarray     #13                 // class java/lang/Class
      11: dup
      12: iconst_0
      13: getstatic     #14                 // Field org/apache/dubbo/metadata/rest/JAXRSClassConstants.HEADER_PARAM_ANNOTATION_CLASS:Ljava/lang/Class;
      16: aastore
      17: dup
      18: iconst_1
      19: getstatic     #15                 // Field org/apache/dubbo/metadata/rest/SpringMvcClassConstants.REQUEST_HEADER_ANNOTATION_CLASS:Ljava/lang/Class;
      22: aastore
      23: invokestatic  #16                 // Method addSupportTypes:([Ljava/lang/Class;)Ljava/util/List;
      26: invokespecial #17                 // Method "<init>":(Ljava/lang/String;ILjava/util/List;)V
      29: putstatic     #18                 // Field HEADER:Lorg/apache/dubbo/metadata/rest/ParamType;
      32: new           #4                  // class org/apache/dubbo/metadata/rest/ParamType
      35: dup
      36: ldc           #19                 // String PARAM
      38: iconst_1
      39: iconst_3
      40: anewarray     #13                 // class java/lang/Class
      43: dup
      44: iconst_0
      45: getstatic     #20                 // Field org/apache/dubbo/metadata/rest/JAXRSClassConstants.QUERY_PARAM_ANNOTATION_CLASS:Ljava/lang/Class;
      48: aastore
      49: dup
      50: iconst_1
      51: getstatic     #21                 // Field org/apache/dubbo/metadata/rest/SpringMvcClassConstants.REQUEST_PARAM_ANNOTATION_CLASS:Ljava/lang/Class;
      54: aastore
      55: dup
      56: iconst_2
      57: ldc           #22                 // class org/apache/dubbo/metadata/rest/tag/ParamTag
      59: aastore
      60: invokestatic  #16                 // Method addSupportTypes:([Ljava/lang/Class;)Ljava/util/List;
      63: invokespecial #17                 // Method "<init>":(Ljava/lang/String;ILjava/util/List;)V
      66: putstatic     #23                 // Field PARAM:Lorg/apache/dubbo/metadata/rest/ParamType;
      69: new           #4                  // class org/apache/dubbo/metadata/rest/ParamType
      72: dup
      73: ldc           #24                 // String BODY
      75: iconst_2
      76: iconst_3
      77: anewarray     #13                 // class java/lang/Class
      80: dup
      81: iconst_0
      82: getstatic     #25                 // Field org/apache/dubbo/metadata/rest/JAXRSClassConstants.REST_EASY_BODY_ANNOTATION_CLASS:Ljava/lang/Class;
      85: aastore
      86: dup
      87: iconst_1
      88: getstatic     #26                 // Field org/apache/dubbo/metadata/rest/SpringMvcClassConstants.REQUEST_BODY_ANNOTATION_CLASS:Ljava/lang/Class;
      91: aastore
      92: dup
      93: iconst_2
      94: ldc           #27                 // class org/apache/dubbo/metadata/rest/tag/BodyTag
      96: aastore
      97: invokestatic  #16                 // Method addSupportTypes:([Ljava/lang/Class;)Ljava/util/List;
     100: invokespecial #17                 // Method "<init>":(Ljava/lang/String;ILjava/util/List;)V
     103: putstatic     #28                 // Field BODY:Lorg/apache/dubbo/metadata/rest/ParamType;
     106: new           #4                  // class org/apache/dubbo/metadata/rest/ParamType
     109: dup
     110: ldc           #29                 // String PATH
     112: iconst_3
     113: iconst_2
     114: anewarray     #13                 // class java/lang/Class
     117: dup
     118: iconst_0
     119: getstatic     #30                 // Field org/apache/dubbo/metadata/rest/JAXRSClassConstants.PATH_PARAM_ANNOTATION_CLASS:Ljava/lang/Class;
     122: aastore
     123: dup
     124: iconst_1
     125: getstatic     #31                 // Field org/apache/dubbo/metadata/rest/SpringMvcClassConstants.PATH_VARIABLE_ANNOTATION_CLASS:Ljava/lang/Class;
     128: aastore
     129: invokestatic  #16                 // Method addSupportTypes:([Ljava/lang/Class;)Ljava/util/List;
     132: invokespecial #17                 // Method "<init>":(Ljava/lang/String;ILjava/util/List;)V
     135: putstatic     #32                 // Field PATH:Lorg/apache/dubbo/metadata/rest/ParamType;
     138: new           #4                  // class org/apache/dubbo/metadata/rest/ParamType
     141: dup
     142: ldc           #33                 // String FORM
     144: iconst_4
     145: iconst_2
     146: anewarray     #13                 // class java/lang/Class
     149: dup
     150: iconst_0
     151: getstatic     #34                 // Field org/apache/dubbo/metadata/rest/JAXRSClassConstants.FORM_PARAM_ANNOTATION_CLASS:Ljava/lang/Class;
     154: aastore
     155: dup
     156: iconst_1
     157: getstatic     #26                 // Field org/apache/dubbo/metadata/rest/SpringMvcClassConstants.REQUEST_BODY_ANNOTATION_CLASS:Ljava/lang/Class;
     160: aastore
     161: invokestatic  #16                 // Method addSupportTypes:([Ljava/lang/Class;)Ljava/util/List;
     164: invokespecial #17                 // Method "<init>":(Ljava/lang/String;ILjava/util/List;)V
     167: putstatic     #35                 // Field FORM:Lorg/apache/dubbo/metadata/rest/ParamType;
     170: new           #4                  // class org/apache/dubbo/metadata/rest/ParamType
     173: dup
     174: ldc           #36                 // String PROVIDER_BODY
     176: iconst_5
     177: iconst_4
     178: anewarray     #13                 // class java/lang/Class
     181: dup
     182: iconst_0
     183: getstatic     #25                 // Field org/apache/dubbo/metadata/rest/JAXRSClassConstants.REST_EASY_BODY_ANNOTATION_CLASS:Ljava/lang/Class;
     186: aastore
     187: dup
     188: iconst_1
     189: getstatic     #34                 // Field org/apache/dubbo/metadata/rest/JAXRSClassConstants.FORM_PARAM_ANNOTATION_CLASS:Ljava/lang/Class;
     192: aastore
     193: dup
     194: iconst_2
     195: getstatic     #26                 // Field org/apache/dubbo/metadata/rest/SpringMvcClassConstants.REQUEST_BODY_ANNOTATION_CLASS:Ljava/lang/Class;
     198: aastore
     199: dup
     200: iconst_3
     201: ldc           #27                 // class org/apache/dubbo/metadata/rest/tag/BodyTag
     203: aastore
     204: invokestatic  #16                 // Method addSupportTypes:([Ljava/lang/Class;)Ljava/util/List;
     207: invokespecial #17                 // Method "<init>":(Ljava/lang/String;ILjava/util/List;)V
     210: putstatic     #37                 // Field PROVIDER_BODY:Lorg/apache/dubbo/metadata/rest/ParamType;
     213: new           #4                  // class org/apache/dubbo/metadata/rest/ParamType
     216: dup
     217: ldc           #38                 // String EMPTY
     219: bipush        6
     221: iconst_0
     222: anewarray     #13                 // class java/lang/Class
     225: invokestatic  #16                 // Method addSupportTypes:([Ljava/lang/Class;)Ljava/util/List;
     228: invokespecial #17                 // Method "<init>":(Ljava/lang/String;ILjava/util/List;)V
     231: putstatic     #39                 // Field EMPTY:Lorg/apache/dubbo/metadata/rest/ParamType;
     234: bipush        7
     236: anewarray     #4                  // class org/apache/dubbo/metadata/rest/ParamType
     239: dup
     240: iconst_0
     241: getstatic     #18                 // Field HEADER:Lorg/apache/dubbo/metadata/rest/ParamType;
     244: aastore
     245: dup
     246: iconst_1
     247: getstatic     #23                 // Field PARAM:Lorg/apache/dubbo/metadata/rest/ParamType;
     250: aastore
     251: dup
     252: iconst_2
     253: getstatic     #28                 // Field BODY:Lorg/apache/dubbo/metadata/rest/ParamType;
     256: aastore
     257: dup
     258: iconst_3
     259: getstatic     #32                 // Field PATH:Lorg/apache/dubbo/metadata/rest/ParamType;
     262: aastore
     263: dup
     264: iconst_4
     265: getstatic     #35                 // Field FORM:Lorg/apache/dubbo/metadata/rest/ParamType;
     268: aastore
     269: dup
     270: iconst_5
     271: getstatic     #37                 // Field PROVIDER_BODY:Lorg/apache/dubbo/metadata/rest/ParamType;
     274: aastore
     275: dup
     276: bipush        6
     278: getstatic     #39                 // Field EMPTY:Lorg/apache/dubbo/metadata/rest/ParamType;
     281: aastore
     282: putstatic     #1                  // Field $VALUES:[Lorg/apache/dubbo/metadata/rest/ParamType;
     285: return
}
