Compiled from "PathUtil.java"
public class org.apache.dubbo.metadata.rest.PathUtil$PathPair {
  java.lang.String value;

  org.apache.dubbo.metadata.rest.ArgInfo argInfo;

  public org.apache.dubbo.metadata.rest.PathUtil$PathPair(org.apache.dubbo.metadata.rest.ArgInfo);
    Code:
       0: aload_0
       1: invokespecial #1                  // Method java/lang/Object."<init>":()V
       4: aload_0
       5: aload_1
       6: putfield      #2                  // Field argInfo:Lorg/apache/dubbo/metadata/rest/ArgInfo;
       9: aload_0
      10: aload_1
      11: invokevirtual #3                  // Method org/apache/dubbo/metadata/rest/ArgInfo.getAnnotationNameAttribute:()Ljava/lang/String;
      14: putfield      #4                  // Field value:Ljava/lang/String;
      17: return

  public java.lang.String getPatten();
    Code:
       0: new           #5                  // class java/lang/StringBuilder
       3: dup
       4: invokespecial #6                  // Method java/lang/StringBuilder."<init>":()V
       7: ldc           #7                  // String {
       9: invokevirtual #8                  // Method java/lang/StringBuilder.append:(Ljava/lang/String;)Ljava/lang/StringBuilder;
      12: aload_0
      13: getfield      #4                  // Field value:Ljava/lang/String;
      16: invokevirtual #8                  // Method java/lang/StringBuilder.append:(Ljava/lang/String;)Ljava/lang/StringBuilder;
      19: ldc           #9                  // String }
      21: invokevirtual #8                  // Method java/lang/StringBuilder.append:(Ljava/lang/String;)Ljava/lang/StringBuilder;
      24: invokevirtual #10                 // Method java/lang/StringBuilder.toString:()Ljava/lang/String;
      27: areturn

  public java.lang.String getLeftPatten();
    Code:
       0: new           #5                  // class java/lang/StringBuilder
       3: dup
       4: invokespecial #6                  // Method java/lang/StringBuilder."<init>":()V
       7: ldc           #7                  // String {
       9: invokevirtual #8                  // Method java/lang/StringBuilder.append:(Ljava/lang/String;)Ljava/lang/StringBuilder;
      12: aload_0
      13: getfield      #4                  // Field value:Ljava/lang/String;
      16: invokevirtual #8                  // Method java/lang/StringBuilder.append:(Ljava/lang/String;)Ljava/lang/StringBuilder;
      19: invokevirtual #10                 // Method java/lang/StringBuilder.toString:()Ljava/lang/String;
      22: areturn

  public java.lang.String getRightPatten();
    Code:
       0: ldc           #9                  // String }
       2: areturn

  public boolean match(java.lang.String);
    Code:
       0: aload_0
       1: invokevirtual #11                 // Method getPatten:()Ljava/lang/String;
       4: aload_1
       5: invokevirtual #12                 // Method java/lang/String.equals:(Ljava/lang/Object;)Z
       8: ifne          33
      11: aload_1
      12: aload_0
      13: invokevirtual #13                 // Method getLeftPatten:()Ljava/lang/String;
      16: invokevirtual #14                 // Method java/lang/String.startsWith:(Ljava/lang/String;)Z
      19: ifeq          37
      22: aload_1
      23: aload_0
      24: invokevirtual #15                 // Method getRightPatten:()Ljava/lang/String;
      27: invokevirtual #16                 // Method java/lang/String.endsWith:(Ljava/lang/String;)Z
      30: ifeq          37
      33: iconst_1
      34: goto          38
      37: iconst_0
      38: ireturn

  public java.lang.String getValue();
    Code:
       0: aload_0
       1: getfield      #4                  // Field value:Ljava/lang/String;
       4: areturn

  public void setArgInfo(org.apache.dubbo.metadata.rest.ArgInfo);
    Code:
       0: aload_0
       1: aload_1
       2: putfield      #2                  // Field argInfo:Lorg/apache/dubbo/metadata/rest/ArgInfo;
       5: return

  public void setArgInfoSplitIndex(int);
    Code:
       0: aload_0
       1: getfield      #2                  // Field argInfo:Lorg/apache/dubbo/metadata/rest/ArgInfo;
       4: iload_1
       5: invokevirtual #17                 // Method org/apache/dubbo/metadata/rest/ArgInfo.setUrlSplitIndex:(I)V
       8: return
}
