Compiled from "PathMatcher.java"
public class org.apache.dubbo.metadata.rest.PathMatcher {
  private static final java.lang.String SEPARATOR;

  private java.lang.String path;

  private java.lang.String version;

  private java.lang.String group;

  private java.lang.Integer port;

  private java.lang.String[] pathSplits;

  private boolean hasPathVariable;

  private java.lang.String contextPath;

  private java.lang.String httpMethod;

  private boolean needCompareMethod;

  public org.apache.dubbo.metadata.rest.PathMatcher(java.lang.String);
    Code:
       0: aload_0
       1: aload_1
       2: aconst_null
       3: aconst_null
       4: aconst_null
       5: invokespecial #1                  // Method "<init>":(Ljava/lang/String;Ljava/lang/String;Ljava/lang/String;Ljava/lang/Integer;)V
       8: return

  public org.apache.dubbo.metadata.rest.PathMatcher(java.lang.String, java.lang.String, java.lang.String, java.lang.Integer);
    Code:
       0: aload_0
       1: invokespecial #2                  // Method java/lang/Object."<init>":()V
       4: aload_0
       5: iconst_1
       6: putfield      #3                  // Field needCompareMethod:Z
       9: aload_0
      10: aload_1
      11: putfield      #4                  // Field path:Ljava/lang/String;
      14: aload_0
      15: aload_1
      16: invokespecial #5                  // Method dealPathVariable:(Ljava/lang/String;)V
      19: aload_0
      20: aload_2
      21: putfield      #6                  // Field version:Ljava/lang/String;
      24: aload_0
      25: aload_3
      26: putfield      #7                  // Field group:Ljava/lang/String;
      29: aload_0
      30: aload         4
      32: ifnull        52
      35: aload         4
      37: invokevirtual #8                  // Method java/lang/Integer.intValue:()I
      40: iconst_m1
      41: if_icmpeq     52
      44: aload         4
      46: invokevirtual #8                  // Method java/lang/Integer.intValue:()I
      49: ifne          56
      52: aconst_null
      53: goto          58
      56: aload         4
      58: putfield      #9                  // Field port:Ljava/lang/Integer;
      61: return

  public org.apache.dubbo.metadata.rest.PathMatcher(java.lang.String, java.lang.String, java.lang.String, java.lang.Integer, java.lang.String);
    Code:
       0: aload_0
       1: aload_1
       2: aload_2
       3: aload_3
       4: aload         4
       6: invokespecial #1                  // Method "<init>":(Ljava/lang/String;Ljava/lang/String;Ljava/lang/String;Ljava/lang/Integer;)V
       9: aload_0
      10: aload         5
      12: invokevirtual #10                 // Method setHttpMethod:(Ljava/lang/String;)Lorg/apache/dubbo/metadata/rest/PathMatcher;
      15: pop
      16: return

  private void dealPathVariable(java.lang.String);
    Code:
       0: aload_0
       1: aload_1
       2: ldc           #12                 // String /
       4: invokevirtual #13                 // Method java/lang/String.split:(Ljava/lang/String;)[Ljava/lang/String;
       7: putfield      #14                 // Field pathSplits:[Ljava/lang/String;
      10: aload_0
      11: getfield      #14                 // Field pathSplits:[Ljava/lang/String;
      14: astore_2
      15: aload_2
      16: arraylength
      17: istore_3
      18: iconst_0
      19: istore        4
      21: iload         4
      23: iload_3
      24: if_icmpge     56
      27: aload_2
      28: iload         4
      30: aaload
      31: astore        5
      33: aload_0
      34: aload         5
      36: invokespecial #15                 // Method isPlaceHold:(Ljava/lang/String;)Z
      39: ifeq          50
      42: aload_0
      43: iconst_1
      44: putfield      #16                 // Field hasPathVariable:Z
      47: goto          56
      50: iinc          4, 1
      53: goto          21
      56: return

  private void setPath(java.lang.String);
    Code:
       0: aload_0
       1: aload_1
       2: putfield      #4                  // Field path:Ljava/lang/String;
       5: return

  public void setVersion(java.lang.String);
    Code:
       0: aload_0
       1: aload_1
       2: putfield      #6                  // Field version:Ljava/lang/String;
       5: return

  public void setGroup(java.lang.String);
    Code:
       0: aload_0
       1: aload_1
       2: putfield      #7                  // Field group:Ljava/lang/String;
       5: return

  public void setPort(java.lang.Integer);
    Code:
       0: aload_0
       1: aload_1
       2: putfield      #9                  // Field port:Ljava/lang/Integer;
       5: return

  public void setContextPath(java.lang.String);
    Code:
       0: aload_0
       1: aload_1
       2: invokespecial #17                 // Method contextPathFormat:(Ljava/lang/String;)Ljava/lang/String;
       5: astore_1
       6: aload_0
       7: aload_1
       8: putfield      #18                 // Field contextPath:Ljava/lang/String;
      11: aload_0
      12: new           #19                 // class java/lang/StringBuilder
      15: dup
      16: invokespecial #20                 // Method java/lang/StringBuilder."<init>":()V
      19: aload_1
      20: invokevirtual #21                 // Method java/lang/StringBuilder.append:(Ljava/lang/String;)Ljava/lang/StringBuilder;
      23: aload_0
      24: getfield      #4                  // Field path:Ljava/lang/String;
      27: invokevirtual #21                 // Method java/lang/StringBuilder.append:(Ljava/lang/String;)Ljava/lang/StringBuilder;
      30: invokevirtual #22                 // Method java/lang/StringBuilder.toString:()Ljava/lang/String;
      33: invokespecial #23                 // Method setPath:(Ljava/lang/String;)V
      36: aload_0
      37: aload_0
      38: getfield      #4                  // Field path:Ljava/lang/String;
      41: invokespecial #5                  // Method dealPathVariable:(Ljava/lang/String;)V
      44: return

  public static org.apache.dubbo.metadata.rest.PathMatcher getInvokeCreatePathMatcher(java.lang.String, java.lang.String, java.lang.String, java.lang.Integer, java.lang.String);
    Code:
       0: new           #11                 // class org/apache/dubbo/metadata/rest/PathMatcher
       3: dup
       4: aload_0
       5: aload_1
       6: aload_2
       7: aload_3
       8: aload         4
      10: invokespecial #24                 // Method "<init>":(Ljava/lang/String;Ljava/lang/String;Ljava/lang/String;Ljava/lang/Integer;Ljava/lang/String;)V
      13: invokespecial #25                 // Method noNeedHttpMethodCompare:()Lorg/apache/dubbo/metadata/rest/PathMatcher;
      16: areturn

  public boolean hasPathVariable();
    Code:
       0: aload_0
       1: getfield      #16                 // Field hasPathVariable:Z
       4: ireturn

  public java.lang.Integer getPort();
    Code:
       0: aload_0
       1: getfield      #9                  // Field port:Ljava/lang/Integer;
       4: areturn

  public java.lang.String getHttpMethod();
    Code:
       0: aload_0
       1: getfield      #26                 // Field httpMethod:Ljava/lang/String;
       4: areturn

  public org.apache.dubbo.metadata.rest.PathMatcher setHttpMethod(java.lang.String);
    Code:
       0: aload_0
       1: aload_1
       2: putfield      #26                 // Field httpMethod:Ljava/lang/String;
       5: aload_0
       6: areturn

  private org.apache.dubbo.metadata.rest.PathMatcher noNeedHttpMethodCompare();
    Code:
       0: aload_0
       1: iconst_0
       2: putfield      #3                  // Field needCompareMethod:Z
       5: aload_0
       6: areturn

  public boolean equals(java.lang.Object);
    Code:
       0: aload_0
       1: aload_1
       2: if_acmpne     7
       5: iconst_1
       6: ireturn
       7: aload_1
       8: ifnull        22
      11: aload_0
      12: invokevirtual #27                 // Method java/lang/Object.getClass:()Ljava/lang/Class;
      15: aload_1
      16: invokevirtual #27                 // Method java/lang/Object.getClass:()Ljava/lang/Class;
      19: if_acmpeq     24
      22: iconst_0
      23: ireturn
      24: aload_1
      25: checkcast     #11                 // class org/apache/dubbo/metadata/rest/PathMatcher
      28: astore_2
      29: aload_0
      30: aload_2
      31: invokespecial #28                 // Method pathEqual:(Lorg/apache/dubbo/metadata/rest/PathMatcher;)Z
      34: ifeq          104
      37: aload_0
      38: getfield      #6                  // Field version:Ljava/lang/String;
      41: aload_2
      42: getfield      #6                  // Field version:Ljava/lang/String;
      45: invokestatic  #29                 // Method java/util/Objects.equals:(Ljava/lang/Object;Ljava/lang/Object;)Z
      48: ifeq          104
      51: aload_0
      52: getfield      #3                  // Field needCompareMethod:Z
      55: ifeq          72
      58: aload_0
      59: getfield      #26                 // Field httpMethod:Ljava/lang/String;
      62: aload_2
      63: getfield      #26                 // Field httpMethod:Ljava/lang/String;
      66: invokestatic  #29                 // Method java/util/Objects.equals:(Ljava/lang/Object;Ljava/lang/Object;)Z
      69: ifeq          104
      72: aload_0
      73: getfield      #7                  // Field group:Ljava/lang/String;
      76: aload_2
      77: getfield      #7                  // Field group:Ljava/lang/String;
      80: invokestatic  #29                 // Method java/util/Objects.equals:(Ljava/lang/Object;Ljava/lang/Object;)Z
      83: ifeq          104
      86: aload_0
      87: getfield      #9                  // Field port:Ljava/lang/Integer;
      90: aload_2
      91: getfield      #9                  // Field port:Ljava/lang/Integer;
      94: invokestatic  #29                 // Method java/util/Objects.equals:(Ljava/lang/Object;Ljava/lang/Object;)Z
      97: ifeq          104
     100: iconst_1
     101: goto          105
     104: iconst_0
     105: ireturn

  public int hashCode();
    Code:
       0: iconst_3
       1: anewarray     #30                 // class java/lang/Object
       4: dup
       5: iconst_0
       6: aload_0
       7: getfield      #6                  // Field version:Ljava/lang/String;
      10: aastore
      11: dup
      12: iconst_1
      13: aload_0
      14: getfield      #7                  // Field group:Ljava/lang/String;
      17: aastore
      18: dup
      19: iconst_2
      20: aload_0
      21: getfield      #9                  // Field port:Ljava/lang/Integer;
      24: aastore
      25: invokestatic  #31                 // Method java/util/Objects.hash:([Ljava/lang/Object;)I
      28: ireturn

  private boolean pathEqual(org.apache.dubbo.metadata.rest.PathMatcher);
    Code:
       0: aload_1
       1: getfield      #16                 // Field hasPathVariable:Z
       4: ifne          19
       7: aload_0
       8: getfield      #4                  // Field path:Ljava/lang/String;
      11: aload_1
      12: getfield      #4                  // Field path:Ljava/lang/String;
      15: invokevirtual #32                 // Method java/lang/String.equals:(Ljava/lang/Object;)Z
      18: ireturn
      19: aload_1
      20: getfield      #14                 // Field pathSplits:[Ljava/lang/String;
      23: astore_2
      24: aload_0
      25: getfield      #14                 // Field pathSplits:[Ljava/lang/String;
      28: astore_3
      29: aload_3
      30: arraylength
      31: aload_2
      32: arraylength
      33: if_icmpeq     38
      36: iconst_0
      37: ireturn
      38: iconst_0
      39: istore        4
      41: iload         4
      43: aload_2
      44: arraylength
      45: if_icmpge     95
      48: aload_3
      49: iload         4
      51: aaload
      52: aload_2
      53: iload         4
      55: aaload
      56: invokevirtual #32                 // Method java/lang/String.equals:(Ljava/lang/Object;)Z
      59: istore        5
      61: iload         5
      63: ifeq          69
      66: goto          89
      69: aload_0
      70: aload_2
      71: iload         4
      73: aaload
      74: aload_3
      75: iload         4
      77: aaload
      78: invokespecial #33                 // Method placeHoldCompare:(Ljava/lang/String;Ljava/lang/String;)Z
      81: ifeq          87
      84: goto          89
      87: iconst_0
      88: ireturn
      89: iinc          4, 1
      92: goto          41
      95: iconst_1
      96: ireturn

  private boolean placeHoldCompare(java.lang.String, java.lang.String);
    Code:
       0: aload_0
       1: aload_1
       2: invokespecial #15                 // Method isPlaceHold:(Ljava/lang/String;)Z
       5: ifne          16
       8: aload_0
       9: aload_2
      10: invokespecial #15                 // Method isPlaceHold:(Ljava/lang/String;)Z
      13: ifeq          20
      16: iconst_1
      17: goto          21
      20: iconst_0
      21: istore_3
      22: iload_3
      23: ifne          28
      26: iconst_0
      27: ireturn
      28: aload_1
      29: invokevirtual #34                 // Method java/lang/String.length:()I
      32: iconst_3
      33: if_icmpge     44
      36: aload_2
      37: invokevirtual #34                 // Method java/lang/String.length:()I
      40: iconst_3
      41: if_icmplt     48
      44: iconst_1
      45: goto          49
      48: iconst_0
      49: istore        4
      51: iload         4
      53: ifne          58
      56: iconst_0
      57: ireturn
      58: iconst_1
      59: ireturn

  private boolean isPlaceHold(java.lang.String);
    Code:
       0: aload_1
       1: ldc           #35                 // String {
       3: invokevirtual #36                 // Method java/lang/String.startsWith:(Ljava/lang/String;)Z
       6: ifeq          22
       9: aload_1
      10: ldc           #37                 // String }
      12: invokevirtual #38                 // Method java/lang/String.endsWith:(Ljava/lang/String;)Z
      15: ifeq          22
      18: iconst_1
      19: goto          23
      22: iconst_0
      23: ireturn

  private java.lang.String contextPathFormat(java.lang.String);
    Code:
       0: aload_1
       1: ifnull        20
       4: aload_1
       5: ldc           #12                 // String /
       7: invokevirtual #32                 // Method java/lang/String.equals:(Ljava/lang/Object;)Z
      10: ifne          20
      13: aload_1
      14: invokevirtual #34                 // Method java/lang/String.length:()I
      17: ifne          23
      20: ldc           #39                 // String
      22: areturn
      23: aload_0
      24: aload_1
      25: invokespecial #40                 // Method pathFormat:(Ljava/lang/String;)Ljava/lang/String;
      28: areturn

  private java.lang.String pathFormat(java.lang.String);
    Code:
       0: aload_1
       1: ldc           #12                 // String /
       3: invokevirtual #36                 // Method java/lang/String.startsWith:(Ljava/lang/String;)Z
       6: ifeq          11
       9: aload_1
      10: areturn
      11: new           #19                 // class java/lang/StringBuilder
      14: dup
      15: invokespecial #20                 // Method java/lang/StringBuilder."<init>":()V
      18: ldc           #12                 // String /
      20: invokevirtual #21                 // Method java/lang/StringBuilder.append:(Ljava/lang/String;)Ljava/lang/StringBuilder;
      23: aload_1
      24: invokevirtual #21                 // Method java/lang/StringBuilder.append:(Ljava/lang/String;)Ljava/lang/StringBuilder;
      27: invokevirtual #22                 // Method java/lang/StringBuilder.toString:()Ljava/lang/String;
      30: areturn

  public java.lang.String toString();
    Code:
       0: new           #19                 // class java/lang/StringBuilder
       3: dup
       4: invokespecial #20                 // Method java/lang/StringBuilder."<init>":()V
       7: ldc           #41                 // String PathMatcher{path=\'
       9: invokevirtual #21                 // Method java/lang/StringBuilder.append:(Ljava/lang/String;)Ljava/lang/StringBuilder;
      12: aload_0
      13: getfield      #4                  // Field path:Ljava/lang/String;
      16: invokevirtual #21                 // Method java/lang/StringBuilder.append:(Ljava/lang/String;)Ljava/lang/StringBuilder;
      19: bipush        39
      21: invokevirtual #42                 // Method java/lang/StringBuilder.append:(C)Ljava/lang/StringBuilder;
      24: ldc           #43                 // String , version=\'
      26: invokevirtual #21                 // Method java/lang/StringBuilder.append:(Ljava/lang/String;)Ljava/lang/StringBuilder;
      29: aload_0
      30: getfield      #6                  // Field version:Ljava/lang/String;
      33: invokevirtual #21                 // Method java/lang/StringBuilder.append:(Ljava/lang/String;)Ljava/lang/StringBuilder;
      36: bipush        39
      38: invokevirtual #42                 // Method java/lang/StringBuilder.append:(C)Ljava/lang/StringBuilder;
      41: ldc           #44                 // String , group=\'
      43: invokevirtual #21                 // Method java/lang/StringBuilder.append:(Ljava/lang/String;)Ljava/lang/StringBuilder;
      46: aload_0
      47: getfield      #7                  // Field group:Ljava/lang/String;
      50: invokevirtual #21                 // Method java/lang/StringBuilder.append:(Ljava/lang/String;)Ljava/lang/StringBuilder;
      53: bipush        39
      55: invokevirtual #42                 // Method java/lang/StringBuilder.append:(C)Ljava/lang/StringBuilder;
      58: ldc           #45                 // String , port=
      60: invokevirtual #21                 // Method java/lang/StringBuilder.append:(Ljava/lang/String;)Ljava/lang/StringBuilder;
      63: aload_0
      64: getfield      #9                  // Field port:Ljava/lang/Integer;
      67: invokevirtual #46                 // Method java/lang/StringBuilder.append:(Ljava/lang/Object;)Ljava/lang/StringBuilder;
      70: ldc           #47                 // String , hasPathVariable=
      72: invokevirtual #21                 // Method java/lang/StringBuilder.append:(Ljava/lang/String;)Ljava/lang/StringBuilder;
      75: aload_0
      76: getfield      #16                 // Field hasPathVariable:Z
      79: invokevirtual #48                 // Method java/lang/StringBuilder.append:(Z)Ljava/lang/StringBuilder;
      82: ldc           #49                 // String , contextPath=\'
      84: invokevirtual #21                 // Method java/lang/StringBuilder.append:(Ljava/lang/String;)Ljava/lang/StringBuilder;
      87: aload_0
      88: getfield      #18                 // Field contextPath:Ljava/lang/String;
      91: invokevirtual #21                 // Method java/lang/StringBuilder.append:(Ljava/lang/String;)Ljava/lang/StringBuilder;
      94: bipush        39
      96: invokevirtual #42                 // Method java/lang/StringBuilder.append:(C)Ljava/lang/StringBuilder;
      99: ldc           #50                 // String , httpMethod=\'
     101: invokevirtual #21                 // Method java/lang/StringBuilder.append:(Ljava/lang/String;)Ljava/lang/StringBuilder;
     104: aload_0
     105: getfield      #26                 // Field httpMethod:Ljava/lang/String;
     108: invokevirtual #21                 // Method java/lang/StringBuilder.append:(Ljava/lang/String;)Ljava/lang/StringBuilder;
     111: bipush        39
     113: invokevirtual #42                 // Method java/lang/StringBuilder.append:(C)Ljava/lang/StringBuilder;
     116: bipush        125
     118: invokevirtual #42                 // Method java/lang/StringBuilder.append:(C)Ljava/lang/StringBuilder;
     121: invokevirtual #22                 // Method java/lang/StringBuilder.toString:()Ljava/lang/String;
     124: areturn
}
