Compiled from "RequestMetadata.java"
public class org.apache.dubbo.metadata.rest.RequestMetadata implements java.io.Serializable {
  private static final long serialVersionUID;

  private java.lang.String method;

  private java.lang.String path;

  private java.util.Map<java.lang.String, java.util.List<java.lang.String>> params;

  private java.util.Map<java.lang.String, java.util.List<java.lang.String>> headers;

  private java.util.Set<java.lang.String> consumes;

  private java.util.Set<java.lang.String> produces;

  public org.apache.dubbo.metadata.rest.RequestMetadata();
    Code:
       0: aload_0
       1: invokespecial #1                  // Method java/lang/Object."<init>":()V
       4: aload_0
       5: new           #2                  // class java/util/LinkedHashMap
       8: dup
       9: invokespecial #3                  // Method java/util/LinkedHashMap."<init>":()V
      12: putfield      #4                  // Field params:Ljava/util/Map;
      15: aload_0
      16: new           #2                  // class java/util/LinkedHashMap
      19: dup
      20: invokespecial #3                  // Method java/util/LinkedHashMap."<init>":()V
      23: putfield      #5                  // Field headers:Ljava/util/Map;
      26: aload_0
      27: new           #6                  // class java/util/LinkedHashSet
      30: dup
      31: invokespecial #7                  // Method java/util/LinkedHashSet."<init>":()V
      34: putfield      #8                  // Field consumes:Ljava/util/Set;
      37: aload_0
      38: new           #6                  // class java/util/LinkedHashSet
      41: dup
      42: invokespecial #7                  // Method java/util/LinkedHashSet."<init>":()V
      45: putfield      #9                  // Field produces:Ljava/util/Set;
      48: return

  public java.lang.String getMethod();
    Code:
       0: aload_0
       1: getfield      #10                 // Field method:Ljava/lang/String;
       4: areturn

  public void setMethod(java.lang.String);
    Code:
       0: aload_0
       1: aload_1
       2: ifnonnull     9
       5: aconst_null
       6: goto          13
       9: aload_1
      10: invokevirtual #11                 // Method java/lang/String.toUpperCase:()Ljava/lang/String;
      13: putfield      #10                 // Field method:Ljava/lang/String;
      16: return

  public java.lang.String getPath();
    Code:
       0: aload_0
       1: getfield      #12                 // Field path:Ljava/lang/String;
       4: areturn

  public void setPath(java.lang.String);
    Code:
       0: aload_0
       1: aload_1
       2: invokestatic  #13                 // InterfaceMethod org/apache/dubbo/common/utils/PathUtils.normalize:(Ljava/lang/String;)Ljava/lang/String;
       5: putfield      #12                 // Field path:Ljava/lang/String;
       8: aload_1
       9: getstatic     #14                 // Field org/apache/dubbo/common/utils/StringUtils.SLASH:Ljava/lang/String;
      12: invokevirtual #15                 // Method java/lang/String.startsWith:(Ljava/lang/String;)Z
      15: ifne          42
      18: aload_0
      19: new           #16                 // class java/lang/StringBuilder
      22: dup
      23: invokespecial #17                 // Method java/lang/StringBuilder."<init>":()V
      26: getstatic     #14                 // Field org/apache/dubbo/common/utils/StringUtils.SLASH:Ljava/lang/String;
      29: invokevirtual #18                 // Method java/lang/StringBuilder.append:(Ljava/lang/String;)Ljava/lang/StringBuilder;
      32: aload_1
      33: invokevirtual #18                 // Method java/lang/StringBuilder.append:(Ljava/lang/String;)Ljava/lang/StringBuilder;
      36: invokevirtual #19                 // Method java/lang/StringBuilder.toString:()Ljava/lang/String;
      39: putfield      #12                 // Field path:Ljava/lang/String;
      42: return

  public java.util.Map<java.lang.String, java.util.List<java.lang.String>> getParams();
    Code:
       0: aload_0
       1: getfield      #4                  // Field params:Ljava/util/Map;
       4: invokestatic  #20                 // Method java/util/Collections.unmodifiableMap:(Ljava/util/Map;)Ljava/util/Map;
       7: areturn

  public void setParams(java.util.Map<java.lang.String, java.util.List<java.lang.String>>);
    Code:
       0: aload_0
       1: aload_1
       2: invokespecial #21                 // Method params:(Ljava/util/Map;)Lorg/apache/dubbo/metadata/rest/RequestMetadata;
       5: pop
       6: return

  private static void add(java.util.Map<java.lang.String, java.util.List<java.lang.String>>, java.lang.String, java.lang.String);
    Code:
       0: aload_1
       1: invokestatic  #22                 // Method org/apache/dubbo/common/utils/StringUtils.isBlank:(Ljava/lang/CharSequence;)Z
       4: ifeq          8
       7: return
       8: aload_0
       9: aload_1
      10: iconst_1
      11: invokestatic  #23                 // Method get:(Ljava/util/Map;Ljava/lang/String;Z)Ljava/util/List;
      14: astore_3
      15: aload_3
      16: aload_2
      17: invokeinterface #24,  2           // InterfaceMethod java/util/List.add:(Ljava/lang/Object;)Z
      22: pop
      23: return

  private static <T extends java.util.Collection<java.lang.String>> void addAll(java.util.Map<java.lang.String, java.util.List<java.lang.String>>, java.util.Map<java.lang.String, T>);
    Code:
       0: aload_1
       1: invokeinterface #25,  1           // InterfaceMethod java/util/Map.entrySet:()Ljava/util/Set;
       6: invokeinterface #26,  1           // InterfaceMethod java/util/Set.iterator:()Ljava/util/Iterator;
      11: astore_2
      12: aload_2
      13: invokeinterface #27,  1           // InterfaceMethod java/util/Iterator.hasNext:()Z
      18: ifeq          94
      21: aload_2
      22: invokeinterface #28,  1           // InterfaceMethod java/util/Iterator.next:()Ljava/lang/Object;
      27: checkcast     #29                 // class java/util/Map$Entry
      30: astore_3
      31: aload_3
      32: invokeinterface #30,  1           // InterfaceMethod java/util/Map$Entry.getKey:()Ljava/lang/Object;
      37: checkcast     #31                 // class java/lang/String
      40: astore        4
      42: aload_3
      43: invokeinterface #32,  1           // InterfaceMethod java/util/Map$Entry.getValue:()Ljava/lang/Object;
      48: checkcast     #33                 // class java/util/Collection
      51: invokeinterface #34,  1           // InterfaceMethod java/util/Collection.iterator:()Ljava/util/Iterator;
      56: astore        5
      58: aload         5
      60: invokeinterface #27,  1           // InterfaceMethod java/util/Iterator.hasNext:()Z
      65: ifeq          91
      68: aload         5
      70: invokeinterface #28,  1           // InterfaceMethod java/util/Iterator.next:()Ljava/lang/Object;
      75: checkcast     #31                 // class java/lang/String
      78: astore        6
      80: aload_0
      81: aload         4
      83: aload         6
      85: invokestatic  #35                 // Method add:(Ljava/util/Map;Ljava/lang/String;Ljava/lang/String;)V
      88: goto          58
      91: goto          12
      94: return

  private static java.lang.String getFirst(java.util.Map<java.lang.String, java.util.List<java.lang.String>>, java.lang.String);
    Code:
       0: aload_0
       1: aload_1
       2: invokestatic  #36                 // Method get:(Ljava/util/Map;Ljava/lang/String;)Ljava/util/List;
       5: astore_2
       6: aload_2
       7: invokestatic  #37                 // Method org/apache/dubbo/common/utils/CollectionUtils.isNotEmpty:(Ljava/util/Collection;)Z
      10: ifeq          26
      13: aload_2
      14: iconst_0
      15: invokeinterface #38,  2           // InterfaceMethod java/util/List.get:(I)Ljava/lang/Object;
      20: checkcast     #31                 // class java/lang/String
      23: goto          27
      26: aconst_null
      27: areturn

  private static java.util.List<java.lang.String> get(java.util.Map<java.lang.String, java.util.List<java.lang.String>>, java.lang.String);
    Code:
       0: aload_0
       1: aload_1
       2: iconst_0
       3: invokestatic  #23                 // Method get:(Ljava/util/Map;Ljava/lang/String;Z)Ljava/util/List;
       6: areturn

  private static java.util.List<java.lang.String> get(java.util.Map<java.lang.String, java.util.List<java.lang.String>>, java.lang.String, boolean);
    Code:
       0: iload_2
       1: ifeq          22
       4: aload_0
       5: aload_1
       6: invokedynamic #39,  0             // InvokeDynamic #0:apply:()Ljava/util/function/Function;
      11: invokeinterface #40,  3           // InterfaceMethod java/util/Map.computeIfAbsent:(Ljava/lang/Object;Ljava/util/function/Function;)Ljava/lang/Object;
      16: checkcast     #41                 // class java/util/List
      19: goto          32
      22: aload_0
      23: aload_1
      24: invokeinterface #42,  2           // InterfaceMethod java/util/Map.get:(Ljava/lang/Object;)Ljava/lang/Object;
      29: checkcast     #41                 // class java/util/List
      32: areturn

  public java.util.Map<java.lang.String, java.util.List<java.lang.String>> getHeaders();
    Code:
       0: aload_0
       1: getfield      #5                  // Field headers:Ljava/util/Map;
       4: invokestatic  #20                 // Method java/util/Collections.unmodifiableMap:(Ljava/util/Map;)Ljava/util/Map;
       7: areturn

  public void setHeaders(java.util.Map<java.lang.String, java.util.List<java.lang.String>>);
    Code:
       0: aload_0
       1: aload_1
       2: invokespecial #43                 // Method headers:(Ljava/util/Map;)Lorg/apache/dubbo/metadata/rest/RequestMetadata;
       5: pop
       6: return

  public java.util.Set<java.lang.String> getConsumes();
    Code:
       0: aload_0
       1: getfield      #8                  // Field consumes:Ljava/util/Set;
       4: areturn

  public void setConsumes(java.util.Set<java.lang.String>);
    Code:
       0: aload_0
       1: aload_1
       2: putfield      #8                  // Field consumes:Ljava/util/Set;
       5: return

  public java.util.Set<java.lang.String> getProduces();
    Code:
       0: aload_0
       1: getfield      #9                  // Field produces:Ljava/util/Set;
       4: areturn

  public void setProduces(java.util.Set<java.lang.String>);
    Code:
       0: aload_0
       1: aload_1
       2: putfield      #9                  // Field produces:Ljava/util/Set;
       5: return

  public java.util.Set<java.lang.String> getParamNames();
    Code:
       0: new           #44                 // class java/util/HashSet
       3: dup
       4: aload_0
       5: getfield      #4                  // Field params:Ljava/util/Map;
       8: invokeinterface #45,  1           // InterfaceMethod java/util/Map.keySet:()Ljava/util/Set;
      13: invokespecial #46                 // Method java/util/HashSet."<init>":(Ljava/util/Collection;)V
      16: areturn

  public java.util.Set<java.lang.String> getHeaderNames();
    Code:
       0: new           #44                 // class java/util/HashSet
       3: dup
       4: aload_0
       5: getfield      #5                  // Field headers:Ljava/util/Map;
       8: invokeinterface #45,  1           // InterfaceMethod java/util/Map.keySet:()Ljava/util/Set;
      13: invokespecial #46                 // Method java/util/HashSet."<init>":(Ljava/util/Collection;)V
      16: areturn

  public java.lang.String getParameter(java.lang.String);
    Code:
       0: aload_0
       1: getfield      #4                  // Field params:Ljava/util/Map;
       4: aload_1
       5: invokestatic  #47                 // Method getFirst:(Ljava/util/Map;Ljava/lang/String;)Ljava/lang/String;
       8: areturn

  public java.lang.String getHeader(java.lang.String);
    Code:
       0: aload_0
       1: getfield      #5                  // Field headers:Ljava/util/Map;
       4: aload_1
       5: invokestatic  #47                 // Method getFirst:(Ljava/util/Map;Ljava/lang/String;)Ljava/lang/String;
       8: areturn

  public org.apache.dubbo.metadata.rest.RequestMetadata addParam(java.lang.String, java.lang.String);
    Code:
       0: aload_0
       1: getfield      #4                  // Field params:Ljava/util/Map;
       4: aload_1
       5: aload_2
       6: invokestatic  #35                 // Method add:(Ljava/util/Map;Ljava/lang/String;Ljava/lang/String;)V
       9: aload_0
      10: areturn

  public org.apache.dubbo.metadata.rest.RequestMetadata addHeader(java.lang.String, java.lang.String);
    Code:
       0: aload_0
       1: getfield      #5                  // Field headers:Ljava/util/Map;
       4: aload_1
       5: aload_2
       6: invokestatic  #35                 // Method add:(Ljava/util/Map;Ljava/lang/String;Ljava/lang/String;)V
       9: aload_0
      10: areturn

  private <T extends java.util.Collection<java.lang.String>> org.apache.dubbo.metadata.rest.RequestMetadata params(java.util.Map<java.lang.String, T>);
    Code:
       0: aload_0
       1: getfield      #4                  // Field params:Ljava/util/Map;
       4: aload_1
       5: invokestatic  #48                 // Method addAll:(Ljava/util/Map;Ljava/util/Map;)V
       8: aload_0
       9: areturn

  private <T extends java.util.Collection<java.lang.String>> org.apache.dubbo.metadata.rest.RequestMetadata headers(java.util.Map<java.lang.String, java.util.List<java.lang.String>>);
    Code:
       0: aload_1
       1: ifnull        36
       4: aload_1
       5: invokeinterface #49,  1           // InterfaceMethod java/util/Map.isEmpty:()Z
      10: ifne          36
      13: new           #2                  // class java/util/LinkedHashMap
      16: dup
      17: invokespecial #3                  // Method java/util/LinkedHashMap."<init>":()V
      20: astore_2
      21: aload_2
      22: aload_1
      23: invokestatic  #48                 // Method addAll:(Ljava/util/Map;Ljava/util/Map;)V
      26: aload_0
      27: getfield      #5                  // Field headers:Ljava/util/Map;
      30: aload_2
      31: invokeinterface #50,  2           // InterfaceMethod java/util/Map.putAll:(Ljava/util/Map;)V
      36: aload_0
      37: areturn

  public void appendContextPathFromUrl(java.lang.String);
    Code:
       0: aload_1
       1: ifnonnull     5
       4: return
       5: aload_0
       6: new           #16                 // class java/lang/StringBuilder
       9: dup
      10: invokespecial #17                 // Method java/lang/StringBuilder."<init>":()V
      13: aload_1
      14: invokevirtual #18                 // Method java/lang/StringBuilder.append:(Ljava/lang/String;)Ljava/lang/StringBuilder;
      17: aload_0
      18: getfield      #12                 // Field path:Ljava/lang/String;
      21: invokevirtual #18                 // Method java/lang/StringBuilder.append:(Ljava/lang/String;)Ljava/lang/StringBuilder;
      24: invokevirtual #19                 // Method java/lang/StringBuilder.toString:()Ljava/lang/String;
      27: invokevirtual #51                 // Method setPath:(Ljava/lang/String;)V
      30: return

  public boolean methodAllowed(java.lang.String);
    Code:
       0: aload_1
       1: ifnull        19
       4: aload_1
       5: aload_0
       6: getfield      #10                 // Field method:Ljava/lang/String;
       9: invokevirtual #52                 // Method java/lang/String.equals:(Ljava/lang/Object;)Z
      12: ifeq          19
      15: iconst_1
      16: goto          20
      19: iconst_0
      20: ireturn

  public boolean equals(java.lang.Object);
    Code:
       0: aload_0
       1: aload_1
       2: if_acmpne     7
       5: iconst_1
       6: ireturn
       7: aload_1
       8: instanceof    #53                 // class org/apache/dubbo/metadata/rest/RequestMetadata
      11: ifne          16
      14: iconst_0
      15: ireturn
      16: aload_1
      17: checkcast     #53                 // class org/apache/dubbo/metadata/rest/RequestMetadata
      20: astore_2
      21: aload_0
      22: getfield      #10                 // Field method:Ljava/lang/String;
      25: aload_2
      26: getfield      #10                 // Field method:Ljava/lang/String;
      29: invokestatic  #54                 // Method java/util/Objects.equals:(Ljava/lang/Object;Ljava/lang/Object;)Z
      32: ifeq          109
      35: aload_0
      36: getfield      #12                 // Field path:Ljava/lang/String;
      39: aload_2
      40: getfield      #12                 // Field path:Ljava/lang/String;
      43: invokestatic  #54                 // Method java/util/Objects.equals:(Ljava/lang/Object;Ljava/lang/Object;)Z
      46: ifeq          109
      49: aload_0
      50: getfield      #8                  // Field consumes:Ljava/util/Set;
      53: aload_2
      54: getfield      #8                  // Field consumes:Ljava/util/Set;
      57: invokestatic  #54                 // Method java/util/Objects.equals:(Ljava/lang/Object;Ljava/lang/Object;)Z
      60: ifeq          109
      63: aload_0
      64: getfield      #9                  // Field produces:Ljava/util/Set;
      67: aload_2
      68: getfield      #9                  // Field produces:Ljava/util/Set;
      71: invokestatic  #54                 // Method java/util/Objects.equals:(Ljava/lang/Object;Ljava/lang/Object;)Z
      74: ifeq          109
      77: aload_0
      78: invokevirtual #55                 // Method getParamNames:()Ljava/util/Set;
      81: aload_2
      82: invokevirtual #55                 // Method getParamNames:()Ljava/util/Set;
      85: invokestatic  #54                 // Method java/util/Objects.equals:(Ljava/lang/Object;Ljava/lang/Object;)Z
      88: ifeq          109
      91: aload_0
      92: invokevirtual #56                 // Method getHeaderNames:()Ljava/util/Set;
      95: aload_2
      96: invokevirtual #56                 // Method getHeaderNames:()Ljava/util/Set;
      99: invokestatic  #54                 // Method java/util/Objects.equals:(Ljava/lang/Object;Ljava/lang/Object;)Z
     102: ifeq          109
     105: iconst_1
     106: goto          110
     109: iconst_0
     110: ireturn

  public int hashCode();
    Code:
       0: bipush        6
       2: anewarray     #57                 // class java/lang/Object
       5: dup
       6: iconst_0
       7: aload_0
       8: getfield      #10                 // Field method:Ljava/lang/String;
      11: aastore
      12: dup
      13: iconst_1
      14: aload_0
      15: getfield      #12                 // Field path:Ljava/lang/String;
      18: aastore
      19: dup
      20: iconst_2
      21: aload_0
      22: getfield      #8                  // Field consumes:Ljava/util/Set;
      25: aastore
      26: dup
      27: iconst_3
      28: aload_0
      29: getfield      #9                  // Field produces:Ljava/util/Set;
      32: aastore
      33: dup
      34: iconst_4
      35: aload_0
      36: invokevirtual #55                 // Method getParamNames:()Ljava/util/Set;
      39: aastore
      40: dup
      41: iconst_5
      42: aload_0
      43: invokevirtual #56                 // Method getHeaderNames:()Ljava/util/Set;
      46: aastore
      47: invokestatic  #58                 // Method java/util/Objects.hash:([Ljava/lang/Object;)I
      50: ireturn

  public java.lang.String toString();
    Code:
       0: new           #16                 // class java/lang/StringBuilder
       3: dup
       4: invokespecial #17                 // Method java/lang/StringBuilder."<init>":()V
       7: ldc           #59                 // String RequestMetadata{method=\'
       9: invokevirtual #18                 // Method java/lang/StringBuilder.append:(Ljava/lang/String;)Ljava/lang/StringBuilder;
      12: aload_0
      13: getfield      #10                 // Field method:Ljava/lang/String;
      16: invokevirtual #18                 // Method java/lang/StringBuilder.append:(Ljava/lang/String;)Ljava/lang/StringBuilder;
      19: bipush        39
      21: invokevirtual #60                 // Method java/lang/StringBuilder.append:(C)Ljava/lang/StringBuilder;
      24: ldc           #61                 // String , path=\'
      26: invokevirtual #18                 // Method java/lang/StringBuilder.append:(Ljava/lang/String;)Ljava/lang/StringBuilder;
      29: aload_0
      30: getfield      #12                 // Field path:Ljava/lang/String;
      33: invokevirtual #18                 // Method java/lang/StringBuilder.append:(Ljava/lang/String;)Ljava/lang/StringBuilder;
      36: bipush        39
      38: invokevirtual #60                 // Method java/lang/StringBuilder.append:(C)Ljava/lang/StringBuilder;
      41: ldc           #62                 // String , params=
      43: invokevirtual #18                 // Method java/lang/StringBuilder.append:(Ljava/lang/String;)Ljava/lang/StringBuilder;
      46: aload_0
      47: getfield      #4                  // Field params:Ljava/util/Map;
      50: invokevirtual #63                 // Method java/lang/StringBuilder.append:(Ljava/lang/Object;)Ljava/lang/StringBuilder;
      53: ldc           #64                 // String , headers=
      55: invokevirtual #18                 // Method java/lang/StringBuilder.append:(Ljava/lang/String;)Ljava/lang/StringBuilder;
      58: aload_0
      59: getfield      #5                  // Field headers:Ljava/util/Map;
      62: invokevirtual #63                 // Method java/lang/StringBuilder.append:(Ljava/lang/Object;)Ljava/lang/StringBuilder;
      65: ldc           #65                 // String , consumes=
      67: invokevirtual #18                 // Method java/lang/StringBuilder.append:(Ljava/lang/String;)Ljava/lang/StringBuilder;
      70: aload_0
      71: getfield      #8                  // Field consumes:Ljava/util/Set;
      74: invokevirtual #63                 // Method java/lang/StringBuilder.append:(Ljava/lang/Object;)Ljava/lang/StringBuilder;
      77: ldc           #66                 // String , produces=
      79: invokevirtual #18                 // Method java/lang/StringBuilder.append:(Ljava/lang/String;)Ljava/lang/StringBuilder;
      82: aload_0
      83: getfield      #9                  // Field produces:Ljava/util/Set;
      86: invokevirtual #63                 // Method java/lang/StringBuilder.append:(Ljava/lang/Object;)Ljava/lang/StringBuilder;
      89: bipush        125
      91: invokevirtual #60                 // Method java/lang/StringBuilder.append:(C)Ljava/lang/StringBuilder;
      94: invokevirtual #19                 // Method java/lang/StringBuilder.toString:()Ljava/lang/String;
      97: areturn

  private static java.util.List lambda$get$0(java.lang.String);
    Code:
       0: new           #67                 // class java/util/LinkedList
       3: dup
       4: invokespecial #68                 // Method java/util/LinkedList."<init>":()V
       7: areturn
}
