Compiled from "RestMethodMetadata.java"
public class org.apache.dubbo.metadata.rest.RestMethodMetadata implements java.io.Serializable {
  private static final long serialVersionUID;

  private org.apache.dubbo.metadata.definition.model.MethodDefinition method;

  private org.apache.dubbo.metadata.rest.RequestMetadata request;

  private java.lang.Integer urlIndex;

  private java.lang.Integer bodyIndex;

  private java.lang.Integer headerMapIndex;

  private java.lang.String bodyType;

  private java.util.Map<java.lang.Integer, java.util.Collection<java.lang.String>> indexToName;

  private java.util.List<java.lang.String> formParams;

  private java.util.Map<java.lang.Integer, java.lang.Boolean> indexToEncoded;

  private java.util.List<org.apache.dubbo.metadata.rest.ArgInfo> argInfos;

  private java.lang.reflect.Method reflectMethod;

  private java.lang.Class codeStyle;

  public org.apache.dubbo.metadata.rest.RestMethodMetadata();
    Code:
       0: aload_0
       1: invokespecial #1                  // Method java/lang/Object."<init>":()V
       4: return

  public org.apache.dubbo.metadata.definition.model.MethodDefinition getMethod();
    Code:
       0: aload_0
       1: getfield      #2                  // Field method:Lorg/apache/dubbo/metadata/definition/model/MethodDefinition;
       4: ifnonnull     18
       7: aload_0
       8: new           #3                  // class org/apache/dubbo/metadata/definition/model/MethodDefinition
      11: dup
      12: invokespecial #4                  // Method org/apache/dubbo/metadata/definition/model/MethodDefinition."<init>":()V
      15: putfield      #2                  // Field method:Lorg/apache/dubbo/metadata/definition/model/MethodDefinition;
      18: aload_0
      19: getfield      #2                  // Field method:Lorg/apache/dubbo/metadata/definition/model/MethodDefinition;
      22: areturn

  public void setMethod(org.apache.dubbo.metadata.definition.model.MethodDefinition);
    Code:
       0: aload_0
       1: aload_1
       2: putfield      #2                  // Field method:Lorg/apache/dubbo/metadata/definition/model/MethodDefinition;
       5: return

  public org.apache.dubbo.metadata.rest.RequestMetadata getRequest();
    Code:
       0: aload_0
       1: getfield      #5                  // Field request:Lorg/apache/dubbo/metadata/rest/RequestMetadata;
       4: ifnonnull     18
       7: aload_0
       8: new           #6                  // class org/apache/dubbo/metadata/rest/RequestMetadata
      11: dup
      12: invokespecial #7                  // Method org/apache/dubbo/metadata/rest/RequestMetadata."<init>":()V
      15: putfield      #5                  // Field request:Lorg/apache/dubbo/metadata/rest/RequestMetadata;
      18: aload_0
      19: getfield      #5                  // Field request:Lorg/apache/dubbo/metadata/rest/RequestMetadata;
      22: areturn

  public void setRequest(org.apache.dubbo.metadata.rest.RequestMetadata);
    Code:
       0: aload_0
       1: aload_1
       2: putfield      #5                  // Field request:Lorg/apache/dubbo/metadata/rest/RequestMetadata;
       5: return

  public java.lang.Integer getUrlIndex();
    Code:
       0: aload_0
       1: getfield      #8                  // Field urlIndex:Ljava/lang/Integer;
       4: areturn

  public void setUrlIndex(java.lang.Integer);
    Code:
       0: aload_0
       1: aload_1
       2: putfield      #8                  // Field urlIndex:Ljava/lang/Integer;
       5: return

  public java.lang.Integer getBodyIndex();
    Code:
       0: aload_0
       1: getfield      #9                  // Field bodyIndex:Ljava/lang/Integer;
       4: areturn

  public void setBodyIndex(java.lang.Integer);
    Code:
       0: aload_0
       1: aload_1
       2: putfield      #9                  // Field bodyIndex:Ljava/lang/Integer;
       5: return

  public java.lang.Integer getHeaderMapIndex();
    Code:
       0: aload_0
       1: getfield      #10                 // Field headerMapIndex:Ljava/lang/Integer;
       4: areturn

  public void setHeaderMapIndex(java.lang.Integer);
    Code:
       0: aload_0
       1: aload_1
       2: putfield      #10                 // Field headerMapIndex:Ljava/lang/Integer;
       5: return

  public java.lang.String getBodyType();
    Code:
       0: aload_0
       1: getfield      #11                 // Field bodyType:Ljava/lang/String;
       4: areturn

  public void setBodyType(java.lang.String);
    Code:
       0: aload_0
       1: aload_1
       2: putfield      #11                 // Field bodyType:Ljava/lang/String;
       5: return

  public java.util.Map<java.lang.Integer, java.util.Collection<java.lang.String>> getIndexToName();
    Code:
       0: aload_0
       1: getfield      #12                 // Field indexToName:Ljava/util/Map;
       4: ifnonnull     18
       7: aload_0
       8: new           #13                 // class java/util/LinkedHashMap
      11: dup
      12: invokespecial #14                 // Method java/util/LinkedHashMap."<init>":()V
      15: putfield      #12                 // Field indexToName:Ljava/util/Map;
      18: aload_0
      19: getfield      #12                 // Field indexToName:Ljava/util/Map;
      22: areturn

  public void setIndexToName(java.util.Map<java.lang.Integer, java.util.Collection<java.lang.String>>);
    Code:
       0: aload_0
       1: aload_1
       2: putfield      #12                 // Field indexToName:Ljava/util/Map;
       5: return

  public void addIndexToName(java.lang.Integer, java.lang.String);
    Code:
       0: aload_1
       1: ifnonnull     5
       4: return
       5: aload_2
       6: ldc           #15                 // String arg
       8: invokevirtual #16                 // Method java/lang/String.startsWith:(Ljava/lang/String;)Z
      11: ifeq          26
      14: aload_2
      15: aload_1
      16: invokevirtual #17                 // Method java/lang/Integer.toString:()Ljava/lang/String;
      19: invokevirtual #18                 // Method java/lang/String.endsWith:(Ljava/lang/String;)Z
      22: ifeq          26
      25: return
      26: aload_0
      27: invokevirtual #19                 // Method getIndexToName:()Ljava/util/Map;
      30: astore_3
      31: aload_3
      32: aload_1
      33: invokedynamic #20,  0             // InvokeDynamic #0:apply:()Ljava/util/function/Function;
      38: invokeinterface #21,  3           // InterfaceMethod java/util/Map.computeIfAbsent:(Ljava/lang/Object;Ljava/util/function/Function;)Ljava/lang/Object;
      43: checkcast     #22                 // class java/util/Collection
      46: astore        4
      48: aload         4
      50: aload_2
      51: invokeinterface #23,  2           // InterfaceMethod java/util/Collection.add:(Ljava/lang/Object;)Z
      56: pop
      57: return

  public boolean hasIndexedName(java.lang.Integer, java.lang.String);
    Code:
       0: aload_0
       1: invokevirtual #19                 // Method getIndexToName:()Ljava/util/Map;
       4: astore_3
       5: aload_3
       6: aload_1
       7: invokestatic  #24                 // Method java/util/Collections.emptyList:()Ljava/util/List;
      10: invokeinterface #25,  3           // InterfaceMethod java/util/Map.getOrDefault:(Ljava/lang/Object;Ljava/lang/Object;)Ljava/lang/Object;
      15: checkcast     #22                 // class java/util/Collection
      18: aload_2
      19: invokeinterface #26,  2           // InterfaceMethod java/util/Collection.contains:(Ljava/lang/Object;)Z
      24: ireturn

  public java.util.List<java.lang.String> getFormParams();
    Code:
       0: aload_0
       1: getfield      #27                 // Field formParams:Ljava/util/List;
       4: areturn

  public void setFormParams(java.util.List<java.lang.String>);
    Code:
       0: aload_0
       1: aload_1
       2: putfield      #27                 // Field formParams:Ljava/util/List;
       5: return

  public java.util.Map<java.lang.Integer, java.lang.Boolean> getIndexToEncoded();
    Code:
       0: aload_0
       1: getfield      #28                 // Field indexToEncoded:Ljava/util/Map;
       4: areturn

  public void setIndexToEncoded(java.util.Map<java.lang.Integer, java.lang.Boolean>);
    Code:
       0: aload_0
       1: aload_1
       2: putfield      #28                 // Field indexToEncoded:Ljava/util/Map;
       5: return

  public java.util.List<org.apache.dubbo.metadata.rest.ArgInfo> getArgInfos();
    Code:
       0: aload_0
       1: getfield      #29                 // Field argInfos:Ljava/util/List;
       4: ifnonnull     18
       7: aload_0
       8: new           #30                 // class java/util/ArrayList
      11: dup
      12: invokespecial #31                 // Method java/util/ArrayList."<init>":()V
      15: putfield      #29                 // Field argInfos:Ljava/util/List;
      18: aload_0
      19: getfield      #29                 // Field argInfos:Ljava/util/List;
      22: areturn

  public void addArgInfo(org.apache.dubbo.metadata.rest.ArgInfo);
    Code:
       0: aload_0
       1: invokevirtual #32                 // Method getArgInfos:()Ljava/util/List;
       4: aload_1
       5: invokeinterface #33,  2           // InterfaceMethod java/util/List.add:(Ljava/lang/Object;)Z
      10: pop
      11: return

  public java.lang.reflect.Method getReflectMethod();
    Code:
       0: aload_0
       1: getfield      #34                 // Field reflectMethod:Ljava/lang/reflect/Method;
       4: areturn

  public void setReflectMethod(java.lang.reflect.Method);
    Code:
       0: aload_0
       1: aload_1
       2: putfield      #34                 // Field reflectMethod:Ljava/lang/reflect/Method;
       5: return

  public java.lang.Class getCodeStyle();
    Code:
       0: aload_0
       1: getfield      #35                 // Field codeStyle:Ljava/lang/Class;
       4: areturn

  public void setCodeStyle(java.lang.Class);
    Code:
       0: aload_0
       1: aload_1
       2: putfield      #35                 // Field codeStyle:Ljava/lang/Class;
       5: return

  public boolean equals(java.lang.Object);
    Code:
       0: aload_0
       1: aload_1
       2: if_acmpne     7
       5: iconst_1
       6: ireturn
       7: aload_1
       8: instanceof    #36                 // class org/apache/dubbo/metadata/rest/RestMethodMetadata
      11: ifne          16
      14: iconst_0
      15: ireturn
      16: aload_1
      17: checkcast     #36                 // class org/apache/dubbo/metadata/rest/RestMethodMetadata
      20: astore_2
      21: aload_0
      22: invokevirtual #37                 // Method getMethod:()Lorg/apache/dubbo/metadata/definition/model/MethodDefinition;
      25: aload_2
      26: invokevirtual #37                 // Method getMethod:()Lorg/apache/dubbo/metadata/definition/model/MethodDefinition;
      29: invokestatic  #38                 // Method java/util/Objects.equals:(Ljava/lang/Object;Ljava/lang/Object;)Z
      32: ifeq          137
      35: aload_0
      36: invokevirtual #39                 // Method getRequest:()Lorg/apache/dubbo/metadata/rest/RequestMetadata;
      39: aload_2
      40: invokevirtual #39                 // Method getRequest:()Lorg/apache/dubbo/metadata/rest/RequestMetadata;
      43: invokestatic  #38                 // Method java/util/Objects.equals:(Ljava/lang/Object;Ljava/lang/Object;)Z
      46: ifeq          137
      49: aload_0
      50: invokevirtual #40                 // Method getUrlIndex:()Ljava/lang/Integer;
      53: aload_2
      54: invokevirtual #40                 // Method getUrlIndex:()Ljava/lang/Integer;
      57: invokestatic  #38                 // Method java/util/Objects.equals:(Ljava/lang/Object;Ljava/lang/Object;)Z
      60: ifeq          137
      63: aload_0
      64: invokevirtual #41                 // Method getBodyIndex:()Ljava/lang/Integer;
      67: aload_2
      68: invokevirtual #41                 // Method getBodyIndex:()Ljava/lang/Integer;
      71: invokestatic  #38                 // Method java/util/Objects.equals:(Ljava/lang/Object;Ljava/lang/Object;)Z
      74: ifeq          137
      77: aload_0
      78: invokevirtual #42                 // Method getHeaderMapIndex:()Ljava/lang/Integer;
      81: aload_2
      82: invokevirtual #42                 // Method getHeaderMapIndex:()Ljava/lang/Integer;
      85: invokestatic  #38                 // Method java/util/Objects.equals:(Ljava/lang/Object;Ljava/lang/Object;)Z
      88: ifeq          137
      91: aload_0
      92: invokevirtual #43                 // Method getBodyType:()Ljava/lang/String;
      95: aload_2
      96: invokevirtual #43                 // Method getBodyType:()Ljava/lang/String;
      99: invokestatic  #38                 // Method java/util/Objects.equals:(Ljava/lang/Object;Ljava/lang/Object;)Z
     102: ifeq          137
     105: aload_0
     106: invokevirtual #44                 // Method getFormParams:()Ljava/util/List;
     109: aload_2
     110: invokevirtual #44                 // Method getFormParams:()Ljava/util/List;
     113: invokestatic  #38                 // Method java/util/Objects.equals:(Ljava/lang/Object;Ljava/lang/Object;)Z
     116: ifeq          137
     119: aload_0
     120: invokevirtual #45                 // Method getIndexToEncoded:()Ljava/util/Map;
     123: aload_2
     124: invokevirtual #45                 // Method getIndexToEncoded:()Ljava/util/Map;
     127: invokestatic  #38                 // Method java/util/Objects.equals:(Ljava/lang/Object;Ljava/lang/Object;)Z
     130: ifeq          137
     133: iconst_1
     134: goto          138
     137: iconst_0
     138: ireturn

  public int hashCode();
    Code:
       0: bipush        8
       2: anewarray     #46                 // class java/lang/Object
       5: dup
       6: iconst_0
       7: aload_0
       8: invokevirtual #37                 // Method getMethod:()Lorg/apache/dubbo/metadata/definition/model/MethodDefinition;
      11: aastore
      12: dup
      13: iconst_1
      14: aload_0
      15: invokevirtual #39                 // Method getRequest:()Lorg/apache/dubbo/metadata/rest/RequestMetadata;
      18: aastore
      19: dup
      20: iconst_2
      21: aload_0
      22: invokevirtual #40                 // Method getUrlIndex:()Ljava/lang/Integer;
      25: aastore
      26: dup
      27: iconst_3
      28: aload_0
      29: invokevirtual #41                 // Method getBodyIndex:()Ljava/lang/Integer;
      32: aastore
      33: dup
      34: iconst_4
      35: aload_0
      36: invokevirtual #42                 // Method getHeaderMapIndex:()Ljava/lang/Integer;
      39: aastore
      40: dup
      41: iconst_5
      42: aload_0
      43: invokevirtual #43                 // Method getBodyType:()Ljava/lang/String;
      46: aastore
      47: dup
      48: bipush        6
      50: aload_0
      51: invokevirtual #44                 // Method getFormParams:()Ljava/util/List;
      54: aastore
      55: dup
      56: bipush        7
      58: aload_0
      59: invokevirtual #45                 // Method getIndexToEncoded:()Ljava/util/Map;
      62: aastore
      63: invokestatic  #47                 // Method java/util/Objects.hash:([Ljava/lang/Object;)I
      66: ireturn

  public java.lang.String toString();
    Code:
       0: new           #48                 // class java/lang/StringBuilder
       3: dup
       4: invokespecial #49                 // Method java/lang/StringBuilder."<init>":()V
       7: ldc           #50                 // String RestMethodMetadata{method=
       9: invokevirtual #51                 // Method java/lang/StringBuilder.append:(Ljava/lang/String;)Ljava/lang/StringBuilder;
      12: aload_0
      13: getfield      #2                  // Field method:Lorg/apache/dubbo/metadata/definition/model/MethodDefinition;
      16: invokevirtual #52                 // Method java/lang/StringBuilder.append:(Ljava/lang/Object;)Ljava/lang/StringBuilder;
      19: ldc           #53                 // String , request=
      21: invokevirtual #51                 // Method java/lang/StringBuilder.append:(Ljava/lang/String;)Ljava/lang/StringBuilder;
      24: aload_0
      25: getfield      #5                  // Field request:Lorg/apache/dubbo/metadata/rest/RequestMetadata;
      28: invokevirtual #52                 // Method java/lang/StringBuilder.append:(Ljava/lang/Object;)Ljava/lang/StringBuilder;
      31: ldc           #54                 // String , urlIndex=
      33: invokevirtual #51                 // Method java/lang/StringBuilder.append:(Ljava/lang/String;)Ljava/lang/StringBuilder;
      36: aload_0
      37: getfield      #8                  // Field urlIndex:Ljava/lang/Integer;
      40: invokevirtual #52                 // Method java/lang/StringBuilder.append:(Ljava/lang/Object;)Ljava/lang/StringBuilder;
      43: ldc           #55                 // String , bodyIndex=
      45: invokevirtual #51                 // Method java/lang/StringBuilder.append:(Ljava/lang/String;)Ljava/lang/StringBuilder;
      48: aload_0
      49: getfield      #9                  // Field bodyIndex:Ljava/lang/Integer;
      52: invokevirtual #52                 // Method java/lang/StringBuilder.append:(Ljava/lang/Object;)Ljava/lang/StringBuilder;
      55: ldc           #56                 // String , headerMapIndex=
      57: invokevirtual #51                 // Method java/lang/StringBuilder.append:(Ljava/lang/String;)Ljava/lang/StringBuilder;
      60: aload_0
      61: getfield      #10                 // Field headerMapIndex:Ljava/lang/Integer;
      64: invokevirtual #52                 // Method java/lang/StringBuilder.append:(Ljava/lang/Object;)Ljava/lang/StringBuilder;
      67: ldc           #57                 // String , bodyType=\'
      69: invokevirtual #51                 // Method java/lang/StringBuilder.append:(Ljava/lang/String;)Ljava/lang/StringBuilder;
      72: aload_0
      73: getfield      #11                 // Field bodyType:Ljava/lang/String;
      76: invokevirtual #51                 // Method java/lang/StringBuilder.append:(Ljava/lang/String;)Ljava/lang/StringBuilder;
      79: bipush        39
      81: invokevirtual #58                 // Method java/lang/StringBuilder.append:(C)Ljava/lang/StringBuilder;
      84: ldc           #59                 // String , indexToName=
      86: invokevirtual #51                 // Method java/lang/StringBuilder.append:(Ljava/lang/String;)Ljava/lang/StringBuilder;
      89: aload_0
      90: getfield      #12                 // Field indexToName:Ljava/util/Map;
      93: invokevirtual #52                 // Method java/lang/StringBuilder.append:(Ljava/lang/Object;)Ljava/lang/StringBuilder;
      96: ldc           #60                 // String , formParams=
      98: invokevirtual #51                 // Method java/lang/StringBuilder.append:(Ljava/lang/String;)Ljava/lang/StringBuilder;
     101: aload_0
     102: getfield      #27                 // Field formParams:Ljava/util/List;
     105: invokevirtual #52                 // Method java/lang/StringBuilder.append:(Ljava/lang/Object;)Ljava/lang/StringBuilder;
     108: ldc           #61                 // String , indexToEncoded=
     110: invokevirtual #51                 // Method java/lang/StringBuilder.append:(Ljava/lang/String;)Ljava/lang/StringBuilder;
     113: aload_0
     114: getfield      #28                 // Field indexToEncoded:Ljava/util/Map;
     117: invokevirtual #52                 // Method java/lang/StringBuilder.append:(Ljava/lang/Object;)Ljava/lang/StringBuilder;
     120: ldc           #62                 // String , argInfos=
     122: invokevirtual #51                 // Method java/lang/StringBuilder.append:(Ljava/lang/String;)Ljava/lang/StringBuilder;
     125: aload_0
     126: getfield      #29                 // Field argInfos:Ljava/util/List;
     129: invokevirtual #52                 // Method java/lang/StringBuilder.append:(Ljava/lang/Object;)Ljava/lang/StringBuilder;
     132: ldc           #63                 // String , reflectMethod=
     134: invokevirtual #51                 // Method java/lang/StringBuilder.append:(Ljava/lang/String;)Ljava/lang/StringBuilder;
     137: aload_0
     138: getfield      #34                 // Field reflectMethod:Ljava/lang/reflect/Method;
     141: invokevirtual #52                 // Method java/lang/StringBuilder.append:(Ljava/lang/Object;)Ljava/lang/StringBuilder;
     144: ldc           #64                 // String , codeStyle=
     146: invokevirtual #51                 // Method java/lang/StringBuilder.append:(Ljava/lang/String;)Ljava/lang/StringBuilder;
     149: aload_0
     150: getfield      #35                 // Field codeStyle:Ljava/lang/Class;
     153: invokevirtual #52                 // Method java/lang/StringBuilder.append:(Ljava/lang/Object;)Ljava/lang/StringBuilder;
     156: bipush        125
     158: invokevirtual #58                 // Method java/lang/StringBuilder.append:(C)Ljava/lang/StringBuilder;
     161: invokevirtual #65                 // Method java/lang/StringBuilder.toString:()Ljava/lang/String;
     164: areturn

  private static java.util.Collection lambda$addIndexToName$0(java.lang.Integer);
    Code:
       0: new           #30                 // class java/util/ArrayList
       3: dup
       4: iconst_1
       5: invokespecial #66                 // Method java/util/ArrayList."<init>":(I)V
       8: areturn
}
