Compiled from "ServiceRestMetadata.java"
public class org.apache.dubbo.metadata.rest.ServiceRestMetadata implements java.io.Serializable {
  private static final long serialVersionUID;

  private java.lang.String serviceInterface;

  private java.lang.String version;

  private java.lang.String group;

  private java.util.Set<org.apache.dubbo.metadata.rest.RestMethodMetadata> meta;

  private java.lang.Integer port;

  private boolean consumer;

  private java.lang.String contextPathFromUrl;

  private java.lang.Class codeStyle;

  private java.util.Map<org.apache.dubbo.metadata.rest.PathMatcher, org.apache.dubbo.metadata.rest.RestMethodMetadata> pathToServiceMapContainPathVariable;

  private java.util.Map<org.apache.dubbo.metadata.rest.PathMatcher, org.apache.dubbo.metadata.rest.RestMethodMetadata> pathToServiceMapUnContainPathVariable;

  private java.util.Map<java.lang.String, java.util.Map<org.apache.dubbo.metadata.ParameterTypesComparator, org.apache.dubbo.metadata.rest.RestMethodMetadata>> methodToServiceMap;

  public org.apache.dubbo.metadata.rest.ServiceRestMetadata(java.lang.String, java.lang.String, java.lang.String, boolean);
    Code:
       0: aload_0
       1: invokespecial #1                  // Method java/lang/Object."<init>":()V
       4: aload_0
       5: new           #2                  // class java/util/HashMap
       8: dup
       9: invokespecial #3                  // Method java/util/HashMap."<init>":()V
      12: putfield      #4                  // Field pathToServiceMapContainPathVariable:Ljava/util/Map;
      15: aload_0
      16: new           #2                  // class java/util/HashMap
      19: dup
      20: invokespecial #3                  // Method java/util/HashMap."<init>":()V
      23: putfield      #5                  // Field pathToServiceMapUnContainPathVariable:Ljava/util/Map;
      26: aload_0
      27: new           #2                  // class java/util/HashMap
      30: dup
      31: invokespecial #3                  // Method java/util/HashMap."<init>":()V
      34: putfield      #6                  // Field methodToServiceMap:Ljava/util/Map;
      37: aload_0
      38: aload_1
      39: putfield      #7                  // Field serviceInterface:Ljava/lang/String;
      42: aload_0
      43: aload_2
      44: putfield      #8                  // Field version:Ljava/lang/String;
      47: aload_0
      48: aload_3
      49: putfield      #9                  // Field group:Ljava/lang/String;
      52: aload_0
      53: iload         4
      55: putfield      #10                 // Field consumer:Z
      58: return

  public org.apache.dubbo.metadata.rest.ServiceRestMetadata();
    Code:
       0: aload_0
       1: invokespecial #1                  // Method java/lang/Object."<init>":()V
       4: aload_0
       5: new           #2                  // class java/util/HashMap
       8: dup
       9: invokespecial #3                  // Method java/util/HashMap."<init>":()V
      12: putfield      #4                  // Field pathToServiceMapContainPathVariable:Ljava/util/Map;
      15: aload_0
      16: new           #2                  // class java/util/HashMap
      19: dup
      20: invokespecial #3                  // Method java/util/HashMap."<init>":()V
      23: putfield      #5                  // Field pathToServiceMapUnContainPathVariable:Ljava/util/Map;
      26: aload_0
      27: new           #2                  // class java/util/HashMap
      30: dup
      31: invokespecial #3                  // Method java/util/HashMap."<init>":()V
      34: putfield      #6                  // Field methodToServiceMap:Ljava/util/Map;
      37: return

  public org.apache.dubbo.metadata.rest.ServiceRestMetadata(java.lang.String, java.lang.String, java.lang.String);
    Code:
       0: aload_0
       1: aload_1
       2: aload_2
       3: aload_3
       4: iconst_0
       5: invokespecial #11                 // Method "<init>":(Ljava/lang/String;Ljava/lang/String;Ljava/lang/String;Z)V
       8: return

  public java.lang.String getServiceInterface();
    Code:
       0: aload_0
       1: getfield      #7                  // Field serviceInterface:Ljava/lang/String;
       4: areturn

  public void setServiceInterface(java.lang.String);
    Code:
       0: aload_0
       1: aload_1
       2: putfield      #7                  // Field serviceInterface:Ljava/lang/String;
       5: return

  public java.lang.String getVersion();
    Code:
       0: aload_0
       1: getfield      #8                  // Field version:Ljava/lang/String;
       4: areturn

  public void setVersion(java.lang.String);
    Code:
       0: aload_0
       1: aload_1
       2: putfield      #8                  // Field version:Ljava/lang/String;
       5: return

  public java.lang.String getGroup();
    Code:
       0: aload_0
       1: getfield      #9                  // Field group:Ljava/lang/String;
       4: areturn

  public void setGroup(java.lang.String);
    Code:
       0: aload_0
       1: aload_1
       2: putfield      #9                  // Field group:Ljava/lang/String;
       5: return

  public java.util.Set<org.apache.dubbo.metadata.rest.RestMethodMetadata> getMeta();
    Code:
       0: aload_0
       1: getfield      #12                 // Field meta:Ljava/util/Set;
       4: ifnonnull     18
       7: aload_0
       8: new           #13                 // class java/util/LinkedHashSet
      11: dup
      12: invokespecial #14                 // Method java/util/LinkedHashSet."<init>":()V
      15: putfield      #12                 // Field meta:Ljava/util/Set;
      18: aload_0
      19: getfield      #12                 // Field meta:Ljava/util/Set;
      22: areturn

  public void setMeta(java.util.Set<org.apache.dubbo.metadata.rest.RestMethodMetadata>);
    Code:
       0: aload_0
       1: aload_1
       2: putfield      #12                 // Field meta:Ljava/util/Set;
       5: return

  public void addRestMethodMetadata(org.apache.dubbo.metadata.rest.RestMethodMetadata);
    Code:
       0: new           #15                 // class org/apache/dubbo/metadata/rest/PathMatcher
       3: dup
       4: aload_1
       5: invokevirtual #16                 // Method org/apache/dubbo/metadata/rest/RestMethodMetadata.getRequest:()Lorg/apache/dubbo/metadata/rest/RequestMetadata;
       8: invokevirtual #17                 // Method org/apache/dubbo/metadata/rest/RequestMetadata.getPath:()Ljava/lang/String;
      11: aload_0
      12: invokevirtual #18                 // Method getVersion:()Ljava/lang/String;
      15: aload_0
      16: invokevirtual #19                 // Method getGroup:()Ljava/lang/String;
      19: aload_0
      20: invokevirtual #20                 // Method getPort:()Ljava/lang/Integer;
      23: aload_1
      24: invokevirtual #16                 // Method org/apache/dubbo/metadata/rest/RestMethodMetadata.getRequest:()Lorg/apache/dubbo/metadata/rest/RequestMetadata;
      27: invokevirtual #21                 // Method org/apache/dubbo/metadata/rest/RequestMetadata.getMethod:()Ljava/lang/String;
      30: invokespecial #22                 // Method org/apache/dubbo/metadata/rest/PathMatcher."<init>":(Ljava/lang/String;Ljava/lang/String;Ljava/lang/String;Ljava/lang/Integer;Ljava/lang/String;)V
      33: astore_2
      34: aload_0
      35: aload_2
      36: aload_1
      37: invokevirtual #23                 // Method addPathToServiceMap:(Lorg/apache/dubbo/metadata/rest/PathMatcher;Lorg/apache/dubbo/metadata/rest/RestMethodMetadata;)V
      40: aload_0
      41: aload_1
      42: invokevirtual #24                 // Method addMethodToServiceMap:(Lorg/apache/dubbo/metadata/rest/RestMethodMetadata;)V
      45: aload_0
      46: invokevirtual #25                 // Method getMeta:()Ljava/util/Set;
      49: aload_1
      50: invokeinterface #26,  2           // InterfaceMethod java/util/Set.add:(Ljava/lang/Object;)Z
      55: pop
      56: return

  public java.util.Map<org.apache.dubbo.metadata.rest.PathMatcher, org.apache.dubbo.metadata.rest.RestMethodMetadata> getPathContainPathVariableToServiceMap();
    Code:
       0: aload_0
       1: getfield      #4                  // Field pathToServiceMapContainPathVariable:Ljava/util/Map;
       4: areturn

  public java.util.Map<org.apache.dubbo.metadata.rest.PathMatcher, org.apache.dubbo.metadata.rest.RestMethodMetadata> getPathUnContainPathVariableToServiceMap();
    Code:
       0: aload_0
       1: getfield      #5                  // Field pathToServiceMapUnContainPathVariable:Ljava/util/Map;
       4: areturn

  public void addPathToServiceMap(org.apache.dubbo.metadata.rest.PathMatcher, org.apache.dubbo.metadata.rest.RestMethodMetadata);
    Code:
       0: aload_1
       1: invokevirtual #27                 // Method org/apache/dubbo/metadata/rest/PathMatcher.hasPathVariable:()Z
       4: ifeq          21
       7: aload_0
       8: aload_0
       9: getfield      #4                  // Field pathToServiceMapContainPathVariable:Ljava/util/Map;
      12: aload_1
      13: aload_2
      14: iconst_1
      15: invokespecial #28                 // Method doublePathCheck:(Ljava/util/Map;Lorg/apache/dubbo/metadata/rest/PathMatcher;Lorg/apache/dubbo/metadata/rest/RestMethodMetadata;Z)V
      18: goto          32
      21: aload_0
      22: aload_0
      23: getfield      #5                  // Field pathToServiceMapUnContainPathVariable:Ljava/util/Map;
      26: aload_1
      27: aload_2
      28: iconst_0
      29: invokespecial #28                 // Method doublePathCheck:(Ljava/util/Map;Lorg/apache/dubbo/metadata/rest/PathMatcher;Lorg/apache/dubbo/metadata/rest/RestMethodMetadata;Z)V
      32: return

  private void doublePathCheck(java.util.Map<org.apache.dubbo.metadata.rest.PathMatcher, org.apache.dubbo.metadata.rest.RestMethodMetadata>, org.apache.dubbo.metadata.rest.PathMatcher, org.apache.dubbo.metadata.rest.RestMethodMetadata, boolean);
    Code:
       0: aload_1
       1: aload_2
       2: invokeinterface #29,  2           // InterfaceMethod java/util/Map.containsKey:(Ljava/lang/Object;)Z
       7: ifeq          87
      10: iload         4
      12: ifeq          51
      15: new           #30                 // class java/lang/IllegalArgumentException
      18: dup
      19: new           #31                 // class java/lang/StringBuilder
      22: dup
      23: invokespecial #32                 // Method java/lang/StringBuilder."<init>":()V
      26: ldc           #33                 // String dubbo rest metadata resolve double path error,and contain path variable  is:
      28: invokevirtual #34                 // Method java/lang/StringBuilder.append:(Ljava/lang/String;)Ljava/lang/StringBuilder;
      31: aload_2
      32: invokevirtual #35                 // Method java/lang/StringBuilder.append:(Ljava/lang/Object;)Ljava/lang/StringBuilder;
      35: ldc           #36                 // String , rest method metadata is:
      37: invokevirtual #34                 // Method java/lang/StringBuilder.append:(Ljava/lang/String;)Ljava/lang/StringBuilder;
      40: aload_3
      41: invokevirtual #35                 // Method java/lang/StringBuilder.append:(Ljava/lang/Object;)Ljava/lang/StringBuilder;
      44: invokevirtual #37                 // Method java/lang/StringBuilder.toString:()Ljava/lang/String;
      47: invokespecial #38                 // Method java/lang/IllegalArgumentException."<init>":(Ljava/lang/String;)V
      50: athrow
      51: new           #30                 // class java/lang/IllegalArgumentException
      54: dup
      55: new           #31                 // class java/lang/StringBuilder
      58: dup
      59: invokespecial #32                 // Method java/lang/StringBuilder."<init>":()V
      62: ldc           #39                 // String dubbo rest metadata resolve double path error,and do not  contain path variable  is:
      64: invokevirtual #34                 // Method java/lang/StringBuilder.append:(Ljava/lang/String;)Ljava/lang/StringBuilder;
      67: aload_2
      68: invokevirtual #35                 // Method java/lang/StringBuilder.append:(Ljava/lang/Object;)Ljava/lang/StringBuilder;
      71: ldc           #36                 // String , rest method metadata is:
      73: invokevirtual #34                 // Method java/lang/StringBuilder.append:(Ljava/lang/String;)Ljava/lang/StringBuilder;
      76: aload_3
      77: invokevirtual #35                 // Method java/lang/StringBuilder.append:(Ljava/lang/Object;)Ljava/lang/StringBuilder;
      80: invokevirtual #37                 // Method java/lang/StringBuilder.toString:()Ljava/lang/String;
      83: invokespecial #38                 // Method java/lang/IllegalArgumentException."<init>":(Ljava/lang/String;)V
      86: athrow
      87: aload_1
      88: aload_2
      89: aload_3
      90: invokeinterface #40,  3           // InterfaceMethod java/util/Map.put:(Ljava/lang/Object;Ljava/lang/Object;)Ljava/lang/Object;
      95: pop
      96: return

  public java.lang.Integer getPort();
    Code:
       0: aload_0
       1: getfield      #41                 // Field port:Ljava/lang/Integer;
       4: areturn

  public void setPort(java.lang.Integer);
    Code:
       0: aload_0
       1: aload_1
       2: putfield      #41                 // Field port:Ljava/lang/Integer;
       5: aload_0
       6: aload_1
       7: aload_0
       8: invokevirtual #42                 // Method getPathContainPathVariableToServiceMap:()Ljava/util/Map;
      11: invokespecial #43                 // Method setPort:(Ljava/lang/Integer;Ljava/util/Map;)V
      14: aload_0
      15: aload_1
      16: aload_0
      17: invokevirtual #44                 // Method getPathUnContainPathVariableToServiceMap:()Ljava/util/Map;
      20: invokespecial #43                 // Method setPort:(Ljava/lang/Integer;Ljava/util/Map;)V
      23: return

  private void setPort(java.lang.Integer, java.util.Map<org.apache.dubbo.metadata.rest.PathMatcher, org.apache.dubbo.metadata.rest.RestMethodMetadata>);
    Code:
       0: aload_2
       1: invokeinterface #45,  1           // InterfaceMethod java/util/Map.keySet:()Ljava/util/Set;
       6: invokeinterface #46,  1           // InterfaceMethod java/util/Set.iterator:()Ljava/util/Iterator;
      11: astore_3
      12: aload_3
      13: invokeinterface #47,  1           // InterfaceMethod java/util/Iterator.hasNext:()Z
      18: ifeq          41
      21: aload_3
      22: invokeinterface #48,  1           // InterfaceMethod java/util/Iterator.next:()Ljava/lang/Object;
      27: checkcast     #15                 // class org/apache/dubbo/metadata/rest/PathMatcher
      30: astore        4
      32: aload         4
      34: aload_1
      35: invokevirtual #49                 // Method org/apache/dubbo/metadata/rest/PathMatcher.setPort:(Ljava/lang/Integer;)V
      38: goto          12
      41: return

  public boolean isConsumer();
    Code:
       0: aload_0
       1: getfield      #10                 // Field consumer:Z
       4: ireturn

  public void setConsumer(boolean);
    Code:
       0: aload_0
       1: iload_1
       2: putfield      #10                 // Field consumer:Z
       5: return

  public java.util.Map<java.lang.String, java.util.Map<org.apache.dubbo.metadata.ParameterTypesComparator, org.apache.dubbo.metadata.rest.RestMethodMetadata>> getMethodToServiceMap();
    Code:
       0: aload_0
       1: getfield      #6                  // Field methodToServiceMap:Ljava/util/Map;
       4: areturn

  public void addMethodToServiceMap(org.apache.dubbo.metadata.rest.RestMethodMetadata);
    Code:
       0: aload_0
       1: getfield      #6                  // Field methodToServiceMap:Ljava/util/Map;
       4: ifnonnull     18
       7: aload_0
       8: new           #2                  // class java/util/HashMap
      11: dup
      12: invokespecial #3                  // Method java/util/HashMap."<init>":()V
      15: putfield      #6                  // Field methodToServiceMap:Ljava/util/Map;
      18: aload_0
      19: getfield      #6                  // Field methodToServiceMap:Ljava/util/Map;
      22: aload_1
      23: invokevirtual #50                 // Method org/apache/dubbo/metadata/rest/RestMethodMetadata.getReflectMethod:()Ljava/lang/reflect/Method;
      26: invokevirtual #51                 // Method java/lang/reflect/Method.getName:()Ljava/lang/String;
      29: invokedynamic #52,  0             // InvokeDynamic #0:apply:()Ljava/util/function/Function;
      34: invokeinterface #53,  3           // InterfaceMethod java/util/Map.computeIfAbsent:(Ljava/lang/Object;Ljava/util/function/Function;)Ljava/lang/Object;
      39: checkcast     #54                 // class java/util/Map
      42: aload_1
      43: invokevirtual #50                 // Method org/apache/dubbo/metadata/rest/RestMethodMetadata.getReflectMethod:()Ljava/lang/reflect/Method;
      46: invokevirtual #55                 // Method java/lang/reflect/Method.getParameterTypes:()[Ljava/lang/Class;
      49: invokestatic  #56                 // Method org/apache/dubbo/metadata/ParameterTypesComparator.getInstance:([Ljava/lang/Class;)Lorg/apache/dubbo/metadata/ParameterTypesComparator;
      52: aload_1
      53: invokeinterface #40,  3           // InterfaceMethod java/util/Map.put:(Ljava/lang/Object;Ljava/lang/Object;)Ljava/lang/Object;
      58: pop
      59: return

  public java.lang.Class getCodeStyle();
    Code:
       0: aload_0
       1: getfield      #57                 // Field codeStyle:Ljava/lang/Class;
       4: areturn

  public void setCodeStyle(java.lang.Class);
    Code:
       0: aload_0
       1: aload_1
       2: putfield      #57                 // Field codeStyle:Ljava/lang/Class;
       5: return

  public java.lang.String getContextPathFromUrl();
    Code:
       0: aload_0
       1: getfield      #58                 // Field contextPathFromUrl:Ljava/lang/String;
       4: ifnonnull     12
       7: ldc           #59                 // String
       9: goto          16
      12: aload_0
      13: getfield      #58                 // Field contextPathFromUrl:Ljava/lang/String;
      16: areturn

  public void setContextPathFromUrl(java.lang.String);
    Code:
       0: aload_0
       1: aload_1
       2: invokestatic  #60                 // InterfaceMethod org/apache/dubbo/common/utils/PathUtils.normalize:(Ljava/lang/String;)Ljava/lang/String;
       5: putfield      #58                 // Field contextPathFromUrl:Ljava/lang/String;
       8: return

  public boolean equals(java.lang.Object);
    Code:
       0: aload_0
       1: aload_1
       2: if_acmpne     7
       5: iconst_1
       6: ireturn
       7: aload_1
       8: instanceof    #61                 // class org/apache/dubbo/metadata/rest/ServiceRestMetadata
      11: ifne          16
      14: iconst_0
      15: ireturn
      16: aload_1
      17: checkcast     #61                 // class org/apache/dubbo/metadata/rest/ServiceRestMetadata
      20: astore_2
      21: aload_0
      22: invokevirtual #62                 // Method getServiceInterface:()Ljava/lang/String;
      25: aload_2
      26: invokevirtual #62                 // Method getServiceInterface:()Ljava/lang/String;
      29: invokestatic  #63                 // Method java/util/Objects.equals:(Ljava/lang/Object;Ljava/lang/Object;)Z
      32: ifeq          95
      35: aload_0
      36: invokevirtual #18                 // Method getVersion:()Ljava/lang/String;
      39: aload_2
      40: invokevirtual #18                 // Method getVersion:()Ljava/lang/String;
      43: invokestatic  #63                 // Method java/util/Objects.equals:(Ljava/lang/Object;Ljava/lang/Object;)Z
      46: ifeq          95
      49: aload_0
      50: invokevirtual #19                 // Method getGroup:()Ljava/lang/String;
      53: aload_2
      54: invokevirtual #19                 // Method getGroup:()Ljava/lang/String;
      57: invokestatic  #63                 // Method java/util/Objects.equals:(Ljava/lang/Object;Ljava/lang/Object;)Z
      60: ifeq          95
      63: aload_0
      64: invokevirtual #25                 // Method getMeta:()Ljava/util/Set;
      67: aload_2
      68: invokevirtual #25                 // Method getMeta:()Ljava/util/Set;
      71: invokestatic  #63                 // Method java/util/Objects.equals:(Ljava/lang/Object;Ljava/lang/Object;)Z
      74: ifeq          95
      77: aload_0
      78: invokevirtual #20                 // Method getPort:()Ljava/lang/Integer;
      81: aload_2
      82: invokevirtual #20                 // Method getPort:()Ljava/lang/Integer;
      85: invokestatic  #63                 // Method java/util/Objects.equals:(Ljava/lang/Object;Ljava/lang/Object;)Z
      88: ifeq          95
      91: iconst_1
      92: goto          96
      95: iconst_0
      96: ireturn

  public int hashCode();
    Code:
       0: iconst_5
       1: anewarray     #64                 // class java/lang/Object
       4: dup
       5: iconst_0
       6: aload_0
       7: invokevirtual #62                 // Method getServiceInterface:()Ljava/lang/String;
      10: aastore
      11: dup
      12: iconst_1
      13: aload_0
      14: invokevirtual #18                 // Method getVersion:()Ljava/lang/String;
      17: aastore
      18: dup
      19: iconst_2
      20: aload_0
      21: invokevirtual #19                 // Method getGroup:()Ljava/lang/String;
      24: aastore
      25: dup
      26: iconst_3
      27: aload_0
      28: invokevirtual #25                 // Method getMeta:()Ljava/util/Set;
      31: aastore
      32: dup
      33: iconst_4
      34: aload_0
      35: invokevirtual #20                 // Method getPort:()Ljava/lang/Integer;
      38: aastore
      39: invokestatic  #65                 // Method java/util/Objects.hash:([Ljava/lang/Object;)I
      42: ireturn

  public java.lang.String toString();
    Code:
       0: new           #31                 // class java/lang/StringBuilder
       3: dup
       4: ldc           #66                 // String ServiceRestMetadata{
       6: invokespecial #67                 // Method java/lang/StringBuilder."<init>":(Ljava/lang/String;)V
       9: astore_1
      10: aload_1
      11: ldc           #68                 // String serviceInterface=\'
      13: invokevirtual #34                 // Method java/lang/StringBuilder.append:(Ljava/lang/String;)Ljava/lang/StringBuilder;
      16: aload_0
      17: getfield      #7                  // Field serviceInterface:Ljava/lang/String;
      20: invokevirtual #34                 // Method java/lang/StringBuilder.append:(Ljava/lang/String;)Ljava/lang/StringBuilder;
      23: bipush        39
      25: invokevirtual #69                 // Method java/lang/StringBuilder.append:(C)Ljava/lang/StringBuilder;
      28: pop
      29: aload_1
      30: ldc           #70                 // String , version=\'
      32: invokevirtual #34                 // Method java/lang/StringBuilder.append:(Ljava/lang/String;)Ljava/lang/StringBuilder;
      35: aload_0
      36: getfield      #8                  // Field version:Ljava/lang/String;
      39: invokevirtual #34                 // Method java/lang/StringBuilder.append:(Ljava/lang/String;)Ljava/lang/StringBuilder;
      42: bipush        39
      44: invokevirtual #69                 // Method java/lang/StringBuilder.append:(C)Ljava/lang/StringBuilder;
      47: pop
      48: aload_1
      49: ldc           #71                 // String , group=\'
      51: invokevirtual #34                 // Method java/lang/StringBuilder.append:(Ljava/lang/String;)Ljava/lang/StringBuilder;
      54: aload_0
      55: getfield      #9                  // Field group:Ljava/lang/String;
      58: invokevirtual #34                 // Method java/lang/StringBuilder.append:(Ljava/lang/String;)Ljava/lang/StringBuilder;
      61: bipush        39
      63: invokevirtual #69                 // Method java/lang/StringBuilder.append:(C)Ljava/lang/StringBuilder;
      66: pop
      67: aload_1
      68: ldc           #72                 // String , meta=
      70: invokevirtual #34                 // Method java/lang/StringBuilder.append:(Ljava/lang/String;)Ljava/lang/StringBuilder;
      73: aload_0
      74: getfield      #12                 // Field meta:Ljava/util/Set;
      77: invokevirtual #35                 // Method java/lang/StringBuilder.append:(Ljava/lang/Object;)Ljava/lang/StringBuilder;
      80: pop
      81: aload_1
      82: ldc           #73                 // String , port=
      84: invokevirtual #34                 // Method java/lang/StringBuilder.append:(Ljava/lang/String;)Ljava/lang/StringBuilder;
      87: aload_0
      88: getfield      #41                 // Field port:Ljava/lang/Integer;
      91: invokevirtual #35                 // Method java/lang/StringBuilder.append:(Ljava/lang/Object;)Ljava/lang/StringBuilder;
      94: pop
      95: aload_1
      96: bipush        125
      98: invokevirtual #69                 // Method java/lang/StringBuilder.append:(C)Ljava/lang/StringBuilder;
     101: pop
     102: aload_1
     103: invokevirtual #37                 // Method java/lang/StringBuilder.toString:()Ljava/lang/String;
     106: areturn

  private static java.util.Map lambda$addMethodToServiceMap$0(java.lang.String);
    Code:
       0: new           #2                  // class java/util/HashMap
       3: dup
       4: invokespecial #3                  // Method java/util/HashMap."<init>":()V
       7: areturn
}
