Compiled from "SingleContains.java"
final class io.reactivex.rxjava3.internal.operators.single.SingleContains$ContainsSingleObserver implements io.reactivex.rxjava3.core.SingleObserver<T> {
  private final io.reactivex.rxjava3.core.SingleObserver<? super java.lang.Boolean> downstream;

  final io.reactivex.rxjava3.internal.operators.single.SingleContains this$0;

  io.reactivex.rxjava3.internal.operators.single.SingleContains$ContainsSingleObserver(io.reactivex.rxjava3.core.SingleObserver<? super java.lang.Boolean>);
    Code:
       0: aload_0
       1: aload_1
       2: putfield      #1                  // Field this$0:Lio/reactivex/rxjava3/internal/operators/single/SingleContains;
       5: aload_0
       6: invokespecial #2                  // Method java/lang/Object."<init>":()V
       9: aload_0
      10: aload_2
      11: putfield      #3                  // Field downstream:Lio/reactivex/rxjava3/core/SingleObserver;
      14: return

  public void onSubscribe(io.reactivex.rxjava3.disposables.Disposable);
    Code:
       0: aload_0
       1: getfield      #3                  // Field downstream:Lio/reactivex/rxjava3/core/SingleObserver;
       4: aload_1
       5: invokeinterface #4,  2            // InterfaceMethod io/reactivex/rxjava3/core/SingleObserver.onSubscribe:(Lio/reactivex/rxjava3/disposables/Disposable;)V
      10: return

  public void onSuccess(T);
    Code:
       0: aload_0
       1: getfield      #1                  // Field this$0:Lio/reactivex/rxjava3/internal/operators/single/SingleContains;
       4: getfield      #5                  // Field io/reactivex/rxjava3/internal/operators/single/SingleContains.comparer:Lio/reactivex/rxjava3/functions/BiPredicate;
       7: aload_1
       8: aload_0
       9: getfield      #1                  // Field this$0:Lio/reactivex/rxjava3/internal/operators/single/SingleContains;
      12: getfield      #6                  // Field io/reactivex/rxjava3/internal/operators/single/SingleContains.value:Ljava/lang/Object;
      15: invokeinterface #7,  3            // InterfaceMethod io/reactivex/rxjava3/functions/BiPredicate.test:(Ljava/lang/Object;Ljava/lang/Object;)Z
      20: istore_2
      21: goto          40
      24: astore_3
      25: aload_3
      26: invokestatic  #9                  // Method io/reactivex/rxjava3/exceptions/Exceptions.throwIfFatal:(Ljava/lang/Throwable;)V
      29: aload_0
      30: getfield      #3                  // Field downstream:Lio/reactivex/rxjava3/core/SingleObserver;
      33: aload_3
      34: invokeinterface #10,  2           // InterfaceMethod io/reactivex/rxjava3/core/SingleObserver.onError:(Ljava/lang/Throwable;)V
      39: return
      40: aload_0
      41: getfield      #3                  // Field downstream:Lio/reactivex/rxjava3/core/SingleObserver;
      44: iload_2
      45: invokestatic  #11                 // Method java/lang/Boolean.valueOf:(Z)Ljava/lang/Boolean;
      48: invokeinterface #12,  2           // InterfaceMethod io/reactivex/rxjava3/core/SingleObserver.onSuccess:(Ljava/lang/Object;)V
      53: return
    Exception table:
       from    to  target type
           0    21    24   Class java/lang/Throwable

  public void onError(java.lang.Throwable);
    Code:
       0: aload_0
       1: getfield      #3                  // Field downstream:Lio/reactivex/rxjava3/core/SingleObserver;
       4: aload_1
       5: invokeinterface #10,  2           // InterfaceMethod io/reactivex/rxjava3/core/SingleObserver.onError:(Ljava/lang/Throwable;)V
      10: return
}
