Compiled from "SingleTakeUntil.java"
public final class io.reactivex.rxjava3.internal.operators.single.SingleTakeUntil<T, U> extends io.reactivex.rxjava3.core.Single<T> {
  final io.reactivex.rxjava3.core.SingleSource<T> source;

  final org.reactivestreams.Publisher<U> other;

  public io.reactivex.rxjava3.internal.operators.single.SingleTakeUntil(io.reactivex.rxjava3.core.SingleSource<T>, org.reactivestreams.Publisher<U>);
    Code:
       0: aload_0
       1: invokespecial #1                  // Method io/reactivex/rxjava3/core/Single."<init>":()V
       4: aload_0
       5: aload_1
       6: putfield      #2                  // Field source:Lio/reactivex/rxjava3/core/SingleSource;
       9: aload_0
      10: aload_2
      11: putfield      #3                  // Field other:Lorg/reactivestreams/Publisher;
      14: return

  protected void subscribeActual(io.reactivex.rxjava3.core.SingleObserver<? super T>);
    Code:
       0: new           #4                  // class io/reactivex/rxjava3/internal/operators/single/SingleTakeUntil$TakeUntilMainObserver
       3: dup
       4: aload_1
       5: invokespecial #5                  // Method io/reactivex/rxjava3/internal/operators/single/SingleTakeUntil$TakeUntilMainObserver."<init>":(Lio/reactivex/rxjava3/core/SingleObserver;)V
       8: astore_2
       9: aload_1
      10: aload_2
      11: invokeinterface #6,  2            // InterfaceMethod io/reactivex/rxjava3/core/SingleObserver.onSubscribe:(Lio/reactivex/rxjava3/disposables/Disposable;)V
      16: aload_0
      17: getfield      #3                  // Field other:Lorg/reactivestreams/Publisher;
      20: aload_2
      21: getfield      #7                  // Field io/reactivex/rxjava3/internal/operators/single/SingleTakeUntil$TakeUntilMainObserver.other:Lio/reactivex/rxjava3/internal/operators/single/SingleTakeUntil$TakeUntilOtherSubscriber;
      24: invokeinterface #8,  2            // InterfaceMethod org/reactivestreams/Publisher.subscribe:(Lorg/reactivestreams/Subscriber;)V
      29: aload_0
      30: getfield      #2                  // Field source:Lio/reactivex/rxjava3/core/SingleSource;
      33: aload_2
      34: invokeinterface #9,  2            // InterfaceMethod io/reactivex/rxjava3/core/SingleSource.subscribe:(Lio/reactivex/rxjava3/core/SingleObserver;)V
      39: return
}
