Compiled from "SingleDelayWithPublisher.java"
final class io.reactivex.rxjava3.internal.operators.single.SingleDelayWithPublisher$OtherSubscriber<T, U> extends java.util.concurrent.atomic.AtomicReference<io.reactivex.rxjava3.disposables.Disposable> implements io.reactivex.rxjava3.core.FlowableSubscriber<U>, io.reactivex.rxjava3.disposables.Disposable {
  private static final long serialVersionUID;

  final io.reactivex.rxjava3.core.SingleObserver<? super T> downstream;

  final io.reactivex.rxjava3.core.SingleSource<T> source;

  boolean done;

  org.reactivestreams.Subscription upstream;

  io.reactivex.rxjava3.internal.operators.single.SingleDelayWithPublisher$OtherSubscriber(io.reactivex.rxjava3.core.SingleObserver<? super T>, io.reactivex.rxjava3.core.SingleSource<T>);
    Code:
       0: aload_0
       1: invokespecial #1                  // Method java/util/concurrent/atomic/AtomicReference."<init>":()V
       4: aload_0
       5: aload_1
       6: putfield      #2                  // Field downstream:Lio/reactivex/rxjava3/core/SingleObserver;
       9: aload_0
      10: aload_2
      11: putfield      #3                  // Field source:Lio/reactivex/rxjava3/core/SingleSource;
      14: return

  public void onSubscribe(org.reactivestreams.Subscription);
    Code:
       0: aload_0
       1: getfield      #4                  // Field upstream:Lorg/reactivestreams/Subscription;
       4: aload_1
       5: invokestatic  #5                  // Method io/reactivex/rxjava3/internal/subscriptions/SubscriptionHelper.validate:(Lorg/reactivestreams/Subscription;Lorg/reactivestreams/Subscription;)Z
       8: ifeq          35
      11: aload_0
      12: aload_1
      13: putfield      #4                  // Field upstream:Lorg/reactivestreams/Subscription;
      16: aload_0
      17: getfield      #2                  // Field downstream:Lio/reactivex/rxjava3/core/SingleObserver;
      20: aload_0
      21: invokeinterface #6,  2            // InterfaceMethod io/reactivex/rxjava3/core/SingleObserver.onSubscribe:(Lio/reactivex/rxjava3/disposables/Disposable;)V
      26: aload_1
      27: ldc2_w        #8                  // long 9223372036854775807l
      30: invokeinterface #10,  3           // InterfaceMethod org/reactivestreams/Subscription.request:(J)V
      35: return

  public void onNext(U);
    Code:
       0: aload_0
       1: getfield      #4                  // Field upstream:Lorg/reactivestreams/Subscription;
       4: invokeinterface #11,  1           // InterfaceMethod org/reactivestreams/Subscription.cancel:()V
       9: aload_0
      10: invokevirtual #12                 // Method onComplete:()V
      13: return

  public void onError(java.lang.Throwable);
    Code:
       0: aload_0
       1: getfield      #13                 // Field done:Z
       4: ifeq          12
       7: aload_1
       8: invokestatic  #14                 // Method io/reactivex/rxjava3/plugins/RxJavaPlugins.onError:(Ljava/lang/Throwable;)V
      11: return
      12: aload_0
      13: iconst_1
      14: putfield      #13                 // Field done:Z
      17: aload_0
      18: getfield      #2                  // Field downstream:Lio/reactivex/rxjava3/core/SingleObserver;
      21: aload_1
      22: invokeinterface #15,  2           // InterfaceMethod io/reactivex/rxjava3/core/SingleObserver.onError:(Ljava/lang/Throwable;)V
      27: return

  public void onComplete();
    Code:
       0: aload_0
       1: getfield      #13                 // Field done:Z
       4: ifeq          8
       7: return
       8: aload_0
       9: iconst_1
      10: putfield      #13                 // Field done:Z
      13: aload_0
      14: getfield      #3                  // Field source:Lio/reactivex/rxjava3/core/SingleSource;
      17: new           #16                 // class io/reactivex/rxjava3/internal/observers/ResumeSingleObserver
      20: dup
      21: aload_0
      22: aload_0
      23: getfield      #2                  // Field downstream:Lio/reactivex/rxjava3/core/SingleObserver;
      26: invokespecial #17                 // Method io/reactivex/rxjava3/internal/observers/ResumeSingleObserver."<init>":(Ljava/util/concurrent/atomic/AtomicReference;Lio/reactivex/rxjava3/core/SingleObserver;)V
      29: invokeinterface #18,  2           // InterfaceMethod io/reactivex/rxjava3/core/SingleSource.subscribe:(Lio/reactivex/rxjava3/core/SingleObserver;)V
      34: return

  public void dispose();
    Code:
       0: aload_0
       1: getfield      #4                  // Field upstream:Lorg/reactivestreams/Subscription;
       4: invokeinterface #11,  1           // InterfaceMethod org/reactivestreams/Subscription.cancel:()V
       9: aload_0
      10: invokestatic  #19                 // Method io/reactivex/rxjava3/internal/disposables/DisposableHelper.dispose:(Ljava/util/concurrent/atomic/AtomicReference;)Z
      13: pop
      14: return

  public boolean isDisposed();
    Code:
       0: aload_0
       1: invokevirtual #20                 // Method get:()Ljava/lang/Object;
       4: checkcast     #21                 // class io/reactivex/rxjava3/disposables/Disposable
       7: invokestatic  #22                 // Method io/reactivex/rxjava3/internal/disposables/DisposableHelper.isDisposed:(Lio/reactivex/rxjava3/disposables/Disposable;)Z
      10: ireturn
}
