Compiled from "SingleDoOnDispose.java"
final class io.reactivex.rxjava3.internal.operators.single.SingleDoOnDispose$DoOnDisposeObserver<T> extends java.util.concurrent.atomic.AtomicReference<io.reactivex.rxjava3.functions.Action> implements io.reactivex.rxjava3.core.SingleObserver<T>, io.reactivex.rxjava3.disposables.Disposable {
  private static final long serialVersionUID;

  final io.reactivex.rxjava3.core.SingleObserver<? super T> downstream;

  io.reactivex.rxjava3.disposables.Disposable upstream;

  io.reactivex.rxjava3.internal.operators.single.SingleDoOnDispose$DoOnDisposeObserver(io.reactivex.rxjava3.core.SingleObserver<? super T>, io.reactivex.rxjava3.functions.Action);
    Code:
       0: aload_0
       1: invokespecial #1                  // Method java/util/concurrent/atomic/AtomicReference."<init>":()V
       4: aload_0
       5: aload_1
       6: putfield      #2                  // Field downstream:Lio/reactivex/rxjava3/core/SingleObserver;
       9: aload_0
      10: aload_2
      11: invokevirtual #3                  // Method lazySet:(Ljava/lang/Object;)V
      14: return

  public void dispose();
    Code:
       0: aload_0
       1: aconst_null
       2: invokevirtual #4                  // Method getAndSet:(Ljava/lang/Object;)Ljava/lang/Object;
       5: checkcast     #5                  // class io/reactivex/rxjava3/functions/Action
       8: astore_1
       9: aload_1
      10: ifnull        40
      13: aload_1
      14: invokeinterface #6,  1            // InterfaceMethod io/reactivex/rxjava3/functions/Action.run:()V
      19: goto          31
      22: astore_2
      23: aload_2
      24: invokestatic  #8                  // Method io/reactivex/rxjava3/exceptions/Exceptions.throwIfFatal:(Ljava/lang/Throwable;)V
      27: aload_2
      28: invokestatic  #9                  // Method io/reactivex/rxjava3/plugins/RxJavaPlugins.onError:(Ljava/lang/Throwable;)V
      31: aload_0
      32: getfield      #10                 // Field upstream:Lio/reactivex/rxjava3/disposables/Disposable;
      35: invokeinterface #11,  1           // InterfaceMethod io/reactivex/rxjava3/disposables/Disposable.dispose:()V
      40: return
    Exception table:
       from    to  target type
          13    19    22   Class java/lang/Throwable

  public boolean isDisposed();
    Code:
       0: aload_0
       1: getfield      #10                 // Field upstream:Lio/reactivex/rxjava3/disposables/Disposable;
       4: invokeinterface #12,  1           // InterfaceMethod io/reactivex/rxjava3/disposables/Disposable.isDisposed:()Z
       9: ireturn

  public void onSubscribe(io.reactivex.rxjava3.disposables.Disposable);
    Code:
       0: aload_0
       1: getfield      #10                 // Field upstream:Lio/reactivex/rxjava3/disposables/Disposable;
       4: aload_1
       5: invokestatic  #13                 // Method io/reactivex/rxjava3/internal/disposables/DisposableHelper.validate:(Lio/reactivex/rxjava3/disposables/Disposable;Lio/reactivex/rxjava3/disposables/Disposable;)Z
       8: ifeq          26
      11: aload_0
      12: aload_1
      13: putfield      #10                 // Field upstream:Lio/reactivex/rxjava3/disposables/Disposable;
      16: aload_0
      17: getfield      #2                  // Field downstream:Lio/reactivex/rxjava3/core/SingleObserver;
      20: aload_0
      21: invokeinterface #14,  2           // InterfaceMethod io/reactivex/rxjava3/core/SingleObserver.onSubscribe:(Lio/reactivex/rxjava3/disposables/Disposable;)V
      26: return

  public void onSuccess(T);
    Code:
       0: aload_0
       1: getfield      #2                  // Field downstream:Lio/reactivex/rxjava3/core/SingleObserver;
       4: aload_1
       5: invokeinterface #15,  2           // InterfaceMethod io/reactivex/rxjava3/core/SingleObserver.onSuccess:(Ljava/lang/Object;)V
      10: return

  public void onError(java.lang.Throwable);
    Code:
       0: aload_0
       1: getfield      #2                  // Field downstream:Lio/reactivex/rxjava3/core/SingleObserver;
       4: aload_1
       5: invokeinterface #16,  2           // InterfaceMethod io/reactivex/rxjava3/core/SingleObserver.onError:(Ljava/lang/Throwable;)V
      10: return
}
