Compiled from "SingleInternalHelper.java"
final class io.reactivex.rxjava3.internal.operators.single.SingleInternalHelper$ToFlowableIterator<T> implements java.util.Iterator<io.reactivex.rxjava3.core.Flowable<T>> {
  private final java.util.Iterator<? extends io.reactivex.rxjava3.core.SingleSource<? extends T>> sit;

  io.reactivex.rxjava3.internal.operators.single.SingleInternalHelper$ToFlowableIterator(java.util.Iterator<? extends io.reactivex.rxjava3.core.SingleSource<? extends T>>);
    Code:
       0: aload_0
       1: invokespecial #1                  // Method java/lang/Object."<init>":()V
       4: aload_0
       5: aload_1
       6: putfield      #2                  // Field sit:Ljava/util/Iterator;
       9: return

  public boolean hasNext();
    Code:
       0: aload_0
       1: getfield      #2                  // Field sit:Ljava/util/Iterator;
       4: invokeinterface #3,  1            // InterfaceMethod java/util/Iterator.hasNext:()Z
       9: ireturn

  public io.reactivex.rxjava3.core.Flowable<T> next();
    Code:
       0: new           #4                  // class io/reactivex/rxjava3/internal/operators/single/SingleToFlowable
       3: dup
       4: aload_0
       5: getfield      #2                  // Field sit:Ljava/util/Iterator;
       8: invokeinterface #5,  1            // InterfaceMethod java/util/Iterator.next:()Ljava/lang/Object;
      13: checkcast     #6                  // class io/reactivex/rxjava3/core/SingleSource
      16: invokespecial #7                  // Method io/reactivex/rxjava3/internal/operators/single/SingleToFlowable."<init>":(Lio/reactivex/rxjava3/core/SingleSource;)V
      19: areturn

  public void remove();
    Code:
       0: new           #8                  // class java/lang/UnsupportedOperationException
       3: dup
       4: invokespecial #9                  // Method java/lang/UnsupportedOperationException."<init>":()V
       7: athrow

  public java.lang.Object next();
    Code:
       0: aload_0
       1: invokevirtual #10                 // Method next:()Lio/reactivex/rxjava3/core/Flowable;
       4: areturn
}
