Compiled from "SingleDoOnEvent.java"
public final class io.reactivex.rxjava3.internal.operators.single.SingleDoOnEvent<T> extends io.reactivex.rxjava3.core.Single<T> {
  final io.reactivex.rxjava3.core.SingleSource<T> source;

  final io.reactivex.rxjava3.functions.BiConsumer<? super T, ? super java.lang.Throwable> onEvent;

  public io.reactivex.rxjava3.internal.operators.single.SingleDoOnEvent(io.reactivex.rxjava3.core.SingleSource<T>, io.reactivex.rxjava3.functions.BiConsumer<? super T, ? super java.lang.Throwable>);
    Code:
       0: aload_0
       1: invokespecial #1                  // Method io/reactivex/rxjava3/core/Single."<init>":()V
       4: aload_0
       5: aload_1
       6: putfield      #2                  // Field source:Lio/reactivex/rxjava3/core/SingleSource;
       9: aload_0
      10: aload_2
      11: putfield      #3                  // Field onEvent:Lio/reactivex/rxjava3/functions/BiConsumer;
      14: return

  protected void subscribeActual(io.reactivex.rxjava3.core.SingleObserver<? super T>);
    Code:
       0: aload_0
       1: getfield      #2                  // Field source:Lio/reactivex/rxjava3/core/SingleSource;
       4: new           #4                  // class io/reactivex/rxjava3/internal/operators/single/SingleDoOnEvent$DoOnEvent
       7: dup
       8: aload_0
       9: aload_1
      10: invokespecial #5                  // Method io/reactivex/rxjava3/internal/operators/single/SingleDoOnEvent$DoOnEvent."<init>":(Lio/reactivex/rxjava3/internal/operators/single/SingleDoOnEvent;Lio/reactivex/rxjava3/core/SingleObserver;)V
      13: invokeinterface #6,  2            // InterfaceMethod io/reactivex/rxjava3/core/SingleSource.subscribe:(Lio/reactivex/rxjava3/core/SingleObserver;)V
      18: return
}
