Compiled from "SingleTimeout.java"
public final class io.reactivex.rxjava3.internal.operators.single.SingleTimeout<T> extends io.reactivex.rxjava3.core.Single<T> {
  final io.reactivex.rxjava3.core.SingleSource<T> source;

  final long timeout;

  final java.util.concurrent.TimeUnit unit;

  final io.reactivex.rxjava3.core.Scheduler scheduler;

  final io.reactivex.rxjava3.core.SingleSource<? extends T> other;

  public io.reactivex.rxjava3.internal.operators.single.SingleTimeout(io.reactivex.rxjava3.core.SingleSource<T>, long, java.util.concurrent.TimeUnit, io.reactivex.rxjava3.core.Scheduler, io.reactivex.rxjava3.core.SingleSource<? extends T>);
    Code:
       0: aload_0
       1: invokespecial #1                  // Method io/reactivex/rxjava3/core/Single."<init>":()V
       4: aload_0
       5: aload_1
       6: putfield      #2                  // Field source:Lio/reactivex/rxjava3/core/SingleSource;
       9: aload_0
      10: lload_2
      11: putfield      #3                  // Field timeout:J
      14: aload_0
      15: aload         4
      17: putfield      #4                  // Field unit:Ljava/util/concurrent/TimeUnit;
      20: aload_0
      21: aload         5
      23: putfield      #5                  // Field scheduler:Lio/reactivex/rxjava3/core/Scheduler;
      26: aload_0
      27: aload         6
      29: putfield      #6                  // Field other:Lio/reactivex/rxjava3/core/SingleSource;
      32: return

  protected void subscribeActual(io.reactivex.rxjava3.core.SingleObserver<? super T>);
    Code:
       0: new           #7                  // class io/reactivex/rxjava3/internal/operators/single/SingleTimeout$TimeoutMainObserver
       3: dup
       4: aload_1
       5: aload_0
       6: getfield      #6                  // Field other:Lio/reactivex/rxjava3/core/SingleSource;
       9: aload_0
      10: getfield      #3                  // Field timeout:J
      13: aload_0
      14: getfield      #4                  // Field unit:Ljava/util/concurrent/TimeUnit;
      17: invokespecial #8                  // Method io/reactivex/rxjava3/internal/operators/single/SingleTimeout$TimeoutMainObserver."<init>":(Lio/reactivex/rxjava3/core/SingleObserver;Lio/reactivex/rxjava3/core/SingleSource;JLjava/util/concurrent/TimeUnit;)V
      20: astore_2
      21: aload_1
      22: aload_2
      23: invokeinterface #9,  2            // InterfaceMethod io/reactivex/rxjava3/core/SingleObserver.onSubscribe:(Lio/reactivex/rxjava3/disposables/Disposable;)V
      28: aload_2
      29: getfield      #10                 // Field io/reactivex/rxjava3/internal/operators/single/SingleTimeout$TimeoutMainObserver.task:Ljava/util/concurrent/atomic/AtomicReference;
      32: aload_0
      33: getfield      #5                  // Field scheduler:Lio/reactivex/rxjava3/core/Scheduler;
      36: aload_2
      37: aload_0
      38: getfield      #3                  // Field timeout:J
      41: aload_0
      42: getfield      #4                  // Field unit:Ljava/util/concurrent/TimeUnit;
      45: invokevirtual #11                 // Method io/reactivex/rxjava3/core/Scheduler.scheduleDirect:(Ljava/lang/Runnable;JLjava/util/concurrent/TimeUnit;)Lio/reactivex/rxjava3/disposables/Disposable;
      48: invokestatic  #12                 // Method io/reactivex/rxjava3/internal/disposables/DisposableHelper.replace:(Ljava/util/concurrent/atomic/AtomicReference;Lio/reactivex/rxjava3/disposables/Disposable;)Z
      51: pop
      52: aload_0
      53: getfield      #2                  // Field source:Lio/reactivex/rxjava3/core/SingleSource;
      56: aload_2
      57: invokeinterface #13,  2           // InterfaceMethod io/reactivex/rxjava3/core/SingleSource.subscribe:(Lio/reactivex/rxjava3/core/SingleObserver;)V
      62: return
}
