Compiled from "SingleCache.java"
final class io.reactivex.rxjava3.internal.operators.single.SingleCache$CacheDisposable<T> extends java.util.concurrent.atomic.AtomicBoolean implements io.reactivex.rxjava3.disposables.Disposable {
  private static final long serialVersionUID;

  final io.reactivex.rxjava3.core.SingleObserver<? super T> downstream;

  final io.reactivex.rxjava3.internal.operators.single.SingleCache<T> parent;

  io.reactivex.rxjava3.internal.operators.single.SingleCache$CacheDisposable(io.reactivex.rxjava3.core.SingleObserver<? super T>, io.reactivex.rxjava3.internal.operators.single.SingleCache<T>);
    Code:
       0: aload_0
       1: invokespecial #1                  // Method java/util/concurrent/atomic/AtomicBoolean."<init>":()V
       4: aload_0
       5: aload_1
       6: putfield      #2                  // Field downstream:Lio/reactivex/rxjava3/core/SingleObserver;
       9: aload_0
      10: aload_2
      11: putfield      #3                  // Field parent:Lio/reactivex/rxjava3/internal/operators/single/SingleCache;
      14: return

  public boolean isDisposed();
    Code:
       0: aload_0
       1: invokevirtual #4                  // Method get:()Z
       4: ireturn

  public void dispose();
    Code:
       0: aload_0
       1: iconst_0
       2: iconst_1
       3: invokevirtual #5                  // Method compareAndSet:(ZZ)Z
       6: ifeq          17
       9: aload_0
      10: getfield      #3                  // Field parent:Lio/reactivex/rxjava3/internal/operators/single/SingleCache;
      13: aload_0
      14: invokevirtual #6                  // Method io/reactivex/rxjava3/internal/operators/single/SingleCache.remove:(Lio/reactivex/rxjava3/internal/operators/single/SingleCache$CacheDisposable;)V
      17: return
}
