Compiled from "SingleTimeout.java"
final class io.reactivex.rxjava3.internal.operators.single.SingleTimeout$TimeoutMainObserver<T> extends java.util.concurrent.atomic.AtomicReference<io.reactivex.rxjava3.disposables.Disposable> implements io.reactivex.rxjava3.core.SingleObserver<T>, java.lang.Runnable, io.reactivex.rxjava3.disposables.Disposable {
  private static final long serialVersionUID;

  final io.reactivex.rxjava3.core.SingleObserver<? super T> downstream;

  final java.util.concurrent.atomic.AtomicReference<io.reactivex.rxjava3.disposables.Disposable> task;

  final io.reactivex.rxjava3.internal.operators.single.SingleTimeout$TimeoutMainObserver$TimeoutFallbackObserver<T> fallback;

  io.reactivex.rxjava3.core.SingleSource<? extends T> other;

  final long timeout;

  final java.util.concurrent.TimeUnit unit;

  io.reactivex.rxjava3.internal.operators.single.SingleTimeout$TimeoutMainObserver(io.reactivex.rxjava3.core.SingleObserver<? super T>, io.reactivex.rxjava3.core.SingleSource<? extends T>, long, java.util.concurrent.TimeUnit);
    Code:
       0: aload_0
       1: invokespecial #1                  // Method java/util/concurrent/atomic/AtomicReference."<init>":()V
       4: aload_0
       5: aload_1
       6: putfield      #2                  // Field downstream:Lio/reactivex/rxjava3/core/SingleObserver;
       9: aload_0
      10: aload_2
      11: putfield      #3                  // Field other:Lio/reactivex/rxjava3/core/SingleSource;
      14: aload_0
      15: lload_3
      16: putfield      #4                  // Field timeout:J
      19: aload_0
      20: aload         5
      22: putfield      #5                  // Field unit:Ljava/util/concurrent/TimeUnit;
      25: aload_0
      26: new           #6                  // class java/util/concurrent/atomic/AtomicReference
      29: dup
      30: invokespecial #1                  // Method java/util/concurrent/atomic/AtomicReference."<init>":()V
      33: putfield      #7                  // Field task:Ljava/util/concurrent/atomic/AtomicReference;
      36: aload_2
      37: ifnull        55
      40: aload_0
      41: new           #8                  // class io/reactivex/rxjava3/internal/operators/single/SingleTimeout$TimeoutMainObserver$TimeoutFallbackObserver
      44: dup
      45: aload_1
      46: invokespecial #9                  // Method io/reactivex/rxjava3/internal/operators/single/SingleTimeout$TimeoutMainObserver$TimeoutFallbackObserver."<init>":(Lio/reactivex/rxjava3/core/SingleObserver;)V
      49: putfield      #10                 // Field fallback:Lio/reactivex/rxjava3/internal/operators/single/SingleTimeout$TimeoutMainObserver$TimeoutFallbackObserver;
      52: goto          60
      55: aload_0
      56: aconst_null
      57: putfield      #10                 // Field fallback:Lio/reactivex/rxjava3/internal/operators/single/SingleTimeout$TimeoutMainObserver$TimeoutFallbackObserver;
      60: return

  public void run();
    Code:
       0: aload_0
       1: invokestatic  #11                 // Method io/reactivex/rxjava3/internal/disposables/DisposableHelper.dispose:(Ljava/util/concurrent/atomic/AtomicReference;)Z
       4: ifeq          61
       7: aload_0
       8: getfield      #3                  // Field other:Lio/reactivex/rxjava3/core/SingleSource;
      11: astore_1
      12: aload_1
      13: ifnonnull     46
      16: aload_0
      17: getfield      #2                  // Field downstream:Lio/reactivex/rxjava3/core/SingleObserver;
      20: new           #12                 // class java/util/concurrent/TimeoutException
      23: dup
      24: aload_0
      25: getfield      #4                  // Field timeout:J
      28: aload_0
      29: getfield      #5                  // Field unit:Ljava/util/concurrent/TimeUnit;
      32: invokestatic  #13                 // Method io/reactivex/rxjava3/internal/util/ExceptionHelper.timeoutMessage:(JLjava/util/concurrent/TimeUnit;)Ljava/lang/String;
      35: invokespecial #14                 // Method java/util/concurrent/TimeoutException."<init>":(Ljava/lang/String;)V
      38: invokeinterface #15,  2           // InterfaceMethod io/reactivex/rxjava3/core/SingleObserver.onError:(Ljava/lang/Throwable;)V
      43: goto          61
      46: aload_0
      47: aconst_null
      48: putfield      #3                  // Field other:Lio/reactivex/rxjava3/core/SingleSource;
      51: aload_1
      52: aload_0
      53: getfield      #10                 // Field fallback:Lio/reactivex/rxjava3/internal/operators/single/SingleTimeout$TimeoutMainObserver$TimeoutFallbackObserver;
      56: invokeinterface #16,  2           // InterfaceMethod io/reactivex/rxjava3/core/SingleSource.subscribe:(Lio/reactivex/rxjava3/core/SingleObserver;)V
      61: return

  public void onSubscribe(io.reactivex.rxjava3.disposables.Disposable);
    Code:
       0: aload_0
       1: aload_1
       2: invokestatic  #17                 // Method io/reactivex/rxjava3/internal/disposables/DisposableHelper.setOnce:(Ljava/util/concurrent/atomic/AtomicReference;Lio/reactivex/rxjava3/disposables/Disposable;)Z
       5: pop
       6: return

  public void onSuccess(T);
    Code:
       0: aload_0
       1: invokevirtual #18                 // Method get:()Ljava/lang/Object;
       4: checkcast     #19                 // class io/reactivex/rxjava3/disposables/Disposable
       7: astore_2
       8: aload_2
       9: getstatic     #20                 // Field io/reactivex/rxjava3/internal/disposables/DisposableHelper.DISPOSED:Lio/reactivex/rxjava3/internal/disposables/DisposableHelper;
      12: if_acmpeq     44
      15: aload_0
      16: aload_2
      17: getstatic     #20                 // Field io/reactivex/rxjava3/internal/disposables/DisposableHelper.DISPOSED:Lio/reactivex/rxjava3/internal/disposables/DisposableHelper;
      20: invokevirtual #21                 // Method compareAndSet:(Ljava/lang/Object;Ljava/lang/Object;)Z
      23: ifeq          44
      26: aload_0
      27: getfield      #7                  // Field task:Ljava/util/concurrent/atomic/AtomicReference;
      30: invokestatic  #11                 // Method io/reactivex/rxjava3/internal/disposables/DisposableHelper.dispose:(Ljava/util/concurrent/atomic/AtomicReference;)Z
      33: pop
      34: aload_0
      35: getfield      #2                  // Field downstream:Lio/reactivex/rxjava3/core/SingleObserver;
      38: aload_1
      39: invokeinterface #22,  2           // InterfaceMethod io/reactivex/rxjava3/core/SingleObserver.onSuccess:(Ljava/lang/Object;)V
      44: return

  public void onError(java.lang.Throwable);
    Code:
       0: aload_0
       1: invokevirtual #18                 // Method get:()Ljava/lang/Object;
       4: checkcast     #19                 // class io/reactivex/rxjava3/disposables/Disposable
       7: astore_2
       8: aload_2
       9: getstatic     #20                 // Field io/reactivex/rxjava3/internal/disposables/DisposableHelper.DISPOSED:Lio/reactivex/rxjava3/internal/disposables/DisposableHelper;
      12: if_acmpeq     47
      15: aload_0
      16: aload_2
      17: getstatic     #20                 // Field io/reactivex/rxjava3/internal/disposables/DisposableHelper.DISPOSED:Lio/reactivex/rxjava3/internal/disposables/DisposableHelper;
      20: invokevirtual #21                 // Method compareAndSet:(Ljava/lang/Object;Ljava/lang/Object;)Z
      23: ifeq          47
      26: aload_0
      27: getfield      #7                  // Field task:Ljava/util/concurrent/atomic/AtomicReference;
      30: invokestatic  #11                 // Method io/reactivex/rxjava3/internal/disposables/DisposableHelper.dispose:(Ljava/util/concurrent/atomic/AtomicReference;)Z
      33: pop
      34: aload_0
      35: getfield      #2                  // Field downstream:Lio/reactivex/rxjava3/core/SingleObserver;
      38: aload_1
      39: invokeinterface #15,  2           // InterfaceMethod io/reactivex/rxjava3/core/SingleObserver.onError:(Ljava/lang/Throwable;)V
      44: goto          51
      47: aload_1
      48: invokestatic  #23                 // Method io/reactivex/rxjava3/plugins/RxJavaPlugins.onError:(Ljava/lang/Throwable;)V
      51: return

  public void dispose();
    Code:
       0: aload_0
       1: invokestatic  #11                 // Method io/reactivex/rxjava3/internal/disposables/DisposableHelper.dispose:(Ljava/util/concurrent/atomic/AtomicReference;)Z
       4: pop
       5: aload_0
       6: getfield      #7                  // Field task:Ljava/util/concurrent/atomic/AtomicReference;
       9: invokestatic  #11                 // Method io/reactivex/rxjava3/internal/disposables/DisposableHelper.dispose:(Ljava/util/concurrent/atomic/AtomicReference;)Z
      12: pop
      13: aload_0
      14: getfield      #10                 // Field fallback:Lio/reactivex/rxjava3/internal/operators/single/SingleTimeout$TimeoutMainObserver$TimeoutFallbackObserver;
      17: ifnull        28
      20: aload_0
      21: getfield      #10                 // Field fallback:Lio/reactivex/rxjava3/internal/operators/single/SingleTimeout$TimeoutMainObserver$TimeoutFallbackObserver;
      24: invokestatic  #11                 // Method io/reactivex/rxjava3/internal/disposables/DisposableHelper.dispose:(Ljava/util/concurrent/atomic/AtomicReference;)Z
      27: pop
      28: return

  public boolean isDisposed();
    Code:
       0: aload_0
       1: invokevirtual #18                 // Method get:()Ljava/lang/Object;
       4: checkcast     #19                 // class io/reactivex/rxjava3/disposables/Disposable
       7: invokestatic  #24                 // Method io/reactivex/rxjava3/internal/disposables/DisposableHelper.isDisposed:(Lio/reactivex/rxjava3/disposables/Disposable;)Z
      10: ireturn
}
