Compiled from "SingleResumeNext.java"
public final class io.reactivex.rxjava3.internal.operators.single.SingleResumeNext<T> extends io.reactivex.rxjava3.core.Single<T> {
  final io.reactivex.rxjava3.core.SingleSource<? extends T> source;

  final io.reactivex.rxjava3.functions.Function<? super java.lang.Throwable, ? extends io.reactivex.rxjava3.core.SingleSource<? extends T>> nextFunction;

  public io.reactivex.rxjava3.internal.operators.single.SingleResumeNext(io.reactivex.rxjava3.core.SingleSource<? extends T>, io.reactivex.rxjava3.functions.Function<? super java.lang.Throwable, ? extends io.reactivex.rxjava3.core.SingleSource<? extends T>>);
    Code:
       0: aload_0
       1: invokespecial #1                  // Method io/reactivex/rxjava3/core/Single."<init>":()V
       4: aload_0
       5: aload_1
       6: putfield      #2                  // Field source:Lio/reactivex/rxjava3/core/SingleSource;
       9: aload_0
      10: aload_2
      11: putfield      #3                  // Field nextFunction:Lio/reactivex/rxjava3/functions/Function;
      14: return

  protected void subscribeActual(io.reactivex.rxjava3.core.SingleObserver<? super T>);
    Code:
       0: aload_0
       1: getfield      #2                  // Field source:Lio/reactivex/rxjava3/core/SingleSource;
       4: new           #4                  // class io/reactivex/rxjava3/internal/operators/single/SingleResumeNext$ResumeMainSingleObserver
       7: dup
       8: aload_1
       9: aload_0
      10: getfield      #3                  // Field nextFunction:Lio/reactivex/rxjava3/functions/Function;
      13: invokespecial #5                  // Method io/reactivex/rxjava3/internal/operators/single/SingleResumeNext$ResumeMainSingleObserver."<init>":(Lio/reactivex/rxjava3/core/SingleObserver;Lio/reactivex/rxjava3/functions/Function;)V
      16: invokeinterface #6,  2            // InterfaceMethod io/reactivex/rxjava3/core/SingleSource.subscribe:(Lio/reactivex/rxjava3/core/SingleObserver;)V
      21: return
}
