Compiled from "SingleMap.java"
final class io.reactivex.rxjava3.internal.operators.single.SingleMap$MapSingleObserver<T, R> implements io.reactivex.rxjava3.core.SingleObserver<T> {
  final io.reactivex.rxjava3.core.SingleObserver<? super R> t;

  final io.reactivex.rxjava3.functions.Function<? super T, ? extends R> mapper;

  io.reactivex.rxjava3.internal.operators.single.SingleMap$MapSingleObserver(io.reactivex.rxjava3.core.SingleObserver<? super R>, io.reactivex.rxjava3.functions.Function<? super T, ? extends R>);
    Code:
       0: aload_0
       1: invokespecial #1                  // Method java/lang/Object."<init>":()V
       4: aload_0
       5: aload_1
       6: putfield      #2                  // Field t:Lio/reactivex/rxjava3/core/SingleObserver;
       9: aload_0
      10: aload_2
      11: putfield      #3                  // Field mapper:Lio/reactivex/rxjava3/functions/Function;
      14: return

  public void onSubscribe(io.reactivex.rxjava3.disposables.Disposable);
    Code:
       0: aload_0
       1: getfield      #2                  // Field t:Lio/reactivex/rxjava3/core/SingleObserver;
       4: aload_1
       5: invokeinterface #4,  2            // InterfaceMethod io/reactivex/rxjava3/core/SingleObserver.onSubscribe:(Lio/reactivex/rxjava3/disposables/Disposable;)V
      10: return

  public void onSuccess(T);
    Code:
       0: aload_0
       1: getfield      #3                  // Field mapper:Lio/reactivex/rxjava3/functions/Function;
       4: aload_1
       5: invokeinterface #5,  2            // InterfaceMethod io/reactivex/rxjava3/functions/Function.apply:(Ljava/lang/Object;)Ljava/lang/Object;
      10: ldc           #6                  // String The mapper function returned a null value.
      12: invokestatic  #7                  // Method java/util/Objects.requireNonNull:(Ljava/lang/Object;Ljava/lang/String;)Ljava/lang/Object;
      15: astore_2
      16: goto          30
      19: astore_3
      20: aload_3
      21: invokestatic  #9                  // Method io/reactivex/rxjava3/exceptions/Exceptions.throwIfFatal:(Ljava/lang/Throwable;)V
      24: aload_0
      25: aload_3
      26: invokevirtual #10                 // Method onError:(Ljava/lang/Throwable;)V
      29: return
      30: aload_0
      31: getfield      #2                  // Field t:Lio/reactivex/rxjava3/core/SingleObserver;
      34: aload_2
      35: invokeinterface #11,  2           // InterfaceMethod io/reactivex/rxjava3/core/SingleObserver.onSuccess:(Ljava/lang/Object;)V
      40: return
    Exception table:
       from    to  target type
           0    16    19   Class java/lang/Throwable

  public void onError(java.lang.Throwable);
    Code:
       0: aload_0
       1: getfield      #2                  // Field t:Lio/reactivex/rxjava3/core/SingleObserver;
       4: aload_1
       5: invokeinterface #12,  2           // InterfaceMethod io/reactivex/rxjava3/core/SingleObserver.onError:(Ljava/lang/Throwable;)V
      10: return
}
