Compiled from "SingleOnErrorComplete.java"
public final class io.reactivex.rxjava3.internal.operators.single.SingleOnErrorComplete<T> extends io.reactivex.rxjava3.core.Maybe<T> {
  final io.reactivex.rxjava3.core.Single<T> source;

  final io.reactivex.rxjava3.functions.Predicate<? super java.lang.Throwable> predicate;

  public io.reactivex.rxjava3.internal.operators.single.SingleOnErrorComplete(io.reactivex.rxjava3.core.Single<T>, io.reactivex.rxjava3.functions.Predicate<? super java.lang.Throwable>);
    Code:
       0: aload_0
       1: invokespecial #1                  // Method io/reactivex/rxjava3/core/Maybe."<init>":()V
       4: aload_0
       5: aload_1
       6: putfield      #2                  // Field source:Lio/reactivex/rxjava3/core/Single;
       9: aload_0
      10: aload_2
      11: putfield      #3                  // Field predicate:Lio/reactivex/rxjava3/functions/Predicate;
      14: return

  protected void subscribeActual(io.reactivex.rxjava3.core.MaybeObserver<? super T>);
    Code:
       0: aload_0
       1: getfield      #2                  // Field source:Lio/reactivex/rxjava3/core/Single;
       4: new           #4                  // class io/reactivex/rxjava3/internal/operators/maybe/MaybeOnErrorComplete$OnErrorCompleteMultiObserver
       7: dup
       8: aload_1
       9: aload_0
      10: getfield      #3                  // Field predicate:Lio/reactivex/rxjava3/functions/Predicate;
      13: invokespecial #5                  // Method io/reactivex/rxjava3/internal/operators/maybe/MaybeOnErrorComplete$OnErrorCompleteMultiObserver."<init>":(Lio/reactivex/rxjava3/core/MaybeObserver;Lio/reactivex/rxjava3/functions/Predicate;)V
      16: invokevirtual #6                  // Method io/reactivex/rxjava3/core/Single.subscribe:(Lio/reactivex/rxjava3/core/SingleObserver;)V
      19: return
}
