Compiled from "SingleTimeInterval.java"
public final class io.reactivex.rxjava3.internal.operators.single.SingleTimeInterval<T> extends io.reactivex.rxjava3.core.Single<io.reactivex.rxjava3.schedulers.Timed<T>> {
  final io.reactivex.rxjava3.core.SingleSource<T> source;

  final java.util.concurrent.TimeUnit unit;

  final io.reactivex.rxjava3.core.Scheduler scheduler;

  final boolean start;

  public io.reactivex.rxjava3.internal.operators.single.SingleTimeInterval(io.reactivex.rxjava3.core.SingleSource<T>, java.util.concurrent.TimeUnit, io.reactivex.rxjava3.core.Scheduler, boolean);
    Code:
       0: aload_0
       1: invokespecial #1                  // Method io/reactivex/rxjava3/core/Single."<init>":()V
       4: aload_0
       5: aload_1
       6: putfield      #2                  // Field source:Lio/reactivex/rxjava3/core/SingleSource;
       9: aload_0
      10: aload_2
      11: putfield      #3                  // Field unit:Ljava/util/concurrent/TimeUnit;
      14: aload_0
      15: aload_3
      16: putfield      #4                  // Field scheduler:Lio/reactivex/rxjava3/core/Scheduler;
      19: aload_0
      20: iload         4
      22: putfield      #5                  // Field start:Z
      25: return

  protected void subscribeActual(io.reactivex.rxjava3.core.SingleObserver<? super io.reactivex.rxjava3.schedulers.Timed<T>>);
    Code:
       0: aload_0
       1: getfield      #2                  // Field source:Lio/reactivex/rxjava3/core/SingleSource;
       4: new           #6                  // class io/reactivex/rxjava3/internal/operators/single/SingleTimeInterval$TimeIntervalSingleObserver
       7: dup
       8: aload_1
       9: aload_0
      10: getfield      #3                  // Field unit:Ljava/util/concurrent/TimeUnit;
      13: aload_0
      14: getfield      #4                  // Field scheduler:Lio/reactivex/rxjava3/core/Scheduler;
      17: aload_0
      18: getfield      #5                  // Field start:Z
      21: invokespecial #7                  // Method io/reactivex/rxjava3/internal/operators/single/SingleTimeInterval$TimeIntervalSingleObserver."<init>":(Lio/reactivex/rxjava3/core/SingleObserver;Ljava/util/concurrent/TimeUnit;Lio/reactivex/rxjava3/core/Scheduler;Z)V
      24: invokeinterface #8,  2            // InterfaceMethod io/reactivex/rxjava3/core/SingleSource.subscribe:(Lio/reactivex/rxjava3/core/SingleObserver;)V
      29: return
}
