Compiled from "SingleOnErrorReturn.java"
final class io.reactivex.rxjava3.internal.operators.single.SingleOnErrorReturn$OnErrorReturn implements io.reactivex.rxjava3.core.SingleObserver<T> {
  private final io.reactivex.rxjava3.core.SingleObserver<? super T> observer;

  final io.reactivex.rxjava3.internal.operators.single.SingleOnErrorReturn this$0;

  io.reactivex.rxjava3.internal.operators.single.SingleOnErrorReturn$OnErrorReturn(io.reactivex.rxjava3.core.SingleObserver<? super T>);
    Code:
       0: aload_0
       1: aload_1
       2: putfield      #1                  // Field this$0:Lio/reactivex/rxjava3/internal/operators/single/SingleOnErrorReturn;
       5: aload_0
       6: invokespecial #2                  // Method java/lang/Object."<init>":()V
       9: aload_0
      10: aload_2
      11: putfield      #3                  // Field observer:Lio/reactivex/rxjava3/core/SingleObserver;
      14: return

  public void onError(java.lang.Throwable);
    Code:
       0: aload_0
       1: getfield      #1                  // Field this$0:Lio/reactivex/rxjava3/internal/operators/single/SingleOnErrorReturn;
       4: getfield      #4                  // Field io/reactivex/rxjava3/internal/operators/single/SingleOnErrorReturn.valueSupplier:Lio/reactivex/rxjava3/functions/Function;
       7: ifnull        61
      10: aload_0
      11: getfield      #1                  // Field this$0:Lio/reactivex/rxjava3/internal/operators/single/SingleOnErrorReturn;
      14: getfield      #4                  // Field io/reactivex/rxjava3/internal/operators/single/SingleOnErrorReturn.valueSupplier:Lio/reactivex/rxjava3/functions/Function;
      17: aload_1
      18: invokeinterface #5,  2            // InterfaceMethod io/reactivex/rxjava3/functions/Function.apply:(Ljava/lang/Object;)Ljava/lang/Object;
      23: astore_2
      24: goto          69
      27: astore_3
      28: aload_3
      29: invokestatic  #7                  // Method io/reactivex/rxjava3/exceptions/Exceptions.throwIfFatal:(Ljava/lang/Throwable;)V
      32: aload_0
      33: getfield      #3                  // Field observer:Lio/reactivex/rxjava3/core/SingleObserver;
      36: new           #8                  // class io/reactivex/rxjava3/exceptions/CompositeException
      39: dup
      40: iconst_2
      41: anewarray     #9                  // class java/lang/Throwable
      44: dup
      45: iconst_0
      46: aload_1
      47: aastore
      48: dup
      49: iconst_1
      50: aload_3
      51: aastore
      52: invokespecial #10                 // Method io/reactivex/rxjava3/exceptions/CompositeException."<init>":([Ljava/lang/Throwable;)V
      55: invokeinterface #11,  2           // InterfaceMethod io/reactivex/rxjava3/core/SingleObserver.onError:(Ljava/lang/Throwable;)V
      60: return
      61: aload_0
      62: getfield      #1                  // Field this$0:Lio/reactivex/rxjava3/internal/operators/single/SingleOnErrorReturn;
      65: getfield      #12                 // Field io/reactivex/rxjava3/internal/operators/single/SingleOnErrorReturn.value:Ljava/lang/Object;
      68: astore_2
      69: aload_2
      70: ifnonnull     100
      73: new           #13                 // class java/lang/NullPointerException
      76: dup
      77: ldc           #14                 // String Value supplied was null
      79: invokespecial #15                 // Method java/lang/NullPointerException."<init>":(Ljava/lang/String;)V
      82: astore_3
      83: aload_3
      84: aload_1
      85: invokevirtual #16                 // Method java/lang/NullPointerException.initCause:(Ljava/lang/Throwable;)Ljava/lang/Throwable;
      88: pop
      89: aload_0
      90: getfield      #3                  // Field observer:Lio/reactivex/rxjava3/core/SingleObserver;
      93: aload_3
      94: invokeinterface #11,  2           // InterfaceMethod io/reactivex/rxjava3/core/SingleObserver.onError:(Ljava/lang/Throwable;)V
      99: return
     100: aload_0
     101: getfield      #3                  // Field observer:Lio/reactivex/rxjava3/core/SingleObserver;
     104: aload_2
     105: invokeinterface #17,  2           // InterfaceMethod io/reactivex/rxjava3/core/SingleObserver.onSuccess:(Ljava/lang/Object;)V
     110: return
    Exception table:
       from    to  target type
          10    24    27   Class java/lang/Throwable

  public void onSubscribe(io.reactivex.rxjava3.disposables.Disposable);
    Code:
       0: aload_0
       1: getfield      #3                  // Field observer:Lio/reactivex/rxjava3/core/SingleObserver;
       4: aload_1
       5: invokeinterface #18,  2           // InterfaceMethod io/reactivex/rxjava3/core/SingleObserver.onSubscribe:(Lio/reactivex/rxjava3/disposables/Disposable;)V
      10: return

  public void onSuccess(T);
    Code:
       0: aload_0
       1: getfield      #3                  // Field observer:Lio/reactivex/rxjava3/core/SingleObserver;
       4: aload_1
       5: invokeinterface #17,  2           // InterfaceMethod io/reactivex/rxjava3/core/SingleObserver.onSuccess:(Ljava/lang/Object;)V
      10: return
}
