Compiled from "SingleTimer.java"
final class io.reactivex.rxjava3.internal.operators.single.SingleTimer$TimerDisposable extends java.util.concurrent.atomic.AtomicReference<io.reactivex.rxjava3.disposables.Disposable> implements io.reactivex.rxjava3.disposables.Disposable, java.lang.Runnable {
  private static final long serialVersionUID;

  final io.reactivex.rxjava3.core.SingleObserver<? super java.lang.Long> downstream;

  io.reactivex.rxjava3.internal.operators.single.SingleTimer$TimerDisposable(io.reactivex.rxjava3.core.SingleObserver<? super java.lang.Long>);
    Code:
       0: aload_0
       1: invokespecial #1                  // Method java/util/concurrent/atomic/AtomicReference."<init>":()V
       4: aload_0
       5: aload_1
       6: putfield      #2                  // Field downstream:Lio/reactivex/rxjava3/core/SingleObserver;
       9: return

  public void run();
    Code:
       0: aload_0
       1: getfield      #2                  // Field downstream:Lio/reactivex/rxjava3/core/SingleObserver;
       4: lconst_0
       5: invokestatic  #3                  // Method java/lang/Long.valueOf:(J)Ljava/lang/Long;
       8: invokeinterface #4,  2            // InterfaceMethod io/reactivex/rxjava3/core/SingleObserver.onSuccess:(Ljava/lang/Object;)V
      13: return

  public void dispose();
    Code:
       0: aload_0
       1: invokestatic  #5                  // Method io/reactivex/rxjava3/internal/disposables/DisposableHelper.dispose:(Ljava/util/concurrent/atomic/AtomicReference;)Z
       4: pop
       5: return

  public boolean isDisposed();
    Code:
       0: aload_0
       1: invokevirtual #6                  // Method get:()Ljava/lang/Object;
       4: checkcast     #7                  // class io/reactivex/rxjava3/disposables/Disposable
       7: invokestatic  #8                  // Method io/reactivex/rxjava3/internal/disposables/DisposableHelper.isDisposed:(Lio/reactivex/rxjava3/disposables/Disposable;)Z
      10: ireturn

  void setFuture(io.reactivex.rxjava3.disposables.Disposable);
    Code:
       0: aload_0
       1: aload_1
       2: invokestatic  #9                  // Method io/reactivex/rxjava3/internal/disposables/DisposableHelper.replace:(Ljava/util/concurrent/atomic/AtomicReference;Lio/reactivex/rxjava3/disposables/Disposable;)Z
       5: pop
       6: return
}
