Compiled from "SingleInternalHelper.java"
final class io.reactivex.rxjava3.internal.operators.single.SingleInternalHelper$NoSuchElementSupplier extends java.lang.Enum<io.reactivex.rxjava3.internal.operators.single.SingleInternalHelper$NoSuchElementSupplier> implements io.reactivex.rxjava3.functions.Supplier<java.util.NoSuchElementException> {
  public static final io.reactivex.rxjava3.internal.operators.single.SingleInternalHelper$NoSuchElementSupplier INSTANCE;

  private static final io.reactivex.rxjava3.internal.operators.single.SingleInternalHelper$NoSuchElementSupplier[] $VALUES;

  public static io.reactivex.rxjava3.internal.operators.single.SingleInternalHelper$NoSuchElementSupplier[] values();
    Code:
       0: getstatic     #1                  // Field $VALUES:[Lio/reactivex/rxjava3/internal/operators/single/SingleInternalHelper$NoSuchElementSupplier;
       3: invokevirtual #2                  // Method "[Lio/reactivex/rxjava3/internal/operators/single/SingleInternalHelper$NoSuchElementSupplier;".clone:()Ljava/lang/Object;
       6: checkcast     #3                  // class "[Lio/reactivex/rxjava3/internal/operators/single/SingleInternalHelper$NoSuchElementSupplier;"
       9: areturn

  public static io.reactivex.rxjava3.internal.operators.single.SingleInternalHelper$NoSuchElementSupplier valueOf(java.lang.String);
    Code:
       0: ldc           #4                  // class io/reactivex/rxjava3/internal/operators/single/SingleInternalHelper$NoSuchElementSupplier
       2: aload_0
       3: invokestatic  #5                  // Method java/lang/Enum.valueOf:(Ljava/lang/Class;Ljava/lang/String;)Ljava/lang/Enum;
       6: checkcast     #4                  // class io/reactivex/rxjava3/internal/operators/single/SingleInternalHelper$NoSuchElementSupplier
       9: areturn

  private io.reactivex.rxjava3.internal.operators.single.SingleInternalHelper$NoSuchElementSupplier();
    Code:
       0: aload_0
       1: aload_1
       2: iload_2
       3: invokespecial #6                  // Method java/lang/Enum."<init>":(Ljava/lang/String;I)V
       6: return

  public java.util.NoSuchElementException get();
    Code:
       0: new           #7                  // class java/util/NoSuchElementException
       3: dup
       4: invokespecial #8                  // Method java/util/NoSuchElementException."<init>":()V
       7: areturn

  public java.lang.Object get() throws java.lang.Throwable;
    Code:
       0: aload_0
       1: invokevirtual #9                  // Method get:()Ljava/util/NoSuchElementException;
       4: areturn

  static {};
    Code:
       0: new           #4                  // class io/reactivex/rxjava3/internal/operators/single/SingleInternalHelper$NoSuchElementSupplier
       3: dup
       4: ldc           #10                 // String INSTANCE
       6: iconst_0
       7: invokespecial #11                 // Method "<init>":(Ljava/lang/String;I)V
      10: putstatic     #12                 // Field INSTANCE:Lio/reactivex/rxjava3/internal/operators/single/SingleInternalHelper$NoSuchElementSupplier;
      13: iconst_1
      14: anewarray     #4                  // class io/reactivex/rxjava3/internal/operators/single/SingleInternalHelper$NoSuchElementSupplier
      17: dup
      18: iconst_0
      19: getstatic     #12                 // Field INSTANCE:Lio/reactivex/rxjava3/internal/operators/single/SingleInternalHelper$NoSuchElementSupplier;
      22: aastore
      23: putstatic     #1                  // Field $VALUES:[Lio/reactivex/rxjava3/internal/operators/single/SingleInternalHelper$NoSuchElementSupplier;
      26: return
}
