Compiled from "SingleJust.java"
public final class io.reactivex.rxjava3.internal.operators.single.SingleJust<T> extends io.reactivex.rxjava3.core.Single<T> {
  final T value;

  public io.reactivex.rxjava3.internal.operators.single.SingleJust(T);
    Code:
       0: aload_0
       1: invokespecial #1                  // Method io/reactivex/rxjava3/core/Single."<init>":()V
       4: aload_0
       5: aload_1
       6: putfield      #2                  // Field value:Ljava/lang/Object;
       9: return

  protected void subscribeActual(io.reactivex.rxjava3.core.SingleObserver<? super T>);
    Code:
       0: aload_1
       1: invokestatic  #3                  // InterfaceMethod io/reactivex/rxjava3/disposables/Disposable.disposed:()Lio/reactivex/rxjava3/disposables/Disposable;
       4: invokeinterface #4,  2            // InterfaceMethod io/reactivex/rxjava3/core/SingleObserver.onSubscribe:(Lio/reactivex/rxjava3/disposables/Disposable;)V
       9: aload_1
      10: aload_0
      11: getfield      #2                  // Field value:Ljava/lang/Object;
      14: invokeinterface #5,  2            // InterfaceMethod io/reactivex/rxjava3/core/SingleObserver.onSuccess:(Ljava/lang/Object;)V
      19: return
}
