Compiled from "SingleDefer.java"
public final class io.reactivex.rxjava3.internal.operators.single.SingleDefer<T> extends io.reactivex.rxjava3.core.Single<T> {
  final io.reactivex.rxjava3.functions.Supplier<? extends io.reactivex.rxjava3.core.SingleSource<? extends T>> singleSupplier;

  public io.reactivex.rxjava3.internal.operators.single.SingleDefer(io.reactivex.rxjava3.functions.Supplier<? extends io.reactivex.rxjava3.core.SingleSource<? extends T>>);
    Code:
       0: aload_0
       1: invokespecial #1                  // Method io/reactivex/rxjava3/core/Single."<init>":()V
       4: aload_0
       5: aload_1
       6: putfield      #2                  // Field singleSupplier:Lio/reactivex/rxjava3/functions/Supplier;
       9: return

  protected void subscribeActual(io.reactivex.rxjava3.core.SingleObserver<? super T>);
    Code:
       0: aload_0
       1: getfield      #2                  // Field singleSupplier:Lio/reactivex/rxjava3/functions/Supplier;
       4: invokeinterface #3,  1            // InterfaceMethod io/reactivex/rxjava3/functions/Supplier.get:()Ljava/lang/Object;
       9: ldc           #4                  // String The singleSupplier returned a null SingleSource
      11: invokestatic  #5                  // Method java/util/Objects.requireNonNull:(Ljava/lang/Object;Ljava/lang/String;)Ljava/lang/Object;
      14: checkcast     #6                  // class io/reactivex/rxjava3/core/SingleSource
      17: astore_2
      18: goto          32
      21: astore_3
      22: aload_3
      23: invokestatic  #8                  // Method io/reactivex/rxjava3/exceptions/Exceptions.throwIfFatal:(Ljava/lang/Throwable;)V
      26: aload_3
      27: aload_1
      28: invokestatic  #9                  // Method io/reactivex/rxjava3/internal/disposables/EmptyDisposable.error:(Ljava/lang/Throwable;Lio/reactivex/rxjava3/core/SingleObserver;)V
      31: return
      32: aload_2
      33: aload_1
      34: invokeinterface #10,  2           // InterfaceMethod io/reactivex/rxjava3/core/SingleSource.subscribe:(Lio/reactivex/rxjava3/core/SingleObserver;)V
      39: return
    Exception table:
       from    to  target type
           0    18    21   Class java/lang/Throwable
}
