Compiled from "SingleToObservable.java"
public final class io.reactivex.rxjava3.internal.operators.single.SingleToObservable<T> extends io.reactivex.rxjava3.core.Observable<T> {
  final io.reactivex.rxjava3.core.SingleSource<? extends T> source;

  public io.reactivex.rxjava3.internal.operators.single.SingleToObservable(io.reactivex.rxjava3.core.SingleSource<? extends T>);
    Code:
       0: aload_0
       1: invokespecial #1                  // Method io/reactivex/rxjava3/core/Observable."<init>":()V
       4: aload_0
       5: aload_1
       6: putfield      #2                  // Field source:Lio/reactivex/rxjava3/core/SingleSource;
       9: return

  public void subscribeActual(io.reactivex.rxjava3.core.Observer<? super T>);
    Code:
       0: aload_0
       1: getfield      #2                  // Field source:Lio/reactivex/rxjava3/core/SingleSource;
       4: aload_1
       5: invokestatic  #3                  // Method create:(Lio/reactivex/rxjava3/core/Observer;)Lio/reactivex/rxjava3/core/SingleObserver;
       8: invokeinterface #4,  2            // InterfaceMethod io/reactivex/rxjava3/core/SingleSource.subscribe:(Lio/reactivex/rxjava3/core/SingleObserver;)V
      13: return

  public static <T> io.reactivex.rxjava3.core.SingleObserver<T> create(io.reactivex.rxjava3.core.Observer<? super T>);
    Code:
       0: new           #5                  // class io/reactivex/rxjava3/internal/operators/single/SingleToObservable$SingleToObservableObserver
       3: dup
       4: aload_0
       5: invokespecial #6                  // Method io/reactivex/rxjava3/internal/operators/single/SingleToObservable$SingleToObservableObserver."<init>":(Lio/reactivex/rxjava3/core/Observer;)V
       8: areturn
}
