Compiled from "SingleEquals.java"
class io.reactivex.rxjava3.internal.operators.single.SingleEquals$InnerObserver<T> implements io.reactivex.rxjava3.core.SingleObserver<T> {
  final int index;

  final io.reactivex.rxjava3.disposables.CompositeDisposable set;

  final java.lang.Object[] values;

  final io.reactivex.rxjava3.core.SingleObserver<? super java.lang.Boolean> downstream;

  final java.util.concurrent.atomic.AtomicInteger count;

  io.reactivex.rxjava3.internal.operators.single.SingleEquals$InnerObserver(int, io.reactivex.rxjava3.disposables.CompositeDisposable, java.lang.Object[], io.reactivex.rxjava3.core.SingleObserver<? super java.lang.Boolean>, java.util.concurrent.atomic.AtomicInteger);
    Code:
       0: aload_0
       1: invokespecial #1                  // Method java/lang/Object."<init>":()V
       4: aload_0
       5: iload_1
       6: putfield      #2                  // Field index:I
       9: aload_0
      10: aload_2
      11: putfield      #3                  // Field set:Lio/reactivex/rxjava3/disposables/CompositeDisposable;
      14: aload_0
      15: aload_3
      16: putfield      #4                  // Field values:[Ljava/lang/Object;
      19: aload_0
      20: aload         4
      22: putfield      #5                  // Field downstream:Lio/reactivex/rxjava3/core/SingleObserver;
      25: aload_0
      26: aload         5
      28: putfield      #6                  // Field count:Ljava/util/concurrent/atomic/AtomicInteger;
      31: return

  public void onSubscribe(io.reactivex.rxjava3.disposables.Disposable);
    Code:
       0: aload_0
       1: getfield      #3                  // Field set:Lio/reactivex/rxjava3/disposables/CompositeDisposable;
       4: aload_1
       5: invokevirtual #7                  // Method io/reactivex/rxjava3/disposables/CompositeDisposable.add:(Lio/reactivex/rxjava3/disposables/Disposable;)Z
       8: pop
       9: return

  public void onSuccess(T);
    Code:
       0: aload_0
       1: getfield      #4                  // Field values:[Ljava/lang/Object;
       4: aload_0
       5: getfield      #2                  // Field index:I
       8: aload_1
       9: aastore
      10: aload_0
      11: getfield      #6                  // Field count:Ljava/util/concurrent/atomic/AtomicInteger;
      14: invokevirtual #8                  // Method java/util/concurrent/atomic/AtomicInteger.incrementAndGet:()I
      17: iconst_2
      18: if_icmpne     48
      21: aload_0
      22: getfield      #5                  // Field downstream:Lio/reactivex/rxjava3/core/SingleObserver;
      25: aload_0
      26: getfield      #4                  // Field values:[Ljava/lang/Object;
      29: iconst_0
      30: aaload
      31: aload_0
      32: getfield      #4                  // Field values:[Ljava/lang/Object;
      35: iconst_1
      36: aaload
      37: invokestatic  #9                  // Method java/util/Objects.equals:(Ljava/lang/Object;Ljava/lang/Object;)Z
      40: invokestatic  #10                 // Method java/lang/Boolean.valueOf:(Z)Ljava/lang/Boolean;
      43: invokeinterface #11,  2           // InterfaceMethod io/reactivex/rxjava3/core/SingleObserver.onSuccess:(Ljava/lang/Object;)V
      48: return

  public void onError(java.lang.Throwable);
    Code:
       0: aload_0
       1: getfield      #6                  // Field count:Ljava/util/concurrent/atomic/AtomicInteger;
       4: iconst_m1
       5: invokevirtual #12                 // Method java/util/concurrent/atomic/AtomicInteger.getAndSet:(I)I
       8: istore_2
       9: iload_2
      10: ifeq          18
      13: iload_2
      14: iconst_1
      15: if_icmpne     38
      18: aload_0
      19: getfield      #3                  // Field set:Lio/reactivex/rxjava3/disposables/CompositeDisposable;
      22: invokevirtual #13                 // Method io/reactivex/rxjava3/disposables/CompositeDisposable.dispose:()V
      25: aload_0
      26: getfield      #5                  // Field downstream:Lio/reactivex/rxjava3/core/SingleObserver;
      29: aload_1
      30: invokeinterface #14,  2           // InterfaceMethod io/reactivex/rxjava3/core/SingleObserver.onError:(Ljava/lang/Throwable;)V
      35: goto          42
      38: aload_1
      39: invokestatic  #15                 // Method io/reactivex/rxjava3/plugins/RxJavaPlugins.onError:(Ljava/lang/Throwable;)V
      42: return
}
