Compiled from "SingleDoOnLifecycle.java"
public final class io.reactivex.rxjava3.internal.operators.single.SingleDoOnLifecycle<T> extends io.reactivex.rxjava3.core.Single<T> {
  final io.reactivex.rxjava3.core.Single<T> source;

  final io.reactivex.rxjava3.functions.Consumer<? super io.reactivex.rxjava3.disposables.Disposable> onSubscribe;

  final io.reactivex.rxjava3.functions.Action onDispose;

  public io.reactivex.rxjava3.internal.operators.single.SingleDoOnLifecycle(io.reactivex.rxjava3.core.Single<T>, io.reactivex.rxjava3.functions.Consumer<? super io.reactivex.rxjava3.disposables.Disposable>, io.reactivex.rxjava3.functions.Action);
    Code:
       0: aload_0
       1: invokespecial #1                  // Method io/reactivex/rxjava3/core/Single."<init>":()V
       4: aload_0
       5: aload_1
       6: putfield      #2                  // Field source:Lio/reactivex/rxjava3/core/Single;
       9: aload_0
      10: aload_2
      11: putfield      #3                  // Field onSubscribe:Lio/reactivex/rxjava3/functions/Consumer;
      14: aload_0
      15: aload_3
      16: putfield      #4                  // Field onDispose:Lio/reactivex/rxjava3/functions/Action;
      19: return

  protected void subscribeActual(io.reactivex.rxjava3.core.SingleObserver<? super T>);
    Code:
       0: aload_0
       1: getfield      #2                  // Field source:Lio/reactivex/rxjava3/core/Single;
       4: new           #5                  // class io/reactivex/rxjava3/internal/operators/single/SingleDoOnLifecycle$SingleLifecycleObserver
       7: dup
       8: aload_1
       9: aload_0
      10: getfield      #3                  // Field onSubscribe:Lio/reactivex/rxjava3/functions/Consumer;
      13: aload_0
      14: getfield      #4                  // Field onDispose:Lio/reactivex/rxjava3/functions/Action;
      17: invokespecial #6                  // Method io/reactivex/rxjava3/internal/operators/single/SingleDoOnLifecycle$SingleLifecycleObserver."<init>":(Lio/reactivex/rxjava3/core/SingleObserver;Lio/reactivex/rxjava3/functions/Consumer;Lio/reactivex/rxjava3/functions/Action;)V
      20: invokevirtual #7                  // Method io/reactivex/rxjava3/core/Single.subscribe:(Lio/reactivex/rxjava3/core/SingleObserver;)V
      23: return
}
