Compiled from "SingleDelayWithCompletable.java"
public final class io.reactivex.rxjava3.internal.operators.single.SingleDelayWithCompletable<T> extends io.reactivex.rxjava3.core.Single<T> {
  final io.reactivex.rxjava3.core.SingleSource<T> source;

  final io.reactivex.rxjava3.core.CompletableSource other;

  public io.reactivex.rxjava3.internal.operators.single.SingleDelayWithCompletable(io.reactivex.rxjava3.core.SingleSource<T>, io.reactivex.rxjava3.core.CompletableSource);
    Code:
       0: aload_0
       1: invokespecial #1                  // Method io/reactivex/rxjava3/core/Single."<init>":()V
       4: aload_0
       5: aload_1
       6: putfield      #2                  // Field source:Lio/reactivex/rxjava3/core/SingleSource;
       9: aload_0
      10: aload_2
      11: putfield      #3                  // Field other:Lio/reactivex/rxjava3/core/CompletableSource;
      14: return

  protected void subscribeActual(io.reactivex.rxjava3.core.SingleObserver<? super T>);
    Code:
       0: aload_0
       1: getfield      #3                  // Field other:Lio/reactivex/rxjava3/core/CompletableSource;
       4: new           #4                  // class io/reactivex/rxjava3/internal/operators/single/SingleDelayWithCompletable$OtherObserver
       7: dup
       8: aload_1
       9: aload_0
      10: getfield      #2                  // Field source:Lio/reactivex/rxjava3/core/SingleSource;
      13: invokespecial #5                  // Method io/reactivex/rxjava3/internal/operators/single/SingleDelayWithCompletable$OtherObserver."<init>":(Lio/reactivex/rxjava3/core/SingleObserver;Lio/reactivex/rxjava3/core/SingleSource;)V
      16: invokeinterface #6,  2            // InterfaceMethod io/reactivex/rxjava3/core/CompletableSource.subscribe:(Lio/reactivex/rxjava3/core/CompletableObserver;)V
      21: return
}
