Compiled from "SingleTakeUntil.java"
final class io.reactivex.rxjava3.internal.operators.single.SingleTakeUntil$TakeUntilOtherSubscriber extends java.util.concurrent.atomic.AtomicReference<org.reactivestreams.Subscription> implements io.reactivex.rxjava3.core.FlowableSubscriber<java.lang.Object> {
  private static final long serialVersionUID;

  final io.reactivex.rxjava3.internal.operators.single.SingleTakeUntil$TakeUntilMainObserver<?> parent;

  io.reactivex.rxjava3.internal.operators.single.SingleTakeUntil$TakeUntilOtherSubscriber(io.reactivex.rxjava3.internal.operators.single.SingleTakeUntil$TakeUntilMainObserver<?>);
    Code:
       0: aload_0
       1: invokespecial #1                  // Method java/util/concurrent/atomic/AtomicReference."<init>":()V
       4: aload_0
       5: aload_1
       6: putfield      #2                  // Field parent:Lio/reactivex/rxjava3/internal/operators/single/SingleTakeUntil$TakeUntilMainObserver;
       9: return

  public void onSubscribe(org.reactivestreams.Subscription);
    Code:
       0: aload_0
       1: aload_1
       2: ldc2_w        #4                  // long 9223372036854775807l
       5: invokestatic  #6                  // Method io/reactivex/rxjava3/internal/subscriptions/SubscriptionHelper.setOnce:(Ljava/util/concurrent/atomic/AtomicReference;Lorg/reactivestreams/Subscription;J)Z
       8: pop
       9: return

  public void onNext(java.lang.Object);
    Code:
       0: aload_0
       1: invokestatic  #7                  // Method io/reactivex/rxjava3/internal/subscriptions/SubscriptionHelper.cancel:(Ljava/util/concurrent/atomic/AtomicReference;)Z
       4: ifeq          21
       7: aload_0
       8: getfield      #2                  // Field parent:Lio/reactivex/rxjava3/internal/operators/single/SingleTakeUntil$TakeUntilMainObserver;
      11: new           #8                  // class java/util/concurrent/CancellationException
      14: dup
      15: invokespecial #9                  // Method java/util/concurrent/CancellationException."<init>":()V
      18: invokevirtual #10                 // Method io/reactivex/rxjava3/internal/operators/single/SingleTakeUntil$TakeUntilMainObserver.otherError:(Ljava/lang/Throwable;)V
      21: return

  public void onError(java.lang.Throwable);
    Code:
       0: aload_0
       1: getfield      #2                  // Field parent:Lio/reactivex/rxjava3/internal/operators/single/SingleTakeUntil$TakeUntilMainObserver;
       4: aload_1
       5: invokevirtual #10                 // Method io/reactivex/rxjava3/internal/operators/single/SingleTakeUntil$TakeUntilMainObserver.otherError:(Ljava/lang/Throwable;)V
       8: return

  public void onComplete();
    Code:
       0: aload_0
       1: invokevirtual #11                 // Method get:()Ljava/lang/Object;
       4: getstatic     #12                 // Field io/reactivex/rxjava3/internal/subscriptions/SubscriptionHelper.CANCELLED:Lio/reactivex/rxjava3/internal/subscriptions/SubscriptionHelper;
       7: if_acmpeq     31
      10: aload_0
      11: getstatic     #12                 // Field io/reactivex/rxjava3/internal/subscriptions/SubscriptionHelper.CANCELLED:Lio/reactivex/rxjava3/internal/subscriptions/SubscriptionHelper;
      14: invokevirtual #13                 // Method lazySet:(Ljava/lang/Object;)V
      17: aload_0
      18: getfield      #2                  // Field parent:Lio/reactivex/rxjava3/internal/operators/single/SingleTakeUntil$TakeUntilMainObserver;
      21: new           #8                  // class java/util/concurrent/CancellationException
      24: dup
      25: invokespecial #9                  // Method java/util/concurrent/CancellationException."<init>":()V
      28: invokevirtual #10                 // Method io/reactivex/rxjava3/internal/operators/single/SingleTakeUntil$TakeUntilMainObserver.otherError:(Ljava/lang/Throwable;)V
      31: return

  public void dispose();
    Code:
       0: aload_0
       1: invokestatic  #7                  // Method io/reactivex/rxjava3/internal/subscriptions/SubscriptionHelper.cancel:(Ljava/util/concurrent/atomic/AtomicReference;)Z
       4: pop
       5: return
}
