Compiled from "SingleDelay.java"
public final class io.reactivex.rxjava3.internal.operators.single.SingleDelay<T> extends io.reactivex.rxjava3.core.Single<T> {
  final io.reactivex.rxjava3.core.SingleSource<? extends T> source;

  final long time;

  final java.util.concurrent.TimeUnit unit;

  final io.reactivex.rxjava3.core.Scheduler scheduler;

  final boolean delayError;

  public io.reactivex.rxjava3.internal.operators.single.SingleDelay(io.reactivex.rxjava3.core.SingleSource<? extends T>, long, java.util.concurrent.TimeUnit, io.reactivex.rxjava3.core.Scheduler, boolean);
    Code:
       0: aload_0
       1: invokespecial #1                  // Method io/reactivex/rxjava3/core/Single."<init>":()V
       4: aload_0
       5: aload_1
       6: putfield      #2                  // Field source:Lio/reactivex/rxjava3/core/SingleSource;
       9: aload_0
      10: lload_2
      11: putfield      #3                  // Field time:J
      14: aload_0
      15: aload         4
      17: putfield      #4                  // Field unit:Ljava/util/concurrent/TimeUnit;
      20: aload_0
      21: aload         5
      23: putfield      #5                  // Field scheduler:Lio/reactivex/rxjava3/core/Scheduler;
      26: aload_0
      27: iload         6
      29: putfield      #6                  // Field delayError:Z
      32: return

  protected void subscribeActual(io.reactivex.rxjava3.core.SingleObserver<? super T>);
    Code:
       0: new           #7                  // class io/reactivex/rxjava3/internal/disposables/SequentialDisposable
       3: dup
       4: invokespecial #8                  // Method io/reactivex/rxjava3/internal/disposables/SequentialDisposable."<init>":()V
       7: astore_2
       8: aload_1
       9: aload_2
      10: invokeinterface #9,  2            // InterfaceMethod io/reactivex/rxjava3/core/SingleObserver.onSubscribe:(Lio/reactivex/rxjava3/disposables/Disposable;)V
      15: aload_0
      16: getfield      #2                  // Field source:Lio/reactivex/rxjava3/core/SingleSource;
      19: new           #10                 // class io/reactivex/rxjava3/internal/operators/single/SingleDelay$Delay
      22: dup
      23: aload_0
      24: aload_2
      25: aload_1
      26: invokespecial #11                 // Method io/reactivex/rxjava3/internal/operators/single/SingleDelay$Delay."<init>":(Lio/reactivex/rxjava3/internal/operators/single/SingleDelay;Lio/reactivex/rxjava3/internal/disposables/SequentialDisposable;Lio/reactivex/rxjava3/core/SingleObserver;)V
      29: invokeinterface #12,  2           // InterfaceMethod io/reactivex/rxjava3/core/SingleSource.subscribe:(Lio/reactivex/rxjava3/core/SingleObserver;)V
      34: return
}
