Compiled from "SingleInternalHelper.java"
final class io.reactivex.rxjava3.internal.operators.single.SingleInternalHelper$ToFlowableIterable<T> implements java.lang.Iterable<io.reactivex.rxjava3.core.Flowable<T>> {
  private final java.lang.Iterable<? extends io.reactivex.rxjava3.core.SingleSource<? extends T>> sources;

  io.reactivex.rxjava3.internal.operators.single.SingleInternalHelper$ToFlowableIterable(java.lang.Iterable<? extends io.reactivex.rxjava3.core.SingleSource<? extends T>>);
    Code:
       0: aload_0
       1: invokespecial #1                  // Method java/lang/Object."<init>":()V
       4: aload_0
       5: aload_1
       6: putfield      #2                  // Field sources:Ljava/lang/Iterable;
       9: return

  public java.util.Iterator<io.reactivex.rxjava3.core.Flowable<T>> iterator();
    Code:
       0: new           #3                  // class io/reactivex/rxjava3/internal/operators/single/SingleInternalHelper$ToFlowableIterator
       3: dup
       4: aload_0
       5: getfield      #2                  // Field sources:Ljava/lang/Iterable;
       8: invokeinterface #4,  1            // InterfaceMethod java/lang/Iterable.iterator:()Ljava/util/Iterator;
      13: invokespecial #5                  // Method io/reactivex/rxjava3/internal/operators/single/SingleInternalHelper$ToFlowableIterator."<init>":(Ljava/util/Iterator;)V
      16: areturn
}
