Compiled from "SingleContains.java"
public final class io.reactivex.rxjava3.internal.operators.single.SingleContains<T> extends io.reactivex.rxjava3.core.Single<java.lang.Boolean> {
  final io.reactivex.rxjava3.core.SingleSource<T> source;

  final java.lang.Object value;

  final io.reactivex.rxjava3.functions.BiPredicate<java.lang.Object, java.lang.Object> comparer;

  public io.reactivex.rxjava3.internal.operators.single.SingleContains(io.reactivex.rxjava3.core.SingleSource<T>, java.lang.Object, io.reactivex.rxjava3.functions.BiPredicate<java.lang.Object, java.lang.Object>);
    Code:
       0: aload_0
       1: invokespecial #1                  // Method io/reactivex/rxjava3/core/Single."<init>":()V
       4: aload_0
       5: aload_1
       6: putfield      #2                  // Field source:Lio/reactivex/rxjava3/core/SingleSource;
       9: aload_0
      10: aload_2
      11: putfield      #3                  // Field value:Ljava/lang/Object;
      14: aload_0
      15: aload_3
      16: putfield      #4                  // Field comparer:Lio/reactivex/rxjava3/functions/BiPredicate;
      19: return

  protected void subscribeActual(io.reactivex.rxjava3.core.SingleObserver<? super java.lang.Boolean>);
    Code:
       0: aload_0
       1: getfield      #2                  // Field source:Lio/reactivex/rxjava3/core/SingleSource;
       4: new           #5                  // class io/reactivex/rxjava3/internal/operators/single/SingleContains$ContainsSingleObserver
       7: dup
       8: aload_0
       9: aload_1
      10: invokespecial #6                  // Method io/reactivex/rxjava3/internal/operators/single/SingleContains$ContainsSingleObserver."<init>":(Lio/reactivex/rxjava3/internal/operators/single/SingleContains;Lio/reactivex/rxjava3/core/SingleObserver;)V
      13: invokeinterface #7,  2            // InterfaceMethod io/reactivex/rxjava3/core/SingleSource.subscribe:(Lio/reactivex/rxjava3/core/SingleObserver;)V
      18: return
}
