Compiled from "SingleEquals.java"
public final class io.reactivex.rxjava3.internal.operators.single.SingleEquals<T> extends io.reactivex.rxjava3.core.Single<java.lang.Boolean> {
  final io.reactivex.rxjava3.core.SingleSource<? extends T> first;

  final io.reactivex.rxjava3.core.SingleSource<? extends T> second;

  public io.reactivex.rxjava3.internal.operators.single.SingleEquals(io.reactivex.rxjava3.core.SingleSource<? extends T>, io.reactivex.rxjava3.core.SingleSource<? extends T>);
    Code:
       0: aload_0
       1: invokespecial #1                  // Method io/reactivex/rxjava3/core/Single."<init>":()V
       4: aload_0
       5: aload_1
       6: putfield      #2                  // Field first:Lio/reactivex/rxjava3/core/SingleSource;
       9: aload_0
      10: aload_2
      11: putfield      #3                  // Field second:Lio/reactivex/rxjava3/core/SingleSource;
      14: return

  protected void subscribeActual(io.reactivex.rxjava3.core.SingleObserver<? super java.lang.Boolean>);
    Code:
       0: new           #4                  // class java/util/concurrent/atomic/AtomicInteger
       3: dup
       4: invokespecial #5                  // Method java/util/concurrent/atomic/AtomicInteger."<init>":()V
       7: astore_2
       8: iconst_2
       9: anewarray     #6                  // class java/lang/Object
      12: dup
      13: iconst_0
      14: aconst_null
      15: aastore
      16: dup
      17: iconst_1
      18: aconst_null
      19: aastore
      20: astore_3
      21: new           #7                  // class io/reactivex/rxjava3/disposables/CompositeDisposable
      24: dup
      25: invokespecial #8                  // Method io/reactivex/rxjava3/disposables/CompositeDisposable."<init>":()V
      28: astore        4
      30: aload_1
      31: aload         4
      33: invokeinterface #9,  2            // InterfaceMethod io/reactivex/rxjava3/core/SingleObserver.onSubscribe:(Lio/reactivex/rxjava3/disposables/Disposable;)V
      38: aload_0
      39: getfield      #2                  // Field first:Lio/reactivex/rxjava3/core/SingleSource;
      42: new           #10                 // class io/reactivex/rxjava3/internal/operators/single/SingleEquals$InnerObserver
      45: dup
      46: iconst_0
      47: aload         4
      49: aload_3
      50: aload_1
      51: aload_2
      52: invokespecial #11                 // Method io/reactivex/rxjava3/internal/operators/single/SingleEquals$InnerObserver."<init>":(ILio/reactivex/rxjava3/disposables/CompositeDisposable;[Ljava/lang/Object;Lio/reactivex/rxjava3/core/SingleObserver;Ljava/util/concurrent/atomic/AtomicInteger;)V
      55: invokeinterface #12,  2           // InterfaceMethod io/reactivex/rxjava3/core/SingleSource.subscribe:(Lio/reactivex/rxjava3/core/SingleObserver;)V
      60: aload_0
      61: getfield      #3                  // Field second:Lio/reactivex/rxjava3/core/SingleSource;
      64: new           #10                 // class io/reactivex/rxjava3/internal/operators/single/SingleEquals$InnerObserver
      67: dup
      68: iconst_1
      69: aload         4
      71: aload_3
      72: aload_1
      73: aload_2
      74: invokespecial #11                 // Method io/reactivex/rxjava3/internal/operators/single/SingleEquals$InnerObserver."<init>":(ILio/reactivex/rxjava3/disposables/CompositeDisposable;[Ljava/lang/Object;Lio/reactivex/rxjava3/core/SingleObserver;Ljava/util/concurrent/atomic/AtomicInteger;)V
      77: invokeinterface #12,  2           // InterfaceMethod io/reactivex/rxjava3/core/SingleSource.subscribe:(Lio/reactivex/rxjava3/core/SingleObserver;)V
      82: return
}
