Compiled from "SingleUsing.java"
public final class io.reactivex.rxjava3.internal.operators.single.SingleUsing<T, U> extends io.reactivex.rxjava3.core.Single<T> {
  final io.reactivex.rxjava3.functions.Supplier<U> resourceSupplier;

  final io.reactivex.rxjava3.functions.Function<? super U, ? extends io.reactivex.rxjava3.core.SingleSource<? extends T>> singleFunction;

  final io.reactivex.rxjava3.functions.Consumer<? super U> disposer;

  final boolean eager;

  public io.reactivex.rxjava3.internal.operators.single.SingleUsing(io.reactivex.rxjava3.functions.Supplier<U>, io.reactivex.rxjava3.functions.Function<? super U, ? extends io.reactivex.rxjava3.core.SingleSource<? extends T>>, io.reactivex.rxjava3.functions.Consumer<? super U>, boolean);
    Code:
       0: aload_0
       1: invokespecial #1                  // Method io/reactivex/rxjava3/core/Single."<init>":()V
       4: aload_0
       5: aload_1
       6: putfield      #2                  // Field resourceSupplier:Lio/reactivex/rxjava3/functions/Supplier;
       9: aload_0
      10: aload_2
      11: putfield      #3                  // Field singleFunction:Lio/reactivex/rxjava3/functions/Function;
      14: aload_0
      15: aload_3
      16: putfield      #4                  // Field disposer:Lio/reactivex/rxjava3/functions/Consumer;
      19: aload_0
      20: iload         4
      22: putfield      #5                  // Field eager:Z
      25: return

  protected void subscribeActual(io.reactivex.rxjava3.core.SingleObserver<? super T>);
    Code:
       0: aload_0
       1: getfield      #2                  // Field resourceSupplier:Lio/reactivex/rxjava3/functions/Supplier;
       4: invokeinterface #6,  1            // InterfaceMethod io/reactivex/rxjava3/functions/Supplier.get:()Ljava/lang/Object;
       9: astore_2
      10: goto          24
      13: astore_3
      14: aload_3
      15: invokestatic  #8                  // Method io/reactivex/rxjava3/exceptions/Exceptions.throwIfFatal:(Ljava/lang/Throwable;)V
      18: aload_3
      19: aload_1
      20: invokestatic  #9                  // Method io/reactivex/rxjava3/internal/disposables/EmptyDisposable.error:(Ljava/lang/Throwable;Lio/reactivex/rxjava3/core/SingleObserver;)V
      23: return
      24: aload_0
      25: getfield      #3                  // Field singleFunction:Lio/reactivex/rxjava3/functions/Function;
      28: aload_2
      29: invokeinterface #10,  2           // InterfaceMethod io/reactivex/rxjava3/functions/Function.apply:(Ljava/lang/Object;)Ljava/lang/Object;
      34: ldc           #11                 // String The singleFunction returned a null SingleSource
      36: invokestatic  #12                 // Method java/util/Objects.requireNonNull:(Ljava/lang/Object;Ljava/lang/String;)Ljava/lang/Object;
      39: checkcast     #13                 // class io/reactivex/rxjava3/core/SingleSource
      42: astore_3
      43: goto          142
      46: astore        4
      48: aload         4
      50: invokestatic  #8                  // Method io/reactivex/rxjava3/exceptions/Exceptions.throwIfFatal:(Ljava/lang/Throwable;)V
      53: aload_0
      54: getfield      #5                  // Field eager:Z
      57: ifeq          103
      60: aload_0
      61: getfield      #4                  // Field disposer:Lio/reactivex/rxjava3/functions/Consumer;
      64: aload_2
      65: invokeinterface #14,  2           // InterfaceMethod io/reactivex/rxjava3/functions/Consumer.accept:(Ljava/lang/Object;)V
      70: goto          103
      73: astore        5
      75: aload         5
      77: invokestatic  #8                  // Method io/reactivex/rxjava3/exceptions/Exceptions.throwIfFatal:(Ljava/lang/Throwable;)V
      80: new           #15                 // class io/reactivex/rxjava3/exceptions/CompositeException
      83: dup
      84: iconst_2
      85: anewarray     #16                 // class java/lang/Throwable
      88: dup
      89: iconst_0
      90: aload         4
      92: aastore
      93: dup
      94: iconst_1
      95: aload         5
      97: aastore
      98: invokespecial #17                 // Method io/reactivex/rxjava3/exceptions/CompositeException."<init>":([Ljava/lang/Throwable;)V
     101: astore        4
     103: aload         4
     105: aload_1
     106: invokestatic  #9                  // Method io/reactivex/rxjava3/internal/disposables/EmptyDisposable.error:(Ljava/lang/Throwable;Lio/reactivex/rxjava3/core/SingleObserver;)V
     109: aload_0
     110: getfield      #5                  // Field eager:Z
     113: ifne          141
     116: aload_0
     117: getfield      #4                  // Field disposer:Lio/reactivex/rxjava3/functions/Consumer;
     120: aload_2
     121: invokeinterface #14,  2           // InterfaceMethod io/reactivex/rxjava3/functions/Consumer.accept:(Ljava/lang/Object;)V
     126: goto          141
     129: astore        5
     131: aload         5
     133: invokestatic  #8                  // Method io/reactivex/rxjava3/exceptions/Exceptions.throwIfFatal:(Ljava/lang/Throwable;)V
     136: aload         5
     138: invokestatic  #18                 // Method io/reactivex/rxjava3/plugins/RxJavaPlugins.onError:(Ljava/lang/Throwable;)V
     141: return
     142: aload_3
     143: new           #19                 // class io/reactivex/rxjava3/internal/operators/single/SingleUsing$UsingSingleObserver
     146: dup
     147: aload_1
     148: aload_2
     149: aload_0
     150: getfield      #5                  // Field eager:Z
     153: aload_0
     154: getfield      #4                  // Field disposer:Lio/reactivex/rxjava3/functions/Consumer;
     157: invokespecial #20                 // Method io/reactivex/rxjava3/internal/operators/single/SingleUsing$UsingSingleObserver."<init>":(Lio/reactivex/rxjava3/core/SingleObserver;Ljava/lang/Object;ZLio/reactivex/rxjava3/functions/Consumer;)V
     160: invokeinterface #21,  2           // InterfaceMethod io/reactivex/rxjava3/core/SingleSource.subscribe:(Lio/reactivex/rxjava3/core/SingleObserver;)V
     165: return
    Exception table:
       from    to  target type
           0    10    13   Class java/lang/Throwable
          24    43    46   Class java/lang/Throwable
          60    70    73   Class java/lang/Throwable
         116   126   129   Class java/lang/Throwable
}
