Compiled from "SingleFromPublisher.java"
public final class io.reactivex.rxjava3.internal.operators.single.SingleFromPublisher<T> extends io.reactivex.rxjava3.core.Single<T> {
  final org.reactivestreams.Publisher<? extends T> publisher;

  public io.reactivex.rxjava3.internal.operators.single.SingleFromPublisher(org.reactivestreams.Publisher<? extends T>);
    Code:
       0: aload_0
       1: invokespecial #1                  // Method io/reactivex/rxjava3/core/Single."<init>":()V
       4: aload_0
       5: aload_1
       6: putfield      #2                  // Field publisher:Lorg/reactivestreams/Publisher;
       9: return

  protected void subscribeActual(io.reactivex.rxjava3.core.SingleObserver<? super T>);
    Code:
       0: aload_0
       1: getfield      #2                  // Field publisher:Lorg/reactivestreams/Publisher;
       4: new           #3                  // class io/reactivex/rxjava3/internal/operators/single/SingleFromPublisher$ToSingleObserver
       7: dup
       8: aload_1
       9: invokespecial #4                  // Method io/reactivex/rxjava3/internal/operators/single/SingleFromPublisher$ToSingleObserver."<init>":(Lio/reactivex/rxjava3/core/SingleObserver;)V
      12: invokeinterface #5,  2            // InterfaceMethod org/reactivestreams/Publisher.subscribe:(Lorg/reactivestreams/Subscriber;)V
      17: return
}
