Compiled from "SingleFlatMapNotification.java"
public final class io.reactivex.rxjava3.internal.operators.single.SingleFlatMapNotification<T, R> extends io.reactivex.rxjava3.core.Single<R> {
  final io.reactivex.rxjava3.core.SingleSource<T> source;

  final io.reactivex.rxjava3.functions.Function<? super T, ? extends io.reactivex.rxjava3.core.SingleSource<? extends R>> onSuccessMapper;

  final io.reactivex.rxjava3.functions.Function<? super java.lang.Throwable, ? extends io.reactivex.rxjava3.core.SingleSource<? extends R>> onErrorMapper;

  public io.reactivex.rxjava3.internal.operators.single.SingleFlatMapNotification(io.reactivex.rxjava3.core.SingleSource<T>, io.reactivex.rxjava3.functions.Function<? super T, ? extends io.reactivex.rxjava3.core.SingleSource<? extends R>>, io.reactivex.rxjava3.functions.Function<? super java.lang.Throwable, ? extends io.reactivex.rxjava3.core.SingleSource<? extends R>>);
    Code:
       0: aload_0
       1: invokespecial #1                  // Method io/reactivex/rxjava3/core/Single."<init>":()V
       4: aload_0
       5: aload_1
       6: putfield      #2                  // Field source:Lio/reactivex/rxjava3/core/SingleSource;
       9: aload_0
      10: aload_2
      11: putfield      #3                  // Field onSuccessMapper:Lio/reactivex/rxjava3/functions/Function;
      14: aload_0
      15: aload_3
      16: putfield      #4                  // Field onErrorMapper:Lio/reactivex/rxjava3/functions/Function;
      19: return

  protected void subscribeActual(io.reactivex.rxjava3.core.SingleObserver<? super R>);
    Code:
       0: aload_0
       1: getfield      #2                  // Field source:Lio/reactivex/rxjava3/core/SingleSource;
       4: new           #5                  // class io/reactivex/rxjava3/internal/operators/single/SingleFlatMapNotification$FlatMapSingleObserver
       7: dup
       8: aload_1
       9: aload_0
      10: getfield      #3                  // Field onSuccessMapper:Lio/reactivex/rxjava3/functions/Function;
      13: aload_0
      14: getfield      #4                  // Field onErrorMapper:Lio/reactivex/rxjava3/functions/Function;
      17: invokespecial #6                  // Method io/reactivex/rxjava3/internal/operators/single/SingleFlatMapNotification$FlatMapSingleObserver."<init>":(Lio/reactivex/rxjava3/core/SingleObserver;Lio/reactivex/rxjava3/functions/Function;Lio/reactivex/rxjava3/functions/Function;)V
      20: invokeinterface #7,  2            // InterfaceMethod io/reactivex/rxjava3/core/SingleSource.subscribe:(Lio/reactivex/rxjava3/core/SingleObserver;)V
      25: return
}
