Compiled from "SingleInternalHelper.java"
public final class io.reactivex.rxjava3.internal.operators.single.SingleInternalHelper {
  private io.reactivex.rxjava3.internal.operators.single.SingleInternalHelper();
    Code:
       0: aload_0
       1: invokespecial #1                  // Method java/lang/Object."<init>":()V
       4: new           #2                  // class java/lang/IllegalStateException
       7: dup
       8: ldc           #3                  // String No instances!
      10: invokespecial #4                  // Method java/lang/IllegalStateException."<init>":(Ljava/lang/String;)V
      13: athrow

  public static io.reactivex.rxjava3.functions.Supplier<java.util.NoSuchElementException> emptyThrower();
    Code:
       0: getstatic     #5                  // Field io/reactivex/rxjava3/internal/operators/single/SingleInternalHelper$NoSuchElementSupplier.INSTANCE:Lio/reactivex/rxjava3/internal/operators/single/SingleInternalHelper$NoSuchElementSupplier;
       3: areturn

  public static <T> io.reactivex.rxjava3.functions.Function<io.reactivex.rxjava3.core.SingleSource<? extends T>, org.reactivestreams.Publisher<? extends T>> toFlowable();
    Code:
       0: getstatic     #6                  // Field io/reactivex/rxjava3/internal/operators/single/SingleInternalHelper$ToFlowable.INSTANCE:Lio/reactivex/rxjava3/internal/operators/single/SingleInternalHelper$ToFlowable;
       3: areturn

  public static <T> java.lang.Iterable<? extends io.reactivex.rxjava3.core.Flowable<T>> iterableToFlowable(java.lang.Iterable<? extends io.reactivex.rxjava3.core.SingleSource<? extends T>>);
    Code:
       0: new           #7                  // class io/reactivex/rxjava3/internal/operators/single/SingleInternalHelper$ToFlowableIterable
       3: dup
       4: aload_0
       5: invokespecial #8                  // Method io/reactivex/rxjava3/internal/operators/single/SingleInternalHelper$ToFlowableIterable."<init>":(Ljava/lang/Iterable;)V
       8: areturn
}
