Compiled from "SingleResumeNext.java"
final class io.reactivex.rxjava3.internal.operators.single.SingleResumeNext$ResumeMainSingleObserver<T> extends java.util.concurrent.atomic.AtomicReference<io.reactivex.rxjava3.disposables.Disposable> implements io.reactivex.rxjava3.core.SingleObserver<T>, io.reactivex.rxjava3.disposables.Disposable {
  private static final long serialVersionUID;

  final io.reactivex.rxjava3.core.SingleObserver<? super T> downstream;

  final io.reactivex.rxjava3.functions.Function<? super java.lang.Throwable, ? extends io.reactivex.rxjava3.core.SingleSource<? extends T>> nextFunction;

  io.reactivex.rxjava3.internal.operators.single.SingleResumeNext$ResumeMainSingleObserver(io.reactivex.rxjava3.core.SingleObserver<? super T>, io.reactivex.rxjava3.functions.Function<? super java.lang.Throwable, ? extends io.reactivex.rxjava3.core.SingleSource<? extends T>>);
    Code:
       0: aload_0
       1: invokespecial #1                  // Method java/util/concurrent/atomic/AtomicReference."<init>":()V
       4: aload_0
       5: aload_1
       6: putfield      #2                  // Field downstream:Lio/reactivex/rxjava3/core/SingleObserver;
       9: aload_0
      10: aload_2
      11: putfield      #3                  // Field nextFunction:Lio/reactivex/rxjava3/functions/Function;
      14: return

  public void onSubscribe(io.reactivex.rxjava3.disposables.Disposable);
    Code:
       0: aload_0
       1: aload_1
       2: invokestatic  #4                  // Method io/reactivex/rxjava3/internal/disposables/DisposableHelper.setOnce:(Ljava/util/concurrent/atomic/AtomicReference;Lio/reactivex/rxjava3/disposables/Disposable;)Z
       5: ifeq          18
       8: aload_0
       9: getfield      #2                  // Field downstream:Lio/reactivex/rxjava3/core/SingleObserver;
      12: aload_0
      13: invokeinterface #5,  2            // InterfaceMethod io/reactivex/rxjava3/core/SingleObserver.onSubscribe:(Lio/reactivex/rxjava3/disposables/Disposable;)V
      18: return

  public void onSuccess(T);
    Code:
       0: aload_0
       1: getfield      #2                  // Field downstream:Lio/reactivex/rxjava3/core/SingleObserver;
       4: aload_1
       5: invokeinterface #6,  2            // InterfaceMethod io/reactivex/rxjava3/core/SingleObserver.onSuccess:(Ljava/lang/Object;)V
      10: return

  public void onError(java.lang.Throwable);
    Code:
       0: aload_0
       1: getfield      #3                  // Field nextFunction:Lio/reactivex/rxjava3/functions/Function;
       4: aload_1
       5: invokeinterface #7,  2            // InterfaceMethod io/reactivex/rxjava3/functions/Function.apply:(Ljava/lang/Object;)Ljava/lang/Object;
      10: ldc           #8                  // String The nextFunction returned a null SingleSource.
      12: invokestatic  #9                  // Method java/util/Objects.requireNonNull:(Ljava/lang/Object;Ljava/lang/String;)Ljava/lang/Object;
      15: checkcast     #10                 // class io/reactivex/rxjava3/core/SingleSource
      18: astore_2
      19: goto          56
      22: astore_3
      23: aload_3
      24: invokestatic  #12                 // Method io/reactivex/rxjava3/exceptions/Exceptions.throwIfFatal:(Ljava/lang/Throwable;)V
      27: aload_0
      28: getfield      #2                  // Field downstream:Lio/reactivex/rxjava3/core/SingleObserver;
      31: new           #13                 // class io/reactivex/rxjava3/exceptions/CompositeException
      34: dup
      35: iconst_2
      36: anewarray     #14                 // class java/lang/Throwable
      39: dup
      40: iconst_0
      41: aload_1
      42: aastore
      43: dup
      44: iconst_1
      45: aload_3
      46: aastore
      47: invokespecial #15                 // Method io/reactivex/rxjava3/exceptions/CompositeException."<init>":([Ljava/lang/Throwable;)V
      50: invokeinterface #16,  2           // InterfaceMethod io/reactivex/rxjava3/core/SingleObserver.onError:(Ljava/lang/Throwable;)V
      55: return
      56: aload_2
      57: new           #17                 // class io/reactivex/rxjava3/internal/observers/ResumeSingleObserver
      60: dup
      61: aload_0
      62: aload_0
      63: getfield      #2                  // Field downstream:Lio/reactivex/rxjava3/core/SingleObserver;
      66: invokespecial #18                 // Method io/reactivex/rxjava3/internal/observers/ResumeSingleObserver."<init>":(Ljava/util/concurrent/atomic/AtomicReference;Lio/reactivex/rxjava3/core/SingleObserver;)V
      69: invokeinterface #19,  2           // InterfaceMethod io/reactivex/rxjava3/core/SingleSource.subscribe:(Lio/reactivex/rxjava3/core/SingleObserver;)V
      74: return
    Exception table:
       from    to  target type
           0    19    22   Class java/lang/Throwable

  public void dispose();
    Code:
       0: aload_0
       1: invokestatic  #20                 // Method io/reactivex/rxjava3/internal/disposables/DisposableHelper.dispose:(Ljava/util/concurrent/atomic/AtomicReference;)Z
       4: pop
       5: return

  public boolean isDisposed();
    Code:
       0: aload_0
       1: invokevirtual #21                 // Method get:()Ljava/lang/Object;
       4: checkcast     #22                 // class io/reactivex/rxjava3/disposables/Disposable
       7: invokestatic  #23                 // Method io/reactivex/rxjava3/internal/disposables/DisposableHelper.isDisposed:(Lio/reactivex/rxjava3/disposables/Disposable;)Z
      10: ireturn
}
