Compiled from "SingleLift.java"
public final class io.reactivex.rxjava3.internal.operators.single.SingleLift<T, R> extends io.reactivex.rxjava3.core.Single<R> {
  final io.reactivex.rxjava3.core.SingleSource<T> source;

  final io.reactivex.rxjava3.core.SingleOperator<? extends R, ? super T> onLift;

  public io.reactivex.rxjava3.internal.operators.single.SingleLift(io.reactivex.rxjava3.core.SingleSource<T>, io.reactivex.rxjava3.core.SingleOperator<? extends R, ? super T>);
    Code:
       0: aload_0
       1: invokespecial #1                  // Method io/reactivex/rxjava3/core/Single."<init>":()V
       4: aload_0
       5: aload_1
       6: putfield      #2                  // Field source:Lio/reactivex/rxjava3/core/SingleSource;
       9: aload_0
      10: aload_2
      11: putfield      #3                  // Field onLift:Lio/reactivex/rxjava3/core/SingleOperator;
      14: return

  protected void subscribeActual(io.reactivex.rxjava3.core.SingleObserver<? super R>);
    Code:
       0: aload_0
       1: getfield      #3                  // Field onLift:Lio/reactivex/rxjava3/core/SingleOperator;
       4: aload_1
       5: invokeinterface #4,  2            // InterfaceMethod io/reactivex/rxjava3/core/SingleOperator.apply:(Lio/reactivex/rxjava3/core/SingleObserver;)Lio/reactivex/rxjava3/core/SingleObserver;
      10: ldc           #5                  // String The onLift returned a null SingleObserver
      12: invokestatic  #6                  // Method java/util/Objects.requireNonNull:(Ljava/lang/Object;Ljava/lang/String;)Ljava/lang/Object;
      15: checkcast     #7                  // class io/reactivex/rxjava3/core/SingleObserver
      18: astore_2
      19: goto          33
      22: astore_3
      23: aload_3
      24: invokestatic  #9                  // Method io/reactivex/rxjava3/exceptions/Exceptions.throwIfFatal:(Ljava/lang/Throwable;)V
      27: aload_3
      28: aload_1
      29: invokestatic  #10                 // Method io/reactivex/rxjava3/internal/disposables/EmptyDisposable.error:(Ljava/lang/Throwable;Lio/reactivex/rxjava3/core/SingleObserver;)V
      32: return
      33: aload_0
      34: getfield      #2                  // Field source:Lio/reactivex/rxjava3/core/SingleSource;
      37: aload_2
      38: invokeinterface #11,  2           // InterfaceMethod io/reactivex/rxjava3/core/SingleSource.subscribe:(Lio/reactivex/rxjava3/core/SingleObserver;)V
      43: return
    Exception table:
       from    to  target type
           0    19    22   Class java/lang/Throwable
}
