Compiled from "SingleFlatMapMaybe.java"
public final class io.reactivex.rxjava3.internal.operators.single.SingleFlatMapMaybe<T, R> extends io.reactivex.rxjava3.core.Maybe<R> {
  final io.reactivex.rxjava3.core.SingleSource<? extends T> source;

  final io.reactivex.rxjava3.functions.Function<? super T, ? extends io.reactivex.rxjava3.core.MaybeSource<? extends R>> mapper;

  public io.reactivex.rxjava3.internal.operators.single.SingleFlatMapMaybe(io.reactivex.rxjava3.core.SingleSource<? extends T>, io.reactivex.rxjava3.functions.Function<? super T, ? extends io.reactivex.rxjava3.core.MaybeSource<? extends R>>);
    Code:
       0: aload_0
       1: invokespecial #1                  // Method io/reactivex/rxjava3/core/Maybe."<init>":()V
       4: aload_0
       5: aload_2
       6: putfield      #2                  // Field mapper:Lio/reactivex/rxjava3/functions/Function;
       9: aload_0
      10: aload_1
      11: putfield      #3                  // Field source:Lio/reactivex/rxjava3/core/SingleSource;
      14: return

  protected void subscribeActual(io.reactivex.rxjava3.core.MaybeObserver<? super R>);
    Code:
       0: aload_0
       1: getfield      #3                  // Field source:Lio/reactivex/rxjava3/core/SingleSource;
       4: new           #4                  // class io/reactivex/rxjava3/internal/operators/single/SingleFlatMapMaybe$FlatMapSingleObserver
       7: dup
       8: aload_1
       9: aload_0
      10: getfield      #2                  // Field mapper:Lio/reactivex/rxjava3/functions/Function;
      13: invokespecial #5                  // Method io/reactivex/rxjava3/internal/operators/single/SingleFlatMapMaybe$FlatMapSingleObserver."<init>":(Lio/reactivex/rxjava3/core/MaybeObserver;Lio/reactivex/rxjava3/functions/Function;)V
      16: invokeinterface #6,  2            // InterfaceMethod io/reactivex/rxjava3/core/SingleSource.subscribe:(Lio/reactivex/rxjava3/core/SingleObserver;)V
      21: return
}
