Compiled from "SingleDelay.java"
final class io.reactivex.rxjava3.internal.operators.single.SingleDelay$Delay implements io.reactivex.rxjava3.core.SingleObserver<T> {
  private final io.reactivex.rxjava3.internal.disposables.SequentialDisposable sd;

  final io.reactivex.rxjava3.core.SingleObserver<? super T> downstream;

  final io.reactivex.rxjava3.internal.operators.single.SingleDelay this$0;

  io.reactivex.rxjava3.internal.operators.single.SingleDelay$Delay(io.reactivex.rxjava3.internal.disposables.SequentialDisposable, io.reactivex.rxjava3.core.SingleObserver<? super T>);
    Code:
       0: aload_0
       1: aload_1
       2: putfield      #1                  // Field this$0:Lio/reactivex/rxjava3/internal/operators/single/SingleDelay;
       5: aload_0
       6: invokespecial #2                  // Method java/lang/Object."<init>":()V
       9: aload_0
      10: aload_2
      11: putfield      #3                  // Field sd:Lio/reactivex/rxjava3/internal/disposables/SequentialDisposable;
      14: aload_0
      15: aload_3
      16: putfield      #4                  // Field downstream:Lio/reactivex/rxjava3/core/SingleObserver;
      19: return

  public void onSubscribe(io.reactivex.rxjava3.disposables.Disposable);
    Code:
       0: aload_0
       1: getfield      #3                  // Field sd:Lio/reactivex/rxjava3/internal/disposables/SequentialDisposable;
       4: aload_1
       5: invokevirtual #5                  // Method io/reactivex/rxjava3/internal/disposables/SequentialDisposable.replace:(Lio/reactivex/rxjava3/disposables/Disposable;)Z
       8: pop
       9: return

  public void onSuccess(T);
    Code:
       0: aload_0
       1: getfield      #3                  // Field sd:Lio/reactivex/rxjava3/internal/disposables/SequentialDisposable;
       4: aload_0
       5: getfield      #1                  // Field this$0:Lio/reactivex/rxjava3/internal/operators/single/SingleDelay;
       8: getfield      #6                  // Field io/reactivex/rxjava3/internal/operators/single/SingleDelay.scheduler:Lio/reactivex/rxjava3/core/Scheduler;
      11: new           #7                  // class io/reactivex/rxjava3/internal/operators/single/SingleDelay$Delay$OnSuccess
      14: dup
      15: aload_0
      16: aload_1
      17: invokespecial #8                  // Method io/reactivex/rxjava3/internal/operators/single/SingleDelay$Delay$OnSuccess."<init>":(Lio/reactivex/rxjava3/internal/operators/single/SingleDelay$Delay;Ljava/lang/Object;)V
      20: aload_0
      21: getfield      #1                  // Field this$0:Lio/reactivex/rxjava3/internal/operators/single/SingleDelay;
      24: getfield      #9                  // Field io/reactivex/rxjava3/internal/operators/single/SingleDelay.time:J
      27: aload_0
      28: getfield      #1                  // Field this$0:Lio/reactivex/rxjava3/internal/operators/single/SingleDelay;
      31: getfield      #10                 // Field io/reactivex/rxjava3/internal/operators/single/SingleDelay.unit:Ljava/util/concurrent/TimeUnit;
      34: invokevirtual #11                 // Method io/reactivex/rxjava3/core/Scheduler.scheduleDirect:(Ljava/lang/Runnable;JLjava/util/concurrent/TimeUnit;)Lio/reactivex/rxjava3/disposables/Disposable;
      37: invokevirtual #5                  // Method io/reactivex/rxjava3/internal/disposables/SequentialDisposable.replace:(Lio/reactivex/rxjava3/disposables/Disposable;)Z
      40: pop
      41: return

  public void onError(java.lang.Throwable);
    Code:
       0: aload_0
       1: getfield      #3                  // Field sd:Lio/reactivex/rxjava3/internal/disposables/SequentialDisposable;
       4: aload_0
       5: getfield      #1                  // Field this$0:Lio/reactivex/rxjava3/internal/operators/single/SingleDelay;
       8: getfield      #6                  // Field io/reactivex/rxjava3/internal/operators/single/SingleDelay.scheduler:Lio/reactivex/rxjava3/core/Scheduler;
      11: new           #12                 // class io/reactivex/rxjava3/internal/operators/single/SingleDelay$Delay$OnError
      14: dup
      15: aload_0
      16: aload_1
      17: invokespecial #13                 // Method io/reactivex/rxjava3/internal/operators/single/SingleDelay$Delay$OnError."<init>":(Lio/reactivex/rxjava3/internal/operators/single/SingleDelay$Delay;Ljava/lang/Throwable;)V
      20: aload_0
      21: getfield      #1                  // Field this$0:Lio/reactivex/rxjava3/internal/operators/single/SingleDelay;
      24: getfield      #14                 // Field io/reactivex/rxjava3/internal/operators/single/SingleDelay.delayError:Z
      27: ifeq          40
      30: aload_0
      31: getfield      #1                  // Field this$0:Lio/reactivex/rxjava3/internal/operators/single/SingleDelay;
      34: getfield      #9                  // Field io/reactivex/rxjava3/internal/operators/single/SingleDelay.time:J
      37: goto          41
      40: lconst_0
      41: aload_0
      42: getfield      #1                  // Field this$0:Lio/reactivex/rxjava3/internal/operators/single/SingleDelay;
      45: getfield      #10                 // Field io/reactivex/rxjava3/internal/operators/single/SingleDelay.unit:Ljava/util/concurrent/TimeUnit;
      48: invokevirtual #11                 // Method io/reactivex/rxjava3/core/Scheduler.scheduleDirect:(Ljava/lang/Runnable;JLjava/util/concurrent/TimeUnit;)Lio/reactivex/rxjava3/disposables/Disposable;
      51: invokevirtual #5                  // Method io/reactivex/rxjava3/internal/disposables/SequentialDisposable.replace:(Lio/reactivex/rxjava3/disposables/Disposable;)Z
      54: pop
      55: return
}
