Compiled from "SingleDoAfterSuccess.java"
public final class io.reactivex.rxjava3.internal.operators.single.SingleDoAfterSuccess<T> extends io.reactivex.rxjava3.core.Single<T> {
  final io.reactivex.rxjava3.core.SingleSource<T> source;

  final io.reactivex.rxjava3.functions.Consumer<? super T> onAfterSuccess;

  public io.reactivex.rxjava3.internal.operators.single.SingleDoAfterSuccess(io.reactivex.rxjava3.core.SingleSource<T>, io.reactivex.rxjava3.functions.Consumer<? super T>);
    Code:
       0: aload_0
       1: invokespecial #1                  // Method io/reactivex/rxjava3/core/Single."<init>":()V
       4: aload_0
       5: aload_1
       6: putfield      #2                  // Field source:Lio/reactivex/rxjava3/core/SingleSource;
       9: aload_0
      10: aload_2
      11: putfield      #3                  // Field onAfterSuccess:Lio/reactivex/rxjava3/functions/Consumer;
      14: return

  protected void subscribeActual(io.reactivex.rxjava3.core.SingleObserver<? super T>);
    Code:
       0: aload_0
       1: getfield      #2                  // Field source:Lio/reactivex/rxjava3/core/SingleSource;
       4: new           #4                  // class io/reactivex/rxjava3/internal/operators/single/SingleDoAfterSuccess$DoAfterObserver
       7: dup
       8: aload_1
       9: aload_0
      10: getfield      #3                  // Field onAfterSuccess:Lio/reactivex/rxjava3/functions/Consumer;
      13: invokespecial #5                  // Method io/reactivex/rxjava3/internal/operators/single/SingleDoAfterSuccess$DoAfterObserver."<init>":(Lio/reactivex/rxjava3/core/SingleObserver;Lio/reactivex/rxjava3/functions/Consumer;)V
      16: invokeinterface #6,  2            // InterfaceMethod io/reactivex/rxjava3/core/SingleSource.subscribe:(Lio/reactivex/rxjava3/core/SingleObserver;)V
      21: return
}
