Compiled from "SingleDelay.java"
final class io.reactivex.rxjava3.internal.operators.single.SingleDelay$Delay$OnError implements java.lang.Runnable {
  private final java.lang.Throwable e;

  final io.reactivex.rxjava3.internal.operators.single.SingleDelay$Delay this$1;

  io.reactivex.rxjava3.internal.operators.single.SingleDelay$Delay$OnError(io.reactivex.rxjava3.internal.operators.single.SingleDelay$Delay, java.lang.Throwable);
    Code:
       0: aload_0
       1: aload_1
       2: putfield      #1                  // Field this$1:Lio/reactivex/rxjava3/internal/operators/single/SingleDelay$Delay;
       5: aload_0
       6: invokespecial #2                  // Method java/lang/Object."<init>":()V
       9: aload_0
      10: aload_2
      11: putfield      #3                  // Field e:Ljava/lang/Throwable;
      14: return

  public void run();
    Code:
       0: aload_0
       1: getfield      #1                  // Field this$1:Lio/reactivex/rxjava3/internal/operators/single/SingleDelay$Delay;
       4: getfield      #4                  // Field io/reactivex/rxjava3/internal/operators/single/SingleDelay$Delay.downstream:Lio/reactivex/rxjava3/core/SingleObserver;
       7: aload_0
       8: getfield      #3                  // Field e:Ljava/lang/Throwable;
      11: invokeinterface #5,  2            // InterfaceMethod io/reactivex/rxjava3/core/SingleObserver.onError:(Ljava/lang/Throwable;)V
      16: return
}
