Compiled from "DubboConfigBeanCustomizer.java"
public interface org.apache.dubbo.config.spring.context.config.DubboConfigBeanCustomizer extends com.alibaba.spring.context.config.ConfigurationBeanCustomizer,org.springframework.core.Ordered {
  public abstract void customize(java.lang.String, org.apache.dubbo.config.AbstractConfig);

  public default void customize(java.lang.String, java.lang.Object);
    Code:
       0: aload_2
       1: instanceof    #1                  // class org/apache/dubbo/config/AbstractConfig
       4: ifeq          18
       7: aload_0
       8: aload_1
       9: aload_2
      10: checkcast     #1                  // class org/apache/dubbo/config/AbstractConfig
      13: invokeinterface #2,  3            // InterfaceMethod customize:(Ljava/lang/String;Lorg/apache/dubbo/config/AbstractConfig;)V
      18: return
}
