Compiled from "NamePropertyDefaultValueDubboConfigBeanCustomizer.java"
public class org.apache.dubbo.config.spring.context.config.NamePropertyDefaultValueDubboConfigBeanCustomizer implements org.apache.dubbo.config.spring.context.config.DubboConfigBeanCustomizer {
  public static final java.lang.String BEAN_NAME;

  private static final java.lang.String PROPERTY_NAME;

  public org.apache.dubbo.config.spring.context.config.NamePropertyDefaultValueDubboConfigBeanCustomizer();
    Code:
       0: aload_0
       1: invokespecial #1                  // Method java/lang/Object."<init>":()V
       4: return

  public void customize(java.lang.String, org.apache.dubbo.config.AbstractConfig);
    Code:
       0: aload_2
       1: invokevirtual #2                  // Method java/lang/Object.getClass:()Ljava/lang/Class;
       4: ldc           #4                  // String name
       6: invokestatic  #5                  // Method org/springframework/beans/BeanUtils.getPropertyDescriptor:(Ljava/lang/Class;Ljava/lang/String;)Ljava/beans/PropertyDescriptor;
       9: astore_3
      10: aload_3
      11: ifnull        89
      14: aload_3
      15: invokevirtual #6                  // Method java/beans/PropertyDescriptor.getReadMethod:()Ljava/lang/reflect/Method;
      18: astore        4
      20: aload         4
      22: ifnonnull     26
      25: return
      26: aload         4
      28: aload_2
      29: invokestatic  #7                  // Method org/springframework/util/ReflectionUtils.invokeMethod:(Ljava/lang/reflect/Method;Ljava/lang/Object;)Ljava/lang/Object;
      32: astore        5
      34: aload         5
      36: ifnull        40
      39: return
      40: aload_3
      41: invokevirtual #8                  // Method java/beans/PropertyDescriptor.getWriteMethod:()Ljava/lang/reflect/Method;
      44: astore        6
      46: aload         6
      48: ifnull        89
      51: iconst_1
      52: anewarray     #9                  // class java/lang/Class
      55: dup
      56: iconst_0
      57: ldc           #10                 // class java/lang/String
      59: aastore
      60: invokestatic  #11                 // Method com/alibaba/spring/util/ObjectUtils.of:([Ljava/lang/Object;)[Ljava/lang/Object;
      63: aload         6
      65: invokevirtual #12                 // Method java/lang/reflect/Method.getParameterTypes:()[Ljava/lang/Class;
      68: invokestatic  #13                 // Method java/util/Arrays.equals:([Ljava/lang/Object;[Ljava/lang/Object;)Z
      71: ifeq          89
      74: aload         6
      76: aload_2
      77: iconst_1
      78: anewarray     #14                 // class java/lang/Object
      81: dup
      82: iconst_0
      83: aload_1
      84: aastore
      85: invokestatic  #15                 // Method org/springframework/util/ReflectionUtils.invokeMethod:(Ljava/lang/reflect/Method;Ljava/lang/Object;[Ljava/lang/Object;)Ljava/lang/Object;
      88: pop
      89: return

  public int getOrder();
    Code:
       0: ldc           #17                 // int -2147483648
       2: ireturn
}
