Compiled from "ConfigurableSourceBeanMetadataElement.java"
public interface org.apache.dubbo.config.spring.beans.factory.config.ConfigurableSourceBeanMetadataElement {
  public default void setSource(org.springframework.beans.BeanMetadataElement);
    Code:
       0: aload_1
       1: instanceof    #1                  // class org/springframework/beans/BeanMetadataAttributeAccessor
       4: ifeq          15
       7: aload_1
       8: checkcast     #1                  // class org/springframework/beans/BeanMetadataAttributeAccessor
      11: aload_0
      12: invokevirtual #2                  // Method org/springframework/beans/BeanMetadataAttributeAccessor.setSource:(Ljava/lang/Object;)V
      15: return
}
