Compiled from "DubboConfigDefaultPropertyValueBeanPostProcessor.java"
public class org.apache.dubbo.config.spring.beans.factory.config.DubboConfigDefaultPropertyValueBeanPostProcessor extends com.alibaba.spring.beans.factory.config.GenericBeanPostProcessorAdapter<org.apache.dubbo.config.AbstractConfig> implements org.springframework.beans.factory.support.MergedBeanDefinitionPostProcessor, org.springframework.core.PriorityOrdered {
  public static final java.lang.String BEAN_NAME;

  public org.apache.dubbo.config.spring.beans.factory.config.DubboConfigDefaultPropertyValueBeanPostProcessor();
    Code:
       0: aload_0
       1: invokespecial #1                  // Method com/alibaba/spring/beans/factory/config/GenericBeanPostProcessorAdapter."<init>":()V
       4: return

  protected void processBeforeInitialization(org.apache.dubbo.config.AbstractConfig, java.lang.String) throws org.springframework.beans.BeansException;
    Code:
       0: aload_2
       1: ldc           #2                  // String #
       3: invokevirtual #3                  // Method java/lang/String.contains:(Ljava/lang/CharSequence;)Z
       6: ifne          17
       9: aload_0
      10: aload_1
      11: ldc           #5                  // String id
      13: aload_2
      14: invokevirtual #6                  // Method setPropertyIfAbsent:(Ljava/lang/Object;Ljava/lang/String;Ljava/lang/String;)V
      17: return

  public void postProcessMergedBeanDefinition(org.springframework.beans.factory.support.RootBeanDefinition, java.lang.Class<?>, java.lang.String);
    Code:
       0: return

  protected void setPropertyIfAbsent(java.lang.Object, java.lang.String, java.lang.String);
    Code:
       0: aload_1
       1: invokestatic  #7                  // Method org/springframework/aop/support/AopUtils.getTargetClass:(Ljava/lang/Object;)Ljava/lang/Class;
       4: astore        4
       6: aload         4
       8: aload_2
       9: invokestatic  #8                  // Method org/springframework/beans/BeanUtils.getPropertyDescriptor:(Ljava/lang/Class;Ljava/lang/String;)Ljava/beans/PropertyDescriptor;
      12: astore        5
      14: aload         5
      16: ifnull        96
      19: aload         5
      21: invokevirtual #9                  // Method java/beans/PropertyDescriptor.getReadMethod:()Ljava/lang/reflect/Method;
      24: astore        6
      26: aload         6
      28: ifnonnull     32
      31: return
      32: aload         6
      34: aload_1
      35: invokestatic  #10                 // Method org/springframework/util/ReflectionUtils.invokeMethod:(Ljava/lang/reflect/Method;Ljava/lang/Object;)Ljava/lang/Object;
      38: astore        7
      40: aload         7
      42: ifnull        46
      45: return
      46: aload         5
      48: invokevirtual #11                 // Method java/beans/PropertyDescriptor.getWriteMethod:()Ljava/lang/reflect/Method;
      51: astore        8
      53: aload         8
      55: ifnull        96
      58: iconst_1
      59: anewarray     #12                 // class java/lang/Class
      62: dup
      63: iconst_0
      64: ldc           #13                 // class java/lang/String
      66: aastore
      67: invokestatic  #14                 // Method com/alibaba/spring/util/ObjectUtils.of:([Ljava/lang/Object;)[Ljava/lang/Object;
      70: aload         8
      72: invokevirtual #15                 // Method java/lang/reflect/Method.getParameterTypes:()[Ljava/lang/Class;
      75: invokestatic  #16                 // Method java/util/Arrays.equals:([Ljava/lang/Object;[Ljava/lang/Object;)Z
      78: ifeq          96
      81: aload         8
      83: aload_1
      84: iconst_1
      85: anewarray     #17                 // class java/lang/Object
      88: dup
      89: iconst_0
      90: aload_3
      91: aastore
      92: invokestatic  #18                 // Method org/springframework/util/ReflectionUtils.invokeMethod:(Ljava/lang/reflect/Method;Ljava/lang/Object;[Ljava/lang/Object;)Ljava/lang/Object;
      95: pop
      96: return

  public int getOrder();
    Code:
       0: ldc           #20                 // int -2147483648
       2: ireturn

  protected void processBeforeInitialization(java.lang.Object, java.lang.String) throws org.springframework.beans.BeansException;
    Code:
       0: aload_0
       1: aload_1
       2: checkcast     #21                 // class org/apache/dubbo/config/AbstractConfig
       5: aload_2
       6: invokevirtual #22                 // Method processBeforeInitialization:(Lorg/apache/dubbo/config/AbstractConfig;Ljava/lang/String;)V
       9: return
}
