Compiled from "DubboServiceAddressURL.java"
public class org.apache.dubbo.common.url.component.DubboServiceAddressURL extends org.apache.dubbo.common.url.component.ServiceAddressURL {
  private org.apache.dubbo.common.url.component.ServiceConfigURL overrideURL;

  public static org.apache.dubbo.common.url.component.DubboServiceAddressURL valueOf(java.lang.String, org.apache.dubbo.common.URL);
    Code:
       0: aload_0
       1: aload_1
       2: aconst_null
       3: invokestatic  #2                  // Method valueOf:(Ljava/lang/String;Lorg/apache/dubbo/common/URL;Lorg/apache/dubbo/common/url/component/ServiceConfigURL;)Lorg/apache/dubbo/common/url/component/DubboServiceAddressURL;
       6: areturn

  public static org.apache.dubbo.common.url.component.DubboServiceAddressURL valueOf(java.lang.String, org.apache.dubbo.common.URL, org.apache.dubbo.common.url.component.ServiceConfigURL);
    Code:
       0: aload_0
       1: iconst_1
       2: invokestatic  #3                  // Method valueOf:(Ljava/lang/String;Z)Lorg/apache/dubbo/common/URL;
       5: astore_3
       6: new           #4                  // class org/apache/dubbo/common/url/component/DubboServiceAddressURL
       9: dup
      10: aload_3
      11: invokevirtual #5                  // Method org/apache/dubbo/common/URL.getUrlAddress:()Lorg/apache/dubbo/common/url/component/URLAddress;
      14: aload_3
      15: invokevirtual #6                  // Method org/apache/dubbo/common/URL.getUrlParam:()Lorg/apache/dubbo/common/url/component/URLParam;
      18: aload_1
      19: aload_2
      20: invokespecial #7                  // Method "<init>":(Lorg/apache/dubbo/common/url/component/URLAddress;Lorg/apache/dubbo/common/url/component/URLParam;Lorg/apache/dubbo/common/URL;Lorg/apache/dubbo/common/url/component/ServiceConfigURL;)V
      23: areturn

  public org.apache.dubbo.common.url.component.DubboServiceAddressURL(org.apache.dubbo.common.url.component.URLAddress, org.apache.dubbo.common.url.component.URLParam, org.apache.dubbo.common.URL, org.apache.dubbo.common.url.component.ServiceConfigURL);
    Code:
       0: aload_0
       1: aload_1
       2: aload_2
       3: aload_3
       4: invokespecial #8                  // Method org/apache/dubbo/common/url/component/ServiceAddressURL."<init>":(Lorg/apache/dubbo/common/url/component/URLAddress;Lorg/apache/dubbo/common/url/component/URLParam;Lorg/apache/dubbo/common/URL;)V
       7: aload_0
       8: aload         4
      10: putfield      #9                  // Field overrideURL:Lorg/apache/dubbo/common/url/component/ServiceConfigURL;
      13: return

  protected <T extends org.apache.dubbo.common.URL> T newURL(org.apache.dubbo.common.url.component.URLAddress, org.apache.dubbo.common.url.component.URLParam);
    Code:
       0: new           #4                  // class org/apache/dubbo/common/url/component/DubboServiceAddressURL
       3: dup
       4: aload_1
       5: aload_2
       6: aload_0
       7: getfield      #10                 // Field consumerURL:Lorg/apache/dubbo/common/URL;
      10: aload_0
      11: getfield      #9                  // Field overrideURL:Lorg/apache/dubbo/common/url/component/ServiceConfigURL;
      14: invokespecial #7                  // Method "<init>":(Lorg/apache/dubbo/common/url/component/URLAddress;Lorg/apache/dubbo/common/url/component/URLParam;Lorg/apache/dubbo/common/URL;Lorg/apache/dubbo/common/url/component/ServiceConfigURL;)V
      17: areturn

  public java.lang.String getSide();
    Code:
       0: aload_0
       1: getfield      #10                 // Field consumerURL:Lorg/apache/dubbo/common/URL;
       4: ldc           #11                 // String side
       6: invokevirtual #12                 // Method org/apache/dubbo/common/URL.getParameter:(Ljava/lang/String;)Ljava/lang/String;
       9: areturn

  public java.lang.String getParameter(java.lang.String);
    Code:
       0: aconst_null
       1: astore_2
       2: aload_0
       3: getfield      #9                  // Field overrideURL:Lorg/apache/dubbo/common/url/component/ServiceConfigURL;
       6: ifnull        18
       9: aload_0
      10: getfield      #9                  // Field overrideURL:Lorg/apache/dubbo/common/url/component/ServiceConfigURL;
      13: aload_1
      14: invokevirtual #13                 // Method org/apache/dubbo/common/url/component/ServiceConfigURL.getParameter:(Ljava/lang/String;)Ljava/lang/String;
      17: astore_2
      18: aload_2
      19: invokestatic  #14                 // Method org/apache/dubbo/common/utils/StringUtils.isEmpty:(Ljava/lang/String;)Z
      22: ifeq          31
      25: aload_0
      26: aload_1
      27: invokespecial #15                 // Method org/apache/dubbo/common/url/component/ServiceAddressURL.getParameter:(Ljava/lang/String;)Ljava/lang/String;
      30: astore_2
      31: aload_2
      32: areturn

  public java.lang.String getMethodParameter(java.lang.String, java.lang.String);
    Code:
       0: aconst_null
       1: astore_3
       2: aload_0
       3: getfield      #9                  // Field overrideURL:Lorg/apache/dubbo/common/url/component/ServiceConfigURL;
       6: ifnull        19
       9: aload_0
      10: getfield      #9                  // Field overrideURL:Lorg/apache/dubbo/common/url/component/ServiceConfigURL;
      13: aload_1
      14: aload_2
      15: invokevirtual #16                 // Method org/apache/dubbo/common/url/component/ServiceConfigURL.getMethodParameterStrict:(Ljava/lang/String;Ljava/lang/String;)Ljava/lang/String;
      18: astore_3
      19: aload_3
      20: invokestatic  #14                 // Method org/apache/dubbo/common/utils/StringUtils.isEmpty:(Ljava/lang/String;)Z
      23: ifeq          33
      26: aload_0
      27: aload_1
      28: aload_2
      29: invokespecial #17                 // Method org/apache/dubbo/common/url/component/ServiceAddressURL.getMethodParameter:(Ljava/lang/String;Ljava/lang/String;)Ljava/lang/String;
      32: astore_3
      33: aload_3
      34: areturn

  public java.lang.String getAnyMethodParameter(java.lang.String);
    Code:
       0: aconst_null
       1: astore_2
       2: aload_0
       3: getfield      #9                  // Field overrideURL:Lorg/apache/dubbo/common/url/component/ServiceConfigURL;
       6: ifnull        18
       9: aload_0
      10: getfield      #9                  // Field overrideURL:Lorg/apache/dubbo/common/url/component/ServiceConfigURL;
      13: aload_1
      14: invokevirtual #18                 // Method org/apache/dubbo/common/url/component/ServiceConfigURL.getAnyMethodParameter:(Ljava/lang/String;)Ljava/lang/String;
      17: astore_2
      18: aload_2
      19: invokestatic  #14                 // Method org/apache/dubbo/common/utils/StringUtils.isEmpty:(Ljava/lang/String;)Z
      22: ifeq          31
      25: aload_0
      26: aload_1
      27: invokespecial #19                 // Method org/apache/dubbo/common/url/component/ServiceAddressURL.getAnyMethodParameter:(Ljava/lang/String;)Ljava/lang/String;
      30: astore_2
      31: aload_2
      32: areturn

  public java.util.Map<java.lang.String, java.lang.String> getAllParameters();
    Code:
       0: new           #20                 // class java/util/HashMap
       3: dup
       4: aload_0
       5: invokespecial #21                 // Method org/apache/dubbo/common/url/component/ServiceAddressURL.getParameters:()Ljava/util/Map;
       8: invokeinterface #22,  1           // InterfaceMethod java/util/Map.size:()I
      13: i2d
      14: ldc2_w        #23                 // double 0.75d
      17: ddiv
      18: dconst_1
      19: dadd
      20: d2i
      21: invokespecial #25                 // Method java/util/HashMap."<init>":(I)V
      24: astore_1
      25: aload_1
      26: aload_0
      27: invokespecial #21                 // Method org/apache/dubbo/common/url/component/ServiceAddressURL.getParameters:()Ljava/util/Map;
      30: invokeinterface #26,  2           // InterfaceMethod java/util/Map.putAll:(Ljava/util/Map;)V
      35: aload_0
      36: getfield      #10                 // Field consumerURL:Lorg/apache/dubbo/common/URL;
      39: ifnull        55
      42: aload_1
      43: aload_0
      44: getfield      #10                 // Field consumerURL:Lorg/apache/dubbo/common/URL;
      47: invokevirtual #27                 // Method org/apache/dubbo/common/URL.getParameters:()Ljava/util/Map;
      50: invokeinterface #26,  2           // InterfaceMethod java/util/Map.putAll:(Ljava/util/Map;)V
      55: aload_0
      56: getfield      #9                  // Field overrideURL:Lorg/apache/dubbo/common/url/component/ServiceConfigURL;
      59: ifnull        75
      62: aload_1
      63: aload_0
      64: getfield      #9                  // Field overrideURL:Lorg/apache/dubbo/common/url/component/ServiceConfigURL;
      67: invokevirtual #28                 // Method org/apache/dubbo/common/url/component/ServiceConfigURL.getParameters:()Ljava/util/Map;
      70: invokeinterface #26,  2           // InterfaceMethod java/util/Map.putAll:(Ljava/util/Map;)V
      75: aload_1
      76: invokestatic  #29                 // Method java/util/Collections.unmodifiableMap:(Ljava/util/Map;)Ljava/util/Map;
      79: areturn

  public org.apache.dubbo.common.url.component.ServiceConfigURL getOverrideURL();
    Code:
       0: aload_0
       1: getfield      #9                  // Field overrideURL:Lorg/apache/dubbo/common/url/component/ServiceConfigURL;
       4: areturn

  public void setOverrideURL(org.apache.dubbo.common.url.component.ServiceConfigURL);
    Code:
       0: aload_0
       1: aload_1
       2: putfield      #9                  // Field overrideURL:Lorg/apache/dubbo/common/url/component/ServiceConfigURL;
       5: return

  public org.apache.dubbo.rpc.model.ScopeModel getScopeModel();
    Code:
       0: aload_0
       1: getfield      #10                 // Field consumerURL:Lorg/apache/dubbo/common/URL;
       4: invokevirtual #30                 // Method org/apache/dubbo/common/URL.getScopeModel:()Lorg/apache/dubbo/rpc/model/ScopeModel;
       7: areturn

  public org.apache.dubbo.rpc.model.ServiceModel getServiceModel();
    Code:
       0: aload_0
       1: getfield      #10                 // Field consumerURL:Lorg/apache/dubbo/common/URL;
       4: invokevirtual #31                 // Method org/apache/dubbo/common/URL.getServiceModel:()Lorg/apache/dubbo/rpc/model/ServiceModel;
       7: areturn

  public int hashCode();
    Code:
       0: bipush        31
       2: istore_1
       3: bipush        31
       5: aload_0
       6: invokespecial #32                 // Method org/apache/dubbo/common/url/component/ServiceAddressURL.hashCode:()I
       9: imul
      10: aload_0
      11: getfield      #9                  // Field overrideURL:Lorg/apache/dubbo/common/url/component/ServiceConfigURL;
      14: ifnonnull     21
      17: iconst_0
      18: goto          28
      21: aload_0
      22: getfield      #9                  // Field overrideURL:Lorg/apache/dubbo/common/url/component/ServiceConfigURL;
      25: invokevirtual #33                 // Method org/apache/dubbo/common/url/component/ServiceConfigURL.hashCode:()I
      28: iadd
      29: ireturn

  public boolean equals(java.lang.Object);
    Code:
       0: aload_0
       1: aload_1
       2: if_acmpne     7
       5: iconst_1
       6: ireturn
       7: aload_1
       8: ifnonnull     13
      11: iconst_0
      12: ireturn
      13: aload_1
      14: instanceof    #4                  // class org/apache/dubbo/common/url/component/DubboServiceAddressURL
      17: ifne          22
      20: iconst_0
      21: ireturn
      22: aload_0
      23: getfield      #9                  // Field overrideURL:Lorg/apache/dubbo/common/url/component/ServiceConfigURL;
      26: ifnonnull     35
      29: aload_0
      30: aload_1
      31: invokespecial #34                 // Method org/apache/dubbo/common/url/component/ServiceAddressURL.equals:(Ljava/lang/Object;)Z
      34: ireturn
      35: aload_1
      36: checkcast     #4                  // class org/apache/dubbo/common/url/component/DubboServiceAddressURL
      39: astore_2
      40: aload_0
      41: getfield      #9                  // Field overrideURL:Lorg/apache/dubbo/common/url/component/ServiceConfigURL;
      44: invokevirtual #28                 // Method org/apache/dubbo/common/url/component/ServiceConfigURL.getParameters:()Ljava/util/Map;
      47: aload_2
      48: invokevirtual #35                 // Method getOverrideURL:()Lorg/apache/dubbo/common/url/component/ServiceConfigURL;
      51: invokevirtual #28                 // Method org/apache/dubbo/common/url/component/ServiceConfigURL.getParameters:()Ljava/util/Map;
      54: invokestatic  #36                 // Method java/util/Objects.equals:(Ljava/lang/Object;Ljava/lang/Object;)Z
      57: istore_3
      58: iload_3
      59: ifne          64
      62: iconst_0
      63: ireturn
      64: aload_0
      65: invokevirtual #37                 // Method getParameters:()Ljava/util/Map;
      68: astore        4
      70: aload         4
      72: invokeinterface #38,  1           // InterfaceMethod java/util/Map.entrySet:()Ljava/util/Set;
      77: invokeinterface #39,  1           // InterfaceMethod java/util/Set.iterator:()Ljava/util/Iterator;
      82: astore        5
      84: aload         5
      86: invokeinterface #40,  1           // InterfaceMethod java/util/Iterator.hasNext:()Z
      91: ifeq          168
      94: aload         5
      96: invokeinterface #41,  1           // InterfaceMethod java/util/Iterator.next:()Ljava/lang/Object;
     101: checkcast     #42                 // class java/util/Map$Entry
     104: astore        6
     106: aload         6
     108: invokeinterface #43,  1           // InterfaceMethod java/util/Map$Entry.getKey:()Ljava/lang/Object;
     113: checkcast     #44                 // class java/lang/String
     116: astore        7
     118: aload_0
     119: getfield      #9                  // Field overrideURL:Lorg/apache/dubbo/common/url/component/ServiceConfigURL;
     122: invokevirtual #28                 // Method org/apache/dubbo/common/url/component/ServiceConfigURL.getParameters:()Ljava/util/Map;
     125: aload         7
     127: invokeinterface #45,  2           // InterfaceMethod java/util/Map.containsKey:(Ljava/lang/Object;)Z
     132: ifeq          138
     135: goto          84
     138: aload         6
     140: invokeinterface #46,  1           // InterfaceMethod java/util/Map$Entry.getValue:()Ljava/lang/Object;
     145: checkcast     #44                 // class java/lang/String
     148: aload_2
     149: invokevirtual #47                 // Method getUrlParam:()Lorg/apache/dubbo/common/url/component/URLParam;
     152: aload         7
     154: invokevirtual #48                 // Method org/apache/dubbo/common/url/component/URLParam.getParameter:(Ljava/lang/String;)Ljava/lang/String;
     157: invokevirtual #49                 // Method java/lang/String.equals:(Ljava/lang/Object;)Z
     160: ifne          165
     163: iconst_0
     164: ireturn
     165: goto          84
     168: iconst_1
     169: ireturn
}
