Compiled from "PathURLAddress.java"
public class org.apache.dubbo.common.url.component.PathURLAddress extends org.apache.dubbo.common.url.component.URLAddress {
  private java.lang.String protocol;

  private java.lang.String username;

  private java.lang.String password;

  private java.lang.String path;

  private transient java.lang.String address;

  private transient java.lang.String ip;

  public org.apache.dubbo.common.url.component.PathURLAddress(java.lang.String, java.lang.String, java.lang.String, java.lang.String, java.lang.String, int);
    Code:
       0: aload_0
       1: aload_1
       2: aload_2
       3: aload_3
       4: aload         4
       6: aload         5
       8: iload         6
      10: aconst_null
      11: invokespecial #1                  // Method "<init>":(Ljava/lang/String;Ljava/lang/String;Ljava/lang/String;Ljava/lang/String;Ljava/lang/String;ILjava/lang/String;)V
      14: return

  public org.apache.dubbo.common.url.component.PathURLAddress(java.lang.String, java.lang.String, java.lang.String, java.lang.String, java.lang.String, int, java.lang.String);
    Code:
       0: aload_0
       1: aload         5
       3: iload         6
       5: aload         7
       7: invokespecial #2                  // Method org/apache/dubbo/common/url/component/URLAddress."<init>":(Ljava/lang/String;ILjava/lang/String;)V
      10: aload_0
      11: aload_1
      12: putfield      #3                  // Field protocol:Ljava/lang/String;
      15: aload_0
      16: aload_2
      17: putfield      #4                  // Field username:Ljava/lang/String;
      20: aload_0
      21: aload_3
      22: putfield      #5                  // Field password:Ljava/lang/String;
      25: aload         4
      27: ifnull        51
      30: aload         4
      32: ldc           #6                  // String /
      34: invokevirtual #7                  // Method java/lang/String.startsWith:(Ljava/lang/String;)Z
      37: ifeq          51
      40: aload         4
      42: iconst_1
      43: invokevirtual #8                  // Method java/lang/String.substring:(I)Ljava/lang/String;
      46: astore        4
      48: goto          25
      51: aload         4
      53: ifnull        63
      56: aload         4
      58: invokevirtual #9                  // Method java/lang/String.intern:()Ljava/lang/String;
      61: astore        4
      63: aload_0
      64: aload         4
      66: putfield      #10                 // Field path:Ljava/lang/String;
      69: return

  public java.lang.String getProtocol();
    Code:
       0: aload_0
       1: getfield      #3                  // Field protocol:Ljava/lang/String;
       4: areturn

  public org.apache.dubbo.common.url.component.URLAddress setProtocol(java.lang.String);
    Code:
       0: new           #11                 // class org/apache/dubbo/common/url/component/PathURLAddress
       3: dup
       4: aload_1
       5: aload_0
       6: getfield      #4                  // Field username:Ljava/lang/String;
       9: aload_0
      10: getfield      #5                  // Field password:Ljava/lang/String;
      13: aload_0
      14: getfield      #10                 // Field path:Ljava/lang/String;
      17: aload_0
      18: getfield      #12                 // Field host:Ljava/lang/String;
      21: aload_0
      22: getfield      #13                 // Field port:I
      25: aload_0
      26: getfield      #14                 // Field rawAddress:Ljava/lang/String;
      29: invokespecial #1                  // Method "<init>":(Ljava/lang/String;Ljava/lang/String;Ljava/lang/String;Ljava/lang/String;Ljava/lang/String;ILjava/lang/String;)V
      32: areturn

  public java.lang.String getUsername();
    Code:
       0: aload_0
       1: getfield      #4                  // Field username:Ljava/lang/String;
       4: areturn

  public org.apache.dubbo.common.url.component.URLAddress setUsername(java.lang.String);
    Code:
       0: new           #11                 // class org/apache/dubbo/common/url/component/PathURLAddress
       3: dup
       4: aload_0
       5: getfield      #3                  // Field protocol:Ljava/lang/String;
       8: aload_1
       9: aload_0
      10: getfield      #5                  // Field password:Ljava/lang/String;
      13: aload_0
      14: getfield      #10                 // Field path:Ljava/lang/String;
      17: aload_0
      18: getfield      #12                 // Field host:Ljava/lang/String;
      21: aload_0
      22: getfield      #13                 // Field port:I
      25: aload_0
      26: getfield      #14                 // Field rawAddress:Ljava/lang/String;
      29: invokespecial #1                  // Method "<init>":(Ljava/lang/String;Ljava/lang/String;Ljava/lang/String;Ljava/lang/String;Ljava/lang/String;ILjava/lang/String;)V
      32: areturn

  public java.lang.String getPassword();
    Code:
       0: aload_0
       1: getfield      #5                  // Field password:Ljava/lang/String;
       4: areturn

  public org.apache.dubbo.common.url.component.PathURLAddress setPassword(java.lang.String);
    Code:
       0: new           #11                 // class org/apache/dubbo/common/url/component/PathURLAddress
       3: dup
       4: aload_0
       5: getfield      #3                  // Field protocol:Ljava/lang/String;
       8: aload_0
       9: getfield      #4                  // Field username:Ljava/lang/String;
      12: aload_1
      13: aload_0
      14: getfield      #10                 // Field path:Ljava/lang/String;
      17: aload_0
      18: getfield      #12                 // Field host:Ljava/lang/String;
      21: aload_0
      22: getfield      #13                 // Field port:I
      25: aload_0
      26: getfield      #14                 // Field rawAddress:Ljava/lang/String;
      29: invokespecial #1                  // Method "<init>":(Ljava/lang/String;Ljava/lang/String;Ljava/lang/String;Ljava/lang/String;Ljava/lang/String;ILjava/lang/String;)V
      32: areturn

  public java.lang.String getPath();
    Code:
       0: aload_0
       1: getfield      #10                 // Field path:Ljava/lang/String;
       4: areturn

  public org.apache.dubbo.common.url.component.PathURLAddress setPath(java.lang.String);
    Code:
       0: new           #11                 // class org/apache/dubbo/common/url/component/PathURLAddress
       3: dup
       4: aload_0
       5: getfield      #3                  // Field protocol:Ljava/lang/String;
       8: aload_0
       9: getfield      #4                  // Field username:Ljava/lang/String;
      12: aload_0
      13: getfield      #5                  // Field password:Ljava/lang/String;
      16: aload_1
      17: aload_0
      18: getfield      #12                 // Field host:Ljava/lang/String;
      21: aload_0
      22: getfield      #13                 // Field port:I
      25: aload_0
      26: getfield      #14                 // Field rawAddress:Ljava/lang/String;
      29: invokespecial #1                  // Method "<init>":(Ljava/lang/String;Ljava/lang/String;Ljava/lang/String;Ljava/lang/String;Ljava/lang/String;ILjava/lang/String;)V
      32: areturn

  public org.apache.dubbo.common.url.component.URLAddress setHost(java.lang.String);
    Code:
       0: new           #11                 // class org/apache/dubbo/common/url/component/PathURLAddress
       3: dup
       4: aload_0
       5: getfield      #3                  // Field protocol:Ljava/lang/String;
       8: aload_0
       9: getfield      #4                  // Field username:Ljava/lang/String;
      12: aload_0
      13: getfield      #5                  // Field password:Ljava/lang/String;
      16: aload_0
      17: getfield      #10                 // Field path:Ljava/lang/String;
      20: aload_1
      21: aload_0
      22: getfield      #13                 // Field port:I
      25: aload_0
      26: getfield      #14                 // Field rawAddress:Ljava/lang/String;
      29: invokespecial #1                  // Method "<init>":(Ljava/lang/String;Ljava/lang/String;Ljava/lang/String;Ljava/lang/String;Ljava/lang/String;ILjava/lang/String;)V
      32: areturn

  public org.apache.dubbo.common.url.component.URLAddress setPort(int);
    Code:
       0: new           #11                 // class org/apache/dubbo/common/url/component/PathURLAddress
       3: dup
       4: aload_0
       5: getfield      #3                  // Field protocol:Ljava/lang/String;
       8: aload_0
       9: getfield      #4                  // Field username:Ljava/lang/String;
      12: aload_0
      13: getfield      #5                  // Field password:Ljava/lang/String;
      16: aload_0
      17: getfield      #10                 // Field path:Ljava/lang/String;
      20: aload_0
      21: getfield      #12                 // Field host:Ljava/lang/String;
      24: iload_1
      25: aload_0
      26: getfield      #14                 // Field rawAddress:Ljava/lang/String;
      29: invokespecial #1                  // Method "<init>":(Ljava/lang/String;Ljava/lang/String;Ljava/lang/String;Ljava/lang/String;Ljava/lang/String;ILjava/lang/String;)V
      32: areturn

  public org.apache.dubbo.common.url.component.URLAddress setAddress(java.lang.String, int);
    Code:
       0: new           #11                 // class org/apache/dubbo/common/url/component/PathURLAddress
       3: dup
       4: aload_0
       5: getfield      #3                  // Field protocol:Ljava/lang/String;
       8: aload_0
       9: getfield      #4                  // Field username:Ljava/lang/String;
      12: aload_0
      13: getfield      #5                  // Field password:Ljava/lang/String;
      16: aload_0
      17: getfield      #10                 // Field path:Ljava/lang/String;
      20: aload_1
      21: iload_2
      22: aload_0
      23: getfield      #14                 // Field rawAddress:Ljava/lang/String;
      26: invokespecial #1                  // Method "<init>":(Ljava/lang/String;Ljava/lang/String;Ljava/lang/String;Ljava/lang/String;Ljava/lang/String;ILjava/lang/String;)V
      29: areturn

  public java.lang.String getAddress();
    Code:
       0: aload_0
       1: getfield      #15                 // Field address:Ljava/lang/String;
       4: ifnonnull     23
       7: aload_0
       8: aload_0
       9: aload_0
      10: invokevirtual #16                 // Method getHost:()Ljava/lang/String;
      13: aload_0
      14: invokevirtual #17                 // Method getPort:()I
      17: invokevirtual #18                 // Method getAddress:(Ljava/lang/String;I)Ljava/lang/String;
      20: putfield      #15                 // Field address:Ljava/lang/String;
      23: aload_0
      24: getfield      #15                 // Field address:Ljava/lang/String;
      27: areturn

  public java.lang.String getIp();
    Code:
       0: aload_0
       1: getfield      #19                 // Field ip:Ljava/lang/String;
       4: ifnonnull     18
       7: aload_0
       8: aload_0
       9: invokevirtual #16                 // Method getHost:()Ljava/lang/String;
      12: invokestatic  #20                 // Method org/apache/dubbo/common/utils/NetUtils.getIpByHost:(Ljava/lang/String;)Ljava/lang/String;
      15: putfield      #19                 // Field ip:Ljava/lang/String;
      18: aload_0
      19: getfield      #19                 // Field ip:Ljava/lang/String;
      22: areturn

  public int hashCode();
    Code:
       0: bipush        6
       2: anewarray     #21                 // class java/lang/Object
       5: dup
       6: iconst_0
       7: aload_0
       8: getfield      #3                  // Field protocol:Ljava/lang/String;
      11: aastore
      12: dup
      13: iconst_1
      14: aload_0
      15: getfield      #4                  // Field username:Ljava/lang/String;
      18: aastore
      19: dup
      20: iconst_2
      21: aload_0
      22: getfield      #5                  // Field password:Ljava/lang/String;
      25: aastore
      26: dup
      27: iconst_3
      28: aload_0
      29: getfield      #10                 // Field path:Ljava/lang/String;
      32: aastore
      33: dup
      34: iconst_4
      35: aload_0
      36: getfield      #12                 // Field host:Ljava/lang/String;
      39: aastore
      40: dup
      41: iconst_5
      42: aload_0
      43: getfield      #13                 // Field port:I
      46: invokestatic  #22                 // Method java/lang/Integer.valueOf:(I)Ljava/lang/Integer;
      49: aastore
      50: invokestatic  #23                 // Method java/util/Objects.hash:([Ljava/lang/Object;)I
      53: ireturn

  public boolean equals(java.lang.Object);
    Code:
       0: aload_0
       1: aload_1
       2: if_acmpne     7
       5: iconst_1
       6: ireturn
       7: aload_1
       8: instanceof    #24                 // class org/apache/dubbo/common/url/component/URLAddress
      11: ifne          16
      14: iconst_0
      15: ireturn
      16: aload_1
      17: checkcast     #24                 // class org/apache/dubbo/common/url/component/URLAddress
      20: astore_2
      21: aload_0
      22: invokevirtual #25                 // Method getProtocol:()Ljava/lang/String;
      25: aload_2
      26: invokevirtual #26                 // Method org/apache/dubbo/common/url/component/URLAddress.getProtocol:()Ljava/lang/String;
      29: invokestatic  #27                 // Method java/util/Objects.equals:(Ljava/lang/Object;Ljava/lang/Object;)Z
      32: ifeq          115
      35: aload_0
      36: invokevirtual #28                 // Method getUsername:()Ljava/lang/String;
      39: aload_2
      40: invokevirtual #29                 // Method org/apache/dubbo/common/url/component/URLAddress.getUsername:()Ljava/lang/String;
      43: invokestatic  #27                 // Method java/util/Objects.equals:(Ljava/lang/Object;Ljava/lang/Object;)Z
      46: ifeq          115
      49: aload_0
      50: invokevirtual #30                 // Method getPassword:()Ljava/lang/String;
      53: aload_2
      54: invokevirtual #31                 // Method org/apache/dubbo/common/url/component/URLAddress.getPassword:()Ljava/lang/String;
      57: invokestatic  #27                 // Method java/util/Objects.equals:(Ljava/lang/Object;Ljava/lang/Object;)Z
      60: ifeq          115
      63: aload_0
      64: invokevirtual #32                 // Method getPath:()Ljava/lang/String;
      67: aload_2
      68: invokevirtual #33                 // Method org/apache/dubbo/common/url/component/URLAddress.getPath:()Ljava/lang/String;
      71: invokestatic  #27                 // Method java/util/Objects.equals:(Ljava/lang/Object;Ljava/lang/Object;)Z
      74: ifeq          115
      77: aload_0
      78: invokevirtual #16                 // Method getHost:()Ljava/lang/String;
      81: aload_2
      82: invokevirtual #34                 // Method org/apache/dubbo/common/url/component/URLAddress.getHost:()Ljava/lang/String;
      85: invokestatic  #27                 // Method java/util/Objects.equals:(Ljava/lang/Object;Ljava/lang/Object;)Z
      88: ifeq          115
      91: aload_0
      92: invokevirtual #17                 // Method getPort:()I
      95: invokestatic  #22                 // Method java/lang/Integer.valueOf:(I)Ljava/lang/Integer;
      98: aload_2
      99: invokevirtual #35                 // Method org/apache/dubbo/common/url/component/URLAddress.getPort:()I
     102: invokestatic  #22                 // Method java/lang/Integer.valueOf:(I)Ljava/lang/Integer;
     105: invokestatic  #27                 // Method java/util/Objects.equals:(Ljava/lang/Object;Ljava/lang/Object;)Z
     108: ifeq          115
     111: iconst_1
     112: goto          116
     115: iconst_0
     116: ireturn

  public java.lang.String toString();
    Code:
       0: aload_0
       1: getfield      #14                 // Field rawAddress:Ljava/lang/String;
       4: ifnull        12
       7: aload_0
       8: getfield      #14                 // Field rawAddress:Ljava/lang/String;
      11: areturn
      12: new           #36                 // class java/lang/StringBuilder
      15: dup
      16: invokespecial #37                 // Method java/lang/StringBuilder."<init>":()V
      19: astore_1
      20: aload_0
      21: getfield      #3                  // Field protocol:Ljava/lang/String;
      24: invokestatic  #38                 // Method org/apache/dubbo/common/utils/StringUtils.isNotEmpty:(Ljava/lang/String;)Z
      27: ifeq          46
      30: aload_1
      31: aload_0
      32: getfield      #3                  // Field protocol:Ljava/lang/String;
      35: invokevirtual #39                 // Method java/lang/StringBuilder.append:(Ljava/lang/String;)Ljava/lang/StringBuilder;
      38: pop
      39: aload_1
      40: ldc           #40                 // String ://
      42: invokevirtual #39                 // Method java/lang/StringBuilder.append:(Ljava/lang/String;)Ljava/lang/StringBuilder;
      45: pop
      46: aload_0
      47: getfield      #12                 // Field host:Ljava/lang/String;
      50: invokestatic  #38                 // Method org/apache/dubbo/common/utils/StringUtils.isNotEmpty:(Ljava/lang/String;)Z
      53: ifeq          88
      56: aload_1
      57: aload_0
      58: getfield      #12                 // Field host:Ljava/lang/String;
      61: invokevirtual #39                 // Method java/lang/StringBuilder.append:(Ljava/lang/String;)Ljava/lang/StringBuilder;
      64: pop
      65: aload_0
      66: getfield      #13                 // Field port:I
      69: ifle          88
      72: aload_1
      73: bipush        58
      75: invokevirtual #41                 // Method java/lang/StringBuilder.append:(C)Ljava/lang/StringBuilder;
      78: pop
      79: aload_1
      80: aload_0
      81: getfield      #13                 // Field port:I
      84: invokevirtual #42                 // Method java/lang/StringBuilder.append:(I)Ljava/lang/StringBuilder;
      87: pop
      88: aload_0
      89: getfield      #10                 // Field path:Ljava/lang/String;
      92: invokestatic  #38                 // Method org/apache/dubbo/common/utils/StringUtils.isNotEmpty:(Ljava/lang/String;)Z
      95: ifeq          114
      98: aload_1
      99: bipush        47
     101: invokevirtual #41                 // Method java/lang/StringBuilder.append:(C)Ljava/lang/StringBuilder;
     104: pop
     105: aload_1
     106: aload_0
     107: getfield      #10                 // Field path:Ljava/lang/String;
     110: invokevirtual #39                 // Method java/lang/StringBuilder.append:(Ljava/lang/String;)Ljava/lang/StringBuilder;
     113: pop
     114: aload_1
     115: invokevirtual #43                 // Method java/lang/StringBuilder.toString:()Ljava/lang/String;
     118: areturn

  public org.apache.dubbo.common.url.component.URLAddress setPath(java.lang.String);
    Code:
       0: aload_0
       1: aload_1
       2: invokevirtual #44                 // Method setPath:(Ljava/lang/String;)Lorg/apache/dubbo/common/url/component/PathURLAddress;
       5: areturn

  public org.apache.dubbo.common.url.component.URLAddress setPassword(java.lang.String);
    Code:
       0: aload_0
       1: aload_1
       2: invokevirtual #45                 // Method setPassword:(Ljava/lang/String;)Lorg/apache/dubbo/common/url/component/PathURLAddress;
       5: areturn
}
