Compiled from "ServiceAddressURL.java"
public abstract class org.apache.dubbo.common.url.component.ServiceAddressURL extends org.apache.dubbo.common.URL {
  protected final transient org.apache.dubbo.common.URL consumerURL;

  private transient java.util.Map<java.lang.String, java.lang.String> concatenatedPrams;

  public org.apache.dubbo.common.url.component.ServiceAddressURL(java.lang.String, java.lang.String, java.lang.String, java.lang.String, int, java.lang.String, java.util.Map<java.lang.String, java.lang.String>, org.apache.dubbo.common.URL);
    Code:
       0: aload_0
       1: aload_1
       2: aload_2
       3: aload_3
       4: aload         4
       6: iload         5
       8: aload         6
      10: aload         7
      12: invokespecial #3                  // Method org/apache/dubbo/common/URL."<init>":(Ljava/lang/String;Ljava/lang/String;Ljava/lang/String;Ljava/lang/String;ILjava/lang/String;Ljava/util/Map;)V
      15: aload_0
      16: aload         8
      18: putfield      #4                  // Field consumerURL:Lorg/apache/dubbo/common/URL;
      21: return

  public org.apache.dubbo.common.url.component.ServiceAddressURL(org.apache.dubbo.common.url.component.URLAddress, org.apache.dubbo.common.url.component.URLParam, org.apache.dubbo.common.URL);
    Code:
       0: aload_0
       1: aload_1
       2: aload_2
       3: invokespecial #5                  // Method org/apache/dubbo/common/URL."<init>":(Lorg/apache/dubbo/common/url/component/URLAddress;Lorg/apache/dubbo/common/url/component/URLParam;)V
       6: aload_0
       7: aload_3
       8: putfield      #4                  // Field consumerURL:Lorg/apache/dubbo/common/URL;
      11: return

  public java.lang.String getPath();
    Code:
       0: aload_0
       1: invokespecial #6                  // Method org/apache/dubbo/common/URL.getPath:()Ljava/lang/String;
       4: astore_1
       5: aload_1
       6: invokestatic  #7                  // Method org/apache/dubbo/common/utils/StringUtils.isNotEmpty:(Ljava/lang/String;)Z
       9: ifeq          14
      12: aload_1
      13: areturn
      14: aload_0
      15: getfield      #4                  // Field consumerURL:Lorg/apache/dubbo/common/URL;
      18: invokevirtual #6                  // Method org/apache/dubbo/common/URL.getPath:()Ljava/lang/String;
      21: areturn

  public java.lang.String getServiceInterface();
    Code:
       0: aload_0
       1: getfield      #4                  // Field consumerURL:Lorg/apache/dubbo/common/URL;
       4: invokevirtual #8                  // Method org/apache/dubbo/common/URL.getServiceInterface:()Ljava/lang/String;
       7: areturn

  public java.lang.String getApplication();
    Code:
       0: aload_0
       1: getfield      #4                  // Field consumerURL:Lorg/apache/dubbo/common/URL;
       4: invokevirtual #9                  // Method org/apache/dubbo/common/URL.getApplication:()Ljava/lang/String;
       7: areturn

  public java.lang.String getRemoteApplication();
    Code:
       0: aload_0
       1: ldc           #10                 // String application
       3: invokespecial #11                 // Method org/apache/dubbo/common/URL.getParameter:(Ljava/lang/String;)Ljava/lang/String;
       6: areturn

  public java.lang.String getGroup();
    Code:
       0: aload_0
       1: ldc           #12                 // String group
       3: invokespecial #11                 // Method org/apache/dubbo/common/URL.getParameter:(Ljava/lang/String;)Ljava/lang/String;
       6: areturn

  public java.lang.String getVersion();
    Code:
       0: aload_0
       1: ldc           #13                 // String version
       3: invokespecial #11                 // Method org/apache/dubbo/common/URL.getParameter:(Ljava/lang/String;)Ljava/lang/String;
       6: areturn

  public java.lang.String getOriginalParameter(java.lang.String);
    Code:
       0: ldc           #12                 // String group
       2: aload_1
       3: invokevirtual #14                 // Method java/lang/String.equals:(Ljava/lang/Object;)Z
       6: ifeq          14
       9: aload_0
      10: invokevirtual #15                 // Method getGroup:()Ljava/lang/String;
      13: areturn
      14: ldc           #13                 // String version
      16: aload_1
      17: invokevirtual #14                 // Method java/lang/String.equals:(Ljava/lang/Object;)Z
      20: ifeq          28
      23: aload_0
      24: invokevirtual #16                 // Method getVersion:()Ljava/lang/String;
      27: areturn
      28: ldc           #10                 // String application
      30: aload_1
      31: invokevirtual #14                 // Method java/lang/String.equals:(Ljava/lang/Object;)Z
      34: ifeq          42
      37: aload_0
      38: invokevirtual #17                 // Method getRemoteApplication:()Ljava/lang/String;
      41: areturn
      42: ldc           #18                 // String side
      44: aload_1
      45: invokevirtual #14                 // Method java/lang/String.equals:(Ljava/lang/Object;)Z
      48: ifeq          56
      51: aload_0
      52: invokevirtual #19                 // Method getSide:()Ljava/lang/String;
      55: areturn
      56: ldc           #20                 // String category
      58: aload_1
      59: invokevirtual #14                 // Method java/lang/String.equals:(Ljava/lang/Object;)Z
      62: ifeq          70
      65: aload_0
      66: invokevirtual #21                 // Method getCategory:()Ljava/lang/String;
      69: areturn
      70: aload_0
      71: aload_1
      72: invokespecial #11                 // Method org/apache/dubbo/common/URL.getParameter:(Ljava/lang/String;)Ljava/lang/String;
      75: areturn

  public java.lang.String getParameter(java.lang.String);
    Code:
       0: ldc           #12                 // String group
       2: aload_1
       3: invokevirtual #14                 // Method java/lang/String.equals:(Ljava/lang/Object;)Z
       6: ifeq          14
       9: aload_0
      10: invokevirtual #15                 // Method getGroup:()Ljava/lang/String;
      13: areturn
      14: ldc           #13                 // String version
      16: aload_1
      17: invokevirtual #14                 // Method java/lang/String.equals:(Ljava/lang/Object;)Z
      20: ifeq          28
      23: aload_0
      24: invokevirtual #16                 // Method getVersion:()Ljava/lang/String;
      27: areturn
      28: ldc           #10                 // String application
      30: aload_1
      31: invokevirtual #14                 // Method java/lang/String.equals:(Ljava/lang/Object;)Z
      34: ifeq          42
      37: aload_0
      38: invokevirtual #17                 // Method getRemoteApplication:()Ljava/lang/String;
      41: areturn
      42: ldc           #18                 // String side
      44: aload_1
      45: invokevirtual #14                 // Method java/lang/String.equals:(Ljava/lang/Object;)Z
      48: ifeq          56
      51: aload_0
      52: invokevirtual #19                 // Method getSide:()Ljava/lang/String;
      55: areturn
      56: ldc           #20                 // String category
      58: aload_1
      59: invokevirtual #14                 // Method java/lang/String.equals:(Ljava/lang/Object;)Z
      62: ifeq          70
      65: aload_0
      66: invokevirtual #21                 // Method getCategory:()Ljava/lang/String;
      69: areturn
      70: aconst_null
      71: astore_2
      72: aload_0
      73: getfield      #4                  // Field consumerURL:Lorg/apache/dubbo/common/URL;
      76: ifnull        88
      79: aload_0
      80: getfield      #4                  // Field consumerURL:Lorg/apache/dubbo/common/URL;
      83: aload_1
      84: invokevirtual #11                 // Method org/apache/dubbo/common/URL.getParameter:(Ljava/lang/String;)Ljava/lang/String;
      87: astore_2
      88: aload_2
      89: invokestatic  #22                 // Method org/apache/dubbo/common/utils/StringUtils.isEmpty:(Ljava/lang/String;)Z
      92: ifeq          101
      95: aload_0
      96: aload_1
      97: invokespecial #11                 // Method org/apache/dubbo/common/URL.getParameter:(Ljava/lang/String;)Ljava/lang/String;
     100: astore_2
     101: aload_2
     102: areturn

  public java.lang.String getMethodParameter(java.lang.String, java.lang.String);
    Code:
       0: aconst_null
       1: astore_3
       2: aload_0
       3: getfield      #4                  // Field consumerURL:Lorg/apache/dubbo/common/URL;
       6: ifnull        19
       9: aload_0
      10: getfield      #4                  // Field consumerURL:Lorg/apache/dubbo/common/URL;
      13: aload_1
      14: aload_2
      15: invokevirtual #23                 // Method org/apache/dubbo/common/URL.getMethodParameterStrict:(Ljava/lang/String;Ljava/lang/String;)Ljava/lang/String;
      18: astore_3
      19: aload_3
      20: invokestatic  #22                 // Method org/apache/dubbo/common/utils/StringUtils.isEmpty:(Ljava/lang/String;)Z
      23: ifeq          33
      26: aload_0
      27: aload_1
      28: aload_2
      29: invokespecial #23                 // Method org/apache/dubbo/common/URL.getMethodParameterStrict:(Ljava/lang/String;Ljava/lang/String;)Ljava/lang/String;
      32: astore_3
      33: aload_3
      34: invokestatic  #22                 // Method org/apache/dubbo/common/utils/StringUtils.isEmpty:(Ljava/lang/String;)Z
      37: ifeq          46
      40: aload_0
      41: aload_2
      42: invokevirtual #24                 // Method getParameter:(Ljava/lang/String;)Ljava/lang/String;
      45: astore_3
      46: aload_3
      47: areturn

  public java.lang.String getAnyMethodParameter(java.lang.String);
    Code:
       0: aconst_null
       1: astore_2
       2: aload_0
       3: getfield      #4                  // Field consumerURL:Lorg/apache/dubbo/common/URL;
       6: ifnull        18
       9: aload_0
      10: getfield      #4                  // Field consumerURL:Lorg/apache/dubbo/common/URL;
      13: aload_1
      14: invokevirtual #25                 // Method org/apache/dubbo/common/URL.getAnyMethodParameter:(Ljava/lang/String;)Ljava/lang/String;
      17: astore_2
      18: aload_2
      19: invokestatic  #22                 // Method org/apache/dubbo/common/utils/StringUtils.isEmpty:(Ljava/lang/String;)Z
      22: ifeq          31
      25: aload_0
      26: aload_1
      27: invokespecial #25                 // Method org/apache/dubbo/common/URL.getAnyMethodParameter:(Ljava/lang/String;)Ljava/lang/String;
      30: astore_2
      31: aload_2
      32: areturn

  public java.lang.String getConcatenatedParameter(java.lang.String);
    Code:
       0: aload_0
       1: getfield      #26                 // Field concatenatedPrams:Ljava/util/Map;
       4: ifnonnull     19
       7: aload_0
       8: new           #27                 // class java/util/HashMap
      11: dup
      12: iconst_1
      13: invokespecial #28                 // Method java/util/HashMap."<init>":(I)V
      16: putfield      #26                 // Field concatenatedPrams:Ljava/util/Map;
      19: aload_0
      20: getfield      #26                 // Field concatenatedPrams:Ljava/util/Map;
      23: aload_1
      24: invokeinterface #29,  2           // InterfaceMethod java/util/Map.get:(Ljava/lang/Object;)Ljava/lang/Object;
      29: checkcast     #30                 // class java/lang/String
      32: astore_2
      33: aload_2
      34: invokestatic  #7                  // Method org/apache/dubbo/common/utils/StringUtils.isNotEmpty:(Ljava/lang/String;)Z
      37: ifeq          42
      40: aload_2
      41: areturn
      42: aload_0
      43: aload_1
      44: invokespecial #11                 // Method org/apache/dubbo/common/URL.getParameter:(Ljava/lang/String;)Ljava/lang/String;
      47: astore_3
      48: aload_0
      49: getfield      #4                  // Field consumerURL:Lorg/apache/dubbo/common/URL;
      52: aload_1
      53: invokevirtual #11                 // Method org/apache/dubbo/common/URL.getParameter:(Ljava/lang/String;)Ljava/lang/String;
      56: astore        4
      58: aload_3
      59: ifnull        121
      62: aload_3
      63: invokevirtual #31                 // Method java/lang/String.length:()I
      66: ifle          121
      69: aload         4
      71: ifnull        121
      74: aload         4
      76: invokevirtual #31                 // Method java/lang/String.length:()I
      79: ifle          121
      82: new           #32                 // class java/lang/StringBuilder
      85: dup
      86: invokespecial #33                 // Method java/lang/StringBuilder."<init>":()V
      89: aload_3
      90: invokevirtual #34                 // Method java/lang/StringBuilder.append:(Ljava/lang/String;)Ljava/lang/StringBuilder;
      93: ldc           #35                 // String ,
      95: invokevirtual #34                 // Method java/lang/StringBuilder.append:(Ljava/lang/String;)Ljava/lang/StringBuilder;
      98: aload         4
     100: invokevirtual #34                 // Method java/lang/StringBuilder.append:(Ljava/lang/String;)Ljava/lang/StringBuilder;
     103: invokevirtual #36                 // Method java/lang/StringBuilder.toString:()Ljava/lang/String;
     106: astore_2
     107: aload_0
     108: getfield      #26                 // Field concatenatedPrams:Ljava/util/Map;
     111: aload_1
     112: aload_2
     113: invokeinterface #37,  3           // InterfaceMethod java/util/Map.put:(Ljava/lang/Object;Ljava/lang/Object;)Ljava/lang/Object;
     118: pop
     119: aload_2
     120: areturn
     121: aload         4
     123: ifnull        140
     126: aload         4
     128: invokevirtual #31                 // Method java/lang/String.length:()I
     131: ifle          140
     134: aload         4
     136: astore_2
     137: goto          153
     140: aload_3
     141: ifnull        153
     144: aload_3
     145: invokevirtual #31                 // Method java/lang/String.length:()I
     148: ifle          153
     151: aload_3
     152: astore_2
     153: aload_0
     154: getfield      #26                 // Field concatenatedPrams:Ljava/util/Map;
     157: aload_1
     158: aload_2
     159: invokeinterface #37,  3           // InterfaceMethod java/util/Map.put:(Ljava/lang/Object;Ljava/lang/Object;)Ljava/lang/Object;
     164: pop
     165: aload_2
     166: areturn

  public java.lang.String getCategory();
    Code:
       0: ldc           #38                 // String providers
       2: areturn

  public java.lang.String getSide();
    Code:
       0: ldc           #39                 // String consumer
       2: areturn

  public org.apache.dubbo.common.URL getConsumerURL();
    Code:
       0: aload_0
       1: getfield      #4                  // Field consumerURL:Lorg/apache/dubbo/common/URL;
       4: areturn

  public int hashCode();
    Code:
       0: aload_0
       1: invokespecial #40                 // Method org/apache/dubbo/common/URL.hashCode:()I
       4: ireturn

  public org.apache.dubbo.rpc.model.ScopeModel getScopeModel();
    Code:
       0: aload_0
       1: getfield      #4                  // Field consumerURL:Lorg/apache/dubbo/common/URL;
       4: invokevirtual #41                 // Method org/apache/dubbo/common/URL.getScopeModel:()Lorg/apache/dubbo/rpc/model/ScopeModel;
       7: areturn

  public org.apache.dubbo.rpc.model.ServiceModel getServiceModel();
    Code:
       0: aload_0
       1: getfield      #4                  // Field consumerURL:Lorg/apache/dubbo/common/URL;
       4: invokevirtual #42                 // Method org/apache/dubbo/common/URL.getServiceModel:()Lorg/apache/dubbo/rpc/model/ServiceModel;
       7: areturn

  public org.apache.dubbo.common.URL setScopeModel(org.apache.dubbo.rpc.model.ScopeModel);
    Code:
       0: new           #43                 // class java/lang/UnsupportedOperationException
       3: dup
       4: ldc           #44                 // String setScopeModel is forbidden for ServiceAddressURL
       6: invokespecial #45                 // Method java/lang/UnsupportedOperationException."<init>":(Ljava/lang/String;)V
       9: athrow

  public org.apache.dubbo.common.URL setServiceModel(org.apache.dubbo.rpc.model.ServiceModel);
    Code:
       0: new           #43                 // class java/lang/UnsupportedOperationException
       3: dup
       4: ldc           #46                 // String setServiceModel is forbidden for ServiceAddressURL
       6: invokespecial #45                 // Method java/lang/UnsupportedOperationException."<init>":(Ljava/lang/String;)V
       9: athrow

  public boolean equals(java.lang.Object);
    Code:
       0: aload_0
       1: aload_1
       2: if_acmpne     7
       5: iconst_1
       6: ireturn
       7: aload_1
       8: ifnonnull     13
      11: iconst_0
      12: ireturn
      13: aload_1
      14: instanceof    #47                 // class org/apache/dubbo/common/url/component/ServiceAddressURL
      17: ifne          22
      20: iconst_0
      21: ireturn
      22: aload_0
      23: aload_1
      24: invokespecial #48                 // Method org/apache/dubbo/common/URL.equals:(Ljava/lang/Object;)Z
      27: ireturn

  public java.lang.String toString();
    Code:
       0: aload_0
       1: invokevirtual #49                 // Method getUrlParam:()Lorg/apache/dubbo/common/url/component/URLParam;
       4: aload_0
       5: getfield      #4                  // Field consumerURL:Lorg/apache/dubbo/common/URL;
       8: invokevirtual #50                 // Method org/apache/dubbo/common/URL.getParameters:()Ljava/util/Map;
      11: invokevirtual #51                 // Method org/apache/dubbo/common/url/component/URLParam.addParametersIfAbsent:(Ljava/util/Map;)Lorg/apache/dubbo/common/url/component/URLParam;
      14: astore_1
      15: new           #52                 // class org/apache/dubbo/common/url/component/ServiceConfigURL
      18: dup
      19: aload_0
      20: invokevirtual #53                 // Method getUrlAddress:()Lorg/apache/dubbo/common/url/component/URLAddress;
      23: aload_1
      24: aconst_null
      25: invokespecial #54                 // Method org/apache/dubbo/common/url/component/ServiceConfigURL."<init>":(Lorg/apache/dubbo/common/url/component/URLAddress;Lorg/apache/dubbo/common/url/component/URLParam;Ljava/util/Map;)V
      28: invokevirtual #55                 // Method org/apache/dubbo/common/url/component/ServiceConfigURL.toString:()Ljava/lang/String;
      31: areturn
}
