Compiled from "ServiceConfigURL.java"
public class org.apache.dubbo.common.url.component.ServiceConfigURL extends org.apache.dubbo.common.URL {
  private volatile transient java.util.concurrent.ConcurrentMap<java.lang.String, org.apache.dubbo.common.URL> urls;

  private volatile transient java.util.concurrent.ConcurrentMap<java.lang.String, java.lang.Number> numbers;

  private volatile transient java.util.concurrent.ConcurrentMap<java.lang.String, java.util.Map<java.lang.String, java.lang.Number>> methodNumbers;

  private volatile transient java.lang.String full;

  private volatile transient java.lang.String string;

  private volatile transient java.lang.String identity;

  private volatile transient java.lang.String parameter;

  public org.apache.dubbo.common.url.component.ServiceConfigURL();
    Code:
       0: aload_0
       1: invokespecial #1                  // Method org/apache/dubbo/common/URL."<init>":()V
       4: return

  public org.apache.dubbo.common.url.component.ServiceConfigURL(org.apache.dubbo.common.url.component.URLAddress, org.apache.dubbo.common.url.component.URLParam, java.util.Map<java.lang.String, java.lang.Object>);
    Code:
       0: aload_0
       1: aload_1
       2: aload_2
       3: aload_3
       4: invokespecial #2                  // Method org/apache/dubbo/common/URL."<init>":(Lorg/apache/dubbo/common/url/component/URLAddress;Lorg/apache/dubbo/common/url/component/URLParam;Ljava/util/Map;)V
       7: return

  public org.apache.dubbo.common.url.component.ServiceConfigURL(java.lang.String, java.lang.String, int);
    Code:
       0: aload_0
       1: aload_1
       2: aconst_null
       3: aconst_null
       4: aload_2
       5: iload_3
       6: aconst_null
       7: aconst_null
       8: checkcast     #3                  // class java/util/Map
      11: invokespecial #4                  // Method "<init>":(Ljava/lang/String;Ljava/lang/String;Ljava/lang/String;Ljava/lang/String;ILjava/lang/String;Ljava/util/Map;)V
      14: return

  public org.apache.dubbo.common.url.component.ServiceConfigURL(java.lang.String, java.lang.String, int, java.lang.String[]);
    Code:
       0: aload_0
       1: aload_1
       2: aconst_null
       3: aconst_null
       4: aload_2
       5: iload_3
       6: aconst_null
       7: aload         4
       9: invokestatic  #5                  // Method org/apache/dubbo/common/utils/CollectionUtils.toStringMap:([Ljava/lang/String;)Ljava/util/Map;
      12: invokespecial #4                  // Method "<init>":(Ljava/lang/String;Ljava/lang/String;Ljava/lang/String;Ljava/lang/String;ILjava/lang/String;Ljava/util/Map;)V
      15: return

  public org.apache.dubbo.common.url.component.ServiceConfigURL(java.lang.String, java.lang.String, int, java.util.Map<java.lang.String, java.lang.String>);
    Code:
       0: aload_0
       1: aload_1
       2: aconst_null
       3: aconst_null
       4: aload_2
       5: iload_3
       6: aconst_null
       7: aload         4
       9: invokespecial #4                  // Method "<init>":(Ljava/lang/String;Ljava/lang/String;Ljava/lang/String;Ljava/lang/String;ILjava/lang/String;Ljava/util/Map;)V
      12: return

  public org.apache.dubbo.common.url.component.ServiceConfigURL(java.lang.String, java.lang.String, int, java.lang.String);
    Code:
       0: aload_0
       1: aload_1
       2: aconst_null
       3: aconst_null
       4: aload_2
       5: iload_3
       6: aload         4
       8: aconst_null
       9: checkcast     #3                  // class java/util/Map
      12: invokespecial #4                  // Method "<init>":(Ljava/lang/String;Ljava/lang/String;Ljava/lang/String;Ljava/lang/String;ILjava/lang/String;Ljava/util/Map;)V
      15: return

  public org.apache.dubbo.common.url.component.ServiceConfigURL(java.lang.String, java.lang.String, int, java.lang.String, java.lang.String...);
    Code:
       0: aload_0
       1: aload_1
       2: aconst_null
       3: aconst_null
       4: aload_2
       5: iload_3
       6: aload         4
       8: aload         5
      10: invokestatic  #5                  // Method org/apache/dubbo/common/utils/CollectionUtils.toStringMap:([Ljava/lang/String;)Ljava/util/Map;
      13: invokespecial #4                  // Method "<init>":(Ljava/lang/String;Ljava/lang/String;Ljava/lang/String;Ljava/lang/String;ILjava/lang/String;Ljava/util/Map;)V
      16: return

  public org.apache.dubbo.common.url.component.ServiceConfigURL(java.lang.String, java.lang.String, int, java.lang.String, java.util.Map<java.lang.String, java.lang.String>);
    Code:
       0: aload_0
       1: aload_1
       2: aconst_null
       3: aconst_null
       4: aload_2
       5: iload_3
       6: aload         4
       8: aload         5
      10: invokespecial #4                  // Method "<init>":(Ljava/lang/String;Ljava/lang/String;Ljava/lang/String;Ljava/lang/String;ILjava/lang/String;Ljava/util/Map;)V
      13: return

  public org.apache.dubbo.common.url.component.ServiceConfigURL(java.lang.String, java.lang.String, java.lang.String, java.lang.String, int, java.lang.String);
    Code:
       0: aload_0
       1: aload_1
       2: aload_2
       3: aload_3
       4: aload         4
       6: iload         5
       8: aload         6
      10: aconst_null
      11: checkcast     #3                  // class java/util/Map
      14: invokespecial #4                  // Method "<init>":(Ljava/lang/String;Ljava/lang/String;Ljava/lang/String;Ljava/lang/String;ILjava/lang/String;Ljava/util/Map;)V
      17: return

  public org.apache.dubbo.common.url.component.ServiceConfigURL(java.lang.String, java.lang.String, java.lang.String, java.lang.String, int, java.lang.String, java.lang.String...);
    Code:
       0: aload_0
       1: aload_1
       2: aload_2
       3: aload_3
       4: aload         4
       6: iload         5
       8: aload         6
      10: aload         7
      12: invokestatic  #5                  // Method org/apache/dubbo/common/utils/CollectionUtils.toStringMap:([Ljava/lang/String;)Ljava/util/Map;
      15: invokespecial #4                  // Method "<init>":(Ljava/lang/String;Ljava/lang/String;Ljava/lang/String;Ljava/lang/String;ILjava/lang/String;Ljava/util/Map;)V
      18: return

  public org.apache.dubbo.common.url.component.ServiceConfigURL(java.lang.String, java.lang.String, java.lang.String, java.lang.String, int, java.lang.String, java.util.Map<java.lang.String, java.lang.String>);
    Code:
       0: aload_0
       1: new           #6                  // class org/apache/dubbo/common/url/component/PathURLAddress
       4: dup
       5: aload_1
       6: aload_2
       7: aload_3
       8: aload         6
      10: aload         4
      12: iload         5
      14: invokespecial #7                  // Method org/apache/dubbo/common/url/component/PathURLAddress."<init>":(Ljava/lang/String;Ljava/lang/String;Ljava/lang/String;Ljava/lang/String;Ljava/lang/String;I)V
      17: aload         7
      19: invokestatic  #8                  // Method org/apache/dubbo/common/url/component/URLParam.parse:(Ljava/util/Map;)Lorg/apache/dubbo/common/url/component/URLParam;
      22: aconst_null
      23: invokespecial #9                  // Method "<init>":(Lorg/apache/dubbo/common/url/component/URLAddress;Lorg/apache/dubbo/common/url/component/URLParam;Ljava/util/Map;)V
      26: return

  public org.apache.dubbo.common.url.component.ServiceConfigURL(java.lang.String, java.lang.String, java.lang.String, java.lang.String, int, java.lang.String, java.util.Map<java.lang.String, java.lang.String>, java.util.Map<java.lang.String, java.lang.Object>);
    Code:
       0: aload_0
       1: new           #6                  // class org/apache/dubbo/common/url/component/PathURLAddress
       4: dup
       5: aload_1
       6: aload_2
       7: aload_3
       8: aload         6
      10: aload         4
      12: iload         5
      14: invokespecial #7                  // Method org/apache/dubbo/common/url/component/PathURLAddress."<init>":(Ljava/lang/String;Ljava/lang/String;Ljava/lang/String;Ljava/lang/String;Ljava/lang/String;I)V
      17: aload         7
      19: invokestatic  #8                  // Method org/apache/dubbo/common/url/component/URLParam.parse:(Ljava/util/Map;)Lorg/apache/dubbo/common/url/component/URLParam;
      22: aload         8
      24: invokespecial #9                  // Method "<init>":(Lorg/apache/dubbo/common/url/component/URLAddress;Lorg/apache/dubbo/common/url/component/URLParam;Ljava/util/Map;)V
      27: return

  protected <T extends org.apache.dubbo.common.URL> T newURL(org.apache.dubbo.common.url.component.URLAddress, org.apache.dubbo.common.url.component.URLParam);
    Code:
       0: new           #10                 // class org/apache/dubbo/common/url/component/ServiceConfigURL
       3: dup
       4: aload_1
       5: aload_2
       6: aload_0
       7: getfield      #11                 // Field attributes:Ljava/util/Map;
      10: invokespecial #9                  // Method "<init>":(Lorg/apache/dubbo/common/url/component/URLAddress;Lorg/apache/dubbo/common/url/component/URLParam;Ljava/util/Map;)V
      13: areturn

  public org.apache.dubbo.common.URL addAttributes(java.util.Map<java.lang.String, java.lang.Object>);
    Code:
       0: new           #12                 // class java/util/HashMap
       3: dup
       4: invokespecial #13                 // Method java/util/HashMap."<init>":()V
       7: astore_2
       8: aload_0
       9: getfield      #11                 // Field attributes:Ljava/util/Map;
      12: ifnull        25
      15: aload_2
      16: aload_0
      17: getfield      #11                 // Field attributes:Ljava/util/Map;
      20: invokeinterface #14,  2           // InterfaceMethod java/util/Map.putAll:(Ljava/util/Map;)V
      25: aload_2
      26: aload_1
      27: invokeinterface #14,  2           // InterfaceMethod java/util/Map.putAll:(Ljava/util/Map;)V
      32: new           #10                 // class org/apache/dubbo/common/url/component/ServiceConfigURL
      35: dup
      36: aload_0
      37: invokevirtual #15                 // Method getUrlAddress:()Lorg/apache/dubbo/common/url/component/URLAddress;
      40: aload_0
      41: invokevirtual #16                 // Method getUrlParam:()Lorg/apache/dubbo/common/url/component/URLParam;
      44: aload_2
      45: invokespecial #9                  // Method "<init>":(Lorg/apache/dubbo/common/url/component/URLAddress;Lorg/apache/dubbo/common/url/component/URLParam;Ljava/util/Map;)V
      48: areturn

  public org.apache.dubbo.common.url.component.ServiceConfigURL putAttribute(java.lang.String, java.lang.Object);
    Code:
       0: new           #12                 // class java/util/HashMap
       3: dup
       4: invokespecial #13                 // Method java/util/HashMap."<init>":()V
       7: astore_3
       8: aload_0
       9: getfield      #11                 // Field attributes:Ljava/util/Map;
      12: ifnull        25
      15: aload_3
      16: aload_0
      17: getfield      #11                 // Field attributes:Ljava/util/Map;
      20: invokeinterface #14,  2           // InterfaceMethod java/util/Map.putAll:(Ljava/util/Map;)V
      25: aload_3
      26: aload_1
      27: aload_2
      28: invokeinterface #17,  3           // InterfaceMethod java/util/Map.put:(Ljava/lang/Object;Ljava/lang/Object;)Ljava/lang/Object;
      33: pop
      34: new           #10                 // class org/apache/dubbo/common/url/component/ServiceConfigURL
      37: dup
      38: aload_0
      39: invokevirtual #15                 // Method getUrlAddress:()Lorg/apache/dubbo/common/url/component/URLAddress;
      42: aload_0
      43: invokevirtual #16                 // Method getUrlParam:()Lorg/apache/dubbo/common/url/component/URLParam;
      46: aload_3
      47: invokespecial #9                  // Method "<init>":(Lorg/apache/dubbo/common/url/component/URLAddress;Lorg/apache/dubbo/common/url/component/URLParam;Ljava/util/Map;)V
      50: areturn

  public org.apache.dubbo.common.URL removeAttribute(java.lang.String);
    Code:
       0: new           #12                 // class java/util/HashMap
       3: dup
       4: invokespecial #13                 // Method java/util/HashMap."<init>":()V
       7: astore_2
       8: aload_0
       9: getfield      #11                 // Field attributes:Ljava/util/Map;
      12: ifnull        25
      15: aload_2
      16: aload_0
      17: getfield      #11                 // Field attributes:Ljava/util/Map;
      20: invokeinterface #14,  2           // InterfaceMethod java/util/Map.putAll:(Ljava/util/Map;)V
      25: aload_2
      26: aload_1
      27: invokeinterface #18,  2           // InterfaceMethod java/util/Map.remove:(Ljava/lang/Object;)Ljava/lang/Object;
      32: pop
      33: new           #10                 // class org/apache/dubbo/common/url/component/ServiceConfigURL
      36: dup
      37: aload_0
      38: invokevirtual #15                 // Method getUrlAddress:()Lorg/apache/dubbo/common/url/component/URLAddress;
      41: aload_0
      42: invokevirtual #16                 // Method getUrlParam:()Lorg/apache/dubbo/common/url/component/URLParam;
      45: aload_2
      46: invokespecial #9                  // Method "<init>":(Lorg/apache/dubbo/common/url/component/URLAddress;Lorg/apache/dubbo/common/url/component/URLParam;Ljava/util/Map;)V
      49: areturn

  public java.lang.String toString();
    Code:
       0: aload_0
       1: getfield      #19                 // Field string:Ljava/lang/String;
       4: ifnull        12
       7: aload_0
       8: getfield      #19                 // Field string:Ljava/lang/String;
      11: areturn
      12: aload_0
      13: aload_0
      14: invokespecial #20                 // Method org/apache/dubbo/common/URL.toString:()Ljava/lang/String;
      17: dup_x1
      18: putfield      #19                 // Field string:Ljava/lang/String;
      21: areturn

  public java.lang.String toFullString();
    Code:
       0: aload_0
       1: getfield      #21                 // Field full:Ljava/lang/String;
       4: ifnull        12
       7: aload_0
       8: getfield      #21                 // Field full:Ljava/lang/String;
      11: areturn
      12: aload_0
      13: aload_0
      14: invokespecial #22                 // Method org/apache/dubbo/common/URL.toFullString:()Ljava/lang/String;
      17: dup_x1
      18: putfield      #21                 // Field full:Ljava/lang/String;
      21: areturn

  public java.lang.String toIdentityString();
    Code:
       0: aload_0
       1: getfield      #23                 // Field identity:Ljava/lang/String;
       4: ifnull        12
       7: aload_0
       8: getfield      #23                 // Field identity:Ljava/lang/String;
      11: areturn
      12: aload_0
      13: aload_0
      14: invokespecial #24                 // Method org/apache/dubbo/common/URL.toIdentityString:()Ljava/lang/String;
      17: dup_x1
      18: putfield      #23                 // Field identity:Ljava/lang/String;
      21: areturn

  public java.lang.String toParameterString();
    Code:
       0: aload_0
       1: getfield      #25                 // Field parameter:Ljava/lang/String;
       4: ifnull        12
       7: aload_0
       8: getfield      #25                 // Field parameter:Ljava/lang/String;
      11: areturn
      12: aload_0
      13: aload_0
      14: invokespecial #26                 // Method org/apache/dubbo/common/URL.toParameterString:()Ljava/lang/String;
      17: dup_x1
      18: putfield      #25                 // Field parameter:Ljava/lang/String;
      21: areturn

  public org.apache.dubbo.common.URL getUrlParameter(java.lang.String);
    Code:
       0: aload_0
       1: invokespecial #27                 // Method getUrls:()Ljava/util/Map;
       4: aload_1
       5: invokeinterface #28,  2           // InterfaceMethod java/util/Map.get:(Ljava/lang/Object;)Ljava/lang/Object;
      10: checkcast     #29                 // class org/apache/dubbo/common/URL
      13: astore_2
      14: aload_2
      15: ifnull        20
      18: aload_2
      19: areturn
      20: aload_0
      21: aload_1
      22: invokevirtual #30                 // Method getParameterAndDecoded:(Ljava/lang/String;)Ljava/lang/String;
      25: astore_3
      26: aload_3
      27: invokestatic  #31                 // Method org/apache/dubbo/common/utils/StringUtils.isEmpty:(Ljava/lang/String;)Z
      30: ifeq          35
      33: aconst_null
      34: areturn
      35: aload_3
      36: invokestatic  #32                 // Method org/apache/dubbo/common/URL.valueOf:(Ljava/lang/String;)Lorg/apache/dubbo/common/URL;
      39: astore_2
      40: aload_0
      41: invokespecial #27                 // Method getUrls:()Ljava/util/Map;
      44: aload_1
      45: aload_2
      46: invokeinterface #17,  3           // InterfaceMethod java/util/Map.put:(Ljava/lang/Object;Ljava/lang/Object;)Ljava/lang/Object;
      51: pop
      52: aload_2
      53: areturn

  public double getParameter(java.lang.String, double);
    Code:
       0: aload_0
       1: invokevirtual #33                 // Method getNumbers:()Ljava/util/Map;
       4: aload_1
       5: invokeinterface #28,  2           // InterfaceMethod java/util/Map.get:(Ljava/lang/Object;)Ljava/lang/Object;
      10: checkcast     #34                 // class java/lang/Number
      13: astore        4
      15: aload         4
      17: ifnull        26
      20: aload         4
      22: invokevirtual #35                 // Method java/lang/Number.doubleValue:()D
      25: dreturn
      26: aload_0
      27: aload_1
      28: invokevirtual #36                 // Method getParameter:(Ljava/lang/String;)Ljava/lang/String;
      31: astore        5
      33: aload         5
      35: invokestatic  #31                 // Method org/apache/dubbo/common/utils/StringUtils.isEmpty:(Ljava/lang/String;)Z
      38: ifeq          43
      41: dload_2
      42: dreturn
      43: aload         5
      45: invokestatic  #37                 // Method java/lang/Double.parseDouble:(Ljava/lang/String;)D
      48: dstore        6
      50: aload_0
      51: invokevirtual #33                 // Method getNumbers:()Ljava/util/Map;
      54: aload_1
      55: dload         6
      57: invokestatic  #38                 // Method java/lang/Double.valueOf:(D)Ljava/lang/Double;
      60: invokeinterface #17,  3           // InterfaceMethod java/util/Map.put:(Ljava/lang/Object;Ljava/lang/Object;)Ljava/lang/Object;
      65: pop
      66: dload         6
      68: dreturn

  public float getParameter(java.lang.String, float);
    Code:
       0: aload_0
       1: invokevirtual #33                 // Method getNumbers:()Ljava/util/Map;
       4: aload_1
       5: invokeinterface #28,  2           // InterfaceMethod java/util/Map.get:(Ljava/lang/Object;)Ljava/lang/Object;
      10: checkcast     #34                 // class java/lang/Number
      13: astore_3
      14: aload_3
      15: ifnull        23
      18: aload_3
      19: invokevirtual #39                 // Method java/lang/Number.floatValue:()F
      22: freturn
      23: aload_0
      24: aload_1
      25: invokevirtual #36                 // Method getParameter:(Ljava/lang/String;)Ljava/lang/String;
      28: astore        4
      30: aload         4
      32: invokestatic  #31                 // Method org/apache/dubbo/common/utils/StringUtils.isEmpty:(Ljava/lang/String;)Z
      35: ifeq          40
      38: fload_2
      39: freturn
      40: aload         4
      42: invokestatic  #40                 // Method java/lang/Float.parseFloat:(Ljava/lang/String;)F
      45: fstore        5
      47: aload_0
      48: invokevirtual #33                 // Method getNumbers:()Ljava/util/Map;
      51: aload_1
      52: fload         5
      54: invokestatic  #41                 // Method java/lang/Float.valueOf:(F)Ljava/lang/Float;
      57: invokeinterface #17,  3           // InterfaceMethod java/util/Map.put:(Ljava/lang/Object;Ljava/lang/Object;)Ljava/lang/Object;
      62: pop
      63: fload         5
      65: freturn

  public long getParameter(java.lang.String, long);
    Code:
       0: aload_0
       1: invokevirtual #33                 // Method getNumbers:()Ljava/util/Map;
       4: aload_1
       5: invokeinterface #28,  2           // InterfaceMethod java/util/Map.get:(Ljava/lang/Object;)Ljava/lang/Object;
      10: checkcast     #34                 // class java/lang/Number
      13: astore        4
      15: aload         4
      17: ifnull        26
      20: aload         4
      22: invokevirtual #42                 // Method java/lang/Number.longValue:()J
      25: lreturn
      26: aload_0
      27: aload_1
      28: invokevirtual #36                 // Method getParameter:(Ljava/lang/String;)Ljava/lang/String;
      31: astore        5
      33: aload         5
      35: invokestatic  #31                 // Method org/apache/dubbo/common/utils/StringUtils.isEmpty:(Ljava/lang/String;)Z
      38: ifeq          43
      41: lload_2
      42: lreturn
      43: aload         5
      45: invokestatic  #43                 // Method java/lang/Long.parseLong:(Ljava/lang/String;)J
      48: lstore        6
      50: aload_0
      51: invokevirtual #33                 // Method getNumbers:()Ljava/util/Map;
      54: aload_1
      55: lload         6
      57: invokestatic  #44                 // Method java/lang/Long.valueOf:(J)Ljava/lang/Long;
      60: invokeinterface #17,  3           // InterfaceMethod java/util/Map.put:(Ljava/lang/Object;Ljava/lang/Object;)Ljava/lang/Object;
      65: pop
      66: lload         6
      68: lreturn

  public int getParameter(java.lang.String, int);
    Code:
       0: aload_0
       1: invokevirtual #33                 // Method getNumbers:()Ljava/util/Map;
       4: aload_1
       5: invokeinterface #28,  2           // InterfaceMethod java/util/Map.get:(Ljava/lang/Object;)Ljava/lang/Object;
      10: checkcast     #34                 // class java/lang/Number
      13: astore_3
      14: aload_3
      15: ifnull        23
      18: aload_3
      19: invokevirtual #45                 // Method java/lang/Number.intValue:()I
      22: ireturn
      23: aload_0
      24: aload_1
      25: invokevirtual #36                 // Method getParameter:(Ljava/lang/String;)Ljava/lang/String;
      28: astore        4
      30: aload         4
      32: invokestatic  #31                 // Method org/apache/dubbo/common/utils/StringUtils.isEmpty:(Ljava/lang/String;)Z
      35: ifeq          40
      38: iload_2
      39: ireturn
      40: aload         4
      42: invokestatic  #46                 // Method java/lang/Integer.parseInt:(Ljava/lang/String;)I
      45: istore        5
      47: aload_0
      48: invokevirtual #33                 // Method getNumbers:()Ljava/util/Map;
      51: aload_1
      52: iload         5
      54: invokestatic  #47                 // Method java/lang/Integer.valueOf:(I)Ljava/lang/Integer;
      57: invokeinterface #17,  3           // InterfaceMethod java/util/Map.put:(Ljava/lang/Object;Ljava/lang/Object;)Ljava/lang/Object;
      62: pop
      63: iload         5
      65: ireturn

  public short getParameter(java.lang.String, short);
    Code:
       0: aload_0
       1: invokevirtual #33                 // Method getNumbers:()Ljava/util/Map;
       4: aload_1
       5: invokeinterface #28,  2           // InterfaceMethod java/util/Map.get:(Ljava/lang/Object;)Ljava/lang/Object;
      10: checkcast     #34                 // class java/lang/Number
      13: astore_3
      14: aload_3
      15: ifnull        23
      18: aload_3
      19: invokevirtual #48                 // Method java/lang/Number.shortValue:()S
      22: ireturn
      23: aload_0
      24: aload_1
      25: invokevirtual #36                 // Method getParameter:(Ljava/lang/String;)Ljava/lang/String;
      28: astore        4
      30: aload         4
      32: invokestatic  #31                 // Method org/apache/dubbo/common/utils/StringUtils.isEmpty:(Ljava/lang/String;)Z
      35: ifeq          40
      38: iload_2
      39: ireturn
      40: aload         4
      42: invokestatic  #49                 // Method java/lang/Short.parseShort:(Ljava/lang/String;)S
      45: istore        5
      47: aload_0
      48: invokevirtual #33                 // Method getNumbers:()Ljava/util/Map;
      51: aload_1
      52: iload         5
      54: invokestatic  #50                 // Method java/lang/Short.valueOf:(S)Ljava/lang/Short;
      57: invokeinterface #17,  3           // InterfaceMethod java/util/Map.put:(Ljava/lang/Object;Ljava/lang/Object;)Ljava/lang/Object;
      62: pop
      63: iload         5
      65: ireturn

  public byte getParameter(java.lang.String, byte);
    Code:
       0: aload_0
       1: invokevirtual #33                 // Method getNumbers:()Ljava/util/Map;
       4: aload_1
       5: invokeinterface #28,  2           // InterfaceMethod java/util/Map.get:(Ljava/lang/Object;)Ljava/lang/Object;
      10: checkcast     #34                 // class java/lang/Number
      13: astore_3
      14: aload_3
      15: ifnull        23
      18: aload_3
      19: invokevirtual #51                 // Method java/lang/Number.byteValue:()B
      22: ireturn
      23: aload_0
      24: aload_1
      25: invokevirtual #36                 // Method getParameter:(Ljava/lang/String;)Ljava/lang/String;
      28: astore        4
      30: aload         4
      32: invokestatic  #31                 // Method org/apache/dubbo/common/utils/StringUtils.isEmpty:(Ljava/lang/String;)Z
      35: ifeq          40
      38: iload_2
      39: ireturn
      40: aload         4
      42: invokestatic  #52                 // Method java/lang/Byte.parseByte:(Ljava/lang/String;)B
      45: istore        5
      47: aload_0
      48: invokevirtual #33                 // Method getNumbers:()Ljava/util/Map;
      51: aload_1
      52: iload         5
      54: invokestatic  #53                 // Method java/lang/Byte.valueOf:(B)Ljava/lang/Byte;
      57: invokeinterface #17,  3           // InterfaceMethod java/util/Map.put:(Ljava/lang/Object;Ljava/lang/Object;)Ljava/lang/Object;
      62: pop
      63: iload         5
      65: ireturn

  public double getMethodParameter(java.lang.String, java.lang.String, double);
    Code:
       0: aload_0
       1: aload_1
       2: aload_2
       3: invokespecial #54                 // Method getCachedNumber:(Ljava/lang/String;Ljava/lang/String;)Ljava/lang/Number;
       6: astore        5
       8: aload         5
      10: ifnull        19
      13: aload         5
      15: invokevirtual #35                 // Method java/lang/Number.doubleValue:()D
      18: dreturn
      19: aload_0
      20: aload_1
      21: aload_2
      22: invokevirtual #55                 // Method getMethodParameter:(Ljava/lang/String;Ljava/lang/String;)Ljava/lang/String;
      25: astore        6
      27: aload         6
      29: invokestatic  #31                 // Method org/apache/dubbo/common/utils/StringUtils.isEmpty:(Ljava/lang/String;)Z
      32: ifeq          37
      35: dload_3
      36: dreturn
      37: aload         6
      39: invokestatic  #37                 // Method java/lang/Double.parseDouble:(Ljava/lang/String;)D
      42: dstore        7
      44: aload_0
      45: aload_1
      46: aload_2
      47: dload         7
      49: invokestatic  #38                 // Method java/lang/Double.valueOf:(D)Ljava/lang/Double;
      52: invokespecial #56                 // Method updateCachedNumber:(Ljava/lang/String;Ljava/lang/String;Ljava/lang/Number;)V
      55: dload         7
      57: dreturn

  public float getMethodParameter(java.lang.String, java.lang.String, float);
    Code:
       0: aload_0
       1: aload_1
       2: aload_2
       3: invokespecial #54                 // Method getCachedNumber:(Ljava/lang/String;Ljava/lang/String;)Ljava/lang/Number;
       6: astore        4
       8: aload         4
      10: ifnull        19
      13: aload         4
      15: invokevirtual #39                 // Method java/lang/Number.floatValue:()F
      18: freturn
      19: aload_0
      20: aload_1
      21: aload_2
      22: invokevirtual #55                 // Method getMethodParameter:(Ljava/lang/String;Ljava/lang/String;)Ljava/lang/String;
      25: astore        5
      27: aload         5
      29: invokestatic  #31                 // Method org/apache/dubbo/common/utils/StringUtils.isEmpty:(Ljava/lang/String;)Z
      32: ifeq          37
      35: fload_3
      36: freturn
      37: aload         5
      39: invokestatic  #40                 // Method java/lang/Float.parseFloat:(Ljava/lang/String;)F
      42: fstore        6
      44: aload_0
      45: aload_1
      46: aload_2
      47: fload         6
      49: invokestatic  #41                 // Method java/lang/Float.valueOf:(F)Ljava/lang/Float;
      52: invokespecial #56                 // Method updateCachedNumber:(Ljava/lang/String;Ljava/lang/String;Ljava/lang/Number;)V
      55: fload         6
      57: freturn

  public long getMethodParameter(java.lang.String, java.lang.String, long);
    Code:
       0: aload_0
       1: aload_1
       2: aload_2
       3: invokespecial #54                 // Method getCachedNumber:(Ljava/lang/String;Ljava/lang/String;)Ljava/lang/Number;
       6: astore        5
       8: aload         5
      10: ifnull        19
      13: aload         5
      15: invokevirtual #42                 // Method java/lang/Number.longValue:()J
      18: lreturn
      19: aload_0
      20: aload_1
      21: aload_2
      22: invokevirtual #55                 // Method getMethodParameter:(Ljava/lang/String;Ljava/lang/String;)Ljava/lang/String;
      25: astore        6
      27: aload         6
      29: invokestatic  #31                 // Method org/apache/dubbo/common/utils/StringUtils.isEmpty:(Ljava/lang/String;)Z
      32: ifeq          37
      35: lload_3
      36: lreturn
      37: aload         6
      39: invokestatic  #43                 // Method java/lang/Long.parseLong:(Ljava/lang/String;)J
      42: lstore        7
      44: aload_0
      45: aload_1
      46: aload_2
      47: lload         7
      49: invokestatic  #44                 // Method java/lang/Long.valueOf:(J)Ljava/lang/Long;
      52: invokespecial #56                 // Method updateCachedNumber:(Ljava/lang/String;Ljava/lang/String;Ljava/lang/Number;)V
      55: lload         7
      57: lreturn

  public int getMethodParameter(java.lang.String, java.lang.String, int);
    Code:
       0: aload_0
       1: aload_1
       2: aload_2
       3: invokespecial #54                 // Method getCachedNumber:(Ljava/lang/String;Ljava/lang/String;)Ljava/lang/Number;
       6: astore        4
       8: aload         4
      10: ifnull        19
      13: aload         4
      15: invokevirtual #45                 // Method java/lang/Number.intValue:()I
      18: ireturn
      19: aload_0
      20: aload_1
      21: aload_2
      22: invokevirtual #55                 // Method getMethodParameter:(Ljava/lang/String;Ljava/lang/String;)Ljava/lang/String;
      25: astore        5
      27: aload         5
      29: invokestatic  #31                 // Method org/apache/dubbo/common/utils/StringUtils.isEmpty:(Ljava/lang/String;)Z
      32: ifeq          37
      35: iload_3
      36: ireturn
      37: aload         5
      39: invokestatic  #46                 // Method java/lang/Integer.parseInt:(Ljava/lang/String;)I
      42: istore        6
      44: aload_0
      45: aload_1
      46: aload_2
      47: iload         6
      49: invokestatic  #47                 // Method java/lang/Integer.valueOf:(I)Ljava/lang/Integer;
      52: invokespecial #56                 // Method updateCachedNumber:(Ljava/lang/String;Ljava/lang/String;Ljava/lang/Number;)V
      55: iload         6
      57: ireturn

  public short getMethodParameter(java.lang.String, java.lang.String, short);
    Code:
       0: aload_0
       1: aload_1
       2: aload_2
       3: invokespecial #54                 // Method getCachedNumber:(Ljava/lang/String;Ljava/lang/String;)Ljava/lang/Number;
       6: astore        4
       8: aload         4
      10: ifnull        19
      13: aload         4
      15: invokevirtual #48                 // Method java/lang/Number.shortValue:()S
      18: ireturn
      19: aload_0
      20: aload_1
      21: aload_2
      22: invokevirtual #55                 // Method getMethodParameter:(Ljava/lang/String;Ljava/lang/String;)Ljava/lang/String;
      25: astore        5
      27: aload         5
      29: invokestatic  #31                 // Method org/apache/dubbo/common/utils/StringUtils.isEmpty:(Ljava/lang/String;)Z
      32: ifeq          37
      35: iload_3
      36: ireturn
      37: aload         5
      39: invokestatic  #49                 // Method java/lang/Short.parseShort:(Ljava/lang/String;)S
      42: istore        6
      44: aload_0
      45: aload_1
      46: aload_2
      47: iload         6
      49: invokestatic  #50                 // Method java/lang/Short.valueOf:(S)Ljava/lang/Short;
      52: invokespecial #56                 // Method updateCachedNumber:(Ljava/lang/String;Ljava/lang/String;Ljava/lang/Number;)V
      55: iload         6
      57: ireturn

  public byte getMethodParameter(java.lang.String, java.lang.String, byte);
    Code:
       0: aload_0
       1: aload_1
       2: aload_2
       3: invokespecial #54                 // Method getCachedNumber:(Ljava/lang/String;Ljava/lang/String;)Ljava/lang/Number;
       6: astore        4
       8: aload         4
      10: ifnull        19
      13: aload         4
      15: invokevirtual #51                 // Method java/lang/Number.byteValue:()B
      18: ireturn
      19: aload_0
      20: aload_1
      21: aload_2
      22: invokevirtual #55                 // Method getMethodParameter:(Ljava/lang/String;Ljava/lang/String;)Ljava/lang/String;
      25: astore        5
      27: aload         5
      29: invokestatic  #31                 // Method org/apache/dubbo/common/utils/StringUtils.isEmpty:(Ljava/lang/String;)Z
      32: ifeq          37
      35: iload_3
      36: ireturn
      37: aload         5
      39: invokestatic  #52                 // Method java/lang/Byte.parseByte:(Ljava/lang/String;)B
      42: istore        6
      44: aload_0
      45: aload_1
      46: aload_2
      47: iload         6
      49: invokestatic  #53                 // Method java/lang/Byte.valueOf:(B)Ljava/lang/Byte;
      52: invokespecial #56                 // Method updateCachedNumber:(Ljava/lang/String;Ljava/lang/String;Ljava/lang/Number;)V
      55: iload         6
      57: ireturn

  public double getServiceParameter(java.lang.String, java.lang.String, double);
    Code:
       0: aload_0
       1: aload_1
       2: invokevirtual #57                 // Method getServiceNumbers:(Ljava/lang/String;)Ljava/util/Map;
       5: aload_2
       6: invokeinterface #28,  2           // InterfaceMethod java/util/Map.get:(Ljava/lang/Object;)Ljava/lang/Object;
      11: checkcast     #34                 // class java/lang/Number
      14: astore        5
      16: aload         5
      18: ifnull        27
      21: aload         5
      23: invokevirtual #35                 // Method java/lang/Number.doubleValue:()D
      26: dreturn
      27: aload_0
      28: aload_1
      29: aload_2
      30: invokevirtual #58                 // Method getServiceParameter:(Ljava/lang/String;Ljava/lang/String;)Ljava/lang/String;
      33: astore        6
      35: aload         6
      37: invokestatic  #31                 // Method org/apache/dubbo/common/utils/StringUtils.isEmpty:(Ljava/lang/String;)Z
      40: ifeq          45
      43: dload_3
      44: dreturn
      45: aload         6
      47: invokestatic  #37                 // Method java/lang/Double.parseDouble:(Ljava/lang/String;)D
      50: dstore        7
      52: aload_0
      53: invokevirtual #33                 // Method getNumbers:()Ljava/util/Map;
      56: aload_2
      57: dload         7
      59: invokestatic  #38                 // Method java/lang/Double.valueOf:(D)Ljava/lang/Double;
      62: invokeinterface #17,  3           // InterfaceMethod java/util/Map.put:(Ljava/lang/Object;Ljava/lang/Object;)Ljava/lang/Object;
      67: pop
      68: dload         7
      70: dreturn

  public float getServiceParameter(java.lang.String, java.lang.String, float);
    Code:
       0: aload_0
       1: aload_1
       2: invokevirtual #57                 // Method getServiceNumbers:(Ljava/lang/String;)Ljava/util/Map;
       5: aload_2
       6: invokeinterface #28,  2           // InterfaceMethod java/util/Map.get:(Ljava/lang/Object;)Ljava/lang/Object;
      11: checkcast     #34                 // class java/lang/Number
      14: astore        4
      16: aload         4
      18: ifnull        27
      21: aload         4
      23: invokevirtual #39                 // Method java/lang/Number.floatValue:()F
      26: freturn
      27: aload_0
      28: aload_1
      29: aload_2
      30: invokevirtual #58                 // Method getServiceParameter:(Ljava/lang/String;Ljava/lang/String;)Ljava/lang/String;
      33: astore        5
      35: aload         5
      37: invokestatic  #31                 // Method org/apache/dubbo/common/utils/StringUtils.isEmpty:(Ljava/lang/String;)Z
      40: ifeq          45
      43: fload_3
      44: freturn
      45: aload         5
      47: invokestatic  #40                 // Method java/lang/Float.parseFloat:(Ljava/lang/String;)F
      50: fstore        6
      52: aload_0
      53: invokevirtual #33                 // Method getNumbers:()Ljava/util/Map;
      56: aload_2
      57: fload         6
      59: invokestatic  #41                 // Method java/lang/Float.valueOf:(F)Ljava/lang/Float;
      62: invokeinterface #17,  3           // InterfaceMethod java/util/Map.put:(Ljava/lang/Object;Ljava/lang/Object;)Ljava/lang/Object;
      67: pop
      68: fload         6
      70: freturn

  public long getServiceParameter(java.lang.String, java.lang.String, long);
    Code:
       0: aload_0
       1: aload_1
       2: invokevirtual #57                 // Method getServiceNumbers:(Ljava/lang/String;)Ljava/util/Map;
       5: aload_2
       6: invokeinterface #28,  2           // InterfaceMethod java/util/Map.get:(Ljava/lang/Object;)Ljava/lang/Object;
      11: checkcast     #34                 // class java/lang/Number
      14: astore        5
      16: aload         5
      18: ifnull        27
      21: aload         5
      23: invokevirtual #42                 // Method java/lang/Number.longValue:()J
      26: lreturn
      27: aload_0
      28: aload_1
      29: aload_2
      30: invokevirtual #58                 // Method getServiceParameter:(Ljava/lang/String;Ljava/lang/String;)Ljava/lang/String;
      33: astore        6
      35: aload         6
      37: invokestatic  #31                 // Method org/apache/dubbo/common/utils/StringUtils.isEmpty:(Ljava/lang/String;)Z
      40: ifeq          45
      43: lload_3
      44: lreturn
      45: aload         6
      47: invokestatic  #43                 // Method java/lang/Long.parseLong:(Ljava/lang/String;)J
      50: lstore        7
      52: aload_0
      53: invokevirtual #33                 // Method getNumbers:()Ljava/util/Map;
      56: aload_2
      57: lload         7
      59: invokestatic  #44                 // Method java/lang/Long.valueOf:(J)Ljava/lang/Long;
      62: invokeinterface #17,  3           // InterfaceMethod java/util/Map.put:(Ljava/lang/Object;Ljava/lang/Object;)Ljava/lang/Object;
      67: pop
      68: lload         7
      70: lreturn

  public short getServiceParameter(java.lang.String, java.lang.String, short);
    Code:
       0: aload_0
       1: aload_1
       2: invokevirtual #57                 // Method getServiceNumbers:(Ljava/lang/String;)Ljava/util/Map;
       5: aload_2
       6: invokeinterface #28,  2           // InterfaceMethod java/util/Map.get:(Ljava/lang/Object;)Ljava/lang/Object;
      11: checkcast     #34                 // class java/lang/Number
      14: astore        4
      16: aload         4
      18: ifnull        27
      21: aload         4
      23: invokevirtual #48                 // Method java/lang/Number.shortValue:()S
      26: ireturn
      27: aload_0
      28: aload_1
      29: aload_2
      30: invokevirtual #58                 // Method getServiceParameter:(Ljava/lang/String;Ljava/lang/String;)Ljava/lang/String;
      33: astore        5
      35: aload         5
      37: invokestatic  #31                 // Method org/apache/dubbo/common/utils/StringUtils.isEmpty:(Ljava/lang/String;)Z
      40: ifeq          45
      43: iload_3
      44: ireturn
      45: aload         5
      47: invokestatic  #49                 // Method java/lang/Short.parseShort:(Ljava/lang/String;)S
      50: istore        6
      52: aload_0
      53: invokevirtual #33                 // Method getNumbers:()Ljava/util/Map;
      56: aload_2
      57: iload         6
      59: invokestatic  #50                 // Method java/lang/Short.valueOf:(S)Ljava/lang/Short;
      62: invokeinterface #17,  3           // InterfaceMethod java/util/Map.put:(Ljava/lang/Object;Ljava/lang/Object;)Ljava/lang/Object;
      67: pop
      68: iload         6
      70: ireturn

  public byte getServiceParameter(java.lang.String, java.lang.String, byte);
    Code:
       0: aload_0
       1: aload_1
       2: invokevirtual #57                 // Method getServiceNumbers:(Ljava/lang/String;)Ljava/util/Map;
       5: aload_2
       6: invokeinterface #28,  2           // InterfaceMethod java/util/Map.get:(Ljava/lang/Object;)Ljava/lang/Object;
      11: checkcast     #34                 // class java/lang/Number
      14: astore        4
      16: aload         4
      18: ifnull        27
      21: aload         4
      23: invokevirtual #51                 // Method java/lang/Number.byteValue:()B
      26: ireturn
      27: aload_0
      28: aload_1
      29: aload_2
      30: invokevirtual #58                 // Method getServiceParameter:(Ljava/lang/String;Ljava/lang/String;)Ljava/lang/String;
      33: astore        5
      35: aload         5
      37: invokestatic  #31                 // Method org/apache/dubbo/common/utils/StringUtils.isEmpty:(Ljava/lang/String;)Z
      40: ifeq          45
      43: iload_3
      44: ireturn
      45: aload         5
      47: invokestatic  #52                 // Method java/lang/Byte.parseByte:(Ljava/lang/String;)B
      50: istore        6
      52: aload_0
      53: invokevirtual #33                 // Method getNumbers:()Ljava/util/Map;
      56: aload_2
      57: iload         6
      59: invokestatic  #53                 // Method java/lang/Byte.valueOf:(B)Ljava/lang/Byte;
      62: invokeinterface #17,  3           // InterfaceMethod java/util/Map.put:(Ljava/lang/Object;Ljava/lang/Object;)Ljava/lang/Object;
      67: pop
      68: iload         6
      70: ireturn

  public double getServiceMethodParameter(java.lang.String, java.lang.String, java.lang.String, double);
    Code:
       0: aload_0
       1: aload_2
       2: aload_3
       3: invokespecial #54                 // Method getCachedNumber:(Ljava/lang/String;Ljava/lang/String;)Ljava/lang/Number;
       6: astore        6
       8: aload         6
      10: ifnull        19
      13: aload         6
      15: invokevirtual #35                 // Method java/lang/Number.doubleValue:()D
      18: dreturn
      19: aload_0
      20: aload_1
      21: aload_2
      22: aload_3
      23: invokevirtual #59                 // Method getServiceMethodParameter:(Ljava/lang/String;Ljava/lang/String;Ljava/lang/String;)Ljava/lang/String;
      26: astore        7
      28: aload         7
      30: invokestatic  #31                 // Method org/apache/dubbo/common/utils/StringUtils.isEmpty:(Ljava/lang/String;)Z
      33: ifeq          39
      36: dload         4
      38: dreturn
      39: aload         7
      41: invokestatic  #37                 // Method java/lang/Double.parseDouble:(Ljava/lang/String;)D
      44: dstore        8
      46: aload_0
      47: aload_2
      48: aload_3
      49: dload         8
      51: invokestatic  #38                 // Method java/lang/Double.valueOf:(D)Ljava/lang/Double;
      54: invokespecial #56                 // Method updateCachedNumber:(Ljava/lang/String;Ljava/lang/String;Ljava/lang/Number;)V
      57: dload         8
      59: dreturn

  public float getServiceMethodParameter(java.lang.String, java.lang.String, java.lang.String, float);
    Code:
       0: aload_0
       1: aload_2
       2: aload_3
       3: invokespecial #54                 // Method getCachedNumber:(Ljava/lang/String;Ljava/lang/String;)Ljava/lang/Number;
       6: astore        5
       8: aload         5
      10: ifnull        19
      13: aload         5
      15: invokevirtual #39                 // Method java/lang/Number.floatValue:()F
      18: freturn
      19: aload_0
      20: aload_1
      21: aload_2
      22: aload_3
      23: invokevirtual #59                 // Method getServiceMethodParameter:(Ljava/lang/String;Ljava/lang/String;Ljava/lang/String;)Ljava/lang/String;
      26: astore        6
      28: aload         6
      30: invokestatic  #31                 // Method org/apache/dubbo/common/utils/StringUtils.isEmpty:(Ljava/lang/String;)Z
      33: ifeq          39
      36: fload         4
      38: freturn
      39: aload         6
      41: invokestatic  #40                 // Method java/lang/Float.parseFloat:(Ljava/lang/String;)F
      44: fstore        7
      46: aload_0
      47: aload_2
      48: aload_3
      49: fload         7
      51: invokestatic  #41                 // Method java/lang/Float.valueOf:(F)Ljava/lang/Float;
      54: invokespecial #56                 // Method updateCachedNumber:(Ljava/lang/String;Ljava/lang/String;Ljava/lang/Number;)V
      57: fload         7
      59: freturn

  public long getServiceMethodParameter(java.lang.String, java.lang.String, java.lang.String, long);
    Code:
       0: aload_0
       1: aload_2
       2: aload_3
       3: invokespecial #54                 // Method getCachedNumber:(Ljava/lang/String;Ljava/lang/String;)Ljava/lang/Number;
       6: astore        6
       8: aload         6
      10: ifnull        19
      13: aload         6
      15: invokevirtual #42                 // Method java/lang/Number.longValue:()J
      18: lreturn
      19: aload_0
      20: aload_1
      21: aload_2
      22: aload_3
      23: invokevirtual #59                 // Method getServiceMethodParameter:(Ljava/lang/String;Ljava/lang/String;Ljava/lang/String;)Ljava/lang/String;
      26: astore        7
      28: aload         7
      30: invokestatic  #31                 // Method org/apache/dubbo/common/utils/StringUtils.isEmpty:(Ljava/lang/String;)Z
      33: ifeq          39
      36: lload         4
      38: lreturn
      39: aload         7
      41: invokestatic  #43                 // Method java/lang/Long.parseLong:(Ljava/lang/String;)J
      44: lstore        8
      46: aload_0
      47: aload_2
      48: aload_3
      49: lload         8
      51: invokestatic  #44                 // Method java/lang/Long.valueOf:(J)Ljava/lang/Long;
      54: invokespecial #56                 // Method updateCachedNumber:(Ljava/lang/String;Ljava/lang/String;Ljava/lang/Number;)V
      57: lload         8
      59: lreturn

  public int getServiceMethodParameter(java.lang.String, java.lang.String, java.lang.String, int);
    Code:
       0: aload_0
       1: aload_2
       2: aload_3
       3: invokespecial #54                 // Method getCachedNumber:(Ljava/lang/String;Ljava/lang/String;)Ljava/lang/Number;
       6: astore        5
       8: aload         5
      10: ifnull        19
      13: aload         5
      15: invokevirtual #45                 // Method java/lang/Number.intValue:()I
      18: ireturn
      19: aload_0
      20: aload_1
      21: aload_2
      22: aload_3
      23: invokevirtual #59                 // Method getServiceMethodParameter:(Ljava/lang/String;Ljava/lang/String;Ljava/lang/String;)Ljava/lang/String;
      26: astore        6
      28: aload         6
      30: invokestatic  #31                 // Method org/apache/dubbo/common/utils/StringUtils.isEmpty:(Ljava/lang/String;)Z
      33: ifeq          39
      36: iload         4
      38: ireturn
      39: aload         6
      41: invokestatic  #46                 // Method java/lang/Integer.parseInt:(Ljava/lang/String;)I
      44: istore        7
      46: aload_0
      47: aload_2
      48: aload_3
      49: iload         7
      51: invokestatic  #47                 // Method java/lang/Integer.valueOf:(I)Ljava/lang/Integer;
      54: invokespecial #56                 // Method updateCachedNumber:(Ljava/lang/String;Ljava/lang/String;Ljava/lang/Number;)V
      57: iload         7
      59: ireturn

  public short getServiceMethodParameter(java.lang.String, java.lang.String, java.lang.String, short);
    Code:
       0: aload_0
       1: aload_2
       2: aload_3
       3: invokespecial #54                 // Method getCachedNumber:(Ljava/lang/String;Ljava/lang/String;)Ljava/lang/Number;
       6: astore        5
       8: aload         5
      10: ifnull        19
      13: aload         5
      15: invokevirtual #48                 // Method java/lang/Number.shortValue:()S
      18: ireturn
      19: aload_0
      20: aload_1
      21: aload_2
      22: aload_3
      23: invokevirtual #59                 // Method getServiceMethodParameter:(Ljava/lang/String;Ljava/lang/String;Ljava/lang/String;)Ljava/lang/String;
      26: astore        6
      28: aload         6
      30: invokestatic  #31                 // Method org/apache/dubbo/common/utils/StringUtils.isEmpty:(Ljava/lang/String;)Z
      33: ifeq          39
      36: iload         4
      38: ireturn
      39: aload         6
      41: invokestatic  #49                 // Method java/lang/Short.parseShort:(Ljava/lang/String;)S
      44: istore        7
      46: aload_0
      47: aload_2
      48: aload_3
      49: iload         7
      51: invokestatic  #50                 // Method java/lang/Short.valueOf:(S)Ljava/lang/Short;
      54: invokespecial #56                 // Method updateCachedNumber:(Ljava/lang/String;Ljava/lang/String;Ljava/lang/Number;)V
      57: iload         7
      59: ireturn

  public byte getServiceMethodParameter(java.lang.String, java.lang.String, java.lang.String, byte);
    Code:
       0: aload_0
       1: aload_2
       2: aload_3
       3: invokespecial #54                 // Method getCachedNumber:(Ljava/lang/String;Ljava/lang/String;)Ljava/lang/Number;
       6: astore        5
       8: aload         5
      10: ifnull        19
      13: aload         5
      15: invokevirtual #51                 // Method java/lang/Number.byteValue:()B
      18: ireturn
      19: aload_0
      20: aload_1
      21: aload_2
      22: aload_3
      23: invokevirtual #59                 // Method getServiceMethodParameter:(Ljava/lang/String;Ljava/lang/String;Ljava/lang/String;)Ljava/lang/String;
      26: astore        6
      28: aload         6
      30: invokestatic  #31                 // Method org/apache/dubbo/common/utils/StringUtils.isEmpty:(Ljava/lang/String;)Z
      33: ifeq          39
      36: iload         4
      38: ireturn
      39: aload         6
      41: invokestatic  #52                 // Method java/lang/Byte.parseByte:(Ljava/lang/String;)B
      44: istore        7
      46: aload_0
      47: aload_2
      48: aload_3
      49: iload         7
      51: invokestatic  #53                 // Method java/lang/Byte.valueOf:(B)Ljava/lang/Byte;
      54: invokespecial #56                 // Method updateCachedNumber:(Ljava/lang/String;Ljava/lang/String;Ljava/lang/Number;)V
      57: iload         7
      59: ireturn

  private java.util.Map<java.lang.String, org.apache.dubbo.common.URL> getUrls();
    Code:
       0: aload_0
       1: getfield      #60                 // Field urls:Ljava/util/concurrent/ConcurrentMap;
       4: ifnonnull     18
       7: aload_0
       8: new           #61                 // class java/util/concurrent/ConcurrentHashMap
      11: dup
      12: invokespecial #62                 // Method java/util/concurrent/ConcurrentHashMap."<init>":()V
      15: putfield      #60                 // Field urls:Ljava/util/concurrent/ConcurrentMap;
      18: aload_0
      19: getfield      #60                 // Field urls:Ljava/util/concurrent/ConcurrentMap;
      22: areturn

  protected java.util.Map<java.lang.String, java.lang.Number> getNumbers();
    Code:
       0: aload_0
       1: getfield      #63                 // Field numbers:Ljava/util/concurrent/ConcurrentMap;
       4: ifnonnull     18
       7: aload_0
       8: new           #61                 // class java/util/concurrent/ConcurrentHashMap
      11: dup
      12: invokespecial #62                 // Method java/util/concurrent/ConcurrentHashMap."<init>":()V
      15: putfield      #63                 // Field numbers:Ljava/util/concurrent/ConcurrentMap;
      18: aload_0
      19: getfield      #63                 // Field numbers:Ljava/util/concurrent/ConcurrentMap;
      22: areturn

  private java.lang.Number getCachedNumber(java.lang.String, java.lang.String);
    Code:
       0: aload_0
       1: invokevirtual #64                 // Method getMethodNumbers:()Ljava/util/concurrent/ConcurrentMap;
       4: aload_1
       5: invokeinterface #65,  2           // InterfaceMethod java/util/concurrent/ConcurrentMap.get:(Ljava/lang/Object;)Ljava/lang/Object;
      10: checkcast     #3                  // class java/util/Map
      13: astore_3
      14: aload_3
      15: ifnull        29
      18: aload_3
      19: aload_2
      20: invokeinterface #28,  2           // InterfaceMethod java/util/Map.get:(Ljava/lang/Object;)Ljava/lang/Object;
      25: checkcast     #34                 // class java/lang/Number
      28: areturn
      29: aconst_null
      30: areturn

  private void updateCachedNumber(java.lang.String, java.lang.String, java.lang.Number);
    Code:
       0: aload_0
       1: invokevirtual #64                 // Method getMethodNumbers:()Ljava/util/concurrent/ConcurrentMap;
       4: aload_1
       5: invokedynamic #66,  0             // InvokeDynamic #0:apply:()Ljava/util/function/Function;
      10: invokestatic  #67                 // Method org/apache/dubbo/common/utils/ConcurrentHashMapUtils.computeIfAbsent:(Ljava/util/concurrent/ConcurrentMap;Ljava/lang/Object;Ljava/util/function/Function;)Ljava/lang/Object;
      13: checkcast     #3                  // class java/util/Map
      16: astore        4
      18: aload         4
      20: aload_2
      21: aload_3
      22: invokeinterface #17,  3           // InterfaceMethod java/util/Map.put:(Ljava/lang/Object;Ljava/lang/Object;)Ljava/lang/Object;
      27: pop
      28: return

  protected java.util.concurrent.ConcurrentMap<java.lang.String, java.util.Map<java.lang.String, java.lang.Number>> getMethodNumbers();
    Code:
       0: aload_0
       1: getfield      #68                 // Field methodNumbers:Ljava/util/concurrent/ConcurrentMap;
       4: ifnonnull     18
       7: aload_0
       8: new           #61                 // class java/util/concurrent/ConcurrentHashMap
      11: dup
      12: invokespecial #62                 // Method java/util/concurrent/ConcurrentHashMap."<init>":()V
      15: putfield      #68                 // Field methodNumbers:Ljava/util/concurrent/ConcurrentMap;
      18: aload_0
      19: getfield      #68                 // Field methodNumbers:Ljava/util/concurrent/ConcurrentMap;
      22: areturn

  protected java.util.Map<java.lang.String, java.lang.Number> getServiceNumbers(java.lang.String);
    Code:
       0: aload_0
       1: invokevirtual #33                 // Method getNumbers:()Ljava/util/Map;
       4: areturn

  protected java.util.Map<java.lang.String, java.util.Map<java.lang.String, java.lang.Number>> getServiceMethodNumbers(java.lang.String);
    Code:
       0: aload_0
       1: invokevirtual #64                 // Method getMethodNumbers:()Ljava/util/concurrent/ConcurrentMap;
       4: areturn

  public org.apache.dubbo.common.URL putAttribute(java.lang.String, java.lang.Object);
    Code:
       0: aload_0
       1: aload_1
       2: aload_2
       3: invokevirtual #69                 // Method putAttribute:(Ljava/lang/String;Ljava/lang/Object;)Lorg/apache/dubbo/common/url/component/ServiceConfigURL;
       6: areturn

  private static java.util.Map lambda$updateCachedNumber$0(java.lang.String);
    Code:
       0: new           #12                 // class java/util/HashMap
       3: dup
       4: invokespecial #13                 // Method java/util/HashMap."<init>":()V
       7: areturn
}
