Compiled from "URLAddress.java"
public class org.apache.dubbo.common.url.component.URLAddress implements java.io.Serializable {
  private static final long serialVersionUID;

  protected java.lang.String host;

  protected int port;

  protected transient java.lang.String rawAddress;

  protected transient long timestamp;

  public org.apache.dubbo.common.url.component.URLAddress(java.lang.String, int);
    Code:
       0: aload_0
       1: aload_1
       2: iload_2
       3: aconst_null
       4: invokespecial #2                  // Method "<init>":(Ljava/lang/String;ILjava/lang/String;)V
       7: return

  public org.apache.dubbo.common.url.component.URLAddress(java.lang.String, int, java.lang.String);
    Code:
       0: aload_0
       1: invokespecial #3                  // Method java/lang/Object."<init>":()V
       4: aload_0
       5: aload_1
       6: putfield      #4                  // Field host:Ljava/lang/String;
       9: iload_2
      10: iconst_0
      11: invokestatic  #5                  // Method java/lang/Math.max:(II)I
      14: istore_2
      15: aload_0
      16: iload_2
      17: putfield      #6                  // Field port:I
      20: aload_0
      21: aload_3
      22: putfield      #7                  // Field rawAddress:Ljava/lang/String;
      25: aload_0
      26: invokestatic  #8                  // Method java/lang/System.currentTimeMillis:()J
      29: putfield      #9                  // Field timestamp:J
      32: return

  public java.lang.String getProtocol();
    Code:
       0: ldc           #10                 // String
       2: areturn

  public org.apache.dubbo.common.url.component.URLAddress setProtocol(java.lang.String);
    Code:
       0: aload_0
       1: areturn

  public java.lang.String getUsername();
    Code:
       0: ldc           #10                 // String
       2: areturn

  public org.apache.dubbo.common.url.component.URLAddress setUsername(java.lang.String);
    Code:
       0: aload_0
       1: areturn

  public java.lang.String getPassword();
    Code:
       0: ldc           #10                 // String
       2: areturn

  public org.apache.dubbo.common.url.component.URLAddress setPassword(java.lang.String);
    Code:
       0: aload_0
       1: areturn

  public java.lang.String getPath();
    Code:
       0: ldc           #10                 // String
       2: areturn

  public org.apache.dubbo.common.url.component.URLAddress setPath(java.lang.String);
    Code:
       0: aload_0
       1: areturn

  public java.lang.String getHost();
    Code:
       0: aload_0
       1: getfield      #4                  // Field host:Ljava/lang/String;
       4: areturn

  public org.apache.dubbo.common.url.component.URLAddress setHost(java.lang.String);
    Code:
       0: new           #11                 // class org/apache/dubbo/common/url/component/URLAddress
       3: dup
       4: aload_1
       5: aload_0
       6: getfield      #6                  // Field port:I
       9: aconst_null
      10: invokespecial #2                  // Method "<init>":(Ljava/lang/String;ILjava/lang/String;)V
      13: areturn

  public int getPort();
    Code:
       0: aload_0
       1: getfield      #6                  // Field port:I
       4: ireturn

  public org.apache.dubbo.common.url.component.URLAddress setPort(int);
    Code:
       0: new           #11                 // class org/apache/dubbo/common/url/component/URLAddress
       3: dup
       4: aload_0
       5: getfield      #4                  // Field host:Ljava/lang/String;
       8: iload_1
       9: aconst_null
      10: invokespecial #2                  // Method "<init>":(Ljava/lang/String;ILjava/lang/String;)V
      13: areturn

  public java.lang.String getAddress();
    Code:
       0: aload_0
       1: getfield      #7                  // Field rawAddress:Ljava/lang/String;
       4: ifnonnull     23
       7: aload_0
       8: aload_0
       9: aload_0
      10: invokevirtual #12                 // Method getHost:()Ljava/lang/String;
      13: aload_0
      14: invokevirtual #13                 // Method getPort:()I
      17: invokevirtual #14                 // Method getAddress:(Ljava/lang/String;I)Ljava/lang/String;
      20: putfield      #7                  // Field rawAddress:Ljava/lang/String;
      23: aload_0
      24: getfield      #7                  // Field rawAddress:Ljava/lang/String;
      27: areturn

  public org.apache.dubbo.common.url.component.URLAddress setAddress(java.lang.String, int);
    Code:
       0: new           #11                 // class org/apache/dubbo/common/url/component/URLAddress
       3: dup
       4: aload_1
       5: iload_2
       6: aload_0
       7: getfield      #7                  // Field rawAddress:Ljava/lang/String;
      10: invokespecial #2                  // Method "<init>":(Ljava/lang/String;ILjava/lang/String;)V
      13: areturn

  public java.lang.String getIp();
    Code:
       0: aload_0
       1: invokevirtual #12                 // Method getHost:()Ljava/lang/String;
       4: invokestatic  #15                 // Method org/apache/dubbo/common/utils/NetUtils.getIpByHost:(Ljava/lang/String;)Ljava/lang/String;
       7: areturn

  public java.lang.String getRawAddress();
    Code:
       0: aload_0
       1: getfield      #7                  // Field rawAddress:Ljava/lang/String;
       4: areturn

  protected java.lang.String getAddress(java.lang.String, int);
    Code:
       0: iload_2
       1: ifgt          8
       4: aload_1
       5: goto          31
       8: new           #16                 // class java/lang/StringBuilder
      11: dup
      12: invokespecial #17                 // Method java/lang/StringBuilder."<init>":()V
      15: aload_1
      16: invokevirtual #18                 // Method java/lang/StringBuilder.append:(Ljava/lang/String;)Ljava/lang/StringBuilder;
      19: bipush        58
      21: invokevirtual #19                 // Method java/lang/StringBuilder.append:(C)Ljava/lang/StringBuilder;
      24: iload_2
      25: invokevirtual #20                 // Method java/lang/StringBuilder.append:(I)Ljava/lang/StringBuilder;
      28: invokevirtual #21                 // Method java/lang/StringBuilder.toString:()Ljava/lang/String;
      31: areturn

  public long getTimestamp();
    Code:
       0: aload_0
       1: getfield      #9                  // Field timestamp:J
       4: lreturn

  public void setTimestamp(long);
    Code:
       0: aload_0
       1: lload_1
       2: putfield      #9                  // Field timestamp:J
       5: return

  public int hashCode();
    Code:
       0: aload_0
       1: getfield      #4                  // Field host:Ljava/lang/String;
       4: invokevirtual #22                 // Method java/lang/String.hashCode:()I
       7: bipush        31
       9: imul
      10: aload_0
      11: getfield      #6                  // Field port:I
      14: iadd
      15: ireturn

  public boolean equals(java.lang.Object);
    Code:
       0: aload_0
       1: aload_1
       2: if_acmpne     7
       5: iconst_1
       6: ireturn
       7: aload_1
       8: instanceof    #11                 // class org/apache/dubbo/common/url/component/URLAddress
      11: ifne          16
      14: iconst_0
      15: ireturn
      16: aload_1
      17: checkcast     #11                 // class org/apache/dubbo/common/url/component/URLAddress
      20: astore_2
      21: aload_0
      22: invokevirtual #23                 // Method getProtocol:()Ljava/lang/String;
      25: aload_2
      26: invokevirtual #23                 // Method getProtocol:()Ljava/lang/String;
      29: invokestatic  #24                 // Method java/util/Objects.equals:(Ljava/lang/Object;Ljava/lang/Object;)Z
      32: ifeq          115
      35: aload_0
      36: invokevirtual #25                 // Method getUsername:()Ljava/lang/String;
      39: aload_2
      40: invokevirtual #25                 // Method getUsername:()Ljava/lang/String;
      43: invokestatic  #24                 // Method java/util/Objects.equals:(Ljava/lang/Object;Ljava/lang/Object;)Z
      46: ifeq          115
      49: aload_0
      50: invokevirtual #26                 // Method getPassword:()Ljava/lang/String;
      53: aload_2
      54: invokevirtual #26                 // Method getPassword:()Ljava/lang/String;
      57: invokestatic  #24                 // Method java/util/Objects.equals:(Ljava/lang/Object;Ljava/lang/Object;)Z
      60: ifeq          115
      63: aload_0
      64: invokevirtual #27                 // Method getPath:()Ljava/lang/String;
      67: aload_2
      68: invokevirtual #27                 // Method getPath:()Ljava/lang/String;
      71: invokestatic  #24                 // Method java/util/Objects.equals:(Ljava/lang/Object;Ljava/lang/Object;)Z
      74: ifeq          115
      77: aload_0
      78: invokevirtual #12                 // Method getHost:()Ljava/lang/String;
      81: aload_2
      82: invokevirtual #12                 // Method getHost:()Ljava/lang/String;
      85: invokestatic  #24                 // Method java/util/Objects.equals:(Ljava/lang/Object;Ljava/lang/Object;)Z
      88: ifeq          115
      91: aload_0
      92: invokevirtual #13                 // Method getPort:()I
      95: invokestatic  #28                 // Method java/lang/Integer.valueOf:(I)Ljava/lang/Integer;
      98: aload_2
      99: invokevirtual #13                 // Method getPort:()I
     102: invokestatic  #28                 // Method java/lang/Integer.valueOf:(I)Ljava/lang/Integer;
     105: invokestatic  #24                 // Method java/util/Objects.equals:(Ljava/lang/Object;Ljava/lang/Object;)Z
     108: ifeq          115
     111: iconst_1
     112: goto          116
     115: iconst_0
     116: ireturn

  public java.lang.String toString();
    Code:
       0: aload_0
       1: getfield      #7                  // Field rawAddress:Ljava/lang/String;
       4: ifnull        12
       7: aload_0
       8: getfield      #7                  // Field rawAddress:Ljava/lang/String;
      11: areturn
      12: new           #16                 // class java/lang/StringBuilder
      15: dup
      16: invokespecial #17                 // Method java/lang/StringBuilder."<init>":()V
      19: astore_1
      20: aload_0
      21: getfield      #4                  // Field host:Ljava/lang/String;
      24: invokestatic  #29                 // Method org/apache/dubbo/common/utils/StringUtils.isNotEmpty:(Ljava/lang/String;)Z
      27: ifeq          62
      30: aload_1
      31: aload_0
      32: getfield      #4                  // Field host:Ljava/lang/String;
      35: invokevirtual #18                 // Method java/lang/StringBuilder.append:(Ljava/lang/String;)Ljava/lang/StringBuilder;
      38: pop
      39: aload_0
      40: getfield      #6                  // Field port:I
      43: ifle          62
      46: aload_1
      47: bipush        58
      49: invokevirtual #19                 // Method java/lang/StringBuilder.append:(C)Ljava/lang/StringBuilder;
      52: pop
      53: aload_1
      54: aload_0
      55: getfield      #6                  // Field port:I
      58: invokevirtual #20                 // Method java/lang/StringBuilder.append:(I)Ljava/lang/StringBuilder;
      61: pop
      62: aload_1
      63: invokevirtual #21                 // Method java/lang/StringBuilder.toString:()Ljava/lang/String;
      66: areturn

  public static org.apache.dubbo.common.url.component.URLAddress parse(java.lang.String, java.lang.String, boolean);
    Code:
       0: aload_0
       1: astore_3
       2: iload_2
       3: ifeq          13
       6: aload_0
       7: ldc           #30                 // String UTF-8
       9: invokestatic  #31                 // Method java/net/URLDecoder.decode:(Ljava/lang/String;Ljava/lang/String;)Ljava/lang/String;
      12: astore_3
      13: aload_3
      14: ldc           #32                 // String /
      16: invokevirtual #33                 // Method java/lang/String.contains:(Ljava/lang/CharSequence;)Z
      19: istore        4
      21: iload         4
      23: ifeq          33
      26: aload_3
      27: aload_0
      28: aload_1
      29: invokestatic  #34                 // Method createPathURLAddress:(Ljava/lang/String;Ljava/lang/String;Ljava/lang/String;)Lorg/apache/dubbo/common/url/component/PathURLAddress;
      32: areturn
      33: aload_3
      34: aload_0
      35: aload_1
      36: invokestatic  #35                 // Method createURLAddress:(Ljava/lang/String;Ljava/lang/String;Ljava/lang/String;)Lorg/apache/dubbo/common/url/component/URLAddress;
      39: areturn
      40: astore_3
      41: new           #37                 // class java/lang/RuntimeException
      44: dup
      45: aload_3
      46: invokevirtual #38                 // Method java/io/UnsupportedEncodingException.getMessage:()Ljava/lang/String;
      49: aload_3
      50: invokespecial #39                 // Method java/lang/RuntimeException."<init>":(Ljava/lang/String;Ljava/lang/Throwable;)V
      53: athrow
    Exception table:
       from    to  target type
           0    32    40   Class java/io/UnsupportedEncodingException
          33    39    40   Class java/io/UnsupportedEncodingException

  private static org.apache.dubbo.common.url.component.URLAddress createURLAddress(java.lang.String, java.lang.String, java.lang.String);
    Code:
       0: aconst_null
       1: astore_3
       2: iconst_0
       3: istore        4
       5: aload_0
       6: bipush        58
       8: invokevirtual #40                 // Method java/lang/String.lastIndexOf:(I)I
      11: istore        5
      13: iload         5
      15: iflt          67
      18: iload         5
      20: aload_0
      21: invokevirtual #41                 // Method java/lang/String.length:()I
      24: iconst_1
      25: isub
      26: if_icmpge     67
      29: aload_0
      30: bipush        37
      32: invokevirtual #40                 // Method java/lang/String.lastIndexOf:(I)I
      35: iload         5
      37: if_icmple     43
      40: goto          69
      43: aload_0
      44: iload         5
      46: iconst_1
      47: iadd
      48: invokevirtual #42                 // Method java/lang/String.substring:(I)Ljava/lang/String;
      51: invokestatic  #43                 // Method java/lang/Integer.parseInt:(Ljava/lang/String;)I
      54: istore        4
      56: aload_0
      57: iconst_0
      58: iload         5
      60: invokevirtual #44                 // Method java/lang/String.substring:(II)Ljava/lang/String;
      63: astore_3
      64: goto          69
      67: aload_0
      68: astore_3
      69: new           #11                 // class org/apache/dubbo/common/url/component/URLAddress
      72: dup
      73: aload_3
      74: iload         4
      76: aload_1
      77: invokespecial #2                  // Method "<init>":(Ljava/lang/String;ILjava/lang/String;)V
      80: areturn

  private static org.apache.dubbo.common.url.component.PathURLAddress createPathURLAddress(java.lang.String, java.lang.String, java.lang.String);
    Code:
       0: aload_2
       1: astore_3
       2: aconst_null
       3: astore        4
       5: aconst_null
       6: astore        5
       8: aconst_null
       9: astore        6
      11: aconst_null
      12: astore        7
      14: iconst_0
      15: istore        8
      17: aload_0
      18: ldc           #45                 // String ://
      20: invokevirtual #46                 // Method java/lang/String.indexOf:(Ljava/lang/String;)I
      23: istore        9
      25: iload         9
      27: iflt          87
      30: iload         9
      32: ifne          67
      35: new           #47                 // class java/lang/IllegalStateException
      38: dup
      39: new           #16                 // class java/lang/StringBuilder
      42: dup
      43: invokespecial #17                 // Method java/lang/StringBuilder."<init>":()V
      46: ldc           #48                 // String url missing protocol: \"
      48: invokevirtual #18                 // Method java/lang/StringBuilder.append:(Ljava/lang/String;)Ljava/lang/StringBuilder;
      51: aload_0
      52: invokevirtual #18                 // Method java/lang/StringBuilder.append:(Ljava/lang/String;)Ljava/lang/StringBuilder;
      55: ldc           #49                 // String \"
      57: invokevirtual #18                 // Method java/lang/StringBuilder.append:(Ljava/lang/String;)Ljava/lang/StringBuilder;
      60: invokevirtual #21                 // Method java/lang/StringBuilder.toString:()Ljava/lang/String;
      63: invokespecial #50                 // Method java/lang/IllegalStateException."<init>":(Ljava/lang/String;)V
      66: athrow
      67: aload_0
      68: iconst_0
      69: iload         9
      71: invokevirtual #44                 // Method java/lang/String.substring:(II)Ljava/lang/String;
      74: astore_3
      75: aload_0
      76: iload         9
      78: iconst_3
      79: iadd
      80: invokevirtual #42                 // Method java/lang/String.substring:(I)Ljava/lang/String;
      83: astore_0
      84: goto          154
      87: aload_0
      88: ldc           #51                 // String :/
      90: invokevirtual #46                 // Method java/lang/String.indexOf:(Ljava/lang/String;)I
      93: istore        9
      95: iload         9
      97: iflt          154
     100: iload         9
     102: ifne          137
     105: new           #47                 // class java/lang/IllegalStateException
     108: dup
     109: new           #16                 // class java/lang/StringBuilder
     112: dup
     113: invokespecial #17                 // Method java/lang/StringBuilder."<init>":()V
     116: ldc           #48                 // String url missing protocol: \"
     118: invokevirtual #18                 // Method java/lang/StringBuilder.append:(Ljava/lang/String;)Ljava/lang/StringBuilder;
     121: aload_0
     122: invokevirtual #18                 // Method java/lang/StringBuilder.append:(Ljava/lang/String;)Ljava/lang/StringBuilder;
     125: ldc           #49                 // String \"
     127: invokevirtual #18                 // Method java/lang/StringBuilder.append:(Ljava/lang/String;)Ljava/lang/StringBuilder;
     130: invokevirtual #21                 // Method java/lang/StringBuilder.toString:()Ljava/lang/String;
     133: invokespecial #50                 // Method java/lang/IllegalStateException."<init>":(Ljava/lang/String;)V
     136: athrow
     137: aload_0
     138: iconst_0
     139: iload         9
     141: invokevirtual #44                 // Method java/lang/String.substring:(II)Ljava/lang/String;
     144: astore_3
     145: aload_0
     146: iload         9
     148: iconst_1
     149: iadd
     150: invokevirtual #42                 // Method java/lang/String.substring:(I)Ljava/lang/String;
     153: astore_0
     154: aload_0
     155: bipush        47
     157: invokevirtual #52                 // Method java/lang/String.indexOf:(I)I
     160: istore        9
     162: iload         9
     164: iflt          185
     167: aload_0
     168: iload         9
     170: iconst_1
     171: iadd
     172: invokevirtual #42                 // Method java/lang/String.substring:(I)Ljava/lang/String;
     175: astore        4
     177: aload_0
     178: iconst_0
     179: iload         9
     181: invokevirtual #44                 // Method java/lang/String.substring:(II)Ljava/lang/String;
     184: astore_0
     185: aload_0
     186: bipush        64
     188: invokevirtual #40                 // Method java/lang/String.lastIndexOf:(I)I
     191: istore        9
     193: iload         9
     195: iflt          251
     198: aload_0
     199: iconst_0
     200: iload         9
     202: invokevirtual #44                 // Method java/lang/String.substring:(II)Ljava/lang/String;
     205: astore        5
     207: aload         5
     209: bipush        58
     211: invokevirtual #52                 // Method java/lang/String.indexOf:(I)I
     214: istore        10
     216: iload         10
     218: iflt          242
     221: aload         5
     223: iload         10
     225: iconst_1
     226: iadd
     227: invokevirtual #42                 // Method java/lang/String.substring:(I)Ljava/lang/String;
     230: astore        6
     232: aload         5
     234: iconst_0
     235: iload         10
     237: invokevirtual #44                 // Method java/lang/String.substring:(II)Ljava/lang/String;
     240: astore        5
     242: aload_0
     243: iload         9
     245: iconst_1
     246: iadd
     247: invokevirtual #42                 // Method java/lang/String.substring:(I)Ljava/lang/String;
     250: astore_0
     251: aload_0
     252: bipush        58
     254: invokevirtual #40                 // Method java/lang/String.lastIndexOf:(I)I
     257: istore        9
     259: iload         9
     261: iflt          311
     264: iload         9
     266: aload_0
     267: invokevirtual #41                 // Method java/lang/String.length:()I
     270: iconst_1
     271: isub
     272: if_icmpge     311
     275: aload_0
     276: bipush        37
     278: invokevirtual #40                 // Method java/lang/String.lastIndexOf:(I)I
     281: iload         9
     283: if_icmple     289
     286: goto          311
     289: aload_0
     290: iload         9
     292: iconst_1
     293: iadd
     294: invokevirtual #42                 // Method java/lang/String.substring:(I)Ljava/lang/String;
     297: invokestatic  #43                 // Method java/lang/Integer.parseInt:(Ljava/lang/String;)I
     300: istore        8
     302: aload_0
     303: iconst_0
     304: iload         9
     306: invokevirtual #44                 // Method java/lang/String.substring:(II)Ljava/lang/String;
     309: astore        7
     311: aload_3
     312: invokestatic  #53                 // Method org/apache/dubbo/common/url/component/URLItemCache.intern:(Ljava/lang/String;)Ljava/lang/String;
     315: astore_3
     316: aload         4
     318: invokestatic  #54                 // Method org/apache/dubbo/common/url/component/URLItemCache.checkPath:(Ljava/lang/String;)Ljava/lang/String;
     321: astore        4
     323: new           #55                 // class org/apache/dubbo/common/url/component/PathURLAddress
     326: dup
     327: aload_3
     328: aload         5
     330: aload         6
     332: aload         4
     334: aload         7
     336: iload         8
     338: aload_1
     339: invokespecial #56                 // Method org/apache/dubbo/common/url/component/PathURLAddress."<init>":(Ljava/lang/String;Ljava/lang/String;Ljava/lang/String;Ljava/lang/String;Ljava/lang/String;ILjava/lang/String;)V
     342: areturn
}
