Compiled from "URLItemCache.java"
public class org.apache.dubbo.common.url.component.URLItemCache {
  private static final java.util.Map<java.lang.String, java.lang.String> PARAM_KEY_CACHE;

  private static final java.util.Map<java.lang.String, java.lang.String> PARAM_VALUE_CACHE;

  private static final java.util.Map<java.lang.String, java.lang.String> PATH_CACHE;

  private static final java.util.Map<java.lang.String, java.lang.String> REVISION_CACHE;

  public org.apache.dubbo.common.url.component.URLItemCache();
    Code:
       0: aload_0
       1: invokespecial #1                  // Method java/lang/Object."<init>":()V
       4: return

  public static void putParams(java.util.Map<java.lang.String, java.lang.String>, java.lang.String, java.lang.String);
    Code:
       0: getstatic     #2                  // Field PARAM_KEY_CACHE:Ljava/util/Map;
       3: aload_1
       4: invokeinterface #3,  2            // InterfaceMethod java/util/Map.get:(Ljava/lang/Object;)Ljava/lang/Object;
       9: checkcast     #4                  // class java/lang/String
      12: astore_3
      13: aload_3
      14: invokestatic  #5                  // Method org/apache/dubbo/common/utils/StringUtils.isBlank:(Ljava/lang/CharSequence;)Z
      17: ifeq          33
      20: aload_1
      21: astore_3
      22: getstatic     #2                  // Field PARAM_KEY_CACHE:Ljava/util/Map;
      25: aload_1
      26: aload_1
      27: invokeinterface #6,  3            // InterfaceMethod java/util/Map.put:(Ljava/lang/Object;Ljava/lang/Object;)Ljava/lang/Object;
      32: pop
      33: getstatic     #7                  // Field PARAM_VALUE_CACHE:Ljava/util/Map;
      36: aload_2
      37: invokeinterface #3,  2            // InterfaceMethod java/util/Map.get:(Ljava/lang/Object;)Ljava/lang/Object;
      42: checkcast     #4                  // class java/lang/String
      45: astore        4
      47: aload         4
      49: invokestatic  #5                  // Method org/apache/dubbo/common/utils/StringUtils.isBlank:(Ljava/lang/CharSequence;)Z
      52: ifeq          69
      55: aload_2
      56: astore        4
      58: getstatic     #7                  // Field PARAM_VALUE_CACHE:Ljava/util/Map;
      61: aload_2
      62: aload_2
      63: invokeinterface #6,  3            // InterfaceMethod java/util/Map.put:(Ljava/lang/Object;Ljava/lang/Object;)Ljava/lang/Object;
      68: pop
      69: aload_0
      70: aload_3
      71: aload         4
      73: invokeinterface #6,  3            // InterfaceMethod java/util/Map.put:(Ljava/lang/Object;Ljava/lang/Object;)Ljava/lang/Object;
      78: pop
      79: return

  public static java.lang.String checkPath(java.lang.String);
    Code:
       0: aload_0
       1: invokestatic  #5                  // Method org/apache/dubbo/common/utils/StringUtils.isBlank:(Ljava/lang/CharSequence;)Z
       4: ifeq          9
       7: aload_0
       8: areturn
       9: getstatic     #8                  // Field PATH_CACHE:Ljava/util/Map;
      12: aload_0
      13: aload_0
      14: invokeinterface #9,  3            // InterfaceMethod java/util/Map.putIfAbsent:(Ljava/lang/Object;Ljava/lang/Object;)Ljava/lang/Object;
      19: checkcast     #4                  // class java/lang/String
      22: astore_1
      23: aload_1
      24: invokestatic  #10                 // Method org/apache/dubbo/common/utils/StringUtils.isNotBlank:(Ljava/lang/CharSequence;)Z
      27: ifeq          32
      30: aload_1
      31: areturn
      32: aload_0
      33: areturn

  public static java.lang.String checkRevision(java.lang.String);
    Code:
       0: aload_0
       1: invokestatic  #5                  // Method org/apache/dubbo/common/utils/StringUtils.isBlank:(Ljava/lang/CharSequence;)Z
       4: ifeq          9
       7: aload_0
       8: areturn
       9: getstatic     #11                 // Field REVISION_CACHE:Ljava/util/Map;
      12: aload_0
      13: aload_0
      14: invokeinterface #9,  3            // InterfaceMethod java/util/Map.putIfAbsent:(Ljava/lang/Object;Ljava/lang/Object;)Ljava/lang/Object;
      19: checkcast     #4                  // class java/lang/String
      22: astore_1
      23: aload_1
      24: invokestatic  #10                 // Method org/apache/dubbo/common/utils/StringUtils.isNotBlank:(Ljava/lang/CharSequence;)Z
      27: ifeq          32
      30: aload_1
      31: areturn
      32: aload_0
      33: areturn

  public static java.lang.String intern(java.lang.String);
    Code:
       0: aload_0
       1: invokestatic  #5                  // Method org/apache/dubbo/common/utils/StringUtils.isBlank:(Ljava/lang/CharSequence;)Z
       4: ifeq          9
       7: aload_0
       8: areturn
       9: aload_0
      10: invokevirtual #12                 // Method java/lang/String.intern:()Ljava/lang/String;
      13: areturn

  public static void putParamsIntern(java.util.Map<java.lang.String, java.lang.String>, java.lang.String, java.lang.String);
    Code:
       0: aload_1
       1: invokestatic  #5                  // Method org/apache/dubbo/common/utils/StringUtils.isBlank:(Ljava/lang/CharSequence;)Z
       4: ifne          14
       7: aload_2
       8: invokestatic  #5                  // Method org/apache/dubbo/common/utils/StringUtils.isBlank:(Ljava/lang/CharSequence;)Z
      11: ifeq          24
      14: aload_0
      15: aload_1
      16: aload_2
      17: invokeinterface #6,  3            // InterfaceMethod java/util/Map.put:(Ljava/lang/Object;Ljava/lang/Object;)Ljava/lang/Object;
      22: pop
      23: return
      24: aload_1
      25: invokevirtual #12                 // Method java/lang/String.intern:()Ljava/lang/String;
      28: astore_1
      29: aload_2
      30: invokevirtual #12                 // Method java/lang/String.intern:()Ljava/lang/String;
      33: astore_2
      34: aload_0
      35: aload_1
      36: aload_2
      37: invokeinterface #6,  3            // InterfaceMethod java/util/Map.put:(Ljava/lang/Object;Ljava/lang/Object;)Ljava/lang/Object;
      42: pop
      43: return

  static {};
    Code:
       0: new           #13                 // class org/apache/dubbo/common/utils/LRUCache
       3: dup
       4: sipush        10000
       7: invokespecial #14                 // Method org/apache/dubbo/common/utils/LRUCache."<init>":(I)V
      10: putstatic     #2                  // Field PARAM_KEY_CACHE:Ljava/util/Map;
      13: new           #13                 // class org/apache/dubbo/common/utils/LRUCache
      16: dup
      17: ldc           #15                 // int 50000
      19: invokespecial #14                 // Method org/apache/dubbo/common/utils/LRUCache."<init>":(I)V
      22: putstatic     #7                  // Field PARAM_VALUE_CACHE:Ljava/util/Map;
      25: new           #13                 // class org/apache/dubbo/common/utils/LRUCache
      28: dup
      29: sipush        10000
      32: invokespecial #14                 // Method org/apache/dubbo/common/utils/LRUCache."<init>":(I)V
      35: putstatic     #8                  // Field PATH_CACHE:Ljava/util/Map;
      38: new           #13                 // class org/apache/dubbo/common/utils/LRUCache
      41: dup
      42: sipush        10000
      45: invokespecial #14                 // Method org/apache/dubbo/common/utils/LRUCache."<init>":(I)V
      48: putstatic     #11                 // Field REVISION_CACHE:Ljava/util/Map;
      51: return
}
