Compiled from "URLParam.java"
public class org.apache.dubbo.common.url.component.URLParam$URLParamMap$Node implements java.util.Map$Entry<java.lang.String, java.lang.String> {
  private final java.lang.String key;

  private java.lang.String value;

  public org.apache.dubbo.common.url.component.URLParam$URLParamMap$Node(java.lang.String, java.lang.String);
    Code:
       0: aload_0
       1: invokespecial #1                  // Method java/lang/Object."<init>":()V
       4: aload_0
       5: aload_1
       6: putfield      #2                  // Field key:Ljava/lang/String;
       9: aload_0
      10: aload_2
      11: putfield      #3                  // Field value:Ljava/lang/String;
      14: return

  public java.lang.String getKey();
    Code:
       0: aload_0
       1: getfield      #2                  // Field key:Ljava/lang/String;
       4: areturn

  public java.lang.String getValue();
    Code:
       0: aload_0
       1: getfield      #3                  // Field value:Ljava/lang/String;
       4: areturn

  public java.lang.String setValue(java.lang.String);
    Code:
       0: new           #4                  // class java/lang/UnsupportedOperationException
       3: dup
       4: invokespecial #5                  // Method java/lang/UnsupportedOperationException."<init>":()V
       7: athrow

  public boolean equals(java.lang.Object);
    Code:
       0: aload_0
       1: aload_1
       2: if_acmpne     7
       5: iconst_1
       6: ireturn
       7: aload_1
       8: ifnull        22
      11: aload_0
      12: invokevirtual #6                  // Method java/lang/Object.getClass:()Ljava/lang/Class;
      15: aload_1
      16: invokevirtual #6                  // Method java/lang/Object.getClass:()Ljava/lang/Class;
      19: if_acmpeq     24
      22: iconst_0
      23: ireturn
      24: aload_1
      25: checkcast     #7                  // class org/apache/dubbo/common/url/component/URLParam$URLParamMap$Node
      28: astore_2
      29: aload_0
      30: getfield      #2                  // Field key:Ljava/lang/String;
      33: aload_2
      34: getfield      #2                  // Field key:Ljava/lang/String;
      37: invokestatic  #8                  // Method java/util/Objects.equals:(Ljava/lang/Object;Ljava/lang/Object;)Z
      40: ifeq          61
      43: aload_0
      44: getfield      #3                  // Field value:Ljava/lang/String;
      47: aload_2
      48: getfield      #3                  // Field value:Ljava/lang/String;
      51: invokestatic  #8                  // Method java/util/Objects.equals:(Ljava/lang/Object;Ljava/lang/Object;)Z
      54: ifeq          61
      57: iconst_1
      58: goto          62
      61: iconst_0
      62: ireturn

  public int hashCode();
    Code:
       0: iconst_2
       1: anewarray     #9                  // class java/lang/Object
       4: dup
       5: iconst_0
       6: aload_0
       7: getfield      #2                  // Field key:Ljava/lang/String;
      10: aastore
      11: dup
      12: iconst_1
      13: aload_0
      14: getfield      #3                  // Field value:Ljava/lang/String;
      17: aastore
      18: invokestatic  #10                 // Method java/util/Objects.hash:([Ljava/lang/Object;)I
      21: ireturn

  public java.lang.Object setValue(java.lang.Object);
    Code:
       0: aload_0
       1: aload_1
       2: checkcast     #11                 // class java/lang/String
       5: invokevirtual #12                 // Method setValue:(Ljava/lang/String;)Ljava/lang/String;
       8: areturn

  public java.lang.Object getValue();
    Code:
       0: aload_0
       1: invokevirtual #13                 // Method getValue:()Ljava/lang/String;
       4: areturn

  public java.lang.Object getKey();
    Code:
       0: aload_0
       1: invokevirtual #14                 // Method getKey:()Ljava/lang/String;
       4: areturn
}
