Compiled from "URLParam.java"
public class org.apache.dubbo.common.url.component.URLParam$URLParamMap implements java.util.Map<java.lang.String, java.lang.String> {
  private org.apache.dubbo.common.url.component.URLParam urlParam;

  public org.apache.dubbo.common.url.component.URLParam$URLParamMap(org.apache.dubbo.common.url.component.URLParam);
    Code:
       0: aload_0
       1: invokespecial #1                  // Method java/lang/Object."<init>":()V
       4: aload_0
       5: aload_1
       6: putfield      #2                  // Field urlParam:Lorg/apache/dubbo/common/url/component/URLParam;
       9: return

  public int size();
    Code:
       0: aload_0
       1: getfield      #2                  // Field urlParam:Lorg/apache/dubbo/common/url/component/URLParam;
       4: invokestatic  #3                  // Method org/apache/dubbo/common/url/component/URLParam.access$000:(Lorg/apache/dubbo/common/url/component/URLParam;)Ljava/util/BitSet;
       7: invokevirtual #4                  // Method java/util/BitSet.cardinality:()I
      10: aload_0
      11: getfield      #2                  // Field urlParam:Lorg/apache/dubbo/common/url/component/URLParam;
      14: invokestatic  #5                  // Method org/apache/dubbo/common/url/component/URLParam.access$100:(Lorg/apache/dubbo/common/url/component/URLParam;)Ljava/util/Map;
      17: invokeinterface #6,  1            // InterfaceMethod java/util/Map.size:()I
      22: iadd
      23: ireturn

  public boolean isEmpty();
    Code:
       0: aload_0
       1: invokevirtual #7                  // Method size:()I
       4: ifne          11
       7: iconst_1
       8: goto          12
      11: iconst_0
      12: ireturn

  public boolean containsKey(java.lang.Object);
    Code:
       0: aload_1
       1: instanceof    #8                  // class java/lang/String
       4: ifeq          19
       7: aload_0
       8: getfield      #2                  // Field urlParam:Lorg/apache/dubbo/common/url/component/URLParam;
      11: aload_1
      12: checkcast     #8                  // class java/lang/String
      15: invokevirtual #9                  // Method org/apache/dubbo/common/url/component/URLParam.hasParameter:(Ljava/lang/String;)Z
      18: ireturn
      19: iconst_0
      20: ireturn

  public boolean containsValue(java.lang.Object);
    Code:
       0: aload_0
       1: invokevirtual #10                 // Method values:()Ljava/util/Collection;
       4: aload_1
       5: invokeinterface #11,  2           // InterfaceMethod java/util/Collection.contains:(Ljava/lang/Object;)Z
      10: ireturn

  public java.lang.String get(java.lang.Object);
    Code:
       0: aload_1
       1: instanceof    #8                  // class java/lang/String
       4: ifeq          19
       7: aload_0
       8: getfield      #2                  // Field urlParam:Lorg/apache/dubbo/common/url/component/URLParam;
      11: aload_1
      12: checkcast     #8                  // class java/lang/String
      15: invokevirtual #12                 // Method org/apache/dubbo/common/url/component/URLParam.getParameter:(Ljava/lang/String;)Ljava/lang/String;
      18: areturn
      19: aconst_null
      20: areturn

  public java.lang.String put(java.lang.String, java.lang.String);
    Code:
       0: aload_0
       1: getfield      #2                  // Field urlParam:Lorg/apache/dubbo/common/url/component/URLParam;
       4: aload_1
       5: invokevirtual #12                 // Method org/apache/dubbo/common/url/component/URLParam.getParameter:(Ljava/lang/String;)Ljava/lang/String;
       8: astore_3
       9: aload_0
      10: aload_0
      11: getfield      #2                  // Field urlParam:Lorg/apache/dubbo/common/url/component/URLParam;
      14: aload_1
      15: aload_2
      16: invokevirtual #13                 // Method org/apache/dubbo/common/url/component/URLParam.addParameter:(Ljava/lang/String;Ljava/lang/String;)Lorg/apache/dubbo/common/url/component/URLParam;
      19: putfield      #2                  // Field urlParam:Lorg/apache/dubbo/common/url/component/URLParam;
      22: aload_3
      23: areturn

  public java.lang.String remove(java.lang.Object);
    Code:
       0: aload_1
       1: instanceof    #8                  // class java/lang/String
       4: ifeq          43
       7: aload_0
       8: getfield      #2                  // Field urlParam:Lorg/apache/dubbo/common/url/component/URLParam;
      11: aload_1
      12: checkcast     #8                  // class java/lang/String
      15: invokevirtual #12                 // Method org/apache/dubbo/common/url/component/URLParam.getParameter:(Ljava/lang/String;)Ljava/lang/String;
      18: astore_2
      19: aload_0
      20: aload_0
      21: getfield      #2                  // Field urlParam:Lorg/apache/dubbo/common/url/component/URLParam;
      24: iconst_1
      25: anewarray     #8                  // class java/lang/String
      28: dup
      29: iconst_0
      30: aload_1
      31: checkcast     #8                  // class java/lang/String
      34: aastore
      35: invokevirtual #14                 // Method org/apache/dubbo/common/url/component/URLParam.removeParameters:([Ljava/lang/String;)Lorg/apache/dubbo/common/url/component/URLParam;
      38: putfield      #2                  // Field urlParam:Lorg/apache/dubbo/common/url/component/URLParam;
      41: aload_2
      42: areturn
      43: aconst_null
      44: areturn

  public void putAll(java.util.Map<? extends java.lang.String, ? extends java.lang.String>);
    Code:
       0: aload_0
       1: aload_0
       2: getfield      #2                  // Field urlParam:Lorg/apache/dubbo/common/url/component/URLParam;
       5: aload_1
       6: invokevirtual #15                 // Method org/apache/dubbo/common/url/component/URLParam.addParameters:(Ljava/util/Map;)Lorg/apache/dubbo/common/url/component/URLParam;
       9: putfield      #2                  // Field urlParam:Lorg/apache/dubbo/common/url/component/URLParam;
      12: return

  public void clear();
    Code:
       0: aload_0
       1: aload_0
       2: getfield      #2                  // Field urlParam:Lorg/apache/dubbo/common/url/component/URLParam;
       5: invokevirtual #16                 // Method org/apache/dubbo/common/url/component/URLParam.clearParameters:()Lorg/apache/dubbo/common/url/component/URLParam;
       8: putfield      #2                  // Field urlParam:Lorg/apache/dubbo/common/url/component/URLParam;
      11: return

  public java.util.Set<java.lang.String> keySet();
    Code:
       0: new           #17                 // class java/util/LinkedHashSet
       3: dup
       4: aload_0
       5: getfield      #2                  // Field urlParam:Lorg/apache/dubbo/common/url/component/URLParam;
       8: invokestatic  #18                 // Method org/apache/dubbo/common/url/component/URLParam.access$200:(Lorg/apache/dubbo/common/url/component/URLParam;)[I
      11: arraylength
      12: aload_0
      13: getfield      #2                  // Field urlParam:Lorg/apache/dubbo/common/url/component/URLParam;
      16: invokestatic  #5                  // Method org/apache/dubbo/common/url/component/URLParam.access$100:(Lorg/apache/dubbo/common/url/component/URLParam;)Ljava/util/Map;
      19: invokeinterface #6,  1            // InterfaceMethod java/util/Map.size:()I
      24: iadd
      25: i2d
      26: ldc2_w        #19                 // double 0.75d
      29: ddiv
      30: d2i
      31: iconst_1
      32: iadd
      33: invokespecial #21                 // Method java/util/LinkedHashSet."<init>":(I)V
      36: astore_1
      37: aload_0
      38: getfield      #2                  // Field urlParam:Lorg/apache/dubbo/common/url/component/URLParam;
      41: invokestatic  #3                  // Method org/apache/dubbo/common/url/component/URLParam.access$000:(Lorg/apache/dubbo/common/url/component/URLParam;)Ljava/util/BitSet;
      44: iconst_0
      45: invokevirtual #22                 // Method java/util/BitSet.nextSetBit:(I)I
      48: istore_2
      49: iload_2
      50: iflt          81
      53: aload_1
      54: iload_2
      55: invokestatic  #23                 // Method org/apache/dubbo/common/url/component/param/DynamicParamTable.getKey:(I)Ljava/lang/String;
      58: invokeinterface #24,  2           // InterfaceMethod java/util/Set.add:(Ljava/lang/Object;)Z
      63: pop
      64: aload_0
      65: getfield      #2                  // Field urlParam:Lorg/apache/dubbo/common/url/component/URLParam;
      68: invokestatic  #3                  // Method org/apache/dubbo/common/url/component/URLParam.access$000:(Lorg/apache/dubbo/common/url/component/URLParam;)Ljava/util/BitSet;
      71: iload_2
      72: iconst_1
      73: iadd
      74: invokevirtual #22                 // Method java/util/BitSet.nextSetBit:(I)I
      77: istore_2
      78: goto          49
      81: aload_0
      82: getfield      #2                  // Field urlParam:Lorg/apache/dubbo/common/url/component/URLParam;
      85: invokestatic  #5                  // Method org/apache/dubbo/common/url/component/URLParam.access$100:(Lorg/apache/dubbo/common/url/component/URLParam;)Ljava/util/Map;
      88: invokeinterface #25,  1           // InterfaceMethod java/util/Map.entrySet:()Ljava/util/Set;
      93: invokeinterface #26,  1           // InterfaceMethod java/util/Set.iterator:()Ljava/util/Iterator;
      98: astore_2
      99: aload_2
     100: invokeinterface #27,  1           // InterfaceMethod java/util/Iterator.hasNext:()Z
     105: ifeq          134
     108: aload_2
     109: invokeinterface #28,  1           // InterfaceMethod java/util/Iterator.next:()Ljava/lang/Object;
     114: checkcast     #29                 // class java/util/Map$Entry
     117: astore_3
     118: aload_1
     119: aload_3
     120: invokeinterface #30,  1           // InterfaceMethod java/util/Map$Entry.getKey:()Ljava/lang/Object;
     125: invokeinterface #24,  2           // InterfaceMethod java/util/Set.add:(Ljava/lang/Object;)Z
     130: pop
     131: goto          99
     134: aload_1
     135: invokestatic  #31                 // Method java/util/Collections.unmodifiableSet:(Ljava/util/Set;)Ljava/util/Set;
     138: areturn

  public java.util.Collection<java.lang.String> values();
    Code:
       0: new           #17                 // class java/util/LinkedHashSet
       3: dup
       4: aload_0
       5: getfield      #2                  // Field urlParam:Lorg/apache/dubbo/common/url/component/URLParam;
       8: invokestatic  #18                 // Method org/apache/dubbo/common/url/component/URLParam.access$200:(Lorg/apache/dubbo/common/url/component/URLParam;)[I
      11: arraylength
      12: aload_0
      13: getfield      #2                  // Field urlParam:Lorg/apache/dubbo/common/url/component/URLParam;
      16: invokestatic  #5                  // Method org/apache/dubbo/common/url/component/URLParam.access$100:(Lorg/apache/dubbo/common/url/component/URLParam;)Ljava/util/Map;
      19: invokeinterface #6,  1            // InterfaceMethod java/util/Map.size:()I
      24: iadd
      25: i2d
      26: ldc2_w        #19                 // double 0.75d
      29: ddiv
      30: d2i
      31: iconst_1
      32: iadd
      33: invokespecial #21                 // Method java/util/LinkedHashSet."<init>":(I)V
      36: astore_1
      37: aload_0
      38: getfield      #2                  // Field urlParam:Lorg/apache/dubbo/common/url/component/URLParam;
      41: invokestatic  #3                  // Method org/apache/dubbo/common/url/component/URLParam.access$000:(Lorg/apache/dubbo/common/url/component/URLParam;)Ljava/util/BitSet;
      44: iconst_0
      45: invokevirtual #22                 // Method java/util/BitSet.nextSetBit:(I)I
      48: istore_2
      49: iload_2
      50: iflt          95
      53: aload_0
      54: getfield      #2                  // Field urlParam:Lorg/apache/dubbo/common/url/component/URLParam;
      57: iload_2
      58: invokestatic  #32                 // Method org/apache/dubbo/common/url/component/URLParam.access$300:(Lorg/apache/dubbo/common/url/component/URLParam;I)I
      61: istore        4
      63: iload_2
      64: iload         4
      66: invokestatic  #33                 // Method org/apache/dubbo/common/url/component/param/DynamicParamTable.getValue:(II)Ljava/lang/String;
      69: astore_3
      70: aload_1
      71: aload_3
      72: invokeinterface #24,  2           // InterfaceMethod java/util/Set.add:(Ljava/lang/Object;)Z
      77: pop
      78: aload_0
      79: getfield      #2                  // Field urlParam:Lorg/apache/dubbo/common/url/component/URLParam;
      82: invokestatic  #3                  // Method org/apache/dubbo/common/url/component/URLParam.access$000:(Lorg/apache/dubbo/common/url/component/URLParam;)Ljava/util/BitSet;
      85: iload_2
      86: iconst_1
      87: iadd
      88: invokevirtual #22                 // Method java/util/BitSet.nextSetBit:(I)I
      91: istore_2
      92: goto          49
      95: aload_0
      96: getfield      #2                  // Field urlParam:Lorg/apache/dubbo/common/url/component/URLParam;
      99: invokestatic  #5                  // Method org/apache/dubbo/common/url/component/URLParam.access$100:(Lorg/apache/dubbo/common/url/component/URLParam;)Ljava/util/Map;
     102: invokeinterface #25,  1           // InterfaceMethod java/util/Map.entrySet:()Ljava/util/Set;
     107: invokeinterface #26,  1           // InterfaceMethod java/util/Set.iterator:()Ljava/util/Iterator;
     112: astore_2
     113: aload_2
     114: invokeinterface #27,  1           // InterfaceMethod java/util/Iterator.hasNext:()Z
     119: ifeq          148
     122: aload_2
     123: invokeinterface #28,  1           // InterfaceMethod java/util/Iterator.next:()Ljava/lang/Object;
     128: checkcast     #29                 // class java/util/Map$Entry
     131: astore_3
     132: aload_1
     133: aload_3
     134: invokeinterface #34,  1           // InterfaceMethod java/util/Map$Entry.getValue:()Ljava/lang/Object;
     139: invokeinterface #24,  2           // InterfaceMethod java/util/Set.add:(Ljava/lang/Object;)Z
     144: pop
     145: goto          113
     148: aload_1
     149: invokestatic  #31                 // Method java/util/Collections.unmodifiableSet:(Ljava/util/Set;)Ljava/util/Set;
     152: areturn

  public java.util.Set<java.util.Map$Entry<java.lang.String, java.lang.String>> entrySet();
    Code:
       0: new           #17                 // class java/util/LinkedHashSet
       3: dup
       4: aload_0
       5: getfield      #2                  // Field urlParam:Lorg/apache/dubbo/common/url/component/URLParam;
       8: invokestatic  #3                  // Method org/apache/dubbo/common/url/component/URLParam.access$000:(Lorg/apache/dubbo/common/url/component/URLParam;)Ljava/util/BitSet;
      11: invokevirtual #4                  // Method java/util/BitSet.cardinality:()I
      14: aload_0
      15: getfield      #2                  // Field urlParam:Lorg/apache/dubbo/common/url/component/URLParam;
      18: invokestatic  #5                  // Method org/apache/dubbo/common/url/component/URLParam.access$100:(Lorg/apache/dubbo/common/url/component/URLParam;)Ljava/util/Map;
      21: invokeinterface #6,  1            // InterfaceMethod java/util/Map.size:()I
      26: iadd
      27: i2d
      28: ldc2_w        #19                 // double 0.75d
      31: ddiv
      32: d2i
      33: iconst_1
      34: iadd
      35: invokespecial #21                 // Method java/util/LinkedHashSet."<init>":(I)V
      38: astore_1
      39: aload_0
      40: getfield      #2                  // Field urlParam:Lorg/apache/dubbo/common/url/component/URLParam;
      43: invokestatic  #3                  // Method org/apache/dubbo/common/url/component/URLParam.access$000:(Lorg/apache/dubbo/common/url/component/URLParam;)Ljava/util/BitSet;
      46: iconst_0
      47: invokevirtual #22                 // Method java/util/BitSet.nextSetBit:(I)I
      50: istore_2
      51: iload_2
      52: iflt          108
      55: aload_0
      56: getfield      #2                  // Field urlParam:Lorg/apache/dubbo/common/url/component/URLParam;
      59: iload_2
      60: invokestatic  #32                 // Method org/apache/dubbo/common/url/component/URLParam.access$300:(Lorg/apache/dubbo/common/url/component/URLParam;I)I
      63: istore        4
      65: iload_2
      66: iload         4
      68: invokestatic  #33                 // Method org/apache/dubbo/common/url/component/param/DynamicParamTable.getValue:(II)Ljava/lang/String;
      71: astore_3
      72: aload_1
      73: new           #35                 // class org/apache/dubbo/common/url/component/URLParam$URLParamMap$Node
      76: dup
      77: iload_2
      78: invokestatic  #23                 // Method org/apache/dubbo/common/url/component/param/DynamicParamTable.getKey:(I)Ljava/lang/String;
      81: aload_3
      82: invokespecial #36                 // Method org/apache/dubbo/common/url/component/URLParam$URLParamMap$Node."<init>":(Ljava/lang/String;Ljava/lang/String;)V
      85: invokeinterface #24,  2           // InterfaceMethod java/util/Set.add:(Ljava/lang/Object;)Z
      90: pop
      91: aload_0
      92: getfield      #2                  // Field urlParam:Lorg/apache/dubbo/common/url/component/URLParam;
      95: invokestatic  #3                  // Method org/apache/dubbo/common/url/component/URLParam.access$000:(Lorg/apache/dubbo/common/url/component/URLParam;)Ljava/util/BitSet;
      98: iload_2
      99: iconst_1
     100: iadd
     101: invokevirtual #22                 // Method java/util/BitSet.nextSetBit:(I)I
     104: istore_2
     105: goto          51
     108: aload_0
     109: getfield      #2                  // Field urlParam:Lorg/apache/dubbo/common/url/component/URLParam;
     112: invokestatic  #5                  // Method org/apache/dubbo/common/url/component/URLParam.access$100:(Lorg/apache/dubbo/common/url/component/URLParam;)Ljava/util/Map;
     115: invokeinterface #25,  1           // InterfaceMethod java/util/Map.entrySet:()Ljava/util/Set;
     120: invokeinterface #26,  1           // InterfaceMethod java/util/Set.iterator:()Ljava/util/Iterator;
     125: astore_2
     126: aload_2
     127: invokeinterface #27,  1           // InterfaceMethod java/util/Iterator.hasNext:()Z
     132: ifeq          180
     135: aload_2
     136: invokeinterface #28,  1           // InterfaceMethod java/util/Iterator.next:()Ljava/lang/Object;
     141: checkcast     #29                 // class java/util/Map$Entry
     144: astore_3
     145: aload_1
     146: new           #35                 // class org/apache/dubbo/common/url/component/URLParam$URLParamMap$Node
     149: dup
     150: aload_3
     151: invokeinterface #30,  1           // InterfaceMethod java/util/Map$Entry.getKey:()Ljava/lang/Object;
     156: checkcast     #8                  // class java/lang/String
     159: aload_3
     160: invokeinterface #34,  1           // InterfaceMethod java/util/Map$Entry.getValue:()Ljava/lang/Object;
     165: checkcast     #8                  // class java/lang/String
     168: invokespecial #36                 // Method org/apache/dubbo/common/url/component/URLParam$URLParamMap$Node."<init>":(Ljava/lang/String;Ljava/lang/String;)V
     171: invokeinterface #24,  2           // InterfaceMethod java/util/Set.add:(Ljava/lang/Object;)Z
     176: pop
     177: goto          126
     180: aload_1
     181: invokestatic  #31                 // Method java/util/Collections.unmodifiableSet:(Ljava/util/Set;)Ljava/util/Set;
     184: areturn

  public org.apache.dubbo.common.url.component.URLParam getUrlParam();
    Code:
       0: aload_0
       1: getfield      #2                  // Field urlParam:Lorg/apache/dubbo/common/url/component/URLParam;
       4: areturn

  public boolean equals(java.lang.Object);
    Code:
       0: aload_0
       1: aload_1
       2: if_acmpne     7
       5: iconst_1
       6: ireturn
       7: aload_1
       8: ifnull        22
      11: aload_0
      12: invokevirtual #37                 // Method java/lang/Object.getClass:()Ljava/lang/Class;
      15: aload_1
      16: invokevirtual #37                 // Method java/lang/Object.getClass:()Ljava/lang/Class;
      19: if_acmpeq     24
      22: iconst_0
      23: ireturn
      24: aload_1
      25: checkcast     #38                 // class org/apache/dubbo/common/url/component/URLParam$URLParamMap
      28: astore_2
      29: aload_0
      30: getfield      #2                  // Field urlParam:Lorg/apache/dubbo/common/url/component/URLParam;
      33: aload_2
      34: getfield      #2                  // Field urlParam:Lorg/apache/dubbo/common/url/component/URLParam;
      37: invokestatic  #39                 // Method java/util/Objects.equals:(Ljava/lang/Object;Ljava/lang/Object;)Z
      40: ireturn

  public int hashCode();
    Code:
       0: iconst_1
       1: anewarray     #40                 // class java/lang/Object
       4: dup
       5: iconst_0
       6: aload_0
       7: getfield      #2                  // Field urlParam:Lorg/apache/dubbo/common/url/component/URLParam;
      10: aastore
      11: invokestatic  #41                 // Method java/util/Objects.hash:([Ljava/lang/Object;)I
      14: ireturn

  public java.lang.Object remove(java.lang.Object);
    Code:
       0: aload_0
       1: aload_1
       2: invokevirtual #42                 // Method remove:(Ljava/lang/Object;)Ljava/lang/String;
       5: areturn

  public java.lang.Object put(java.lang.Object, java.lang.Object);
    Code:
       0: aload_0
       1: aload_1
       2: checkcast     #8                  // class java/lang/String
       5: aload_2
       6: checkcast     #8                  // class java/lang/String
       9: invokevirtual #43                 // Method put:(Ljava/lang/String;Ljava/lang/String;)Ljava/lang/String;
      12: areturn

  public java.lang.Object get(java.lang.Object);
    Code:
       0: aload_0
       1: aload_1
       2: invokevirtual #44                 // Method get:(Ljava/lang/Object;)Ljava/lang/String;
       5: areturn
}
