Compiled from "URLPlainParam.java"
public class org.apache.dubbo.common.url.component.URLPlainParam extends org.apache.dubbo.common.url.component.URLParam implements java.io.Serializable {
  private static final long serialVersionUID;

  protected org.apache.dubbo.common.url.component.URLPlainParam(java.util.BitSet, int[], java.util.Map<java.lang.String, java.lang.String>, java.util.Map<java.lang.String, java.util.Map<java.lang.String, java.lang.String>>, java.lang.String);
    Code:
       0: aload_0
       1: aload_1
       2: aload_2
       3: aload_3
       4: aload         4
       6: aload         5
       8: invokespecial #1                  // Method org/apache/dubbo/common/url/component/URLParam."<init>":(Ljava/util/BitSet;[ILjava/util/Map;Ljava/util/Map;Ljava/lang/String;)V
      11: aload_0
      12: iconst_0
      13: putfield      #2                  // Field enableCompressed:Z
      16: return

  public static org.apache.dubbo.common.url.component.URLPlainParam toURLPlainParam(org.apache.dubbo.common.url.component.URLParam);
    Code:
       0: new           #3                  // class java/util/HashMap
       3: dup
       4: aload_0
       5: invokevirtual #4                  // Method org/apache/dubbo/common/url/component/URLParam.getParameters:()Ljava/util/Map;
       8: invokespecial #5                  // Method java/util/HashMap."<init>":(Ljava/util/Map;)V
      11: invokestatic  #6                  // Method java/util/Collections.unmodifiableMap:(Ljava/util/Map;)Ljava/util/Map;
      14: astore_1
      15: new           #7                  // class org/apache/dubbo/common/url/component/URLPlainParam
      18: dup
      19: new           #8                  // class java/util/BitSet
      22: dup
      23: invokespecial #9                  // Method java/util/BitSet."<init>":()V
      26: iconst_0
      27: newarray       int
      29: aload_1
      30: aload_0
      31: invokevirtual #10                 // Method org/apache/dubbo/common/url/component/URLParam.getMethodParameters:()Ljava/util/Map;
      34: aload_0
      35: invokevirtual #11                 // Method org/apache/dubbo/common/url/component/URLParam.getRawParam:()Ljava/lang/String;
      38: invokespecial #12                 // Method "<init>":(Ljava/util/BitSet;[ILjava/util/Map;Ljava/util/Map;Ljava/lang/String;)V
      41: areturn
}
