Compiled from "RemoteServerInternalException.java"
public class org.apache.dubbo.rpc.protocol.rest.exception.RemoteServerInternalException extends org.apache.dubbo.rpc.protocol.rest.exception.RestException {
  public org.apache.dubbo.rpc.protocol.rest.exception.RemoteServerInternalException(java.lang.String);
    Code:
       0: aload_0
       1: new           #1                  // class java/lang/StringBuilder
       4: dup
       5: invokespecial #2                  // Method java/lang/StringBuilder."<init>":()V
       8: ldc           #3                  // String dubbo http rest protocol remote error :
      10: invokevirtual #4                  // Method java/lang/StringBuilder.append:(Ljava/lang/String;)Ljava/lang/StringBuilder;
      13: aload_1
      14: invokevirtual #4                  // Method java/lang/StringBuilder.append:(Ljava/lang/String;)Ljava/lang/StringBuilder;
      17: invokevirtual #5                  // Method java/lang/StringBuilder.toString:()Ljava/lang/String;
      20: invokespecial #6                  // Method org/apache/dubbo/rpc/protocol/rest/exception/RestException."<init>":(Ljava/lang/String;)V
      23: return
}
