Compiled from "UnSupportContentTypeException.java"
public class org.apache.dubbo.rpc.protocol.rest.exception.UnSupportContentTypeException extends org.apache.dubbo.rpc.protocol.rest.exception.MediaTypeUnSupportException {
  public org.apache.dubbo.rpc.protocol.rest.exception.UnSupportContentTypeException(java.lang.String);
    Code:
       0: aload_0
       1: new           #1                  // class java/lang/StringBuilder
       4: dup
       5: invokespecial #2                  // Method java/lang/StringBuilder."<init>":()V
       8: ldc           #3                  // String Current Support content type:
      10: invokevirtual #4                  // Method java/lang/StringBuilder.append:(Ljava/lang/String;)Ljava/lang/StringBuilder;
      13: invokestatic  #5                  // Method org/apache/dubbo/metadata/rest/media/MediaType.getAllContentType:()Ljava/lang/String;
      16: invokevirtual #4                  // Method java/lang/StringBuilder.append:(Ljava/lang/String;)Ljava/lang/StringBuilder;
      19: ldc           #6                  // String ; Do not support  content type
      21: invokevirtual #4                  // Method java/lang/StringBuilder.append:(Ljava/lang/String;)Ljava/lang/StringBuilder;
      24: aload_1
      25: invokevirtual #4                  // Method java/lang/StringBuilder.append:(Ljava/lang/String;)Ljava/lang/StringBuilder;
      28: invokevirtual #7                  // Method java/lang/StringBuilder.toString:()Ljava/lang/String;
      31: invokespecial #8                  // Method org/apache/dubbo/rpc/protocol/rest/exception/MediaTypeUnSupportException."<init>":(Ljava/lang/String;)V
      34: return
}
