Compiled from "Compiler.java"
public interface org.apache.dubbo.common.compiler.Compiler {
  public default java.lang.Class<?> compile(java.lang.String, java.lang.ClassLoader);
    Code:
       0: aload_0
       1: aconst_null
       2: aload_1
       3: aload_2
       4: invokeinterface #1,  4            // InterfaceMethod compile:(Ljava/lang/Class;Ljava/lang/String;Ljava/lang/ClassLoader;)Ljava/lang/Class;
       9: areturn

  public default java.lang.Class<?> compile(java.lang.Class<?>, java.lang.String, java.lang.ClassLoader);
    Code:
       0: aload_0
       1: aload_2
       2: aload_3
       3: invokeinterface #2,  3            // InterfaceMethod compile:(Ljava/lang/String;Ljava/lang/ClassLoader;)Ljava/lang/Class;
       8: areturn
}
