Compiled from "BasicFuseableConditionalSubscriber.java"
public abstract class io.reactivex.rxjava3.internal.subscribers.BasicFuseableConditionalSubscriber<T, R> implements io.reactivex.rxjava3.operators.ConditionalSubscriber<T>, io.reactivex.rxjava3.operators.QueueSubscription<R> {
  protected final io.reactivex.rxjava3.operators.ConditionalSubscriber<? super R> downstream;

  protected org.reactivestreams.Subscription upstream;

  protected io.reactivex.rxjava3.operators.QueueSubscription<T> qs;

  protected boolean done;

  protected int sourceMode;

  public io.reactivex.rxjava3.internal.subscribers.BasicFuseableConditionalSubscriber(io.reactivex.rxjava3.operators.ConditionalSubscriber<? super R>);
    Code:
       0: aload_0
       1: invokespecial #1                  // Method java/lang/Object."<init>":()V
       4: aload_0
       5: aload_1
       6: putfield      #2                  // Field downstream:Lio/reactivex/rxjava3/operators/ConditionalSubscriber;
       9: return

  public final void onSubscribe(org.reactivestreams.Subscription);
    Code:
       0: aload_0
       1: getfield      #3                  // Field upstream:Lorg/reactivestreams/Subscription;
       4: aload_1
       5: invokestatic  #4                  // Method io/reactivex/rxjava3/internal/subscriptions/SubscriptionHelper.validate:(Lorg/reactivestreams/Subscription;Lorg/reactivestreams/Subscription;)Z
       8: ifeq          52
      11: aload_0
      12: aload_1
      13: putfield      #3                  // Field upstream:Lorg/reactivestreams/Subscription;
      16: aload_1
      17: instanceof    #5                  // class io/reactivex/rxjava3/operators/QueueSubscription
      20: ifeq          31
      23: aload_0
      24: aload_1
      25: checkcast     #5                  // class io/reactivex/rxjava3/operators/QueueSubscription
      28: putfield      #6                  // Field qs:Lio/reactivex/rxjava3/operators/QueueSubscription;
      31: aload_0
      32: invokevirtual #7                  // Method beforeDownstream:()Z
      35: ifeq          52
      38: aload_0
      39: getfield      #2                  // Field downstream:Lio/reactivex/rxjava3/operators/ConditionalSubscriber;
      42: aload_0
      43: invokeinterface #8,  2            // InterfaceMethod io/reactivex/rxjava3/operators/ConditionalSubscriber.onSubscribe:(Lorg/reactivestreams/Subscription;)V
      48: aload_0
      49: invokevirtual #9                  // Method afterDownstream:()V
      52: return

  protected boolean beforeDownstream();
    Code:
       0: iconst_1
       1: ireturn

  protected void afterDownstream();
    Code:
       0: return

  public void onError(java.lang.Throwable);
    Code:
       0: aload_0
       1: getfield      #10                 // Field done:Z
       4: ifeq          12
       7: aload_1
       8: invokestatic  #11                 // Method io/reactivex/rxjava3/plugins/RxJavaPlugins.onError:(Ljava/lang/Throwable;)V
      11: return
      12: aload_0
      13: iconst_1
      14: putfield      #10                 // Field done:Z
      17: aload_0
      18: getfield      #2                  // Field downstream:Lio/reactivex/rxjava3/operators/ConditionalSubscriber;
      21: aload_1
      22: invokeinterface #12,  2           // InterfaceMethod io/reactivex/rxjava3/operators/ConditionalSubscriber.onError:(Ljava/lang/Throwable;)V
      27: return

  protected final void fail(java.lang.Throwable);
    Code:
       0: aload_1
       1: invokestatic  #13                 // Method io/reactivex/rxjava3/exceptions/Exceptions.throwIfFatal:(Ljava/lang/Throwable;)V
       4: aload_0
       5: getfield      #3                  // Field upstream:Lorg/reactivestreams/Subscription;
       8: invokeinterface #14,  1           // InterfaceMethod org/reactivestreams/Subscription.cancel:()V
      13: aload_0
      14: aload_1
      15: invokevirtual #15                 // Method onError:(Ljava/lang/Throwable;)V
      18: return

  public void onComplete();
    Code:
       0: aload_0
       1: getfield      #10                 // Field done:Z
       4: ifeq          8
       7: return
       8: aload_0
       9: iconst_1
      10: putfield      #10                 // Field done:Z
      13: aload_0
      14: getfield      #2                  // Field downstream:Lio/reactivex/rxjava3/operators/ConditionalSubscriber;
      17: invokeinterface #16,  1           // InterfaceMethod io/reactivex/rxjava3/operators/ConditionalSubscriber.onComplete:()V
      22: return

  protected final int transitiveBoundaryFusion(int);
    Code:
       0: aload_0
       1: getfield      #6                  // Field qs:Lio/reactivex/rxjava3/operators/QueueSubscription;
       4: astore_2
       5: aload_2
       6: ifnull        34
       9: iload_1
      10: iconst_4
      11: iand
      12: ifne          34
      15: aload_2
      16: iload_1
      17: invokeinterface #18,  2           // InterfaceMethod io/reactivex/rxjava3/operators/QueueSubscription.requestFusion:(I)I
      22: istore_3
      23: iload_3
      24: ifeq          32
      27: aload_0
      28: iload_3
      29: putfield      #19                 // Field sourceMode:I
      32: iload_3
      33: ireturn
      34: iconst_0
      35: ireturn

  public void request(long);
    Code:
       0: aload_0
       1: getfield      #3                  // Field upstream:Lorg/reactivestreams/Subscription;
       4: lload_1
       5: invokeinterface #20,  3           // InterfaceMethod org/reactivestreams/Subscription.request:(J)V
      10: return

  public void cancel();
    Code:
       0: aload_0
       1: getfield      #3                  // Field upstream:Lorg/reactivestreams/Subscription;
       4: invokeinterface #14,  1           // InterfaceMethod org/reactivestreams/Subscription.cancel:()V
       9: return

  public boolean isEmpty();
    Code:
       0: aload_0
       1: getfield      #6                  // Field qs:Lio/reactivex/rxjava3/operators/QueueSubscription;
       4: invokeinterface #21,  1           // InterfaceMethod io/reactivex/rxjava3/operators/QueueSubscription.isEmpty:()Z
       9: ireturn

  public void clear();
    Code:
       0: aload_0
       1: getfield      #6                  // Field qs:Lio/reactivex/rxjava3/operators/QueueSubscription;
       4: invokeinterface #22,  1           // InterfaceMethod io/reactivex/rxjava3/operators/QueueSubscription.clear:()V
       9: return

  public final boolean offer(R);
    Code:
       0: new           #23                 // class java/lang/UnsupportedOperationException
       3: dup
       4: ldc           #24                 // String Should not be called!
       6: invokespecial #25                 // Method java/lang/UnsupportedOperationException."<init>":(Ljava/lang/String;)V
       9: athrow

  public final boolean offer(R, R);
    Code:
       0: new           #23                 // class java/lang/UnsupportedOperationException
       3: dup
       4: ldc           #24                 // String Should not be called!
       6: invokespecial #25                 // Method java/lang/UnsupportedOperationException."<init>":(Ljava/lang/String;)V
       9: athrow
}
