Compiled from "BlockingFirstSubscriber.java"
public final class io.reactivex.rxjava3.internal.subscribers.BlockingFirstSubscriber<T> extends io.reactivex.rxjava3.internal.subscribers.BlockingBaseSubscriber<T> {
  public io.reactivex.rxjava3.internal.subscribers.BlockingFirstSubscriber();
    Code:
       0: aload_0
       1: invokespecial #1                  // Method io/reactivex/rxjava3/internal/subscribers/BlockingBaseSubscriber."<init>":()V
       4: return

  public void onNext(T);
    Code:
       0: aload_0
       1: getfield      #2                  // Field value:Ljava/lang/Object;
       4: ifnonnull     25
       7: aload_0
       8: aload_1
       9: putfield      #2                  // Field value:Ljava/lang/Object;
      12: aload_0
      13: getfield      #3                  // Field upstream:Lorg/reactivestreams/Subscription;
      16: invokeinterface #4,  1            // InterfaceMethod org/reactivestreams/Subscription.cancel:()V
      21: aload_0
      22: invokevirtual #5                  // Method countDown:()V
      25: return

  public void onError(java.lang.Throwable);
    Code:
       0: aload_0
       1: getfield      #2                  // Field value:Ljava/lang/Object;
       4: ifnonnull     15
       7: aload_0
       8: aload_1
       9: putfield      #6                  // Field error:Ljava/lang/Throwable;
      12: goto          19
      15: aload_1
      16: invokestatic  #7                  // Method io/reactivex/rxjava3/plugins/RxJavaPlugins.onError:(Ljava/lang/Throwable;)V
      19: aload_0
      20: invokevirtual #5                  // Method countDown:()V
      23: return
}
