Compiled from "BlockingLastSubscriber.java"
public final class io.reactivex.rxjava3.internal.subscribers.BlockingLastSubscriber<T> extends io.reactivex.rxjava3.internal.subscribers.BlockingBaseSubscriber<T> {
  public io.reactivex.rxjava3.internal.subscribers.BlockingLastSubscriber();
    Code:
       0: aload_0
       1: invokespecial #1                  // Method io/reactivex/rxjava3/internal/subscribers/BlockingBaseSubscriber."<init>":()V
       4: return

  public void onNext(T);
    Code:
       0: aload_0
       1: aload_1
       2: putfield      #2                  // Field value:Ljava/lang/Object;
       5: return

  public void onError(java.lang.Throwable);
    Code:
       0: aload_0
       1: aconst_null
       2: putfield      #2                  // Field value:Ljava/lang/Object;
       5: aload_0
       6: aload_1
       7: putfield      #3                  // Field error:Ljava/lang/Throwable;
      10: aload_0
      11: invokevirtual #4                  // Method countDown:()V
      14: return
}
