Compiled from "QueueDrainSubscriber.java"
class io.reactivex.rxjava3.internal.subscribers.QueueDrainSubscriberPad3 extends io.reactivex.rxjava3.internal.subscribers.QueueDrainSubscriberPad2 {
  final java.util.concurrent.atomic.AtomicLong requested;

  io.reactivex.rxjava3.internal.subscribers.QueueDrainSubscriberPad3();
    Code:
       0: aload_0
       1: invokespecial #1                  // Method io/reactivex/rxjava3/internal/subscribers/QueueDrainSubscriberPad2."<init>":()V
       4: aload_0
       5: new           #2                  // class java/util/concurrent/atomic/AtomicLong
       8: dup
       9: invokespecial #3                  // Method java/util/concurrent/atomic/AtomicLong."<init>":()V
      12: putfield      #4                  // Field requested:Ljava/util/concurrent/atomic/AtomicLong;
      15: return
}
