Compiled from "SinglePostCompleteSubscriber.java"
public abstract class io.reactivex.rxjava3.internal.subscribers.SinglePostCompleteSubscriber<T, R> extends java.util.concurrent.atomic.AtomicLong implements io.reactivex.rxjava3.core.FlowableSubscriber<T>, org.reactivestreams.Subscription {
  private static final long serialVersionUID;

  protected final org.reactivestreams.Subscriber<? super R> downstream;

  protected org.reactivestreams.Subscription upstream;

  protected R value;

  protected long produced;

  static final long COMPLETE_MASK;

  static final long REQUEST_MASK;

  public io.reactivex.rxjava3.internal.subscribers.SinglePostCompleteSubscriber(org.reactivestreams.Subscriber<? super R>);
    Code:
       0: aload_0
       1: invokespecial #2                  // Method java/util/concurrent/atomic/AtomicLong."<init>":()V
       4: aload_0
       5: aload_1
       6: putfield      #3                  // Field downstream:Lorg/reactivestreams/Subscriber;
       9: return

  public void onSubscribe(org.reactivestreams.Subscription);
    Code:
       0: aload_0
       1: getfield      #4                  // Field upstream:Lorg/reactivestreams/Subscription;
       4: aload_1
       5: invokestatic  #5                  // Method io/reactivex/rxjava3/internal/subscriptions/SubscriptionHelper.validate:(Lorg/reactivestreams/Subscription;Lorg/reactivestreams/Subscription;)Z
       8: ifeq          26
      11: aload_0
      12: aload_1
      13: putfield      #4                  // Field upstream:Lorg/reactivestreams/Subscription;
      16: aload_0
      17: getfield      #3                  // Field downstream:Lorg/reactivestreams/Subscriber;
      20: aload_0
      21: invokeinterface #6,  2            // InterfaceMethod org/reactivestreams/Subscriber.onSubscribe:(Lorg/reactivestreams/Subscription;)V
      26: return

  protected final void complete(R);
    Code:
       0: aload_0
       1: getfield      #7                  // Field produced:J
       4: lstore_2
       5: lload_2
       6: lconst_0
       7: lcmp
       8: ifeq          17
      11: aload_0
      12: lload_2
      13: invokestatic  #8                  // Method io/reactivex/rxjava3/internal/util/BackpressureHelper.produced:(Ljava/util/concurrent/atomic/AtomicLong;J)J
      16: pop2
      17: aload_0
      18: invokevirtual #9                  // Method get:()J
      21: lstore        4
      23: lload         4
      25: ldc2_w        #11                 // long -9223372036854775808l
      28: land
      29: lconst_0
      30: lcmp
      31: ifeq          40
      34: aload_0
      35: aload_1
      36: invokevirtual #13                 // Method onDrop:(Ljava/lang/Object;)V
      39: return
      40: lload         4
      42: ldc2_w        #14                 // long 9223372036854775807l
      45: land
      46: lconst_0
      47: lcmp
      48: ifeq          78
      51: aload_0
      52: ldc2_w        #16                 // long -9223372036854775807l
      55: invokevirtual #18                 // Method lazySet:(J)V
      58: aload_0
      59: getfield      #3                  // Field downstream:Lorg/reactivestreams/Subscriber;
      62: aload_1
      63: invokeinterface #19,  2           // InterfaceMethod org/reactivestreams/Subscriber.onNext:(Ljava/lang/Object;)V
      68: aload_0
      69: getfield      #3                  // Field downstream:Lorg/reactivestreams/Subscriber;
      72: invokeinterface #20,  1           // InterfaceMethod org/reactivestreams/Subscriber.onComplete:()V
      77: return
      78: aload_0
      79: aload_1
      80: putfield      #21                 // Field value:Ljava/lang/Object;
      83: aload_0
      84: lconst_0
      85: ldc2_w        #11                 // long -9223372036854775808l
      88: invokevirtual #22                 // Method compareAndSet:(JJ)Z
      91: ifeq          95
      94: return
      95: aload_0
      96: aconst_null
      97: putfield      #21                 // Field value:Ljava/lang/Object;
     100: goto          17

  protected void onDrop(R);
    Code:
       0: return

  public final void request(long);
    Code:
       0: lload_1
       1: invokestatic  #23                 // Method io/reactivex/rxjava3/internal/subscriptions/SubscriptionHelper.validate:(J)Z
       4: ifeq          93
       7: aload_0
       8: invokevirtual #9                  // Method get:()J
      11: lstore_3
      12: lload_3
      13: ldc2_w        #11                 // long -9223372036854775808l
      16: land
      17: lconst_0
      18: lcmp
      19: ifeq          60
      22: aload_0
      23: ldc2_w        #11                 // long -9223372036854775808l
      26: ldc2_w        #16                 // long -9223372036854775807l
      29: invokevirtual #22                 // Method compareAndSet:(JJ)Z
      32: ifeq          93
      35: aload_0
      36: getfield      #3                  // Field downstream:Lorg/reactivestreams/Subscriber;
      39: aload_0
      40: getfield      #21                 // Field value:Ljava/lang/Object;
      43: invokeinterface #19,  2           // InterfaceMethod org/reactivestreams/Subscriber.onNext:(Ljava/lang/Object;)V
      48: aload_0
      49: getfield      #3                  // Field downstream:Lorg/reactivestreams/Subscriber;
      52: invokeinterface #20,  1           // InterfaceMethod org/reactivestreams/Subscriber.onComplete:()V
      57: goto          93
      60: lload_3
      61: lload_1
      62: invokestatic  #24                 // Method io/reactivex/rxjava3/internal/util/BackpressureHelper.addCap:(JJ)J
      65: lstore        5
      67: aload_0
      68: lload_3
      69: lload         5
      71: invokevirtual #22                 // Method compareAndSet:(JJ)Z
      74: ifeq          90
      77: aload_0
      78: getfield      #4                  // Field upstream:Lorg/reactivestreams/Subscription;
      81: lload_1
      82: invokeinterface #25,  3           // InterfaceMethod org/reactivestreams/Subscription.request:(J)V
      87: goto          93
      90: goto          7
      93: return

  public void cancel();
    Code:
       0: aload_0
       1: getfield      #4                  // Field upstream:Lorg/reactivestreams/Subscription;
       4: invokeinterface #26,  1           // InterfaceMethod org/reactivestreams/Subscription.cancel:()V
       9: return
}
