Compiled from "StrictSubscriber.java"
public class io.reactivex.rxjava3.internal.subscribers.StrictSubscriber<T> extends java.util.concurrent.atomic.AtomicInteger implements io.reactivex.rxjava3.core.FlowableSubscriber<T>, org.reactivestreams.Subscription {
  private static final long serialVersionUID;

  final org.reactivestreams.Subscriber<? super T> downstream;

  final io.reactivex.rxjava3.internal.util.AtomicThrowable error;

  final java.util.concurrent.atomic.AtomicLong requested;

  final java.util.concurrent.atomic.AtomicReference<org.reactivestreams.Subscription> upstream;

  final java.util.concurrent.atomic.AtomicBoolean once;

  volatile boolean done;

  public io.reactivex.rxjava3.internal.subscribers.StrictSubscriber(org.reactivestreams.Subscriber<? super T>);
    Code:
       0: aload_0
       1: invokespecial #1                  // Method java/util/concurrent/atomic/AtomicInteger."<init>":()V
       4: aload_0
       5: aload_1
       6: putfield      #2                  // Field downstream:Lorg/reactivestreams/Subscriber;
       9: aload_0
      10: new           #3                  // class io/reactivex/rxjava3/internal/util/AtomicThrowable
      13: dup
      14: invokespecial #4                  // Method io/reactivex/rxjava3/internal/util/AtomicThrowable."<init>":()V
      17: putfield      #5                  // Field error:Lio/reactivex/rxjava3/internal/util/AtomicThrowable;
      20: aload_0
      21: new           #6                  // class java/util/concurrent/atomic/AtomicLong
      24: dup
      25: invokespecial #7                  // Method java/util/concurrent/atomic/AtomicLong."<init>":()V
      28: putfield      #8                  // Field requested:Ljava/util/concurrent/atomic/AtomicLong;
      31: aload_0
      32: new           #9                  // class java/util/concurrent/atomic/AtomicReference
      35: dup
      36: invokespecial #10                 // Method java/util/concurrent/atomic/AtomicReference."<init>":()V
      39: putfield      #11                 // Field upstream:Ljava/util/concurrent/atomic/AtomicReference;
      42: aload_0
      43: new           #12                 // class java/util/concurrent/atomic/AtomicBoolean
      46: dup
      47: invokespecial #13                 // Method java/util/concurrent/atomic/AtomicBoolean."<init>":()V
      50: putfield      #14                 // Field once:Ljava/util/concurrent/atomic/AtomicBoolean;
      53: return

  public void request(long);
    Code:
       0: lload_1
       1: lconst_0
       2: lcmp
       3: ifgt          43
       6: aload_0
       7: invokevirtual #15                 // Method cancel:()V
      10: aload_0
      11: new           #16                 // class java/lang/IllegalArgumentException
      14: dup
      15: new           #17                 // class java/lang/StringBuilder
      18: dup
      19: invokespecial #18                 // Method java/lang/StringBuilder."<init>":()V
      22: ldc           #19                 // String ¡×3.9 violated: positive request amount required but it was
      24: invokevirtual #20                 // Method java/lang/StringBuilder.append:(Ljava/lang/String;)Ljava/lang/StringBuilder;
      27: lload_1
      28: invokevirtual #21                 // Method java/lang/StringBuilder.append:(J)Ljava/lang/StringBuilder;
      31: invokevirtual #22                 // Method java/lang/StringBuilder.toString:()Ljava/lang/String;
      34: invokespecial #23                 // Method java/lang/IllegalArgumentException."<init>":(Ljava/lang/String;)V
      37: invokevirtual #24                 // Method onError:(Ljava/lang/Throwable;)V
      40: goto          55
      43: aload_0
      44: getfield      #11                 // Field upstream:Ljava/util/concurrent/atomic/AtomicReference;
      47: aload_0
      48: getfield      #8                  // Field requested:Ljava/util/concurrent/atomic/AtomicLong;
      51: lload_1
      52: invokestatic  #25                 // Method io/reactivex/rxjava3/internal/subscriptions/SubscriptionHelper.deferredRequest:(Ljava/util/concurrent/atomic/AtomicReference;Ljava/util/concurrent/atomic/AtomicLong;J)V
      55: return

  public void cancel();
    Code:
       0: aload_0
       1: getfield      #26                 // Field done:Z
       4: ifne          15
       7: aload_0
       8: getfield      #11                 // Field upstream:Ljava/util/concurrent/atomic/AtomicReference;
      11: invokestatic  #27                 // Method io/reactivex/rxjava3/internal/subscriptions/SubscriptionHelper.cancel:(Ljava/util/concurrent/atomic/AtomicReference;)Z
      14: pop
      15: return

  public void onSubscribe(org.reactivestreams.Subscription);
    Code:
       0: aload_0
       1: getfield      #14                 // Field once:Ljava/util/concurrent/atomic/AtomicBoolean;
       4: iconst_0
       5: iconst_1
       6: invokevirtual #28                 // Method java/util/concurrent/atomic/AtomicBoolean.compareAndSet:(ZZ)Z
       9: ifeq          38
      12: aload_0
      13: getfield      #2                  // Field downstream:Lorg/reactivestreams/Subscriber;
      16: aload_0
      17: invokeinterface #29,  2           // InterfaceMethod org/reactivestreams/Subscriber.onSubscribe:(Lorg/reactivestreams/Subscription;)V
      22: aload_0
      23: getfield      #11                 // Field upstream:Ljava/util/concurrent/atomic/AtomicReference;
      26: aload_0
      27: getfield      #8                  // Field requested:Ljava/util/concurrent/atomic/AtomicLong;
      30: aload_1
      31: invokestatic  #30                 // Method io/reactivex/rxjava3/internal/subscriptions/SubscriptionHelper.deferredSetOnce:(Ljava/util/concurrent/atomic/AtomicReference;Ljava/util/concurrent/atomic/AtomicLong;Lorg/reactivestreams/Subscription;)Z
      34: pop
      35: goto          61
      38: aload_1
      39: invokeinterface #31,  1           // InterfaceMethod org/reactivestreams/Subscription.cancel:()V
      44: aload_0
      45: invokevirtual #15                 // Method cancel:()V
      48: aload_0
      49: new           #32                 // class java/lang/IllegalStateException
      52: dup
      53: ldc           #33                 // String ¡×2.12 violated: onSubscribe must be called at most once
      55: invokespecial #34                 // Method java/lang/IllegalStateException."<init>":(Ljava/lang/String;)V
      58: invokevirtual #24                 // Method onError:(Ljava/lang/Throwable;)V
      61: return

  public void onNext(T);
    Code:
       0: aload_0
       1: getfield      #2                  // Field downstream:Lorg/reactivestreams/Subscriber;
       4: aload_1
       5: aload_0
       6: aload_0
       7: getfield      #5                  // Field error:Lio/reactivex/rxjava3/internal/util/AtomicThrowable;
      10: invokestatic  #35                 // Method io/reactivex/rxjava3/internal/util/HalfSerializer.onNext:(Lorg/reactivestreams/Subscriber;Ljava/lang/Object;Ljava/util/concurrent/atomic/AtomicInteger;Lio/reactivex/rxjava3/internal/util/AtomicThrowable;)Z
      13: pop
      14: return

  public void onError(java.lang.Throwable);
    Code:
       0: aload_0
       1: iconst_1
       2: putfield      #26                 // Field done:Z
       5: aload_0
       6: getfield      #2                  // Field downstream:Lorg/reactivestreams/Subscriber;
       9: aload_1
      10: aload_0
      11: aload_0
      12: getfield      #5                  // Field error:Lio/reactivex/rxjava3/internal/util/AtomicThrowable;
      15: invokestatic  #36                 // Method io/reactivex/rxjava3/internal/util/HalfSerializer.onError:(Lorg/reactivestreams/Subscriber;Ljava/lang/Throwable;Ljava/util/concurrent/atomic/AtomicInteger;Lio/reactivex/rxjava3/internal/util/AtomicThrowable;)V
      18: return

  public void onComplete();
    Code:
       0: aload_0
       1: iconst_1
       2: putfield      #26                 // Field done:Z
       5: aload_0
       6: getfield      #2                  // Field downstream:Lorg/reactivestreams/Subscriber;
       9: aload_0
      10: aload_0
      11: getfield      #5                  // Field error:Lio/reactivex/rxjava3/internal/util/AtomicThrowable;
      14: invokestatic  #37                 // Method io/reactivex/rxjava3/internal/util/HalfSerializer.onComplete:(Lorg/reactivestreams/Subscriber;Ljava/util/concurrent/atomic/AtomicInteger;Lio/reactivex/rxjava3/internal/util/AtomicThrowable;)V
      17: return
}
