Compiled from "SubscriberResourceWrapper.java"
public final class io.reactivex.rxjava3.internal.subscribers.SubscriberResourceWrapper<T> extends java.util.concurrent.atomic.AtomicReference<io.reactivex.rxjava3.disposables.Disposable> implements io.reactivex.rxjava3.core.FlowableSubscriber<T>, io.reactivex.rxjava3.disposables.Disposable, org.reactivestreams.Subscription {
  private static final long serialVersionUID;

  final org.reactivestreams.Subscriber<? super T> downstream;

  final java.util.concurrent.atomic.AtomicReference<org.reactivestreams.Subscription> upstream;

  public io.reactivex.rxjava3.internal.subscribers.SubscriberResourceWrapper(org.reactivestreams.Subscriber<? super T>);
    Code:
       0: aload_0
       1: invokespecial #1                  // Method java/util/concurrent/atomic/AtomicReference."<init>":()V
       4: aload_0
       5: new           #2                  // class java/util/concurrent/atomic/AtomicReference
       8: dup
       9: invokespecial #1                  // Method java/util/concurrent/atomic/AtomicReference."<init>":()V
      12: putfield      #3                  // Field upstream:Ljava/util/concurrent/atomic/AtomicReference;
      15: aload_0
      16: aload_1
      17: putfield      #4                  // Field downstream:Lorg/reactivestreams/Subscriber;
      20: return

  public void onSubscribe(org.reactivestreams.Subscription);
    Code:
       0: aload_0
       1: getfield      #3                  // Field upstream:Ljava/util/concurrent/atomic/AtomicReference;
       4: aload_1
       5: invokestatic  #5                  // Method io/reactivex/rxjava3/internal/subscriptions/SubscriptionHelper.setOnce:(Ljava/util/concurrent/atomic/AtomicReference;Lorg/reactivestreams/Subscription;)Z
       8: ifeq          21
      11: aload_0
      12: getfield      #4                  // Field downstream:Lorg/reactivestreams/Subscriber;
      15: aload_0
      16: invokeinterface #6,  2            // InterfaceMethod org/reactivestreams/Subscriber.onSubscribe:(Lorg/reactivestreams/Subscription;)V
      21: return

  public void onNext(T);
    Code:
       0: aload_0
       1: getfield      #4                  // Field downstream:Lorg/reactivestreams/Subscriber;
       4: aload_1
       5: invokeinterface #7,  2            // InterfaceMethod org/reactivestreams/Subscriber.onNext:(Ljava/lang/Object;)V
      10: return

  public void onError(java.lang.Throwable);
    Code:
       0: aload_0
       1: invokestatic  #8                  // Method io/reactivex/rxjava3/internal/disposables/DisposableHelper.dispose:(Ljava/util/concurrent/atomic/AtomicReference;)Z
       4: pop
       5: aload_0
       6: getfield      #4                  // Field downstream:Lorg/reactivestreams/Subscriber;
       9: aload_1
      10: invokeinterface #9,  2            // InterfaceMethod org/reactivestreams/Subscriber.onError:(Ljava/lang/Throwable;)V
      15: return

  public void onComplete();
    Code:
       0: aload_0
       1: invokestatic  #8                  // Method io/reactivex/rxjava3/internal/disposables/DisposableHelper.dispose:(Ljava/util/concurrent/atomic/AtomicReference;)Z
       4: pop
       5: aload_0
       6: getfield      #4                  // Field downstream:Lorg/reactivestreams/Subscriber;
       9: invokeinterface #10,  1           // InterfaceMethod org/reactivestreams/Subscriber.onComplete:()V
      14: return

  public void request(long);
    Code:
       0: lload_1
       1: invokestatic  #11                 // Method io/reactivex/rxjava3/internal/subscriptions/SubscriptionHelper.validate:(J)Z
       4: ifeq          23
       7: aload_0
       8: getfield      #3                  // Field upstream:Ljava/util/concurrent/atomic/AtomicReference;
      11: invokevirtual #12                 // Method java/util/concurrent/atomic/AtomicReference.get:()Ljava/lang/Object;
      14: checkcast     #13                 // class org/reactivestreams/Subscription
      17: lload_1
      18: invokeinterface #14,  3           // InterfaceMethod org/reactivestreams/Subscription.request:(J)V
      23: return

  public void dispose();
    Code:
       0: aload_0
       1: getfield      #3                  // Field upstream:Ljava/util/concurrent/atomic/AtomicReference;
       4: invokestatic  #15                 // Method io/reactivex/rxjava3/internal/subscriptions/SubscriptionHelper.cancel:(Ljava/util/concurrent/atomic/AtomicReference;)Z
       7: pop
       8: aload_0
       9: invokestatic  #8                  // Method io/reactivex/rxjava3/internal/disposables/DisposableHelper.dispose:(Ljava/util/concurrent/atomic/AtomicReference;)Z
      12: pop
      13: return

  public boolean isDisposed();
    Code:
       0: aload_0
       1: getfield      #3                  // Field upstream:Ljava/util/concurrent/atomic/AtomicReference;
       4: invokevirtual #12                 // Method java/util/concurrent/atomic/AtomicReference.get:()Ljava/lang/Object;
       7: getstatic     #16                 // Field io/reactivex/rxjava3/internal/subscriptions/SubscriptionHelper.CANCELLED:Lio/reactivex/rxjava3/internal/subscriptions/SubscriptionHelper;
      10: if_acmpne     17
      13: iconst_1
      14: goto          18
      17: iconst_0
      18: ireturn

  public void cancel();
    Code:
       0: aload_0
       1: invokevirtual #17                 // Method dispose:()V
       4: return

  public void setResource(io.reactivex.rxjava3.disposables.Disposable);
    Code:
       0: aload_0
       1: aload_1
       2: invokestatic  #18                 // Method io/reactivex/rxjava3/internal/disposables/DisposableHelper.set:(Ljava/util/concurrent/atomic/AtomicReference;Lio/reactivex/rxjava3/disposables/Disposable;)Z
       5: pop
       6: return
}
