Compiled from "AbstractInvoker.java"
public abstract class org.apache.dubbo.rpc.protocol.AbstractInvoker<T> implements org.apache.dubbo.rpc.Invoker<T> {
  protected static final org.apache.dubbo.common.logger.ErrorTypeAwareLogger logger;

  private final java.lang.Class<T> type;

  private final org.apache.dubbo.common.URL url;

  private final java.util.Map<java.lang.String, java.lang.Object> attachment;

  protected final java.lang.String version;

  private volatile boolean available;

  private boolean destroyed;

  private static final boolean setFutureWhenSync;

  public org.apache.dubbo.rpc.protocol.AbstractInvoker(java.lang.Class<T>, org.apache.dubbo.common.URL);
    Code:
       0: aload_0
       1: aload_1
       2: aload_2
       3: aconst_null
       4: checkcast     #4                  // class java/util/Map
       7: invokespecial #5                  // Method "<init>":(Ljava/lang/Class;Lorg/apache/dubbo/common/URL;Ljava/util/Map;)V
      10: return

  public org.apache.dubbo.rpc.protocol.AbstractInvoker(java.lang.Class<T>, org.apache.dubbo.common.URL, java.lang.String[]);
    Code:
       0: aload_0
       1: aload_1
       2: aload_2
       3: aload_2
       4: aload_3
       5: invokestatic  #6                  // Method convertAttachment:(Lorg/apache/dubbo/common/URL;[Ljava/lang/String;)Ljava/util/Map;
       8: invokespecial #5                  // Method "<init>":(Ljava/lang/Class;Lorg/apache/dubbo/common/URL;Ljava/util/Map;)V
      11: return

  public org.apache.dubbo.rpc.protocol.AbstractInvoker(java.lang.Class<T>, org.apache.dubbo.common.URL, java.util.Map<java.lang.String, java.lang.Object>);
    Code:
       0: aload_0
       1: invokespecial #7                  // Method java/lang/Object."<init>":()V
       4: aload_0
       5: iconst_1
       6: putfield      #8                  // Field available:Z
       9: aload_0
      10: iconst_0
      11: putfield      #9                  // Field destroyed:Z
      14: aload_1
      15: ifnonnull     28
      18: new           #10                 // class java/lang/IllegalArgumentException
      21: dup
      22: ldc           #11                 // String service type == null
      24: invokespecial #12                 // Method java/lang/IllegalArgumentException."<init>":(Ljava/lang/String;)V
      27: athrow
      28: aload_2
      29: ifnonnull     42
      32: new           #10                 // class java/lang/IllegalArgumentException
      35: dup
      36: ldc           #13                 // String service url == null
      38: invokespecial #12                 // Method java/lang/IllegalArgumentException."<init>":(Ljava/lang/String;)V
      41: athrow
      42: aload_0
      43: aload_1
      44: putfield      #14                 // Field type:Ljava/lang/Class;
      47: aload_0
      48: aload_2
      49: putfield      #15                 // Field url:Lorg/apache/dubbo/common/URL;
      52: aload_0
      53: aload_3
      54: ifnonnull     61
      57: aconst_null
      58: goto          65
      61: aload_3
      62: invokestatic  #16                 // Method java/util/Collections.unmodifiableMap:(Ljava/util/Map;)Ljava/util/Map;
      65: putfield      #17                 // Field attachment:Ljava/util/Map;
      68: aload_0
      69: aload_2
      70: ldc           #18                 // String 0.0.0
      72: invokevirtual #19                 // Method org/apache/dubbo/common/URL.getVersion:(Ljava/lang/String;)Ljava/lang/String;
      75: putfield      #20                 // Field version:Ljava/lang/String;
      78: return

  private static java.util.Map<java.lang.String, java.lang.Object> convertAttachment(org.apache.dubbo.common.URL, java.lang.String[]);
    Code:
       0: aload_1
       1: invokestatic  #21                 // Method org/apache/dubbo/common/utils/ArrayUtils.isEmpty:([Ljava/lang/Object;)Z
       4: ifeq          9
       7: aconst_null
       8: areturn
       9: new           #22                 // class java/util/HashMap
      12: dup
      13: aload_1
      14: arraylength
      15: invokespecial #23                 // Method java/util/HashMap."<init>":(I)V
      18: astore_2
      19: aload_1
      20: astore_3
      21: aload_3
      22: arraylength
      23: istore        4
      25: iconst_0
      26: istore        5
      28: iload         5
      30: iload         4
      32: if_icmpge     79
      35: aload_3
      36: iload         5
      38: aaload
      39: astore        6
      41: aload_0
      42: aload         6
      44: invokevirtual #24                 // Method org/apache/dubbo/common/URL.getParameter:(Ljava/lang/String;)Ljava/lang/String;
      47: astore        7
      49: aload         7
      51: ifnull        73
      54: aload         7
      56: invokevirtual #25                 // Method java/lang/String.length:()I
      59: ifle          73
      62: aload_2
      63: aload         6
      65: aload         7
      67: invokeinterface #26,  3           // InterfaceMethod java/util/Map.put:(Ljava/lang/Object;Ljava/lang/Object;)Ljava/lang/Object;
      72: pop
      73: iinc          5, 1
      76: goto          28
      79: aload_2
      80: areturn

  public java.lang.Class<T> getInterface();
    Code:
       0: aload_0
       1: getfield      #14                 // Field type:Ljava/lang/Class;
       4: areturn

  public org.apache.dubbo.common.URL getUrl();
    Code:
       0: aload_0
       1: getfield      #15                 // Field url:Lorg/apache/dubbo/common/URL;
       4: areturn

  public boolean isAvailable();
    Code:
       0: aload_0
       1: getfield      #8                  // Field available:Z
       4: ireturn

  public void destroy();
    Code:
       0: aload_0
       1: iconst_1
       2: putfield      #9                  // Field destroyed:Z
       5: aload_0
       6: iconst_0
       7: invokevirtual #27                 // Method setAvailable:(Z)V
      10: return

  protected void setAvailable(boolean);
    Code:
       0: aload_0
       1: iload_1
       2: putfield      #8                  // Field available:Z
       5: return

  public boolean isDestroyed();
    Code:
       0: aload_0
       1: getfield      #9                  // Field destroyed:Z
       4: ireturn

  public java.lang.String toString();
    Code:
       0: new           #28                 // class java/lang/StringBuilder
       3: dup
       4: invokespecial #29                 // Method java/lang/StringBuilder."<init>":()V
       7: aload_0
       8: invokevirtual #30                 // Method getInterface:()Ljava/lang/Class;
      11: invokevirtual #31                 // Method java/lang/StringBuilder.append:(Ljava/lang/Object;)Ljava/lang/StringBuilder;
      14: ldc           #32                 // String  ->
      16: invokevirtual #33                 // Method java/lang/StringBuilder.append:(Ljava/lang/String;)Ljava/lang/StringBuilder;
      19: aload_0
      20: invokevirtual #34                 // Method getUrl:()Lorg/apache/dubbo/common/URL;
      23: ifnonnull     31
      26: ldc           #35                 // String
      28: goto          38
      31: aload_0
      32: invokevirtual #34                 // Method getUrl:()Lorg/apache/dubbo/common/URL;
      35: invokevirtual #36                 // Method org/apache/dubbo/common/URL.getAddress:()Ljava/lang/String;
      38: invokevirtual #33                 // Method java/lang/StringBuilder.append:(Ljava/lang/String;)Ljava/lang/StringBuilder;
      41: invokevirtual #37                 // Method java/lang/StringBuilder.toString:()Ljava/lang/String;
      44: areturn

  public org.apache.dubbo.rpc.Result invoke(org.apache.dubbo.rpc.Invocation) throws org.apache.dubbo.rpc.RpcException;
    Code:
       0: aload_0
       1: invokevirtual #38                 // Method isDestroyed:()Z
       4: ifeq          67
       7: getstatic     #39                 // Field logger:Lorg/apache/dubbo/common/logger/ErrorTypeAwareLogger;
      10: ldc           #40                 // String 4-11
      12: ldc           #35                 // String
      14: ldc           #35                 // String
      16: new           #28                 // class java/lang/StringBuilder
      19: dup
      20: invokespecial #29                 // Method java/lang/StringBuilder."<init>":()V
      23: ldc           #41                 // String Invoker for service
      25: invokevirtual #33                 // Method java/lang/StringBuilder.append:(Ljava/lang/String;)Ljava/lang/StringBuilder;
      28: aload_0
      29: invokevirtual #31                 // Method java/lang/StringBuilder.append:(Ljava/lang/Object;)Ljava/lang/StringBuilder;
      32: ldc           #42                 // String  on consumer
      34: invokevirtual #33                 // Method java/lang/StringBuilder.append:(Ljava/lang/String;)Ljava/lang/StringBuilder;
      37: invokestatic  #43                 // Method org/apache/dubbo/common/utils/NetUtils.getLocalHost:()Ljava/lang/String;
      40: invokevirtual #33                 // Method java/lang/StringBuilder.append:(Ljava/lang/String;)Ljava/lang/StringBuilder;
      43: ldc           #44                 // String  is destroyed, , dubbo version is
      45: invokevirtual #33                 // Method java/lang/StringBuilder.append:(Ljava/lang/String;)Ljava/lang/StringBuilder;
      48: invokestatic  #45                 // Method org/apache/dubbo/common/Version.getVersion:()Ljava/lang/String;
      51: invokevirtual #33                 // Method java/lang/StringBuilder.append:(Ljava/lang/String;)Ljava/lang/StringBuilder;
      54: ldc           #46                 // String , this invoker should not be used any longer
      56: invokevirtual #33                 // Method java/lang/StringBuilder.append:(Ljava/lang/String;)Ljava/lang/StringBuilder;
      59: invokevirtual #37                 // Method java/lang/StringBuilder.toString:()Ljava/lang/String;
      62: invokeinterface #47,  5           // InterfaceMethod org/apache/dubbo/common/logger/ErrorTypeAwareLogger.warn:(Ljava/lang/String;Ljava/lang/String;Ljava/lang/String;Ljava/lang/String;)V
      67: aload_1
      68: checkcast     #48                 // class org/apache/dubbo/rpc/RpcInvocation
      71: astore_2
      72: aload_0
      73: aload_2
      74: invokespecial #49                 // Method prepareInvocation:(Lorg/apache/dubbo/rpc/RpcInvocation;)V
      77: aload_0
      78: aload_2
      79: invokespecial #50                 // Method doInvokeAndReturn:(Lorg/apache/dubbo/rpc/RpcInvocation;)Lorg/apache/dubbo/rpc/AsyncRpcResult;
      82: astore_3
      83: aload_0
      84: aload_3
      85: aload_2
      86: invokespecial #51                 // Method waitForResultIfSync:(Lorg/apache/dubbo/rpc/AsyncRpcResult;Lorg/apache/dubbo/rpc/RpcInvocation;)V
      89: aload_3
      90: areturn

  private void prepareInvocation(org.apache.dubbo.rpc.RpcInvocation);
    Code:
       0: aload_1
       1: aload_0
       2: invokevirtual #52                 // Method org/apache/dubbo/rpc/RpcInvocation.setInvoker:(Lorg/apache/dubbo/rpc/Invoker;)V
       5: aload_0
       6: aload_1
       7: invokespecial #53                 // Method addInvocationAttachments:(Lorg/apache/dubbo/rpc/RpcInvocation;)V
      10: aload_1
      11: aload_0
      12: getfield      #15                 // Field url:Lorg/apache/dubbo/common/URL;
      15: aload_1
      16: invokestatic  #54                 // Method org/apache/dubbo/rpc/support/RpcUtils.getInvokeMode:(Lorg/apache/dubbo/common/URL;Lorg/apache/dubbo/rpc/Invocation;)Lorg/apache/dubbo/rpc/InvokeMode;
      19: invokevirtual #55                 // Method org/apache/dubbo/rpc/RpcInvocation.setInvokeMode:(Lorg/apache/dubbo/rpc/InvokeMode;)V
      22: aload_0
      23: invokevirtual #34                 // Method getUrl:()Lorg/apache/dubbo/common/URL;
      26: aload_1
      27: invokestatic  #56                 // Method org/apache/dubbo/rpc/support/RpcUtils.attachInvocationIdIfAsync:(Lorg/apache/dubbo/common/URL;Lorg/apache/dubbo/rpc/Invocation;)V
      30: aload_0
      31: aload_1
      32: invokespecial #57                 // Method attachInvocationSerializationId:(Lorg/apache/dubbo/rpc/RpcInvocation;)V
      35: return

  private void attachInvocationSerializationId(org.apache.dubbo.rpc.RpcInvocation);
    Code:
       0: aload_0
       1: invokevirtual #34                 // Method getUrl:()Lorg/apache/dubbo/common/URL;
       4: invokestatic  #58                 // Method org/apache/dubbo/remoting/utils/UrlUtils.serializationId:(Lorg/apache/dubbo/common/URL;)Ljava/lang/Byte;
       7: astore_2
       8: aload_2
       9: ifnull        20
      12: aload_1
      13: ldc           #59                 // String serialization_id
      15: aload_2
      16: invokevirtual #60                 // Method org/apache/dubbo/rpc/RpcInvocation.put:(Ljava/lang/Object;Ljava/lang/Object;)Ljava/lang/Object;
      19: pop
      20: return

  private void addInvocationAttachments(org.apache.dubbo.rpc.RpcInvocation);
    Code:
       0: aload_0
       1: getfield      #17                 // Field attachment:Ljava/util/Map;
       4: invokestatic  #61                 // Method org/apache/dubbo/common/utils/CollectionUtils.isNotEmptyMap:(Ljava/util/Map;)Z
       7: ifeq          18
      10: aload_1
      11: aload_0
      12: getfield      #17                 // Field attachment:Ljava/util/Map;
      15: invokevirtual #62                 // Method org/apache/dubbo/rpc/RpcInvocation.addObjectAttachmentsIfAbsent:(Ljava/util/Map;)V
      18: invokestatic  #63                 // Method org/apache/dubbo/rpc/RpcContext.getClientAttachment:()Lorg/apache/dubbo/rpc/RpcContextAttachment;
      21: invokevirtual #64                 // Method org/apache/dubbo/rpc/RpcContextAttachment.getObjectAttachments:()Ljava/util/Map;
      24: astore_2
      25: aload_2
      26: invokestatic  #61                 // Method org/apache/dubbo/common/utils/CollectionUtils.isNotEmptyMap:(Ljava/util/Map;)Z
      29: ifeq          37
      32: aload_1
      33: aload_2
      34: invokevirtual #62                 // Method org/apache/dubbo/rpc/RpcInvocation.addObjectAttachmentsIfAbsent:(Ljava/util/Map;)V
      37: return

  private org.apache.dubbo.rpc.AsyncRpcResult doInvokeAndReturn(org.apache.dubbo.rpc.RpcInvocation);
    Code:
       0: aload_0
       1: aload_1
       2: invokevirtual #65                 // Method doInvoke:(Lorg/apache/dubbo/rpc/Invocation;)Lorg/apache/dubbo/rpc/Result;
       5: checkcast     #66                 // class org/apache/dubbo/rpc/AsyncRpcResult
       8: astore_2
       9: goto          93
      12: astore_3
      13: aload_3
      14: invokevirtual #68                 // Method java/lang/reflect/InvocationTargetException.getTargetException:()Ljava/lang/Throwable;
      17: astore        4
      19: aload         4
      21: ifnull        52
      24: aload         4
      26: instanceof    #69                 // class org/apache/dubbo/rpc/RpcException
      29: ifeq          41
      32: aload         4
      34: checkcast     #69                 // class org/apache/dubbo/rpc/RpcException
      37: iconst_3
      38: invokevirtual #70                 // Method org/apache/dubbo/rpc/RpcException.setCode:(I)V
      41: aconst_null
      42: aload         4
      44: aload_1
      45: invokestatic  #71                 // Method org/apache/dubbo/rpc/AsyncRpcResult.newDefaultAsyncResult:(Ljava/lang/Object;Ljava/lang/Throwable;Lorg/apache/dubbo/rpc/Invocation;)Lorg/apache/dubbo/rpc/AsyncRpcResult;
      48: astore_2
      49: goto          59
      52: aconst_null
      53: aload_3
      54: aload_1
      55: invokestatic  #71                 // Method org/apache/dubbo/rpc/AsyncRpcResult.newDefaultAsyncResult:(Ljava/lang/Object;Ljava/lang/Throwable;Lorg/apache/dubbo/rpc/Invocation;)Lorg/apache/dubbo/rpc/AsyncRpcResult;
      58: astore_2
      59: goto          93
      62: astore_3
      63: aload_3
      64: invokevirtual #72                 // Method org/apache/dubbo/rpc/RpcException.isBiz:()Z
      67: ifeq          80
      70: aconst_null
      71: aload_3
      72: aload_1
      73: invokestatic  #71                 // Method org/apache/dubbo/rpc/AsyncRpcResult.newDefaultAsyncResult:(Ljava/lang/Object;Ljava/lang/Throwable;Lorg/apache/dubbo/rpc/Invocation;)Lorg/apache/dubbo/rpc/AsyncRpcResult;
      76: astore_2
      77: goto          82
      80: aload_3
      81: athrow
      82: goto          93
      85: astore_3
      86: aconst_null
      87: aload_3
      88: aload_1
      89: invokestatic  #71                 // Method org/apache/dubbo/rpc/AsyncRpcResult.newDefaultAsyncResult:(Ljava/lang/Object;Ljava/lang/Throwable;Lorg/apache/dubbo/rpc/Invocation;)Lorg/apache/dubbo/rpc/AsyncRpcResult;
      92: astore_2
      93: getstatic     #74                 // Field setFutureWhenSync:Z
      96: ifne          109
      99: aload_1
     100: invokevirtual #75                 // Method org/apache/dubbo/rpc/RpcInvocation.getInvokeMode:()Lorg/apache/dubbo/rpc/InvokeMode;
     103: getstatic     #76                 // Field org/apache/dubbo/rpc/InvokeMode.SYNC:Lorg/apache/dubbo/rpc/InvokeMode;
     106: if_acmpeq     126
     109: invokestatic  #77                 // Method org/apache/dubbo/rpc/RpcContext.getServiceContext:()Lorg/apache/dubbo/rpc/RpcServiceContext;
     112: new           #78                 // class org/apache/dubbo/rpc/protocol/dubbo/FutureAdapter
     115: dup
     116: aload_2
     117: invokevirtual #79                 // Method org/apache/dubbo/rpc/AsyncRpcResult.getResponseFuture:()Ljava/util/concurrent/CompletableFuture;
     120: invokespecial #80                 // Method org/apache/dubbo/rpc/protocol/dubbo/FutureAdapter."<init>":(Ljava/util/concurrent/CompletableFuture;)V
     123: invokevirtual #81                 // Method org/apache/dubbo/rpc/RpcServiceContext.setFuture:(Ljava/util/concurrent/CompletableFuture;)V
     126: aload_2
     127: areturn
    Exception table:
       from    to  target type
           0     9    12   Class java/lang/reflect/InvocationTargetException
           0     9    62   Class org/apache/dubbo/rpc/RpcException
           0     9    85   Class java/lang/Throwable

  private void waitForResultIfSync(org.apache.dubbo.rpc.AsyncRpcResult, org.apache.dubbo.rpc.RpcInvocation);
    Code:
       0: getstatic     #76                 // Field org/apache/dubbo/rpc/InvokeMode.SYNC:Lorg/apache/dubbo/rpc/InvokeMode;
       3: aload_2
       4: invokevirtual #75                 // Method org/apache/dubbo/rpc/RpcInvocation.getInvokeMode:()Lorg/apache/dubbo/rpc/InvokeMode;
       7: if_acmpeq     11
      10: return
      11: aload_2
      12: ldc           #82                 // String timeout
      14: invokevirtual #83                 // Method org/apache/dubbo/rpc/RpcInvocation.getObjectAttachmentWithoutConvert:(Ljava/lang/String;)Ljava/lang/Object;
      17: astore_3
      18: aload_3
      19: ldc2_w        #85                 // long 2147483647l
      22: invokestatic  #87                 // Method org/apache/dubbo/rpc/support/RpcUtils.convertToNumber:(Ljava/lang/Object;J)Ljava/lang/Long;
      25: invokevirtual #88                 // Method java/lang/Long.longValue:()J
      28: lstore        4
      30: aload_1
      31: lload         4
      33: getstatic     #89                 // Field java/util/concurrent/TimeUnit.MILLISECONDS:Ljava/util/concurrent/TimeUnit;
      36: invokevirtual #90                 // Method org/apache/dubbo/rpc/AsyncRpcResult.get:(JLjava/util/concurrent/TimeUnit;)Lorg/apache/dubbo/rpc/Result;
      39: pop
      40: goto          367
      43: astore_3
      44: invokestatic  #92                 // Method java/lang/Thread.currentThread:()Ljava/lang/Thread;
      47: invokevirtual #93                 // Method java/lang/Thread.interrupt:()V
      50: new           #69                 // class org/apache/dubbo/rpc/RpcException
      53: dup
      54: new           #28                 // class java/lang/StringBuilder
      57: dup
      58: invokespecial #29                 // Method java/lang/StringBuilder."<init>":()V
      61: ldc           #94                 // String Interrupted unexpectedly while waiting for remote result to return! method:
      63: invokevirtual #33                 // Method java/lang/StringBuilder.append:(Ljava/lang/String;)Ljava/lang/StringBuilder;
      66: aload_2
      67: invokevirtual #95                 // Method org/apache/dubbo/rpc/RpcInvocation.getMethodName:()Ljava/lang/String;
      70: invokevirtual #33                 // Method java/lang/StringBuilder.append:(Ljava/lang/String;)Ljava/lang/StringBuilder;
      73: ldc           #96                 // String , provider:
      75: invokevirtual #33                 // Method java/lang/StringBuilder.append:(Ljava/lang/String;)Ljava/lang/StringBuilder;
      78: aload_0
      79: invokevirtual #34                 // Method getUrl:()Lorg/apache/dubbo/common/URL;
      82: invokevirtual #31                 // Method java/lang/StringBuilder.append:(Ljava/lang/Object;)Ljava/lang/StringBuilder;
      85: ldc           #97                 // String , cause:
      87: invokevirtual #33                 // Method java/lang/StringBuilder.append:(Ljava/lang/String;)Ljava/lang/StringBuilder;
      90: aload_3
      91: invokevirtual #98                 // Method java/lang/InterruptedException.getMessage:()Ljava/lang/String;
      94: invokevirtual #33                 // Method java/lang/StringBuilder.append:(Ljava/lang/String;)Ljava/lang/StringBuilder;
      97: invokevirtual #37                 // Method java/lang/StringBuilder.toString:()Ljava/lang/String;
     100: aload_3
     101: invokespecial #99                 // Method org/apache/dubbo/rpc/RpcException."<init>":(Ljava/lang/String;Ljava/lang/Throwable;)V
     104: athrow
     105: astore_3
     106: aload_3
     107: invokevirtual #101                // Method java/util/concurrent/ExecutionException.getCause:()Ljava/lang/Throwable;
     110: astore        4
     112: aload         4
     114: instanceof    #102                // class org/apache/dubbo/remoting/TimeoutException
     117: ifeq          176
     120: new           #69                 // class org/apache/dubbo/rpc/RpcException
     123: dup
     124: iconst_2
     125: new           #28                 // class java/lang/StringBuilder
     128: dup
     129: invokespecial #29                 // Method java/lang/StringBuilder."<init>":()V
     132: ldc           #103                // String Invoke remote method timeout. method:
     134: invokevirtual #33                 // Method java/lang/StringBuilder.append:(Ljava/lang/String;)Ljava/lang/StringBuilder;
     137: aload_2
     138: invokevirtual #95                 // Method org/apache/dubbo/rpc/RpcInvocation.getMethodName:()Ljava/lang/String;
     141: invokevirtual #33                 // Method java/lang/StringBuilder.append:(Ljava/lang/String;)Ljava/lang/StringBuilder;
     144: ldc           #96                 // String , provider:
     146: invokevirtual #33                 // Method java/lang/StringBuilder.append:(Ljava/lang/String;)Ljava/lang/StringBuilder;
     149: aload_0
     150: invokevirtual #34                 // Method getUrl:()Lorg/apache/dubbo/common/URL;
     153: invokevirtual #31                 // Method java/lang/StringBuilder.append:(Ljava/lang/Object;)Ljava/lang/StringBuilder;
     156: ldc           #97                 // String , cause:
     158: invokevirtual #33                 // Method java/lang/StringBuilder.append:(Ljava/lang/String;)Ljava/lang/StringBuilder;
     161: aload_3
     162: invokevirtual #104                // Method java/util/concurrent/ExecutionException.getMessage:()Ljava/lang/String;
     165: invokevirtual #33                 // Method java/lang/StringBuilder.append:(Ljava/lang/String;)Ljava/lang/StringBuilder;
     168: invokevirtual #37                 // Method java/lang/StringBuilder.toString:()Ljava/lang/String;
     171: aload_3
     172: invokespecial #105                // Method org/apache/dubbo/rpc/RpcException."<init>":(ILjava/lang/String;Ljava/lang/Throwable;)V
     175: athrow
     176: aload         4
     178: instanceof    #106                // class org/apache/dubbo/remoting/RemotingException
     181: ifeq          240
     184: new           #69                 // class org/apache/dubbo/rpc/RpcException
     187: dup
     188: iconst_1
     189: new           #28                 // class java/lang/StringBuilder
     192: dup
     193: invokespecial #29                 // Method java/lang/StringBuilder."<init>":()V
     196: ldc           #107                // String Failed to invoke remote method:
     198: invokevirtual #33                 // Method java/lang/StringBuilder.append:(Ljava/lang/String;)Ljava/lang/StringBuilder;
     201: aload_2
     202: invokevirtual #95                 // Method org/apache/dubbo/rpc/RpcInvocation.getMethodName:()Ljava/lang/String;
     205: invokevirtual #33                 // Method java/lang/StringBuilder.append:(Ljava/lang/String;)Ljava/lang/StringBuilder;
     208: ldc           #96                 // String , provider:
     210: invokevirtual #33                 // Method java/lang/StringBuilder.append:(Ljava/lang/String;)Ljava/lang/StringBuilder;
     213: aload_0
     214: invokevirtual #34                 // Method getUrl:()Lorg/apache/dubbo/common/URL;
     217: invokevirtual #31                 // Method java/lang/StringBuilder.append:(Ljava/lang/Object;)Ljava/lang/StringBuilder;
     220: ldc           #97                 // String , cause:
     222: invokevirtual #33                 // Method java/lang/StringBuilder.append:(Ljava/lang/String;)Ljava/lang/StringBuilder;
     225: aload_3
     226: invokevirtual #104                // Method java/util/concurrent/ExecutionException.getMessage:()Ljava/lang/String;
     229: invokevirtual #33                 // Method java/lang/StringBuilder.append:(Ljava/lang/String;)Ljava/lang/StringBuilder;
     232: invokevirtual #37                 // Method java/lang/StringBuilder.toString:()Ljava/lang/String;
     235: aload_3
     236: invokespecial #105                // Method org/apache/dubbo/rpc/RpcException."<init>":(ILjava/lang/String;Ljava/lang/Throwable;)V
     239: athrow
     240: new           #69                 // class org/apache/dubbo/rpc/RpcException
     243: dup
     244: iconst_0
     245: new           #28                 // class java/lang/StringBuilder
     248: dup
     249: invokespecial #29                 // Method java/lang/StringBuilder."<init>":()V
     252: ldc           #108                // String Fail to invoke remote method:
     254: invokevirtual #33                 // Method java/lang/StringBuilder.append:(Ljava/lang/String;)Ljava/lang/StringBuilder;
     257: aload_2
     258: invokevirtual #95                 // Method org/apache/dubbo/rpc/RpcInvocation.getMethodName:()Ljava/lang/String;
     261: invokevirtual #33                 // Method java/lang/StringBuilder.append:(Ljava/lang/String;)Ljava/lang/StringBuilder;
     264: ldc           #96                 // String , provider:
     266: invokevirtual #33                 // Method java/lang/StringBuilder.append:(Ljava/lang/String;)Ljava/lang/StringBuilder;
     269: aload_0
     270: invokevirtual #34                 // Method getUrl:()Lorg/apache/dubbo/common/URL;
     273: invokevirtual #31                 // Method java/lang/StringBuilder.append:(Ljava/lang/Object;)Ljava/lang/StringBuilder;
     276: ldc           #97                 // String , cause:
     278: invokevirtual #33                 // Method java/lang/StringBuilder.append:(Ljava/lang/String;)Ljava/lang/StringBuilder;
     281: aload_3
     282: invokevirtual #104                // Method java/util/concurrent/ExecutionException.getMessage:()Ljava/lang/String;
     285: invokevirtual #33                 // Method java/lang/StringBuilder.append:(Ljava/lang/String;)Ljava/lang/StringBuilder;
     288: invokevirtual #37                 // Method java/lang/StringBuilder.toString:()Ljava/lang/String;
     291: aload_3
     292: invokespecial #105                // Method org/apache/dubbo/rpc/RpcException."<init>":(ILjava/lang/String;Ljava/lang/Throwable;)V
     295: athrow
     296: astore_3
     297: new           #69                 // class org/apache/dubbo/rpc/RpcException
     300: dup
     301: iconst_2
     302: new           #28                 // class java/lang/StringBuilder
     305: dup
     306: invokespecial #29                 // Method java/lang/StringBuilder."<init>":()V
     309: ldc           #103                // String Invoke remote method timeout. method:
     311: invokevirtual #33                 // Method java/lang/StringBuilder.append:(Ljava/lang/String;)Ljava/lang/StringBuilder;
     314: aload_2
     315: invokevirtual #95                 // Method org/apache/dubbo/rpc/RpcInvocation.getMethodName:()Ljava/lang/String;
     318: invokevirtual #33                 // Method java/lang/StringBuilder.append:(Ljava/lang/String;)Ljava/lang/StringBuilder;
     321: ldc           #96                 // String , provider:
     323: invokevirtual #33                 // Method java/lang/StringBuilder.append:(Ljava/lang/String;)Ljava/lang/StringBuilder;
     326: aload_0
     327: invokevirtual #34                 // Method getUrl:()Lorg/apache/dubbo/common/URL;
     330: invokevirtual #31                 // Method java/lang/StringBuilder.append:(Ljava/lang/Object;)Ljava/lang/StringBuilder;
     333: ldc           #97                 // String , cause:
     335: invokevirtual #33                 // Method java/lang/StringBuilder.append:(Ljava/lang/String;)Ljava/lang/StringBuilder;
     338: aload_3
     339: invokevirtual #110                // Method java/util/concurrent/TimeoutException.getMessage:()Ljava/lang/String;
     342: invokevirtual #33                 // Method java/lang/StringBuilder.append:(Ljava/lang/String;)Ljava/lang/StringBuilder;
     345: invokevirtual #37                 // Method java/lang/StringBuilder.toString:()Ljava/lang/String;
     348: aload_3
     349: invokespecial #105                // Method org/apache/dubbo/rpc/RpcException."<init>":(ILjava/lang/String;Ljava/lang/Throwable;)V
     352: athrow
     353: astore_3
     354: new           #69                 // class org/apache/dubbo/rpc/RpcException
     357: dup
     358: aload_3
     359: invokevirtual #111                // Method java/lang/Throwable.getMessage:()Ljava/lang/String;
     362: aload_3
     363: invokespecial #99                 // Method org/apache/dubbo/rpc/RpcException."<init>":(Ljava/lang/String;Ljava/lang/Throwable;)V
     366: athrow
     367: return
    Exception table:
       from    to  target type
          11    40    43   Class java/lang/InterruptedException
          11    40   105   Class java/util/concurrent/ExecutionException
          11    40   296   Class java/util/concurrent/TimeoutException
          11    40   353   Class java/lang/Throwable

  protected java.util.concurrent.ExecutorService getCallbackExecutor(org.apache.dubbo.common.URL, org.apache.dubbo.rpc.Invocation);
    Code:
       0: getstatic     #76                 // Field org/apache/dubbo/rpc/InvokeMode.SYNC:Lorg/apache/dubbo/rpc/InvokeMode;
       3: aload_0
       4: invokevirtual #34                 // Method getUrl:()Lorg/apache/dubbo/common/URL;
       7: aload_2
       8: invokestatic  #54                 // Method org/apache/dubbo/rpc/support/RpcUtils.getInvokeMode:(Lorg/apache/dubbo/common/URL;Lorg/apache/dubbo/rpc/Invocation;)Lorg/apache/dubbo/rpc/InvokeMode;
      11: if_acmpne     22
      14: new           #112                // class org/apache/dubbo/common/threadpool/ThreadlessExecutor
      17: dup
      18: invokespecial #113                // Method org/apache/dubbo/common/threadpool/ThreadlessExecutor."<init>":()V
      21: areturn
      22: aload_1
      23: invokevirtual #114                // Method org/apache/dubbo/common/URL.getOrDefaultApplicationModel:()Lorg/apache/dubbo/rpc/model/ApplicationModel;
      26: invokestatic  #115                // InterfaceMethod org/apache/dubbo/common/threadpool/manager/ExecutorRepository.getInstance:(Lorg/apache/dubbo/rpc/model/ApplicationModel;)Lorg/apache/dubbo/common/threadpool/manager/ExecutorRepository;
      29: aload_1
      30: invokeinterface #116,  2          // InterfaceMethod org/apache/dubbo/common/threadpool/manager/ExecutorRepository.getExecutor:(Lorg/apache/dubbo/common/URL;)Ljava/util/concurrent/ExecutorService;
      35: areturn

  protected abstract org.apache.dubbo.rpc.Result doInvoke(org.apache.dubbo.rpc.Invocation) throws java.lang.Throwable;

  static {};
    Code:
       0: ldc           #117                // class org/apache/dubbo/rpc/protocol/AbstractInvoker
       2: invokestatic  #118                // Method org/apache/dubbo/common/logger/LoggerFactory.getErrorTypeAwareLogger:(Ljava/lang/Class;)Lorg/apache/dubbo/common/logger/ErrorTypeAwareLogger;
       5: putstatic     #39                 // Field logger:Lorg/apache/dubbo/common/logger/ErrorTypeAwareLogger;
       8: ldc           #119                // String future.sync.set
      10: ldc           #120                // String true
      12: invokestatic  #121                // Method java/lang/System.getProperty:(Ljava/lang/String;Ljava/lang/String;)Ljava/lang/String;
      15: invokestatic  #122                // Method java/lang/Boolean.parseBoolean:(Ljava/lang/String;)Z
      18: putstatic     #74                 // Field setFutureWhenSync:Z
      21: return
}
