Compiled from "AbstractExporter.java"
public abstract class org.apache.dubbo.rpc.protocol.AbstractExporter<T> implements org.apache.dubbo.rpc.Exporter<T> {
  protected final org.apache.dubbo.common.logger.ErrorTypeAwareLogger logger;

  private final org.apache.dubbo.rpc.Invoker<T> invoker;

  private volatile boolean unexported;

  public org.apache.dubbo.rpc.protocol.AbstractExporter(org.apache.dubbo.rpc.Invoker<T>);
    Code:
       0: aload_0
       1: invokespecial #1                  // Method java/lang/Object."<init>":()V
       4: aload_0
       5: aload_0
       6: invokevirtual #2                  // Method java/lang/Object.getClass:()Ljava/lang/Class;
       9: invokestatic  #3                  // Method org/apache/dubbo/common/logger/LoggerFactory.getErrorTypeAwareLogger:(Ljava/lang/Class;)Lorg/apache/dubbo/common/logger/ErrorTypeAwareLogger;
      12: putfield      #4                  // Field logger:Lorg/apache/dubbo/common/logger/ErrorTypeAwareLogger;
      15: aload_0
      16: iconst_0
      17: putfield      #5                  // Field unexported:Z
      20: aload_1
      21: ifnonnull     34
      24: new           #6                  // class java/lang/IllegalStateException
      27: dup
      28: ldc           #7                  // String service invoker == null
      30: invokespecial #8                  // Method java/lang/IllegalStateException."<init>":(Ljava/lang/String;)V
      33: athrow
      34: aload_1
      35: invokeinterface #9,  1            // InterfaceMethod org/apache/dubbo/rpc/Invoker.getInterface:()Ljava/lang/Class;
      40: ifnonnull     53
      43: new           #6                  // class java/lang/IllegalStateException
      46: dup
      47: ldc           #10                 // String service type == null
      49: invokespecial #8                  // Method java/lang/IllegalStateException."<init>":(Ljava/lang/String;)V
      52: athrow
      53: aload_1
      54: invokeinterface #11,  1           // InterfaceMethod org/apache/dubbo/rpc/Invoker.getUrl:()Lorg/apache/dubbo/common/URL;
      59: ifnonnull     72
      62: new           #6                  // class java/lang/IllegalStateException
      65: dup
      66: ldc           #12                 // String service url == null
      68: invokespecial #8                  // Method java/lang/IllegalStateException."<init>":(Ljava/lang/String;)V
      71: athrow
      72: aload_0
      73: aload_1
      74: putfield      #13                 // Field invoker:Lorg/apache/dubbo/rpc/Invoker;
      77: return

  public org.apache.dubbo.rpc.Invoker<T> getInvoker();
    Code:
       0: aload_0
       1: getfield      #13                 // Field invoker:Lorg/apache/dubbo/rpc/Invoker;
       4: areturn

  public final void unexport();
    Code:
       0: aload_0
       1: getfield      #5                  // Field unexported:Z
       4: ifeq          8
       7: return
       8: aload_0
       9: iconst_1
      10: putfield      #5                  // Field unexported:Z
      13: aload_0
      14: invokevirtual #14                 // Method getInvoker:()Lorg/apache/dubbo/rpc/Invoker;
      17: invokeinterface #15,  1           // InterfaceMethod org/apache/dubbo/rpc/Invoker.destroy:()V
      22: aload_0
      23: invokevirtual #16                 // Method afterUnExport:()V
      26: return

  public void unregister();
    Code:
       0: return

  public void afterUnExport();
    Code:
       0: return

  public java.lang.String toString();
    Code:
       0: aload_0
       1: invokevirtual #14                 // Method getInvoker:()Lorg/apache/dubbo/rpc/Invoker;
       4: invokevirtual #17                 // Method java/lang/Object.toString:()Ljava/lang/String;
       7: areturn
}
