Compiled from "AbstractProxyProtocol.java"
class org.apache.dubbo.rpc.protocol.AbstractProxyProtocol$2 extends org.apache.dubbo.rpc.protocol.AbstractExporter<T> {
  final java.lang.String val$uri;

  final java.lang.Runnable val$runnable;

  final org.apache.dubbo.rpc.protocol.AbstractProxyProtocol this$0;

  org.apache.dubbo.rpc.protocol.AbstractProxyProtocol$2(org.apache.dubbo.rpc.protocol.AbstractProxyProtocol, org.apache.dubbo.rpc.Invoker, java.lang.String, java.lang.Runnable);
    Code:
       0: aload_0
       1: aload_1
       2: putfield      #2                  // Field this$0:Lorg/apache/dubbo/rpc/protocol/AbstractProxyProtocol;
       5: aload_0
       6: aload_3
       7: putfield      #3                  // Field val$uri:Ljava/lang/String;
      10: aload_0
      11: aload         4
      13: putfield      #4                  // Field val$runnable:Ljava/lang/Runnable;
      16: aload_0
      17: aload_2
      18: invokespecial #5                  // Method org/apache/dubbo/rpc/protocol/AbstractExporter."<init>":(Lorg/apache/dubbo/rpc/Invoker;)V
      21: return

  public void afterUnExport();
    Code:
       0: aload_0
       1: getfield      #2                  // Field this$0:Lorg/apache/dubbo/rpc/protocol/AbstractProxyProtocol;
       4: getfield      #6                  // Field org/apache/dubbo/rpc/protocol/AbstractProxyProtocol.exporterMap:Ljava/util/Map;
       7: aload_0
       8: getfield      #3                  // Field val$uri:Ljava/lang/String;
      11: invokeinterface #7,  2            // InterfaceMethod java/util/Map.remove:(Ljava/lang/Object;)Ljava/lang/Object;
      16: pop
      17: aload_0
      18: getfield      #4                  // Field val$runnable:Ljava/lang/Runnable;
      21: ifnull        57
      24: aload_0
      25: getfield      #4                  // Field val$runnable:Ljava/lang/Runnable;
      28: invokeinterface #8,  1            // InterfaceMethod java/lang/Runnable.run:()V
      33: goto          57
      36: astore_1
      37: aload_0
      38: getfield      #10                 // Field logger:Lorg/apache/dubbo/common/logger/ErrorTypeAwareLogger;
      41: ldc           #11                 // String 4-1
      43: ldc           #12                 // String
      45: ldc           #12                 // String
      47: aload_1
      48: invokevirtual #13                 // Method java/lang/Throwable.getMessage:()Ljava/lang/String;
      51: aload_1
      52: invokeinterface #14,  6           // InterfaceMethod org/apache/dubbo/common/logger/ErrorTypeAwareLogger.warn:(Ljava/lang/String;Ljava/lang/String;Ljava/lang/String;Ljava/lang/String;Ljava/lang/Throwable;)V
      57: return
    Exception table:
       from    to  target type
          24    33    36   Class java/lang/Throwable
}
