Compiled from "AbstractProtocol.java"
public abstract class org.apache.dubbo.rpc.protocol.AbstractProtocol implements org.apache.dubbo.rpc.Protocol,org.apache.dubbo.rpc.model.ScopeModelAware {
  protected final org.apache.dubbo.common.logger.ErrorTypeAwareLogger logger;

  protected final java.util.Map<java.lang.String, org.apache.dubbo.rpc.Exporter<?>> exporterMap;

  protected final java.util.concurrent.ConcurrentMap<java.lang.String, org.apache.dubbo.rpc.ProtocolServer> serverMap;

  protected final java.util.Set<org.apache.dubbo.rpc.Invoker<?>> invokers;

  protected org.apache.dubbo.rpc.model.FrameworkModel frameworkModel;

  private final java.util.Set<java.lang.String> optimizers;

  public org.apache.dubbo.rpc.protocol.AbstractProtocol();
    Code:
       0: aload_0
       1: invokespecial #3                  // Method java/lang/Object."<init>":()V
       4: aload_0
       5: aload_0
       6: invokevirtual #4                  // Method java/lang/Object.getClass:()Ljava/lang/Class;
       9: invokestatic  #5                  // Method org/apache/dubbo/common/logger/LoggerFactory.getErrorTypeAwareLogger:(Ljava/lang/Class;)Lorg/apache/dubbo/common/logger/ErrorTypeAwareLogger;
      12: putfield      #6                  // Field logger:Lorg/apache/dubbo/common/logger/ErrorTypeAwareLogger;
      15: aload_0
      16: new           #7                  // class java/util/concurrent/ConcurrentHashMap
      19: dup
      20: invokespecial #8                  // Method java/util/concurrent/ConcurrentHashMap."<init>":()V
      23: putfield      #9                  // Field exporterMap:Ljava/util/Map;
      26: aload_0
      27: new           #7                  // class java/util/concurrent/ConcurrentHashMap
      30: dup
      31: invokespecial #8                  // Method java/util/concurrent/ConcurrentHashMap."<init>":()V
      34: putfield      #10                 // Field serverMap:Ljava/util/concurrent/ConcurrentMap;
      37: aload_0
      38: new           #11                 // class org/apache/dubbo/common/utils/ConcurrentHashSet
      41: dup
      42: invokespecial #12                 // Method org/apache/dubbo/common/utils/ConcurrentHashSet."<init>":()V
      45: putfield      #13                 // Field invokers:Ljava/util/Set;
      48: aload_0
      49: new           #11                 // class org/apache/dubbo/common/utils/ConcurrentHashSet
      52: dup
      53: invokespecial #12                 // Method org/apache/dubbo/common/utils/ConcurrentHashSet."<init>":()V
      56: putfield      #14                 // Field optimizers:Ljava/util/Set;
      59: return

  public void setFrameworkModel(org.apache.dubbo.rpc.model.FrameworkModel);
    Code:
       0: aload_0
       1: aload_1
       2: putfield      #15                 // Field frameworkModel:Lorg/apache/dubbo/rpc/model/FrameworkModel;
       5: return

  protected static java.lang.String serviceKey(org.apache.dubbo.common.URL);
    Code:
       0: aload_0
       1: ldc           #17                 // String bind.port
       3: aload_0
       4: invokevirtual #18                 // Method org/apache/dubbo/common/URL.getPort:()I
       7: invokevirtual #19                 // Method org/apache/dubbo/common/URL.getParameter:(Ljava/lang/String;I)I
      10: istore_1
      11: iload_1
      12: aload_0
      13: invokevirtual #20                 // Method org/apache/dubbo/common/URL.getPath:()Ljava/lang/String;
      16: aload_0
      17: invokevirtual #21                 // Method org/apache/dubbo/common/URL.getVersion:()Ljava/lang/String;
      20: aload_0
      21: invokevirtual #22                 // Method org/apache/dubbo/common/URL.getGroup:()Ljava/lang/String;
      24: invokestatic  #23                 // Method serviceKey:(ILjava/lang/String;Ljava/lang/String;Ljava/lang/String;)Ljava/lang/String;
      27: areturn

  protected static java.lang.String serviceKey(int, java.lang.String, java.lang.String, java.lang.String);
    Code:
       0: iload_0
       1: aload_1
       2: aload_2
       3: aload_3
       4: invokestatic  #24                 // Method org/apache/dubbo/rpc/support/ProtocolUtils.serviceKey:(ILjava/lang/String;Ljava/lang/String;Ljava/lang/String;)Ljava/lang/String;
       7: areturn

  public java.util.List<org.apache.dubbo.rpc.ProtocolServer> getServers();
    Code:
       0: new           #25                 // class java/util/ArrayList
       3: dup
       4: aload_0
       5: getfield      #10                 // Field serverMap:Ljava/util/concurrent/ConcurrentMap;
       8: invokeinterface #26,  1           // InterfaceMethod java/util/concurrent/ConcurrentMap.values:()Ljava/util/Collection;
      13: invokespecial #27                 // Method java/util/ArrayList."<init>":(Ljava/util/Collection;)V
      16: invokestatic  #28                 // Method java/util/Collections.unmodifiableList:(Ljava/util/List;)Ljava/util/List;
      19: areturn

  protected void loadServerProperties(org.apache.dubbo.rpc.ProtocolServer);
    Code:
       0: aload_1
       1: invokeinterface #29,  1           // InterfaceMethod org/apache/dubbo/rpc/ProtocolServer.getUrl:()Lorg/apache/dubbo/common/URL;
       6: invokevirtual #30                 // Method org/apache/dubbo/common/URL.getScopeModel:()Lorg/apache/dubbo/rpc/model/ScopeModel;
       9: invokestatic  #31                 // Method org/apache/dubbo/common/config/ConfigurationUtils.getServerShutdownTimeout:(Lorg/apache/dubbo/rpc/model/ScopeModel;)I
      12: istore_2
      13: aload_1
      14: invokeinterface #32,  1           // InterfaceMethod org/apache/dubbo/rpc/ProtocolServer.getAttributes:()Ljava/util/Map;
      19: ldc           #33                 // String dubbo.service.shutdown.wait
      21: iload_2
      22: invokestatic  #34                 // Method java/lang/Integer.valueOf:(I)Ljava/lang/Integer;
      25: invokeinterface #35,  3           // InterfaceMethod java/util/Map.put:(Ljava/lang/Object;Ljava/lang/Object;)Ljava/lang/Object;
      30: pop
      31: return

  protected int getServerShutdownTimeout(org.apache.dubbo.rpc.ProtocolServer);
    Code:
       0: aload_1
       1: invokeinterface #32,  1           // InterfaceMethod org/apache/dubbo/rpc/ProtocolServer.getAttributes:()Ljava/util/Map;
       6: ldc           #33                 // String dubbo.service.shutdown.wait
       8: sipush        10000
      11: invokestatic  #34                 // Method java/lang/Integer.valueOf:(I)Ljava/lang/Integer;
      14: invokeinterface #36,  3           // InterfaceMethod java/util/Map.getOrDefault:(Ljava/lang/Object;Ljava/lang/Object;)Ljava/lang/Object;
      19: checkcast     #37                 // class java/lang/Integer
      22: invokevirtual #38                 // Method java/lang/Integer.intValue:()I
      25: ireturn

  public void destroy();
    Code:
       0: aload_0
       1: getfield      #13                 // Field invokers:Ljava/util/Set;
       4: invokeinterface #39,  1           // InterfaceMethod java/util/Set.iterator:()Ljava/util/Iterator;
       9: astore_1
      10: aload_1
      11: invokeinterface #40,  1           // InterfaceMethod java/util/Iterator.hasNext:()Z
      16: ifeq          111
      19: aload_1
      20: invokeinterface #41,  1           // InterfaceMethod java/util/Iterator.next:()Ljava/lang/Object;
      25: checkcast     #42                 // class org/apache/dubbo/rpc/Invoker
      28: astore_2
      29: aload_2
      30: ifnull        108
      33: aload_0
      34: getfield      #6                  // Field logger:Lorg/apache/dubbo/common/logger/ErrorTypeAwareLogger;
      37: invokeinterface #43,  1           // InterfaceMethod org/apache/dubbo/common/logger/ErrorTypeAwareLogger.isInfoEnabled:()Z
      42: ifeq          78
      45: aload_0
      46: getfield      #6                  // Field logger:Lorg/apache/dubbo/common/logger/ErrorTypeAwareLogger;
      49: new           #44                 // class java/lang/StringBuilder
      52: dup
      53: invokespecial #45                 // Method java/lang/StringBuilder."<init>":()V
      56: ldc           #46                 // String Destroy reference:
      58: invokevirtual #47                 // Method java/lang/StringBuilder.append:(Ljava/lang/String;)Ljava/lang/StringBuilder;
      61: aload_2
      62: invokeinterface #48,  1           // InterfaceMethod org/apache/dubbo/rpc/Invoker.getUrl:()Lorg/apache/dubbo/common/URL;
      67: invokevirtual #49                 // Method java/lang/StringBuilder.append:(Ljava/lang/Object;)Ljava/lang/StringBuilder;
      70: invokevirtual #50                 // Method java/lang/StringBuilder.toString:()Ljava/lang/String;
      73: invokeinterface #51,  2           // InterfaceMethod org/apache/dubbo/common/logger/ErrorTypeAwareLogger.info:(Ljava/lang/String;)V
      78: aload_2
      79: invokeinterface #52,  1           // InterfaceMethod org/apache/dubbo/rpc/Invoker.destroy:()V
      84: goto          108
      87: astore_3
      88: aload_0
      89: getfield      #6                  // Field logger:Lorg/apache/dubbo/common/logger/ErrorTypeAwareLogger;
      92: ldc           #54                 // String 4-17
      94: ldc           #55                 // String
      96: ldc           #55                 // String
      98: aload_3
      99: invokevirtual #56                 // Method java/lang/Throwable.getMessage:()Ljava/lang/String;
     102: aload_3
     103: invokeinterface #57,  6           // InterfaceMethod org/apache/dubbo/common/logger/ErrorTypeAwareLogger.warn:(Ljava/lang/String;Ljava/lang/String;Ljava/lang/String;Ljava/lang/String;Ljava/lang/Throwable;)V
     108: goto          10
     111: aload_0
     112: getfield      #13                 // Field invokers:Ljava/util/Set;
     115: invokeinterface #58,  1           // InterfaceMethod java/util/Set.clear:()V
     120: aload_0
     121: getfield      #9                  // Field exporterMap:Ljava/util/Map;
     124: aload_0
     125: invokedynamic #59,  0             // InvokeDynamic #0:accept:(Lorg/apache/dubbo/rpc/protocol/AbstractProtocol;)Ljava/util/function/BiConsumer;
     130: invokeinterface #60,  2           // InterfaceMethod java/util/Map.forEach:(Ljava/util/function/BiConsumer;)V
     135: aload_0
     136: getfield      #9                  // Field exporterMap:Ljava/util/Map;
     139: invokeinterface #61,  1           // InterfaceMethod java/util/Map.clear:()V
     144: return
    Exception table:
       from    to  target type
          33    84    87   Class java/lang/Throwable

  public <T> org.apache.dubbo.rpc.Invoker<T> refer(java.lang.Class<T>, org.apache.dubbo.common.URL) throws org.apache.dubbo.rpc.RpcException;
    Code:
       0: aload_0
       1: aload_1
       2: aload_2
       3: invokevirtual #62                 // Method protocolBindingRefer:(Ljava/lang/Class;Lorg/apache/dubbo/common/URL;)Lorg/apache/dubbo/rpc/Invoker;
       6: areturn

  protected abstract <T> org.apache.dubbo.rpc.Invoker<T> protocolBindingRefer(java.lang.Class<T>, org.apache.dubbo.common.URL) throws org.apache.dubbo.rpc.RpcException;

  public java.util.Map<java.lang.String, org.apache.dubbo.rpc.Exporter<?>> getExporterMap();
    Code:
       0: aload_0
       1: getfield      #9                  // Field exporterMap:Ljava/util/Map;
       4: areturn

  public java.util.Collection<org.apache.dubbo.rpc.Exporter<?>> getExporters();
    Code:
       0: aload_0
       1: getfield      #9                  // Field exporterMap:Ljava/util/Map;
       4: invokeinterface #63,  1           // InterfaceMethod java/util/Map.values:()Ljava/util/Collection;
       9: invokestatic  #64                 // Method java/util/Collections.unmodifiableCollection:(Ljava/util/Collection;)Ljava/util/Collection;
      12: areturn

  protected void optimizeSerialization(org.apache.dubbo.common.URL) throws org.apache.dubbo.rpc.RpcException;
    Code:
       0: aload_1
       1: ldc           #65                 // String optimizer
       3: ldc           #55                 // String
       5: invokevirtual #66                 // Method org/apache/dubbo/common/URL.getParameter:(Ljava/lang/String;Ljava/lang/String;)Ljava/lang/String;
       8: astore_2
       9: aload_2
      10: invokestatic  #67                 // Method org/apache/dubbo/common/utils/StringUtils.isEmpty:(Ljava/lang/String;)Z
      13: ifne          29
      16: aload_0
      17: getfield      #14                 // Field optimizers:Ljava/util/Set;
      20: aload_2
      21: invokeinterface #68,  2           // InterfaceMethod java/util/Set.contains:(Ljava/lang/Object;)Z
      26: ifeq          30
      29: return
      30: aload_0
      31: getfield      #6                  // Field logger:Lorg/apache/dubbo/common/logger/ErrorTypeAwareLogger;
      34: ldc           #69                 // String Optimizing the serialization process for Kryo, FST, etc...
      36: invokeinterface #51,  2           // InterfaceMethod org/apache/dubbo/common/logger/ErrorTypeAwareLogger.info:(Ljava/lang/String;)V
      41: invokestatic  #70                 // Method java/lang/Thread.currentThread:()Ljava/lang/Thread;
      44: invokevirtual #71                 // Method java/lang/Thread.getContextClassLoader:()Ljava/lang/ClassLoader;
      47: aload_2
      48: invokevirtual #72                 // Method java/lang/ClassLoader.loadClass:(Ljava/lang/String;)Ljava/lang/Class;
      51: astore_3
      52: ldc           #73                 // class org/apache/dubbo/common/serialize/support/SerializationOptimizer
      54: aload_3
      55: invokevirtual #74                 // Method java/lang/Class.isAssignableFrom:(Ljava/lang/Class;)Z
      58: ifne          101
      61: new           #75                 // class org/apache/dubbo/rpc/RpcException
      64: dup
      65: new           #44                 // class java/lang/StringBuilder
      68: dup
      69: invokespecial #45                 // Method java/lang/StringBuilder."<init>":()V
      72: ldc           #76                 // String The serialization optimizer
      74: invokevirtual #47                 // Method java/lang/StringBuilder.append:(Ljava/lang/String;)Ljava/lang/StringBuilder;
      77: aload_2
      78: invokevirtual #47                 // Method java/lang/StringBuilder.append:(Ljava/lang/String;)Ljava/lang/StringBuilder;
      81: ldc           #77                 // String  isn\'t an instance of
      83: invokevirtual #47                 // Method java/lang/StringBuilder.append:(Ljava/lang/String;)Ljava/lang/StringBuilder;
      86: ldc           #73                 // class org/apache/dubbo/common/serialize/support/SerializationOptimizer
      88: invokevirtual #78                 // Method java/lang/Class.getName:()Ljava/lang/String;
      91: invokevirtual #47                 // Method java/lang/StringBuilder.append:(Ljava/lang/String;)Ljava/lang/StringBuilder;
      94: invokevirtual #50                 // Method java/lang/StringBuilder.toString:()Ljava/lang/String;
      97: invokespecial #79                 // Method org/apache/dubbo/rpc/RpcException."<init>":(Ljava/lang/String;)V
     100: athrow
     101: aload_3
     102: invokevirtual #80                 // Method java/lang/Class.newInstance:()Ljava/lang/Object;
     105: checkcast     #73                 // class org/apache/dubbo/common/serialize/support/SerializationOptimizer
     108: astore        4
     110: aload         4
     112: invokeinterface #81,  1           // InterfaceMethod org/apache/dubbo/common/serialize/support/SerializationOptimizer.getSerializableClasses:()Ljava/util/Collection;
     117: ifnonnull     121
     120: return
     121: aload         4
     123: invokeinterface #81,  1           // InterfaceMethod org/apache/dubbo/common/serialize/support/SerializationOptimizer.getSerializableClasses:()Ljava/util/Collection;
     128: invokeinterface #82,  1           // InterfaceMethod java/util/Collection.iterator:()Ljava/util/Iterator;
     133: astore        5
     135: aload         5
     137: invokeinterface #40,  1           // InterfaceMethod java/util/Iterator.hasNext:()Z
     142: ifeq          165
     145: aload         5
     147: invokeinterface #41,  1           // InterfaceMethod java/util/Iterator.next:()Ljava/lang/Object;
     152: checkcast     #83                 // class java/lang/Class
     155: astore        6
     157: aload         6
     159: invokestatic  #84                 // Method org/apache/dubbo/common/serialize/support/SerializableClassRegistry.registerClass:(Ljava/lang/Class;)V
     162: goto          135
     165: aload_0
     166: getfield      #14                 // Field optimizers:Ljava/util/Set;
     169: aload_2
     170: invokeinterface #85,  2           // InterfaceMethod java/util/Set.add:(Ljava/lang/Object;)Z
     175: pop
     176: goto          237
     179: astore_3
     180: new           #75                 // class org/apache/dubbo/rpc/RpcException
     183: dup
     184: new           #44                 // class java/lang/StringBuilder
     187: dup
     188: invokespecial #45                 // Method java/lang/StringBuilder."<init>":()V
     191: ldc           #87                 // String Cannot find the serialization optimizer class:
     193: invokevirtual #47                 // Method java/lang/StringBuilder.append:(Ljava/lang/String;)Ljava/lang/StringBuilder;
     196: aload_2
     197: invokevirtual #47                 // Method java/lang/StringBuilder.append:(Ljava/lang/String;)Ljava/lang/StringBuilder;
     200: invokevirtual #50                 // Method java/lang/StringBuilder.toString:()Ljava/lang/String;
     203: aload_3
     204: invokespecial #88                 // Method org/apache/dubbo/rpc/RpcException."<init>":(Ljava/lang/String;Ljava/lang/Throwable;)V
     207: athrow
     208: astore_3
     209: new           #75                 // class org/apache/dubbo/rpc/RpcException
     212: dup
     213: new           #44                 // class java/lang/StringBuilder
     216: dup
     217: invokespecial #45                 // Method java/lang/StringBuilder."<init>":()V
     220: ldc           #91                 // String Cannot instantiate the serialization optimizer class:
     222: invokevirtual #47                 // Method java/lang/StringBuilder.append:(Ljava/lang/String;)Ljava/lang/StringBuilder;
     225: aload_2
     226: invokevirtual #47                 // Method java/lang/StringBuilder.append:(Ljava/lang/String;)Ljava/lang/StringBuilder;
     229: invokevirtual #50                 // Method java/lang/StringBuilder.toString:()Ljava/lang/String;
     232: aload_3
     233: invokespecial #88                 // Method org/apache/dubbo/rpc/RpcException."<init>":(Ljava/lang/String;Ljava/lang/Throwable;)V
     236: athrow
     237: return
    Exception table:
       from    to  target type
          41   120   179   Class java/lang/ClassNotFoundException
         121   176   179   Class java/lang/ClassNotFoundException
          41   120   208   Class java/lang/InstantiationException
          41   120   208   Class java/lang/IllegalAccessException
         121   176   208   Class java/lang/InstantiationException
         121   176   208   Class java/lang/IllegalAccessException

  protected java.lang.String getAddr(org.apache.dubbo.common.URL);
    Code:
       0: aload_1
       1: ldc           #92                 // String bind.ip
       3: aload_1
       4: invokevirtual #93                 // Method org/apache/dubbo/common/URL.getHost:()Ljava/lang/String;
       7: invokevirtual #66                 // Method org/apache/dubbo/common/URL.getParameter:(Ljava/lang/String;Ljava/lang/String;)Ljava/lang/String;
      10: astore_2
      11: aload_1
      12: ldc           #94                 // String anyhost
      14: iconst_0
      15: invokevirtual #95                 // Method org/apache/dubbo/common/URL.getParameter:(Ljava/lang/String;Z)Z
      18: ifeq          24
      21: ldc           #96                 // String 0.0.0.0
      23: astore_2
      24: new           #44                 // class java/lang/StringBuilder
      27: dup
      28: invokespecial #45                 // Method java/lang/StringBuilder."<init>":()V
      31: aload_2
      32: invokestatic  #97                 // Method org/apache/dubbo/common/utils/NetUtils.getIpByHost:(Ljava/lang/String;)Ljava/lang/String;
      35: invokevirtual #47                 // Method java/lang/StringBuilder.append:(Ljava/lang/String;)Ljava/lang/StringBuilder;
      38: ldc           #98                 // String :
      40: invokevirtual #47                 // Method java/lang/StringBuilder.append:(Ljava/lang/String;)Ljava/lang/StringBuilder;
      43: aload_1
      44: ldc           #17                 // String bind.port
      46: aload_1
      47: invokevirtual #18                 // Method org/apache/dubbo/common/URL.getPort:()I
      50: invokevirtual #19                 // Method org/apache/dubbo/common/URL.getParameter:(Ljava/lang/String;I)I
      53: invokevirtual #99                 // Method java/lang/StringBuilder.append:(I)Ljava/lang/StringBuilder;
      56: invokevirtual #50                 // Method java/lang/StringBuilder.toString:()Ljava/lang/String;
      59: areturn

  private void lambda$destroy$0(java.lang.String, org.apache.dubbo.rpc.Exporter);
    Code:
       0: aload_2
       1: ifnull        84
       4: aload_0
       5: getfield      #6                  // Field logger:Lorg/apache/dubbo/common/logger/ErrorTypeAwareLogger;
       8: invokeinterface #43,  1           // InterfaceMethod org/apache/dubbo/common/logger/ErrorTypeAwareLogger.isInfoEnabled:()Z
      13: ifeq          54
      16: aload_0
      17: getfield      #6                  // Field logger:Lorg/apache/dubbo/common/logger/ErrorTypeAwareLogger;
      20: new           #44                 // class java/lang/StringBuilder
      23: dup
      24: invokespecial #45                 // Method java/lang/StringBuilder."<init>":()V
      27: ldc           #100                // String Unexport service:
      29: invokevirtual #47                 // Method java/lang/StringBuilder.append:(Ljava/lang/String;)Ljava/lang/StringBuilder;
      32: aload_2
      33: invokeinterface #101,  1          // InterfaceMethod org/apache/dubbo/rpc/Exporter.getInvoker:()Lorg/apache/dubbo/rpc/Invoker;
      38: invokeinterface #48,  1           // InterfaceMethod org/apache/dubbo/rpc/Invoker.getUrl:()Lorg/apache/dubbo/common/URL;
      43: invokevirtual #49                 // Method java/lang/StringBuilder.append:(Ljava/lang/Object;)Ljava/lang/StringBuilder;
      46: invokevirtual #50                 // Method java/lang/StringBuilder.toString:()Ljava/lang/String;
      49: invokeinterface #51,  2           // InterfaceMethod org/apache/dubbo/common/logger/ErrorTypeAwareLogger.info:(Ljava/lang/String;)V
      54: aload_2
      55: invokeinterface #102,  1          // InterfaceMethod org/apache/dubbo/rpc/Exporter.unexport:()V
      60: goto          84
      63: astore_3
      64: aload_0
      65: getfield      #6                  // Field logger:Lorg/apache/dubbo/common/logger/ErrorTypeAwareLogger;
      68: ldc           #54                 // String 4-17
      70: ldc           #55                 // String
      72: ldc           #55                 // String
      74: aload_3
      75: invokevirtual #56                 // Method java/lang/Throwable.getMessage:()Ljava/lang/String;
      78: aload_3
      79: invokeinterface #57,  6           // InterfaceMethod org/apache/dubbo/common/logger/ErrorTypeAwareLogger.warn:(Ljava/lang/String;Ljava/lang/String;Ljava/lang/String;Ljava/lang/String;Ljava/lang/Throwable;)V
      84: return
    Exception table:
       from    to  target type
           4    60    63   Class java/lang/Throwable
}
