Compiled from "AbstractProxyProtocol.java"
public abstract class org.apache.dubbo.rpc.protocol.AbstractProxyProtocol extends org.apache.dubbo.rpc.protocol.AbstractProtocol {
  protected final java.util.List<java.lang.Class<?>> rpcExceptions;

  protected org.apache.dubbo.rpc.ProxyFactory proxyFactory;

  public org.apache.dubbo.rpc.protocol.AbstractProxyProtocol();
    Code:
       0: aload_0
       1: invokespecial #1                  // Method org/apache/dubbo/rpc/protocol/AbstractProtocol."<init>":()V
       4: aload_0
       5: new           #2                  // class java/util/concurrent/CopyOnWriteArrayList
       8: dup
       9: invokespecial #3                  // Method java/util/concurrent/CopyOnWriteArrayList."<init>":()V
      12: putfield      #4                  // Field rpcExceptions:Ljava/util/List;
      15: return

  public org.apache.dubbo.rpc.protocol.AbstractProxyProtocol(java.lang.Class<?>...);
    Code:
       0: aload_0
       1: invokespecial #1                  // Method org/apache/dubbo/rpc/protocol/AbstractProtocol."<init>":()V
       4: aload_0
       5: new           #2                  // class java/util/concurrent/CopyOnWriteArrayList
       8: dup
       9: invokespecial #3                  // Method java/util/concurrent/CopyOnWriteArrayList."<init>":()V
      12: putfield      #4                  // Field rpcExceptions:Ljava/util/List;
      15: aload_1
      16: astore_2
      17: aload_2
      18: arraylength
      19: istore_3
      20: iconst_0
      21: istore        4
      23: iload         4
      25: iload_3
      26: if_icmpge     47
      29: aload_2
      30: iload         4
      32: aaload
      33: astore        5
      35: aload_0
      36: aload         5
      38: invokevirtual #5                  // Method addRpcException:(Ljava/lang/Class;)V
      41: iinc          4, 1
      44: goto          23
      47: return

  public void addRpcException(java.lang.Class<?>);
    Code:
       0: aload_0
       1: getfield      #4                  // Field rpcExceptions:Ljava/util/List;
       4: aload_1
       5: invokeinterface #6,  2            // InterfaceMethod java/util/List.add:(Ljava/lang/Object;)Z
      10: pop
      11: return

  public org.apache.dubbo.rpc.ProxyFactory getProxyFactory();
    Code:
       0: aload_0
       1: getfield      #7                  // Field proxyFactory:Lorg/apache/dubbo/rpc/ProxyFactory;
       4: areturn

  public void setProxyFactory(org.apache.dubbo.rpc.ProxyFactory);
    Code:
       0: aload_0
       1: aload_1
       2: putfield      #7                  // Field proxyFactory:Lorg/apache/dubbo/rpc/ProxyFactory;
       5: return

  public <T> org.apache.dubbo.rpc.Exporter<T> export(org.apache.dubbo.rpc.Invoker<T>) throws org.apache.dubbo.rpc.RpcException;
    Code:
       0: aload_1
       1: invokeinterface #8,  1            // InterfaceMethod org/apache/dubbo/rpc/Invoker.getUrl:()Lorg/apache/dubbo/common/URL;
       6: invokestatic  #9                  // Method serviceKey:(Lorg/apache/dubbo/common/URL;)Ljava/lang/String;
       9: astore_2
      10: aload_0
      11: getfield      #10                 // Field exporterMap:Ljava/util/Map;
      14: aload_2
      15: invokeinterface #11,  2           // InterfaceMethod java/util/Map.get:(Ljava/lang/Object;)Ljava/lang/Object;
      20: checkcast     #12                 // class org/apache/dubbo/rpc/Exporter
      23: astore_3
      24: aload_3
      25: ifnull        53
      28: aload_3
      29: invokeinterface #13,  1           // InterfaceMethod org/apache/dubbo/rpc/Exporter.getInvoker:()Lorg/apache/dubbo/rpc/Invoker;
      34: invokeinterface #8,  1            // InterfaceMethod org/apache/dubbo/rpc/Invoker.getUrl:()Lorg/apache/dubbo/common/URL;
      39: aload_1
      40: invokeinterface #8,  1            // InterfaceMethod org/apache/dubbo/rpc/Invoker.getUrl:()Lorg/apache/dubbo/common/URL;
      45: invokestatic  #14                 // Method java/util/Objects.equals:(Ljava/lang/Object;Ljava/lang/Object;)Z
      48: ifeq          53
      51: aload_3
      52: areturn
      53: aload_0
      54: aload_0
      55: getfield      #7                  // Field proxyFactory:Lorg/apache/dubbo/rpc/ProxyFactory;
      58: new           #15                 // class org/apache/dubbo/rpc/protocol/AbstractProxyProtocol$1
      61: dup
      62: aload_0
      63: aload_1
      64: invokespecial #16                 // Method org/apache/dubbo/rpc/protocol/AbstractProxyProtocol$1."<init>":(Lorg/apache/dubbo/rpc/protocol/AbstractProxyProtocol;Lorg/apache/dubbo/rpc/Invoker;)V
      67: iconst_1
      68: invokeinterface #17,  3           // InterfaceMethod org/apache/dubbo/rpc/ProxyFactory.getProxy:(Lorg/apache/dubbo/rpc/Invoker;Z)Ljava/lang/Object;
      73: aload_1
      74: invokeinterface #18,  1           // InterfaceMethod org/apache/dubbo/rpc/Invoker.getInterface:()Ljava/lang/Class;
      79: aload_1
      80: invokeinterface #8,  1            // InterfaceMethod org/apache/dubbo/rpc/Invoker.getUrl:()Lorg/apache/dubbo/common/URL;
      85: invokevirtual #19                 // Method doExport:(Ljava/lang/Object;Ljava/lang/Class;Lorg/apache/dubbo/common/URL;)Ljava/lang/Runnable;
      88: astore        4
      90: new           #20                 // class org/apache/dubbo/rpc/protocol/AbstractProxyProtocol$2
      93: dup
      94: aload_0
      95: aload_1
      96: aload_2
      97: aload         4
      99: invokespecial #21                 // Method org/apache/dubbo/rpc/protocol/AbstractProxyProtocol$2."<init>":(Lorg/apache/dubbo/rpc/protocol/AbstractProxyProtocol;Lorg/apache/dubbo/rpc/Invoker;Ljava/lang/String;Ljava/lang/Runnable;)V
     102: astore_3
     103: aload_0
     104: getfield      #10                 // Field exporterMap:Ljava/util/Map;
     107: aload_2
     108: aload_3
     109: invokeinterface #22,  3           // InterfaceMethod java/util/Map.put:(Ljava/lang/Object;Ljava/lang/Object;)Ljava/lang/Object;
     114: pop
     115: aload_3
     116: areturn

  protected void destroyInternal(org.apache.dubbo.common.URL);
    Code:
       0: return

  protected org.apache.dubbo.rpc.RpcException getRpcException(java.lang.Class<?>, org.apache.dubbo.common.URL, org.apache.dubbo.rpc.Invocation, java.lang.Throwable);
    Code:
       0: new           #23                 // class org/apache/dubbo/rpc/RpcException
       3: dup
       4: new           #24                 // class java/lang/StringBuilder
       7: dup
       8: invokespecial #25                 // Method java/lang/StringBuilder."<init>":()V
      11: ldc           #26                 // String Failed to invoke remote service:
      13: invokevirtual #27                 // Method java/lang/StringBuilder.append:(Ljava/lang/String;)Ljava/lang/StringBuilder;
      16: aload_1
      17: invokevirtual #28                 // Method java/lang/StringBuilder.append:(Ljava/lang/Object;)Ljava/lang/StringBuilder;
      20: ldc           #29                 // String , method:
      22: invokevirtual #27                 // Method java/lang/StringBuilder.append:(Ljava/lang/String;)Ljava/lang/StringBuilder;
      25: aload_3
      26: invokeinterface #30,  1           // InterfaceMethod org/apache/dubbo/rpc/Invocation.getMethodName:()Ljava/lang/String;
      31: invokevirtual #27                 // Method java/lang/StringBuilder.append:(Ljava/lang/String;)Ljava/lang/StringBuilder;
      34: ldc           #31                 // String , cause:
      36: invokevirtual #27                 // Method java/lang/StringBuilder.append:(Ljava/lang/String;)Ljava/lang/StringBuilder;
      39: aload         4
      41: invokevirtual #32                 // Method java/lang/Throwable.getMessage:()Ljava/lang/String;
      44: invokevirtual #27                 // Method java/lang/StringBuilder.append:(Ljava/lang/String;)Ljava/lang/StringBuilder;
      47: invokevirtual #33                 // Method java/lang/StringBuilder.toString:()Ljava/lang/String;
      50: aload         4
      52: invokespecial #34                 // Method org/apache/dubbo/rpc/RpcException."<init>":(Ljava/lang/String;Ljava/lang/Throwable;)V
      55: astore        5
      57: aload         5
      59: aload_0
      60: aload         4
      62: invokevirtual #35                 // Method getErrorCode:(Ljava/lang/Throwable;)I
      65: invokevirtual #36                 // Method org/apache/dubbo/rpc/RpcException.setCode:(I)V
      68: aload         5
      70: areturn

  protected int getErrorCode(java.lang.Throwable);
    Code:
       0: iconst_0
       1: ireturn

  protected abstract <T> java.lang.Runnable doExport(T, java.lang.Class<T>, org.apache.dubbo.common.URL) throws org.apache.dubbo.rpc.RpcException;
}
