Compiled from "InvokerCountWrapper.java"
public class org.apache.dubbo.rpc.protocol.InvokerCountWrapper implements org.apache.dubbo.rpc.Protocol {
  private final org.apache.dubbo.rpc.Protocol protocol;

  public org.apache.dubbo.rpc.protocol.InvokerCountWrapper(org.apache.dubbo.rpc.Protocol);
    Code:
       0: aload_0
       1: invokespecial #1                  // Method java/lang/Object."<init>":()V
       4: aload_0
       5: aload_1
       6: putfield      #2                  // Field protocol:Lorg/apache/dubbo/rpc/Protocol;
       9: return

  public int getDefaultPort();
    Code:
       0: aload_0
       1: getfield      #2                  // Field protocol:Lorg/apache/dubbo/rpc/Protocol;
       4: invokeinterface #3,  1            // InterfaceMethod org/apache/dubbo/rpc/Protocol.getDefaultPort:()I
       9: ireturn

  public <T> org.apache.dubbo.rpc.Exporter<T> export(org.apache.dubbo.rpc.Invoker<T>) throws org.apache.dubbo.rpc.RpcException;
    Code:
       0: aload_0
       1: getfield      #2                  // Field protocol:Lorg/apache/dubbo/rpc/Protocol;
       4: aload_1
       5: invokeinterface #4,  2            // InterfaceMethod org/apache/dubbo/rpc/Protocol.export:(Lorg/apache/dubbo/rpc/Invoker;)Lorg/apache/dubbo/rpc/Exporter;
      10: areturn

  public <T> org.apache.dubbo.rpc.Invoker<T> refer(java.lang.Class<T>, org.apache.dubbo.common.URL) throws org.apache.dubbo.rpc.RpcException;
    Code:
       0: aload_2
       1: invokestatic  #5                  // Method org/apache/dubbo/common/utils/UrlUtils.isRegistry:(Lorg/apache/dubbo/common/URL;)Z
       4: ifeq          19
       7: aload_0
       8: getfield      #2                  // Field protocol:Lorg/apache/dubbo/rpc/Protocol;
      11: aload_1
      12: aload_2
      13: invokeinterface #6,  3            // InterfaceMethod org/apache/dubbo/rpc/Protocol.refer:(Ljava/lang/Class;Lorg/apache/dubbo/common/URL;)Lorg/apache/dubbo/rpc/Invoker;
      18: areturn
      19: new           #7                  // class org/apache/dubbo/rpc/protocol/ReferenceCountInvokerWrapper
      22: dup
      23: aload_0
      24: getfield      #2                  // Field protocol:Lorg/apache/dubbo/rpc/Protocol;
      27: aload_1
      28: aload_2
      29: invokeinterface #6,  3            // InterfaceMethod org/apache/dubbo/rpc/Protocol.refer:(Ljava/lang/Class;Lorg/apache/dubbo/common/URL;)Lorg/apache/dubbo/rpc/Invoker;
      34: invokespecial #8                  // Method org/apache/dubbo/rpc/protocol/ReferenceCountInvokerWrapper."<init>":(Lorg/apache/dubbo/rpc/Invoker;)V
      37: areturn

  public void destroy();
    Code:
       0: aload_0
       1: getfield      #2                  // Field protocol:Lorg/apache/dubbo/rpc/Protocol;
       4: invokeinterface #9,  1            // InterfaceMethod org/apache/dubbo/rpc/Protocol.destroy:()V
       9: return
}
