Compiled from "PermittedSerializationKeeper.java"
public class org.apache.dubbo.rpc.protocol.PermittedSerializationKeeper {
  private final java.util.concurrent.ConcurrentMap<java.lang.String, java.util.Set<java.lang.Byte>> serviceToSerializationId;

  private final java.util.Set<java.lang.Byte> globalPermittedSerializationIds;

  public org.apache.dubbo.rpc.protocol.PermittedSerializationKeeper();
    Code:
       0: aload_0
       1: invokespecial #1                  // Method java/lang/Object."<init>":()V
       4: aload_0
       5: new           #2                  // class java/util/concurrent/ConcurrentHashMap
       8: dup
       9: invokespecial #3                  // Method java/util/concurrent/ConcurrentHashMap."<init>":()V
      12: putfield      #4                  // Field serviceToSerializationId:Ljava/util/concurrent/ConcurrentMap;
      15: aload_0
      16: new           #5                  // class org/apache/dubbo/common/utils/ConcurrentHashSet
      19: dup
      20: invokespecial #6                  // Method org/apache/dubbo/common/utils/ConcurrentHashSet."<init>":()V
      23: putfield      #7                  // Field globalPermittedSerializationIds:Ljava/util/Set;
      26: return

  public void registerService(org.apache.dubbo.common.URL);
    Code:
       0: aload_0
       1: getfield      #4                  // Field serviceToSerializationId:Ljava/util/concurrent/ConcurrentMap;
       4: aload_1
       5: invokevirtual #8                  // Method org/apache/dubbo/common/URL.getServiceKey:()Ljava/lang/String;
       8: invokestatic  #9                  // Method keyWithoutGroup:(Ljava/lang/String;)Ljava/lang/String;
      11: invokedynamic #10,  0             // InvokeDynamic #0:apply:()Ljava/util/function/Function;
      16: invokestatic  #11                 // Method org/apache/dubbo/common/utils/ConcurrentHashMapUtils.computeIfAbsent:(Ljava/util/concurrent/ConcurrentMap;Ljava/lang/Object;Ljava/util/function/Function;)Ljava/lang/Object;
      19: checkcast     #12                 // class java/util/Set
      22: astore_2
      23: aload_1
      24: invokestatic  #13                 // Method org/apache/dubbo/remoting/utils/UrlUtils.allSerializations:(Lorg/apache/dubbo/common/URL;)Ljava/util/Collection;
      27: astore_3
      28: aload_3
      29: invokeinterface #14,  1           // InterfaceMethod java/util/Collection.iterator:()Ljava/util/Iterator;
      34: astore        4
      36: aload         4
      38: invokeinterface #15,  1           // InterfaceMethod java/util/Iterator.hasNext:()Z
      43: ifeq          94
      46: aload         4
      48: invokeinterface #16,  1           // InterfaceMethod java/util/Iterator.next:()Ljava/lang/Object;
      53: checkcast     #17                 // class java/lang/String
      56: astore        5
      58: aload         5
      60: invokestatic  #18                 // Method org/apache/dubbo/remoting/transport/CodecSupport.getIDByName:(Ljava/lang/String;)Ljava/lang/Byte;
      63: astore        6
      65: aload         6
      67: ifnull        91
      70: aload_2
      71: aload         6
      73: invokeinterface #19,  2           // InterfaceMethod java/util/Set.add:(Ljava/lang/Object;)Z
      78: pop
      79: aload_0
      80: getfield      #7                  // Field globalPermittedSerializationIds:Ljava/util/Set;
      83: aload         6
      85: invokeinterface #19,  2           // InterfaceMethod java/util/Set.add:(Ljava/lang/Object;)Z
      90: pop
      91: goto          36
      94: return

  public boolean checkSerializationPermitted(java.lang.String, java.lang.Byte) throws java.io.IOException;
    Code:
       0: aload_0
       1: getfield      #4                  // Field serviceToSerializationId:Ljava/util/concurrent/ConcurrentMap;
       4: aload_1
       5: invokeinterface #20,  2           // InterfaceMethod java/util/concurrent/ConcurrentMap.get:(Ljava/lang/Object;)Ljava/lang/Object;
      10: checkcast     #12                 // class java/util/Set
      13: astore_3
      14: aload_3
      15: ifnonnull     50
      18: new           #21                 // class java/io/IOException
      21: dup
      22: new           #22                 // class java/lang/StringBuilder
      25: dup
      26: invokespecial #23                 // Method java/lang/StringBuilder."<init>":()V
      29: ldc           #24                 // String Service
      31: invokevirtual #25                 // Method java/lang/StringBuilder.append:(Ljava/lang/String;)Ljava/lang/StringBuilder;
      34: aload_1
      35: invokevirtual #25                 // Method java/lang/StringBuilder.append:(Ljava/lang/String;)Ljava/lang/StringBuilder;
      38: ldc           #26                 // String  not found, invocation rejected.
      40: invokevirtual #25                 // Method java/lang/StringBuilder.append:(Ljava/lang/String;)Ljava/lang/StringBuilder;
      43: invokevirtual #27                 // Method java/lang/StringBuilder.toString:()Ljava/lang/String;
      46: invokespecial #28                 // Method java/io/IOException."<init>":(Ljava/lang/String;)V
      49: athrow
      50: aload_3
      51: aload_2
      52: invokeinterface #29,  2           // InterfaceMethod java/util/Set.contains:(Ljava/lang/Object;)Z
      57: ireturn

  private static java.lang.String keyWithoutGroup(java.lang.String);
    Code:
       0: aload_0
       1: invokestatic  #30                 // Method org/apache/dubbo/common/BaseServiceMetadata.interfaceFromServiceKey:(Ljava/lang/String;)Ljava/lang/String;
       4: astore_1
       5: aload_0
       6: invokestatic  #31                 // Method org/apache/dubbo/common/BaseServiceMetadata.versionFromServiceKey:(Ljava/lang/String;)Ljava/lang/String;
       9: astore_2
      10: aload_2
      11: invokestatic  #32                 // Method org/apache/dubbo/common/utils/StringUtils.isEmpty:(Ljava/lang/String;)Z
      14: ifeq          19
      17: aload_1
      18: areturn
      19: new           #22                 // class java/lang/StringBuilder
      22: dup
      23: invokespecial #23                 // Method java/lang/StringBuilder."<init>":()V
      26: aload_1
      27: invokevirtual #25                 // Method java/lang/StringBuilder.append:(Ljava/lang/String;)Ljava/lang/StringBuilder;
      30: ldc           #34                 // String :
      32: invokevirtual #25                 // Method java/lang/StringBuilder.append:(Ljava/lang/String;)Ljava/lang/StringBuilder;
      35: aload_2
      36: invokevirtual #25                 // Method java/lang/StringBuilder.append:(Ljava/lang/String;)Ljava/lang/StringBuilder;
      39: invokevirtual #27                 // Method java/lang/StringBuilder.toString:()Ljava/lang/String;
      42: areturn

  private static java.util.Set lambda$registerService$0(java.lang.String);
    Code:
       0: new           #5                  // class org/apache/dubbo/common/utils/ConcurrentHashSet
       3: dup
       4: invokespecial #6                  // Method org/apache/dubbo/common/utils/ConcurrentHashSet."<init>":()V
       7: areturn
}
