Compiled from "ProtocolListenerWrapper.java"
public class org.apache.dubbo.rpc.protocol.ProtocolListenerWrapper implements org.apache.dubbo.rpc.Protocol {
  private final org.apache.dubbo.rpc.Protocol protocol;

  public org.apache.dubbo.rpc.protocol.ProtocolListenerWrapper(org.apache.dubbo.rpc.Protocol);
    Code:
       0: aload_0
       1: invokespecial #4                  // Method java/lang/Object."<init>":()V
       4: aload_1
       5: ifnonnull     18
       8: new           #5                  // class java/lang/IllegalArgumentException
      11: dup
      12: ldc           #6                  // String protocol == null
      14: invokespecial #7                  // Method java/lang/IllegalArgumentException."<init>":(Ljava/lang/String;)V
      17: athrow
      18: aload_0
      19: aload_1
      20: putfield      #8                  // Field protocol:Lorg/apache/dubbo/rpc/Protocol;
      23: return

  public int getDefaultPort();
    Code:
       0: aload_0
       1: getfield      #8                  // Field protocol:Lorg/apache/dubbo/rpc/Protocol;
       4: invokeinterface #9,  1            // InterfaceMethod org/apache/dubbo/rpc/Protocol.getDefaultPort:()I
       9: ireturn

  public <T> org.apache.dubbo.rpc.Exporter<T> export(org.apache.dubbo.rpc.Invoker<T>) throws org.apache.dubbo.rpc.RpcException;
    Code:
       0: aload_1
       1: invokeinterface #10,  1           // InterfaceMethod org/apache/dubbo/rpc/Invoker.getUrl:()Lorg/apache/dubbo/common/URL;
       6: invokestatic  #11                 // Method org/apache/dubbo/common/utils/UrlUtils.isRegistry:(Lorg/apache/dubbo/common/URL;)Z
       9: ifeq          23
      12: aload_0
      13: getfield      #8                  // Field protocol:Lorg/apache/dubbo/rpc/Protocol;
      16: aload_1
      17: invokeinterface #12,  2           // InterfaceMethod org/apache/dubbo/rpc/Protocol.export:(Lorg/apache/dubbo/rpc/Invoker;)Lorg/apache/dubbo/rpc/Exporter;
      22: areturn
      23: ldc           #13                 // class org/apache/dubbo/rpc/ExporterListener
      25: aload_1
      26: invokeinterface #10,  1           // InterfaceMethod org/apache/dubbo/rpc/Invoker.getUrl:()Lorg/apache/dubbo/common/URL;
      31: invokevirtual #14                 // Method org/apache/dubbo/common/URL.getScopeModel:()Lorg/apache/dubbo/rpc/model/ScopeModel;
      34: invokestatic  #15                 // Method org/apache/dubbo/rpc/model/ScopeModelUtil.getExtensionLoader:(Ljava/lang/Class;Lorg/apache/dubbo/rpc/model/ScopeModel;)Lorg/apache/dubbo/common/extension/ExtensionLoader;
      37: aload_1
      38: invokeinterface #10,  1           // InterfaceMethod org/apache/dubbo/rpc/Invoker.getUrl:()Lorg/apache/dubbo/common/URL;
      43: ldc           #16                 // String exporter.listener
      45: invokevirtual #17                 // Method org/apache/dubbo/common/extension/ExtensionLoader.getActivateExtension:(Lorg/apache/dubbo/common/URL;Ljava/lang/String;)Ljava/util/List;
      48: astore_2
      49: ldc           #18                 // String injvm
      51: aload_1
      52: invokeinterface #10,  1           // InterfaceMethod org/apache/dubbo/rpc/Invoker.getUrl:()Lorg/apache/dubbo/common/URL;
      57: invokevirtual #19                 // Method org/apache/dubbo/common/URL.getProtocol:()Ljava/lang/String;
      60: invokevirtual #20                 // Method java/lang/String.equals:(Ljava/lang/Object;)Z
      63: ifeq          90
      66: aload_2
      67: aload_1
      68: invokeinterface #10,  1           // InterfaceMethod org/apache/dubbo/rpc/Invoker.getUrl:()Lorg/apache/dubbo/common/URL;
      73: invokevirtual #21                 // Method org/apache/dubbo/common/URL.getOrDefaultFrameworkModel:()Lorg/apache/dubbo/rpc/model/FrameworkModel;
      76: invokevirtual #22                 // Method org/apache/dubbo/rpc/model/FrameworkModel.getBeanFactory:()Lorg/apache/dubbo/common/beans/factory/ScopeBeanFactory;
      79: ldc           #23                 // class org/apache/dubbo/rpc/listener/InjvmExporterListener
      81: invokevirtual #24                 // Method org/apache/dubbo/common/beans/factory/ScopeBeanFactory.getBean:(Ljava/lang/Class;)Ljava/lang/Object;
      84: invokeinterface #25,  2           // InterfaceMethod java/util/List.add:(Ljava/lang/Object;)Z
      89: pop
      90: new           #26                 // class org/apache/dubbo/rpc/listener/ListenerExporterWrapper
      93: dup
      94: aload_0
      95: getfield      #8                  // Field protocol:Lorg/apache/dubbo/rpc/Protocol;
      98: aload_1
      99: invokeinterface #12,  2           // InterfaceMethod org/apache/dubbo/rpc/Protocol.export:(Lorg/apache/dubbo/rpc/Invoker;)Lorg/apache/dubbo/rpc/Exporter;
     104: aload_2
     105: invokestatic  #27                 // Method java/util/Collections.unmodifiableList:(Ljava/util/List;)Ljava/util/List;
     108: invokespecial #28                 // Method org/apache/dubbo/rpc/listener/ListenerExporterWrapper."<init>":(Lorg/apache/dubbo/rpc/Exporter;Ljava/util/List;)V
     111: areturn

  public <T> org.apache.dubbo.rpc.Invoker<T> refer(java.lang.Class<T>, org.apache.dubbo.common.URL) throws org.apache.dubbo.rpc.RpcException;
    Code:
       0: aload_2
       1: invokestatic  #11                 // Method org/apache/dubbo/common/utils/UrlUtils.isRegistry:(Lorg/apache/dubbo/common/URL;)Z
       4: ifeq          19
       7: aload_0
       8: getfield      #8                  // Field protocol:Lorg/apache/dubbo/rpc/Protocol;
      11: aload_1
      12: aload_2
      13: invokeinterface #29,  3           // InterfaceMethod org/apache/dubbo/rpc/Protocol.refer:(Ljava/lang/Class;Lorg/apache/dubbo/common/URL;)Lorg/apache/dubbo/rpc/Invoker;
      18: areturn
      19: aload_0
      20: getfield      #8                  // Field protocol:Lorg/apache/dubbo/rpc/Protocol;
      23: aload_1
      24: aload_2
      25: invokeinterface #29,  3           // InterfaceMethod org/apache/dubbo/rpc/Protocol.refer:(Ljava/lang/Class;Lorg/apache/dubbo/common/URL;)Lorg/apache/dubbo/rpc/Invoker;
      30: astore_3
      31: aload_2
      32: ldc           #30                 // String registry-cluster-type
      34: invokevirtual #31                 // Method org/apache/dubbo/common/URL.getParameter:(Ljava/lang/String;)Ljava/lang/String;
      37: invokestatic  #32                 // Method org/apache/dubbo/common/utils/StringUtils.isEmpty:(Ljava/lang/String;)Z
      40: ifeq          75
      43: new           #33                 // class org/apache/dubbo/rpc/listener/ListenerInvokerWrapper
      46: dup
      47: aload_3
      48: ldc           #34                 // class org/apache/dubbo/rpc/InvokerListener
      50: aload_3
      51: invokeinterface #10,  1           // InterfaceMethod org/apache/dubbo/rpc/Invoker.getUrl:()Lorg/apache/dubbo/common/URL;
      56: invokevirtual #14                 // Method org/apache/dubbo/common/URL.getScopeModel:()Lorg/apache/dubbo/rpc/model/ScopeModel;
      59: invokestatic  #15                 // Method org/apache/dubbo/rpc/model/ScopeModelUtil.getExtensionLoader:(Ljava/lang/Class;Lorg/apache/dubbo/rpc/model/ScopeModel;)Lorg/apache/dubbo/common/extension/ExtensionLoader;
      62: aload_2
      63: ldc           #35                 // String invoker.listener
      65: invokevirtual #17                 // Method org/apache/dubbo/common/extension/ExtensionLoader.getActivateExtension:(Lorg/apache/dubbo/common/URL;Ljava/lang/String;)Ljava/util/List;
      68: invokestatic  #27                 // Method java/util/Collections.unmodifiableList:(Ljava/util/List;)Ljava/util/List;
      71: invokespecial #36                 // Method org/apache/dubbo/rpc/listener/ListenerInvokerWrapper."<init>":(Lorg/apache/dubbo/rpc/Invoker;Ljava/util/List;)V
      74: astore_3
      75: aload_3
      76: areturn

  public void destroy();
    Code:
       0: aload_0
       1: getfield      #8                  // Field protocol:Lorg/apache/dubbo/rpc/Protocol;
       4: invokeinterface #37,  1           // InterfaceMethod org/apache/dubbo/rpc/Protocol.destroy:()V
       9: return

  public java.util.List<org.apache.dubbo.rpc.ProtocolServer> getServers();
    Code:
       0: aload_0
       1: getfield      #8                  // Field protocol:Lorg/apache/dubbo/rpc/Protocol;
       4: invokeinterface #38,  1           // InterfaceMethod org/apache/dubbo/rpc/Protocol.getServers:()Ljava/util/List;
       9: areturn
}
