Compiled from "ContextHolderParametersSelectedTransferFilter.java"
public class org.apache.dubbo.spring.security.filter.ContextHolderParametersSelectedTransferFilter implements org.apache.dubbo.rpc.cluster.filter.ClusterFilter {
  public org.apache.dubbo.spring.security.filter.ContextHolderParametersSelectedTransferFilter();
    Code:
       0: aload_0
       1: invokespecial #2                  // Method java/lang/Object."<init>":()V
       4: return

  public org.apache.dubbo.rpc.Result invoke(org.apache.dubbo.rpc.Invoker<?>, org.apache.dubbo.rpc.Invocation);
    Code:
       0: aload_0
       1: aload_2
       2: invokespecial #3                  // Method setSecurityContextIfExists:(Lorg/apache/dubbo/rpc/Invocation;)V
       5: aload_1
       6: aload_2
       7: invokeinterface #4,  2            // InterfaceMethod org/apache/dubbo/rpc/Invoker.invoke:(Lorg/apache/dubbo/rpc/Invocation;)Lorg/apache/dubbo/rpc/Result;
      12: areturn

  private void setSecurityContextIfExists(org.apache.dubbo.rpc.Invocation);
    Code:
       0: invokestatic  #5                  // Method org/apache/dubbo/rpc/RpcContext.getServerAttachment:()Lorg/apache/dubbo/rpc/RpcContextAttachment;
       3: invokevirtual #6                  // Method org/apache/dubbo/rpc/RpcContextAttachment.getObjectAttachments:()Ljava/util/Map;
       6: astore_2
       7: aload_2
       8: ldc           #7                  // String security_authentication_context
      10: invokeinterface #8,  2            // InterfaceMethod java/util/Map.get:(Ljava/lang/Object;)Ljava/lang/Object;
      15: astore_3
      16: aload_3
      17: invokestatic  #9                  // Method java/util/Objects.isNull:(Ljava/lang/Object;)Z
      20: ifeq          24
      23: return
      24: aload_1
      25: ldc           #7                  // String security_authentication_context
      27: aload_3
      28: invokeinterface #10,  3           // InterfaceMethod org/apache/dubbo/rpc/Invocation.setObjectAttachment:(Ljava/lang/String;Ljava/lang/Object;)V
      33: return
}
