Compiled from "ContextHolderAuthenticationResolverFilter.java"
public class org.apache.dubbo.spring.security.filter.ContextHolderAuthenticationResolverFilter implements org.apache.dubbo.rpc.Filter {
  private final org.apache.dubbo.spring.security.jackson.ObjectMapperCodec mapper;

  public org.apache.dubbo.spring.security.filter.ContextHolderAuthenticationResolverFilter(org.apache.dubbo.rpc.model.ApplicationModel);
    Code:
       0: aload_0
       1: invokespecial #1                  // Method java/lang/Object."<init>":()V
       4: aload_0
       5: aload_1
       6: invokevirtual #2                  // Method org/apache/dubbo/rpc/model/ApplicationModel.getBeanFactory:()Lorg/apache/dubbo/common/beans/factory/ScopeBeanFactory;
       9: ldc           #3                  // class org/apache/dubbo/spring/security/jackson/ObjectMapperCodec
      11: invokevirtual #4                  // Method org/apache/dubbo/common/beans/factory/ScopeBeanFactory.getBean:(Ljava/lang/Class;)Ljava/lang/Object;
      14: checkcast     #3                  // class org/apache/dubbo/spring/security/jackson/ObjectMapperCodec
      17: putfield      #5                  // Field mapper:Lorg/apache/dubbo/spring/security/jackson/ObjectMapperCodec;
      20: return

  public org.apache.dubbo.rpc.Result invoke(org.apache.dubbo.rpc.Invoker<?>, org.apache.dubbo.rpc.Invocation) throws org.apache.dubbo.rpc.RpcException;
    Code:
       0: aload_0
       1: aload_2
       2: invokespecial #6                  // Method getSecurityContext:(Lorg/apache/dubbo/rpc/Invocation;)V
       5: aload_1
       6: aload_2
       7: invokeinterface #7,  2            // InterfaceMethod org/apache/dubbo/rpc/Invoker.invoke:(Lorg/apache/dubbo/rpc/Invocation;)Lorg/apache/dubbo/rpc/Result;
      12: areturn

  private void getSecurityContext(org.apache.dubbo.rpc.Invocation);
    Code:
       0: aload_1
       1: ldc           #9                  // String security_authentication_context
       3: invokeinterface #10,  2           // InterfaceMethod org/apache/dubbo/rpc/Invocation.getAttachment:(Ljava/lang/String;)Ljava/lang/String;
       8: astore_2
       9: aload_2
      10: invokestatic  #11                 // Method org/apache/dubbo/common/utils/StringUtils.isBlank:(Ljava/lang/CharSequence;)Z
      13: ifeq          17
      16: return
      17: aload_0
      18: getfield      #5                  // Field mapper:Lorg/apache/dubbo/spring/security/jackson/ObjectMapperCodec;
      21: aload_2
      22: ldc           #12                 // class org/springframework/security/core/Authentication
      24: invokevirtual #13                 // Method org/apache/dubbo/spring/security/jackson/ObjectMapperCodec.deserialize:(Ljava/lang/String;Ljava/lang/Class;)Ljava/lang/Object;
      27: checkcast     #12                 // class org/springframework/security/core/Authentication
      30: astore_3
      31: aload_3
      32: ifnonnull     36
      35: return
      36: invokestatic  #14                 // Method org/springframework/security/core/context/SecurityContextHolder.getContext:()Lorg/springframework/security/core/context/SecurityContext;
      39: aload_3
      40: invokeinterface #15,  2           // InterfaceMethod org/springframework/security/core/context/SecurityContext.setAuthentication:(Lorg/springframework/security/core/Authentication;)V
      45: return
}
