Compiled from "NoUnboundElementsBindHandler.java"
final class org.springframework.boot.context.properties.bind.handler.NoUnboundElementsBindHandler$Indexed {
  private final java.lang.String name;

  private final java.lang.String nestedPropertyName;

  private org.springframework.boot.context.properties.bind.handler.NoUnboundElementsBindHandler$Indexed(java.lang.String, java.lang.String);
    Code:
       0: aload_0
       1: invokespecial #1                  // Method java/lang/Object."<init>":()V
       4: aload_0
       5: aload_1
       6: putfield      #7                  // Field name:Ljava/lang/String;
       9: aload_0
      10: aload_2
      11: putfield      #13                 // Field nestedPropertyName:Ljava/lang/String;
      14: return

  java.lang.String getName();
    Code:
       0: aload_0
       1: getfield      #7                  // Field name:Ljava/lang/String;
       4: areturn

  java.lang.String getNestedPropertyName();
    Code:
       0: aload_0
       1: getfield      #13                 // Field nestedPropertyName:Ljava/lang/String;
       4: areturn
}
