Compiled from "ClientHttpRequestFactories.java"
class org.springframework.boot.web.client.ClientHttpRequestFactories$Reflective {
  org.springframework.boot.web.client.ClientHttpRequestFactories$Reflective();
    Code:
       0: aload_0
       1: invokespecial #1                  // Method java/lang/Object."<init>":()V
       4: return

  static <T extends org.springframework.http.client.ClientHttpRequestFactory> T get(java.util.function.Supplier<T>, org.springframework.boot.web.client.ClientHttpRequestFactorySettings);
    Code:
       0: aload_0
       1: invokeinterface #7,  1            // InterfaceMethod java/util/function/Supplier.get:()Ljava/lang/Object;
       6: checkcast     #13                 // class org/springframework/http/client/ClientHttpRequestFactory
       9: astore_2
      10: aload_2
      11: aload_1
      12: invokestatic  #15                 // Method configure:(Lorg/springframework/http/client/ClientHttpRequestFactory;Lorg/springframework/boot/web/client/ClientHttpRequestFactorySettings;)V
      15: aload_2
      16: areturn

  private static void configure(org.springframework.http.client.ClientHttpRequestFactory, org.springframework.boot.web.client.ClientHttpRequestFactorySettings);
    Code:
       0: aload_0
       1: invokestatic  #21                 // Method unwrapRequestFactoryIfNecessary:(Lorg/springframework/http/client/ClientHttpRequestFactory;)Lorg/springframework/http/client/ClientHttpRequestFactory;
       4: astore_2
       5: invokestatic  #25                 // Method org/springframework/boot/context/properties/PropertyMapper.get:()Lorg/springframework/boot/context/properties/PropertyMapper;
       8: invokevirtual #30                 // Method org/springframework/boot/context/properties/PropertyMapper.alwaysApplyingWhenNonNull:()Lorg/springframework/boot/context/properties/PropertyMapper;
      11: astore_3
      12: aload_3
      13: aload_1
      14: dup
      15: invokestatic  #33                 // Method java/util/Objects.requireNonNull:(Ljava/lang/Object;)Ljava/lang/Object;
      18: pop
      19: invokedynamic #39,  0             // InvokeDynamic #0:get:(Lorg/springframework/boot/web/client/ClientHttpRequestFactorySettings;)Ljava/util/function/Supplier;
      24: invokevirtual #42                 // Method org/springframework/boot/context/properties/PropertyMapper.from:(Ljava/util/function/Supplier;)Lorg/springframework/boot/context/properties/PropertyMapper$Source;
      27: aload_2
      28: invokedynamic #46,  0             // InvokeDynamic #1:accept:(Lorg/springframework/http/client/ClientHttpRequestFactory;)Ljava/util/function/Consumer;
      33: invokevirtual #50                 // Method org/springframework/boot/context/properties/PropertyMapper$Source.to:(Ljava/util/function/Consumer;)V
      36: aload_3
      37: aload_1
      38: dup
      39: invokestatic  #33                 // Method java/util/Objects.requireNonNull:(Ljava/lang/Object;)Ljava/lang/Object;
      42: pop
      43: invokedynamic #56,  0             // InvokeDynamic #2:get:(Lorg/springframework/boot/web/client/ClientHttpRequestFactorySettings;)Ljava/util/function/Supplier;
      48: invokevirtual #42                 // Method org/springframework/boot/context/properties/PropertyMapper.from:(Ljava/util/function/Supplier;)Lorg/springframework/boot/context/properties/PropertyMapper$Source;
      51: aload_2
      52: invokedynamic #57,  0             // InvokeDynamic #3:accept:(Lorg/springframework/http/client/ClientHttpRequestFactory;)Ljava/util/function/Consumer;
      57: invokevirtual #50                 // Method org/springframework/boot/context/properties/PropertyMapper$Source.to:(Ljava/util/function/Consumer;)V
      60: aload_3
      61: aload_1
      62: dup
      63: invokestatic  #33                 // Method java/util/Objects.requireNonNull:(Ljava/lang/Object;)Ljava/lang/Object;
      66: pop
      67: invokedynamic #58,  0             // InvokeDynamic #4:get:(Lorg/springframework/boot/web/client/ClientHttpRequestFactorySettings;)Ljava/util/function/Supplier;
      72: invokevirtual #42                 // Method org/springframework/boot/context/properties/PropertyMapper.from:(Ljava/util/function/Supplier;)Lorg/springframework/boot/context/properties/PropertyMapper$Source;
      75: aload_2
      76: invokedynamic #59,  0             // InvokeDynamic #5:accept:(Lorg/springframework/http/client/ClientHttpRequestFactory;)Ljava/util/function/Consumer;
      81: invokevirtual #50                 // Method org/springframework/boot/context/properties/PropertyMapper$Source.to:(Ljava/util/function/Consumer;)V
      84: return

  private static org.springframework.http.client.ClientHttpRequestFactory unwrapRequestFactoryIfNecessary(org.springframework.http.client.ClientHttpRequestFactory);
    Code:
       0: aload_0
       1: instanceof    #60                 // class org/springframework/http/client/AbstractClientHttpRequestFactoryWrapper
       4: ifne          9
       7: aload_0
       8: areturn
       9: ldc           #60                 // class org/springframework/http/client/AbstractClientHttpRequestFactoryWrapper
      11: ldc           #62                 // String requestFactory
      13: invokestatic  #64                 // Method org/springframework/util/ReflectionUtils.findField:(Ljava/lang/Class;Ljava/lang/String;)Ljava/lang/reflect/Field;
      16: astore_1
      17: aload_1
      18: invokestatic  #70                 // Method org/springframework/util/ReflectionUtils.makeAccessible:(Ljava/lang/reflect/Field;)V
      21: aload_0
      22: astore_2
      23: aload_2
      24: instanceof    #60                 // class org/springframework/http/client/AbstractClientHttpRequestFactoryWrapper
      27: ifeq          42
      30: aload_1
      31: aload_2
      32: invokestatic  #74                 // Method org/springframework/util/ReflectionUtils.getField:(Ljava/lang/reflect/Field;Ljava/lang/Object;)Ljava/lang/Object;
      35: checkcast     #13                 // class org/springframework/http/client/ClientHttpRequestFactory
      38: astore_2
      39: goto          23
      42: aload_2
      43: areturn

  private static void setConnectTimeout(org.springframework.http.client.ClientHttpRequestFactory, java.time.Duration);
    Code:
       0: aload_0
       1: ldc           #78                 // String setConnectTimeout
       3: iconst_1
       4: anewarray     #80                 // class java/lang/Class
       7: dup
       8: iconst_0
       9: getstatic     #82                 // Field java/lang/Integer.TYPE:Ljava/lang/Class;
      12: aastore
      13: invokestatic  #88                 // Method findMethod:(Lorg/springframework/http/client/ClientHttpRequestFactory;Ljava/lang/String;[Ljava/lang/Class;)Ljava/lang/reflect/Method;
      16: astore_2
      17: aload_1
      18: invokevirtual #92                 // Method java/time/Duration.toMillis:()J
      21: invokestatic  #98                 // Method java/lang/Math.toIntExact:(J)I
      24: istore_3
      25: aload_0
      26: aload_2
      27: iconst_1
      28: anewarray     #2                  // class java/lang/Object
      31: dup
      32: iconst_0
      33: iload_3
      34: invokestatic  #104                // Method java/lang/Integer.valueOf:(I)Ljava/lang/Integer;
      37: aastore
      38: invokestatic  #108                // Method invoke:(Lorg/springframework/http/client/ClientHttpRequestFactory;Ljava/lang/reflect/Method;[Ljava/lang/Object;)V
      41: return

  private static void setReadTimeout(org.springframework.http.client.ClientHttpRequestFactory, java.time.Duration);
    Code:
       0: aload_0
       1: ldc           #112                // String setReadTimeout
       3: iconst_1
       4: anewarray     #80                 // class java/lang/Class
       7: dup
       8: iconst_0
       9: getstatic     #82                 // Field java/lang/Integer.TYPE:Ljava/lang/Class;
      12: aastore
      13: invokestatic  #88                 // Method findMethod:(Lorg/springframework/http/client/ClientHttpRequestFactory;Ljava/lang/String;[Ljava/lang/Class;)Ljava/lang/reflect/Method;
      16: astore_2
      17: aload_1
      18: invokevirtual #92                 // Method java/time/Duration.toMillis:()J
      21: invokestatic  #98                 // Method java/lang/Math.toIntExact:(J)I
      24: istore_3
      25: aload_0
      26: aload_2
      27: iconst_1
      28: anewarray     #2                  // class java/lang/Object
      31: dup
      32: iconst_0
      33: iload_3
      34: invokestatic  #104                // Method java/lang/Integer.valueOf:(I)Ljava/lang/Integer;
      37: aastore
      38: invokestatic  #108                // Method invoke:(Lorg/springframework/http/client/ClientHttpRequestFactory;Ljava/lang/reflect/Method;[Ljava/lang/Object;)V
      41: return

  private static void setBufferRequestBody(org.springframework.http.client.ClientHttpRequestFactory, boolean);
    Code:
       0: aload_0
       1: ldc           #114                // String setBufferRequestBody
       3: iconst_1
       4: anewarray     #80                 // class java/lang/Class
       7: dup
       8: iconst_0
       9: getstatic     #116                // Field java/lang/Boolean.TYPE:Ljava/lang/Class;
      12: aastore
      13: invokestatic  #88                 // Method findMethod:(Lorg/springframework/http/client/ClientHttpRequestFactory;Ljava/lang/String;[Ljava/lang/Class;)Ljava/lang/reflect/Method;
      16: astore_2
      17: aload_0
      18: aload_2
      19: iconst_1
      20: anewarray     #2                  // class java/lang/Object
      23: dup
      24: iconst_0
      25: iload_1
      26: invokestatic  #119                // Method java/lang/Boolean.valueOf:(Z)Ljava/lang/Boolean;
      29: aastore
      30: invokestatic  #108                // Method invoke:(Lorg/springframework/http/client/ClientHttpRequestFactory;Ljava/lang/reflect/Method;[Ljava/lang/Object;)V
      33: return

  private static java.lang.reflect.Method findMethod(org.springframework.http.client.ClientHttpRequestFactory, java.lang.String, java.lang.Class<?>...);
    Code:
       0: aload_0
       1: invokevirtual #122                // Method java/lang/Object.getClass:()Ljava/lang/Class;
       4: aload_1
       5: aload_2
       6: invokestatic  #126                // Method org/springframework/util/ReflectionUtils.findMethod:(Ljava/lang/Class;Ljava/lang/String;[Ljava/lang/Class;)Ljava/lang/reflect/Method;
       9: astore_3
      10: aload_3
      11: ifnull        18
      14: iconst_1
      15: goto          19
      18: iconst_0
      19: aload_0
      20: aload_1
      21: invokedynamic #129,  0            // InvokeDynamic #6:get:(Lorg/springframework/http/client/ClientHttpRequestFactory;Ljava/lang/String;)Ljava/util/function/Supplier;
      26: invokestatic  #132                // Method org/springframework/util/Assert.state:(ZLjava/util/function/Supplier;)V
      29: aload_3
      30: ldc           #138                // class java/lang/Deprecated
      32: invokevirtual #140                // Method java/lang/reflect/Method.isAnnotationPresent:(Ljava/lang/Class;)Z
      35: ifne          42
      38: iconst_1
      39: goto          43
      42: iconst_0
      43: aload_0
      44: aload_1
      45: invokedynamic #146,  0            // InvokeDynamic #7:get:(Lorg/springframework/http/client/ClientHttpRequestFactory;Ljava/lang/String;)Ljava/util/function/Supplier;
      50: invokestatic  #132                // Method org/springframework/util/Assert.state:(ZLjava/util/function/Supplier;)V
      53: aload_3
      54: areturn

  private static void invoke(org.springframework.http.client.ClientHttpRequestFactory, java.lang.reflect.Method, java.lang.Object...);
    Code:
       0: aload_1
       1: aload_0
       2: aload_2
       3: invokestatic  #147                // Method org/springframework/util/ReflectionUtils.invokeMethod:(Ljava/lang/reflect/Method;Ljava/lang/Object;[Ljava/lang/Object;)Ljava/lang/Object;
       6: pop
       7: return

  private static java.lang.String lambda$findMethod$4(org.springframework.http.client.ClientHttpRequestFactory, java.lang.String);
    Code:
       0: ldc           #151                // String Request factory %s has the %s method marked as deprecated
       2: iconst_2
       3: anewarray     #2                  // class java/lang/Object
       6: dup
       7: iconst_0
       8: aload_0
       9: invokevirtual #122                // Method java/lang/Object.getClass:()Ljava/lang/Class;
      12: invokevirtual #153                // Method java/lang/Class.getName:()Ljava/lang/String;
      15: aastore
      16: dup
      17: iconst_1
      18: aload_1
      19: aastore
      20: invokevirtual #157                // Method java/lang/String.formatted:([Ljava/lang/Object;)Ljava/lang/String;
      23: areturn

  private static java.lang.String lambda$findMethod$3(org.springframework.http.client.ClientHttpRequestFactory, java.lang.String);
    Code:
       0: ldc           #163                // String Request factory %s does not have a suitable %s method
       2: iconst_2
       3: anewarray     #2                  // class java/lang/Object
       6: dup
       7: iconst_0
       8: aload_0
       9: invokevirtual #122                // Method java/lang/Object.getClass:()Ljava/lang/Class;
      12: invokevirtual #153                // Method java/lang/Class.getName:()Ljava/lang/String;
      15: aastore
      16: dup
      17: iconst_1
      18: aload_1
      19: aastore
      20: invokevirtual #157                // Method java/lang/String.formatted:([Ljava/lang/Object;)Ljava/lang/String;
      23: areturn

  private static void lambda$configure$2(org.springframework.http.client.ClientHttpRequestFactory, java.lang.Boolean);
    Code:
       0: aload_0
       1: aload_1
       2: invokevirtual #165                // Method java/lang/Boolean.booleanValue:()Z
       5: invokestatic  #169                // Method setBufferRequestBody:(Lorg/springframework/http/client/ClientHttpRequestFactory;Z)V
       8: return

  private static void lambda$configure$1(org.springframework.http.client.ClientHttpRequestFactory, java.time.Duration);
    Code:
       0: aload_0
       1: aload_1
       2: invokestatic  #172                // Method setReadTimeout:(Lorg/springframework/http/client/ClientHttpRequestFactory;Ljava/time/Duration;)V
       5: return

  private static void lambda$configure$0(org.springframework.http.client.ClientHttpRequestFactory, java.time.Duration);
    Code:
       0: aload_0
       1: aload_1
       2: invokestatic  #175                // Method setConnectTimeout:(Lorg/springframework/http/client/ClientHttpRequestFactory;Ljava/time/Duration;)V
       5: return
}
