Compiled from "ClientHttpRequestFactories.java"
class org.springframework.boot.web.client.ClientHttpRequestFactories$HttpComponents {
  org.springframework.boot.web.client.ClientHttpRequestFactories$HttpComponents();
    Code:
       0: aload_0
       1: invokespecial #1                  // Method java/lang/Object."<init>":()V
       4: return

  static org.springframework.http.client.HttpComponentsClientHttpRequestFactory get(org.springframework.boot.web.client.ClientHttpRequestFactorySettings);
    Code:
       0: aload_0
       1: invokevirtual #7                  // Method org/springframework/boot/web/client/ClientHttpRequestFactorySettings.readTimeout:()Ljava/time/Duration;
       4: aload_0
       5: invokevirtual #13                 // Method org/springframework/boot/web/client/ClientHttpRequestFactorySettings.sslBundle:()Lorg/springframework/boot/ssl/SslBundle;
       8: invokestatic  #17                 // Method createRequestFactory:(Ljava/time/Duration;Lorg/springframework/boot/ssl/SslBundle;)Lorg/springframework/http/client/HttpComponentsClientHttpRequestFactory;
      11: astore_1
      12: invokestatic  #23                 // Method org/springframework/boot/context/properties/PropertyMapper.get:()Lorg/springframework/boot/context/properties/PropertyMapper;
      15: invokevirtual #29                 // Method org/springframework/boot/context/properties/PropertyMapper.alwaysApplyingWhenNonNull:()Lorg/springframework/boot/context/properties/PropertyMapper;
      18: astore_2
      19: aload_2
      20: aload_0
      21: dup
      22: invokestatic  #32                 // Method java/util/Objects.requireNonNull:(Ljava/lang/Object;)Ljava/lang/Object;
      25: pop
      26: invokedynamic #38,  0             // InvokeDynamic #0:get:(Lorg/springframework/boot/web/client/ClientHttpRequestFactorySettings;)Ljava/util/function/Supplier;
      31: invokevirtual #41                 // Method org/springframework/boot/context/properties/PropertyMapper.from:(Ljava/util/function/Supplier;)Lorg/springframework/boot/context/properties/PropertyMapper$Source;
      34: invokedynamic #45,  0             // InvokeDynamic #1:apply:()Ljava/util/function/Function;
      39: invokevirtual #49                 // Method org/springframework/boot/context/properties/PropertyMapper$Source.asInt:(Ljava/util/function/Function;)Lorg/springframework/boot/context/properties/PropertyMapper$Source;
      42: aload_1
      43: dup
      44: invokestatic  #32                 // Method java/util/Objects.requireNonNull:(Ljava/lang/Object;)Ljava/lang/Object;
      47: pop
      48: invokedynamic #55,  0             // InvokeDynamic #2:accept:(Lorg/springframework/http/client/HttpComponentsClientHttpRequestFactory;)Ljava/util/function/Consumer;
      53: invokevirtual #59                 // Method org/springframework/boot/context/properties/PropertyMapper$Source.to:(Ljava/util/function/Consumer;)V
      56: aload_2
      57: aload_0
      58: dup
      59: invokestatic  #32                 // Method java/util/Objects.requireNonNull:(Ljava/lang/Object;)Ljava/lang/Object;
      62: pop
      63: invokedynamic #63,  0             // InvokeDynamic #3:get:(Lorg/springframework/boot/web/client/ClientHttpRequestFactorySettings;)Ljava/util/function/Supplier;
      68: invokevirtual #41                 // Method org/springframework/boot/context/properties/PropertyMapper.from:(Ljava/util/function/Supplier;)Lorg/springframework/boot/context/properties/PropertyMapper$Source;
      71: aload_1
      72: dup
      73: invokestatic  #32                 // Method java/util/Objects.requireNonNull:(Ljava/lang/Object;)Ljava/lang/Object;
      76: pop
      77: invokedynamic #64,  0             // InvokeDynamic #4:accept:(Lorg/springframework/http/client/HttpComponentsClientHttpRequestFactory;)Ljava/util/function/Consumer;
      82: invokevirtual #59                 // Method org/springframework/boot/context/properties/PropertyMapper$Source.to:(Ljava/util/function/Consumer;)V
      85: aload_1
      86: areturn

  private static org.springframework.http.client.HttpComponentsClientHttpRequestFactory createRequestFactory(java.time.Duration, org.springframework.boot.ssl.SslBundle);
    Code:
       0: new           #65                 // class org/springframework/http/client/HttpComponentsClientHttpRequestFactory
       3: dup
       4: aload_0
       5: aload_1
       6: invokestatic  #67                 // Method createHttpClient:(Ljava/time/Duration;Lorg/springframework/boot/ssl/SslBundle;)Lorg/apache/hc/client5/http/classic/HttpClient;
       9: invokespecial #71                 // Method org/springframework/http/client/HttpComponentsClientHttpRequestFactory."<init>":(Lorg/apache/hc/client5/http/classic/HttpClient;)V
      12: areturn

  private static org.apache.hc.client5.http.classic.HttpClient createHttpClient(java.time.Duration, org.springframework.boot.ssl.SslBundle);
    Code:
       0: invokestatic  #74                 // Method org/apache/hc/client5/http/impl/io/PoolingHttpClientConnectionManagerBuilder.create:()Lorg/apache/hc/client5/http/impl/io/PoolingHttpClientConnectionManagerBuilder;
       3: astore_2
       4: aload_0
       5: ifnull        32
       8: invokestatic  #80                 // Method org/apache/hc/core5/http/io/SocketConfig.custom:()Lorg/apache/hc/core5/http/io/SocketConfig$Builder;
      11: aload_0
      12: invokevirtual #86                 // Method java/time/Duration.toMillis:()J
      15: l2i
      16: getstatic     #92                 // Field java/util/concurrent/TimeUnit.MILLISECONDS:Ljava/util/concurrent/TimeUnit;
      19: invokevirtual #98                 // Method org/apache/hc/core5/http/io/SocketConfig$Builder.setSoTimeout:(ILjava/util/concurrent/TimeUnit;)Lorg/apache/hc/core5/http/io/SocketConfig$Builder;
      22: invokevirtual #104                // Method org/apache/hc/core5/http/io/SocketConfig$Builder.build:()Lorg/apache/hc/core5/http/io/SocketConfig;
      25: astore_3
      26: aload_2
      27: aload_3
      28: invokevirtual #108                // Method org/apache/hc/client5/http/impl/io/PoolingHttpClientConnectionManagerBuilder.setDefaultSocketConfig:(Lorg/apache/hc/core5/http/io/SocketConfig;)Lorg/apache/hc/client5/http/impl/io/PoolingHttpClientConnectionManagerBuilder;
      31: pop
      32: aload_1
      33: ifnull        84
      36: aload_1
      37: invokeinterface #112,  1          // InterfaceMethod org/springframework/boot/ssl/SslBundle.getOptions:()Lorg/springframework/boot/ssl/SslOptions;
      42: astore_3
      43: new           #118                // class org/apache/hc/client5/http/ssl/SSLConnectionSocketFactory
      46: dup
      47: aload_1
      48: invokeinterface #120,  1          // InterfaceMethod org/springframework/boot/ssl/SslBundle.createSslContext:()Ljavax/net/ssl/SSLContext;
      53: aload_3
      54: invokeinterface #124,  1          // InterfaceMethod org/springframework/boot/ssl/SslOptions.getEnabledProtocols:()[Ljava/lang/String;
      59: aload_3
      60: invokeinterface #130,  1          // InterfaceMethod org/springframework/boot/ssl/SslOptions.getCiphers:()[Ljava/lang/String;
      65: new           #133                // class org/apache/hc/client5/http/ssl/DefaultHostnameVerifier
      68: dup
      69: invokespecial #135                // Method org/apache/hc/client5/http/ssl/DefaultHostnameVerifier."<init>":()V
      72: invokespecial #136                // Method org/apache/hc/client5/http/ssl/SSLConnectionSocketFactory."<init>":(Ljavax/net/ssl/SSLContext;[Ljava/lang/String;[Ljava/lang/String;Ljavax/net/ssl/HostnameVerifier;)V
      75: astore        4
      77: aload_2
      78: aload         4
      80: invokevirtual #139                // Method org/apache/hc/client5/http/impl/io/PoolingHttpClientConnectionManagerBuilder.setSSLSocketFactory:(Lorg/apache/hc/client5/http/socket/LayeredConnectionSocketFactory;)Lorg/apache/hc/client5/http/impl/io/PoolingHttpClientConnectionManagerBuilder;
      83: pop
      84: aload_2
      85: invokevirtual #143                // Method org/apache/hc/client5/http/impl/io/PoolingHttpClientConnectionManagerBuilder.build:()Lorg/apache/hc/client5/http/impl/io/PoolingHttpClientConnectionManager;
      88: astore_3
      89: invokestatic  #146                // Method org/apache/hc/client5/http/impl/classic/HttpClientBuilder.create:()Lorg/apache/hc/client5/http/impl/classic/HttpClientBuilder;
      92: aload_3
      93: invokevirtual #151                // Method org/apache/hc/client5/http/impl/classic/HttpClientBuilder.setConnectionManager:(Lorg/apache/hc/client5/http/io/HttpClientConnectionManager;)Lorg/apache/hc/client5/http/impl/classic/HttpClientBuilder;
      96: invokevirtual #155                // Method org/apache/hc/client5/http/impl/classic/HttpClientBuilder.build:()Lorg/apache/hc/client5/http/impl/classic/CloseableHttpClient;
      99: areturn
}
