Compiled from "ClientHttpRequestFactories.java"
class org.springframework.boot.web.client.ClientHttpRequestFactories$OkHttp {
  org.springframework.boot.web.client.ClientHttpRequestFactories$OkHttp();
    Code:
       0: aload_0
       1: invokespecial #1                  // Method java/lang/Object."<init>":()V
       4: return

  static org.springframework.http.client.OkHttp3ClientHttpRequestFactory get(org.springframework.boot.web.client.ClientHttpRequestFactorySettings);
    Code:
       0: aload_0
       1: invokevirtual #7                  // Method org/springframework/boot/web/client/ClientHttpRequestFactorySettings.bufferRequestBody:()Ljava/lang/Boolean;
       4: ifnonnull     11
       7: iconst_1
       8: goto          12
      11: iconst_0
      12: invokedynamic #13,  0             // InvokeDynamic #0:get:()Ljava/util/function/Supplier;
      17: invokestatic  #17                 // Method org/springframework/util/Assert.state:(ZLjava/util/function/Supplier;)V
      20: aload_0
      21: invokevirtual #23                 // Method org/springframework/boot/web/client/ClientHttpRequestFactorySettings.sslBundle:()Lorg/springframework/boot/ssl/SslBundle;
      24: invokestatic  #27                 // Method createRequestFactory:(Lorg/springframework/boot/ssl/SslBundle;)Lorg/springframework/http/client/OkHttp3ClientHttpRequestFactory;
      27: astore_1
      28: invokestatic  #33                 // Method org/springframework/boot/context/properties/PropertyMapper.get:()Lorg/springframework/boot/context/properties/PropertyMapper;
      31: invokevirtual #38                 // Method org/springframework/boot/context/properties/PropertyMapper.alwaysApplyingWhenNonNull:()Lorg/springframework/boot/context/properties/PropertyMapper;
      34: astore_2
      35: aload_2
      36: aload_0
      37: dup
      38: invokestatic  #41                 // Method java/util/Objects.requireNonNull:(Ljava/lang/Object;)Ljava/lang/Object;
      41: pop
      42: invokedynamic #47,  0             // InvokeDynamic #1:get:(Lorg/springframework/boot/web/client/ClientHttpRequestFactorySettings;)Ljava/util/function/Supplier;
      47: invokevirtual #50                 // Method org/springframework/boot/context/properties/PropertyMapper.from:(Ljava/util/function/Supplier;)Lorg/springframework/boot/context/properties/PropertyMapper$Source;
      50: invokedynamic #54,  0             // InvokeDynamic #2:apply:()Ljava/util/function/Function;
      55: invokevirtual #58                 // Method org/springframework/boot/context/properties/PropertyMapper$Source.asInt:(Ljava/util/function/Function;)Lorg/springframework/boot/context/properties/PropertyMapper$Source;
      58: aload_1
      59: dup
      60: invokestatic  #41                 // Method java/util/Objects.requireNonNull:(Ljava/lang/Object;)Ljava/lang/Object;
      63: pop
      64: invokedynamic #64,  0             // InvokeDynamic #3:accept:(Lorg/springframework/http/client/OkHttp3ClientHttpRequestFactory;)Ljava/util/function/Consumer;
      69: invokevirtual #68                 // Method org/springframework/boot/context/properties/PropertyMapper$Source.to:(Ljava/util/function/Consumer;)V
      72: aload_2
      73: aload_0
      74: dup
      75: invokestatic  #41                 // Method java/util/Objects.requireNonNull:(Ljava/lang/Object;)Ljava/lang/Object;
      78: pop
      79: invokedynamic #72,  0             // InvokeDynamic #4:get:(Lorg/springframework/boot/web/client/ClientHttpRequestFactorySettings;)Ljava/util/function/Supplier;
      84: invokevirtual #50                 // Method org/springframework/boot/context/properties/PropertyMapper.from:(Ljava/util/function/Supplier;)Lorg/springframework/boot/context/properties/PropertyMapper$Source;
      87: invokedynamic #54,  0             // InvokeDynamic #2:apply:()Ljava/util/function/Function;
      92: invokevirtual #58                 // Method org/springframework/boot/context/properties/PropertyMapper$Source.asInt:(Ljava/util/function/Function;)Lorg/springframework/boot/context/properties/PropertyMapper$Source;
      95: aload_1
      96: dup
      97: invokestatic  #41                 // Method java/util/Objects.requireNonNull:(Ljava/lang/Object;)Ljava/lang/Object;
     100: pop
     101: invokedynamic #73,  0             // InvokeDynamic #5:accept:(Lorg/springframework/http/client/OkHttp3ClientHttpRequestFactory;)Ljava/util/function/Consumer;
     106: invokevirtual #68                 // Method org/springframework/boot/context/properties/PropertyMapper$Source.to:(Ljava/util/function/Consumer;)V
     109: aload_1
     110: areturn

  private static org.springframework.http.client.OkHttp3ClientHttpRequestFactory createRequestFactory(org.springframework.boot.ssl.SslBundle);
    Code:
       0: aload_0
       1: ifnull        96
       4: aload_0
       5: invokeinterface #74,  1           // InterfaceMethod org/springframework/boot/ssl/SslBundle.getOptions:()Lorg/springframework/boot/ssl/SslOptions;
      10: invokeinterface #80,  1           // InterfaceMethod org/springframework/boot/ssl/SslOptions.isSpecified:()Z
      15: ifne          22
      18: iconst_1
      19: goto          23
      22: iconst_0
      23: ldc           #86                 // String SSL Options cannot be specified with OkHttp
      25: invokestatic  #88                 // Method org/springframework/util/Assert.state:(ZLjava/lang/String;)V
      28: aload_0
      29: invokeinterface #91,  1           // InterfaceMethod org/springframework/boot/ssl/SslBundle.createSslContext:()Ljavax/net/ssl/SSLContext;
      34: invokevirtual #95                 // Method javax/net/ssl/SSLContext.getSocketFactory:()Ljavax/net/ssl/SSLSocketFactory;
      37: astore_1
      38: aload_0
      39: invokeinterface #101,  1          // InterfaceMethod org/springframework/boot/ssl/SslBundle.getManagers:()Lorg/springframework/boot/ssl/SslManagerBundle;
      44: invokeinterface #105,  1          // InterfaceMethod org/springframework/boot/ssl/SslManagerBundle.getTrustManagers:()[Ljavax/net/ssl/TrustManager;
      49: astore_2
      50: aload_2
      51: arraylength
      52: iconst_1
      53: if_icmpne     60
      56: iconst_1
      57: goto          61
      60: iconst_0
      61: ldc           #111                // String Trust material must be provided in the SSL bundle for OkHttp3ClientHttpRequestFactory
      63: invokestatic  #88                 // Method org/springframework/util/Assert.state:(ZLjava/lang/String;)V
      66: new           #113                // class okhttp3/OkHttpClient$Builder
      69: dup
      70: invokespecial #115                // Method okhttp3/OkHttpClient$Builder."<init>":()V
      73: aload_1
      74: aload_2
      75: iconst_0
      76: aaload
      77: checkcast     #116                // class javax/net/ssl/X509TrustManager
      80: invokevirtual #118                // Method okhttp3/OkHttpClient$Builder.sslSocketFactory:(Ljavax/net/ssl/SSLSocketFactory;Ljavax/net/ssl/X509TrustManager;)Lokhttp3/OkHttpClient$Builder;
      83: invokevirtual #122                // Method okhttp3/OkHttpClient$Builder.build:()Lokhttp3/OkHttpClient;
      86: astore_3
      87: new           #126                // class org/springframework/http/client/OkHttp3ClientHttpRequestFactory
      90: dup
      91: aload_3
      92: invokespecial #128                // Method org/springframework/http/client/OkHttp3ClientHttpRequestFactory."<init>":(Lokhttp3/OkHttpClient;)V
      95: areturn
      96: new           #126                // class org/springframework/http/client/OkHttp3ClientHttpRequestFactory
      99: dup
     100: invokespecial #131                // Method org/springframework/http/client/OkHttp3ClientHttpRequestFactory."<init>":()V
     103: areturn

  private static java.lang.String lambda$get$0();
    Code:
       0: ldc           #132                // String OkHttp3ClientHttpRequestFactory does not support request body buffering
       2: areturn
}
