Compiled from "ClientHttpRequestFactorySupplier.java"
public class org.springframework.boot.web.client.ClientHttpRequestFactorySupplier implements java.util.function.Supplier<org.springframework.http.client.ClientHttpRequestFactory> {
  public org.springframework.boot.web.client.ClientHttpRequestFactorySupplier();
    Code:
       0: aload_0
       1: invokespecial #1                  // Method java/lang/Object."<init>":()V
       4: return

  public org.springframework.http.client.ClientHttpRequestFactory get();
    Code:
       0: getstatic     #7                  // Field org/springframework/boot/web/client/ClientHttpRequestFactorySettings.DEFAULTS:Lorg/springframework/boot/web/client/ClientHttpRequestFactorySettings;
       3: invokestatic  #13                 // Method org/springframework/boot/web/client/ClientHttpRequestFactories.get:(Lorg/springframework/boot/web/client/ClientHttpRequestFactorySettings;)Lorg/springframework/http/client/ClientHttpRequestFactory;
       6: areturn

  public java.lang.Object get();
    Code:
       0: aload_0
       1: invokevirtual #19                 // Method get:()Lorg/springframework/http/client/ClientHttpRequestFactory;
       4: areturn
}
