Compiled from "ClientHttpRequestFactoriesRuntimeHints.java"
class org.springframework.boot.web.client.ClientHttpRequestFactoriesRuntimeHints implements org.springframework.aot.hint.RuntimeHintsRegistrar {
  org.springframework.boot.web.client.ClientHttpRequestFactoriesRuntimeHints();
    Code:
       0: aload_0
       1: invokespecial #1                  // Method java/lang/Object."<init>":()V
       4: return

  public void registerHints(org.springframework.aot.hint.RuntimeHints, java.lang.ClassLoader);
    Code:
       0: ldc           #7                  // String org.springframework.http.client.ClientHttpRequestFactory
       2: aload_2
       3: invokestatic  #9                  // Method org/springframework/util/ClassUtils.isPresent:(Ljava/lang/String;Ljava/lang/ClassLoader;)Z
       6: ifeq          18
       9: aload_0
      10: aload_1
      11: invokevirtual #15                 // Method org/springframework/aot/hint/RuntimeHints.reflection:()Lorg/springframework/aot/hint/ReflectionHints;
      14: aload_2
      15: invokevirtual #21                 // Method registerHints:(Lorg/springframework/aot/hint/ReflectionHints;Ljava/lang/ClassLoader;)V
      18: return

  private void registerHints(org.springframework.aot.hint.ReflectionHints, java.lang.ClassLoader);
    Code:
       0: aload_1
       1: aload_0
       2: ldc           #27                 // class org/springframework/http/client/AbstractClientHttpRequestFactoryWrapper
       4: ldc           #29                 // String requestFactory
       6: invokevirtual #31                 // Method findField:(Ljava/lang/Class;Ljava/lang/String;)Ljava/lang/reflect/Field;
       9: invokevirtual #35                 // Method org/springframework/aot/hint/ReflectionHints.registerField:(Ljava/lang/reflect/Field;)Lorg/springframework/aot/hint/ReflectionHints;
      12: pop
      13: aload_1
      14: aload_2
      15: ldc           #43                 // String org.apache.hc.client5.http.impl.classic.HttpClients
      17: aload_0
      18: aload_1
      19: invokedynamic #45,  0             // InvokeDynamic #0:accept:(Lorg/springframework/boot/web/client/ClientHttpRequestFactoriesRuntimeHints;Lorg/springframework/aot/hint/ReflectionHints;)Ljava/util/function/Consumer;
      24: invokevirtual #49                 // Method org/springframework/aot/hint/ReflectionHints.registerTypeIfPresent:(Ljava/lang/ClassLoader;Ljava/lang/String;Ljava/util/function/Consumer;)Lorg/springframework/aot/hint/ReflectionHints;
      27: pop
      28: aload_1
      29: aload_2
      30: ldc           #53                 // String okhttp3.OkHttpClient
      32: aload_0
      33: aload_1
      34: invokedynamic #55,  0             // InvokeDynamic #1:accept:(Lorg/springframework/boot/web/client/ClientHttpRequestFactoriesRuntimeHints;Lorg/springframework/aot/hint/ReflectionHints;)Ljava/util/function/Consumer;
      39: invokevirtual #49                 // Method org/springframework/aot/hint/ReflectionHints.registerTypeIfPresent:(Ljava/lang/ClassLoader;Ljava/lang/String;Ljava/util/function/Consumer;)Lorg/springframework/aot/hint/ReflectionHints;
      42: pop
      43: aload_1
      44: ldc           #56                 // class org/springframework/http/client/SimpleClientHttpRequestFactory
      46: aload_0
      47: aload_1
      48: invokedynamic #58,  0             // InvokeDynamic #2:accept:(Lorg/springframework/boot/web/client/ClientHttpRequestFactoriesRuntimeHints;Lorg/springframework/aot/hint/ReflectionHints;)Ljava/util/function/Consumer;
      53: invokevirtual #59                 // Method org/springframework/aot/hint/ReflectionHints.registerType:(Ljava/lang/Class;Ljava/util/function/Consumer;)Lorg/springframework/aot/hint/ReflectionHints;
      56: pop
      57: return

  private void registerReflectionHints(org.springframework.aot.hint.ReflectionHints, java.lang.Class<? extends org.springframework.http.client.ClientHttpRequestFactory>);
    Code:
       0: aload_0
       1: aload_1
       2: aload_2
       3: ldc           #63                 // String setConnectTimeout
       5: iconst_1
       6: anewarray     #65                 // class java/lang/Class
       9: dup
      10: iconst_0
      11: getstatic     #67                 // Field java/lang/Integer.TYPE:Ljava/lang/Class;
      14: aastore
      15: invokevirtual #73                 // Method registerMethod:(Lorg/springframework/aot/hint/ReflectionHints;Ljava/lang/Class;Ljava/lang/String;[Ljava/lang/Class;)V
      18: aload_0
      19: aload_1
      20: aload_2
      21: ldc           #77                 // String setReadTimeout
      23: iconst_1
      24: anewarray     #65                 // class java/lang/Class
      27: dup
      28: iconst_0
      29: getstatic     #67                 // Field java/lang/Integer.TYPE:Ljava/lang/Class;
      32: aastore
      33: invokevirtual #73                 // Method registerMethod:(Lorg/springframework/aot/hint/ReflectionHints;Ljava/lang/Class;Ljava/lang/String;[Ljava/lang/Class;)V
      36: aload_0
      37: aload_1
      38: aload_2
      39: ldc           #79                 // String setBufferRequestBody
      41: iconst_1
      42: anewarray     #65                 // class java/lang/Class
      45: dup
      46: iconst_0
      47: getstatic     #81                 // Field java/lang/Boolean.TYPE:Ljava/lang/Class;
      50: aastore
      51: invokevirtual #73                 // Method registerMethod:(Lorg/springframework/aot/hint/ReflectionHints;Ljava/lang/Class;Ljava/lang/String;[Ljava/lang/Class;)V
      54: return

  private void registerMethod(org.springframework.aot.hint.ReflectionHints, java.lang.Class<? extends org.springframework.http.client.ClientHttpRequestFactory>, java.lang.String, java.lang.Class<?>...);
    Code:
       0: aload_2
       1: aload_3
       2: aload         4
       4: invokestatic  #84                 // Method org/springframework/util/ReflectionUtils.findMethod:(Ljava/lang/Class;Ljava/lang/String;[Ljava/lang/Class;)Ljava/lang/reflect/Method;
       7: astore        5
       9: aload         5
      11: ifnull        24
      14: aload_1
      15: aload         5
      17: getstatic     #90                 // Field org/springframework/aot/hint/ExecutableMode.INVOKE:Lorg/springframework/aot/hint/ExecutableMode;
      20: invokevirtual #96                 // Method org/springframework/aot/hint/ReflectionHints.registerMethod:(Ljava/lang/reflect/Method;Lorg/springframework/aot/hint/ExecutableMode;)Lorg/springframework/aot/hint/ReflectionHints;
      23: pop
      24: return

  private java.lang.reflect.Field findField(java.lang.Class<?>, java.lang.String);
    Code:
       0: aload_1
       1: aload_2
       2: invokestatic  #99                 // Method org/springframework/util/ReflectionUtils.findField:(Ljava/lang/Class;Ljava/lang/String;)Ljava/lang/reflect/Field;
       5: astore_3
       6: aload_3
       7: ifnull        14
      10: iconst_1
      11: goto          15
      14: iconst_0
      15: aload_1
      16: aload_2
      17: invokedynamic #100,  0            // InvokeDynamic #3:get:(Ljava/lang/Class;Ljava/lang/String;)Ljava/util/function/Supplier;
      22: invokestatic  #104                // Method org/springframework/util/Assert.state:(ZLjava/util/function/Supplier;)V
      25: aload_3
      26: areturn

  private static java.lang.String lambda$findField$3(java.lang.Class, java.lang.String);
    Code:
       0: ldc           #110                // String Unable to find field \'%s\' on %s
       2: iconst_2
       3: anewarray     #2                  // class java/lang/Object
       6: dup
       7: iconst_0
       8: aload_0
       9: invokevirtual #112                // Method java/lang/Class.getName:()Ljava/lang/String;
      12: aastore
      13: dup
      14: iconst_1
      15: aload_1
      16: aastore
      17: invokevirtual #116                // Method java/lang/String.formatted:([Ljava/lang/Object;)Ljava/lang/String;
      20: areturn

  private void lambda$registerHints$2(org.springframework.aot.hint.ReflectionHints, org.springframework.aot.hint.TypeHint$Builder);
    Code:
       0: aload_2
       1: ldc           #122                // class java/net/HttpURLConnection
       3: invokevirtual #124                // Method org/springframework/aot/hint/TypeHint$Builder.onReachableType:(Ljava/lang/Class;)Lorg/springframework/aot/hint/TypeHint$Builder;
       6: pop
       7: aload_0
       8: aload_1
       9: ldc           #56                 // class org/springframework/http/client/SimpleClientHttpRequestFactory
      11: invokevirtual #130                // Method registerReflectionHints:(Lorg/springframework/aot/hint/ReflectionHints;Ljava/lang/Class;)V
      14: return

  private void lambda$registerHints$1(org.springframework.aot.hint.ReflectionHints, org.springframework.aot.hint.TypeHint$Builder);
    Code:
       0: aload_2
       1: ldc           #53                 // String okhttp3.OkHttpClient
       3: invokestatic  #134                // InterfaceMethod org/springframework/aot/hint/TypeReference.of:(Ljava/lang/String;)Lorg/springframework/aot/hint/TypeReference;
       6: invokevirtual #140                // Method org/springframework/aot/hint/TypeHint$Builder.onReachableType:(Lorg/springframework/aot/hint/TypeReference;)Lorg/springframework/aot/hint/TypeHint$Builder;
       9: pop
      10: aload_0
      11: aload_1
      12: ldc           #143                // class org/springframework/http/client/OkHttp3ClientHttpRequestFactory
      14: invokevirtual #130                // Method registerReflectionHints:(Lorg/springframework/aot/hint/ReflectionHints;Ljava/lang/Class;)V
      17: return

  private void lambda$registerHints$0(org.springframework.aot.hint.ReflectionHints, org.springframework.aot.hint.TypeHint$Builder);
    Code:
       0: aload_2
       1: ldc           #43                 // String org.apache.hc.client5.http.impl.classic.HttpClients
       3: invokestatic  #134                // InterfaceMethod org/springframework/aot/hint/TypeReference.of:(Ljava/lang/String;)Lorg/springframework/aot/hint/TypeReference;
       6: invokevirtual #140                // Method org/springframework/aot/hint/TypeHint$Builder.onReachableType:(Lorg/springframework/aot/hint/TypeReference;)Lorg/springframework/aot/hint/TypeHint$Builder;
       9: pop
      10: aload_0
      11: aload_1
      12: ldc           #145                // class org/springframework/http/client/HttpComponentsClientHttpRequestFactory
      14: invokevirtual #130                // Method registerReflectionHints:(Lorg/springframework/aot/hint/ReflectionHints;Ljava/lang/Class;)V
      17: return
}
