Compiled from "ClientHttpRequestFactories.java"
class org.springframework.boot.web.client.ClientHttpRequestFactories$Simple$SimpleClientHttpsRequestFactory extends org.springframework.http.client.SimpleClientHttpRequestFactory {
  private org.springframework.boot.ssl.SslBundle sslBundle;

  org.springframework.boot.web.client.ClientHttpRequestFactories$Simple$SimpleClientHttpsRequestFactory(org.springframework.boot.ssl.SslBundle);
    Code:
       0: aload_0
       1: invokespecial #1                  // Method org/springframework/http/client/SimpleClientHttpRequestFactory."<init>":()V
       4: aload_0
       5: aload_1
       6: putfield      #7                  // Field sslBundle:Lorg/springframework/boot/ssl/SslBundle;
       9: return

  protected void prepareConnection(java.net.HttpURLConnection, java.lang.String) throws java.io.IOException;
    Code:
       0: aload_0
       1: getfield      #7                  // Field sslBundle:Lorg/springframework/boot/ssl/SslBundle;
       4: ifnull        39
       7: aload_1
       8: instanceof    #13                 // class javax/net/ssl/HttpsURLConnection
      11: ifeq          39
      14: aload_1
      15: checkcast     #13                 // class javax/net/ssl/HttpsURLConnection
      18: astore_3
      19: aload_0
      20: getfield      #7                  // Field sslBundle:Lorg/springframework/boot/ssl/SslBundle;
      23: invokeinterface #15,  1           // InterfaceMethod org/springframework/boot/ssl/SslBundle.createSslContext:()Ljavax/net/ssl/SSLContext;
      28: invokevirtual #21                 // Method javax/net/ssl/SSLContext.getSocketFactory:()Ljavax/net/ssl/SSLSocketFactory;
      31: astore        4
      33: aload_3
      34: aload         4
      36: invokevirtual #27                 // Method javax/net/ssl/HttpsURLConnection.setSSLSocketFactory:(Ljavax/net/ssl/SSLSocketFactory;)V
      39: return
}
