Compiled from "ClientHttpRequestFactorySettings.java"
public final class org.springframework.boot.web.client.ClientHttpRequestFactorySettings extends java.lang.Record {
  private final java.time.Duration connectTimeout;

  private final java.time.Duration readTimeout;

  private final java.lang.Boolean bufferRequestBody;

  private final org.springframework.boot.ssl.SslBundle sslBundle;

  public static final org.springframework.boot.web.client.ClientHttpRequestFactorySettings DEFAULTS;

  public org.springframework.boot.web.client.ClientHttpRequestFactorySettings(java.time.Duration, java.time.Duration, java.lang.Boolean, org.springframework.boot.ssl.SslBundle);
    Code:
       0: aload_0
       1: invokespecial #1                  // Method java/lang/Record."<init>":()V
       4: aload_0
       5: aload_1
       6: putfield      #7                  // Field connectTimeout:Ljava/time/Duration;
       9: aload_0
      10: aload_2
      11: putfield      #13                 // Field readTimeout:Ljava/time/Duration;
      14: aload_0
      15: aload_3
      16: putfield      #16                 // Field bufferRequestBody:Ljava/lang/Boolean;
      19: aload_0
      20: aload         4
      22: putfield      #20                 // Field sslBundle:Lorg/springframework/boot/ssl/SslBundle;
      25: return

  public org.springframework.boot.web.client.ClientHttpRequestFactorySettings(java.time.Duration, java.time.Duration, java.lang.Boolean);
    Code:
       0: aload_0
       1: aload_1
       2: aload_2
       3: aload_3
       4: aconst_null
       5: invokespecial #24                 // Method "<init>":(Ljava/time/Duration;Ljava/time/Duration;Ljava/lang/Boolean;Lorg/springframework/boot/ssl/SslBundle;)V
       8: return

  public org.springframework.boot.web.client.ClientHttpRequestFactorySettings withConnectTimeout(java.time.Duration);
    Code:
       0: new           #8                  // class org/springframework/boot/web/client/ClientHttpRequestFactorySettings
       3: dup
       4: aload_1
       5: aload_0
       6: getfield      #13                 // Field readTimeout:Ljava/time/Duration;
       9: aload_0
      10: getfield      #16                 // Field bufferRequestBody:Ljava/lang/Boolean;
      13: aload_0
      14: getfield      #20                 // Field sslBundle:Lorg/springframework/boot/ssl/SslBundle;
      17: invokespecial #24                 // Method "<init>":(Ljava/time/Duration;Ljava/time/Duration;Ljava/lang/Boolean;Lorg/springframework/boot/ssl/SslBundle;)V
      20: areturn

  public org.springframework.boot.web.client.ClientHttpRequestFactorySettings withReadTimeout(java.time.Duration);
    Code:
       0: new           #8                  // class org/springframework/boot/web/client/ClientHttpRequestFactorySettings
       3: dup
       4: aload_0
       5: getfield      #7                  // Field connectTimeout:Ljava/time/Duration;
       8: aload_1
       9: aload_0
      10: getfield      #16                 // Field bufferRequestBody:Ljava/lang/Boolean;
      13: aload_0
      14: getfield      #20                 // Field sslBundle:Lorg/springframework/boot/ssl/SslBundle;
      17: invokespecial #24                 // Method "<init>":(Ljava/time/Duration;Ljava/time/Duration;Ljava/lang/Boolean;Lorg/springframework/boot/ssl/SslBundle;)V
      20: areturn

  public org.springframework.boot.web.client.ClientHttpRequestFactorySettings withBufferRequestBody(java.lang.Boolean);
    Code:
       0: new           #8                  // class org/springframework/boot/web/client/ClientHttpRequestFactorySettings
       3: dup
       4: aload_0
       5: getfield      #7                  // Field connectTimeout:Ljava/time/Duration;
       8: aload_0
       9: getfield      #13                 // Field readTimeout:Ljava/time/Duration;
      12: aload_1
      13: aload_0
      14: getfield      #20                 // Field sslBundle:Lorg/springframework/boot/ssl/SslBundle;
      17: invokespecial #24                 // Method "<init>":(Ljava/time/Duration;Ljava/time/Duration;Ljava/lang/Boolean;Lorg/springframework/boot/ssl/SslBundle;)V
      20: areturn

  public org.springframework.boot.web.client.ClientHttpRequestFactorySettings withSslBundle(org.springframework.boot.ssl.SslBundle);
    Code:
       0: new           #8                  // class org/springframework/boot/web/client/ClientHttpRequestFactorySettings
       3: dup
       4: aload_0
       5: getfield      #7                  // Field connectTimeout:Ljava/time/Duration;
       8: aload_0
       9: getfield      #13                 // Field readTimeout:Ljava/time/Duration;
      12: aload_0
      13: getfield      #16                 // Field bufferRequestBody:Ljava/lang/Boolean;
      16: aload_1
      17: invokespecial #24                 // Method "<init>":(Ljava/time/Duration;Ljava/time/Duration;Ljava/lang/Boolean;Lorg/springframework/boot/ssl/SslBundle;)V
      20: areturn

  public final java.lang.String toString();
    Code:
       0: aload_0
       1: invokedynamic #27,  0             // InvokeDynamic #0:toString:(Lorg/springframework/boot/web/client/ClientHttpRequestFactorySettings;)Ljava/lang/String;
       6: areturn

  public final int hashCode();
    Code:
       0: aload_0
       1: invokedynamic #31,  0             // InvokeDynamic #0:hashCode:(Lorg/springframework/boot/web/client/ClientHttpRequestFactorySettings;)I
       6: ireturn

  public final boolean equals(java.lang.Object);
    Code:
       0: aload_0
       1: aload_1
       2: invokedynamic #35,  0             // InvokeDynamic #0:equals:(Lorg/springframework/boot/web/client/ClientHttpRequestFactorySettings;Ljava/lang/Object;)Z
       7: ireturn

  public java.time.Duration connectTimeout();
    Code:
       0: aload_0
       1: getfield      #7                  // Field connectTimeout:Ljava/time/Duration;
       4: areturn

  public java.time.Duration readTimeout();
    Code:
       0: aload_0
       1: getfield      #13                 // Field readTimeout:Ljava/time/Duration;
       4: areturn

  public java.lang.Boolean bufferRequestBody();
    Code:
       0: aload_0
       1: getfield      #16                 // Field bufferRequestBody:Ljava/lang/Boolean;
       4: areturn

  public org.springframework.boot.ssl.SslBundle sslBundle();
    Code:
       0: aload_0
       1: getfield      #20                 // Field sslBundle:Lorg/springframework/boot/ssl/SslBundle;
       4: areturn

  static {};
    Code:
       0: new           #8                  // class org/springframework/boot/web/client/ClientHttpRequestFactorySettings
       3: dup
       4: aconst_null
       5: aconst_null
       6: aconst_null
       7: aconst_null
       8: invokespecial #24                 // Method "<init>":(Ljava/time/Duration;Ljava/time/Duration;Ljava/lang/Boolean;Lorg/springframework/boot/ssl/SslBundle;)V
      11: putstatic     #39                 // Field DEFAULTS:Lorg/springframework/boot/web/client/ClientHttpRequestFactorySettings;
      14: return
}
