Compiled from "ClientHttpRequestFactories.java"
class org.springframework.boot.web.client.ClientHttpRequestFactories$Simple {
  org.springframework.boot.web.client.ClientHttpRequestFactories$Simple();
    Code:
       0: aload_0
       1: invokespecial #1                  // Method java/lang/Object."<init>":()V
       4: return

  static org.springframework.http.client.SimpleClientHttpRequestFactory get(org.springframework.boot.web.client.ClientHttpRequestFactorySettings);
    Code:
       0: aload_0
       1: invokevirtual #7                  // Method org/springframework/boot/web/client/ClientHttpRequestFactorySettings.sslBundle:()Lorg/springframework/boot/ssl/SslBundle;
       4: astore_1
       5: aload_1
       6: ifnull        20
       9: new           #13                 // class org/springframework/boot/web/client/ClientHttpRequestFactories$Simple$SimpleClientHttpsRequestFactory
      12: dup
      13: aload_1
      14: invokespecial #15                 // Method org/springframework/boot/web/client/ClientHttpRequestFactories$Simple$SimpleClientHttpsRequestFactory."<init>":(Lorg/springframework/boot/ssl/SslBundle;)V
      17: goto          27
      20: new           #18                 // class org/springframework/http/client/SimpleClientHttpRequestFactory
      23: dup
      24: invokespecial #20                 // Method org/springframework/http/client/SimpleClientHttpRequestFactory."<init>":()V
      27: astore_2
      28: aload_1
      29: ifnull        46
      32: aload_1
      33: invokeinterface #21,  1           // InterfaceMethod org/springframework/boot/ssl/SslBundle.getOptions:()Lorg/springframework/boot/ssl/SslOptions;
      38: invokeinterface #27,  1           // InterfaceMethod org/springframework/boot/ssl/SslOptions.isSpecified:()Z
      43: ifne          50
      46: iconst_1
      47: goto          51
      50: iconst_0
      51: ldc           #33                 // String SSL Options cannot be specified with Java connections
      53: invokestatic  #35                 // Method org/springframework/util/Assert.state:(ZLjava/lang/String;)V
      56: invokestatic  #41                 // Method org/springframework/boot/context/properties/PropertyMapper.get:()Lorg/springframework/boot/context/properties/PropertyMapper;
      59: invokevirtual #47                 // Method org/springframework/boot/context/properties/PropertyMapper.alwaysApplyingWhenNonNull:()Lorg/springframework/boot/context/properties/PropertyMapper;
      62: astore_3
      63: aload_3
      64: aload_0
      65: dup
      66: invokestatic  #50                 // Method java/util/Objects.requireNonNull:(Ljava/lang/Object;)Ljava/lang/Object;
      69: pop
      70: invokedynamic #56,  0             // InvokeDynamic #0:get:(Lorg/springframework/boot/web/client/ClientHttpRequestFactorySettings;)Ljava/util/function/Supplier;
      75: invokevirtual #59                 // Method org/springframework/boot/context/properties/PropertyMapper.from:(Ljava/util/function/Supplier;)Lorg/springframework/boot/context/properties/PropertyMapper$Source;
      78: invokedynamic #63,  0             // InvokeDynamic #1:apply:()Ljava/util/function/Function;
      83: invokevirtual #67                 // Method org/springframework/boot/context/properties/PropertyMapper$Source.asInt:(Ljava/util/function/Function;)Lorg/springframework/boot/context/properties/PropertyMapper$Source;
      86: aload_2
      87: dup
      88: invokestatic  #50                 // Method java/util/Objects.requireNonNull:(Ljava/lang/Object;)Ljava/lang/Object;
      91: pop
      92: invokedynamic #73,  0             // InvokeDynamic #2:accept:(Lorg/springframework/http/client/SimpleClientHttpRequestFactory;)Ljava/util/function/Consumer;
      97: invokevirtual #77                 // Method org/springframework/boot/context/properties/PropertyMapper$Source.to:(Ljava/util/function/Consumer;)V
     100: aload_3
     101: aload_0
     102: dup
     103: invokestatic  #50                 // Method java/util/Objects.requireNonNull:(Ljava/lang/Object;)Ljava/lang/Object;
     106: pop
     107: invokedynamic #81,  0             // InvokeDynamic #3:get:(Lorg/springframework/boot/web/client/ClientHttpRequestFactorySettings;)Ljava/util/function/Supplier;
     112: invokevirtual #59                 // Method org/springframework/boot/context/properties/PropertyMapper.from:(Ljava/util/function/Supplier;)Lorg/springframework/boot/context/properties/PropertyMapper$Source;
     115: invokedynamic #63,  0             // InvokeDynamic #1:apply:()Ljava/util/function/Function;
     120: invokevirtual #67                 // Method org/springframework/boot/context/properties/PropertyMapper$Source.asInt:(Ljava/util/function/Function;)Lorg/springframework/boot/context/properties/PropertyMapper$Source;
     123: aload_2
     124: dup
     125: invokestatic  #50                 // Method java/util/Objects.requireNonNull:(Ljava/lang/Object;)Ljava/lang/Object;
     128: pop
     129: invokedynamic #82,  0             // InvokeDynamic #4:accept:(Lorg/springframework/http/client/SimpleClientHttpRequestFactory;)Ljava/util/function/Consumer;
     134: invokevirtual #77                 // Method org/springframework/boot/context/properties/PropertyMapper$Source.to:(Ljava/util/function/Consumer;)V
     137: aload_3
     138: aload_0
     139: dup
     140: invokestatic  #50                 // Method java/util/Objects.requireNonNull:(Ljava/lang/Object;)Ljava/lang/Object;
     143: pop
     144: invokedynamic #83,  0             // InvokeDynamic #5:get:(Lorg/springframework/boot/web/client/ClientHttpRequestFactorySettings;)Ljava/util/function/Supplier;
     149: invokevirtual #59                 // Method org/springframework/boot/context/properties/PropertyMapper.from:(Ljava/util/function/Supplier;)Lorg/springframework/boot/context/properties/PropertyMapper$Source;
     152: aload_2
     153: dup
     154: invokestatic  #50                 // Method java/util/Objects.requireNonNull:(Ljava/lang/Object;)Ljava/lang/Object;
     157: pop
     158: invokedynamic #84,  0             // InvokeDynamic #6:accept:(Lorg/springframework/http/client/SimpleClientHttpRequestFactory;)Ljava/util/function/Consumer;
     163: invokevirtual #77                 // Method org/springframework/boot/context/properties/PropertyMapper$Source.to:(Ljava/util/function/Consumer;)V
     166: aload_2
     167: areturn
}
