Compiled from "ClientHttpRequestFactories.java"
public final class org.springframework.boot.web.client.ClientHttpRequestFactories {
  static final java.lang.String APACHE_HTTP_CLIENT_CLASS;

  private static final boolean APACHE_HTTP_CLIENT_PRESENT;

  static final java.lang.String OKHTTP_CLIENT_CLASS;

  private static final boolean OKHTTP_CLIENT_PRESENT;

  private org.springframework.boot.web.client.ClientHttpRequestFactories();
    Code:
       0: aload_0
       1: invokespecial #1                  // Method java/lang/Object."<init>":()V
       4: return

  public static org.springframework.http.client.ClientHttpRequestFactory get(org.springframework.boot.web.client.ClientHttpRequestFactorySettings);
    Code:
       0: aload_0
       1: ldc           #7                  // String Settings must not be null
       3: invokestatic  #9                  // Method org/springframework/util/Assert.notNull:(Ljava/lang/Object;Ljava/lang/String;)V
       6: getstatic     #15                 // Field APACHE_HTTP_CLIENT_PRESENT:Z
       9: ifeq          17
      12: aload_0
      13: invokestatic  #21                 // Method org/springframework/boot/web/client/ClientHttpRequestFactories$HttpComponents.get:(Lorg/springframework/boot/web/client/ClientHttpRequestFactorySettings;)Lorg/springframework/http/client/HttpComponentsClientHttpRequestFactory;
      16: areturn
      17: getstatic     #27                 // Field OKHTTP_CLIENT_PRESENT:Z
      20: ifeq          28
      23: aload_0
      24: invokestatic  #30                 // Method org/springframework/boot/web/client/ClientHttpRequestFactories$OkHttp.get:(Lorg/springframework/boot/web/client/ClientHttpRequestFactorySettings;)Lorg/springframework/http/client/OkHttp3ClientHttpRequestFactory;
      27: areturn
      28: aload_0
      29: invokestatic  #35                 // Method org/springframework/boot/web/client/ClientHttpRequestFactories$Simple.get:(Lorg/springframework/boot/web/client/ClientHttpRequestFactorySettings;)Lorg/springframework/http/client/SimpleClientHttpRequestFactory;
      32: areturn

  public static <T extends org.springframework.http.client.ClientHttpRequestFactory> T get(java.lang.Class<T>, org.springframework.boot.web.client.ClientHttpRequestFactorySettings);
    Code:
       0: aload_1
       1: ldc           #7                  // String Settings must not be null
       3: invokestatic  #9                  // Method org/springframework/util/Assert.notNull:(Ljava/lang/Object;Ljava/lang/String;)V
       6: aload_0
       7: ldc           #40                 // class org/springframework/http/client/ClientHttpRequestFactory
       9: if_acmpne     17
      12: aload_1
      13: invokestatic  #42                 // Method get:(Lorg/springframework/boot/web/client/ClientHttpRequestFactorySettings;)Lorg/springframework/http/client/ClientHttpRequestFactory;
      16: areturn
      17: aload_0
      18: ldc           #45                 // class org/springframework/http/client/HttpComponentsClientHttpRequestFactory
      20: if_acmpne     28
      23: aload_1
      24: invokestatic  #21                 // Method org/springframework/boot/web/client/ClientHttpRequestFactories$HttpComponents.get:(Lorg/springframework/boot/web/client/ClientHttpRequestFactorySettings;)Lorg/springframework/http/client/HttpComponentsClientHttpRequestFactory;
      27: areturn
      28: aload_0
      29: ldc           #47                 // class org/springframework/http/client/OkHttp3ClientHttpRequestFactory
      31: if_acmpne     39
      34: aload_1
      35: invokestatic  #30                 // Method org/springframework/boot/web/client/ClientHttpRequestFactories$OkHttp.get:(Lorg/springframework/boot/web/client/ClientHttpRequestFactorySettings;)Lorg/springframework/http/client/OkHttp3ClientHttpRequestFactory;
      38: areturn
      39: aload_0
      40: ldc           #49                 // class org/springframework/http/client/SimpleClientHttpRequestFactory
      42: if_acmpne     50
      45: aload_1
      46: invokestatic  #35                 // Method org/springframework/boot/web/client/ClientHttpRequestFactories$Simple.get:(Lorg/springframework/boot/web/client/ClientHttpRequestFactorySettings;)Lorg/springframework/http/client/SimpleClientHttpRequestFactory;
      49: areturn
      50: aload_0
      51: invokedynamic #51,  0             // InvokeDynamic #0:get:(Ljava/lang/Class;)Ljava/util/function/Supplier;
      56: aload_1
      57: invokestatic  #54                 // Method get:(Ljava/util/function/Supplier;Lorg/springframework/boot/web/client/ClientHttpRequestFactorySettings;)Lorg/springframework/http/client/ClientHttpRequestFactory;
      60: areturn

  public static <T extends org.springframework.http.client.ClientHttpRequestFactory> T get(java.util.function.Supplier<T>, org.springframework.boot.web.client.ClientHttpRequestFactorySettings);
    Code:
       0: aload_0
       1: aload_1
       2: invokestatic  #57                 // Method org/springframework/boot/web/client/ClientHttpRequestFactories$Reflective.get:(Ljava/util/function/Supplier;Lorg/springframework/boot/web/client/ClientHttpRequestFactorySettings;)Lorg/springframework/http/client/ClientHttpRequestFactory;
       5: areturn

  private static <T extends org.springframework.http.client.ClientHttpRequestFactory> T createRequestFactory(java.lang.Class<T>);
    Code:
       0: aload_0
       1: iconst_0
       2: anewarray     #60                 // class java/lang/Class
       5: invokevirtual #62                 // Method java/lang/Class.getDeclaredConstructor:([Ljava/lang/Class;)Ljava/lang/reflect/Constructor;
       8: astore_1
       9: aload_1
      10: iconst_1
      11: invokevirtual #66                 // Method java/lang/reflect/Constructor.setAccessible:(Z)V
      14: aload_1
      15: iconst_0
      16: anewarray     #2                  // class java/lang/Object
      19: invokevirtual #72                 // Method java/lang/reflect/Constructor.newInstance:([Ljava/lang/Object;)Ljava/lang/Object;
      22: checkcast     #40                 // class org/springframework/http/client/ClientHttpRequestFactory
      25: areturn
      26: astore_1
      27: new           #78                 // class java/lang/IllegalStateException
      30: dup
      31: aload_1
      32: invokespecial #80                 // Method java/lang/IllegalStateException."<init>":(Ljava/lang/Throwable;)V
      35: athrow
    Exception table:
       from    to  target type
           0    25    26   Class java/lang/Exception

  private static org.springframework.http.client.ClientHttpRequestFactory lambda$get$0(java.lang.Class);
    Code:
       0: aload_0
       1: invokestatic  #83                 // Method createRequestFactory:(Ljava/lang/Class;)Lorg/springframework/http/client/ClientHttpRequestFactory;
       4: areturn

  static {};
    Code:
       0: ldc           #87                 // String org.apache.hc.client5.http.impl.classic.HttpClients
       2: aconst_null
       3: invokestatic  #89                 // Method org/springframework/util/ClassUtils.isPresent:(Ljava/lang/String;Ljava/lang/ClassLoader;)Z
       6: putstatic     #15                 // Field APACHE_HTTP_CLIENT_PRESENT:Z
       9: ldc           #95                 // String okhttp3.OkHttpClient
      11: aconst_null
      12: invokestatic  #89                 // Method org/springframework/util/ClassUtils.isPresent:(Ljava/lang/String;Ljava/lang/ClassLoader;)Z
      15: putstatic     #27                 // Field OKHTTP_CLIENT_PRESENT:Z
      18: return
}
