Compiled from "RestTemplateBuilderClientHttpRequestInitializer.java"
class org.springframework.boot.web.client.RestTemplateBuilderClientHttpRequestInitializer implements org.springframework.http.client.ClientHttpRequestInitializer {
  private final org.springframework.boot.web.client.BasicAuthentication basicAuthentication;

  private final java.util.Map<java.lang.String, java.util.List<java.lang.String>> defaultHeaders;

  private final java.util.Set<org.springframework.boot.web.client.RestTemplateRequestCustomizer<?>> requestCustomizers;

  org.springframework.boot.web.client.RestTemplateBuilderClientHttpRequestInitializer(org.springframework.boot.web.client.BasicAuthentication, java.util.Map<java.lang.String, java.util.List<java.lang.String>>, java.util.Set<org.springframework.boot.web.client.RestTemplateRequestCustomizer<?>>);
    Code:
       0: aload_0
       1: invokespecial #1                  // Method java/lang/Object."<init>":()V
       4: aload_0
       5: aload_1
       6: putfield      #7                  // Field basicAuthentication:Lorg/springframework/boot/web/client/BasicAuthentication;
       9: aload_0
      10: aload_2
      11: putfield      #13                 // Field defaultHeaders:Ljava/util/Map;
      14: aload_0
      15: aload_3
      16: putfield      #17                 // Field requestCustomizers:Ljava/util/Set;
      19: return

  public void initialize(org.springframework.http.client.ClientHttpRequest);
    Code:
       0: aload_1
       1: invokeinterface #21,  1           // InterfaceMethod org/springframework/http/client/ClientHttpRequest.getHeaders:()Lorg/springframework/http/HttpHeaders;
       6: astore_2
       7: aload_0
       8: getfield      #7                  // Field basicAuthentication:Lorg/springframework/boot/web/client/BasicAuthentication;
      11: ifnull        22
      14: aload_0
      15: getfield      #7                  // Field basicAuthentication:Lorg/springframework/boot/web/client/BasicAuthentication;
      18: aload_2
      19: invokevirtual #27                 // Method org/springframework/boot/web/client/BasicAuthentication.applyTo:(Lorg/springframework/http/HttpHeaders;)V
      22: aload_0
      23: getfield      #13                 // Field defaultHeaders:Ljava/util/Map;
      26: aload_2
      27: dup
      28: invokestatic  #33                 // Method java/util/Objects.requireNonNull:(Ljava/lang/Object;)Ljava/lang/Object;
      31: pop
      32: invokedynamic #39,  0             // InvokeDynamic #0:accept:(Lorg/springframework/http/HttpHeaders;)Ljava/util/function/BiConsumer;
      37: invokeinterface #43,  2           // InterfaceMethod java/util/Map.forEach:(Ljava/util/function/BiConsumer;)V
      42: ldc           #49                 // class org/springframework/boot/web/client/RestTemplateRequestCustomizer
      44: aload_0
      45: getfield      #17                 // Field requestCustomizers:Ljava/util/Set;
      48: aload_1
      49: iconst_0
      50: anewarray     #2                  // class java/lang/Object
      53: invokestatic  #51                 // Method org/springframework/boot/util/LambdaSafe.callbacks:(Ljava/lang/Class;Ljava/util/Collection;Ljava/lang/Object;[Ljava/lang/Object;)Lorg/springframework/boot/util/LambdaSafe$Callbacks;
      56: aload_1
      57: invokedynamic #57,  0             // InvokeDynamic #1:accept:(Lorg/springframework/http/client/ClientHttpRequest;)Ljava/util/function/Consumer;
      62: invokevirtual #60                 // Method org/springframework/boot/util/LambdaSafe$Callbacks.invoke:(Ljava/util/function/Consumer;)V
      65: return

  private static void lambda$initialize$0(org.springframework.http.client.ClientHttpRequest, org.springframework.boot.web.client.RestTemplateRequestCustomizer);
    Code:
       0: aload_1
       1: aload_0
       2: invokeinterface #66,  2           // InterfaceMethod org/springframework/boot/web/client/RestTemplateRequestCustomizer.customize:(Lorg/springframework/http/client/ClientHttpRequest;)V
       7: return
}
