Compiled from "RestTemplateBuilder.java"
public class org.springframework.boot.web.client.RestTemplateBuilder {
  private final org.springframework.boot.web.client.ClientHttpRequestFactorySettings requestFactorySettings;

  private final boolean detectRequestFactory;

  private final java.lang.String rootUri;

  private final java.util.Set<org.springframework.http.converter.HttpMessageConverter<?>> messageConverters;

  private final java.util.Set<org.springframework.http.client.ClientHttpRequestInterceptor> interceptors;

  private final java.util.function.Function<org.springframework.boot.web.client.ClientHttpRequestFactorySettings, org.springframework.http.client.ClientHttpRequestFactory> requestFactory;

  private final org.springframework.web.util.UriTemplateHandler uriTemplateHandler;

  private final org.springframework.web.client.ResponseErrorHandler errorHandler;

  private final org.springframework.boot.web.client.BasicAuthentication basicAuthentication;

  private final java.util.Map<java.lang.String, java.util.List<java.lang.String>> defaultHeaders;

  private final java.util.Set<org.springframework.boot.web.client.RestTemplateCustomizer> customizers;

  private final java.util.Set<org.springframework.boot.web.client.RestTemplateRequestCustomizer<?>> requestCustomizers;

  public org.springframework.boot.web.client.RestTemplateBuilder(org.springframework.boot.web.client.RestTemplateCustomizer...);
    Code:
       0: aload_0
       1: invokespecial #1                  // Method java/lang/Object."<init>":()V
       4: aload_1
       5: ldc           #7                  // String Customizers must not be null
       7: invokestatic  #9                  // Method org/springframework/util/Assert.notNull:(Ljava/lang/Object;Ljava/lang/String;)V
      10: aload_0
      11: getstatic     #15                 // Field org/springframework/boot/web/client/ClientHttpRequestFactorySettings.DEFAULTS:Lorg/springframework/boot/web/client/ClientHttpRequestFactorySettings;
      14: putfield      #21                 // Field requestFactorySettings:Lorg/springframework/boot/web/client/ClientHttpRequestFactorySettings;
      17: aload_0
      18: iconst_1
      19: putfield      #26                 // Field detectRequestFactory:Z
      22: aload_0
      23: aconst_null
      24: putfield      #30                 // Field rootUri:Ljava/lang/String;
      27: aload_0
      28: aconst_null
      29: putfield      #34                 // Field messageConverters:Ljava/util/Set;
      32: aload_0
      33: invokestatic  #38                 // Method java/util/Collections.emptySet:()Ljava/util/Set;
      36: putfield      #44                 // Field interceptors:Ljava/util/Set;
      39: aload_0
      40: aconst_null
      41: putfield      #47                 // Field requestFactory:Ljava/util/function/Function;
      44: aload_0
      45: aconst_null
      46: putfield      #51                 // Field uriTemplateHandler:Lorg/springframework/web/util/UriTemplateHandler;
      49: aload_0
      50: aconst_null
      51: putfield      #55                 // Field errorHandler:Lorg/springframework/web/client/ResponseErrorHandler;
      54: aload_0
      55: aconst_null
      56: putfield      #59                 // Field basicAuthentication:Lorg/springframework/boot/web/client/BasicAuthentication;
      59: aload_0
      60: invokestatic  #63                 // Method java/util/Collections.emptyMap:()Ljava/util/Map;
      63: putfield      #67                 // Field defaultHeaders:Ljava/util/Map;
      66: aload_0
      67: aload_0
      68: aload_1
      69: invokevirtual #71                 // Method copiedSetOf:([Ljava/lang/Object;)Ljava/util/Set;
      72: putfield      #75                 // Field customizers:Ljava/util/Set;
      75: aload_0
      76: invokestatic  #38                 // Method java/util/Collections.emptySet:()Ljava/util/Set;
      79: putfield      #78                 // Field requestCustomizers:Ljava/util/Set;
      82: return

  private org.springframework.boot.web.client.RestTemplateBuilder(org.springframework.boot.web.client.ClientHttpRequestFactorySettings, boolean, java.lang.String, java.util.Set<org.springframework.http.converter.HttpMessageConverter<?>>, java.util.Set<org.springframework.http.client.ClientHttpRequestInterceptor>, java.util.function.Function<org.springframework.boot.web.client.ClientHttpRequestFactorySettings, org.springframework.http.client.ClientHttpRequestFactory>, org.springframework.web.util.UriTemplateHandler, org.springframework.web.client.ResponseErrorHandler, org.springframework.boot.web.client.BasicAuthentication, java.util.Map<java.lang.String, java.util.List<java.lang.String>>, java.util.Set<org.springframework.boot.web.client.RestTemplateCustomizer>, java.util.Set<org.springframework.boot.web.client.RestTemplateRequestCustomizer<?>>);
    Code:
       0: aload_0
       1: invokespecial #1                  // Method java/lang/Object."<init>":()V
       4: aload_0
       5: aload_1
       6: putfield      #21                 // Field requestFactorySettings:Lorg/springframework/boot/web/client/ClientHttpRequestFactorySettings;
       9: aload_0
      10: iload_2
      11: putfield      #26                 // Field detectRequestFactory:Z
      14: aload_0
      15: aload_3
      16: putfield      #30                 // Field rootUri:Ljava/lang/String;
      19: aload_0
      20: aload         4
      22: putfield      #34                 // Field messageConverters:Ljava/util/Set;
      25: aload_0
      26: aload         5
      28: putfield      #44                 // Field interceptors:Ljava/util/Set;
      31: aload_0
      32: aload         6
      34: putfield      #47                 // Field requestFactory:Ljava/util/function/Function;
      37: aload_0
      38: aload         7
      40: putfield      #51                 // Field uriTemplateHandler:Lorg/springframework/web/util/UriTemplateHandler;
      43: aload_0
      44: aload         8
      46: putfield      #55                 // Field errorHandler:Lorg/springframework/web/client/ResponseErrorHandler;
      49: aload_0
      50: aload         9
      52: putfield      #59                 // Field basicAuthentication:Lorg/springframework/boot/web/client/BasicAuthentication;
      55: aload_0
      56: aload         10
      58: putfield      #67                 // Field defaultHeaders:Ljava/util/Map;
      61: aload_0
      62: aload         11
      64: putfield      #75                 // Field customizers:Ljava/util/Set;
      67: aload_0
      68: aload         12
      70: putfield      #78                 // Field requestCustomizers:Ljava/util/Set;
      73: return

  public org.springframework.boot.web.client.RestTemplateBuilder detectRequestFactory(boolean);
    Code:
       0: new           #22                 // class org/springframework/boot/web/client/RestTemplateBuilder
       3: dup
       4: aload_0
       5: getfield      #21                 // Field requestFactorySettings:Lorg/springframework/boot/web/client/ClientHttpRequestFactorySettings;
       8: iload_1
       9: aload_0
      10: getfield      #30                 // Field rootUri:Ljava/lang/String;
      13: aload_0
      14: getfield      #34                 // Field messageConverters:Ljava/util/Set;
      17: aload_0
      18: getfield      #44                 // Field interceptors:Ljava/util/Set;
      21: aload_0
      22: getfield      #47                 // Field requestFactory:Ljava/util/function/Function;
      25: aload_0
      26: getfield      #51                 // Field uriTemplateHandler:Lorg/springframework/web/util/UriTemplateHandler;
      29: aload_0
      30: getfield      #55                 // Field errorHandler:Lorg/springframework/web/client/ResponseErrorHandler;
      33: aload_0
      34: getfield      #59                 // Field basicAuthentication:Lorg/springframework/boot/web/client/BasicAuthentication;
      37: aload_0
      38: getfield      #67                 // Field defaultHeaders:Ljava/util/Map;
      41: aload_0
      42: getfield      #75                 // Field customizers:Ljava/util/Set;
      45: aload_0
      46: getfield      #78                 // Field requestCustomizers:Ljava/util/Set;
      49: invokespecial #81                 // Method "<init>":(Lorg/springframework/boot/web/client/ClientHttpRequestFactorySettings;ZLjava/lang/String;Ljava/util/Set;Ljava/util/Set;Ljava/util/function/Function;Lorg/springframework/web/util/UriTemplateHandler;Lorg/springframework/web/client/ResponseErrorHandler;Lorg/springframework/boot/web/client/BasicAuthentication;Ljava/util/Map;Ljava/util/Set;Ljava/util/Set;)V
      52: areturn

  public org.springframework.boot.web.client.RestTemplateBuilder rootUri(java.lang.String);
    Code:
       0: new           #22                 // class org/springframework/boot/web/client/RestTemplateBuilder
       3: dup
       4: aload_0
       5: getfield      #21                 // Field requestFactorySettings:Lorg/springframework/boot/web/client/ClientHttpRequestFactorySettings;
       8: aload_0
       9: getfield      #26                 // Field detectRequestFactory:Z
      12: aload_1
      13: aload_0
      14: getfield      #34                 // Field messageConverters:Ljava/util/Set;
      17: aload_0
      18: getfield      #44                 // Field interceptors:Ljava/util/Set;
      21: aload_0
      22: getfield      #47                 // Field requestFactory:Ljava/util/function/Function;
      25: aload_0
      26: getfield      #51                 // Field uriTemplateHandler:Lorg/springframework/web/util/UriTemplateHandler;
      29: aload_0
      30: getfield      #55                 // Field errorHandler:Lorg/springframework/web/client/ResponseErrorHandler;
      33: aload_0
      34: getfield      #59                 // Field basicAuthentication:Lorg/springframework/boot/web/client/BasicAuthentication;
      37: aload_0
      38: getfield      #67                 // Field defaultHeaders:Ljava/util/Map;
      41: aload_0
      42: getfield      #75                 // Field customizers:Ljava/util/Set;
      45: aload_0
      46: getfield      #78                 // Field requestCustomizers:Ljava/util/Set;
      49: invokespecial #81                 // Method "<init>":(Lorg/springframework/boot/web/client/ClientHttpRequestFactorySettings;ZLjava/lang/String;Ljava/util/Set;Ljava/util/Set;Ljava/util/function/Function;Lorg/springframework/web/util/UriTemplateHandler;Lorg/springframework/web/client/ResponseErrorHandler;Lorg/springframework/boot/web/client/BasicAuthentication;Ljava/util/Map;Ljava/util/Set;Ljava/util/Set;)V
      52: areturn

  public org.springframework.boot.web.client.RestTemplateBuilder messageConverters(org.springframework.http.converter.HttpMessageConverter<?>...);
    Code:
       0: aload_1
       1: ldc           #84                 // String MessageConverters must not be null
       3: invokestatic  #9                  // Method org/springframework/util/Assert.notNull:(Ljava/lang/Object;Ljava/lang/String;)V
       6: aload_0
       7: aload_1
       8: invokestatic  #86                 // Method java/util/Arrays.asList:([Ljava/lang/Object;)Ljava/util/List;
      11: invokevirtual #92                 // Method messageConverters:(Ljava/util/Collection;)Lorg/springframework/boot/web/client/RestTemplateBuilder;
      14: areturn

  public org.springframework.boot.web.client.RestTemplateBuilder messageConverters(java.util.Collection<? extends org.springframework.http.converter.HttpMessageConverter<?>>);
    Code:
       0: aload_1
       1: ldc           #84                 // String MessageConverters must not be null
       3: invokestatic  #9                  // Method org/springframework/util/Assert.notNull:(Ljava/lang/Object;Ljava/lang/String;)V
       6: new           #22                 // class org/springframework/boot/web/client/RestTemplateBuilder
       9: dup
      10: aload_0
      11: getfield      #21                 // Field requestFactorySettings:Lorg/springframework/boot/web/client/ClientHttpRequestFactorySettings;
      14: aload_0
      15: getfield      #26                 // Field detectRequestFactory:Z
      18: aload_0
      19: getfield      #30                 // Field rootUri:Ljava/lang/String;
      22: aload_0
      23: aload_1
      24: invokevirtual #95                 // Method copiedSetOf:(Ljava/util/Collection;)Ljava/util/Set;
      27: aload_0
      28: getfield      #44                 // Field interceptors:Ljava/util/Set;
      31: aload_0
      32: getfield      #47                 // Field requestFactory:Ljava/util/function/Function;
      35: aload_0
      36: getfield      #51                 // Field uriTemplateHandler:Lorg/springframework/web/util/UriTemplateHandler;
      39: aload_0
      40: getfield      #55                 // Field errorHandler:Lorg/springframework/web/client/ResponseErrorHandler;
      43: aload_0
      44: getfield      #59                 // Field basicAuthentication:Lorg/springframework/boot/web/client/BasicAuthentication;
      47: aload_0
      48: getfield      #67                 // Field defaultHeaders:Ljava/util/Map;
      51: aload_0
      52: getfield      #75                 // Field customizers:Ljava/util/Set;
      55: aload_0
      56: getfield      #78                 // Field requestCustomizers:Ljava/util/Set;
      59: invokespecial #81                 // Method "<init>":(Lorg/springframework/boot/web/client/ClientHttpRequestFactorySettings;ZLjava/lang/String;Ljava/util/Set;Ljava/util/Set;Ljava/util/function/Function;Lorg/springframework/web/util/UriTemplateHandler;Lorg/springframework/web/client/ResponseErrorHandler;Lorg/springframework/boot/web/client/BasicAuthentication;Ljava/util/Map;Ljava/util/Set;Ljava/util/Set;)V
      62: areturn

  public org.springframework.boot.web.client.RestTemplateBuilder additionalMessageConverters(org.springframework.http.converter.HttpMessageConverter<?>...);
    Code:
       0: aload_1
       1: ldc           #84                 // String MessageConverters must not be null
       3: invokestatic  #9                  // Method org/springframework/util/Assert.notNull:(Ljava/lang/Object;Ljava/lang/String;)V
       6: aload_0
       7: aload_1
       8: invokestatic  #86                 // Method java/util/Arrays.asList:([Ljava/lang/Object;)Ljava/util/List;
      11: invokevirtual #98                 // Method additionalMessageConverters:(Ljava/util/Collection;)Lorg/springframework/boot/web/client/RestTemplateBuilder;
      14: areturn

  public org.springframework.boot.web.client.RestTemplateBuilder additionalMessageConverters(java.util.Collection<? extends org.springframework.http.converter.HttpMessageConverter<?>>);
    Code:
       0: aload_1
       1: ldc           #84                 // String MessageConverters must not be null
       3: invokestatic  #9                  // Method org/springframework/util/Assert.notNull:(Ljava/lang/Object;Ljava/lang/String;)V
       6: new           #22                 // class org/springframework/boot/web/client/RestTemplateBuilder
       9: dup
      10: aload_0
      11: getfield      #21                 // Field requestFactorySettings:Lorg/springframework/boot/web/client/ClientHttpRequestFactorySettings;
      14: aload_0
      15: getfield      #26                 // Field detectRequestFactory:Z
      18: aload_0
      19: getfield      #30                 // Field rootUri:Ljava/lang/String;
      22: aload_0
      23: getfield      #34                 // Field messageConverters:Ljava/util/Set;
      26: aload_1
      27: invokestatic  #101                // Method append:(Ljava/util/Collection;Ljava/util/Collection;)Ljava/util/Set;
      30: aload_0
      31: getfield      #44                 // Field interceptors:Ljava/util/Set;
      34: aload_0
      35: getfield      #47                 // Field requestFactory:Ljava/util/function/Function;
      38: aload_0
      39: getfield      #51                 // Field uriTemplateHandler:Lorg/springframework/web/util/UriTemplateHandler;
      42: aload_0
      43: getfield      #55                 // Field errorHandler:Lorg/springframework/web/client/ResponseErrorHandler;
      46: aload_0
      47: getfield      #59                 // Field basicAuthentication:Lorg/springframework/boot/web/client/BasicAuthentication;
      50: aload_0
      51: getfield      #67                 // Field defaultHeaders:Ljava/util/Map;
      54: aload_0
      55: getfield      #75                 // Field customizers:Ljava/util/Set;
      58: aload_0
      59: getfield      #78                 // Field requestCustomizers:Ljava/util/Set;
      62: invokespecial #81                 // Method "<init>":(Lorg/springframework/boot/web/client/ClientHttpRequestFactorySettings;ZLjava/lang/String;Ljava/util/Set;Ljava/util/Set;Ljava/util/function/Function;Lorg/springframework/web/util/UriTemplateHandler;Lorg/springframework/web/client/ResponseErrorHandler;Lorg/springframework/boot/web/client/BasicAuthentication;Ljava/util/Map;Ljava/util/Set;Ljava/util/Set;)V
      65: areturn

  public org.springframework.boot.web.client.RestTemplateBuilder defaultMessageConverters();
    Code:
       0: new           #22                 // class org/springframework/boot/web/client/RestTemplateBuilder
       3: dup
       4: aload_0
       5: getfield      #21                 // Field requestFactorySettings:Lorg/springframework/boot/web/client/ClientHttpRequestFactorySettings;
       8: aload_0
       9: getfield      #26                 // Field detectRequestFactory:Z
      12: aload_0
      13: getfield      #30                 // Field rootUri:Ljava/lang/String;
      16: aload_0
      17: new           #105                // class org/springframework/web/client/RestTemplate
      20: dup
      21: invokespecial #107                // Method org/springframework/web/client/RestTemplate."<init>":()V
      24: invokevirtual #108                // Method org/springframework/web/client/RestTemplate.getMessageConverters:()Ljava/util/List;
      27: invokevirtual #95                 // Method copiedSetOf:(Ljava/util/Collection;)Ljava/util/Set;
      30: aload_0
      31: getfield      #44                 // Field interceptors:Ljava/util/Set;
      34: aload_0
      35: getfield      #47                 // Field requestFactory:Ljava/util/function/Function;
      38: aload_0
      39: getfield      #51                 // Field uriTemplateHandler:Lorg/springframework/web/util/UriTemplateHandler;
      42: aload_0
      43: getfield      #55                 // Field errorHandler:Lorg/springframework/web/client/ResponseErrorHandler;
      46: aload_0
      47: getfield      #59                 // Field basicAuthentication:Lorg/springframework/boot/web/client/BasicAuthentication;
      50: aload_0
      51: getfield      #67                 // Field defaultHeaders:Ljava/util/Map;
      54: aload_0
      55: getfield      #75                 // Field customizers:Ljava/util/Set;
      58: aload_0
      59: getfield      #78                 // Field requestCustomizers:Ljava/util/Set;
      62: invokespecial #81                 // Method "<init>":(Lorg/springframework/boot/web/client/ClientHttpRequestFactorySettings;ZLjava/lang/String;Ljava/util/Set;Ljava/util/Set;Ljava/util/function/Function;Lorg/springframework/web/util/UriTemplateHandler;Lorg/springframework/web/client/ResponseErrorHandler;Lorg/springframework/boot/web/client/BasicAuthentication;Ljava/util/Map;Ljava/util/Set;Ljava/util/Set;)V
      65: areturn

  public org.springframework.boot.web.client.RestTemplateBuilder interceptors(org.springframework.http.client.ClientHttpRequestInterceptor...);
    Code:
       0: aload_1
       1: ldc           #112                // String interceptors must not be null
       3: invokestatic  #9                  // Method org/springframework/util/Assert.notNull:(Ljava/lang/Object;Ljava/lang/String;)V
       6: aload_0
       7: aload_1
       8: invokestatic  #86                 // Method java/util/Arrays.asList:([Ljava/lang/Object;)Ljava/util/List;
      11: invokevirtual #114                // Method interceptors:(Ljava/util/Collection;)Lorg/springframework/boot/web/client/RestTemplateBuilder;
      14: areturn

  public org.springframework.boot.web.client.RestTemplateBuilder interceptors(java.util.Collection<org.springframework.http.client.ClientHttpRequestInterceptor>);
    Code:
       0: aload_1
       1: ldc           #112                // String interceptors must not be null
       3: invokestatic  #9                  // Method org/springframework/util/Assert.notNull:(Ljava/lang/Object;Ljava/lang/String;)V
       6: new           #22                 // class org/springframework/boot/web/client/RestTemplateBuilder
       9: dup
      10: aload_0
      11: getfield      #21                 // Field requestFactorySettings:Lorg/springframework/boot/web/client/ClientHttpRequestFactorySettings;
      14: aload_0
      15: getfield      #26                 // Field detectRequestFactory:Z
      18: aload_0
      19: getfield      #30                 // Field rootUri:Ljava/lang/String;
      22: aload_0
      23: getfield      #34                 // Field messageConverters:Ljava/util/Set;
      26: aload_0
      27: aload_1
      28: invokevirtual #95                 // Method copiedSetOf:(Ljava/util/Collection;)Ljava/util/Set;
      31: aload_0
      32: getfield      #47                 // Field requestFactory:Ljava/util/function/Function;
      35: aload_0
      36: getfield      #51                 // Field uriTemplateHandler:Lorg/springframework/web/util/UriTemplateHandler;
      39: aload_0
      40: getfield      #55                 // Field errorHandler:Lorg/springframework/web/client/ResponseErrorHandler;
      43: aload_0
      44: getfield      #59                 // Field basicAuthentication:Lorg/springframework/boot/web/client/BasicAuthentication;
      47: aload_0
      48: getfield      #67                 // Field defaultHeaders:Ljava/util/Map;
      51: aload_0
      52: getfield      #75                 // Field customizers:Ljava/util/Set;
      55: aload_0
      56: getfield      #78                 // Field requestCustomizers:Ljava/util/Set;
      59: invokespecial #81                 // Method "<init>":(Lorg/springframework/boot/web/client/ClientHttpRequestFactorySettings;ZLjava/lang/String;Ljava/util/Set;Ljava/util/Set;Ljava/util/function/Function;Lorg/springframework/web/util/UriTemplateHandler;Lorg/springframework/web/client/ResponseErrorHandler;Lorg/springframework/boot/web/client/BasicAuthentication;Ljava/util/Map;Ljava/util/Set;Ljava/util/Set;)V
      62: areturn

  public org.springframework.boot.web.client.RestTemplateBuilder additionalInterceptors(org.springframework.http.client.ClientHttpRequestInterceptor...);
    Code:
       0: aload_1
       1: ldc           #112                // String interceptors must not be null
       3: invokestatic  #9                  // Method org/springframework/util/Assert.notNull:(Ljava/lang/Object;Ljava/lang/String;)V
       6: aload_0
       7: aload_1
       8: invokestatic  #86                 // Method java/util/Arrays.asList:([Ljava/lang/Object;)Ljava/util/List;
      11: invokevirtual #116                // Method additionalInterceptors:(Ljava/util/Collection;)Lorg/springframework/boot/web/client/RestTemplateBuilder;
      14: areturn

  public org.springframework.boot.web.client.RestTemplateBuilder additionalInterceptors(java.util.Collection<? extends org.springframework.http.client.ClientHttpRequestInterceptor>);
    Code:
       0: aload_1
       1: ldc           #112                // String interceptors must not be null
       3: invokestatic  #9                  // Method org/springframework/util/Assert.notNull:(Ljava/lang/Object;Ljava/lang/String;)V
       6: new           #22                 // class org/springframework/boot/web/client/RestTemplateBuilder
       9: dup
      10: aload_0
      11: getfield      #21                 // Field requestFactorySettings:Lorg/springframework/boot/web/client/ClientHttpRequestFactorySettings;
      14: aload_0
      15: getfield      #26                 // Field detectRequestFactory:Z
      18: aload_0
      19: getfield      #30                 // Field rootUri:Ljava/lang/String;
      22: aload_0
      23: getfield      #34                 // Field messageConverters:Ljava/util/Set;
      26: aload_0
      27: getfield      #44                 // Field interceptors:Ljava/util/Set;
      30: aload_1
      31: invokestatic  #101                // Method append:(Ljava/util/Collection;Ljava/util/Collection;)Ljava/util/Set;
      34: aload_0
      35: getfield      #47                 // Field requestFactory:Ljava/util/function/Function;
      38: aload_0
      39: getfield      #51                 // Field uriTemplateHandler:Lorg/springframework/web/util/UriTemplateHandler;
      42: aload_0
      43: getfield      #55                 // Field errorHandler:Lorg/springframework/web/client/ResponseErrorHandler;
      46: aload_0
      47: getfield      #59                 // Field basicAuthentication:Lorg/springframework/boot/web/client/BasicAuthentication;
      50: aload_0
      51: getfield      #67                 // Field defaultHeaders:Ljava/util/Map;
      54: aload_0
      55: getfield      #75                 // Field customizers:Ljava/util/Set;
      58: aload_0
      59: getfield      #78                 // Field requestCustomizers:Ljava/util/Set;
      62: invokespecial #81                 // Method "<init>":(Lorg/springframework/boot/web/client/ClientHttpRequestFactorySettings;ZLjava/lang/String;Ljava/util/Set;Ljava/util/Set;Ljava/util/function/Function;Lorg/springframework/web/util/UriTemplateHandler;Lorg/springframework/web/client/ResponseErrorHandler;Lorg/springframework/boot/web/client/BasicAuthentication;Ljava/util/Map;Ljava/util/Set;Ljava/util/Set;)V
      65: areturn

  public org.springframework.boot.web.client.RestTemplateBuilder requestFactory(java.lang.Class<? extends org.springframework.http.client.ClientHttpRequestFactory>);
    Code:
       0: aload_1
       1: ldc           #119                // String RequestFactoryType must not be null
       3: invokestatic  #9                  // Method org/springframework/util/Assert.notNull:(Ljava/lang/Object;Ljava/lang/String;)V
       6: aload_0
       7: aload_1
       8: invokedynamic #121,  0            // InvokeDynamic #0:apply:(Ljava/lang/Class;)Ljava/util/function/Function;
      13: invokevirtual #125                // Method requestFactory:(Ljava/util/function/Function;)Lorg/springframework/boot/web/client/RestTemplateBuilder;
      16: areturn

  public org.springframework.boot.web.client.RestTemplateBuilder requestFactory(java.util.function.Supplier<org.springframework.http.client.ClientHttpRequestFactory>);
    Code:
       0: aload_1
       1: ldc           #128                // String RequestFactorySupplier must not be null
       3: invokestatic  #9                  // Method org/springframework/util/Assert.notNull:(Ljava/lang/Object;Ljava/lang/String;)V
       6: aload_0
       7: aload_1
       8: invokedynamic #130,  0            // InvokeDynamic #1:apply:(Ljava/util/function/Supplier;)Ljava/util/function/Function;
      13: invokevirtual #125                // Method requestFactory:(Ljava/util/function/Function;)Lorg/springframework/boot/web/client/RestTemplateBuilder;
      16: areturn

  public org.springframework.boot.web.client.RestTemplateBuilder requestFactory(java.util.function.Function<org.springframework.boot.web.client.ClientHttpRequestFactorySettings, org.springframework.http.client.ClientHttpRequestFactory>);
    Code:
       0: aload_1
       1: ldc           #133                // String RequestFactoryFunction must not be null
       3: invokestatic  #9                  // Method org/springframework/util/Assert.notNull:(Ljava/lang/Object;Ljava/lang/String;)V
       6: new           #22                 // class org/springframework/boot/web/client/RestTemplateBuilder
       9: dup
      10: aload_0
      11: getfield      #21                 // Field requestFactorySettings:Lorg/springframework/boot/web/client/ClientHttpRequestFactorySettings;
      14: aload_0
      15: getfield      #26                 // Field detectRequestFactory:Z
      18: aload_0
      19: getfield      #30                 // Field rootUri:Ljava/lang/String;
      22: aload_0
      23: getfield      #34                 // Field messageConverters:Ljava/util/Set;
      26: aload_0
      27: getfield      #44                 // Field interceptors:Ljava/util/Set;
      30: aload_1
      31: aload_0
      32: getfield      #51                 // Field uriTemplateHandler:Lorg/springframework/web/util/UriTemplateHandler;
      35: aload_0
      36: getfield      #55                 // Field errorHandler:Lorg/springframework/web/client/ResponseErrorHandler;
      39: aload_0
      40: getfield      #59                 // Field basicAuthentication:Lorg/springframework/boot/web/client/BasicAuthentication;
      43: aload_0
      44: getfield      #67                 // Field defaultHeaders:Ljava/util/Map;
      47: aload_0
      48: getfield      #75                 // Field customizers:Ljava/util/Set;
      51: aload_0
      52: getfield      #78                 // Field requestCustomizers:Ljava/util/Set;
      55: invokespecial #81                 // Method "<init>":(Lorg/springframework/boot/web/client/ClientHttpRequestFactorySettings;ZLjava/lang/String;Ljava/util/Set;Ljava/util/Set;Ljava/util/function/Function;Lorg/springframework/web/util/UriTemplateHandler;Lorg/springframework/web/client/ResponseErrorHandler;Lorg/springframework/boot/web/client/BasicAuthentication;Ljava/util/Map;Ljava/util/Set;Ljava/util/Set;)V
      58: areturn

  public org.springframework.boot.web.client.RestTemplateBuilder uriTemplateHandler(org.springframework.web.util.UriTemplateHandler);
    Code:
       0: aload_1
       1: ldc           #135                // String UriTemplateHandler must not be null
       3: invokestatic  #9                  // Method org/springframework/util/Assert.notNull:(Ljava/lang/Object;Ljava/lang/String;)V
       6: new           #22                 // class org/springframework/boot/web/client/RestTemplateBuilder
       9: dup
      10: aload_0
      11: getfield      #21                 // Field requestFactorySettings:Lorg/springframework/boot/web/client/ClientHttpRequestFactorySettings;
      14: aload_0
      15: getfield      #26                 // Field detectRequestFactory:Z
      18: aload_0
      19: getfield      #30                 // Field rootUri:Ljava/lang/String;
      22: aload_0
      23: getfield      #34                 // Field messageConverters:Ljava/util/Set;
      26: aload_0
      27: getfield      #44                 // Field interceptors:Ljava/util/Set;
      30: aload_0
      31: getfield      #47                 // Field requestFactory:Ljava/util/function/Function;
      34: aload_1
      35: aload_0
      36: getfield      #55                 // Field errorHandler:Lorg/springframework/web/client/ResponseErrorHandler;
      39: aload_0
      40: getfield      #59                 // Field basicAuthentication:Lorg/springframework/boot/web/client/BasicAuthentication;
      43: aload_0
      44: getfield      #67                 // Field defaultHeaders:Ljava/util/Map;
      47: aload_0
      48: getfield      #75                 // Field customizers:Ljava/util/Set;
      51: aload_0
      52: getfield      #78                 // Field requestCustomizers:Ljava/util/Set;
      55: invokespecial #81                 // Method "<init>":(Lorg/springframework/boot/web/client/ClientHttpRequestFactorySettings;ZLjava/lang/String;Ljava/util/Set;Ljava/util/Set;Ljava/util/function/Function;Lorg/springframework/web/util/UriTemplateHandler;Lorg/springframework/web/client/ResponseErrorHandler;Lorg/springframework/boot/web/client/BasicAuthentication;Ljava/util/Map;Ljava/util/Set;Ljava/util/Set;)V
      58: areturn

  public org.springframework.boot.web.client.RestTemplateBuilder errorHandler(org.springframework.web.client.ResponseErrorHandler);
    Code:
       0: aload_1
       1: ldc           #137                // String ErrorHandler must not be null
       3: invokestatic  #9                  // Method org/springframework/util/Assert.notNull:(Ljava/lang/Object;Ljava/lang/String;)V
       6: new           #22                 // class org/springframework/boot/web/client/RestTemplateBuilder
       9: dup
      10: aload_0
      11: getfield      #21                 // Field requestFactorySettings:Lorg/springframework/boot/web/client/ClientHttpRequestFactorySettings;
      14: aload_0
      15: getfield      #26                 // Field detectRequestFactory:Z
      18: aload_0
      19: getfield      #30                 // Field rootUri:Ljava/lang/String;
      22: aload_0
      23: getfield      #34                 // Field messageConverters:Ljava/util/Set;
      26: aload_0
      27: getfield      #44                 // Field interceptors:Ljava/util/Set;
      30: aload_0
      31: getfield      #47                 // Field requestFactory:Ljava/util/function/Function;
      34: aload_0
      35: getfield      #51                 // Field uriTemplateHandler:Lorg/springframework/web/util/UriTemplateHandler;
      38: aload_1
      39: aload_0
      40: getfield      #59                 // Field basicAuthentication:Lorg/springframework/boot/web/client/BasicAuthentication;
      43: aload_0
      44: getfield      #67                 // Field defaultHeaders:Ljava/util/Map;
      47: aload_0
      48: getfield      #75                 // Field customizers:Ljava/util/Set;
      51: aload_0
      52: getfield      #78                 // Field requestCustomizers:Ljava/util/Set;
      55: invokespecial #81                 // Method "<init>":(Lorg/springframework/boot/web/client/ClientHttpRequestFactorySettings;ZLjava/lang/String;Ljava/util/Set;Ljava/util/Set;Ljava/util/function/Function;Lorg/springframework/web/util/UriTemplateHandler;Lorg/springframework/web/client/ResponseErrorHandler;Lorg/springframework/boot/web/client/BasicAuthentication;Ljava/util/Map;Ljava/util/Set;Ljava/util/Set;)V
      58: areturn

  public org.springframework.boot.web.client.RestTemplateBuilder basicAuthentication(java.lang.String, java.lang.String);
    Code:
       0: aload_0
       1: aload_1
       2: aload_2
       3: aconst_null
       4: invokevirtual #139                // Method basicAuthentication:(Ljava/lang/String;Ljava/lang/String;Ljava/nio/charset/Charset;)Lorg/springframework/boot/web/client/RestTemplateBuilder;
       7: areturn

  public org.springframework.boot.web.client.RestTemplateBuilder basicAuthentication(java.lang.String, java.lang.String, java.nio.charset.Charset);
    Code:
       0: new           #22                 // class org/springframework/boot/web/client/RestTemplateBuilder
       3: dup
       4: aload_0
       5: getfield      #21                 // Field requestFactorySettings:Lorg/springframework/boot/web/client/ClientHttpRequestFactorySettings;
       8: aload_0
       9: getfield      #26                 // Field detectRequestFactory:Z
      12: aload_0
      13: getfield      #30                 // Field rootUri:Ljava/lang/String;
      16: aload_0
      17: getfield      #34                 // Field messageConverters:Ljava/util/Set;
      20: aload_0
      21: getfield      #44                 // Field interceptors:Ljava/util/Set;
      24: aload_0
      25: getfield      #47                 // Field requestFactory:Ljava/util/function/Function;
      28: aload_0
      29: getfield      #51                 // Field uriTemplateHandler:Lorg/springframework/web/util/UriTemplateHandler;
      32: aload_0
      33: getfield      #55                 // Field errorHandler:Lorg/springframework/web/client/ResponseErrorHandler;
      36: new           #142                // class org/springframework/boot/web/client/BasicAuthentication
      39: dup
      40: aload_1
      41: aload_2
      42: aload_3
      43: invokespecial #144                // Method org/springframework/boot/web/client/BasicAuthentication."<init>":(Ljava/lang/String;Ljava/lang/String;Ljava/nio/charset/Charset;)V
      46: aload_0
      47: getfield      #67                 // Field defaultHeaders:Ljava/util/Map;
      50: aload_0
      51: getfield      #75                 // Field customizers:Ljava/util/Set;
      54: aload_0
      55: getfield      #78                 // Field requestCustomizers:Ljava/util/Set;
      58: invokespecial #81                 // Method "<init>":(Lorg/springframework/boot/web/client/ClientHttpRequestFactorySettings;ZLjava/lang/String;Ljava/util/Set;Ljava/util/Set;Ljava/util/function/Function;Lorg/springframework/web/util/UriTemplateHandler;Lorg/springframework/web/client/ResponseErrorHandler;Lorg/springframework/boot/web/client/BasicAuthentication;Ljava/util/Map;Ljava/util/Set;Ljava/util/Set;)V
      61: areturn

  public org.springframework.boot.web.client.RestTemplateBuilder defaultHeader(java.lang.String, java.lang.String...);
    Code:
       0: aload_1
       1: ldc           #147                // String Name must not be null
       3: invokestatic  #9                  // Method org/springframework/util/Assert.notNull:(Ljava/lang/Object;Ljava/lang/String;)V
       6: aload_2
       7: ldc           #149                // String Values must not be null
       9: invokestatic  #9                  // Method org/springframework/util/Assert.notNull:(Ljava/lang/Object;Ljava/lang/String;)V
      12: new           #22                 // class org/springframework/boot/web/client/RestTemplateBuilder
      15: dup
      16: aload_0
      17: getfield      #21                 // Field requestFactorySettings:Lorg/springframework/boot/web/client/ClientHttpRequestFactorySettings;
      20: aload_0
      21: getfield      #26                 // Field detectRequestFactory:Z
      24: aload_0
      25: getfield      #30                 // Field rootUri:Ljava/lang/String;
      28: aload_0
      29: getfield      #34                 // Field messageConverters:Ljava/util/Set;
      32: aload_0
      33: getfield      #44                 // Field interceptors:Ljava/util/Set;
      36: aload_0
      37: getfield      #47                 // Field requestFactory:Ljava/util/function/Function;
      40: aload_0
      41: getfield      #51                 // Field uriTemplateHandler:Lorg/springframework/web/util/UriTemplateHandler;
      44: aload_0
      45: getfield      #55                 // Field errorHandler:Lorg/springframework/web/client/ResponseErrorHandler;
      48: aload_0
      49: getfield      #59                 // Field basicAuthentication:Lorg/springframework/boot/web/client/BasicAuthentication;
      52: aload_0
      53: getfield      #67                 // Field defaultHeaders:Ljava/util/Map;
      56: aload_1
      57: aload_2
      58: invokestatic  #151                // Method append:(Ljava/util/Map;Ljava/lang/Object;[Ljava/lang/Object;)Ljava/util/Map;
      61: aload_0
      62: getfield      #75                 // Field customizers:Ljava/util/Set;
      65: aload_0
      66: getfield      #78                 // Field requestCustomizers:Ljava/util/Set;
      69: invokespecial #81                 // Method "<init>":(Lorg/springframework/boot/web/client/ClientHttpRequestFactorySettings;ZLjava/lang/String;Ljava/util/Set;Ljava/util/Set;Ljava/util/function/Function;Lorg/springframework/web/util/UriTemplateHandler;Lorg/springframework/web/client/ResponseErrorHandler;Lorg/springframework/boot/web/client/BasicAuthentication;Ljava/util/Map;Ljava/util/Set;Ljava/util/Set;)V
      72: areturn

  public org.springframework.boot.web.client.RestTemplateBuilder setConnectTimeout(java.time.Duration);
    Code:
       0: new           #22                 // class org/springframework/boot/web/client/RestTemplateBuilder
       3: dup
       4: aload_0
       5: getfield      #21                 // Field requestFactorySettings:Lorg/springframework/boot/web/client/ClientHttpRequestFactorySettings;
       8: aload_1
       9: invokevirtual #154                // Method org/springframework/boot/web/client/ClientHttpRequestFactorySettings.withConnectTimeout:(Ljava/time/Duration;)Lorg/springframework/boot/web/client/ClientHttpRequestFactorySettings;
      12: aload_0
      13: getfield      #26                 // Field detectRequestFactory:Z
      16: aload_0
      17: getfield      #30                 // Field rootUri:Ljava/lang/String;
      20: aload_0
      21: getfield      #34                 // Field messageConverters:Ljava/util/Set;
      24: aload_0
      25: getfield      #44                 // Field interceptors:Ljava/util/Set;
      28: aload_0
      29: getfield      #47                 // Field requestFactory:Ljava/util/function/Function;
      32: aload_0
      33: getfield      #51                 // Field uriTemplateHandler:Lorg/springframework/web/util/UriTemplateHandler;
      36: aload_0
      37: getfield      #55                 // Field errorHandler:Lorg/springframework/web/client/ResponseErrorHandler;
      40: aload_0
      41: getfield      #59                 // Field basicAuthentication:Lorg/springframework/boot/web/client/BasicAuthentication;
      44: aload_0
      45: getfield      #67                 // Field defaultHeaders:Ljava/util/Map;
      48: aload_0
      49: getfield      #75                 // Field customizers:Ljava/util/Set;
      52: aload_0
      53: getfield      #78                 // Field requestCustomizers:Ljava/util/Set;
      56: invokespecial #81                 // Method "<init>":(Lorg/springframework/boot/web/client/ClientHttpRequestFactorySettings;ZLjava/lang/String;Ljava/util/Set;Ljava/util/Set;Ljava/util/function/Function;Lorg/springframework/web/util/UriTemplateHandler;Lorg/springframework/web/client/ResponseErrorHandler;Lorg/springframework/boot/web/client/BasicAuthentication;Ljava/util/Map;Ljava/util/Set;Ljava/util/Set;)V
      59: areturn

  public org.springframework.boot.web.client.RestTemplateBuilder setReadTimeout(java.time.Duration);
    Code:
       0: new           #22                 // class org/springframework/boot/web/client/RestTemplateBuilder
       3: dup
       4: aload_0
       5: getfield      #21                 // Field requestFactorySettings:Lorg/springframework/boot/web/client/ClientHttpRequestFactorySettings;
       8: aload_1
       9: invokevirtual #158                // Method org/springframework/boot/web/client/ClientHttpRequestFactorySettings.withReadTimeout:(Ljava/time/Duration;)Lorg/springframework/boot/web/client/ClientHttpRequestFactorySettings;
      12: aload_0
      13: getfield      #26                 // Field detectRequestFactory:Z
      16: aload_0
      17: getfield      #30                 // Field rootUri:Ljava/lang/String;
      20: aload_0
      21: getfield      #34                 // Field messageConverters:Ljava/util/Set;
      24: aload_0
      25: getfield      #44                 // Field interceptors:Ljava/util/Set;
      28: aload_0
      29: getfield      #47                 // Field requestFactory:Ljava/util/function/Function;
      32: aload_0
      33: getfield      #51                 // Field uriTemplateHandler:Lorg/springframework/web/util/UriTemplateHandler;
      36: aload_0
      37: getfield      #55                 // Field errorHandler:Lorg/springframework/web/client/ResponseErrorHandler;
      40: aload_0
      41: getfield      #59                 // Field basicAuthentication:Lorg/springframework/boot/web/client/BasicAuthentication;
      44: aload_0
      45: getfield      #67                 // Field defaultHeaders:Ljava/util/Map;
      48: aload_0
      49: getfield      #75                 // Field customizers:Ljava/util/Set;
      52: aload_0
      53: getfield      #78                 // Field requestCustomizers:Ljava/util/Set;
      56: invokespecial #81                 // Method "<init>":(Lorg/springframework/boot/web/client/ClientHttpRequestFactorySettings;ZLjava/lang/String;Ljava/util/Set;Ljava/util/Set;Ljava/util/function/Function;Lorg/springframework/web/util/UriTemplateHandler;Lorg/springframework/web/client/ResponseErrorHandler;Lorg/springframework/boot/web/client/BasicAuthentication;Ljava/util/Map;Ljava/util/Set;Ljava/util/Set;)V
      59: areturn

  public org.springframework.boot.web.client.RestTemplateBuilder setBufferRequestBody(boolean);
    Code:
       0: new           #22                 // class org/springframework/boot/web/client/RestTemplateBuilder
       3: dup
       4: aload_0
       5: getfield      #21                 // Field requestFactorySettings:Lorg/springframework/boot/web/client/ClientHttpRequestFactorySettings;
       8: iload_1
       9: invokestatic  #161                // Method java/lang/Boolean.valueOf:(Z)Ljava/lang/Boolean;
      12: invokevirtual #167                // Method org/springframework/boot/web/client/ClientHttpRequestFactorySettings.withBufferRequestBody:(Ljava/lang/Boolean;)Lorg/springframework/boot/web/client/ClientHttpRequestFactorySettings;
      15: aload_0
      16: getfield      #26                 // Field detectRequestFactory:Z
      19: aload_0
      20: getfield      #30                 // Field rootUri:Ljava/lang/String;
      23: aload_0
      24: getfield      #34                 // Field messageConverters:Ljava/util/Set;
      27: aload_0
      28: getfield      #44                 // Field interceptors:Ljava/util/Set;
      31: aload_0
      32: getfield      #47                 // Field requestFactory:Ljava/util/function/Function;
      35: aload_0
      36: getfield      #51                 // Field uriTemplateHandler:Lorg/springframework/web/util/UriTemplateHandler;
      39: aload_0
      40: getfield      #55                 // Field errorHandler:Lorg/springframework/web/client/ResponseErrorHandler;
      43: aload_0
      44: getfield      #59                 // Field basicAuthentication:Lorg/springframework/boot/web/client/BasicAuthentication;
      47: aload_0
      48: getfield      #67                 // Field defaultHeaders:Ljava/util/Map;
      51: aload_0
      52: getfield      #75                 // Field customizers:Ljava/util/Set;
      55: aload_0
      56: getfield      #78                 // Field requestCustomizers:Ljava/util/Set;
      59: invokespecial #81                 // Method "<init>":(Lorg/springframework/boot/web/client/ClientHttpRequestFactorySettings;ZLjava/lang/String;Ljava/util/Set;Ljava/util/Set;Ljava/util/function/Function;Lorg/springframework/web/util/UriTemplateHandler;Lorg/springframework/web/client/ResponseErrorHandler;Lorg/springframework/boot/web/client/BasicAuthentication;Ljava/util/Map;Ljava/util/Set;Ljava/util/Set;)V
      62: areturn

  public org.springframework.boot.web.client.RestTemplateBuilder setSslBundle(org.springframework.boot.ssl.SslBundle);
    Code:
       0: new           #22                 // class org/springframework/boot/web/client/RestTemplateBuilder
       3: dup
       4: aload_0
       5: getfield      #21                 // Field requestFactorySettings:Lorg/springframework/boot/web/client/ClientHttpRequestFactorySettings;
       8: aload_1
       9: invokevirtual #171                // Method org/springframework/boot/web/client/ClientHttpRequestFactorySettings.withSslBundle:(Lorg/springframework/boot/ssl/SslBundle;)Lorg/springframework/boot/web/client/ClientHttpRequestFactorySettings;
      12: aload_0
      13: getfield      #26                 // Field detectRequestFactory:Z
      16: aload_0
      17: getfield      #30                 // Field rootUri:Ljava/lang/String;
      20: aload_0
      21: getfield      #34                 // Field messageConverters:Ljava/util/Set;
      24: aload_0
      25: getfield      #44                 // Field interceptors:Ljava/util/Set;
      28: aload_0
      29: getfield      #47                 // Field requestFactory:Ljava/util/function/Function;
      32: aload_0
      33: getfield      #51                 // Field uriTemplateHandler:Lorg/springframework/web/util/UriTemplateHandler;
      36: aload_0
      37: getfield      #55                 // Field errorHandler:Lorg/springframework/web/client/ResponseErrorHandler;
      40: aload_0
      41: getfield      #59                 // Field basicAuthentication:Lorg/springframework/boot/web/client/BasicAuthentication;
      44: aload_0
      45: getfield      #67                 // Field defaultHeaders:Ljava/util/Map;
      48: aload_0
      49: getfield      #75                 // Field customizers:Ljava/util/Set;
      52: aload_0
      53: getfield      #78                 // Field requestCustomizers:Ljava/util/Set;
      56: invokespecial #81                 // Method "<init>":(Lorg/springframework/boot/web/client/ClientHttpRequestFactorySettings;ZLjava/lang/String;Ljava/util/Set;Ljava/util/Set;Ljava/util/function/Function;Lorg/springframework/web/util/UriTemplateHandler;Lorg/springframework/web/client/ResponseErrorHandler;Lorg/springframework/boot/web/client/BasicAuthentication;Ljava/util/Map;Ljava/util/Set;Ljava/util/Set;)V
      59: areturn

  public org.springframework.boot.web.client.RestTemplateBuilder customizers(org.springframework.boot.web.client.RestTemplateCustomizer...);
    Code:
       0: aload_1
       1: ldc           #7                  // String Customizers must not be null
       3: invokestatic  #9                  // Method org/springframework/util/Assert.notNull:(Ljava/lang/Object;Ljava/lang/String;)V
       6: aload_0
       7: aload_1
       8: invokestatic  #86                 // Method java/util/Arrays.asList:([Ljava/lang/Object;)Ljava/util/List;
      11: invokevirtual #175                // Method customizers:(Ljava/util/Collection;)Lorg/springframework/boot/web/client/RestTemplateBuilder;
      14: areturn

  public org.springframework.boot.web.client.RestTemplateBuilder customizers(java.util.Collection<? extends org.springframework.boot.web.client.RestTemplateCustomizer>);
    Code:
       0: aload_1
       1: ldc           #7                  // String Customizers must not be null
       3: invokestatic  #9                  // Method org/springframework/util/Assert.notNull:(Ljava/lang/Object;Ljava/lang/String;)V
       6: new           #22                 // class org/springframework/boot/web/client/RestTemplateBuilder
       9: dup
      10: aload_0
      11: getfield      #21                 // Field requestFactorySettings:Lorg/springframework/boot/web/client/ClientHttpRequestFactorySettings;
      14: aload_0
      15: getfield      #26                 // Field detectRequestFactory:Z
      18: aload_0
      19: getfield      #30                 // Field rootUri:Ljava/lang/String;
      22: aload_0
      23: getfield      #34                 // Field messageConverters:Ljava/util/Set;
      26: aload_0
      27: getfield      #44                 // Field interceptors:Ljava/util/Set;
      30: aload_0
      31: getfield      #47                 // Field requestFactory:Ljava/util/function/Function;
      34: aload_0
      35: getfield      #51                 // Field uriTemplateHandler:Lorg/springframework/web/util/UriTemplateHandler;
      38: aload_0
      39: getfield      #55                 // Field errorHandler:Lorg/springframework/web/client/ResponseErrorHandler;
      42: aload_0
      43: getfield      #59                 // Field basicAuthentication:Lorg/springframework/boot/web/client/BasicAuthentication;
      46: aload_0
      47: getfield      #67                 // Field defaultHeaders:Ljava/util/Map;
      50: aload_0
      51: aload_1
      52: invokevirtual #95                 // Method copiedSetOf:(Ljava/util/Collection;)Ljava/util/Set;
      55: aload_0
      56: getfield      #78                 // Field requestCustomizers:Ljava/util/Set;
      59: invokespecial #81                 // Method "<init>":(Lorg/springframework/boot/web/client/ClientHttpRequestFactorySettings;ZLjava/lang/String;Ljava/util/Set;Ljava/util/Set;Ljava/util/function/Function;Lorg/springframework/web/util/UriTemplateHandler;Lorg/springframework/web/client/ResponseErrorHandler;Lorg/springframework/boot/web/client/BasicAuthentication;Ljava/util/Map;Ljava/util/Set;Ljava/util/Set;)V
      62: areturn

  public org.springframework.boot.web.client.RestTemplateBuilder additionalCustomizers(org.springframework.boot.web.client.RestTemplateCustomizer...);
    Code:
       0: aload_1
       1: ldc           #7                  // String Customizers must not be null
       3: invokestatic  #9                  // Method org/springframework/util/Assert.notNull:(Ljava/lang/Object;Ljava/lang/String;)V
       6: aload_0
       7: aload_1
       8: invokestatic  #86                 // Method java/util/Arrays.asList:([Ljava/lang/Object;)Ljava/util/List;
      11: invokevirtual #177                // Method additionalCustomizers:(Ljava/util/Collection;)Lorg/springframework/boot/web/client/RestTemplateBuilder;
      14: areturn

  public org.springframework.boot.web.client.RestTemplateBuilder additionalCustomizers(java.util.Collection<? extends org.springframework.boot.web.client.RestTemplateCustomizer>);
    Code:
       0: aload_1
       1: ldc           #180                // String RestTemplateCustomizers must not be null
       3: invokestatic  #9                  // Method org/springframework/util/Assert.notNull:(Ljava/lang/Object;Ljava/lang/String;)V
       6: new           #22                 // class org/springframework/boot/web/client/RestTemplateBuilder
       9: dup
      10: aload_0
      11: getfield      #21                 // Field requestFactorySettings:Lorg/springframework/boot/web/client/ClientHttpRequestFactorySettings;
      14: aload_0
      15: getfield      #26                 // Field detectRequestFactory:Z
      18: aload_0
      19: getfield      #30                 // Field rootUri:Ljava/lang/String;
      22: aload_0
      23: getfield      #34                 // Field messageConverters:Ljava/util/Set;
      26: aload_0
      27: getfield      #44                 // Field interceptors:Ljava/util/Set;
      30: aload_0
      31: getfield      #47                 // Field requestFactory:Ljava/util/function/Function;
      34: aload_0
      35: getfield      #51                 // Field uriTemplateHandler:Lorg/springframework/web/util/UriTemplateHandler;
      38: aload_0
      39: getfield      #55                 // Field errorHandler:Lorg/springframework/web/client/ResponseErrorHandler;
      42: aload_0
      43: getfield      #59                 // Field basicAuthentication:Lorg/springframework/boot/web/client/BasicAuthentication;
      46: aload_0
      47: getfield      #67                 // Field defaultHeaders:Ljava/util/Map;
      50: aload_0
      51: getfield      #75                 // Field customizers:Ljava/util/Set;
      54: aload_1
      55: invokestatic  #101                // Method append:(Ljava/util/Collection;Ljava/util/Collection;)Ljava/util/Set;
      58: aload_0
      59: getfield      #78                 // Field requestCustomizers:Ljava/util/Set;
      62: invokespecial #81                 // Method "<init>":(Lorg/springframework/boot/web/client/ClientHttpRequestFactorySettings;ZLjava/lang/String;Ljava/util/Set;Ljava/util/Set;Ljava/util/function/Function;Lorg/springframework/web/util/UriTemplateHandler;Lorg/springframework/web/client/ResponseErrorHandler;Lorg/springframework/boot/web/client/BasicAuthentication;Ljava/util/Map;Ljava/util/Set;Ljava/util/Set;)V
      65: areturn

  public org.springframework.boot.web.client.RestTemplateBuilder requestCustomizers(org.springframework.boot.web.client.RestTemplateRequestCustomizer<?>...);
    Code:
       0: aload_1
       1: ldc           #182                // String RequestCustomizers must not be null
       3: invokestatic  #9                  // Method org/springframework/util/Assert.notNull:(Ljava/lang/Object;Ljava/lang/String;)V
       6: aload_0
       7: aload_1
       8: invokestatic  #86                 // Method java/util/Arrays.asList:([Ljava/lang/Object;)Ljava/util/List;
      11: invokevirtual #184                // Method requestCustomizers:(Ljava/util/Collection;)Lorg/springframework/boot/web/client/RestTemplateBuilder;
      14: areturn

  public org.springframework.boot.web.client.RestTemplateBuilder requestCustomizers(java.util.Collection<? extends org.springframework.boot.web.client.RestTemplateRequestCustomizer<?>>);
    Code:
       0: aload_1
       1: ldc           #182                // String RequestCustomizers must not be null
       3: invokestatic  #9                  // Method org/springframework/util/Assert.notNull:(Ljava/lang/Object;Ljava/lang/String;)V
       6: new           #22                 // class org/springframework/boot/web/client/RestTemplateBuilder
       9: dup
      10: aload_0
      11: getfield      #21                 // Field requestFactorySettings:Lorg/springframework/boot/web/client/ClientHttpRequestFactorySettings;
      14: aload_0
      15: getfield      #26                 // Field detectRequestFactory:Z
      18: aload_0
      19: getfield      #30                 // Field rootUri:Ljava/lang/String;
      22: aload_0
      23: getfield      #34                 // Field messageConverters:Ljava/util/Set;
      26: aload_0
      27: getfield      #44                 // Field interceptors:Ljava/util/Set;
      30: aload_0
      31: getfield      #47                 // Field requestFactory:Ljava/util/function/Function;
      34: aload_0
      35: getfield      #51                 // Field uriTemplateHandler:Lorg/springframework/web/util/UriTemplateHandler;
      38: aload_0
      39: getfield      #55                 // Field errorHandler:Lorg/springframework/web/client/ResponseErrorHandler;
      42: aload_0
      43: getfield      #59                 // Field basicAuthentication:Lorg/springframework/boot/web/client/BasicAuthentication;
      46: aload_0
      47: getfield      #67                 // Field defaultHeaders:Ljava/util/Map;
      50: aload_0
      51: getfield      #75                 // Field customizers:Ljava/util/Set;
      54: aload_0
      55: aload_1
      56: invokevirtual #95                 // Method copiedSetOf:(Ljava/util/Collection;)Ljava/util/Set;
      59: invokespecial #81                 // Method "<init>":(Lorg/springframework/boot/web/client/ClientHttpRequestFactorySettings;ZLjava/lang/String;Ljava/util/Set;Ljava/util/Set;Ljava/util/function/Function;Lorg/springframework/web/util/UriTemplateHandler;Lorg/springframework/web/client/ResponseErrorHandler;Lorg/springframework/boot/web/client/BasicAuthentication;Ljava/util/Map;Ljava/util/Set;Ljava/util/Set;)V
      62: areturn

  public org.springframework.boot.web.client.RestTemplateBuilder additionalRequestCustomizers(org.springframework.boot.web.client.RestTemplateRequestCustomizer<?>...);
    Code:
       0: aload_1
       1: ldc           #182                // String RequestCustomizers must not be null
       3: invokestatic  #9                  // Method org/springframework/util/Assert.notNull:(Ljava/lang/Object;Ljava/lang/String;)V
       6: aload_0
       7: aload_1
       8: invokestatic  #86                 // Method java/util/Arrays.asList:([Ljava/lang/Object;)Ljava/util/List;
      11: invokevirtual #186                // Method additionalRequestCustomizers:(Ljava/util/Collection;)Lorg/springframework/boot/web/client/RestTemplateBuilder;
      14: areturn

  public org.springframework.boot.web.client.RestTemplateBuilder additionalRequestCustomizers(java.util.Collection<? extends org.springframework.boot.web.client.RestTemplateRequestCustomizer<?>>);
    Code:
       0: aload_1
       1: ldc           #182                // String RequestCustomizers must not be null
       3: invokestatic  #9                  // Method org/springframework/util/Assert.notNull:(Ljava/lang/Object;Ljava/lang/String;)V
       6: new           #22                 // class org/springframework/boot/web/client/RestTemplateBuilder
       9: dup
      10: aload_0
      11: getfield      #21                 // Field requestFactorySettings:Lorg/springframework/boot/web/client/ClientHttpRequestFactorySettings;
      14: aload_0
      15: getfield      #26                 // Field detectRequestFactory:Z
      18: aload_0
      19: getfield      #30                 // Field rootUri:Ljava/lang/String;
      22: aload_0
      23: getfield      #34                 // Field messageConverters:Ljava/util/Set;
      26: aload_0
      27: getfield      #44                 // Field interceptors:Ljava/util/Set;
      30: aload_0
      31: getfield      #47                 // Field requestFactory:Ljava/util/function/Function;
      34: aload_0
      35: getfield      #51                 // Field uriTemplateHandler:Lorg/springframework/web/util/UriTemplateHandler;
      38: aload_0
      39: getfield      #55                 // Field errorHandler:Lorg/springframework/web/client/ResponseErrorHandler;
      42: aload_0
      43: getfield      #59                 // Field basicAuthentication:Lorg/springframework/boot/web/client/BasicAuthentication;
      46: aload_0
      47: getfield      #67                 // Field defaultHeaders:Ljava/util/Map;
      50: aload_0
      51: getfield      #75                 // Field customizers:Ljava/util/Set;
      54: aload_0
      55: getfield      #78                 // Field requestCustomizers:Ljava/util/Set;
      58: aload_1
      59: invokestatic  #101                // Method append:(Ljava/util/Collection;Ljava/util/Collection;)Ljava/util/Set;
      62: invokespecial #81                 // Method "<init>":(Lorg/springframework/boot/web/client/ClientHttpRequestFactorySettings;ZLjava/lang/String;Ljava/util/Set;Ljava/util/Set;Ljava/util/function/Function;Lorg/springframework/web/util/UriTemplateHandler;Lorg/springframework/web/client/ResponseErrorHandler;Lorg/springframework/boot/web/client/BasicAuthentication;Ljava/util/Map;Ljava/util/Set;Ljava/util/Set;)V
      65: areturn

  public org.springframework.web.client.RestTemplate build();
    Code:
       0: aload_0
       1: new           #105                // class org/springframework/web/client/RestTemplate
       4: dup
       5: invokespecial #107                // Method org/springframework/web/client/RestTemplate."<init>":()V
       8: invokevirtual #189                // Method configure:(Lorg/springframework/web/client/RestTemplate;)Lorg/springframework/web/client/RestTemplate;
      11: areturn

  public <T extends org.springframework.web.client.RestTemplate> T build(java.lang.Class<T>);
    Code:
       0: aload_0
       1: aload_1
       2: invokestatic  #193                // Method org/springframework/beans/BeanUtils.instantiateClass:(Ljava/lang/Class;)Ljava/lang/Object;
       5: checkcast     #105                // class org/springframework/web/client/RestTemplate
       8: invokevirtual #189                // Method configure:(Lorg/springframework/web/client/RestTemplate;)Lorg/springframework/web/client/RestTemplate;
      11: areturn

  public <T extends org.springframework.web.client.RestTemplate> T configure(T);
    Code:
       0: aload_0
       1: invokevirtual #199                // Method buildRequestFactory:()Lorg/springframework/http/client/ClientHttpRequestFactory;
       4: astore_2
       5: aload_2
       6: ifnull        14
       9: aload_1
      10: aload_2
      11: invokevirtual #203                // Method org/springframework/web/client/RestTemplate.setRequestFactory:(Lorg/springframework/http/client/ClientHttpRequestFactory;)V
      14: aload_0
      15: aload_1
      16: invokevirtual #207                // Method addClientHttpRequestInitializer:(Lorg/springframework/web/client/RestTemplate;)V
      19: aload_0
      20: getfield      #34                 // Field messageConverters:Ljava/util/Set;
      23: invokestatic  #211                // Method org/springframework/util/CollectionUtils.isEmpty:(Ljava/util/Collection;)Z
      26: ifne          44
      29: aload_1
      30: new           #217                // class java/util/ArrayList
      33: dup
      34: aload_0
      35: getfield      #34                 // Field messageConverters:Ljava/util/Set;
      38: invokespecial #219                // Method java/util/ArrayList."<init>":(Ljava/util/Collection;)V
      41: invokevirtual #222                // Method org/springframework/web/client/RestTemplate.setMessageConverters:(Ljava/util/List;)V
      44: aload_0
      45: getfield      #51                 // Field uriTemplateHandler:Lorg/springframework/web/util/UriTemplateHandler;
      48: ifnull        59
      51: aload_1
      52: aload_0
      53: getfield      #51                 // Field uriTemplateHandler:Lorg/springframework/web/util/UriTemplateHandler;
      56: invokevirtual #226                // Method org/springframework/web/client/RestTemplate.setUriTemplateHandler:(Lorg/springframework/web/util/UriTemplateHandler;)V
      59: aload_0
      60: getfield      #55                 // Field errorHandler:Lorg/springframework/web/client/ResponseErrorHandler;
      63: ifnull        74
      66: aload_1
      67: aload_0
      68: getfield      #55                 // Field errorHandler:Lorg/springframework/web/client/ResponseErrorHandler;
      71: invokevirtual #230                // Method org/springframework/web/client/RestTemplate.setErrorHandler:(Lorg/springframework/web/client/ResponseErrorHandler;)V
      74: aload_0
      75: getfield      #30                 // Field rootUri:Ljava/lang/String;
      78: ifnull        90
      81: aload_1
      82: aload_0
      83: getfield      #30                 // Field rootUri:Ljava/lang/String;
      86: invokestatic  #234                // Method org/springframework/boot/web/client/RootUriTemplateHandler.addTo:(Lorg/springframework/web/client/RestTemplate;Ljava/lang/String;)Lorg/springframework/boot/web/client/RootUriTemplateHandler;
      89: pop
      90: aload_1
      91: invokevirtual #240                // Method org/springframework/web/client/RestTemplate.getInterceptors:()Ljava/util/List;
      94: aload_0
      95: getfield      #44                 // Field interceptors:Ljava/util/Set;
      98: invokeinterface #243,  2          // InterfaceMethod java/util/List.addAll:(Ljava/util/Collection;)Z
     103: pop
     104: aload_0
     105: getfield      #75                 // Field customizers:Ljava/util/Set;
     108: invokestatic  #211                // Method org/springframework/util/CollectionUtils.isEmpty:(Ljava/util/Collection;)Z
     111: ifne          155
     114: aload_0
     115: getfield      #75                 // Field customizers:Ljava/util/Set;
     118: invokeinterface #248,  1          // InterfaceMethod java/util/Set.iterator:()Ljava/util/Iterator;
     123: astore_3
     124: aload_3
     125: invokeinterface #254,  1          // InterfaceMethod java/util/Iterator.hasNext:()Z
     130: ifeq          155
     133: aload_3
     134: invokeinterface #260,  1          // InterfaceMethod java/util/Iterator.next:()Ljava/lang/Object;
     139: checkcast     #264                // class org/springframework/boot/web/client/RestTemplateCustomizer
     142: astore        4
     144: aload         4
     146: aload_1
     147: invokeinterface #266,  2          // InterfaceMethod org/springframework/boot/web/client/RestTemplateCustomizer.customize:(Lorg/springframework/web/client/RestTemplate;)V
     152: goto          124
     155: aload_1
     156: areturn

  public org.springframework.http.client.ClientHttpRequestFactory buildRequestFactory();
    Code:
       0: aload_0
       1: getfield      #47                 // Field requestFactory:Ljava/util/function/Function;
       4: ifnull        24
       7: aload_0
       8: getfield      #47                 // Field requestFactory:Ljava/util/function/Function;
      11: aload_0
      12: getfield      #21                 // Field requestFactorySettings:Lorg/springframework/boot/web/client/ClientHttpRequestFactorySettings;
      15: invokeinterface #269,  2          // InterfaceMethod java/util/function/Function.apply:(Ljava/lang/Object;)Ljava/lang/Object;
      20: checkcast     #274                // class org/springframework/http/client/ClientHttpRequestFactory
      23: areturn
      24: aload_0
      25: getfield      #26                 // Field detectRequestFactory:Z
      28: ifeq          39
      31: aload_0
      32: getfield      #21                 // Field requestFactorySettings:Lorg/springframework/boot/web/client/ClientHttpRequestFactorySettings;
      35: invokestatic  #276                // Method org/springframework/boot/web/client/ClientHttpRequestFactories.get:(Lorg/springframework/boot/web/client/ClientHttpRequestFactorySettings;)Lorg/springframework/http/client/ClientHttpRequestFactory;
      38: areturn
      39: aconst_null
      40: areturn

  private void addClientHttpRequestInitializer(org.springframework.web.client.RestTemplate);
    Code:
       0: aload_0
       1: getfield      #59                 // Field basicAuthentication:Lorg/springframework/boot/web/client/BasicAuthentication;
       4: ifnonnull     32
       7: aload_0
       8: getfield      #67                 // Field defaultHeaders:Ljava/util/Map;
      11: invokeinterface #282,  1          // InterfaceMethod java/util/Map.isEmpty:()Z
      16: ifeq          32
      19: aload_0
      20: getfield      #78                 // Field requestCustomizers:Ljava/util/Set;
      23: invokeinterface #286,  1          // InterfaceMethod java/util/Set.isEmpty:()Z
      28: ifeq          32
      31: return
      32: aload_1
      33: invokevirtual #287                // Method org/springframework/web/client/RestTemplate.getClientHttpRequestInitializers:()Ljava/util/List;
      36: new           #290                // class org/springframework/boot/web/client/RestTemplateBuilderClientHttpRequestInitializer
      39: dup
      40: aload_0
      41: getfield      #59                 // Field basicAuthentication:Lorg/springframework/boot/web/client/BasicAuthentication;
      44: aload_0
      45: getfield      #67                 // Field defaultHeaders:Ljava/util/Map;
      48: aload_0
      49: getfield      #78                 // Field requestCustomizers:Ljava/util/Set;
      52: invokespecial #292                // Method org/springframework/boot/web/client/RestTemplateBuilderClientHttpRequestInitializer."<init>":(Lorg/springframework/boot/web/client/BasicAuthentication;Ljava/util/Map;Ljava/util/Set;)V
      55: invokeinterface #295,  2          // InterfaceMethod java/util/List.add:(Ljava/lang/Object;)Z
      60: pop
      61: return

  private <T> java.util.Set<T> copiedSetOf(T...);
    Code:
       0: aload_0
       1: aload_1
       2: invokestatic  #86                 // Method java/util/Arrays.asList:([Ljava/lang/Object;)Ljava/util/List;
       5: invokevirtual #95                 // Method copiedSetOf:(Ljava/util/Collection;)Ljava/util/Set;
       8: areturn

  private <T> java.util.Set<T> copiedSetOf(java.util.Collection<? extends T>);
    Code:
       0: new           #299                // class java/util/LinkedHashSet
       3: dup
       4: aload_1
       5: invokespecial #301                // Method java/util/LinkedHashSet."<init>":(Ljava/util/Collection;)V
       8: invokestatic  #302                // Method java/util/Collections.unmodifiableSet:(Ljava/util/Set;)Ljava/util/Set;
      11: areturn

  private static <T> java.util.List<T> copiedListOf(T[]);
    Code:
       0: aload_0
       1: aload_0
       2: arraylength
       3: invokestatic  #306                // Method java/util/Arrays.copyOf:([Ljava/lang/Object;I)[Ljava/lang/Object;
       6: invokestatic  #86                 // Method java/util/Arrays.asList:([Ljava/lang/Object;)Ljava/util/List;
       9: invokestatic  #310                // Method java/util/Collections.unmodifiableList:(Ljava/util/List;)Ljava/util/List;
      12: areturn

  private static <T> java.util.Set<T> append(java.util.Collection<? extends T>, java.util.Collection<? extends T>);
    Code:
       0: new           #299                // class java/util/LinkedHashSet
       3: dup
       4: aload_0
       5: ifnull        12
       8: aload_0
       9: goto          15
      12: invokestatic  #38                 // Method java/util/Collections.emptySet:()Ljava/util/Set;
      15: invokespecial #301                // Method java/util/LinkedHashSet."<init>":(Ljava/util/Collection;)V
      18: astore_2
      19: aload_1
      20: ifnull        31
      23: aload_2
      24: aload_1
      25: invokeinterface #314,  2          // InterfaceMethod java/util/Set.addAll:(Ljava/util/Collection;)Z
      30: pop
      31: aload_2
      32: invokestatic  #302                // Method java/util/Collections.unmodifiableSet:(Ljava/util/Set;)Ljava/util/Set;
      35: areturn

  private static <K, V> java.util.Map<K, java.util.List<V>> append(java.util.Map<K, java.util.List<V>>, K, V[]);
    Code:
       0: new           #315                // class java/util/LinkedHashMap
       3: dup
       4: aload_0
       5: ifnull        12
       8: aload_0
       9: goto          15
      12: invokestatic  #63                 // Method java/util/Collections.emptyMap:()Ljava/util/Map;
      15: invokespecial #317                // Method java/util/LinkedHashMap."<init>":(Ljava/util/Map;)V
      18: astore_3
      19: aload_2
      20: ifnull        35
      23: aload_3
      24: aload_1
      25: aload_2
      26: invokestatic  #320                // Method copiedListOf:([Ljava/lang/Object;)Ljava/util/List;
      29: invokeinterface #323,  3          // InterfaceMethod java/util/Map.put:(Ljava/lang/Object;Ljava/lang/Object;)Ljava/lang/Object;
      34: pop
      35: aload_3
      36: invokestatic  #327                // Method java/util/Collections.unmodifiableMap:(Ljava/util/Map;)Ljava/util/Map;
      39: areturn

  private static org.springframework.http.client.ClientHttpRequestFactory lambda$requestFactory$1(java.util.function.Supplier, org.springframework.boot.web.client.ClientHttpRequestFactorySettings);
    Code:
       0: aload_0
       1: aload_1
       2: invokestatic  #331                // Method org/springframework/boot/web/client/ClientHttpRequestFactories.get:(Ljava/util/function/Supplier;Lorg/springframework/boot/web/client/ClientHttpRequestFactorySettings;)Lorg/springframework/http/client/ClientHttpRequestFactory;
       5: areturn

  private static org.springframework.http.client.ClientHttpRequestFactory lambda$requestFactory$0(java.lang.Class, org.springframework.boot.web.client.ClientHttpRequestFactorySettings);
    Code:
       0: aload_0
       1: aload_1
       2: invokestatic  #334                // Method org/springframework/boot/web/client/ClientHttpRequestFactories.get:(Ljava/lang/Class;Lorg/springframework/boot/web/client/ClientHttpRequestFactorySettings;)Lorg/springframework/http/client/ClientHttpRequestFactory;
       5: areturn
}
