Compiled from "RootUriTemplateHandler.java"
public class org.springframework.boot.web.client.RootUriTemplateHandler implements org.springframework.web.util.UriTemplateHandler {
  private final java.lang.String rootUri;

  private final org.springframework.web.util.UriTemplateHandler handler;

  protected org.springframework.boot.web.client.RootUriTemplateHandler(org.springframework.web.util.UriTemplateHandler);
    Code:
       0: aload_0
       1: invokespecial #1                  // Method java/lang/Object."<init>":()V
       4: aload_1
       5: ldc           #7                  // String Handler must not be null
       7: invokestatic  #9                  // Method org/springframework/util/Assert.notNull:(Ljava/lang/Object;Ljava/lang/String;)V
      10: aload_0
      11: aconst_null
      12: putfield      #15                 // Field rootUri:Ljava/lang/String;
      15: aload_0
      16: aload_1
      17: putfield      #21                 // Field handler:Lorg/springframework/web/util/UriTemplateHandler;
      20: return

  public org.springframework.boot.web.client.RootUriTemplateHandler(java.lang.String);
    Code:
       0: aload_0
       1: aload_1
       2: new           #25                 // class org/springframework/web/util/DefaultUriBuilderFactory
       5: dup
       6: invokespecial #27                 // Method org/springframework/web/util/DefaultUriBuilderFactory."<init>":()V
       9: invokespecial #28                 // Method "<init>":(Ljava/lang/String;Lorg/springframework/web/util/UriTemplateHandler;)V
      12: return

  public org.springframework.boot.web.client.RootUriTemplateHandler(java.lang.String, org.springframework.web.util.UriTemplateHandler);
    Code:
       0: aload_0
       1: invokespecial #1                  // Method java/lang/Object."<init>":()V
       4: aload_1
       5: ldc           #31                 // String RootUri must not be null
       7: invokestatic  #9                  // Method org/springframework/util/Assert.notNull:(Ljava/lang/Object;Ljava/lang/String;)V
      10: aload_2
      11: ldc           #7                  // String Handler must not be null
      13: invokestatic  #9                  // Method org/springframework/util/Assert.notNull:(Ljava/lang/Object;Ljava/lang/String;)V
      16: aload_0
      17: aload_1
      18: putfield      #15                 // Field rootUri:Ljava/lang/String;
      21: aload_0
      22: aload_2
      23: putfield      #21                 // Field handler:Lorg/springframework/web/util/UriTemplateHandler;
      26: return

  public java.net.URI expand(java.lang.String, java.util.Map<java.lang.String, ?>);
    Code:
       0: aload_0
       1: getfield      #21                 // Field handler:Lorg/springframework/web/util/UriTemplateHandler;
       4: aload_0
       5: aload_1
       6: invokevirtual #33                 // Method apply:(Ljava/lang/String;)Ljava/lang/String;
       9: aload_2
      10: invokeinterface #37,  3           // InterfaceMethod org/springframework/web/util/UriTemplateHandler.expand:(Ljava/lang/String;Ljava/util/Map;)Ljava/net/URI;
      15: areturn

  public java.net.URI expand(java.lang.String, java.lang.Object...);
    Code:
       0: aload_0
       1: getfield      #21                 // Field handler:Lorg/springframework/web/util/UriTemplateHandler;
       4: aload_0
       5: aload_1
       6: invokevirtual #33                 // Method apply:(Ljava/lang/String;)Ljava/lang/String;
       9: aload_2
      10: invokeinterface #43,  3           // InterfaceMethod org/springframework/web/util/UriTemplateHandler.expand:(Ljava/lang/String;[Ljava/lang/Object;)Ljava/net/URI;
      15: areturn

  private java.lang.String apply(java.lang.String);
    Code:
       0: aload_1
       1: ldc           #46                 // String /
       3: invokestatic  #48                 // Method org/springframework/util/StringUtils.startsWithIgnoreCase:(Ljava/lang/String;Ljava/lang/String;)Z
       6: ifeq          20
       9: aload_0
      10: invokevirtual #54                 // Method getRootUri:()Ljava/lang/String;
      13: aload_1
      14: invokedynamic #58,  0             // InvokeDynamic #0:makeConcatWithConstants:(Ljava/lang/String;Ljava/lang/String;)Ljava/lang/String;
      19: areturn
      20: aload_1
      21: areturn

  public java.lang.String getRootUri();
    Code:
       0: aload_0
       1: getfield      #15                 // Field rootUri:Ljava/lang/String;
       4: areturn

  public org.springframework.boot.web.client.RootUriTemplateHandler withHandlerWrapper(java.util.function.Function<org.springframework.web.util.UriTemplateHandler, org.springframework.web.util.UriTemplateHandler>);
    Code:
       0: new           #16                 // class org/springframework/boot/web/client/RootUriTemplateHandler
       3: dup
       4: aload_0
       5: invokevirtual #54                 // Method getRootUri:()Ljava/lang/String;
       8: aload_1
       9: aload_0
      10: getfield      #21                 // Field handler:Lorg/springframework/web/util/UriTemplateHandler;
      13: invokeinterface #62,  2           // InterfaceMethod java/util/function/Function.apply:(Ljava/lang/Object;)Ljava/lang/Object;
      18: checkcast     #38                 // class org/springframework/web/util/UriTemplateHandler
      21: invokespecial #28                 // Method "<init>":(Ljava/lang/String;Lorg/springframework/web/util/UriTemplateHandler;)V
      24: areturn

  public static org.springframework.boot.web.client.RootUriTemplateHandler addTo(org.springframework.web.client.RestTemplate, java.lang.String);
    Code:
       0: aload_0
       1: ldc           #67                 // String RestTemplate must not be null
       3: invokestatic  #9                  // Method org/springframework/util/Assert.notNull:(Ljava/lang/Object;Ljava/lang/String;)V
       6: new           #16                 // class org/springframework/boot/web/client/RootUriTemplateHandler
       9: dup
      10: aload_1
      11: aload_0
      12: invokevirtual #69                 // Method org/springframework/web/client/RestTemplate.getUriTemplateHandler:()Lorg/springframework/web/util/UriTemplateHandler;
      15: invokespecial #28                 // Method "<init>":(Ljava/lang/String;Lorg/springframework/web/util/UriTemplateHandler;)V
      18: astore_2
      19: aload_0
      20: aload_2
      21: invokevirtual #75                 // Method org/springframework/web/client/RestTemplate.setUriTemplateHandler:(Lorg/springframework/web/util/UriTemplateHandler;)V
      24: aload_2
      25: areturn
}
