Compiled from "TripleClientHandler.java"
public class org.apache.dubbo.rpc.protocol.tri.transport.TripleClientHandler extends io.netty.channel.ChannelDuplexHandler {
  private final org.apache.dubbo.rpc.model.FrameworkModel frameworkModel;

  private static final java.lang.String CONNECTION_HANDLER_NAME;

  public org.apache.dubbo.rpc.protocol.tri.transport.TripleClientHandler(org.apache.dubbo.rpc.model.FrameworkModel);
    Code:
       0: aload_0
       1: invokespecial #1                  // Method io/netty/channel/ChannelDuplexHandler."<init>":()V
       4: aload_0
       5: aload_1
       6: putfield      #2                  // Field frameworkModel:Lorg/apache/dubbo/rpc/model/FrameworkModel;
       9: return

  public void channelRead(io.netty.channel.ChannelHandlerContext, java.lang.Object) throws java.lang.Exception;
    Code:
       0: aload_2
       1: instanceof    #3                  // class io/netty/handler/codec/http2/Http2GoAwayFrame
       4: ifeq          36
       7: aload_1
       8: invokeinterface #4,  1            // InterfaceMethod io/netty/channel/ChannelHandlerContext.pipeline:()Lio/netty/channel/ChannelPipeline;
      13: ldc           #6                  // String connectionHandler
      15: invokeinterface #7,  2            // InterfaceMethod io/netty/channel/ChannelPipeline.get:(Ljava/lang/String;)Lio/netty/channel/ChannelHandler;
      20: checkcast     #8                  // class org/apache/dubbo/remoting/api/connection/ConnectionHandler
      23: astore_3
      24: aload_3
      25: aload_1
      26: invokeinterface #9,  1            // InterfaceMethod io/netty/channel/ChannelHandlerContext.channel:()Lio/netty/channel/Channel;
      31: invokeinterface #10,  2           // InterfaceMethod org/apache/dubbo/remoting/api/connection/ConnectionHandler.onGoAway:(Ljava/lang/Object;)V
      36: aload_2
      37: invokestatic  #11                 // Method io/netty/util/ReferenceCountUtil.release:(Ljava/lang/Object;)Z
      40: pop
      41: return
}
