Compiled from "TripleServerConnectionHandler.java"
public class org.apache.dubbo.rpc.protocol.tri.transport.TripleServerConnectionHandler extends io.netty.handler.codec.http2.Http2ChannelDuplexHandler {
  private static final org.apache.dubbo.common.logger.ErrorTypeAwareLogger logger;

  private static final java.util.Set<java.lang.String> QUIET_EXCEPTIONS;

  private static final java.util.Set<java.lang.Class<?>> QUIET_EXCEPTIONS_CLASS;

  private org.apache.dubbo.rpc.protocol.tri.transport.GracefulShutdown gracefulShutdown;

  public org.apache.dubbo.rpc.protocol.tri.transport.TripleServerConnectionHandler();
    Code:
       0: aload_0
       1: invokespecial #3                  // Method io/netty/handler/codec/http2/Http2ChannelDuplexHandler."<init>":()V
       4: return

  public void channelRead(io.netty.channel.ChannelHandlerContext, java.lang.Object) throws java.lang.Exception;
    Code:
       0: aload_2
       1: instanceof    #4                  // class io/netty/handler/codec/http2/Http2PingFrame
       4: ifeq          60
       7: aload_2
       8: checkcast     #4                  // class io/netty/handler/codec/http2/Http2PingFrame
      11: invokeinterface #5,  1            // InterfaceMethod io/netty/handler/codec/http2/Http2PingFrame.content:()J
      16: ldc2_w        #6                  // long 40715087873l
      19: lcmp
      20: ifne          81
      23: aload_0
      24: getfield      #8                  // Field gracefulShutdown:Lorg/apache/dubbo/rpc/protocol/tri/transport/GracefulShutdown;
      27: ifnonnull     49
      30: getstatic     #9                  // Field logger:Lorg/apache/dubbo/common/logger/ErrorTypeAwareLogger;
      33: ldc           #10                 // String 4-14
      35: ldc           #11                 // String
      37: ldc           #11                 // String
      39: ldc           #12                 // String Received GRACEFUL_SHUTDOWN_PING Ack but gracefulShutdown is null
      41: invokeinterface #13,  5           // InterfaceMethod org/apache/dubbo/common/logger/ErrorTypeAwareLogger.warn:(Ljava/lang/String;Ljava/lang/String;Ljava/lang/String;Ljava/lang/String;)V
      46: goto          81
      49: aload_0
      50: getfield      #8                  // Field gracefulShutdown:Lorg/apache/dubbo/rpc/protocol/tri/transport/GracefulShutdown;
      53: aload_1
      54: invokevirtual #14                 // Method org/apache/dubbo/rpc/protocol/tri/transport/GracefulShutdown.secondGoAwayAndClose:(Lio/netty/channel/ChannelHandlerContext;)V
      57: goto          81
      60: aload_2
      61: instanceof    #15                 // class io/netty/handler/codec/http2/Http2GoAwayFrame
      64: ifeq          75
      67: aload_2
      68: invokestatic  #16                 // Method io/netty/util/ReferenceCountUtil.release:(Ljava/lang/Object;)Z
      71: pop
      72: goto          81
      75: aload_0
      76: aload_1
      77: aload_2
      78: invokespecial #17                 // Method io/netty/handler/codec/http2/Http2ChannelDuplexHandler.channelRead:(Lio/netty/channel/ChannelHandlerContext;Ljava/lang/Object;)V
      81: return

  private boolean isQuiteException(java.lang.Throwable);
    Code:
       0: getstatic     #18                 // Field QUIET_EXCEPTIONS_CLASS:Ljava/util/Set;
       3: aload_1
       4: invokevirtual #19                 // Method java/lang/Object.getClass:()Ljava/lang/Class;
       7: invokeinterface #20,  2           // InterfaceMethod java/util/Set.contains:(Ljava/lang/Object;)Z
      12: ifeq          17
      15: iconst_1
      16: ireturn
      17: getstatic     #21                 // Field QUIET_EXCEPTIONS:Ljava/util/Set;
      20: aload_1
      21: invokevirtual #19                 // Method java/lang/Object.getClass:()Ljava/lang/Class;
      24: invokevirtual #22                 // Method java/lang/Class.getSimpleName:()Ljava/lang/String;
      27: invokeinterface #20,  2           // InterfaceMethod java/util/Set.contains:(Ljava/lang/Object;)Z
      32: ireturn

  public void userEventTriggered(io.netty.channel.ChannelHandlerContext, java.lang.Object) throws java.lang.Exception;
    Code:
       0: aload_0
       1: aload_1
       2: aload_2
       3: invokespecial #23                 // Method io/netty/handler/codec/http2/Http2ChannelDuplexHandler.userEventTriggered:(Lio/netty/channel/ChannelHandlerContext;Ljava/lang/Object;)V
       6: return

  public void exceptionCaught(io.netty.channel.ChannelHandlerContext, java.lang.Throwable) throws java.lang.Exception;
    Code:
       0: aload_0
       1: aload_2
       2: invokespecial #24                 // Method isQuiteException:(Ljava/lang/Throwable;)Z
       5: ifeq          49
       8: getstatic     #9                  // Field logger:Lorg/apache/dubbo/common/logger/ErrorTypeAwareLogger;
      11: invokeinterface #25,  1           // InterfaceMethod org/apache/dubbo/common/logger/ErrorTypeAwareLogger.isDebugEnabled:()Z
      16: ifeq          82
      19: getstatic     #9                  // Field logger:Lorg/apache/dubbo/common/logger/ErrorTypeAwareLogger;
      22: ldc           #26                 // String Channel:%s Error
      24: iconst_1
      25: anewarray     #27                 // class java/lang/Object
      28: dup
      29: iconst_0
      30: aload_1
      31: invokeinterface #28,  1           // InterfaceMethod io/netty/channel/ChannelHandlerContext.channel:()Lio/netty/channel/Channel;
      36: aastore
      37: invokestatic  #29                 // Method java/lang/String.format:(Ljava/lang/String;[Ljava/lang/Object;)Ljava/lang/String;
      40: aload_2
      41: invokeinterface #30,  3           // InterfaceMethod org/apache/dubbo/common/logger/ErrorTypeAwareLogger.debug:(Ljava/lang/String;Ljava/lang/Throwable;)V
      46: goto          82
      49: getstatic     #9                  // Field logger:Lorg/apache/dubbo/common/logger/ErrorTypeAwareLogger;
      52: ldc           #10                 // String 4-14
      54: ldc           #11                 // String
      56: ldc           #11                 // String
      58: ldc           #26                 // String Channel:%s Error
      60: iconst_1
      61: anewarray     #27                 // class java/lang/Object
      64: dup
      65: iconst_0
      66: aload_1
      67: invokeinterface #28,  1           // InterfaceMethod io/netty/channel/ChannelHandlerContext.channel:()Lio/netty/channel/Channel;
      72: aastore
      73: invokestatic  #29                 // Method java/lang/String.format:(Ljava/lang/String;[Ljava/lang/Object;)Ljava/lang/String;
      76: aload_2
      77: invokeinterface #31,  6           // InterfaceMethod org/apache/dubbo/common/logger/ErrorTypeAwareLogger.warn:(Ljava/lang/String;Ljava/lang/String;Ljava/lang/String;Ljava/lang/String;Ljava/lang/Throwable;)V
      82: aload_1
      83: invokeinterface #32,  1           // InterfaceMethod io/netty/channel/ChannelHandlerContext.close:()Lio/netty/channel/ChannelFuture;
      88: pop
      89: return

  public void close(io.netty.channel.ChannelHandlerContext, io.netty.channel.ChannelPromise) throws java.lang.Exception;
    Code:
       0: aload_0
       1: getfield      #8                  // Field gracefulShutdown:Lorg/apache/dubbo/rpc/protocol/tri/transport/GracefulShutdown;
       4: ifnonnull     22
       7: aload_0
       8: new           #2                  // class org/apache/dubbo/rpc/protocol/tri/transport/GracefulShutdown
      11: dup
      12: aload_1
      13: ldc           #33                 // String app_requested
      15: aload_2
      16: invokespecial #34                 // Method org/apache/dubbo/rpc/protocol/tri/transport/GracefulShutdown."<init>":(Lio/netty/channel/ChannelHandlerContext;Ljava/lang/String;Lio/netty/channel/ChannelPromise;)V
      19: putfield      #8                  // Field gracefulShutdown:Lorg/apache/dubbo/rpc/protocol/tri/transport/GracefulShutdown;
      22: aload_0
      23: getfield      #8                  // Field gracefulShutdown:Lorg/apache/dubbo/rpc/protocol/tri/transport/GracefulShutdown;
      26: invokevirtual #35                 // Method org/apache/dubbo/rpc/protocol/tri/transport/GracefulShutdown.gracefulShutdown:()V
      29: return

  static {};
    Code:
       0: ldc           #36                 // class org/apache/dubbo/rpc/protocol/tri/transport/TripleServerConnectionHandler
       2: invokestatic  #37                 // Method org/apache/dubbo/common/logger/LoggerFactory.getErrorTypeAwareLogger:(Ljava/lang/Class;)Lorg/apache/dubbo/common/logger/ErrorTypeAwareLogger;
       5: putstatic     #9                  // Field logger:Lorg/apache/dubbo/common/logger/ErrorTypeAwareLogger;
       8: new           #38                 // class java/util/HashSet
      11: dup
      12: invokespecial #39                 // Method java/util/HashSet."<init>":()V
      15: putstatic     #21                 // Field QUIET_EXCEPTIONS:Ljava/util/Set;
      18: new           #38                 // class java/util/HashSet
      21: dup
      22: invokespecial #39                 // Method java/util/HashSet."<init>":()V
      25: putstatic     #18                 // Field QUIET_EXCEPTIONS_CLASS:Ljava/util/Set;
      28: getstatic     #21                 // Field QUIET_EXCEPTIONS:Ljava/util/Set;
      31: ldc           #40                 // String NativeIoException
      33: invokeinterface #41,  2           // InterfaceMethod java/util/Set.add:(Ljava/lang/Object;)Z
      38: pop
      39: getstatic     #18                 // Field QUIET_EXCEPTIONS_CLASS:Ljava/util/Set;
      42: ldc           #42                 // class java/io/IOException
      44: invokeinterface #41,  2           // InterfaceMethod java/util/Set.add:(Ljava/lang/Object;)Z
      49: pop
      50: getstatic     #18                 // Field QUIET_EXCEPTIONS_CLASS:Ljava/util/Set;
      53: ldc           #43                 // class java/net/SocketException
      55: invokeinterface #41,  2           // InterfaceMethod java/util/Set.add:(Ljava/lang/Object;)Z
      60: pop
      61: return
}
