Compiled from "TripleTailHandler.java"
public class org.apache.dubbo.rpc.protocol.tri.transport.TripleTailHandler extends io.netty.channel.ChannelInboundHandlerAdapter {
  public org.apache.dubbo.rpc.protocol.tri.transport.TripleTailHandler();
    Code:
       0: aload_0
       1: invokespecial #1                  // Method io/netty/channel/ChannelInboundHandlerAdapter."<init>":()V
       4: return

  public void channelRead(io.netty.channel.ChannelHandlerContext, java.lang.Object) throws java.lang.Exception;
    Code:
       0: aload_2
       1: instanceof    #2                  // class io/netty/util/ReferenceCounted
       4: ifeq          12
       7: aload_2
       8: invokestatic  #3                  // Method io/netty/util/ReferenceCountUtil.release:(Ljava/lang/Object;)Z
      11: pop
      12: return
}
