Compiled from "TripleHttp2FrameServerHandler.java"
public class org.apache.dubbo.rpc.protocol.tri.transport.TripleHttp2FrameServerHandler extends io.netty.channel.ChannelDuplexHandler {
  private static final org.apache.dubbo.common.logger.ErrorTypeAwareLogger LOGGER;

  private final org.apache.dubbo.rpc.PathResolver pathResolver;

  private final org.apache.dubbo.rpc.executor.ExecutorSupport executorSupport;

  private final java.lang.String acceptEncoding;

  private final org.apache.dubbo.rpc.protocol.tri.stream.TripleServerStream tripleServerStream;

  public org.apache.dubbo.rpc.protocol.tri.transport.TripleHttp2FrameServerHandler(org.apache.dubbo.rpc.model.FrameworkModel, org.apache.dubbo.rpc.executor.ExecutorSupport, java.util.List<org.apache.dubbo.rpc.HeaderFilter>, io.netty.handler.codec.http2.Http2StreamChannel, org.apache.dubbo.rpc.protocol.tri.transport.TripleWriteQueue);
    Code:
       0: aload_0
       1: invokespecial #2                  // Method io/netty/channel/ChannelDuplexHandler."<init>":()V
       4: aload_0
       5: aload_2
       6: putfield      #3                  // Field executorSupport:Lorg/apache/dubbo/rpc/executor/ExecutorSupport;
       9: aload_0
      10: ldc           #4                  // String ,
      12: aload_1
      13: ldc           #5                  // class org/apache/dubbo/rpc/protocol/tri/compressor/DeCompressor
      15: invokevirtual #6                  // Method org/apache/dubbo/rpc/model/FrameworkModel.getExtensionLoader:(Ljava/lang/Class;)Lorg/apache/dubbo/common/extension/ExtensionLoader;
      18: invokevirtual #7                  // Method org/apache/dubbo/common/extension/ExtensionLoader.getSupportedExtensions:()Ljava/util/Set;
      21: invokestatic  #8                  // Method java/lang/String.join:(Ljava/lang/CharSequence;Ljava/lang/Iterable;)Ljava/lang/String;
      24: putfield      #9                  // Field acceptEncoding:Ljava/lang/String;
      27: aload_0
      28: aload_1
      29: ldc           #10                 // class org/apache/dubbo/rpc/PathResolver
      31: invokevirtual #6                  // Method org/apache/dubbo/rpc/model/FrameworkModel.getExtensionLoader:(Ljava/lang/Class;)Lorg/apache/dubbo/common/extension/ExtensionLoader;
      34: invokevirtual #11                 // Method org/apache/dubbo/common/extension/ExtensionLoader.getDefaultExtension:()Ljava/lang/Object;
      37: checkcast     #10                 // class org/apache/dubbo/rpc/PathResolver
      40: putfield      #12                 // Field pathResolver:Lorg/apache/dubbo/rpc/PathResolver;
      43: aload_0
      44: new           #13                 // class org/apache/dubbo/rpc/protocol/tri/stream/TripleServerStream
      47: dup
      48: aload         4
      50: aload_1
      51: aconst_null
      52: aload_0
      53: getfield      #12                 // Field pathResolver:Lorg/apache/dubbo/rpc/PathResolver;
      56: aload_0
      57: getfield      #9                  // Field acceptEncoding:Ljava/lang/String;
      60: aload_3
      61: aload         5
      63: invokespecial #14                 // Method org/apache/dubbo/rpc/protocol/tri/stream/TripleServerStream."<init>":(Lio/netty/handler/codec/http2/Http2StreamChannel;Lorg/apache/dubbo/rpc/model/FrameworkModel;Ljava/util/concurrent/Executor;Lorg/apache/dubbo/rpc/PathResolver;Ljava/lang/String;Ljava/util/List;Lorg/apache/dubbo/rpc/protocol/tri/transport/TripleWriteQueue;)V
      66: putfield      #15                 // Field tripleServerStream:Lorg/apache/dubbo/rpc/protocol/tri/stream/TripleServerStream;
      69: return

  public void channelRead(io.netty.channel.ChannelHandlerContext, java.lang.Object) throws java.lang.Exception;
    Code:
       0: aload_2
       1: instanceof    #16                 // class io/netty/handler/codec/http2/Http2HeadersFrame
       4: ifeq          19
       7: aload_0
       8: aload_1
       9: aload_2
      10: checkcast     #16                 // class io/netty/handler/codec/http2/Http2HeadersFrame
      13: invokevirtual #17                 // Method onHeadersRead:(Lio/netty/channel/ChannelHandlerContext;Lio/netty/handler/codec/http2/Http2HeadersFrame;)V
      16: goto          50
      19: aload_2
      20: instanceof    #18                 // class io/netty/handler/codec/http2/Http2DataFrame
      23: ifeq          38
      26: aload_0
      27: aload_1
      28: aload_2
      29: checkcast     #18                 // class io/netty/handler/codec/http2/Http2DataFrame
      32: invokevirtual #19                 // Method onDataRead:(Lio/netty/channel/ChannelHandlerContext;Lio/netty/handler/codec/http2/Http2DataFrame;)V
      35: goto          50
      38: aload_2
      39: instanceof    #20                 // class io/netty/util/ReferenceCounted
      42: ifeq          50
      45: aload_2
      46: invokestatic  #21                 // Method io/netty/util/ReferenceCountUtil.release:(Ljava/lang/Object;)Z
      49: pop
      50: return

  public void userEventTriggered(io.netty.channel.ChannelHandlerContext, java.lang.Object) throws java.lang.Exception;
    Code:
       0: aload_2
       1: instanceof    #22                 // class io/netty/handler/codec/http2/Http2ResetFrame
       4: ifeq          19
       7: aload_0
       8: aload_1
       9: aload_2
      10: checkcast     #22                 // class io/netty/handler/codec/http2/Http2ResetFrame
      13: invokevirtual #23                 // Method onResetRead:(Lio/netty/channel/ChannelHandlerContext;Lio/netty/handler/codec/http2/Http2ResetFrame;)V
      16: goto          25
      19: aload_0
      20: aload_1
      21: aload_2
      22: invokespecial #24                 // Method io/netty/channel/ChannelDuplexHandler.userEventTriggered:(Lio/netty/channel/ChannelHandlerContext;Ljava/lang/Object;)V
      25: return

  public void onResetRead(io.netty.channel.ChannelHandlerContext, io.netty.handler.codec.http2.Http2ResetFrame);
    Code:
       0: getstatic     #25                 // Field LOGGER:Lorg/apache/dubbo/common/logger/ErrorTypeAwareLogger;
       3: ldc           #26                 // String 4-14
       5: ldc           #27                 // String
       7: ldc           #27                 // String
       9: new           #28                 // class java/lang/StringBuilder
      12: dup
      13: invokespecial #29                 // Method java/lang/StringBuilder."<init>":()V
      16: ldc           #30                 // String Triple Server received remote reset errorCode=
      18: invokevirtual #31                 // Method java/lang/StringBuilder.append:(Ljava/lang/String;)Ljava/lang/StringBuilder;
      21: aload_2
      22: invokeinterface #32,  1           // InterfaceMethod io/netty/handler/codec/http2/Http2ResetFrame.errorCode:()J
      27: invokevirtual #33                 // Method java/lang/StringBuilder.append:(J)Ljava/lang/StringBuilder;
      30: invokevirtual #34                 // Method java/lang/StringBuilder.toString:()Ljava/lang/String;
      33: invokeinterface #35,  5           // InterfaceMethod org/apache/dubbo/common/logger/ErrorTypeAwareLogger.warn:(Ljava/lang/String;Ljava/lang/String;Ljava/lang/String;Ljava/lang/String;)V
      38: aload_0
      39: getfield      #15                 // Field tripleServerStream:Lorg/apache/dubbo/rpc/protocol/tri/stream/TripleServerStream;
      42: ifnull        61
      45: aload_0
      46: getfield      #15                 // Field tripleServerStream:Lorg/apache/dubbo/rpc/protocol/tri/stream/TripleServerStream;
      49: getfield      #36                 // Field org/apache/dubbo/rpc/protocol/tri/stream/TripleServerStream.transportObserver:Lorg/apache/dubbo/rpc/protocol/tri/stream/TripleServerStream$ServerTransportObserver;
      52: aload_2
      53: invokeinterface #32,  1           // InterfaceMethod io/netty/handler/codec/http2/Http2ResetFrame.errorCode:()J
      58: invokevirtual #37                 // Method org/apache/dubbo/rpc/protocol/tri/stream/TripleServerStream$ServerTransportObserver.cancelByRemote:(J)V
      61: return

  public void exceptionCaught(io.netty.channel.ChannelHandlerContext, java.lang.Throwable) throws java.lang.Exception;
    Code:
       0: getstatic     #25                 // Field LOGGER:Lorg/apache/dubbo/common/logger/ErrorTypeAwareLogger;
       3: invokeinterface #38,  1           // InterfaceMethod org/apache/dubbo/common/logger/ErrorTypeAwareLogger.isWarnEnabled:()Z
       8: ifeq          28
      11: getstatic     #25                 // Field LOGGER:Lorg/apache/dubbo/common/logger/ErrorTypeAwareLogger;
      14: ldc           #26                 // String 4-14
      16: ldc           #27                 // String
      18: ldc           #27                 // String
      20: ldc           #39                 // String Exception in processing triple message
      22: aload_2
      23: invokeinterface #40,  6           // InterfaceMethod org/apache/dubbo/common/logger/ErrorTypeAwareLogger.warn:(Ljava/lang/String;Ljava/lang/String;Ljava/lang/String;Ljava/lang/String;Ljava/lang/Throwable;)V
      28: aload_2
      29: new           #28                 // class java/lang/StringBuilder
      32: dup
      33: invokespecial #29                 // Method java/lang/StringBuilder."<init>":()V
      36: ldc           #41                 // String Provider\'s error:\n
      38: invokevirtual #31                 // Method java/lang/StringBuilder.append:(Ljava/lang/String;)Ljava/lang/StringBuilder;
      41: aload_2
      42: invokevirtual #42                 // Method java/lang/Throwable.getMessage:()Ljava/lang/String;
      45: invokevirtual #31                 // Method java/lang/StringBuilder.append:(Ljava/lang/String;)Ljava/lang/StringBuilder;
      48: invokevirtual #34                 // Method java/lang/StringBuilder.toString:()Ljava/lang/String;
      51: invokestatic  #43                 // Method org/apache/dubbo/rpc/TriRpcStatus.getStatus:(Ljava/lang/Throwable;Ljava/lang/String;)Lorg/apache/dubbo/rpc/TriRpcStatus;
      54: astore_3
      55: aload_0
      56: getfield      #15                 // Field tripleServerStream:Lorg/apache/dubbo/rpc/protocol/tri/stream/TripleServerStream;
      59: aload_3
      60: invokevirtual #44                 // Method org/apache/dubbo/rpc/protocol/tri/stream/TripleServerStream.cancelByLocal:(Lorg/apache/dubbo/rpc/TriRpcStatus;)Lio/netty/util/concurrent/Future;
      63: pop
      64: return

  public void onDataRead(io.netty.channel.ChannelHandlerContext, io.netty.handler.codec.http2.Http2DataFrame) throws java.lang.Exception;
    Code:
       0: aload_0
       1: getfield      #15                 // Field tripleServerStream:Lorg/apache/dubbo/rpc/protocol/tri/stream/TripleServerStream;
       4: getfield      #36                 // Field org/apache/dubbo/rpc/protocol/tri/stream/TripleServerStream.transportObserver:Lorg/apache/dubbo/rpc/protocol/tri/stream/TripleServerStream$ServerTransportObserver;
       7: aload_2
       8: invokeinterface #45,  1           // InterfaceMethod io/netty/handler/codec/http2/Http2DataFrame.content:()Lio/netty/buffer/ByteBuf;
      13: aload_2
      14: invokeinterface #46,  1           // InterfaceMethod io/netty/handler/codec/http2/Http2DataFrame.isEndStream:()Z
      19: invokevirtual #47                 // Method org/apache/dubbo/rpc/protocol/tri/stream/TripleServerStream$ServerTransportObserver.onData:(Lio/netty/buffer/ByteBuf;Z)V
      22: return

  public void onHeadersRead(io.netty.channel.ChannelHandlerContext, io.netty.handler.codec.http2.Http2HeadersFrame) throws java.lang.Exception;
    Code:
       0: aload_0
       1: getfield      #3                  // Field executorSupport:Lorg/apache/dubbo/rpc/executor/ExecutorSupport;
       4: aload_2
       5: invokeinterface #48,  1           // InterfaceMethod io/netty/handler/codec/http2/Http2HeadersFrame.headers:()Lio/netty/handler/codec/http2/Http2Headers;
      10: invokeinterface #49,  2           // InterfaceMethod org/apache/dubbo/rpc/executor/ExecutorSupport.getExecutor:(Ljava/lang/Object;)Ljava/util/concurrent/Executor;
      15: astore_3
      16: aload_0
      17: getfield      #15                 // Field tripleServerStream:Lorg/apache/dubbo/rpc/protocol/tri/stream/TripleServerStream;
      20: aload_3
      21: invokevirtual #50                 // Method org/apache/dubbo/rpc/protocol/tri/stream/TripleServerStream.setExecutor:(Ljava/util/concurrent/Executor;)V
      24: aload_0
      25: getfield      #15                 // Field tripleServerStream:Lorg/apache/dubbo/rpc/protocol/tri/stream/TripleServerStream;
      28: getfield      #36                 // Field org/apache/dubbo/rpc/protocol/tri/stream/TripleServerStream.transportObserver:Lorg/apache/dubbo/rpc/protocol/tri/stream/TripleServerStream$ServerTransportObserver;
      31: aload_2
      32: invokeinterface #48,  1           // InterfaceMethod io/netty/handler/codec/http2/Http2HeadersFrame.headers:()Lio/netty/handler/codec/http2/Http2Headers;
      37: aload_2
      38: invokeinterface #51,  1           // InterfaceMethod io/netty/handler/codec/http2/Http2HeadersFrame.isEndStream:()Z
      43: invokevirtual #52                 // Method org/apache/dubbo/rpc/protocol/tri/stream/TripleServerStream$ServerTransportObserver.onHeader:(Lio/netty/handler/codec/http2/Http2Headers;Z)V
      46: return

  static {};
    Code:
       0: ldc           #53                 // class org/apache/dubbo/rpc/protocol/tri/transport/TripleHttp2FrameServerHandler
       2: invokestatic  #54                 // Method org/apache/dubbo/common/logger/LoggerFactory.getErrorTypeAwareLogger:(Ljava/lang/Class;)Lorg/apache/dubbo/common/logger/ErrorTypeAwareLogger;
       5: putstatic     #25                 // Field LOGGER:Lorg/apache/dubbo/common/logger/ErrorTypeAwareLogger;
       8: return
}
