Compiled from "TripleWriteQueue.java"
public class org.apache.dubbo.rpc.protocol.tri.transport.TripleWriteQueue extends org.apache.dubbo.common.BatchExecutorQueue<org.apache.dubbo.rpc.protocol.tri.command.QueuedCommand> {
  public org.apache.dubbo.rpc.protocol.tri.transport.TripleWriteQueue();
    Code:
       0: aload_0
       1: invokespecial #1                  // Method org/apache/dubbo/common/BatchExecutorQueue."<init>":()V
       4: return

  public org.apache.dubbo.rpc.protocol.tri.transport.TripleWriteQueue(int);
    Code:
       0: aload_0
       1: iload_1
       2: invokespecial #2                  // Method org/apache/dubbo/common/BatchExecutorQueue."<init>":(I)V
       5: return

  public io.netty.channel.ChannelFuture enqueue(org.apache.dubbo.rpc.protocol.tri.command.QueuedCommand, boolean);
    Code:
       0: aload_0
       1: aload_1
       2: invokevirtual #3                  // Method enqueue:(Lorg/apache/dubbo/rpc/protocol/tri/command/QueuedCommand;)Lio/netty/channel/ChannelFuture;
       5: areturn

  public io.netty.channel.ChannelFuture enqueue(org.apache.dubbo.rpc.protocol.tri.command.QueuedCommand);
    Code:
       0: aload_0
       1: aload_1
       2: aload_1
       3: invokevirtual #4                  // Method org/apache/dubbo/rpc/protocol/tri/command/QueuedCommand.channel:()Lio/netty/channel/Channel;
       6: invokeinterface #5,  1            // InterfaceMethod io/netty/channel/Channel.eventLoop:()Lio/netty/channel/EventLoop;
      11: invokevirtual #6                  // Method enqueueFuture:(Lorg/apache/dubbo/rpc/protocol/tri/command/QueuedCommand;Ljava/util/concurrent/Executor;)Lio/netty/channel/ChannelFuture;
      14: areturn

  public io.netty.channel.ChannelFuture enqueueFuture(org.apache.dubbo.rpc.protocol.tri.command.QueuedCommand, java.util.concurrent.Executor);
    Code:
       0: aload_1
       1: invokevirtual #7                  // Method org/apache/dubbo/rpc/protocol/tri/command/QueuedCommand.promise:()Lio/netty/channel/ChannelPromise;
       4: astore_3
       5: aload_3
       6: ifnonnull     28
       9: aload_1
      10: invokevirtual #4                  // Method org/apache/dubbo/rpc/protocol/tri/command/QueuedCommand.channel:()Lio/netty/channel/Channel;
      13: astore        4
      15: aload         4
      17: invokeinterface #8,  1            // InterfaceMethod io/netty/channel/Channel.newPromise:()Lio/netty/channel/ChannelPromise;
      22: astore_3
      23: aload_1
      24: aload_3
      25: invokevirtual #9                  // Method org/apache/dubbo/rpc/protocol/tri/command/QueuedCommand.promise:(Lio/netty/channel/ChannelPromise;)V
      28: aload_0
      29: aload_1
      30: aload_2
      31: invokespecial #10                 // Method org/apache/dubbo/common/BatchExecutorQueue.enqueue:(Ljava/lang/Object;Ljava/util/concurrent/Executor;)V
      34: aload_3
      35: areturn

  protected void prepare(org.apache.dubbo.rpc.protocol.tri.command.QueuedCommand);
    Code:
       0: aload_1
       1: aload_1
       2: invokevirtual #4                  // Method org/apache/dubbo/rpc/protocol/tri/command/QueuedCommand.channel:()Lio/netty/channel/Channel;
       5: invokevirtual #11                 // Method org/apache/dubbo/rpc/protocol/tri/command/QueuedCommand.run:(Lio/netty/channel/Channel;)V
       8: return

  protected void flush(org.apache.dubbo.rpc.protocol.tri.command.QueuedCommand);
    Code:
       0: aload_1
       1: invokevirtual #4                  // Method org/apache/dubbo/rpc/protocol/tri/command/QueuedCommand.channel:()Lio/netty/channel/Channel;
       4: astore_2
       5: aload_1
       6: aload_2
       7: invokevirtual #11                 // Method org/apache/dubbo/rpc/protocol/tri/command/QueuedCommand.run:(Lio/netty/channel/Channel;)V
      10: aload_2
      11: invokeinterface #12,  1           // InterfaceMethod io/netty/channel/Channel.flush:()Lio/netty/channel/Channel;
      16: pop
      17: return

  protected void flush(java.lang.Object);
    Code:
       0: aload_0
       1: aload_1
       2: checkcast     #13                 // class org/apache/dubbo/rpc/protocol/tri/command/QueuedCommand
       5: invokevirtual #14                 // Method flush:(Lorg/apache/dubbo/rpc/protocol/tri/command/QueuedCommand;)V
       8: return

  protected void prepare(java.lang.Object);
    Code:
       0: aload_0
       1: aload_1
       2: checkcast     #13                 // class org/apache/dubbo/rpc/protocol/tri/command/QueuedCommand
       5: invokevirtual #15                 // Method prepare:(Lorg/apache/dubbo/rpc/protocol/tri/command/QueuedCommand;)V
       8: return
}
