Compiled from "TripleCommandOutBoundHandler.java"
public class org.apache.dubbo.rpc.protocol.tri.transport.TripleCommandOutBoundHandler extends io.netty.channel.ChannelOutboundHandlerAdapter {
  public org.apache.dubbo.rpc.protocol.tri.transport.TripleCommandOutBoundHandler();
    Code:
       0: aload_0
       1: invokespecial #1                  // Method io/netty/channel/ChannelOutboundHandlerAdapter."<init>":()V
       4: return

  public void write(io.netty.channel.ChannelHandlerContext, java.lang.Object, io.netty.channel.ChannelPromise) throws java.lang.Exception;
    Code:
       0: aload_2
       1: instanceof    #2                  // class org/apache/dubbo/rpc/protocol/tri/command/QueuedCommand
       4: ifeq          23
       7: aload_2
       8: checkcast     #2                  // class org/apache/dubbo/rpc/protocol/tri/command/QueuedCommand
      11: astore        4
      13: aload         4
      15: aload_1
      16: aload_3
      17: invokevirtual #3                  // Method org/apache/dubbo/rpc/protocol/tri/command/QueuedCommand.send:(Lio/netty/channel/ChannelHandlerContext;Lio/netty/channel/ChannelPromise;)V
      20: goto          30
      23: aload_0
      24: aload_1
      25: aload_2
      26: aload_3
      27: invokespecial #4                  // Method io/netty/channel/ChannelOutboundHandlerAdapter.write:(Lio/netty/channel/ChannelHandlerContext;Ljava/lang/Object;Lio/netty/channel/ChannelPromise;)V
      30: return
}
