Compiled from "TripleIsolationExecutorSupport.java"
public class org.apache.dubbo.rpc.protocol.tri.transport.TripleIsolationExecutorSupport extends org.apache.dubbo.rpc.executor.AbstractIsolationExecutorSupport {
  private static final org.apache.dubbo.common.logger.ErrorTypeAwareLogger logger;

  public org.apache.dubbo.rpc.protocol.tri.transport.TripleIsolationExecutorSupport(org.apache.dubbo.common.URL);
    Code:
       0: aload_0
       1: aload_1
       2: invokespecial #1                  // Method org/apache/dubbo/rpc/executor/AbstractIsolationExecutorSupport."<init>":(Lorg/apache/dubbo/common/URL;)V
       5: return

  protected org.apache.dubbo.common.ServiceKey getServiceKey(java.lang.Object);
    Code:
       0: aload_1
       1: instanceof    #2                  // class io/netty/handler/codec/http2/Http2Headers
       4: ifne          9
       7: aconst_null
       8: areturn
       9: aload_1
      10: checkcast     #2                  // class io/netty/handler/codec/http2/Http2Headers
      13: astore_2
      14: aload_2
      15: invokeinterface #3,  1            // InterfaceMethod io/netty/handler/codec/http2/Http2Headers.path:()Ljava/lang/CharSequence;
      20: invokeinterface #4,  1            // InterfaceMethod java/lang/CharSequence.toString:()Ljava/lang/String;
      25: astore_3
      26: aload_3
      27: ldc           #5                  // String /
      29: invokevirtual #6                  // Method java/lang/String.split:(Ljava/lang/String;)[Ljava/lang/String;
      32: astore        4
      34: aload         4
      36: iconst_1
      37: aaload
      38: astore        5
      40: aload_2
      41: getstatic     #7                  // Field org/apache/dubbo/rpc/protocol/tri/TripleHeaderEnum.SERVICE_VERSION:Lorg/apache/dubbo/rpc/protocol/tri/TripleHeaderEnum;
      44: invokevirtual #8                  // Method org/apache/dubbo/rpc/protocol/tri/TripleHeaderEnum.getHeader:()Ljava/lang/String;
      47: invokeinterface #9,  2            // InterfaceMethod io/netty/handler/codec/http2/Http2Headers.contains:(Ljava/lang/Object;)Z
      52: ifeq          78
      55: aload_2
      56: getstatic     #7                  // Field org/apache/dubbo/rpc/protocol/tri/TripleHeaderEnum.SERVICE_VERSION:Lorg/apache/dubbo/rpc/protocol/tri/TripleHeaderEnum;
      59: invokevirtual #8                  // Method org/apache/dubbo/rpc/protocol/tri/TripleHeaderEnum.getHeader:()Ljava/lang/String;
      62: invokeinterface #10,  2           // InterfaceMethod io/netty/handler/codec/http2/Http2Headers.get:(Ljava/lang/Object;)Ljava/lang/Object;
      67: checkcast     #11                 // class java/lang/CharSequence
      70: invokeinterface #4,  1            // InterfaceMethod java/lang/CharSequence.toString:()Ljava/lang/String;
      75: goto          79
      78: aconst_null
      79: astore        6
      81: aload_2
      82: getstatic     #12                 // Field org/apache/dubbo/rpc/protocol/tri/TripleHeaderEnum.SERVICE_GROUP:Lorg/apache/dubbo/rpc/protocol/tri/TripleHeaderEnum;
      85: invokevirtual #8                  // Method org/apache/dubbo/rpc/protocol/tri/TripleHeaderEnum.getHeader:()Ljava/lang/String;
      88: invokeinterface #9,  2            // InterfaceMethod io/netty/handler/codec/http2/Http2Headers.contains:(Ljava/lang/Object;)Z
      93: ifeq          119
      96: aload_2
      97: getstatic     #12                 // Field org/apache/dubbo/rpc/protocol/tri/TripleHeaderEnum.SERVICE_GROUP:Lorg/apache/dubbo/rpc/protocol/tri/TripleHeaderEnum;
     100: invokevirtual #8                  // Method org/apache/dubbo/rpc/protocol/tri/TripleHeaderEnum.getHeader:()Ljava/lang/String;
     103: invokeinterface #10,  2           // InterfaceMethod io/netty/handler/codec/http2/Http2Headers.get:(Ljava/lang/Object;)Ljava/lang/Object;
     108: checkcast     #11                 // class java/lang/CharSequence
     111: invokeinterface #4,  1            // InterfaceMethod java/lang/CharSequence.toString:()Ljava/lang/String;
     116: goto          120
     119: aconst_null
     120: astore        7
     122: new           #13                 // class org/apache/dubbo/common/ServiceKey
     125: dup
     126: aload         5
     128: aload         6
     130: aload         7
     132: invokespecial #14                 // Method org/apache/dubbo/common/ServiceKey."<init>":(Ljava/lang/String;Ljava/lang/String;Ljava/lang/String;)V
     135: areturn

  static {};
    Code:
       0: ldc           #15                 // class org/apache/dubbo/rpc/protocol/tri/transport/TripleIsolationExecutorSupport
       2: invokestatic  #16                 // Method org/apache/dubbo/common/logger/LoggerFactory.getErrorTypeAwareLogger:(Ljava/lang/Class;)Lorg/apache/dubbo/common/logger/ErrorTypeAwareLogger;
       5: putstatic     #17                 // Field logger:Lorg/apache/dubbo/common/logger/ErrorTypeAwareLogger;
       8: return
}
