Compiled from "WriteQueue.java"
public class org.apache.dubbo.rpc.protocol.tri.transport.WriteQueue {
  static final int DEQUE_CHUNK_SIZE;

  private final java.util.Queue<org.apache.dubbo.rpc.protocol.tri.command.QueuedCommand> queue;

  private final java.util.concurrent.atomic.AtomicBoolean scheduled;

  public org.apache.dubbo.rpc.protocol.tri.transport.WriteQueue();
    Code:
       0: aload_0
       1: invokespecial #1                  // Method java/lang/Object."<init>":()V
       4: aload_0
       5: new           #2                  // class java/util/concurrent/ConcurrentLinkedQueue
       8: dup
       9: invokespecial #3                  // Method java/util/concurrent/ConcurrentLinkedQueue."<init>":()V
      12: putfield      #4                  // Field queue:Ljava/util/Queue;
      15: aload_0
      16: new           #5                  // class java/util/concurrent/atomic/AtomicBoolean
      19: dup
      20: iconst_0
      21: invokespecial #6                  // Method java/util/concurrent/atomic/AtomicBoolean."<init>":(Z)V
      24: putfield      #7                  // Field scheduled:Ljava/util/concurrent/atomic/AtomicBoolean;
      27: return

  public io.netty.channel.ChannelFuture enqueue(org.apache.dubbo.rpc.protocol.tri.command.QueuedCommand, boolean);
    Code:
       0: aload_0
       1: aload_1
       2: invokevirtual #8                  // Method enqueue:(Lorg/apache/dubbo/rpc/protocol/tri/command/QueuedCommand;)Lio/netty/channel/ChannelFuture;
       5: areturn

  public io.netty.channel.ChannelFuture enqueue(org.apache.dubbo.rpc.protocol.tri.command.QueuedCommand);
    Code:
       0: aload_1
       1: invokevirtual #9                  // Method org/apache/dubbo/rpc/protocol/tri/command/QueuedCommand.promise:()Lio/netty/channel/ChannelPromise;
       4: astore_2
       5: aload_2
       6: ifnonnull     26
       9: aload_1
      10: invokevirtual #10                 // Method org/apache/dubbo/rpc/protocol/tri/command/QueuedCommand.channel:()Lio/netty/channel/Channel;
      13: astore_3
      14: aload_3
      15: invokeinterface #11,  1           // InterfaceMethod io/netty/channel/Channel.newPromise:()Lio/netty/channel/ChannelPromise;
      20: astore_2
      21: aload_1
      22: aload_2
      23: invokevirtual #12                 // Method org/apache/dubbo/rpc/protocol/tri/command/QueuedCommand.promise:(Lio/netty/channel/ChannelPromise;)V
      26: aload_0
      27: getfield      #4                  // Field queue:Ljava/util/Queue;
      30: aload_1
      31: invokeinterface #13,  2           // InterfaceMethod java/util/Queue.add:(Ljava/lang/Object;)Z
      36: pop
      37: aload_0
      38: aload_1
      39: invokevirtual #10                 // Method org/apache/dubbo/rpc/protocol/tri/command/QueuedCommand.channel:()Lio/netty/channel/Channel;
      42: invokevirtual #14                 // Method scheduleFlush:(Lio/netty/channel/Channel;)V
      45: aload_2
      46: areturn

  public void scheduleFlush(io.netty.channel.Channel);
    Code:
       0: aload_0
       1: getfield      #7                  // Field scheduled:Ljava/util/concurrent/atomic/AtomicBoolean;
       4: iconst_0
       5: iconst_1
       6: invokevirtual #15                 // Method java/util/concurrent/atomic/AtomicBoolean.compareAndSet:(ZZ)Z
       9: ifeq          34
      12: aload_1
      13: invokeinterface #16,  1           // InterfaceMethod io/netty/channel/Channel.parent:()Lio/netty/channel/Channel;
      18: invokeinterface #17,  1           // InterfaceMethod io/netty/channel/Channel.eventLoop:()Lio/netty/channel/EventLoop;
      23: aload_0
      24: invokedynamic #18,  0             // InvokeDynamic #0:run:(Lorg/apache/dubbo/rpc/protocol/tri/transport/WriteQueue;)Ljava/lang/Runnable;
      29: invokeinterface #19,  2           // InterfaceMethod io/netty/channel/EventLoop.execute:(Ljava/lang/Runnable;)V
      34: return

  private void flush();
    Code:
       0: aconst_null
       1: astore_1
       2: iconst_0
       3: istore_3
       4: iconst_0
       5: istore        4
       7: aload_0
       8: getfield      #4                  // Field queue:Ljava/util/Queue;
      11: invokeinterface #20,  1           // InterfaceMethod java/util/Queue.poll:()Ljava/lang/Object;
      16: checkcast     #21                 // class org/apache/dubbo/rpc/protocol/tri/command/QueuedCommand
      19: dup
      20: astore_2
      21: ifnull        64
      24: aload_2
      25: invokevirtual #10                 // Method org/apache/dubbo/rpc/protocol/tri/command/QueuedCommand.channel:()Lio/netty/channel/Channel;
      28: astore_1
      29: aload_2
      30: aload_1
      31: invokevirtual #22                 // Method org/apache/dubbo/rpc/protocol/tri/command/QueuedCommand.run:(Lio/netty/channel/Channel;)V
      34: iinc          3, 1
      37: iload_3
      38: sipush        128
      41: if_icmpne     7
      44: iconst_0
      45: istore_3
      46: aload_1
      47: invokeinterface #16,  1           // InterfaceMethod io/netty/channel/Channel.parent:()Lio/netty/channel/Channel;
      52: invokeinterface #24,  1           // InterfaceMethod io/netty/channel/Channel.flush:()Lio/netty/channel/Channel;
      57: pop
      58: iconst_1
      59: istore        4
      61: goto          7
      64: aload_1
      65: ifnull        89
      68: iload_3
      69: ifne          77
      72: iload         4
      74: ifne          89
      77: aload_1
      78: invokeinterface #16,  1           // InterfaceMethod io/netty/channel/Channel.parent:()Lio/netty/channel/Channel;
      83: invokeinterface #24,  1           // InterfaceMethod io/netty/channel/Channel.flush:()Lio/netty/channel/Channel;
      88: pop
      89: aload_0
      90: getfield      #7                  // Field scheduled:Ljava/util/concurrent/atomic/AtomicBoolean;
      93: iconst_0
      94: invokevirtual #25                 // Method java/util/concurrent/atomic/AtomicBoolean.set:(Z)V
      97: aload_0
      98: getfield      #4                  // Field queue:Ljava/util/Queue;
     101: invokeinterface #26,  1           // InterfaceMethod java/util/Queue.isEmpty:()Z
     106: ifne          147
     109: aload_0
     110: aload_1
     111: invokevirtual #14                 // Method scheduleFlush:(Lio/netty/channel/Channel;)V
     114: goto          147
     117: astore        5
     119: aload_0
     120: getfield      #7                  // Field scheduled:Ljava/util/concurrent/atomic/AtomicBoolean;
     123: iconst_0
     124: invokevirtual #25                 // Method java/util/concurrent/atomic/AtomicBoolean.set:(Z)V
     127: aload_0
     128: getfield      #4                  // Field queue:Ljava/util/Queue;
     131: invokeinterface #26,  1           // InterfaceMethod java/util/Queue.isEmpty:()Z
     136: ifne          144
     139: aload_0
     140: aload_1
     141: invokevirtual #14                 // Method scheduleFlush:(Lio/netty/channel/Channel;)V
     144: aload         5
     146: athrow
     147: return
    Exception table:
       from    to  target type
           2    89   117   any
         117   119   117   any
}
