Compiled from "AdaptiveClassCodeGenerator.java"
public class org.apache.dubbo.common.extension.AdaptiveClassCodeGenerator {
  private static final org.apache.dubbo.common.logger.Logger logger;

  private static final java.lang.String CLASS_NAME_INVOCATION;

  private static final java.lang.String CODE_PACKAGE;

  private static final java.lang.String CODE_IMPORTS;

  private static final java.lang.String CODE_CLASS_DECLARATION;

  private static final java.lang.String CODE_METHOD_DECLARATION;

  private static final java.lang.String CODE_METHOD_ARGUMENT;

  private static final java.lang.String CODE_METHOD_THROWS;

  private static final java.lang.String CODE_UNSUPPORTED;

  private static final java.lang.String CODE_URL_NULL_CHECK;

  private static final java.lang.String CODE_EXT_NAME_ASSIGNMENT;

  private static final java.lang.String CODE_EXT_NAME_NULL_CHECK;

  private static final java.lang.String CODE_INVOCATION_ARGUMENT_NULL_CHECK;

  private static final java.lang.String CODE_SCOPE_MODEL_ASSIGNMENT;

  private static final java.lang.String CODE_EXTENSION_ASSIGNMENT;

  private static final java.lang.String CODE_EXTENSION_METHOD_INVOKE_ARGUMENT;

  private final java.lang.Class<?> type;

  private final java.lang.String defaultExtName;

  public org.apache.dubbo.common.extension.AdaptiveClassCodeGenerator(java.lang.Class<?>, java.lang.String);
    Code:
       0: aload_0
       1: invokespecial #1                  // Method java/lang/Object."<init>":()V
       4: aload_0
       5: aload_1
       6: putfield      #2                  // Field type:Ljava/lang/Class;
       9: aload_0
      10: aload_2
      11: putfield      #3                  // Field defaultExtName:Ljava/lang/String;
      14: return

  private boolean hasAdaptiveMethod();
    Code:
       0: aload_0
       1: getfield      #2                  // Field type:Ljava/lang/Class;
       4: invokevirtual #4                  // Method java/lang/Class.getMethods:()[Ljava/lang/reflect/Method;
       7: invokestatic  #5                  // Method java/util/Arrays.stream:([Ljava/lang/Object;)Ljava/util/stream/Stream;
      10: invokedynamic #6,  0              // InvokeDynamic #0:test:()Ljava/util/function/Predicate;
      15: invokeinterface #7,  2            // InterfaceMethod java/util/stream/Stream.anyMatch:(Ljava/util/function/Predicate;)Z
      20: ireturn

  public java.lang.String generate();
    Code:
       0: aload_0
       1: iconst_0
       2: invokevirtual #8                  // Method generate:(Z)Ljava/lang/String;
       5: areturn

  public java.lang.String generate(boolean);
    Code:
       0: aload_0
       1: invokespecial #9                  // Method hasAdaptiveMethod:()Z
       4: ifne          45
       7: new           #10                 // class java/lang/IllegalStateException
      10: dup
      11: new           #11                 // class java/lang/StringBuilder
      14: dup
      15: invokespecial #12                 // Method java/lang/StringBuilder."<init>":()V
      18: ldc           #13                 // String No adaptive method exist on extension
      20: invokevirtual #14                 // Method java/lang/StringBuilder.append:(Ljava/lang/String;)Ljava/lang/StringBuilder;
      23: aload_0
      24: getfield      #2                  // Field type:Ljava/lang/Class;
      27: invokevirtual #15                 // Method java/lang/Class.getName:()Ljava/lang/String;
      30: invokevirtual #14                 // Method java/lang/StringBuilder.append:(Ljava/lang/String;)Ljava/lang/StringBuilder;
      33: ldc           #16                 // String , refuse to create the adaptive class!
      35: invokevirtual #14                 // Method java/lang/StringBuilder.append:(Ljava/lang/String;)Ljava/lang/StringBuilder;
      38: invokevirtual #17                 // Method java/lang/StringBuilder.toString:()Ljava/lang/String;
      41: invokespecial #18                 // Method java/lang/IllegalStateException."<init>":(Ljava/lang/String;)V
      44: athrow
      45: new           #11                 // class java/lang/StringBuilder
      48: dup
      49: invokespecial #12                 // Method java/lang/StringBuilder."<init>":()V
      52: astore_2
      53: aload_2
      54: aload_0
      55: invokespecial #19                 // Method generatePackageInfo:()Ljava/lang/String;
      58: invokevirtual #14                 // Method java/lang/StringBuilder.append:(Ljava/lang/String;)Ljava/lang/StringBuilder;
      61: pop
      62: aload_2
      63: aload_0
      64: invokespecial #20                 // Method generateImports:()Ljava/lang/String;
      67: invokevirtual #14                 // Method java/lang/StringBuilder.append:(Ljava/lang/String;)Ljava/lang/StringBuilder;
      70: pop
      71: aload_2
      72: aload_0
      73: invokespecial #21                 // Method generateClassDeclaration:()Ljava/lang/String;
      76: invokevirtual #14                 // Method java/lang/StringBuilder.append:(Ljava/lang/String;)Ljava/lang/StringBuilder;
      79: pop
      80: aload_0
      81: getfield      #2                  // Field type:Ljava/lang/Class;
      84: invokevirtual #4                  // Method java/lang/Class.getMethods:()[Ljava/lang/reflect/Method;
      87: astore_3
      88: iload_1
      89: ifeq          104
      92: aload_3
      93: invokedynamic #22,  0             // InvokeDynamic #1:apply:()Ljava/util/function/Function;
      98: invokestatic  #23                 // InterfaceMethod java/util/Comparator.comparing:(Ljava/util/function/Function;)Ljava/util/Comparator;
     101: invokestatic  #24                 // Method java/util/Arrays.sort:([Ljava/lang/Object;Ljava/util/Comparator;)V
     104: aload_3
     105: astore        4
     107: aload         4
     109: arraylength
     110: istore        5
     112: iconst_0
     113: istore        6
     115: iload         6
     117: iload         5
     119: if_icmpge     146
     122: aload         4
     124: iload         6
     126: aaload
     127: astore        7
     129: aload_2
     130: aload_0
     131: aload         7
     133: invokespecial #25                 // Method generateMethod:(Ljava/lang/reflect/Method;)Ljava/lang/String;
     136: invokevirtual #14                 // Method java/lang/StringBuilder.append:(Ljava/lang/String;)Ljava/lang/StringBuilder;
     139: pop
     140: iinc          6, 1
     143: goto          115
     146: aload_2
     147: bipush        125
     149: invokevirtual #26                 // Method java/lang/StringBuilder.append:(C)Ljava/lang/StringBuilder;
     152: pop
     153: getstatic     #27                 // Field logger:Lorg/apache/dubbo/common/logger/Logger;
     156: invokeinterface #28,  1           // InterfaceMethod org/apache/dubbo/common/logger/Logger.isDebugEnabled:()Z
     161: ifeq          176
     164: getstatic     #27                 // Field logger:Lorg/apache/dubbo/common/logger/Logger;
     167: aload_2
     168: invokevirtual #17                 // Method java/lang/StringBuilder.toString:()Ljava/lang/String;
     171: invokeinterface #29,  2           // InterfaceMethod org/apache/dubbo/common/logger/Logger.debug:(Ljava/lang/String;)V
     176: aload_2
     177: invokevirtual #17                 // Method java/lang/StringBuilder.toString:()Ljava/lang/String;
     180: areturn

  private java.lang.String generatePackageInfo();
    Code:
       0: ldc           #31                 // String package %s;\n
       2: iconst_1
       3: anewarray     #32                 // class java/lang/Object
       6: dup
       7: iconst_0
       8: aload_0
       9: getfield      #2                  // Field type:Ljava/lang/Class;
      12: invokevirtual #33                 // Method java/lang/Class.getPackage:()Ljava/lang/Package;
      15: invokevirtual #34                 // Method java/lang/Package.getName:()Ljava/lang/String;
      18: aastore
      19: invokestatic  #35                 // Method java/lang/String.format:(Ljava/lang/String;[Ljava/lang/Object;)Ljava/lang/String;
      22: areturn

  private java.lang.String generateImports();
    Code:
       0: new           #11                 // class java/lang/StringBuilder
       3: dup
       4: invokespecial #12                 // Method java/lang/StringBuilder."<init>":()V
       7: astore_1
       8: aload_1
       9: ldc           #36                 // String import %s;\n
      11: iconst_1
      12: anewarray     #32                 // class java/lang/Object
      15: dup
      16: iconst_0
      17: ldc           #37                 // class org/apache/dubbo/rpc/model/ScopeModel
      19: invokevirtual #15                 // Method java/lang/Class.getName:()Ljava/lang/String;
      22: aastore
      23: invokestatic  #35                 // Method java/lang/String.format:(Ljava/lang/String;[Ljava/lang/Object;)Ljava/lang/String;
      26: invokevirtual #14                 // Method java/lang/StringBuilder.append:(Ljava/lang/String;)Ljava/lang/StringBuilder;
      29: pop
      30: aload_1
      31: ldc           #36                 // String import %s;\n
      33: iconst_1
      34: anewarray     #32                 // class java/lang/Object
      37: dup
      38: iconst_0
      39: ldc           #38                 // class org/apache/dubbo/rpc/model/ScopeModelUtil
      41: invokevirtual #15                 // Method java/lang/Class.getName:()Ljava/lang/String;
      44: aastore
      45: invokestatic  #35                 // Method java/lang/String.format:(Ljava/lang/String;[Ljava/lang/Object;)Ljava/lang/String;
      48: invokevirtual #14                 // Method java/lang/StringBuilder.append:(Ljava/lang/String;)Ljava/lang/StringBuilder;
      51: pop
      52: aload_1
      53: invokevirtual #17                 // Method java/lang/StringBuilder.toString:()Ljava/lang/String;
      56: areturn

  private java.lang.String generateClassDeclaration();
    Code:
       0: ldc           #39                 // String public class %s$Adaptive implements %s {\n
       2: iconst_2
       3: anewarray     #32                 // class java/lang/Object
       6: dup
       7: iconst_0
       8: aload_0
       9: getfield      #2                  // Field type:Ljava/lang/Class;
      12: invokevirtual #40                 // Method java/lang/Class.getSimpleName:()Ljava/lang/String;
      15: aastore
      16: dup
      17: iconst_1
      18: aload_0
      19: getfield      #2                  // Field type:Ljava/lang/Class;
      22: invokevirtual #41                 // Method java/lang/Class.getCanonicalName:()Ljava/lang/String;
      25: aastore
      26: invokestatic  #35                 // Method java/lang/String.format:(Ljava/lang/String;[Ljava/lang/Object;)Ljava/lang/String;
      29: areturn

  private java.lang.String generateUnsupported(java.lang.reflect.Method);
    Code:
       0: ldc           #42                 // String throw new UnsupportedOperationException(\"The method %s of interface %s is not adaptive method!\");\n
       2: iconst_2
       3: anewarray     #32                 // class java/lang/Object
       6: dup
       7: iconst_0
       8: aload_1
       9: aastore
      10: dup
      11: iconst_1
      12: aload_0
      13: getfield      #2                  // Field type:Ljava/lang/Class;
      16: invokevirtual #15                 // Method java/lang/Class.getName:()Ljava/lang/String;
      19: aastore
      20: invokestatic  #35                 // Method java/lang/String.format:(Ljava/lang/String;[Ljava/lang/Object;)Ljava/lang/String;
      23: areturn

  private int getUrlTypeIndex(java.lang.reflect.Method);
    Code:
       0: iconst_m1
       1: istore_2
       2: aload_1
       3: invokevirtual #43                 // Method java/lang/reflect/Method.getParameterTypes:()[Ljava/lang/Class;
       6: astore_3
       7: iconst_0
       8: istore        4
      10: iload         4
      12: aload_3
      13: arraylength
      14: if_icmpge     41
      17: aload_3
      18: iload         4
      20: aaload
      21: ldc           #44                 // class org/apache/dubbo/common/URL
      23: invokevirtual #45                 // Method java/lang/Object.equals:(Ljava/lang/Object;)Z
      26: ifeq          35
      29: iload         4
      31: istore_2
      32: goto          41
      35: iinc          4, 1
      38: goto          10
      41: iload_2
      42: ireturn

  private java.lang.String generateMethod(java.lang.reflect.Method);
    Code:
       0: aload_1
       1: invokevirtual #46                 // Method java/lang/reflect/Method.getReturnType:()Ljava/lang/Class;
       4: invokevirtual #41                 // Method java/lang/Class.getCanonicalName:()Ljava/lang/String;
       7: astore_2
       8: aload_1
       9: invokevirtual #47                 // Method java/lang/reflect/Method.getName:()Ljava/lang/String;
      12: astore_3
      13: aload_0
      14: aload_1
      15: invokespecial #48                 // Method generateMethodContent:(Ljava/lang/reflect/Method;)Ljava/lang/String;
      18: astore        4
      20: aload_0
      21: aload_1
      22: invokespecial #49                 // Method generateMethodArguments:(Ljava/lang/reflect/Method;)Ljava/lang/String;
      25: astore        5
      27: aload_0
      28: aload_1
      29: invokespecial #50                 // Method generateMethodThrows:(Ljava/lang/reflect/Method;)Ljava/lang/String;
      32: astore        6
      34: ldc           #51                 // String public %s %s(%s) %s {\n%s}\n
      36: iconst_5
      37: anewarray     #32                 // class java/lang/Object
      40: dup
      41: iconst_0
      42: aload_2
      43: aastore
      44: dup
      45: iconst_1
      46: aload_3
      47: aastore
      48: dup
      49: iconst_2
      50: aload         5
      52: aastore
      53: dup
      54: iconst_3
      55: aload         6
      57: aastore
      58: dup
      59: iconst_4
      60: aload         4
      62: aastore
      63: invokestatic  #35                 // Method java/lang/String.format:(Ljava/lang/String;[Ljava/lang/Object;)Ljava/lang/String;
      66: areturn

  private java.lang.String generateMethodArguments(java.lang.reflect.Method);
    Code:
       0: aload_1
       1: invokevirtual #43                 // Method java/lang/reflect/Method.getParameterTypes:()[Ljava/lang/Class;
       4: astore_2
       5: iconst_0
       6: aload_2
       7: arraylength
       8: invokestatic  #52                 // InterfaceMethod java/util/stream/IntStream.range:(II)Ljava/util/stream/IntStream;
      11: aload_2
      12: invokedynamic #53,  0             // InvokeDynamic #2:apply:([Ljava/lang/Class;)Ljava/util/function/IntFunction;
      17: invokeinterface #54,  2           // InterfaceMethod java/util/stream/IntStream.mapToObj:(Ljava/util/function/IntFunction;)Ljava/util/stream/Stream;
      22: ldc           #55                 // String ,
      24: invokestatic  #56                 // Method java/util/stream/Collectors.joining:(Ljava/lang/CharSequence;)Ljava/util/stream/Collector;
      27: invokeinterface #57,  2           // InterfaceMethod java/util/stream/Stream.collect:(Ljava/util/stream/Collector;)Ljava/lang/Object;
      32: checkcast     #58                 // class java/lang/String
      35: areturn

  private java.lang.String generateMethodThrows(java.lang.reflect.Method);
    Code:
       0: aload_1
       1: invokevirtual #59                 // Method java/lang/reflect/Method.getExceptionTypes:()[Ljava/lang/Class;
       4: astore_2
       5: aload_2
       6: arraylength
       7: ifle          52
      10: aload_2
      11: invokestatic  #5                  // Method java/util/Arrays.stream:([Ljava/lang/Object;)Ljava/util/stream/Stream;
      14: invokedynamic #60,  0             // InvokeDynamic #3:apply:()Ljava/util/function/Function;
      19: invokeinterface #61,  2           // InterfaceMethod java/util/stream/Stream.map:(Ljava/util/function/Function;)Ljava/util/stream/Stream;
      24: ldc           #55                 // String ,
      26: invokestatic  #56                 // Method java/util/stream/Collectors.joining:(Ljava/lang/CharSequence;)Ljava/util/stream/Collector;
      29: invokeinterface #57,  2           // InterfaceMethod java/util/stream/Stream.collect:(Ljava/util/stream/Collector;)Ljava/lang/Object;
      34: checkcast     #58                 // class java/lang/String
      37: astore_3
      38: ldc           #62                 // String throws %s
      40: iconst_1
      41: anewarray     #32                 // class java/lang/Object
      44: dup
      45: iconst_0
      46: aload_3
      47: aastore
      48: invokestatic  #35                 // Method java/lang/String.format:(Ljava/lang/String;[Ljava/lang/Object;)Ljava/lang/String;
      51: areturn
      52: ldc           #63                 // String
      54: areturn

  private java.lang.String generateUrlNullCheck(int);
    Code:
       0: ldc           #64                 // String if (arg%d == null) throw new IllegalArgumentException(\"url == null\");\n%s url = arg%d;\n
       2: iconst_3
       3: anewarray     #32                 // class java/lang/Object
       6: dup
       7: iconst_0
       8: iload_1
       9: invokestatic  #65                 // Method java/lang/Integer.valueOf:(I)Ljava/lang/Integer;
      12: aastore
      13: dup
      14: iconst_1
      15: ldc           #44                 // class org/apache/dubbo/common/URL
      17: invokevirtual #15                 // Method java/lang/Class.getName:()Ljava/lang/String;
      20: aastore
      21: dup
      22: iconst_2
      23: iload_1
      24: invokestatic  #65                 // Method java/lang/Integer.valueOf:(I)Ljava/lang/Integer;
      27: aastore
      28: invokestatic  #35                 // Method java/lang/String.format:(Ljava/lang/String;[Ljava/lang/Object;)Ljava/lang/String;
      31: areturn

  private java.lang.String generateMethodContent(java.lang.reflect.Method);
    Code:
       0: aload_1
       1: ldc           #66                 // class org/apache/dubbo/common/extension/Adaptive
       3: invokevirtual #67                 // Method java/lang/reflect/Method.getAnnotation:(Ljava/lang/Class;)Ljava/lang/annotation/Annotation;
       6: checkcast     #66                 // class org/apache/dubbo/common/extension/Adaptive
       9: astore_2
      10: new           #11                 // class java/lang/StringBuilder
      13: dup
      14: sipush        512
      17: invokespecial #68                 // Method java/lang/StringBuilder."<init>":(I)V
      20: astore_3
      21: aload_2
      22: ifnonnull     31
      25: aload_0
      26: aload_1
      27: invokespecial #69                 // Method generateUnsupported:(Ljava/lang/reflect/Method;)Ljava/lang/String;
      30: areturn
      31: aload_0
      32: aload_1
      33: invokespecial #70                 // Method getUrlTypeIndex:(Ljava/lang/reflect/Method;)I
      36: istore        4
      38: iload         4
      40: iconst_m1
      41: if_icmpeq     58
      44: aload_3
      45: aload_0
      46: iload         4
      48: invokespecial #71                 // Method generateUrlNullCheck:(I)Ljava/lang/String;
      51: invokevirtual #14                 // Method java/lang/StringBuilder.append:(Ljava/lang/String;)Ljava/lang/StringBuilder;
      54: pop
      55: goto          68
      58: aload_3
      59: aload_0
      60: aload_1
      61: invokespecial #72                 // Method generateUrlAssignmentIndirectly:(Ljava/lang/reflect/Method;)Ljava/lang/String;
      64: invokevirtual #14                 // Method java/lang/StringBuilder.append:(Ljava/lang/String;)Ljava/lang/StringBuilder;
      67: pop
      68: aload_0
      69: aload_2
      70: invokespecial #73                 // Method getMethodAdaptiveValue:(Lorg/apache/dubbo/common/extension/Adaptive;)[Ljava/lang/String;
      73: astore        5
      75: aload_0
      76: aload_1
      77: invokespecial #74                 // Method hasInvocationArgument:(Ljava/lang/reflect/Method;)Z
      80: istore        6
      82: aload_3
      83: aload_0
      84: aload_1
      85: invokespecial #75                 // Method generateInvocationArgumentNullCheck:(Ljava/lang/reflect/Method;)Ljava/lang/String;
      88: invokevirtual #14                 // Method java/lang/StringBuilder.append:(Ljava/lang/String;)Ljava/lang/StringBuilder;
      91: pop
      92: aload_3
      93: aload_0
      94: aload         5
      96: iload         6
      98: invokespecial #76                 // Method generateExtNameAssignment:([Ljava/lang/String;Z)Ljava/lang/String;
     101: invokevirtual #14                 // Method java/lang/StringBuilder.append:(Ljava/lang/String;)Ljava/lang/StringBuilder;
     104: pop
     105: aload_3
     106: aload_0
     107: aload         5
     109: invokespecial #77                 // Method generateExtNameNullCheck:([Ljava/lang/String;)Ljava/lang/String;
     112: invokevirtual #14                 // Method java/lang/StringBuilder.append:(Ljava/lang/String;)Ljava/lang/StringBuilder;
     115: pop
     116: aload_3
     117: aload_0
     118: invokespecial #78                 // Method generateScopeModelAssignment:()Ljava/lang/String;
     121: invokevirtual #14                 // Method java/lang/StringBuilder.append:(Ljava/lang/String;)Ljava/lang/StringBuilder;
     124: pop
     125: aload_3
     126: aload_0
     127: invokespecial #79                 // Method generateExtensionAssignment:()Ljava/lang/String;
     130: invokevirtual #14                 // Method java/lang/StringBuilder.append:(Ljava/lang/String;)Ljava/lang/StringBuilder;
     133: pop
     134: aload_3
     135: aload_0
     136: aload_1
     137: invokespecial #80                 // Method generateReturnAndInvocation:(Ljava/lang/reflect/Method;)Ljava/lang/String;
     140: invokevirtual #14                 // Method java/lang/StringBuilder.append:(Ljava/lang/String;)Ljava/lang/StringBuilder;
     143: pop
     144: aload_3
     145: invokevirtual #17                 // Method java/lang/StringBuilder.toString:()Ljava/lang/String;
     148: areturn

  private java.lang.String generateExtNameNullCheck(java.lang.String[]);
    Code:
       0: ldc           #81                 // String if(extName == null) throw new IllegalStateException(\"Failed to get extension (%s) name from url (\" + url.toString() + \") use keys(%s)\");\n
       2: iconst_2
       3: anewarray     #32                 // class java/lang/Object
       6: dup
       7: iconst_0
       8: aload_0
       9: getfield      #2                  // Field type:Ljava/lang/Class;
      12: invokevirtual #15                 // Method java/lang/Class.getName:()Ljava/lang/String;
      15: aastore
      16: dup
      17: iconst_1
      18: aload_1
      19: invokestatic  #82                 // Method java/util/Arrays.toString:([Ljava/lang/Object;)Ljava/lang/String;
      22: aastore
      23: invokestatic  #35                 // Method java/lang/String.format:(Ljava/lang/String;[Ljava/lang/Object;)Ljava/lang/String;
      26: areturn

  private java.lang.String generateExtNameAssignment(java.lang.String[], boolean);
    Code:
       0: aconst_null
       1: astore_3
       2: aload_1
       3: arraylength
       4: iconst_1
       5: isub
       6: istore        4
       8: iload         4
      10: iflt          276
      13: iload         4
      15: aload_1
      16: arraylength
      17: iconst_1
      18: isub
      19: if_icmpne     189
      22: aconst_null
      23: aload_0
      24: getfield      #3                  // Field defaultExtName:Ljava/lang/String;
      27: if_acmpeq     120
      30: ldc           #84                 // String protocol
      32: aload_1
      33: iload         4
      35: aaload
      36: invokevirtual #85                 // Method java/lang/String.equals:(Ljava/lang/Object;)Z
      39: ifne          100
      42: iload_2
      43: ifeq          73
      46: ldc           #86                 // String url.getMethodParameter(methodName, \"%s\", \"%s\")
      48: iconst_2
      49: anewarray     #32                 // class java/lang/Object
      52: dup
      53: iconst_0
      54: aload_1
      55: iload         4
      57: aaload
      58: aastore
      59: dup
      60: iconst_1
      61: aload_0
      62: getfield      #3                  // Field defaultExtName:Ljava/lang/String;
      65: aastore
      66: invokestatic  #35                 // Method java/lang/String.format:(Ljava/lang/String;[Ljava/lang/Object;)Ljava/lang/String;
      69: astore_3
      70: goto          270
      73: ldc           #87                 // String url.getParameter(\"%s\", \"%s\")
      75: iconst_2
      76: anewarray     #32                 // class java/lang/Object
      79: dup
      80: iconst_0
      81: aload_1
      82: iload         4
      84: aaload
      85: aastore
      86: dup
      87: iconst_1
      88: aload_0
      89: getfield      #3                  // Field defaultExtName:Ljava/lang/String;
      92: aastore
      93: invokestatic  #35                 // Method java/lang/String.format:(Ljava/lang/String;[Ljava/lang/Object;)Ljava/lang/String;
      96: astore_3
      97: goto          270
     100: ldc           #88                 // String ( url.getProtocol() == null ? \"%s\" : url.getProtocol() )
     102: iconst_1
     103: anewarray     #32                 // class java/lang/Object
     106: dup
     107: iconst_0
     108: aload_0
     109: getfield      #3                  // Field defaultExtName:Ljava/lang/String;
     112: aastore
     113: invokestatic  #35                 // Method java/lang/String.format:(Ljava/lang/String;[Ljava/lang/Object;)Ljava/lang/String;
     116: astore_3
     117: goto          270
     120: ldc           #84                 // String protocol
     122: aload_1
     123: iload         4
     125: aaload
     126: invokevirtual #85                 // Method java/lang/String.equals:(Ljava/lang/Object;)Z
     129: ifne          183
     132: iload_2
     133: ifeq          163
     136: ldc           #86                 // String url.getMethodParameter(methodName, \"%s\", \"%s\")
     138: iconst_2
     139: anewarray     #32                 // class java/lang/Object
     142: dup
     143: iconst_0
     144: aload_1
     145: iload         4
     147: aaload
     148: aastore
     149: dup
     150: iconst_1
     151: aload_0
     152: getfield      #3                  // Field defaultExtName:Ljava/lang/String;
     155: aastore
     156: invokestatic  #35                 // Method java/lang/String.format:(Ljava/lang/String;[Ljava/lang/Object;)Ljava/lang/String;
     159: astore_3
     160: goto          270
     163: ldc           #89                 // String url.getParameter(\"%s\")
     165: iconst_1
     166: anewarray     #32                 // class java/lang/Object
     169: dup
     170: iconst_0
     171: aload_1
     172: iload         4
     174: aaload
     175: aastore
     176: invokestatic  #35                 // Method java/lang/String.format:(Ljava/lang/String;[Ljava/lang/Object;)Ljava/lang/String;
     179: astore_3
     180: goto          270
     183: ldc           #90                 // String url.getProtocol()
     185: astore_3
     186: goto          270
     189: ldc           #84                 // String protocol
     191: aload_1
     192: iload         4
     194: aaload
     195: invokevirtual #85                 // Method java/lang/String.equals:(Ljava/lang/Object;)Z
     198: ifne          256
     201: iload_2
     202: ifeq          232
     205: ldc           #86                 // String url.getMethodParameter(methodName, \"%s\", \"%s\")
     207: iconst_2
     208: anewarray     #32                 // class java/lang/Object
     211: dup
     212: iconst_0
     213: aload_1
     214: iload         4
     216: aaload
     217: aastore
     218: dup
     219: iconst_1
     220: aload_0
     221: getfield      #3                  // Field defaultExtName:Ljava/lang/String;
     224: aastore
     225: invokestatic  #35                 // Method java/lang/String.format:(Ljava/lang/String;[Ljava/lang/Object;)Ljava/lang/String;
     228: astore_3
     229: goto          270
     232: ldc           #91                 // String url.getParameter(\"%s\", %s)
     234: iconst_2
     235: anewarray     #32                 // class java/lang/Object
     238: dup
     239: iconst_0
     240: aload_1
     241: iload         4
     243: aaload
     244: aastore
     245: dup
     246: iconst_1
     247: aload_3
     248: aastore
     249: invokestatic  #35                 // Method java/lang/String.format:(Ljava/lang/String;[Ljava/lang/Object;)Ljava/lang/String;
     252: astore_3
     253: goto          270
     256: ldc           #92                 // String url.getProtocol() == null ? (%s) : url.getProtocol()
     258: iconst_1
     259: anewarray     #32                 // class java/lang/Object
     262: dup
     263: iconst_0
     264: aload_3
     265: aastore
     266: invokestatic  #35                 // Method java/lang/String.format:(Ljava/lang/String;[Ljava/lang/Object;)Ljava/lang/String;
     269: astore_3
     270: iinc          4, -1
     273: goto          8
     276: ldc           #93                 // String String extName = %s;\n
     278: iconst_1
     279: anewarray     #32                 // class java/lang/Object
     282: dup
     283: iconst_0
     284: aload_3
     285: aastore
     286: invokestatic  #35                 // Method java/lang/String.format:(Ljava/lang/String;[Ljava/lang/Object;)Ljava/lang/String;
     289: areturn

  private java.lang.String generateScopeModelAssignment();
    Code:
       0: ldc           #94                 // String ScopeModel scopeModel = ScopeModelUtil.getOrDefault(url.getScopeModel(), %s.class);\n
       2: iconst_1
       3: anewarray     #32                 // class java/lang/Object
       6: dup
       7: iconst_0
       8: aload_0
       9: getfield      #2                  // Field type:Ljava/lang/Class;
      12: invokevirtual #15                 // Method java/lang/Class.getName:()Ljava/lang/String;
      15: aastore
      16: invokestatic  #35                 // Method java/lang/String.format:(Ljava/lang/String;[Ljava/lang/Object;)Ljava/lang/String;
      19: areturn

  private java.lang.String generateExtensionAssignment();
    Code:
       0: ldc           #95                 // String %s extension = (%<s)scopeModel.getExtensionLoader(%s.class).getExtension(extName);\n
       2: iconst_2
       3: anewarray     #32                 // class java/lang/Object
       6: dup
       7: iconst_0
       8: aload_0
       9: getfield      #2                  // Field type:Ljava/lang/Class;
      12: invokevirtual #15                 // Method java/lang/Class.getName:()Ljava/lang/String;
      15: aastore
      16: dup
      17: iconst_1
      18: aload_0
      19: getfield      #2                  // Field type:Ljava/lang/Class;
      22: invokevirtual #15                 // Method java/lang/Class.getName:()Ljava/lang/String;
      25: aastore
      26: invokestatic  #35                 // Method java/lang/String.format:(Ljava/lang/String;[Ljava/lang/Object;)Ljava/lang/String;
      29: areturn

  private java.lang.String generateReturnAndInvocation(java.lang.reflect.Method);
    Code:
       0: aload_1
       1: invokevirtual #46                 // Method java/lang/reflect/Method.getReturnType:()Ljava/lang/Class;
       4: getstatic     #96                 // Field java/lang/Void.TYPE:Ljava/lang/Class;
       7: invokevirtual #45                 // Method java/lang/Object.equals:(Ljava/lang/Object;)Z
      10: ifeq          18
      13: ldc           #63                 // String
      15: goto          20
      18: ldc           #97                 // String return
      20: astore_2
      21: iconst_0
      22: aload_1
      23: invokevirtual #98                 // Method java/lang/reflect/Method.getParameters:()[Ljava/lang/reflect/Parameter;
      26: arraylength
      27: invokestatic  #52                 // InterfaceMethod java/util/stream/IntStream.range:(II)Ljava/util/stream/IntStream;
      30: invokedynamic #99,  0             // InvokeDynamic #4:apply:()Ljava/util/function/IntFunction;
      35: invokeinterface #54,  2           // InterfaceMethod java/util/stream/IntStream.mapToObj:(Ljava/util/function/IntFunction;)Ljava/util/stream/Stream;
      40: ldc           #55                 // String ,
      42: invokestatic  #56                 // Method java/util/stream/Collectors.joining:(Ljava/lang/CharSequence;)Ljava/util/stream/Collector;
      45: invokeinterface #57,  2           // InterfaceMethod java/util/stream/Stream.collect:(Ljava/util/stream/Collector;)Ljava/lang/Object;
      50: checkcast     #58                 // class java/lang/String
      53: astore_3
      54: new           #11                 // class java/lang/StringBuilder
      57: dup
      58: invokespecial #12                 // Method java/lang/StringBuilder."<init>":()V
      61: aload_2
      62: invokevirtual #14                 // Method java/lang/StringBuilder.append:(Ljava/lang/String;)Ljava/lang/StringBuilder;
      65: ldc           #100                // String extension.%s(%s);\n
      67: iconst_2
      68: anewarray     #32                 // class java/lang/Object
      71: dup
      72: iconst_0
      73: aload_1
      74: invokevirtual #47                 // Method java/lang/reflect/Method.getName:()Ljava/lang/String;
      77: aastore
      78: dup
      79: iconst_1
      80: aload_3
      81: aastore
      82: invokestatic  #35                 // Method java/lang/String.format:(Ljava/lang/String;[Ljava/lang/Object;)Ljava/lang/String;
      85: invokevirtual #14                 // Method java/lang/StringBuilder.append:(Ljava/lang/String;)Ljava/lang/StringBuilder;
      88: invokevirtual #17                 // Method java/lang/StringBuilder.toString:()Ljava/lang/String;
      91: areturn

  private boolean hasInvocationArgument(java.lang.reflect.Method);
    Code:
       0: aload_1
       1: invokevirtual #43                 // Method java/lang/reflect/Method.getParameterTypes:()[Ljava/lang/Class;
       4: astore_2
       5: aload_2
       6: invokestatic  #5                  // Method java/util/Arrays.stream:([Ljava/lang/Object;)Ljava/util/stream/Stream;
       9: invokedynamic #101,  0            // InvokeDynamic #5:test:()Ljava/util/function/Predicate;
      14: invokeinterface #7,  2            // InterfaceMethod java/util/stream/Stream.anyMatch:(Ljava/util/function/Predicate;)Z
      19: ireturn

  private java.lang.String generateInvocationArgumentNullCheck(java.lang.reflect.Method);
    Code:
       0: aload_1
       1: invokevirtual #43                 // Method java/lang/reflect/Method.getParameterTypes:()[Ljava/lang/Class;
       4: astore_2
       5: iconst_0
       6: aload_2
       7: arraylength
       8: invokestatic  #52                 // InterfaceMethod java/util/stream/IntStream.range:(II)Ljava/util/stream/IntStream;
      11: aload_2
      12: invokedynamic #102,  0            // InvokeDynamic #6:test:([Ljava/lang/Class;)Ljava/util/function/IntPredicate;
      17: invokeinterface #103,  2          // InterfaceMethod java/util/stream/IntStream.filter:(Ljava/util/function/IntPredicate;)Ljava/util/stream/IntStream;
      22: invokedynamic #104,  0            // InvokeDynamic #7:apply:()Ljava/util/function/IntFunction;
      27: invokeinterface #54,  2           // InterfaceMethod java/util/stream/IntStream.mapToObj:(Ljava/util/function/IntFunction;)Ljava/util/stream/Stream;
      32: invokeinterface #105,  1          // InterfaceMethod java/util/stream/Stream.findFirst:()Ljava/util/Optional;
      37: ldc           #63                 // String
      39: invokevirtual #106                // Method java/util/Optional.orElse:(Ljava/lang/Object;)Ljava/lang/Object;
      42: checkcast     #58                 // class java/lang/String
      45: areturn

  private java.lang.String[] getMethodAdaptiveValue(org.apache.dubbo.common.extension.Adaptive);
    Code:
       0: aload_1
       1: invokeinterface #107,  1          // InterfaceMethod org/apache/dubbo/common/extension/Adaptive.value:()[Ljava/lang/String;
       6: astore_2
       7: aload_2
       8: arraylength
       9: ifne          34
      12: aload_0
      13: getfield      #2                  // Field type:Ljava/lang/Class;
      16: invokevirtual #40                 // Method java/lang/Class.getSimpleName:()Ljava/lang/String;
      19: ldc           #108                // String .
      21: invokestatic  #109                // Method org/apache/dubbo/common/utils/StringUtils.camelToSplitName:(Ljava/lang/String;Ljava/lang/String;)Ljava/lang/String;
      24: astore_3
      25: iconst_1
      26: anewarray     #58                 // class java/lang/String
      29: dup
      30: iconst_0
      31: aload_3
      32: aastore
      33: astore_2
      34: aload_2
      35: areturn

  private java.lang.String generateUrlAssignmentIndirectly(java.lang.reflect.Method);
    Code:
       0: aload_1
       1: invokevirtual #43                 // Method java/lang/reflect/Method.getParameterTypes:()[Ljava/lang/Class;
       4: astore_2
       5: new           #110                // class java/util/HashMap
       8: dup
       9: invokespecial #111                // Method java/util/HashMap."<init>":()V
      12: astore_3
      13: iconst_0
      14: istore        4
      16: iload         4
      18: aload_2
      19: arraylength
      20: if_icmpge     147
      23: aload_2
      24: iload         4
      26: aaload
      27: invokevirtual #4                  // Method java/lang/Class.getMethods:()[Ljava/lang/reflect/Method;
      30: astore        5
      32: aload         5
      34: arraylength
      35: istore        6
      37: iconst_0
      38: istore        7
      40: iload         7
      42: iload         6
      44: if_icmpge     141
      47: aload         5
      49: iload         7
      51: aaload
      52: astore        8
      54: aload         8
      56: invokevirtual #47                 // Method java/lang/reflect/Method.getName:()Ljava/lang/String;
      59: astore        9
      61: aload         9
      63: ldc           #112                // String get
      65: invokevirtual #113                // Method java/lang/String.startsWith:(Ljava/lang/String;)Z
      68: ifne          80
      71: aload         9
      73: invokevirtual #114                // Method java/lang/String.length:()I
      76: iconst_3
      77: if_icmple     135
      80: aload         8
      82: invokevirtual #115                // Method java/lang/reflect/Method.getModifiers:()I
      85: invokestatic  #116                // Method java/lang/reflect/Modifier.isPublic:(I)Z
      88: ifeq          135
      91: aload         8
      93: invokevirtual #115                // Method java/lang/reflect/Method.getModifiers:()I
      96: invokestatic  #117                // Method java/lang/reflect/Modifier.isStatic:(I)Z
      99: ifne          135
     102: aload         8
     104: invokevirtual #43                 // Method java/lang/reflect/Method.getParameterTypes:()[Ljava/lang/Class;
     107: arraylength
     108: ifne          135
     111: aload         8
     113: invokevirtual #46                 // Method java/lang/reflect/Method.getReturnType:()Ljava/lang/Class;
     116: ldc           #44                 // class org/apache/dubbo/common/URL
     118: if_acmpne     135
     121: aload_3
     122: aload         9
     124: iload         4
     126: invokestatic  #65                 // Method java/lang/Integer.valueOf:(I)Ljava/lang/Integer;
     129: invokeinterface #118,  3          // InterfaceMethod java/util/Map.put:(Ljava/lang/Object;Ljava/lang/Object;)Ljava/lang/Object;
     134: pop
     135: iinc          7, 1
     138: goto          40
     141: iinc          4, 1
     144: goto          16
     147: aload_3
     148: invokeinterface #119,  1          // InterfaceMethod java/util/Map.size:()I
     153: ifgt          201
     156: new           #10                 // class java/lang/IllegalStateException
     159: dup
     160: new           #11                 // class java/lang/StringBuilder
     163: dup
     164: invokespecial #12                 // Method java/lang/StringBuilder."<init>":()V
     167: ldc           #120                // String Failed to create adaptive class for interface
     169: invokevirtual #14                 // Method java/lang/StringBuilder.append:(Ljava/lang/String;)Ljava/lang/StringBuilder;
     172: aload_0
     173: getfield      #2                  // Field type:Ljava/lang/Class;
     176: invokevirtual #15                 // Method java/lang/Class.getName:()Ljava/lang/String;
     179: invokevirtual #14                 // Method java/lang/StringBuilder.append:(Ljava/lang/String;)Ljava/lang/StringBuilder;
     182: ldc           #121                // String : not found url parameter or url attribute in parameters of method
     184: invokevirtual #14                 // Method java/lang/StringBuilder.append:(Ljava/lang/String;)Ljava/lang/StringBuilder;
     187: aload_1
     188: invokevirtual #47                 // Method java/lang/reflect/Method.getName:()Ljava/lang/String;
     191: invokevirtual #14                 // Method java/lang/StringBuilder.append:(Ljava/lang/String;)Ljava/lang/StringBuilder;
     194: invokevirtual #17                 // Method java/lang/StringBuilder.toString:()Ljava/lang/String;
     197: invokespecial #18                 // Method java/lang/IllegalStateException."<init>":(Ljava/lang/String;)V
     200: athrow
     201: aload_3
     202: ldc           #122                // String getUrl
     204: invokeinterface #123,  2          // InterfaceMethod java/util/Map.get:(Ljava/lang/Object;)Ljava/lang/Object;
     209: checkcast     #124                // class java/lang/Integer
     212: astore        4
     214: aload         4
     216: ifnull        238
     219: aload_0
     220: aload         4
     222: invokevirtual #125                // Method java/lang/Integer.intValue:()I
     225: aload_2
     226: aload         4
     228: invokevirtual #125                // Method java/lang/Integer.intValue:()I
     231: aaload
     232: ldc           #122                // String getUrl
     234: invokespecial #126                // Method generateGetUrlNullCheck:(ILjava/lang/Class;Ljava/lang/String;)Ljava/lang/String;
     237: areturn
     238: aload_3
     239: invokeinterface #127,  1          // InterfaceMethod java/util/Map.entrySet:()Ljava/util/Set;
     244: invokeinterface #128,  1          // InterfaceMethod java/util/Set.iterator:()Ljava/util/Iterator;
     249: invokeinterface #129,  1          // InterfaceMethod java/util/Iterator.next:()Ljava/lang/Object;
     254: checkcast     #130                // class java/util/Map$Entry
     257: astore        5
     259: aload_0
     260: aload         5
     262: invokeinterface #131,  1          // InterfaceMethod java/util/Map$Entry.getValue:()Ljava/lang/Object;
     267: checkcast     #124                // class java/lang/Integer
     270: invokevirtual #125                // Method java/lang/Integer.intValue:()I
     273: aload_2
     274: aload         5
     276: invokeinterface #131,  1          // InterfaceMethod java/util/Map$Entry.getValue:()Ljava/lang/Object;
     281: checkcast     #124                // class java/lang/Integer
     284: invokevirtual #125                // Method java/lang/Integer.intValue:()I
     287: aaload
     288: aload         5
     290: invokeinterface #132,  1          // InterfaceMethod java/util/Map$Entry.getKey:()Ljava/lang/Object;
     295: checkcast     #58                 // class java/lang/String
     298: invokespecial #126                // Method generateGetUrlNullCheck:(ILjava/lang/Class;Ljava/lang/String;)Ljava/lang/String;
     301: areturn

  private java.lang.String generateGetUrlNullCheck(int, java.lang.Class<?>, java.lang.String);
    Code:
       0: new           #11                 // class java/lang/StringBuilder
       3: dup
       4: invokespecial #12                 // Method java/lang/StringBuilder."<init>":()V
       7: astore        4
       9: aload         4
      11: ldc           #133                // String if (arg%d == null) throw new IllegalArgumentException(\"%s argument == null\");\n
      13: iconst_2
      14: anewarray     #32                 // class java/lang/Object
      17: dup
      18: iconst_0
      19: iload_1
      20: invokestatic  #65                 // Method java/lang/Integer.valueOf:(I)Ljava/lang/Integer;
      23: aastore
      24: dup
      25: iconst_1
      26: aload_2
      27: invokevirtual #15                 // Method java/lang/Class.getName:()Ljava/lang/String;
      30: aastore
      31: invokestatic  #35                 // Method java/lang/String.format:(Ljava/lang/String;[Ljava/lang/Object;)Ljava/lang/String;
      34: invokevirtual #14                 // Method java/lang/StringBuilder.append:(Ljava/lang/String;)Ljava/lang/StringBuilder;
      37: pop
      38: aload         4
      40: ldc           #134                // String if (arg%d.%s() == null) throw new IllegalArgumentException(\"%s argument %s() == null\");\n
      42: iconst_4
      43: anewarray     #32                 // class java/lang/Object
      46: dup
      47: iconst_0
      48: iload_1
      49: invokestatic  #65                 // Method java/lang/Integer.valueOf:(I)Ljava/lang/Integer;
      52: aastore
      53: dup
      54: iconst_1
      55: aload_3
      56: aastore
      57: dup
      58: iconst_2
      59: aload_2
      60: invokevirtual #15                 // Method java/lang/Class.getName:()Ljava/lang/String;
      63: aastore
      64: dup
      65: iconst_3
      66: aload_3
      67: aastore
      68: invokestatic  #35                 // Method java/lang/String.format:(Ljava/lang/String;[Ljava/lang/Object;)Ljava/lang/String;
      71: invokevirtual #14                 // Method java/lang/StringBuilder.append:(Ljava/lang/String;)Ljava/lang/StringBuilder;
      74: pop
      75: aload         4
      77: ldc           #135                // String %s url = arg%d.%s();\n
      79: iconst_3
      80: anewarray     #32                 // class java/lang/Object
      83: dup
      84: iconst_0
      85: ldc           #44                 // class org/apache/dubbo/common/URL
      87: invokevirtual #15                 // Method java/lang/Class.getName:()Ljava/lang/String;
      90: aastore
      91: dup
      92: iconst_1
      93: iload_1
      94: invokestatic  #65                 // Method java/lang/Integer.valueOf:(I)Ljava/lang/Integer;
      97: aastore
      98: dup
      99: iconst_2
     100: aload_3
     101: aastore
     102: invokestatic  #35                 // Method java/lang/String.format:(Ljava/lang/String;[Ljava/lang/Object;)Ljava/lang/String;
     105: invokevirtual #14                 // Method java/lang/StringBuilder.append:(Ljava/lang/String;)Ljava/lang/StringBuilder;
     108: pop
     109: aload         4
     111: invokevirtual #17                 // Method java/lang/StringBuilder.toString:()Ljava/lang/String;
     114: areturn

  private static java.lang.String lambda$generateInvocationArgumentNullCheck$5(int);
    Code:
       0: ldc           #136                // String if (arg%d == null) throw new IllegalArgumentException(\"invocation == null\"); String methodName = arg%d.getMethodName();\n
       2: iconst_2
       3: anewarray     #32                 // class java/lang/Object
       6: dup
       7: iconst_0
       8: iload_0
       9: invokestatic  #65                 // Method java/lang/Integer.valueOf:(I)Ljava/lang/Integer;
      12: aastore
      13: dup
      14: iconst_1
      15: iload_0
      16: invokestatic  #65                 // Method java/lang/Integer.valueOf:(I)Ljava/lang/Integer;
      19: aastore
      20: invokestatic  #35                 // Method java/lang/String.format:(Ljava/lang/String;[Ljava/lang/Object;)Ljava/lang/String;
      23: areturn

  private static boolean lambda$generateInvocationArgumentNullCheck$4(java.lang.Class[], int);
    Code:
       0: ldc           #137                // String org.apache.dubbo.rpc.Invocation
       2: aload_0
       3: iload_1
       4: aaload
       5: invokevirtual #15                 // Method java/lang/Class.getName:()Ljava/lang/String;
       8: invokevirtual #85                 // Method java/lang/String.equals:(Ljava/lang/Object;)Z
      11: ireturn

  private static boolean lambda$hasInvocationArgument$3(java.lang.Class);
    Code:
       0: ldc           #137                // String org.apache.dubbo.rpc.Invocation
       2: aload_0
       3: invokevirtual #15                 // Method java/lang/Class.getName:()Ljava/lang/String;
       6: invokevirtual #85                 // Method java/lang/String.equals:(Ljava/lang/Object;)Z
       9: ireturn

  private static java.lang.String lambda$generateReturnAndInvocation$2(int);
    Code:
       0: ldc           #138                // String arg%d
       2: iconst_1
       3: anewarray     #32                 // class java/lang/Object
       6: dup
       7: iconst_0
       8: iload_0
       9: invokestatic  #65                 // Method java/lang/Integer.valueOf:(I)Ljava/lang/Integer;
      12: aastore
      13: invokestatic  #35                 // Method java/lang/String.format:(Ljava/lang/String;[Ljava/lang/Object;)Ljava/lang/String;
      16: areturn

  private static java.lang.String lambda$generateMethodArguments$1(java.lang.Class[], int);
    Code:
       0: ldc           #139                // String %s arg%d
       2: iconst_2
       3: anewarray     #32                 // class java/lang/Object
       6: dup
       7: iconst_0
       8: aload_0
       9: iload_1
      10: aaload
      11: invokevirtual #41                 // Method java/lang/Class.getCanonicalName:()Ljava/lang/String;
      14: aastore
      15: dup
      16: iconst_1
      17: iload_1
      18: invokestatic  #65                 // Method java/lang/Integer.valueOf:(I)Ljava/lang/Integer;
      21: aastore
      22: invokestatic  #35                 // Method java/lang/String.format:(Ljava/lang/String;[Ljava/lang/Object;)Ljava/lang/String;
      25: areturn

  private static boolean lambda$hasAdaptiveMethod$0(java.lang.reflect.Method);
    Code:
       0: aload_0
       1: ldc           #66                 // class org/apache/dubbo/common/extension/Adaptive
       3: invokevirtual #140                // Method java/lang/reflect/Method.isAnnotationPresent:(Ljava/lang/Class;)Z
       6: ireturn

  static {};
    Code:
       0: ldc           #30                 // class org/apache/dubbo/common/extension/AdaptiveClassCodeGenerator
       2: invokestatic  #141                // Method org/apache/dubbo/common/logger/LoggerFactory.getLogger:(Ljava/lang/Class;)Lorg/apache/dubbo/common/logger/Logger;
       5: putstatic     #27                 // Field logger:Lorg/apache/dubbo/common/logger/Logger;
       8: return
}
