Compiled from "DubboInternalLoadingStrategy.java"
public class org.apache.dubbo.common.extension.DubboInternalLoadingStrategy implements org.apache.dubbo.common.extension.LoadingStrategy {
  public org.apache.dubbo.common.extension.DubboInternalLoadingStrategy();
    Code:
       0: aload_0
       1: invokespecial #1                  // Method java/lang/Object."<init>":()V
       4: return

  public java.lang.String directory();
    Code:
       0: ldc           #2                  // String META-INF/dubbo/internal/
       2: areturn

  public int getPriority();
    Code:
       0: ldc           #4                  // int -2147483648
       2: ireturn

  public java.lang.String getName();
    Code:
       0: ldc           #5                  // String DUBBO_INTERNAL
       2: areturn
}
