Compiled from "ExtensionScope.java"
public final class org.apache.dubbo.common.extension.ExtensionScope extends java.lang.Enum<org.apache.dubbo.common.extension.ExtensionScope> {
  public static final org.apache.dubbo.common.extension.ExtensionScope FRAMEWORK;

  public static final org.apache.dubbo.common.extension.ExtensionScope APPLICATION;

  public static final org.apache.dubbo.common.extension.ExtensionScope MODULE;

  public static final org.apache.dubbo.common.extension.ExtensionScope SELF;

  private static final org.apache.dubbo.common.extension.ExtensionScope[] $VALUES;

  public static org.apache.dubbo.common.extension.ExtensionScope[] values();
    Code:
       0: getstatic     #1                  // Field $VALUES:[Lorg/apache/dubbo/common/extension/ExtensionScope;
       3: invokevirtual #2                  // Method "[Lorg/apache/dubbo/common/extension/ExtensionScope;".clone:()Ljava/lang/Object;
       6: checkcast     #3                  // class "[Lorg/apache/dubbo/common/extension/ExtensionScope;"
       9: areturn

  public static org.apache.dubbo.common.extension.ExtensionScope valueOf(java.lang.String);
    Code:
       0: ldc           #4                  // class org/apache/dubbo/common/extension/ExtensionScope
       2: aload_0
       3: invokestatic  #5                  // Method java/lang/Enum.valueOf:(Ljava/lang/Class;Ljava/lang/String;)Ljava/lang/Enum;
       6: checkcast     #4                  // class org/apache/dubbo/common/extension/ExtensionScope
       9: areturn

  private org.apache.dubbo.common.extension.ExtensionScope();
    Code:
       0: aload_0
       1: aload_1
       2: iload_2
       3: invokespecial #6                  // Method java/lang/Enum."<init>":(Ljava/lang/String;I)V
       6: return

  static {};
    Code:
       0: new           #4                  // class org/apache/dubbo/common/extension/ExtensionScope
       3: dup
       4: ldc           #7                  // String FRAMEWORK
       6: iconst_0
       7: invokespecial #8                  // Method "<init>":(Ljava/lang/String;I)V
      10: putstatic     #9                  // Field FRAMEWORK:Lorg/apache/dubbo/common/extension/ExtensionScope;
      13: new           #4                  // class org/apache/dubbo/common/extension/ExtensionScope
      16: dup
      17: ldc           #10                 // String APPLICATION
      19: iconst_1
      20: invokespecial #8                  // Method "<init>":(Ljava/lang/String;I)V
      23: putstatic     #11                 // Field APPLICATION:Lorg/apache/dubbo/common/extension/ExtensionScope;
      26: new           #4                  // class org/apache/dubbo/common/extension/ExtensionScope
      29: dup
      30: ldc           #12                 // String MODULE
      32: iconst_2
      33: invokespecial #8                  // Method "<init>":(Ljava/lang/String;I)V
      36: putstatic     #13                 // Field MODULE:Lorg/apache/dubbo/common/extension/ExtensionScope;
      39: new           #4                  // class org/apache/dubbo/common/extension/ExtensionScope
      42: dup
      43: ldc           #14                 // String SELF
      45: iconst_3
      46: invokespecial #8                  // Method "<init>":(Ljava/lang/String;I)V
      49: putstatic     #15                 // Field SELF:Lorg/apache/dubbo/common/extension/ExtensionScope;
      52: iconst_4
      53: anewarray     #4                  // class org/apache/dubbo/common/extension/ExtensionScope
      56: dup
      57: iconst_0
      58: getstatic     #9                  // Field FRAMEWORK:Lorg/apache/dubbo/common/extension/ExtensionScope;
      61: aastore
      62: dup
      63: iconst_1
      64: getstatic     #11                 // Field APPLICATION:Lorg/apache/dubbo/common/extension/ExtensionScope;
      67: aastore
      68: dup
      69: iconst_2
      70: getstatic     #13                 // Field MODULE:Lorg/apache/dubbo/common/extension/ExtensionScope;
      73: aastore
      74: dup
      75: iconst_3
      76: getstatic     #15                 // Field SELF:Lorg/apache/dubbo/common/extension/ExtensionScope;
      79: aastore
      80: putstatic     #1                  // Field $VALUES:[Lorg/apache/dubbo/common/extension/ExtensionScope;
      83: return
}
