Compiled from "ExtensionAccessor.java"
public interface org.apache.dubbo.common.extension.ExtensionAccessor {
  public abstract org.apache.dubbo.common.extension.ExtensionDirector getExtensionDirector();

  public default <T> org.apache.dubbo.common.extension.ExtensionLoader<T> getExtensionLoader(java.lang.Class<T>);
    Code:
       0: aload_0
       1: invokeinterface #1,  1            // InterfaceMethod getExtensionDirector:()Lorg/apache/dubbo/common/extension/ExtensionDirector;
       6: aload_1
       7: invokevirtual #2                  // Method org/apache/dubbo/common/extension/ExtensionDirector.getExtensionLoader:(Ljava/lang/Class;)Lorg/apache/dubbo/common/extension/ExtensionLoader;
      10: areturn

  public default <T> T getExtension(java.lang.Class<T>, java.lang.String);
    Code:
       0: aload_0
       1: aload_1
       2: invokeinterface #3,  2            // InterfaceMethod getExtensionLoader:(Ljava/lang/Class;)Lorg/apache/dubbo/common/extension/ExtensionLoader;
       7: astore_3
       8: aload_3
       9: ifnull        20
      12: aload_3
      13: aload_2
      14: invokevirtual #4                  // Method org/apache/dubbo/common/extension/ExtensionLoader.getExtension:(Ljava/lang/String;)Ljava/lang/Object;
      17: goto          21
      20: aconst_null
      21: areturn

  public default <T> T getAdaptiveExtension(java.lang.Class<T>);
    Code:
       0: aload_0
       1: aload_1
       2: invokeinterface #3,  2            // InterfaceMethod getExtensionLoader:(Ljava/lang/Class;)Lorg/apache/dubbo/common/extension/ExtensionLoader;
       7: astore_2
       8: aload_2
       9: ifnull        19
      12: aload_2
      13: invokevirtual #5                  // Method org/apache/dubbo/common/extension/ExtensionLoader.getAdaptiveExtension:()Ljava/lang/Object;
      16: goto          20
      19: aconst_null
      20: areturn

  public default <T> T getDefaultExtension(java.lang.Class<T>);
    Code:
       0: aload_0
       1: aload_1
       2: invokeinterface #3,  2            // InterfaceMethod getExtensionLoader:(Ljava/lang/Class;)Lorg/apache/dubbo/common/extension/ExtensionLoader;
       7: astore_2
       8: aload_2
       9: ifnull        19
      12: aload_2
      13: invokevirtual #6                  // Method org/apache/dubbo/common/extension/ExtensionLoader.getDefaultExtension:()Ljava/lang/Object;
      16: goto          20
      19: aconst_null
      20: areturn
}
