Compiled from "ExtensionLoader.java"
public class org.apache.dubbo.common.extension.ExtensionLoader<T> {
  private static final org.apache.dubbo.common.logger.ErrorTypeAwareLogger logger;

  private static final java.util.regex.Pattern NAME_SEPARATOR;

  private static final java.lang.String SPECIAL_SPI_PROPERTIES;

  private final java.util.concurrent.ConcurrentMap<java.lang.Class<?>, java.lang.Object> extensionInstances;

  private final java.lang.Class<?> type;

  private final org.apache.dubbo.common.extension.ExtensionInjector injector;

  private final java.util.concurrent.ConcurrentMap<java.lang.Class<?>, java.lang.String> cachedNames;

  private final org.apache.dubbo.common.utils.Holder<java.util.Map<java.lang.String, java.lang.Class<?>>> cachedClasses;

  private final java.util.Map<java.lang.String, java.lang.Object> cachedActivates;

  private final java.util.Map<java.lang.String, java.util.Set<java.lang.String>> cachedActivateGroups;

  private final java.util.Map<java.lang.String, java.lang.String[][]> cachedActivateValues;

  private final java.util.concurrent.ConcurrentMap<java.lang.String, org.apache.dubbo.common.utils.Holder<java.lang.Object>> cachedInstances;

  private final org.apache.dubbo.common.utils.Holder<java.lang.Object> cachedAdaptiveInstance;

  private volatile java.lang.Class<?> cachedAdaptiveClass;

  private java.lang.String cachedDefaultName;

  private volatile java.lang.Throwable createAdaptiveInstanceError;

  private java.util.Set<java.lang.Class<?>> cachedWrapperClasses;

  private final java.util.Map<java.lang.String, java.lang.IllegalStateException> exceptions;

  private static volatile org.apache.dubbo.common.extension.LoadingStrategy[] strategies;

  private static final java.util.Map<java.lang.String, java.lang.String> specialSPILoadingStrategyMap;

  private static java.lang.ref.SoftReference<java.util.Map<java.net.URL, java.util.List<java.lang.String>>> urlListMapCache;

  private static final java.util.List<java.lang.String> ignoredInjectMethodsDesc;

  private final java.util.Set<java.lang.String> unacceptableExceptions;

  private final org.apache.dubbo.common.extension.ExtensionDirector extensionDirector;

  private final java.util.List<org.apache.dubbo.common.extension.ExtensionPostProcessor> extensionPostProcessors;

  private org.apache.dubbo.common.beans.support.InstantiationStrategy instantiationStrategy;

  private final org.apache.dubbo.common.extension.support.ActivateComparator activateComparator;

  private final org.apache.dubbo.rpc.model.ScopeModel scopeModel;

  private final java.util.concurrent.atomic.AtomicBoolean destroyed;

  public static void setLoadingStrategies(org.apache.dubbo.common.extension.LoadingStrategy...);
    Code:
       0: aload_0
       1: invokestatic  #3                  // Method org/apache/dubbo/common/utils/ArrayUtils.isNotEmpty:([Ljava/lang/Object;)Z
       4: ifeq          11
       7: aload_0
       8: putstatic     #4                  // Field strategies:[Lorg/apache/dubbo/common/extension/LoadingStrategy;
      11: return

  private static org.apache.dubbo.common.extension.LoadingStrategy[] loadLoadingStrategies();
    Code:
       0: ldc           #5                  // class org/apache/dubbo/common/extension/LoadingStrategy
       2: invokestatic  #6                  // Method java/util/ServiceLoader.load:(Ljava/lang/Class;)Ljava/util/ServiceLoader;
       5: invokevirtual #7                  // Method java/util/ServiceLoader.spliterator:()Ljava/util/Spliterator;
       8: iconst_0
       9: invokestatic  #8                  // Method java/util/stream/StreamSupport.stream:(Ljava/util/Spliterator;Z)Ljava/util/stream/Stream;
      12: invokeinterface #9,  1            // InterfaceMethod java/util/stream/Stream.sorted:()Ljava/util/stream/Stream;
      17: invokedynamic #10,  0             // InvokeDynamic #0:apply:()Ljava/util/function/IntFunction;
      22: invokeinterface #11,  2           // InterfaceMethod java/util/stream/Stream.toArray:(Ljava/util/function/IntFunction;)[Ljava/lang/Object;
      27: checkcast     #12                 // class "[Lorg/apache/dubbo/common/extension/LoadingStrategy;"
      30: areturn

  private static java.util.Map<java.lang.String, java.lang.String> getSpecialSPILoadingStrategyMap();
    Code:
       0: new           #13                 // class java/util/concurrent/ConcurrentHashMap
       3: dup
       4: invokespecial #14                 // Method java/util/concurrent/ConcurrentHashMap."<init>":()V
       7: astore_0
       8: ldc           #15                 // class org/apache/dubbo/common/extension/ExtensionLoader
      10: invokevirtual #16                 // Method java/lang/Class.getClassLoader:()Ljava/lang/ClassLoader;
      13: ldc           #17                 // String special_spi.properties
      15: invokestatic  #18                 // Method loadProperties:(Ljava/lang/ClassLoader;Ljava/lang/String;)Ljava/util/Properties;
      18: astore_1
      19: aload_0
      20: aload_1
      21: invokeinterface #19,  2           // InterfaceMethod java/util/Map.putAll:(Ljava/util/Map;)V
      26: aload_0
      27: areturn

  public static java.util.List<org.apache.dubbo.common.extension.LoadingStrategy> getLoadingStrategies();
    Code:
       0: getstatic     #4                  // Field strategies:[Lorg/apache/dubbo/common/extension/LoadingStrategy;
       3: invokestatic  #20                 // Method java/util/Arrays.asList:([Ljava/lang/Object;)Ljava/util/List;
       6: areturn

  private static java.util.List<java.lang.String> getIgnoredInjectMethodsDesc();
    Code:
       0: new           #21                 // class java/util/ArrayList
       3: dup
       4: invokespecial #22                 // Method java/util/ArrayList."<init>":()V
       7: astore_0
       8: ldc           #23                 // class org/apache/dubbo/rpc/model/ScopeModelAware
      10: invokevirtual #24                 // Method java/lang/Class.getMethods:()[Ljava/lang/reflect/Method;
      13: invokestatic  #25                 // Method java/util/Arrays.stream:([Ljava/lang/Object;)Ljava/util/stream/Stream;
      16: invokedynamic #26,  0             // InvokeDynamic #1:apply:()Ljava/util/function/Function;
      21: invokeinterface #27,  2           // InterfaceMethod java/util/stream/Stream.map:(Ljava/util/function/Function;)Ljava/util/stream/Stream;
      26: aload_0
      27: dup
      28: invokevirtual #28                 // Method java/lang/Object.getClass:()Ljava/lang/Class;
      31: pop
      32: invokedynamic #29,  0             // InvokeDynamic #2:accept:(Ljava/util/List;)Ljava/util/function/Consumer;
      37: invokeinterface #30,  2           // InterfaceMethod java/util/stream/Stream.forEach:(Ljava/util/function/Consumer;)V
      42: ldc           #31                 // class org/apache/dubbo/common/extension/ExtensionAccessorAware
      44: invokevirtual #24                 // Method java/lang/Class.getMethods:()[Ljava/lang/reflect/Method;
      47: invokestatic  #25                 // Method java/util/Arrays.stream:([Ljava/lang/Object;)Ljava/util/stream/Stream;
      50: invokedynamic #26,  0             // InvokeDynamic #1:apply:()Ljava/util/function/Function;
      55: invokeinterface #27,  2           // InterfaceMethod java/util/stream/Stream.map:(Ljava/util/function/Function;)Ljava/util/stream/Stream;
      60: aload_0
      61: dup
      62: invokevirtual #28                 // Method java/lang/Object.getClass:()Ljava/lang/Class;
      65: pop
      66: invokedynamic #29,  0             // InvokeDynamic #2:accept:(Ljava/util/List;)Ljava/util/function/Consumer;
      71: invokeinterface #30,  2           // InterfaceMethod java/util/stream/Stream.forEach:(Ljava/util/function/Consumer;)V
      76: aload_0
      77: areturn

  org.apache.dubbo.common.extension.ExtensionLoader(java.lang.Class<?>, org.apache.dubbo.common.extension.ExtensionDirector, org.apache.dubbo.rpc.model.ScopeModel);
    Code:
       0: aload_0
       1: invokespecial #32                 // Method java/lang/Object."<init>":()V
       4: aload_0
       5: new           #13                 // class java/util/concurrent/ConcurrentHashMap
       8: dup
       9: bipush        64
      11: invokespecial #33                 // Method java/util/concurrent/ConcurrentHashMap."<init>":(I)V
      14: putfield      #34                 // Field extensionInstances:Ljava/util/concurrent/ConcurrentMap;
      17: aload_0
      18: new           #13                 // class java/util/concurrent/ConcurrentHashMap
      21: dup
      22: invokespecial #14                 // Method java/util/concurrent/ConcurrentHashMap."<init>":()V
      25: putfield      #35                 // Field cachedNames:Ljava/util/concurrent/ConcurrentMap;
      28: aload_0
      29: new           #36                 // class org/apache/dubbo/common/utils/Holder
      32: dup
      33: invokespecial #37                 // Method org/apache/dubbo/common/utils/Holder."<init>":()V
      36: putfield      #38                 // Field cachedClasses:Lorg/apache/dubbo/common/utils/Holder;
      39: aload_0
      40: new           #39                 // class java/util/LinkedHashMap
      43: dup
      44: invokespecial #40                 // Method java/util/LinkedHashMap."<init>":()V
      47: invokestatic  #41                 // Method java/util/Collections.synchronizedMap:(Ljava/util/Map;)Ljava/util/Map;
      50: putfield      #42                 // Field cachedActivates:Ljava/util/Map;
      53: aload_0
      54: new           #39                 // class java/util/LinkedHashMap
      57: dup
      58: invokespecial #40                 // Method java/util/LinkedHashMap."<init>":()V
      61: invokestatic  #41                 // Method java/util/Collections.synchronizedMap:(Ljava/util/Map;)Ljava/util/Map;
      64: putfield      #43                 // Field cachedActivateGroups:Ljava/util/Map;
      67: aload_0
      68: new           #39                 // class java/util/LinkedHashMap
      71: dup
      72: invokespecial #40                 // Method java/util/LinkedHashMap."<init>":()V
      75: invokestatic  #41                 // Method java/util/Collections.synchronizedMap:(Ljava/util/Map;)Ljava/util/Map;
      78: putfield      #44                 // Field cachedActivateValues:Ljava/util/Map;
      81: aload_0
      82: new           #13                 // class java/util/concurrent/ConcurrentHashMap
      85: dup
      86: invokespecial #14                 // Method java/util/concurrent/ConcurrentHashMap."<init>":()V
      89: putfield      #45                 // Field cachedInstances:Ljava/util/concurrent/ConcurrentMap;
      92: aload_0
      93: new           #36                 // class org/apache/dubbo/common/utils/Holder
      96: dup
      97: invokespecial #37                 // Method org/apache/dubbo/common/utils/Holder."<init>":()V
     100: putfield      #46                 // Field cachedAdaptiveInstance:Lorg/apache/dubbo/common/utils/Holder;
     103: aload_0
     104: aconst_null
     105: putfield      #47                 // Field cachedAdaptiveClass:Ljava/lang/Class;
     108: aload_0
     109: new           #13                 // class java/util/concurrent/ConcurrentHashMap
     112: dup
     113: invokespecial #14                 // Method java/util/concurrent/ConcurrentHashMap."<init>":()V
     116: putfield      #48                 // Field exceptions:Ljava/util/Map;
     119: aload_0
     120: new           #49                 // class org/apache/dubbo/common/utils/ConcurrentHashSet
     123: dup
     124: invokespecial #50                 // Method org/apache/dubbo/common/utils/ConcurrentHashSet."<init>":()V
     127: putfield      #51                 // Field unacceptableExceptions:Ljava/util/Set;
     130: aload_0
     131: new           #52                 // class java/util/concurrent/atomic/AtomicBoolean
     134: dup
     135: invokespecial #53                 // Method java/util/concurrent/atomic/AtomicBoolean."<init>":()V
     138: putfield      #54                 // Field destroyed:Ljava/util/concurrent/atomic/AtomicBoolean;
     141: aload_0
     142: aload_1
     143: putfield      #55                 // Field type:Ljava/lang/Class;
     146: aload_0
     147: aload_2
     148: putfield      #56                 // Field extensionDirector:Lorg/apache/dubbo/common/extension/ExtensionDirector;
     151: aload_0
     152: aload_2
     153: invokevirtual #57                 // Method org/apache/dubbo/common/extension/ExtensionDirector.getExtensionPostProcessors:()Ljava/util/List;
     156: putfield      #58                 // Field extensionPostProcessors:Ljava/util/List;
     159: aload_0
     160: invokespecial #59                 // Method initInstantiationStrategy:()V
     163: aload_0
     164: aload_1
     165: ldc           #60                 // class org/apache/dubbo/common/extension/ExtensionInjector
     167: if_acmpne     174
     170: aconst_null
     171: goto          186
     174: aload_2
     175: ldc           #60                 // class org/apache/dubbo/common/extension/ExtensionInjector
     177: invokevirtual #61                 // Method org/apache/dubbo/common/extension/ExtensionDirector.getExtensionLoader:(Ljava/lang/Class;)Lorg/apache/dubbo/common/extension/ExtensionLoader;
     180: invokevirtual #62                 // Method getAdaptiveExtension:()Ljava/lang/Object;
     183: checkcast     #60                 // class org/apache/dubbo/common/extension/ExtensionInjector
     186: putfield      #63                 // Field injector:Lorg/apache/dubbo/common/extension/ExtensionInjector;
     189: aload_0
     190: new           #64                 // class org/apache/dubbo/common/extension/support/ActivateComparator
     193: dup
     194: aload_2
     195: invokespecial #65                 // Method org/apache/dubbo/common/extension/support/ActivateComparator."<init>":(Lorg/apache/dubbo/common/extension/ExtensionDirector;)V
     198: putfield      #66                 // Field activateComparator:Lorg/apache/dubbo/common/extension/support/ActivateComparator;
     201: aload_0
     202: aload_3
     203: putfield      #67                 // Field scopeModel:Lorg/apache/dubbo/rpc/model/ScopeModel;
     206: return

  private void initInstantiationStrategy();
    Code:
       0: aload_0
       1: aload_0
       2: getfield      #58                 // Field extensionPostProcessors:Ljava/util/List;
       5: invokeinterface #68,  1           // InterfaceMethod java/util/List.stream:()Ljava/util/stream/Stream;
      10: invokedynamic #69,  0             // InvokeDynamic #3:test:()Ljava/util/function/Predicate;
      15: invokeinterface #70,  2           // InterfaceMethod java/util/stream/Stream.filter:(Ljava/util/function/Predicate;)Ljava/util/stream/Stream;
      20: invokedynamic #71,  0             // InvokeDynamic #4:apply:()Ljava/util/function/Function;
      25: invokeinterface #27,  2           // InterfaceMethod java/util/stream/Stream.map:(Ljava/util/function/Function;)Ljava/util/stream/Stream;
      30: invokeinterface #72,  1           // InterfaceMethod java/util/stream/Stream.findFirst:()Ljava/util/Optional;
      35: new           #73                 // class org/apache/dubbo/common/beans/support/InstantiationStrategy
      38: dup
      39: invokespecial #74                 // Method org/apache/dubbo/common/beans/support/InstantiationStrategy."<init>":()V
      42: invokevirtual #75                 // Method java/util/Optional.orElse:(Ljava/lang/Object;)Ljava/lang/Object;
      45: checkcast     #73                 // class org/apache/dubbo/common/beans/support/InstantiationStrategy
      48: putfield      #76                 // Field instantiationStrategy:Lorg/apache/dubbo/common/beans/support/InstantiationStrategy;
      51: return

  public static <T> org.apache.dubbo.common.extension.ExtensionLoader<T> getExtensionLoader(java.lang.Class<T>);
    Code:
       0: invokestatic  #77                 // Method org/apache/dubbo/rpc/model/ApplicationModel.defaultModel:()Lorg/apache/dubbo/rpc/model/ApplicationModel;
       3: invokevirtual #78                 // Method org/apache/dubbo/rpc/model/ApplicationModel.getDefaultModule:()Lorg/apache/dubbo/rpc/model/ModuleModel;
       6: aload_0
       7: invokevirtual #79                 // Method org/apache/dubbo/rpc/model/ModuleModel.getExtensionLoader:(Ljava/lang/Class;)Lorg/apache/dubbo/common/extension/ExtensionLoader;
      10: areturn

  public static void resetExtensionLoader(java.lang.Class);
    Code:
       0: return

  public void destroy();
    Code:
       0: aload_0
       1: getfield      #54                 // Field destroyed:Ljava/util/concurrent/atomic/AtomicBoolean;
       4: iconst_0
       5: iconst_1
       6: invokevirtual #80                 // Method java/util/concurrent/atomic/AtomicBoolean.compareAndSet:(ZZ)Z
       9: ifne          13
      12: return
      13: aload_0
      14: getfield      #34                 // Field extensionInstances:Ljava/util/concurrent/ConcurrentMap;
      17: invokedynamic #81,  0             // InvokeDynamic #5:accept:()Ljava/util/function/BiConsumer;
      22: invokeinterface #82,  2           // InterfaceMethod java/util/concurrent/ConcurrentMap.forEach:(Ljava/util/function/BiConsumer;)V
      27: aload_0
      28: getfield      #34                 // Field extensionInstances:Ljava/util/concurrent/ConcurrentMap;
      31: invokeinterface #83,  1           // InterfaceMethod java/util/concurrent/ConcurrentMap.clear:()V
      36: aload_0
      37: getfield      #45                 // Field cachedInstances:Ljava/util/concurrent/ConcurrentMap;
      40: invokeinterface #84,  1           // InterfaceMethod java/util/concurrent/ConcurrentMap.values:()Ljava/util/Collection;
      45: invokeinterface #85,  1           // InterfaceMethod java/util/Collection.iterator:()Ljava/util/Iterator;
      50: astore_1
      51: aload_1
      52: invokeinterface #86,  1           // InterfaceMethod java/util/Iterator.hasNext:()Z
      57: ifeq          139
      60: aload_1
      61: invokeinterface #87,  1           // InterfaceMethod java/util/Iterator.next:()Ljava/lang/Object;
      66: checkcast     #36                 // class org/apache/dubbo/common/utils/Holder
      69: astore_2
      70: aload_2
      71: invokevirtual #88                 // Method org/apache/dubbo/common/utils/Holder.get:()Ljava/lang/Object;
      74: astore_3
      75: aload_3
      76: instanceof    #89                 // class org/apache/dubbo/common/resource/Disposable
      79: ifeq          136
      82: aload_3
      83: checkcast     #89                 // class org/apache/dubbo/common/resource/Disposable
      86: astore        4
      88: aload         4
      90: invokeinterface #90,  1           // InterfaceMethod org/apache/dubbo/common/resource/Disposable.destroy:()V
      95: goto          136
      98: astore        5
     100: getstatic     #92                 // Field logger:Lorg/apache/dubbo/common/logger/ErrorTypeAwareLogger;
     103: ldc           #93                 // String 0-15
     105: ldc           #94                 // String
     107: ldc           #94                 // String
     109: new           #95                 // class java/lang/StringBuilder
     112: dup
     113: invokespecial #96                 // Method java/lang/StringBuilder."<init>":()V
     116: ldc           #97                 // String Error destroying extension
     118: invokevirtual #98                 // Method java/lang/StringBuilder.append:(Ljava/lang/String;)Ljava/lang/StringBuilder;
     121: aload         4
     123: invokevirtual #99                 // Method java/lang/StringBuilder.append:(Ljava/lang/Object;)Ljava/lang/StringBuilder;
     126: invokevirtual #100                // Method java/lang/StringBuilder.toString:()Ljava/lang/String;
     129: aload         5
     131: invokeinterface #101,  6          // InterfaceMethod org/apache/dubbo/common/logger/ErrorTypeAwareLogger.error:(Ljava/lang/String;Ljava/lang/String;Ljava/lang/String;Ljava/lang/String;Ljava/lang/Throwable;)V
     136: goto          51
     139: aload_0
     140: getfield      #45                 // Field cachedInstances:Ljava/util/concurrent/ConcurrentMap;
     143: invokeinterface #83,  1           // InterfaceMethod java/util/concurrent/ConcurrentMap.clear:()V
     148: return
    Exception table:
       from    to  target type
          88    95    98   Class java/lang/Exception

  private void checkDestroyed();
    Code:
       0: aload_0
       1: getfield      #54                 // Field destroyed:Ljava/util/concurrent/atomic/AtomicBoolean;
       4: invokevirtual #102                // Method java/util/concurrent/atomic/AtomicBoolean.get:()Z
       7: ifeq          40
      10: new           #103                // class java/lang/IllegalStateException
      13: dup
      14: new           #95                 // class java/lang/StringBuilder
      17: dup
      18: invokespecial #96                 // Method java/lang/StringBuilder."<init>":()V
      21: ldc           #104                // String ExtensionLoader is destroyed:
      23: invokevirtual #98                 // Method java/lang/StringBuilder.append:(Ljava/lang/String;)Ljava/lang/StringBuilder;
      26: aload_0
      27: getfield      #55                 // Field type:Ljava/lang/Class;
      30: invokevirtual #99                 // Method java/lang/StringBuilder.append:(Ljava/lang/Object;)Ljava/lang/StringBuilder;
      33: invokevirtual #100                // Method java/lang/StringBuilder.toString:()Ljava/lang/String;
      36: invokespecial #105                // Method java/lang/IllegalStateException."<init>":(Ljava/lang/String;)V
      39: athrow
      40: return

  public java.lang.String getExtensionName(T);
    Code:
       0: aload_0
       1: aload_1
       2: invokevirtual #28                 // Method java/lang/Object.getClass:()Ljava/lang/Class;
       5: invokevirtual #106                // Method getExtensionName:(Ljava/lang/Class;)Ljava/lang/String;
       8: areturn

  public java.lang.String getExtensionName(java.lang.Class<?>);
    Code:
       0: aload_0
       1: invokespecial #107                // Method getExtensionClasses:()Ljava/util/Map;
       4: pop
       5: aload_0
       6: getfield      #35                 // Field cachedNames:Ljava/util/concurrent/ConcurrentMap;
       9: aload_1
      10: invokeinterface #108,  2          // InterfaceMethod java/util/concurrent/ConcurrentMap.get:(Ljava/lang/Object;)Ljava/lang/Object;
      15: checkcast     #109                // class java/lang/String
      18: areturn

  public java.util.List<T> getActivateExtension(org.apache.dubbo.common.URL, java.lang.String);
    Code:
       0: aload_0
       1: aload_1
       2: aload_2
       3: aconst_null
       4: invokevirtual #110                // Method getActivateExtension:(Lorg/apache/dubbo/common/URL;Ljava/lang/String;Ljava/lang/String;)Ljava/util/List;
       7: areturn

  public java.util.List<T> getActivateExtension(org.apache.dubbo.common.URL, java.lang.String[]);
    Code:
       0: aload_0
       1: aload_1
       2: aload_2
       3: aconst_null
       4: invokevirtual #111                // Method getActivateExtension:(Lorg/apache/dubbo/common/URL;[Ljava/lang/String;Ljava/lang/String;)Ljava/util/List;
       7: areturn

  public java.util.List<T> getActivateExtension(org.apache.dubbo.common.URL, java.lang.String, java.lang.String);
    Code:
       0: aload_1
       1: aload_2
       2: invokevirtual #112                // Method org/apache/dubbo/common/URL.getParameter:(Ljava/lang/String;)Ljava/lang/String;
       5: astore        4
       7: aload_0
       8: aload_1
       9: aload         4
      11: invokestatic  #113                // Method org/apache/dubbo/common/utils/StringUtils.isEmpty:(Ljava/lang/String;)Z
      14: ifeq          21
      17: aconst_null
      18: goto          29
      21: getstatic     #114                // Field org/apache/dubbo/common/constants/CommonConstants.COMMA_SPLIT_PATTERN:Ljava/util/regex/Pattern;
      24: aload         4
      26: invokevirtual #115                // Method java/util/regex/Pattern.split:(Ljava/lang/CharSequence;)[Ljava/lang/String;
      29: aload_3
      30: invokevirtual #111                // Method getActivateExtension:(Lorg/apache/dubbo/common/URL;[Ljava/lang/String;Ljava/lang/String;)Ljava/util/List;
      33: areturn

  public java.util.List<T> getActivateExtension(org.apache.dubbo.common.URL, java.lang.String[], java.lang.String);
    Code:
       0: aload_0
       1: invokespecial #116                // Method checkDestroyed:()V
       4: new           #117                // class java/util/TreeMap
       7: dup
       8: aload_0
       9: getfield      #66                 // Field activateComparator:Lorg/apache/dubbo/common/extension/support/ActivateComparator;
      12: invokespecial #118                // Method java/util/TreeMap."<init>":(Ljava/util/Comparator;)V
      15: astore        4
      17: aload_2
      18: ifnonnull     32
      21: new           #21                 // class java/util/ArrayList
      24: dup
      25: iconst_0
      26: invokespecial #119                // Method java/util/ArrayList."<init>":(I)V
      29: goto          36
      32: aload_2
      33: invokestatic  #20                 // Method java/util/Arrays.asList:([Ljava/lang/Object;)Ljava/util/List;
      36: astore        5
      38: new           #120                // class java/util/HashSet
      41: dup
      42: aload         5
      44: invokespecial #121                // Method java/util/HashSet."<init>":(Ljava/util/Collection;)V
      47: astore        6
      49: aload         6
      51: ldc           #122                // String -default
      53: invokeinterface #123,  2          // InterfaceMethod java/util/Set.contains:(Ljava/lang/Object;)Z
      58: ifne          405
      61: aload_0
      62: getfield      #43                 // Field cachedActivateGroups:Ljava/util/Map;
      65: invokeinterface #124,  1          // InterfaceMethod java/util/Map.size:()I
      70: ifne          384
      73: aload_0
      74: getfield      #43                 // Field cachedActivateGroups:Ljava/util/Map;
      77: dup
      78: astore        7
      80: monitorenter
      81: aload_0
      82: getfield      #43                 // Field cachedActivateGroups:Ljava/util/Map;
      85: invokeinterface #124,  1          // InterfaceMethod java/util/Map.size:()I
      90: ifne          370
      93: aload_0
      94: invokespecial #107                // Method getExtensionClasses:()Ljava/util/Map;
      97: pop
      98: aload_0
      99: getfield      #42                 // Field cachedActivates:Ljava/util/Map;
     102: invokeinterface #125,  1          // InterfaceMethod java/util/Map.entrySet:()Ljava/util/Set;
     107: invokeinterface #126,  1          // InterfaceMethod java/util/Set.iterator:()Ljava/util/Iterator;
     112: astore        8
     114: aload         8
     116: invokeinterface #86,  1           // InterfaceMethod java/util/Iterator.hasNext:()Z
     121: ifeq          370
     124: aload         8
     126: invokeinterface #87,  1           // InterfaceMethod java/util/Iterator.next:()Ljava/lang/Object;
     131: checkcast     #127                // class java/util/Map$Entry
     134: astore        9
     136: aload         9
     138: invokeinterface #128,  1          // InterfaceMethod java/util/Map$Entry.getKey:()Ljava/lang/Object;
     143: checkcast     #109                // class java/lang/String
     146: astore        10
     148: aload         9
     150: invokeinterface #129,  1          // InterfaceMethod java/util/Map$Entry.getValue:()Ljava/lang/Object;
     155: astore        11
     157: aload         11
     159: instanceof    #130                // class org/apache/dubbo/common/extension/Activate
     162: ifeq          192
     165: aload         11
     167: checkcast     #130                // class org/apache/dubbo/common/extension/Activate
     170: invokeinterface #131,  1          // InterfaceMethod org/apache/dubbo/common/extension/Activate.group:()[Ljava/lang/String;
     175: astore        12
     177: aload         11
     179: checkcast     #130                // class org/apache/dubbo/common/extension/Activate
     182: invokeinterface #132,  1          // InterfaceMethod org/apache/dubbo/common/extension/Activate.value:()[Ljava/lang/String;
     187: astore        13
     189: goto          224
     192: aload         11
     194: instanceof    #133                // class com/alibaba/dubbo/common/extension/Activate
     197: ifeq          114
     200: aload         11
     202: checkcast     #133                // class com/alibaba/dubbo/common/extension/Activate
     205: invokeinterface #134,  1          // InterfaceMethod com/alibaba/dubbo/common/extension/Activate.group:()[Ljava/lang/String;
     210: astore        12
     212: aload         11
     214: checkcast     #133                // class com/alibaba/dubbo/common/extension/Activate
     217: invokeinterface #135,  1          // InterfaceMethod com/alibaba/dubbo/common/extension/Activate.value:()[Ljava/lang/String;
     222: astore        13
     224: aload_0
     225: getfield      #43                 // Field cachedActivateGroups:Ljava/util/Map;
     228: aload         10
     230: new           #120                // class java/util/HashSet
     233: dup
     234: aload         12
     236: invokestatic  #20                 // Method java/util/Arrays.asList:([Ljava/lang/Object;)Ljava/util/List;
     239: invokespecial #121                // Method java/util/HashSet."<init>":(Ljava/util/Collection;)V
     242: invokeinterface #136,  3          // InterfaceMethod java/util/Map.put:(Ljava/lang/Object;Ljava/lang/Object;)Ljava/lang/Object;
     247: pop
     248: aload         13
     250: arraylength
     251: anewarray     #137                // class "[Ljava/lang/String;"
     254: astore        14
     256: iconst_0
     257: istore        15
     259: iload         15
     261: aload         13
     263: arraylength
     264: if_icmpge     353
     267: aload         13
     269: iload         15
     271: aaload
     272: ldc           #138                // String :
     274: invokevirtual #139                // Method java/lang/String.contains:(Ljava/lang/CharSequence;)Z
     277: ifeq          326
     280: aload         14
     282: iload         15
     284: iconst_2
     285: anewarray     #109                // class java/lang/String
     288: aastore
     289: aload         13
     291: iload         15
     293: aaload
     294: ldc           #138                // String :
     296: invokevirtual #140                // Method java/lang/String.split:(Ljava/lang/String;)[Ljava/lang/String;
     299: astore        16
     301: aload         14
     303: iload         15
     305: aaload
     306: iconst_0
     307: aload         16
     309: iconst_0
     310: aaload
     311: aastore
     312: aload         14
     314: iload         15
     316: aaload
     317: iconst_1
     318: aload         16
     320: iconst_1
     321: aaload
     322: aastore
     323: goto          347
     326: aload         14
     328: iload         15
     330: iconst_1
     331: anewarray     #109                // class java/lang/String
     334: aastore
     335: aload         14
     337: iload         15
     339: aaload
     340: iconst_0
     341: aload         13
     343: iload         15
     345: aaload
     346: aastore
     347: iinc          15, 1
     350: goto          259
     353: aload_0
     354: getfield      #44                 // Field cachedActivateValues:Ljava/util/Map;
     357: aload         10
     359: aload         14
     361: invokeinterface #136,  3          // InterfaceMethod java/util/Map.put:(Ljava/lang/Object;Ljava/lang/Object;)Ljava/lang/Object;
     366: pop
     367: goto          114
     370: aload         7
     372: monitorexit
     373: goto          384
     376: astore        17
     378: aload         7
     380: monitorexit
     381: aload         17
     383: athrow
     384: aload_0
     385: getfield      #43                 // Field cachedActivateGroups:Ljava/util/Map;
     388: aload_0
     389: aload_3
     390: aload         6
     392: aload_1
     393: aload         4
     395: invokedynamic #141,  0            // InvokeDynamic #6:accept:(Lorg/apache/dubbo/common/extension/ExtensionLoader;Ljava/lang/String;Ljava/util/Set;Lorg/apache/dubbo/common/URL;Ljava/util/Map;)Ljava/util/function/BiConsumer;
     400: invokeinterface #142,  2          // InterfaceMethod java/util/Map.forEach:(Ljava/util/function/BiConsumer;)V
     405: aload         6
     407: ldc           #143                // String default
     409: invokeinterface #123,  2          // InterfaceMethod java/util/Set.contains:(Ljava/lang/Object;)Z
     414: ifeq          568
     417: new           #21                 // class java/util/ArrayList
     420: dup
     421: aload         4
     423: invokeinterface #124,  1          // InterfaceMethod java/util/Map.size:()I
     428: aload         5
     430: invokeinterface #144,  1          // InterfaceMethod java/util/List.size:()I
     435: iadd
     436: invokespecial #119                // Method java/util/ArrayList."<init>":(I)V
     439: astore        7
     441: aload         5
     443: invokeinterface #145,  1          // InterfaceMethod java/util/List.iterator:()Ljava/util/Iterator;
     448: astore        8
     450: aload         8
     452: invokeinterface #86,  1           // InterfaceMethod java/util/Iterator.hasNext:()Z
     457: ifeq          565
     460: aload         8
     462: invokeinterface #87,  1           // InterfaceMethod java/util/Iterator.next:()Ljava/lang/Object;
     467: checkcast     #109                // class java/lang/String
     470: astore        9
     472: aload         9
     474: ldc           #146                // String -
     476: invokevirtual #147                // Method java/lang/String.startsWith:(Ljava/lang/String;)Z
     479: ifne          450
     482: aload         6
     484: new           #95                 // class java/lang/StringBuilder
     487: dup
     488: invokespecial #96                 // Method java/lang/StringBuilder."<init>":()V
     491: ldc           #146                // String -
     493: invokevirtual #98                 // Method java/lang/StringBuilder.append:(Ljava/lang/String;)Ljava/lang/StringBuilder;
     496: aload         9
     498: invokevirtual #98                 // Method java/lang/StringBuilder.append:(Ljava/lang/String;)Ljava/lang/StringBuilder;
     501: invokevirtual #100                // Method java/lang/StringBuilder.toString:()Ljava/lang/String;
     504: invokeinterface #123,  2          // InterfaceMethod java/util/Set.contains:(Ljava/lang/Object;)Z
     509: ifeq          515
     512: goto          450
     515: ldc           #143                // String default
     517: aload         9
     519: invokevirtual #148                // Method java/lang/String.equals:(Ljava/lang/Object;)Z
     522: ifeq          541
     525: aload         7
     527: aload         4
     529: invokeinterface #149,  1          // InterfaceMethod java/util/Map.values:()Ljava/util/Collection;
     534: invokevirtual #150                // Method java/util/ArrayList.addAll:(Ljava/util/Collection;)Z
     537: pop
     538: goto          450
     541: aload_0
     542: aload         9
     544: invokespecial #151                // Method containsExtension:(Ljava/lang/String;)Z
     547: ifeq          562
     550: aload         7
     552: aload_0
     553: aload         9
     555: invokevirtual #152                // Method getExtension:(Ljava/lang/String;)Ljava/lang/Object;
     558: invokevirtual #153                // Method java/util/ArrayList.add:(Ljava/lang/Object;)Z
     561: pop
     562: goto          450
     565: aload         7
     567: areturn
     568: aload         5
     570: invokeinterface #145,  1          // InterfaceMethod java/util/List.iterator:()Ljava/util/Iterator;
     575: astore        7
     577: aload         7
     579: invokeinterface #86,  1           // InterfaceMethod java/util/Iterator.hasNext:()Z
     584: ifeq          687
     587: aload         7
     589: invokeinterface #87,  1           // InterfaceMethod java/util/Iterator.next:()Ljava/lang/Object;
     594: checkcast     #109                // class java/lang/String
     597: astore        8
     599: aload         8
     601: ldc           #146                // String -
     603: invokevirtual #147                // Method java/lang/String.startsWith:(Ljava/lang/String;)Z
     606: ifne          577
     609: aload         6
     611: new           #95                 // class java/lang/StringBuilder
     614: dup
     615: invokespecial #96                 // Method java/lang/StringBuilder."<init>":()V
     618: ldc           #146                // String -
     620: invokevirtual #98                 // Method java/lang/StringBuilder.append:(Ljava/lang/String;)Ljava/lang/StringBuilder;
     623: aload         8
     625: invokevirtual #98                 // Method java/lang/StringBuilder.append:(Ljava/lang/String;)Ljava/lang/StringBuilder;
     628: invokevirtual #100                // Method java/lang/StringBuilder.toString:()Ljava/lang/String;
     631: invokeinterface #123,  2          // InterfaceMethod java/util/Set.contains:(Ljava/lang/Object;)Z
     636: ifeq          642
     639: goto          577
     642: ldc           #143                // String default
     644: aload         8
     646: invokevirtual #148                // Method java/lang/String.equals:(Ljava/lang/Object;)Z
     649: ifeq          655
     652: goto          577
     655: aload_0
     656: aload         8
     658: invokespecial #151                // Method containsExtension:(Ljava/lang/String;)Z
     661: ifeq          684
     664: aload         4
     666: aload_0
     667: aload         8
     669: invokespecial #154                // Method getExtensionClass:(Ljava/lang/String;)Ljava/lang/Class;
     672: aload_0
     673: aload         8
     675: invokevirtual #152                // Method getExtension:(Ljava/lang/String;)Ljava/lang/Object;
     678: invokeinterface #136,  3          // InterfaceMethod java/util/Map.put:(Ljava/lang/Object;Ljava/lang/Object;)Ljava/lang/Object;
     683: pop
     684: goto          577
     687: new           #21                 // class java/util/ArrayList
     690: dup
     691: aload         4
     693: invokeinterface #149,  1          // InterfaceMethod java/util/Map.values:()Ljava/util/Collection;
     698: invokespecial #155                // Method java/util/ArrayList."<init>":(Ljava/util/Collection;)V
     701: areturn
    Exception table:
       from    to  target type
          81   373   376   any
         376   381   376   any

  public java.util.List<T> getActivateExtensions();
    Code:
       0: aload_0
       1: invokespecial #116                // Method checkDestroyed:()V
       4: new           #21                 // class java/util/ArrayList
       7: dup
       8: invokespecial #22                 // Method java/util/ArrayList."<init>":()V
      11: astore_1
      12: new           #117                // class java/util/TreeMap
      15: dup
      16: aload_0
      17: getfield      #66                 // Field activateComparator:Lorg/apache/dubbo/common/extension/support/ActivateComparator;
      20: invokespecial #118                // Method java/util/TreeMap."<init>":(Ljava/util/Comparator;)V
      23: astore_2
      24: aload_0
      25: invokespecial #107                // Method getExtensionClasses:()Ljava/util/Map;
      28: pop
      29: aload_0
      30: getfield      #42                 // Field cachedActivates:Ljava/util/Map;
      33: invokeinterface #125,  1          // InterfaceMethod java/util/Map.entrySet:()Ljava/util/Set;
      38: invokeinterface #126,  1          // InterfaceMethod java/util/Set.iterator:()Ljava/util/Iterator;
      43: astore_3
      44: aload_3
      45: invokeinterface #86,  1           // InterfaceMethod java/util/Iterator.hasNext:()Z
      50: ifeq          116
      53: aload_3
      54: invokeinterface #87,  1           // InterfaceMethod java/util/Iterator.next:()Ljava/lang/Object;
      59: checkcast     #127                // class java/util/Map$Entry
      62: astore        4
      64: aload         4
      66: invokeinterface #128,  1          // InterfaceMethod java/util/Map$Entry.getKey:()Ljava/lang/Object;
      71: checkcast     #109                // class java/lang/String
      74: astore        5
      76: aload         4
      78: invokeinterface #129,  1          // InterfaceMethod java/util/Map$Entry.getValue:()Ljava/lang/Object;
      83: astore        6
      85: aload         6
      87: instanceof    #130                // class org/apache/dubbo/common/extension/Activate
      90: ifne          96
      93: goto          44
      96: aload_2
      97: aload_0
      98: aload         5
     100: invokespecial #154                // Method getExtensionClass:(Ljava/lang/String;)Ljava/lang/Class;
     103: aload_0
     104: aload         5
     106: invokevirtual #152                // Method getExtension:(Ljava/lang/String;)Ljava/lang/Object;
     109: invokevirtual #156                // Method java/util/TreeMap.put:(Ljava/lang/Object;Ljava/lang/Object;)Ljava/lang/Object;
     112: pop
     113: goto          44
     116: aload_2
     117: invokevirtual #157                // Method java/util/TreeMap.isEmpty:()Z
     120: ifne          134
     123: aload_1
     124: aload_2
     125: invokevirtual #158                // Method java/util/TreeMap.values:()Ljava/util/Collection;
     128: invokeinterface #159,  2          // InterfaceMethod java/util/List.addAll:(Ljava/util/Collection;)Z
     133: pop
     134: aload_1
     135: areturn

  private boolean isMatchGroup(java.lang.String, java.util.Set<java.lang.String>);
    Code:
       0: aload_1
       1: invokestatic  #113                // Method org/apache/dubbo/common/utils/StringUtils.isEmpty:(Ljava/lang/String;)Z
       4: ifeq          9
       7: iconst_1
       8: ireturn
       9: aload_2
      10: invokestatic  #160                // Method org/apache/dubbo/common/utils/CollectionUtils.isNotEmpty:(Ljava/util/Collection;)Z
      13: ifeq          24
      16: aload_2
      17: aload_1
      18: invokeinterface #123,  2          // InterfaceMethod java/util/Set.contains:(Ljava/lang/Object;)Z
      23: ireturn
      24: iconst_0
      25: ireturn

  private boolean isActive(java.lang.String[][], org.apache.dubbo.common.URL);
    Code:
       0: aload_1
       1: arraylength
       2: ifne          7
       5: iconst_1
       6: ireturn
       7: aload_1
       8: astore_3
       9: aload_3
      10: arraylength
      11: istore        4
      13: iconst_0
      14: istore        5
      16: iload         5
      18: iload         4
      20: if_icmpge     120
      23: aload_3
      24: iload         5
      26: aaload
      27: astore        6
      29: aconst_null
      30: astore        8
      32: aload         6
      34: arraylength
      35: iconst_1
      36: if_icmple     54
      39: aload         6
      41: iconst_0
      42: aaload
      43: astore        7
      45: aload         6
      47: iconst_1
      48: aaload
      49: astore        8
      51: goto          60
      54: aload         6
      56: iconst_0
      57: aaload
      58: astore        7
      60: aload_2
      61: aload         7
      63: invokevirtual #112                // Method org/apache/dubbo/common/URL.getParameter:(Ljava/lang/String;)Ljava/lang/String;
      66: astore        9
      68: aload         9
      70: invokestatic  #113                // Method org/apache/dubbo/common/utils/StringUtils.isEmpty:(Ljava/lang/String;)Z
      73: ifeq          84
      76: aload_2
      77: aload         7
      79: invokevirtual #161                // Method org/apache/dubbo/common/URL.getAnyMethodParameter:(Ljava/lang/String;)Ljava/lang/String;
      82: astore        9
      84: aload         8
      86: ifnull        99
      89: aload         8
      91: aload         9
      93: invokevirtual #148                // Method java/lang/String.equals:(Ljava/lang/Object;)Z
      96: ifne          112
      99: aload         8
     101: ifnonnull     114
     104: aload         9
     106: invokestatic  #162                // Method org/apache/dubbo/common/utils/ConfigUtils.isNotEmpty:(Ljava/lang/String;)Z
     109: ifeq          114
     112: iconst_1
     113: ireturn
     114: iinc          5, 1
     117: goto          16
     120: iconst_0
     121: ireturn

  public T getLoadedExtension(java.lang.String);
    Code:
       0: aload_0
       1: invokespecial #116                // Method checkDestroyed:()V
       4: aload_1
       5: invokestatic  #113                // Method org/apache/dubbo/common/utils/StringUtils.isEmpty:(Ljava/lang/String;)Z
       8: ifeq          21
      11: new           #163                // class java/lang/IllegalArgumentException
      14: dup
      15: ldc           #164                // String Extension name == null
      17: invokespecial #165                // Method java/lang/IllegalArgumentException."<init>":(Ljava/lang/String;)V
      20: athrow
      21: aload_0
      22: aload_1
      23: invokespecial #166                // Method getOrCreateHolder:(Ljava/lang/String;)Lorg/apache/dubbo/common/utils/Holder;
      26: astore_2
      27: aload_2
      28: invokevirtual #88                 // Method org/apache/dubbo/common/utils/Holder.get:()Ljava/lang/Object;
      31: areturn

  private org.apache.dubbo.common.utils.Holder<java.lang.Object> getOrCreateHolder(java.lang.String);
    Code:
       0: aload_0
       1: getfield      #45                 // Field cachedInstances:Ljava/util/concurrent/ConcurrentMap;
       4: aload_1
       5: invokeinterface #108,  2          // InterfaceMethod java/util/concurrent/ConcurrentMap.get:(Ljava/lang/Object;)Ljava/lang/Object;
      10: checkcast     #36                 // class org/apache/dubbo/common/utils/Holder
      13: astore_2
      14: aload_2
      15: ifnonnull     50
      18: aload_0
      19: getfield      #45                 // Field cachedInstances:Ljava/util/concurrent/ConcurrentMap;
      22: aload_1
      23: new           #36                 // class org/apache/dubbo/common/utils/Holder
      26: dup
      27: invokespecial #37                 // Method org/apache/dubbo/common/utils/Holder."<init>":()V
      30: invokeinterface #167,  3          // InterfaceMethod java/util/concurrent/ConcurrentMap.putIfAbsent:(Ljava/lang/Object;Ljava/lang/Object;)Ljava/lang/Object;
      35: pop
      36: aload_0
      37: getfield      #45                 // Field cachedInstances:Ljava/util/concurrent/ConcurrentMap;
      40: aload_1
      41: invokeinterface #108,  2          // InterfaceMethod java/util/concurrent/ConcurrentMap.get:(Ljava/lang/Object;)Ljava/lang/Object;
      46: checkcast     #36                 // class org/apache/dubbo/common/utils/Holder
      49: astore_2
      50: aload_2
      51: areturn

  public java.util.Set<java.lang.String> getLoadedExtensions();
    Code:
       0: new           #168                // class java/util/TreeSet
       3: dup
       4: aload_0
       5: getfield      #45                 // Field cachedInstances:Ljava/util/concurrent/ConcurrentMap;
       8: invokeinterface #169,  1          // InterfaceMethod java/util/concurrent/ConcurrentMap.keySet:()Ljava/util/Set;
      13: invokespecial #170                // Method java/util/TreeSet."<init>":(Ljava/util/Collection;)V
      16: invokestatic  #171                // Method java/util/Collections.unmodifiableSet:(Ljava/util/Set;)Ljava/util/Set;
      19: areturn

  public java.util.List<T> getLoadedExtensionInstances();
    Code:
       0: aload_0
       1: invokespecial #116                // Method checkDestroyed:()V
       4: new           #21                 // class java/util/ArrayList
       7: dup
       8: invokespecial #22                 // Method java/util/ArrayList."<init>":()V
      11: astore_1
      12: aload_0
      13: getfield      #45                 // Field cachedInstances:Ljava/util/concurrent/ConcurrentMap;
      16: invokeinterface #84,  1           // InterfaceMethod java/util/concurrent/ConcurrentMap.values:()Ljava/util/Collection;
      21: aload_1
      22: invokedynamic #172,  0            // InvokeDynamic #7:accept:(Ljava/util/List;)Ljava/util/function/Consumer;
      27: invokeinterface #173,  2          // InterfaceMethod java/util/Collection.forEach:(Ljava/util/function/Consumer;)V
      32: aload_1
      33: areturn

  public T getExtension(java.lang.String);
    Code:
       0: aload_0
       1: aload_1
       2: iconst_1
       3: invokevirtual #174                // Method getExtension:(Ljava/lang/String;Z)Ljava/lang/Object;
       6: astore_2
       7: aload_2
       8: ifnonnull     38
      11: new           #163                // class java/lang/IllegalArgumentException
      14: dup
      15: new           #95                 // class java/lang/StringBuilder
      18: dup
      19: invokespecial #96                 // Method java/lang/StringBuilder."<init>":()V
      22: ldc           #175                // String Not find extension:
      24: invokevirtual #98                 // Method java/lang/StringBuilder.append:(Ljava/lang/String;)Ljava/lang/StringBuilder;
      27: aload_1
      28: invokevirtual #98                 // Method java/lang/StringBuilder.append:(Ljava/lang/String;)Ljava/lang/StringBuilder;
      31: invokevirtual #100                // Method java/lang/StringBuilder.toString:()Ljava/lang/String;
      34: invokespecial #165                // Method java/lang/IllegalArgumentException."<init>":(Ljava/lang/String;)V
      37: athrow
      38: aload_2
      39: areturn

  public T getExtension(java.lang.String, boolean);
    Code:
       0: aload_0
       1: invokespecial #116                // Method checkDestroyed:()V
       4: aload_1
       5: invokestatic  #113                // Method org/apache/dubbo/common/utils/StringUtils.isEmpty:(Ljava/lang/String;)Z
       8: ifeq          21
      11: new           #163                // class java/lang/IllegalArgumentException
      14: dup
      15: ldc           #164                // String Extension name == null
      17: invokespecial #165                // Method java/lang/IllegalArgumentException."<init>":(Ljava/lang/String;)V
      20: athrow
      21: ldc           #176                // String true
      23: aload_1
      24: invokevirtual #148                // Method java/lang/String.equals:(Ljava/lang/Object;)Z
      27: ifeq          35
      30: aload_0
      31: invokevirtual #177                // Method getDefaultExtension:()Ljava/lang/Object;
      34: areturn
      35: aload_1
      36: astore_3
      37: iload_2
      38: ifne          61
      41: new           #95                 // class java/lang/StringBuilder
      44: dup
      45: invokespecial #96                 // Method java/lang/StringBuilder."<init>":()V
      48: aload_3
      49: invokevirtual #98                 // Method java/lang/StringBuilder.append:(Ljava/lang/String;)Ljava/lang/StringBuilder;
      52: ldc           #178                // String _origin
      54: invokevirtual #98                 // Method java/lang/StringBuilder.append:(Ljava/lang/String;)Ljava/lang/StringBuilder;
      57: invokevirtual #100                // Method java/lang/StringBuilder.toString:()Ljava/lang/String;
      60: astore_3
      61: aload_0
      62: aload_3
      63: invokespecial #166                // Method getOrCreateHolder:(Ljava/lang/String;)Lorg/apache/dubbo/common/utils/Holder;
      66: astore        4
      68: aload         4
      70: invokevirtual #88                 // Method org/apache/dubbo/common/utils/Holder.get:()Ljava/lang/Object;
      73: astore        5
      75: aload         5
      77: ifnonnull     127
      80: aload         4
      82: dup
      83: astore        6
      85: monitorenter
      86: aload         4
      88: invokevirtual #88                 // Method org/apache/dubbo/common/utils/Holder.get:()Ljava/lang/Object;
      91: astore        5
      93: aload         5
      95: ifnonnull     113
      98: aload_0
      99: aload_1
     100: iload_2
     101: invokespecial #179                // Method createExtension:(Ljava/lang/String;Z)Ljava/lang/Object;
     104: astore        5
     106: aload         4
     108: aload         5
     110: invokevirtual #180                // Method org/apache/dubbo/common/utils/Holder.set:(Ljava/lang/Object;)V
     113: aload         6
     115: monitorexit
     116: goto          127
     119: astore        7
     121: aload         6
     123: monitorexit
     124: aload         7
     126: athrow
     127: aload         5
     129: areturn
    Exception table:
       from    to  target type
          86   116   119   any
         119   124   119   any

  public T getOrDefaultExtension(java.lang.String);
    Code:
       0: aload_0
       1: aload_1
       2: invokespecial #151                // Method containsExtension:(Ljava/lang/String;)Z
       5: ifeq          16
       8: aload_0
       9: aload_1
      10: invokevirtual #152                // Method getExtension:(Ljava/lang/String;)Ljava/lang/Object;
      13: goto          20
      16: aload_0
      17: invokevirtual #177                // Method getDefaultExtension:()Ljava/lang/Object;
      20: areturn

  public T getDefaultExtension();
    Code:
       0: aload_0
       1: invokespecial #107                // Method getExtensionClasses:()Ljava/util/Map;
       4: pop
       5: aload_0
       6: getfield      #181                // Field cachedDefaultName:Ljava/lang/String;
       9: invokestatic  #182                // Method org/apache/dubbo/common/utils/StringUtils.isBlank:(Ljava/lang/CharSequence;)Z
      12: ifne          27
      15: ldc           #176                // String true
      17: aload_0
      18: getfield      #181                // Field cachedDefaultName:Ljava/lang/String;
      21: invokevirtual #148                // Method java/lang/String.equals:(Ljava/lang/Object;)Z
      24: ifeq          29
      27: aconst_null
      28: areturn
      29: aload_0
      30: aload_0
      31: getfield      #181                // Field cachedDefaultName:Ljava/lang/String;
      34: invokevirtual #152                // Method getExtension:(Ljava/lang/String;)Ljava/lang/Object;
      37: areturn

  public boolean hasExtension(java.lang.String);
    Code:
       0: aload_0
       1: invokespecial #116                // Method checkDestroyed:()V
       4: aload_1
       5: invokestatic  #113                // Method org/apache/dubbo/common/utils/StringUtils.isEmpty:(Ljava/lang/String;)Z
       8: ifeq          21
      11: new           #163                // class java/lang/IllegalArgumentException
      14: dup
      15: ldc           #164                // String Extension name == null
      17: invokespecial #165                // Method java/lang/IllegalArgumentException."<init>":(Ljava/lang/String;)V
      20: athrow
      21: aload_0
      22: aload_1
      23: invokespecial #154                // Method getExtensionClass:(Ljava/lang/String;)Ljava/lang/Class;
      26: astore_2
      27: aload_2
      28: ifnull        35
      31: iconst_1
      32: goto          36
      35: iconst_0
      36: ireturn

  public java.util.Set<java.lang.String> getSupportedExtensions();
    Code:
       0: aload_0
       1: invokespecial #116                // Method checkDestroyed:()V
       4: aload_0
       5: invokespecial #107                // Method getExtensionClasses:()Ljava/util/Map;
       8: astore_1
       9: new           #168                // class java/util/TreeSet
      12: dup
      13: aload_1
      14: invokeinterface #183,  1          // InterfaceMethod java/util/Map.keySet:()Ljava/util/Set;
      19: invokespecial #170                // Method java/util/TreeSet."<init>":(Ljava/util/Collection;)V
      22: invokestatic  #171                // Method java/util/Collections.unmodifiableSet:(Ljava/util/Set;)Ljava/util/Set;
      25: areturn

  public java.util.Set<T> getSupportedExtensionInstances();
    Code:
       0: aload_0
       1: invokespecial #116                // Method checkDestroyed:()V
       4: new           #184                // class java/util/LinkedList
       7: dup
       8: invokespecial #185                // Method java/util/LinkedList."<init>":()V
      11: astore_1
      12: aload_0
      13: invokevirtual #186                // Method getSupportedExtensions:()Ljava/util/Set;
      16: astore_2
      17: aload_2
      18: invokestatic  #160                // Method org/apache/dubbo/common/utils/CollectionUtils.isNotEmpty:(Ljava/util/Collection;)Z
      21: ifeq          67
      24: aload_2
      25: invokeinterface #126,  1          // InterfaceMethod java/util/Set.iterator:()Ljava/util/Iterator;
      30: astore_3
      31: aload_3
      32: invokeinterface #86,  1           // InterfaceMethod java/util/Iterator.hasNext:()Z
      37: ifeq          67
      40: aload_3
      41: invokeinterface #87,  1           // InterfaceMethod java/util/Iterator.next:()Ljava/lang/Object;
      46: checkcast     #109                // class java/lang/String
      49: astore        4
      51: aload_1
      52: aload_0
      53: aload         4
      55: invokevirtual #152                // Method getExtension:(Ljava/lang/String;)Ljava/lang/Object;
      58: invokeinterface #187,  2          // InterfaceMethod java/util/List.add:(Ljava/lang/Object;)Z
      63: pop
      64: goto          31
      67: aload_1
      68: getstatic     #188                // Field org/apache/dubbo/common/lang/Prioritized.COMPARATOR:Ljava/util/Comparator;
      71: invokeinterface #189,  2          // InterfaceMethod java/util/List.sort:(Ljava/util/Comparator;)V
      76: new           #190                // class java/util/LinkedHashSet
      79: dup
      80: aload_1
      81: invokespecial #191                // Method java/util/LinkedHashSet."<init>":(Ljava/util/Collection;)V
      84: areturn

  public java.lang.String getDefaultExtensionName();
    Code:
       0: aload_0
       1: invokespecial #107                // Method getExtensionClasses:()Ljava/util/Map;
       4: pop
       5: aload_0
       6: getfield      #181                // Field cachedDefaultName:Ljava/lang/String;
       9: areturn

  public void addExtension(java.lang.String, java.lang.Class<?>);
    Code:
       0: aload_0
       1: invokespecial #116                // Method checkDestroyed:()V
       4: aload_0
       5: invokespecial #107                // Method getExtensionClasses:()Ljava/util/Map;
       8: pop
       9: aload_0
      10: getfield      #55                 // Field type:Ljava/lang/Class;
      13: aload_2
      14: invokevirtual #192                // Method java/lang/Class.isAssignableFrom:(Ljava/lang/Class;)Z
      17: ifne          59
      20: new           #103                // class java/lang/IllegalStateException
      23: dup
      24: new           #95                 // class java/lang/StringBuilder
      27: dup
      28: invokespecial #96                 // Method java/lang/StringBuilder."<init>":()V
      31: ldc           #193                // String Input type
      33: invokevirtual #98                 // Method java/lang/StringBuilder.append:(Ljava/lang/String;)Ljava/lang/StringBuilder;
      36: aload_2
      37: invokevirtual #99                 // Method java/lang/StringBuilder.append:(Ljava/lang/Object;)Ljava/lang/StringBuilder;
      40: ldc           #194                // String  doesn\'t implement the Extension
      42: invokevirtual #98                 // Method java/lang/StringBuilder.append:(Ljava/lang/String;)Ljava/lang/StringBuilder;
      45: aload_0
      46: getfield      #55                 // Field type:Ljava/lang/Class;
      49: invokevirtual #99                 // Method java/lang/StringBuilder.append:(Ljava/lang/Object;)Ljava/lang/StringBuilder;
      52: invokevirtual #100                // Method java/lang/StringBuilder.toString:()Ljava/lang/String;
      55: invokespecial #105                // Method java/lang/IllegalStateException."<init>":(Ljava/lang/String;)V
      58: athrow
      59: aload_2
      60: invokevirtual #195                // Method java/lang/Class.isInterface:()Z
      63: ifeq          98
      66: new           #103                // class java/lang/IllegalStateException
      69: dup
      70: new           #95                 // class java/lang/StringBuilder
      73: dup
      74: invokespecial #96                 // Method java/lang/StringBuilder."<init>":()V
      77: ldc           #193                // String Input type
      79: invokevirtual #98                 // Method java/lang/StringBuilder.append:(Ljava/lang/String;)Ljava/lang/StringBuilder;
      82: aload_2
      83: invokevirtual #99                 // Method java/lang/StringBuilder.append:(Ljava/lang/Object;)Ljava/lang/StringBuilder;
      86: ldc           #196                // String  can\'t be interface!
      88: invokevirtual #98                 // Method java/lang/StringBuilder.append:(Ljava/lang/String;)Ljava/lang/StringBuilder;
      91: invokevirtual #100                // Method java/lang/StringBuilder.toString:()Ljava/lang/String;
      94: invokespecial #105                // Method java/lang/IllegalStateException."<init>":(Ljava/lang/String;)V
      97: athrow
      98: aload_2
      99: ldc           #197                // class org/apache/dubbo/common/extension/Adaptive
     101: invokevirtual #198                // Method java/lang/Class.isAnnotationPresent:(Ljava/lang/Class;)Z
     104: ifne          245
     107: aload_1
     108: invokestatic  #182                // Method org/apache/dubbo/common/utils/StringUtils.isBlank:(Ljava/lang/CharSequence;)Z
     111: ifeq          149
     114: new           #103                // class java/lang/IllegalStateException
     117: dup
     118: new           #95                 // class java/lang/StringBuilder
     121: dup
     122: invokespecial #96                 // Method java/lang/StringBuilder."<init>":()V
     125: ldc           #199                // String Extension name is blank (Extension
     127: invokevirtual #98                 // Method java/lang/StringBuilder.append:(Ljava/lang/String;)Ljava/lang/StringBuilder;
     130: aload_0
     131: getfield      #55                 // Field type:Ljava/lang/Class;
     134: invokevirtual #99                 // Method java/lang/StringBuilder.append:(Ljava/lang/Object;)Ljava/lang/StringBuilder;
     137: ldc           #200                // String )!
     139: invokevirtual #98                 // Method java/lang/StringBuilder.append:(Ljava/lang/String;)Ljava/lang/StringBuilder;
     142: invokevirtual #100                // Method java/lang/StringBuilder.toString:()Ljava/lang/String;
     145: invokespecial #105                // Method java/lang/IllegalStateException."<init>":(Ljava/lang/String;)V
     148: athrow
     149: aload_0
     150: getfield      #38                 // Field cachedClasses:Lorg/apache/dubbo/common/utils/Holder;
     153: invokevirtual #88                 // Method org/apache/dubbo/common/utils/Holder.get:()Ljava/lang/Object;
     156: checkcast     #201                // class java/util/Map
     159: aload_1
     160: invokeinterface #202,  2          // InterfaceMethod java/util/Map.containsKey:(Ljava/lang/Object;)Z
     165: ifeq          212
     168: new           #103                // class java/lang/IllegalStateException
     171: dup
     172: new           #95                 // class java/lang/StringBuilder
     175: dup
     176: invokespecial #96                 // Method java/lang/StringBuilder."<init>":()V
     179: ldc           #203                // String Extension name
     181: invokevirtual #98                 // Method java/lang/StringBuilder.append:(Ljava/lang/String;)Ljava/lang/StringBuilder;
     184: aload_1
     185: invokevirtual #98                 // Method java/lang/StringBuilder.append:(Ljava/lang/String;)Ljava/lang/StringBuilder;
     188: ldc           #204                // String  already exists (Extension
     190: invokevirtual #98                 // Method java/lang/StringBuilder.append:(Ljava/lang/String;)Ljava/lang/StringBuilder;
     193: aload_0
     194: getfield      #55                 // Field type:Ljava/lang/Class;
     197: invokevirtual #99                 // Method java/lang/StringBuilder.append:(Ljava/lang/Object;)Ljava/lang/StringBuilder;
     200: ldc           #200                // String )!
     202: invokevirtual #98                 // Method java/lang/StringBuilder.append:(Ljava/lang/String;)Ljava/lang/StringBuilder;
     205: invokevirtual #100                // Method java/lang/StringBuilder.toString:()Ljava/lang/String;
     208: invokespecial #105                // Method java/lang/IllegalStateException."<init>":(Ljava/lang/String;)V
     211: athrow
     212: aload_0
     213: getfield      #35                 // Field cachedNames:Ljava/util/concurrent/ConcurrentMap;
     216: aload_2
     217: aload_1
     218: invokeinterface #205,  3          // InterfaceMethod java/util/concurrent/ConcurrentMap.put:(Ljava/lang/Object;Ljava/lang/Object;)Ljava/lang/Object;
     223: pop
     224: aload_0
     225: getfield      #38                 // Field cachedClasses:Lorg/apache/dubbo/common/utils/Holder;
     228: invokevirtual #88                 // Method org/apache/dubbo/common/utils/Holder.get:()Ljava/lang/Object;
     231: checkcast     #201                // class java/util/Map
     234: aload_1
     235: aload_2
     236: invokeinterface #136,  3          // InterfaceMethod java/util/Map.put:(Ljava/lang/Object;Ljava/lang/Object;)Ljava/lang/Object;
     241: pop
     242: goto          292
     245: aload_0
     246: getfield      #47                 // Field cachedAdaptiveClass:Ljava/lang/Class;
     249: ifnull        287
     252: new           #103                // class java/lang/IllegalStateException
     255: dup
     256: new           #95                 // class java/lang/StringBuilder
     259: dup
     260: invokespecial #96                 // Method java/lang/StringBuilder."<init>":()V
     263: ldc           #206                // String Adaptive Extension already exists (Extension
     265: invokevirtual #98                 // Method java/lang/StringBuilder.append:(Ljava/lang/String;)Ljava/lang/StringBuilder;
     268: aload_0
     269: getfield      #55                 // Field type:Ljava/lang/Class;
     272: invokevirtual #99                 // Method java/lang/StringBuilder.append:(Ljava/lang/Object;)Ljava/lang/StringBuilder;
     275: ldc           #200                // String )!
     277: invokevirtual #98                 // Method java/lang/StringBuilder.append:(Ljava/lang/String;)Ljava/lang/StringBuilder;
     280: invokevirtual #100                // Method java/lang/StringBuilder.toString:()Ljava/lang/String;
     283: invokespecial #105                // Method java/lang/IllegalStateException."<init>":(Ljava/lang/String;)V
     286: athrow
     287: aload_0
     288: aload_2
     289: putfield      #47                 // Field cachedAdaptiveClass:Ljava/lang/Class;
     292: return

  public void replaceExtension(java.lang.String, java.lang.Class<?>);
    Code:
       0: aload_0
       1: invokespecial #116                // Method checkDestroyed:()V
       4: aload_0
       5: invokespecial #107                // Method getExtensionClasses:()Ljava/util/Map;
       8: pop
       9: aload_0
      10: getfield      #55                 // Field type:Ljava/lang/Class;
      13: aload_2
      14: invokevirtual #192                // Method java/lang/Class.isAssignableFrom:(Ljava/lang/Class;)Z
      17: ifne          59
      20: new           #103                // class java/lang/IllegalStateException
      23: dup
      24: new           #95                 // class java/lang/StringBuilder
      27: dup
      28: invokespecial #96                 // Method java/lang/StringBuilder."<init>":()V
      31: ldc           #193                // String Input type
      33: invokevirtual #98                 // Method java/lang/StringBuilder.append:(Ljava/lang/String;)Ljava/lang/StringBuilder;
      36: aload_2
      37: invokevirtual #99                 // Method java/lang/StringBuilder.append:(Ljava/lang/Object;)Ljava/lang/StringBuilder;
      40: ldc           #207                // String  doesn\'t implement Extension
      42: invokevirtual #98                 // Method java/lang/StringBuilder.append:(Ljava/lang/String;)Ljava/lang/StringBuilder;
      45: aload_0
      46: getfield      #55                 // Field type:Ljava/lang/Class;
      49: invokevirtual #99                 // Method java/lang/StringBuilder.append:(Ljava/lang/Object;)Ljava/lang/StringBuilder;
      52: invokevirtual #100                // Method java/lang/StringBuilder.toString:()Ljava/lang/String;
      55: invokespecial #105                // Method java/lang/IllegalStateException."<init>":(Ljava/lang/String;)V
      58: athrow
      59: aload_2
      60: invokevirtual #195                // Method java/lang/Class.isInterface:()Z
      63: ifeq          98
      66: new           #103                // class java/lang/IllegalStateException
      69: dup
      70: new           #95                 // class java/lang/StringBuilder
      73: dup
      74: invokespecial #96                 // Method java/lang/StringBuilder."<init>":()V
      77: ldc           #193                // String Input type
      79: invokevirtual #98                 // Method java/lang/StringBuilder.append:(Ljava/lang/String;)Ljava/lang/StringBuilder;
      82: aload_2
      83: invokevirtual #99                 // Method java/lang/StringBuilder.append:(Ljava/lang/Object;)Ljava/lang/StringBuilder;
      86: ldc           #196                // String  can\'t be interface!
      88: invokevirtual #98                 // Method java/lang/StringBuilder.append:(Ljava/lang/String;)Ljava/lang/StringBuilder;
      91: invokevirtual #100                // Method java/lang/StringBuilder.toString:()Ljava/lang/String;
      94: invokespecial #105                // Method java/lang/IllegalStateException."<init>":(Ljava/lang/String;)V
      97: athrow
      98: aload_2
      99: ldc           #197                // class org/apache/dubbo/common/extension/Adaptive
     101: invokevirtual #198                // Method java/lang/Class.isAnnotationPresent:(Ljava/lang/Class;)Z
     104: ifne          256
     107: aload_1
     108: invokestatic  #182                // Method org/apache/dubbo/common/utils/StringUtils.isBlank:(Ljava/lang/CharSequence;)Z
     111: ifeq          149
     114: new           #103                // class java/lang/IllegalStateException
     117: dup
     118: new           #95                 // class java/lang/StringBuilder
     121: dup
     122: invokespecial #96                 // Method java/lang/StringBuilder."<init>":()V
     125: ldc           #199                // String Extension name is blank (Extension
     127: invokevirtual #98                 // Method java/lang/StringBuilder.append:(Ljava/lang/String;)Ljava/lang/StringBuilder;
     130: aload_0
     131: getfield      #55                 // Field type:Ljava/lang/Class;
     134: invokevirtual #99                 // Method java/lang/StringBuilder.append:(Ljava/lang/Object;)Ljava/lang/StringBuilder;
     137: ldc           #200                // String )!
     139: invokevirtual #98                 // Method java/lang/StringBuilder.append:(Ljava/lang/String;)Ljava/lang/StringBuilder;
     142: invokevirtual #100                // Method java/lang/StringBuilder.toString:()Ljava/lang/String;
     145: invokespecial #105                // Method java/lang/IllegalStateException."<init>":(Ljava/lang/String;)V
     148: athrow
     149: aload_0
     150: getfield      #38                 // Field cachedClasses:Lorg/apache/dubbo/common/utils/Holder;
     153: invokevirtual #88                 // Method org/apache/dubbo/common/utils/Holder.get:()Ljava/lang/Object;
     156: checkcast     #201                // class java/util/Map
     159: aload_1
     160: invokeinterface #202,  2          // InterfaceMethod java/util/Map.containsKey:(Ljava/lang/Object;)Z
     165: ifne          212
     168: new           #103                // class java/lang/IllegalStateException
     171: dup
     172: new           #95                 // class java/lang/StringBuilder
     175: dup
     176: invokespecial #96                 // Method java/lang/StringBuilder."<init>":()V
     179: ldc           #203                // String Extension name
     181: invokevirtual #98                 // Method java/lang/StringBuilder.append:(Ljava/lang/String;)Ljava/lang/StringBuilder;
     184: aload_1
     185: invokevirtual #98                 // Method java/lang/StringBuilder.append:(Ljava/lang/String;)Ljava/lang/StringBuilder;
     188: ldc           #208                // String  doesn\'t exist (Extension
     190: invokevirtual #98                 // Method java/lang/StringBuilder.append:(Ljava/lang/String;)Ljava/lang/StringBuilder;
     193: aload_0
     194: getfield      #55                 // Field type:Ljava/lang/Class;
     197: invokevirtual #99                 // Method java/lang/StringBuilder.append:(Ljava/lang/Object;)Ljava/lang/StringBuilder;
     200: ldc           #200                // String )!
     202: invokevirtual #98                 // Method java/lang/StringBuilder.append:(Ljava/lang/String;)Ljava/lang/StringBuilder;
     205: invokevirtual #100                // Method java/lang/StringBuilder.toString:()Ljava/lang/String;
     208: invokespecial #105                // Method java/lang/IllegalStateException."<init>":(Ljava/lang/String;)V
     211: athrow
     212: aload_0
     213: getfield      #35                 // Field cachedNames:Ljava/util/concurrent/ConcurrentMap;
     216: aload_2
     217: aload_1
     218: invokeinterface #205,  3          // InterfaceMethod java/util/concurrent/ConcurrentMap.put:(Ljava/lang/Object;Ljava/lang/Object;)Ljava/lang/Object;
     223: pop
     224: aload_0
     225: getfield      #38                 // Field cachedClasses:Lorg/apache/dubbo/common/utils/Holder;
     228: invokevirtual #88                 // Method org/apache/dubbo/common/utils/Holder.get:()Ljava/lang/Object;
     231: checkcast     #201                // class java/util/Map
     234: aload_1
     235: aload_2
     236: invokeinterface #136,  3          // InterfaceMethod java/util/Map.put:(Ljava/lang/Object;Ljava/lang/Object;)Ljava/lang/Object;
     241: pop
     242: aload_0
     243: getfield      #45                 // Field cachedInstances:Ljava/util/concurrent/ConcurrentMap;
     246: aload_1
     247: invokeinterface #209,  2          // InterfaceMethod java/util/concurrent/ConcurrentMap.remove:(Ljava/lang/Object;)Ljava/lang/Object;
     252: pop
     253: goto          311
     256: aload_0
     257: getfield      #47                 // Field cachedAdaptiveClass:Ljava/lang/Class;
     260: ifnonnull     298
     263: new           #103                // class java/lang/IllegalStateException
     266: dup
     267: new           #95                 // class java/lang/StringBuilder
     270: dup
     271: invokespecial #96                 // Method java/lang/StringBuilder."<init>":()V
     274: ldc           #210                // String Adaptive Extension doesn\'t exist (Extension
     276: invokevirtual #98                 // Method java/lang/StringBuilder.append:(Ljava/lang/String;)Ljava/lang/StringBuilder;
     279: aload_0
     280: getfield      #55                 // Field type:Ljava/lang/Class;
     283: invokevirtual #99                 // Method java/lang/StringBuilder.append:(Ljava/lang/Object;)Ljava/lang/StringBuilder;
     286: ldc           #200                // String )!
     288: invokevirtual #98                 // Method java/lang/StringBuilder.append:(Ljava/lang/String;)Ljava/lang/StringBuilder;
     291: invokevirtual #100                // Method java/lang/StringBuilder.toString:()Ljava/lang/String;
     294: invokespecial #105                // Method java/lang/IllegalStateException."<init>":(Ljava/lang/String;)V
     297: athrow
     298: aload_0
     299: aload_2
     300: putfield      #47                 // Field cachedAdaptiveClass:Ljava/lang/Class;
     303: aload_0
     304: getfield      #46                 // Field cachedAdaptiveInstance:Lorg/apache/dubbo/common/utils/Holder;
     307: aconst_null
     308: invokevirtual #180                // Method org/apache/dubbo/common/utils/Holder.set:(Ljava/lang/Object;)V
     311: return

  public T getAdaptiveExtension();
    Code:
       0: aload_0
       1: invokespecial #116                // Method checkDestroyed:()V
       4: aload_0
       5: getfield      #46                 // Field cachedAdaptiveInstance:Lorg/apache/dubbo/common/utils/Holder;
       8: invokevirtual #88                 // Method org/apache/dubbo/common/utils/Holder.get:()Ljava/lang/Object;
      11: astore_1
      12: aload_1
      13: ifnonnull     144
      16: aload_0
      17: getfield      #211                // Field createAdaptiveInstanceError:Ljava/lang/Throwable;
      20: ifnull        60
      23: new           #103                // class java/lang/IllegalStateException
      26: dup
      27: new           #95                 // class java/lang/StringBuilder
      30: dup
      31: invokespecial #96                 // Method java/lang/StringBuilder."<init>":()V
      34: ldc           #212                // String Failed to create adaptive instance:
      36: invokevirtual #98                 // Method java/lang/StringBuilder.append:(Ljava/lang/String;)Ljava/lang/StringBuilder;
      39: aload_0
      40: getfield      #211                // Field createAdaptiveInstanceError:Ljava/lang/Throwable;
      43: invokevirtual #213                // Method java/lang/Throwable.toString:()Ljava/lang/String;
      46: invokevirtual #98                 // Method java/lang/StringBuilder.append:(Ljava/lang/String;)Ljava/lang/StringBuilder;
      49: invokevirtual #100                // Method java/lang/StringBuilder.toString:()Ljava/lang/String;
      52: aload_0
      53: getfield      #211                // Field createAdaptiveInstanceError:Ljava/lang/Throwable;
      56: invokespecial #214                // Method java/lang/IllegalStateException."<init>":(Ljava/lang/String;Ljava/lang/Throwable;)V
      59: athrow
      60: aload_0
      61: getfield      #46                 // Field cachedAdaptiveInstance:Lorg/apache/dubbo/common/utils/Holder;
      64: dup
      65: astore_2
      66: monitorenter
      67: aload_0
      68: getfield      #46                 // Field cachedAdaptiveInstance:Lorg/apache/dubbo/common/utils/Holder;
      71: invokevirtual #88                 // Method org/apache/dubbo/common/utils/Holder.get:()Ljava/lang/Object;
      74: astore_1
      75: aload_1
      76: ifnonnull     132
      79: aload_0
      80: invokespecial #215                // Method createAdaptiveExtension:()Ljava/lang/Object;
      83: astore_1
      84: aload_0
      85: getfield      #46                 // Field cachedAdaptiveInstance:Lorg/apache/dubbo/common/utils/Holder;
      88: aload_1
      89: invokevirtual #180                // Method org/apache/dubbo/common/utils/Holder.set:(Ljava/lang/Object;)V
      92: goto          132
      95: astore_3
      96: aload_0
      97: aload_3
      98: putfield      #211                // Field createAdaptiveInstanceError:Ljava/lang/Throwable;
     101: new           #103                // class java/lang/IllegalStateException
     104: dup
     105: new           #95                 // class java/lang/StringBuilder
     108: dup
     109: invokespecial #96                 // Method java/lang/StringBuilder."<init>":()V
     112: ldc           #212                // String Failed to create adaptive instance:
     114: invokevirtual #98                 // Method java/lang/StringBuilder.append:(Ljava/lang/String;)Ljava/lang/StringBuilder;
     117: aload_3
     118: invokevirtual #213                // Method java/lang/Throwable.toString:()Ljava/lang/String;
     121: invokevirtual #98                 // Method java/lang/StringBuilder.append:(Ljava/lang/String;)Ljava/lang/StringBuilder;
     124: invokevirtual #100                // Method java/lang/StringBuilder.toString:()Ljava/lang/String;
     127: aload_3
     128: invokespecial #214                // Method java/lang/IllegalStateException."<init>":(Ljava/lang/String;Ljava/lang/Throwable;)V
     131: athrow
     132: aload_2
     133: monitorexit
     134: goto          144
     137: astore        4
     139: aload_2
     140: monitorexit
     141: aload         4
     143: athrow
     144: aload_1
     145: areturn
    Exception table:
       from    to  target type
          79    92    95   Class java/lang/Throwable
          67   134   137   any
         137   141   137   any

  private java.lang.IllegalStateException findException(java.lang.String);
    Code:
       0: new           #95                 // class java/lang/StringBuilder
       3: dup
       4: new           #95                 // class java/lang/StringBuilder
       7: dup
       8: invokespecial #96                 // Method java/lang/StringBuilder."<init>":()V
      11: ldc           #217                // String No such extension
      13: invokevirtual #98                 // Method java/lang/StringBuilder.append:(Ljava/lang/String;)Ljava/lang/StringBuilder;
      16: aload_0
      17: getfield      #55                 // Field type:Ljava/lang/Class;
      20: invokevirtual #218                // Method java/lang/Class.getName:()Ljava/lang/String;
      23: invokevirtual #98                 // Method java/lang/StringBuilder.append:(Ljava/lang/String;)Ljava/lang/StringBuilder;
      26: ldc           #219                // String  by name
      28: invokevirtual #98                 // Method java/lang/StringBuilder.append:(Ljava/lang/String;)Ljava/lang/StringBuilder;
      31: aload_1
      32: invokevirtual #98                 // Method java/lang/StringBuilder.append:(Ljava/lang/String;)Ljava/lang/StringBuilder;
      35: invokevirtual #100                // Method java/lang/StringBuilder.toString:()Ljava/lang/String;
      38: invokespecial #220                // Method java/lang/StringBuilder."<init>":(Ljava/lang/String;)V
      41: astore_2
      42: iconst_1
      43: istore_3
      44: aload_0
      45: getfield      #48                 // Field exceptions:Ljava/util/Map;
      48: invokeinterface #125,  1          // InterfaceMethod java/util/Map.entrySet:()Ljava/util/Set;
      53: invokeinterface #126,  1          // InterfaceMethod java/util/Set.iterator:()Ljava/util/Iterator;
      58: astore        4
      60: aload         4
      62: invokeinterface #86,  1           // InterfaceMethod java/util/Iterator.hasNext:()Z
      67: ifeq          183
      70: aload         4
      72: invokeinterface #87,  1           // InterfaceMethod java/util/Iterator.next:()Ljava/lang/Object;
      77: checkcast     #127                // class java/util/Map$Entry
      80: astore        5
      82: aload         5
      84: invokeinterface #128,  1          // InterfaceMethod java/util/Map$Entry.getKey:()Ljava/lang/Object;
      89: checkcast     #109                // class java/lang/String
      92: invokevirtual #221                // Method java/lang/String.toLowerCase:()Ljava/lang/String;
      95: aload_1
      96: invokevirtual #221                // Method java/lang/String.toLowerCase:()Ljava/lang/String;
      99: invokevirtual #147                // Method java/lang/String.startsWith:(Ljava/lang/String;)Z
     102: ifeq          180
     105: iload_3
     106: iconst_1
     107: if_icmpne     117
     110: aload_2
     111: ldc           #222                // String , possible causes:
     113: invokevirtual #98                 // Method java/lang/StringBuilder.append:(Ljava/lang/String;)Ljava/lang/StringBuilder;
     116: pop
     117: aload_2
     118: ldc           #223                // String \r\n(
     120: invokevirtual #98                 // Method java/lang/StringBuilder.append:(Ljava/lang/String;)Ljava/lang/StringBuilder;
     123: pop
     124: aload_2
     125: iload_3
     126: iinc          3, 1
     129: invokevirtual #224                // Method java/lang/StringBuilder.append:(I)Ljava/lang/StringBuilder;
     132: pop
     133: aload_2
     134: ldc           #225                // String )
     136: invokevirtual #98                 // Method java/lang/StringBuilder.append:(Ljava/lang/String;)Ljava/lang/StringBuilder;
     139: pop
     140: aload_2
     141: aload         5
     143: invokeinterface #128,  1          // InterfaceMethod java/util/Map$Entry.getKey:()Ljava/lang/Object;
     148: checkcast     #109                // class java/lang/String
     151: invokevirtual #98                 // Method java/lang/StringBuilder.append:(Ljava/lang/String;)Ljava/lang/StringBuilder;
     154: pop
     155: aload_2
     156: ldc           #226                // String :\r\n
     158: invokevirtual #98                 // Method java/lang/StringBuilder.append:(Ljava/lang/String;)Ljava/lang/StringBuilder;
     161: pop
     162: aload_2
     163: aload         5
     165: invokeinterface #129,  1          // InterfaceMethod java/util/Map$Entry.getValue:()Ljava/lang/Object;
     170: checkcast     #216                // class java/lang/Throwable
     173: invokestatic  #227                // Method org/apache/dubbo/common/utils/StringUtils.toString:(Ljava/lang/Throwable;)Ljava/lang/String;
     176: invokevirtual #98                 // Method java/lang/StringBuilder.append:(Ljava/lang/String;)Ljava/lang/StringBuilder;
     179: pop
     180: goto          60
     183: iload_3
     184: iconst_1
     185: if_icmpne     195
     188: aload_2
     189: ldc           #228                // String , no related exception was found, please check whether related SPI module is missing.
     191: invokevirtual #98                 // Method java/lang/StringBuilder.append:(Ljava/lang/String;)Ljava/lang/StringBuilder;
     194: pop
     195: new           #103                // class java/lang/IllegalStateException
     198: dup
     199: aload_2
     200: invokevirtual #100                // Method java/lang/StringBuilder.toString:()Ljava/lang/String;
     203: invokespecial #105                // Method java/lang/IllegalStateException."<init>":(Ljava/lang/String;)V
     206: areturn

  private T createExtension(java.lang.String, boolean);
    Code:
       0: aload_0
       1: invokespecial #107                // Method getExtensionClasses:()Ljava/util/Map;
       4: aload_1
       5: invokeinterface #229,  2          // InterfaceMethod java/util/Map.get:(Ljava/lang/Object;)Ljava/lang/Object;
      10: checkcast     #230                // class java/lang/Class
      13: astore_3
      14: aload_3
      15: ifnull        31
      18: aload_0
      19: getfield      #51                 // Field unacceptableExceptions:Ljava/util/Set;
      22: aload_1
      23: invokeinterface #123,  2          // InterfaceMethod java/util/Set.contains:(Ljava/lang/Object;)Z
      28: ifeq          37
      31: aload_0
      32: aload_1
      33: invokespecial #231                // Method findException:(Ljava/lang/String;)Ljava/lang/IllegalStateException;
      36: athrow
      37: aload_0
      38: getfield      #34                 // Field extensionInstances:Ljava/util/concurrent/ConcurrentMap;
      41: aload_3
      42: invokeinterface #108,  2          // InterfaceMethod java/util/concurrent/ConcurrentMap.get:(Ljava/lang/Object;)Ljava/lang/Object;
      47: astore        4
      49: aload         4
      51: ifnonnull     107
      54: aload_0
      55: getfield      #34                 // Field extensionInstances:Ljava/util/concurrent/ConcurrentMap;
      58: aload_3
      59: aload_0
      60: aload_3
      61: invokespecial #232                // Method createExtensionInstance:(Ljava/lang/Class;)Ljava/lang/Object;
      64: invokeinterface #167,  3          // InterfaceMethod java/util/concurrent/ConcurrentMap.putIfAbsent:(Ljava/lang/Object;Ljava/lang/Object;)Ljava/lang/Object;
      69: pop
      70: aload_0
      71: getfield      #34                 // Field extensionInstances:Ljava/util/concurrent/ConcurrentMap;
      74: aload_3
      75: invokeinterface #108,  2          // InterfaceMethod java/util/concurrent/ConcurrentMap.get:(Ljava/lang/Object;)Ljava/lang/Object;
      80: astore        4
      82: aload_0
      83: aload         4
      85: aload_1
      86: invokespecial #233                // Method postProcessBeforeInitialization:(Ljava/lang/Object;Ljava/lang/String;)Ljava/lang/Object;
      89: astore        4
      91: aload_0
      92: aload         4
      94: invokespecial #234                // Method injectExtension:(Ljava/lang/Object;)Ljava/lang/Object;
      97: pop
      98: aload_0
      99: aload         4
     101: aload_1
     102: invokespecial #235                // Method postProcessAfterInitialization:(Ljava/lang/Object;Ljava/lang/String;)Ljava/lang/Object;
     105: astore        4
     107: iload_2
     108: ifeq          309
     111: new           #21                 // class java/util/ArrayList
     114: dup
     115: invokespecial #22                 // Method java/util/ArrayList."<init>":()V
     118: astore        5
     120: aload_0
     121: getfield      #236                // Field cachedWrapperClasses:Ljava/util/Set;
     124: ifnull        154
     127: aload         5
     129: aload_0
     130: getfield      #236                // Field cachedWrapperClasses:Ljava/util/Set;
     133: invokeinterface #159,  2          // InterfaceMethod java/util/List.addAll:(Ljava/util/Collection;)Z
     138: pop
     139: aload         5
     141: getstatic     #237                // Field org/apache/dubbo/common/extension/support/WrapperComparator.COMPARATOR:Ljava/util/Comparator;
     144: invokeinterface #189,  2          // InterfaceMethod java/util/List.sort:(Ljava/util/Comparator;)V
     149: aload         5
     151: invokestatic  #238                // Method java/util/Collections.reverse:(Ljava/util/List;)V
     154: aload         5
     156: invokestatic  #160                // Method org/apache/dubbo/common/utils/CollectionUtils.isNotEmpty:(Ljava/util/Collection;)Z
     159: ifeq          309
     162: aload         5
     164: invokeinterface #145,  1          // InterfaceMethod java/util/List.iterator:()Ljava/util/Iterator;
     169: astore        6
     171: aload         6
     173: invokeinterface #86,  1           // InterfaceMethod java/util/Iterator.hasNext:()Z
     178: ifeq          309
     181: aload         6
     183: invokeinterface #87,  1           // InterfaceMethod java/util/Iterator.next:()Ljava/lang/Object;
     188: checkcast     #230                // class java/lang/Class
     191: astore        7
     193: aload         7
     195: ldc           #239                // class org/apache/dubbo/common/extension/Wrapper
     197: invokevirtual #240                // Method java/lang/Class.getAnnotation:(Ljava/lang/Class;)Ljava/lang/annotation/Annotation;
     200: checkcast     #239                // class org/apache/dubbo/common/extension/Wrapper
     203: astore        8
     205: aload         8
     207: ifnull        251
     210: aload         8
     212: invokeinterface #241,  1          // InterfaceMethod org/apache/dubbo/common/extension/Wrapper.matches:()[Ljava/lang/String;
     217: invokestatic  #242                // Method org/apache/dubbo/common/utils/ArrayUtils.isEmpty:([Ljava/lang/Object;)Z
     220: ifne          237
     223: aload         8
     225: invokeinterface #241,  1          // InterfaceMethod org/apache/dubbo/common/extension/Wrapper.matches:()[Ljava/lang/String;
     230: aload_1
     231: invokestatic  #243                // Method org/apache/dubbo/common/utils/ArrayUtils.contains:([Ljava/lang/String;Ljava/lang/String;)Z
     234: ifeq          255
     237: aload         8
     239: invokeinterface #244,  1          // InterfaceMethod org/apache/dubbo/common/extension/Wrapper.mismatches:()[Ljava/lang/String;
     244: aload_1
     245: invokestatic  #243                // Method org/apache/dubbo/common/utils/ArrayUtils.contains:([Ljava/lang/String;Ljava/lang/String;)Z
     248: ifne          255
     251: iconst_1
     252: goto          256
     255: iconst_0
     256: istore        9
     258: iload         9
     260: ifeq          306
     263: aload_0
     264: aload         7
     266: iconst_1
     267: anewarray     #230                // class java/lang/Class
     270: dup
     271: iconst_0
     272: aload_0
     273: getfield      #55                 // Field type:Ljava/lang/Class;
     276: aastore
     277: invokevirtual #245                // Method java/lang/Class.getConstructor:([Ljava/lang/Class;)Ljava/lang/reflect/Constructor;
     280: iconst_1
     281: anewarray     #246                // class java/lang/Object
     284: dup
     285: iconst_0
     286: aload         4
     288: aastore
     289: invokevirtual #247                // Method java/lang/reflect/Constructor.newInstance:([Ljava/lang/Object;)Ljava/lang/Object;
     292: invokespecial #234                // Method injectExtension:(Ljava/lang/Object;)Ljava/lang/Object;
     295: astore        4
     297: aload_0
     298: aload         4
     300: aload_1
     301: invokespecial #235                // Method postProcessAfterInitialization:(Ljava/lang/Object;Ljava/lang/String;)Ljava/lang/Object;
     304: astore        4
     306: goto          171
     309: aload_0
     310: aload         4
     312: invokespecial #248                // Method initExtension:(Ljava/lang/Object;)V
     315: aload         4
     317: areturn
     318: astore        4
     320: new           #103                // class java/lang/IllegalStateException
     323: dup
     324: new           #95                 // class java/lang/StringBuilder
     327: dup
     328: invokespecial #96                 // Method java/lang/StringBuilder."<init>":()V
     331: ldc           #249                // String Extension instance (name:
     333: invokevirtual #98                 // Method java/lang/StringBuilder.append:(Ljava/lang/String;)Ljava/lang/StringBuilder;
     336: aload_1
     337: invokevirtual #98                 // Method java/lang/StringBuilder.append:(Ljava/lang/String;)Ljava/lang/StringBuilder;
     340: ldc           #250                // String , class:
     342: invokevirtual #98                 // Method java/lang/StringBuilder.append:(Ljava/lang/String;)Ljava/lang/StringBuilder;
     345: aload_0
     346: getfield      #55                 // Field type:Ljava/lang/Class;
     349: invokevirtual #99                 // Method java/lang/StringBuilder.append:(Ljava/lang/Object;)Ljava/lang/StringBuilder;
     352: ldc           #251                // String ) couldn\'t be instantiated:
     354: invokevirtual #98                 // Method java/lang/StringBuilder.append:(Ljava/lang/String;)Ljava/lang/StringBuilder;
     357: aload         4
     359: invokevirtual #252                // Method java/lang/Throwable.getMessage:()Ljava/lang/String;
     362: invokevirtual #98                 // Method java/lang/StringBuilder.append:(Ljava/lang/String;)Ljava/lang/StringBuilder;
     365: invokevirtual #100                // Method java/lang/StringBuilder.toString:()Ljava/lang/String;
     368: aload         4
     370: invokespecial #214                // Method java/lang/IllegalStateException."<init>":(Ljava/lang/String;Ljava/lang/Throwable;)V
     373: athrow
    Exception table:
       from    to  target type
          37   317   318   Class java/lang/Throwable

  private java.lang.Object createExtensionInstance(java.lang.Class<?>) throws java.lang.ReflectiveOperationException;
    Code:
       0: aload_0
       1: getfield      #76                 // Field instantiationStrategy:Lorg/apache/dubbo/common/beans/support/InstantiationStrategy;
       4: aload_1
       5: invokevirtual #253                // Method org/apache/dubbo/common/beans/support/InstantiationStrategy.instantiate:(Ljava/lang/Class;)Ljava/lang/Object;
       8: areturn

  private T postProcessBeforeInitialization(T, java.lang.String) throws java.lang.Exception;
    Code:
       0: aload_0
       1: getfield      #58                 // Field extensionPostProcessors:Ljava/util/List;
       4: ifnull        50
       7: aload_0
       8: getfield      #58                 // Field extensionPostProcessors:Ljava/util/List;
      11: invokeinterface #145,  1          // InterfaceMethod java/util/List.iterator:()Ljava/util/Iterator;
      16: astore_3
      17: aload_3
      18: invokeinterface #86,  1           // InterfaceMethod java/util/Iterator.hasNext:()Z
      23: ifeq          50
      26: aload_3
      27: invokeinterface #87,  1           // InterfaceMethod java/util/Iterator.next:()Ljava/lang/Object;
      32: checkcast     #254                // class org/apache/dubbo/common/extension/ExtensionPostProcessor
      35: astore        4
      37: aload         4
      39: aload_1
      40: aload_2
      41: invokeinterface #255,  3          // InterfaceMethod org/apache/dubbo/common/extension/ExtensionPostProcessor.postProcessBeforeInitialization:(Ljava/lang/Object;Ljava/lang/String;)Ljava/lang/Object;
      46: astore_1
      47: goto          17
      50: aload_1
      51: areturn

  private T postProcessAfterInitialization(T, java.lang.String) throws java.lang.Exception;
    Code:
       0: aload_1
       1: instanceof    #31                 // class org/apache/dubbo/common/extension/ExtensionAccessorAware
       4: ifeq          20
       7: aload_1
       8: checkcast     #31                 // class org/apache/dubbo/common/extension/ExtensionAccessorAware
      11: aload_0
      12: getfield      #56                 // Field extensionDirector:Lorg/apache/dubbo/common/extension/ExtensionDirector;
      15: invokeinterface #256,  2          // InterfaceMethod org/apache/dubbo/common/extension/ExtensionAccessorAware.setExtensionAccessor:(Lorg/apache/dubbo/common/extension/ExtensionAccessor;)V
      20: aload_0
      21: getfield      #58                 // Field extensionPostProcessors:Ljava/util/List;
      24: ifnull        70
      27: aload_0
      28: getfield      #58                 // Field extensionPostProcessors:Ljava/util/List;
      31: invokeinterface #145,  1          // InterfaceMethod java/util/List.iterator:()Ljava/util/Iterator;
      36: astore_3
      37: aload_3
      38: invokeinterface #86,  1           // InterfaceMethod java/util/Iterator.hasNext:()Z
      43: ifeq          70
      46: aload_3
      47: invokeinterface #87,  1           // InterfaceMethod java/util/Iterator.next:()Ljava/lang/Object;
      52: checkcast     #254                // class org/apache/dubbo/common/extension/ExtensionPostProcessor
      55: astore        4
      57: aload         4
      59: aload_1
      60: aload_2
      61: invokeinterface #257,  3          // InterfaceMethod org/apache/dubbo/common/extension/ExtensionPostProcessor.postProcessAfterInitialization:(Ljava/lang/Object;Ljava/lang/String;)Ljava/lang/Object;
      66: astore_1
      67: goto          37
      70: aload_1
      71: areturn

  private boolean containsExtension(java.lang.String);
    Code:
       0: aload_0
       1: invokespecial #107                // Method getExtensionClasses:()Ljava/util/Map;
       4: aload_1
       5: invokeinterface #202,  2          // InterfaceMethod java/util/Map.containsKey:(Ljava/lang/Object;)Z
      10: ireturn

  private T injectExtension(T);
    Code:
       0: aload_0
       1: getfield      #63                 // Field injector:Lorg/apache/dubbo/common/extension/ExtensionInjector;
       4: ifnonnull     9
       7: aload_1
       8: areturn
       9: aload_1
      10: invokevirtual #28                 // Method java/lang/Object.getClass:()Ljava/lang/Class;
      13: invokevirtual #24                 // Method java/lang/Class.getMethods:()[Ljava/lang/reflect/Method;
      16: astore_2
      17: aload_2
      18: arraylength
      19: istore_3
      20: iconst_0
      21: istore        4
      23: iload         4
      25: iload_3
      26: if_icmpge     252
      29: aload_2
      30: iload         4
      32: aaload
      33: astore        5
      35: aload_0
      36: aload         5
      38: invokespecial #258                // Method isSetter:(Ljava/lang/reflect/Method;)Z
      41: ifne          47
      44: goto          246
      47: aload         5
      49: ldc_w         #259                // class org/apache/dubbo/common/extension/DisableInject
      52: invokevirtual #260                // Method java/lang/reflect/Method.isAnnotationPresent:(Ljava/lang/Class;)Z
      55: ifeq          61
      58: goto          246
      61: aload         5
      63: invokevirtual #261                // Method java/lang/reflect/Method.getDeclaringClass:()Ljava/lang/Class;
      66: ldc           #23                 // class org/apache/dubbo/rpc/model/ScopeModelAware
      68: if_acmpne     74
      71: goto          246
      74: aload_1
      75: instanceof    #23                 // class org/apache/dubbo/rpc/model/ScopeModelAware
      78: ifne          88
      81: aload_1
      82: instanceof    #31                 // class org/apache/dubbo/common/extension/ExtensionAccessorAware
      85: ifeq          107
      88: getstatic     #262                // Field ignoredInjectMethodsDesc:Ljava/util/List;
      91: aload         5
      93: invokestatic  #263                // Method org/apache/dubbo/common/utils/ReflectUtils.getDesc:(Ljava/lang/reflect/Method;)Ljava/lang/String;
      96: invokeinterface #264,  2          // InterfaceMethod java/util/List.contains:(Ljava/lang/Object;)Z
     101: ifeq          107
     104: goto          246
     107: aload         5
     109: invokevirtual #265                // Method java/lang/reflect/Method.getParameterTypes:()[Ljava/lang/Class;
     112: iconst_0
     113: aaload
     114: astore        6
     116: aload         6
     118: invokestatic  #266                // Method org/apache/dubbo/common/utils/ReflectUtils.isPrimitives:(Ljava/lang/Class;)Z
     121: ifeq          127
     124: goto          246
     127: aload_0
     128: aload         5
     130: invokespecial #267                // Method getSetterProperty:(Ljava/lang/reflect/Method;)Ljava/lang/String;
     133: astore        7
     135: aload_0
     136: getfield      #63                 // Field injector:Lorg/apache/dubbo/common/extension/ExtensionInjector;
     139: aload         6
     141: aload         7
     143: invokeinterface #268,  3          // InterfaceMethod org/apache/dubbo/common/extension/ExtensionInjector.getInstance:(Ljava/lang/Class;Ljava/lang/String;)Ljava/lang/Object;
     148: astore        8
     150: aload         8
     152: ifnull        171
     155: aload         5
     157: aload_1
     158: iconst_1
     159: anewarray     #246                // class java/lang/Object
     162: dup
     163: iconst_0
     164: aload         8
     166: aastore
     167: invokevirtual #269                // Method java/lang/reflect/Method.invoke:(Ljava/lang/Object;[Ljava/lang/Object;)Ljava/lang/Object;
     170: pop
     171: goto          246
     174: astore        7
     176: getstatic     #92                 // Field logger:Lorg/apache/dubbo/common/logger/ErrorTypeAwareLogger;
     179: ldc           #93                 // String 0-15
     181: ldc           #94                 // String
     183: ldc           #94                 // String
     185: new           #95                 // class java/lang/StringBuilder
     188: dup
     189: invokespecial #96                 // Method java/lang/StringBuilder."<init>":()V
     192: ldc_w         #270                // String Failed to inject via method
     195: invokevirtual #98                 // Method java/lang/StringBuilder.append:(Ljava/lang/String;)Ljava/lang/StringBuilder;
     198: aload         5
     200: invokevirtual #271                // Method java/lang/reflect/Method.getName:()Ljava/lang/String;
     203: invokevirtual #98                 // Method java/lang/StringBuilder.append:(Ljava/lang/String;)Ljava/lang/StringBuilder;
     206: ldc_w         #272                // String  of interface
     209: invokevirtual #98                 // Method java/lang/StringBuilder.append:(Ljava/lang/String;)Ljava/lang/StringBuilder;
     212: aload_0
     213: getfield      #55                 // Field type:Ljava/lang/Class;
     216: invokevirtual #218                // Method java/lang/Class.getName:()Ljava/lang/String;
     219: invokevirtual #98                 // Method java/lang/StringBuilder.append:(Ljava/lang/String;)Ljava/lang/StringBuilder;
     222: ldc_w         #273                // String :
     225: invokevirtual #98                 // Method java/lang/StringBuilder.append:(Ljava/lang/String;)Ljava/lang/StringBuilder;
     228: aload         7
     230: invokevirtual #274                // Method java/lang/Exception.getMessage:()Ljava/lang/String;
     233: invokevirtual #98                 // Method java/lang/StringBuilder.append:(Ljava/lang/String;)Ljava/lang/StringBuilder;
     236: invokevirtual #100                // Method java/lang/StringBuilder.toString:()Ljava/lang/String;
     239: aload         7
     241: invokeinterface #101,  6          // InterfaceMethod org/apache/dubbo/common/logger/ErrorTypeAwareLogger.error:(Ljava/lang/String;Ljava/lang/String;Ljava/lang/String;Ljava/lang/String;Ljava/lang/Throwable;)V
     246: iinc          4, 1
     249: goto          23
     252: goto          275
     255: astore_2
     256: getstatic     #92                 // Field logger:Lorg/apache/dubbo/common/logger/ErrorTypeAwareLogger;
     259: ldc           #93                 // String 0-15
     261: ldc           #94                 // String
     263: ldc           #94                 // String
     265: aload_2
     266: invokevirtual #274                // Method java/lang/Exception.getMessage:()Ljava/lang/String;
     269: aload_2
     270: invokeinterface #101,  6          // InterfaceMethod org/apache/dubbo/common/logger/ErrorTypeAwareLogger.error:(Ljava/lang/String;Ljava/lang/String;Ljava/lang/String;Ljava/lang/String;Ljava/lang/Throwable;)V
     275: aload_1
     276: areturn
    Exception table:
       from    to  target type
         127   171   174   Class java/lang/Exception
           9   252   255   Class java/lang/Exception

  private void initExtension(T);
    Code:
       0: aload_1
       1: instanceof    #275                // class org/apache/dubbo/common/context/Lifecycle
       4: ifeq          18
       7: aload_1
       8: checkcast     #275                // class org/apache/dubbo/common/context/Lifecycle
      11: astore_2
      12: aload_2
      13: invokeinterface #276,  1          // InterfaceMethod org/apache/dubbo/common/context/Lifecycle.initialize:()V
      18: return

  private java.lang.String getSetterProperty(java.lang.reflect.Method);
    Code:
       0: aload_1
       1: invokevirtual #271                // Method java/lang/reflect/Method.getName:()Ljava/lang/String;
       4: invokevirtual #277                // Method java/lang/String.length:()I
       7: iconst_3
       8: if_icmple     50
      11: new           #95                 // class java/lang/StringBuilder
      14: dup
      15: invokespecial #96                 // Method java/lang/StringBuilder."<init>":()V
      18: aload_1
      19: invokevirtual #271                // Method java/lang/reflect/Method.getName:()Ljava/lang/String;
      22: iconst_3
      23: iconst_4
      24: invokevirtual #278                // Method java/lang/String.substring:(II)Ljava/lang/String;
      27: invokevirtual #221                // Method java/lang/String.toLowerCase:()Ljava/lang/String;
      30: invokevirtual #98                 // Method java/lang/StringBuilder.append:(Ljava/lang/String;)Ljava/lang/StringBuilder;
      33: aload_1
      34: invokevirtual #271                // Method java/lang/reflect/Method.getName:()Ljava/lang/String;
      37: iconst_4
      38: invokevirtual #279                // Method java/lang/String.substring:(I)Ljava/lang/String;
      41: invokevirtual #98                 // Method java/lang/StringBuilder.append:(Ljava/lang/String;)Ljava/lang/StringBuilder;
      44: invokevirtual #100                // Method java/lang/StringBuilder.toString:()Ljava/lang/String;
      47: goto          52
      50: ldc           #94                 // String
      52: areturn

  private boolean isSetter(java.lang.reflect.Method);
    Code:
       0: aload_1
       1: invokevirtual #271                // Method java/lang/reflect/Method.getName:()Ljava/lang/String;
       4: ldc_w         #280                // String set
       7: invokevirtual #147                // Method java/lang/String.startsWith:(Ljava/lang/String;)Z
      10: ifeq          36
      13: aload_1
      14: invokevirtual #265                // Method java/lang/reflect/Method.getParameterTypes:()[Ljava/lang/Class;
      17: arraylength
      18: iconst_1
      19: if_icmpne     36
      22: aload_1
      23: invokevirtual #281                // Method java/lang/reflect/Method.getModifiers:()I
      26: invokestatic  #282                // Method java/lang/reflect/Modifier.isPublic:(I)Z
      29: ifeq          36
      32: iconst_1
      33: goto          37
      36: iconst_0
      37: ireturn

  private java.lang.Class<?> getExtensionClass(java.lang.String);
    Code:
       0: aload_0
       1: getfield      #55                 // Field type:Ljava/lang/Class;
       4: ifnonnull     18
       7: new           #163                // class java/lang/IllegalArgumentException
      10: dup
      11: ldc_w         #283                // String Extension type == null
      14: invokespecial #165                // Method java/lang/IllegalArgumentException."<init>":(Ljava/lang/String;)V
      17: athrow
      18: aload_1
      19: ifnonnull     32
      22: new           #163                // class java/lang/IllegalArgumentException
      25: dup
      26: ldc           #164                // String Extension name == null
      28: invokespecial #165                // Method java/lang/IllegalArgumentException."<init>":(Ljava/lang/String;)V
      31: athrow
      32: aload_0
      33: invokespecial #107                // Method getExtensionClasses:()Ljava/util/Map;
      36: aload_1
      37: invokeinterface #229,  2          // InterfaceMethod java/util/Map.get:(Ljava/lang/Object;)Ljava/lang/Object;
      42: checkcast     #230                // class java/lang/Class
      45: areturn

  private java.util.Map<java.lang.String, java.lang.Class<?>> getExtensionClasses();
    Code:
       0: aload_0
       1: getfield      #38                 // Field cachedClasses:Lorg/apache/dubbo/common/utils/Holder;
       4: invokevirtual #88                 // Method org/apache/dubbo/common/utils/Holder.get:()Ljava/lang/Object;
       7: checkcast     #201                // class java/util/Map
      10: astore_1
      11: aload_1
      12: ifnonnull     148
      15: aload_0
      16: getfield      #38                 // Field cachedClasses:Lorg/apache/dubbo/common/utils/Holder;
      19: dup
      20: astore_2
      21: monitorenter
      22: aload_0
      23: getfield      #38                 // Field cachedClasses:Lorg/apache/dubbo/common/utils/Holder;
      26: invokevirtual #88                 // Method org/apache/dubbo/common/utils/Holder.get:()Ljava/lang/Object;
      29: checkcast     #201                // class java/util/Map
      32: astore_1
      33: aload_1
      34: ifnonnull     136
      37: aload_0
      38: invokespecial #284                // Method loadExtensionClasses:()Ljava/util/Map;
      41: astore_1
      42: goto          128
      45: astore_3
      46: getstatic     #92                 // Field logger:Lorg/apache/dubbo/common/logger/ErrorTypeAwareLogger;
      49: ldc           #93                 // String 0-15
      51: ldc           #94                 // String
      53: ldc           #94                 // String
      55: new           #95                 // class java/lang/StringBuilder
      58: dup
      59: invokespecial #96                 // Method java/lang/StringBuilder."<init>":()V
      62: ldc_w         #286                // String Exception occurred when loading extension class (interface:
      65: invokevirtual #98                 // Method java/lang/StringBuilder.append:(Ljava/lang/String;)Ljava/lang/StringBuilder;
      68: aload_0
      69: getfield      #55                 // Field type:Ljava/lang/Class;
      72: invokevirtual #99                 // Method java/lang/StringBuilder.append:(Ljava/lang/Object;)Ljava/lang/StringBuilder;
      75: ldc_w         #287                // String )
      78: invokevirtual #98                 // Method java/lang/StringBuilder.append:(Ljava/lang/String;)Ljava/lang/StringBuilder;
      81: invokevirtual #100                // Method java/lang/StringBuilder.toString:()Ljava/lang/String;
      84: aload_3
      85: invokeinterface #101,  6          // InterfaceMethod org/apache/dubbo/common/logger/ErrorTypeAwareLogger.error:(Ljava/lang/String;Ljava/lang/String;Ljava/lang/String;Ljava/lang/String;Ljava/lang/Throwable;)V
      90: new           #103                // class java/lang/IllegalStateException
      93: dup
      94: new           #95                 // class java/lang/StringBuilder
      97: dup
      98: invokespecial #96                 // Method java/lang/StringBuilder."<init>":()V
     101: ldc_w         #286                // String Exception occurred when loading extension class (interface:
     104: invokevirtual #98                 // Method java/lang/StringBuilder.append:(Ljava/lang/String;)Ljava/lang/StringBuilder;
     107: aload_0
     108: getfield      #55                 // Field type:Ljava/lang/Class;
     111: invokevirtual #99                 // Method java/lang/StringBuilder.append:(Ljava/lang/Object;)Ljava/lang/StringBuilder;
     114: ldc_w         #287                // String )
     117: invokevirtual #98                 // Method java/lang/StringBuilder.append:(Ljava/lang/String;)Ljava/lang/StringBuilder;
     120: invokevirtual #100                // Method java/lang/StringBuilder.toString:()Ljava/lang/String;
     123: aload_3
     124: invokespecial #214                // Method java/lang/IllegalStateException."<init>":(Ljava/lang/String;Ljava/lang/Throwable;)V
     127: athrow
     128: aload_0
     129: getfield      #38                 // Field cachedClasses:Lorg/apache/dubbo/common/utils/Holder;
     132: aload_1
     133: invokevirtual #180                // Method org/apache/dubbo/common/utils/Holder.set:(Ljava/lang/Object;)V
     136: aload_2
     137: monitorexit
     138: goto          148
     141: astore        4
     143: aload_2
     144: monitorexit
     145: aload         4
     147: athrow
     148: aload_1
     149: areturn
    Exception table:
       from    to  target type
          37    42    45   Class java/lang/InterruptedException
          22   138   141   any
         141   145   141   any

  private java.util.Map<java.lang.String, java.lang.Class<?>> loadExtensionClasses() throws java.lang.InterruptedException;
    Code:
       0: aload_0
       1: invokespecial #116                // Method checkDestroyed:()V
       4: aload_0
       5: invokespecial #288                // Method cacheDefaultExtensionName:()V
       8: new           #289                // class java/util/HashMap
      11: dup
      12: invokespecial #290                // Method java/util/HashMap."<init>":()V
      15: astore_1
      16: getstatic     #4                  // Field strategies:[Lorg/apache/dubbo/common/extension/LoadingStrategy;
      19: astore_2
      20: aload_2
      21: arraylength
      22: istore_3
      23: iconst_0
      24: istore        4
      26: iload         4
      28: iload_3
      29: if_icmpge     80
      32: aload_2
      33: iload         4
      35: aaload
      36: astore        5
      38: aload_0
      39: aload_1
      40: aload         5
      42: aload_0
      43: getfield      #55                 // Field type:Ljava/lang/Class;
      46: invokevirtual #218                // Method java/lang/Class.getName:()Ljava/lang/String;
      49: invokespecial #291                // Method loadDirectory:(Ljava/util/Map;Lorg/apache/dubbo/common/extension/LoadingStrategy;Ljava/lang/String;)V
      52: aload_0
      53: getfield      #55                 // Field type:Ljava/lang/Class;
      56: ldc           #60                 // class org/apache/dubbo/common/extension/ExtensionInjector
      58: if_acmpne     74
      61: aload_0
      62: aload_1
      63: aload         5
      65: ldc_w         #292                // class org/apache/dubbo/common/extension/ExtensionFactory
      68: invokevirtual #218                // Method java/lang/Class.getName:()Ljava/lang/String;
      71: invokespecial #291                // Method loadDirectory:(Ljava/util/Map;Lorg/apache/dubbo/common/extension/LoadingStrategy;Ljava/lang/String;)V
      74: iinc          4, 1
      77: goto          26
      80: aload_1
      81: areturn

  private void loadDirectory(java.util.Map<java.lang.String, java.lang.Class<?>>, org.apache.dubbo.common.extension.LoadingStrategy, java.lang.String) throws java.lang.InterruptedException;
    Code:
       0: aload_0
       1: aload_1
       2: aload_2
       3: aload_3
       4: invokespecial #293                // Method loadDirectoryInternal:(Ljava/util/Map;Lorg/apache/dubbo/common/extension/LoadingStrategy;Ljava/lang/String;)V
       7: aload_3
       8: ldc_w         #294                // String org.apache
      11: ldc_w         #295                // String com.alibaba
      14: invokevirtual #296                // Method java/lang/String.replace:(Ljava/lang/CharSequence;Ljava/lang/CharSequence;)Ljava/lang/String;
      17: astore        4
      19: aload         4
      21: aload_3
      22: invokevirtual #148                // Method java/lang/String.equals:(Ljava/lang/Object;)Z
      25: ifeq          29
      28: return
      29: aload         4
      31: invokestatic  #297                // Method org/apache/dubbo/common/utils/ClassUtils.forName:(Ljava/lang/String;)Ljava/lang/Class;
      34: pop
      35: aload_0
      36: aload_1
      37: aload_2
      38: aload         4
      40: invokespecial #293                // Method loadDirectoryInternal:(Ljava/util/Map;Lorg/apache/dubbo/common/extension/LoadingStrategy;Ljava/lang/String;)V
      43: goto          48
      46: astore        4
      48: return
    Exception table:
       from    to  target type
           7    28    46   Class java/lang/ClassNotFoundException
          29    43    46   Class java/lang/ClassNotFoundException

  private void cacheDefaultExtensionName();
    Code:
       0: aload_0
       1: getfield      #55                 // Field type:Ljava/lang/Class;
       4: ldc_w         #299                // class org/apache/dubbo/common/extension/SPI
       7: invokevirtual #240                // Method java/lang/Class.getAnnotation:(Ljava/lang/Class;)Ljava/lang/annotation/Annotation;
      10: checkcast     #299                // class org/apache/dubbo/common/extension/SPI
      13: astore_1
      14: aload_1
      15: ifnonnull     19
      18: return
      19: aload_1
      20: invokeinterface #300,  1          // InterfaceMethod org/apache/dubbo/common/extension/SPI.value:()Ljava/lang/String;
      25: astore_2
      26: aload_2
      27: invokevirtual #301                // Method java/lang/String.trim:()Ljava/lang/String;
      30: dup
      31: astore_2
      32: invokevirtual #277                // Method java/lang/String.length:()I
      35: ifle          112
      38: getstatic     #302                // Field NAME_SEPARATOR:Ljava/util/regex/Pattern;
      41: aload_2
      42: invokevirtual #115                // Method java/util/regex/Pattern.split:(Ljava/lang/CharSequence;)[Ljava/lang/String;
      45: astore_3
      46: aload_3
      47: arraylength
      48: iconst_1
      49: if_icmple     99
      52: new           #103                // class java/lang/IllegalStateException
      55: dup
      56: new           #95                 // class java/lang/StringBuilder
      59: dup
      60: invokespecial #96                 // Method java/lang/StringBuilder."<init>":()V
      63: ldc_w         #303                // String More than 1 default extension name on extension
      66: invokevirtual #98                 // Method java/lang/StringBuilder.append:(Ljava/lang/String;)Ljava/lang/StringBuilder;
      69: aload_0
      70: getfield      #55                 // Field type:Ljava/lang/Class;
      73: invokevirtual #218                // Method java/lang/Class.getName:()Ljava/lang/String;
      76: invokevirtual #98                 // Method java/lang/StringBuilder.append:(Ljava/lang/String;)Ljava/lang/StringBuilder;
      79: ldc_w         #273                // String :
      82: invokevirtual #98                 // Method java/lang/StringBuilder.append:(Ljava/lang/String;)Ljava/lang/StringBuilder;
      85: aload_3
      86: invokestatic  #304                // Method java/util/Arrays.toString:([Ljava/lang/Object;)Ljava/lang/String;
      89: invokevirtual #98                 // Method java/lang/StringBuilder.append:(Ljava/lang/String;)Ljava/lang/StringBuilder;
      92: invokevirtual #100                // Method java/lang/StringBuilder.toString:()Ljava/lang/String;
      95: invokespecial #105                // Method java/lang/IllegalStateException."<init>":(Ljava/lang/String;)V
      98: athrow
      99: aload_3
     100: arraylength
     101: iconst_1
     102: if_icmpne     112
     105: aload_0
     106: aload_3
     107: iconst_0
     108: aaload
     109: putfield      #181                // Field cachedDefaultName:Ljava/lang/String;
     112: return

  private void loadDirectoryInternal(java.util.Map<java.lang.String, java.lang.Class<?>>, org.apache.dubbo.common.extension.LoadingStrategy, java.lang.String) throws java.lang.InterruptedException;
    Code:
       0: new           #95                 // class java/lang/StringBuilder
       3: dup
       4: invokespecial #96                 // Method java/lang/StringBuilder."<init>":()V
       7: aload_2
       8: invokeinterface #305,  1          // InterfaceMethod org/apache/dubbo/common/extension/LoadingStrategy.directory:()Ljava/lang/String;
      13: invokevirtual #98                 // Method java/lang/StringBuilder.append:(Ljava/lang/String;)Ljava/lang/StringBuilder;
      16: aload_3
      17: invokevirtual #98                 // Method java/lang/StringBuilder.append:(Ljava/lang/String;)Ljava/lang/StringBuilder;
      20: invokevirtual #100                // Method java/lang/StringBuilder.toString:()Ljava/lang/String;
      23: astore        4
      25: new           #184                // class java/util/LinkedList
      28: dup
      29: invokespecial #185                // Method java/util/LinkedList."<init>":()V
      32: astore        5
      34: aload_2
      35: invokeinterface #306,  1          // InterfaceMethod org/apache/dubbo/common/extension/LoadingStrategy.preferExtensionClassLoader:()Z
      40: ifeq          68
      43: ldc           #15                 // class org/apache/dubbo/common/extension/ExtensionLoader
      45: invokevirtual #16                 // Method java/lang/Class.getClassLoader:()Ljava/lang/ClassLoader;
      48: astore        6
      50: invokestatic  #307                // Method java/lang/ClassLoader.getSystemClassLoader:()Ljava/lang/ClassLoader;
      53: aload         6
      55: if_acmpeq     68
      58: aload         5
      60: aload         6
      62: invokeinterface #187,  2          // InterfaceMethod java/util/List.add:(Ljava/lang/Object;)Z
      67: pop
      68: getstatic     #308                // Field specialSPILoadingStrategyMap:Ljava/util/Map;
      71: aload_3
      72: invokeinterface #202,  2          // InterfaceMethod java/util/Map.containsKey:(Ljava/lang/Object;)Z
      77: ifeq          143
      80: getstatic     #308                // Field specialSPILoadingStrategyMap:Ljava/util/Map;
      83: aload_3
      84: invokeinterface #229,  2          // InterfaceMethod java/util/Map.get:(Ljava/lang/Object;)Ljava/lang/Object;
      89: checkcast     #109                // class java/lang/String
      92: astore        6
      94: ldc_w         #309                // String ALL
      97: aload         6
      99: invokevirtual #148                // Method java/lang/String.equals:(Ljava/lang/Object;)Z
     102: ifne          120
     105: aload         6
     107: aload_2
     108: invokeinterface #310,  1          // InterfaceMethod org/apache/dubbo/common/extension/LoadingStrategy.getName:()Ljava/lang/String;
     113: invokevirtual #148                // Method java/lang/String.equals:(Ljava/lang/Object;)Z
     116: ifne          120
     119: return
     120: aload         5
     122: invokeinterface #311,  1          // InterfaceMethod java/util/List.clear:()V
     127: aload         5
     129: ldc           #15                 // class org/apache/dubbo/common/extension/ExtensionLoader
     131: invokevirtual #16                 // Method java/lang/Class.getClassLoader:()Ljava/lang/ClassLoader;
     134: invokeinterface #187,  2          // InterfaceMethod java/util/List.add:(Ljava/lang/Object;)Z
     139: pop
     140: goto          238
     143: aload_0
     144: getfield      #67                 // Field scopeModel:Lorg/apache/dubbo/rpc/model/ScopeModel;
     147: invokevirtual #312                // Method org/apache/dubbo/rpc/model/ScopeModel.getClassLoaders:()Ljava/util/Set;
     150: astore        6
     152: aload         6
     154: invokestatic  #313                // Method org/apache/dubbo/common/utils/CollectionUtils.isEmpty:(Ljava/util/Collection;)Z
     157: ifeq          228
     160: aload         4
     162: invokestatic  #314                // Method java/lang/ClassLoader.getSystemResources:(Ljava/lang/String;)Ljava/util/Enumeration;
     165: astore        7
     167: aload         7
     169: ifnull        225
     172: aload         7
     174: invokeinterface #315,  1          // InterfaceMethod java/util/Enumeration.hasMoreElements:()Z
     179: ifeq          225
     182: aload_0
     183: aload_1
     184: aconst_null
     185: aload         7
     187: invokeinterface #316,  1          // InterfaceMethod java/util/Enumeration.nextElement:()Ljava/lang/Object;
     192: checkcast     #317                // class java/net/URL
     195: aload_2
     196: invokeinterface #318,  1          // InterfaceMethod org/apache/dubbo/common/extension/LoadingStrategy.overridden:()Z
     201: aload_2
     202: invokeinterface #319,  1          // InterfaceMethod org/apache/dubbo/common/extension/LoadingStrategy.includedPackages:()[Ljava/lang/String;
     207: aload_2
     208: invokeinterface #320,  1          // InterfaceMethod org/apache/dubbo/common/extension/LoadingStrategy.excludedPackages:()[Ljava/lang/String;
     213: aload_2
     214: invokeinterface #321,  1          // InterfaceMethod org/apache/dubbo/common/extension/LoadingStrategy.onlyExtensionClassLoaderPackages:()[Ljava/lang/String;
     219: invokespecial #322                // Method loadResource:(Ljava/util/Map;Ljava/lang/ClassLoader;Ljava/net/URL;Z[Ljava/lang/String;[Ljava/lang/String;[Ljava/lang/String;)V
     222: goto          172
     225: goto          238
     228: aload         5
     230: aload         6
     232: invokeinterface #159,  2          // InterfaceMethod java/util/List.addAll:(Ljava/util/Collection;)Z
     237: pop
     238: aload         4
     240: aload         5
     242: invokestatic  #323                // Method org/apache/dubbo/common/utils/ClassLoaderResourceLoader.loadResources:(Ljava/lang/String;Ljava/util/Collection;)Ljava/util/Map;
     245: astore        6
     247: aload         6
     249: aload_0
     250: aload_1
     251: aload_2
     252: invokedynamic #324,  0            // InvokeDynamic #8:accept:(Lorg/apache/dubbo/common/extension/ExtensionLoader;Ljava/util/Map;Lorg/apache/dubbo/common/extension/LoadingStrategy;)Ljava/util/function/BiConsumer;
     257: invokeinterface #142,  2          // InterfaceMethod java/util/Map.forEach:(Ljava/util/function/BiConsumer;)V
     262: goto          325
     265: astore        5
     267: aload         5
     269: athrow
     270: astore        5
     272: getstatic     #92                 // Field logger:Lorg/apache/dubbo/common/logger/ErrorTypeAwareLogger;
     275: ldc           #93                 // String 0-15
     277: ldc           #94                 // String
     279: ldc           #94                 // String
     281: new           #95                 // class java/lang/StringBuilder
     284: dup
     285: invokespecial #96                 // Method java/lang/StringBuilder."<init>":()V
     288: ldc_w         #286                // String Exception occurred when loading extension class (interface:
     291: invokevirtual #98                 // Method java/lang/StringBuilder.append:(Ljava/lang/String;)Ljava/lang/StringBuilder;
     294: aload_3
     295: invokevirtual #98                 // Method java/lang/StringBuilder.append:(Ljava/lang/String;)Ljava/lang/StringBuilder;
     298: ldc_w         #325                // String , description file:
     301: invokevirtual #98                 // Method java/lang/StringBuilder.append:(Ljava/lang/String;)Ljava/lang/StringBuilder;
     304: aload         4
     306: invokevirtual #98                 // Method java/lang/StringBuilder.append:(Ljava/lang/String;)Ljava/lang/StringBuilder;
     309: ldc_w         #326                // String ).
     312: invokevirtual #98                 // Method java/lang/StringBuilder.append:(Ljava/lang/String;)Ljava/lang/StringBuilder;
     315: invokevirtual #100                // Method java/lang/StringBuilder.toString:()Ljava/lang/String;
     318: aload         5
     320: invokeinterface #101,  6          // InterfaceMethod org/apache/dubbo/common/logger/ErrorTypeAwareLogger.error:(Ljava/lang/String;Ljava/lang/String;Ljava/lang/String;Ljava/lang/String;Ljava/lang/Throwable;)V
     325: return
    Exception table:
       from    to  target type
          25   119   265   Class java/lang/InterruptedException
         120   262   265   Class java/lang/InterruptedException
          25   119   270   Class java/lang/Throwable
         120   262   270   Class java/lang/Throwable

  private void loadFromClass(java.util.Map<java.lang.String, java.lang.Class<?>>, boolean, java.util.Set<java.net.URL>, java.lang.ClassLoader, java.lang.String[], java.lang.String[], java.lang.String[]);
    Code:
       0: aload_3
       1: invokestatic  #160                // Method org/apache/dubbo/common/utils/CollectionUtils.isNotEmpty:(Ljava/util/Collection;)Z
       4: ifeq          56
       7: aload_3
       8: invokeinterface #126,  1          // InterfaceMethod java/util/Set.iterator:()Ljava/util/Iterator;
      13: astore        8
      15: aload         8
      17: invokeinterface #86,  1           // InterfaceMethod java/util/Iterator.hasNext:()Z
      22: ifeq          56
      25: aload         8
      27: invokeinterface #87,  1           // InterfaceMethod java/util/Iterator.next:()Ljava/lang/Object;
      32: checkcast     #317                // class java/net/URL
      35: astore        9
      37: aload_0
      38: aload_1
      39: aload         4
      41: aload         9
      43: iload_2
      44: aload         5
      46: aload         6
      48: aload         7
      50: invokespecial #322                // Method loadResource:(Ljava/util/Map;Ljava/lang/ClassLoader;Ljava/net/URL;Z[Ljava/lang/String;[Ljava/lang/String;[Ljava/lang/String;)V
      53: goto          15
      56: return

  private void loadResource(java.util.Map<java.lang.String, java.lang.Class<?>>, java.lang.ClassLoader, java.net.URL, boolean, java.lang.String[], java.lang.String[], java.lang.String[]);
    Code:
       0: aload_0
       1: aload_3
       2: invokespecial #327                // Method getResourceContent:(Ljava/net/URL;)Ljava/util/List;
       5: astore        8
       7: aload         8
       9: invokeinterface #145,  1          // InterfaceMethod java/util/List.iterator:()Ljava/util/Iterator;
      14: astore        10
      16: aload         10
      18: invokeinterface #86,  1           // InterfaceMethod java/util/Iterator.hasNext:()Z
      23: ifeq          240
      26: aload         10
      28: invokeinterface #87,  1           // InterfaceMethod java/util/Iterator.next:()Ljava/lang/Object;
      33: checkcast     #109                // class java/lang/String
      36: astore        11
      38: aconst_null
      39: astore        12
      41: aload         11
      43: bipush        61
      45: invokevirtual #328                // Method java/lang/String.indexOf:(I)I
      48: istore        13
      50: iload         13
      52: ifle          85
      55: aload         11
      57: iconst_0
      58: iload         13
      60: invokevirtual #278                // Method java/lang/String.substring:(II)Ljava/lang/String;
      63: invokevirtual #301                // Method java/lang/String.trim:()Ljava/lang/String;
      66: astore        12
      68: aload         11
      70: iload         13
      72: iconst_1
      73: iadd
      74: invokevirtual #279                // Method java/lang/String.substring:(I)Ljava/lang/String;
      77: invokevirtual #301                // Method java/lang/String.trim:()Ljava/lang/String;
      80: astore        9
      82: goto          89
      85: aload         11
      87: astore        9
      89: aload         9
      91: invokestatic  #329                // Method org/apache/dubbo/common/utils/StringUtils.isNotEmpty:(Ljava/lang/String;)Z
      94: ifeq          149
      97: aload_0
      98: aload         9
     100: aload         6
     102: invokespecial #330                // Method isExcluded:(Ljava/lang/String;[Ljava/lang/String;)Z
     105: ifne          149
     108: aload_0
     109: aload         9
     111: aload         5
     113: invokespecial #331                // Method isIncluded:(Ljava/lang/String;[Ljava/lang/String;)Z
     116: ifeq          149
     119: aload_0
     120: aload         9
     122: aload_2
     123: aload         7
     125: invokespecial #332                // Method isExcludedByClassLoader:(Ljava/lang/String;Ljava/lang/ClassLoader;[Ljava/lang/String;)Z
     128: ifne          149
     131: aload_0
     132: aload_2
     133: aload_1
     134: aload_3
     135: aload         9
     137: iconst_1
     138: aload_2
     139: invokestatic  #333                // Method java/lang/Class.forName:(Ljava/lang/String;ZLjava/lang/ClassLoader;)Ljava/lang/Class;
     142: aload         12
     144: iload         4
     146: invokespecial #334                // Method loadClass:(Ljava/lang/ClassLoader;Ljava/util/Map;Ljava/net/URL;Ljava/lang/Class;Ljava/lang/String;Z)V
     149: goto          237
     152: astore        12
     154: new           #103                // class java/lang/IllegalStateException
     157: dup
     158: new           #95                 // class java/lang/StringBuilder
     161: dup
     162: invokespecial #96                 // Method java/lang/StringBuilder."<init>":()V
     165: ldc_w         #335                // String Failed to load extension class (interface:
     168: invokevirtual #98                 // Method java/lang/StringBuilder.append:(Ljava/lang/String;)Ljava/lang/StringBuilder;
     171: aload_0
     172: getfield      #55                 // Field type:Ljava/lang/Class;
     175: invokevirtual #99                 // Method java/lang/StringBuilder.append:(Ljava/lang/Object;)Ljava/lang/StringBuilder;
     178: ldc_w         #336                // String , class line:
     181: invokevirtual #98                 // Method java/lang/StringBuilder.append:(Ljava/lang/String;)Ljava/lang/StringBuilder;
     184: aload         11
     186: invokevirtual #98                 // Method java/lang/StringBuilder.append:(Ljava/lang/String;)Ljava/lang/StringBuilder;
     189: ldc_w         #337                // String ) in
     192: invokevirtual #98                 // Method java/lang/StringBuilder.append:(Ljava/lang/String;)Ljava/lang/StringBuilder;
     195: aload_3
     196: invokevirtual #99                 // Method java/lang/StringBuilder.append:(Ljava/lang/Object;)Ljava/lang/StringBuilder;
     199: ldc_w         #338                // String , cause:
     202: invokevirtual #98                 // Method java/lang/StringBuilder.append:(Ljava/lang/String;)Ljava/lang/StringBuilder;
     205: aload         12
     207: invokevirtual #252                // Method java/lang/Throwable.getMessage:()Ljava/lang/String;
     210: invokevirtual #98                 // Method java/lang/StringBuilder.append:(Ljava/lang/String;)Ljava/lang/StringBuilder;
     213: invokevirtual #100                // Method java/lang/StringBuilder.toString:()Ljava/lang/String;
     216: aload         12
     218: invokespecial #214                // Method java/lang/IllegalStateException."<init>":(Ljava/lang/String;Ljava/lang/Throwable;)V
     221: astore        13
     223: aload_0
     224: getfield      #48                 // Field exceptions:Ljava/util/Map;
     227: aload         11
     229: aload         13
     231: invokeinterface #136,  3          // InterfaceMethod java/util/Map.put:(Ljava/lang/Object;Ljava/lang/Object;)Ljava/lang/Object;
     236: pop
     237: goto          16
     240: goto          304
     243: astore        8
     245: getstatic     #92                 // Field logger:Lorg/apache/dubbo/common/logger/ErrorTypeAwareLogger;
     248: ldc           #93                 // String 0-15
     250: ldc           #94                 // String
     252: ldc           #94                 // String
     254: new           #95                 // class java/lang/StringBuilder
     257: dup
     258: invokespecial #96                 // Method java/lang/StringBuilder."<init>":()V
     261: ldc_w         #286                // String Exception occurred when loading extension class (interface:
     264: invokevirtual #98                 // Method java/lang/StringBuilder.append:(Ljava/lang/String;)Ljava/lang/StringBuilder;
     267: aload_0
     268: getfield      #55                 // Field type:Ljava/lang/Class;
     271: invokevirtual #99                 // Method java/lang/StringBuilder.append:(Ljava/lang/Object;)Ljava/lang/StringBuilder;
     274: ldc_w         #339                // String , class file:
     277: invokevirtual #98                 // Method java/lang/StringBuilder.append:(Ljava/lang/String;)Ljava/lang/StringBuilder;
     280: aload_3
     281: invokevirtual #99                 // Method java/lang/StringBuilder.append:(Ljava/lang/Object;)Ljava/lang/StringBuilder;
     284: ldc_w         #337                // String ) in
     287: invokevirtual #98                 // Method java/lang/StringBuilder.append:(Ljava/lang/String;)Ljava/lang/StringBuilder;
     290: aload_3
     291: invokevirtual #99                 // Method java/lang/StringBuilder.append:(Ljava/lang/Object;)Ljava/lang/StringBuilder;
     294: invokevirtual #100                // Method java/lang/StringBuilder.toString:()Ljava/lang/String;
     297: aload         8
     299: invokeinterface #101,  6          // InterfaceMethod org/apache/dubbo/common/logger/ErrorTypeAwareLogger.error:(Ljava/lang/String;Ljava/lang/String;Ljava/lang/String;Ljava/lang/String;Ljava/lang/Throwable;)V
     304: return
    Exception table:
       from    to  target type
          38   149   152   Class java/lang/Throwable
           0   240   243   Class java/lang/Throwable

  private java.util.List<java.lang.String> getResourceContent(java.net.URL) throws java.io.IOException;
    Code:
       0: getstatic     #340                // Field urlListMapCache:Ljava/lang/ref/SoftReference;
       3: invokevirtual #341                // Method java/lang/ref/SoftReference.get:()Ljava/lang/Object;
       6: checkcast     #201                // class java/util/Map
       9: astore_2
      10: aload_2
      11: ifnonnull     64
      14: ldc           #15                 // class org/apache/dubbo/common/extension/ExtensionLoader
      16: dup
      17: astore_3
      18: monitorenter
      19: getstatic     #340                // Field urlListMapCache:Ljava/lang/ref/SoftReference;
      22: invokevirtual #341                // Method java/lang/ref/SoftReference.get:()Ljava/lang/Object;
      25: checkcast     #201                // class java/util/Map
      28: dup
      29: astore_2
      30: ifnonnull     52
      33: new           #13                 // class java/util/concurrent/ConcurrentHashMap
      36: dup
      37: invokespecial #14                 // Method java/util/concurrent/ConcurrentHashMap."<init>":()V
      40: astore_2
      41: new           #342                // class java/lang/ref/SoftReference
      44: dup
      45: aload_2
      46: invokespecial #343                // Method java/lang/ref/SoftReference."<init>":(Ljava/lang/Object;)V
      49: putstatic     #340                // Field urlListMapCache:Ljava/lang/ref/SoftReference;
      52: aload_3
      53: monitorexit
      54: goto          64
      57: astore        4
      59: aload_3
      60: monitorexit
      61: aload         4
      63: athrow
      64: aload_2
      65: aload_1
      66: aload_1
      67: invokedynamic #344,  0            // InvokeDynamic #9:apply:(Ljava/net/URL;)Ljava/util/function/Function;
      72: invokeinterface #345,  3          // InterfaceMethod java/util/Map.computeIfAbsent:(Ljava/lang/Object;Ljava/util/function/Function;)Ljava/lang/Object;
      77: checkcast     #346                // class java/util/List
      80: astore_3
      81: aload_3
      82: areturn
    Exception table:
       from    to  target type
          19    54    57   any
          57    61    57   any

  private boolean isIncluded(java.lang.String, java.lang.String...);
    Code:
       0: aload_2
       1: ifnull        69
       4: aload_2
       5: arraylength
       6: ifle          69
       9: aload_2
      10: astore_3
      11: aload_3
      12: arraylength
      13: istore        4
      15: iconst_0
      16: istore        5
      18: iload         5
      20: iload         4
      22: if_icmpge     67
      25: aload_3
      26: iload         5
      28: aaload
      29: astore        6
      31: aload_1
      32: new           #95                 // class java/lang/StringBuilder
      35: dup
      36: invokespecial #96                 // Method java/lang/StringBuilder."<init>":()V
      39: aload         6
      41: invokevirtual #98                 // Method java/lang/StringBuilder.append:(Ljava/lang/String;)Ljava/lang/StringBuilder;
      44: ldc_w         #347                // String .
      47: invokevirtual #98                 // Method java/lang/StringBuilder.append:(Ljava/lang/String;)Ljava/lang/StringBuilder;
      50: invokevirtual #100                // Method java/lang/StringBuilder.toString:()Ljava/lang/String;
      53: invokevirtual #147                // Method java/lang/String.startsWith:(Ljava/lang/String;)Z
      56: ifeq          61
      59: iconst_1
      60: ireturn
      61: iinc          5, 1
      64: goto          18
      67: iconst_0
      68: ireturn
      69: iconst_1
      70: ireturn

  private boolean isExcluded(java.lang.String, java.lang.String...);
    Code:
       0: aload_2
       1: ifnull        62
       4: aload_2
       5: astore_3
       6: aload_3
       7: arraylength
       8: istore        4
      10: iconst_0
      11: istore        5
      13: iload         5
      15: iload         4
      17: if_icmpge     62
      20: aload_3
      21: iload         5
      23: aaload
      24: astore        6
      26: aload_1
      27: new           #95                 // class java/lang/StringBuilder
      30: dup
      31: invokespecial #96                 // Method java/lang/StringBuilder."<init>":()V
      34: aload         6
      36: invokevirtual #98                 // Method java/lang/StringBuilder.append:(Ljava/lang/String;)Ljava/lang/StringBuilder;
      39: ldc_w         #347                // String .
      42: invokevirtual #98                 // Method java/lang/StringBuilder.append:(Ljava/lang/String;)Ljava/lang/StringBuilder;
      45: invokevirtual #100                // Method java/lang/StringBuilder.toString:()Ljava/lang/String;
      48: invokevirtual #147                // Method java/lang/String.startsWith:(Ljava/lang/String;)Z
      51: ifeq          56
      54: iconst_1
      55: ireturn
      56: iinc          5, 1
      59: goto          13
      62: iconst_0
      63: ireturn

  private boolean isExcludedByClassLoader(java.lang.String, java.lang.ClassLoader, java.lang.String...);
    Code:
       0: aload_3
       1: ifnull        81
       4: aload_3
       5: astore        4
       7: aload         4
       9: arraylength
      10: istore        5
      12: iconst_0
      13: istore        6
      15: iload         6
      17: iload         5
      19: if_icmpge     81
      22: aload         4
      24: iload         6
      26: aaload
      27: astore        7
      29: aload_1
      30: new           #95                 // class java/lang/StringBuilder
      33: dup
      34: invokespecial #96                 // Method java/lang/StringBuilder."<init>":()V
      37: aload         7
      39: invokevirtual #98                 // Method java/lang/StringBuilder.append:(Ljava/lang/String;)Ljava/lang/StringBuilder;
      42: ldc_w         #347                // String .
      45: invokevirtual #98                 // Method java/lang/StringBuilder.append:(Ljava/lang/String;)Ljava/lang/StringBuilder;
      48: invokevirtual #100                // Method java/lang/StringBuilder.toString:()Ljava/lang/String;
      51: invokevirtual #147                // Method java/lang/String.startsWith:(Ljava/lang/String;)Z
      54: ifeq          75
      57: ldc           #15                 // class org/apache/dubbo/common/extension/ExtensionLoader
      59: invokevirtual #16                 // Method java/lang/Class.getClassLoader:()Ljava/lang/ClassLoader;
      62: aload_2
      63: invokestatic  #348                // Method java/util/Objects.equals:(Ljava/lang/Object;Ljava/lang/Object;)Z
      66: ifne          73
      69: iconst_1
      70: goto          74
      73: iconst_0
      74: ireturn
      75: iinc          6, 1
      78: goto          15
      81: iconst_0
      82: ireturn

  private void loadClass(java.lang.ClassLoader, java.util.Map<java.lang.String, java.lang.Class<?>>, java.net.URL, java.lang.Class<?>, java.lang.String, boolean);
    Code:
       0: aload_0
       1: getfield      #55                 // Field type:Ljava/lang/Class;
       4: aload         4
       6: invokevirtual #192                // Method java/lang/Class.isAssignableFrom:(Ljava/lang/Class;)Z
       9: ifne          77
      12: new           #103                // class java/lang/IllegalStateException
      15: dup
      16: new           #95                 // class java/lang/StringBuilder
      19: dup
      20: invokespecial #96                 // Method java/lang/StringBuilder."<init>":()V
      23: ldc_w         #349                // String Error occurred when loading extension class (interface:
      26: invokevirtual #98                 // Method java/lang/StringBuilder.append:(Ljava/lang/String;)Ljava/lang/StringBuilder;
      29: aload_0
      30: getfield      #55                 // Field type:Ljava/lang/Class;
      33: invokevirtual #99                 // Method java/lang/StringBuilder.append:(Ljava/lang/Object;)Ljava/lang/StringBuilder;
      36: ldc_w         #336                // String , class line:
      39: invokevirtual #98                 // Method java/lang/StringBuilder.append:(Ljava/lang/String;)Ljava/lang/StringBuilder;
      42: aload         4
      44: invokevirtual #218                // Method java/lang/Class.getName:()Ljava/lang/String;
      47: invokevirtual #98                 // Method java/lang/StringBuilder.append:(Ljava/lang/String;)Ljava/lang/StringBuilder;
      50: ldc_w         #350                // String ), class
      53: invokevirtual #98                 // Method java/lang/StringBuilder.append:(Ljava/lang/String;)Ljava/lang/StringBuilder;
      56: aload         4
      58: invokevirtual #218                // Method java/lang/Class.getName:()Ljava/lang/String;
      61: invokevirtual #98                 // Method java/lang/StringBuilder.append:(Ljava/lang/String;)Ljava/lang/StringBuilder;
      64: ldc_w         #351                // String  is not subtype of interface.
      67: invokevirtual #98                 // Method java/lang/StringBuilder.append:(Ljava/lang/String;)Ljava/lang/StringBuilder;
      70: invokevirtual #100                // Method java/lang/StringBuilder.toString:()Ljava/lang/String;
      73: invokespecial #105                // Method java/lang/IllegalStateException."<init>":(Ljava/lang/String;)V
      76: athrow
      77: aload_0
      78: aload_1
      79: aload         4
      81: invokespecial #352                // Method loadClassIfActive:(Ljava/lang/ClassLoader;Ljava/lang/Class;)Z
      84: istore        7
      86: iload         7
      88: ifne          92
      91: return
      92: aload         4
      94: ldc           #197                // class org/apache/dubbo/common/extension/Adaptive
      96: invokevirtual #198                // Method java/lang/Class.isAnnotationPresent:(Ljava/lang/Class;)Z
      99: ifeq          113
     102: aload_0
     103: aload         4
     105: iload         6
     107: invokespecial #353                // Method cacheAdaptiveClass:(Ljava/lang/Class;Z)V
     110: goto          276
     113: aload_0
     114: aload         4
     116: invokevirtual #354                // Method isWrapperClass:(Ljava/lang/Class;)Z
     119: ifeq          131
     122: aload_0
     123: aload         4
     125: invokespecial #355                // Method cacheWrapperClass:(Ljava/lang/Class;)V
     128: goto          276
     131: aload         5
     133: invokestatic  #113                // Method org/apache/dubbo/common/utils/StringUtils.isEmpty:(Ljava/lang/String;)Z
     136: ifeq          197
     139: aload_0
     140: aload         4
     142: invokespecial #356                // Method findAnnotationName:(Ljava/lang/Class;)Ljava/lang/String;
     145: astore        5
     147: aload         5
     149: invokevirtual #277                // Method java/lang/String.length:()I
     152: ifne          197
     155: new           #103                // class java/lang/IllegalStateException
     158: dup
     159: new           #95                 // class java/lang/StringBuilder
     162: dup
     163: invokespecial #96                 // Method java/lang/StringBuilder."<init>":()V
     166: ldc_w         #357                // String No such extension name for the class
     169: invokevirtual #98                 // Method java/lang/StringBuilder.append:(Ljava/lang/String;)Ljava/lang/StringBuilder;
     172: aload         4
     174: invokevirtual #218                // Method java/lang/Class.getName:()Ljava/lang/String;
     177: invokevirtual #98                 // Method java/lang/StringBuilder.append:(Ljava/lang/String;)Ljava/lang/StringBuilder;
     180: ldc_w         #358                // String  in the config
     183: invokevirtual #98                 // Method java/lang/StringBuilder.append:(Ljava/lang/String;)Ljava/lang/StringBuilder;
     186: aload_3
     187: invokevirtual #99                 // Method java/lang/StringBuilder.append:(Ljava/lang/Object;)Ljava/lang/StringBuilder;
     190: invokevirtual #100                // Method java/lang/StringBuilder.toString:()Ljava/lang/String;
     193: invokespecial #105                // Method java/lang/IllegalStateException."<init>":(Ljava/lang/String;)V
     196: athrow
     197: getstatic     #302                // Field NAME_SEPARATOR:Ljava/util/regex/Pattern;
     200: aload         5
     202: invokevirtual #115                // Method java/util/regex/Pattern.split:(Ljava/lang/CharSequence;)[Ljava/lang/String;
     205: astore        8
     207: aload         8
     209: invokestatic  #3                  // Method org/apache/dubbo/common/utils/ArrayUtils.isNotEmpty:([Ljava/lang/Object;)Z
     212: ifeq          276
     215: aload_0
     216: aload         4
     218: aload         8
     220: iconst_0
     221: aaload
     222: invokespecial #359                // Method cacheActivateClass:(Ljava/lang/Class;Ljava/lang/String;)V
     225: aload         8
     227: astore        9
     229: aload         9
     231: arraylength
     232: istore        10
     234: iconst_0
     235: istore        11
     237: iload         11
     239: iload         10
     241: if_icmpge     276
     244: aload         9
     246: iload         11
     248: aaload
     249: astore        12
     251: aload_0
     252: aload         4
     254: aload         12
     256: invokespecial #360                // Method cacheName:(Ljava/lang/Class;Ljava/lang/String;)V
     259: aload_0
     260: aload_2
     261: aload         4
     263: aload         12
     265: iload         6
     267: invokespecial #361                // Method saveInExtensionClass:(Ljava/util/Map;Ljava/lang/Class;Ljava/lang/String;Z)V
     270: iinc          11, 1
     273: goto          237
     276: return

  private boolean loadClassIfActive(java.lang.ClassLoader, java.lang.Class<?>);
    Code:
       0: aload_2
       1: ldc           #130                // class org/apache/dubbo/common/extension/Activate
       3: invokevirtual #240                // Method java/lang/Class.getAnnotation:(Ljava/lang/Class;)Ljava/lang/annotation/Annotation;
       6: checkcast     #130                // class org/apache/dubbo/common/extension/Activate
       9: astore_3
      10: aload_3
      11: ifnonnull     16
      14: iconst_1
      15: ireturn
      16: aconst_null
      17: astore        4
      19: aload_3
      20: instanceof    #130                // class org/apache/dubbo/common/extension/Activate
      23: ifeq          37
      26: aload_3
      27: invokeinterface #362,  1          // InterfaceMethod org/apache/dubbo/common/extension/Activate.onClass:()[Ljava/lang/String;
      32: astore        4
      34: goto          55
      37: aload_3
      38: instanceof    #133                // class com/alibaba/dubbo/common/extension/Activate
      41: ifeq          55
      44: aload_3
      45: checkcast     #133                // class com/alibaba/dubbo/common/extension/Activate
      48: invokeinterface #363,  1          // InterfaceMethod com/alibaba/dubbo/common/extension/Activate.onClass:()[Ljava/lang/String;
      53: astore        4
      55: iconst_1
      56: istore        5
      58: aconst_null
      59: aload         4
      61: if_acmpeq     98
      64: aload         4
      66: arraylength
      67: ifle          98
      70: aload         4
      72: invokestatic  #25                 // Method java/util/Arrays.stream:([Ljava/lang/Object;)Ljava/util/stream/Stream;
      75: invokedynamic #364,  0            // InvokeDynamic #10:test:()Ljava/util/function/Predicate;
      80: invokeinterface #70,  2           // InterfaceMethod java/util/stream/Stream.filter:(Ljava/util/function/Predicate;)Ljava/util/stream/Stream;
      85: aload_1
      86: invokedynamic #365,  0            // InvokeDynamic #11:test:(Ljava/lang/ClassLoader;)Ljava/util/function/Predicate;
      91: invokeinterface #366,  2          // InterfaceMethod java/util/stream/Stream.allMatch:(Ljava/util/function/Predicate;)Z
      96: istore        5
      98: iload         5
     100: ireturn

  private void cacheName(java.lang.Class<?>, java.lang.String);
    Code:
       0: aload_0
       1: getfield      #35                 // Field cachedNames:Ljava/util/concurrent/ConcurrentMap;
       4: aload_1
       5: invokeinterface #367,  2          // InterfaceMethod java/util/concurrent/ConcurrentMap.containsKey:(Ljava/lang/Object;)Z
      10: ifne          25
      13: aload_0
      14: getfield      #35                 // Field cachedNames:Ljava/util/concurrent/ConcurrentMap;
      17: aload_1
      18: aload_2
      19: invokeinterface #205,  3          // InterfaceMethod java/util/concurrent/ConcurrentMap.put:(Ljava/lang/Object;Ljava/lang/Object;)Ljava/lang/Object;
      24: pop
      25: return

  private void saveInExtensionClass(java.util.Map<java.lang.String, java.lang.Class<?>>, java.lang.Class<?>, java.lang.String, boolean);
    Code:
       0: aload_1
       1: aload_3
       2: invokeinterface #229,  2          // InterfaceMethod java/util/Map.get:(Ljava/lang/Object;)Ljava/lang/Object;
       7: checkcast     #230                // class java/lang/Class
      10: astore        5
      12: aload         5
      14: ifnull        22
      17: iload         4
      19: ifeq          34
      22: aload_1
      23: aload_3
      24: aload_2
      25: invokeinterface #136,  3          // InterfaceMethod java/util/Map.put:(Ljava/lang/Object;Ljava/lang/Object;)Ljava/lang/Object;
      30: pop
      31: goto          142
      34: aload         5
      36: aload_2
      37: if_acmpeq     142
      40: aload_0
      41: getfield      #51                 // Field unacceptableExceptions:Ljava/util/Set;
      44: aload_3
      45: invokeinterface #368,  2          // InterfaceMethod java/util/Set.add:(Ljava/lang/Object;)Z
      50: pop
      51: new           #95                 // class java/lang/StringBuilder
      54: dup
      55: invokespecial #96                 // Method java/lang/StringBuilder."<init>":()V
      58: ldc_w         #369                // String Duplicate extension
      61: invokevirtual #98                 // Method java/lang/StringBuilder.append:(Ljava/lang/String;)Ljava/lang/StringBuilder;
      64: aload_0
      65: getfield      #55                 // Field type:Ljava/lang/Class;
      68: invokevirtual #218                // Method java/lang/Class.getName:()Ljava/lang/String;
      71: invokevirtual #98                 // Method java/lang/StringBuilder.append:(Ljava/lang/String;)Ljava/lang/StringBuilder;
      74: ldc_w         #370                // String  name
      77: invokevirtual #98                 // Method java/lang/StringBuilder.append:(Ljava/lang/String;)Ljava/lang/StringBuilder;
      80: aload_3
      81: invokevirtual #98                 // Method java/lang/StringBuilder.append:(Ljava/lang/String;)Ljava/lang/StringBuilder;
      84: ldc_w         #371                // String  on
      87: invokevirtual #98                 // Method java/lang/StringBuilder.append:(Ljava/lang/String;)Ljava/lang/StringBuilder;
      90: aload         5
      92: invokevirtual #218                // Method java/lang/Class.getName:()Ljava/lang/String;
      95: invokevirtual #98                 // Method java/lang/StringBuilder.append:(Ljava/lang/String;)Ljava/lang/StringBuilder;
      98: ldc_w         #372                // String  and
     101: invokevirtual #98                 // Method java/lang/StringBuilder.append:(Ljava/lang/String;)Ljava/lang/StringBuilder;
     104: aload_2
     105: invokevirtual #218                // Method java/lang/Class.getName:()Ljava/lang/String;
     108: invokevirtual #98                 // Method java/lang/StringBuilder.append:(Ljava/lang/String;)Ljava/lang/StringBuilder;
     111: invokevirtual #100                // Method java/lang/StringBuilder.toString:()Ljava/lang/String;
     114: astore        6
     116: getstatic     #92                 // Field logger:Lorg/apache/dubbo/common/logger/ErrorTypeAwareLogger;
     119: ldc           #93                 // String 0-15
     121: ldc           #94                 // String
     123: ldc           #94                 // String
     125: aload         6
     127: invokeinterface #373,  5          // InterfaceMethod org/apache/dubbo/common/logger/ErrorTypeAwareLogger.error:(Ljava/lang/String;Ljava/lang/String;Ljava/lang/String;Ljava/lang/String;)V
     132: new           #103                // class java/lang/IllegalStateException
     135: dup
     136: aload         6
     138: invokespecial #105                // Method java/lang/IllegalStateException."<init>":(Ljava/lang/String;)V
     141: athrow
     142: return

  private void cacheActivateClass(java.lang.Class<?>, java.lang.String);
    Code:
       0: aload_1
       1: ldc           #130                // class org/apache/dubbo/common/extension/Activate
       3: invokevirtual #240                // Method java/lang/Class.getAnnotation:(Ljava/lang/Class;)Ljava/lang/annotation/Annotation;
       6: checkcast     #130                // class org/apache/dubbo/common/extension/Activate
       9: astore_3
      10: aload_3
      11: ifnull        29
      14: aload_0
      15: getfield      #42                 // Field cachedActivates:Ljava/util/Map;
      18: aload_2
      19: aload_3
      20: invokeinterface #136,  3          // InterfaceMethod java/util/Map.put:(Ljava/lang/Object;Ljava/lang/Object;)Ljava/lang/Object;
      25: pop
      26: goto          58
      29: aload_1
      30: ldc           #133                // class com/alibaba/dubbo/common/extension/Activate
      32: invokevirtual #240                // Method java/lang/Class.getAnnotation:(Ljava/lang/Class;)Ljava/lang/annotation/Annotation;
      35: checkcast     #133                // class com/alibaba/dubbo/common/extension/Activate
      38: astore        4
      40: aload         4
      42: ifnull        58
      45: aload_0
      46: getfield      #42                 // Field cachedActivates:Ljava/util/Map;
      49: aload_2
      50: aload         4
      52: invokeinterface #136,  3          // InterfaceMethod java/util/Map.put:(Ljava/lang/Object;Ljava/lang/Object;)Ljava/lang/Object;
      57: pop
      58: return

  private void cacheAdaptiveClass(java.lang.Class<?>, boolean);
    Code:
       0: aload_0
       1: getfield      #47                 // Field cachedAdaptiveClass:Ljava/lang/Class;
       4: ifnull        11
       7: iload_2
       8: ifeq          19
      11: aload_0
      12: aload_1
      13: putfield      #47                 // Field cachedAdaptiveClass:Ljava/lang/Class;
      16: goto          77
      19: aload_0
      20: getfield      #47                 // Field cachedAdaptiveClass:Ljava/lang/Class;
      23: aload_1
      24: invokevirtual #374                // Method java/lang/Object.equals:(Ljava/lang/Object;)Z
      27: ifne          77
      30: new           #103                // class java/lang/IllegalStateException
      33: dup
      34: new           #95                 // class java/lang/StringBuilder
      37: dup
      38: invokespecial #96                 // Method java/lang/StringBuilder."<init>":()V
      41: ldc_w         #375                // String More than 1 adaptive class found:
      44: invokevirtual #98                 // Method java/lang/StringBuilder.append:(Ljava/lang/String;)Ljava/lang/StringBuilder;
      47: aload_0
      48: getfield      #47                 // Field cachedAdaptiveClass:Ljava/lang/Class;
      51: invokevirtual #218                // Method java/lang/Class.getName:()Ljava/lang/String;
      54: invokevirtual #98                 // Method java/lang/StringBuilder.append:(Ljava/lang/String;)Ljava/lang/StringBuilder;
      57: ldc_w         #376                // String ,
      60: invokevirtual #98                 // Method java/lang/StringBuilder.append:(Ljava/lang/String;)Ljava/lang/StringBuilder;
      63: aload_1
      64: invokevirtual #218                // Method java/lang/Class.getName:()Ljava/lang/String;
      67: invokevirtual #98                 // Method java/lang/StringBuilder.append:(Ljava/lang/String;)Ljava/lang/StringBuilder;
      70: invokevirtual #100                // Method java/lang/StringBuilder.toString:()Ljava/lang/String;
      73: invokespecial #105                // Method java/lang/IllegalStateException."<init>":(Ljava/lang/String;)V
      76: athrow
      77: return

  private void cacheWrapperClass(java.lang.Class<?>);
    Code:
       0: aload_0
       1: getfield      #236                // Field cachedWrapperClasses:Ljava/util/Set;
       4: ifnonnull     18
       7: aload_0
       8: new           #49                 // class org/apache/dubbo/common/utils/ConcurrentHashSet
      11: dup
      12: invokespecial #50                 // Method org/apache/dubbo/common/utils/ConcurrentHashSet."<init>":()V
      15: putfield      #236                // Field cachedWrapperClasses:Ljava/util/Set;
      18: aload_0
      19: getfield      #236                // Field cachedWrapperClasses:Ljava/util/Set;
      22: aload_1
      23: invokeinterface #368,  2          // InterfaceMethod java/util/Set.add:(Ljava/lang/Object;)Z
      28: pop
      29: return

  protected boolean isWrapperClass(java.lang.Class<?>);
    Code:
       0: aload_1
       1: invokevirtual #377                // Method java/lang/Class.getConstructors:()[Ljava/lang/reflect/Constructor;
       4: astore_2
       5: aload_2
       6: astore_3
       7: aload_3
       8: arraylength
       9: istore        4
      11: iconst_0
      12: istore        5
      14: iload         5
      16: iload         4
      18: if_icmpge     59
      21: aload_3
      22: iload         5
      24: aaload
      25: astore        6
      27: aload         6
      29: invokevirtual #378                // Method java/lang/reflect/Constructor.getParameterTypes:()[Ljava/lang/Class;
      32: arraylength
      33: iconst_1
      34: if_icmpne     53
      37: aload         6
      39: invokevirtual #378                // Method java/lang/reflect/Constructor.getParameterTypes:()[Ljava/lang/Class;
      42: iconst_0
      43: aaload
      44: aload_0
      45: getfield      #55                 // Field type:Ljava/lang/Class;
      48: if_acmpne     53
      51: iconst_1
      52: ireturn
      53: iinc          5, 1
      56: goto          14
      59: iconst_0
      60: ireturn

  private java.lang.String findAnnotationName(java.lang.Class<?>);
    Code:
       0: aload_1
       1: ldc_w         #379                // class org/apache/dubbo/common/Extension
       4: invokevirtual #240                // Method java/lang/Class.getAnnotation:(Ljava/lang/Class;)Ljava/lang/annotation/Annotation;
       7: checkcast     #379                // class org/apache/dubbo/common/Extension
      10: astore_2
      11: aload_2
      12: ifnull        22
      15: aload_2
      16: invokeinterface #380,  1          // InterfaceMethod org/apache/dubbo/common/Extension.value:()Ljava/lang/String;
      21: areturn
      22: aload_1
      23: invokevirtual #381                // Method java/lang/Class.getSimpleName:()Ljava/lang/String;
      26: astore_3
      27: aload_3
      28: aload_0
      29: getfield      #55                 // Field type:Ljava/lang/Class;
      32: invokevirtual #381                // Method java/lang/Class.getSimpleName:()Ljava/lang/String;
      35: invokevirtual #382                // Method java/lang/String.endsWith:(Ljava/lang/String;)Z
      38: ifeq          62
      41: aload_3
      42: iconst_0
      43: aload_3
      44: invokevirtual #277                // Method java/lang/String.length:()I
      47: aload_0
      48: getfield      #55                 // Field type:Ljava/lang/Class;
      51: invokevirtual #381                // Method java/lang/Class.getSimpleName:()Ljava/lang/String;
      54: invokevirtual #277                // Method java/lang/String.length:()I
      57: isub
      58: invokevirtual #278                // Method java/lang/String.substring:(II)Ljava/lang/String;
      61: astore_3
      62: aload_3
      63: invokevirtual #221                // Method java/lang/String.toLowerCase:()Ljava/lang/String;
      66: areturn

  private T createAdaptiveExtension();
    Code:
       0: aload_0
       1: invokespecial #383                // Method getAdaptiveExtensionClass:()Ljava/lang/Class;
       4: invokevirtual #384                // Method java/lang/Class.newInstance:()Ljava/lang/Object;
       7: astore_1
       8: aload_0
       9: aload_1
      10: aconst_null
      11: invokespecial #233                // Method postProcessBeforeInitialization:(Ljava/lang/Object;Ljava/lang/String;)Ljava/lang/Object;
      14: astore_1
      15: aload_0
      16: aload_1
      17: invokespecial #234                // Method injectExtension:(Ljava/lang/Object;)Ljava/lang/Object;
      20: pop
      21: aload_0
      22: aload_1
      23: aconst_null
      24: invokespecial #235                // Method postProcessAfterInitialization:(Ljava/lang/Object;Ljava/lang/String;)Ljava/lang/Object;
      27: astore_1
      28: aload_0
      29: aload_1
      30: invokespecial #248                // Method initExtension:(Ljava/lang/Object;)V
      33: aload_1
      34: areturn
      35: astore_1
      36: new           #103                // class java/lang/IllegalStateException
      39: dup
      40: new           #95                 // class java/lang/StringBuilder
      43: dup
      44: invokespecial #96                 // Method java/lang/StringBuilder."<init>":()V
      47: ldc_w         #385                // String Can\'t create adaptive extension
      50: invokevirtual #98                 // Method java/lang/StringBuilder.append:(Ljava/lang/String;)Ljava/lang/StringBuilder;
      53: aload_0
      54: getfield      #55                 // Field type:Ljava/lang/Class;
      57: invokevirtual #99                 // Method java/lang/StringBuilder.append:(Ljava/lang/Object;)Ljava/lang/StringBuilder;
      60: ldc_w         #338                // String , cause:
      63: invokevirtual #98                 // Method java/lang/StringBuilder.append:(Ljava/lang/String;)Ljava/lang/StringBuilder;
      66: aload_1
      67: invokevirtual #274                // Method java/lang/Exception.getMessage:()Ljava/lang/String;
      70: invokevirtual #98                 // Method java/lang/StringBuilder.append:(Ljava/lang/String;)Ljava/lang/StringBuilder;
      73: invokevirtual #100                // Method java/lang/StringBuilder.toString:()Ljava/lang/String;
      76: aload_1
      77: invokespecial #214                // Method java/lang/IllegalStateException."<init>":(Ljava/lang/String;Ljava/lang/Throwable;)V
      80: athrow
    Exception table:
       from    to  target type
           0    34    35   Class java/lang/Exception

  private java.lang.Class<?> getAdaptiveExtensionClass();
    Code:
       0: aload_0
       1: invokespecial #107                // Method getExtensionClasses:()Ljava/util/Map;
       4: pop
       5: aload_0
       6: getfield      #47                 // Field cachedAdaptiveClass:Ljava/lang/Class;
       9: ifnull        17
      12: aload_0
      13: getfield      #47                 // Field cachedAdaptiveClass:Ljava/lang/Class;
      16: areturn
      17: aload_0
      18: aload_0
      19: invokespecial #386                // Method createAdaptiveExtensionClass:()Ljava/lang/Class;
      22: dup_x1
      23: putfield      #47                 // Field cachedAdaptiveClass:Ljava/lang/Class;
      26: areturn

  private java.lang.Class<?> createAdaptiveExtensionClass();
    Code:
       0: aload_0
       1: getfield      #55                 // Field type:Ljava/lang/Class;
       4: invokevirtual #16                 // Method java/lang/Class.getClassLoader:()Ljava/lang/ClassLoader;
       7: astore_1
       8: invokestatic  #387                // Method org/apache/dubbo/common/utils/NativeUtils.isNative:()Z
      11: ifeq          45
      14: aload_1
      15: new           #95                 // class java/lang/StringBuilder
      18: dup
      19: invokespecial #96                 // Method java/lang/StringBuilder."<init>":()V
      22: aload_0
      23: getfield      #55                 // Field type:Ljava/lang/Class;
      26: invokevirtual #218                // Method java/lang/Class.getName:()Ljava/lang/String;
      29: invokevirtual #98                 // Method java/lang/StringBuilder.append:(Ljava/lang/String;)Ljava/lang/StringBuilder;
      32: ldc_w         #388                // String $Adaptive
      35: invokevirtual #98                 // Method java/lang/StringBuilder.append:(Ljava/lang/String;)Ljava/lang/StringBuilder;
      38: invokevirtual #100                // Method java/lang/StringBuilder.toString:()Ljava/lang/String;
      41: invokevirtual #389                // Method java/lang/ClassLoader.loadClass:(Ljava/lang/String;)Ljava/lang/Class;
      44: areturn
      45: goto          49
      48: astore_2
      49: new           #390                // class org/apache/dubbo/common/extension/AdaptiveClassCodeGenerator
      52: dup
      53: aload_0
      54: getfield      #55                 // Field type:Ljava/lang/Class;
      57: aload_0
      58: getfield      #181                // Field cachedDefaultName:Ljava/lang/String;
      61: invokespecial #391                // Method org/apache/dubbo/common/extension/AdaptiveClassCodeGenerator."<init>":(Ljava/lang/Class;Ljava/lang/String;)V
      64: invokevirtual #392                // Method org/apache/dubbo/common/extension/AdaptiveClassCodeGenerator.generate:()Ljava/lang/String;
      67: astore_2
      68: aload_0
      69: getfield      #56                 // Field extensionDirector:Lorg/apache/dubbo/common/extension/ExtensionDirector;
      72: ldc_w         #393                // class org/apache/dubbo/common/compiler/Compiler
      75: invokevirtual #61                 // Method org/apache/dubbo/common/extension/ExtensionDirector.getExtensionLoader:(Ljava/lang/Class;)Lorg/apache/dubbo/common/extension/ExtensionLoader;
      78: invokevirtual #62                 // Method getAdaptiveExtension:()Ljava/lang/Object;
      81: checkcast     #393                // class org/apache/dubbo/common/compiler/Compiler
      84: astore_3
      85: aload_3
      86: aload_0
      87: getfield      #55                 // Field type:Ljava/lang/Class;
      90: aload_2
      91: aload_1
      92: invokeinterface #394,  4          // InterfaceMethod org/apache/dubbo/common/compiler/Compiler.compile:(Ljava/lang/Class;Ljava/lang/String;Ljava/lang/ClassLoader;)Ljava/lang/Class;
      97: areturn
    Exception table:
       from    to  target type
           8    44    48   Class java/lang/Throwable

  public java.lang.String toString();
    Code:
       0: new           #95                 // class java/lang/StringBuilder
       3: dup
       4: invokespecial #96                 // Method java/lang/StringBuilder."<init>":()V
       7: aload_0
       8: invokevirtual #28                 // Method java/lang/Object.getClass:()Ljava/lang/Class;
      11: invokevirtual #218                // Method java/lang/Class.getName:()Ljava/lang/String;
      14: invokevirtual #98                 // Method java/lang/StringBuilder.append:(Ljava/lang/String;)Ljava/lang/StringBuilder;
      17: ldc_w         #395                // String [
      20: invokevirtual #98                 // Method java/lang/StringBuilder.append:(Ljava/lang/String;)Ljava/lang/StringBuilder;
      23: aload_0
      24: getfield      #55                 // Field type:Ljava/lang/Class;
      27: invokevirtual #218                // Method java/lang/Class.getName:()Ljava/lang/String;
      30: invokevirtual #98                 // Method java/lang/StringBuilder.append:(Ljava/lang/String;)Ljava/lang/StringBuilder;
      33: ldc_w         #396                // String ]
      36: invokevirtual #98                 // Method java/lang/StringBuilder.append:(Ljava/lang/String;)Ljava/lang/StringBuilder;
      39: invokevirtual #100                // Method java/lang/StringBuilder.toString:()Ljava/lang/String;
      42: areturn

  private static java.util.Properties loadProperties(java.lang.ClassLoader, java.lang.String);
    Code:
       0: new           #397                // class java/util/Properties
       3: dup
       4: invokespecial #398                // Method java/util/Properties."<init>":()V
       7: astore_2
       8: aload_0
       9: ifnull        149
      12: aload_0
      13: aload_1
      14: invokevirtual #399                // Method java/lang/ClassLoader.getResources:(Ljava/lang/String;)Ljava/util/Enumeration;
      17: astore_3
      18: aload_3
      19: invokeinterface #315,  1          // InterfaceMethod java/util/Enumeration.hasMoreElements:()Z
      24: ifeq          126
      27: aload_3
      28: invokeinterface #316,  1          // InterfaceMethod java/util/Enumeration.nextElement:()Ljava/lang/Object;
      33: checkcast     #317                // class java/net/URL
      36: astore        4
      38: aload         4
      40: invokestatic  #400                // Method loadFromUrl:(Ljava/net/URL;)Ljava/util/Properties;
      43: astore        5
      45: aload         5
      47: invokevirtual #401                // Method java/util/Properties.entrySet:()Ljava/util/Set;
      50: invokeinterface #126,  1          // InterfaceMethod java/util/Set.iterator:()Ljava/util/Iterator;
      55: astore        6
      57: aload         6
      59: invokeinterface #86,  1           // InterfaceMethod java/util/Iterator.hasNext:()Z
      64: ifeq          123
      67: aload         6
      69: invokeinterface #87,  1           // InterfaceMethod java/util/Iterator.next:()Ljava/lang/Object;
      74: checkcast     #127                // class java/util/Map$Entry
      77: astore        7
      79: aload         7
      81: invokeinterface #128,  1          // InterfaceMethod java/util/Map$Entry.getKey:()Ljava/lang/Object;
      86: invokevirtual #402                // Method java/lang/Object.toString:()Ljava/lang/String;
      89: astore        8
      91: aload_2
      92: aload         8
      94: invokevirtual #403                // Method java/util/Properties.containsKey:(Ljava/lang/Object;)Z
      97: ifeq          103
     100: goto          57
     103: aload_2
     104: aload         8
     106: aload         7
     108: invokeinterface #129,  1          // InterfaceMethod java/util/Map$Entry.getValue:()Ljava/lang/Object;
     113: invokevirtual #402                // Method java/lang/Object.toString:()Ljava/lang/String;
     116: invokevirtual #404                // Method java/util/Properties.put:(Ljava/lang/Object;Ljava/lang/Object;)Ljava/lang/Object;
     119: pop
     120: goto          57
     123: goto          18
     126: goto          149
     129: astore_3
     130: getstatic     #92                 // Field logger:Lorg/apache/dubbo/common/logger/ErrorTypeAwareLogger;
     133: ldc_w         #406                // String 5-5
     136: ldc           #94                 // String
     138: ldc           #94                 // String
     140: ldc_w         #407                // String load properties failed.
     143: aload_3
     144: invokeinterface #101,  6          // InterfaceMethod org/apache/dubbo/common/logger/ErrorTypeAwareLogger.error:(Ljava/lang/String;Ljava/lang/String;Ljava/lang/String;Ljava/lang/String;Ljava/lang/Throwable;)V
     149: aload_2
     150: areturn
    Exception table:
       from    to  target type
          12   126   129   Class java/io/IOException

  private static java.util.Properties loadFromUrl(java.net.URL);
    Code:
       0: new           #397                // class java/util/Properties
       3: dup
       4: invokespecial #398                // Method java/util/Properties."<init>":()V
       7: astore_1
       8: aconst_null
       9: astore_2
      10: aload_0
      11: invokevirtual #408                // Method java/net/URL.openStream:()Ljava/io/InputStream;
      14: astore_2
      15: aload_1
      16: aload_2
      17: invokevirtual #409                // Method java/util/Properties.load:(Ljava/io/InputStream;)V
      20: aload_2
      21: ifnull        69
      24: aload_2
      25: invokevirtual #410                // Method java/io/InputStream.close:()V
      28: goto          69
      31: astore_3
      32: goto          69
      35: astore_3
      36: aload_2
      37: ifnull        69
      40: aload_2
      41: invokevirtual #410                // Method java/io/InputStream.close:()V
      44: goto          69
      47: astore_3
      48: goto          69
      51: astore        4
      53: aload_2
      54: ifnull        66
      57: aload_2
      58: invokevirtual #410                // Method java/io/InputStream.close:()V
      61: goto          66
      64: astore        5
      66: aload         4
      68: athrow
      69: aload_1
      70: areturn
    Exception table:
       from    to  target type
          24    28    31   Class java/io/IOException
          10    20    35   Class java/io/IOException
          40    44    47   Class java/io/IOException
          10    20    51   any
          57    61    64   Class java/io/IOException
          51    53    51   any

  private static boolean lambda$loadClassIfActive$8(java.lang.ClassLoader, java.lang.String);
    Code:
       0: aload_1
       1: aload_0
       2: invokestatic  #411                // Method org/apache/dubbo/common/utils/ClassUtils.isPresent:(Ljava/lang/String;Ljava/lang/ClassLoader;)Z
       5: ireturn

  private static java.util.List lambda$getResourceContent$7(java.net.URL, java.net.URL);
    Code:
       0: new           #21                 // class java/util/ArrayList
       3: dup
       4: invokespecial #22                 // Method java/util/ArrayList."<init>":()V
       7: astore_2
       8: new           #412                // class java/io/BufferedReader
      11: dup
      12: new           #413                // class java/io/InputStreamReader
      15: dup
      16: aload_0
      17: invokevirtual #408                // Method java/net/URL.openStream:()Ljava/io/InputStream;
      20: getstatic     #414                // Field java/nio/charset/StandardCharsets.UTF_8:Ljava/nio/charset/Charset;
      23: invokespecial #415                // Method java/io/InputStreamReader."<init>":(Ljava/io/InputStream;Ljava/nio/charset/Charset;)V
      26: invokespecial #416                // Method java/io/BufferedReader."<init>":(Ljava/io/Reader;)V
      29: astore_3
      30: aconst_null
      31: astore        4
      33: aload_3
      34: invokevirtual #417                // Method java/io/BufferedReader.readLine:()Ljava/lang/String;
      37: dup
      38: astore        5
      40: ifnull        94
      43: aload         5
      45: bipush        35
      47: invokevirtual #328                // Method java/lang/String.indexOf:(I)I
      50: istore        6
      52: iload         6
      54: iflt          67
      57: aload         5
      59: iconst_0
      60: iload         6
      62: invokevirtual #278                // Method java/lang/String.substring:(II)Ljava/lang/String;
      65: astore        5
      67: aload         5
      69: invokevirtual #301                // Method java/lang/String.trim:()Ljava/lang/String;
      72: astore        5
      74: aload         5
      76: invokevirtual #277                // Method java/lang/String.length:()I
      79: ifle          91
      82: aload_2
      83: aload         5
      85: invokeinterface #187,  2          // InterfaceMethod java/util/List.add:(Ljava/lang/Object;)Z
      90: pop
      91: goto          33
      94: aload_3
      95: ifnull        175
      98: aload         4
     100: ifnull        122
     103: aload_3
     104: invokevirtual #418                // Method java/io/BufferedReader.close:()V
     107: goto          175
     110: astore        5
     112: aload         4
     114: aload         5
     116: invokevirtual #419                // Method java/lang/Throwable.addSuppressed:(Ljava/lang/Throwable;)V
     119: goto          175
     122: aload_3
     123: invokevirtual #418                // Method java/io/BufferedReader.close:()V
     126: goto          175
     129: astore        5
     131: aload         5
     133: astore        4
     135: aload         5
     137: athrow
     138: astore        7
     140: aload_3
     141: ifnull        172
     144: aload         4
     146: ifnull        168
     149: aload_3
     150: invokevirtual #418                // Method java/io/BufferedReader.close:()V
     153: goto          172
     156: astore        8
     158: aload         4
     160: aload         8
     162: invokevirtual #419                // Method java/lang/Throwable.addSuppressed:(Ljava/lang/Throwable;)V
     165: goto          172
     168: aload_3
     169: invokevirtual #418                // Method java/io/BufferedReader.close:()V
     172: aload         7
     174: athrow
     175: goto          192
     178: astore_3
     179: new           #420                // class java/lang/RuntimeException
     182: dup
     183: aload_3
     184: invokevirtual #421                // Method java/io/IOException.getMessage:()Ljava/lang/String;
     187: aload_3
     188: invokespecial #422                // Method java/lang/RuntimeException."<init>":(Ljava/lang/String;Ljava/lang/Throwable;)V
     191: athrow
     192: aload_2
     193: areturn
    Exception table:
       from    to  target type
         103   107   110   Class java/lang/Throwable
          33    94   129   Class java/lang/Throwable
          33    94   138   any
         149   153   156   Class java/lang/Throwable
         129   140   138   any
           8   175   178   Class java/io/IOException

  private void lambda$loadDirectoryInternal$6(java.util.Map, org.apache.dubbo.common.extension.LoadingStrategy, java.lang.ClassLoader, java.util.Set);
    Code:
       0: aload_0
       1: aload_1
       2: aload_2
       3: invokeinterface #318,  1          // InterfaceMethod org/apache/dubbo/common/extension/LoadingStrategy.overridden:()Z
       8: aload         4
      10: aload_3
      11: aload_2
      12: invokeinterface #319,  1          // InterfaceMethod org/apache/dubbo/common/extension/LoadingStrategy.includedPackages:()[Ljava/lang/String;
      17: aload_2
      18: invokeinterface #320,  1          // InterfaceMethod org/apache/dubbo/common/extension/LoadingStrategy.excludedPackages:()[Ljava/lang/String;
      23: aload_2
      24: invokeinterface #321,  1          // InterfaceMethod org/apache/dubbo/common/extension/LoadingStrategy.onlyExtensionClassLoaderPackages:()[Ljava/lang/String;
      29: invokespecial #423                // Method loadFromClass:(Ljava/util/Map;ZLjava/util/Set;Ljava/lang/ClassLoader;[Ljava/lang/String;[Ljava/lang/String;[Ljava/lang/String;)V
      32: return

  private static void lambda$getLoadedExtensionInstances$5(java.util.List, org.apache.dubbo.common.utils.Holder);
    Code:
       0: aload_0
       1: aload_1
       2: invokevirtual #88                 // Method org/apache/dubbo/common/utils/Holder.get:()Ljava/lang/Object;
       5: invokeinterface #187,  2          // InterfaceMethod java/util/List.add:(Ljava/lang/Object;)Z
      10: pop
      11: return

  private void lambda$getActivateExtension$4(java.lang.String, java.util.Set, org.apache.dubbo.common.URL, java.util.Map, java.lang.String, java.util.Set);
    Code:
       0: aload_0
       1: aload_1
       2: aload         6
       4: invokespecial #424                // Method isMatchGroup:(Ljava/lang/String;Ljava/util/Set;)Z
       7: ifeq          92
      10: aload_2
      11: aload         5
      13: invokeinterface #123,  2          // InterfaceMethod java/util/Set.contains:(Ljava/lang/Object;)Z
      18: ifne          92
      21: aload_2
      22: new           #95                 // class java/lang/StringBuilder
      25: dup
      26: invokespecial #96                 // Method java/lang/StringBuilder."<init>":()V
      29: ldc           #146                // String -
      31: invokevirtual #98                 // Method java/lang/StringBuilder.append:(Ljava/lang/String;)Ljava/lang/StringBuilder;
      34: aload         5
      36: invokevirtual #98                 // Method java/lang/StringBuilder.append:(Ljava/lang/String;)Ljava/lang/StringBuilder;
      39: invokevirtual #100                // Method java/lang/StringBuilder.toString:()Ljava/lang/String;
      42: invokeinterface #123,  2          // InterfaceMethod java/util/Set.contains:(Ljava/lang/Object;)Z
      47: ifne          92
      50: aload_0
      51: aload_0
      52: getfield      #44                 // Field cachedActivateValues:Ljava/util/Map;
      55: aload         5
      57: invokeinterface #229,  2          // InterfaceMethod java/util/Map.get:(Ljava/lang/Object;)Ljava/lang/Object;
      62: checkcast     #425                // class "[[Ljava/lang/String;"
      65: aload_3
      66: invokespecial #426                // Method isActive:([[Ljava/lang/String;Lorg/apache/dubbo/common/URL;)Z
      69: ifeq          92
      72: aload         4
      74: aload_0
      75: aload         5
      77: invokespecial #154                // Method getExtensionClass:(Ljava/lang/String;)Ljava/lang/Class;
      80: aload_0
      81: aload         5
      83: invokevirtual #152                // Method getExtension:(Ljava/lang/String;)Ljava/lang/Object;
      86: invokeinterface #136,  3          // InterfaceMethod java/util/Map.put:(Ljava/lang/Object;Ljava/lang/Object;)Ljava/lang/Object;
      91: pop
      92: return

  private static void lambda$destroy$3(java.lang.Class, java.lang.Object);
    Code:
       0: aload_1
       1: instanceof    #89                 // class org/apache/dubbo/common/resource/Disposable
       4: ifeq          56
       7: aload_1
       8: checkcast     #89                 // class org/apache/dubbo/common/resource/Disposable
      11: astore_2
      12: aload_2
      13: invokeinterface #90,  1           // InterfaceMethod org/apache/dubbo/common/resource/Disposable.destroy:()V
      18: goto          56
      21: astore_3
      22: getstatic     #92                 // Field logger:Lorg/apache/dubbo/common/logger/ErrorTypeAwareLogger;
      25: ldc           #93                 // String 0-15
      27: ldc           #94                 // String
      29: ldc           #94                 // String
      31: new           #95                 // class java/lang/StringBuilder
      34: dup
      35: invokespecial #96                 // Method java/lang/StringBuilder."<init>":()V
      38: ldc           #97                 // String Error destroying extension
      40: invokevirtual #98                 // Method java/lang/StringBuilder.append:(Ljava/lang/String;)Ljava/lang/StringBuilder;
      43: aload_2
      44: invokevirtual #99                 // Method java/lang/StringBuilder.append:(Ljava/lang/Object;)Ljava/lang/StringBuilder;
      47: invokevirtual #100                // Method java/lang/StringBuilder.toString:()Ljava/lang/String;
      50: aload_3
      51: invokeinterface #101,  6          // InterfaceMethod org/apache/dubbo/common/logger/ErrorTypeAwareLogger.error:(Ljava/lang/String;Ljava/lang/String;Ljava/lang/String;Ljava/lang/String;Ljava/lang/Throwable;)V
      56: return
    Exception table:
       from    to  target type
          12    18    21   Class java/lang/Exception

  private static org.apache.dubbo.common.beans.support.InstantiationStrategy lambda$initInstantiationStrategy$2(org.apache.dubbo.common.extension.ExtensionPostProcessor);
    Code:
       0: new           #73                 // class org/apache/dubbo/common/beans/support/InstantiationStrategy
       3: dup
       4: aload_0
       5: checkcast     #427                // class org/apache/dubbo/rpc/model/ScopeModelAccessor
       8: invokespecial #428                // Method org/apache/dubbo/common/beans/support/InstantiationStrategy."<init>":(Lorg/apache/dubbo/rpc/model/ScopeModelAccessor;)V
      11: areturn

  private static boolean lambda$initInstantiationStrategy$1(org.apache.dubbo.common.extension.ExtensionPostProcessor);
    Code:
       0: aload_0
       1: instanceof    #427                // class org/apache/dubbo/rpc/model/ScopeModelAccessor
       4: ireturn

  private static org.apache.dubbo.common.extension.LoadingStrategy[] lambda$loadLoadingStrategies$0(int);
    Code:
       0: iload_0
       1: anewarray     #5                  // class org/apache/dubbo/common/extension/LoadingStrategy
       4: areturn

  static {};
    Code:
       0: ldc           #15                 // class org/apache/dubbo/common/extension/ExtensionLoader
       2: invokestatic  #429                // Method org/apache/dubbo/common/logger/LoggerFactory.getErrorTypeAwareLogger:(Ljava/lang/Class;)Lorg/apache/dubbo/common/logger/ErrorTypeAwareLogger;
       5: putstatic     #92                 // Field logger:Lorg/apache/dubbo/common/logger/ErrorTypeAwareLogger;
       8: ldc_w         #430                // String \\s*[,]+\\s*
      11: invokestatic  #431                // Method java/util/regex/Pattern.compile:(Ljava/lang/String;)Ljava/util/regex/Pattern;
      14: putstatic     #302                // Field NAME_SEPARATOR:Ljava/util/regex/Pattern;
      17: invokestatic  #432                // Method loadLoadingStrategies:()[Lorg/apache/dubbo/common/extension/LoadingStrategy;
      20: putstatic     #4                  // Field strategies:[Lorg/apache/dubbo/common/extension/LoadingStrategy;
      23: invokestatic  #433                // Method getSpecialSPILoadingStrategyMap:()Ljava/util/Map;
      26: putstatic     #308                // Field specialSPILoadingStrategyMap:Ljava/util/Map;
      29: new           #342                // class java/lang/ref/SoftReference
      32: dup
      33: new           #13                 // class java/util/concurrent/ConcurrentHashMap
      36: dup
      37: invokespecial #14                 // Method java/util/concurrent/ConcurrentHashMap."<init>":()V
      40: invokespecial #343                // Method java/lang/ref/SoftReference."<init>":(Ljava/lang/Object;)V
      43: putstatic     #340                // Field urlListMapCache:Ljava/lang/ref/SoftReference;
      46: invokestatic  #434                // Method getIgnoredInjectMethodsDesc:()Ljava/util/List;
      49: putstatic     #262                // Field ignoredInjectMethodsDesc:Ljava/util/List;
      52: return
}
