Compiled from "LoadingStrategy.java"
public interface org.apache.dubbo.common.extension.LoadingStrategy extends org.apache.dubbo.common.lang.Prioritized {
  public static final java.lang.String ALL;

  public abstract java.lang.String directory();

  public default boolean preferExtensionClassLoader();
    Code:
       0: iconst_0
       1: ireturn

  public default java.lang.String[] excludedPackages();
    Code:
       0: aconst_null
       1: areturn

  public default java.lang.String[] includedPackages();
    Code:
       0: aconst_null
       1: areturn

  public default java.lang.String[] includedPackagesInCompatibleType();
    Code:
       0: aconst_null
       1: areturn

  public default java.lang.String[] onlyExtensionClassLoaderPackages();
    Code:
       0: iconst_0
       1: anewarray     #1                  // class java/lang/String
       4: areturn

  public default boolean overridden();
    Code:
       0: iconst_0
       1: ireturn

  public default java.lang.String getName();
    Code:
       0: aload_0
       1: invokevirtual #2                  // Method java/lang/Object.getClass:()Ljava/lang/Class;
       4: invokevirtual #3                  // Method java/lang/Class.getSimpleName:()Ljava/lang/String;
       7: areturn
}
