Compiled from "ServicesLoadingStrategy.java"
public class org.apache.dubbo.common.extension.ServicesLoadingStrategy implements org.apache.dubbo.common.extension.LoadingStrategy {
  public org.apache.dubbo.common.extension.ServicesLoadingStrategy();
    Code:
       0: aload_0
       1: invokespecial #1                  // Method java/lang/Object."<init>":()V
       4: return

  public java.lang.String directory();
    Code:
       0: ldc           #2                  // String META-INF/services/
       2: areturn

  public boolean overridden();
    Code:
       0: iconst_1
       1: ireturn

  public int getPriority();
    Code:
       0: ldc           #4                  // int 2147483647
       2: ireturn

  public java.lang.String getName();
    Code:
       0: ldc           #5                  // String SERVICES
       2: areturn
}
