Compiled from "NettyConfigOperator.java"
public class org.apache.dubbo.remoting.transport.netty4.NettyConfigOperator implements org.apache.dubbo.remoting.api.pu.ChannelOperator {
  private final org.apache.dubbo.remoting.Channel channel;

  private org.apache.dubbo.remoting.ChannelHandler handler;

  public org.apache.dubbo.remoting.transport.netty4.NettyConfigOperator(org.apache.dubbo.remoting.transport.netty4.NettyChannel, org.apache.dubbo.remoting.ChannelHandler);
    Code:
       0: aload_0
       1: invokespecial #1                  // Method java/lang/Object."<init>":()V
       4: aload_0
       5: aload_1
       6: putfield      #2                  // Field channel:Lorg/apache/dubbo/remoting/Channel;
       9: aload_0
      10: aload_2
      11: putfield      #3                  // Field handler:Lorg/apache/dubbo/remoting/ChannelHandler;
      14: return

  public void configChannelHandler(java.util.List<org.apache.dubbo.remoting.ChannelHandler>);
    Code:
       0: aload_0
       1: getfield      #2                  // Field channel:Lorg/apache/dubbo/remoting/Channel;
       4: invokeinterface #4,  1            // InterfaceMethod org/apache/dubbo/remoting/Channel.getUrl:()Lorg/apache/dubbo/common/URL;
       9: astore_2
      10: aload_2
      11: ldc           #6                  // String codec
      13: invokevirtual #7                  // Method org/apache/dubbo/common/URL.getParameter:(Ljava/lang/String;)Ljava/lang/String;
      16: astore        4
      18: aload         4
      20: invokestatic  #8                  // Method org/apache/dubbo/common/utils/StringUtils.isEmpty:(Ljava/lang/String;)Z
      23: ifeq          32
      26: aload_2
      27: invokevirtual #9                  // Method org/apache/dubbo/common/URL.getProtocol:()Ljava/lang/String;
      30: astore        4
      32: aload_2
      33: invokevirtual #10                 // Method org/apache/dubbo/common/URL.getOrDefaultFrameworkModel:()Lorg/apache/dubbo/rpc/model/FrameworkModel;
      36: ldc           #11                 // class org/apache/dubbo/remoting/Codec2
      38: invokevirtual #12                 // Method org/apache/dubbo/rpc/model/FrameworkModel.getExtensionLoader:(Ljava/lang/Class;)Lorg/apache/dubbo/common/extension/ExtensionLoader;
      41: aload         4
      43: invokevirtual #13                 // Method org/apache/dubbo/common/extension/ExtensionLoader.hasExtension:(Ljava/lang/String;)Z
      46: ifeq          70
      49: aload_2
      50: invokevirtual #10                 // Method org/apache/dubbo/common/URL.getOrDefaultFrameworkModel:()Lorg/apache/dubbo/rpc/model/FrameworkModel;
      53: ldc           #11                 // class org/apache/dubbo/remoting/Codec2
      55: invokevirtual #12                 // Method org/apache/dubbo/rpc/model/FrameworkModel.getExtensionLoader:(Ljava/lang/Class;)Lorg/apache/dubbo/common/extension/ExtensionLoader;
      58: aload         4
      60: invokevirtual #14                 // Method org/apache/dubbo/common/extension/ExtensionLoader.getExtension:(Ljava/lang/String;)Ljava/lang/Object;
      63: checkcast     #11                 // class org/apache/dubbo/remoting/Codec2
      66: astore_3
      67: goto          133
      70: aload_2
      71: invokevirtual #10                 // Method org/apache/dubbo/common/URL.getOrDefaultFrameworkModel:()Lorg/apache/dubbo/rpc/model/FrameworkModel;
      74: ldc           #15                 // class org/apache/dubbo/remoting/Codec
      76: invokevirtual #12                 // Method org/apache/dubbo/rpc/model/FrameworkModel.getExtensionLoader:(Ljava/lang/Class;)Lorg/apache/dubbo/common/extension/ExtensionLoader;
      79: aload         4
      81: invokevirtual #13                 // Method org/apache/dubbo/common/extension/ExtensionLoader.hasExtension:(Ljava/lang/String;)Z
      84: ifeq          115
      87: new           #16                 // class org/apache/dubbo/remoting/transport/codec/CodecAdapter
      90: dup
      91: aload_2
      92: invokevirtual #10                 // Method org/apache/dubbo/common/URL.getOrDefaultFrameworkModel:()Lorg/apache/dubbo/rpc/model/FrameworkModel;
      95: ldc           #15                 // class org/apache/dubbo/remoting/Codec
      97: invokevirtual #12                 // Method org/apache/dubbo/rpc/model/FrameworkModel.getExtensionLoader:(Ljava/lang/Class;)Lorg/apache/dubbo/common/extension/ExtensionLoader;
     100: aload         4
     102: invokevirtual #14                 // Method org/apache/dubbo/common/extension/ExtensionLoader.getExtension:(Ljava/lang/String;)Ljava/lang/Object;
     105: checkcast     #15                 // class org/apache/dubbo/remoting/Codec
     108: invokespecial #17                 // Method org/apache/dubbo/remoting/transport/codec/CodecAdapter."<init>":(Lorg/apache/dubbo/remoting/Codec;)V
     111: astore_3
     112: goto          133
     115: aload_2
     116: invokevirtual #10                 // Method org/apache/dubbo/common/URL.getOrDefaultFrameworkModel:()Lorg/apache/dubbo/rpc/model/FrameworkModel;
     119: ldc           #11                 // class org/apache/dubbo/remoting/Codec2
     121: invokevirtual #12                 // Method org/apache/dubbo/rpc/model/FrameworkModel.getExtensionLoader:(Ljava/lang/Class;)Lorg/apache/dubbo/common/extension/ExtensionLoader;
     124: ldc           #18                 // String default
     126: invokevirtual #14                 // Method org/apache/dubbo/common/extension/ExtensionLoader.getExtension:(Ljava/lang/String;)Ljava/lang/Object;
     129: checkcast     #11                 // class org/apache/dubbo/remoting/Codec2
     132: astore_3
     133: aload_3
     134: instanceof    #19                 // class org/apache/dubbo/remoting/api/pu/DefaultCodec
     137: ifne          224
     140: aload_0
     141: getfield      #2                  // Field channel:Lorg/apache/dubbo/remoting/Channel;
     144: checkcast     #20                 // class org/apache/dubbo/remoting/transport/netty4/NettyChannel
     147: aload_3
     148: invokevirtual #21                 // Method org/apache/dubbo/remoting/transport/netty4/NettyChannel.setCodec:(Lorg/apache/dubbo/remoting/Codec2;)V
     151: new           #22                 // class org/apache/dubbo/remoting/transport/netty4/NettyCodecAdapter
     154: dup
     155: aload_3
     156: aload_0
     157: getfield      #2                  // Field channel:Lorg/apache/dubbo/remoting/Channel;
     160: invokeinterface #4,  1            // InterfaceMethod org/apache/dubbo/remoting/Channel.getUrl:()Lorg/apache/dubbo/common/URL;
     165: aload_0
     166: getfield      #3                  // Field handler:Lorg/apache/dubbo/remoting/ChannelHandler;
     169: invokespecial #23                 // Method org/apache/dubbo/remoting/transport/netty4/NettyCodecAdapter."<init>":(Lorg/apache/dubbo/remoting/Codec2;Lorg/apache/dubbo/common/URL;Lorg/apache/dubbo/remoting/ChannelHandler;)V
     172: astore        5
     174: aload_0
     175: getfield      #2                  // Field channel:Lorg/apache/dubbo/remoting/Channel;
     178: checkcast     #20                 // class org/apache/dubbo/remoting/transport/netty4/NettyChannel
     181: invokevirtual #24                 // Method org/apache/dubbo/remoting/transport/netty4/NettyChannel.getNioChannel:()Lio/netty/channel/Channel;
     184: invokeinterface #25,  1           // InterfaceMethod io/netty/channel/Channel.pipeline:()Lio/netty/channel/ChannelPipeline;
     189: iconst_1
     190: anewarray     #26                 // class io/netty/channel/ChannelHandler
     193: dup
     194: iconst_0
     195: aload         5
     197: invokevirtual #27                 // Method org/apache/dubbo/remoting/transport/netty4/NettyCodecAdapter.getDecoder:()Lio/netty/channel/ChannelHandler;
     200: aastore
     201: invokeinterface #28,  2           // InterfaceMethod io/netty/channel/ChannelPipeline.addLast:([Lio/netty/channel/ChannelHandler;)Lio/netty/channel/ChannelPipeline;
     206: iconst_1
     207: anewarray     #26                 // class io/netty/channel/ChannelHandler
     210: dup
     211: iconst_0
     212: aload         5
     214: invokevirtual #29                 // Method org/apache/dubbo/remoting/transport/netty4/NettyCodecAdapter.getEncoder:()Lio/netty/channel/ChannelHandler;
     217: aastore
     218: invokeinterface #28,  2           // InterfaceMethod io/netty/channel/ChannelPipeline.addLast:([Lio/netty/channel/ChannelHandler;)Lio/netty/channel/ChannelPipeline;
     223: pop
     224: aload_1
     225: invokeinterface #30,  1           // InterfaceMethod java/util/List.iterator:()Ljava/util/Iterator;
     230: astore        5
     232: aload         5
     234: invokeinterface #31,  1           // InterfaceMethod java/util/Iterator.hasNext:()Z
     239: ifeq          316
     242: aload         5
     244: invokeinterface #32,  1           // InterfaceMethod java/util/Iterator.next:()Ljava/lang/Object;
     249: checkcast     #33                 // class org/apache/dubbo/remoting/ChannelHandler
     252: astore        6
     254: aload         6
     256: instanceof    #34                 // class org/apache/dubbo/remoting/api/pu/ChannelHandlerPretender
     259: ifeq          313
     262: aload         6
     264: checkcast     #34                 // class org/apache/dubbo/remoting/api/pu/ChannelHandlerPretender
     267: invokevirtual #35                 // Method org/apache/dubbo/remoting/api/pu/ChannelHandlerPretender.getRealHandler:()Ljava/lang/Object;
     270: astore        7
     272: aload         7
     274: instanceof    #26                 // class io/netty/channel/ChannelHandler
     277: ifeq          313
     280: aload_0
     281: getfield      #2                  // Field channel:Lorg/apache/dubbo/remoting/Channel;
     284: checkcast     #20                 // class org/apache/dubbo/remoting/transport/netty4/NettyChannel
     287: invokevirtual #24                 // Method org/apache/dubbo/remoting/transport/netty4/NettyChannel.getNioChannel:()Lio/netty/channel/Channel;
     290: invokeinterface #25,  1           // InterfaceMethod io/netty/channel/Channel.pipeline:()Lio/netty/channel/ChannelPipeline;
     295: iconst_1
     296: anewarray     #26                 // class io/netty/channel/ChannelHandler
     299: dup
     300: iconst_0
     301: aload         7
     303: checkcast     #26                 // class io/netty/channel/ChannelHandler
     306: aastore
     307: invokeinterface #28,  2           // InterfaceMethod io/netty/channel/ChannelPipeline.addLast:([Lio/netty/channel/ChannelHandler;)Lio/netty/channel/ChannelPipeline;
     312: pop
     313: goto          232
     316: aload_0
     317: aload_0
     318: getfield      #2                  // Field channel:Lorg/apache/dubbo/remoting/Channel;
     321: invokespecial #36                 // Method isClientSide:(Lorg/apache/dubbo/remoting/Channel;)Z
     324: ifeq          330
     327: goto          382
     330: new           #37                 // class org/apache/dubbo/remoting/transport/netty4/NettyServerHandler
     333: dup
     334: aload_0
     335: getfield      #2                  // Field channel:Lorg/apache/dubbo/remoting/Channel;
     338: invokeinterface #4,  1            // InterfaceMethod org/apache/dubbo/remoting/Channel.getUrl:()Lorg/apache/dubbo/common/URL;
     343: aload_0
     344: getfield      #3                  // Field handler:Lorg/apache/dubbo/remoting/ChannelHandler;
     347: invokespecial #38                 // Method org/apache/dubbo/remoting/transport/netty4/NettyServerHandler."<init>":(Lorg/apache/dubbo/common/URL;Lorg/apache/dubbo/remoting/ChannelHandler;)V
     350: astore        5
     352: aload_0
     353: getfield      #2                  // Field channel:Lorg/apache/dubbo/remoting/Channel;
     356: checkcast     #20                 // class org/apache/dubbo/remoting/transport/netty4/NettyChannel
     359: invokevirtual #24                 // Method org/apache/dubbo/remoting/transport/netty4/NettyChannel.getNioChannel:()Lio/netty/channel/Channel;
     362: invokeinterface #25,  1           // InterfaceMethod io/netty/channel/Channel.pipeline:()Lio/netty/channel/ChannelPipeline;
     367: iconst_1
     368: anewarray     #26                 // class io/netty/channel/ChannelHandler
     371: dup
     372: iconst_0
     373: aload         5
     375: aastore
     376: invokeinterface #28,  2           // InterfaceMethod io/netty/channel/ChannelPipeline.addLast:([Lio/netty/channel/ChannelHandler;)Lio/netty/channel/ChannelPipeline;
     381: pop
     382: return

  private boolean isClientSide(org.apache.dubbo.remoting.Channel);
    Code:
       0: aload_1
       1: invokeinterface #4,  1            // InterfaceMethod org/apache/dubbo/remoting/Channel.getUrl:()Lorg/apache/dubbo/common/URL;
       6: ldc           #39                 // String
       8: invokevirtual #40                 // Method org/apache/dubbo/common/URL.getSide:(Ljava/lang/String;)Ljava/lang/String;
      11: ldc           #42                 // String consumer
      13: invokevirtual #43                 // Method java/lang/String.equalsIgnoreCase:(Ljava/lang/String;)Z
      16: ireturn
}
