Compiled from "NettyConnectionClient.java"
class org.apache.dubbo.remoting.transport.netty4.NettyConnectionClient$1 extends io.netty.channel.ChannelInitializer<io.netty.channel.socket.SocketChannel> {
  final io.netty.handler.ssl.SslContext val$sslContext;

  final org.apache.dubbo.remoting.transport.netty4.NettyConnectionHandler val$connectionHandler;

  final org.apache.dubbo.remoting.transport.netty4.NettyConnectionClient this$0;

  org.apache.dubbo.remoting.transport.netty4.NettyConnectionClient$1(org.apache.dubbo.remoting.transport.netty4.NettyConnectionClient, io.netty.handler.ssl.SslContext, org.apache.dubbo.remoting.transport.netty4.NettyConnectionHandler);
    Code:
       0: aload_0
       1: aload_1
       2: putfield      #1                  // Field this$0:Lorg/apache/dubbo/remoting/transport/netty4/NettyConnectionClient;
       5: aload_0
       6: aload_2
       7: putfield      #2                  // Field val$sslContext:Lio/netty/handler/ssl/SslContext;
      10: aload_0
      11: aload_3
      12: putfield      #3                  // Field val$connectionHandler:Lorg/apache/dubbo/remoting/transport/netty4/NettyConnectionHandler;
      15: aload_0
      16: invokespecial #4                  // Method io/netty/channel/ChannelInitializer."<init>":()V
      19: return

  protected void initChannel(io.netty.channel.socket.SocketChannel);
    Code:
       0: aload_1
       1: aload_0
       2: getfield      #1                  // Field this$0:Lorg/apache/dubbo/remoting/transport/netty4/NettyConnectionClient;
       5: invokevirtual #5                  // Method org/apache/dubbo/remoting/transport/netty4/NettyConnectionClient.getUrl:()Lorg/apache/dubbo/common/URL;
       8: aload_0
       9: getfield      #1                  // Field this$0:Lorg/apache/dubbo/remoting/transport/netty4/NettyConnectionClient;
      12: invokevirtual #6                  // Method org/apache/dubbo/remoting/transport/netty4/NettyConnectionClient.getChannelHandler:()Lorg/apache/dubbo/remoting/ChannelHandler;
      15: invokestatic  #7                  // Method org/apache/dubbo/remoting/transport/netty4/NettyChannel.getOrAddChannel:(Lio/netty/channel/Channel;Lorg/apache/dubbo/common/URL;Lorg/apache/dubbo/remoting/ChannelHandler;)Lorg/apache/dubbo/remoting/transport/netty4/NettyChannel;
      18: astore_2
      19: aload_1
      20: invokeinterface #8,  1            // InterfaceMethod io/netty/channel/socket/SocketChannel.pipeline:()Lio/netty/channel/ChannelPipeline;
      25: astore_3
      26: new           #9                  // class org/apache/dubbo/remoting/transport/netty4/NettySslContextOperator
      29: dup
      30: invokespecial #10                 // Method org/apache/dubbo/remoting/transport/netty4/NettySslContextOperator."<init>":()V
      33: astore        4
      35: aload_0
      36: getfield      #2                  // Field val$sslContext:Lio/netty/handler/ssl/SslContext;
      39: ifnull        62
      42: aload_3
      43: ldc           #11                 // String negotiation
      45: new           #12                 // class org/apache/dubbo/remoting/transport/netty4/ssl/SslClientTlsHandler
      48: dup
      49: aload_0
      50: getfield      #2                  // Field val$sslContext:Lio/netty/handler/ssl/SslContext;
      53: invokespecial #13                 // Method org/apache/dubbo/remoting/transport/netty4/ssl/SslClientTlsHandler."<init>":(Lio/netty/handler/ssl/SslContext;)V
      56: invokeinterface #14,  3           // InterfaceMethod io/netty/channel/ChannelPipeline.addLast:(Ljava/lang/String;Lio/netty/channel/ChannelHandler;)Lio/netty/channel/ChannelPipeline;
      61: pop
      62: aload_3
      63: ldc           #15                 // String connectionHandler
      65: aload_0
      66: getfield      #3                  // Field val$connectionHandler:Lorg/apache/dubbo/remoting/transport/netty4/NettyConnectionHandler;
      69: invokeinterface #14,  3           // InterfaceMethod io/netty/channel/ChannelPipeline.addLast:(Ljava/lang/String;Lio/netty/channel/ChannelHandler;)Lio/netty/channel/ChannelPipeline;
      74: pop
      75: new           #16                 // class org/apache/dubbo/remoting/transport/netty4/NettyConfigOperator
      78: dup
      79: aload_2
      80: aload_0
      81: getfield      #1                  // Field this$0:Lorg/apache/dubbo/remoting/transport/netty4/NettyConnectionClient;
      84: invokevirtual #6                  // Method org/apache/dubbo/remoting/transport/netty4/NettyConnectionClient.getChannelHandler:()Lorg/apache/dubbo/remoting/ChannelHandler;
      87: invokespecial #17                 // Method org/apache/dubbo/remoting/transport/netty4/NettyConfigOperator."<init>":(Lorg/apache/dubbo/remoting/transport/netty4/NettyChannel;Lorg/apache/dubbo/remoting/ChannelHandler;)V
      90: astore        5
      92: aload_0
      93: getfield      #1                  // Field this$0:Lorg/apache/dubbo/remoting/transport/netty4/NettyConnectionClient;
      96: invokestatic  #18                 // Method org/apache/dubbo/remoting/transport/netty4/NettyConnectionClient.access$000:(Lorg/apache/dubbo/remoting/transport/netty4/NettyConnectionClient;)Lorg/apache/dubbo/remoting/api/WireProtocol;
      99: aload_0
     100: getfield      #1                  // Field this$0:Lorg/apache/dubbo/remoting/transport/netty4/NettyConnectionClient;
     103: invokevirtual #5                  // Method org/apache/dubbo/remoting/transport/netty4/NettyConnectionClient.getUrl:()Lorg/apache/dubbo/common/URL;
     106: aload         5
     108: aload         4
     110: invokeinterface #19,  4           // InterfaceMethod org/apache/dubbo/remoting/api/WireProtocol.configClientPipeline:(Lorg/apache/dubbo/common/URL;Lorg/apache/dubbo/remoting/api/pu/ChannelOperator;Lorg/apache/dubbo/remoting/api/ssl/ContextOperator;)V
     115: return

  protected void initChannel(io.netty.channel.Channel) throws java.lang.Exception;
    Code:
       0: aload_0
       1: aload_1
       2: checkcast     #20                 // class io/netty/channel/socket/SocketChannel
       5: invokevirtual #21                 // Method initChannel:(Lio/netty/channel/socket/SocketChannel;)V
       8: return
}
