Compiled from "NettyConnectionClient.java"
class org.apache.dubbo.remoting.transport.netty4.NettyConnectionClient$ConnectionListener implements io.netty.channel.ChannelFutureListener {
  final org.apache.dubbo.remoting.transport.netty4.NettyConnectionClient this$0;

  org.apache.dubbo.remoting.transport.netty4.NettyConnectionClient$ConnectionListener(org.apache.dubbo.remoting.transport.netty4.NettyConnectionClient);
    Code:
       0: aload_0
       1: aload_1
       2: putfield      #2                  // Field this$0:Lorg/apache/dubbo/remoting/transport/netty4/NettyConnectionClient;
       5: aload_0
       6: invokespecial #3                  // Method java/lang/Object."<init>":()V
       9: return

  public void operationComplete(io.netty.channel.ChannelFuture);
    Code:
       0: aload_1
       1: invokeinterface #4,  1            // InterfaceMethod io/netty/channel/ChannelFuture.isSuccess:()Z
       6: ifeq          10
       9: return
      10: aload_0
      11: getfield      #2                  // Field this$0:Lorg/apache/dubbo/remoting/transport/netty4/NettyConnectionClient;
      14: astore_2
      15: aload_2
      16: invokevirtual #5                  // Method org/apache/dubbo/remoting/transport/netty4/NettyConnectionClient.isClosed:()Z
      19: ifne          31
      22: aload_2
      23: invokevirtual #6                  // Method org/apache/dubbo/remoting/transport/netty4/NettyConnectionClient.getCounter:()J
      26: lconst_0
      27: lcmp
      28: ifne          76
      31: invokestatic  #7                  // Method org/apache/dubbo/remoting/transport/netty4/NettyConnectionClient.access$100:()Lorg/apache/dubbo/common/logger/ErrorTypeAwareLogger;
      34: invokeinterface #8,  1            // InterfaceMethod org/apache/dubbo/common/logger/ErrorTypeAwareLogger.isDebugEnabled:()Z
      39: ifeq          75
      42: invokestatic  #7                  // Method org/apache/dubbo/remoting/transport/netty4/NettyConnectionClient.access$100:()Lorg/apache/dubbo/common/logger/ErrorTypeAwareLogger;
      45: ldc           #9                  // String %s aborted to reconnect. %s
      47: iconst_2
      48: anewarray     #10                 // class java/lang/Object
      51: dup
      52: iconst_0
      53: aload_2
      54: aastore
      55: dup
      56: iconst_1
      57: aload_1
      58: invokeinterface #11,  1           // InterfaceMethod io/netty/channel/ChannelFuture.cause:()Ljava/lang/Throwable;
      63: invokevirtual #12                 // Method java/lang/Throwable.getMessage:()Ljava/lang/String;
      66: aastore
      67: invokestatic  #13                 // Method java/lang/String.format:(Ljava/lang/String;[Ljava/lang/Object;)Ljava/lang/String;
      70: invokeinterface #14,  2           // InterfaceMethod org/apache/dubbo/common/logger/ErrorTypeAwareLogger.debug:(Ljava/lang/String;)V
      75: return
      76: invokestatic  #7                  // Method org/apache/dubbo/remoting/transport/netty4/NettyConnectionClient.access$100:()Lorg/apache/dubbo/common/logger/ErrorTypeAwareLogger;
      79: invokeinterface #8,  1            // InterfaceMethod org/apache/dubbo/common/logger/ErrorTypeAwareLogger.isDebugEnabled:()Z
      84: ifeq          127
      87: invokestatic  #7                  // Method org/apache/dubbo/remoting/transport/netty4/NettyConnectionClient.access$100:()Lorg/apache/dubbo/common/logger/ErrorTypeAwareLogger;
      90: ldc           #15                 // String %s is reconnecting, attempt=%d cause=%s
      92: iconst_3
      93: anewarray     #10                 // class java/lang/Object
      96: dup
      97: iconst_0
      98: aload_2
      99: aastore
     100: dup
     101: iconst_1
     102: iconst_0
     103: invokestatic  #16                 // Method java/lang/Integer.valueOf:(I)Ljava/lang/Integer;
     106: aastore
     107: dup
     108: iconst_2
     109: aload_1
     110: invokeinterface #11,  1           // InterfaceMethod io/netty/channel/ChannelFuture.cause:()Ljava/lang/Throwable;
     115: invokevirtual #12                 // Method java/lang/Throwable.getMessage:()Ljava/lang/String;
     118: aastore
     119: invokestatic  #13                 // Method java/lang/String.format:(Ljava/lang/String;[Ljava/lang/Object;)Ljava/lang/String;
     122: invokeinterface #14,  2           // InterfaceMethod org/apache/dubbo/common/logger/ErrorTypeAwareLogger.debug:(Ljava/lang/String;)V
     127: aload_1
     128: invokeinterface #17,  1           // InterfaceMethod io/netty/channel/ChannelFuture.channel:()Lio/netty/channel/Channel;
     133: invokeinterface #18,  1           // InterfaceMethod io/netty/channel/Channel.eventLoop:()Lio/netty/channel/EventLoop;
     138: astore_3
     139: aload_3
     140: aload_0
     141: aload_2
     142: invokedynamic #19,  0             // InvokeDynamic #0:run:(Lorg/apache/dubbo/remoting/transport/netty4/NettyConnectionClient$ConnectionListener;Lorg/apache/dubbo/remoting/transport/netty4/NettyConnectionClient;)Ljava/lang/Runnable;
     147: lconst_1
     148: getstatic     #20                 // Field java/util/concurrent/TimeUnit.SECONDS:Ljava/util/concurrent/TimeUnit;
     151: invokeinterface #21,  5           // InterfaceMethod io/netty/channel/EventLoop.schedule:(Ljava/lang/Runnable;JLjava/util/concurrent/TimeUnit;)Lio/netty/util/concurrent/ScheduledFuture;
     156: pop
     157: return

  public void operationComplete(io.netty.util.concurrent.Future) throws java.lang.Exception;
    Code:
       0: aload_0
       1: aload_1
       2: checkcast     #22                 // class io/netty/channel/ChannelFuture
       5: invokevirtual #23                 // Method operationComplete:(Lio/netty/channel/ChannelFuture;)V
       8: return

  private void lambda$operationComplete$0(org.apache.dubbo.remoting.transport.netty4.NettyConnectionClient);
    Code:
       0: aload_1
       1: invokevirtual #24                 // Method org/apache/dubbo/remoting/transport/netty4/NettyConnectionClient.doConnect:()V
       4: goto          47
       7: astore_2
       8: invokestatic  #7                  // Method org/apache/dubbo/remoting/transport/netty4/NettyConnectionClient.access$100:()Lorg/apache/dubbo/common/logger/ErrorTypeAwareLogger;
      11: ldc           #26                 // String 6-16
      13: ldc           #27                 // String
      15: ldc           #27                 // String
      17: new           #28                 // class java/lang/StringBuilder
      20: dup
      21: invokespecial #29                 // Method java/lang/StringBuilder."<init>":()V
      24: ldc           #30                 // String Failed to connect to server:
      26: invokevirtual #31                 // Method java/lang/StringBuilder.append:(Ljava/lang/String;)Ljava/lang/StringBuilder;
      29: aload_0
      30: getfield      #2                  // Field this$0:Lorg/apache/dubbo/remoting/transport/netty4/NettyConnectionClient;
      33: invokevirtual #32                 // Method org/apache/dubbo/remoting/transport/netty4/NettyConnectionClient.getConnectAddress:()Ljava/net/InetSocketAddress;
      36: invokevirtual #33                 // Method java/lang/StringBuilder.append:(Ljava/lang/Object;)Ljava/lang/StringBuilder;
      39: invokevirtual #34                 // Method java/lang/StringBuilder.toString:()Ljava/lang/String;
      42: invokeinterface #35,  5           // InterfaceMethod org/apache/dubbo/common/logger/ErrorTypeAwareLogger.error:(Ljava/lang/String;Ljava/lang/String;Ljava/lang/String;Ljava/lang/String;)V
      47: return
    Exception table:
       from    to  target type
           0     4     7   Class org/apache/dubbo/remoting/RemotingException
}
