Compiled from "Netty4BatchWriteQueue.java"
class org.apache.dubbo.remoting.transport.netty4.Netty4BatchWriteQueue$1 implements io.netty.channel.ChannelFutureListener {
  final org.apache.dubbo.remoting.transport.netty4.Netty4BatchWriteQueue this$0;

  org.apache.dubbo.remoting.transport.netty4.Netty4BatchWriteQueue$1(org.apache.dubbo.remoting.transport.netty4.Netty4BatchWriteQueue);
    Code:
       0: aload_0
       1: aload_1
       2: putfield      #1                  // Field this$0:Lorg/apache/dubbo/remoting/transport/netty4/Netty4BatchWriteQueue;
       5: aload_0
       6: invokespecial #2                  // Method java/lang/Object."<init>":()V
       9: return

  public void operationComplete(io.netty.channel.ChannelFuture) throws java.lang.Exception;
    Code:
       0: aload_0
       1: getfield      #1                  // Field this$0:Lorg/apache/dubbo/remoting/transport/netty4/Netty4BatchWriteQueue;
       4: invokestatic  #3                  // Method org/apache/dubbo/remoting/transport/netty4/Netty4BatchWriteQueue.access$200:(Lorg/apache/dubbo/remoting/transport/netty4/Netty4BatchWriteQueue;)Ljava/util/Queue;
       7: invokeinterface #4,  1            // InterfaceMethod java/util/Queue.poll:()Ljava/lang/Object;
      12: checkcast     #5                  // class io/netty/channel/ChannelPromise
      15: dup
      16: astore_2
      17: ifnull        55
      20: aload_1
      21: invokeinterface #6,  1            // InterfaceMethod io/netty/channel/ChannelFuture.isSuccess:()Z
      26: ifeq          39
      29: aload_2
      30: invokeinterface #7,  1            // InterfaceMethod io/netty/channel/ChannelPromise.setSuccess:()Lio/netty/channel/ChannelPromise;
      35: pop
      36: goto          0
      39: aload_2
      40: aload_1
      41: invokeinterface #8,  1            // InterfaceMethod io/netty/channel/ChannelFuture.cause:()Ljava/lang/Throwable;
      46: invokeinterface #9,  2            // InterfaceMethod io/netty/channel/ChannelPromise.setFailure:(Ljava/lang/Throwable;)Lio/netty/channel/ChannelPromise;
      51: pop
      52: goto          0
      55: return

  public void operationComplete(io.netty.util.concurrent.Future) throws java.lang.Exception;
    Code:
       0: aload_0
       1: aload_1
       2: checkcast     #10                 // class io/netty/channel/ChannelFuture
       5: invokevirtual #11                 // Method operationComplete:(Lio/netty/channel/ChannelFuture;)V
       8: return
}
