Compiled from "NettyPortUnificationServer.java"
public class org.apache.dubbo.remoting.transport.netty4.NettyPortUnificationServer extends org.apache.dubbo.remoting.api.pu.AbstractPortUnificationServer {
  private static final org.apache.dubbo.common.logger.ErrorTypeAwareLogger logger;

  private final int serverShutdownTimeoutMills;

  private io.netty.bootstrap.ServerBootstrap bootstrap;

  private io.netty.channel.Channel channel;

  private io.netty.channel.EventLoopGroup bossGroup;

  private io.netty.channel.EventLoopGroup workerGroup;

  private final java.util.Map<java.lang.String, org.apache.dubbo.remoting.Channel> dubboChannels;

  public org.apache.dubbo.remoting.transport.netty4.NettyPortUnificationServer(org.apache.dubbo.common.URL, org.apache.dubbo.remoting.ChannelHandler) throws org.apache.dubbo.remoting.RemotingException;
    Code:
       0: aload_0
       1: aload_1
       2: aload_2
       3: aload_1
       4: invokestatic  #6                  // Method org/apache/dubbo/remoting/transport/dispatcher/ChannelHandlers.wrap:(Lorg/apache/dubbo/remoting/ChannelHandler;Lorg/apache/dubbo/common/URL;)Lorg/apache/dubbo/remoting/ChannelHandler;
       7: invokespecial #7                  // Method org/apache/dubbo/remoting/api/pu/AbstractPortUnificationServer."<init>":(Lorg/apache/dubbo/common/URL;Lorg/apache/dubbo/remoting/ChannelHandler;)V
      10: aload_0
      11: new           #8                  // class java/util/concurrent/ConcurrentHashMap
      14: dup
      15: invokespecial #9                  // Method java/util/concurrent/ConcurrentHashMap."<init>":()V
      18: putfield      #5                  // Field dubboChannels:Ljava/util/Map;
      21: aload_0
      22: aload_0
      23: invokevirtual #10                 // Method getUrl:()Lorg/apache/dubbo/common/URL;
      26: invokevirtual #11                 // Method org/apache/dubbo/common/URL.getOrDefaultModuleModel:()Lorg/apache/dubbo/rpc/model/ModuleModel;
      29: invokestatic  #12                 // Method org/apache/dubbo/common/config/ConfigurationUtils.getServerShutdownTimeout:(Lorg/apache/dubbo/rpc/model/ScopeModel;)I
      32: putfield      #13                 // Field serverShutdownTimeoutMills:I
      35: return

  public void addSupportedProtocol(org.apache.dubbo.common.URL, org.apache.dubbo.remoting.ChannelHandler);
    Code:
       0: aload_0
       1: aload_1
       2: aload_2
       3: aload_1
       4: invokestatic  #6                  // Method org/apache/dubbo/remoting/transport/dispatcher/ChannelHandlers.wrap:(Lorg/apache/dubbo/remoting/ChannelHandler;Lorg/apache/dubbo/common/URL;)Lorg/apache/dubbo/remoting/ChannelHandler;
       7: invokespecial #14                 // Method org/apache/dubbo/remoting/api/pu/AbstractPortUnificationServer.addSupportedProtocol:(Lorg/apache/dubbo/common/URL;Lorg/apache/dubbo/remoting/ChannelHandler;)V
      10: return

  public void close();
    Code:
       0: aload_0
       1: getfield      #15                 // Field channel:Lio/netty/channel/Channel;
       4: ifnull        11
       7: aload_0
       8: invokevirtual #16                 // Method doClose:()V
      11: return

  public void bind();
    Code:
       0: aload_0
       1: getfield      #15                 // Field channel:Lio/netty/channel/Channel;
       4: ifnonnull     11
       7: aload_0
       8: invokevirtual #17                 // Method doOpen:()V
      11: return

  public void doOpen();
    Code:
       0: aload_0
       1: new           #18                 // class io/netty/bootstrap/ServerBootstrap
       4: dup
       5: invokespecial #19                 // Method io/netty/bootstrap/ServerBootstrap."<init>":()V
       8: putfield      #20                 // Field bootstrap:Lio/netty/bootstrap/ServerBootstrap;
      11: aload_0
      12: iconst_1
      13: ldc           #21                 // String NettyServerBoss
      15: invokestatic  #22                 // Method org/apache/dubbo/remoting/transport/netty4/NettyEventLoopFactory.eventLoopGroup:(ILjava/lang/String;)Lio/netty/channel/EventLoopGroup;
      18: putfield      #23                 // Field bossGroup:Lio/netty/channel/EventLoopGroup;
      21: aload_0
      22: aload_0
      23: invokevirtual #10                 // Method getUrl:()Lorg/apache/dubbo/common/URL;
      26: ldc           #24                 // String iothreads
      28: getstatic     #25                 // Field org/apache/dubbo/remoting/Constants.DEFAULT_IO_THREADS:I
      31: invokevirtual #26                 // Method org/apache/dubbo/common/URL.getPositiveParameter:(Ljava/lang/String;I)I
      34: ldc           #27                 // String NettyServerWorker
      36: invokestatic  #22                 // Method org/apache/dubbo/remoting/transport/netty4/NettyEventLoopFactory.eventLoopGroup:(ILjava/lang/String;)Lio/netty/channel/EventLoopGroup;
      39: putfield      #28                 // Field workerGroup:Lio/netty/channel/EventLoopGroup;
      42: aload_0
      43: getfield      #20                 // Field bootstrap:Lio/netty/bootstrap/ServerBootstrap;
      46: aload_0
      47: getfield      #23                 // Field bossGroup:Lio/netty/channel/EventLoopGroup;
      50: aload_0
      51: getfield      #28                 // Field workerGroup:Lio/netty/channel/EventLoopGroup;
      54: invokevirtual #29                 // Method io/netty/bootstrap/ServerBootstrap.group:(Lio/netty/channel/EventLoopGroup;Lio/netty/channel/EventLoopGroup;)Lio/netty/bootstrap/ServerBootstrap;
      57: invokestatic  #30                 // Method org/apache/dubbo/remoting/transport/netty4/NettyEventLoopFactory.serverSocketChannelClass:()Ljava/lang/Class;
      60: invokevirtual #31                 // Method io/netty/bootstrap/ServerBootstrap.channel:(Ljava/lang/Class;)Lio/netty/bootstrap/AbstractBootstrap;
      63: checkcast     #18                 // class io/netty/bootstrap/ServerBootstrap
      66: getstatic     #32                 // Field io/netty/channel/ChannelOption.SO_REUSEADDR:Lio/netty/channel/ChannelOption;
      69: getstatic     #33                 // Field java/lang/Boolean.TRUE:Ljava/lang/Boolean;
      72: invokevirtual #34                 // Method io/netty/bootstrap/ServerBootstrap.option:(Lio/netty/channel/ChannelOption;Ljava/lang/Object;)Lio/netty/bootstrap/AbstractBootstrap;
      75: checkcast     #18                 // class io/netty/bootstrap/ServerBootstrap
      78: getstatic     #35                 // Field io/netty/channel/ChannelOption.TCP_NODELAY:Lio/netty/channel/ChannelOption;
      81: getstatic     #33                 // Field java/lang/Boolean.TRUE:Ljava/lang/Boolean;
      84: invokevirtual #36                 // Method io/netty/bootstrap/ServerBootstrap.childOption:(Lio/netty/channel/ChannelOption;Ljava/lang/Object;)Lio/netty/bootstrap/ServerBootstrap;
      87: getstatic     #37                 // Field io/netty/channel/ChannelOption.ALLOCATOR:Lio/netty/channel/ChannelOption;
      90: getstatic     #38                 // Field io/netty/buffer/PooledByteBufAllocator.DEFAULT:Lio/netty/buffer/PooledByteBufAllocator;
      93: invokevirtual #36                 // Method io/netty/bootstrap/ServerBootstrap.childOption:(Lio/netty/channel/ChannelOption;Ljava/lang/Object;)Lio/netty/bootstrap/ServerBootstrap;
      96: new           #39                 // class org/apache/dubbo/remoting/transport/netty4/NettyPortUnificationServer$1
      99: dup
     100: aload_0
     101: invokespecial #40                 // Method org/apache/dubbo/remoting/transport/netty4/NettyPortUnificationServer$1."<init>":(Lorg/apache/dubbo/remoting/transport/netty4/NettyPortUnificationServer;)V
     104: invokevirtual #41                 // Method io/netty/bootstrap/ServerBootstrap.childHandler:(Lio/netty/channel/ChannelHandler;)Lio/netty/bootstrap/ServerBootstrap;
     107: pop
     108: aload_0
     109: invokevirtual #10                 // Method getUrl:()Lorg/apache/dubbo/common/URL;
     112: ldc           #42                 // String bind.ip
     114: aload_0
     115: invokevirtual #10                 // Method getUrl:()Lorg/apache/dubbo/common/URL;
     118: invokevirtual #43                 // Method org/apache/dubbo/common/URL.getHost:()Ljava/lang/String;
     121: invokevirtual #44                 // Method org/apache/dubbo/common/URL.getParameter:(Ljava/lang/String;Ljava/lang/String;)Ljava/lang/String;
     124: astore_1
     125: aload_0
     126: invokevirtual #10                 // Method getUrl:()Lorg/apache/dubbo/common/URL;
     129: ldc           #45                 // String bind.port
     131: aload_0
     132: invokevirtual #10                 // Method getUrl:()Lorg/apache/dubbo/common/URL;
     135: invokevirtual #46                 // Method org/apache/dubbo/common/URL.getPort:()I
     138: invokevirtual #47                 // Method org/apache/dubbo/common/URL.getParameter:(Ljava/lang/String;I)I
     141: istore_2
     142: aload_0
     143: invokevirtual #10                 // Method getUrl:()Lorg/apache/dubbo/common/URL;
     146: ldc           #48                 // String anyhost
     148: iconst_0
     149: invokevirtual #49                 // Method org/apache/dubbo/common/URL.getParameter:(Ljava/lang/String;Z)Z
     152: ifne          162
     155: aload_1
     156: invokestatic  #50                 // Method org/apache/dubbo/common/utils/NetUtils.isInvalidLocalHost:(Ljava/lang/String;)Z
     159: ifeq          165
     162: ldc           #51                 // String 0.0.0.0
     164: astore_1
     165: new           #52                 // class java/net/InetSocketAddress
     168: dup
     169: aload_1
     170: iload_2
     171: invokespecial #53                 // Method java/net/InetSocketAddress."<init>":(Ljava/lang/String;I)V
     174: astore_3
     175: aload_0
     176: getfield      #20                 // Field bootstrap:Lio/netty/bootstrap/ServerBootstrap;
     179: aload_3
     180: invokevirtual #54                 // Method io/netty/bootstrap/ServerBootstrap.bind:(Ljava/net/SocketAddress;)Lio/netty/channel/ChannelFuture;
     183: astore        4
     185: aload         4
     187: invokeinterface #55,  1           // InterfaceMethod io/netty/channel/ChannelFuture.syncUninterruptibly:()Lio/netty/channel/ChannelFuture;
     192: pop
     193: aload_0
     194: aload         4
     196: invokeinterface #56,  1           // InterfaceMethod io/netty/channel/ChannelFuture.channel:()Lio/netty/channel/Channel;
     201: putfield      #15                 // Field channel:Lio/netty/channel/Channel;
     204: return

  public void doClose();
    Code:
       0: aload_0
       1: getfield      #15                 // Field channel:Lio/netty/channel/Channel;
       4: ifnull        22
       7: aload_0
       8: getfield      #15                 // Field channel:Lio/netty/channel/Channel;
      11: invokeinterface #57,  1           // InterfaceMethod io/netty/channel/Channel.close:()Lio/netty/channel/ChannelFuture;
      16: pop
      17: aload_0
      18: aconst_null
      19: putfield      #15                 // Field channel:Lio/netty/channel/Channel;
      22: goto          43
      25: astore_1
      26: getstatic     #59                 // Field logger:Lorg/apache/dubbo/common/logger/ErrorTypeAwareLogger;
      29: ldc           #60                 // String 6-3
      31: ldc           #61                 // String
      33: ldc           #61                 // String
      35: ldc           #62                 // String Interrupted while shutting down
      37: aload_1
      38: invokeinterface #63,  6           // InterfaceMethod org/apache/dubbo/common/logger/ErrorTypeAwareLogger.warn:(Ljava/lang/String;Ljava/lang/String;Ljava/lang/String;Ljava/lang/String;Ljava/lang/Throwable;)V
      43: aload_0
      44: invokevirtual #64                 // Method getChannels:()Ljava/util/Collection;
      47: astore_1
      48: aload_1
      49: invokestatic  #65                 // Method org/apache/dubbo/common/utils/CollectionUtils.isNotEmpty:(Ljava/util/Collection;)Z
      52: ifeq          116
      55: aload_1
      56: invokeinterface #66,  1           // InterfaceMethod java/util/Collection.iterator:()Ljava/util/Iterator;
      61: astore_2
      62: aload_2
      63: invokeinterface #67,  1           // InterfaceMethod java/util/Iterator.hasNext:()Z
      68: ifeq          116
      71: aload_2
      72: invokeinterface #68,  1           // InterfaceMethod java/util/Iterator.next:()Ljava/lang/Object;
      77: checkcast     #69                 // class org/apache/dubbo/remoting/Channel
      80: astore_3
      81: aload_3
      82: invokeinterface #70,  1           // InterfaceMethod org/apache/dubbo/remoting/Channel.close:()V
      87: goto          113
      90: astore        4
      92: getstatic     #59                 // Field logger:Lorg/apache/dubbo/common/logger/ErrorTypeAwareLogger;
      95: ldc           #60                 // String 6-3
      97: ldc           #61                 // String
      99: ldc           #61                 // String
     101: aload         4
     103: invokevirtual #71                 // Method java/lang/Throwable.getMessage:()Ljava/lang/String;
     106: aload         4
     108: invokeinterface #63,  6           // InterfaceMethod org/apache/dubbo/common/logger/ErrorTypeAwareLogger.warn:(Ljava/lang/String;Ljava/lang/String;Ljava/lang/String;Ljava/lang/String;Ljava/lang/Throwable;)V
     113: goto          62
     116: goto          139
     119: astore_1
     120: getstatic     #59                 // Field logger:Lorg/apache/dubbo/common/logger/ErrorTypeAwareLogger;
     123: ldc           #60                 // String 6-3
     125: ldc           #61                 // String
     127: ldc           #61                 // String
     129: aload_1
     130: invokevirtual #71                 // Method java/lang/Throwable.getMessage:()Ljava/lang/String;
     133: aload_1
     134: invokeinterface #63,  6           // InterfaceMethod org/apache/dubbo/common/logger/ErrorTypeAwareLogger.warn:(Ljava/lang/String;Ljava/lang/String;Ljava/lang/String;Ljava/lang/String;Ljava/lang/Throwable;)V
     139: aload_0
     140: invokevirtual #72                 // Method getProtocols:()Ljava/util/List;
     143: invokeinterface #73,  1           // InterfaceMethod java/util/List.iterator:()Ljava/util/Iterator;
     148: astore_1
     149: aload_1
     150: invokeinterface #67,  1           // InterfaceMethod java/util/Iterator.hasNext:()Z
     155: ifeq          177
     158: aload_1
     159: invokeinterface #68,  1           // InterfaceMethod java/util/Iterator.next:()Ljava/lang/Object;
     164: checkcast     #74                 // class org/apache/dubbo/remoting/api/WireProtocol
     167: astore_2
     168: aload_2
     169: invokeinterface #75,  1           // InterfaceMethod org/apache/dubbo/remoting/api/WireProtocol.close:()V
     174: goto          149
     177: aload_0
     178: getfield      #20                 // Field bootstrap:Lio/netty/bootstrap/ServerBootstrap;
     181: ifnull        254
     184: aload_0
     185: getfield      #13                 // Field serverShutdownTimeoutMills:I
     188: i2l
     189: lstore_1
     190: ldc2_w        #76                 // long 2000l
     193: lload_1
     194: invokestatic  #78                 // Method java/lang/Math.min:(JJ)J
     197: lstore_3
     198: aload_0
     199: getfield      #23                 // Field bossGroup:Lio/netty/channel/EventLoopGroup;
     202: lload_3
     203: lload_1
     204: getstatic     #79                 // Field java/util/concurrent/TimeUnit.MILLISECONDS:Ljava/util/concurrent/TimeUnit;
     207: invokeinterface #80,  6           // InterfaceMethod io/netty/channel/EventLoopGroup.shutdownGracefully:(JJLjava/util/concurrent/TimeUnit;)Lio/netty/util/concurrent/Future;
     212: astore        5
     214: aload_0
     215: getfield      #28                 // Field workerGroup:Lio/netty/channel/EventLoopGroup;
     218: lload_3
     219: lload_1
     220: getstatic     #79                 // Field java/util/concurrent/TimeUnit.MILLISECONDS:Ljava/util/concurrent/TimeUnit;
     223: invokeinterface #80,  6           // InterfaceMethod io/netty/channel/EventLoopGroup.shutdownGracefully:(JJLjava/util/concurrent/TimeUnit;)Lio/netty/util/concurrent/Future;
     228: astore        6
     230: aload         5
     232: lload_1
     233: getstatic     #79                 // Field java/util/concurrent/TimeUnit.MILLISECONDS:Ljava/util/concurrent/TimeUnit;
     236: invokeinterface #81,  4           // InterfaceMethod io/netty/util/concurrent/Future.awaitUninterruptibly:(JLjava/util/concurrent/TimeUnit;)Z
     241: pop
     242: aload         6
     244: lload_1
     245: getstatic     #79                 // Field java/util/concurrent/TimeUnit.MILLISECONDS:Ljava/util/concurrent/TimeUnit;
     248: invokeinterface #81,  4           // InterfaceMethod io/netty/util/concurrent/Future.awaitUninterruptibly:(JLjava/util/concurrent/TimeUnit;)Z
     253: pop
     254: goto          277
     257: astore_1
     258: getstatic     #59                 // Field logger:Lorg/apache/dubbo/common/logger/ErrorTypeAwareLogger;
     261: ldc           #60                 // String 6-3
     263: ldc           #61                 // String
     265: ldc           #61                 // String
     267: aload_1
     268: invokevirtual #71                 // Method java/lang/Throwable.getMessage:()Ljava/lang/String;
     271: aload_1
     272: invokeinterface #63,  6           // InterfaceMethod org/apache/dubbo/common/logger/ErrorTypeAwareLogger.warn:(Ljava/lang/String;Ljava/lang/String;Ljava/lang/String;Ljava/lang/String;Ljava/lang/Throwable;)V
     277: return
    Exception table:
       from    to  target type
           0    22    25   Class java/lang/Throwable
          81    87    90   Class java/lang/Throwable
          43   116   119   Class java/lang/Throwable
         177   254   257   Class java/lang/Throwable

  protected int getChannelsSize();
    Code:
       0: aload_0
       1: getfield      #5                  // Field dubboChannels:Ljava/util/Map;
       4: invokeinterface #82,  1           // InterfaceMethod java/util/Map.size:()I
       9: ireturn

  public boolean isBound();
    Code:
       0: aload_0
       1: getfield      #15                 // Field channel:Lio/netty/channel/Channel;
       4: invokeinterface #83,  1           // InterfaceMethod io/netty/channel/Channel.isActive:()Z
       9: ireturn

  public java.util.Collection<org.apache.dubbo.remoting.Channel> getChannels();
    Code:
       0: new           #84                 // class java/util/ArrayList
       3: dup
       4: aload_0
       5: getfield      #5                  // Field dubboChannels:Ljava/util/Map;
       8: invokeinterface #82,  1           // InterfaceMethod java/util/Map.size:()I
      13: invokespecial #85                 // Method java/util/ArrayList."<init>":(I)V
      16: astore_1
      17: aload_1
      18: aload_0
      19: getfield      #5                  // Field dubboChannels:Ljava/util/Map;
      22: invokeinterface #86,  1           // InterfaceMethod java/util/Map.values:()Ljava/util/Collection;
      27: invokeinterface #87,  2           // InterfaceMethod java/util/Collection.addAll:(Ljava/util/Collection;)Z
      32: pop
      33: aload_1
      34: areturn

  public org.apache.dubbo.remoting.Channel getChannel(java.net.InetSocketAddress);
    Code:
       0: aload_0
       1: getfield      #5                  // Field dubboChannels:Ljava/util/Map;
       4: aload_1
       5: invokestatic  #88                 // Method org/apache/dubbo/common/utils/NetUtils.toAddressString:(Ljava/net/InetSocketAddress;)Ljava/lang/String;
       8: invokeinterface #89,  2           // InterfaceMethod java/util/Map.get:(Ljava/lang/Object;)Ljava/lang/Object;
      13: checkcast     #69                 // class org/apache/dubbo/remoting/Channel
      16: areturn

  public java.net.InetSocketAddress getLocalAddress();
    Code:
       0: aload_0
       1: getfield      #15                 // Field channel:Lio/netty/channel/Channel;
       4: invokeinterface #90,  1           // InterfaceMethod io/netty/channel/Channel.localAddress:()Ljava/net/SocketAddress;
       9: checkcast     #52                 // class java/net/InetSocketAddress
      12: areturn

  public boolean canHandleIdle();
    Code:
       0: iconst_1
       1: ireturn

  static java.util.Map access$000(org.apache.dubbo.remoting.transport.netty4.NettyPortUnificationServer);
    Code:
       0: aload_0
       1: getfield      #5                  // Field dubboChannels:Ljava/util/Map;
       4: areturn

  static java.util.Map access$100(org.apache.dubbo.remoting.transport.netty4.NettyPortUnificationServer);
    Code:
       0: aload_0
       1: invokevirtual #4                  // Method getSupportedUrls:()Ljava/util/Map;
       4: areturn

  static {};
    Code:
       0: ldc           #91                 // class org/apache/dubbo/remoting/transport/netty4/NettyPortUnificationServer
       2: invokestatic  #92                 // Method org/apache/dubbo/common/logger/LoggerFactory.getErrorTypeAwareLogger:(Ljava/lang/Class;)Lorg/apache/dubbo/common/logger/ErrorTypeAwareLogger;
       5: putstatic     #59                 // Field logger:Lorg/apache/dubbo/common/logger/ErrorTypeAwareLogger;
       8: return
}
