Compiled from "NettyEventLoopFactory.java"
public class org.apache.dubbo.remoting.transport.netty4.NettyEventLoopFactory {
  public static final org.apache.dubbo.common.resource.GlobalResourceInitializer<io.netty.channel.EventLoopGroup> NIO_EVENT_LOOP_GROUP;

  public org.apache.dubbo.remoting.transport.netty4.NettyEventLoopFactory();
    Code:
       0: aload_0
       1: invokespecial #3                  // Method java/lang/Object."<init>":()V
       4: return

  public static io.netty.channel.EventLoopGroup eventLoopGroup(int, java.lang.String);
    Code:
       0: new           #4                  // class io/netty/util/concurrent/DefaultThreadFactory
       3: dup
       4: aload_1
       5: iconst_1
       6: invokespecial #5                  // Method io/netty/util/concurrent/DefaultThreadFactory."<init>":(Ljava/lang/String;Z)V
       9: astore_2
      10: invokestatic  #6                  // Method shouldEpoll:()Z
      13: ifeq          28
      16: new           #7                  // class io/netty/channel/epoll/EpollEventLoopGroup
      19: dup
      20: iload_0
      21: aload_2
      22: invokespecial #8                  // Method io/netty/channel/epoll/EpollEventLoopGroup."<init>":(ILjava/util/concurrent/ThreadFactory;)V
      25: goto          37
      28: new           #9                  // class io/netty/channel/nio/NioEventLoopGroup
      31: dup
      32: iload_0
      33: aload_2
      34: invokespecial #10                 // Method io/netty/channel/nio/NioEventLoopGroup."<init>":(ILjava/util/concurrent/ThreadFactory;)V
      37: areturn

  public static java.lang.Class<? extends io.netty.channel.socket.SocketChannel> socketChannelClass();
    Code:
       0: invokestatic  #6                  // Method shouldEpoll:()Z
       3: ifeq          11
       6: ldc           #11                 // class io/netty/channel/epoll/EpollSocketChannel
       8: goto          13
      11: ldc           #12                 // class io/netty/channel/socket/nio/NioSocketChannel
      13: areturn

  public static java.lang.Class<? extends io.netty.channel.socket.ServerSocketChannel> serverSocketChannelClass();
    Code:
       0: invokestatic  #6                  // Method shouldEpoll:()Z
       3: ifeq          11
       6: ldc           #13                 // class io/netty/channel/epoll/EpollServerSocketChannel
       8: goto          13
      11: ldc           #14                 // class io/netty/channel/socket/nio/NioServerSocketChannel
      13: areturn

  private static boolean shouldEpoll();
    Code:
       0: ldc           #15                 // String netty.epoll.enable
       2: ldc           #16                 // String false
       4: invokestatic  #17                 // Method java/lang/System.getProperty:(Ljava/lang/String;Ljava/lang/String;)Ljava/lang/String;
       7: invokestatic  #18                 // Method java/lang/Boolean.parseBoolean:(Ljava/lang/String;)Z
      10: ifeq          43
      13: ldc           #19                 // String os.name
      15: invokestatic  #20                 // Method java/lang/System.getProperty:(Ljava/lang/String;)Ljava/lang/String;
      18: astore_0
      19: aload_0
      20: invokevirtual #21                 // Method java/lang/String.toLowerCase:()Ljava/lang/String;
      23: ldc           #22                 // String linux
      25: invokevirtual #23                 // Method java/lang/String.contains:(Ljava/lang/CharSequence;)Z
      28: ifeq          41
      31: invokestatic  #24                 // Method io/netty/channel/epoll/Epoll.isAvailable:()Z
      34: ifeq          41
      37: iconst_1
      38: goto          42
      41: iconst_0
      42: ireturn
      43: iconst_0
      44: ireturn

  private static void lambda$static$1(io.netty.channel.EventLoopGroup);
    Code:
       0: aload_0
       1: invokeinterface #25,  1           // InterfaceMethod io/netty/channel/EventLoopGroup.shutdownGracefully:()Lio/netty/util/concurrent/Future;
       6: pop
       7: return

  private static io.netty.channel.EventLoopGroup lambda$static$0() throws java.lang.Exception;
    Code:
       0: getstatic     #26                 // Field org/apache/dubbo/remoting/Constants.DEFAULT_IO_THREADS:I
       3: ldc           #27                 // String NettyClientWorker
       5: invokestatic  #28                 // Method eventLoopGroup:(ILjava/lang/String;)Lio/netty/channel/EventLoopGroup;
       8: areturn

  static {};
    Code:
       0: new           #29                 // class org/apache/dubbo/common/resource/GlobalResourceInitializer
       3: dup
       4: invokedynamic #30,  0             // InvokeDynamic #0:call:()Ljava/util/concurrent/Callable;
       9: invokedynamic #31,  0             // InvokeDynamic #1:accept:()Ljava/util/function/Consumer;
      14: invokespecial #32                 // Method org/apache/dubbo/common/resource/GlobalResourceInitializer."<init>":(Ljava/util/concurrent/Callable;Ljava/util/function/Consumer;)V
      17: putstatic     #33                 // Field NIO_EVENT_LOOP_GROUP:Lorg/apache/dubbo/common/resource/GlobalResourceInitializer;
      20: return
}
