Compiled from "NettySslContextOperator.java"
public class org.apache.dubbo.remoting.transport.netty4.NettySslContextOperator implements org.apache.dubbo.remoting.api.ssl.ContextOperator {
  public org.apache.dubbo.remoting.transport.netty4.NettySslContextOperator();
    Code:
       0: aload_0
       1: invokespecial #1                  // Method java/lang/Object."<init>":()V
       4: return

  public io.netty.handler.ssl.SslContext buildContext();
    Code:
       0: aconst_null
       1: areturn

  public java.lang.Object buildContext();
    Code:
       0: aload_0
       1: invokevirtual #2                  // Method buildContext:()Lio/netty/handler/ssl/SslContext;
       4: areturn
}
