Compiled from "NettyTransporter.java"
public class org.apache.dubbo.remoting.transport.netty4.NettyTransporter implements org.apache.dubbo.remoting.Transporter {
  public static final java.lang.String NAME;

  public org.apache.dubbo.remoting.transport.netty4.NettyTransporter();
    Code:
       0: aload_0
       1: invokespecial #1                  // Method java/lang/Object."<init>":()V
       4: return

  public org.apache.dubbo.remoting.RemotingServer bind(org.apache.dubbo.common.URL, org.apache.dubbo.remoting.ChannelHandler) throws org.apache.dubbo.remoting.RemotingException;
    Code:
       0: new           #2                  // class org/apache/dubbo/remoting/transport/netty4/NettyServer
       3: dup
       4: aload_1
       5: aload_2
       6: invokespecial #3                  // Method org/apache/dubbo/remoting/transport/netty4/NettyServer."<init>":(Lorg/apache/dubbo/common/URL;Lorg/apache/dubbo/remoting/ChannelHandler;)V
       9: areturn

  public org.apache.dubbo.remoting.Client connect(org.apache.dubbo.common.URL, org.apache.dubbo.remoting.ChannelHandler) throws org.apache.dubbo.remoting.RemotingException;
    Code:
       0: new           #4                  // class org/apache/dubbo/remoting/transport/netty4/NettyClient
       3: dup
       4: aload_1
       5: aload_2
       6: invokespecial #5                  // Method org/apache/dubbo/remoting/transport/netty4/NettyClient."<init>":(Lorg/apache/dubbo/common/URL;Lorg/apache/dubbo/remoting/ChannelHandler;)V
       9: areturn
}
