Compiled from "NettyCodecAdapter.java"
public final class org.apache.dubbo.remoting.transport.netty4.NettyCodecAdapter {
  private final io.netty.channel.ChannelHandler encoder;

  private final io.netty.channel.ChannelHandler decoder;

  private final org.apache.dubbo.remoting.Codec2 codec;

  private final org.apache.dubbo.common.URL url;

  private final org.apache.dubbo.remoting.ChannelHandler handler;

  public org.apache.dubbo.remoting.transport.netty4.NettyCodecAdapter(org.apache.dubbo.remoting.Codec2, org.apache.dubbo.common.URL, org.apache.dubbo.remoting.ChannelHandler);
    Code:
       0: aload_0
       1: invokespecial #4                  // Method java/lang/Object."<init>":()V
       4: aload_0
       5: new           #5                  // class org/apache/dubbo/remoting/transport/netty4/NettyCodecAdapter$InternalEncoder
       8: dup
       9: aload_0
      10: aconst_null
      11: invokespecial #6                  // Method org/apache/dubbo/remoting/transport/netty4/NettyCodecAdapter$InternalEncoder."<init>":(Lorg/apache/dubbo/remoting/transport/netty4/NettyCodecAdapter;Lorg/apache/dubbo/remoting/transport/netty4/NettyCodecAdapter$1;)V
      14: putfield      #7                  // Field encoder:Lio/netty/channel/ChannelHandler;
      17: aload_0
      18: new           #8                  // class org/apache/dubbo/remoting/transport/netty4/NettyCodecAdapter$InternalDecoder
      21: dup
      22: aload_0
      23: aconst_null
      24: invokespecial #9                  // Method org/apache/dubbo/remoting/transport/netty4/NettyCodecAdapter$InternalDecoder."<init>":(Lorg/apache/dubbo/remoting/transport/netty4/NettyCodecAdapter;Lorg/apache/dubbo/remoting/transport/netty4/NettyCodecAdapter$1;)V
      27: putfield      #10                 // Field decoder:Lio/netty/channel/ChannelHandler;
      30: aload_0
      31: aload_1
      32: putfield      #1                  // Field codec:Lorg/apache/dubbo/remoting/Codec2;
      35: aload_0
      36: aload_2
      37: putfield      #3                  // Field url:Lorg/apache/dubbo/common/URL;
      40: aload_0
      41: aload_3
      42: putfield      #2                  // Field handler:Lorg/apache/dubbo/remoting/ChannelHandler;
      45: return

  public io.netty.channel.ChannelHandler getEncoder();
    Code:
       0: aload_0
       1: getfield      #7                  // Field encoder:Lio/netty/channel/ChannelHandler;
       4: areturn

  public io.netty.channel.ChannelHandler getDecoder();
    Code:
       0: aload_0
       1: getfield      #10                 // Field decoder:Lio/netty/channel/ChannelHandler;
       4: areturn

  static org.apache.dubbo.common.URL access$200(org.apache.dubbo.remoting.transport.netty4.NettyCodecAdapter);
    Code:
       0: aload_0
       1: getfield      #3                  // Field url:Lorg/apache/dubbo/common/URL;
       4: areturn

  static org.apache.dubbo.remoting.ChannelHandler access$300(org.apache.dubbo.remoting.transport.netty4.NettyCodecAdapter);
    Code:
       0: aload_0
       1: getfield      #2                  // Field handler:Lorg/apache/dubbo/remoting/ChannelHandler;
       4: areturn

  static org.apache.dubbo.remoting.Codec2 access$400(org.apache.dubbo.remoting.transport.netty4.NettyCodecAdapter);
    Code:
       0: aload_0
       1: getfield      #1                  // Field codec:Lorg/apache/dubbo/remoting/Codec2;
       4: areturn
}
