Compiled from "NettyConnectionClient.java"
public class org.apache.dubbo.remoting.transport.netty4.NettyConnectionClient extends org.apache.dubbo.remoting.api.connection.AbstractConnectionClient {
  private static final org.apache.dubbo.common.logger.ErrorTypeAwareLogger LOGGER;

  private java.util.concurrent.atomic.AtomicReference<io.netty.util.concurrent.Promise<java.lang.Object>> connectingPromise;

  private io.netty.util.concurrent.Promise<java.lang.Void> closePromise;

  private java.util.concurrent.atomic.AtomicReference<io.netty.channel.Channel> channel;

  private org.apache.dubbo.remoting.transport.netty4.NettyConnectionClient$ConnectionListener connectionListener;

  private io.netty.bootstrap.Bootstrap bootstrap;

  public static final io.netty.util.AttributeKey<org.apache.dubbo.remoting.api.connection.AbstractConnectionClient> CONNECTION;

  public org.apache.dubbo.remoting.transport.netty4.NettyConnectionClient(org.apache.dubbo.common.URL, org.apache.dubbo.remoting.ChannelHandler) throws org.apache.dubbo.remoting.RemotingException;
    Code:
       0: aload_0
       1: aload_1
       2: aload_2
       3: invokespecial #5                  // Method org/apache/dubbo/remoting/api/connection/AbstractConnectionClient."<init>":(Lorg/apache/dubbo/common/URL;Lorg/apache/dubbo/remoting/ChannelHandler;)V
       6: return

  protected void initConnectionClient();
    Code:
       0: aload_0
       1: invokevirtual #6                  // Method getUrl:()Lorg/apache/dubbo/common/URL;
       4: ldc           #7                  // String DubboClientHandler
       6: invokestatic  #8                  // Method org/apache/dubbo/common/utils/ExecutorUtil.setThreadName:(Lorg/apache/dubbo/common/URL;Ljava/lang/String;)Lorg/apache/dubbo/common/URL;
       9: astore_1
      10: aload_1
      11: ldc           #9                  // String threadpool
      13: ldc           #10                 // String cached
      15: invokevirtual #11                 // Method org/apache/dubbo/common/URL.addParameterIfAbsent:(Ljava/lang/String;Ljava/lang/String;)Lorg/apache/dubbo/common/URL;
      18: astore_1
      19: aload_0
      20: aload_1
      21: invokevirtual #12                 // Method setUrl:(Lorg/apache/dubbo/common/URL;)V
      24: aload_0
      25: aload_1
      26: invokevirtual #13                 // Method org/apache/dubbo/common/URL.getOrDefaultFrameworkModel:()Lorg/apache/dubbo/rpc/model/FrameworkModel;
      29: ldc           #14                 // class org/apache/dubbo/remoting/api/WireProtocol
      31: invokevirtual #15                 // Method org/apache/dubbo/rpc/model/FrameworkModel.getExtensionLoader:(Ljava/lang/Class;)Lorg/apache/dubbo/common/extension/ExtensionLoader;
      34: aload_1
      35: invokevirtual #16                 // Method org/apache/dubbo/common/URL.getProtocol:()Ljava/lang/String;
      38: invokevirtual #17                 // Method org/apache/dubbo/common/extension/ExtensionLoader.getExtension:(Ljava/lang/String;)Ljava/lang/Object;
      41: checkcast     #14                 // class org/apache/dubbo/remoting/api/WireProtocol
      44: putfield      #4                  // Field protocol:Lorg/apache/dubbo/remoting/api/WireProtocol;
      47: aload_0
      48: aload_0
      49: invokevirtual #18                 // Method getConnectAddress:()Ljava/net/InetSocketAddress;
      52: putfield      #19                 // Field remote:Ljava/net/InetSocketAddress;
      55: aload_0
      56: new           #20                 // class java/util/concurrent/atomic/AtomicReference
      59: dup
      60: invokespecial #21                 // Method java/util/concurrent/atomic/AtomicReference."<init>":()V
      63: putfield      #22                 // Field connectingPromise:Ljava/util/concurrent/atomic/AtomicReference;
      66: aload_0
      67: new           #23                 // class org/apache/dubbo/remoting/transport/netty4/NettyConnectionClient$ConnectionListener
      70: dup
      71: aload_0
      72: invokespecial #24                 // Method org/apache/dubbo/remoting/transport/netty4/NettyConnectionClient$ConnectionListener."<init>":(Lorg/apache/dubbo/remoting/transport/netty4/NettyConnectionClient;)V
      75: putfield      #25                 // Field connectionListener:Lorg/apache/dubbo/remoting/transport/netty4/NettyConnectionClient$ConnectionListener;
      78: aload_0
      79: new           #20                 // class java/util/concurrent/atomic/AtomicReference
      82: dup
      83: invokespecial #21                 // Method java/util/concurrent/atomic/AtomicReference."<init>":()V
      86: putfield      #26                 // Field channel:Ljava/util/concurrent/atomic/AtomicReference;
      89: aload_0
      90: new           #27                 // class io/netty/util/concurrent/DefaultPromise
      93: dup
      94: getstatic     #28                 // Field io/netty/util/concurrent/GlobalEventExecutor.INSTANCE:Lio/netty/util/concurrent/GlobalEventExecutor;
      97: invokespecial #29                 // Method io/netty/util/concurrent/DefaultPromise."<init>":(Lio/netty/util/concurrent/EventExecutor;)V
     100: putfield      #30                 // Field closePromise:Lio/netty/util/concurrent/Promise;
     103: aload_0
     104: new           #31                 // class java/util/concurrent/atomic/AtomicBoolean
     107: dup
     108: iconst_0
     109: invokespecial #32                 // Method java/util/concurrent/atomic/AtomicBoolean."<init>":(Z)V
     112: putfield      #33                 // Field init:Ljava/util/concurrent/atomic/AtomicBoolean;
     115: return

  protected void doOpen() throws java.lang.Throwable;
    Code:
       0: aload_0
       1: invokevirtual #34                 // Method initConnectionClient:()V
       4: aload_0
       5: invokespecial #35                 // Method initBootstrap:()V
       8: return

  private void initBootstrap();
    Code:
       0: new           #36                 // class io/netty/bootstrap/Bootstrap
       3: dup
       4: invokespecial #37                 // Method io/netty/bootstrap/Bootstrap."<init>":()V
       7: astore_1
       8: aload_1
       9: getstatic     #38                 // Field org/apache/dubbo/remoting/transport/netty4/NettyEventLoopFactory.NIO_EVENT_LOOP_GROUP:Lorg/apache/dubbo/common/resource/GlobalResourceInitializer;
      12: invokevirtual #39                 // Method org/apache/dubbo/common/resource/GlobalResourceInitializer.get:()Ljava/lang/Object;
      15: checkcast     #40                 // class io/netty/channel/EventLoopGroup
      18: invokevirtual #41                 // Method io/netty/bootstrap/Bootstrap.group:(Lio/netty/channel/EventLoopGroup;)Lio/netty/bootstrap/AbstractBootstrap;
      21: checkcast     #36                 // class io/netty/bootstrap/Bootstrap
      24: getstatic     #42                 // Field io/netty/channel/ChannelOption.SO_KEEPALIVE:Lio/netty/channel/ChannelOption;
      27: iconst_1
      28: invokestatic  #43                 // Method java/lang/Boolean.valueOf:(Z)Ljava/lang/Boolean;
      31: invokevirtual #44                 // Method io/netty/bootstrap/Bootstrap.option:(Lio/netty/channel/ChannelOption;Ljava/lang/Object;)Lio/netty/bootstrap/AbstractBootstrap;
      34: checkcast     #36                 // class io/netty/bootstrap/Bootstrap
      37: getstatic     #45                 // Field io/netty/channel/ChannelOption.TCP_NODELAY:Lio/netty/channel/ChannelOption;
      40: iconst_1
      41: invokestatic  #43                 // Method java/lang/Boolean.valueOf:(Z)Ljava/lang/Boolean;
      44: invokevirtual #44                 // Method io/netty/bootstrap/Bootstrap.option:(Lio/netty/channel/ChannelOption;Ljava/lang/Object;)Lio/netty/bootstrap/AbstractBootstrap;
      47: checkcast     #36                 // class io/netty/bootstrap/Bootstrap
      50: getstatic     #46                 // Field io/netty/channel/ChannelOption.ALLOCATOR:Lio/netty/channel/ChannelOption;
      53: getstatic     #47                 // Field io/netty/buffer/PooledByteBufAllocator.DEFAULT:Lio/netty/buffer/PooledByteBufAllocator;
      56: invokevirtual #44                 // Method io/netty/bootstrap/Bootstrap.option:(Lio/netty/channel/ChannelOption;Ljava/lang/Object;)Lio/netty/bootstrap/AbstractBootstrap;
      59: checkcast     #36                 // class io/netty/bootstrap/Bootstrap
      62: aload_0
      63: invokevirtual #18                 // Method getConnectAddress:()Ljava/net/InetSocketAddress;
      66: invokevirtual #48                 // Method io/netty/bootstrap/Bootstrap.remoteAddress:(Ljava/net/SocketAddress;)Lio/netty/bootstrap/Bootstrap;
      69: invokestatic  #49                 // Method org/apache/dubbo/remoting/transport/netty4/NettyEventLoopFactory.socketChannelClass:()Ljava/lang/Class;
      72: invokevirtual #50                 // Method io/netty/bootstrap/Bootstrap.channel:(Ljava/lang/Class;)Lio/netty/bootstrap/AbstractBootstrap;
      75: pop
      76: new           #51                 // class org/apache/dubbo/remoting/transport/netty4/NettyConnectionHandler
      79: dup
      80: aload_0
      81: invokespecial #52                 // Method org/apache/dubbo/remoting/transport/netty4/NettyConnectionHandler."<init>":(Lorg/apache/dubbo/remoting/transport/netty4/NettyConnectionClient;)V
      84: astore_2
      85: aload_1
      86: getstatic     #53                 // Field io/netty/channel/ChannelOption.CONNECT_TIMEOUT_MILLIS:Lio/netty/channel/ChannelOption;
      89: aload_0
      90: invokevirtual #54                 // Method getConnectTimeout:()I
      93: invokestatic  #55                 // Method java/lang/Integer.valueOf:(I)Ljava/lang/Integer;
      96: invokevirtual #44                 // Method io/netty/bootstrap/Bootstrap.option:(Lio/netty/channel/ChannelOption;Ljava/lang/Object;)Lio/netty/bootstrap/AbstractBootstrap;
      99: pop
     100: aload_0
     101: invokevirtual #6                  // Method getUrl:()Lorg/apache/dubbo/common/URL;
     104: invokestatic  #56                 // Method org/apache/dubbo/remoting/transport/netty4/ssl/SslContexts.buildClientSslContext:(Lorg/apache/dubbo/common/URL;)Lio/netty/handler/ssl/SslContext;
     107: astore_3
     108: aload_1
     109: new           #57                 // class org/apache/dubbo/remoting/transport/netty4/NettyConnectionClient$1
     112: dup
     113: aload_0
     114: aload_3
     115: aload_2
     116: invokespecial #58                 // Method org/apache/dubbo/remoting/transport/netty4/NettyConnectionClient$1."<init>":(Lorg/apache/dubbo/remoting/transport/netty4/NettyConnectionClient;Lio/netty/handler/ssl/SslContext;Lorg/apache/dubbo/remoting/transport/netty4/NettyConnectionHandler;)V
     119: invokevirtual #59                 // Method io/netty/bootstrap/Bootstrap.handler:(Lio/netty/channel/ChannelHandler;)Lio/netty/bootstrap/AbstractBootstrap;
     122: pop
     123: aload_0
     124: aload_1
     125: putfield      #60                 // Field bootstrap:Lio/netty/bootstrap/Bootstrap;
     128: return

  protected void doClose();
    Code:
       0: aload_0
       1: invokevirtual #61                 // Method isClosed:()Z
       4: ifeq          74
       7: getstatic     #3                  // Field LOGGER:Lorg/apache/dubbo/common/logger/ErrorTypeAwareLogger;
      10: invokeinterface #62,  1           // InterfaceMethod org/apache/dubbo/common/logger/ErrorTypeAwareLogger.isDebugEnabled:()Z
      15: ifeq          39
      18: getstatic     #3                  // Field LOGGER:Lorg/apache/dubbo/common/logger/ErrorTypeAwareLogger;
      21: ldc           #63                 // String Connection:%s freed
      23: iconst_1
      24: anewarray     #64                 // class java/lang/Object
      27: dup
      28: iconst_0
      29: aload_0
      30: aastore
      31: invokestatic  #65                 // Method java/lang/String.format:(Ljava/lang/String;[Ljava/lang/Object;)Ljava/lang/String;
      34: invokeinterface #66,  2           // InterfaceMethod org/apache/dubbo/common/logger/ErrorTypeAwareLogger.debug:(Ljava/lang/String;)V
      39: aload_0
      40: invokevirtual #67                 // Method getNettyChannel:()Lio/netty/channel/Channel;
      43: astore_1
      44: aload_1
      45: ifnull        55
      48: aload_1
      49: invokeinterface #68,  1           // InterfaceMethod io/netty/channel/Channel.close:()Lio/netty/channel/ChannelFuture;
      54: pop
      55: aload_0
      56: getfield      #26                 // Field channel:Ljava/util/concurrent/atomic/AtomicReference;
      59: aconst_null
      60: invokevirtual #69                 // Method java/util/concurrent/atomic/AtomicReference.set:(Ljava/lang/Object;)V
      63: aload_0
      64: getfield      #30                 // Field closePromise:Lio/netty/util/concurrent/Promise;
      67: aconst_null
      68: invokeinterface #70,  2           // InterfaceMethod io/netty/util/concurrent/Promise.setSuccess:(Ljava/lang/Object;)Lio/netty/util/concurrent/Promise;
      73: pop
      74: return

  protected void doConnect() throws org.apache.dubbo.remoting.RemotingException;
    Code:
       0: aload_0
       1: invokevirtual #61                 // Method isClosed:()Z
       4: ifeq          39
       7: getstatic     #3                  // Field LOGGER:Lorg/apache/dubbo/common/logger/ErrorTypeAwareLogger;
      10: invokeinterface #62,  1           // InterfaceMethod org/apache/dubbo/common/logger/ErrorTypeAwareLogger.isDebugEnabled:()Z
      15: ifeq          39
      18: getstatic     #3                  // Field LOGGER:Lorg/apache/dubbo/common/logger/ErrorTypeAwareLogger;
      21: ldc           #71                 // String %s aborted to reconnect cause connection closed.
      23: iconst_1
      24: anewarray     #64                 // class java/lang/Object
      27: dup
      28: iconst_0
      29: aload_0
      30: aastore
      31: invokestatic  #65                 // Method java/lang/String.format:(Ljava/lang/String;[Ljava/lang/Object;)Ljava/lang/String;
      34: invokeinterface #66,  2           // InterfaceMethod org/apache/dubbo/common/logger/ErrorTypeAwareLogger.debug:(Ljava/lang/String;)V
      39: aload_0
      40: getfield      #33                 // Field init:Ljava/util/concurrent/atomic/AtomicBoolean;
      43: iconst_0
      44: iconst_1
      45: invokevirtual #72                 // Method java/util/concurrent/atomic/AtomicBoolean.compareAndSet:(ZZ)Z
      48: pop
      49: invokestatic  #73                 // Method java/lang/System.currentTimeMillis:()J
      52: lstore_1
      53: aload_0
      54: invokevirtual #74                 // Method createConnectingPromise:()V
      57: aload_0
      58: getfield      #60                 // Field bootstrap:Lio/netty/bootstrap/Bootstrap;
      61: invokevirtual #75                 // Method io/netty/bootstrap/Bootstrap.connect:()Lio/netty/channel/ChannelFuture;
      64: astore_3
      65: aload_3
      66: aload_0
      67: getfield      #25                 // Field connectionListener:Lorg/apache/dubbo/remoting/transport/netty4/NettyConnectionClient$ConnectionListener;
      70: invokeinterface #76,  2           // InterfaceMethod io/netty/channel/ChannelFuture.addListener:(Lio/netty/util/concurrent/GenericFutureListener;)Lio/netty/channel/ChannelFuture;
      75: pop
      76: aload_0
      77: getfield      #22                 // Field connectingPromise:Ljava/util/concurrent/atomic/AtomicReference;
      80: invokevirtual #77                 // Method java/util/concurrent/atomic/AtomicReference.get:()Ljava/lang/Object;
      83: checkcast     #78                 // class io/netty/util/concurrent/Promise
      86: aload_0
      87: invokevirtual #54                 // Method getConnectTimeout:()I
      90: i2l
      91: getstatic     #79                 // Field java/util/concurrent/TimeUnit.MILLISECONDS:Ljava/util/concurrent/TimeUnit;
      94: invokeinterface #80,  4           // InterfaceMethod io/netty/util/concurrent/Promise.awaitUninterruptibly:(JLjava/util/concurrent/TimeUnit;)Z
      99: istore        4
     101: aload_0
     102: dup
     103: astore        5
     105: monitorenter
     106: aload_0
     107: getfield      #22                 // Field connectingPromise:Ljava/util/concurrent/atomic/AtomicReference;
     110: aconst_null
     111: invokevirtual #69                 // Method java/util/concurrent/atomic/AtomicReference.set:(Ljava/lang/Object;)V
     114: aload         5
     116: monitorexit
     117: goto          128
     120: astore        6
     122: aload         5
     124: monitorexit
     125: aload         6
     127: athrow
     128: aload_3
     129: invokeinterface #81,  1           // InterfaceMethod io/netty/channel/ChannelFuture.cause:()Ljava/lang/Throwable;
     134: ifnull        225
     137: aload_3
     138: invokeinterface #81,  1           // InterfaceMethod io/netty/channel/ChannelFuture.cause:()Ljava/lang/Throwable;
     143: astore        5
     145: new           #82                 // class org/apache/dubbo/remoting/RemotingException
     148: dup
     149: aload_0
     150: new           #83                 // class java/lang/StringBuilder
     153: dup
     154: invokespecial #84                 // Method java/lang/StringBuilder."<init>":()V
     157: ldc           #85                 // String client(url:
     159: invokevirtual #86                 // Method java/lang/StringBuilder.append:(Ljava/lang/String;)Ljava/lang/StringBuilder;
     162: aload_0
     163: invokevirtual #6                  // Method getUrl:()Lorg/apache/dubbo/common/URL;
     166: invokevirtual #87                 // Method java/lang/StringBuilder.append:(Ljava/lang/Object;)Ljava/lang/StringBuilder;
     169: ldc           #88                 // String ) failed to connect to server
     171: invokevirtual #86                 // Method java/lang/StringBuilder.append:(Ljava/lang/String;)Ljava/lang/StringBuilder;
     174: aload_0
     175: invokevirtual #18                 // Method getConnectAddress:()Ljava/net/InetSocketAddress;
     178: invokevirtual #87                 // Method java/lang/StringBuilder.append:(Ljava/lang/Object;)Ljava/lang/StringBuilder;
     181: ldc           #89                 // String , error message is:
     183: invokevirtual #86                 // Method java/lang/StringBuilder.append:(Ljava/lang/String;)Ljava/lang/StringBuilder;
     186: aload         5
     188: invokevirtual #90                 // Method java/lang/Throwable.getMessage:()Ljava/lang/String;
     191: invokevirtual #86                 // Method java/lang/StringBuilder.append:(Ljava/lang/String;)Ljava/lang/StringBuilder;
     194: invokevirtual #91                 // Method java/lang/StringBuilder.toString:()Ljava/lang/String;
     197: aload         5
     199: invokespecial #92                 // Method org/apache/dubbo/remoting/RemotingException."<init>":(Lorg/apache/dubbo/remoting/Channel;Ljava/lang/String;Ljava/lang/Throwable;)V
     202: astore        6
     204: getstatic     #3                  // Field LOGGER:Lorg/apache/dubbo/common/logger/ErrorTypeAwareLogger;
     207: ldc           #93                 // String 6-1
     209: ldc           #94                 // String network disconnected
     211: ldc           #95                 // String
     213: ldc           #96                 // String Failed to connect to provider server by other reason.
     215: aload         5
     217: invokeinterface #97,  6           // InterfaceMethod org/apache/dubbo/common/logger/ErrorTypeAwareLogger.error:(Ljava/lang/String;Ljava/lang/String;Ljava/lang/String;Ljava/lang/String;Ljava/lang/Throwable;)V
     222: aload         6
     224: athrow
     225: iload         4
     227: ifeq          239
     230: aload_3
     231: invokeinterface #98,  1           // InterfaceMethod io/netty/channel/ChannelFuture.isSuccess:()Z
     236: ifne          351
     239: new           #82                 // class org/apache/dubbo/remoting/RemotingException
     242: dup
     243: aload_0
     244: new           #83                 // class java/lang/StringBuilder
     247: dup
     248: invokespecial #84                 // Method java/lang/StringBuilder."<init>":()V
     251: ldc           #85                 // String client(url:
     253: invokevirtual #86                 // Method java/lang/StringBuilder.append:(Ljava/lang/String;)Ljava/lang/StringBuilder;
     256: aload_0
     257: invokevirtual #6                  // Method getUrl:()Lorg/apache/dubbo/common/URL;
     260: invokevirtual #87                 // Method java/lang/StringBuilder.append:(Ljava/lang/Object;)Ljava/lang/StringBuilder;
     263: ldc           #88                 // String ) failed to connect to server
     265: invokevirtual #86                 // Method java/lang/StringBuilder.append:(Ljava/lang/String;)Ljava/lang/StringBuilder;
     268: aload_0
     269: invokevirtual #18                 // Method getConnectAddress:()Ljava/net/InetSocketAddress;
     272: invokevirtual #87                 // Method java/lang/StringBuilder.append:(Ljava/lang/Object;)Ljava/lang/StringBuilder;
     275: ldc           #99                 // String  client-side timeout
     277: invokevirtual #86                 // Method java/lang/StringBuilder.append:(Ljava/lang/String;)Ljava/lang/StringBuilder;
     280: aload_0
     281: invokevirtual #54                 // Method getConnectTimeout:()I
     284: invokevirtual #100                // Method java/lang/StringBuilder.append:(I)Ljava/lang/StringBuilder;
     287: ldc           #101                // String ms (elapsed:
     289: invokevirtual #86                 // Method java/lang/StringBuilder.append:(Ljava/lang/String;)Ljava/lang/StringBuilder;
     292: invokestatic  #73                 // Method java/lang/System.currentTimeMillis:()J
     295: lload_1
     296: lsub
     297: invokevirtual #102                // Method java/lang/StringBuilder.append:(J)Ljava/lang/StringBuilder;
     300: ldc           #103                // String ms) from netty client
     302: invokevirtual #86                 // Method java/lang/StringBuilder.append:(Ljava/lang/String;)Ljava/lang/StringBuilder;
     305: invokestatic  #104                // Method org/apache/dubbo/common/utils/NetUtils.getLocalHost:()Ljava/lang/String;
     308: invokevirtual #86                 // Method java/lang/StringBuilder.append:(Ljava/lang/String;)Ljava/lang/StringBuilder;
     311: ldc           #105                // String  using dubbo version
     313: invokevirtual #86                 // Method java/lang/StringBuilder.append:(Ljava/lang/String;)Ljava/lang/StringBuilder;
     316: invokestatic  #106                // Method org/apache/dubbo/common/Version.getVersion:()Ljava/lang/String;
     319: invokevirtual #86                 // Method java/lang/StringBuilder.append:(Ljava/lang/String;)Ljava/lang/StringBuilder;
     322: invokevirtual #91                 // Method java/lang/StringBuilder.toString:()Ljava/lang/String;
     325: invokespecial #107                // Method org/apache/dubbo/remoting/RemotingException."<init>":(Lorg/apache/dubbo/remoting/Channel;Ljava/lang/String;)V
     328: astore        5
     330: getstatic     #3                  // Field LOGGER:Lorg/apache/dubbo/common/logger/ErrorTypeAwareLogger;
     333: ldc           #108                // String 6-2
     335: ldc           #109                // String provider crash
     337: ldc           #95                 // String
     339: ldc           #110                // String Client-side timeout.
     341: aload         5
     343: invokeinterface #97,  6           // InterfaceMethod org/apache/dubbo/common/logger/ErrorTypeAwareLogger.error:(Ljava/lang/String;Ljava/lang/String;Ljava/lang/String;Ljava/lang/String;Ljava/lang/Throwable;)V
     348: aload         5
     350: athrow
     351: return
    Exception table:
       from    to  target type
         106   117   120   any
         120   125   120   any

  protected void doDisConnect();
    Code:
       0: aload_0
       1: invokevirtual #67                 // Method getNettyChannel:()Lio/netty/channel/Channel;
       4: invokestatic  #111                // Method org/apache/dubbo/remoting/transport/netty4/NettyChannel.removeChannelIfDisconnected:(Lio/netty/channel/Channel;)V
       7: return

  public void onConnected(java.lang.Object);
    Code:
       0: aload_1
       1: instanceof    #112                // class io/netty/channel/Channel
       4: ifne          8
       7: return
       8: aload_1
       9: checkcast     #112                // class io/netty/channel/Channel
      12: astore_2
      13: aload_0
      14: invokevirtual #61                 // Method isClosed:()Z
      17: ifeq          60
      20: aload_2
      21: invokeinterface #68,  1           // InterfaceMethod io/netty/channel/Channel.close:()Lio/netty/channel/ChannelFuture;
      26: pop
      27: getstatic     #3                  // Field LOGGER:Lorg/apache/dubbo/common/logger/ErrorTypeAwareLogger;
      30: invokeinterface #62,  1           // InterfaceMethod org/apache/dubbo/common/logger/ErrorTypeAwareLogger.isDebugEnabled:()Z
      35: ifeq          59
      38: getstatic     #3                  // Field LOGGER:Lorg/apache/dubbo/common/logger/ErrorTypeAwareLogger;
      41: ldc           #113                // String %s is closed, ignoring connected event
      43: iconst_1
      44: anewarray     #64                 // class java/lang/Object
      47: dup
      48: iconst_0
      49: aload_0
      50: aastore
      51: invokestatic  #65                 // Method java/lang/String.format:(Ljava/lang/String;[Ljava/lang/Object;)Ljava/lang/String;
      54: invokeinterface #66,  2           // InterfaceMethod org/apache/dubbo/common/logger/ErrorTypeAwareLogger.debug:(Ljava/lang/String;)V
      59: return
      60: aload_0
      61: getfield      #26                 // Field channel:Ljava/util/concurrent/atomic/AtomicReference;
      64: aload_2
      65: invokevirtual #69                 // Method java/util/concurrent/atomic/AtomicReference.set:(Ljava/lang/Object;)V
      68: aload_0
      69: getfield      #22                 // Field connectingPromise:Ljava/util/concurrent/atomic/AtomicReference;
      72: invokevirtual #77                 // Method java/util/concurrent/atomic/AtomicReference.get:()Ljava/lang/Object;
      75: ifnull        97
      78: aload_0
      79: getfield      #22                 // Field connectingPromise:Ljava/util/concurrent/atomic/AtomicReference;
      82: invokevirtual #77                 // Method java/util/concurrent/atomic/AtomicReference.get:()Ljava/lang/Object;
      85: checkcast     #78                 // class io/netty/util/concurrent/Promise
      88: getstatic     #114                // Field CONNECTED_OBJECT:Ljava/lang/Object;
      91: invokeinterface #115,  2          // InterfaceMethod io/netty/util/concurrent/Promise.trySuccess:(Ljava/lang/Object;)Z
      96: pop
      97: aload_2
      98: getstatic     #116                // Field CONNECTION:Lio/netty/util/AttributeKey;
     101: invokeinterface #117,  2          // InterfaceMethod io/netty/channel/Channel.attr:(Lio/netty/util/AttributeKey;)Lio/netty/util/Attribute;
     106: aload_0
     107: invokeinterface #118,  2          // InterfaceMethod io/netty/util/Attribute.set:(Ljava/lang/Object;)V
     112: getstatic     #3                  // Field LOGGER:Lorg/apache/dubbo/common/logger/ErrorTypeAwareLogger;
     115: invokeinterface #62,  1           // InterfaceMethod org/apache/dubbo/common/logger/ErrorTypeAwareLogger.isDebugEnabled:()Z
     120: ifeq          144
     123: getstatic     #3                  // Field LOGGER:Lorg/apache/dubbo/common/logger/ErrorTypeAwareLogger;
     126: ldc           #119                // String %s connected
     128: iconst_1
     129: anewarray     #64                 // class java/lang/Object
     132: dup
     133: iconst_0
     134: aload_0
     135: aastore
     136: invokestatic  #65                 // Method java/lang/String.format:(Ljava/lang/String;[Ljava/lang/Object;)Ljava/lang/String;
     139: invokeinterface #66,  2           // InterfaceMethod org/apache/dubbo/common/logger/ErrorTypeAwareLogger.debug:(Ljava/lang/String;)V
     144: return

  public void onGoaway(java.lang.Object);
    Code:
       0: aload_1
       1: instanceof    #112                // class io/netty/channel/Channel
       4: ifne          8
       7: return
       8: aload_1
       9: checkcast     #112                // class io/netty/channel/Channel
      12: astore_2
      13: aload_0
      14: getfield      #26                 // Field channel:Ljava/util/concurrent/atomic/AtomicReference;
      17: aload_2
      18: aconst_null
      19: invokevirtual #120                // Method java/util/concurrent/atomic/AtomicReference.compareAndSet:(Ljava/lang/Object;Ljava/lang/Object;)Z
      22: ifeq          61
      25: aload_2
      26: invokestatic  #111                // Method org/apache/dubbo/remoting/transport/netty4/NettyChannel.removeChannelIfDisconnected:(Lio/netty/channel/Channel;)V
      29: getstatic     #3                  // Field LOGGER:Lorg/apache/dubbo/common/logger/ErrorTypeAwareLogger;
      32: invokeinterface #62,  1           // InterfaceMethod org/apache/dubbo/common/logger/ErrorTypeAwareLogger.isDebugEnabled:()Z
      37: ifeq          61
      40: getstatic     #3                  // Field LOGGER:Lorg/apache/dubbo/common/logger/ErrorTypeAwareLogger;
      43: ldc           #121                // String %s goaway
      45: iconst_1
      46: anewarray     #64                 // class java/lang/Object
      49: dup
      50: iconst_0
      51: aload_0
      52: aastore
      53: invokestatic  #65                 // Method java/lang/String.format:(Ljava/lang/String;[Ljava/lang/Object;)Ljava/lang/String;
      56: invokeinterface #66,  2           // InterfaceMethod org/apache/dubbo/common/logger/ErrorTypeAwareLogger.debug:(Ljava/lang/String;)V
      61: return

  protected org.apache.dubbo.remoting.Channel getChannel();
    Code:
       0: aload_0
       1: invokevirtual #67                 // Method getNettyChannel:()Lio/netty/channel/Channel;
       4: astore_1
       5: aload_1
       6: ifnonnull     11
       9: aconst_null
      10: areturn
      11: aload_1
      12: aload_0
      13: invokevirtual #6                  // Method getUrl:()Lorg/apache/dubbo/common/URL;
      16: aload_0
      17: invokestatic  #122                // Method org/apache/dubbo/remoting/transport/netty4/NettyChannel.getOrAddChannel:(Lio/netty/channel/Channel;Lorg/apache/dubbo/common/URL;Lorg/apache/dubbo/remoting/ChannelHandler;)Lorg/apache/dubbo/remoting/transport/netty4/NettyChannel;
      20: areturn

  io.netty.channel.Channel getNettyChannel();
    Code:
       0: aload_0
       1: getfield      #26                 // Field channel:Ljava/util/concurrent/atomic/AtomicReference;
       4: invokevirtual #77                 // Method java/util/concurrent/atomic/AtomicReference.get:()Ljava/lang/Object;
       7: checkcast     #112                // class io/netty/channel/Channel
      10: areturn

  public java.lang.Object getChannel(java.lang.Boolean);
    Code:
       0: getstatic     #123                // Field java/lang/Boolean.TRUE:Ljava/lang/Boolean;
       3: aload_1
       4: invokevirtual #124                // Method java/lang/Boolean.equals:(Ljava/lang/Object;)Z
       7: ifeq          17
      10: aload_0
      11: invokevirtual #67                 // Method getNettyChannel:()Lio/netty/channel/Channel;
      14: goto          21
      17: aload_0
      18: invokevirtual #125                // Method getChannel:()Lorg/apache/dubbo/remoting/Channel;
      21: areturn

  public boolean isAvailable();
    Code:
       0: aload_0
       1: invokevirtual #61                 // Method isClosed:()Z
       4: ifeq          9
       7: iconst_0
       8: ireturn
       9: aload_0
      10: invokevirtual #67                 // Method getNettyChannel:()Lio/netty/channel/Channel;
      13: astore_1
      14: aload_1
      15: ifnull        29
      18: aload_1
      19: invokeinterface #126,  1          // InterfaceMethod io/netty/channel/Channel.isActive:()Z
      24: ifeq          29
      27: iconst_1
      28: ireturn
      29: aload_0
      30: getfield      #33                 // Field init:Ljava/util/concurrent/atomic/AtomicBoolean;
      33: iconst_0
      34: iconst_1
      35: invokevirtual #72                 // Method java/util/concurrent/atomic/AtomicBoolean.compareAndSet:(ZZ)Z
      38: ifeq          85
      41: aload_0
      42: invokevirtual #127                // Method doConnect:()V
      45: goto          85
      48: astore_2
      49: getstatic     #3                  // Field LOGGER:Lorg/apache/dubbo/common/logger/ErrorTypeAwareLogger;
      52: ldc           #128                // String 6-16
      54: ldc           #95                 // String
      56: ldc           #95                 // String
      58: new           #83                 // class java/lang/StringBuilder
      61: dup
      62: invokespecial #84                 // Method java/lang/StringBuilder."<init>":()V
      65: ldc           #129                // String Failed to connect to server:
      67: invokevirtual #86                 // Method java/lang/StringBuilder.append:(Ljava/lang/String;)Ljava/lang/StringBuilder;
      70: aload_0
      71: invokevirtual #18                 // Method getConnectAddress:()Ljava/net/InetSocketAddress;
      74: invokevirtual #87                 // Method java/lang/StringBuilder.append:(Ljava/lang/Object;)Ljava/lang/StringBuilder;
      77: invokevirtual #91                 // Method java/lang/StringBuilder.toString:()Ljava/lang/String;
      80: invokeinterface #130,  5          // InterfaceMethod org/apache/dubbo/common/logger/ErrorTypeAwareLogger.error:(Ljava/lang/String;Ljava/lang/String;Ljava/lang/String;Ljava/lang/String;)V
      85: aload_0
      86: invokevirtual #74                 // Method createConnectingPromise:()V
      89: aload_0
      90: getfield      #22                 // Field connectingPromise:Ljava/util/concurrent/atomic/AtomicReference;
      93: invokevirtual #77                 // Method java/util/concurrent/atomic/AtomicReference.get:()Ljava/lang/Object;
      96: checkcast     #78                 // class io/netty/util/concurrent/Promise
      99: aload_0
     100: invokevirtual #54                 // Method getConnectTimeout:()I
     103: i2l
     104: getstatic     #79                 // Field java/util/concurrent/TimeUnit.MILLISECONDS:Ljava/util/concurrent/TimeUnit;
     107: invokeinterface #80,  4           // InterfaceMethod io/netty/util/concurrent/Promise.awaitUninterruptibly:(JLjava/util/concurrent/TimeUnit;)Z
     112: pop
     113: aload_0
     114: dup
     115: astore_2
     116: monitorenter
     117: aload_0
     118: getfield      #22                 // Field connectingPromise:Ljava/util/concurrent/atomic/AtomicReference;
     121: aconst_null
     122: invokevirtual #69                 // Method java/util/concurrent/atomic/AtomicReference.set:(Ljava/lang/Object;)V
     125: aload_2
     126: monitorexit
     127: goto          135
     130: astore_3
     131: aload_2
     132: monitorexit
     133: aload_3
     134: athrow
     135: aload_0
     136: invokevirtual #67                 // Method getNettyChannel:()Lio/netty/channel/Channel;
     139: astore_1
     140: aload_1
     141: ifnull        157
     144: aload_1
     145: invokeinterface #126,  1          // InterfaceMethod io/netty/channel/Channel.isActive:()Z
     150: ifeq          157
     153: iconst_1
     154: goto          158
     157: iconst_0
     158: ireturn
    Exception table:
       from    to  target type
          41    45    48   Class org/apache/dubbo/remoting/RemotingException
         117   127   130   any
         130   133   130   any

  public void createConnectingPromise();
    Code:
       0: aload_0
       1: getfield      #22                 // Field connectingPromise:Ljava/util/concurrent/atomic/AtomicReference;
       4: aconst_null
       5: new           #27                 // class io/netty/util/concurrent/DefaultPromise
       8: dup
       9: getstatic     #28                 // Field io/netty/util/concurrent/GlobalEventExecutor.INSTANCE:Lio/netty/util/concurrent/GlobalEventExecutor;
      12: invokespecial #29                 // Method io/netty/util/concurrent/DefaultPromise."<init>":(Lio/netty/util/concurrent/EventExecutor;)V
      15: invokevirtual #120                // Method java/util/concurrent/atomic/AtomicReference.compareAndSet:(Ljava/lang/Object;Ljava/lang/Object;)Z
      18: pop
      19: return

  public io.netty.util.concurrent.Promise<java.lang.Void> getClosePromise();
    Code:
       0: aload_0
       1: getfield      #30                 // Field closePromise:Lio/netty/util/concurrent/Promise;
       4: areturn

  public static org.apache.dubbo.remoting.api.connection.AbstractConnectionClient getConnectionClientFromChannel(io.netty.channel.Channel);
    Code:
       0: aload_0
       1: getstatic     #116                // Field CONNECTION:Lio/netty/util/AttributeKey;
       4: invokeinterface #117,  2          // InterfaceMethod io/netty/channel/Channel.attr:(Lio/netty/util/AttributeKey;)Lio/netty/util/Attribute;
       9: invokeinterface #131,  1          // InterfaceMethod io/netty/util/Attribute.get:()Ljava/lang/Object;
      14: checkcast     #132                // class org/apache/dubbo/remoting/api/connection/AbstractConnectionClient
      17: areturn

  public io.netty.channel.ChannelFuture write(java.lang.Object) throws org.apache.dubbo.remoting.RemotingException;
    Code:
       0: aload_0
       1: invokevirtual #133                // Method isAvailable:()Z
       4: ifne          53
       7: new           #82                 // class org/apache/dubbo/remoting/RemotingException
      10: dup
      11: aconst_null
      12: aconst_null
      13: new           #83                 // class java/lang/StringBuilder
      16: dup
      17: invokespecial #84                 // Method java/lang/StringBuilder."<init>":()V
      20: ldc           #134                // String Failed to send request
      22: invokevirtual #86                 // Method java/lang/StringBuilder.append:(Ljava/lang/String;)Ljava/lang/StringBuilder;
      25: aload_1
      26: invokevirtual #87                 // Method java/lang/StringBuilder.append:(Ljava/lang/Object;)Ljava/lang/StringBuilder;
      29: ldc           #135                // String , cause: The channel to
      31: invokevirtual #86                 // Method java/lang/StringBuilder.append:(Ljava/lang/String;)Ljava/lang/StringBuilder;
      34: aload_0
      35: getfield      #19                 // Field remote:Ljava/net/InetSocketAddress;
      38: invokevirtual #87                 // Method java/lang/StringBuilder.append:(Ljava/lang/Object;)Ljava/lang/StringBuilder;
      41: ldc           #136                // String  is closed!
      43: invokevirtual #86                 // Method java/lang/StringBuilder.append:(Ljava/lang/String;)Ljava/lang/StringBuilder;
      46: invokevirtual #91                 // Method java/lang/StringBuilder.toString:()Ljava/lang/String;
      49: invokespecial #137                // Method org/apache/dubbo/remoting/RemotingException."<init>":(Ljava/net/InetSocketAddress;Ljava/net/InetSocketAddress;Ljava/lang/String;)V
      52: athrow
      53: aload_0
      54: invokevirtual #125                // Method getChannel:()Lorg/apache/dubbo/remoting/Channel;
      57: checkcast     #112                // class io/netty/channel/Channel
      60: aload_1
      61: invokeinterface #138,  2          // InterfaceMethod io/netty/channel/Channel.writeAndFlush:(Ljava/lang/Object;)Lio/netty/channel/ChannelFuture;
      66: areturn

  public void addCloseListener(java.lang.Runnable);
    Code:
       0: aload_0
       1: invokevirtual #139                // Method getClosePromise:()Lio/netty/util/concurrent/Promise;
       4: aload_1
       5: invokedynamic #140,  0            // InvokeDynamic #0:operationComplete:(Ljava/lang/Runnable;)Lio/netty/util/concurrent/GenericFutureListener;
      10: invokeinterface #141,  2          // InterfaceMethod io/netty/util/concurrent/Promise.addListener:(Lio/netty/util/concurrent/GenericFutureListener;)Lio/netty/util/concurrent/Promise;
      15: pop
      16: return

  public void destroy();
    Code:
       0: aload_0
       1: invokevirtual #142                // Method close:()V
       4: return

  public java.lang.String toString();
    Code:
       0: new           #83                 // class java/lang/StringBuilder
       3: dup
       4: invokespecial #84                 // Method java/lang/StringBuilder."<init>":()V
       7: aload_0
       8: invokespecial #143                // Method org/apache/dubbo/remoting/api/connection/AbstractConnectionClient.toString:()Ljava/lang/String;
      11: invokevirtual #86                 // Method java/lang/StringBuilder.append:(Ljava/lang/String;)Ljava/lang/StringBuilder;
      14: ldc           #144                // String  (Ref=
      16: invokevirtual #86                 // Method java/lang/StringBuilder.append:(Ljava/lang/String;)Ljava/lang/StringBuilder;
      19: aload_0
      20: invokevirtual #145                // Method getCounter:()J
      23: invokevirtual #102                // Method java/lang/StringBuilder.append:(J)Ljava/lang/StringBuilder;
      26: ldc           #146                // String ,local=
      28: invokevirtual #86                 // Method java/lang/StringBuilder.append:(Ljava/lang/String;)Ljava/lang/StringBuilder;
      31: aload_0
      32: invokevirtual #125                // Method getChannel:()Lorg/apache/dubbo/remoting/Channel;
      35: ifnonnull     42
      38: aconst_null
      39: goto          51
      42: aload_0
      43: invokevirtual #125                // Method getChannel:()Lorg/apache/dubbo/remoting/Channel;
      46: invokeinterface #147,  1          // InterfaceMethod org/apache/dubbo/remoting/Channel.getLocalAddress:()Ljava/net/InetSocketAddress;
      51: invokevirtual #87                 // Method java/lang/StringBuilder.append:(Ljava/lang/Object;)Ljava/lang/StringBuilder;
      54: ldc           #148                // String ,remote=
      56: invokevirtual #86                 // Method java/lang/StringBuilder.append:(Ljava/lang/String;)Ljava/lang/StringBuilder;
      59: aload_0
      60: invokevirtual #149                // Method getRemoteAddress:()Ljava/net/InetSocketAddress;
      63: invokevirtual #87                 // Method java/lang/StringBuilder.append:(Ljava/lang/Object;)Ljava/lang/StringBuilder;
      66: invokevirtual #91                 // Method java/lang/StringBuilder.toString:()Ljava/lang/String;
      69: areturn

  private static void lambda$addCloseListener$0(java.lang.Runnable, io.netty.util.concurrent.Future) throws java.lang.Exception;
    Code:
       0: aload_0
       1: invokeinterface #150,  1          // InterfaceMethod java/lang/Runnable.run:()V
       6: return

  static org.apache.dubbo.remoting.api.WireProtocol access$000(org.apache.dubbo.remoting.transport.netty4.NettyConnectionClient);
    Code:
       0: aload_0
       1: getfield      #4                  // Field protocol:Lorg/apache/dubbo/remoting/api/WireProtocol;
       4: areturn

  static org.apache.dubbo.common.logger.ErrorTypeAwareLogger access$100();
    Code:
       0: getstatic     #3                  // Field LOGGER:Lorg/apache/dubbo/common/logger/ErrorTypeAwareLogger;
       3: areturn

  static {};
    Code:
       0: ldc           #151                // class org/apache/dubbo/remoting/transport/netty4/NettyConnectionClient
       2: invokestatic  #152                // Method org/apache/dubbo/common/logger/LoggerFactory.getErrorTypeAwareLogger:(Ljava/lang/Class;)Lorg/apache/dubbo/common/logger/ErrorTypeAwareLogger;
       5: putstatic     #3                  // Field LOGGER:Lorg/apache/dubbo/common/logger/ErrorTypeAwareLogger;
       8: ldc           #153                // String connection
      10: invokestatic  #154                // Method io/netty/util/AttributeKey.valueOf:(Ljava/lang/String;)Lio/netty/util/AttributeKey;
      13: putstatic     #116                // Field CONNECTION:Lio/netty/util/AttributeKey;
      16: return
}
