Compiled from "NettyPortUnificationServerHandler.java"
public class org.apache.dubbo.remoting.transport.netty4.NettyPortUnificationServerHandler extends io.netty.handler.codec.ByteToMessageDecoder {
  private static final org.apache.dubbo.common.logger.ErrorTypeAwareLogger LOGGER;

  private final org.apache.dubbo.common.URL url;

  private final org.apache.dubbo.remoting.ChannelHandler handler;

  private final boolean detectSsl;

  private final java.util.List<org.apache.dubbo.remoting.api.WireProtocol> protocols;

  private final java.util.Map<java.lang.String, org.apache.dubbo.common.URL> urlMapper;

  private final java.util.Map<java.lang.String, org.apache.dubbo.remoting.ChannelHandler> handlerMapper;

  public org.apache.dubbo.remoting.transport.netty4.NettyPortUnificationServerHandler(org.apache.dubbo.common.URL, boolean, java.util.List<org.apache.dubbo.remoting.api.WireProtocol>, org.apache.dubbo.remoting.ChannelHandler, java.util.Map<java.lang.String, org.apache.dubbo.common.URL>, java.util.Map<java.lang.String, org.apache.dubbo.remoting.ChannelHandler>);
    Code:
       0: aload_0
       1: invokespecial #2                  // Method io/netty/handler/codec/ByteToMessageDecoder."<init>":()V
       4: aload_0
       5: aload_1
       6: putfield      #3                  // Field url:Lorg/apache/dubbo/common/URL;
       9: aload_0
      10: aload_3
      11: putfield      #4                  // Field protocols:Ljava/util/List;
      14: aload_0
      15: iload_2
      16: putfield      #5                  // Field detectSsl:Z
      19: aload_0
      20: aload         4
      22: putfield      #6                  // Field handler:Lorg/apache/dubbo/remoting/ChannelHandler;
      25: aload_0
      26: aload         5
      28: putfield      #7                  // Field urlMapper:Ljava/util/Map;
      31: aload_0
      32: aload         6
      34: putfield      #8                  // Field handlerMapper:Ljava/util/Map;
      37: return

  public void exceptionCaught(io.netty.channel.ChannelHandlerContext, java.lang.Throwable) throws java.lang.Exception;
    Code:
       0: getstatic     #9                  // Field LOGGER:Lorg/apache/dubbo/common/logger/ErrorTypeAwareLogger;
       3: ldc           #10                 // String 99-0
       5: ldc           #11                 // String unknown error in remoting module
       7: ldc           #12                 // String
       9: ldc           #13                 // String Unexpected exception from downstream before protocol detected.
      11: aload_2
      12: invokeinterface #14,  6           // InterfaceMethod org/apache/dubbo/common/logger/ErrorTypeAwareLogger.error:(Ljava/lang/String;Ljava/lang/String;Ljava/lang/String;Ljava/lang/String;Ljava/lang/Throwable;)V
      17: return

  public void userEventTriggered(io.netty.channel.ChannelHandlerContext, java.lang.Object) throws java.lang.Exception;
    Code:
       0: aload_2
       1: instanceof    #15                 // class io/netty/handler/ssl/SslHandshakeCompletionEvent
       4: ifeq          101
       7: aload_2
       8: checkcast     #15                 // class io/netty/handler/ssl/SslHandshakeCompletionEvent
      11: astore_3
      12: aload_3
      13: invokevirtual #16                 // Method io/netty/handler/ssl/SslHandshakeCompletionEvent.isSuccess:()Z
      16: ifeq          74
      19: aload_1
      20: invokeinterface #17,  1           // InterfaceMethod io/netty/channel/ChannelHandlerContext.pipeline:()Lio/netty/channel/ChannelPipeline;
      25: ldc           #18                 // class io/netty/handler/ssl/SslHandler
      27: invokeinterface #19,  2           // InterfaceMethod io/netty/channel/ChannelPipeline.get:(Ljava/lang/Class;)Lio/netty/channel/ChannelHandler;
      32: checkcast     #18                 // class io/netty/handler/ssl/SslHandler
      35: invokevirtual #20                 // Method io/netty/handler/ssl/SslHandler.engine:()Ljavax/net/ssl/SSLEngine;
      38: invokevirtual #21                 // Method javax/net/ssl/SSLEngine.getSession:()Ljavax/net/ssl/SSLSession;
      41: astore        4
      43: getstatic     #9                  // Field LOGGER:Lorg/apache/dubbo/common/logger/ErrorTypeAwareLogger;
      46: new           #22                 // class java/lang/StringBuilder
      49: dup
      50: invokespecial #23                 // Method java/lang/StringBuilder."<init>":()V
      53: ldc           #24                 // String TLS negotiation succeed with session:
      55: invokevirtual #25                 // Method java/lang/StringBuilder.append:(Ljava/lang/String;)Ljava/lang/StringBuilder;
      58: aload         4
      60: invokevirtual #26                 // Method java/lang/StringBuilder.append:(Ljava/lang/Object;)Ljava/lang/StringBuilder;
      63: invokevirtual #27                 // Method java/lang/StringBuilder.toString:()Ljava/lang/String;
      66: invokeinterface #28,  2           // InterfaceMethod org/apache/dubbo/common/logger/ErrorTypeAwareLogger.info:(Ljava/lang/String;)V
      71: goto          101
      74: getstatic     #9                  // Field LOGGER:Lorg/apache/dubbo/common/logger/ErrorTypeAwareLogger;
      77: ldc           #10                 // String 99-0
      79: ldc           #12                 // String
      81: ldc           #12                 // String
      83: ldc           #29                 // String TLS negotiation failed when trying to accept new connection.
      85: aload_3
      86: invokevirtual #30                 // Method io/netty/handler/ssl/SslHandshakeCompletionEvent.cause:()Ljava/lang/Throwable;
      89: invokeinterface #14,  6           // InterfaceMethod org/apache/dubbo/common/logger/ErrorTypeAwareLogger.error:(Ljava/lang/String;Ljava/lang/String;Ljava/lang/String;Ljava/lang/String;Ljava/lang/Throwable;)V
      94: aload_1
      95: invokeinterface #31,  1           // InterfaceMethod io/netty/channel/ChannelHandlerContext.close:()Lio/netty/channel/ChannelFuture;
     100: pop
     101: aload_0
     102: aload_1
     103: aload_2
     104: invokespecial #32                 // Method io/netty/handler/codec/ByteToMessageDecoder.userEventTriggered:(Lio/netty/channel/ChannelHandlerContext;Ljava/lang/Object;)V
     107: return

  protected void decode(io.netty.channel.ChannelHandlerContext, io.netty.buffer.ByteBuf, java.util.List<java.lang.Object>) throws java.lang.Exception;
    Code:
       0: aload_1
       1: invokeinterface #33,  1           // InterfaceMethod io/netty/channel/ChannelHandlerContext.channel:()Lio/netty/channel/Channel;
       6: aload_0
       7: getfield      #3                  // Field url:Lorg/apache/dubbo/common/URL;
      10: aload_0
      11: getfield      #6                  // Field handler:Lorg/apache/dubbo/remoting/ChannelHandler;
      14: invokestatic  #34                 // Method org/apache/dubbo/remoting/transport/netty4/NettyChannel.getOrAddChannel:(Lio/netty/channel/Channel;Lorg/apache/dubbo/common/URL;Lorg/apache/dubbo/remoting/ChannelHandler;)Lorg/apache/dubbo/remoting/transport/netty4/NettyChannel;
      17: astore        4
      19: aload_2
      20: invokevirtual #35                 // Method io/netty/buffer/ByteBuf.readableBytes:()I
      23: iconst_2
      24: if_icmpge     28
      27: return
      28: aload_0
      29: getfield      #3                  // Field url:Lorg/apache/dubbo/common/URL;
      32: invokevirtual #36                 // Method org/apache/dubbo/common/URL.getOrDefaultFrameworkModel:()Lorg/apache/dubbo/rpc/model/FrameworkModel;
      35: invokevirtual #37                 // Method org/apache/dubbo/rpc/model/FrameworkModel.getBeanFactory:()Lorg/apache/dubbo/common/beans/factory/ScopeBeanFactory;
      38: ldc           #38                 // class org/apache/dubbo/common/ssl/CertManager
      40: invokevirtual #39                 // Method org/apache/dubbo/common/beans/factory/ScopeBeanFactory.getBean:(Ljava/lang/Class;)Ljava/lang/Object;
      43: checkcast     #38                 // class org/apache/dubbo/common/ssl/CertManager
      46: astore        5
      48: aload         5
      50: aload_0
      51: getfield      #3                  // Field url:Lorg/apache/dubbo/common/URL;
      54: aload_1
      55: invokeinterface #33,  1           // InterfaceMethod io/netty/channel/ChannelHandlerContext.channel:()Lio/netty/channel/Channel;
      60: invokeinterface #40,  1           // InterfaceMethod io/netty/channel/Channel.remoteAddress:()Ljava/net/SocketAddress;
      65: invokevirtual #41                 // Method org/apache/dubbo/common/ssl/CertManager.getProviderConnectionConfig:(Lorg/apache/dubbo/common/URL;Ljava/net/SocketAddress;)Lorg/apache/dubbo/common/ssl/ProviderCert;
      68: astore        6
      70: aload         6
      72: ifnull        93
      75: aload_0
      76: aload_2
      77: invokespecial #42                 // Method isSsl:(Lio/netty/buffer/ByteBuf;)Z
      80: ifeq          93
      83: aload_0
      84: aload_1
      85: aload         6
      87: invokespecial #43                 // Method enableSsl:(Lio/netty/channel/ChannelHandlerContext;Lorg/apache/dubbo/common/ssl/ProviderCert;)V
      90: goto          400
      93: aload_0
      94: getfield      #4                  // Field protocols:Ljava/util/List;
      97: invokeinterface #44,  1           // InterfaceMethod java/util/List.iterator:()Ljava/util/Iterator;
     102: astore        7
     104: aload         7
     106: invokeinterface #45,  1           // InterfaceMethod java/util/Iterator.hasNext:()Z
     111: ifeq          306
     114: aload         7
     116: invokeinterface #46,  1           // InterfaceMethod java/util/Iterator.next:()Ljava/lang/Object;
     121: checkcast     #47                 // class org/apache/dubbo/remoting/api/WireProtocol
     124: astore        8
     126: aload_2
     127: invokevirtual #48                 // Method io/netty/buffer/ByteBuf.markReaderIndex:()Lio/netty/buffer/ByteBuf;
     130: pop
     131: new           #49                 // class org/apache/dubbo/remoting/transport/netty4/NettyBackedChannelBuffer
     134: dup
     135: aload_2
     136: invokespecial #50                 // Method org/apache/dubbo/remoting/transport/netty4/NettyBackedChannelBuffer."<init>":(Lio/netty/buffer/ByteBuf;)V
     139: astore        9
     141: aload         8
     143: invokeinterface #51,  1           // InterfaceMethod org/apache/dubbo/remoting/api/WireProtocol.detector:()Lorg/apache/dubbo/remoting/api/ProtocolDetector;
     148: aload         9
     150: invokeinterface #52,  2           // InterfaceMethod org/apache/dubbo/remoting/api/ProtocolDetector.detect:(Lorg/apache/dubbo/remoting/buffer/ChannelBuffer;)Lorg/apache/dubbo/remoting/api/ProtocolDetector$Result;
     155: astore        10
     157: aload_2
     158: invokevirtual #53                 // Method io/netty/buffer/ByteBuf.resetReaderIndex:()Lio/netty/buffer/ByteBuf;
     161: pop
     162: getstatic     #54                 // Field org/apache/dubbo/remoting/transport/netty4/NettyPortUnificationServerHandler$1.$SwitchMap$org$apache$dubbo$remoting$api$ProtocolDetector$Result:[I
     165: aload         10
     167: invokevirtual #55                 // Method org/apache/dubbo/remoting/api/ProtocolDetector$Result.ordinal:()I
     170: iaload
     171: tableswitch   { // 1 to 3
                     1: 196
                     2: 199
                     3: 304
               default: 305
          }
     196: goto          104
     199: aload_0
     200: getfield      #3                  // Field url:Lorg/apache/dubbo/common/URL;
     203: invokevirtual #36                 // Method org/apache/dubbo/common/URL.getOrDefaultFrameworkModel:()Lorg/apache/dubbo/rpc/model/FrameworkModel;
     206: ldc           #47                 // class org/apache/dubbo/remoting/api/WireProtocol
     208: invokevirtual #56                 // Method org/apache/dubbo/rpc/model/FrameworkModel.getExtensionLoader:(Ljava/lang/Class;)Lorg/apache/dubbo/common/extension/ExtensionLoader;
     211: aload         8
     213: invokevirtual #57                 // Method org/apache/dubbo/common/extension/ExtensionLoader.getExtensionName:(Ljava/lang/Object;)Ljava/lang/String;
     216: astore        11
     218: aload_0
     219: getfield      #8                  // Field handlerMapper:Ljava/util/Map;
     222: aload         11
     224: aload_0
     225: getfield      #6                  // Field handler:Lorg/apache/dubbo/remoting/ChannelHandler;
     228: invokeinterface #58,  3           // InterfaceMethod java/util/Map.getOrDefault:(Ljava/lang/Object;Ljava/lang/Object;)Ljava/lang/Object;
     233: checkcast     #59                 // class org/apache/dubbo/remoting/ChannelHandler
     236: astore        12
     238: aload_0
     239: getfield      #7                  // Field urlMapper:Ljava/util/Map;
     242: aload         11
     244: aload_0
     245: getfield      #3                  // Field url:Lorg/apache/dubbo/common/URL;
     248: invokeinterface #58,  3           // InterfaceMethod java/util/Map.getOrDefault:(Ljava/lang/Object;Ljava/lang/Object;)Ljava/lang/Object;
     253: checkcast     #60                 // class org/apache/dubbo/common/URL
     256: astore        13
     258: aload         4
     260: aload         13
     262: invokevirtual #61                 // Method org/apache/dubbo/remoting/transport/netty4/NettyChannel.setUrl:(Lorg/apache/dubbo/common/URL;)V
     265: new           #62                 // class org/apache/dubbo/remoting/transport/netty4/NettyConfigOperator
     268: dup
     269: aload         4
     271: aload         12
     273: invokespecial #63                 // Method org/apache/dubbo/remoting/transport/netty4/NettyConfigOperator."<init>":(Lorg/apache/dubbo/remoting/transport/netty4/NettyChannel;Lorg/apache/dubbo/remoting/ChannelHandler;)V
     276: astore        14
     278: aload         8
     280: aload_0
     281: getfield      #3                  // Field url:Lorg/apache/dubbo/common/URL;
     284: aload         14
     286: invokeinterface #64,  3           // InterfaceMethod org/apache/dubbo/remoting/api/WireProtocol.configServerProtocolHandler:(Lorg/apache/dubbo/common/URL;Lorg/apache/dubbo/remoting/api/pu/ChannelOperator;)V
     291: aload_1
     292: invokeinterface #17,  1           // InterfaceMethod io/netty/channel/ChannelHandlerContext.pipeline:()Lio/netty/channel/ChannelPipeline;
     297: aload_0
     298: invokeinterface #65,  2           // InterfaceMethod io/netty/channel/ChannelPipeline.remove:(Lio/netty/channel/ChannelHandler;)Lio/netty/channel/ChannelPipeline;
     303: pop
     304: return
     305: return
     306: aload_2
     307: invokevirtual #35                 // Method io/netty/buffer/ByteBuf.readableBytes:()I
     310: newarray       byte
     312: astore        7
     314: aload_2
     315: aload         7
     317: invokevirtual #66                 // Method io/netty/buffer/ByteBuf.readBytes:([B)Lio/netty/buffer/ByteBuf;
     320: pop
     321: aload_0
     322: getfield      #3                  // Field url:Lorg/apache/dubbo/common/URL;
     325: invokevirtual #67                 // Method org/apache/dubbo/common/URL.getApplicationModel:()Lorg/apache/dubbo/rpc/model/ApplicationModel;
     328: ldc           #47                 // class org/apache/dubbo/remoting/api/WireProtocol
     330: invokevirtual #68                 // Method org/apache/dubbo/rpc/model/ApplicationModel.getExtensionLoader:(Ljava/lang/Class;)Lorg/apache/dubbo/common/extension/ExtensionLoader;
     333: invokevirtual #69                 // Method org/apache/dubbo/common/extension/ExtensionLoader.getSupportedExtensions:()Ljava/util/Set;
     336: astore        8
     338: getstatic     #9                  // Field LOGGER:Lorg/apache/dubbo/common/logger/ErrorTypeAwareLogger;
     341: ldc           #10                 // String 99-0
     343: ldc           #11                 // String unknown error in remoting module
     345: ldc           #12                 // String
     347: ldc           #70                 // String Can not recognize protocol from downstream=%s . preface=%s protocols=%s
     349: iconst_3
     350: anewarray     #71                 // class java/lang/Object
     353: dup
     354: iconst_0
     355: aload_1
     356: invokeinterface #33,  1           // InterfaceMethod io/netty/channel/ChannelHandlerContext.channel:()Lio/netty/channel/Channel;
     361: invokeinterface #40,  1           // InterfaceMethod io/netty/channel/Channel.remoteAddress:()Ljava/net/SocketAddress;
     366: aastore
     367: dup
     368: iconst_1
     369: aload         7
     371: invokestatic  #72                 // Method org/apache/dubbo/common/io/Bytes.bytes2hex:([B)Ljava/lang/String;
     374: aastore
     375: dup
     376: iconst_2
     377: aload         8
     379: aastore
     380: invokestatic  #73                 // Method java/lang/String.format:(Ljava/lang/String;[Ljava/lang/Object;)Ljava/lang/String;
     383: invokeinterface #74,  5           // InterfaceMethod org/apache/dubbo/common/logger/ErrorTypeAwareLogger.error:(Ljava/lang/String;Ljava/lang/String;Ljava/lang/String;Ljava/lang/String;)V
     388: aload_2
     389: invokevirtual #75                 // Method io/netty/buffer/ByteBuf.clear:()Lio/netty/buffer/ByteBuf;
     392: pop
     393: aload_1
     394: invokeinterface #31,  1           // InterfaceMethod io/netty/channel/ChannelHandlerContext.close:()Lio/netty/channel/ChannelFuture;
     399: pop
     400: return

  private void enableSsl(io.netty.channel.ChannelHandlerContext, org.apache.dubbo.common.ssl.ProviderCert);
    Code:
       0: aload_1
       1: invokeinterface #17,  1           // InterfaceMethod io/netty/channel/ChannelHandlerContext.pipeline:()Lio/netty/channel/ChannelPipeline;
       6: astore_3
       7: aload_2
       8: invokestatic  #76                 // Method org/apache/dubbo/remoting/transport/netty4/ssl/SslContexts.buildServerSslContext:(Lorg/apache/dubbo/common/ssl/ProviderCert;)Lio/netty/handler/ssl/SslContext;
      11: astore        4
      13: aload_3
      14: ldc           #77                 // String ssl
      16: aload         4
      18: aload_1
      19: invokeinterface #78,  1           // InterfaceMethod io/netty/channel/ChannelHandlerContext.alloc:()Lio/netty/buffer/ByteBufAllocator;
      24: invokevirtual #79                 // Method io/netty/handler/ssl/SslContext.newHandler:(Lio/netty/buffer/ByteBufAllocator;)Lio/netty/handler/ssl/SslHandler;
      27: invokeinterface #80,  3           // InterfaceMethod io/netty/channel/ChannelPipeline.addLast:(Ljava/lang/String;Lio/netty/channel/ChannelHandler;)Lio/netty/channel/ChannelPipeline;
      32: pop
      33: aload_3
      34: ldc           #81                 // String unificationA
      36: new           #82                 // class org/apache/dubbo/remoting/transport/netty4/NettyPortUnificationServerHandler
      39: dup
      40: aload_0
      41: getfield      #3                  // Field url:Lorg/apache/dubbo/common/URL;
      44: iconst_0
      45: aload_0
      46: getfield      #4                  // Field protocols:Ljava/util/List;
      49: aload_0
      50: getfield      #6                  // Field handler:Lorg/apache/dubbo/remoting/ChannelHandler;
      53: aload_0
      54: getfield      #7                  // Field urlMapper:Ljava/util/Map;
      57: aload_0
      58: getfield      #8                  // Field handlerMapper:Ljava/util/Map;
      61: invokespecial #83                 // Method "<init>":(Lorg/apache/dubbo/common/URL;ZLjava/util/List;Lorg/apache/dubbo/remoting/ChannelHandler;Ljava/util/Map;Ljava/util/Map;)V
      64: invokeinterface #80,  3           // InterfaceMethod io/netty/channel/ChannelPipeline.addLast:(Ljava/lang/String;Lio/netty/channel/ChannelHandler;)Lio/netty/channel/ChannelPipeline;
      69: pop
      70: aload_3
      71: aload_0
      72: invokeinterface #65,  2           // InterfaceMethod io/netty/channel/ChannelPipeline.remove:(Lio/netty/channel/ChannelHandler;)Lio/netty/channel/ChannelPipeline;
      77: pop
      78: return

  private boolean isSsl(io.netty.buffer.ByteBuf);
    Code:
       0: aload_0
       1: getfield      #5                  // Field detectSsl:Z
       4: ifeq          20
       7: aload_1
       8: invokevirtual #35                 // Method io/netty/buffer/ByteBuf.readableBytes:()I
      11: iconst_5
      12: if_icmplt     20
      15: aload_1
      16: invokestatic  #84                 // Method io/netty/handler/ssl/SslHandler.isEncrypted:(Lio/netty/buffer/ByteBuf;)Z
      19: ireturn
      20: iconst_0
      21: ireturn

  static {};
    Code:
       0: ldc           #82                 // class org/apache/dubbo/remoting/transport/netty4/NettyPortUnificationServerHandler
       2: invokestatic  #85                 // Method org/apache/dubbo/common/logger/LoggerFactory.getErrorTypeAwareLogger:(Ljava/lang/Class;)Lorg/apache/dubbo/common/logger/ErrorTypeAwareLogger;
       5: putstatic     #9                  // Field LOGGER:Lorg/apache/dubbo/common/logger/ErrorTypeAwareLogger;
       8: return
}
