Compiled from "NettyChannel.java"
class org.apache.dubbo.remoting.transport.netty4.NettyChannel$1 implements io.netty.channel.ChannelFutureListener {
  final java.lang.Object val$message;

  final org.apache.dubbo.remoting.transport.netty4.NettyChannel this$0;

  org.apache.dubbo.remoting.transport.netty4.NettyChannel$1(org.apache.dubbo.remoting.transport.netty4.NettyChannel, java.lang.Object);
    Code:
       0: aload_0
       1: aload_1
       2: putfield      #1                  // Field this$0:Lorg/apache/dubbo/remoting/transport/netty4/NettyChannel;
       5: aload_0
       6: aload_2
       7: putfield      #2                  // Field val$message:Ljava/lang/Object;
      10: aload_0
      11: invokespecial #3                  // Method java/lang/Object."<init>":()V
      14: return

  public void operationComplete(io.netty.channel.ChannelFuture) throws java.lang.Exception;
    Code:
       0: aload_0
       1: getfield      #2                  // Field val$message:Ljava/lang/Object;
       4: instanceof    #4                  // class org/apache/dubbo/remoting/exchange/Request
       7: ifne          11
      10: return
      11: aload_0
      12: getfield      #1                  // Field this$0:Lorg/apache/dubbo/remoting/transport/netty4/NettyChannel;
      15: invokevirtual #5                  // Method org/apache/dubbo/remoting/transport/netty4/NettyChannel.getChannelHandler:()Lorg/apache/dubbo/remoting/ChannelHandler;
      18: astore_2
      19: aload_1
      20: invokeinterface #6,  1            // InterfaceMethod io/netty/channel/ChannelFuture.isSuccess:()Z
      25: ifeq          45
      28: aload_2
      29: aload_0
      30: getfield      #1                  // Field this$0:Lorg/apache/dubbo/remoting/transport/netty4/NettyChannel;
      33: aload_0
      34: getfield      #2                  // Field val$message:Ljava/lang/Object;
      37: invokeinterface #7,  3            // InterfaceMethod org/apache/dubbo/remoting/ChannelHandler.sent:(Lorg/apache/dubbo/remoting/Channel;Ljava/lang/Object;)V
      42: goto          82
      45: aload_1
      46: invokeinterface #8,  1            // InterfaceMethod io/netty/channel/ChannelFuture.cause:()Ljava/lang/Throwable;
      51: astore_3
      52: aload_3
      53: ifnonnull     57
      56: return
      57: aload_0
      58: getfield      #2                  // Field val$message:Ljava/lang/Object;
      61: checkcast     #4                  // class org/apache/dubbo/remoting/exchange/Request
      64: aload_3
      65: invokestatic  #9                  // Method org/apache/dubbo/remoting/transport/netty4/NettyChannel.access$000:(Lorg/apache/dubbo/remoting/exchange/Request;Ljava/lang/Throwable;)Lorg/apache/dubbo/remoting/exchange/Response;
      68: astore        4
      70: aload_2
      71: aload_0
      72: getfield      #1                  // Field this$0:Lorg/apache/dubbo/remoting/transport/netty4/NettyChannel;
      75: aload         4
      77: invokeinterface #10,  3           // InterfaceMethod org/apache/dubbo/remoting/ChannelHandler.received:(Lorg/apache/dubbo/remoting/Channel;Ljava/lang/Object;)V
      82: return

  public void operationComplete(io.netty.util.concurrent.Future) throws java.lang.Exception;
    Code:
       0: aload_0
       1: aload_1
       2: checkcast     #11                 // class io/netty/channel/ChannelFuture
       5: invokevirtual #12                 // Method operationComplete:(Lio/netty/channel/ChannelFuture;)V
       8: return
}
