Compiled from "NettyPortUnificationServer.java"
class org.apache.dubbo.remoting.transport.netty4.NettyPortUnificationServer$1 extends io.netty.channel.ChannelInitializer<io.netty.channel.socket.SocketChannel> {
  final org.apache.dubbo.remoting.transport.netty4.NettyPortUnificationServer this$0;

  org.apache.dubbo.remoting.transport.netty4.NettyPortUnificationServer$1(org.apache.dubbo.remoting.transport.netty4.NettyPortUnificationServer);
    Code:
       0: aload_0
       1: aload_1
       2: putfield      #1                  // Field this$0:Lorg/apache/dubbo/remoting/transport/netty4/NettyPortUnificationServer;
       5: aload_0
       6: invokespecial #2                  // Method io/netty/channel/ChannelInitializer."<init>":()V
       9: return

  protected void initChannel(io.netty.channel.socket.SocketChannel) throws java.lang.Exception;
    Code:
       0: aload_1
       1: invokeinterface #3,  1            // InterfaceMethod io/netty/channel/socket/SocketChannel.pipeline:()Lio/netty/channel/ChannelPipeline;
       6: astore_2
       7: new           #4                  // class org/apache/dubbo/remoting/transport/netty4/NettyChannelHandler
      10: dup
      11: aload_0
      12: getfield      #1                  // Field this$0:Lorg/apache/dubbo/remoting/transport/netty4/NettyPortUnificationServer;
      15: invokestatic  #5                  // Method org/apache/dubbo/remoting/transport/netty4/NettyPortUnificationServer.access$000:(Lorg/apache/dubbo/remoting/transport/netty4/NettyPortUnificationServer;)Ljava/util/Map;
      18: aload_0
      19: getfield      #1                  // Field this$0:Lorg/apache/dubbo/remoting/transport/netty4/NettyPortUnificationServer;
      22: invokevirtual #6                  // Method org/apache/dubbo/remoting/transport/netty4/NettyPortUnificationServer.getUrl:()Lorg/apache/dubbo/common/URL;
      25: aload_0
      26: getfield      #1                  // Field this$0:Lorg/apache/dubbo/remoting/transport/netty4/NettyPortUnificationServer;
      29: invokespecial #7                  // Method org/apache/dubbo/remoting/transport/netty4/NettyChannelHandler."<init>":(Ljava/util/Map;Lorg/apache/dubbo/common/URL;Lorg/apache/dubbo/remoting/ChannelHandler;)V
      32: astore_3
      33: new           #8                  // class org/apache/dubbo/remoting/transport/netty4/NettyPortUnificationServerHandler
      36: dup
      37: aload_0
      38: getfield      #1                  // Field this$0:Lorg/apache/dubbo/remoting/transport/netty4/NettyPortUnificationServer;
      41: invokevirtual #6                  // Method org/apache/dubbo/remoting/transport/netty4/NettyPortUnificationServer.getUrl:()Lorg/apache/dubbo/common/URL;
      44: iconst_1
      45: aload_0
      46: getfield      #1                  // Field this$0:Lorg/apache/dubbo/remoting/transport/netty4/NettyPortUnificationServer;
      49: invokevirtual #9                  // Method org/apache/dubbo/remoting/transport/netty4/NettyPortUnificationServer.getProtocols:()Ljava/util/List;
      52: aload_0
      53: getfield      #1                  // Field this$0:Lorg/apache/dubbo/remoting/transport/netty4/NettyPortUnificationServer;
      56: aload_0
      57: getfield      #1                  // Field this$0:Lorg/apache/dubbo/remoting/transport/netty4/NettyPortUnificationServer;
      60: invokestatic  #10                 // Method org/apache/dubbo/remoting/transport/netty4/NettyPortUnificationServer.access$100:(Lorg/apache/dubbo/remoting/transport/netty4/NettyPortUnificationServer;)Ljava/util/Map;
      63: aload_0
      64: getfield      #1                  // Field this$0:Lorg/apache/dubbo/remoting/transport/netty4/NettyPortUnificationServer;
      67: invokevirtual #11                 // Method org/apache/dubbo/remoting/transport/netty4/NettyPortUnificationServer.getSupportedHandlers:()Ljava/util/Map;
      70: invokespecial #12                 // Method org/apache/dubbo/remoting/transport/netty4/NettyPortUnificationServerHandler."<init>":(Lorg/apache/dubbo/common/URL;ZLjava/util/List;Lorg/apache/dubbo/remoting/ChannelHandler;Ljava/util/Map;Ljava/util/Map;)V
      73: astore        4
      75: aload_2
      76: ldc           #13                 // String channel-handler
      78: aload_3
      79: invokeinterface #14,  3           // InterfaceMethod io/netty/channel/ChannelPipeline.addLast:(Ljava/lang/String;Lio/netty/channel/ChannelHandler;)Lio/netty/channel/ChannelPipeline;
      84: pop
      85: aload_2
      86: ldc           #15                 // String negotiation-protocol
      88: aload         4
      90: invokeinterface #14,  3           // InterfaceMethod io/netty/channel/ChannelPipeline.addLast:(Ljava/lang/String;Lio/netty/channel/ChannelHandler;)Lio/netty/channel/ChannelPipeline;
      95: pop
      96: return

  protected void initChannel(io.netty.channel.Channel) throws java.lang.Exception;
    Code:
       0: aload_0
       1: aload_1
       2: checkcast     #16                 // class io/netty/channel/socket/SocketChannel
       5: invokevirtual #17                 // Method initChannel:(Lio/netty/channel/socket/SocketChannel;)V
       8: return
}
