Compiled from "NettyClient.java"
class org.apache.dubbo.remoting.transport.netty4.NettyClient$1 extends io.netty.channel.ChannelInitializer<io.netty.channel.socket.SocketChannel> {
  final io.netty.handler.ssl.SslContext val$sslContext;

  final org.apache.dubbo.remoting.transport.netty4.NettyClientHandler val$nettyClientHandler;

  final org.apache.dubbo.remoting.transport.netty4.NettyClient this$0;

  org.apache.dubbo.remoting.transport.netty4.NettyClient$1(org.apache.dubbo.remoting.transport.netty4.NettyClient, io.netty.handler.ssl.SslContext, org.apache.dubbo.remoting.transport.netty4.NettyClientHandler);
    Code:
       0: aload_0
       1: aload_1
       2: putfield      #2                  // Field this$0:Lorg/apache/dubbo/remoting/transport/netty4/NettyClient;
       5: aload_0
       6: aload_2
       7: putfield      #3                  // Field val$sslContext:Lio/netty/handler/ssl/SslContext;
      10: aload_0
      11: aload_3
      12: putfield      #4                  // Field val$nettyClientHandler:Lorg/apache/dubbo/remoting/transport/netty4/NettyClientHandler;
      15: aload_0
      16: invokespecial #5                  // Method io/netty/channel/ChannelInitializer."<init>":()V
      19: return

  protected void initChannel(io.netty.channel.socket.SocketChannel) throws java.lang.Exception;
    Code:
       0: aload_0
       1: getfield      #2                  // Field this$0:Lorg/apache/dubbo/remoting/transport/netty4/NettyClient;
       4: invokevirtual #6                  // Method org/apache/dubbo/remoting/transport/netty4/NettyClient.getUrl:()Lorg/apache/dubbo/common/URL;
       7: invokestatic  #7                  // Method org/apache/dubbo/remoting/utils/UrlUtils.getHeartbeat:(Lorg/apache/dubbo/common/URL;)I
      10: istore_2
      11: aload_0
      12: getfield      #3                  // Field val$sslContext:Lio/netty/handler/ssl/SslContext;
      15: ifnull        43
      18: aload_1
      19: invokeinterface #8,  1            // InterfaceMethod io/netty/channel/socket/SocketChannel.pipeline:()Lio/netty/channel/ChannelPipeline;
      24: ldc           #9                  // String negotiation
      26: new           #10                 // class org/apache/dubbo/remoting/transport/netty4/ssl/SslClientTlsHandler
      29: dup
      30: aload_0
      31: getfield      #3                  // Field val$sslContext:Lio/netty/handler/ssl/SslContext;
      34: invokespecial #11                 // Method org/apache/dubbo/remoting/transport/netty4/ssl/SslClientTlsHandler."<init>":(Lio/netty/handler/ssl/SslContext;)V
      37: invokeinterface #12,  3           // InterfaceMethod io/netty/channel/ChannelPipeline.addLast:(Ljava/lang/String;Lio/netty/channel/ChannelHandler;)Lio/netty/channel/ChannelPipeline;
      42: pop
      43: new           #13                 // class org/apache/dubbo/remoting/transport/netty4/NettyCodecAdapter
      46: dup
      47: aload_0
      48: getfield      #2                  // Field this$0:Lorg/apache/dubbo/remoting/transport/netty4/NettyClient;
      51: invokestatic  #14                 // Method org/apache/dubbo/remoting/transport/netty4/NettyClient.access$000:(Lorg/apache/dubbo/remoting/transport/netty4/NettyClient;)Lorg/apache/dubbo/remoting/Codec2;
      54: aload_0
      55: getfield      #2                  // Field this$0:Lorg/apache/dubbo/remoting/transport/netty4/NettyClient;
      58: invokevirtual #6                  // Method org/apache/dubbo/remoting/transport/netty4/NettyClient.getUrl:()Lorg/apache/dubbo/common/URL;
      61: aload_0
      62: getfield      #2                  // Field this$0:Lorg/apache/dubbo/remoting/transport/netty4/NettyClient;
      65: invokespecial #15                 // Method org/apache/dubbo/remoting/transport/netty4/NettyCodecAdapter."<init>":(Lorg/apache/dubbo/remoting/Codec2;Lorg/apache/dubbo/common/URL;Lorg/apache/dubbo/remoting/ChannelHandler;)V
      68: astore_3
      69: aload_1
      70: invokeinterface #8,  1            // InterfaceMethod io/netty/channel/socket/SocketChannel.pipeline:()Lio/netty/channel/ChannelPipeline;
      75: ldc           #16                 // String decoder
      77: aload_3
      78: invokevirtual #17                 // Method org/apache/dubbo/remoting/transport/netty4/NettyCodecAdapter.getDecoder:()Lio/netty/channel/ChannelHandler;
      81: invokeinterface #12,  3           // InterfaceMethod io/netty/channel/ChannelPipeline.addLast:(Ljava/lang/String;Lio/netty/channel/ChannelHandler;)Lio/netty/channel/ChannelPipeline;
      86: ldc           #18                 // String encoder
      88: aload_3
      89: invokevirtual #19                 // Method org/apache/dubbo/remoting/transport/netty4/NettyCodecAdapter.getEncoder:()Lio/netty/channel/ChannelHandler;
      92: invokeinterface #12,  3           // InterfaceMethod io/netty/channel/ChannelPipeline.addLast:(Ljava/lang/String;Lio/netty/channel/ChannelHandler;)Lio/netty/channel/ChannelPipeline;
      97: ldc           #20                 // String client-idle-handler
      99: new           #21                 // class io/netty/handler/timeout/IdleStateHandler
     102: dup
     103: iload_2
     104: i2l
     105: lconst_0
     106: lconst_0
     107: getstatic     #22                 // Field java/util/concurrent/TimeUnit.MILLISECONDS:Ljava/util/concurrent/TimeUnit;
     110: invokespecial #23                 // Method io/netty/handler/timeout/IdleStateHandler."<init>":(JJJLjava/util/concurrent/TimeUnit;)V
     113: invokeinterface #12,  3           // InterfaceMethod io/netty/channel/ChannelPipeline.addLast:(Ljava/lang/String;Lio/netty/channel/ChannelHandler;)Lio/netty/channel/ChannelPipeline;
     118: ldc           #24                 // String handler
     120: aload_0
     121: getfield      #4                  // Field val$nettyClientHandler:Lorg/apache/dubbo/remoting/transport/netty4/NettyClientHandler;
     124: invokeinterface #12,  3           // InterfaceMethod io/netty/channel/ChannelPipeline.addLast:(Ljava/lang/String;Lio/netty/channel/ChannelHandler;)Lio/netty/channel/ChannelPipeline;
     129: pop
     130: aload_0
     131: getfield      #2                  // Field this$0:Lorg/apache/dubbo/remoting/transport/netty4/NettyClient;
     134: invokevirtual #6                  // Method org/apache/dubbo/remoting/transport/netty4/NettyClient.getUrl:()Lorg/apache/dubbo/common/URL;
     137: invokevirtual #25                 // Method org/apache/dubbo/common/URL.getOrDefaultApplicationModel:()Lorg/apache/dubbo/rpc/model/ApplicationModel;
     140: ldc           #26                 // String socksProxyHost
     142: invokestatic  #27                 // Method org/apache/dubbo/common/config/ConfigurationUtils.getProperty:(Lorg/apache/dubbo/rpc/model/ScopeModel;Ljava/lang/String;)Ljava/lang/String;
     145: astore        4
     147: aload         4
     149: ifnull        235
     152: aload_0
     153: getfield      #2                  // Field this$0:Lorg/apache/dubbo/remoting/transport/netty4/NettyClient;
     156: aload_0
     157: getfield      #2                  // Field this$0:Lorg/apache/dubbo/remoting/transport/netty4/NettyClient;
     160: invokevirtual #6                  // Method org/apache/dubbo/remoting/transport/netty4/NettyClient.getUrl:()Lorg/apache/dubbo/common/URL;
     163: invokevirtual #28                 // Method org/apache/dubbo/common/URL.getHost:()Ljava/lang/String;
     166: invokestatic  #29                 // Method org/apache/dubbo/remoting/transport/netty4/NettyClient.access$100:(Lorg/apache/dubbo/remoting/transport/netty4/NettyClient;Ljava/lang/String;)Z
     169: ifne          235
     172: aload_0
     173: getfield      #2                  // Field this$0:Lorg/apache/dubbo/remoting/transport/netty4/NettyClient;
     176: invokevirtual #6                  // Method org/apache/dubbo/remoting/transport/netty4/NettyClient.getUrl:()Lorg/apache/dubbo/common/URL;
     179: invokevirtual #25                 // Method org/apache/dubbo/common/URL.getOrDefaultApplicationModel:()Lorg/apache/dubbo/rpc/model/ApplicationModel;
     182: ldc           #30                 // String socksProxyPort
     184: ldc           #31                 // String 1080
     186: invokestatic  #32                 // Method org/apache/dubbo/common/config/ConfigurationUtils.getProperty:(Lorg/apache/dubbo/rpc/model/ScopeModel;Ljava/lang/String;Ljava/lang/String;)Ljava/lang/String;
     189: invokestatic  #33                 // Method java/lang/Integer.parseInt:(Ljava/lang/String;)I
     192: istore        5
     194: new           #34                 // class io/netty/handler/proxy/Socks5ProxyHandler
     197: dup
     198: new           #35                 // class java/net/InetSocketAddress
     201: dup
     202: aload         4
     204: iload         5
     206: invokespecial #36                 // Method java/net/InetSocketAddress."<init>":(Ljava/lang/String;I)V
     209: invokespecial #37                 // Method io/netty/handler/proxy/Socks5ProxyHandler."<init>":(Ljava/net/SocketAddress;)V
     212: astore        6
     214: aload_1
     215: invokeinterface #8,  1            // InterfaceMethod io/netty/channel/socket/SocketChannel.pipeline:()Lio/netty/channel/ChannelPipeline;
     220: iconst_1
     221: anewarray     #38                 // class io/netty/channel/ChannelHandler
     224: dup
     225: iconst_0
     226: aload         6
     228: aastore
     229: invokeinterface #39,  2           // InterfaceMethod io/netty/channel/ChannelPipeline.addFirst:([Lio/netty/channel/ChannelHandler;)Lio/netty/channel/ChannelPipeline;
     234: pop
     235: return

  protected void initChannel(io.netty.channel.Channel) throws java.lang.Exception;
    Code:
       0: aload_0
       1: aload_1
       2: checkcast     #40                 // class io/netty/channel/socket/SocketChannel
       5: invokevirtual #41                 // Method initChannel:(Lio/netty/channel/socket/SocketChannel;)V
       8: return
}
