Compiled from "NettyCodecAdapter.java"
class org.apache.dubbo.remoting.transport.netty4.NettyCodecAdapter$InternalEncoder extends io.netty.handler.codec.MessageToByteEncoder {
  final org.apache.dubbo.remoting.transport.netty4.NettyCodecAdapter this$0;

  private org.apache.dubbo.remoting.transport.netty4.NettyCodecAdapter$InternalEncoder(org.apache.dubbo.remoting.transport.netty4.NettyCodecAdapter);
    Code:
       0: aload_0
       1: aload_1
       2: putfield      #2                  // Field this$0:Lorg/apache/dubbo/remoting/transport/netty4/NettyCodecAdapter;
       5: aload_0
       6: invokespecial #3                  // Method io/netty/handler/codec/MessageToByteEncoder."<init>":()V
       9: return

  protected void encode(io.netty.channel.ChannelHandlerContext, java.lang.Object, io.netty.buffer.ByteBuf) throws java.lang.Exception;
    Code:
       0: iconst_0
       1: istore        4
       3: aload_2
       4: instanceof    #4                  // class io/netty/buffer/ByteBuf
       7: ifeq          25
      10: aload_3
      11: aload_2
      12: checkcast     #4                  // class io/netty/buffer/ByteBuf
      15: invokevirtual #5                  // Method io/netty/buffer/ByteBuf.writeBytes:(Lio/netty/buffer/ByteBuf;)Lio/netty/buffer/ByteBuf;
      18: pop
      19: iconst_1
      20: istore        4
      22: goto          94
      25: aload_2
      26: instanceof    #6                  // class org/apache/dubbo/remoting/exchange/support/MultiMessage
      29: ifeq          94
      32: aload_2
      33: checkcast     #6                  // class org/apache/dubbo/remoting/exchange/support/MultiMessage
      36: invokevirtual #7                  // Method org/apache/dubbo/remoting/exchange/support/MultiMessage.iterator:()Ljava/util/Iterator;
      39: astore        5
      41: aload         5
      43: invokeinterface #8,  1            // InterfaceMethod java/util/Iterator.hasNext:()Z
      48: ifeq          94
      51: aload         5
      53: invokeinterface #9,  1            // InterfaceMethod java/util/Iterator.next:()Ljava/lang/Object;
      58: astore        6
      60: aload         6
      62: instanceof    #4                  // class io/netty/buffer/ByteBuf
      65: ifeq          91
      68: aload         6
      70: checkcast     #4                  // class io/netty/buffer/ByteBuf
      73: astore        7
      75: aload_3
      76: aload         7
      78: invokevirtual #5                  // Method io/netty/buffer/ByteBuf.writeBytes:(Lio/netty/buffer/ByteBuf;)Lio/netty/buffer/ByteBuf;
      81: pop
      82: iconst_1
      83: istore        4
      85: aload         7
      87: invokevirtual #10                 // Method io/netty/buffer/ByteBuf.release:()Z
      90: pop
      91: goto          41
      94: iload         4
      96: ifne          155
      99: new           #11                 // class org/apache/dubbo/remoting/transport/netty4/NettyBackedChannelBuffer
     102: dup
     103: aload_3
     104: invokespecial #12                 // Method org/apache/dubbo/remoting/transport/netty4/NettyBackedChannelBuffer."<init>":(Lio/netty/buffer/ByteBuf;)V
     107: astore        5
     109: aload_1
     110: invokeinterface #13,  1           // InterfaceMethod io/netty/channel/ChannelHandlerContext.channel:()Lio/netty/channel/Channel;
     115: astore        6
     117: aload         6
     119: aload_0
     120: getfield      #2                  // Field this$0:Lorg/apache/dubbo/remoting/transport/netty4/NettyCodecAdapter;
     123: invokestatic  #14                 // Method org/apache/dubbo/remoting/transport/netty4/NettyCodecAdapter.access$200:(Lorg/apache/dubbo/remoting/transport/netty4/NettyCodecAdapter;)Lorg/apache/dubbo/common/URL;
     126: aload_0
     127: getfield      #2                  // Field this$0:Lorg/apache/dubbo/remoting/transport/netty4/NettyCodecAdapter;
     130: invokestatic  #15                 // Method org/apache/dubbo/remoting/transport/netty4/NettyCodecAdapter.access$300:(Lorg/apache/dubbo/remoting/transport/netty4/NettyCodecAdapter;)Lorg/apache/dubbo/remoting/ChannelHandler;
     133: invokestatic  #16                 // Method org/apache/dubbo/remoting/transport/netty4/NettyChannel.getOrAddChannel:(Lio/netty/channel/Channel;Lorg/apache/dubbo/common/URL;Lorg/apache/dubbo/remoting/ChannelHandler;)Lorg/apache/dubbo/remoting/transport/netty4/NettyChannel;
     136: astore        7
     138: aload_0
     139: getfield      #2                  // Field this$0:Lorg/apache/dubbo/remoting/transport/netty4/NettyCodecAdapter;
     142: invokestatic  #17                 // Method org/apache/dubbo/remoting/transport/netty4/NettyCodecAdapter.access$400:(Lorg/apache/dubbo/remoting/transport/netty4/NettyCodecAdapter;)Lorg/apache/dubbo/remoting/Codec2;
     145: aload         7
     147: aload         5
     149: aload_2
     150: invokeinterface #18,  4           // InterfaceMethod org/apache/dubbo/remoting/Codec2.encode:(Lorg/apache/dubbo/remoting/Channel;Lorg/apache/dubbo/remoting/buffer/ChannelBuffer;Ljava/lang/Object;)V
     155: return

  org.apache.dubbo.remoting.transport.netty4.NettyCodecAdapter$InternalEncoder(org.apache.dubbo.remoting.transport.netty4.NettyCodecAdapter, org.apache.dubbo.remoting.transport.netty4.NettyCodecAdapter$1);
    Code:
       0: aload_0
       1: aload_1
       2: invokespecial #1                  // Method "<init>":(Lorg/apache/dubbo/remoting/transport/netty4/NettyCodecAdapter;)V
       5: return
}
