Compiled from "NettyChannel.java"
final class org.apache.dubbo.remoting.transport.netty4.NettyChannel extends org.apache.dubbo.remoting.transport.AbstractChannel {
  private static final org.apache.dubbo.common.logger.ErrorTypeAwareLogger logger;

  private static final java.util.concurrent.ConcurrentMap<io.netty.channel.Channel, org.apache.dubbo.remoting.transport.netty4.NettyChannel> CHANNEL_MAP;

  private final io.netty.channel.Channel channel;

  private final java.util.Map<java.lang.String, java.lang.Object> attributes;

  private final java.util.concurrent.atomic.AtomicBoolean active;

  private final org.apache.dubbo.remoting.transport.netty4.Netty4BatchWriteQueue writeQueue;

  private org.apache.dubbo.remoting.Codec2 codec;

  private final boolean encodeInIOThread;

  private org.apache.dubbo.remoting.transport.netty4.NettyChannel(io.netty.channel.Channel, org.apache.dubbo.common.URL, org.apache.dubbo.remoting.ChannelHandler);
    Code:
       0: aload_0
       1: aload_2
       2: aload_3
       3: invokespecial #4                  // Method org/apache/dubbo/remoting/transport/AbstractChannel."<init>":(Lorg/apache/dubbo/common/URL;Lorg/apache/dubbo/remoting/ChannelHandler;)V
       6: aload_0
       7: new           #5                  // class java/util/concurrent/ConcurrentHashMap
      10: dup
      11: invokespecial #6                  // Method java/util/concurrent/ConcurrentHashMap."<init>":()V
      14: putfield      #7                  // Field attributes:Ljava/util/Map;
      17: aload_0
      18: new           #8                  // class java/util/concurrent/atomic/AtomicBoolean
      21: dup
      22: iconst_0
      23: invokespecial #9                  // Method java/util/concurrent/atomic/AtomicBoolean."<init>":(Z)V
      26: putfield      #10                 // Field active:Ljava/util/concurrent/atomic/AtomicBoolean;
      29: aload_1
      30: ifnonnull     43
      33: new           #11                 // class java/lang/IllegalArgumentException
      36: dup
      37: ldc           #12                 // String netty channel == null;
      39: invokespecial #13                 // Method java/lang/IllegalArgumentException."<init>":(Ljava/lang/String;)V
      42: athrow
      43: aload_0
      44: aload_1
      45: putfield      #14                 // Field channel:Lio/netty/channel/Channel;
      48: aload_0
      49: aload_1
      50: invokestatic  #15                 // Method org/apache/dubbo/remoting/transport/netty4/Netty4BatchWriteQueue.createWriteQueue:(Lio/netty/channel/Channel;)Lorg/apache/dubbo/remoting/transport/netty4/Netty4BatchWriteQueue;
      53: putfield      #16                 // Field writeQueue:Lorg/apache/dubbo/remoting/transport/netty4/Netty4BatchWriteQueue;
      56: aload_0
      57: aload_2
      58: invokestatic  #17                 // Method getChannelCodec:(Lorg/apache/dubbo/common/URL;)Lorg/apache/dubbo/remoting/Codec2;
      61: putfield      #18                 // Field codec:Lorg/apache/dubbo/remoting/Codec2;
      64: aload_0
      65: aload_0
      66: invokevirtual #19                 // Method getUrl:()Lorg/apache/dubbo/common/URL;
      69: ldc           #20                 // String encode.in.io
      71: iconst_0
      72: invokevirtual #21                 // Method org/apache/dubbo/common/URL.getParameter:(Ljava/lang/String;Z)Z
      75: putfield      #22                 // Field encodeInIOThread:Z
      78: return

  static org.apache.dubbo.remoting.transport.netty4.NettyChannel getOrAddChannel(io.netty.channel.Channel, org.apache.dubbo.common.URL, org.apache.dubbo.remoting.ChannelHandler);
    Code:
       0: aload_0
       1: ifnonnull     6
       4: aconst_null
       5: areturn
       6: getstatic     #23                 // Field CHANNEL_MAP:Ljava/util/concurrent/ConcurrentMap;
       9: aload_0
      10: invokeinterface #24,  2           // InterfaceMethod java/util/concurrent/ConcurrentMap.get:(Ljava/lang/Object;)Ljava/lang/Object;
      15: checkcast     #25                 // class org/apache/dubbo/remoting/transport/netty4/NettyChannel
      18: astore_3
      19: aload_3
      20: ifnonnull     75
      23: new           #25                 // class org/apache/dubbo/remoting/transport/netty4/NettyChannel
      26: dup
      27: aload_0
      28: aload_1
      29: aload_2
      30: invokespecial #26                 // Method "<init>":(Lio/netty/channel/Channel;Lorg/apache/dubbo/common/URL;Lorg/apache/dubbo/remoting/ChannelHandler;)V
      33: astore        4
      35: aload_0
      36: invokeinterface #27,  1           // InterfaceMethod io/netty/channel/Channel.isActive:()Z
      41: ifeq          65
      44: aload         4
      46: iconst_1
      47: invokevirtual #28                 // Method markActive:(Z)V
      50: getstatic     #23                 // Field CHANNEL_MAP:Ljava/util/concurrent/ConcurrentMap;
      53: aload_0
      54: aload         4
      56: invokeinterface #29,  3           // InterfaceMethod java/util/concurrent/ConcurrentMap.putIfAbsent:(Ljava/lang/Object;Ljava/lang/Object;)Ljava/lang/Object;
      61: checkcast     #25                 // class org/apache/dubbo/remoting/transport/netty4/NettyChannel
      64: astore_3
      65: aload_3
      66: ifnonnull     72
      69: aload         4
      71: astore_3
      72: goto          80
      75: aload_3
      76: iconst_1
      77: invokevirtual #28                 // Method markActive:(Z)V
      80: aload_3
      81: areturn

  static void removeChannelIfDisconnected(io.netty.channel.Channel);
    Code:
       0: aload_0
       1: ifnull        35
       4: aload_0
       5: invokeinterface #27,  1           // InterfaceMethod io/netty/channel/Channel.isActive:()Z
      10: ifne          35
      13: getstatic     #23                 // Field CHANNEL_MAP:Ljava/util/concurrent/ConcurrentMap;
      16: aload_0
      17: invokeinterface #30,  2           // InterfaceMethod java/util/concurrent/ConcurrentMap.remove:(Ljava/lang/Object;)Ljava/lang/Object;
      22: checkcast     #25                 // class org/apache/dubbo/remoting/transport/netty4/NettyChannel
      25: astore_1
      26: aload_1
      27: ifnull        35
      30: aload_1
      31: iconst_0
      32: invokevirtual #28                 // Method markActive:(Z)V
      35: return

  static void removeChannel(io.netty.channel.Channel);
    Code:
       0: aload_0
       1: ifnull        26
       4: getstatic     #23                 // Field CHANNEL_MAP:Ljava/util/concurrent/ConcurrentMap;
       7: aload_0
       8: invokeinterface #30,  2           // InterfaceMethod java/util/concurrent/ConcurrentMap.remove:(Ljava/lang/Object;)Ljava/lang/Object;
      13: checkcast     #25                 // class org/apache/dubbo/remoting/transport/netty4/NettyChannel
      16: astore_1
      17: aload_1
      18: ifnull        26
      21: aload_1
      22: iconst_0
      23: invokevirtual #28                 // Method markActive:(Z)V
      26: return

  public java.net.InetSocketAddress getLocalAddress();
    Code:
       0: aload_0
       1: getfield      #14                 // Field channel:Lio/netty/channel/Channel;
       4: invokeinterface #31,  1           // InterfaceMethod io/netty/channel/Channel.localAddress:()Ljava/net/SocketAddress;
       9: checkcast     #32                 // class java/net/InetSocketAddress
      12: areturn

  public java.net.InetSocketAddress getRemoteAddress();
    Code:
       0: aload_0
       1: getfield      #14                 // Field channel:Lio/netty/channel/Channel;
       4: invokeinterface #33,  1           // InterfaceMethod io/netty/channel/Channel.remoteAddress:()Ljava/net/SocketAddress;
       9: checkcast     #32                 // class java/net/InetSocketAddress
      12: areturn

  public boolean isConnected();
    Code:
       0: aload_0
       1: invokevirtual #34                 // Method isClosed:()Z
       4: ifne          21
       7: aload_0
       8: getfield      #10                 // Field active:Ljava/util/concurrent/atomic/AtomicBoolean;
      11: invokevirtual #35                 // Method java/util/concurrent/atomic/AtomicBoolean.get:()Z
      14: ifeq          21
      17: iconst_1
      18: goto          22
      21: iconst_0
      22: ireturn

  public boolean isActive();
    Code:
       0: aload_0
       1: getfield      #10                 // Field active:Ljava/util/concurrent/atomic/AtomicBoolean;
       4: invokevirtual #35                 // Method java/util/concurrent/atomic/AtomicBoolean.get:()Z
       7: ireturn

  public void markActive(boolean);
    Code:
       0: aload_0
       1: getfield      #10                 // Field active:Ljava/util/concurrent/atomic/AtomicBoolean;
       4: iload_1
       5: invokevirtual #36                 // Method java/util/concurrent/atomic/AtomicBoolean.set:(Z)V
       8: return

  public void send(java.lang.Object, boolean) throws org.apache.dubbo.remoting.RemotingException;
    Code:
       0: aload_0
       1: aload_1
       2: iload_2
       3: invokespecial #37                 // Method org/apache/dubbo/remoting/transport/AbstractChannel.send:(Ljava/lang/Object;Z)V
       6: iconst_1
       7: istore_3
       8: iconst_0
       9: istore        4
      11: aload_1
      12: astore        5
      14: aload_0
      15: getfield      #22                 // Field encodeInIOThread:Z
      18: ifne          65
      21: aload_0
      22: getfield      #14                 // Field channel:Lio/netty/channel/Channel;
      25: invokeinterface #38,  1           // InterfaceMethod io/netty/channel/Channel.alloc:()Lio/netty/buffer/ByteBufAllocator;
      30: invokeinterface #39,  1           // InterfaceMethod io/netty/buffer/ByteBufAllocator.buffer:()Lio/netty/buffer/ByteBuf;
      35: astore        6
      37: new           #40                 // class org/apache/dubbo/remoting/transport/netty4/NettyBackedChannelBuffer
      40: dup
      41: aload         6
      43: invokespecial #41                 // Method org/apache/dubbo/remoting/transport/netty4/NettyBackedChannelBuffer."<init>":(Lio/netty/buffer/ByteBuf;)V
      46: astore        7
      48: aload_0
      49: getfield      #18                 // Field codec:Lorg/apache/dubbo/remoting/Codec2;
      52: aload_0
      53: aload         7
      55: aload_1
      56: invokeinterface #42,  4           // InterfaceMethod org/apache/dubbo/remoting/Codec2.encode:(Lorg/apache/dubbo/remoting/Channel;Lorg/apache/dubbo/remoting/buffer/ChannelBuffer;Ljava/lang/Object;)V
      61: aload         6
      63: astore        5
      65: aload_0
      66: getfield      #16                 // Field writeQueue:Lorg/apache/dubbo/remoting/transport/netty4/Netty4BatchWriteQueue;
      69: aload         5
      71: invokevirtual #43                 // Method org/apache/dubbo/remoting/transport/netty4/Netty4BatchWriteQueue.enqueue:(Ljava/lang/Object;)Lio/netty/channel/ChannelFuture;
      74: new           #44                 // class org/apache/dubbo/remoting/transport/netty4/NettyChannel$1
      77: dup
      78: aload_0
      79: aload_1
      80: invokespecial #45                 // Method org/apache/dubbo/remoting/transport/netty4/NettyChannel$1."<init>":(Lorg/apache/dubbo/remoting/transport/netty4/NettyChannel;Ljava/lang/Object;)V
      83: invokeinterface #46,  2           // InterfaceMethod io/netty/channel/ChannelFuture.addListener:(Lio/netty/util/concurrent/GenericFutureListener;)Lio/netty/channel/ChannelFuture;
      88: astore        6
      90: iload_2
      91: ifeq          119
      94: aload_0
      95: invokevirtual #19                 // Method getUrl:()Lorg/apache/dubbo/common/URL;
      98: ldc           #47                 // String timeout
     100: sipush        1000
     103: invokevirtual #48                 // Method org/apache/dubbo/common/URL.getPositiveParameter:(Ljava/lang/String;I)I
     106: istore        4
     108: aload         6
     110: iload         4
     112: i2l
     113: invokeinterface #49,  3           // InterfaceMethod io/netty/channel/ChannelFuture.await:(J)Z
     118: istore_3
     119: aload         6
     121: invokeinterface #50,  1           // InterfaceMethod io/netty/channel/ChannelFuture.cause:()Ljava/lang/Throwable;
     126: astore        7
     128: aload         7
     130: ifnull        136
     133: aload         7
     135: athrow
     136: goto          206
     139: astore        5
     141: aload_0
     142: getfield      #14                 // Field channel:Lio/netty/channel/Channel;
     145: invokestatic  #52                 // Method removeChannelIfDisconnected:(Lio/netty/channel/Channel;)V
     148: new           #53                 // class org/apache/dubbo/remoting/RemotingException
     151: dup
     152: aload_0
     153: new           #54                 // class java/lang/StringBuilder
     156: dup
     157: invokespecial #55                 // Method java/lang/StringBuilder."<init>":()V
     160: ldc           #56                 // String Failed to send message
     162: invokevirtual #57                 // Method java/lang/StringBuilder.append:(Ljava/lang/String;)Ljava/lang/StringBuilder;
     165: aload_1
     166: invokestatic  #58                 // Method org/apache/dubbo/remoting/utils/PayloadDropper.getRequestWithoutData:(Ljava/lang/Object;)Ljava/lang/Object;
     169: invokevirtual #59                 // Method java/lang/StringBuilder.append:(Ljava/lang/Object;)Ljava/lang/StringBuilder;
     172: ldc           #60                 // String  to
     174: invokevirtual #57                 // Method java/lang/StringBuilder.append:(Ljava/lang/String;)Ljava/lang/StringBuilder;
     177: aload_0
     178: invokevirtual #61                 // Method getRemoteAddress:()Ljava/net/InetSocketAddress;
     181: invokevirtual #59                 // Method java/lang/StringBuilder.append:(Ljava/lang/Object;)Ljava/lang/StringBuilder;
     184: ldc           #62                 // String , cause:
     186: invokevirtual #57                 // Method java/lang/StringBuilder.append:(Ljava/lang/String;)Ljava/lang/StringBuilder;
     189: aload         5
     191: invokevirtual #63                 // Method java/lang/Throwable.getMessage:()Ljava/lang/String;
     194: invokevirtual #57                 // Method java/lang/StringBuilder.append:(Ljava/lang/String;)Ljava/lang/StringBuilder;
     197: invokevirtual #64                 // Method java/lang/StringBuilder.toString:()Ljava/lang/String;
     200: aload         5
     202: invokespecial #65                 // Method org/apache/dubbo/remoting/RemotingException."<init>":(Lorg/apache/dubbo/remoting/Channel;Ljava/lang/String;Ljava/lang/Throwable;)V
     205: athrow
     206: iload_3
     207: ifne          268
     210: new           #53                 // class org/apache/dubbo/remoting/RemotingException
     213: dup
     214: aload_0
     215: new           #54                 // class java/lang/StringBuilder
     218: dup
     219: invokespecial #55                 // Method java/lang/StringBuilder."<init>":()V
     222: ldc           #56                 // String Failed to send message
     224: invokevirtual #57                 // Method java/lang/StringBuilder.append:(Ljava/lang/String;)Ljava/lang/StringBuilder;
     227: aload_1
     228: invokestatic  #58                 // Method org/apache/dubbo/remoting/utils/PayloadDropper.getRequestWithoutData:(Ljava/lang/Object;)Ljava/lang/Object;
     231: invokevirtual #59                 // Method java/lang/StringBuilder.append:(Ljava/lang/Object;)Ljava/lang/StringBuilder;
     234: ldc           #60                 // String  to
     236: invokevirtual #57                 // Method java/lang/StringBuilder.append:(Ljava/lang/String;)Ljava/lang/StringBuilder;
     239: aload_0
     240: invokevirtual #61                 // Method getRemoteAddress:()Ljava/net/InetSocketAddress;
     243: invokevirtual #59                 // Method java/lang/StringBuilder.append:(Ljava/lang/Object;)Ljava/lang/StringBuilder;
     246: ldc           #66                 // String in timeout(
     248: invokevirtual #57                 // Method java/lang/StringBuilder.append:(Ljava/lang/String;)Ljava/lang/StringBuilder;
     251: iload         4
     253: invokevirtual #67                 // Method java/lang/StringBuilder.append:(I)Ljava/lang/StringBuilder;
     256: ldc           #68                 // String ms) limit
     258: invokevirtual #57                 // Method java/lang/StringBuilder.append:(Ljava/lang/String;)Ljava/lang/StringBuilder;
     261: invokevirtual #64                 // Method java/lang/StringBuilder.toString:()Ljava/lang/String;
     264: invokespecial #69                 // Method org/apache/dubbo/remoting/RemotingException."<init>":(Lorg/apache/dubbo/remoting/Channel;Ljava/lang/String;)V
     267: athrow
     268: return
    Exception table:
       from    to  target type
          11   136   139   Class java/lang/Throwable

  public void close();
    Code:
       0: aload_0
       1: invokespecial #70                 // Method org/apache/dubbo/remoting/transport/AbstractChannel.close:()V
       4: goto          27
       7: astore_1
       8: getstatic     #72                 // Field logger:Lorg/apache/dubbo/common/logger/ErrorTypeAwareLogger;
      11: ldc           #73                 // String 6-3
      13: ldc           #74                 // String
      15: ldc           #74                 // String
      17: aload_1
      18: invokevirtual #75                 // Method java/lang/Exception.getMessage:()Ljava/lang/String;
      21: aload_1
      22: invokeinterface #76,  6           // InterfaceMethod org/apache/dubbo/common/logger/ErrorTypeAwareLogger.warn:(Ljava/lang/String;Ljava/lang/String;Ljava/lang/String;Ljava/lang/String;Ljava/lang/Throwable;)V
      27: aload_0
      28: getfield      #14                 // Field channel:Lio/netty/channel/Channel;
      31: invokestatic  #52                 // Method removeChannelIfDisconnected:(Lio/netty/channel/Channel;)V
      34: goto          57
      37: astore_1
      38: getstatic     #72                 // Field logger:Lorg/apache/dubbo/common/logger/ErrorTypeAwareLogger;
      41: ldc           #73                 // String 6-3
      43: ldc           #74                 // String
      45: ldc           #74                 // String
      47: aload_1
      48: invokevirtual #75                 // Method java/lang/Exception.getMessage:()Ljava/lang/String;
      51: aload_1
      52: invokeinterface #76,  6           // InterfaceMethod org/apache/dubbo/common/logger/ErrorTypeAwareLogger.warn:(Ljava/lang/String;Ljava/lang/String;Ljava/lang/String;Ljava/lang/String;Ljava/lang/Throwable;)V
      57: aload_0
      58: getfield      #7                  // Field attributes:Ljava/util/Map;
      61: invokeinterface #77,  1           // InterfaceMethod java/util/Map.clear:()V
      66: goto          89
      69: astore_1
      70: getstatic     #72                 // Field logger:Lorg/apache/dubbo/common/logger/ErrorTypeAwareLogger;
      73: ldc           #73                 // String 6-3
      75: ldc           #74                 // String
      77: ldc           #74                 // String
      79: aload_1
      80: invokevirtual #75                 // Method java/lang/Exception.getMessage:()Ljava/lang/String;
      83: aload_1
      84: invokeinterface #76,  6           // InterfaceMethod org/apache/dubbo/common/logger/ErrorTypeAwareLogger.warn:(Ljava/lang/String;Ljava/lang/String;Ljava/lang/String;Ljava/lang/String;Ljava/lang/Throwable;)V
      89: getstatic     #72                 // Field logger:Lorg/apache/dubbo/common/logger/ErrorTypeAwareLogger;
      92: invokeinterface #78,  1           // InterfaceMethod org/apache/dubbo/common/logger/ErrorTypeAwareLogger.isInfoEnabled:()Z
      97: ifeq          130
     100: getstatic     #72                 // Field logger:Lorg/apache/dubbo/common/logger/ErrorTypeAwareLogger;
     103: new           #54                 // class java/lang/StringBuilder
     106: dup
     107: invokespecial #55                 // Method java/lang/StringBuilder."<init>":()V
     110: ldc           #79                 // String Close netty channel
     112: invokevirtual #57                 // Method java/lang/StringBuilder.append:(Ljava/lang/String;)Ljava/lang/StringBuilder;
     115: aload_0
     116: getfield      #14                 // Field channel:Lio/netty/channel/Channel;
     119: invokevirtual #59                 // Method java/lang/StringBuilder.append:(Ljava/lang/Object;)Ljava/lang/StringBuilder;
     122: invokevirtual #64                 // Method java/lang/StringBuilder.toString:()Ljava/lang/String;
     125: invokeinterface #80,  2           // InterfaceMethod org/apache/dubbo/common/logger/ErrorTypeAwareLogger.info:(Ljava/lang/String;)V
     130: aload_0
     131: getfield      #14                 // Field channel:Lio/netty/channel/Channel;
     134: invokeinterface #81,  1           // InterfaceMethod io/netty/channel/Channel.close:()Lio/netty/channel/ChannelFuture;
     139: pop
     140: goto          163
     143: astore_1
     144: getstatic     #72                 // Field logger:Lorg/apache/dubbo/common/logger/ErrorTypeAwareLogger;
     147: ldc           #73                 // String 6-3
     149: ldc           #74                 // String
     151: ldc           #74                 // String
     153: aload_1
     154: invokevirtual #75                 // Method java/lang/Exception.getMessage:()Ljava/lang/String;
     157: aload_1
     158: invokeinterface #76,  6           // InterfaceMethod org/apache/dubbo/common/logger/ErrorTypeAwareLogger.warn:(Ljava/lang/String;Ljava/lang/String;Ljava/lang/String;Ljava/lang/String;Ljava/lang/Throwable;)V
     163: return
    Exception table:
       from    to  target type
           0     4     7   Class java/lang/Exception
          27    34    37   Class java/lang/Exception
          57    66    69   Class java/lang/Exception
          89   140   143   Class java/lang/Exception

  public boolean hasAttribute(java.lang.String);
    Code:
       0: aload_0
       1: getfield      #7                  // Field attributes:Ljava/util/Map;
       4: aload_1
       5: invokeinterface #82,  2           // InterfaceMethod java/util/Map.containsKey:(Ljava/lang/Object;)Z
      10: ireturn

  public java.lang.Object getAttribute(java.lang.String);
    Code:
       0: aload_0
       1: getfield      #7                  // Field attributes:Ljava/util/Map;
       4: aload_1
       5: invokeinterface #83,  2           // InterfaceMethod java/util/Map.get:(Ljava/lang/Object;)Ljava/lang/Object;
      10: areturn

  public void setAttribute(java.lang.String, java.lang.Object);
    Code:
       0: aload_2
       1: ifnonnull     18
       4: aload_0
       5: getfield      #7                  // Field attributes:Ljava/util/Map;
       8: aload_1
       9: invokeinterface #84,  2           // InterfaceMethod java/util/Map.remove:(Ljava/lang/Object;)Ljava/lang/Object;
      14: pop
      15: goto          30
      18: aload_0
      19: getfield      #7                  // Field attributes:Ljava/util/Map;
      22: aload_1
      23: aload_2
      24: invokeinterface #85,  3           // InterfaceMethod java/util/Map.put:(Ljava/lang/Object;Ljava/lang/Object;)Ljava/lang/Object;
      29: pop
      30: return

  public void removeAttribute(java.lang.String);
    Code:
       0: aload_0
       1: getfield      #7                  // Field attributes:Ljava/util/Map;
       4: aload_1
       5: invokeinterface #84,  2           // InterfaceMethod java/util/Map.remove:(Ljava/lang/Object;)Ljava/lang/Object;
      10: pop
      11: return

  public int hashCode();
    Code:
       0: bipush        31
       2: istore_1
       3: iconst_1
       4: istore_2
       5: bipush        31
       7: iload_2
       8: imul
       9: aload_0
      10: getfield      #14                 // Field channel:Lio/netty/channel/Channel;
      13: ifnonnull     20
      16: iconst_0
      17: goto          27
      20: aload_0
      21: getfield      #14                 // Field channel:Lio/netty/channel/Channel;
      24: invokevirtual #86                 // Method java/lang/Object.hashCode:()I
      27: iadd
      28: istore_2
      29: iload_2
      30: ireturn

  protected void setUrl(org.apache.dubbo.common.URL);
    Code:
       0: aload_0
       1: aload_1
       2: invokespecial #87                 // Method org/apache/dubbo/remoting/transport/AbstractChannel.setUrl:(Lorg/apache/dubbo/common/URL;)V
       5: return

  public boolean equals(java.lang.Object);
    Code:
       0: aload_0
       1: aload_1
       2: if_acmpne     7
       5: iconst_1
       6: ireturn
       7: aload_1
       8: ifnonnull     13
      11: iconst_0
      12: ireturn
      13: aload_1
      14: instanceof    #88                 // class org/apache/dubbo/remoting/transport/netty4/NettyClient
      17: ifeq          37
      20: aload_1
      21: checkcast     #88                 // class org/apache/dubbo/remoting/transport/netty4/NettyClient
      24: astore_2
      25: aload_0
      26: getfield      #14                 // Field channel:Lio/netty/channel/Channel;
      29: aload_2
      30: invokevirtual #89                 // Method org/apache/dubbo/remoting/transport/netty4/NettyClient.getNettyChannel:()Lio/netty/channel/Channel;
      33: invokevirtual #90                 // Method java/lang/Object.equals:(Ljava/lang/Object;)Z
      36: ireturn
      37: aload_0
      38: invokevirtual #91                 // Method java/lang/Object.getClass:()Ljava/lang/Class;
      41: aload_1
      42: invokevirtual #91                 // Method java/lang/Object.getClass:()Ljava/lang/Class;
      45: if_acmpeq     50
      48: iconst_0
      49: ireturn
      50: aload_1
      51: checkcast     #25                 // class org/apache/dubbo/remoting/transport/netty4/NettyChannel
      54: astore_2
      55: aload_0
      56: getfield      #14                 // Field channel:Lio/netty/channel/Channel;
      59: ifnonnull     71
      62: aload_2
      63: getfield      #14                 // Field channel:Lio/netty/channel/Channel;
      66: ifnull        87
      69: iconst_0
      70: ireturn
      71: aload_0
      72: getfield      #14                 // Field channel:Lio/netty/channel/Channel;
      75: aload_2
      76: getfield      #14                 // Field channel:Lio/netty/channel/Channel;
      79: invokevirtual #90                 // Method java/lang/Object.equals:(Ljava/lang/Object;)Z
      82: ifne          87
      85: iconst_0
      86: ireturn
      87: iconst_1
      88: ireturn

  public java.lang.String toString();
    Code:
       0: new           #54                 // class java/lang/StringBuilder
       3: dup
       4: invokespecial #55                 // Method java/lang/StringBuilder."<init>":()V
       7: ldc           #92                 // String NettyChannel [channel=
       9: invokevirtual #57                 // Method java/lang/StringBuilder.append:(Ljava/lang/String;)Ljava/lang/StringBuilder;
      12: aload_0
      13: getfield      #14                 // Field channel:Lio/netty/channel/Channel;
      16: invokevirtual #59                 // Method java/lang/StringBuilder.append:(Ljava/lang/Object;)Ljava/lang/StringBuilder;
      19: ldc           #93                 // String ]
      21: invokevirtual #57                 // Method java/lang/StringBuilder.append:(Ljava/lang/String;)Ljava/lang/StringBuilder;
      24: invokevirtual #64                 // Method java/lang/StringBuilder.toString:()Ljava/lang/String;
      27: areturn

  public io.netty.channel.Channel getNioChannel();
    Code:
       0: aload_0
       1: getfield      #14                 // Field channel:Lio/netty/channel/Channel;
       4: areturn

  private static org.apache.dubbo.remoting.exchange.Response buildErrorResponse(org.apache.dubbo.remoting.exchange.Request, java.lang.Throwable);
    Code:
       0: new           #94                 // class org/apache/dubbo/remoting/exchange/Response
       3: dup
       4: aload_0
       5: invokevirtual #95                 // Method org/apache/dubbo/remoting/exchange/Request.getId:()J
       8: aload_0
       9: invokevirtual #96                 // Method org/apache/dubbo/remoting/exchange/Request.getVersion:()Ljava/lang/String;
      12: invokespecial #97                 // Method org/apache/dubbo/remoting/exchange/Response."<init>":(JLjava/lang/String;)V
      15: astore_2
      16: aload_2
      17: bipush        40
      19: invokevirtual #98                 // Method org/apache/dubbo/remoting/exchange/Response.setStatus:(B)V
      22: aload_2
      23: aload_1
      24: invokestatic  #99                 // Method org/apache/dubbo/common/utils/StringUtils.toString:(Ljava/lang/Throwable;)Ljava/lang/String;
      27: invokevirtual #100                // Method org/apache/dubbo/remoting/exchange/Response.setErrorMessage:(Ljava/lang/String;)V
      30: aload_2
      31: areturn

  private static org.apache.dubbo.remoting.Codec2 getChannelCodec(org.apache.dubbo.common.URL);
    Code:
       0: aload_0
       1: ldc           #102                // String codec
       3: invokevirtual #103                // Method org/apache/dubbo/common/URL.getParameter:(Ljava/lang/String;)Ljava/lang/String;
       6: astore_1
       7: aload_1
       8: invokestatic  #104                // Method org/apache/dubbo/common/utils/StringUtils.isEmpty:(Ljava/lang/String;)Z
      11: ifeq          19
      14: aload_0
      15: invokevirtual #105                // Method org/apache/dubbo/common/URL.getProtocol:()Ljava/lang/String;
      18: astore_1
      19: aload_0
      20: invokevirtual #106                // Method org/apache/dubbo/common/URL.getScopeModel:()Lorg/apache/dubbo/rpc/model/ScopeModel;
      23: invokestatic  #107                // Method org/apache/dubbo/rpc/model/ScopeModelUtil.getFrameworkModel:(Lorg/apache/dubbo/rpc/model/ScopeModel;)Lorg/apache/dubbo/rpc/model/FrameworkModel;
      26: astore_2
      27: aload_2
      28: ldc           #108                // class org/apache/dubbo/remoting/Codec2
      30: invokevirtual #109                // Method org/apache/dubbo/rpc/model/FrameworkModel.getExtensionLoader:(Ljava/lang/Class;)Lorg/apache/dubbo/common/extension/ExtensionLoader;
      33: aload_1
      34: invokevirtual #110                // Method org/apache/dubbo/common/extension/ExtensionLoader.hasExtension:(Ljava/lang/String;)Z
      37: ifeq          54
      40: aload_2
      41: ldc           #108                // class org/apache/dubbo/remoting/Codec2
      43: invokevirtual #109                // Method org/apache/dubbo/rpc/model/FrameworkModel.getExtensionLoader:(Ljava/lang/Class;)Lorg/apache/dubbo/common/extension/ExtensionLoader;
      46: aload_1
      47: invokevirtual #111                // Method org/apache/dubbo/common/extension/ExtensionLoader.getExtension:(Ljava/lang/String;)Ljava/lang/Object;
      50: checkcast     #108                // class org/apache/dubbo/remoting/Codec2
      53: areturn
      54: aload_2
      55: ldc           #112                // class org/apache/dubbo/remoting/Codec
      57: invokevirtual #109                // Method org/apache/dubbo/rpc/model/FrameworkModel.getExtensionLoader:(Ljava/lang/Class;)Lorg/apache/dubbo/common/extension/ExtensionLoader;
      60: aload_1
      61: invokevirtual #110                // Method org/apache/dubbo/common/extension/ExtensionLoader.hasExtension:(Ljava/lang/String;)Z
      64: ifeq          88
      67: new           #113                // class org/apache/dubbo/remoting/transport/codec/CodecAdapter
      70: dup
      71: aload_2
      72: ldc           #112                // class org/apache/dubbo/remoting/Codec
      74: invokevirtual #109                // Method org/apache/dubbo/rpc/model/FrameworkModel.getExtensionLoader:(Ljava/lang/Class;)Lorg/apache/dubbo/common/extension/ExtensionLoader;
      77: aload_1
      78: invokevirtual #111                // Method org/apache/dubbo/common/extension/ExtensionLoader.getExtension:(Ljava/lang/String;)Ljava/lang/Object;
      81: checkcast     #112                // class org/apache/dubbo/remoting/Codec
      84: invokespecial #114                // Method org/apache/dubbo/remoting/transport/codec/CodecAdapter."<init>":(Lorg/apache/dubbo/remoting/Codec;)V
      87: areturn
      88: aload_2
      89: ldc           #108                // class org/apache/dubbo/remoting/Codec2
      91: invokevirtual #109                // Method org/apache/dubbo/rpc/model/FrameworkModel.getExtensionLoader:(Ljava/lang/Class;)Lorg/apache/dubbo/common/extension/ExtensionLoader;
      94: ldc           #115                // String default
      96: invokevirtual #111                // Method org/apache/dubbo/common/extension/ExtensionLoader.getExtension:(Ljava/lang/String;)Ljava/lang/Object;
      99: checkcast     #108                // class org/apache/dubbo/remoting/Codec2
     102: areturn

  public void setCodec(org.apache.dubbo.remoting.Codec2);
    Code:
       0: aload_0
       1: aload_1
       2: putfield      #18                 // Field codec:Lorg/apache/dubbo/remoting/Codec2;
       5: return

  static org.apache.dubbo.remoting.exchange.Response access$000(org.apache.dubbo.remoting.exchange.Request, java.lang.Throwable);
    Code:
       0: aload_0
       1: aload_1
       2: invokestatic  #3                  // Method buildErrorResponse:(Lorg/apache/dubbo/remoting/exchange/Request;Ljava/lang/Throwable;)Lorg/apache/dubbo/remoting/exchange/Response;
       5: areturn

  static {};
    Code:
       0: ldc           #25                 // class org/apache/dubbo/remoting/transport/netty4/NettyChannel
       2: invokestatic  #116                // Method org/apache/dubbo/common/logger/LoggerFactory.getErrorTypeAwareLogger:(Ljava/lang/Class;)Lorg/apache/dubbo/common/logger/ErrorTypeAwareLogger;
       5: putstatic     #72                 // Field logger:Lorg/apache/dubbo/common/logger/ErrorTypeAwareLogger;
       8: new           #5                  // class java/util/concurrent/ConcurrentHashMap
      11: dup
      12: invokespecial #6                  // Method java/util/concurrent/ConcurrentHashMap."<init>":()V
      15: putstatic     #23                 // Field CHANNEL_MAP:Ljava/util/concurrent/ConcurrentMap;
      18: return
}
