Compiled from "NettyPortUnificationTransporter.java"
public class org.apache.dubbo.remoting.transport.netty4.NettyPortUnificationTransporter implements org.apache.dubbo.remoting.api.pu.PortUnificationTransporter {
  public static final java.lang.String NAME;

  public org.apache.dubbo.remoting.transport.netty4.NettyPortUnificationTransporter();
    Code:
       0: aload_0
       1: invokespecial #1                  // Method java/lang/Object."<init>":()V
       4: return

  public org.apache.dubbo.remoting.api.pu.AbstractPortUnificationServer bind(org.apache.dubbo.common.URL, org.apache.dubbo.remoting.ChannelHandler) throws org.apache.dubbo.remoting.RemotingException;
    Code:
       0: new           #2                  // class org/apache/dubbo/remoting/transport/netty4/NettyPortUnificationServer
       3: dup
       4: aload_1
       5: aload_2
       6: invokespecial #3                  // Method org/apache/dubbo/remoting/transport/netty4/NettyPortUnificationServer."<init>":(Lorg/apache/dubbo/common/URL;Lorg/apache/dubbo/remoting/ChannelHandler;)V
       9: areturn

  public org.apache.dubbo.remoting.api.connection.AbstractConnectionClient connect(org.apache.dubbo.common.URL, org.apache.dubbo.remoting.ChannelHandler) throws org.apache.dubbo.remoting.RemotingException;
    Code:
       0: aload_1
       1: invokevirtual #4                  // Method org/apache/dubbo/common/URL.getOrDefaultFrameworkModel:()Lorg/apache/dubbo/rpc/model/FrameworkModel;
       4: ldc           #5                  // class org/apache/dubbo/remoting/api/connection/ConnectionManager
       6: invokevirtual #6                  // Method org/apache/dubbo/rpc/model/FrameworkModel.getExtensionLoader:(Ljava/lang/Class;)Lorg/apache/dubbo/common/extension/ExtensionLoader;
       9: ldc           #8                  // String multiple
      11: invokevirtual #9                  // Method org/apache/dubbo/common/extension/ExtensionLoader.getExtension:(Ljava/lang/String;)Ljava/lang/Object;
      14: checkcast     #5                  // class org/apache/dubbo/remoting/api/connection/ConnectionManager
      17: astore_3
      18: aload_3
      19: aload_1
      20: aload_2
      21: invokeinterface #10,  3           // InterfaceMethod org/apache/dubbo/remoting/api/connection/ConnectionManager.connect:(Lorg/apache/dubbo/common/URL;Lorg/apache/dubbo/remoting/ChannelHandler;)Lorg/apache/dubbo/remoting/api/connection/AbstractConnectionClient;
      26: areturn
}
