Compiled from "NettyBackedChannelBuffer.java"
public class org.apache.dubbo.remoting.transport.netty4.NettyBackedChannelBuffer implements org.apache.dubbo.remoting.buffer.ChannelBuffer {
  private final io.netty.buffer.ByteBuf buffer;

  public org.apache.dubbo.remoting.transport.netty4.NettyBackedChannelBuffer(io.netty.buffer.ByteBuf);
    Code:
       0: aload_0
       1: invokespecial #1                  // Method java/lang/Object."<init>":()V
       4: aload_1
       5: ldc           #2                  // String buffer == null
       7: invokestatic  #3                  // Method org/apache/dubbo/common/utils/Assert.notNull:(Ljava/lang/Object;Ljava/lang/String;)V
      10: aload_0
      11: aload_1
      12: putfield      #4                  // Field buffer:Lio/netty/buffer/ByteBuf;
      15: return

  public int capacity();
    Code:
       0: aload_0
       1: getfield      #4                  // Field buffer:Lio/netty/buffer/ByteBuf;
       4: invokevirtual #5                  // Method io/netty/buffer/ByteBuf.capacity:()I
       7: ireturn

  public org.apache.dubbo.remoting.buffer.ChannelBuffer copy(int, int);
    Code:
       0: new           #6                  // class org/apache/dubbo/remoting/transport/netty4/NettyBackedChannelBuffer
       3: dup
       4: aload_0
       5: getfield      #4                  // Field buffer:Lio/netty/buffer/ByteBuf;
       8: iload_1
       9: iload_2
      10: invokevirtual #7                  // Method io/netty/buffer/ByteBuf.copy:(II)Lio/netty/buffer/ByteBuf;
      13: invokespecial #8                  // Method "<init>":(Lio/netty/buffer/ByteBuf;)V
      16: areturn

  public org.apache.dubbo.remoting.buffer.ChannelBufferFactory factory();
    Code:
       0: aconst_null
       1: areturn

  public byte getByte(int);
    Code:
       0: aload_0
       1: getfield      #4                  // Field buffer:Lio/netty/buffer/ByteBuf;
       4: iload_1
       5: invokevirtual #9                  // Method io/netty/buffer/ByteBuf.getByte:(I)B
       8: ireturn

  public void getBytes(int, byte[], int, int);
    Code:
       0: aload_0
       1: getfield      #4                  // Field buffer:Lio/netty/buffer/ByteBuf;
       4: iload_1
       5: aload_2
       6: iload_3
       7: iload         4
       9: invokevirtual #10                 // Method io/netty/buffer/ByteBuf.getBytes:(I[BII)Lio/netty/buffer/ByteBuf;
      12: pop
      13: return

  public void getBytes(int, java.nio.ByteBuffer);
    Code:
       0: aload_0
       1: getfield      #4                  // Field buffer:Lio/netty/buffer/ByteBuf;
       4: iload_1
       5: aload_2
       6: invokevirtual #11                 // Method io/netty/buffer/ByteBuf.getBytes:(ILjava/nio/ByteBuffer;)Lio/netty/buffer/ByteBuf;
       9: pop
      10: return

  public void getBytes(int, org.apache.dubbo.remoting.buffer.ChannelBuffer, int, int);
    Code:
       0: iload         4
       2: newarray       byte
       4: astore        5
       6: aload_0
       7: getfield      #4                  // Field buffer:Lio/netty/buffer/ByteBuf;
      10: iload_1
      11: aload         5
      13: iconst_0
      14: iload         4
      16: invokevirtual #10                 // Method io/netty/buffer/ByteBuf.getBytes:(I[BII)Lio/netty/buffer/ByteBuf;
      19: pop
      20: aload_2
      21: iload_3
      22: aload         5
      24: iconst_0
      25: iload         4
      27: invokeinterface #12,  5           // InterfaceMethod org/apache/dubbo/remoting/buffer/ChannelBuffer.setBytes:(I[BII)V
      32: return

  public void getBytes(int, java.io.OutputStream, int) throws java.io.IOException;
    Code:
       0: aload_0
       1: getfield      #4                  // Field buffer:Lio/netty/buffer/ByteBuf;
       4: iload_1
       5: aload_2
       6: iload_3
       7: invokevirtual #13                 // Method io/netty/buffer/ByteBuf.getBytes:(ILjava/io/OutputStream;I)Lio/netty/buffer/ByteBuf;
      10: pop
      11: return

  public boolean isDirect();
    Code:
       0: aload_0
       1: getfield      #4                  // Field buffer:Lio/netty/buffer/ByteBuf;
       4: invokevirtual #14                 // Method io/netty/buffer/ByteBuf.isDirect:()Z
       7: ireturn

  public void setByte(int, int);
    Code:
       0: aload_0
       1: getfield      #4                  // Field buffer:Lio/netty/buffer/ByteBuf;
       4: iload_1
       5: iload_2
       6: invokevirtual #15                 // Method io/netty/buffer/ByteBuf.setByte:(II)Lio/netty/buffer/ByteBuf;
       9: pop
      10: return

  public void setBytes(int, byte[], int, int);
    Code:
       0: aload_0
       1: getfield      #4                  // Field buffer:Lio/netty/buffer/ByteBuf;
       4: iload_1
       5: aload_2
       6: iload_3
       7: iload         4
       9: invokevirtual #16                 // Method io/netty/buffer/ByteBuf.setBytes:(I[BII)Lio/netty/buffer/ByteBuf;
      12: pop
      13: return

  public void setBytes(int, java.nio.ByteBuffer);
    Code:
       0: aload_0
       1: getfield      #4                  // Field buffer:Lio/netty/buffer/ByteBuf;
       4: iload_1
       5: aload_2
       6: invokevirtual #17                 // Method io/netty/buffer/ByteBuf.setBytes:(ILjava/nio/ByteBuffer;)Lio/netty/buffer/ByteBuf;
       9: pop
      10: return

  public void setBytes(int, org.apache.dubbo.remoting.buffer.ChannelBuffer, int, int);
    Code:
       0: iload         4
       2: aload_2
       3: invokeinterface #18,  1           // InterfaceMethod org/apache/dubbo/remoting/buffer/ChannelBuffer.readableBytes:()I
       8: if_icmple     19
      11: new           #19                 // class java/lang/IndexOutOfBoundsException
      14: dup
      15: invokespecial #20                 // Method java/lang/IndexOutOfBoundsException."<init>":()V
      18: athrow
      19: iload         4
      21: newarray       byte
      23: astore        5
      25: aload_2
      26: iload_3
      27: aload         5
      29: iconst_0
      30: iload         4
      32: invokeinterface #21,  5           // InterfaceMethod org/apache/dubbo/remoting/buffer/ChannelBuffer.getBytes:(I[BII)V
      37: aload_0
      38: iload_1
      39: aload         5
      41: iconst_0
      42: iload         4
      44: invokevirtual #22                 // Method setBytes:(I[BII)V
      47: return

  public int setBytes(int, java.io.InputStream, int) throws java.io.IOException;
    Code:
       0: aload_0
       1: getfield      #4                  // Field buffer:Lio/netty/buffer/ByteBuf;
       4: iload_1
       5: aload_2
       6: iload_3
       7: invokevirtual #23                 // Method io/netty/buffer/ByteBuf.setBytes:(ILjava/io/InputStream;I)I
      10: ireturn

  public java.nio.ByteBuffer toByteBuffer(int, int);
    Code:
       0: aload_0
       1: getfield      #4                  // Field buffer:Lio/netty/buffer/ByteBuf;
       4: iload_1
       5: iload_2
       6: invokevirtual #24                 // Method io/netty/buffer/ByteBuf.nioBuffer:(II)Ljava/nio/ByteBuffer;
       9: areturn

  public byte[] array();
    Code:
       0: aload_0
       1: getfield      #4                  // Field buffer:Lio/netty/buffer/ByteBuf;
       4: invokevirtual #25                 // Method io/netty/buffer/ByteBuf.array:()[B
       7: areturn

  public boolean hasArray();
    Code:
       0: aload_0
       1: getfield      #4                  // Field buffer:Lio/netty/buffer/ByteBuf;
       4: invokevirtual #26                 // Method io/netty/buffer/ByteBuf.hasArray:()Z
       7: ireturn

  public int arrayOffset();
    Code:
       0: aload_0
       1: getfield      #4                  // Field buffer:Lio/netty/buffer/ByteBuf;
       4: invokevirtual #27                 // Method io/netty/buffer/ByteBuf.arrayOffset:()I
       7: ireturn

  public void clear();
    Code:
       0: aload_0
       1: getfield      #4                  // Field buffer:Lio/netty/buffer/ByteBuf;
       4: invokevirtual #28                 // Method io/netty/buffer/ByteBuf.clear:()Lio/netty/buffer/ByteBuf;
       7: pop
       8: return

  public org.apache.dubbo.remoting.buffer.ChannelBuffer copy();
    Code:
       0: new           #6                  // class org/apache/dubbo/remoting/transport/netty4/NettyBackedChannelBuffer
       3: dup
       4: aload_0
       5: getfield      #4                  // Field buffer:Lio/netty/buffer/ByteBuf;
       8: invokevirtual #29                 // Method io/netty/buffer/ByteBuf.copy:()Lio/netty/buffer/ByteBuf;
      11: invokespecial #8                  // Method "<init>":(Lio/netty/buffer/ByteBuf;)V
      14: areturn

  public void discardReadBytes();
    Code:
       0: aload_0
       1: getfield      #4                  // Field buffer:Lio/netty/buffer/ByteBuf;
       4: invokevirtual #30                 // Method io/netty/buffer/ByteBuf.discardReadBytes:()Lio/netty/buffer/ByteBuf;
       7: pop
       8: return

  public void ensureWritableBytes(int);
    Code:
       0: aload_0
       1: getfield      #4                  // Field buffer:Lio/netty/buffer/ByteBuf;
       4: iload_1
       5: invokevirtual #31                 // Method io/netty/buffer/ByteBuf.ensureWritable:(I)Lio/netty/buffer/ByteBuf;
       8: pop
       9: return

  public void getBytes(int, byte[]);
    Code:
       0: aload_0
       1: getfield      #4                  // Field buffer:Lio/netty/buffer/ByteBuf;
       4: iload_1
       5: aload_2
       6: invokevirtual #32                 // Method io/netty/buffer/ByteBuf.getBytes:(I[B)Lio/netty/buffer/ByteBuf;
       9: pop
      10: return

  public void getBytes(int, org.apache.dubbo.remoting.buffer.ChannelBuffer);
    Code:
       0: aload_0
       1: iload_1
       2: aload_2
       3: aload_2
       4: invokeinterface #33,  1           // InterfaceMethod org/apache/dubbo/remoting/buffer/ChannelBuffer.writableBytes:()I
       9: invokevirtual #34                 // Method getBytes:(ILorg/apache/dubbo/remoting/buffer/ChannelBuffer;I)V
      12: return

  public void getBytes(int, org.apache.dubbo.remoting.buffer.ChannelBuffer, int);
    Code:
       0: iload_3
       1: aload_2
       2: invokeinterface #33,  1           // InterfaceMethod org/apache/dubbo/remoting/buffer/ChannelBuffer.writableBytes:()I
       7: if_icmple     18
      10: new           #19                 // class java/lang/IndexOutOfBoundsException
      13: dup
      14: invokespecial #20                 // Method java/lang/IndexOutOfBoundsException."<init>":()V
      17: athrow
      18: aload_0
      19: iload_1
      20: aload_2
      21: aload_2
      22: invokeinterface #35,  1           // InterfaceMethod org/apache/dubbo/remoting/buffer/ChannelBuffer.writerIndex:()I
      27: iload_3
      28: invokevirtual #36                 // Method getBytes:(ILorg/apache/dubbo/remoting/buffer/ChannelBuffer;II)V
      31: aload_2
      32: aload_2
      33: invokeinterface #35,  1           // InterfaceMethod org/apache/dubbo/remoting/buffer/ChannelBuffer.writerIndex:()I
      38: iload_3
      39: iadd
      40: invokeinterface #37,  2           // InterfaceMethod org/apache/dubbo/remoting/buffer/ChannelBuffer.writerIndex:(I)V
      45: return

  public void markReaderIndex();
    Code:
       0: aload_0
       1: getfield      #4                  // Field buffer:Lio/netty/buffer/ByteBuf;
       4: invokevirtual #38                 // Method io/netty/buffer/ByteBuf.markReaderIndex:()Lio/netty/buffer/ByteBuf;
       7: pop
       8: return

  public void markWriterIndex();
    Code:
       0: aload_0
       1: getfield      #4                  // Field buffer:Lio/netty/buffer/ByteBuf;
       4: invokevirtual #39                 // Method io/netty/buffer/ByteBuf.markWriterIndex:()Lio/netty/buffer/ByteBuf;
       7: pop
       8: return

  public boolean readable();
    Code:
       0: aload_0
       1: getfield      #4                  // Field buffer:Lio/netty/buffer/ByteBuf;
       4: invokevirtual #40                 // Method io/netty/buffer/ByteBuf.isReadable:()Z
       7: ireturn

  public int readableBytes();
    Code:
       0: aload_0
       1: getfield      #4                  // Field buffer:Lio/netty/buffer/ByteBuf;
       4: invokevirtual #41                 // Method io/netty/buffer/ByteBuf.readableBytes:()I
       7: ireturn

  public byte readByte();
    Code:
       0: aload_0
       1: getfield      #4                  // Field buffer:Lio/netty/buffer/ByteBuf;
       4: invokevirtual #42                 // Method io/netty/buffer/ByteBuf.readByte:()B
       7: ireturn

  public void readBytes(byte[]);
    Code:
       0: aload_0
       1: getfield      #4                  // Field buffer:Lio/netty/buffer/ByteBuf;
       4: aload_1
       5: invokevirtual #43                 // Method io/netty/buffer/ByteBuf.readBytes:([B)Lio/netty/buffer/ByteBuf;
       8: pop
       9: return

  public void readBytes(byte[], int, int);
    Code:
       0: aload_0
       1: getfield      #4                  // Field buffer:Lio/netty/buffer/ByteBuf;
       4: aload_1
       5: iload_2
       6: iload_3
       7: invokevirtual #44                 // Method io/netty/buffer/ByteBuf.readBytes:([BII)Lio/netty/buffer/ByteBuf;
      10: pop
      11: return

  public void readBytes(java.nio.ByteBuffer);
    Code:
       0: aload_0
       1: getfield      #4                  // Field buffer:Lio/netty/buffer/ByteBuf;
       4: aload_1
       5: invokevirtual #45                 // Method io/netty/buffer/ByteBuf.readBytes:(Ljava/nio/ByteBuffer;)Lio/netty/buffer/ByteBuf;
       8: pop
       9: return

  public void readBytes(org.apache.dubbo.remoting.buffer.ChannelBuffer);
    Code:
       0: aload_0
       1: aload_1
       2: aload_1
       3: invokeinterface #33,  1           // InterfaceMethod org/apache/dubbo/remoting/buffer/ChannelBuffer.writableBytes:()I
       8: invokevirtual #46                 // Method readBytes:(Lorg/apache/dubbo/remoting/buffer/ChannelBuffer;I)V
      11: return

  public void readBytes(org.apache.dubbo.remoting.buffer.ChannelBuffer, int);
    Code:
       0: iload_2
       1: aload_1
       2: invokeinterface #33,  1           // InterfaceMethod org/apache/dubbo/remoting/buffer/ChannelBuffer.writableBytes:()I
       7: if_icmple     18
      10: new           #19                 // class java/lang/IndexOutOfBoundsException
      13: dup
      14: invokespecial #20                 // Method java/lang/IndexOutOfBoundsException."<init>":()V
      17: athrow
      18: aload_0
      19: aload_1
      20: aload_1
      21: invokeinterface #35,  1           // InterfaceMethod org/apache/dubbo/remoting/buffer/ChannelBuffer.writerIndex:()I
      26: iload_2
      27: invokevirtual #47                 // Method readBytes:(Lorg/apache/dubbo/remoting/buffer/ChannelBuffer;II)V
      30: aload_1
      31: aload_1
      32: invokeinterface #35,  1           // InterfaceMethod org/apache/dubbo/remoting/buffer/ChannelBuffer.writerIndex:()I
      37: iload_2
      38: iadd
      39: invokeinterface #37,  2           // InterfaceMethod org/apache/dubbo/remoting/buffer/ChannelBuffer.writerIndex:(I)V
      44: return

  public void readBytes(org.apache.dubbo.remoting.buffer.ChannelBuffer, int, int);
    Code:
       0: aload_0
       1: invokevirtual #48                 // Method readableBytes:()I
       4: iload_3
       5: if_icmpge     16
       8: new           #19                 // class java/lang/IndexOutOfBoundsException
      11: dup
      12: invokespecial #20                 // Method java/lang/IndexOutOfBoundsException."<init>":()V
      15: athrow
      16: iload_3
      17: newarray       byte
      19: astore        4
      21: aload_0
      22: getfield      #4                  // Field buffer:Lio/netty/buffer/ByteBuf;
      25: aload         4
      27: iconst_0
      28: iload_3
      29: invokevirtual #44                 // Method io/netty/buffer/ByteBuf.readBytes:([BII)Lio/netty/buffer/ByteBuf;
      32: pop
      33: aload_1
      34: iload_2
      35: aload         4
      37: iconst_0
      38: iload_3
      39: invokeinterface #12,  5           // InterfaceMethod org/apache/dubbo/remoting/buffer/ChannelBuffer.setBytes:(I[BII)V
      44: return

  public org.apache.dubbo.remoting.buffer.ChannelBuffer readBytes(int);
    Code:
       0: new           #6                  // class org/apache/dubbo/remoting/transport/netty4/NettyBackedChannelBuffer
       3: dup
       4: aload_0
       5: getfield      #4                  // Field buffer:Lio/netty/buffer/ByteBuf;
       8: iload_1
       9: invokevirtual #49                 // Method io/netty/buffer/ByteBuf.readBytes:(I)Lio/netty/buffer/ByteBuf;
      12: invokespecial #8                  // Method "<init>":(Lio/netty/buffer/ByteBuf;)V
      15: areturn

  public void resetReaderIndex();
    Code:
       0: aload_0
       1: getfield      #4                  // Field buffer:Lio/netty/buffer/ByteBuf;
       4: invokevirtual #50                 // Method io/netty/buffer/ByteBuf.resetReaderIndex:()Lio/netty/buffer/ByteBuf;
       7: pop
       8: return

  public void resetWriterIndex();
    Code:
       0: aload_0
       1: getfield      #4                  // Field buffer:Lio/netty/buffer/ByteBuf;
       4: invokevirtual #51                 // Method io/netty/buffer/ByteBuf.resetWriterIndex:()Lio/netty/buffer/ByteBuf;
       7: pop
       8: return

  public int readerIndex();
    Code:
       0: aload_0
       1: getfield      #4                  // Field buffer:Lio/netty/buffer/ByteBuf;
       4: invokevirtual #52                 // Method io/netty/buffer/ByteBuf.readerIndex:()I
       7: ireturn

  public void readerIndex(int);
    Code:
       0: aload_0
       1: getfield      #4                  // Field buffer:Lio/netty/buffer/ByteBuf;
       4: iload_1
       5: invokevirtual #53                 // Method io/netty/buffer/ByteBuf.readerIndex:(I)Lio/netty/buffer/ByteBuf;
       8: pop
       9: return

  public void readBytes(java.io.OutputStream, int) throws java.io.IOException;
    Code:
       0: aload_0
       1: getfield      #4                  // Field buffer:Lio/netty/buffer/ByteBuf;
       4: aload_1
       5: iload_2
       6: invokevirtual #54                 // Method io/netty/buffer/ByteBuf.readBytes:(Ljava/io/OutputStream;I)Lio/netty/buffer/ByteBuf;
       9: pop
      10: return

  public void setBytes(int, byte[]);
    Code:
       0: aload_0
       1: getfield      #4                  // Field buffer:Lio/netty/buffer/ByteBuf;
       4: iload_1
       5: aload_2
       6: invokevirtual #55                 // Method io/netty/buffer/ByteBuf.setBytes:(I[B)Lio/netty/buffer/ByteBuf;
       9: pop
      10: return

  public void setBytes(int, org.apache.dubbo.remoting.buffer.ChannelBuffer);
    Code:
       0: aload_0
       1: iload_1
       2: aload_2
       3: aload_2
       4: invokeinterface #18,  1           // InterfaceMethod org/apache/dubbo/remoting/buffer/ChannelBuffer.readableBytes:()I
       9: invokevirtual #56                 // Method setBytes:(ILorg/apache/dubbo/remoting/buffer/ChannelBuffer;I)V
      12: return

  public void setBytes(int, org.apache.dubbo.remoting.buffer.ChannelBuffer, int);
    Code:
       0: iload_3
       1: aload_2
       2: invokeinterface #18,  1           // InterfaceMethod org/apache/dubbo/remoting/buffer/ChannelBuffer.readableBytes:()I
       7: if_icmple     18
      10: new           #19                 // class java/lang/IndexOutOfBoundsException
      13: dup
      14: invokespecial #20                 // Method java/lang/IndexOutOfBoundsException."<init>":()V
      17: athrow
      18: aload_0
      19: iload_1
      20: aload_2
      21: aload_2
      22: invokeinterface #57,  1           // InterfaceMethod org/apache/dubbo/remoting/buffer/ChannelBuffer.readerIndex:()I
      27: iload_3
      28: invokevirtual #58                 // Method setBytes:(ILorg/apache/dubbo/remoting/buffer/ChannelBuffer;II)V
      31: aload_2
      32: aload_2
      33: invokeinterface #57,  1           // InterfaceMethod org/apache/dubbo/remoting/buffer/ChannelBuffer.readerIndex:()I
      38: iload_3
      39: iadd
      40: invokeinterface #59,  2           // InterfaceMethod org/apache/dubbo/remoting/buffer/ChannelBuffer.readerIndex:(I)V
      45: return

  public void setIndex(int, int);
    Code:
       0: aload_0
       1: getfield      #4                  // Field buffer:Lio/netty/buffer/ByteBuf;
       4: iload_1
       5: iload_2
       6: invokevirtual #60                 // Method io/netty/buffer/ByteBuf.setIndex:(II)Lio/netty/buffer/ByteBuf;
       9: pop
      10: return

  public void skipBytes(int);
    Code:
       0: aload_0
       1: getfield      #4                  // Field buffer:Lio/netty/buffer/ByteBuf;
       4: iload_1
       5: invokevirtual #61                 // Method io/netty/buffer/ByteBuf.skipBytes:(I)Lio/netty/buffer/ByteBuf;
       8: pop
       9: return

  public java.nio.ByteBuffer toByteBuffer();
    Code:
       0: aload_0
       1: getfield      #4                  // Field buffer:Lio/netty/buffer/ByteBuf;
       4: invokevirtual #62                 // Method io/netty/buffer/ByteBuf.nioBuffer:()Ljava/nio/ByteBuffer;
       7: areturn

  public boolean writable();
    Code:
       0: aload_0
       1: getfield      #4                  // Field buffer:Lio/netty/buffer/ByteBuf;
       4: invokevirtual #63                 // Method io/netty/buffer/ByteBuf.isWritable:()Z
       7: ireturn

  public int writableBytes();
    Code:
       0: aload_0
       1: getfield      #4                  // Field buffer:Lio/netty/buffer/ByteBuf;
       4: invokevirtual #64                 // Method io/netty/buffer/ByteBuf.writableBytes:()I
       7: ireturn

  public void writeByte(int);
    Code:
       0: aload_0
       1: getfield      #4                  // Field buffer:Lio/netty/buffer/ByteBuf;
       4: iload_1
       5: invokevirtual #65                 // Method io/netty/buffer/ByteBuf.writeByte:(I)Lio/netty/buffer/ByteBuf;
       8: pop
       9: return

  public void writeBytes(byte[]);
    Code:
       0: aload_0
       1: getfield      #4                  // Field buffer:Lio/netty/buffer/ByteBuf;
       4: aload_1
       5: invokevirtual #66                 // Method io/netty/buffer/ByteBuf.writeBytes:([B)Lio/netty/buffer/ByteBuf;
       8: pop
       9: return

  public void writeBytes(byte[], int, int);
    Code:
       0: aload_0
       1: getfield      #4                  // Field buffer:Lio/netty/buffer/ByteBuf;
       4: aload_1
       5: iload_2
       6: iload_3
       7: invokevirtual #67                 // Method io/netty/buffer/ByteBuf.writeBytes:([BII)Lio/netty/buffer/ByteBuf;
      10: pop
      11: return

  public void writeBytes(java.nio.ByteBuffer);
    Code:
       0: aload_0
       1: getfield      #4                  // Field buffer:Lio/netty/buffer/ByteBuf;
       4: aload_1
       5: invokevirtual #68                 // Method io/netty/buffer/ByteBuf.writeBytes:(Ljava/nio/ByteBuffer;)Lio/netty/buffer/ByteBuf;
       8: pop
       9: return

  public void writeBytes(org.apache.dubbo.remoting.buffer.ChannelBuffer);
    Code:
       0: aload_0
       1: aload_1
       2: aload_1
       3: invokeinterface #18,  1           // InterfaceMethod org/apache/dubbo/remoting/buffer/ChannelBuffer.readableBytes:()I
       8: invokevirtual #69                 // Method writeBytes:(Lorg/apache/dubbo/remoting/buffer/ChannelBuffer;I)V
      11: return

  public void writeBytes(org.apache.dubbo.remoting.buffer.ChannelBuffer, int);
    Code:
       0: iload_2
       1: aload_1
       2: invokeinterface #18,  1           // InterfaceMethod org/apache/dubbo/remoting/buffer/ChannelBuffer.readableBytes:()I
       7: if_icmple     18
      10: new           #19                 // class java/lang/IndexOutOfBoundsException
      13: dup
      14: invokespecial #20                 // Method java/lang/IndexOutOfBoundsException."<init>":()V
      17: athrow
      18: aload_0
      19: aload_1
      20: aload_1
      21: invokeinterface #57,  1           // InterfaceMethod org/apache/dubbo/remoting/buffer/ChannelBuffer.readerIndex:()I
      26: iload_2
      27: invokevirtual #70                 // Method writeBytes:(Lorg/apache/dubbo/remoting/buffer/ChannelBuffer;II)V
      30: aload_1
      31: aload_1
      32: invokeinterface #57,  1           // InterfaceMethod org/apache/dubbo/remoting/buffer/ChannelBuffer.readerIndex:()I
      37: iload_2
      38: iadd
      39: invokeinterface #59,  2           // InterfaceMethod org/apache/dubbo/remoting/buffer/ChannelBuffer.readerIndex:(I)V
      44: return

  public void writeBytes(org.apache.dubbo.remoting.buffer.ChannelBuffer, int, int);
    Code:
       0: iload_3
       1: newarray       byte
       3: astore        4
       5: aload_1
       6: iload_2
       7: aload         4
       9: iconst_0
      10: iload_3
      11: invokeinterface #21,  5           // InterfaceMethod org/apache/dubbo/remoting/buffer/ChannelBuffer.getBytes:(I[BII)V
      16: aload_0
      17: aload         4
      19: iconst_0
      20: iload_3
      21: invokevirtual #71                 // Method writeBytes:([BII)V
      24: return

  public int writeBytes(java.io.InputStream, int) throws java.io.IOException;
    Code:
       0: aload_0
       1: getfield      #4                  // Field buffer:Lio/netty/buffer/ByteBuf;
       4: aload_1
       5: iload_2
       6: invokevirtual #72                 // Method io/netty/buffer/ByteBuf.writeBytes:(Ljava/io/InputStream;I)I
       9: ireturn

  public int writerIndex();
    Code:
       0: aload_0
       1: getfield      #4                  // Field buffer:Lio/netty/buffer/ByteBuf;
       4: invokevirtual #73                 // Method io/netty/buffer/ByteBuf.writerIndex:()I
       7: ireturn

  public void writerIndex(int);
    Code:
       0: aload_0
       1: getfield      #4                  // Field buffer:Lio/netty/buffer/ByteBuf;
       4: iload_1
       5: invokevirtual #31                 // Method io/netty/buffer/ByteBuf.ensureWritable:(I)Lio/netty/buffer/ByteBuf;
       8: pop
       9: aload_0
      10: getfield      #4                  // Field buffer:Lio/netty/buffer/ByteBuf;
      13: iload_1
      14: invokevirtual #74                 // Method io/netty/buffer/ByteBuf.writerIndex:(I)Lio/netty/buffer/ByteBuf;
      17: pop
      18: return

  public int compareTo(org.apache.dubbo.remoting.buffer.ChannelBuffer);
    Code:
       0: aload_0
       1: aload_1
       2: invokestatic  #75                 // Method org/apache/dubbo/remoting/buffer/ChannelBuffers.compare:(Lorg/apache/dubbo/remoting/buffer/ChannelBuffer;Lorg/apache/dubbo/remoting/buffer/ChannelBuffer;)I
       5: ireturn

  public void release();
    Code:
       0: aload_0
       1: getfield      #4                  // Field buffer:Lio/netty/buffer/ByteBuf;
       4: invokestatic  #76                 // Method io/netty/util/ReferenceCountUtil.safeRelease:(Ljava/lang/Object;)V
       7: return

  public int compareTo(java.lang.Object);
    Code:
       0: aload_0
       1: aload_1
       2: checkcast     #77                 // class org/apache/dubbo/remoting/buffer/ChannelBuffer
       5: invokevirtual #78                 // Method compareTo:(Lorg/apache/dubbo/remoting/buffer/ChannelBuffer;)I
       8: ireturn
}
