Compiled from "NettyServer.java"
class org.apache.dubbo.remoting.transport.netty4.NettyServer$1 extends io.netty.channel.ChannelInitializer<io.netty.channel.socket.SocketChannel> {
  final org.apache.dubbo.remoting.transport.netty4.NettyServerHandler val$nettyServerHandler;

  final org.apache.dubbo.remoting.transport.netty4.NettyServer this$0;

  org.apache.dubbo.remoting.transport.netty4.NettyServer$1(org.apache.dubbo.remoting.transport.netty4.NettyServer, org.apache.dubbo.remoting.transport.netty4.NettyServerHandler);
    Code:
       0: aload_0
       1: aload_1
       2: putfield      #1                  // Field this$0:Lorg/apache/dubbo/remoting/transport/netty4/NettyServer;
       5: aload_0
       6: aload_2
       7: putfield      #2                  // Field val$nettyServerHandler:Lorg/apache/dubbo/remoting/transport/netty4/NettyServerHandler;
      10: aload_0
      11: invokespecial #3                  // Method io/netty/channel/ChannelInitializer."<init>":()V
      14: return

  protected void initChannel(io.netty.channel.socket.SocketChannel) throws java.lang.Exception;
    Code:
       0: aload_0
       1: getfield      #1                  // Field this$0:Lorg/apache/dubbo/remoting/transport/netty4/NettyServer;
       4: invokevirtual #4                  // Method org/apache/dubbo/remoting/transport/netty4/NettyServer.getUrl:()Lorg/apache/dubbo/common/URL;
       7: invokestatic  #5                  // Method org/apache/dubbo/remoting/utils/UrlUtils.getIdleTimeout:(Lorg/apache/dubbo/common/URL;)I
      10: istore_2
      11: new           #6                  // class org/apache/dubbo/remoting/transport/netty4/NettyCodecAdapter
      14: dup
      15: aload_0
      16: getfield      #1                  // Field this$0:Lorg/apache/dubbo/remoting/transport/netty4/NettyServer;
      19: invokestatic  #7                  // Method org/apache/dubbo/remoting/transport/netty4/NettyServer.access$000:(Lorg/apache/dubbo/remoting/transport/netty4/NettyServer;)Lorg/apache/dubbo/remoting/Codec2;
      22: aload_0
      23: getfield      #1                  // Field this$0:Lorg/apache/dubbo/remoting/transport/netty4/NettyServer;
      26: invokevirtual #4                  // Method org/apache/dubbo/remoting/transport/netty4/NettyServer.getUrl:()Lorg/apache/dubbo/common/URL;
      29: aload_0
      30: getfield      #1                  // Field this$0:Lorg/apache/dubbo/remoting/transport/netty4/NettyServer;
      33: invokespecial #8                  // Method org/apache/dubbo/remoting/transport/netty4/NettyCodecAdapter."<init>":(Lorg/apache/dubbo/remoting/Codec2;Lorg/apache/dubbo/common/URL;Lorg/apache/dubbo/remoting/ChannelHandler;)V
      36: astore_3
      37: aload_1
      38: invokeinterface #9,  1            // InterfaceMethod io/netty/channel/socket/SocketChannel.pipeline:()Lio/netty/channel/ChannelPipeline;
      43: ldc           #10                 // String negotiation
      45: new           #11                 // class org/apache/dubbo/remoting/transport/netty4/ssl/SslServerTlsHandler
      48: dup
      49: aload_0
      50: getfield      #1                  // Field this$0:Lorg/apache/dubbo/remoting/transport/netty4/NettyServer;
      53: invokevirtual #4                  // Method org/apache/dubbo/remoting/transport/netty4/NettyServer.getUrl:()Lorg/apache/dubbo/common/URL;
      56: invokespecial #12                 // Method org/apache/dubbo/remoting/transport/netty4/ssl/SslServerTlsHandler."<init>":(Lorg/apache/dubbo/common/URL;)V
      59: invokeinterface #13,  3           // InterfaceMethod io/netty/channel/ChannelPipeline.addLast:(Ljava/lang/String;Lio/netty/channel/ChannelHandler;)Lio/netty/channel/ChannelPipeline;
      64: pop
      65: aload_1
      66: invokeinterface #9,  1            // InterfaceMethod io/netty/channel/socket/SocketChannel.pipeline:()Lio/netty/channel/ChannelPipeline;
      71: ldc           #14                 // String decoder
      73: aload_3
      74: invokevirtual #15                 // Method org/apache/dubbo/remoting/transport/netty4/NettyCodecAdapter.getDecoder:()Lio/netty/channel/ChannelHandler;
      77: invokeinterface #13,  3           // InterfaceMethod io/netty/channel/ChannelPipeline.addLast:(Ljava/lang/String;Lio/netty/channel/ChannelHandler;)Lio/netty/channel/ChannelPipeline;
      82: ldc           #16                 // String encoder
      84: aload_3
      85: invokevirtual #17                 // Method org/apache/dubbo/remoting/transport/netty4/NettyCodecAdapter.getEncoder:()Lio/netty/channel/ChannelHandler;
      88: invokeinterface #13,  3           // InterfaceMethod io/netty/channel/ChannelPipeline.addLast:(Ljava/lang/String;Lio/netty/channel/ChannelHandler;)Lio/netty/channel/ChannelPipeline;
      93: ldc           #18                 // String server-idle-handler
      95: new           #19                 // class io/netty/handler/timeout/IdleStateHandler
      98: dup
      99: lconst_0
     100: lconst_0
     101: iload_2
     102: i2l
     103: getstatic     #20                 // Field java/util/concurrent/TimeUnit.MILLISECONDS:Ljava/util/concurrent/TimeUnit;
     106: invokespecial #21                 // Method io/netty/handler/timeout/IdleStateHandler."<init>":(JJJLjava/util/concurrent/TimeUnit;)V
     109: invokeinterface #13,  3           // InterfaceMethod io/netty/channel/ChannelPipeline.addLast:(Ljava/lang/String;Lio/netty/channel/ChannelHandler;)Lio/netty/channel/ChannelPipeline;
     114: ldc           #22                 // String handler
     116: aload_0
     117: getfield      #2                  // Field val$nettyServerHandler:Lorg/apache/dubbo/remoting/transport/netty4/NettyServerHandler;
     120: invokeinterface #13,  3           // InterfaceMethod io/netty/channel/ChannelPipeline.addLast:(Ljava/lang/String;Lio/netty/channel/ChannelHandler;)Lio/netty/channel/ChannelPipeline;
     125: pop
     126: return

  protected void initChannel(io.netty.channel.Channel) throws java.lang.Exception;
    Code:
       0: aload_0
       1: aload_1
       2: checkcast     #23                 // class io/netty/channel/socket/SocketChannel
       5: invokevirtual #24                 // Method initChannel:(Lio/netty/channel/socket/SocketChannel;)V
       8: return
}
