Compiled from "NettyCodecAdapter.java"
class org.apache.dubbo.remoting.transport.netty4.NettyCodecAdapter$InternalDecoder extends io.netty.handler.codec.ByteToMessageDecoder {
  final org.apache.dubbo.remoting.transport.netty4.NettyCodecAdapter this$0;

  private org.apache.dubbo.remoting.transport.netty4.NettyCodecAdapter$InternalDecoder(org.apache.dubbo.remoting.transport.netty4.NettyCodecAdapter);
    Code:
       0: aload_0
       1: aload_1
       2: putfield      #2                  // Field this$0:Lorg/apache/dubbo/remoting/transport/netty4/NettyCodecAdapter;
       5: aload_0
       6: invokespecial #3                  // Method io/netty/handler/codec/ByteToMessageDecoder."<init>":()V
       9: return

  protected void decode(io.netty.channel.ChannelHandlerContext, io.netty.buffer.ByteBuf, java.util.List<java.lang.Object>) throws java.lang.Exception;
    Code:
       0: new           #4                  // class org/apache/dubbo/remoting/transport/netty4/NettyBackedChannelBuffer
       3: dup
       4: aload_2
       5: invokespecial #5                  // Method org/apache/dubbo/remoting/transport/netty4/NettyBackedChannelBuffer."<init>":(Lio/netty/buffer/ByteBuf;)V
       8: astore        4
      10: aload_1
      11: invokeinterface #6,  1            // InterfaceMethod io/netty/channel/ChannelHandlerContext.channel:()Lio/netty/channel/Channel;
      16: aload_0
      17: getfield      #2                  // Field this$0:Lorg/apache/dubbo/remoting/transport/netty4/NettyCodecAdapter;
      20: invokestatic  #7                  // Method org/apache/dubbo/remoting/transport/netty4/NettyCodecAdapter.access$200:(Lorg/apache/dubbo/remoting/transport/netty4/NettyCodecAdapter;)Lorg/apache/dubbo/common/URL;
      23: aload_0
      24: getfield      #2                  // Field this$0:Lorg/apache/dubbo/remoting/transport/netty4/NettyCodecAdapter;
      27: invokestatic  #8                  // Method org/apache/dubbo/remoting/transport/netty4/NettyCodecAdapter.access$300:(Lorg/apache/dubbo/remoting/transport/netty4/NettyCodecAdapter;)Lorg/apache/dubbo/remoting/ChannelHandler;
      30: invokestatic  #9                  // Method org/apache/dubbo/remoting/transport/netty4/NettyChannel.getOrAddChannel:(Lio/netty/channel/Channel;Lorg/apache/dubbo/common/URL;Lorg/apache/dubbo/remoting/ChannelHandler;)Lorg/apache/dubbo/remoting/transport/netty4/NettyChannel;
      33: astore        5
      35: aload         4
      37: invokeinterface #10,  1           // InterfaceMethod org/apache/dubbo/remoting/buffer/ChannelBuffer.readerIndex:()I
      42: istore        6
      44: aload_0
      45: getfield      #2                  // Field this$0:Lorg/apache/dubbo/remoting/transport/netty4/NettyCodecAdapter;
      48: invokestatic  #11                 // Method org/apache/dubbo/remoting/transport/netty4/NettyCodecAdapter.access$400:(Lorg/apache/dubbo/remoting/transport/netty4/NettyCodecAdapter;)Lorg/apache/dubbo/remoting/Codec2;
      51: aload         5
      53: aload         4
      55: invokeinterface #12,  3           // InterfaceMethod org/apache/dubbo/remoting/Codec2.decode:(Lorg/apache/dubbo/remoting/Channel;Lorg/apache/dubbo/remoting/buffer/ChannelBuffer;)Ljava/lang/Object;
      60: astore        7
      62: aload         7
      64: getstatic     #13                 // Field org/apache/dubbo/remoting/Codec2$DecodeResult.NEED_MORE_INPUT:Lorg/apache/dubbo/remoting/Codec2$DecodeResult;
      67: if_acmpne     82
      70: aload         4
      72: iload         6
      74: invokeinterface #14,  2           // InterfaceMethod org/apache/dubbo/remoting/buffer/ChannelBuffer.readerIndex:(I)V
      79: goto          128
      82: iload         6
      84: aload         4
      86: invokeinterface #10,  1           // InterfaceMethod org/apache/dubbo/remoting/buffer/ChannelBuffer.readerIndex:()I
      91: if_icmpne     104
      94: new           #15                 // class java/io/IOException
      97: dup
      98: ldc           #16                 // String Decode without read data.
     100: invokespecial #17                 // Method java/io/IOException."<init>":(Ljava/lang/String;)V
     103: athrow
     104: aload         7
     106: ifnull        118
     109: aload_3
     110: aload         7
     112: invokeinterface #18,  2           // InterfaceMethod java/util/List.add:(Ljava/lang/Object;)Z
     117: pop
     118: aload         4
     120: invokeinterface #19,  1           // InterfaceMethod org/apache/dubbo/remoting/buffer/ChannelBuffer.readable:()Z
     125: ifne          35
     128: return

  org.apache.dubbo.remoting.transport.netty4.NettyCodecAdapter$InternalDecoder(org.apache.dubbo.remoting.transport.netty4.NettyCodecAdapter, org.apache.dubbo.remoting.transport.netty4.NettyCodecAdapter$1);
    Code:
       0: aload_0
       1: aload_1
       2: invokespecial #1                  // Method "<init>":(Lorg/apache/dubbo/remoting/transport/netty4/NettyCodecAdapter;)V
       5: return
}
