Compiled from "NettyConnectionManager.java"
public class org.apache.dubbo.remoting.transport.netty4.NettyConnectionManager implements org.apache.dubbo.remoting.api.connection.ConnectionManager {
  public static final java.lang.String NAME;

  public org.apache.dubbo.remoting.transport.netty4.NettyConnectionManager();
    Code:
       0: aload_0
       1: invokespecial #1                  // Method java/lang/Object."<init>":()V
       4: return

  public org.apache.dubbo.remoting.api.connection.AbstractConnectionClient connect(org.apache.dubbo.common.URL, org.apache.dubbo.remoting.ChannelHandler);
    Code:
       0: new           #2                  // class org/apache/dubbo/remoting/transport/netty4/NettyConnectionClient
       3: dup
       4: aload_1
       5: aload_2
       6: invokespecial #3                  // Method org/apache/dubbo/remoting/transport/netty4/NettyConnectionClient."<init>":(Lorg/apache/dubbo/common/URL;Lorg/apache/dubbo/remoting/ChannelHandler;)V
       9: areturn
      10: astore_3
      11: new           #5                  // class java/lang/RuntimeException
      14: dup
      15: aload_3
      16: invokespecial #6                  // Method java/lang/RuntimeException."<init>":(Ljava/lang/Throwable;)V
      19: athrow
    Exception table:
       from    to  target type
           0     9    10   Class org/apache/dubbo/remoting/RemotingException

  public void forEachConnection(java.util.function.Consumer<org.apache.dubbo.remoting.api.connection.AbstractConnectionClient>);
    Code:
       0: return
}
