Compiled from "Netty4BatchWriteQueue.java"
class org.apache.dubbo.remoting.transport.netty4.Netty4BatchWriteQueue$MessageTuple {
  private final java.lang.Object originMessage;

  private final io.netty.channel.ChannelPromise channelPromise;

  public org.apache.dubbo.remoting.transport.netty4.Netty4BatchWriteQueue$MessageTuple(java.lang.Object, io.netty.channel.ChannelPromise);
    Code:
       0: aload_0
       1: invokespecial #3                  // Method java/lang/Object."<init>":()V
       4: aload_0
       5: aload_1
       6: putfield      #1                  // Field originMessage:Ljava/lang/Object;
       9: aload_0
      10: aload_2
      11: putfield      #2                  // Field channelPromise:Lio/netty/channel/ChannelPromise;
      14: return

  static io.netty.channel.ChannelPromise access$000(org.apache.dubbo.remoting.transport.netty4.Netty4BatchWriteQueue$MessageTuple);
    Code:
       0: aload_0
       1: getfield      #2                  // Field channelPromise:Lio/netty/channel/ChannelPromise;
       4: areturn

  static java.lang.Object access$100(org.apache.dubbo.remoting.transport.netty4.Netty4BatchWriteQueue$MessageTuple);
    Code:
       0: aload_0
       1: getfield      #1                  // Field originMessage:Ljava/lang/Object;
       4: areturn
}
