Compiled from "Detector.java"
public class com.google.zxing.qrcode.detector.Detector {
  private final com.google.zxing.common.BitMatrix image;

  private com.google.zxing.ResultPointCallback resultPointCallback;

  public com.google.zxing.qrcode.detector.Detector(com.google.zxing.common.BitMatrix);
    Code:
       0: aload_0
       1: invokespecial #1                  // Method java/lang/Object."<init>":()V
       4: aload_0
       5: aload_1
       6: putfield      #2                  // Field image:Lcom/google/zxing/common/BitMatrix;
       9: return

  protected final com.google.zxing.common.BitMatrix getImage();
    Code:
       0: aload_0
       1: getfield      #2                  // Field image:Lcom/google/zxing/common/BitMatrix;
       4: areturn

  protected final com.google.zxing.ResultPointCallback getResultPointCallback();
    Code:
       0: aload_0
       1: getfield      #3                  // Field resultPointCallback:Lcom/google/zxing/ResultPointCallback;
       4: areturn

  public com.google.zxing.common.DetectorResult detect() throws com.google.zxing.NotFoundException, com.google.zxing.FormatException;
    Code:
       0: aload_0
       1: aconst_null
       2: invokevirtual #4                  // Method detect:(Ljava/util/Map;)Lcom/google/zxing/common/DetectorResult;
       5: areturn

  public final com.google.zxing.common.DetectorResult detect(java.util.Map<com.google.zxing.DecodeHintType, ?>) throws com.google.zxing.NotFoundException, com.google.zxing.FormatException;
    Code:
       0: aload_0
       1: aload_1
       2: ifnonnull     9
       5: aconst_null
       6: goto          21
       9: aload_1
      10: getstatic     #5                  // Field com/google/zxing/DecodeHintType.NEED_RESULT_POINT_CALLBACK:Lcom/google/zxing/DecodeHintType;
      13: invokeinterface #6,  2            // InterfaceMethod java/util/Map.get:(Ljava/lang/Object;)Ljava/lang/Object;
      18: checkcast     #7                  // class com/google/zxing/ResultPointCallback
      21: putfield      #3                  // Field resultPointCallback:Lcom/google/zxing/ResultPointCallback;
      24: new           #8                  // class com/google/zxing/qrcode/detector/FinderPatternFinder
      27: dup
      28: aload_0
      29: getfield      #2                  // Field image:Lcom/google/zxing/common/BitMatrix;
      32: aload_0
      33: getfield      #3                  // Field resultPointCallback:Lcom/google/zxing/ResultPointCallback;
      36: invokespecial #9                  // Method com/google/zxing/qrcode/detector/FinderPatternFinder."<init>":(Lcom/google/zxing/common/BitMatrix;Lcom/google/zxing/ResultPointCallback;)V
      39: astore_2
      40: aload_2
      41: aload_1
      42: invokevirtual #10                 // Method com/google/zxing/qrcode/detector/FinderPatternFinder.find:(Ljava/util/Map;)Lcom/google/zxing/qrcode/detector/FinderPatternInfo;
      45: astore_3
      46: aload_0
      47: aload_3
      48: invokevirtual #11                 // Method processFinderPatternInfo:(Lcom/google/zxing/qrcode/detector/FinderPatternInfo;)Lcom/google/zxing/common/DetectorResult;
      51: areturn

  protected final com.google.zxing.common.DetectorResult processFinderPatternInfo(com.google.zxing.qrcode.detector.FinderPatternInfo) throws com.google.zxing.NotFoundException, com.google.zxing.FormatException;
    Code:
       0: aload_1
       1: invokevirtual #12                 // Method com/google/zxing/qrcode/detector/FinderPatternInfo.getTopLeft:()Lcom/google/zxing/qrcode/detector/FinderPattern;
       4: astore_2
       5: aload_1
       6: invokevirtual #13                 // Method com/google/zxing/qrcode/detector/FinderPatternInfo.getTopRight:()Lcom/google/zxing/qrcode/detector/FinderPattern;
       9: astore_3
      10: aload_1
      11: invokevirtual #14                 // Method com/google/zxing/qrcode/detector/FinderPatternInfo.getBottomLeft:()Lcom/google/zxing/qrcode/detector/FinderPattern;
      14: astore        4
      16: aload_0
      17: aload_2
      18: aload_3
      19: aload         4
      21: invokevirtual #15                 // Method calculateModuleSize:(Lcom/google/zxing/ResultPoint;Lcom/google/zxing/ResultPoint;Lcom/google/zxing/ResultPoint;)F
      24: fstore        5
      26: fload         5
      28: fconst_1
      29: fcmpg
      30: ifge          37
      33: invokestatic  #16                 // Method com/google/zxing/NotFoundException.getNotFoundInstance:()Lcom/google/zxing/NotFoundException;
      36: athrow
      37: aload_2
      38: aload_3
      39: aload         4
      41: fload         5
      43: invokestatic  #17                 // Method computeDimension:(Lcom/google/zxing/ResultPoint;Lcom/google/zxing/ResultPoint;Lcom/google/zxing/ResultPoint;F)I
      46: istore        6
      48: iload         6
      50: invokestatic  #18                 // Method com/google/zxing/qrcode/decoder/Version.getProvisionalVersionForDimension:(I)Lcom/google/zxing/qrcode/decoder/Version;
      53: astore        7
      55: aload         7
      57: invokevirtual #19                 // Method com/google/zxing/qrcode/decoder/Version.getDimensionForVersion:()I
      60: bipush        7
      62: isub
      63: istore        8
      65: aconst_null
      66: astore        9
      68: aload         7
      70: invokevirtual #20                 // Method com/google/zxing/qrcode/decoder/Version.getAlignmentPatternCenters:()[I
      73: arraylength
      74: ifle          196
      77: aload_3
      78: invokevirtual #21                 // Method com/google/zxing/qrcode/detector/FinderPattern.getX:()F
      81: aload_2
      82: invokevirtual #21                 // Method com/google/zxing/qrcode/detector/FinderPattern.getX:()F
      85: fsub
      86: aload         4
      88: invokevirtual #21                 // Method com/google/zxing/qrcode/detector/FinderPattern.getX:()F
      91: fadd
      92: fstore        10
      94: aload_3
      95: invokevirtual #22                 // Method com/google/zxing/qrcode/detector/FinderPattern.getY:()F
      98: aload_2
      99: invokevirtual #22                 // Method com/google/zxing/qrcode/detector/FinderPattern.getY:()F
     102: fsub
     103: aload         4
     105: invokevirtual #22                 // Method com/google/zxing/qrcode/detector/FinderPattern.getY:()F
     108: fadd
     109: fstore        11
     111: fconst_1
     112: ldc           #23                 // float 3.0f
     114: iload         8
     116: i2f
     117: fdiv
     118: fsub
     119: fstore        12
     121: aload_2
     122: invokevirtual #21                 // Method com/google/zxing/qrcode/detector/FinderPattern.getX:()F
     125: fload         12
     127: fload         10
     129: aload_2
     130: invokevirtual #21                 // Method com/google/zxing/qrcode/detector/FinderPattern.getX:()F
     133: fsub
     134: fmul
     135: fadd
     136: f2i
     137: istore        13
     139: aload_2
     140: invokevirtual #22                 // Method com/google/zxing/qrcode/detector/FinderPattern.getY:()F
     143: fload         12
     145: fload         11
     147: aload_2
     148: invokevirtual #22                 // Method com/google/zxing/qrcode/detector/FinderPattern.getY:()F
     151: fsub
     152: fmul
     153: fadd
     154: f2i
     155: istore        14
     157: iconst_4
     158: istore        15
     160: iload         15
     162: bipush        16
     164: if_icmpgt     196
     167: aload_0
     168: fload         5
     170: iload         13
     172: iload         14
     174: iload         15
     176: i2f
     177: invokevirtual #24                 // Method findAlignmentInRegion:(FIIF)Lcom/google/zxing/qrcode/detector/AlignmentPattern;
     180: astore        9
     182: goto          196
     185: astore        16
     187: iload         15
     189: iconst_1
     190: ishl
     191: istore        15
     193: goto          160
     196: aload_2
     197: aload_3
     198: aload         4
     200: aload         9
     202: iload         6
     204: invokestatic  #26                 // Method createTransform:(Lcom/google/zxing/ResultPoint;Lcom/google/zxing/ResultPoint;Lcom/google/zxing/ResultPoint;Lcom/google/zxing/ResultPoint;I)Lcom/google/zxing/common/PerspectiveTransform;
     207: astore        10
     209: aload_0
     210: getfield      #2                  // Field image:Lcom/google/zxing/common/BitMatrix;
     213: aload         10
     215: iload         6
     217: invokestatic  #27                 // Method sampleGrid:(Lcom/google/zxing/common/BitMatrix;Lcom/google/zxing/common/PerspectiveTransform;I)Lcom/google/zxing/common/BitMatrix;
     220: astore        11
     222: aload         9
     224: ifnonnull     249
     227: iconst_3
     228: anewarray     #28                 // class com/google/zxing/ResultPoint
     231: dup
     232: iconst_0
     233: aload         4
     235: aastore
     236: dup
     237: iconst_1
     238: aload_2
     239: aastore
     240: dup
     241: iconst_2
     242: aload_3
     243: aastore
     244: astore        12
     246: goto          273
     249: iconst_4
     250: anewarray     #28                 // class com/google/zxing/ResultPoint
     253: dup
     254: iconst_0
     255: aload         4
     257: aastore
     258: dup
     259: iconst_1
     260: aload_2
     261: aastore
     262: dup
     263: iconst_2
     264: aload_3
     265: aastore
     266: dup
     267: iconst_3
     268: aload         9
     270: aastore
     271: astore        12
     273: new           #29                 // class com/google/zxing/common/DetectorResult
     276: dup
     277: aload         11
     279: aload         12
     281: invokespecial #30                 // Method com/google/zxing/common/DetectorResult."<init>":(Lcom/google/zxing/common/BitMatrix;[Lcom/google/zxing/ResultPoint;)V
     284: areturn
    Exception table:
       from    to  target type
         167   182   185   Class com/google/zxing/NotFoundException

  private static com.google.zxing.common.PerspectiveTransform createTransform(com.google.zxing.ResultPoint, com.google.zxing.ResultPoint, com.google.zxing.ResultPoint, com.google.zxing.ResultPoint, int);
    Code:
       0: iload         4
       2: i2f
       3: ldc           #31                 // float 3.5f
       5: fsub
       6: fstore        5
       8: aload_3
       9: ifnull        38
      12: aload_3
      13: invokevirtual #32                 // Method com/google/zxing/ResultPoint.getX:()F
      16: fstore        6
      18: aload_3
      19: invokevirtual #33                 // Method com/google/zxing/ResultPoint.getY:()F
      22: fstore        7
      24: fload         5
      26: ldc           #23                 // float 3.0f
      28: fsub
      29: fstore        8
      31: fload         8
      33: fstore        9
      35: goto          78
      38: aload_1
      39: invokevirtual #32                 // Method com/google/zxing/ResultPoint.getX:()F
      42: aload_0
      43: invokevirtual #32                 // Method com/google/zxing/ResultPoint.getX:()F
      46: fsub
      47: aload_2
      48: invokevirtual #32                 // Method com/google/zxing/ResultPoint.getX:()F
      51: fadd
      52: fstore        6
      54: aload_1
      55: invokevirtual #33                 // Method com/google/zxing/ResultPoint.getY:()F
      58: aload_0
      59: invokevirtual #33                 // Method com/google/zxing/ResultPoint.getY:()F
      62: fsub
      63: aload_2
      64: invokevirtual #33                 // Method com/google/zxing/ResultPoint.getY:()F
      67: fadd
      68: fstore        7
      70: fload         5
      72: fstore        8
      74: fload         5
      76: fstore        9
      78: ldc           #31                 // float 3.5f
      80: ldc           #31                 // float 3.5f
      82: fload         5
      84: ldc           #31                 // float 3.5f
      86: fload         8
      88: fload         9
      90: ldc           #31                 // float 3.5f
      92: fload         5
      94: aload_0
      95: invokevirtual #32                 // Method com/google/zxing/ResultPoint.getX:()F
      98: aload_0
      99: invokevirtual #33                 // Method com/google/zxing/ResultPoint.getY:()F
     102: aload_1
     103: invokevirtual #32                 // Method com/google/zxing/ResultPoint.getX:()F
     106: aload_1
     107: invokevirtual #33                 // Method com/google/zxing/ResultPoint.getY:()F
     110: fload         6
     112: fload         7
     114: aload_2
     115: invokevirtual #32                 // Method com/google/zxing/ResultPoint.getX:()F
     118: aload_2
     119: invokevirtual #33                 // Method com/google/zxing/ResultPoint.getY:()F
     122: invokestatic  #34                 // Method com/google/zxing/common/PerspectiveTransform.quadrilateralToQuadrilateral:(FFFFFFFFFFFFFFFF)Lcom/google/zxing/common/PerspectiveTransform;
     125: areturn

  private static com.google.zxing.common.BitMatrix sampleGrid(com.google.zxing.common.BitMatrix, com.google.zxing.common.PerspectiveTransform, int) throws com.google.zxing.NotFoundException;
    Code:
       0: invokestatic  #35                 // Method com/google/zxing/common/GridSampler.getInstance:()Lcom/google/zxing/common/GridSampler;
       3: astore_3
       4: aload_3
       5: aload_0
       6: iload_2
       7: iload_2
       8: aload_1
       9: invokevirtual #36                 // Method com/google/zxing/common/GridSampler.sampleGrid:(Lcom/google/zxing/common/BitMatrix;IILcom/google/zxing/common/PerspectiveTransform;)Lcom/google/zxing/common/BitMatrix;
      12: areturn

  private static int computeDimension(com.google.zxing.ResultPoint, com.google.zxing.ResultPoint, com.google.zxing.ResultPoint, float) throws com.google.zxing.NotFoundException;
    Code:
       0: aload_0
       1: aload_1
       2: invokestatic  #37                 // Method com/google/zxing/ResultPoint.distance:(Lcom/google/zxing/ResultPoint;Lcom/google/zxing/ResultPoint;)F
       5: fload_3
       6: fdiv
       7: invokestatic  #38                 // Method com/google/zxing/common/detector/MathUtils.round:(F)I
      10: istore        4
      12: aload_0
      13: aload_2
      14: invokestatic  #37                 // Method com/google/zxing/ResultPoint.distance:(Lcom/google/zxing/ResultPoint;Lcom/google/zxing/ResultPoint;)F
      17: fload_3
      18: fdiv
      19: invokestatic  #38                 // Method com/google/zxing/common/detector/MathUtils.round:(F)I
      22: istore        5
      24: iload         4
      26: iload         5
      28: iadd
      29: iconst_2
      30: idiv
      31: bipush        7
      33: iadd
      34: istore        6
      36: iload         6
      38: iconst_3
      39: iand
      40: tableswitch   { // 0 to 3
                     0: 72
                     1: 88
                     2: 78
                     3: 84
               default: 88
          }
      72: iinc          6, 1
      75: goto          88
      78: iinc          6, -1
      81: goto          88
      84: invokestatic  #16                 // Method com/google/zxing/NotFoundException.getNotFoundInstance:()Lcom/google/zxing/NotFoundException;
      87: athrow
      88: iload         6
      90: ireturn

  protected final float calculateModuleSize(com.google.zxing.ResultPoint, com.google.zxing.ResultPoint, com.google.zxing.ResultPoint);
    Code:
       0: aload_0
       1: aload_1
       2: aload_2
       3: invokespecial #39                 // Method calculateModuleSizeOneWay:(Lcom/google/zxing/ResultPoint;Lcom/google/zxing/ResultPoint;)F
       6: aload_0
       7: aload_1
       8: aload_3
       9: invokespecial #39                 // Method calculateModuleSizeOneWay:(Lcom/google/zxing/ResultPoint;Lcom/google/zxing/ResultPoint;)F
      12: fadd
      13: fconst_2
      14: fdiv
      15: freturn

  private float calculateModuleSizeOneWay(com.google.zxing.ResultPoint, com.google.zxing.ResultPoint);
    Code:
       0: aload_0
       1: aload_1
       2: invokevirtual #32                 // Method com/google/zxing/ResultPoint.getX:()F
       5: f2i
       6: aload_1
       7: invokevirtual #33                 // Method com/google/zxing/ResultPoint.getY:()F
      10: f2i
      11: aload_2
      12: invokevirtual #32                 // Method com/google/zxing/ResultPoint.getX:()F
      15: f2i
      16: aload_2
      17: invokevirtual #33                 // Method com/google/zxing/ResultPoint.getY:()F
      20: f2i
      21: invokespecial #40                 // Method sizeOfBlackWhiteBlackRunBothWays:(IIII)F
      24: fstore_3
      25: aload_0
      26: aload_2
      27: invokevirtual #32                 // Method com/google/zxing/ResultPoint.getX:()F
      30: f2i
      31: aload_2
      32: invokevirtual #33                 // Method com/google/zxing/ResultPoint.getY:()F
      35: f2i
      36: aload_1
      37: invokevirtual #32                 // Method com/google/zxing/ResultPoint.getX:()F
      40: f2i
      41: aload_1
      42: invokevirtual #33                 // Method com/google/zxing/ResultPoint.getY:()F
      45: f2i
      46: invokespecial #40                 // Method sizeOfBlackWhiteBlackRunBothWays:(IIII)F
      49: fstore        4
      51: fload_3
      52: invokestatic  #41                 // Method java/lang/Float.isNaN:(F)Z
      55: ifeq          64
      58: fload         4
      60: ldc           #42                 // float 7.0f
      62: fdiv
      63: freturn
      64: fload         4
      66: invokestatic  #41                 // Method java/lang/Float.isNaN:(F)Z
      69: ifeq          77
      72: fload_3
      73: ldc           #42                 // float 7.0f
      75: fdiv
      76: freturn
      77: fload_3
      78: fload         4
      80: fadd
      81: ldc           #43                 // float 14.0f
      83: fdiv
      84: freturn

  private float sizeOfBlackWhiteBlackRunBothWays(int, int, int, int);
    Code:
       0: aload_0
       1: iload_1
       2: iload_2
       3: iload_3
       4: iload         4
       6: invokespecial #44                 // Method sizeOfBlackWhiteBlackRun:(IIII)F
       9: fstore        5
      11: fconst_1
      12: fstore        6
      14: iload_1
      15: iload_3
      16: iload_1
      17: isub
      18: isub
      19: istore        7
      21: iload         7
      23: ifge          42
      26: iload_1
      27: i2f
      28: iload_1
      29: iload         7
      31: isub
      32: i2f
      33: fdiv
      34: fstore        6
      36: iconst_0
      37: istore        7
      39: goto          85
      42: iload         7
      44: aload_0
      45: getfield      #2                  // Field image:Lcom/google/zxing/common/BitMatrix;
      48: invokevirtual #45                 // Method com/google/zxing/common/BitMatrix.getWidth:()I
      51: if_icmplt     85
      54: aload_0
      55: getfield      #2                  // Field image:Lcom/google/zxing/common/BitMatrix;
      58: invokevirtual #45                 // Method com/google/zxing/common/BitMatrix.getWidth:()I
      61: iconst_1
      62: isub
      63: iload_1
      64: isub
      65: i2f
      66: iload         7
      68: iload_1
      69: isub
      70: i2f
      71: fdiv
      72: fstore        6
      74: aload_0
      75: getfield      #2                  // Field image:Lcom/google/zxing/common/BitMatrix;
      78: invokevirtual #45                 // Method com/google/zxing/common/BitMatrix.getWidth:()I
      81: iconst_1
      82: isub
      83: istore        7
      85: iload_2
      86: i2f
      87: iload         4
      89: iload_2
      90: isub
      91: i2f
      92: fload         6
      94: fmul
      95: fsub
      96: f2i
      97: istore        8
      99: fconst_1
     100: fstore        6
     102: iload         8
     104: ifge          123
     107: iload_2
     108: i2f
     109: iload_2
     110: iload         8
     112: isub
     113: i2f
     114: fdiv
     115: fstore        6
     117: iconst_0
     118: istore        8
     120: goto          166
     123: iload         8
     125: aload_0
     126: getfield      #2                  // Field image:Lcom/google/zxing/common/BitMatrix;
     129: invokevirtual #46                 // Method com/google/zxing/common/BitMatrix.getHeight:()I
     132: if_icmplt     166
     135: aload_0
     136: getfield      #2                  // Field image:Lcom/google/zxing/common/BitMatrix;
     139: invokevirtual #46                 // Method com/google/zxing/common/BitMatrix.getHeight:()I
     142: iconst_1
     143: isub
     144: iload_2
     145: isub
     146: i2f
     147: iload         8
     149: iload_2
     150: isub
     151: i2f
     152: fdiv
     153: fstore        6
     155: aload_0
     156: getfield      #2                  // Field image:Lcom/google/zxing/common/BitMatrix;
     159: invokevirtual #46                 // Method com/google/zxing/common/BitMatrix.getHeight:()I
     162: iconst_1
     163: isub
     164: istore        8
     166: iload_1
     167: i2f
     168: iload         7
     170: iload_1
     171: isub
     172: i2f
     173: fload         6
     175: fmul
     176: fadd
     177: f2i
     178: istore        7
     180: fload         5
     182: aload_0
     183: iload_1
     184: iload_2
     185: iload         7
     187: iload         8
     189: invokespecial #44                 // Method sizeOfBlackWhiteBlackRun:(IIII)F
     192: fadd
     193: fstore        5
     195: fload         5
     197: fconst_1
     198: fsub
     199: freturn

  private float sizeOfBlackWhiteBlackRun(int, int, int, int);
    Code:
       0: iload         4
       2: iload_2
       3: isub
       4: invokestatic  #47                 // Method java/lang/Math.abs:(I)I
       7: iload_3
       8: iload_1
       9: isub
      10: invokestatic  #47                 // Method java/lang/Math.abs:(I)I
      13: if_icmple     20
      16: iconst_1
      17: goto          21
      20: iconst_0
      21: istore        5
      23: iload         5
      25: ifeq          46
      28: iload_1
      29: istore        6
      31: iload_2
      32: istore_1
      33: iload         6
      35: istore_2
      36: iload_3
      37: istore        6
      39: iload         4
      41: istore_3
      42: iload         6
      44: istore        4
      46: iload_3
      47: iload_1
      48: isub
      49: invokestatic  #47                 // Method java/lang/Math.abs:(I)I
      52: istore        6
      54: iload         4
      56: iload_2
      57: isub
      58: invokestatic  #47                 // Method java/lang/Math.abs:(I)I
      61: istore        7
      63: iload         6
      65: ineg
      66: iconst_2
      67: idiv
      68: istore        8
      70: iload_1
      71: iload_3
      72: if_icmpge     79
      75: iconst_1
      76: goto          80
      79: iconst_m1
      80: istore        9
      82: iload_2
      83: iload         4
      85: if_icmpge     92
      88: iconst_1
      89: goto          93
      92: iconst_m1
      93: istore        10
      95: iconst_0
      96: istore        11
      98: iload_3
      99: iload         9
     101: iadd
     102: istore        12
     104: iload_1
     105: istore        13
     107: iload_2
     108: istore        14
     110: iload         13
     112: iload         12
     114: if_icmpeq     235
     117: iload         5
     119: ifeq          127
     122: iload         14
     124: goto          129
     127: iload         13
     129: istore        15
     131: iload         5
     133: ifeq          141
     136: iload         13
     138: goto          143
     141: iload         14
     143: istore        16
     145: iload         11
     147: iconst_1
     148: if_icmpne     155
     151: iconst_1
     152: goto          156
     155: iconst_0
     156: aload_0
     157: getfield      #2                  // Field image:Lcom/google/zxing/common/BitMatrix;
     160: iload         15
     162: iload         16
     164: invokevirtual #48                 // Method com/google/zxing/common/BitMatrix.get:(II)Z
     167: if_icmpne     189
     170: iload         11
     172: iconst_2
     173: if_icmpne     186
     176: iload         13
     178: iload         14
     180: iload_1
     181: iload_2
     182: invokestatic  #49                 // Method com/google/zxing/common/detector/MathUtils.distance:(IIII)F
     185: freturn
     186: iinc          11, 1
     189: iload         8
     191: iload         7
     193: iadd
     194: istore        8
     196: iload         8
     198: ifle          225
     201: iload         14
     203: iload         4
     205: if_icmpne     211
     208: goto          235
     211: iload         14
     213: iload         10
     215: iadd
     216: istore        14
     218: iload         8
     220: iload         6
     222: isub
     223: istore        8
     225: iload         13
     227: iload         9
     229: iadd
     230: istore        13
     232: goto          110
     235: iload         11
     237: iconst_2
     238: if_icmpne     253
     241: iload_3
     242: iload         9
     244: iadd
     245: iload         4
     247: iload_1
     248: iload_2
     249: invokestatic  #49                 // Method com/google/zxing/common/detector/MathUtils.distance:(IIII)F
     252: freturn
     253: ldc           #51                 // float NaNf
     255: freturn

  protected final com.google.zxing.qrcode.detector.AlignmentPattern findAlignmentInRegion(float, int, int, float) throws com.google.zxing.NotFoundException;
    Code:
       0: fload         4
       2: fload_1
       3: fmul
       4: f2i
       5: istore        5
       7: iconst_0
       8: iload_2
       9: iload         5
      11: isub
      12: invokestatic  #52                 // Method java/lang/Math.max:(II)I
      15: istore        6
      17: aload_0
      18: getfield      #2                  // Field image:Lcom/google/zxing/common/BitMatrix;
      21: invokevirtual #45                 // Method com/google/zxing/common/BitMatrix.getWidth:()I
      24: iconst_1
      25: isub
      26: iload_2
      27: iload         5
      29: iadd
      30: invokestatic  #53                 // Method java/lang/Math.min:(II)I
      33: istore        7
      35: iload         7
      37: iload         6
      39: isub
      40: i2f
      41: fload_1
      42: ldc           #23                 // float 3.0f
      44: fmul
      45: fcmpg
      46: ifge          53
      49: invokestatic  #16                 // Method com/google/zxing/NotFoundException.getNotFoundInstance:()Lcom/google/zxing/NotFoundException;
      52: athrow
      53: iconst_0
      54: iload_3
      55: iload         5
      57: isub
      58: invokestatic  #52                 // Method java/lang/Math.max:(II)I
      61: istore        8
      63: aload_0
      64: getfield      #2                  // Field image:Lcom/google/zxing/common/BitMatrix;
      67: invokevirtual #46                 // Method com/google/zxing/common/BitMatrix.getHeight:()I
      70: iconst_1
      71: isub
      72: iload_3
      73: iload         5
      75: iadd
      76: invokestatic  #53                 // Method java/lang/Math.min:(II)I
      79: istore        9
      81: iload         9
      83: iload         8
      85: isub
      86: i2f
      87: fload_1
      88: ldc           #23                 // float 3.0f
      90: fmul
      91: fcmpg
      92: ifge          99
      95: invokestatic  #16                 // Method com/google/zxing/NotFoundException.getNotFoundInstance:()Lcom/google/zxing/NotFoundException;
      98: athrow
      99: new           #54                 // class com/google/zxing/qrcode/detector/AlignmentPatternFinder
     102: dup
     103: aload_0
     104: getfield      #2                  // Field image:Lcom/google/zxing/common/BitMatrix;
     107: iload         6
     109: iload         8
     111: iload         7
     113: iload         6
     115: isub
     116: iload         9
     118: iload         8
     120: isub
     121: fload_1
     122: aload_0
     123: getfield      #3                  // Field resultPointCallback:Lcom/google/zxing/ResultPointCallback;
     126: invokespecial #55                 // Method com/google/zxing/qrcode/detector/AlignmentPatternFinder."<init>":(Lcom/google/zxing/common/BitMatrix;IIIIFLcom/google/zxing/ResultPointCallback;)V
     129: astore        10
     131: aload         10
     133: invokevirtual #56                 // Method com/google/zxing/qrcode/detector/AlignmentPatternFinder.find:()Lcom/google/zxing/qrcode/detector/AlignmentPattern;
     136: areturn
}
