Compiled from "FinderPatternFinder.java"
final class com.google.zxing.qrcode.detector.FinderPatternFinder$EstimatedModuleComparator implements java.util.Comparator<com.google.zxing.qrcode.detector.FinderPattern>, java.io.Serializable {
  private com.google.zxing.qrcode.detector.FinderPatternFinder$EstimatedModuleComparator();
    Code:
       0: aload_0
       1: invokespecial #2                  // Method java/lang/Object."<init>":()V
       4: return

  public int compare(com.google.zxing.qrcode.detector.FinderPattern, com.google.zxing.qrcode.detector.FinderPattern);
    Code:
       0: aload_1
       1: invokevirtual #3                  // Method com/google/zxing/qrcode/detector/FinderPattern.getEstimatedModuleSize:()F
       4: aload_2
       5: invokevirtual #3                  // Method com/google/zxing/qrcode/detector/FinderPattern.getEstimatedModuleSize:()F
       8: invokestatic  #4                  // Method java/lang/Float.compare:(FF)I
      11: ireturn

  public int compare(java.lang.Object, java.lang.Object);
    Code:
       0: aload_0
       1: aload_1
       2: checkcast     #5                  // class com/google/zxing/qrcode/detector/FinderPattern
       5: aload_2
       6: checkcast     #5                  // class com/google/zxing/qrcode/detector/FinderPattern
       9: invokevirtual #6                  // Method compare:(Lcom/google/zxing/qrcode/detector/FinderPattern;Lcom/google/zxing/qrcode/detector/FinderPattern;)I
      12: ireturn

  com.google.zxing.qrcode.detector.FinderPatternFinder$EstimatedModuleComparator(com.google.zxing.qrcode.detector.FinderPatternFinder$1);
    Code:
       0: aload_0
       1: invokespecial #1                  // Method "<init>":()V
       4: return
}
