Compiled from "FinderPatternInfo.java"
public final class com.google.zxing.qrcode.detector.FinderPatternInfo {
  private final com.google.zxing.qrcode.detector.FinderPattern bottomLeft;

  private final com.google.zxing.qrcode.detector.FinderPattern topLeft;

  private final com.google.zxing.qrcode.detector.FinderPattern topRight;

  public com.google.zxing.qrcode.detector.FinderPatternInfo(com.google.zxing.qrcode.detector.FinderPattern[]);
    Code:
       0: aload_0
       1: invokespecial #1                  // Method java/lang/Object."<init>":()V
       4: aload_0
       5: aload_1
       6: iconst_0
       7: aaload
       8: putfield      #2                  // Field bottomLeft:Lcom/google/zxing/qrcode/detector/FinderPattern;
      11: aload_0
      12: aload_1
      13: iconst_1
      14: aaload
      15: putfield      #3                  // Field topLeft:Lcom/google/zxing/qrcode/detector/FinderPattern;
      18: aload_0
      19: aload_1
      20: iconst_2
      21: aaload
      22: putfield      #4                  // Field topRight:Lcom/google/zxing/qrcode/detector/FinderPattern;
      25: return

  public com.google.zxing.qrcode.detector.FinderPattern getBottomLeft();
    Code:
       0: aload_0
       1: getfield      #2                  // Field bottomLeft:Lcom/google/zxing/qrcode/detector/FinderPattern;
       4: areturn

  public com.google.zxing.qrcode.detector.FinderPattern getTopLeft();
    Code:
       0: aload_0
       1: getfield      #3                  // Field topLeft:Lcom/google/zxing/qrcode/detector/FinderPattern;
       4: areturn

  public com.google.zxing.qrcode.detector.FinderPattern getTopRight();
    Code:
       0: aload_0
       1: getfield      #4                  // Field topRight:Lcom/google/zxing/qrcode/detector/FinderPattern;
       4: areturn
}
