Compiled from "MetadataResolver.java"
public class org.apache.dubbo.rpc.protocol.rest.annotation.metadata.MetadataResolver {
  private org.apache.dubbo.rpc.protocol.rest.annotation.metadata.MetadataResolver();
    Code:
       0: aload_0
       1: invokespecial #1                  // Method java/lang/Object."<init>":()V
       4: return

  public static org.apache.dubbo.metadata.rest.ServiceRestMetadata resolveConsumerServiceMetadata(java.lang.Class<?>, org.apache.dubbo.common.URL, java.lang.String);
    Code:
       0: aload_1
       1: invokevirtual #2                  // Method org/apache/dubbo/common/URL.getOrDefaultApplicationModel:()Lorg/apache/dubbo/rpc/model/ApplicationModel;
       4: ldc           #3                  // class org/apache/dubbo/metadata/rest/ServiceRestMetadataResolver
       6: invokevirtual #4                  // Method org/apache/dubbo/rpc/model/ApplicationModel.getExtensionLoader:(Ljava/lang/Class;)Lorg/apache/dubbo/common/extension/ExtensionLoader;
       9: astore_3
      10: aload_3
      11: invokevirtual #5                  // Method org/apache/dubbo/common/extension/ExtensionLoader.getSupportedExtensionInstances:()Ljava/util/Set;
      14: invokeinterface #6,  1            // InterfaceMethod java/util/Set.iterator:()Ljava/util/Iterator;
      19: astore        4
      21: aload         4
      23: invokeinterface #7,  1            // InterfaceMethod java/util/Iterator.hasNext:()Z
      28: ifeq          101
      31: aload         4
      33: invokeinterface #8,  1            // InterfaceMethod java/util/Iterator.next:()Ljava/lang/Object;
      38: checkcast     #3                  // class org/apache/dubbo/metadata/rest/ServiceRestMetadataResolver
      41: astore        5
      43: aload         5
      45: aload_0
      46: iconst_1
      47: invokeinterface #9,  3            // InterfaceMethod org/apache/dubbo/metadata/rest/ServiceRestMetadataResolver.supports:(Ljava/lang/Class;Z)Z
      52: ifeq          98
      55: new           #10                 // class org/apache/dubbo/metadata/rest/ServiceRestMetadata
      58: dup
      59: aload_1
      60: invokevirtual #11                 // Method org/apache/dubbo/common/URL.getServiceInterface:()Ljava/lang/String;
      63: aload_1
      64: invokevirtual #12                 // Method org/apache/dubbo/common/URL.getVersion:()Ljava/lang/String;
      67: aload_1
      68: invokevirtual #13                 // Method org/apache/dubbo/common/URL.getGroup:()Ljava/lang/String;
      71: iconst_1
      72: invokespecial #14                 // Method org/apache/dubbo/metadata/rest/ServiceRestMetadata."<init>":(Ljava/lang/String;Ljava/lang/String;Ljava/lang/String;Z)V
      75: astore        6
      77: aload         6
      79: aload_2
      80: invokevirtual #15                 // Method org/apache/dubbo/metadata/rest/ServiceRestMetadata.setContextPathFromUrl:(Ljava/lang/String;)V
      83: aload         5
      85: aload_0
      86: aload         6
      88: invokeinterface #16,  3           // InterfaceMethod org/apache/dubbo/metadata/rest/ServiceRestMetadataResolver.resolve:(Ljava/lang/Class;Lorg/apache/dubbo/metadata/rest/ServiceRestMetadata;)Lorg/apache/dubbo/metadata/rest/ServiceRestMetadata;
      93: astore        7
      95: aload         7
      97: areturn
      98: goto          21
     101: new           #17                 // class org/apache/dubbo/rpc/protocol/rest/exception/CodeStyleNotSupportException
     104: dup
     105: new           #18                 // class java/lang/StringBuilder
     108: dup
     109: invokespecial #19                 // Method java/lang/StringBuilder."<init>":()V
     112: ldc           #20                 // String service is:
     114: invokevirtual #21                 // Method java/lang/StringBuilder.append:(Ljava/lang/String;)Ljava/lang/StringBuilder;
     117: aload_0
     118: invokevirtual #22                 // Method java/lang/StringBuilder.append:(Ljava/lang/Object;)Ljava/lang/StringBuilder;
     121: ldc           #23                 // String , only support
     123: invokevirtual #21                 // Method java/lang/StringBuilder.append:(Ljava/lang/String;)Ljava/lang/StringBuilder;
     126: aload_3
     127: invokevirtual #24                 // Method org/apache/dubbo/common/extension/ExtensionLoader.getSupportedExtensions:()Ljava/util/Set;
     130: invokevirtual #22                 // Method java/lang/StringBuilder.append:(Ljava/lang/Object;)Ljava/lang/StringBuilder;
     133: ldc           #25                 // String  annotation
     135: invokevirtual #21                 // Method java/lang/StringBuilder.append:(Ljava/lang/String;)Ljava/lang/StringBuilder;
     138: invokevirtual #26                 // Method java/lang/StringBuilder.toString:()Ljava/lang/String;
     141: invokespecial #27                 // Method org/apache/dubbo/rpc/protocol/rest/exception/CodeStyleNotSupportException."<init>":(Ljava/lang/String;)V
     144: athrow

  public static org.apache.dubbo.metadata.rest.ServiceRestMetadata resolveProviderServiceMetadata(java.lang.Class, org.apache.dubbo.common.URL, java.lang.String);
    Code:
       0: aload_1
       1: invokevirtual #2                  // Method org/apache/dubbo/common/URL.getOrDefaultApplicationModel:()Lorg/apache/dubbo/rpc/model/ApplicationModel;
       4: ldc           #3                  // class org/apache/dubbo/metadata/rest/ServiceRestMetadataResolver
       6: invokevirtual #4                  // Method org/apache/dubbo/rpc/model/ApplicationModel.getExtensionLoader:(Ljava/lang/Class;)Lorg/apache/dubbo/common/extension/ExtensionLoader;
       9: astore_3
      10: aload_3
      11: invokevirtual #5                  // Method org/apache/dubbo/common/extension/ExtensionLoader.getSupportedExtensionInstances:()Ljava/util/Set;
      14: invokeinterface #6,  1            // InterfaceMethod java/util/Set.iterator:()Ljava/util/Iterator;
      19: astore        4
      21: aload         4
      23: invokeinterface #7,  1            // InterfaceMethod java/util/Iterator.hasNext:()Z
      28: ifeq          104
      31: aload         4
      33: invokeinterface #8,  1            // InterfaceMethod java/util/Iterator.next:()Ljava/lang/Object;
      38: checkcast     #3                  // class org/apache/dubbo/metadata/rest/ServiceRestMetadataResolver
      41: astore        5
      43: aload         5
      45: aload_0
      46: invokeinterface #28,  2           // InterfaceMethod org/apache/dubbo/metadata/rest/ServiceRestMetadataResolver.supports:(Ljava/lang/Class;)Z
      51: istore        6
      53: iload         6
      55: ifeq          101
      58: new           #10                 // class org/apache/dubbo/metadata/rest/ServiceRestMetadata
      61: dup
      62: aload_1
      63: invokevirtual #11                 // Method org/apache/dubbo/common/URL.getServiceInterface:()Ljava/lang/String;
      66: aload_1
      67: invokevirtual #12                 // Method org/apache/dubbo/common/URL.getVersion:()Ljava/lang/String;
      70: aload_1
      71: invokevirtual #13                 // Method org/apache/dubbo/common/URL.getGroup:()Ljava/lang/String;
      74: iconst_0
      75: invokespecial #14                 // Method org/apache/dubbo/metadata/rest/ServiceRestMetadata."<init>":(Ljava/lang/String;Ljava/lang/String;Ljava/lang/String;Z)V
      78: astore        7
      80: aload         7
      82: aload_2
      83: invokevirtual #15                 // Method org/apache/dubbo/metadata/rest/ServiceRestMetadata.setContextPathFromUrl:(Ljava/lang/String;)V
      86: aload         5
      88: aload_0
      89: aload         7
      91: invokeinterface #16,  3           // InterfaceMethod org/apache/dubbo/metadata/rest/ServiceRestMetadataResolver.resolve:(Ljava/lang/Class;Lorg/apache/dubbo/metadata/rest/ServiceRestMetadata;)Lorg/apache/dubbo/metadata/rest/ServiceRestMetadata;
      96: astore        8
      98: aload         8
     100: areturn
     101: goto          21
     104: new           #17                 // class org/apache/dubbo/rpc/protocol/rest/exception/CodeStyleNotSupportException
     107: dup
     108: new           #18                 // class java/lang/StringBuilder
     111: dup
     112: invokespecial #19                 // Method java/lang/StringBuilder."<init>":()V
     115: ldc           #29                 // String service is:
     117: invokevirtual #21                 // Method java/lang/StringBuilder.append:(Ljava/lang/String;)Ljava/lang/StringBuilder;
     120: aload_0
     121: invokevirtual #22                 // Method java/lang/StringBuilder.append:(Ljava/lang/Object;)Ljava/lang/StringBuilder;
     124: ldc           #30                 // String ,just support rest or spring-web annotation
     126: invokevirtual #21                 // Method java/lang/StringBuilder.append:(Ljava/lang/String;)Ljava/lang/StringBuilder;
     129: invokevirtual #26                 // Method java/lang/StringBuilder.toString:()Ljava/lang/String;
     132: invokespecial #27                 // Method org/apache/dubbo/rpc/protocol/rest/exception/CodeStyleNotSupportException."<init>":(Ljava/lang/String;)V
     135: athrow
}
