Compiled from "BaseStatComposite.java"
public abstract class org.apache.dubbo.metrics.data.BaseStatComposite implements org.apache.dubbo.metrics.report.MetricsExport {
  private org.apache.dubbo.metrics.data.ApplicationStatComposite applicationStatComposite;

  private org.apache.dubbo.metrics.data.ServiceStatComposite serviceStatComposite;

  private org.apache.dubbo.metrics.data.MethodStatComposite methodStatComposite;

  private org.apache.dubbo.metrics.data.RtStatComposite rtStatComposite;

  public org.apache.dubbo.metrics.data.BaseStatComposite(org.apache.dubbo.rpc.model.ApplicationModel);
    Code:
       0: aload_0
       1: invokespecial #1                  // Method java/lang/Object."<init>":()V
       4: aload_0
       5: new           #2                  // class org/apache/dubbo/metrics/data/ApplicationStatComposite
       8: dup
       9: aload_1
      10: invokespecial #3                  // Method org/apache/dubbo/metrics/data/ApplicationStatComposite."<init>":(Lorg/apache/dubbo/rpc/model/ApplicationModel;)V
      13: invokevirtual #4                  // Method init:(Lorg/apache/dubbo/metrics/data/ApplicationStatComposite;)V
      16: aload_0
      17: new           #5                  // class org/apache/dubbo/metrics/data/ServiceStatComposite
      20: dup
      21: aload_1
      22: invokespecial #6                  // Method org/apache/dubbo/metrics/data/ServiceStatComposite."<init>":(Lorg/apache/dubbo/rpc/model/ApplicationModel;)V
      25: invokevirtual #7                  // Method init:(Lorg/apache/dubbo/metrics/data/ServiceStatComposite;)V
      28: aload_0
      29: new           #8                  // class org/apache/dubbo/metrics/data/MethodStatComposite
      32: dup
      33: aload_1
      34: invokespecial #9                  // Method org/apache/dubbo/metrics/data/MethodStatComposite."<init>":(Lorg/apache/dubbo/rpc/model/ApplicationModel;)V
      37: invokevirtual #10                 // Method init:(Lorg/apache/dubbo/metrics/data/MethodStatComposite;)V
      40: aload_0
      41: new           #11                 // class org/apache/dubbo/metrics/data/RtStatComposite
      44: dup
      45: aload_1
      46: invokespecial #12                 // Method org/apache/dubbo/metrics/data/RtStatComposite."<init>":(Lorg/apache/dubbo/rpc/model/ApplicationModel;)V
      49: invokevirtual #13                 // Method init:(Lorg/apache/dubbo/metrics/data/RtStatComposite;)V
      52: return

  protected void init(org.apache.dubbo.metrics.data.ApplicationStatComposite);
    Code:
       0: aload_0
       1: aload_1
       2: putfield      #14                 // Field applicationStatComposite:Lorg/apache/dubbo/metrics/data/ApplicationStatComposite;
       5: return

  protected void init(org.apache.dubbo.metrics.data.ServiceStatComposite);
    Code:
       0: aload_0
       1: aload_1
       2: putfield      #15                 // Field serviceStatComposite:Lorg/apache/dubbo/metrics/data/ServiceStatComposite;
       5: return

  protected void init(org.apache.dubbo.metrics.data.MethodStatComposite);
    Code:
       0: aload_0
       1: aload_1
       2: putfield      #16                 // Field methodStatComposite:Lorg/apache/dubbo/metrics/data/MethodStatComposite;
       5: return

  protected void init(org.apache.dubbo.metrics.data.RtStatComposite);
    Code:
       0: aload_0
       1: aload_1
       2: putfield      #17                 // Field rtStatComposite:Lorg/apache/dubbo/metrics/data/RtStatComposite;
       5: return

  public void calcApplicationRt(java.lang.String, java.lang.Long);
    Code:
       0: aload_0
       1: getfield      #17                 // Field rtStatComposite:Lorg/apache/dubbo/metrics/data/RtStatComposite;
       4: aload_1
       5: aload_2
       6: invokevirtual #18                 // Method org/apache/dubbo/metrics/data/RtStatComposite.calcApplicationRt:(Ljava/lang/String;Ljava/lang/Long;)V
       9: return

  public void calcServiceKeyRt(java.lang.String, java.lang.String, java.lang.Long);
    Code:
       0: aload_0
       1: getfield      #17                 // Field rtStatComposite:Lorg/apache/dubbo/metrics/data/RtStatComposite;
       4: aload_1
       5: aload_2
       6: aload_3
       7: invokevirtual #19                 // Method org/apache/dubbo/metrics/data/RtStatComposite.calcServiceKeyRt:(Ljava/lang/String;Ljava/lang/String;Ljava/lang/Long;)V
      10: return

  public void calcMethodKeyRt(org.apache.dubbo.rpc.Invocation, java.lang.String, java.lang.Long);
    Code:
       0: aload_0
       1: getfield      #17                 // Field rtStatComposite:Lorg/apache/dubbo/metrics/data/RtStatComposite;
       4: aload_1
       5: aload_2
       6: aload_3
       7: invokevirtual #20                 // Method org/apache/dubbo/metrics/data/RtStatComposite.calcMethodKeyRt:(Lorg/apache/dubbo/rpc/Invocation;Ljava/lang/String;Ljava/lang/Long;)V
      10: return

  public void setServiceKey(org.apache.dubbo.metrics.model.key.MetricsKeyWrapper, java.lang.String, int);
    Code:
       0: aload_0
       1: getfield      #15                 // Field serviceStatComposite:Lorg/apache/dubbo/metrics/data/ServiceStatComposite;
       4: aload_1
       5: aload_2
       6: iload_3
       7: invokevirtual #21                 // Method org/apache/dubbo/metrics/data/ServiceStatComposite.setServiceKey:(Lorg/apache/dubbo/metrics/model/key/MetricsKeyWrapper;Ljava/lang/String;I)V
      10: return

  public void incrementApp(org.apache.dubbo.metrics.model.key.MetricsKey, int);
    Code:
       0: aload_0
       1: getfield      #14                 // Field applicationStatComposite:Lorg/apache/dubbo/metrics/data/ApplicationStatComposite;
       4: aload_1
       5: iload_2
       6: invokevirtual #22                 // Method org/apache/dubbo/metrics/data/ApplicationStatComposite.incrementSize:(Lorg/apache/dubbo/metrics/model/key/MetricsKey;I)V
       9: return

  public void incrementServiceKey(org.apache.dubbo.metrics.model.key.MetricsKeyWrapper, java.lang.String, int);
    Code:
       0: aload_0
       1: getfield      #15                 // Field serviceStatComposite:Lorg/apache/dubbo/metrics/data/ServiceStatComposite;
       4: aload_1
       5: aload_2
       6: iload_3
       7: invokevirtual #23                 // Method org/apache/dubbo/metrics/data/ServiceStatComposite.incrementServiceKey:(Lorg/apache/dubbo/metrics/model/key/MetricsKeyWrapper;Ljava/lang/String;I)V
      10: return

  public void incrementMethodKey(org.apache.dubbo.metrics.model.key.MetricsKeyWrapper, org.apache.dubbo.rpc.Invocation, int);
    Code:
       0: aload_0
       1: getfield      #16                 // Field methodStatComposite:Lorg/apache/dubbo/metrics/data/MethodStatComposite;
       4: aload_1
       5: aload_2
       6: iload_3
       7: invokevirtual #24                 // Method org/apache/dubbo/metrics/data/MethodStatComposite.incrementMethodKey:(Lorg/apache/dubbo/metrics/model/key/MetricsKeyWrapper;Lorg/apache/dubbo/rpc/Invocation;I)V
      10: return

  public java.util.List<org.apache.dubbo.metrics.model.sample.MetricSample> export(org.apache.dubbo.metrics.model.MetricsCategory);
    Code:
       0: new           #25                 // class java/util/ArrayList
       3: dup
       4: invokespecial #26                 // Method java/util/ArrayList."<init>":()V
       7: astore_2
       8: aload_2
       9: aload_0
      10: getfield      #14                 // Field applicationStatComposite:Lorg/apache/dubbo/metrics/data/ApplicationStatComposite;
      13: aload_1
      14: invokevirtual #27                 // Method org/apache/dubbo/metrics/data/ApplicationStatComposite.export:(Lorg/apache/dubbo/metrics/model/MetricsCategory;)Ljava/util/List;
      17: invokeinterface #28,  2           // InterfaceMethod java/util/List.addAll:(Ljava/util/Collection;)Z
      22: pop
      23: aload_2
      24: aload_0
      25: getfield      #17                 // Field rtStatComposite:Lorg/apache/dubbo/metrics/data/RtStatComposite;
      28: aload_1
      29: invokevirtual #29                 // Method org/apache/dubbo/metrics/data/RtStatComposite.export:(Lorg/apache/dubbo/metrics/model/MetricsCategory;)Ljava/util/List;
      32: invokeinterface #28,  2           // InterfaceMethod java/util/List.addAll:(Ljava/util/Collection;)Z
      37: pop
      38: aload_2
      39: aload_0
      40: getfield      #15                 // Field serviceStatComposite:Lorg/apache/dubbo/metrics/data/ServiceStatComposite;
      43: aload_1
      44: invokevirtual #30                 // Method org/apache/dubbo/metrics/data/ServiceStatComposite.export:(Lorg/apache/dubbo/metrics/model/MetricsCategory;)Ljava/util/List;
      47: invokeinterface #28,  2           // InterfaceMethod java/util/List.addAll:(Ljava/util/Collection;)Z
      52: pop
      53: aload_2
      54: aload_0
      55: getfield      #16                 // Field methodStatComposite:Lorg/apache/dubbo/metrics/data/MethodStatComposite;
      58: aload_1
      59: invokevirtual #31                 // Method org/apache/dubbo/metrics/data/MethodStatComposite.export:(Lorg/apache/dubbo/metrics/model/MetricsCategory;)Ljava/util/List;
      62: invokeinterface #28,  2           // InterfaceMethod java/util/List.addAll:(Ljava/util/Collection;)Z
      67: pop
      68: aload_2
      69: areturn

  public org.apache.dubbo.metrics.data.ApplicationStatComposite getApplicationStatComposite();
    Code:
       0: aload_0
       1: getfield      #14                 // Field applicationStatComposite:Lorg/apache/dubbo/metrics/data/ApplicationStatComposite;
       4: areturn

  public org.apache.dubbo.metrics.data.RtStatComposite getRtStatComposite();
    Code:
       0: aload_0
       1: getfield      #17                 // Field rtStatComposite:Lorg/apache/dubbo/metrics/data/RtStatComposite;
       4: areturn
}
