Compiled from "RtStatComposite.java"
public class org.apache.dubbo.metrics.data.RtStatComposite extends org.apache.dubbo.metrics.report.AbstractMetricsExport {
  private final java.util.List<org.apache.dubbo.metrics.model.container.LongContainer<? extends java.lang.Number>> rtStats;

  public org.apache.dubbo.metrics.data.RtStatComposite(org.apache.dubbo.rpc.model.ApplicationModel);
    Code:
       0: aload_0
       1: aload_1
       2: invokespecial #1                  // Method org/apache/dubbo/metrics/report/AbstractMetricsExport."<init>":(Lorg/apache/dubbo/rpc/model/ApplicationModel;)V
       5: aload_0
       6: new           #2                  // class java/util/ArrayList
       9: dup
      10: invokespecial #3                  // Method java/util/ArrayList."<init>":()V
      13: putfield      #4                  // Field rtStats:Ljava/util/List;
      16: return

  public void init(org.apache.dubbo.metrics.model.key.MetricsPlaceValue...);
    Code:
       0: aload_1
       1: ifnonnull     5
       4: return
       5: aload_1
       6: invokestatic  #5                  // Method java/util/Arrays.stream:([Ljava/lang/Object;)Ljava/util/stream/Stream;
       9: aload_0
      10: invokedynamic #6,  0              // InvokeDynamic #0:accept:(Lorg/apache/dubbo/metrics/data/RtStatComposite;)Ljava/util/function/Consumer;
      15: invokeinterface #7,  2            // InterfaceMethod java/util/stream/Stream.forEach:(Ljava/util/function/Consumer;)V
      20: return

  private java.util.List<org.apache.dubbo.metrics.model.container.LongContainer<? extends java.lang.Number>> initStats(org.apache.dubbo.metrics.model.key.MetricsPlaceValue);
    Code:
       0: new           #2                  // class java/util/ArrayList
       3: dup
       4: invokespecial #3                  // Method java/util/ArrayList."<init>":()V
       7: astore_2
       8: aload_2
       9: new           #8                  // class org/apache/dubbo/metrics/model/container/AtomicLongContainer
      12: dup
      13: new           #9                  // class org/apache/dubbo/metrics/model/key/MetricsKeyWrapper
      16: dup
      17: getstatic     #10                 // Field org/apache/dubbo/metrics/model/key/MetricsKey.METRIC_RT_LAST:Lorg/apache/dubbo/metrics/model/key/MetricsKey;
      20: aload_1
      21: invokespecial #11                 // Method org/apache/dubbo/metrics/model/key/MetricsKeyWrapper."<init>":(Lorg/apache/dubbo/metrics/model/key/MetricsKey;Lorg/apache/dubbo/metrics/model/key/MetricsPlaceValue;)V
      24: invokespecial #12                 // Method org/apache/dubbo/metrics/model/container/AtomicLongContainer."<init>":(Lorg/apache/dubbo/metrics/model/key/MetricsKeyWrapper;)V
      27: invokeinterface #13,  2           // InterfaceMethod java/util/List.add:(Ljava/lang/Object;)Z
      32: pop
      33: aload_2
      34: new           #14                 // class org/apache/dubbo/metrics/model/container/LongAccumulatorContainer
      37: dup
      38: new           #9                  // class org/apache/dubbo/metrics/model/key/MetricsKeyWrapper
      41: dup
      42: getstatic     #15                 // Field org/apache/dubbo/metrics/model/key/MetricsKey.METRIC_RT_MIN:Lorg/apache/dubbo/metrics/model/key/MetricsKey;
      45: aload_1
      46: invokespecial #11                 // Method org/apache/dubbo/metrics/model/key/MetricsKeyWrapper."<init>":(Lorg/apache/dubbo/metrics/model/key/MetricsKey;Lorg/apache/dubbo/metrics/model/key/MetricsPlaceValue;)V
      49: new           #16                 // class java/util/concurrent/atomic/LongAccumulator
      52: dup
      53: invokedynamic #17,  0             // InvokeDynamic #1:applyAsLong:()Ljava/util/function/LongBinaryOperator;
      58: ldc2_w        #19                 // long 9223372036854775807l
      61: invokespecial #21                 // Method java/util/concurrent/atomic/LongAccumulator."<init>":(Ljava/util/function/LongBinaryOperator;J)V
      64: invokespecial #22                 // Method org/apache/dubbo/metrics/model/container/LongAccumulatorContainer."<init>":(Lorg/apache/dubbo/metrics/model/key/MetricsKeyWrapper;Ljava/util/concurrent/atomic/LongAccumulator;)V
      67: invokeinterface #13,  2           // InterfaceMethod java/util/List.add:(Ljava/lang/Object;)Z
      72: pop
      73: aload_2
      74: new           #14                 // class org/apache/dubbo/metrics/model/container/LongAccumulatorContainer
      77: dup
      78: new           #9                  // class org/apache/dubbo/metrics/model/key/MetricsKeyWrapper
      81: dup
      82: getstatic     #23                 // Field org/apache/dubbo/metrics/model/key/MetricsKey.METRIC_RT_MAX:Lorg/apache/dubbo/metrics/model/key/MetricsKey;
      85: aload_1
      86: invokespecial #11                 // Method org/apache/dubbo/metrics/model/key/MetricsKeyWrapper."<init>":(Lorg/apache/dubbo/metrics/model/key/MetricsKey;Lorg/apache/dubbo/metrics/model/key/MetricsPlaceValue;)V
      89: new           #16                 // class java/util/concurrent/atomic/LongAccumulator
      92: dup
      93: invokedynamic #24,  0             // InvokeDynamic #2:applyAsLong:()Ljava/util/function/LongBinaryOperator;
      98: ldc2_w        #25                 // long -9223372036854775808l
     101: invokespecial #21                 // Method java/util/concurrent/atomic/LongAccumulator."<init>":(Ljava/util/function/LongBinaryOperator;J)V
     104: invokespecial #22                 // Method org/apache/dubbo/metrics/model/container/LongAccumulatorContainer."<init>":(Lorg/apache/dubbo/metrics/model/key/MetricsKeyWrapper;Ljava/util/concurrent/atomic/LongAccumulator;)V
     107: invokeinterface #13,  2           // InterfaceMethod java/util/List.add:(Ljava/lang/Object;)Z
     112: pop
     113: aload_2
     114: new           #8                  // class org/apache/dubbo/metrics/model/container/AtomicLongContainer
     117: dup
     118: new           #9                  // class org/apache/dubbo/metrics/model/key/MetricsKeyWrapper
     121: dup
     122: getstatic     #27                 // Field org/apache/dubbo/metrics/model/key/MetricsKey.METRIC_RT_SUM:Lorg/apache/dubbo/metrics/model/key/MetricsKey;
     125: aload_1
     126: invokespecial #11                 // Method org/apache/dubbo/metrics/model/key/MetricsKeyWrapper."<init>":(Lorg/apache/dubbo/metrics/model/key/MetricsKey;Lorg/apache/dubbo/metrics/model/key/MetricsPlaceValue;)V
     129: invokedynamic #28,  0             // InvokeDynamic #3:accept:()Ljava/util/function/BiConsumer;
     134: invokespecial #29                 // Method org/apache/dubbo/metrics/model/container/AtomicLongContainer."<init>":(Lorg/apache/dubbo/metrics/model/key/MetricsKeyWrapper;Ljava/util/function/BiConsumer;)V
     137: invokeinterface #13,  2           // InterfaceMethod java/util/List.add:(Ljava/lang/Object;)Z
     142: pop
     143: new           #8                  // class org/apache/dubbo/metrics/model/container/AtomicLongContainer
     146: dup
     147: new           #9                  // class org/apache/dubbo/metrics/model/key/MetricsKeyWrapper
     150: dup
     151: getstatic     #30                 // Field org/apache/dubbo/metrics/model/key/MetricsKey.METRIC_RT_AVG:Lorg/apache/dubbo/metrics/model/key/MetricsKey;
     154: aload_1
     155: invokespecial #11                 // Method org/apache/dubbo/metrics/model/key/MetricsKeyWrapper."<init>":(Lorg/apache/dubbo/metrics/model/key/MetricsKey;Lorg/apache/dubbo/metrics/model/key/MetricsPlaceValue;)V
     158: invokedynamic #31,  0             // InvokeDynamic #4:accept:()Ljava/util/function/BiConsumer;
     163: invokespecial #29                 // Method org/apache/dubbo/metrics/model/container/AtomicLongContainer."<init>":(Lorg/apache/dubbo/metrics/model/key/MetricsKeyWrapper;Ljava/util/function/BiConsumer;)V
     166: astore_3
     167: aload_3
     168: aload_0
     169: aload_1
     170: aload_3
     171: invokedynamic #32,  0             // InvokeDynamic #5:apply:(Lorg/apache/dubbo/metrics/data/RtStatComposite;Lorg/apache/dubbo/metrics/model/key/MetricsPlaceValue;Lorg/apache/dubbo/metrics/model/container/AtomicLongContainer;)Ljava/util/function/Function;
     176: invokevirtual #33                 // Method org/apache/dubbo/metrics/model/container/AtomicLongContainer.setValueSupplier:(Ljava/util/function/Function;)V
     179: aload_2
     180: aload_3
     181: invokeinterface #13,  2           // InterfaceMethod java/util/List.add:(Ljava/lang/Object;)Z
     186: pop
     187: aload_2
     188: areturn

  public void calcApplicationRt(java.lang.String, java.lang.Long);
    Code:
       0: aload_0
       1: getfield      #4                  // Field rtStats:Ljava/util/List;
       4: invokeinterface #34,  1           // InterfaceMethod java/util/List.stream:()Ljava/util/stream/Stream;
       9: aload_1
      10: invokedynamic #35,  0             // InvokeDynamic #6:test:(Ljava/lang/String;)Ljava/util/function/Predicate;
      15: invokeinterface #36,  2           // InterfaceMethod java/util/stream/Stream.filter:(Ljava/util/function/Predicate;)Ljava/util/stream/Stream;
      20: invokestatic  #37                 // Method java/util/stream/Collectors.toList:()Ljava/util/stream/Collector;
      23: invokeinterface #38,  2           // InterfaceMethod java/util/stream/Stream.collect:(Ljava/util/stream/Collector;)Ljava/lang/Object;
      28: checkcast     #39                 // class java/util/List
      31: invokeinterface #40,  1           // InterfaceMethod java/util/List.iterator:()Ljava/util/Iterator;
      36: astore_3
      37: aload_3
      38: invokeinterface #41,  1           // InterfaceMethod java/util/Iterator.hasNext:()Z
      43: ifeq          92
      46: aload_3
      47: invokeinterface #42,  1           // InterfaceMethod java/util/Iterator.next:()Ljava/lang/Object;
      52: checkcast     #43                 // class org/apache/dubbo/metrics/model/container/LongContainer
      55: astore        4
      57: aload         4
      59: aload_0
      60: invokevirtual #44                 // Method getAppName:()Ljava/lang/String;
      63: aload         4
      65: invokevirtual #45                 // Method org/apache/dubbo/metrics/model/container/LongContainer.getInitFunc:()Ljava/util/function/Function;
      68: invokestatic  #46                 // Method org/apache/dubbo/common/utils/ConcurrentHashMapUtils.computeIfAbsent:(Ljava/util/concurrent/ConcurrentMap;Ljava/lang/Object;Ljava/util/function/Function;)Ljava/lang/Object;
      71: checkcast     #47                 // class java/lang/Number
      74: astore        5
      76: aload         4
      78: invokevirtual #48                 // Method org/apache/dubbo/metrics/model/container/LongContainer.getConsumerFunc:()Ljava/util/function/BiConsumer;
      81: aload_2
      82: aload         5
      84: invokeinterface #49,  3           // InterfaceMethod java/util/function/BiConsumer.accept:(Ljava/lang/Object;Ljava/lang/Object;)V
      89: goto          37
      92: return

  public void calcServiceKeyRt(java.lang.String, java.lang.String, java.lang.Long);
    Code:
       0: aload_0
       1: getfield      #4                  // Field rtStats:Ljava/util/List;
       4: invokeinterface #34,  1           // InterfaceMethod java/util/List.stream:()Ljava/util/stream/Stream;
       9: aload_2
      10: invokedynamic #50,  0             // InvokeDynamic #7:test:(Ljava/lang/String;)Ljava/util/function/Predicate;
      15: invokeinterface #36,  2           // InterfaceMethod java/util/stream/Stream.filter:(Ljava/util/function/Predicate;)Ljava/util/stream/Stream;
      20: invokestatic  #37                 // Method java/util/stream/Collectors.toList:()Ljava/util/stream/Collector;
      23: invokeinterface #38,  2           // InterfaceMethod java/util/stream/Stream.collect:(Ljava/util/stream/Collector;)Ljava/lang/Object;
      28: checkcast     #39                 // class java/util/List
      31: invokeinterface #40,  1           // InterfaceMethod java/util/List.iterator:()Ljava/util/Iterator;
      36: astore        4
      38: aload         4
      40: invokeinterface #41,  1           // InterfaceMethod java/util/Iterator.hasNext:()Z
      45: ifeq          92
      48: aload         4
      50: invokeinterface #42,  1           // InterfaceMethod java/util/Iterator.next:()Ljava/lang/Object;
      55: checkcast     #43                 // class org/apache/dubbo/metrics/model/container/LongContainer
      58: astore        5
      60: aload         5
      62: aload_1
      63: aload         5
      65: invokevirtual #45                 // Method org/apache/dubbo/metrics/model/container/LongContainer.getInitFunc:()Ljava/util/function/Function;
      68: invokestatic  #46                 // Method org/apache/dubbo/common/utils/ConcurrentHashMapUtils.computeIfAbsent:(Ljava/util/concurrent/ConcurrentMap;Ljava/lang/Object;Ljava/util/function/Function;)Ljava/lang/Object;
      71: checkcast     #47                 // class java/lang/Number
      74: astore        6
      76: aload         5
      78: invokevirtual #48                 // Method org/apache/dubbo/metrics/model/container/LongContainer.getConsumerFunc:()Ljava/util/function/BiConsumer;
      81: aload_3
      82: aload         6
      84: invokeinterface #49,  3           // InterfaceMethod java/util/function/BiConsumer.accept:(Ljava/lang/Object;Ljava/lang/Object;)V
      89: goto          38
      92: return

  public void calcMethodKeyRt(org.apache.dubbo.rpc.Invocation, java.lang.String, java.lang.Long);
    Code:
       0: aload_0
       1: getfield      #4                  // Field rtStats:Ljava/util/List;
       4: invokeinterface #34,  1           // InterfaceMethod java/util/List.stream:()Ljava/util/stream/Stream;
       9: aload_2
      10: invokedynamic #51,  0             // InvokeDynamic #8:test:(Ljava/lang/String;)Ljava/util/function/Predicate;
      15: invokeinterface #36,  2           // InterfaceMethod java/util/stream/Stream.filter:(Ljava/util/function/Predicate;)Ljava/util/stream/Stream;
      20: invokestatic  #37                 // Method java/util/stream/Collectors.toList:()Ljava/util/stream/Collector;
      23: invokeinterface #38,  2           // InterfaceMethod java/util/stream/Stream.collect:(Ljava/util/stream/Collector;)Ljava/lang/Object;
      28: checkcast     #39                 // class java/util/List
      31: invokeinterface #40,  1           // InterfaceMethod java/util/List.iterator:()Ljava/util/Iterator;
      36: astore        4
      38: aload         4
      40: invokeinterface #41,  1           // InterfaceMethod java/util/Iterator.hasNext:()Z
      45: ifeq          124
      48: aload         4
      50: invokeinterface #42,  1           // InterfaceMethod java/util/Iterator.next:()Ljava/lang/Object;
      55: checkcast     #43                 // class org/apache/dubbo/metrics/model/container/LongContainer
      58: astore        5
      60: aload         5
      62: new           #52                 // class java/lang/StringBuilder
      65: dup
      66: invokespecial #53                 // Method java/lang/StringBuilder."<init>":()V
      69: aload_1
      70: invokeinterface #54,  1           // InterfaceMethod org/apache/dubbo/rpc/Invocation.getServiceName:()Ljava/lang/String;
      75: invokevirtual #55                 // Method java/lang/StringBuilder.append:(Ljava/lang/String;)Ljava/lang/StringBuilder;
      78: ldc           #56                 // String _
      80: invokevirtual #55                 // Method java/lang/StringBuilder.append:(Ljava/lang/String;)Ljava/lang/StringBuilder;
      83: aload_1
      84: invokeinterface #57,  1           // InterfaceMethod org/apache/dubbo/rpc/Invocation.getMethodName:()Ljava/lang/String;
      89: invokevirtual #55                 // Method java/lang/StringBuilder.append:(Ljava/lang/String;)Ljava/lang/StringBuilder;
      92: invokevirtual #58                 // Method java/lang/StringBuilder.toString:()Ljava/lang/String;
      95: aload         5
      97: invokevirtual #45                 // Method org/apache/dubbo/metrics/model/container/LongContainer.getInitFunc:()Ljava/util/function/Function;
     100: invokestatic  #46                 // Method org/apache/dubbo/common/utils/ConcurrentHashMapUtils.computeIfAbsent:(Ljava/util/concurrent/ConcurrentMap;Ljava/lang/Object;Ljava/util/function/Function;)Ljava/lang/Object;
     103: checkcast     #47                 // class java/lang/Number
     106: astore        6
     108: aload         5
     110: invokevirtual #48                 // Method org/apache/dubbo/metrics/model/container/LongContainer.getConsumerFunc:()Ljava/util/function/BiConsumer;
     113: aload_3
     114: aload         6
     116: invokeinterface #49,  3           // InterfaceMethod java/util/function/BiConsumer.accept:(Ljava/lang/Object;Ljava/lang/Object;)V
     121: goto          38
     124: return

  public java.util.List<org.apache.dubbo.metrics.model.sample.MetricSample> export(org.apache.dubbo.metrics.model.MetricsCategory);
    Code:
       0: new           #2                  // class java/util/ArrayList
       3: dup
       4: invokespecial #3                  // Method java/util/ArrayList."<init>":()V
       7: astore_2
       8: aload_0
       9: getfield      #4                  // Field rtStats:Ljava/util/List;
      12: invokeinterface #40,  1           // InterfaceMethod java/util/List.iterator:()Ljava/util/Iterator;
      17: astore_3
      18: aload_3
      19: invokeinterface #41,  1           // InterfaceMethod java/util/Iterator.hasNext:()Z
      24: ifeq          149
      27: aload_3
      28: invokeinterface #42,  1           // InterfaceMethod java/util/Iterator.next:()Ljava/lang/Object;
      33: checkcast     #43                 // class org/apache/dubbo/metrics/model/container/LongContainer
      36: astore        4
      38: aload         4
      40: invokevirtual #59                 // Method org/apache/dubbo/metrics/model/container/LongContainer.getMetricsKeyWrapper:()Lorg/apache/dubbo/metrics/model/key/MetricsKeyWrapper;
      43: astore        5
      45: aload         4
      47: invokevirtual #60                 // Method org/apache/dubbo/metrics/model/container/LongContainer.entrySet:()Ljava/util/Set;
      50: invokeinterface #61,  1           // InterfaceMethod java/util/Set.iterator:()Ljava/util/Iterator;
      55: astore        6
      57: aload         6
      59: invokeinterface #41,  1           // InterfaceMethod java/util/Iterator.hasNext:()Z
      64: ifeq          146
      67: aload         6
      69: invokeinterface #42,  1           // InterfaceMethod java/util/Iterator.next:()Ljava/lang/Object;
      74: checkcast     #62                 // class java/util/Map$Entry
      77: astore        7
      79: aload_2
      80: new           #63                 // class org/apache/dubbo/metrics/model/sample/GaugeMetricSample
      83: dup
      84: aload         5
      86: invokevirtual #64                 // Method org/apache/dubbo/metrics/model/key/MetricsKeyWrapper.targetKey:()Ljava/lang/String;
      89: aload         5
      91: invokevirtual #65                 // Method org/apache/dubbo/metrics/model/key/MetricsKeyWrapper.targetDesc:()Ljava/lang/String;
      94: aload         5
      96: aload_0
      97: invokevirtual #66                 // Method getApplicationModel:()Lorg/apache/dubbo/rpc/model/ApplicationModel;
     100: aload         7
     102: invokeinterface #67,  1           // InterfaceMethod java/util/Map$Entry.getKey:()Ljava/lang/Object;
     107: checkcast     #68                 // class java/lang/String
     110: invokevirtual #69                 // Method org/apache/dubbo/metrics/model/key/MetricsKeyWrapper.tagName:(Lorg/apache/dubbo/rpc/model/ApplicationModel;Ljava/lang/String;)Ljava/util/Map;
     113: aload_1
     114: aload         7
     116: invokeinterface #67,  1           // InterfaceMethod java/util/Map$Entry.getKey:()Ljava/lang/Object;
     121: checkcast     #68                 // class java/lang/String
     124: invokevirtual #70                 // Method java/lang/String.intern:()Ljava/lang/String;
     127: aload         4
     129: invokedynamic #71,  0             // InvokeDynamic #9:applyAsDouble:(Lorg/apache/dubbo/metrics/model/container/LongContainer;)Ljava/util/function/ToDoubleFunction;
     134: invokespecial #72                 // Method org/apache/dubbo/metrics/model/sample/GaugeMetricSample."<init>":(Ljava/lang/String;Ljava/lang/String;Ljava/util/Map;Lorg/apache/dubbo/metrics/model/MetricsCategory;Ljava/lang/Object;Ljava/util/function/ToDoubleFunction;)V
     137: invokeinterface #13,  2           // InterfaceMethod java/util/List.add:(Ljava/lang/Object;)Z
     142: pop
     143: goto          57
     146: goto          18
     149: aload_2
     150: areturn

  public java.util.List<org.apache.dubbo.metrics.model.container.LongContainer<? extends java.lang.Number>> getRtStats();
    Code:
       0: aload_0
       1: getfield      #4                  // Field rtStats:Ljava/util/List;
       4: areturn

  private static double lambda$export$8(org.apache.dubbo.metrics.model.container.LongContainer, java.lang.String);
    Code:
       0: aload_0
       1: invokevirtual #73                 // Method org/apache/dubbo/metrics/model/container/LongContainer.getValueSupplier:()Ljava/util/function/Function;
       4: aload_1
       5: invokevirtual #70                 // Method java/lang/String.intern:()Ljava/lang/String;
       8: invokeinterface #74,  2           // InterfaceMethod java/util/function/Function.apply:(Ljava/lang/Object;)Ljava/lang/Object;
      13: checkcast     #18                 // class java/lang/Long
      16: invokevirtual #75                 // Method java/lang/Long.longValue:()J
      19: l2d
      20: dreturn

  private static boolean lambda$calcMethodKeyRt$7(java.lang.String, org.apache.dubbo.metrics.model.container.LongContainer);
    Code:
       0: aload_1
       1: aload_0
       2: invokevirtual #76                 // Method org/apache/dubbo/metrics/model/container/LongContainer.specifyType:(Ljava/lang/String;)Z
       5: ireturn

  private static boolean lambda$calcServiceKeyRt$6(java.lang.String, org.apache.dubbo.metrics.model.container.LongContainer);
    Code:
       0: aload_1
       1: aload_0
       2: invokevirtual #76                 // Method org/apache/dubbo/metrics/model/container/LongContainer.specifyType:(Ljava/lang/String;)Z
       5: ireturn

  private static boolean lambda$calcApplicationRt$5(java.lang.String, org.apache.dubbo.metrics.model.container.LongContainer);
    Code:
       0: aload_1
       1: aload_0
       2: invokevirtual #76                 // Method org/apache/dubbo/metrics/model/container/LongContainer.specifyType:(Ljava/lang/String;)Z
       5: ireturn

  private java.lang.Long lambda$initStats$4(org.apache.dubbo.metrics.model.key.MetricsPlaceValue, org.apache.dubbo.metrics.model.container.AtomicLongContainer, java.lang.String);
    Code:
       0: aload_0
       1: getfield      #4                  // Field rtStats:Ljava/util/List;
       4: invokeinterface #34,  1           // InterfaceMethod java/util/List.stream:()Ljava/util/stream/Stream;
       9: aload_1
      10: invokedynamic #77,  0             // InvokeDynamic #10:test:(Lorg/apache/dubbo/metrics/model/key/MetricsPlaceValue;)Ljava/util/function/Predicate;
      15: invokeinterface #36,  2           // InterfaceMethod java/util/stream/Stream.filter:(Ljava/util/function/Predicate;)Ljava/util/stream/Stream;
      20: invokeinterface #78,  1           // InterfaceMethod java/util/stream/Stream.findFirst:()Ljava/util/Optional;
      25: invokevirtual #79                 // Method java/util/Optional.get:()Ljava/lang/Object;
      28: checkcast     #43                 // class org/apache/dubbo/metrics/model/container/LongContainer
      31: astore        4
      33: aload_2
      34: aload_3
      35: invokevirtual #80                 // Method org/apache/dubbo/metrics/model/container/AtomicLongContainer.get:(Ljava/lang/Object;)Ljava/lang/Object;
      38: checkcast     #81                 // class java/util/concurrent/atomic/AtomicLong
      41: astore        5
      43: aload         4
      45: aload_3
      46: invokevirtual #82                 // Method org/apache/dubbo/metrics/model/container/LongContainer.get:(Ljava/lang/Object;)Ljava/lang/Object;
      49: checkcast     #81                 // class java/util/concurrent/atomic/AtomicLong
      52: astore        6
      54: aload         6
      56: invokevirtual #83                 // Method java/util/concurrent/atomic/AtomicLong.get:()J
      59: aload         5
      61: invokevirtual #83                 // Method java/util/concurrent/atomic/AtomicLong.get:()J
      64: ldiv
      65: invokestatic  #84                 // Method java/lang/Long.valueOf:(J)Ljava/lang/Long;
      68: areturn

  private static boolean lambda$null$3(org.apache.dubbo.metrics.model.key.MetricsPlaceValue, org.apache.dubbo.metrics.model.container.LongContainer);
    Code:
       0: aload_1
       1: getstatic     #27                 // Field org/apache/dubbo/metrics/model/key/MetricsKey.METRIC_RT_SUM:Lorg/apache/dubbo/metrics/model/key/MetricsKey;
       4: aload_0
       5: invokevirtual #85                 // Method org/apache/dubbo/metrics/model/key/MetricsPlaceValue.getType:()Ljava/lang/String;
       8: invokevirtual #86                 // Method org/apache/dubbo/metrics/model/container/LongContainer.isKeyWrapper:(Lorg/apache/dubbo/metrics/model/key/MetricsKey;Ljava/lang/String;)Z
      11: ireturn

  private static void lambda$initStats$2(java.lang.Long, java.util.concurrent.atomic.AtomicLong);
    Code:
       0: aload_1
       1: invokevirtual #87                 // Method java/util/concurrent/atomic/AtomicLong.incrementAndGet:()J
       4: pop2
       5: return

  private static void lambda$initStats$1(java.lang.Long, java.util.concurrent.atomic.AtomicLong);
    Code:
       0: aload_1
       1: aload_0
       2: invokevirtual #75                 // Method java/lang/Long.longValue:()J
       5: invokevirtual #88                 // Method java/util/concurrent/atomic/AtomicLong.addAndGet:(J)J
       8: pop2
       9: return

  private void lambda$init$0(org.apache.dubbo.metrics.model.key.MetricsPlaceValue);
    Code:
       0: aload_0
       1: getfield      #4                  // Field rtStats:Ljava/util/List;
       4: aload_0
       5: aload_1
       6: invokespecial #89                 // Method initStats:(Lorg/apache/dubbo/metrics/model/key/MetricsPlaceValue;)Ljava/util/List;
       9: invokeinterface #90,  2           // InterfaceMethod java/util/List.addAll:(Ljava/util/Collection;)Z
      14: pop
      15: return
}
