Compiled from "ServiceStatComposite.java"
public class org.apache.dubbo.metrics.data.ServiceStatComposite extends org.apache.dubbo.metrics.report.AbstractMetricsExport {
  private final java.util.Map<org.apache.dubbo.metrics.model.key.MetricsKeyWrapper, java.util.Map<org.apache.dubbo.metrics.model.ServiceKeyMetric, java.util.concurrent.atomic.AtomicLong>> serviceWrapperNumStats;

  public org.apache.dubbo.metrics.data.ServiceStatComposite(org.apache.dubbo.rpc.model.ApplicationModel);
    Code:
       0: aload_0
       1: aload_1
       2: invokespecial #1                  // Method org/apache/dubbo/metrics/report/AbstractMetricsExport."<init>":(Lorg/apache/dubbo/rpc/model/ApplicationModel;)V
       5: aload_0
       6: new           #2                  // class java/util/concurrent/ConcurrentHashMap
       9: dup
      10: invokespecial #3                  // Method java/util/concurrent/ConcurrentHashMap."<init>":()V
      13: putfield      #4                  // Field serviceWrapperNumStats:Ljava/util/Map;
      16: return

  public void initWrapper(java.util.List<org.apache.dubbo.metrics.model.key.MetricsKeyWrapper>);
    Code:
       0: aload_1
       1: invokestatic  #5                  // Method org/apache/dubbo/common/utils/CollectionUtils.isEmpty:(Ljava/util/Collection;)Z
       4: ifeq          8
       7: return
       8: aload_1
       9: aload_0
      10: invokedynamic #6,  0              // InvokeDynamic #0:accept:(Lorg/apache/dubbo/metrics/data/ServiceStatComposite;)Ljava/util/function/Consumer;
      15: invokeinterface #7,  2            // InterfaceMethod java/util/List.forEach:(Ljava/util/function/Consumer;)V
      20: return

  public void incrementServiceKey(org.apache.dubbo.metrics.model.key.MetricsKeyWrapper, java.lang.String, int);
    Code:
       0: aload_0
       1: getfield      #4                  // Field serviceWrapperNumStats:Ljava/util/Map;
       4: aload_1
       5: invokeinterface #8,  2            // InterfaceMethod java/util/Map.containsKey:(Ljava/lang/Object;)Z
      10: ifne          14
      13: return
      14: aload_0
      15: getfield      #4                  // Field serviceWrapperNumStats:Ljava/util/Map;
      18: aload_1
      19: invokeinterface #9,  2            // InterfaceMethod java/util/Map.get:(Ljava/lang/Object;)Ljava/lang/Object;
      24: checkcast     #10                 // class java/util/Map
      27: new           #11                 // class org/apache/dubbo/metrics/model/ServiceKeyMetric
      30: dup
      31: aload_0
      32: invokevirtual #12                 // Method getApplicationModel:()Lorg/apache/dubbo/rpc/model/ApplicationModel;
      35: aload_2
      36: invokespecial #13                 // Method org/apache/dubbo/metrics/model/ServiceKeyMetric."<init>":(Lorg/apache/dubbo/rpc/model/ApplicationModel;Ljava/lang/String;)V
      39: invokedynamic #14,  0             // InvokeDynamic #1:apply:()Ljava/util/function/Function;
      44: invokeinterface #15,  3           // InterfaceMethod java/util/Map.computeIfAbsent:(Ljava/lang/Object;Ljava/util/function/Function;)Ljava/lang/Object;
      49: checkcast     #16                 // class java/util/concurrent/atomic/AtomicLong
      52: iload_3
      53: i2l
      54: invokevirtual #17                 // Method java/util/concurrent/atomic/AtomicLong.getAndAdd:(J)J
      57: pop2
      58: return

  public void setServiceKey(org.apache.dubbo.metrics.model.key.MetricsKeyWrapper, java.lang.String, int);
    Code:
       0: aload_0
       1: getfield      #4                  // Field serviceWrapperNumStats:Ljava/util/Map;
       4: aload_1
       5: invokeinterface #8,  2            // InterfaceMethod java/util/Map.containsKey:(Ljava/lang/Object;)Z
      10: ifne          14
      13: return
      14: aload_0
      15: getfield      #4                  // Field serviceWrapperNumStats:Ljava/util/Map;
      18: aload_1
      19: invokeinterface #9,  2            // InterfaceMethod java/util/Map.get:(Ljava/lang/Object;)Ljava/lang/Object;
      24: checkcast     #10                 // class java/util/Map
      27: new           #11                 // class org/apache/dubbo/metrics/model/ServiceKeyMetric
      30: dup
      31: aload_0
      32: invokevirtual #12                 // Method getApplicationModel:()Lorg/apache/dubbo/rpc/model/ApplicationModel;
      35: aload_2
      36: invokespecial #13                 // Method org/apache/dubbo/metrics/model/ServiceKeyMetric."<init>":(Lorg/apache/dubbo/rpc/model/ApplicationModel;Ljava/lang/String;)V
      39: invokedynamic #18,  0             // InvokeDynamic #2:apply:()Ljava/util/function/Function;
      44: invokeinterface #15,  3           // InterfaceMethod java/util/Map.computeIfAbsent:(Ljava/lang/Object;Ljava/util/function/Function;)Ljava/lang/Object;
      49: checkcast     #16                 // class java/util/concurrent/atomic/AtomicLong
      52: iload_3
      53: i2l
      54: invokevirtual #19                 // Method java/util/concurrent/atomic/AtomicLong.set:(J)V
      57: return

  public java.util.List<org.apache.dubbo.metrics.model.sample.MetricSample> export(org.apache.dubbo.metrics.model.MetricsCategory);
    Code:
       0: new           #20                 // class java/util/ArrayList
       3: dup
       4: invokespecial #21                 // Method java/util/ArrayList."<init>":()V
       7: astore_2
       8: aload_0
       9: getfield      #4                  // Field serviceWrapperNumStats:Ljava/util/Map;
      12: invokeinterface #22,  1           // InterfaceMethod java/util/Map.keySet:()Ljava/util/Set;
      17: invokeinterface #23,  1           // InterfaceMethod java/util/Set.iterator:()Ljava/util/Iterator;
      22: astore_3
      23: aload_3
      24: invokeinterface #24,  1           // InterfaceMethod java/util/Iterator.hasNext:()Z
      29: ifeq          132
      32: aload_3
      33: invokeinterface #25,  1           // InterfaceMethod java/util/Iterator.next:()Ljava/lang/Object;
      38: checkcast     #26                 // class org/apache/dubbo/metrics/model/key/MetricsKeyWrapper
      41: astore        4
      43: aload_0
      44: getfield      #4                  // Field serviceWrapperNumStats:Ljava/util/Map;
      47: aload         4
      49: invokeinterface #9,  2            // InterfaceMethod java/util/Map.get:(Ljava/lang/Object;)Ljava/lang/Object;
      54: checkcast     #10                 // class java/util/Map
      57: astore        5
      59: aload         5
      61: invokeinterface #22,  1           // InterfaceMethod java/util/Map.keySet:()Ljava/util/Set;
      66: invokeinterface #23,  1           // InterfaceMethod java/util/Set.iterator:()Ljava/util/Iterator;
      71: astore        6
      73: aload         6
      75: invokeinterface #24,  1           // InterfaceMethod java/util/Iterator.hasNext:()Z
      80: ifeq          129
      83: aload         6
      85: invokeinterface #25,  1           // InterfaceMethod java/util/Iterator.next:()Ljava/lang/Object;
      90: checkcast     #11                 // class org/apache/dubbo/metrics/model/ServiceKeyMetric
      93: astore        7
      95: aload_2
      96: new           #27                 // class org/apache/dubbo/metrics/model/sample/GaugeMetricSample
      99: dup
     100: aload         4
     102: aload         7
     104: invokevirtual #28                 // Method org/apache/dubbo/metrics/model/ServiceKeyMetric.getTags:()Ljava/util/Map;
     107: aload_1
     108: aload         5
     110: aload         7
     112: invokedynamic #29,  0             // InvokeDynamic #3:applyAsDouble:(Lorg/apache/dubbo/metrics/model/ServiceKeyMetric;)Ljava/util/function/ToDoubleFunction;
     117: invokespecial #30                 // Method org/apache/dubbo/metrics/model/sample/GaugeMetricSample."<init>":(Lorg/apache/dubbo/metrics/model/key/MetricsKeyWrapper;Ljava/util/Map;Lorg/apache/dubbo/metrics/model/MetricsCategory;Ljava/lang/Object;Ljava/util/function/ToDoubleFunction;)V
     120: invokeinterface #31,  2           // InterfaceMethod java/util/List.add:(Ljava/lang/Object;)Z
     125: pop
     126: goto          73
     129: goto          23
     132: aload_2
     133: areturn

  private static double lambda$export$3(org.apache.dubbo.metrics.model.ServiceKeyMetric, java.util.Map);
    Code:
       0: aload_1
       1: aload_0
       2: invokeinterface #9,  2            // InterfaceMethod java/util/Map.get:(Ljava/lang/Object;)Ljava/lang/Object;
       7: checkcast     #16                 // class java/util/concurrent/atomic/AtomicLong
      10: invokevirtual #32                 // Method java/util/concurrent/atomic/AtomicLong.get:()J
      13: l2d
      14: dreturn

  private static java.util.concurrent.atomic.AtomicLong lambda$setServiceKey$2(org.apache.dubbo.metrics.model.ServiceKeyMetric);
    Code:
       0: new           #16                 // class java/util/concurrent/atomic/AtomicLong
       3: dup
       4: lconst_0
       5: invokespecial #33                 // Method java/util/concurrent/atomic/AtomicLong."<init>":(J)V
       8: areturn

  private static java.util.concurrent.atomic.AtomicLong lambda$incrementServiceKey$1(org.apache.dubbo.metrics.model.ServiceKeyMetric);
    Code:
       0: new           #16                 // class java/util/concurrent/atomic/AtomicLong
       3: dup
       4: lconst_0
       5: invokespecial #33                 // Method java/util/concurrent/atomic/AtomicLong."<init>":(J)V
       8: areturn

  private void lambda$initWrapper$0(org.apache.dubbo.metrics.model.key.MetricsKeyWrapper);
    Code:
       0: aload_0
       1: getfield      #4                  // Field serviceWrapperNumStats:Ljava/util/Map;
       4: aload_1
       5: new           #2                  // class java/util/concurrent/ConcurrentHashMap
       8: dup
       9: invokespecial #3                  // Method java/util/concurrent/ConcurrentHashMap."<init>":()V
      12: invokeinterface #34,  3           // InterfaceMethod java/util/Map.put:(Ljava/lang/Object;Ljava/lang/Object;)Ljava/lang/Object;
      17: checkcast     #10                 // class java/util/Map
      20: pop
      21: return
}
