Compiled from "AliasKeyManagerFactory.java"
final class org.springframework.boot.ssl.AliasKeyManagerFactory extends javax.net.ssl.KeyManagerFactory {
  org.springframework.boot.ssl.AliasKeyManagerFactory(javax.net.ssl.KeyManagerFactory, java.lang.String, java.lang.String);
    Code:
       0: aload_0
       1: new           #1                  // class org/springframework/boot/ssl/AliasKeyManagerFactory$AliasKeyManagerFactorySpi
       4: dup
       5: aload_1
       6: aload_2
       7: invokespecial #3                  // Method org/springframework/boot/ssl/AliasKeyManagerFactory$AliasKeyManagerFactorySpi."<init>":(Ljavax/net/ssl/KeyManagerFactory;Ljava/lang/String;)V
      10: aload_1
      11: invokevirtual #7                  // Method javax/net/ssl/KeyManagerFactory.getProvider:()Ljava/security/Provider;
      14: aload_3
      15: invokespecial #13                 // Method javax/net/ssl/KeyManagerFactory."<init>":(Ljavax/net/ssl/KeyManagerFactorySpi;Ljava/security/Provider;Ljava/lang/String;)V
      18: return
}
