Compiled from "AliasKeyManagerFactory.java"
final class org.springframework.boot.ssl.AliasKeyManagerFactory$AliasKeyManagerFactorySpi extends javax.net.ssl.KeyManagerFactorySpi {
  private final javax.net.ssl.KeyManagerFactory delegate;

  private final java.lang.String alias;

  private org.springframework.boot.ssl.AliasKeyManagerFactory$AliasKeyManagerFactorySpi(javax.net.ssl.KeyManagerFactory, java.lang.String);
    Code:
       0: aload_0
       1: invokespecial #1                  // Method javax/net/ssl/KeyManagerFactorySpi."<init>":()V
       4: aload_0
       5: aload_1
       6: putfield      #7                  // Field delegate:Ljavax/net/ssl/KeyManagerFactory;
       9: aload_0
      10: aload_2
      11: putfield      #13                 // Field alias:Ljava/lang/String;
      14: return

  protected void engineInit(java.security.KeyStore, char[]) throws java.security.KeyStoreException, java.security.NoSuchAlgorithmException, java.security.UnrecoverableKeyException;
    Code:
       0: aload_0
       1: getfield      #7                  // Field delegate:Ljavax/net/ssl/KeyManagerFactory;
       4: aload_1
       5: aload_2
       6: invokevirtual #17                 // Method javax/net/ssl/KeyManagerFactory.init:(Ljava/security/KeyStore;[C)V
       9: return

  protected void engineInit(javax.net.ssl.ManagerFactoryParameters) throws java.security.InvalidAlgorithmParameterException;
    Code:
       0: new           #23                 // class java/security/InvalidAlgorithmParameterException
       3: dup
       4: ldc           #25                 // String Unsupported ManagerFactoryParameters
       6: invokespecial #27                 // Method java/security/InvalidAlgorithmParameterException."<init>":(Ljava/lang/String;)V
       9: athrow

  protected javax.net.ssl.KeyManager[] engineGetKeyManagers();
    Code:
       0: aload_0
       1: getfield      #7                  // Field delegate:Ljavax/net/ssl/KeyManagerFactory;
       4: invokevirtual #30                 // Method javax/net/ssl/KeyManagerFactory.getKeyManagers:()[Ljavax/net/ssl/KeyManager;
       7: invokestatic  #34                 // Method java/util/Arrays.stream:([Ljava/lang/Object;)Ljava/util/stream/Stream;
      10: ldc           #40                 // class javax/net/ssl/X509ExtendedKeyManager
      12: dup
      13: invokestatic  #42                 // Method java/util/Objects.requireNonNull:(Ljava/lang/Object;)Ljava/lang/Object;
      16: pop
      17: invokedynamic #48,  0             // InvokeDynamic #0:test:(Ljava/lang/Class;)Ljava/util/function/Predicate;
      22: invokeinterface #52,  2           // InterfaceMethod java/util/stream/Stream.filter:(Ljava/util/function/Predicate;)Ljava/util/stream/Stream;
      27: ldc           #40                 // class javax/net/ssl/X509ExtendedKeyManager
      29: dup
      30: invokestatic  #42                 // Method java/util/Objects.requireNonNull:(Ljava/lang/Object;)Ljava/lang/Object;
      33: pop
      34: invokedynamic #58,  0             // InvokeDynamic #1:apply:(Ljava/lang/Class;)Ljava/util/function/Function;
      39: invokeinterface #62,  2           // InterfaceMethod java/util/stream/Stream.map:(Ljava/util/function/Function;)Ljava/util/stream/Stream;
      44: aload_0
      45: invokedynamic #66,  0             // InvokeDynamic #2:apply:(Lorg/springframework/boot/ssl/AliasKeyManagerFactory$AliasKeyManagerFactorySpi;)Ljava/util/function/Function;
      50: invokeinterface #62,  2           // InterfaceMethod java/util/stream/Stream.map:(Ljava/util/function/Function;)Ljava/util/stream/Stream;
      55: invokedynamic #69,  0             // InvokeDynamic #3:apply:()Ljava/util/function/IntFunction;
      60: invokeinterface #72,  2           // InterfaceMethod java/util/stream/Stream.toArray:(Ljava/util/function/IntFunction;)[Ljava/lang/Object;
      65: checkcast     #76                 // class "[Ljavax/net/ssl/KeyManager;"
      68: areturn

  private org.springframework.boot.ssl.AliasKeyManagerFactory$AliasX509ExtendedKeyManager wrap(javax.net.ssl.X509ExtendedKeyManager);
    Code:
       0: new           #78                 // class org/springframework/boot/ssl/AliasKeyManagerFactory$AliasX509ExtendedKeyManager
       3: dup
       4: aload_1
       5: aload_0
       6: getfield      #13                 // Field alias:Ljava/lang/String;
       9: invokespecial #80                 // Method org/springframework/boot/ssl/AliasKeyManagerFactory$AliasX509ExtendedKeyManager."<init>":(Ljavax/net/ssl/X509ExtendedKeyManager;Ljava/lang/String;)V
      12: areturn

  private static javax.net.ssl.KeyManager[] lambda$engineGetKeyManagers$0(int);
    Code:
       0: iload_0
       1: anewarray     #83                 // class javax/net/ssl/KeyManager
       4: areturn
}
