Compiled from "DefaultSslManagerBundle.java"
class org.springframework.boot.ssl.DefaultSslManagerBundle implements org.springframework.boot.ssl.SslManagerBundle {
  private final org.springframework.boot.ssl.SslStoreBundle storeBundle;

  private final org.springframework.boot.ssl.SslBundleKey key;

  org.springframework.boot.ssl.DefaultSslManagerBundle(org.springframework.boot.ssl.SslStoreBundle, org.springframework.boot.ssl.SslBundleKey);
    Code:
       0: aload_0
       1: invokespecial #1                  // Method java/lang/Object."<init>":()V
       4: aload_0
       5: aload_1
       6: ifnull        13
       9: aload_1
      10: goto          16
      13: getstatic     #7                  // Field org/springframework/boot/ssl/SslStoreBundle.NONE:Lorg/springframework/boot/ssl/SslStoreBundle;
      16: putfield      #13                 // Field storeBundle:Lorg/springframework/boot/ssl/SslStoreBundle;
      19: aload_0
      20: aload_2
      21: ifnull        28
      24: aload_2
      25: goto          31
      28: getstatic     #18                 // Field org/springframework/boot/ssl/SslBundleKey.NONE:Lorg/springframework/boot/ssl/SslBundleKey;
      31: putfield      #23                 // Field key:Lorg/springframework/boot/ssl/SslBundleKey;
      34: return

  public javax.net.ssl.KeyManagerFactory getKeyManagerFactory();
    Code:
       0: aload_0
       1: getfield      #13                 // Field storeBundle:Lorg/springframework/boot/ssl/SslStoreBundle;
       4: invokeinterface #26,  1           // InterfaceMethod org/springframework/boot/ssl/SslStoreBundle.getKeyStore:()Ljava/security/KeyStore;
       9: astore_1
      10: aload_0
      11: getfield      #23                 // Field key:Lorg/springframework/boot/ssl/SslBundleKey;
      14: aload_1
      15: invokeinterface #30,  2           // InterfaceMethod org/springframework/boot/ssl/SslBundleKey.assertContainsAlias:(Ljava/security/KeyStore;)V
      20: aload_0
      21: getfield      #23                 // Field key:Lorg/springframework/boot/ssl/SslBundleKey;
      24: invokeinterface #34,  1           // InterfaceMethod org/springframework/boot/ssl/SslBundleKey.getAlias:()Ljava/lang/String;
      29: astore_2
      30: invokestatic  #38                 // Method javax/net/ssl/KeyManagerFactory.getDefaultAlgorithm:()Ljava/lang/String;
      33: astore_3
      34: aload_0
      35: aload_3
      36: invokevirtual #43                 // Method getKeyManagerFactoryInstance:(Ljava/lang/String;)Ljavax/net/ssl/KeyManagerFactory;
      39: astore        4
      41: aload_2
      42: ifnull        59
      45: new           #47                 // class org/springframework/boot/ssl/AliasKeyManagerFactory
      48: dup
      49: aload         4
      51: aload_2
      52: aload_3
      53: invokespecial #49                 // Method org/springframework/boot/ssl/AliasKeyManagerFactory."<init>":(Ljavax/net/ssl/KeyManagerFactory;Ljava/lang/String;Ljava/lang/String;)V
      56: goto          61
      59: aload         4
      61: astore        4
      63: aload_0
      64: getfield      #23                 // Field key:Lorg/springframework/boot/ssl/SslBundleKey;
      67: invokeinterface #52,  1           // InterfaceMethod org/springframework/boot/ssl/SslBundleKey.getPassword:()Ljava/lang/String;
      72: astore        5
      74: aload         5
      76: ifnull        84
      79: aload         5
      81: goto          93
      84: aload_0
      85: getfield      #13                 // Field storeBundle:Lorg/springframework/boot/ssl/SslStoreBundle;
      88: invokeinterface #55,  1           // InterfaceMethod org/springframework/boot/ssl/SslStoreBundle.getKeyStorePassword:()Ljava/lang/String;
      93: astore        5
      95: aload         4
      97: aload_1
      98: aload         5
     100: ifnull        111
     103: aload         5
     105: invokevirtual #58                 // Method java/lang/String.toCharArray:()[C
     108: goto          112
     111: aconst_null
     112: invokevirtual #64                 // Method javax/net/ssl/KeyManagerFactory.init:(Ljava/security/KeyStore;[C)V
     115: aload         4
     117: areturn
     118: astore_1
     119: aload_1
     120: athrow
     121: astore_1
     122: new           #72                 // class java/lang/IllegalStateException
     125: dup
     126: aload_1
     127: invokevirtual #74                 // Method java/lang/Exception.getMessage:()Ljava/lang/String;
     130: invokedynamic #77,  0             // InvokeDynamic #0:makeConcatWithConstants:(Ljava/lang/String;)Ljava/lang/String;
     135: aload_1
     136: invokespecial #81                 // Method java/lang/IllegalStateException."<init>":(Ljava/lang/String;Ljava/lang/Throwable;)V
     139: athrow
    Exception table:
       from    to  target type
           0   117   118   Class java/lang/RuntimeException
           0   117   121   Class java/lang/Exception

  public javax.net.ssl.TrustManagerFactory getTrustManagerFactory();
    Code:
       0: aload_0
       1: getfield      #13                 // Field storeBundle:Lorg/springframework/boot/ssl/SslStoreBundle;
       4: invokeinterface #84,  1           // InterfaceMethod org/springframework/boot/ssl/SslStoreBundle.getTrustStore:()Ljava/security/KeyStore;
       9: astore_1
      10: invokestatic  #87                 // Method javax/net/ssl/TrustManagerFactory.getDefaultAlgorithm:()Ljava/lang/String;
      13: astore_2
      14: aload_0
      15: aload_2
      16: invokevirtual #90                 // Method getTrustManagerFactoryInstance:(Ljava/lang/String;)Ljavax/net/ssl/TrustManagerFactory;
      19: astore_3
      20: aload_3
      21: aload_1
      22: invokevirtual #94                 // Method javax/net/ssl/TrustManagerFactory.init:(Ljava/security/KeyStore;)V
      25: aload_3
      26: areturn
      27: astore_1
      28: new           #72                 // class java/lang/IllegalStateException
      31: dup
      32: aload_1
      33: invokevirtual #74                 // Method java/lang/Exception.getMessage:()Ljava/lang/String;
      36: invokedynamic #96,  0             // InvokeDynamic #1:makeConcatWithConstants:(Ljava/lang/String;)Ljava/lang/String;
      41: aload_1
      42: invokespecial #81                 // Method java/lang/IllegalStateException."<init>":(Ljava/lang/String;Ljava/lang/Throwable;)V
      45: athrow
    Exception table:
       from    to  target type
           0    26    27   Class java/lang/Exception

  protected javax.net.ssl.KeyManagerFactory getKeyManagerFactoryInstance(java.lang.String) throws java.security.NoSuchAlgorithmException;
    Code:
       0: aload_1
       1: invokestatic  #97                 // Method javax/net/ssl/KeyManagerFactory.getInstance:(Ljava/lang/String;)Ljavax/net/ssl/KeyManagerFactory;
       4: areturn

  protected javax.net.ssl.TrustManagerFactory getTrustManagerFactoryInstance(java.lang.String) throws java.security.NoSuchAlgorithmException;
    Code:
       0: aload_1
       1: invokestatic  #100                // Method javax/net/ssl/TrustManagerFactory.getInstance:(Ljava/lang/String;)Ljavax/net/ssl/TrustManagerFactory;
       4: areturn
}
