Compiled from "DefaultSslBundleRegistry.java"
public class org.springframework.boot.ssl.DefaultSslBundleRegistry implements org.springframework.boot.ssl.SslBundleRegistry,org.springframework.boot.ssl.SslBundles {
  private final java.util.Map<java.lang.String, org.springframework.boot.ssl.SslBundle> bundles;

  public org.springframework.boot.ssl.DefaultSslBundleRegistry();
    Code:
       0: aload_0
       1: invokespecial #1                  // Method java/lang/Object."<init>":()V
       4: aload_0
       5: new           #7                  // class java/util/concurrent/ConcurrentHashMap
       8: dup
       9: invokespecial #9                  // Method java/util/concurrent/ConcurrentHashMap."<init>":()V
      12: putfield      #10                 // Field bundles:Ljava/util/Map;
      15: return

  public org.springframework.boot.ssl.DefaultSslBundleRegistry(java.lang.String, org.springframework.boot.ssl.SslBundle);
    Code:
       0: aload_0
       1: invokespecial #1                  // Method java/lang/Object."<init>":()V
       4: aload_0
       5: new           #7                  // class java/util/concurrent/ConcurrentHashMap
       8: dup
       9: invokespecial #9                  // Method java/util/concurrent/ConcurrentHashMap."<init>":()V
      12: putfield      #10                 // Field bundles:Ljava/util/Map;
      15: aload_0
      16: aload_1
      17: aload_2
      18: invokevirtual #16                 // Method registerBundle:(Ljava/lang/String;Lorg/springframework/boot/ssl/SslBundle;)V
      21: return

  public void registerBundle(java.lang.String, org.springframework.boot.ssl.SslBundle);
    Code:
       0: aload_1
       1: ldc           #20                 // String Name must not be null
       3: invokestatic  #22                 // Method org/springframework/util/Assert.notNull:(Ljava/lang/Object;Ljava/lang/String;)V
       6: aload_2
       7: ldc           #28                 // String Bundle must not be null
       9: invokestatic  #22                 // Method org/springframework/util/Assert.notNull:(Ljava/lang/Object;Ljava/lang/String;)V
      12: aload_0
      13: getfield      #10                 // Field bundles:Ljava/util/Map;
      16: aload_1
      17: aload_2
      18: invokeinterface #30,  3           // InterfaceMethod java/util/Map.putIfAbsent:(Ljava/lang/Object;Ljava/lang/Object;)Ljava/lang/Object;
      23: checkcast     #36                 // class org/springframework/boot/ssl/SslBundle
      26: astore_3
      27: aload_3
      28: ifnonnull     35
      31: iconst_1
      32: goto          36
      35: iconst_0
      36: aload_1
      37: invokedynamic #38,  0             // InvokeDynamic #0:get:(Ljava/lang/String;)Ljava/util/function/Supplier;
      42: invokestatic  #42                 // Method org/springframework/util/Assert.state:(ZLjava/util/function/Supplier;)V
      45: return

  public org.springframework.boot.ssl.SslBundle getBundle(java.lang.String);
    Code:
       0: aload_1
       1: ldc           #20                 // String Name must not be null
       3: invokestatic  #22                 // Method org/springframework/util/Assert.notNull:(Ljava/lang/Object;Ljava/lang/String;)V
       6: aload_0
       7: getfield      #10                 // Field bundles:Ljava/util/Map;
      10: aload_1
      11: invokeinterface #46,  2           // InterfaceMethod java/util/Map.get:(Ljava/lang/Object;)Ljava/lang/Object;
      16: checkcast     #36                 // class org/springframework/boot/ssl/SslBundle
      19: astore_2
      20: aload_2
      21: ifnonnull     46
      24: new           #49                 // class org/springframework/boot/ssl/NoSuchSslBundleException
      27: dup
      28: aload_1
      29: ldc           #51                 // String SSL bundle name \'%s\' cannot be found
      31: iconst_1
      32: anewarray     #2                  // class java/lang/Object
      35: dup
      36: iconst_0
      37: aload_1
      38: aastore
      39: invokevirtual #53                 // Method java/lang/String.formatted:([Ljava/lang/Object;)Ljava/lang/String;
      42: invokespecial #59                 // Method org/springframework/boot/ssl/NoSuchSslBundleException."<init>":(Ljava/lang/String;Ljava/lang/String;)V
      45: athrow
      46: aload_2
      47: areturn

  private static java.lang.String lambda$registerBundle$0(java.lang.String);
    Code:
       0: ldc           #62                 // String Cannot replace existing SSL bundle \'%s\'
       2: iconst_1
       3: anewarray     #2                  // class java/lang/Object
       6: dup
       7: iconst_0
       8: aload_0
       9: aastore
      10: invokevirtual #53                 // Method java/lang/String.formatted:([Ljava/lang/Object;)Ljava/lang/String;
      13: areturn
}
