Compiled from "NoSuchSslBundleException.java"
public class org.springframework.boot.ssl.NoSuchSslBundleException extends java.lang.RuntimeException {
  private final java.lang.String bundleName;

  public org.springframework.boot.ssl.NoSuchSslBundleException(java.lang.String, java.lang.String);
    Code:
       0: aload_0
       1: aload_1
       2: aload_2
       3: aconst_null
       4: invokespecial #1                  // Method "<init>":(Ljava/lang/String;Ljava/lang/String;Ljava/lang/Throwable;)V
       7: return

  public org.springframework.boot.ssl.NoSuchSslBundleException(java.lang.String, java.lang.String, java.lang.Throwable);
    Code:
       0: aload_0
       1: aload_2
       2: aload_3
       3: invokespecial #7                  // Method java/lang/RuntimeException."<init>":(Ljava/lang/String;Ljava/lang/Throwable;)V
       6: aload_0
       7: aload_1
       8: putfield      #12                 // Field bundleName:Ljava/lang/String;
      11: return

  public java.lang.String getBundleName();
    Code:
       0: aload_0
       1: getfield      #12                 // Field bundleName:Ljava/lang/String;
       4: areturn
}
