Compiled from "SslBundleKey.java"
public interface org.springframework.boot.ssl.SslBundleKey {
  public static final org.springframework.boot.ssl.SslBundleKey NONE;

  public abstract java.lang.String getPassword();

  public abstract java.lang.String getAlias();

  public default void assertContainsAlias(java.security.KeyStore);
    Code:
       0: aload_0
       1: invokeinterface #1,  1            // InterfaceMethod getAlias:()Ljava/lang/String;
       6: astore_2
       7: aload_2
       8: invokestatic  #7                  // Method org/springframework/util/StringUtils.hasLength:(Ljava/lang/String;)Z
      11: ifeq          58
      14: aload_1
      15: ifnull        58
      18: aload_1
      19: aload_2
      20: invokevirtual #13                 // Method java/security/KeyStore.containsAlias:(Ljava/lang/String;)Z
      23: aload_2
      24: invokedynamic #18,  0             // InvokeDynamic #0:get:(Ljava/lang/String;)Ljava/util/function/Supplier;
      29: invokestatic  #22                 // Method org/springframework/util/Assert.state:(ZLjava/util/function/Supplier;)V
      32: goto          58
      35: astore_3
      36: new           #30                 // class java/lang/IllegalStateException
      39: dup
      40: ldc           #32                 // String Could not determine if keystore contains alias \'%s\'
      42: iconst_1
      43: anewarray     #34                 // class java/lang/Object
      46: dup
      47: iconst_0
      48: aload_2
      49: aastore
      50: invokestatic  #36                 // Method java/lang/String.format:(Ljava/lang/String;[Ljava/lang/Object;)Ljava/lang/String;
      53: aload_3
      54: invokespecial #42                 // Method java/lang/IllegalStateException."<init>":(Ljava/lang/String;Ljava/lang/Throwable;)V
      57: athrow
      58: return
    Exception table:
       from    to  target type
          18    32    35   Class java/security/KeyStoreException

  public static org.springframework.boot.ssl.SslBundleKey of(java.lang.String);
    Code:
       0: aload_0
       1: aconst_null
       2: invokestatic  #46                 // InterfaceMethod of:(Ljava/lang/String;Ljava/lang/String;)Lorg/springframework/boot/ssl/SslBundleKey;
       5: areturn

  public static org.springframework.boot.ssl.SslBundleKey of(java.lang.String, java.lang.String);
    Code:
       0: new           #50                 // class org/springframework/boot/ssl/SslBundleKey$1
       3: dup
       4: aload_0
       5: aload_1
       6: invokespecial #52                 // Method org/springframework/boot/ssl/SslBundleKey$1."<init>":(Ljava/lang/String;Ljava/lang/String;)V
       9: areturn

  private static java.lang.String lambda$assertContainsAlias$0(java.lang.String);
    Code:
       0: ldc           #55                 // String Keystore does not contain alias \'%s\'
       2: iconst_1
       3: anewarray     #34                 // class java/lang/Object
       6: dup
       7: iconst_0
       8: aload_0
       9: aastore
      10: invokestatic  #36                 // Method java/lang/String.format:(Ljava/lang/String;[Ljava/lang/Object;)Ljava/lang/String;
      13: areturn

  static {};
    Code:
       0: aconst_null
       1: aconst_null
       2: invokestatic  #46                 // InterfaceMethod of:(Ljava/lang/String;Ljava/lang/String;)Lorg/springframework/boot/ssl/SslBundleKey;
       5: putstatic     #57                 // Field NONE:Lorg/springframework/boot/ssl/SslBundleKey;
       8: return
}
