Compiled from "SslBundle.java"
class org.springframework.boot.ssl.SslBundle$1 implements org.springframework.boot.ssl.SslBundle {
  final org.springframework.boot.ssl.SslStoreBundle val$stores;

  final org.springframework.boot.ssl.SslBundleKey val$key;

  final org.springframework.boot.ssl.SslOptions val$options;

  final java.lang.String val$protocol;

  final org.springframework.boot.ssl.SslManagerBundle val$managersToUse;

  org.springframework.boot.ssl.SslBundle$1();
    Code:
       0: aload_0
       1: aload_1
       2: putfield      #1                  // Field val$stores:Lorg/springframework/boot/ssl/SslStoreBundle;
       5: aload_0
       6: aload_2
       7: putfield      #7                  // Field val$key:Lorg/springframework/boot/ssl/SslBundleKey;
      10: aload_0
      11: aload_3
      12: putfield      #11                 // Field val$options:Lorg/springframework/boot/ssl/SslOptions;
      15: aload_0
      16: aload         4
      18: putfield      #15                 // Field val$protocol:Ljava/lang/String;
      21: aload_0
      22: aload         5
      24: putfield      #19                 // Field val$managersToUse:Lorg/springframework/boot/ssl/SslManagerBundle;
      27: aload_0
      28: invokespecial #23                 // Method java/lang/Object."<init>":()V
      31: return

  public org.springframework.boot.ssl.SslStoreBundle getStores();
    Code:
       0: aload_0
       1: getfield      #1                  // Field val$stores:Lorg/springframework/boot/ssl/SslStoreBundle;
       4: ifnull        14
       7: aload_0
       8: getfield      #1                  // Field val$stores:Lorg/springframework/boot/ssl/SslStoreBundle;
      11: goto          17
      14: getstatic     #29                 // Field org/springframework/boot/ssl/SslStoreBundle.NONE:Lorg/springframework/boot/ssl/SslStoreBundle;
      17: areturn

  public org.springframework.boot.ssl.SslBundleKey getKey();
    Code:
       0: aload_0
       1: getfield      #7                  // Field val$key:Lorg/springframework/boot/ssl/SslBundleKey;
       4: ifnull        14
       7: aload_0
       8: getfield      #7                  // Field val$key:Lorg/springframework/boot/ssl/SslBundleKey;
      11: goto          17
      14: getstatic     #34                 // Field org/springframework/boot/ssl/SslBundleKey.NONE:Lorg/springframework/boot/ssl/SslBundleKey;
      17: areturn

  public org.springframework.boot.ssl.SslOptions getOptions();
    Code:
       0: aload_0
       1: getfield      #11                 // Field val$options:Lorg/springframework/boot/ssl/SslOptions;
       4: ifnull        14
       7: aload_0
       8: getfield      #11                 // Field val$options:Lorg/springframework/boot/ssl/SslOptions;
      11: goto          17
      14: getstatic     #38                 // Field org/springframework/boot/ssl/SslOptions.NONE:Lorg/springframework/boot/ssl/SslOptions;
      17: areturn

  public java.lang.String getProtocol();
    Code:
       0: aload_0
       1: getfield      #15                 // Field val$protocol:Ljava/lang/String;
       4: invokestatic  #42                 // Method org/springframework/util/StringUtils.hasText:(Ljava/lang/String;)Z
       7: ifne          15
      10: ldc           #50                 // String TLS
      12: goto          19
      15: aload_0
      16: getfield      #15                 // Field val$protocol:Ljava/lang/String;
      19: areturn

  public org.springframework.boot.ssl.SslManagerBundle getManagers();
    Code:
       0: aload_0
       1: getfield      #19                 // Field val$managersToUse:Lorg/springframework/boot/ssl/SslManagerBundle;
       4: areturn
}
