Compiled from "SslBundleKey.java"
class org.springframework.boot.ssl.SslBundleKey$1 implements org.springframework.boot.ssl.SslBundleKey {
  final java.lang.String val$password;

  final java.lang.String val$alias;

  org.springframework.boot.ssl.SslBundleKey$1();
    Code:
       0: aload_0
       1: aload_1
       2: putfield      #1                  // Field val$password:Ljava/lang/String;
       5: aload_0
       6: aload_2
       7: putfield      #7                  // Field val$alias:Ljava/lang/String;
      10: aload_0
      11: invokespecial #10                 // Method java/lang/Object."<init>":()V
      14: return

  public java.lang.String getPassword();
    Code:
       0: aload_0
       1: getfield      #1                  // Field val$password:Ljava/lang/String;
       4: areturn

  public java.lang.String getAlias();
    Code:
       0: aload_0
       1: getfield      #7                  // Field val$alias:Ljava/lang/String;
       4: areturn
}
