Compiled from "SslBundle.java"
public interface org.springframework.boot.ssl.SslBundle {
  public static final java.lang.String DEFAULT_PROTOCOL;

  public abstract org.springframework.boot.ssl.SslStoreBundle getStores();

  public abstract org.springframework.boot.ssl.SslBundleKey getKey();

  public abstract org.springframework.boot.ssl.SslOptions getOptions();

  public abstract java.lang.String getProtocol();

  public abstract org.springframework.boot.ssl.SslManagerBundle getManagers();

  public default javax.net.ssl.SSLContext createSslContext();
    Code:
       0: aload_0
       1: invokeinterface #1,  1            // InterfaceMethod getManagers:()Lorg/springframework/boot/ssl/SslManagerBundle;
       6: aload_0
       7: invokeinterface #7,  1            // InterfaceMethod getProtocol:()Ljava/lang/String;
      12: invokeinterface #11,  2           // InterfaceMethod org/springframework/boot/ssl/SslManagerBundle.createSslContext:(Ljava/lang/String;)Ljavax/net/ssl/SSLContext;
      17: areturn

  public static org.springframework.boot.ssl.SslBundle of(org.springframework.boot.ssl.SslStoreBundle);
    Code:
       0: aload_0
       1: aconst_null
       2: aconst_null
       3: invokestatic  #17                 // InterfaceMethod of:(Lorg/springframework/boot/ssl/SslStoreBundle;Lorg/springframework/boot/ssl/SslBundleKey;Lorg/springframework/boot/ssl/SslOptions;)Lorg/springframework/boot/ssl/SslBundle;
       6: areturn

  public static org.springframework.boot.ssl.SslBundle of(org.springframework.boot.ssl.SslStoreBundle, org.springframework.boot.ssl.SslBundleKey);
    Code:
       0: aload_0
       1: aload_1
       2: aconst_null
       3: invokestatic  #17                 // InterfaceMethod of:(Lorg/springframework/boot/ssl/SslStoreBundle;Lorg/springframework/boot/ssl/SslBundleKey;Lorg/springframework/boot/ssl/SslOptions;)Lorg/springframework/boot/ssl/SslBundle;
       6: areturn

  public static org.springframework.boot.ssl.SslBundle of(org.springframework.boot.ssl.SslStoreBundle, org.springframework.boot.ssl.SslBundleKey, org.springframework.boot.ssl.SslOptions);
    Code:
       0: aload_0
       1: aload_1
       2: aload_2
       3: aconst_null
       4: invokestatic  #21                 // InterfaceMethod of:(Lorg/springframework/boot/ssl/SslStoreBundle;Lorg/springframework/boot/ssl/SslBundleKey;Lorg/springframework/boot/ssl/SslOptions;Ljava/lang/String;)Lorg/springframework/boot/ssl/SslBundle;
       7: areturn

  public static org.springframework.boot.ssl.SslBundle of(org.springframework.boot.ssl.SslStoreBundle, org.springframework.boot.ssl.SslBundleKey, org.springframework.boot.ssl.SslOptions, java.lang.String);
    Code:
       0: aload_0
       1: aload_1
       2: aload_2
       3: aload_3
       4: aconst_null
       5: invokestatic  #24                 // InterfaceMethod of:(Lorg/springframework/boot/ssl/SslStoreBundle;Lorg/springframework/boot/ssl/SslBundleKey;Lorg/springframework/boot/ssl/SslOptions;Ljava/lang/String;Lorg/springframework/boot/ssl/SslManagerBundle;)Lorg/springframework/boot/ssl/SslBundle;
       8: areturn

  public static org.springframework.boot.ssl.SslBundle of(org.springframework.boot.ssl.SslStoreBundle, org.springframework.boot.ssl.SslBundleKey, org.springframework.boot.ssl.SslOptions, java.lang.String, org.springframework.boot.ssl.SslManagerBundle);
    Code:
       0: aload         4
       2: ifnull        10
       5: aload         4
       7: goto          15
      10: aload_0
      11: aload_1
      12: invokestatic  #27                 // InterfaceMethod org/springframework/boot/ssl/SslManagerBundle.from:(Lorg/springframework/boot/ssl/SslStoreBundle;Lorg/springframework/boot/ssl/SslBundleKey;)Lorg/springframework/boot/ssl/SslManagerBundle;
      15: astore        5
      17: new           #31                 // class org/springframework/boot/ssl/SslBundle$1
      20: dup
      21: aload_0
      22: aload_1
      23: aload_2
      24: aload_3
      25: aload         5
      27: invokespecial #33                 // Method org/springframework/boot/ssl/SslBundle$1."<init>":(Lorg/springframework/boot/ssl/SslStoreBundle;Lorg/springframework/boot/ssl/SslBundleKey;Lorg/springframework/boot/ssl/SslOptions;Ljava/lang/String;Lorg/springframework/boot/ssl/SslManagerBundle;)V
      30: areturn
}
