Compiled from "SslManagerBundle.java"
public interface org.springframework.boot.ssl.SslManagerBundle {
  public default javax.net.ssl.KeyManager[] getKeyManagers();
    Code:
       0: aload_0
       1: invokeinterface #1,  1            // InterfaceMethod getKeyManagerFactory:()Ljavax/net/ssl/KeyManagerFactory;
       6: invokevirtual #7                  // Method javax/net/ssl/KeyManagerFactory.getKeyManagers:()[Ljavax/net/ssl/KeyManager;
       9: areturn

  public abstract javax.net.ssl.KeyManagerFactory getKeyManagerFactory();

  public default javax.net.ssl.TrustManager[] getTrustManagers();
    Code:
       0: aload_0
       1: invokeinterface #13,  1           // InterfaceMethod getTrustManagerFactory:()Ljavax/net/ssl/TrustManagerFactory;
       6: invokevirtual #17                 // Method javax/net/ssl/TrustManagerFactory.getTrustManagers:()[Ljavax/net/ssl/TrustManager;
       9: areturn

  public abstract javax.net.ssl.TrustManagerFactory getTrustManagerFactory();

  public default javax.net.ssl.SSLContext createSslContext(java.lang.String);
    Code:
       0: aload_1
       1: invokestatic  #23                 // Method javax/net/ssl/SSLContext.getInstance:(Ljava/lang/String;)Ljavax/net/ssl/SSLContext;
       4: astore_2
       5: aload_2
       6: aload_0
       7: invokeinterface #29,  1           // InterfaceMethod getKeyManagers:()[Ljavax/net/ssl/KeyManager;
      12: aload_0
      13: invokeinterface #30,  1           // InterfaceMethod getTrustManagers:()[Ljavax/net/ssl/TrustManager;
      18: aconst_null
      19: invokevirtual #31                 // Method javax/net/ssl/SSLContext.init:([Ljavax/net/ssl/KeyManager;[Ljavax/net/ssl/TrustManager;Ljava/security/SecureRandom;)V
      22: aload_2
      23: areturn
      24: astore_2
      25: new           #37                 // class java/lang/IllegalStateException
      28: dup
      29: aload_2
      30: invokevirtual #39                 // Method java/lang/Exception.getMessage:()Ljava/lang/String;
      33: invokedynamic #43,  0             // InvokeDynamic #0:makeConcatWithConstants:(Ljava/lang/String;)Ljava/lang/String;
      38: aload_2
      39: invokespecial #47                 // Method java/lang/IllegalStateException."<init>":(Ljava/lang/String;Ljava/lang/Throwable;)V
      42: athrow
    Exception table:
       from    to  target type
           0    23    24   Class java/lang/Exception

  public static org.springframework.boot.ssl.SslManagerBundle of(javax.net.ssl.KeyManagerFactory, javax.net.ssl.TrustManagerFactory);
    Code:
       0: aload_0
       1: ldc           #51                 // String KeyManagerFactory must not be null
       3: invokestatic  #53                 // Method org/springframework/util/Assert.notNull:(Ljava/lang/Object;Ljava/lang/String;)V
       6: aload_1
       7: ldc           #59                 // String TrustManagerFactory must not be null
       9: invokestatic  #53                 // Method org/springframework/util/Assert.notNull:(Ljava/lang/Object;Ljava/lang/String;)V
      12: new           #61                 // class org/springframework/boot/ssl/SslManagerBundle$1
      15: dup
      16: aload_0
      17: aload_1
      18: invokespecial #63                 // Method org/springframework/boot/ssl/SslManagerBundle$1."<init>":(Ljavax/net/ssl/KeyManagerFactory;Ljavax/net/ssl/TrustManagerFactory;)V
      21: areturn

  public static org.springframework.boot.ssl.SslManagerBundle from(org.springframework.boot.ssl.SslStoreBundle, org.springframework.boot.ssl.SslBundleKey);
    Code:
       0: new           #66                 // class org/springframework/boot/ssl/DefaultSslManagerBundle
       3: dup
       4: aload_0
       5: aload_1
       6: invokespecial #68                 // Method org/springframework/boot/ssl/DefaultSslManagerBundle."<init>":(Lorg/springframework/boot/ssl/SslStoreBundle;Lorg/springframework/boot/ssl/SslBundleKey;)V
       9: areturn
}
