Compiled from "SslManagerBundle.java"
class org.springframework.boot.ssl.SslManagerBundle$1 implements org.springframework.boot.ssl.SslManagerBundle {
  final javax.net.ssl.KeyManagerFactory val$keyManagerFactory;

  final javax.net.ssl.TrustManagerFactory val$trustManagerFactory;

  org.springframework.boot.ssl.SslManagerBundle$1();
    Code:
       0: aload_0
       1: aload_1
       2: putfield      #1                  // Field val$keyManagerFactory:Ljavax/net/ssl/KeyManagerFactory;
       5: aload_0
       6: aload_2
       7: putfield      #7                  // Field val$trustManagerFactory:Ljavax/net/ssl/TrustManagerFactory;
      10: aload_0
      11: invokespecial #11                 // Method java/lang/Object."<init>":()V
      14: return

  public javax.net.ssl.KeyManagerFactory getKeyManagerFactory();
    Code:
       0: aload_0
       1: getfield      #1                  // Field val$keyManagerFactory:Ljavax/net/ssl/KeyManagerFactory;
       4: areturn

  public javax.net.ssl.TrustManagerFactory getTrustManagerFactory();
    Code:
       0: aload_0
       1: getfield      #7                  // Field val$trustManagerFactory:Ljavax/net/ssl/TrustManagerFactory;
       4: areturn
}
