Compiled from "SslOptions.java"
public interface org.springframework.boot.ssl.SslOptions {
  public static final org.springframework.boot.ssl.SslOptions NONE;

  public default boolean isSpecified();
    Code:
       0: aload_0
       1: invokeinterface #1,  1            // InterfaceMethod getCiphers:()[Ljava/lang/String;
       6: ifnull        22
       9: aload_0
      10: invokeinterface #7,  1            // InterfaceMethod getEnabledProtocols:()[Ljava/lang/String;
      15: ifnull        22
      18: iconst_1
      19: goto          23
      22: iconst_0
      23: ireturn

  public abstract java.lang.String[] getCiphers();

  public abstract java.lang.String[] getEnabledProtocols();

  public static org.springframework.boot.ssl.SslOptions of(java.lang.String[], java.lang.String[]);
    Code:
       0: new           #10                 // class org/springframework/boot/ssl/SslOptions$1
       3: dup
       4: aload_0
       5: aload_1
       6: invokespecial #12                 // Method org/springframework/boot/ssl/SslOptions$1."<init>":([Ljava/lang/String;[Ljava/lang/String;)V
       9: areturn

  public static org.springframework.boot.ssl.SslOptions of(java.util.Set<java.lang.String>, java.util.Set<java.lang.String>);
    Code:
       0: aload_0
       1: invokestatic  #16                 // InterfaceMethod toArray:(Ljava/util/Collection;)[Ljava/lang/String;
       4: aload_1
       5: invokestatic  #16                 // InterfaceMethod toArray:(Ljava/util/Collection;)[Ljava/lang/String;
       8: invokestatic  #20                 // InterfaceMethod of:([Ljava/lang/String;[Ljava/lang/String;)Lorg/springframework/boot/ssl/SslOptions;
      11: areturn

  public static java.util.Set<java.lang.String> asSet(java.lang.String[]);
    Code:
       0: aload_0
       1: ifnull        21
       4: new           #24                 // class java/util/LinkedHashSet
       7: dup
       8: aload_0
       9: invokestatic  #26                 // Method java/util/Arrays.asList:([Ljava/lang/Object;)Ljava/util/List;
      12: invokespecial #32                 // Method java/util/LinkedHashSet."<init>":(Ljava/util/Collection;)V
      15: invokestatic  #35                 // Method java/util/Collections.unmodifiableSet:(Ljava/util/Set;)Ljava/util/Set;
      18: goto          22
      21: aconst_null
      22: areturn

  private static java.lang.String[] toArray(java.util.Collection<java.lang.String>);
    Code:
       0: aload_0
       1: ifnull        21
       4: aload_0
       5: invokedynamic #41,  0             // InvokeDynamic #0:apply:()Ljava/util/function/IntFunction;
      10: invokeinterface #45,  2           // InterfaceMethod java/util/Collection.toArray:(Ljava/util/function/IntFunction;)[Ljava/lang/Object;
      15: checkcast     #50                 // class "[Ljava/lang/String;"
      18: goto          22
      21: aconst_null
      22: areturn

  private static java.lang.String[] lambda$toArray$0(int);
    Code:
       0: iload_0
       1: anewarray     #52                 // class java/lang/String
       4: areturn

  static {};
    Code:
       0: aconst_null
       1: checkcast     #54                 // class java/util/Set
       4: aconst_null
       5: checkcast     #54                 // class java/util/Set
       8: invokestatic  #56                 // InterfaceMethod of:(Ljava/util/Set;Ljava/util/Set;)Lorg/springframework/boot/ssl/SslOptions;
      11: putstatic     #59                 // Field NONE:Lorg/springframework/boot/ssl/SslOptions;
      14: return
}
