Compiled from "SslOptions.java"
class org.springframework.boot.ssl.SslOptions$1 implements org.springframework.boot.ssl.SslOptions {
  final java.lang.String[] val$ciphers;

  final java.lang.String[] val$enabledProtocols;

  org.springframework.boot.ssl.SslOptions$1();
    Code:
       0: aload_0
       1: aload_1
       2: putfield      #1                  // Field val$ciphers:[Ljava/lang/String;
       5: aload_0
       6: aload_2
       7: putfield      #7                  // Field val$enabledProtocols:[Ljava/lang/String;
      10: aload_0
      11: invokespecial #10                 // Method java/lang/Object."<init>":()V
      14: return

  public java.lang.String[] getCiphers();
    Code:
       0: aload_0
       1: getfield      #1                  // Field val$ciphers:[Ljava/lang/String;
       4: areturn

  public java.lang.String[] getEnabledProtocols();
    Code:
       0: aload_0
       1: getfield      #7                  // Field val$enabledProtocols:[Ljava/lang/String;
       4: areturn
}
