Compiled from "SslStoreBundle.java"
public interface org.springframework.boot.ssl.SslStoreBundle {
  public static final org.springframework.boot.ssl.SslStoreBundle NONE;

  public abstract java.security.KeyStore getKeyStore();

  public abstract java.lang.String getKeyStorePassword();

  public abstract java.security.KeyStore getTrustStore();

  public static org.springframework.boot.ssl.SslStoreBundle of(java.security.KeyStore, java.lang.String, java.security.KeyStore);
    Code:
       0: new           #1                  // class org/springframework/boot/ssl/SslStoreBundle$1
       3: dup
       4: aload_0
       5: aload_2
       6: aload_1
       7: invokespecial #3                  // Method org/springframework/boot/ssl/SslStoreBundle$1."<init>":(Ljava/security/KeyStore;Ljava/security/KeyStore;Ljava/lang/String;)V
      10: areturn

  static {};
    Code:
       0: aconst_null
       1: aconst_null
       2: aconst_null
       3: invokestatic  #7                  // InterfaceMethod of:(Ljava/security/KeyStore;Ljava/lang/String;Ljava/security/KeyStore;)Lorg/springframework/boot/ssl/SslStoreBundle;
       6: putstatic     #13                 // Field NONE:Lorg/springframework/boot/ssl/SslStoreBundle;
       9: return
}
