Compiled from "SslStoreBundle.java"
class org.springframework.boot.ssl.SslStoreBundle$1 implements org.springframework.boot.ssl.SslStoreBundle {
  final java.security.KeyStore val$keyStore;

  final java.security.KeyStore val$trustStore;

  final java.lang.String val$keyStorePassword;

  org.springframework.boot.ssl.SslStoreBundle$1();
    Code:
       0: aload_0
       1: aload_1
       2: putfield      #1                  // Field val$keyStore:Ljava/security/KeyStore;
       5: aload_0
       6: aload_2
       7: putfield      #7                  // Field val$trustStore:Ljava/security/KeyStore;
      10: aload_0
      11: aload_3
      12: putfield      #10                 // Field val$keyStorePassword:Ljava/lang/String;
      15: aload_0
      16: invokespecial #14                 // Method java/lang/Object."<init>":()V
      19: return

  public java.security.KeyStore getKeyStore();
    Code:
       0: aload_0
       1: getfield      #1                  // Field val$keyStore:Ljava/security/KeyStore;
       4: areturn

  public java.security.KeyStore getTrustStore();
    Code:
       0: aload_0
       1: getfield      #7                  // Field val$trustStore:Ljava/security/KeyStore;
       4: areturn

  public java.lang.String getKeyStorePassword();
    Code:
       0: aload_0
       1: getfield      #10                 // Field val$keyStorePassword:Ljava/lang/String;
       4: areturn
}
