Compiled from "DubboComponentScanRegistrar.java"
public class org.apache.dubbo.config.spring.context.annotation.DubboComponentScanRegistrar implements org.springframework.context.annotation.ImportBeanDefinitionRegistrar {
  public org.apache.dubbo.config.spring.context.annotation.DubboComponentScanRegistrar();
    Code:
       0: aload_0
       1: invokespecial #1                  // Method java/lang/Object."<init>":()V
       4: return

  public void registerBeanDefinitions(org.springframework.core.type.AnnotationMetadata, org.springframework.beans.factory.support.BeanDefinitionRegistry);
    Code:
       0: aload_2
       1: invokestatic  #2                  // Method org/apache/dubbo/config/spring/context/DubboSpringInitializer.initialize:(Lorg/springframework/beans/factory/support/BeanDefinitionRegistry;)V
       4: aload_0
       5: aload_1
       6: invokespecial #3                  // Method getPackagesToScan:(Lorg/springframework/core/type/AnnotationMetadata;)Ljava/util/Set;
       9: astore_3
      10: aload_0
      11: aload_3
      12: aload_2
      13: invokespecial #4                  // Method registerServiceAnnotationPostProcessor:(Ljava/util/Set;Lorg/springframework/beans/factory/support/BeanDefinitionRegistry;)V
      16: return

  private void registerServiceAnnotationPostProcessor(java.util.Set<java.lang.String>, org.springframework.beans.factory.support.BeanDefinitionRegistry);
    Code:
       0: ldc           #5                  // class org/apache/dubbo/config/spring/beans/factory/annotation/ServiceAnnotationPostProcessor
       2: invokestatic  #6                  // Method org/springframework/beans/factory/support/BeanDefinitionBuilder.rootBeanDefinition:(Ljava/lang/Class;)Lorg/springframework/beans/factory/support/BeanDefinitionBuilder;
       5: astore_3
       6: aload_3
       7: aload_1
       8: invokevirtual #7                  // Method org/springframework/beans/factory/support/BeanDefinitionBuilder.addConstructorArgValue:(Ljava/lang/Object;)Lorg/springframework/beans/factory/support/BeanDefinitionBuilder;
      11: pop
      12: aload_3
      13: iconst_2
      14: invokevirtual #9                  // Method org/springframework/beans/factory/support/BeanDefinitionBuilder.setRole:(I)Lorg/springframework/beans/factory/support/BeanDefinitionBuilder;
      17: pop
      18: aload_3
      19: invokevirtual #10                 // Method org/springframework/beans/factory/support/BeanDefinitionBuilder.getBeanDefinition:()Lorg/springframework/beans/factory/support/AbstractBeanDefinition;
      22: astore        4
      24: aload         4
      26: aload_2
      27: invokestatic  #11                 // Method org/springframework/beans/factory/support/BeanDefinitionReaderUtils.registerWithGeneratedName:(Lorg/springframework/beans/factory/support/AbstractBeanDefinition;Lorg/springframework/beans/factory/support/BeanDefinitionRegistry;)Ljava/lang/String;
      30: pop
      31: return

  private java.util.Set<java.lang.String> getPackagesToScan(org.springframework.core.type.AnnotationMetadata);
    Code:
       0: aload_0
       1: aload_1
       2: ldc           #12                 // class org/apache/dubbo/config/spring/context/annotation/DubboComponentScan
       4: ldc           #13                 // String basePackages
       6: ldc           #14                 // String basePackageClasses
       8: invokespecial #15                 // Method getPackagesToScan0:(Lorg/springframework/core/type/AnnotationMetadata;Ljava/lang/Class;Ljava/lang/String;Ljava/lang/String;)Ljava/util/Set;
      11: astore_2
      12: aload_2
      13: invokeinterface #16,  1           // InterfaceMethod java/util/Set.isEmpty:()Z
      18: ifeq          33
      21: aload_0
      22: aload_1
      23: ldc           #17                 // class org/apache/dubbo/config/spring/context/annotation/EnableDubbo
      25: ldc           #18                 // String scanBasePackages
      27: ldc           #19                 // String scanBasePackageClasses
      29: invokespecial #15                 // Method getPackagesToScan0:(Lorg/springframework/core/type/AnnotationMetadata;Ljava/lang/Class;Ljava/lang/String;Ljava/lang/String;)Ljava/util/Set;
      32: astore_2
      33: aload_2
      34: invokeinterface #16,  1           // InterfaceMethod java/util/Set.isEmpty:()Z
      39: ifeq          55
      42: aload_1
      43: invokeinterface #20,  1           // InterfaceMethod org/springframework/core/type/AnnotationMetadata.getClassName:()Ljava/lang/String;
      48: invokestatic  #21                 // Method org/springframework/util/ClassUtils.getPackageName:(Ljava/lang/String;)Ljava/lang/String;
      51: invokestatic  #22                 // Method java/util/Collections.singleton:(Ljava/lang/Object;)Ljava/util/Set;
      54: areturn
      55: aload_2
      56: areturn

  private java.util.Set<java.lang.String> getPackagesToScan0(org.springframework.core.type.AnnotationMetadata, java.lang.Class, java.lang.String, java.lang.String);
    Code:
       0: aload_1
       1: aload_2
       2: invokevirtual #23                 // Method java/lang/Class.getName:()Ljava/lang/String;
       5: invokeinterface #24,  2           // InterfaceMethod org/springframework/core/type/AnnotationMetadata.getAnnotationAttributes:(Ljava/lang/String;)Ljava/util/Map;
      10: invokestatic  #25                 // Method org/springframework/core/annotation/AnnotationAttributes.fromMap:(Ljava/util/Map;)Lorg/springframework/core/annotation/AnnotationAttributes;
      13: astore        5
      15: aload         5
      17: ifnonnull     24
      20: invokestatic  #26                 // Method java/util/Collections.emptySet:()Ljava/util/Set;
      23: areturn
      24: new           #27                 // class java/util/LinkedHashSet
      27: dup
      28: invokespecial #28                 // Method java/util/LinkedHashSet."<init>":()V
      31: astore        6
      33: aload         5
      35: aload_3
      36: invokevirtual #29                 // Method org/springframework/core/annotation/AnnotationAttributes.getStringArray:(Ljava/lang/String;)[Ljava/lang/String;
      39: astore        7
      41: aload         6
      43: aload         7
      45: invokestatic  #30                 // Method java/util/Arrays.asList:([Ljava/lang/Object;)Ljava/util/List;
      48: invokeinterface #31,  2           // InterfaceMethod java/util/Set.addAll:(Ljava/util/Collection;)Z
      53: pop
      54: aload         5
      56: aload         4
      58: invokevirtual #32                 // Method org/springframework/core/annotation/AnnotationAttributes.getClassArray:(Ljava/lang/String;)[Ljava/lang/Class;
      61: astore        8
      63: aload         8
      65: astore        9
      67: aload         9
      69: arraylength
      70: istore        10
      72: iconst_0
      73: istore        11
      75: iload         11
      77: iload         10
      79: if_icmpge     108
      82: aload         9
      84: iload         11
      86: aaload
      87: astore        12
      89: aload         6
      91: aload         12
      93: invokestatic  #33                 // Method org/springframework/util/ClassUtils.getPackageName:(Ljava/lang/Class;)Ljava/lang/String;
      96: invokeinterface #34,  2           // InterfaceMethod java/util/Set.add:(Ljava/lang/Object;)Z
     101: pop
     102: iinc          11, 1
     105: goto          75
     108: aload         5
     110: ldc           #35                 // String value
     112: invokevirtual #36                 // Method org/springframework/core/annotation/AnnotationAttributes.containsKey:(Ljava/lang/Object;)Z
     115: ifeq          140
     118: aload         5
     120: ldc           #35                 // String value
     122: invokevirtual #29                 // Method org/springframework/core/annotation/AnnotationAttributes.getStringArray:(Ljava/lang/String;)[Ljava/lang/String;
     125: astore        9
     127: aload         6
     129: aload         9
     131: invokestatic  #30                 // Method java/util/Arrays.asList:([Ljava/lang/Object;)Ljava/util/List;
     134: invokeinterface #31,  2           // InterfaceMethod java/util/Set.addAll:(Ljava/util/Collection;)Z
     139: pop
     140: aload         6
     142: areturn
}
