Compiled from "DubboClassPathBeanDefinitionScanner.java"
public class org.apache.dubbo.config.spring.context.annotation.DubboClassPathBeanDefinitionScanner extends org.springframework.context.annotation.ClassPathBeanDefinitionScanner {
  private final java.util.concurrent.ConcurrentMap<java.lang.String, java.util.Set<org.springframework.beans.factory.config.BeanDefinition>> beanDefinitionMap;

  public org.apache.dubbo.config.spring.context.annotation.DubboClassPathBeanDefinitionScanner(org.springframework.beans.factory.support.BeanDefinitionRegistry, boolean, org.springframework.core.env.Environment, org.springframework.core.io.ResourceLoader);
    Code:
       0: aload_0
       1: aload_1
       2: iload_2
       3: invokespecial #1                  // Method org/springframework/context/annotation/ClassPathBeanDefinitionScanner."<init>":(Lorg/springframework/beans/factory/support/BeanDefinitionRegistry;Z)V
       6: aload_0
       7: new           #2                  // class java/util/concurrent/ConcurrentHashMap
      10: dup
      11: invokespecial #3                  // Method java/util/concurrent/ConcurrentHashMap."<init>":()V
      14: putfield      #4                  // Field beanDefinitionMap:Ljava/util/concurrent/ConcurrentMap;
      17: aload_0
      18: aload_3
      19: invokevirtual #5                  // Method setEnvironment:(Lorg/springframework/core/env/Environment;)V
      22: aload_0
      23: aload         4
      25: invokevirtual #6                  // Method setResourceLoader:(Lorg/springframework/core/io/ResourceLoader;)V
      28: aload_1
      29: invokestatic  #7                  // Method org/springframework/context/annotation/AnnotationConfigUtils.registerAnnotationConfigProcessors:(Lorg/springframework/beans/factory/support/BeanDefinitionRegistry;)V
      32: return

  public org.apache.dubbo.config.spring.context.annotation.DubboClassPathBeanDefinitionScanner(org.springframework.beans.factory.support.BeanDefinitionRegistry, org.springframework.core.env.Environment, org.springframework.core.io.ResourceLoader);
    Code:
       0: aload_0
       1: aload_1
       2: iconst_0
       3: aload_2
       4: aload_3
       5: invokespecial #8                  // Method "<init>":(Lorg/springframework/beans/factory/support/BeanDefinitionRegistry;ZLorg/springframework/core/env/Environment;Lorg/springframework/core/io/ResourceLoader;)V
       8: return

  public java.util.Set<org.springframework.beans.factory.config.BeanDefinition> findCandidateComponents(java.lang.String);
    Code:
       0: aload_0
       1: getfield      #4                  // Field beanDefinitionMap:Ljava/util/concurrent/ConcurrentMap;
       4: aload_1
       5: invokeinterface #9,  2            // InterfaceMethod java/util/concurrent/ConcurrentMap.get:(Ljava/lang/Object;)Ljava/lang/Object;
      10: checkcast     #10                 // class java/util/Set
      13: astore_2
      14: aload_2
      15: invokestatic  #11                 // Method java/util/Objects.isNull:(Ljava/lang/Object;)Z
      18: ifeq          39
      21: aload_0
      22: aload_1
      23: invokespecial #12                 // Method org/springframework/context/annotation/ClassPathBeanDefinitionScanner.findCandidateComponents:(Ljava/lang/String;)Ljava/util/Set;
      26: astore_2
      27: aload_0
      28: getfield      #4                  // Field beanDefinitionMap:Ljava/util/concurrent/ConcurrentMap;
      31: aload_1
      32: aload_2
      33: invokeinterface #13,  3           // InterfaceMethod java/util/concurrent/ConcurrentMap.put:(Ljava/lang/Object;Ljava/lang/Object;)Ljava/lang/Object;
      38: pop
      39: aload_2
      40: areturn
}
