Compiled from "AnnotationsAttr.java"
public class jadx.api.plugins.input.data.attributes.types.AnnotationsAttr extends jadx.api.plugins.input.data.attributes.PinnedAttribute {
  private final java.util.Map<java.lang.String, jadx.api.plugins.input.data.annotations.IAnnotation> map;

  public static jadx.api.plugins.input.data.attributes.types.AnnotationsAttr pack(java.util.List<jadx.api.plugins.input.data.annotations.IAnnotation>);
    Code:
       0: aload_0
       1: invokeinterface #1,  1            // InterfaceMethod java/util/List.isEmpty:()Z
       6: ifeq          11
       9: aconst_null
      10: areturn
      11: new           #2                  // class java/util/HashMap
      14: dup
      15: aload_0
      16: invokeinterface #3,  1            // InterfaceMethod java/util/List.size:()I
      21: invokespecial #4                  // Method java/util/HashMap."<init>":(I)V
      24: astore_1
      25: aload_0
      26: invokeinterface #5,  1            // InterfaceMethod java/util/List.iterator:()Ljava/util/Iterator;
      31: astore_2
      32: aload_2
      33: invokeinterface #6,  1            // InterfaceMethod java/util/Iterator.hasNext:()Z
      38: ifeq          80
      41: aload_2
      42: invokeinterface #7,  1            // InterfaceMethod java/util/Iterator.next:()Ljava/lang/Object;
      47: checkcast     #8                  // class jadx/api/plugins/input/data/annotations/IAnnotation
      50: astore_3
      51: aload_3
      52: invokeinterface #9,  1            // InterfaceMethod jadx/api/plugins/input/data/annotations/IAnnotation.getVisibility:()Ljadx/api/plugins/input/data/annotations/AnnotationVisibility;
      57: getstatic     #10                 // Field jadx/api/plugins/input/data/annotations/AnnotationVisibility.SYSTEM:Ljadx/api/plugins/input/data/annotations/AnnotationVisibility;
      60: if_acmpeq     77
      63: aload_1
      64: aload_3
      65: invokeinterface #11,  1           // InterfaceMethod jadx/api/plugins/input/data/annotations/IAnnotation.getAnnotationClass:()Ljava/lang/String;
      70: aload_3
      71: invokeinterface #12,  3           // InterfaceMethod java/util/Map.put:(Ljava/lang/Object;Ljava/lang/Object;)Ljava/lang/Object;
      76: pop
      77: goto          32
      80: aload_1
      81: invokeinterface #13,  1           // InterfaceMethod java/util/Map.isEmpty:()Z
      86: ifeq          91
      89: aconst_null
      90: areturn
      91: new           #14                 // class jadx/api/plugins/input/data/attributes/types/AnnotationsAttr
      94: dup
      95: aload_1
      96: invokespecial #15                 // Method "<init>":(Ljava/util/Map;)V
      99: areturn

  public jadx.api.plugins.input.data.attributes.types.AnnotationsAttr(java.util.Map<java.lang.String, jadx.api.plugins.input.data.annotations.IAnnotation>);
    Code:
       0: aload_0
       1: invokespecial #16                 // Method jadx/api/plugins/input/data/attributes/PinnedAttribute."<init>":()V
       4: aload_0
       5: aload_1
       6: putfield      #17                 // Field map:Ljava/util/Map;
       9: return

  public jadx.api.plugins.input.data.annotations.IAnnotation get(java.lang.String);
    Code:
       0: aload_0
       1: getfield      #17                 // Field map:Ljava/util/Map;
       4: aload_1
       5: invokeinterface #18,  2           // InterfaceMethod java/util/Map.get:(Ljava/lang/Object;)Ljava/lang/Object;
      10: checkcast     #8                  // class jadx/api/plugins/input/data/annotations/IAnnotation
      13: areturn

  public java.util.Collection<jadx.api.plugins.input.data.annotations.IAnnotation> getAll();
    Code:
       0: aload_0
       1: getfield      #17                 // Field map:Ljava/util/Map;
       4: invokeinterface #19,  1           // InterfaceMethod java/util/Map.values:()Ljava/util/Collection;
       9: areturn

  public java.util.List<jadx.api.plugins.input.data.annotations.IAnnotation> getList();
    Code:
       0: aload_0
       1: getfield      #17                 // Field map:Ljava/util/Map;
       4: invokeinterface #13,  1           // InterfaceMethod java/util/Map.isEmpty:()Z
       9: ifeq          18
      12: invokestatic  #20                 // Method java/util/Collections.emptyList:()Ljava/util/List;
      15: goto          34
      18: new           #21                 // class java/util/ArrayList
      21: dup
      22: aload_0
      23: getfield      #17                 // Field map:Ljava/util/Map;
      26: invokeinterface #19,  1           // InterfaceMethod java/util/Map.values:()Ljava/util/Collection;
      31: invokespecial #22                 // Method java/util/ArrayList."<init>":(Ljava/util/Collection;)V
      34: areturn

  public int size();
    Code:
       0: aload_0
       1: getfield      #17                 // Field map:Ljava/util/Map;
       4: invokeinterface #23,  1           // InterfaceMethod java/util/Map.size:()I
       9: ireturn

  public boolean isEmpty();
    Code:
       0: aload_0
       1: getfield      #17                 // Field map:Ljava/util/Map;
       4: invokeinterface #13,  1           // InterfaceMethod java/util/Map.isEmpty:()Z
       9: ireturn

  public jadx.api.plugins.input.data.attributes.JadxAttrType<jadx.api.plugins.input.data.attributes.types.AnnotationsAttr> getAttrType();
    Code:
       0: getstatic     #24                 // Field jadx/api/plugins/input/data/attributes/JadxAttrType.ANNOTATION_LIST:Ljadx/api/plugins/input/data/attributes/JadxAttrType;
       3: areturn

  public java.lang.String toString();
    Code:
       0: aload_0
       1: getfield      #17                 // Field map:Ljava/util/Map;
       4: invokevirtual #25                 // Method java/lang/Object.toString:()Ljava/lang/String;
       7: areturn

  public jadx.api.plugins.input.data.attributes.IJadxAttrType getAttrType();
    Code:
       0: aload_0
       1: invokevirtual #26                 // Method getAttrType:()Ljadx/api/plugins/input/data/attributes/JadxAttrType;
       4: areturn
}
