Compiled from "AnnotationMethodParamsAttr.java"
public class jadx.api.plugins.input.data.attributes.types.AnnotationMethodParamsAttr extends jadx.api.plugins.input.data.attributes.PinnedAttribute {
  private final java.util.List<jadx.api.plugins.input.data.attributes.types.AnnotationsAttr> paramList;

  public static jadx.api.plugins.input.data.attributes.types.AnnotationMethodParamsAttr pack(java.util.List<java.util.List<jadx.api.plugins.input.data.annotations.IAnnotation>>);
    Code:
       0: aload_0
       1: invokeinterface #1,  1            // InterfaceMethod java/util/List.isEmpty:()Z
       6: ifeq          11
       9: aconst_null
      10: areturn
      11: new           #2                  // class java/util/ArrayList
      14: dup
      15: aload_0
      16: invokeinterface #3,  1            // InterfaceMethod java/util/List.size:()I
      21: invokespecial #4                  // Method java/util/ArrayList."<init>":(I)V
      24: astore_1
      25: aload_0
      26: invokeinterface #5,  1            // InterfaceMethod java/util/List.iterator:()Ljava/util/Iterator;
      31: astore_2
      32: aload_2
      33: invokeinterface #6,  1            // InterfaceMethod java/util/Iterator.hasNext:()Z
      38: ifeq          65
      41: aload_2
      42: invokeinterface #7,  1            // InterfaceMethod java/util/Iterator.next:()Ljava/lang/Object;
      47: checkcast     #8                  // class java/util/List
      50: astore_3
      51: aload_1
      52: aload_3
      53: invokestatic  #9                  // Method jadx/api/plugins/input/data/attributes/types/AnnotationsAttr.pack:(Ljava/util/List;)Ljadx/api/plugins/input/data/attributes/types/AnnotationsAttr;
      56: invokeinterface #10,  2           // InterfaceMethod java/util/List.add:(Ljava/lang/Object;)Z
      61: pop
      62: goto          32
      65: new           #11                 // class jadx/api/plugins/input/data/attributes/types/AnnotationMethodParamsAttr
      68: dup
      69: aload_1
      70: invokespecial #12                 // Method "<init>":(Ljava/util/List;)V
      73: areturn

  private jadx.api.plugins.input.data.attributes.types.AnnotationMethodParamsAttr(java.util.List<jadx.api.plugins.input.data.attributes.types.AnnotationsAttr>);
    Code:
       0: aload_0
       1: invokespecial #13                 // Method jadx/api/plugins/input/data/attributes/PinnedAttribute."<init>":()V
       4: aload_0
       5: aload_1
       6: putfield      #14                 // Field paramList:Ljava/util/List;
       9: return

  public java.util.List<jadx.api.plugins.input.data.attributes.types.AnnotationsAttr> getParamList();
    Code:
       0: aload_0
       1: getfield      #14                 // Field paramList:Ljava/util/List;
       4: areturn

  public jadx.api.plugins.input.data.attributes.JadxAttrType<jadx.api.plugins.input.data.attributes.types.AnnotationMethodParamsAttr> getAttrType();
    Code:
       0: getstatic     #15                 // Field jadx/api/plugins/input/data/attributes/JadxAttrType.ANNOTATION_MTH_PARAMETERS:Ljadx/api/plugins/input/data/attributes/JadxAttrType;
       3: areturn

  public java.lang.String toString();
    Code:
       0: aload_0
       1: getfield      #14                 // Field paramList:Ljava/util/List;
       4: invokevirtual #16                 // Method java/lang/Object.toString:()Ljava/lang/String;
       7: areturn

  public jadx.api.plugins.input.data.attributes.IJadxAttrType getAttrType();
    Code:
       0: aload_0
       1: invokevirtual #17                 // Method getAttrType:()Ljadx/api/plugins/input/data/attributes/JadxAttrType;
       4: areturn
}
