Compiled from "AnnotationDefaultClassAttr.java"
public class jadx.api.plugins.input.data.attributes.types.AnnotationDefaultClassAttr extends jadx.api.plugins.input.data.attributes.PinnedAttribute {
  private final java.util.Map<java.lang.String, jadx.api.plugins.input.data.annotations.EncodedValue> values;

  public jadx.api.plugins.input.data.attributes.types.AnnotationDefaultClassAttr(java.util.Map<java.lang.String, jadx.api.plugins.input.data.annotations.EncodedValue>);
    Code:
       0: aload_0
       1: invokespecial #1                  // Method jadx/api/plugins/input/data/attributes/PinnedAttribute."<init>":()V
       4: aload_0
       5: aload_1
       6: putfield      #2                  // Field values:Ljava/util/Map;
       9: return

  public java.util.Map<java.lang.String, jadx.api.plugins.input.data.annotations.EncodedValue> getValues();
    Code:
       0: aload_0
       1: getfield      #2                  // Field values:Ljava/util/Map;
       4: areturn

  public jadx.api.plugins.input.data.attributes.IJadxAttrType<? extends jadx.api.plugins.input.data.attributes.IJadxAttribute> getAttrType();
    Code:
       0: getstatic     #3                  // Field jadx/api/plugins/input/data/attributes/JadxAttrType.ANNOTATION_DEFAULT_CLASS:Ljadx/api/plugins/input/data/attributes/JadxAttrType;
       3: areturn

  public java.lang.String toString();
    Code:
       0: new           #4                  // class java/lang/StringBuilder
       3: dup
       4: invokespecial #5                  // Method java/lang/StringBuilder."<init>":()V
       7: ldc           #6                  // String ANNOTATION_DEFAULT_CLASS:
       9: invokevirtual #7                  // Method java/lang/StringBuilder.append:(Ljava/lang/String;)Ljava/lang/StringBuilder;
      12: aload_0
      13: getfield      #2                  // Field values:Ljava/util/Map;
      16: invokevirtual #8                  // Method java/lang/StringBuilder.append:(Ljava/lang/Object;)Ljava/lang/StringBuilder;
      19: invokevirtual #9                  // Method java/lang/StringBuilder.toString:()Ljava/lang/String;
      22: areturn
}
