Compiled from "InnerClsInfo.java"
public class jadx.api.plugins.input.data.attributes.types.InnerClsInfo {
  private final java.lang.String innerCls;

  private final java.lang.String outerCls;

  private final java.lang.String name;

  private final int accessFlags;

  public jadx.api.plugins.input.data.attributes.types.InnerClsInfo(java.lang.String, java.lang.String, java.lang.String, int);
    Code:
       0: aload_0
       1: invokespecial #1                  // Method java/lang/Object."<init>":()V
       4: aload_0
       5: aload_1
       6: putfield      #2                  // Field innerCls:Ljava/lang/String;
       9: aload_0
      10: aload_2
      11: putfield      #3                  // Field outerCls:Ljava/lang/String;
      14: aload_0
      15: aload_3
      16: putfield      #4                  // Field name:Ljava/lang/String;
      19: aload_0
      20: iload         4
      22: putfield      #5                  // Field accessFlags:I
      25: return

  public java.lang.String getInnerCls();
    Code:
       0: aload_0
       1: getfield      #2                  // Field innerCls:Ljava/lang/String;
       4: areturn

  public java.lang.String getOuterCls();
    Code:
       0: aload_0
       1: getfield      #3                  // Field outerCls:Ljava/lang/String;
       4: areturn

  public java.lang.String getName();
    Code:
       0: aload_0
       1: getfield      #4                  // Field name:Ljava/lang/String;
       4: areturn

  public int getAccessFlags();
    Code:
       0: aload_0
       1: getfield      #5                  // Field accessFlags:I
       4: ireturn

  public java.lang.String toString();
    Code:
       0: new           #6                  // class java/lang/StringBuilder
       3: dup
       4: invokespecial #7                  // Method java/lang/StringBuilder."<init>":()V
       7: ldc           #8                  // String InnerCls{
       9: invokevirtual #9                  // Method java/lang/StringBuilder.append:(Ljava/lang/String;)Ljava/lang/StringBuilder;
      12: aload_0
      13: getfield      #2                  // Field innerCls:Ljava/lang/String;
      16: invokevirtual #9                  // Method java/lang/StringBuilder.append:(Ljava/lang/String;)Ljava/lang/StringBuilder;
      19: ldc           #10                 // String , outerCls=
      21: invokevirtual #9                  // Method java/lang/StringBuilder.append:(Ljava/lang/String;)Ljava/lang/StringBuilder;
      24: aload_0
      25: getfield      #3                  // Field outerCls:Ljava/lang/String;
      28: invokevirtual #9                  // Method java/lang/StringBuilder.append:(Ljava/lang/String;)Ljava/lang/StringBuilder;
      31: ldc           #11                 // String , name=
      33: invokevirtual #9                  // Method java/lang/StringBuilder.append:(Ljava/lang/String;)Ljava/lang/StringBuilder;
      36: aload_0
      37: getfield      #4                  // Field name:Ljava/lang/String;
      40: invokevirtual #9                  // Method java/lang/StringBuilder.append:(Ljava/lang/String;)Ljava/lang/StringBuilder;
      43: ldc           #12                 // String , accessFlags=
      45: invokevirtual #9                  // Method java/lang/StringBuilder.append:(Ljava/lang/String;)Ljava/lang/StringBuilder;
      48: aload_0
      49: getfield      #5                  // Field accessFlags:I
      52: getstatic     #13                 // Field jadx/api/plugins/input/data/AccessFlagsScope.CLASS:Ljadx/api/plugins/input/data/AccessFlagsScope;
      55: invokestatic  #14                 // Method jadx/api/plugins/input/data/AccessFlags.format:(ILjadx/api/plugins/input/data/AccessFlagsScope;)Ljava/lang/String;
      58: invokevirtual #9                  // Method java/lang/StringBuilder.append:(Ljava/lang/String;)Ljava/lang/StringBuilder;
      61: bipush        125
      63: invokevirtual #15                 // Method java/lang/StringBuilder.append:(C)Ljava/lang/StringBuilder;
      66: invokevirtual #16                 // Method java/lang/StringBuilder.toString:()Ljava/lang/String;
      69: areturn
}
