Compiled from "MethodParametersAttr.java"
public class jadx.api.plugins.input.data.attributes.types.MethodParametersAttr extends jadx.api.plugins.input.data.attributes.PinnedAttribute {
  private final java.util.List<jadx.api.plugins.input.data.attributes.types.MethodParametersAttr$Info> list;

  public jadx.api.plugins.input.data.attributes.types.MethodParametersAttr(java.util.List<jadx.api.plugins.input.data.attributes.types.MethodParametersAttr$Info>);
    Code:
       0: aload_0
       1: invokespecial #1                  // Method jadx/api/plugins/input/data/attributes/PinnedAttribute."<init>":()V
       4: aload_0
       5: aload_1
       6: putfield      #2                  // Field list:Ljava/util/List;
       9: return

  public java.util.List<jadx.api.plugins.input.data.attributes.types.MethodParametersAttr$Info> getList();
    Code:
       0: aload_0
       1: getfield      #2                  // Field list:Ljava/util/List;
       4: areturn

  public jadx.api.plugins.input.data.attributes.IJadxAttrType<jadx.api.plugins.input.data.attributes.types.MethodParametersAttr> getAttrType();
    Code:
       0: getstatic     #3                  // Field jadx/api/plugins/input/data/attributes/JadxAttrType.METHOD_PARAMETERS:Ljadx/api/plugins/input/data/attributes/JadxAttrType;
       3: areturn

  public java.lang.String toString();
    Code:
       0: new           #4                  // class java/lang/StringBuilder
       3: dup
       4: invokespecial #5                  // Method java/lang/StringBuilder."<init>":()V
       7: ldc           #6                  // String METHOD_PARAMETERS:
       9: invokevirtual #7                  // Method java/lang/StringBuilder.append:(Ljava/lang/String;)Ljava/lang/StringBuilder;
      12: aload_0
      13: getfield      #2                  // Field list:Ljava/util/List;
      16: invokevirtual #8                  // Method java/lang/StringBuilder.append:(Ljava/lang/Object;)Ljava/lang/StringBuilder;
      19: invokevirtual #9                  // Method java/lang/StringBuilder.toString:()Ljava/lang/String;
      22: areturn
}
