Compiled from "MethodParametersAttr.java"
public class jadx.api.plugins.input.data.attributes.types.MethodParametersAttr$Info {
  private final int accFlags;

  private final java.lang.String name;

  public jadx.api.plugins.input.data.attributes.types.MethodParametersAttr$Info(int, java.lang.String);
    Code:
       0: aload_0
       1: invokespecial #1                  // Method java/lang/Object."<init>":()V
       4: aload_0
       5: iload_1
       6: putfield      #2                  // Field accFlags:I
       9: aload_0
      10: aload_2
      11: putfield      #3                  // Field name:Ljava/lang/String;
      14: return

  public int getAccFlags();
    Code:
       0: aload_0
       1: getfield      #2                  // Field accFlags:I
       4: ireturn

  public java.lang.String getName();
    Code:
       0: aload_0
       1: getfield      #3                  // Field name:Ljava/lang/String;
       4: areturn

  public java.lang.String toString();
    Code:
       0: new           #4                  // class java/lang/StringBuilder
       3: dup
       4: invokespecial #5                  // Method java/lang/StringBuilder."<init>":()V
       7: aload_0
       8: getfield      #2                  // Field accFlags:I
      11: getstatic     #6                  // Field jadx/api/plugins/input/data/AccessFlagsScope.METHOD:Ljadx/api/plugins/input/data/AccessFlagsScope;
      14: invokestatic  #7                  // Method jadx/api/plugins/input/data/AccessFlags.format:(ILjadx/api/plugins/input/data/AccessFlagsScope;)Ljava/lang/String;
      17: invokevirtual #8                  // Method java/lang/StringBuilder.append:(Ljava/lang/String;)Ljava/lang/StringBuilder;
      20: aload_0
      21: getfield      #3                  // Field name:Ljava/lang/String;
      24: invokevirtual #8                  // Method java/lang/StringBuilder.append:(Ljava/lang/String;)Ljava/lang/StringBuilder;
      27: invokevirtual #9                  // Method java/lang/StringBuilder.toString:()Ljava/lang/String;
      30: areturn
}
