Compiled from "DefaultSubscriber.java"
public abstract class io.reactivex.rxjava3.subscribers.DefaultSubscriber<T> implements io.reactivex.rxjava3.core.FlowableSubscriber<T> {
  org.reactivestreams.Subscription upstream;

  public io.reactivex.rxjava3.subscribers.DefaultSubscriber();
    Code:
       0: aload_0
       1: invokespecial #1                  // Method java/lang/Object."<init>":()V
       4: return

  public final void onSubscribe(org.reactivestreams.Subscription);
    Code:
       0: aload_0
       1: getfield      #2                  // Field upstream:Lorg/reactivestreams/Subscription;
       4: aload_1
       5: aload_0
       6: invokevirtual #3                  // Method java/lang/Object.getClass:()Ljava/lang/Class;
       9: invokestatic  #4                  // Method io/reactivex/rxjava3/internal/util/EndConsumerHelper.validate:(Lorg/reactivestreams/Subscription;Lorg/reactivestreams/Subscription;Ljava/lang/Class;)Z
      12: ifeq          24
      15: aload_0
      16: aload_1
      17: putfield      #2                  // Field upstream:Lorg/reactivestreams/Subscription;
      20: aload_0
      21: invokevirtual #5                  // Method onStart:()V
      24: return

  protected final void request(long);
    Code:
       0: aload_0
       1: getfield      #2                  // Field upstream:Lorg/reactivestreams/Subscription;
       4: astore_3
       5: aload_3
       6: ifnull        16
       9: aload_3
      10: lload_1
      11: invokeinterface #6,  3            // InterfaceMethod org/reactivestreams/Subscription.request:(J)V
      16: return

  protected final void cancel();
    Code:
       0: aload_0
       1: getfield      #2                  // Field upstream:Lorg/reactivestreams/Subscription;
       4: astore_1
       5: aload_0
       6: getstatic     #7                  // Field io/reactivex/rxjava3/internal/subscriptions/SubscriptionHelper.CANCELLED:Lio/reactivex/rxjava3/internal/subscriptions/SubscriptionHelper;
       9: putfield      #2                  // Field upstream:Lorg/reactivestreams/Subscription;
      12: aload_1
      13: invokeinterface #8,  1            // InterfaceMethod org/reactivestreams/Subscription.cancel:()V
      18: return

  protected void onStart();
    Code:
       0: aload_0
       1: ldc2_w        #10                 // long 9223372036854775807l
       4: invokevirtual #12                 // Method request:(J)V
       7: return
}
