Compiled from "ResourceSubscriber.java"
public abstract class io.reactivex.rxjava3.subscribers.ResourceSubscriber<T> implements io.reactivex.rxjava3.core.FlowableSubscriber<T>, io.reactivex.rxjava3.disposables.Disposable {
  private final java.util.concurrent.atomic.AtomicReference<org.reactivestreams.Subscription> upstream;

  private final io.reactivex.rxjava3.internal.disposables.ListCompositeDisposable resources;

  private final java.util.concurrent.atomic.AtomicLong missedRequested;

  public io.reactivex.rxjava3.subscribers.ResourceSubscriber();
    Code:
       0: aload_0
       1: invokespecial #1                  // Method java/lang/Object."<init>":()V
       4: aload_0
       5: new           #2                  // class java/util/concurrent/atomic/AtomicReference
       8: dup
       9: invokespecial #3                  // Method java/util/concurrent/atomic/AtomicReference."<init>":()V
      12: putfield      #4                  // Field upstream:Ljava/util/concurrent/atomic/AtomicReference;
      15: aload_0
      16: new           #5                  // class io/reactivex/rxjava3/internal/disposables/ListCompositeDisposable
      19: dup
      20: invokespecial #6                  // Method io/reactivex/rxjava3/internal/disposables/ListCompositeDisposable."<init>":()V
      23: putfield      #7                  // Field resources:Lio/reactivex/rxjava3/internal/disposables/ListCompositeDisposable;
      26: aload_0
      27: new           #8                  // class java/util/concurrent/atomic/AtomicLong
      30: dup
      31: invokespecial #9                  // Method java/util/concurrent/atomic/AtomicLong."<init>":()V
      34: putfield      #10                 // Field missedRequested:Ljava/util/concurrent/atomic/AtomicLong;
      37: return

  public final void add(io.reactivex.rxjava3.disposables.Disposable);
    Code:
       0: aload_1
       1: ldc           #11                 // String resource is null
       3: invokestatic  #12                 // Method java/util/Objects.requireNonNull:(Ljava/lang/Object;Ljava/lang/String;)Ljava/lang/Object;
       6: pop
       7: aload_0
       8: getfield      #7                  // Field resources:Lio/reactivex/rxjava3/internal/disposables/ListCompositeDisposable;
      11: aload_1
      12: invokevirtual #13                 // Method io/reactivex/rxjava3/internal/disposables/ListCompositeDisposable.add:(Lio/reactivex/rxjava3/disposables/Disposable;)Z
      15: pop
      16: return

  public final void onSubscribe(org.reactivestreams.Subscription);
    Code:
       0: aload_0
       1: getfield      #4                  // Field upstream:Ljava/util/concurrent/atomic/AtomicReference;
       4: aload_1
       5: aload_0
       6: invokevirtual #14                 // Method java/lang/Object.getClass:()Ljava/lang/Class;
       9: invokestatic  #15                 // Method io/reactivex/rxjava3/internal/util/EndConsumerHelper.setOnce:(Ljava/util/concurrent/atomic/AtomicReference;Lorg/reactivestreams/Subscription;Ljava/lang/Class;)Z
      12: ifeq          41
      15: aload_0
      16: getfield      #10                 // Field missedRequested:Ljava/util/concurrent/atomic/AtomicLong;
      19: lconst_0
      20: invokevirtual #16                 // Method java/util/concurrent/atomic/AtomicLong.getAndSet:(J)J
      23: lstore_2
      24: lload_2
      25: lconst_0
      26: lcmp
      27: ifeq          37
      30: aload_1
      31: lload_2
      32: invokeinterface #17,  3           // InterfaceMethod org/reactivestreams/Subscription.request:(J)V
      37: aload_0
      38: invokevirtual #18                 // Method onStart:()V
      41: return

  protected void onStart();
    Code:
       0: aload_0
       1: ldc2_w        #20                 // long 9223372036854775807l
       4: invokevirtual #22                 // Method request:(J)V
       7: return

  protected final void request(long);
    Code:
       0: aload_0
       1: getfield      #4                  // Field upstream:Ljava/util/concurrent/atomic/AtomicReference;
       4: aload_0
       5: getfield      #10                 // Field missedRequested:Ljava/util/concurrent/atomic/AtomicLong;
       8: lload_1
       9: invokestatic  #23                 // Method io/reactivex/rxjava3/internal/subscriptions/SubscriptionHelper.deferredRequest:(Ljava/util/concurrent/atomic/AtomicReference;Ljava/util/concurrent/atomic/AtomicLong;J)V
      12: return

  public final void dispose();
    Code:
       0: aload_0
       1: getfield      #4                  // Field upstream:Ljava/util/concurrent/atomic/AtomicReference;
       4: invokestatic  #24                 // Method io/reactivex/rxjava3/internal/subscriptions/SubscriptionHelper.cancel:(Ljava/util/concurrent/atomic/AtomicReference;)Z
       7: ifeq          17
      10: aload_0
      11: getfield      #7                  // Field resources:Lio/reactivex/rxjava3/internal/disposables/ListCompositeDisposable;
      14: invokevirtual #25                 // Method io/reactivex/rxjava3/internal/disposables/ListCompositeDisposable.dispose:()V
      17: return

  public final boolean isDisposed();
    Code:
       0: aload_0
       1: getfield      #4                  // Field upstream:Ljava/util/concurrent/atomic/AtomicReference;
       4: invokevirtual #26                 // Method java/util/concurrent/atomic/AtomicReference.get:()Ljava/lang/Object;
       7: getstatic     #27                 // Field io/reactivex/rxjava3/internal/subscriptions/SubscriptionHelper.CANCELLED:Lio/reactivex/rxjava3/internal/subscriptions/SubscriptionHelper;
      10: if_acmpne     17
      13: iconst_1
      14: goto          18
      17: iconst_0
      18: ireturn
}
