Compiled from "SafeSubscriber.java"
public final class io.reactivex.rxjava3.subscribers.SafeSubscriber<T> implements io.reactivex.rxjava3.core.FlowableSubscriber<T>, org.reactivestreams.Subscription {
  final org.reactivestreams.Subscriber<? super T> downstream;

  org.reactivestreams.Subscription upstream;

  boolean done;

  public io.reactivex.rxjava3.subscribers.SafeSubscriber(org.reactivestreams.Subscriber<? super T>);
    Code:
       0: aload_0
       1: invokespecial #1                  // Method java/lang/Object."<init>":()V
       4: aload_0
       5: aload_1
       6: putfield      #2                  // Field downstream:Lorg/reactivestreams/Subscriber;
       9: return

  public void onSubscribe(org.reactivestreams.Subscription);
    Code:
       0: aload_0
       1: getfield      #3                  // Field upstream:Lorg/reactivestreams/Subscription;
       4: aload_1
       5: invokestatic  #4                  // Method io/reactivex/rxjava3/internal/subscriptions/SubscriptionHelper.validate:(Lorg/reactivestreams/Subscription;Lorg/reactivestreams/Subscription;)Z
       8: ifeq          80
      11: aload_0
      12: aload_1
      13: putfield      #3                  // Field upstream:Lorg/reactivestreams/Subscription;
      16: aload_0
      17: getfield      #2                  // Field downstream:Lorg/reactivestreams/Subscriber;
      20: aload_0
      21: invokeinterface #5,  2            // InterfaceMethod org/reactivestreams/Subscriber.onSubscribe:(Lorg/reactivestreams/Subscription;)V
      26: goto          80
      29: astore_2
      30: aload_2
      31: invokestatic  #7                  // Method io/reactivex/rxjava3/exceptions/Exceptions.throwIfFatal:(Ljava/lang/Throwable;)V
      34: aload_0
      35: iconst_1
      36: putfield      #8                  // Field done:Z
      39: aload_1
      40: invokeinterface #9,  1            // InterfaceMethod org/reactivestreams/Subscription.cancel:()V
      45: goto          76
      48: astore_3
      49: aload_3
      50: invokestatic  #7                  // Method io/reactivex/rxjava3/exceptions/Exceptions.throwIfFatal:(Ljava/lang/Throwable;)V
      53: new           #10                 // class io/reactivex/rxjava3/exceptions/CompositeException
      56: dup
      57: iconst_2
      58: anewarray     #11                 // class java/lang/Throwable
      61: dup
      62: iconst_0
      63: aload_2
      64: aastore
      65: dup
      66: iconst_1
      67: aload_3
      68: aastore
      69: invokespecial #12                 // Method io/reactivex/rxjava3/exceptions/CompositeException."<init>":([Ljava/lang/Throwable;)V
      72: invokestatic  #13                 // Method io/reactivex/rxjava3/plugins/RxJavaPlugins.onError:(Ljava/lang/Throwable;)V
      75: return
      76: aload_2
      77: invokestatic  #13                 // Method io/reactivex/rxjava3/plugins/RxJavaPlugins.onError:(Ljava/lang/Throwable;)V
      80: return
    Exception table:
       from    to  target type
          16    26    29   Class java/lang/Throwable
          39    45    48   Class java/lang/Throwable

  public void onNext(T);
    Code:
       0: aload_0
       1: getfield      #8                  // Field done:Z
       4: ifeq          8
       7: return
       8: aload_0
       9: getfield      #3                  // Field upstream:Lorg/reactivestreams/Subscription;
      12: ifnonnull     20
      15: aload_0
      16: invokevirtual #14                 // Method onNextNoSubscription:()V
      19: return
      20: aload_1
      21: ifnonnull     77
      24: ldc           #15                 // String onNext called with a null Throwable.
      26: invokestatic  #16                 // Method io/reactivex/rxjava3/internal/util/ExceptionHelper.createNullPointerException:(Ljava/lang/String;)Ljava/lang/NullPointerException;
      29: astore_2
      30: aload_0
      31: getfield      #3                  // Field upstream:Lorg/reactivestreams/Subscription;
      34: invokeinterface #9,  1            // InterfaceMethod org/reactivestreams/Subscription.cancel:()V
      39: goto          71
      42: astore_3
      43: aload_3
      44: invokestatic  #7                  // Method io/reactivex/rxjava3/exceptions/Exceptions.throwIfFatal:(Ljava/lang/Throwable;)V
      47: aload_0
      48: new           #10                 // class io/reactivex/rxjava3/exceptions/CompositeException
      51: dup
      52: iconst_2
      53: anewarray     #11                 // class java/lang/Throwable
      56: dup
      57: iconst_0
      58: aload_2
      59: aastore
      60: dup
      61: iconst_1
      62: aload_3
      63: aastore
      64: invokespecial #12                 // Method io/reactivex/rxjava3/exceptions/CompositeException."<init>":([Ljava/lang/Throwable;)V
      67: invokevirtual #17                 // Method onError:(Ljava/lang/Throwable;)V
      70: return
      71: aload_0
      72: aload_2
      73: invokevirtual #17                 // Method onError:(Ljava/lang/Throwable;)V
      76: return
      77: aload_0
      78: getfield      #2                  // Field downstream:Lorg/reactivestreams/Subscriber;
      81: aload_1
      82: invokeinterface #18,  2           // InterfaceMethod org/reactivestreams/Subscriber.onNext:(Ljava/lang/Object;)V
      87: goto          141
      90: astore_2
      91: aload_2
      92: invokestatic  #7                  // Method io/reactivex/rxjava3/exceptions/Exceptions.throwIfFatal:(Ljava/lang/Throwable;)V
      95: aload_0
      96: getfield      #3                  // Field upstream:Lorg/reactivestreams/Subscription;
      99: invokeinterface #9,  1            // InterfaceMethod org/reactivestreams/Subscription.cancel:()V
     104: goto          136
     107: astore_3
     108: aload_3
     109: invokestatic  #7                  // Method io/reactivex/rxjava3/exceptions/Exceptions.throwIfFatal:(Ljava/lang/Throwable;)V
     112: aload_0
     113: new           #10                 // class io/reactivex/rxjava3/exceptions/CompositeException
     116: dup
     117: iconst_2
     118: anewarray     #11                 // class java/lang/Throwable
     121: dup
     122: iconst_0
     123: aload_2
     124: aastore
     125: dup
     126: iconst_1
     127: aload_3
     128: aastore
     129: invokespecial #12                 // Method io/reactivex/rxjava3/exceptions/CompositeException."<init>":([Ljava/lang/Throwable;)V
     132: invokevirtual #17                 // Method onError:(Ljava/lang/Throwable;)V
     135: return
     136: aload_0
     137: aload_2
     138: invokevirtual #17                 // Method onError:(Ljava/lang/Throwable;)V
     141: return
    Exception table:
       from    to  target type
          30    39    42   Class java/lang/Throwable
          77    87    90   Class java/lang/Throwable
          95   104   107   Class java/lang/Throwable

  void onNextNoSubscription();
    Code:
       0: aload_0
       1: iconst_1
       2: putfield      #8                  // Field done:Z
       5: new           #19                 // class java/lang/NullPointerException
       8: dup
       9: ldc           #20                 // String Subscription not set!
      11: invokespecial #21                 // Method java/lang/NullPointerException."<init>":(Ljava/lang/String;)V
      14: astore_1
      15: aload_0
      16: getfield      #2                  // Field downstream:Lorg/reactivestreams/Subscriber;
      19: getstatic     #22                 // Field io/reactivex/rxjava3/internal/subscriptions/EmptySubscription.INSTANCE:Lio/reactivex/rxjava3/internal/subscriptions/EmptySubscription;
      22: invokeinterface #5,  2            // InterfaceMethod org/reactivestreams/Subscriber.onSubscribe:(Lorg/reactivestreams/Subscription;)V
      27: goto          58
      30: astore_2
      31: aload_2
      32: invokestatic  #7                  // Method io/reactivex/rxjava3/exceptions/Exceptions.throwIfFatal:(Ljava/lang/Throwable;)V
      35: new           #10                 // class io/reactivex/rxjava3/exceptions/CompositeException
      38: dup
      39: iconst_2
      40: anewarray     #11                 // class java/lang/Throwable
      43: dup
      44: iconst_0
      45: aload_1
      46: aastore
      47: dup
      48: iconst_1
      49: aload_2
      50: aastore
      51: invokespecial #12                 // Method io/reactivex/rxjava3/exceptions/CompositeException."<init>":([Ljava/lang/Throwable;)V
      54: invokestatic  #13                 // Method io/reactivex/rxjava3/plugins/RxJavaPlugins.onError:(Ljava/lang/Throwable;)V
      57: return
      58: aload_0
      59: getfield      #2                  // Field downstream:Lorg/reactivestreams/Subscriber;
      62: aload_1
      63: invokeinterface #23,  2           // InterfaceMethod org/reactivestreams/Subscriber.onError:(Ljava/lang/Throwable;)V
      68: goto          98
      71: astore_2
      72: aload_2
      73: invokestatic  #7                  // Method io/reactivex/rxjava3/exceptions/Exceptions.throwIfFatal:(Ljava/lang/Throwable;)V
      76: new           #10                 // class io/reactivex/rxjava3/exceptions/CompositeException
      79: dup
      80: iconst_2
      81: anewarray     #11                 // class java/lang/Throwable
      84: dup
      85: iconst_0
      86: aload_1
      87: aastore
      88: dup
      89: iconst_1
      90: aload_2
      91: aastore
      92: invokespecial #12                 // Method io/reactivex/rxjava3/exceptions/CompositeException."<init>":([Ljava/lang/Throwable;)V
      95: invokestatic  #13                 // Method io/reactivex/rxjava3/plugins/RxJavaPlugins.onError:(Ljava/lang/Throwable;)V
      98: return
    Exception table:
       from    to  target type
          15    27    30   Class java/lang/Throwable
          58    68    71   Class java/lang/Throwable

  public void onError(java.lang.Throwable);
    Code:
       0: aload_0
       1: getfield      #8                  // Field done:Z
       4: ifeq          12
       7: aload_1
       8: invokestatic  #13                 // Method io/reactivex/rxjava3/plugins/RxJavaPlugins.onError:(Ljava/lang/Throwable;)V
      11: return
      12: aload_0
      13: iconst_1
      14: putfield      #8                  // Field done:Z
      17: aload_0
      18: getfield      #3                  // Field upstream:Lorg/reactivestreams/Subscription;
      21: ifnonnull     144
      24: new           #19                 // class java/lang/NullPointerException
      27: dup
      28: ldc           #20                 // String Subscription not set!
      30: invokespecial #21                 // Method java/lang/NullPointerException."<init>":(Ljava/lang/String;)V
      33: astore_2
      34: aload_0
      35: getfield      #2                  // Field downstream:Lorg/reactivestreams/Subscriber;
      38: getstatic     #22                 // Field io/reactivex/rxjava3/internal/subscriptions/EmptySubscription.INSTANCE:Lio/reactivex/rxjava3/internal/subscriptions/EmptySubscription;
      41: invokeinterface #5,  2            // InterfaceMethod org/reactivestreams/Subscriber.onSubscribe:(Lorg/reactivestreams/Subscription;)V
      46: goto          81
      49: astore_3
      50: aload_3
      51: invokestatic  #7                  // Method io/reactivex/rxjava3/exceptions/Exceptions.throwIfFatal:(Ljava/lang/Throwable;)V
      54: new           #10                 // class io/reactivex/rxjava3/exceptions/CompositeException
      57: dup
      58: iconst_3
      59: anewarray     #11                 // class java/lang/Throwable
      62: dup
      63: iconst_0
      64: aload_1
      65: aastore
      66: dup
      67: iconst_1
      68: aload_2
      69: aastore
      70: dup
      71: iconst_2
      72: aload_3
      73: aastore
      74: invokespecial #12                 // Method io/reactivex/rxjava3/exceptions/CompositeException."<init>":([Ljava/lang/Throwable;)V
      77: invokestatic  #13                 // Method io/reactivex/rxjava3/plugins/RxJavaPlugins.onError:(Ljava/lang/Throwable;)V
      80: return
      81: aload_0
      82: getfield      #2                  // Field downstream:Lorg/reactivestreams/Subscriber;
      85: new           #10                 // class io/reactivex/rxjava3/exceptions/CompositeException
      88: dup
      89: iconst_2
      90: anewarray     #11                 // class java/lang/Throwable
      93: dup
      94: iconst_0
      95: aload_1
      96: aastore
      97: dup
      98: iconst_1
      99: aload_2
     100: aastore
     101: invokespecial #12                 // Method io/reactivex/rxjava3/exceptions/CompositeException."<init>":([Ljava/lang/Throwable;)V
     104: invokeinterface #23,  2           // InterfaceMethod org/reactivestreams/Subscriber.onError:(Ljava/lang/Throwable;)V
     109: goto          143
     112: astore_3
     113: aload_3
     114: invokestatic  #7                  // Method io/reactivex/rxjava3/exceptions/Exceptions.throwIfFatal:(Ljava/lang/Throwable;)V
     117: new           #10                 // class io/reactivex/rxjava3/exceptions/CompositeException
     120: dup
     121: iconst_3
     122: anewarray     #11                 // class java/lang/Throwable
     125: dup
     126: iconst_0
     127: aload_1
     128: aastore
     129: dup
     130: iconst_1
     131: aload_2
     132: aastore
     133: dup
     134: iconst_2
     135: aload_3
     136: aastore
     137: invokespecial #12                 // Method io/reactivex/rxjava3/exceptions/CompositeException."<init>":([Ljava/lang/Throwable;)V
     140: invokestatic  #13                 // Method io/reactivex/rxjava3/plugins/RxJavaPlugins.onError:(Ljava/lang/Throwable;)V
     143: return
     144: aload_1
     145: ifnonnull     154
     148: ldc           #24                 // String onError called with a null Throwable.
     150: invokestatic  #16                 // Method io/reactivex/rxjava3/internal/util/ExceptionHelper.createNullPointerException:(Ljava/lang/String;)Ljava/lang/NullPointerException;
     153: astore_1
     154: aload_0
     155: getfield      #2                  // Field downstream:Lorg/reactivestreams/Subscriber;
     158: aload_1
     159: invokeinterface #23,  2           // InterfaceMethod org/reactivestreams/Subscriber.onError:(Ljava/lang/Throwable;)V
     164: goto          194
     167: astore_2
     168: aload_2
     169: invokestatic  #7                  // Method io/reactivex/rxjava3/exceptions/Exceptions.throwIfFatal:(Ljava/lang/Throwable;)V
     172: new           #10                 // class io/reactivex/rxjava3/exceptions/CompositeException
     175: dup
     176: iconst_2
     177: anewarray     #11                 // class java/lang/Throwable
     180: dup
     181: iconst_0
     182: aload_1
     183: aastore
     184: dup
     185: iconst_1
     186: aload_2
     187: aastore
     188: invokespecial #12                 // Method io/reactivex/rxjava3/exceptions/CompositeException."<init>":([Ljava/lang/Throwable;)V
     191: invokestatic  #13                 // Method io/reactivex/rxjava3/plugins/RxJavaPlugins.onError:(Ljava/lang/Throwable;)V
     194: return
    Exception table:
       from    to  target type
          34    46    49   Class java/lang/Throwable
          81   109   112   Class java/lang/Throwable
         154   164   167   Class java/lang/Throwable

  public void onComplete();
    Code:
       0: aload_0
       1: getfield      #8                  // Field done:Z
       4: ifeq          8
       7: return
       8: aload_0
       9: iconst_1
      10: putfield      #8                  // Field done:Z
      13: aload_0
      14: getfield      #3                  // Field upstream:Lorg/reactivestreams/Subscription;
      17: ifnonnull     25
      20: aload_0
      21: invokevirtual #25                 // Method onCompleteNoSubscription:()V
      24: return
      25: aload_0
      26: getfield      #2                  // Field downstream:Lorg/reactivestreams/Subscriber;
      29: invokeinterface #26,  1           // InterfaceMethod org/reactivestreams/Subscriber.onComplete:()V
      34: goto          46
      37: astore_1
      38: aload_1
      39: invokestatic  #7                  // Method io/reactivex/rxjava3/exceptions/Exceptions.throwIfFatal:(Ljava/lang/Throwable;)V
      42: aload_1
      43: invokestatic  #13                 // Method io/reactivex/rxjava3/plugins/RxJavaPlugins.onError:(Ljava/lang/Throwable;)V
      46: return
    Exception table:
       from    to  target type
          25    34    37   Class java/lang/Throwable

  void onCompleteNoSubscription();
    Code:
       0: new           #19                 // class java/lang/NullPointerException
       3: dup
       4: ldc           #20                 // String Subscription not set!
       6: invokespecial #21                 // Method java/lang/NullPointerException."<init>":(Ljava/lang/String;)V
       9: astore_1
      10: aload_0
      11: getfield      #2                  // Field downstream:Lorg/reactivestreams/Subscriber;
      14: getstatic     #22                 // Field io/reactivex/rxjava3/internal/subscriptions/EmptySubscription.INSTANCE:Lio/reactivex/rxjava3/internal/subscriptions/EmptySubscription;
      17: invokeinterface #5,  2            // InterfaceMethod org/reactivestreams/Subscriber.onSubscribe:(Lorg/reactivestreams/Subscription;)V
      22: goto          53
      25: astore_2
      26: aload_2
      27: invokestatic  #7                  // Method io/reactivex/rxjava3/exceptions/Exceptions.throwIfFatal:(Ljava/lang/Throwable;)V
      30: new           #10                 // class io/reactivex/rxjava3/exceptions/CompositeException
      33: dup
      34: iconst_2
      35: anewarray     #11                 // class java/lang/Throwable
      38: dup
      39: iconst_0
      40: aload_1
      41: aastore
      42: dup
      43: iconst_1
      44: aload_2
      45: aastore
      46: invokespecial #12                 // Method io/reactivex/rxjava3/exceptions/CompositeException."<init>":([Ljava/lang/Throwable;)V
      49: invokestatic  #13                 // Method io/reactivex/rxjava3/plugins/RxJavaPlugins.onError:(Ljava/lang/Throwable;)V
      52: return
      53: aload_0
      54: getfield      #2                  // Field downstream:Lorg/reactivestreams/Subscriber;
      57: aload_1
      58: invokeinterface #23,  2           // InterfaceMethod org/reactivestreams/Subscriber.onError:(Ljava/lang/Throwable;)V
      63: goto          93
      66: astore_2
      67: aload_2
      68: invokestatic  #7                  // Method io/reactivex/rxjava3/exceptions/Exceptions.throwIfFatal:(Ljava/lang/Throwable;)V
      71: new           #10                 // class io/reactivex/rxjava3/exceptions/CompositeException
      74: dup
      75: iconst_2
      76: anewarray     #11                 // class java/lang/Throwable
      79: dup
      80: iconst_0
      81: aload_1
      82: aastore
      83: dup
      84: iconst_1
      85: aload_2
      86: aastore
      87: invokespecial #12                 // Method io/reactivex/rxjava3/exceptions/CompositeException."<init>":([Ljava/lang/Throwable;)V
      90: invokestatic  #13                 // Method io/reactivex/rxjava3/plugins/RxJavaPlugins.onError:(Ljava/lang/Throwable;)V
      93: return
    Exception table:
       from    to  target type
          10    22    25   Class java/lang/Throwable
          53    63    66   Class java/lang/Throwable

  public void request(long);
    Code:
       0: aload_0
       1: getfield      #3                  // Field upstream:Lorg/reactivestreams/Subscription;
       4: lload_1
       5: invokeinterface #27,  3           // InterfaceMethod org/reactivestreams/Subscription.request:(J)V
      10: goto          65
      13: astore_3
      14: aload_3
      15: invokestatic  #7                  // Method io/reactivex/rxjava3/exceptions/Exceptions.throwIfFatal:(Ljava/lang/Throwable;)V
      18: aload_0
      19: getfield      #3                  // Field upstream:Lorg/reactivestreams/Subscription;
      22: invokeinterface #9,  1            // InterfaceMethod org/reactivestreams/Subscription.cancel:()V
      27: goto          61
      30: astore        4
      32: aload         4
      34: invokestatic  #7                  // Method io/reactivex/rxjava3/exceptions/Exceptions.throwIfFatal:(Ljava/lang/Throwable;)V
      37: new           #10                 // class io/reactivex/rxjava3/exceptions/CompositeException
      40: dup
      41: iconst_2
      42: anewarray     #11                 // class java/lang/Throwable
      45: dup
      46: iconst_0
      47: aload_3
      48: aastore
      49: dup
      50: iconst_1
      51: aload         4
      53: aastore
      54: invokespecial #12                 // Method io/reactivex/rxjava3/exceptions/CompositeException."<init>":([Ljava/lang/Throwable;)V
      57: invokestatic  #13                 // Method io/reactivex/rxjava3/plugins/RxJavaPlugins.onError:(Ljava/lang/Throwable;)V
      60: return
      61: aload_3
      62: invokestatic  #13                 // Method io/reactivex/rxjava3/plugins/RxJavaPlugins.onError:(Ljava/lang/Throwable;)V
      65: return
    Exception table:
       from    to  target type
           0    10    13   Class java/lang/Throwable
          18    27    30   Class java/lang/Throwable

  public void cancel();
    Code:
       0: aload_0
       1: getfield      #3                  // Field upstream:Lorg/reactivestreams/Subscription;
       4: invokeinterface #9,  1            // InterfaceMethod org/reactivestreams/Subscription.cancel:()V
       9: goto          21
      12: astore_1
      13: aload_1
      14: invokestatic  #7                  // Method io/reactivex/rxjava3/exceptions/Exceptions.throwIfFatal:(Ljava/lang/Throwable;)V
      17: aload_1
      18: invokestatic  #13                 // Method io/reactivex/rxjava3/plugins/RxJavaPlugins.onError:(Ljava/lang/Throwable;)V
      21: return
    Exception table:
       from    to  target type
           0     9    12   Class java/lang/Throwable
}
