Compiled from "TestSubscriber.java"
final class io.reactivex.rxjava3.subscribers.TestSubscriber$EmptySubscriber extends java.lang.Enum<io.reactivex.rxjava3.subscribers.TestSubscriber$EmptySubscriber> implements io.reactivex.rxjava3.core.FlowableSubscriber<java.lang.Object> {
  public static final io.reactivex.rxjava3.subscribers.TestSubscriber$EmptySubscriber INSTANCE;

  private static final io.reactivex.rxjava3.subscribers.TestSubscriber$EmptySubscriber[] $VALUES;

  public static io.reactivex.rxjava3.subscribers.TestSubscriber$EmptySubscriber[] values();
    Code:
       0: getstatic     #1                  // Field $VALUES:[Lio/reactivex/rxjava3/subscribers/TestSubscriber$EmptySubscriber;
       3: invokevirtual #2                  // Method "[Lio/reactivex/rxjava3/subscribers/TestSubscriber$EmptySubscriber;".clone:()Ljava/lang/Object;
       6: checkcast     #3                  // class "[Lio/reactivex/rxjava3/subscribers/TestSubscriber$EmptySubscriber;"
       9: areturn

  public static io.reactivex.rxjava3.subscribers.TestSubscriber$EmptySubscriber valueOf(java.lang.String);
    Code:
       0: ldc           #4                  // class io/reactivex/rxjava3/subscribers/TestSubscriber$EmptySubscriber
       2: aload_0
       3: invokestatic  #5                  // Method java/lang/Enum.valueOf:(Ljava/lang/Class;Ljava/lang/String;)Ljava/lang/Enum;
       6: checkcast     #4                  // class io/reactivex/rxjava3/subscribers/TestSubscriber$EmptySubscriber
       9: areturn

  private io.reactivex.rxjava3.subscribers.TestSubscriber$EmptySubscriber();
    Code:
       0: aload_0
       1: aload_1
       2: iload_2
       3: invokespecial #6                  // Method java/lang/Enum."<init>":(Ljava/lang/String;I)V
       6: return

  public void onSubscribe(org.reactivestreams.Subscription);
    Code:
       0: return

  public void onNext(java.lang.Object);
    Code:
       0: return

  public void onError(java.lang.Throwable);
    Code:
       0: return

  public void onComplete();
    Code:
       0: return

  static {};
    Code:
       0: new           #4                  // class io/reactivex/rxjava3/subscribers/TestSubscriber$EmptySubscriber
       3: dup
       4: ldc           #7                  // String INSTANCE
       6: iconst_0
       7: invokespecial #8                  // Method "<init>":(Ljava/lang/String;I)V
      10: putstatic     #9                  // Field INSTANCE:Lio/reactivex/rxjava3/subscribers/TestSubscriber$EmptySubscriber;
      13: iconst_1
      14: anewarray     #4                  // class io/reactivex/rxjava3/subscribers/TestSubscriber$EmptySubscriber
      17: dup
      18: iconst_0
      19: getstatic     #9                  // Field INSTANCE:Lio/reactivex/rxjava3/subscribers/TestSubscriber$EmptySubscriber;
      22: aastore
      23: putstatic     #1                  // Field $VALUES:[Lio/reactivex/rxjava3/subscribers/TestSubscriber$EmptySubscriber;
      26: return
}
