Compiled from "ZookeeperMetadataReport.java"
public class org.apache.dubbo.metadata.store.zookeeper.ZookeeperMetadataReport extends org.apache.dubbo.metadata.report.support.AbstractMetadataReport {
  private static final org.apache.dubbo.common.logger.ErrorTypeAwareLogger logger;

  private final java.lang.String root;

  org.apache.dubbo.remoting.zookeeper.ZookeeperClient zkClient;

  private java.util.concurrent.ConcurrentMap<java.lang.String, org.apache.dubbo.metadata.store.zookeeper.ZookeeperMetadataReport$MappingDataListener> casListenerMap;

  public org.apache.dubbo.metadata.store.zookeeper.ZookeeperMetadataReport(org.apache.dubbo.common.URL, org.apache.dubbo.remoting.zookeeper.ZookeeperTransporter);
    Code:
       0: aload_0
       1: aload_1
       2: invokespecial #4                  // Method org/apache/dubbo/metadata/report/support/AbstractMetadataReport."<init>":(Lorg/apache/dubbo/common/URL;)V
       5: aload_0
       6: new           #5                  // class java/util/concurrent/ConcurrentHashMap
       9: dup
      10: invokespecial #6                  // Method java/util/concurrent/ConcurrentHashMap."<init>":()V
      13: putfield      #7                  // Field casListenerMap:Ljava/util/concurrent/ConcurrentMap;
      16: aload_1
      17: invokevirtual #8                  // Method org/apache/dubbo/common/URL.isAnyHost:()Z
      20: ifeq          33
      23: new           #9                  // class java/lang/IllegalStateException
      26: dup
      27: ldc           #10                 // String registry address == null
      29: invokespecial #11                 // Method java/lang/IllegalStateException."<init>":(Ljava/lang/String;)V
      32: athrow
      33: aload_1
      34: ldc           #13                 // String dubbo
      36: invokevirtual #14                 // Method org/apache/dubbo/common/URL.getGroup:(Ljava/lang/String;)Ljava/lang/String;
      39: astore_3
      40: aload_3
      41: ldc           #15                 // String /
      43: invokevirtual #16                 // Method java/lang/String.startsWith:(Ljava/lang/String;)Z
      46: ifne          69
      49: new           #17                 // class java/lang/StringBuilder
      52: dup
      53: invokespecial #18                 // Method java/lang/StringBuilder."<init>":()V
      56: ldc           #15                 // String /
      58: invokevirtual #19                 // Method java/lang/StringBuilder.append:(Ljava/lang/String;)Ljava/lang/StringBuilder;
      61: aload_3
      62: invokevirtual #19                 // Method java/lang/StringBuilder.append:(Ljava/lang/String;)Ljava/lang/StringBuilder;
      65: invokevirtual #20                 // Method java/lang/StringBuilder.toString:()Ljava/lang/String;
      68: astore_3
      69: aload_0
      70: aload_3
      71: putfield      #21                 // Field root:Ljava/lang/String;
      74: aload_0
      75: aload_2
      76: aload_1
      77: invokeinterface #22,  2           // InterfaceMethod org/apache/dubbo/remoting/zookeeper/ZookeeperTransporter.connect:(Lorg/apache/dubbo/common/URL;)Lorg/apache/dubbo/remoting/zookeeper/ZookeeperClient;
      82: putfield      #23                 // Field zkClient:Lorg/apache/dubbo/remoting/zookeeper/ZookeeperClient;
      85: return

  protected java.lang.String toRootDir();
    Code:
       0: aload_0
       1: getfield      #21                 // Field root:Ljava/lang/String;
       4: ldc           #15                 // String /
       6: invokevirtual #24                 // Method java/lang/String.equals:(Ljava/lang/Object;)Z
       9: ifeq          17
      12: aload_0
      13: getfield      #21                 // Field root:Ljava/lang/String;
      16: areturn
      17: new           #17                 // class java/lang/StringBuilder
      20: dup
      21: invokespecial #18                 // Method java/lang/StringBuilder."<init>":()V
      24: aload_0
      25: getfield      #21                 // Field root:Ljava/lang/String;
      28: invokevirtual #19                 // Method java/lang/StringBuilder.append:(Ljava/lang/String;)Ljava/lang/StringBuilder;
      31: ldc           #15                 // String /
      33: invokevirtual #19                 // Method java/lang/StringBuilder.append:(Ljava/lang/String;)Ljava/lang/StringBuilder;
      36: invokevirtual #20                 // Method java/lang/StringBuilder.toString:()Ljava/lang/String;
      39: areturn

  protected void doStoreProviderMetadata(org.apache.dubbo.metadata.report.identifier.MetadataIdentifier, java.lang.String);
    Code:
       0: aload_0
       1: aload_1
       2: aload_2
       3: invokespecial #25                 // Method storeMetadata:(Lorg/apache/dubbo/metadata/report/identifier/MetadataIdentifier;Ljava/lang/String;)V
       6: return

  protected void doStoreConsumerMetadata(org.apache.dubbo.metadata.report.identifier.MetadataIdentifier, java.lang.String);
    Code:
       0: aload_0
       1: aload_1
       2: aload_2
       3: invokespecial #25                 // Method storeMetadata:(Lorg/apache/dubbo/metadata/report/identifier/MetadataIdentifier;Ljava/lang/String;)V
       6: return

  protected void doSaveMetadata(org.apache.dubbo.metadata.report.identifier.ServiceMetadataIdentifier, org.apache.dubbo.common.URL);
    Code:
       0: aload_0
       1: getfield      #23                 // Field zkClient:Lorg/apache/dubbo/remoting/zookeeper/ZookeeperClient;
       4: aload_0
       5: aload_1
       6: invokevirtual #26                 // Method getNodePath:(Lorg/apache/dubbo/metadata/report/identifier/BaseMetadataIdentifier;)Ljava/lang/String;
       9: aload_2
      10: invokevirtual #27                 // Method org/apache/dubbo/common/URL.toFullString:()Ljava/lang/String;
      13: invokestatic  #28                 // Method org/apache/dubbo/common/URL.encode:(Ljava/lang/String;)Ljava/lang/String;
      16: iconst_0
      17: invokeinterface #29,  4           // InterfaceMethod org/apache/dubbo/remoting/zookeeper/ZookeeperClient.createOrUpdate:(Ljava/lang/String;Ljava/lang/String;Z)V
      22: return

  protected void doRemoveMetadata(org.apache.dubbo.metadata.report.identifier.ServiceMetadataIdentifier);
    Code:
       0: aload_0
       1: getfield      #23                 // Field zkClient:Lorg/apache/dubbo/remoting/zookeeper/ZookeeperClient;
       4: aload_0
       5: aload_1
       6: invokevirtual #26                 // Method getNodePath:(Lorg/apache/dubbo/metadata/report/identifier/BaseMetadataIdentifier;)Ljava/lang/String;
       9: invokeinterface #30,  2           // InterfaceMethod org/apache/dubbo/remoting/zookeeper/ZookeeperClient.delete:(Ljava/lang/String;)V
      14: return

  protected java.util.List<java.lang.String> doGetExportedURLs(org.apache.dubbo.metadata.report.identifier.ServiceMetadataIdentifier);
    Code:
       0: aload_0
       1: getfield      #23                 // Field zkClient:Lorg/apache/dubbo/remoting/zookeeper/ZookeeperClient;
       4: aload_0
       5: aload_1
       6: invokevirtual #26                 // Method getNodePath:(Lorg/apache/dubbo/metadata/report/identifier/BaseMetadataIdentifier;)Ljava/lang/String;
       9: invokeinterface #31,  2           // InterfaceMethod org/apache/dubbo/remoting/zookeeper/ZookeeperClient.getContent:(Ljava/lang/String;)Ljava/lang/String;
      14: astore_2
      15: aload_2
      16: invokestatic  #32                 // Method org/apache/dubbo/common/utils/StringUtils.isEmpty:(Ljava/lang/String;)Z
      19: ifeq          26
      22: invokestatic  #33                 // Method java/util/Collections.emptyList:()Ljava/util/List;
      25: areturn
      26: new           #34                 // class java/util/ArrayList
      29: dup
      30: aload_2
      31: invokestatic  #35                 // Method org/apache/dubbo/common/URL.decode:(Ljava/lang/String;)Ljava/lang/String;
      34: invokestatic  #36                 // Method java/util/Collections.singletonList:(Ljava/lang/Object;)Ljava/util/List;
      37: invokespecial #37                 // Method java/util/ArrayList."<init>":(Ljava/util/Collection;)V
      40: areturn

  protected void doSaveSubscriberData(org.apache.dubbo.metadata.report.identifier.SubscriberMetadataIdentifier, java.lang.String);
    Code:
       0: aload_0
       1: getfield      #23                 // Field zkClient:Lorg/apache/dubbo/remoting/zookeeper/ZookeeperClient;
       4: aload_0
       5: aload_1
       6: invokevirtual #26                 // Method getNodePath:(Lorg/apache/dubbo/metadata/report/identifier/BaseMetadataIdentifier;)Ljava/lang/String;
       9: aload_2
      10: iconst_0
      11: invokeinterface #29,  4           // InterfaceMethod org/apache/dubbo/remoting/zookeeper/ZookeeperClient.createOrUpdate:(Ljava/lang/String;Ljava/lang/String;Z)V
      16: return

  protected java.lang.String doGetSubscribedURLs(org.apache.dubbo.metadata.report.identifier.SubscriberMetadataIdentifier);
    Code:
       0: aload_0
       1: getfield      #23                 // Field zkClient:Lorg/apache/dubbo/remoting/zookeeper/ZookeeperClient;
       4: aload_0
       5: aload_1
       6: invokevirtual #26                 // Method getNodePath:(Lorg/apache/dubbo/metadata/report/identifier/BaseMetadataIdentifier;)Ljava/lang/String;
       9: invokeinterface #31,  2           // InterfaceMethod org/apache/dubbo/remoting/zookeeper/ZookeeperClient.getContent:(Ljava/lang/String;)Ljava/lang/String;
      14: areturn

  public java.lang.String getServiceDefinition(org.apache.dubbo.metadata.report.identifier.MetadataIdentifier);
    Code:
       0: aload_0
       1: getfield      #23                 // Field zkClient:Lorg/apache/dubbo/remoting/zookeeper/ZookeeperClient;
       4: aload_0
       5: aload_1
       6: invokevirtual #26                 // Method getNodePath:(Lorg/apache/dubbo/metadata/report/identifier/BaseMetadataIdentifier;)Ljava/lang/String;
       9: invokeinterface #31,  2           // InterfaceMethod org/apache/dubbo/remoting/zookeeper/ZookeeperClient.getContent:(Ljava/lang/String;)Ljava/lang/String;
      14: areturn

  private void storeMetadata(org.apache.dubbo.metadata.report.identifier.MetadataIdentifier, java.lang.String);
    Code:
       0: aload_0
       1: getfield      #23                 // Field zkClient:Lorg/apache/dubbo/remoting/zookeeper/ZookeeperClient;
       4: aload_0
       5: aload_1
       6: invokevirtual #26                 // Method getNodePath:(Lorg/apache/dubbo/metadata/report/identifier/BaseMetadataIdentifier;)Ljava/lang/String;
       9: aload_2
      10: iconst_0
      11: invokeinterface #29,  4           // InterfaceMethod org/apache/dubbo/remoting/zookeeper/ZookeeperClient.createOrUpdate:(Ljava/lang/String;Ljava/lang/String;Z)V
      16: return

  java.lang.String getNodePath(org.apache.dubbo.metadata.report.identifier.BaseMetadataIdentifier);
    Code:
       0: new           #17                 // class java/lang/StringBuilder
       3: dup
       4: invokespecial #18                 // Method java/lang/StringBuilder."<init>":()V
       7: aload_0
       8: invokevirtual #38                 // Method toRootDir:()Ljava/lang/String;
      11: invokevirtual #19                 // Method java/lang/StringBuilder.append:(Ljava/lang/String;)Ljava/lang/StringBuilder;
      14: aload_1
      15: getstatic     #39                 // Field org/apache/dubbo/metadata/report/identifier/KeyTypeEnum.PATH:Lorg/apache/dubbo/metadata/report/identifier/KeyTypeEnum;
      18: invokeinterface #40,  2           // InterfaceMethod org/apache/dubbo/metadata/report/identifier/BaseMetadataIdentifier.getUniqueKey:(Lorg/apache/dubbo/metadata/report/identifier/KeyTypeEnum;)Ljava/lang/String;
      23: invokevirtual #19                 // Method java/lang/StringBuilder.append:(Ljava/lang/String;)Ljava/lang/StringBuilder;
      26: invokevirtual #20                 // Method java/lang/StringBuilder.toString:()Ljava/lang/String;
      29: areturn

  public void publishAppMetadata(org.apache.dubbo.metadata.report.identifier.SubscriberMetadataIdentifier, org.apache.dubbo.metadata.MetadataInfo);
    Code:
       0: aload_0
       1: aload_1
       2: invokevirtual #26                 // Method getNodePath:(Lorg/apache/dubbo/metadata/report/identifier/BaseMetadataIdentifier;)Ljava/lang/String;
       5: astore_3
       6: aload_0
       7: getfield      #23                 // Field zkClient:Lorg/apache/dubbo/remoting/zookeeper/ZookeeperClient;
      10: aload_3
      11: invokeinterface #31,  2           // InterfaceMethod org/apache/dubbo/remoting/zookeeper/ZookeeperClient.getContent:(Ljava/lang/String;)Ljava/lang/String;
      16: invokestatic  #41                 // Method org/apache/dubbo/common/utils/StringUtils.isBlank:(Ljava/lang/CharSequence;)Z
      19: ifeq          47
      22: aload_2
      23: invokevirtual #42                 // Method org/apache/dubbo/metadata/MetadataInfo.getContent:()Ljava/lang/String;
      26: invokestatic  #43                 // Method org/apache/dubbo/common/utils/StringUtils.isNotEmpty:(Ljava/lang/String;)Z
      29: ifeq          47
      32: aload_0
      33: getfield      #23                 // Field zkClient:Lorg/apache/dubbo/remoting/zookeeper/ZookeeperClient;
      36: aload_3
      37: aload_2
      38: invokevirtual #42                 // Method org/apache/dubbo/metadata/MetadataInfo.getContent:()Ljava/lang/String;
      41: iconst_0
      42: invokeinterface #29,  4           // InterfaceMethod org/apache/dubbo/remoting/zookeeper/ZookeeperClient.createOrUpdate:(Ljava/lang/String;Ljava/lang/String;Z)V
      47: return

  public void unPublishAppMetadata(org.apache.dubbo.metadata.report.identifier.SubscriberMetadataIdentifier, org.apache.dubbo.metadata.MetadataInfo);
    Code:
       0: aload_0
       1: aload_1
       2: invokevirtual #26                 // Method getNodePath:(Lorg/apache/dubbo/metadata/report/identifier/BaseMetadataIdentifier;)Ljava/lang/String;
       5: astore_3
       6: aload_0
       7: getfield      #23                 // Field zkClient:Lorg/apache/dubbo/remoting/zookeeper/ZookeeperClient;
      10: aload_3
      11: invokeinterface #31,  2           // InterfaceMethod org/apache/dubbo/remoting/zookeeper/ZookeeperClient.getContent:(Ljava/lang/String;)Ljava/lang/String;
      16: invokestatic  #43                 // Method org/apache/dubbo/common/utils/StringUtils.isNotEmpty:(Ljava/lang/String;)Z
      19: ifeq          32
      22: aload_0
      23: getfield      #23                 // Field zkClient:Lorg/apache/dubbo/remoting/zookeeper/ZookeeperClient;
      26: aload_3
      27: invokeinterface #30,  2           // InterfaceMethod org/apache/dubbo/remoting/zookeeper/ZookeeperClient.delete:(Ljava/lang/String;)V
      32: return

  public org.apache.dubbo.metadata.MetadataInfo getAppMetadata(org.apache.dubbo.metadata.report.identifier.SubscriberMetadataIdentifier, java.util.Map<java.lang.String, java.lang.String>);
    Code:
       0: aload_0
       1: getfield      #23                 // Field zkClient:Lorg/apache/dubbo/remoting/zookeeper/ZookeeperClient;
       4: aload_0
       5: aload_1
       6: invokevirtual #26                 // Method getNodePath:(Lorg/apache/dubbo/metadata/report/identifier/BaseMetadataIdentifier;)Ljava/lang/String;
       9: invokeinterface #31,  2           // InterfaceMethod org/apache/dubbo/remoting/zookeeper/ZookeeperClient.getContent:(Ljava/lang/String;)Ljava/lang/String;
      14: astore_3
      15: aload_3
      16: ldc           #44                 // class org/apache/dubbo/metadata/MetadataInfo
      18: invokestatic  #45                 // Method org/apache/dubbo/common/utils/JsonUtils.toJavaObject:(Ljava/lang/String;Ljava/lang/reflect/Type;)Ljava/lang/Object;
      21: checkcast     #44                 // class org/apache/dubbo/metadata/MetadataInfo
      24: areturn

  public java.util.Set<java.lang.String> getServiceAppMapping(java.lang.String, org.apache.dubbo.metadata.MappingListener, org.apache.dubbo.common.URL);
    Code:
       0: aload_0
       1: ldc           #46                 // String mapping
       3: aload_1
       4: invokespecial #47                 // Method buildPathKey:(Ljava/lang/String;Ljava/lang/String;)Ljava/lang/String;
       7: astore        4
       9: aload_0
      10: getfield      #7                  // Field casListenerMap:Ljava/util/concurrent/ConcurrentMap;
      13: aload         4
      15: aload_0
      16: aload_1
      17: aload         4
      19: invokedynamic #48,  0             // InvokeDynamic #0:apply:(Lorg/apache/dubbo/metadata/store/zookeeper/ZookeeperMetadataReport;Ljava/lang/String;Ljava/lang/String;)Ljava/util/function/Function;
      24: invokestatic  #49                 // Method org/apache/dubbo/common/utils/ConcurrentHashMapUtils.computeIfAbsent:(Ljava/util/concurrent/ConcurrentMap;Ljava/lang/Object;Ljava/util/function/Function;)Ljava/lang/Object;
      27: checkcast     #50                 // class org/apache/dubbo/metadata/store/zookeeper/ZookeeperMetadataReport$MappingDataListener
      30: astore        5
      32: aload         5
      34: aload_2
      35: invokevirtual #51                 // Method org/apache/dubbo/metadata/store/zookeeper/ZookeeperMetadataReport$MappingDataListener.addListener:(Lorg/apache/dubbo/metadata/MappingListener;)V
      38: aload_0
      39: getfield      #23                 // Field zkClient:Lorg/apache/dubbo/remoting/zookeeper/ZookeeperClient;
      42: aload         4
      44: invokeinterface #31,  2           // InterfaceMethod org/apache/dubbo/remoting/zookeeper/ZookeeperClient.getContent:(Ljava/lang/String;)Ljava/lang/String;
      49: invokestatic  #52                 // InterfaceMethod org/apache/dubbo/metadata/ServiceNameMapping.getAppNames:(Ljava/lang/String;)Ljava/util/Set;
      52: areturn

  public void removeServiceAppMappingListener(java.lang.String, org.apache.dubbo.metadata.MappingListener);
    Code:
       0: aload_0
       1: ldc           #46                 // String mapping
       3: aload_1
       4: invokespecial #47                 // Method buildPathKey:(Ljava/lang/String;Ljava/lang/String;)Ljava/lang/String;
       7: astore_3
       8: aconst_null
       9: aload_0
      10: getfield      #7                  // Field casListenerMap:Ljava/util/concurrent/ConcurrentMap;
      13: aload_3
      14: invokeinterface #53,  2           // InterfaceMethod java/util/concurrent/ConcurrentMap.get:(Ljava/lang/Object;)Ljava/lang/Object;
      19: if_acmpeq     28
      22: aload_0
      23: aload_3
      24: aload_2
      25: invokespecial #54                 // Method removeCasServiceMappingListener:(Ljava/lang/String;Lorg/apache/dubbo/metadata/MappingListener;)V
      28: return

  public java.util.Set<java.lang.String> getServiceAppMapping(java.lang.String, org.apache.dubbo.common.URL);
    Code:
       0: aload_0
       1: ldc           #46                 // String mapping
       3: aload_1
       4: invokespecial #47                 // Method buildPathKey:(Ljava/lang/String;Ljava/lang/String;)Ljava/lang/String;
       7: astore_3
       8: aload_0
       9: getfield      #23                 // Field zkClient:Lorg/apache/dubbo/remoting/zookeeper/ZookeeperClient;
      12: aload_3
      13: invokeinterface #31,  2           // InterfaceMethod org/apache/dubbo/remoting/zookeeper/ZookeeperClient.getContent:(Ljava/lang/String;)Ljava/lang/String;
      18: invokestatic  #52                 // InterfaceMethod org/apache/dubbo/metadata/ServiceNameMapping.getAppNames:(Ljava/lang/String;)Ljava/util/Set;
      21: areturn

  public org.apache.dubbo.common.config.configcenter.ConfigItem getConfigItem(java.lang.String, java.lang.String);
    Code:
       0: aload_0
       1: aload_2
       2: aload_1
       3: invokespecial #47                 // Method buildPathKey:(Ljava/lang/String;Ljava/lang/String;)Ljava/lang/String;
       6: astore_3
       7: aload_0
       8: getfield      #23                 // Field zkClient:Lorg/apache/dubbo/remoting/zookeeper/ZookeeperClient;
      11: aload_3
      12: invokeinterface #55,  2           // InterfaceMethod org/apache/dubbo/remoting/zookeeper/ZookeeperClient.getConfigItem:(Ljava/lang/String;)Lorg/apache/dubbo/common/config/configcenter/ConfigItem;
      17: areturn

  public boolean registerServiceAppMapping(java.lang.String, java.lang.String, java.lang.String, java.lang.Object);
    Code:
       0: aload         4
       2: ifnull        23
       5: aload         4
       7: instanceof    #56                 // class org/apache/zookeeper/data/Stat
      10: ifne          23
      13: new           #57                 // class java/lang/IllegalArgumentException
      16: dup
      17: ldc           #58                 // String zookeeper publishConfigCas requires stat type ticket
      19: invokespecial #59                 // Method java/lang/IllegalArgumentException."<init>":(Ljava/lang/String;)V
      22: athrow
      23: aload_0
      24: aload_2
      25: aload_1
      26: invokespecial #47                 // Method buildPathKey:(Ljava/lang/String;Ljava/lang/String;)Ljava/lang/String;
      29: astore        5
      31: aload_0
      32: getfield      #23                 // Field zkClient:Lorg/apache/dubbo/remoting/zookeeper/ZookeeperClient;
      35: aload         5
      37: aload_3
      38: iconst_0
      39: aload         4
      41: ifnonnull     48
      44: aconst_null
      45: goto          59
      48: aload         4
      50: checkcast     #56                 // class org/apache/zookeeper/data/Stat
      53: invokevirtual #60                 // Method org/apache/zookeeper/data/Stat.getVersion:()I
      56: invokestatic  #61                 // Method java/lang/Integer.valueOf:(I)Ljava/lang/Integer;
      59: invokeinterface #62,  5           // InterfaceMethod org/apache/dubbo/remoting/zookeeper/ZookeeperClient.createOrUpdate:(Ljava/lang/String;Ljava/lang/String;ZLjava/lang/Integer;)V
      64: iconst_1
      65: ireturn
      66: astore        5
      68: getstatic     #64                 // Field logger:Lorg/apache/dubbo/common/logger/ErrorTypeAwareLogger;
      71: ldc           #65                 // String 1-35
      73: ldc           #66                 // String
      75: ldc           #66                 // String
      77: ldc           #67                 // String zookeeper publishConfigCas failed.
      79: aload         5
      81: invokeinterface #68,  6           // InterfaceMethod org/apache/dubbo/common/logger/ErrorTypeAwareLogger.warn:(Ljava/lang/String;Ljava/lang/String;Ljava/lang/String;Ljava/lang/String;Ljava/lang/Throwable;)V
      86: iconst_0
      87: ireturn
    Exception table:
       from    to  target type
           0    65    66   Class java/lang/Exception

  public void destroy();
    Code:
       0: aload_0
       1: invokespecial #69                 // Method org/apache/dubbo/metadata/report/support/AbstractMetadataReport.destroy:()V
       4: aload_0
       5: aconst_null
       6: putfield      #23                 // Field zkClient:Lorg/apache/dubbo/remoting/zookeeper/ZookeeperClient;
       9: return

  private java.lang.String buildPathKey(java.lang.String, java.lang.String);
    Code:
       0: new           #17                 // class java/lang/StringBuilder
       3: dup
       4: invokespecial #18                 // Method java/lang/StringBuilder."<init>":()V
       7: aload_0
       8: invokevirtual #38                 // Method toRootDir:()Ljava/lang/String;
      11: invokevirtual #19                 // Method java/lang/StringBuilder.append:(Ljava/lang/String;)Ljava/lang/StringBuilder;
      14: aload_1
      15: invokevirtual #19                 // Method java/lang/StringBuilder.append:(Ljava/lang/String;)Ljava/lang/StringBuilder;
      18: ldc           #15                 // String /
      20: invokevirtual #19                 // Method java/lang/StringBuilder.append:(Ljava/lang/String;)Ljava/lang/StringBuilder;
      23: aload_2
      24: invokevirtual #19                 // Method java/lang/StringBuilder.append:(Ljava/lang/String;)Ljava/lang/StringBuilder;
      27: invokevirtual #20                 // Method java/lang/StringBuilder.toString:()Ljava/lang/String;
      30: areturn

  private void removeCasServiceMappingListener(java.lang.String, org.apache.dubbo.metadata.MappingListener);
    Code:
       0: aload_0
       1: getfield      #7                  // Field casListenerMap:Ljava/util/concurrent/ConcurrentMap;
       4: aload_1
       5: invokeinterface #53,  2           // InterfaceMethod java/util/concurrent/ConcurrentMap.get:(Ljava/lang/Object;)Ljava/lang/Object;
      10: checkcast     #50                 // class org/apache/dubbo/metadata/store/zookeeper/ZookeeperMetadataReport$MappingDataListener
      13: astore_3
      14: aload_3
      15: aload_2
      16: invokevirtual #70                 // Method org/apache/dubbo/metadata/store/zookeeper/ZookeeperMetadataReport$MappingDataListener.removeListener:(Lorg/apache/dubbo/metadata/MappingListener;)V
      19: aload_3
      20: invokevirtual #71                 // Method org/apache/dubbo/metadata/store/zookeeper/ZookeeperMetadataReport$MappingDataListener.isEmpty:()Z
      23: ifeq          49
      26: aload_0
      27: getfield      #23                 // Field zkClient:Lorg/apache/dubbo/remoting/zookeeper/ZookeeperClient;
      30: aload_1
      31: aload_3
      32: invokeinterface #72,  3           // InterfaceMethod org/apache/dubbo/remoting/zookeeper/ZookeeperClient.removeDataListener:(Ljava/lang/String;Lorg/apache/dubbo/remoting/zookeeper/DataListener;)V
      37: aload_0
      38: getfield      #7                  // Field casListenerMap:Ljava/util/concurrent/ConcurrentMap;
      41: aload_1
      42: aload_3
      43: invokeinterface #73,  3           // InterfaceMethod java/util/concurrent/ConcurrentMap.remove:(Ljava/lang/Object;Ljava/lang/Object;)Z
      48: pop
      49: return

  private org.apache.dubbo.metadata.store.zookeeper.ZookeeperMetadataReport$MappingDataListener lambda$getServiceAppMapping$0(java.lang.String, java.lang.String, java.lang.String);
    Code:
       0: new           #50                 // class org/apache/dubbo/metadata/store/zookeeper/ZookeeperMetadataReport$MappingDataListener
       3: dup
       4: aload_1
       5: aload_2
       6: invokespecial #74                 // Method org/apache/dubbo/metadata/store/zookeeper/ZookeeperMetadataReport$MappingDataListener."<init>":(Ljava/lang/String;Ljava/lang/String;)V
       9: astore        4
      11: aload_0
      12: getfield      #23                 // Field zkClient:Lorg/apache/dubbo/remoting/zookeeper/ZookeeperClient;
      15: aload_2
      16: aload         4
      18: invokeinterface #75,  3           // InterfaceMethod org/apache/dubbo/remoting/zookeeper/ZookeeperClient.addDataListener:(Ljava/lang/String;Lorg/apache/dubbo/remoting/zookeeper/DataListener;)V
      23: aload         4
      25: areturn

  static {};
    Code:
       0: ldc           #76                 // class org/apache/dubbo/metadata/store/zookeeper/ZookeeperMetadataReport
       2: invokestatic  #77                 // Method org/apache/dubbo/common/logger/LoggerFactory.getErrorTypeAwareLogger:(Ljava/lang/Class;)Lorg/apache/dubbo/common/logger/ErrorTypeAwareLogger;
       5: putstatic     #64                 // Field logger:Lorg/apache/dubbo/common/logger/ErrorTypeAwareLogger;
       8: return
}
