Compiled from "ZookeeperMetadataReportFactory.java"
public class org.apache.dubbo.metadata.store.zookeeper.ZookeeperMetadataReportFactory extends org.apache.dubbo.metadata.report.support.AbstractMetadataReportFactory {
  private org.apache.dubbo.remoting.zookeeper.ZookeeperTransporter zookeeperTransporter;

  private org.apache.dubbo.rpc.model.ApplicationModel applicationModel;

  public org.apache.dubbo.metadata.store.zookeeper.ZookeeperMetadataReportFactory(org.apache.dubbo.rpc.model.ApplicationModel);
    Code:
       0: aload_0
       1: invokespecial #1                  // Method org/apache/dubbo/metadata/report/support/AbstractMetadataReportFactory."<init>":()V
       4: aload_0
       5: aload_1
       6: putfield      #2                  // Field applicationModel:Lorg/apache/dubbo/rpc/model/ApplicationModel;
       9: aload_0
      10: aload_1
      11: invokestatic  #3                  // InterfaceMethod org/apache/dubbo/remoting/zookeeper/ZookeeperTransporter.getExtension:(Lorg/apache/dubbo/rpc/model/ApplicationModel;)Lorg/apache/dubbo/remoting/zookeeper/ZookeeperTransporter;
      14: putfield      #4                  // Field zookeeperTransporter:Lorg/apache/dubbo/remoting/zookeeper/ZookeeperTransporter;
      17: return

  public void setZookeeperTransporter(org.apache.dubbo.remoting.zookeeper.ZookeeperTransporter);
    Code:
       0: aload_0
       1: aload_1
       2: putfield      #4                  // Field zookeeperTransporter:Lorg/apache/dubbo/remoting/zookeeper/ZookeeperTransporter;
       5: return

  public org.apache.dubbo.metadata.report.MetadataReport createMetadataReport(org.apache.dubbo.common.URL);
    Code:
       0: new           #5                  // class org/apache/dubbo/metadata/store/zookeeper/ZookeeperMetadataReport
       3: dup
       4: aload_1
       5: aload_0
       6: getfield      #4                  // Field zookeeperTransporter:Lorg/apache/dubbo/remoting/zookeeper/ZookeeperTransporter;
       9: invokespecial #6                  // Method org/apache/dubbo/metadata/store/zookeeper/ZookeeperMetadataReport."<init>":(Lorg/apache/dubbo/common/URL;Lorg/apache/dubbo/remoting/zookeeper/ZookeeperTransporter;)V
      12: areturn
}
