Compiled from "ProfilerEntry.java"
public class org.apache.dubbo.common.profiler.ProfilerEntry {
  private final java.util.List<org.apache.dubbo.common.profiler.ProfilerEntry> sub;

  private final java.lang.String message;

  private final org.apache.dubbo.common.profiler.ProfilerEntry parent;

  private final org.apache.dubbo.common.profiler.ProfilerEntry first;

  private final long startTime;

  private final java.util.concurrent.atomic.AtomicInteger requestCount;

  private long endTime;

  public org.apache.dubbo.common.profiler.ProfilerEntry(java.lang.String);
    Code:
       0: aload_0
       1: invokespecial #1                  // Method java/lang/Object."<init>":()V
       4: aload_0
       5: new           #2                  // class java/util/ArrayList
       8: dup
       9: iconst_4
      10: invokespecial #3                  // Method java/util/ArrayList."<init>":(I)V
      13: putfield      #4                  // Field sub:Ljava/util/List;
      16: aload_0
      17: aload_1
      18: putfield      #5                  // Field message:Ljava/lang/String;
      21: aload_0
      22: aconst_null
      23: putfield      #6                  // Field parent:Lorg/apache/dubbo/common/profiler/ProfilerEntry;
      26: aload_0
      27: aload_0
      28: putfield      #7                  // Field first:Lorg/apache/dubbo/common/profiler/ProfilerEntry;
      31: aload_0
      32: invokestatic  #8                  // Method java/lang/System.nanoTime:()J
      35: putfield      #9                  // Field startTime:J
      38: aload_0
      39: new           #10                 // class java/util/concurrent/atomic/AtomicInteger
      42: dup
      43: iconst_1
      44: invokespecial #11                 // Method java/util/concurrent/atomic/AtomicInteger."<init>":(I)V
      47: putfield      #12                 // Field requestCount:Ljava/util/concurrent/atomic/AtomicInteger;
      50: return

  public org.apache.dubbo.common.profiler.ProfilerEntry(java.lang.String, org.apache.dubbo.common.profiler.ProfilerEntry, org.apache.dubbo.common.profiler.ProfilerEntry);
    Code:
       0: aload_0
       1: invokespecial #1                  // Method java/lang/Object."<init>":()V
       4: aload_0
       5: new           #2                  // class java/util/ArrayList
       8: dup
       9: iconst_4
      10: invokespecial #3                  // Method java/util/ArrayList."<init>":(I)V
      13: putfield      #4                  // Field sub:Ljava/util/List;
      16: aload_0
      17: aload_1
      18: putfield      #5                  // Field message:Ljava/lang/String;
      21: aload_0
      22: aload_2
      23: putfield      #6                  // Field parent:Lorg/apache/dubbo/common/profiler/ProfilerEntry;
      26: aload_0
      27: aload_3
      28: putfield      #7                  // Field first:Lorg/apache/dubbo/common/profiler/ProfilerEntry;
      31: aload_0
      32: invokestatic  #8                  // Method java/lang/System.nanoTime:()J
      35: putfield      #9                  // Field startTime:J
      38: aload_0
      39: aload_2
      40: invokevirtual #13                 // Method getRequestCount:()Ljava/util/concurrent/atomic/AtomicInteger;
      43: putfield      #12                 // Field requestCount:Ljava/util/concurrent/atomic/AtomicInteger;
      46: return

  public java.util.List<org.apache.dubbo.common.profiler.ProfilerEntry> getSub();
    Code:
       0: aload_0
       1: getfield      #4                  // Field sub:Ljava/util/List;
       4: areturn

  public java.lang.String getMessage();
    Code:
       0: aload_0
       1: getfield      #5                  // Field message:Ljava/lang/String;
       4: areturn

  public org.apache.dubbo.common.profiler.ProfilerEntry getParent();
    Code:
       0: aload_0
       1: getfield      #6                  // Field parent:Lorg/apache/dubbo/common/profiler/ProfilerEntry;
       4: areturn

  public org.apache.dubbo.common.profiler.ProfilerEntry getFirst();
    Code:
       0: aload_0
       1: getfield      #7                  // Field first:Lorg/apache/dubbo/common/profiler/ProfilerEntry;
       4: areturn

  public long getStartTime();
    Code:
       0: aload_0
       1: getfield      #9                  // Field startTime:J
       4: lreturn

  public void setEndTime(long);
    Code:
       0: aload_0
       1: lload_1
       2: putfield      #14                 // Field endTime:J
       5: return

  public long getEndTime();
    Code:
       0: aload_0
       1: getfield      #14                 // Field endTime:J
       4: lreturn

  public java.util.concurrent.atomic.AtomicInteger getRequestCount();
    Code:
       0: aload_0
       1: getfield      #12                 // Field requestCount:Ljava/util/concurrent/atomic/AtomicInteger;
       4: areturn
}
