Compiled from "ProfilerSwitch.java"
public class org.apache.dubbo.common.profiler.ProfilerSwitch {
  private static final java.util.concurrent.atomic.AtomicBoolean enableDetailProfiler;

  private static final java.util.concurrent.atomic.AtomicBoolean enableSimpleProfiler;

  private static final java.util.concurrent.atomic.AtomicReference<java.lang.Double> warnPercent;

  public org.apache.dubbo.common.profiler.ProfilerSwitch();
    Code:
       0: aload_0
       1: invokespecial #1                  // Method java/lang/Object."<init>":()V
       4: return

  public static void enableSimpleProfiler();
    Code:
       0: getstatic     #2                  // Field enableSimpleProfiler:Ljava/util/concurrent/atomic/AtomicBoolean;
       3: iconst_1
       4: invokevirtual #3                  // Method java/util/concurrent/atomic/AtomicBoolean.set:(Z)V
       7: return

  public static void disableSimpleProfiler();
    Code:
       0: getstatic     #2                  // Field enableSimpleProfiler:Ljava/util/concurrent/atomic/AtomicBoolean;
       3: iconst_0
       4: invokevirtual #3                  // Method java/util/concurrent/atomic/AtomicBoolean.set:(Z)V
       7: return

  public static void enableDetailProfiler();
    Code:
       0: getstatic     #4                  // Field enableDetailProfiler:Ljava/util/concurrent/atomic/AtomicBoolean;
       3: iconst_1
       4: invokevirtual #3                  // Method java/util/concurrent/atomic/AtomicBoolean.set:(Z)V
       7: return

  public static void disableDetailProfiler();
    Code:
       0: getstatic     #4                  // Field enableDetailProfiler:Ljava/util/concurrent/atomic/AtomicBoolean;
       3: iconst_0
       4: invokevirtual #3                  // Method java/util/concurrent/atomic/AtomicBoolean.set:(Z)V
       7: return

  public static boolean isEnableDetailProfiler();
    Code:
       0: getstatic     #4                  // Field enableDetailProfiler:Ljava/util/concurrent/atomic/AtomicBoolean;
       3: invokevirtual #5                  // Method java/util/concurrent/atomic/AtomicBoolean.get:()Z
       6: ifeq          22
       9: getstatic     #2                  // Field enableSimpleProfiler:Ljava/util/concurrent/atomic/AtomicBoolean;
      12: invokevirtual #5                  // Method java/util/concurrent/atomic/AtomicBoolean.get:()Z
      15: ifeq          22
      18: iconst_1
      19: goto          23
      22: iconst_0
      23: ireturn

  public static boolean isEnableSimpleProfiler();
    Code:
       0: getstatic     #2                  // Field enableSimpleProfiler:Ljava/util/concurrent/atomic/AtomicBoolean;
       3: invokevirtual #5                  // Method java/util/concurrent/atomic/AtomicBoolean.get:()Z
       6: ireturn

  public static double getWarnPercent();
    Code:
       0: getstatic     #6                  // Field warnPercent:Ljava/util/concurrent/atomic/AtomicReference;
       3: invokevirtual #7                  // Method java/util/concurrent/atomic/AtomicReference.get:()Ljava/lang/Object;
       6: checkcast     #8                  // class java/lang/Double
       9: invokevirtual #9                  // Method java/lang/Double.doubleValue:()D
      12: dreturn

  public static void setWarnPercent(double);
    Code:
       0: getstatic     #6                  // Field warnPercent:Ljava/util/concurrent/atomic/AtomicReference;
       3: dload_0
       4: invokestatic  #10                 // Method java/lang/Double.valueOf:(D)Ljava/lang/Double;
       7: invokevirtual #11                 // Method java/util/concurrent/atomic/AtomicReference.set:(Ljava/lang/Object;)V
      10: return

  static {};
    Code:
       0: new           #12                 // class java/util/concurrent/atomic/AtomicBoolean
       3: dup
       4: iconst_0
       5: invokespecial #13                 // Method java/util/concurrent/atomic/AtomicBoolean."<init>":(Z)V
       8: putstatic     #4                  // Field enableDetailProfiler:Ljava/util/concurrent/atomic/AtomicBoolean;
      11: new           #12                 // class java/util/concurrent/atomic/AtomicBoolean
      14: dup
      15: iconst_1
      16: invokespecial #13                 // Method java/util/concurrent/atomic/AtomicBoolean."<init>":(Z)V
      19: putstatic     #2                  // Field enableSimpleProfiler:Ljava/util/concurrent/atomic/AtomicBoolean;
      22: new           #14                 // class java/util/concurrent/atomic/AtomicReference
      25: dup
      26: ldc2_w        #15                 // double 0.75d
      29: invokestatic  #10                 // Method java/lang/Double.valueOf:(D)Ljava/lang/Double;
      32: invokespecial #17                 // Method java/util/concurrent/atomic/AtomicReference."<init>":(Ljava/lang/Object;)V
      35: putstatic     #6                  // Field warnPercent:Ljava/util/concurrent/atomic/AtomicReference;
      38: return
}
