Compiled from "Profiler.java"
public class org.apache.dubbo.common.profiler.Profiler {
  public static final java.lang.String PROFILER_KEY;

  public static final int MAX_ENTRY_SIZE;

  private static final org.apache.dubbo.common.threadlocal.InternalThreadLocal<org.apache.dubbo.common.profiler.ProfilerEntry> bizProfiler;

  public org.apache.dubbo.common.profiler.Profiler();
    Code:
       0: aload_0
       1: invokespecial #1                  // Method java/lang/Object."<init>":()V
       4: return

  public static org.apache.dubbo.common.profiler.ProfilerEntry start(java.lang.String);
    Code:
       0: new           #2                  // class org/apache/dubbo/common/profiler/ProfilerEntry
       3: dup
       4: aload_0
       5: invokespecial #3                  // Method org/apache/dubbo/common/profiler/ProfilerEntry."<init>":(Ljava/lang/String;)V
       8: areturn

  public static org.apache.dubbo.common.profiler.ProfilerEntry enter(org.apache.dubbo.common.profiler.ProfilerEntry, java.lang.String);
    Code:
       0: new           #2                  // class org/apache/dubbo/common/profiler/ProfilerEntry
       3: dup
       4: aload_1
       5: aload_0
       6: aload_0
       7: invokevirtual #4                  // Method org/apache/dubbo/common/profiler/ProfilerEntry.getFirst:()Lorg/apache/dubbo/common/profiler/ProfilerEntry;
      10: invokespecial #5                  // Method org/apache/dubbo/common/profiler/ProfilerEntry."<init>":(Ljava/lang/String;Lorg/apache/dubbo/common/profiler/ProfilerEntry;Lorg/apache/dubbo/common/profiler/ProfilerEntry;)V
      13: astore_2
      14: aload_2
      15: invokevirtual #6                  // Method org/apache/dubbo/common/profiler/ProfilerEntry.getRequestCount:()Ljava/util/concurrent/atomic/AtomicInteger;
      18: invokevirtual #7                  // Method java/util/concurrent/atomic/AtomicInteger.incrementAndGet:()I
      21: sipush        1000
      24: if_icmpge     38
      27: aload_0
      28: invokevirtual #9                  // Method org/apache/dubbo/common/profiler/ProfilerEntry.getSub:()Ljava/util/List;
      31: aload_2
      32: invokeinterface #10,  2           // InterfaceMethod java/util/List.add:(Ljava/lang/Object;)Z
      37: pop
      38: aload_2
      39: areturn

  public static org.apache.dubbo.common.profiler.ProfilerEntry release(org.apache.dubbo.common.profiler.ProfilerEntry);
    Code:
       0: aload_0
       1: invokestatic  #11                 // Method java/lang/System.nanoTime:()J
       4: invokevirtual #12                 // Method org/apache/dubbo/common/profiler/ProfilerEntry.setEndTime:(J)V
       7: aload_0
       8: invokevirtual #13                 // Method org/apache/dubbo/common/profiler/ProfilerEntry.getParent:()Lorg/apache/dubbo/common/profiler/ProfilerEntry;
      11: astore_1
      12: aload_1
      13: ifnull        18
      16: aload_1
      17: areturn
      18: aload_0
      19: areturn

  public static org.apache.dubbo.common.profiler.ProfilerEntry setToBizProfiler(org.apache.dubbo.common.profiler.ProfilerEntry);
    Code:
       0: getstatic     #14                 // Field bizProfiler:Lorg/apache/dubbo/common/threadlocal/InternalThreadLocal;
       3: invokevirtual #15                 // Method org/apache/dubbo/common/threadlocal/InternalThreadLocal.get:()Ljava/lang/Object;
       6: checkcast     #2                  // class org/apache/dubbo/common/profiler/ProfilerEntry
       9: astore_1
      10: getstatic     #14                 // Field bizProfiler:Lorg/apache/dubbo/common/threadlocal/InternalThreadLocal;
      13: aload_0
      14: invokevirtual #16                 // Method org/apache/dubbo/common/threadlocal/InternalThreadLocal.set:(Ljava/lang/Object;)V
      17: aload_1
      18: areturn
      19: astore_2
      20: getstatic     #14                 // Field bizProfiler:Lorg/apache/dubbo/common/threadlocal/InternalThreadLocal;
      23: aload_0
      24: invokevirtual #16                 // Method org/apache/dubbo/common/threadlocal/InternalThreadLocal.set:(Ljava/lang/Object;)V
      27: aload_2
      28: athrow
    Exception table:
       from    to  target type
           0    10    19   any

  public static org.apache.dubbo.common.profiler.ProfilerEntry getBizProfiler();
    Code:
       0: getstatic     #14                 // Field bizProfiler:Lorg/apache/dubbo/common/threadlocal/InternalThreadLocal;
       3: invokevirtual #15                 // Method org/apache/dubbo/common/threadlocal/InternalThreadLocal.get:()Ljava/lang/Object;
       6: checkcast     #2                  // class org/apache/dubbo/common/profiler/ProfilerEntry
       9: areturn

  public static void removeBizProfiler();
    Code:
       0: getstatic     #14                 // Field bizProfiler:Lorg/apache/dubbo/common/threadlocal/InternalThreadLocal;
       3: invokevirtual #17                 // Method org/apache/dubbo/common/threadlocal/InternalThreadLocal.remove:()V
       6: return

  public static java.lang.String buildDetail(org.apache.dubbo.common.profiler.ProfilerEntry);
    Code:
       0: aload_0
       1: invokevirtual #18                 // Method org/apache/dubbo/common/profiler/ProfilerEntry.getEndTime:()J
       4: aload_0
       5: invokevirtual #19                 // Method org/apache/dubbo/common/profiler/ProfilerEntry.getStartTime:()J
       8: lsub
       9: lstore_1
      10: new           #20                 // class java/lang/StringBuilder
      13: dup
      14: invokespecial #21                 // Method java/lang/StringBuilder."<init>":()V
      17: ldc           #22                 // String Start time:
      19: invokevirtual #23                 // Method java/lang/StringBuilder.append:(Ljava/lang/String;)Ljava/lang/StringBuilder;
      22: aload_0
      23: invokevirtual #19                 // Method org/apache/dubbo/common/profiler/ProfilerEntry.getStartTime:()J
      26: invokevirtual #24                 // Method java/lang/StringBuilder.append:(J)Ljava/lang/StringBuilder;
      29: ldc           #25                 // String \n
      31: invokevirtual #23                 // Method java/lang/StringBuilder.append:(Ljava/lang/String;)Ljava/lang/StringBuilder;
      34: ldc           #25                 // String \n
      36: aload_0
      37: aload_0
      38: invokevirtual #19                 // Method org/apache/dubbo/common/profiler/ProfilerEntry.getStartTime:()J
      41: lload_1
      42: iconst_0
      43: invokestatic  #26                 // Method buildDetail:(Lorg/apache/dubbo/common/profiler/ProfilerEntry;JJI)Ljava/util/List;
      46: invokestatic  #27                 // Method java/lang/String.join:(Ljava/lang/CharSequence;Ljava/lang/Iterable;)Ljava/lang/String;
      49: invokevirtual #23                 // Method java/lang/StringBuilder.append:(Ljava/lang/String;)Ljava/lang/StringBuilder;
      52: invokevirtual #28                 // Method java/lang/StringBuilder.toString:()Ljava/lang/String;
      55: areturn

  public static java.util.List<java.lang.String> buildDetail(org.apache.dubbo.common.profiler.ProfilerEntry, long, long, int);
    Code:
       0: new           #20                 // class java/lang/StringBuilder
       3: dup
       4: invokespecial #21                 // Method java/lang/StringBuilder."<init>":()V
       7: astore        6
       9: aload_0
      10: invokevirtual #18                 // Method org/apache/dubbo/common/profiler/ProfilerEntry.getEndTime:()J
      13: aload_0
      14: invokevirtual #19                 // Method org/apache/dubbo/common/profiler/ProfilerEntry.getStartTime:()J
      17: lsub
      18: lstore        7
      20: lload         7
      22: ldc2_w        #29                 // long 100l
      25: lmul
      26: lload_3
      27: ldiv
      28: l2i
      29: istore        9
      31: aload_0
      32: invokevirtual #19                 // Method org/apache/dubbo/common/profiler/ProfilerEntry.getStartTime:()J
      35: lload_1
      36: lsub
      37: lstore        10
      39: new           #31                 // class java/util/LinkedList
      42: dup
      43: invokespecial #32                 // Method java/util/LinkedList."<init>":()V
      46: astore        12
      48: aload         6
      50: ldc           #33                 // String +-[ Offset:
      52: invokevirtual #23                 // Method java/lang/StringBuilder.append:(Ljava/lang/String;)Ljava/lang/StringBuilder;
      55: lload         10
      57: ldc2_w        #34                 // long 1000000l
      60: ldiv
      61: invokevirtual #24                 // Method java/lang/StringBuilder.append:(J)Ljava/lang/StringBuilder;
      64: bipush        46
      66: invokevirtual #36                 // Method java/lang/StringBuilder.append:(C)Ljava/lang/StringBuilder;
      69: ldc           #37                 // String %06d
      71: iconst_1
      72: anewarray     #38                 // class java/lang/Object
      75: dup
      76: iconst_0
      77: lload         10
      79: ldc2_w        #34                 // long 1000000l
      82: lrem
      83: invokestatic  #39                 // Method java/lang/Long.valueOf:(J)Ljava/lang/Long;
      86: aastore
      87: invokestatic  #40                 // Method java/lang/String.format:(Ljava/lang/String;[Ljava/lang/Object;)Ljava/lang/String;
      90: invokevirtual #23                 // Method java/lang/StringBuilder.append:(Ljava/lang/String;)Ljava/lang/StringBuilder;
      93: ldc           #41                 // String ms; Usage:
      95: invokevirtual #23                 // Method java/lang/StringBuilder.append:(Ljava/lang/String;)Ljava/lang/StringBuilder;
      98: lload         7
     100: ldc2_w        #34                 // long 1000000l
     103: ldiv
     104: invokevirtual #24                 // Method java/lang/StringBuilder.append:(J)Ljava/lang/StringBuilder;
     107: bipush        46
     109: invokevirtual #36                 // Method java/lang/StringBuilder.append:(C)Ljava/lang/StringBuilder;
     112: ldc           #37                 // String %06d
     114: iconst_1
     115: anewarray     #38                 // class java/lang/Object
     118: dup
     119: iconst_0
     120: lload         7
     122: ldc2_w        #34                 // long 1000000l
     125: lrem
     126: invokestatic  #39                 // Method java/lang/Long.valueOf:(J)Ljava/lang/Long;
     129: aastore
     130: invokestatic  #40                 // Method java/lang/String.format:(Ljava/lang/String;[Ljava/lang/Object;)Ljava/lang/String;
     133: invokevirtual #23                 // Method java/lang/StringBuilder.append:(Ljava/lang/String;)Ljava/lang/StringBuilder;
     136: ldc           #42                 // String ms,
     138: invokevirtual #23                 // Method java/lang/StringBuilder.append:(Ljava/lang/String;)Ljava/lang/StringBuilder;
     141: iload         9
     143: invokevirtual #43                 // Method java/lang/StringBuilder.append:(I)Ljava/lang/StringBuilder;
     146: ldc           #44                 // String % ]
     148: invokevirtual #23                 // Method java/lang/StringBuilder.append:(Ljava/lang/String;)Ljava/lang/StringBuilder;
     151: aload_0
     152: invokevirtual #45                 // Method org/apache/dubbo/common/profiler/ProfilerEntry.getMessage:()Ljava/lang/String;
     155: invokevirtual #23                 // Method java/lang/StringBuilder.append:(Ljava/lang/String;)Ljava/lang/StringBuilder;
     158: pop
     159: aload         12
     161: aload         6
     163: invokevirtual #28                 // Method java/lang/StringBuilder.toString:()Ljava/lang/String;
     166: invokeinterface #10,  2           // InterfaceMethod java/util/List.add:(Ljava/lang/Object;)Z
     171: pop
     172: aload_0
     173: invokevirtual #9                  // Method org/apache/dubbo/common/profiler/ProfilerEntry.getSub:()Ljava/util/List;
     176: astore        13
     178: iconst_0
     179: istore        14
     181: aload         13
     183: invokeinterface #46,  1           // InterfaceMethod java/util/List.size:()I
     188: istore        15
     190: iload         14
     192: iload         15
     194: if_icmpge     450
     197: aload         13
     199: iload         14
     201: invokeinterface #47,  2           // InterfaceMethod java/util/List.get:(I)Ljava/lang/Object;
     206: checkcast     #2                  // class org/apache/dubbo/common/profiler/ProfilerEntry
     209: astore        16
     211: aload         16
     213: lload_1
     214: lload_3
     215: iload         5
     217: iconst_1
     218: iadd
     219: invokestatic  #26                 // Method buildDetail:(Lorg/apache/dubbo/common/profiler/ProfilerEntry;JJI)Ljava/util/List;
     222: astore        17
     224: iload         14
     226: iload         15
     228: iconst_1
     229: isub
     230: if_icmpge     340
     233: aload         12
     235: new           #20                 // class java/lang/StringBuilder
     238: dup
     239: invokespecial #21                 // Method java/lang/StringBuilder."<init>":()V
     242: ldc           #48                 // String
     244: invokevirtual #23                 // Method java/lang/StringBuilder.append:(Ljava/lang/String;)Ljava/lang/StringBuilder;
     247: aload         17
     249: iconst_0
     250: invokeinterface #47,  2           // InterfaceMethod java/util/List.get:(I)Ljava/lang/Object;
     255: checkcast     #49                 // class java/lang/String
     258: invokevirtual #23                 // Method java/lang/StringBuilder.append:(Ljava/lang/String;)Ljava/lang/StringBuilder;
     261: invokevirtual #28                 // Method java/lang/StringBuilder.toString:()Ljava/lang/String;
     264: invokeinterface #10,  2           // InterfaceMethod java/util/List.add:(Ljava/lang/Object;)Z
     269: pop
     270: iconst_1
     271: istore        18
     273: aload         17
     275: invokeinterface #46,  1           // InterfaceMethod java/util/List.size:()I
     280: istore        19
     282: iload         18
     284: iload         19
     286: if_icmpge     337
     289: aload         17
     291: iload         18
     293: invokeinterface #47,  2           // InterfaceMethod java/util/List.get:(I)Ljava/lang/Object;
     298: checkcast     #49                 // class java/lang/String
     301: astore        20
     303: aload         12
     305: new           #20                 // class java/lang/StringBuilder
     308: dup
     309: invokespecial #21                 // Method java/lang/StringBuilder."<init>":()V
     312: ldc           #50                 // String   |
     314: invokevirtual #23                 // Method java/lang/StringBuilder.append:(Ljava/lang/String;)Ljava/lang/StringBuilder;
     317: aload         20
     319: invokevirtual #23                 // Method java/lang/StringBuilder.append:(Ljava/lang/String;)Ljava/lang/StringBuilder;
     322: invokevirtual #28                 // Method java/lang/StringBuilder.toString:()Ljava/lang/String;
     325: invokeinterface #10,  2           // InterfaceMethod java/util/List.add:(Ljava/lang/Object;)Z
     330: pop
     331: iinc          18, 1
     334: goto          282
     337: goto          444
     340: aload         12
     342: new           #20                 // class java/lang/StringBuilder
     345: dup
     346: invokespecial #21                 // Method java/lang/StringBuilder."<init>":()V
     349: ldc           #48                 // String
     351: invokevirtual #23                 // Method java/lang/StringBuilder.append:(Ljava/lang/String;)Ljava/lang/StringBuilder;
     354: aload         17
     356: iconst_0
     357: invokeinterface #47,  2           // InterfaceMethod java/util/List.get:(I)Ljava/lang/Object;
     362: checkcast     #49                 // class java/lang/String
     365: invokevirtual #23                 // Method java/lang/StringBuilder.append:(Ljava/lang/String;)Ljava/lang/StringBuilder;
     368: invokevirtual #28                 // Method java/lang/StringBuilder.toString:()Ljava/lang/String;
     371: invokeinterface #10,  2           // InterfaceMethod java/util/List.add:(Ljava/lang/Object;)Z
     376: pop
     377: iconst_1
     378: istore        18
     380: aload         17
     382: invokeinterface #46,  1           // InterfaceMethod java/util/List.size:()I
     387: istore        19
     389: iload         18
     391: iload         19
     393: if_icmpge     444
     396: aload         17
     398: iload         18
     400: invokeinterface #47,  2           // InterfaceMethod java/util/List.get:(I)Ljava/lang/Object;
     405: checkcast     #49                 // class java/lang/String
     408: astore        20
     410: aload         12
     412: new           #20                 // class java/lang/StringBuilder
     415: dup
     416: invokespecial #21                 // Method java/lang/StringBuilder."<init>":()V
     419: ldc           #51                 // String
     421: invokevirtual #23                 // Method java/lang/StringBuilder.append:(Ljava/lang/String;)Ljava/lang/StringBuilder;
     424: aload         20
     426: invokevirtual #23                 // Method java/lang/StringBuilder.append:(Ljava/lang/String;)Ljava/lang/StringBuilder;
     429: invokevirtual #28                 // Method java/lang/StringBuilder.toString:()Ljava/lang/String;
     432: invokeinterface #10,  2           // InterfaceMethod java/util/List.add:(Ljava/lang/Object;)Z
     437: pop
     438: iinc          18, 1
     441: goto          389
     444: iinc          14, 1
     447: goto          190
     450: aload         12
     452: areturn

  static {};
    Code:
       0: new           #52                 // class org/apache/dubbo/common/threadlocal/InternalThreadLocal
       3: dup
       4: invokespecial #53                 // Method org/apache/dubbo/common/threadlocal/InternalThreadLocal."<init>":()V
       7: putstatic     #14                 // Field bizProfiler:Lorg/apache/dubbo/common/threadlocal/InternalThreadLocal;
      10: return
}
