Compiled from "DubboHealthTriple.java"
public abstract class io.grpc.health.v1.DubboHealthTriple$HealthImplBase implements io.grpc.health.v1.Health, org.apache.dubbo.rpc.ServerService<io.grpc.health.v1.Health> {
  public io.grpc.health.v1.DubboHealthTriple$HealthImplBase();
    Code:
       0: aload_0
       1: invokespecial #1                  // Method java/lang/Object."<init>":()V
       4: return

  private <T, R> java.util.function.BiConsumer<T, org.apache.dubbo.common.stream.StreamObserver<R>> syncToAsync(java.util.function.Function<T, R>);
    Code:
       0: new           #2                  // class io/grpc/health/v1/DubboHealthTriple$HealthImplBase$1
       3: dup
       4: aload_0
       5: aload_1
       6: invokespecial #3                  // Method io/grpc/health/v1/DubboHealthTriple$HealthImplBase$1."<init>":(Lio/grpc/health/v1/DubboHealthTriple$HealthImplBase;Ljava/util/function/Function;)V
       9: areturn

  public final org.apache.dubbo.rpc.Invoker<io.grpc.health.v1.Health> getInvoker(org.apache.dubbo.common.URL);
    Code:
       0: aload_1
       1: invokevirtual #4                  // Method org/apache/dubbo/common/URL.getOrDefaultFrameworkModel:()Lorg/apache/dubbo/rpc/model/FrameworkModel;
       4: ldc           #5                  // class org/apache/dubbo/rpc/PathResolver
       6: invokevirtual #6                  // Method org/apache/dubbo/rpc/model/FrameworkModel.getExtensionLoader:(Ljava/lang/Class;)Lorg/apache/dubbo/common/extension/ExtensionLoader;
       9: invokevirtual #7                  // Method org/apache/dubbo/common/extension/ExtensionLoader.getDefaultExtension:()Ljava/lang/Object;
      12: checkcast     #5                  // class org/apache/dubbo/rpc/PathResolver
      15: astore_2
      16: new           #8                  // class java/util/HashMap
      19: dup
      20: invokespecial #9                  // Method java/util/HashMap."<init>":()V
      23: astore_3
      24: aload_2
      25: ldc           #11                 // String /grpc.health.v1.Health/Check
      27: invokeinterface #12,  2           // InterfaceMethod org/apache/dubbo/rpc/PathResolver.addNativeStub:(Ljava/lang/String;)V
      32: aload_2
      33: ldc           #13                 // String /grpc.health.v1.Health/CheckAsync
      35: invokeinterface #12,  2           // InterfaceMethod org/apache/dubbo/rpc/PathResolver.addNativeStub:(Ljava/lang/String;)V
      40: aload_2
      41: ldc           #14                 // String /grpc.health.v1.Health/Watch
      43: invokeinterface #12,  2           // InterfaceMethod org/apache/dubbo/rpc/PathResolver.addNativeStub:(Ljava/lang/String;)V
      48: aload_2
      49: ldc           #15                 // String /grpc.health.v1.Health/WatchAsync
      51: invokeinterface #12,  2           // InterfaceMethod org/apache/dubbo/rpc/PathResolver.addNativeStub:(Ljava/lang/String;)V
      56: aload_0
      57: invokedynamic #16,  0             // InvokeDynamic #0:accept:(Lio/grpc/health/v1/DubboHealthTriple$HealthImplBase;)Ljava/util/function/BiConsumer;
      62: astore        4
      64: aload_3
      65: invokestatic  #17                 // Method io/grpc/health/v1/DubboHealthTriple.access$000:()Lorg/apache/dubbo/rpc/model/StubMethodDescriptor;
      68: invokevirtual #18                 // Method org/apache/dubbo/rpc/model/StubMethodDescriptor.getMethodName:()Ljava/lang/String;
      71: new           #19                 // class org/apache/dubbo/rpc/stub/UnaryStubMethodHandler
      74: dup
      75: aload         4
      77: invokespecial #20                 // Method org/apache/dubbo/rpc/stub/UnaryStubMethodHandler."<init>":(Ljava/util/function/BiConsumer;)V
      80: invokeinterface #21,  3           // InterfaceMethod java/util/Map.put:(Ljava/lang/Object;Ljava/lang/Object;)Ljava/lang/Object;
      85: pop
      86: aload_0
      87: aload_0
      88: invokedynamic #22,  0             // InvokeDynamic #1:apply:(Lio/grpc/health/v1/DubboHealthTriple$HealthImplBase;)Ljava/util/function/Function;
      93: invokespecial #23                 // Method syncToAsync:(Ljava/util/function/Function;)Ljava/util/function/BiConsumer;
      96: astore        5
      98: aload_3
      99: invokestatic  #24                 // Method io/grpc/health/v1/DubboHealthTriple.access$300:()Lorg/apache/dubbo/rpc/model/StubMethodDescriptor;
     102: invokevirtual #18                 // Method org/apache/dubbo/rpc/model/StubMethodDescriptor.getMethodName:()Ljava/lang/String;
     105: new           #19                 // class org/apache/dubbo/rpc/stub/UnaryStubMethodHandler
     108: dup
     109: aload         5
     111: invokespecial #20                 // Method org/apache/dubbo/rpc/stub/UnaryStubMethodHandler."<init>":(Ljava/util/function/BiConsumer;)V
     114: invokeinterface #21,  3           // InterfaceMethod java/util/Map.put:(Ljava/lang/Object;Ljava/lang/Object;)Ljava/lang/Object;
     119: pop
     120: aload_3
     121: invokestatic  #25                 // Method io/grpc/health/v1/DubboHealthTriple.access$200:()Lorg/apache/dubbo/rpc/model/StubMethodDescriptor;
     124: invokevirtual #18                 // Method org/apache/dubbo/rpc/model/StubMethodDescriptor.getMethodName:()Ljava/lang/String;
     127: new           #26                 // class org/apache/dubbo/rpc/stub/ServerStreamMethodHandler
     130: dup
     131: aload_0
     132: invokedynamic #27,  0             // InvokeDynamic #2:accept:(Lio/grpc/health/v1/DubboHealthTriple$HealthImplBase;)Ljava/util/function/BiConsumer;
     137: invokespecial #28                 // Method org/apache/dubbo/rpc/stub/ServerStreamMethodHandler."<init>":(Ljava/util/function/BiConsumer;)V
     140: invokeinterface #21,  3           // InterfaceMethod java/util/Map.put:(Ljava/lang/Object;Ljava/lang/Object;)Ljava/lang/Object;
     145: pop
     146: new           #29                 // class org/apache/dubbo/rpc/stub/StubInvoker
     149: dup
     150: aload_0
     151: aload_1
     152: ldc           #10                 // class io/grpc/health/v1/Health
     154: aload_3
     155: invokespecial #30                 // Method org/apache/dubbo/rpc/stub/StubInvoker."<init>":(Ljava/lang/Object;Lorg/apache/dubbo/common/URL;Ljava/lang/Class;Ljava/util/Map;)V
     158: areturn

  public io.grpc.health.v1.HealthCheckResponse check(io.grpc.health.v1.HealthCheckRequest);
    Code:
       0: aload_0
       1: invokestatic  #17                 // Method io/grpc/health/v1/DubboHealthTriple.access$000:()Lorg/apache/dubbo/rpc/model/StubMethodDescriptor;
       4: invokespecial #31                 // Method unimplementedMethodException:(Lorg/apache/dubbo/rpc/model/StubMethodDescriptor;)Lorg/apache/dubbo/rpc/RpcException;
       7: athrow

  public void watch(io.grpc.health.v1.HealthCheckRequest, org.apache.dubbo.common.stream.StreamObserver<io.grpc.health.v1.HealthCheckResponse>);
    Code:
       0: aload_0
       1: invokestatic  #25                 // Method io/grpc/health/v1/DubboHealthTriple.access$200:()Lorg/apache/dubbo/rpc/model/StubMethodDescriptor;
       4: invokespecial #31                 // Method unimplementedMethodException:(Lorg/apache/dubbo/rpc/model/StubMethodDescriptor;)Lorg/apache/dubbo/rpc/RpcException;
       7: athrow

  public final org.apache.dubbo.rpc.model.ServiceDescriptor getServiceDescriptor();
    Code:
       0: invokestatic  #32                 // Method io/grpc/health/v1/DubboHealthTriple.access$400:()Lorg/apache/dubbo/rpc/model/StubServiceDescriptor;
       3: areturn

  private org.apache.dubbo.rpc.RpcException unimplementedMethodException(org.apache.dubbo.rpc.model.StubMethodDescriptor);
    Code:
       0: getstatic     #33                 // Field org/apache/dubbo/rpc/TriRpcStatus.UNIMPLEMENTED:Lorg/apache/dubbo/rpc/TriRpcStatus;
       3: ldc           #34                 // String Method %s is unimplemented
       5: iconst_1
       6: anewarray     #35                 // class java/lang/Object
       9: dup
      10: iconst_0
      11: new           #36                 // class java/lang/StringBuilder
      14: dup
      15: invokespecial #37                 // Method java/lang/StringBuilder."<init>":()V
      18: ldc           #38                 // String /
      20: invokevirtual #39                 // Method java/lang/StringBuilder.append:(Ljava/lang/String;)Ljava/lang/StringBuilder;
      23: invokestatic  #32                 // Method io/grpc/health/v1/DubboHealthTriple.access$400:()Lorg/apache/dubbo/rpc/model/StubServiceDescriptor;
      26: invokevirtual #40                 // Method org/apache/dubbo/rpc/model/StubServiceDescriptor.getInterfaceName:()Ljava/lang/String;
      29: invokevirtual #39                 // Method java/lang/StringBuilder.append:(Ljava/lang/String;)Ljava/lang/StringBuilder;
      32: ldc           #38                 // String /
      34: invokevirtual #39                 // Method java/lang/StringBuilder.append:(Ljava/lang/String;)Ljava/lang/StringBuilder;
      37: aload_1
      38: invokevirtual #18                 // Method org/apache/dubbo/rpc/model/StubMethodDescriptor.getMethodName:()Ljava/lang/String;
      41: invokevirtual #39                 // Method java/lang/StringBuilder.append:(Ljava/lang/String;)Ljava/lang/StringBuilder;
      44: invokevirtual #41                 // Method java/lang/StringBuilder.toString:()Ljava/lang/String;
      47: aastore
      48: invokestatic  #42                 // Method java/lang/String.format:(Ljava/lang/String;[Ljava/lang/Object;)Ljava/lang/String;
      51: invokevirtual #43                 // Method org/apache/dubbo/rpc/TriRpcStatus.withDescription:(Ljava/lang/String;)Lorg/apache/dubbo/rpc/TriRpcStatus;
      54: invokevirtual #44                 // Method org/apache/dubbo/rpc/TriRpcStatus.asException:()Lorg/apache/dubbo/rpc/StatusRpcException;
      57: areturn
}
