Compiled from "DubboHealthTriple.java"
public final class io.grpc.health.v1.DubboHealthTriple {
  public static final java.lang.String SERVICE_NAME;

  private static final org.apache.dubbo.rpc.model.StubServiceDescriptor serviceDescriptor;

  private static final org.apache.dubbo.rpc.model.StubMethodDescriptor checkMethod;

  private static final org.apache.dubbo.rpc.model.StubMethodDescriptor checkAsyncMethod;

  private static final org.apache.dubbo.rpc.model.StubMethodDescriptor checkProxyAsyncMethod;

  private static final org.apache.dubbo.rpc.model.StubMethodDescriptor watchMethod;

  public io.grpc.health.v1.DubboHealthTriple();
    Code:
       0: aload_0
       1: invokespecial #7                  // Method java/lang/Object."<init>":()V
       4: return

  public static io.grpc.health.v1.Health newStub(org.apache.dubbo.rpc.Invoker<?>);
    Code:
       0: new           #8                  // class io/grpc/health/v1/DubboHealthTriple$HealthStub
       3: dup
       4: aload_0
       5: invokespecial #9                  // Method io/grpc/health/v1/DubboHealthTriple$HealthStub."<init>":(Lorg/apache/dubbo/rpc/Invoker;)V
       8: areturn

  private static byte[] lambda$static$7(java.lang.Object) throws java.lang.Exception;
    Code:
       0: aload_0
       1: checkcast     #10                 // class com/google/protobuf/Message
       4: invokeinterface #11,  1           // InterfaceMethod com/google/protobuf/Message.toByteArray:()[B
       9: areturn

  private static byte[] lambda$static$6(java.lang.Object) throws java.lang.Exception;
    Code:
       0: aload_0
       1: checkcast     #10                 // class com/google/protobuf/Message
       4: invokeinterface #11,  1           // InterfaceMethod com/google/protobuf/Message.toByteArray:()[B
       9: areturn

  private static byte[] lambda$static$5(java.lang.Object) throws java.lang.Exception;
    Code:
       0: aload_0
       1: checkcast     #10                 // class com/google/protobuf/Message
       4: invokeinterface #11,  1           // InterfaceMethod com/google/protobuf/Message.toByteArray:()[B
       9: areturn

  private static byte[] lambda$static$4(java.lang.Object) throws java.lang.Exception;
    Code:
       0: aload_0
       1: checkcast     #10                 // class com/google/protobuf/Message
       4: invokeinterface #11,  1           // InterfaceMethod com/google/protobuf/Message.toByteArray:()[B
       9: areturn

  private static byte[] lambda$static$3(java.lang.Object) throws java.lang.Exception;
    Code:
       0: aload_0
       1: checkcast     #10                 // class com/google/protobuf/Message
       4: invokeinterface #11,  1           // InterfaceMethod com/google/protobuf/Message.toByteArray:()[B
       9: areturn

  private static byte[] lambda$static$2(java.lang.Object) throws java.lang.Exception;
    Code:
       0: aload_0
       1: checkcast     #10                 // class com/google/protobuf/Message
       4: invokeinterface #11,  1           // InterfaceMethod com/google/protobuf/Message.toByteArray:()[B
       9: areturn

  private static byte[] lambda$static$1(java.lang.Object) throws java.lang.Exception;
    Code:
       0: aload_0
       1: checkcast     #10                 // class com/google/protobuf/Message
       4: invokeinterface #11,  1           // InterfaceMethod com/google/protobuf/Message.toByteArray:()[B
       9: areturn

  private static byte[] lambda$static$0(java.lang.Object) throws java.lang.Exception;
    Code:
       0: aload_0
       1: checkcast     #10                 // class com/google/protobuf/Message
       4: invokeinterface #11,  1           // InterfaceMethod com/google/protobuf/Message.toByteArray:()[B
       9: areturn

  static org.apache.dubbo.rpc.model.StubMethodDescriptor access$000();
    Code:
       0: getstatic     #6                  // Field checkMethod:Lorg/apache/dubbo/rpc/model/StubMethodDescriptor;
       3: areturn

  static org.apache.dubbo.rpc.model.StubMethodDescriptor access$100();
    Code:
       0: getstatic     #5                  // Field checkAsyncMethod:Lorg/apache/dubbo/rpc/model/StubMethodDescriptor;
       3: areturn

  static org.apache.dubbo.rpc.model.StubMethodDescriptor access$200();
    Code:
       0: getstatic     #4                  // Field watchMethod:Lorg/apache/dubbo/rpc/model/StubMethodDescriptor;
       3: areturn

  static org.apache.dubbo.rpc.model.StubMethodDescriptor access$300();
    Code:
       0: getstatic     #3                  // Field checkProxyAsyncMethod:Lorg/apache/dubbo/rpc/model/StubMethodDescriptor;
       3: areturn

  static org.apache.dubbo.rpc.model.StubServiceDescriptor access$400();
    Code:
       0: getstatic     #2                  // Field serviceDescriptor:Lorg/apache/dubbo/rpc/model/StubServiceDescriptor;
       3: areturn

  static {};
    Code:
       0: new           #12                 // class org/apache/dubbo/rpc/model/StubServiceDescriptor
       3: dup
       4: ldc           #14                 // String grpc.health.v1.Health
       6: ldc           #1                  // class io/grpc/health/v1/Health
       8: invokespecial #15                 // Method org/apache/dubbo/rpc/model/StubServiceDescriptor."<init>":(Ljava/lang/String;Ljava/lang/Class;)V
      11: putstatic     #2                  // Field serviceDescriptor:Lorg/apache/dubbo/rpc/model/StubServiceDescriptor;
      14: ldc           #14                 // String grpc.health.v1.Health
      16: invokestatic  #16                 // Method io/grpc/health/v1/HealthProto.getDescriptor:()Lcom/google/protobuf/Descriptors$FileDescriptor;
      19: invokestatic  #17                 // Method org/apache/dubbo/rpc/protocol/tri/service/SchemaDescriptorRegistry.addSchemaDescriptor:(Ljava/lang/String;Lcom/google/protobuf/Descriptors$FileDescriptor;)V
      22: ldc           #14                 // String grpc.health.v1.Health
      24: invokedynamic #18,  0             // InvokeDynamic #0:apply:()Ljava/util/function/Function;
      29: invokestatic  #19                 // Method org/apache/dubbo/rpc/stub/StubSuppliers.addSupplier:(Ljava/lang/String;Ljava/util/function/Function;)V
      32: ldc           #20                 // String io.grpc.health.v1.Health
      34: invokedynamic #18,  0             // InvokeDynamic #0:apply:()Ljava/util/function/Function;
      39: invokestatic  #19                 // Method org/apache/dubbo/rpc/stub/StubSuppliers.addSupplier:(Ljava/lang/String;Ljava/util/function/Function;)V
      42: ldc           #14                 // String grpc.health.v1.Health
      44: getstatic     #2                  // Field serviceDescriptor:Lorg/apache/dubbo/rpc/model/StubServiceDescriptor;
      47: invokestatic  #21                 // Method org/apache/dubbo/rpc/stub/StubSuppliers.addDescriptor:(Ljava/lang/String;Lorg/apache/dubbo/rpc/model/ServiceDescriptor;)V
      50: ldc           #20                 // String io.grpc.health.v1.Health
      52: getstatic     #2                  // Field serviceDescriptor:Lorg/apache/dubbo/rpc/model/StubServiceDescriptor;
      55: invokestatic  #21                 // Method org/apache/dubbo/rpc/stub/StubSuppliers.addDescriptor:(Ljava/lang/String;Lorg/apache/dubbo/rpc/model/ServiceDescriptor;)V
      58: new           #22                 // class org/apache/dubbo/rpc/model/StubMethodDescriptor
      61: dup
      62: ldc           #23                 // String Check
      64: ldc           #24                 // class io/grpc/health/v1/HealthCheckRequest
      66: ldc           #25                 // class io/grpc/health/v1/HealthCheckResponse
      68: getstatic     #2                  // Field serviceDescriptor:Lorg/apache/dubbo/rpc/model/StubServiceDescriptor;
      71: getstatic     #26                 // Field org/apache/dubbo/rpc/model/MethodDescriptor$RpcType.UNARY:Lorg/apache/dubbo/rpc/model/MethodDescriptor$RpcType;
      74: invokedynamic #27,  0             // InvokeDynamic #1:pack:()Lorg/apache/dubbo/rpc/model/Pack;
      79: invokedynamic #28,  0             // InvokeDynamic #2:pack:()Lorg/apache/dubbo/rpc/model/Pack;
      84: invokedynamic #29,  0             // InvokeDynamic #3:unpack:()Lorg/apache/dubbo/rpc/model/UnPack;
      89: invokedynamic #30,  0             // InvokeDynamic #4:unpack:()Lorg/apache/dubbo/rpc/model/UnPack;
      94: invokespecial #31                 // Method org/apache/dubbo/rpc/model/StubMethodDescriptor."<init>":(Ljava/lang/String;Ljava/lang/Class;Ljava/lang/Class;Lorg/apache/dubbo/rpc/model/StubServiceDescriptor;Lorg/apache/dubbo/rpc/model/MethodDescriptor$RpcType;Lorg/apache/dubbo/rpc/model/Pack;Lorg/apache/dubbo/rpc/model/Pack;Lorg/apache/dubbo/rpc/model/UnPack;Lorg/apache/dubbo/rpc/model/UnPack;)V
      97: putstatic     #6                  // Field checkMethod:Lorg/apache/dubbo/rpc/model/StubMethodDescriptor;
     100: new           #22                 // class org/apache/dubbo/rpc/model/StubMethodDescriptor
     103: dup
     104: ldc           #23                 // String Check
     106: ldc           #24                 // class io/grpc/health/v1/HealthCheckRequest
     108: ldc           #32                 // class java/util/concurrent/CompletableFuture
     110: getstatic     #2                  // Field serviceDescriptor:Lorg/apache/dubbo/rpc/model/StubServiceDescriptor;
     113: getstatic     #26                 // Field org/apache/dubbo/rpc/model/MethodDescriptor$RpcType.UNARY:Lorg/apache/dubbo/rpc/model/MethodDescriptor$RpcType;
     116: invokedynamic #33,  0             // InvokeDynamic #5:pack:()Lorg/apache/dubbo/rpc/model/Pack;
     121: invokedynamic #34,  0             // InvokeDynamic #6:pack:()Lorg/apache/dubbo/rpc/model/Pack;
     126: invokedynamic #29,  0             // InvokeDynamic #3:unpack:()Lorg/apache/dubbo/rpc/model/UnPack;
     131: invokedynamic #30,  0             // InvokeDynamic #4:unpack:()Lorg/apache/dubbo/rpc/model/UnPack;
     136: invokespecial #31                 // Method org/apache/dubbo/rpc/model/StubMethodDescriptor."<init>":(Ljava/lang/String;Ljava/lang/Class;Ljava/lang/Class;Lorg/apache/dubbo/rpc/model/StubServiceDescriptor;Lorg/apache/dubbo/rpc/model/MethodDescriptor$RpcType;Lorg/apache/dubbo/rpc/model/Pack;Lorg/apache/dubbo/rpc/model/Pack;Lorg/apache/dubbo/rpc/model/UnPack;Lorg/apache/dubbo/rpc/model/UnPack;)V
     139: putstatic     #5                  // Field checkAsyncMethod:Lorg/apache/dubbo/rpc/model/StubMethodDescriptor;
     142: new           #22                 // class org/apache/dubbo/rpc/model/StubMethodDescriptor
     145: dup
     146: ldc           #35                 // String CheckAsync
     148: ldc           #24                 // class io/grpc/health/v1/HealthCheckRequest
     150: ldc           #25                 // class io/grpc/health/v1/HealthCheckResponse
     152: getstatic     #2                  // Field serviceDescriptor:Lorg/apache/dubbo/rpc/model/StubServiceDescriptor;
     155: getstatic     #26                 // Field org/apache/dubbo/rpc/model/MethodDescriptor$RpcType.UNARY:Lorg/apache/dubbo/rpc/model/MethodDescriptor$RpcType;
     158: invokedynamic #36,  0             // InvokeDynamic #7:pack:()Lorg/apache/dubbo/rpc/model/Pack;
     163: invokedynamic #37,  0             // InvokeDynamic #8:pack:()Lorg/apache/dubbo/rpc/model/Pack;
     168: invokedynamic #29,  0             // InvokeDynamic #3:unpack:()Lorg/apache/dubbo/rpc/model/UnPack;
     173: invokedynamic #30,  0             // InvokeDynamic #4:unpack:()Lorg/apache/dubbo/rpc/model/UnPack;
     178: invokespecial #31                 // Method org/apache/dubbo/rpc/model/StubMethodDescriptor."<init>":(Ljava/lang/String;Ljava/lang/Class;Ljava/lang/Class;Lorg/apache/dubbo/rpc/model/StubServiceDescriptor;Lorg/apache/dubbo/rpc/model/MethodDescriptor$RpcType;Lorg/apache/dubbo/rpc/model/Pack;Lorg/apache/dubbo/rpc/model/Pack;Lorg/apache/dubbo/rpc/model/UnPack;Lorg/apache/dubbo/rpc/model/UnPack;)V
     181: putstatic     #3                  // Field checkProxyAsyncMethod:Lorg/apache/dubbo/rpc/model/StubMethodDescriptor;
     184: new           #22                 // class org/apache/dubbo/rpc/model/StubMethodDescriptor
     187: dup
     188: ldc           #38                 // String Watch
     190: ldc           #24                 // class io/grpc/health/v1/HealthCheckRequest
     192: ldc           #25                 // class io/grpc/health/v1/HealthCheckResponse
     194: getstatic     #2                  // Field serviceDescriptor:Lorg/apache/dubbo/rpc/model/StubServiceDescriptor;
     197: getstatic     #39                 // Field org/apache/dubbo/rpc/model/MethodDescriptor$RpcType.SERVER_STREAM:Lorg/apache/dubbo/rpc/model/MethodDescriptor$RpcType;
     200: invokedynamic #40,  0             // InvokeDynamic #9:pack:()Lorg/apache/dubbo/rpc/model/Pack;
     205: invokedynamic #41,  0             // InvokeDynamic #10:pack:()Lorg/apache/dubbo/rpc/model/Pack;
     210: invokedynamic #29,  0             // InvokeDynamic #3:unpack:()Lorg/apache/dubbo/rpc/model/UnPack;
     215: invokedynamic #30,  0             // InvokeDynamic #4:unpack:()Lorg/apache/dubbo/rpc/model/UnPack;
     220: invokespecial #31                 // Method org/apache/dubbo/rpc/model/StubMethodDescriptor."<init>":(Ljava/lang/String;Ljava/lang/Class;Ljava/lang/Class;Lorg/apache/dubbo/rpc/model/StubServiceDescriptor;Lorg/apache/dubbo/rpc/model/MethodDescriptor$RpcType;Lorg/apache/dubbo/rpc/model/Pack;Lorg/apache/dubbo/rpc/model/Pack;Lorg/apache/dubbo/rpc/model/UnPack;Lorg/apache/dubbo/rpc/model/UnPack;)V
     223: putstatic     #4                  // Field watchMethod:Lorg/apache/dubbo/rpc/model/StubMethodDescriptor;
     226: return
}
