Compiled from "DubboHealthTriple.java"
public class io.grpc.health.v1.DubboHealthTriple$HealthStub implements io.grpc.health.v1.Health {
  private final org.apache.dubbo.rpc.Invoker<io.grpc.health.v1.Health> invoker;

  public io.grpc.health.v1.DubboHealthTriple$HealthStub(org.apache.dubbo.rpc.Invoker<io.grpc.health.v1.Health>);
    Code:
       0: aload_0
       1: invokespecial #1                  // Method java/lang/Object."<init>":()V
       4: aload_0
       5: aload_1
       6: putfield      #2                  // Field invoker:Lorg/apache/dubbo/rpc/Invoker;
       9: return

  public io.grpc.health.v1.HealthCheckResponse check(io.grpc.health.v1.HealthCheckRequest);
    Code:
       0: aload_0
       1: getfield      #2                  // Field invoker:Lorg/apache/dubbo/rpc/Invoker;
       4: invokestatic  #3                  // Method io/grpc/health/v1/DubboHealthTriple.access$000:()Lorg/apache/dubbo/rpc/model/StubMethodDescriptor;
       7: aload_1
       8: invokestatic  #4                  // Method org/apache/dubbo/rpc/stub/StubInvocationUtil.unaryCall:(Lorg/apache/dubbo/rpc/Invoker;Lorg/apache/dubbo/rpc/model/MethodDescriptor;Ljava/lang/Object;)Ljava/lang/Object;
      11: checkcast     #5                  // class io/grpc/health/v1/HealthCheckResponse
      14: areturn

  public java.util.concurrent.CompletableFuture<io.grpc.health.v1.HealthCheckResponse> checkAsync(io.grpc.health.v1.HealthCheckRequest);
    Code:
       0: aload_0
       1: getfield      #2                  // Field invoker:Lorg/apache/dubbo/rpc/Invoker;
       4: invokestatic  #6                  // Method io/grpc/health/v1/DubboHealthTriple.access$100:()Lorg/apache/dubbo/rpc/model/StubMethodDescriptor;
       7: aload_1
       8: invokestatic  #4                  // Method org/apache/dubbo/rpc/stub/StubInvocationUtil.unaryCall:(Lorg/apache/dubbo/rpc/Invoker;Lorg/apache/dubbo/rpc/model/MethodDescriptor;Ljava/lang/Object;)Ljava/lang/Object;
      11: checkcast     #7                  // class java/util/concurrent/CompletableFuture
      14: areturn

  public void check(io.grpc.health.v1.HealthCheckRequest, org.apache.dubbo.common.stream.StreamObserver<io.grpc.health.v1.HealthCheckResponse>);
    Code:
       0: aload_0
       1: getfield      #2                  // Field invoker:Lorg/apache/dubbo/rpc/Invoker;
       4: invokestatic  #3                  // Method io/grpc/health/v1/DubboHealthTriple.access$000:()Lorg/apache/dubbo/rpc/model/StubMethodDescriptor;
       7: aload_1
       8: aload_2
       9: invokestatic  #8                  // Method org/apache/dubbo/rpc/stub/StubInvocationUtil.unaryCall:(Lorg/apache/dubbo/rpc/Invoker;Lorg/apache/dubbo/rpc/model/MethodDescriptor;Ljava/lang/Object;Lorg/apache/dubbo/common/stream/StreamObserver;)V
      12: return

  public void watch(io.grpc.health.v1.HealthCheckRequest, org.apache.dubbo.common.stream.StreamObserver<io.grpc.health.v1.HealthCheckResponse>);
    Code:
       0: aload_0
       1: getfield      #2                  // Field invoker:Lorg/apache/dubbo/rpc/Invoker;
       4: invokestatic  #9                  // Method io/grpc/health/v1/DubboHealthTriple.access$200:()Lorg/apache/dubbo/rpc/model/StubMethodDescriptor;
       7: aload_1
       8: aload_2
       9: invokestatic  #10                 // Method org/apache/dubbo/rpc/stub/StubInvocationUtil.serverStreamCall:(Lorg/apache/dubbo/rpc/Invoker;Lorg/apache/dubbo/rpc/model/MethodDescriptor;Ljava/lang/Object;Lorg/apache/dubbo/common/stream/StreamObserver;)V
      12: return
}
