Compiled from "HealthCheckResponse.java"
public final class io.grpc.health.v1.HealthCheckResponse extends com.google.protobuf.GeneratedMessageV3 implements io.grpc.health.v1.HealthCheckResponseOrBuilder {
  private static final long serialVersionUID;

  public static final int STATUS_FIELD_NUMBER;

  private int status_;

  private byte memoizedIsInitialized;

  private static final io.grpc.health.v1.HealthCheckResponse DEFAULT_INSTANCE;

  private static final com.google.protobuf.Parser<io.grpc.health.v1.HealthCheckResponse> PARSER;

  private io.grpc.health.v1.HealthCheckResponse(com.google.protobuf.GeneratedMessageV3$Builder<?>);
    Code:
       0: aload_0
       1: aload_1
       2: invokespecial #3                  // Method com/google/protobuf/GeneratedMessageV3."<init>":(Lcom/google/protobuf/GeneratedMessageV3$Builder;)V
       5: aload_0
       6: iconst_0
       7: putfield      #1                  // Field status_:I
      10: aload_0
      11: iconst_m1
      12: putfield      #4                  // Field memoizedIsInitialized:B
      15: return

  private io.grpc.health.v1.HealthCheckResponse();
    Code:
       0: aload_0
       1: invokespecial #5                  // Method com/google/protobuf/GeneratedMessageV3."<init>":()V
       4: aload_0
       5: iconst_0
       6: putfield      #1                  // Field status_:I
       9: aload_0
      10: iconst_m1
      11: putfield      #4                  // Field memoizedIsInitialized:B
      14: aload_0
      15: iconst_0
      16: putfield      #1                  // Field status_:I
      19: return

  protected java.lang.Object newInstance(com.google.protobuf.GeneratedMessageV3$UnusedPrivateParameter);
    Code:
       0: new           #6                  // class io/grpc/health/v1/HealthCheckResponse
       3: dup
       4: invokespecial #7                  // Method "<init>":()V
       7: areturn

  public static final com.google.protobuf.Descriptors$Descriptor getDescriptor();
    Code:
       0: getstatic     #8                  // Field io/grpc/health/v1/HealthProto.internal_static_grpc_health_v1_HealthCheckResponse_descriptor:Lcom/google/protobuf/Descriptors$Descriptor;
       3: areturn

  protected com.google.protobuf.GeneratedMessageV3$FieldAccessorTable internalGetFieldAccessorTable();
    Code:
       0: getstatic     #9                  // Field io/grpc/health/v1/HealthProto.internal_static_grpc_health_v1_HealthCheckResponse_fieldAccessorTable:Lcom/google/protobuf/GeneratedMessageV3$FieldAccessorTable;
       3: ldc           #6                  // class io/grpc/health/v1/HealthCheckResponse
       5: ldc           #10                 // class io/grpc/health/v1/HealthCheckResponse$Builder
       7: invokevirtual #11                 // Method com/google/protobuf/GeneratedMessageV3$FieldAccessorTable.ensureFieldAccessorsInitialized:(Ljava/lang/Class;Ljava/lang/Class;)Lcom/google/protobuf/GeneratedMessageV3$FieldAccessorTable;
      10: areturn

  public int getStatusValue();
    Code:
       0: aload_0
       1: getfield      #1                  // Field status_:I
       4: ireturn

  public io.grpc.health.v1.HealthCheckResponse$ServingStatus getStatus();
    Code:
       0: aload_0
       1: getfield      #1                  // Field status_:I
       4: invokestatic  #12                 // Method io/grpc/health/v1/HealthCheckResponse$ServingStatus.forNumber:(I)Lio/grpc/health/v1/HealthCheckResponse$ServingStatus;
       7: astore_1
       8: aload_1
       9: ifnonnull     18
      12: getstatic     #13                 // Field io/grpc/health/v1/HealthCheckResponse$ServingStatus.UNRECOGNIZED:Lio/grpc/health/v1/HealthCheckResponse$ServingStatus;
      15: goto          19
      18: aload_1
      19: areturn

  public final boolean isInitialized();
    Code:
       0: aload_0
       1: getfield      #4                  // Field memoizedIsInitialized:B
       4: istore_1
       5: iload_1
       6: iconst_1
       7: if_icmpne     12
      10: iconst_1
      11: ireturn
      12: iload_1
      13: ifne          18
      16: iconst_0
      17: ireturn
      18: aload_0
      19: iconst_1
      20: putfield      #4                  // Field memoizedIsInitialized:B
      23: iconst_1
      24: ireturn

  public void writeTo(com.google.protobuf.CodedOutputStream) throws java.io.IOException;
    Code:
       0: aload_0
       1: getfield      #1                  // Field status_:I
       4: getstatic     #14                 // Field io/grpc/health/v1/HealthCheckResponse$ServingStatus.UNKNOWN:Lio/grpc/health/v1/HealthCheckResponse$ServingStatus;
       7: invokevirtual #15                 // Method io/grpc/health/v1/HealthCheckResponse$ServingStatus.getNumber:()I
      10: if_icmpeq     22
      13: aload_1
      14: iconst_1
      15: aload_0
      16: getfield      #1                  // Field status_:I
      19: invokevirtual #16                 // Method com/google/protobuf/CodedOutputStream.writeEnum:(II)V
      22: aload_0
      23: invokevirtual #17                 // Method getUnknownFields:()Lcom/google/protobuf/UnknownFieldSet;
      26: aload_1
      27: invokevirtual #18                 // Method com/google/protobuf/UnknownFieldSet.writeTo:(Lcom/google/protobuf/CodedOutputStream;)V
      30: return

  public int getSerializedSize();
    Code:
       0: aload_0
       1: getfield      #19                 // Field memoizedSize:I
       4: istore_1
       5: iload_1
       6: iconst_m1
       7: if_icmpeq     12
      10: iload_1
      11: ireturn
      12: iconst_0
      13: istore_1
      14: aload_0
      15: getfield      #1                  // Field status_:I
      18: getstatic     #14                 // Field io/grpc/health/v1/HealthCheckResponse$ServingStatus.UNKNOWN:Lio/grpc/health/v1/HealthCheckResponse$ServingStatus;
      21: invokevirtual #15                 // Method io/grpc/health/v1/HealthCheckResponse$ServingStatus.getNumber:()I
      24: if_icmpeq     38
      27: iload_1
      28: iconst_1
      29: aload_0
      30: getfield      #1                  // Field status_:I
      33: invokestatic  #20                 // Method com/google/protobuf/CodedOutputStream.computeEnumSize:(II)I
      36: iadd
      37: istore_1
      38: iload_1
      39: aload_0
      40: invokevirtual #17                 // Method getUnknownFields:()Lcom/google/protobuf/UnknownFieldSet;
      43: invokevirtual #21                 // Method com/google/protobuf/UnknownFieldSet.getSerializedSize:()I
      46: iadd
      47: istore_1
      48: aload_0
      49: iload_1
      50: putfield      #19                 // Field memoizedSize:I
      53: iload_1
      54: ireturn

  public boolean equals(java.lang.Object);
    Code:
       0: aload_1
       1: aload_0
       2: if_acmpne     7
       5: iconst_1
       6: ireturn
       7: aload_1
       8: instanceof    #6                  // class io/grpc/health/v1/HealthCheckResponse
      11: ifne          20
      14: aload_0
      15: aload_1
      16: invokespecial #22                 // Method com/google/protobuf/GeneratedMessageV3.equals:(Ljava/lang/Object;)Z
      19: ireturn
      20: aload_1
      21: checkcast     #6                  // class io/grpc/health/v1/HealthCheckResponse
      24: astore_2
      25: aload_0
      26: getfield      #1                  // Field status_:I
      29: aload_2
      30: getfield      #1                  // Field status_:I
      33: if_icmpeq     38
      36: iconst_0
      37: ireturn
      38: aload_0
      39: invokevirtual #17                 // Method getUnknownFields:()Lcom/google/protobuf/UnknownFieldSet;
      42: aload_2
      43: invokevirtual #17                 // Method getUnknownFields:()Lcom/google/protobuf/UnknownFieldSet;
      46: invokevirtual #23                 // Method com/google/protobuf/UnknownFieldSet.equals:(Ljava/lang/Object;)Z
      49: ifne          54
      52: iconst_0
      53: ireturn
      54: iconst_1
      55: ireturn

  public int hashCode();
    Code:
       0: aload_0
       1: getfield      #24                 // Field memoizedHashCode:I
       4: ifeq          12
       7: aload_0
       8: getfield      #24                 // Field memoizedHashCode:I
      11: ireturn
      12: bipush        41
      14: istore_1
      15: bipush        19
      17: iload_1
      18: imul
      19: invokestatic  #25                 // Method getDescriptor:()Lcom/google/protobuf/Descriptors$Descriptor;
      22: invokevirtual #26                 // Method java/lang/Object.hashCode:()I
      25: iadd
      26: istore_1
      27: bipush        37
      29: iload_1
      30: imul
      31: iconst_1
      32: iadd
      33: istore_1
      34: bipush        53
      36: iload_1
      37: imul
      38: aload_0
      39: getfield      #1                  // Field status_:I
      42: iadd
      43: istore_1
      44: bipush        29
      46: iload_1
      47: imul
      48: aload_0
      49: invokevirtual #17                 // Method getUnknownFields:()Lcom/google/protobuf/UnknownFieldSet;
      52: invokevirtual #27                 // Method com/google/protobuf/UnknownFieldSet.hashCode:()I
      55: iadd
      56: istore_1
      57: aload_0
      58: iload_1
      59: putfield      #24                 // Field memoizedHashCode:I
      62: iload_1
      63: ireturn

  public static io.grpc.health.v1.HealthCheckResponse parseFrom(java.nio.ByteBuffer) throws com.google.protobuf.InvalidProtocolBufferException;
    Code:
       0: getstatic     #28                 // Field PARSER:Lcom/google/protobuf/Parser;
       3: aload_0
       4: invokeinterface #29,  2           // InterfaceMethod com/google/protobuf/Parser.parseFrom:(Ljava/nio/ByteBuffer;)Ljava/lang/Object;
       9: checkcast     #6                  // class io/grpc/health/v1/HealthCheckResponse
      12: areturn

  public static io.grpc.health.v1.HealthCheckResponse parseFrom(java.nio.ByteBuffer, com.google.protobuf.ExtensionRegistryLite) throws com.google.protobuf.InvalidProtocolBufferException;
    Code:
       0: getstatic     #28                 // Field PARSER:Lcom/google/protobuf/Parser;
       3: aload_0
       4: aload_1
       5: invokeinterface #30,  3           // InterfaceMethod com/google/protobuf/Parser.parseFrom:(Ljava/nio/ByteBuffer;Lcom/google/protobuf/ExtensionRegistryLite;)Ljava/lang/Object;
      10: checkcast     #6                  // class io/grpc/health/v1/HealthCheckResponse
      13: areturn

  public static io.grpc.health.v1.HealthCheckResponse parseFrom(com.google.protobuf.ByteString) throws com.google.protobuf.InvalidProtocolBufferException;
    Code:
       0: getstatic     #28                 // Field PARSER:Lcom/google/protobuf/Parser;
       3: aload_0
       4: invokeinterface #31,  2           // InterfaceMethod com/google/protobuf/Parser.parseFrom:(Lcom/google/protobuf/ByteString;)Ljava/lang/Object;
       9: checkcast     #6                  // class io/grpc/health/v1/HealthCheckResponse
      12: areturn

  public static io.grpc.health.v1.HealthCheckResponse parseFrom(com.google.protobuf.ByteString, com.google.protobuf.ExtensionRegistryLite) throws com.google.protobuf.InvalidProtocolBufferException;
    Code:
       0: getstatic     #28                 // Field PARSER:Lcom/google/protobuf/Parser;
       3: aload_0
       4: aload_1
       5: invokeinterface #32,  3           // InterfaceMethod com/google/protobuf/Parser.parseFrom:(Lcom/google/protobuf/ByteString;Lcom/google/protobuf/ExtensionRegistryLite;)Ljava/lang/Object;
      10: checkcast     #6                  // class io/grpc/health/v1/HealthCheckResponse
      13: areturn

  public static io.grpc.health.v1.HealthCheckResponse parseFrom(byte[]) throws com.google.protobuf.InvalidProtocolBufferException;
    Code:
       0: getstatic     #28                 // Field PARSER:Lcom/google/protobuf/Parser;
       3: aload_0
       4: invokeinterface #33,  2           // InterfaceMethod com/google/protobuf/Parser.parseFrom:([B)Ljava/lang/Object;
       9: checkcast     #6                  // class io/grpc/health/v1/HealthCheckResponse
      12: areturn

  public static io.grpc.health.v1.HealthCheckResponse parseFrom(byte[], com.google.protobuf.ExtensionRegistryLite) throws com.google.protobuf.InvalidProtocolBufferException;
    Code:
       0: getstatic     #28                 // Field PARSER:Lcom/google/protobuf/Parser;
       3: aload_0
       4: aload_1
       5: invokeinterface #34,  3           // InterfaceMethod com/google/protobuf/Parser.parseFrom:([BLcom/google/protobuf/ExtensionRegistryLite;)Ljava/lang/Object;
      10: checkcast     #6                  // class io/grpc/health/v1/HealthCheckResponse
      13: areturn

  public static io.grpc.health.v1.HealthCheckResponse parseFrom(java.io.InputStream) throws java.io.IOException;
    Code:
       0: getstatic     #28                 // Field PARSER:Lcom/google/protobuf/Parser;
       3: aload_0
       4: invokestatic  #35                 // Method com/google/protobuf/GeneratedMessageV3.parseWithIOException:(Lcom/google/protobuf/Parser;Ljava/io/InputStream;)Lcom/google/protobuf/Message;
       7: checkcast     #6                  // class io/grpc/health/v1/HealthCheckResponse
      10: areturn

  public static io.grpc.health.v1.HealthCheckResponse parseFrom(java.io.InputStream, com.google.protobuf.ExtensionRegistryLite) throws java.io.IOException;
    Code:
       0: getstatic     #28                 // Field PARSER:Lcom/google/protobuf/Parser;
       3: aload_0
       4: aload_1
       5: invokestatic  #36                 // Method com/google/protobuf/GeneratedMessageV3.parseWithIOException:(Lcom/google/protobuf/Parser;Ljava/io/InputStream;Lcom/google/protobuf/ExtensionRegistryLite;)Lcom/google/protobuf/Message;
       8: checkcast     #6                  // class io/grpc/health/v1/HealthCheckResponse
      11: areturn

  public static io.grpc.health.v1.HealthCheckResponse parseDelimitedFrom(java.io.InputStream) throws java.io.IOException;
    Code:
       0: getstatic     #28                 // Field PARSER:Lcom/google/protobuf/Parser;
       3: aload_0
       4: invokestatic  #37                 // Method com/google/protobuf/GeneratedMessageV3.parseDelimitedWithIOException:(Lcom/google/protobuf/Parser;Ljava/io/InputStream;)Lcom/google/protobuf/Message;
       7: checkcast     #6                  // class io/grpc/health/v1/HealthCheckResponse
      10: areturn

  public static io.grpc.health.v1.HealthCheckResponse parseDelimitedFrom(java.io.InputStream, com.google.protobuf.ExtensionRegistryLite) throws java.io.IOException;
    Code:
       0: getstatic     #28                 // Field PARSER:Lcom/google/protobuf/Parser;
       3: aload_0
       4: aload_1
       5: invokestatic  #38                 // Method com/google/protobuf/GeneratedMessageV3.parseDelimitedWithIOException:(Lcom/google/protobuf/Parser;Ljava/io/InputStream;Lcom/google/protobuf/ExtensionRegistryLite;)Lcom/google/protobuf/Message;
       8: checkcast     #6                  // class io/grpc/health/v1/HealthCheckResponse
      11: areturn

  public static io.grpc.health.v1.HealthCheckResponse parseFrom(com.google.protobuf.CodedInputStream) throws java.io.IOException;
    Code:
       0: getstatic     #28                 // Field PARSER:Lcom/google/protobuf/Parser;
       3: aload_0
       4: invokestatic  #39                 // Method com/google/protobuf/GeneratedMessageV3.parseWithIOException:(Lcom/google/protobuf/Parser;Lcom/google/protobuf/CodedInputStream;)Lcom/google/protobuf/Message;
       7: checkcast     #6                  // class io/grpc/health/v1/HealthCheckResponse
      10: areturn

  public static io.grpc.health.v1.HealthCheckResponse parseFrom(com.google.protobuf.CodedInputStream, com.google.protobuf.ExtensionRegistryLite) throws java.io.IOException;
    Code:
       0: getstatic     #28                 // Field PARSER:Lcom/google/protobuf/Parser;
       3: aload_0
       4: aload_1
       5: invokestatic  #40                 // Method com/google/protobuf/GeneratedMessageV3.parseWithIOException:(Lcom/google/protobuf/Parser;Lcom/google/protobuf/CodedInputStream;Lcom/google/protobuf/ExtensionRegistryLite;)Lcom/google/protobuf/Message;
       8: checkcast     #6                  // class io/grpc/health/v1/HealthCheckResponse
      11: areturn

  public io.grpc.health.v1.HealthCheckResponse$Builder newBuilderForType();
    Code:
       0: invokestatic  #41                 // Method newBuilder:()Lio/grpc/health/v1/HealthCheckResponse$Builder;
       3: areturn

  public static io.grpc.health.v1.HealthCheckResponse$Builder newBuilder();
    Code:
       0: getstatic     #42                 // Field DEFAULT_INSTANCE:Lio/grpc/health/v1/HealthCheckResponse;
       3: invokevirtual #43                 // Method toBuilder:()Lio/grpc/health/v1/HealthCheckResponse$Builder;
       6: areturn

  public static io.grpc.health.v1.HealthCheckResponse$Builder newBuilder(io.grpc.health.v1.HealthCheckResponse);
    Code:
       0: getstatic     #42                 // Field DEFAULT_INSTANCE:Lio/grpc/health/v1/HealthCheckResponse;
       3: invokevirtual #43                 // Method toBuilder:()Lio/grpc/health/v1/HealthCheckResponse$Builder;
       6: aload_0
       7: invokevirtual #44                 // Method io/grpc/health/v1/HealthCheckResponse$Builder.mergeFrom:(Lio/grpc/health/v1/HealthCheckResponse;)Lio/grpc/health/v1/HealthCheckResponse$Builder;
      10: areturn

  public io.grpc.health.v1.HealthCheckResponse$Builder toBuilder();
    Code:
       0: aload_0
       1: getstatic     #42                 // Field DEFAULT_INSTANCE:Lio/grpc/health/v1/HealthCheckResponse;
       4: if_acmpne     18
       7: new           #10                 // class io/grpc/health/v1/HealthCheckResponse$Builder
      10: dup
      11: aconst_null
      12: invokespecial #45                 // Method io/grpc/health/v1/HealthCheckResponse$Builder."<init>":(Lio/grpc/health/v1/HealthCheckResponse$1;)V
      15: goto          30
      18: new           #10                 // class io/grpc/health/v1/HealthCheckResponse$Builder
      21: dup
      22: aconst_null
      23: invokespecial #45                 // Method io/grpc/health/v1/HealthCheckResponse$Builder."<init>":(Lio/grpc/health/v1/HealthCheckResponse$1;)V
      26: aload_0
      27: invokevirtual #44                 // Method io/grpc/health/v1/HealthCheckResponse$Builder.mergeFrom:(Lio/grpc/health/v1/HealthCheckResponse;)Lio/grpc/health/v1/HealthCheckResponse$Builder;
      30: areturn

  protected io.grpc.health.v1.HealthCheckResponse$Builder newBuilderForType(com.google.protobuf.GeneratedMessageV3$BuilderParent);
    Code:
       0: new           #10                 // class io/grpc/health/v1/HealthCheckResponse$Builder
       3: dup
       4: aload_1
       5: aconst_null
       6: invokespecial #46                 // Method io/grpc/health/v1/HealthCheckResponse$Builder."<init>":(Lcom/google/protobuf/GeneratedMessageV3$BuilderParent;Lio/grpc/health/v1/HealthCheckResponse$1;)V
       9: astore_2
      10: aload_2
      11: areturn

  public static io.grpc.health.v1.HealthCheckResponse getDefaultInstance();
    Code:
       0: getstatic     #42                 // Field DEFAULT_INSTANCE:Lio/grpc/health/v1/HealthCheckResponse;
       3: areturn

  public static com.google.protobuf.Parser<io.grpc.health.v1.HealthCheckResponse> parser();
    Code:
       0: getstatic     #28                 // Field PARSER:Lcom/google/protobuf/Parser;
       3: areturn

  public com.google.protobuf.Parser<io.grpc.health.v1.HealthCheckResponse> getParserForType();
    Code:
       0: getstatic     #28                 // Field PARSER:Lcom/google/protobuf/Parser;
       3: areturn

  public io.grpc.health.v1.HealthCheckResponse getDefaultInstanceForType();
    Code:
       0: getstatic     #42                 // Field DEFAULT_INSTANCE:Lio/grpc/health/v1/HealthCheckResponse;
       3: areturn

  protected com.google.protobuf.Message$Builder newBuilderForType(com.google.protobuf.GeneratedMessageV3$BuilderParent);
    Code:
       0: aload_0
       1: aload_1
       2: invokevirtual #47                 // Method newBuilderForType:(Lcom/google/protobuf/GeneratedMessageV3$BuilderParent;)Lio/grpc/health/v1/HealthCheckResponse$Builder;
       5: areturn

  public com.google.protobuf.Message$Builder toBuilder();
    Code:
       0: aload_0
       1: invokevirtual #43                 // Method toBuilder:()Lio/grpc/health/v1/HealthCheckResponse$Builder;
       4: areturn

  public com.google.protobuf.Message$Builder newBuilderForType();
    Code:
       0: aload_0
       1: invokevirtual #48                 // Method newBuilderForType:()Lio/grpc/health/v1/HealthCheckResponse$Builder;
       4: areturn

  public com.google.protobuf.MessageLite$Builder toBuilder();
    Code:
       0: aload_0
       1: invokevirtual #43                 // Method toBuilder:()Lio/grpc/health/v1/HealthCheckResponse$Builder;
       4: areturn

  public com.google.protobuf.MessageLite$Builder newBuilderForType();
    Code:
       0: aload_0
       1: invokevirtual #48                 // Method newBuilderForType:()Lio/grpc/health/v1/HealthCheckResponse$Builder;
       4: areturn

  public com.google.protobuf.MessageLite getDefaultInstanceForType();
    Code:
       0: aload_0
       1: invokevirtual #49                 // Method getDefaultInstanceForType:()Lio/grpc/health/v1/HealthCheckResponse;
       4: areturn

  public com.google.protobuf.Message getDefaultInstanceForType();
    Code:
       0: aload_0
       1: invokevirtual #49                 // Method getDefaultInstanceForType:()Lio/grpc/health/v1/HealthCheckResponse;
       4: areturn

  io.grpc.health.v1.HealthCheckResponse(com.google.protobuf.GeneratedMessageV3$Builder, io.grpc.health.v1.HealthCheckResponse$1);
    Code:
       0: aload_0
       1: aload_1
       2: invokespecial #2                  // Method "<init>":(Lcom/google/protobuf/GeneratedMessageV3$Builder;)V
       5: return

  static int access$302(io.grpc.health.v1.HealthCheckResponse, int);
    Code:
       0: aload_0
       1: iload_1
       2: dup_x1
       3: putfield      #1                  // Field status_:I
       6: ireturn

  static int access$300(io.grpc.health.v1.HealthCheckResponse);
    Code:
       0: aload_0
       1: getfield      #1                  // Field status_:I
       4: ireturn

  static {};
    Code:
       0: new           #6                  // class io/grpc/health/v1/HealthCheckResponse
       3: dup
       4: invokespecial #7                  // Method "<init>":()V
       7: putstatic     #42                 // Field DEFAULT_INSTANCE:Lio/grpc/health/v1/HealthCheckResponse;
      10: new           #50                 // class io/grpc/health/v1/HealthCheckResponse$1
      13: dup
      14: invokespecial #51                 // Method io/grpc/health/v1/HealthCheckResponse$1."<init>":()V
      17: putstatic     #28                 // Field PARSER:Lcom/google/protobuf/Parser;
      20: return
}
