Compiled from "Health.java"
public interface io.grpc.health.v1.Health extends org.apache.dubbo.rpc.model.DubboStub {
  public static final java.lang.String JAVA_SERVICE_NAME;

  public static final java.lang.String SERVICE_NAME;

  public abstract io.grpc.health.v1.HealthCheckResponse check(io.grpc.health.v1.HealthCheckRequest);

  public default java.util.concurrent.CompletableFuture<io.grpc.health.v1.HealthCheckResponse> checkAsync(io.grpc.health.v1.HealthCheckRequest);
    Code:
       0: aload_0
       1: aload_1
       2: invokeinterface #1,  2            // InterfaceMethod check:(Lio/grpc/health/v1/HealthCheckRequest;)Lio/grpc/health/v1/HealthCheckResponse;
       7: invokestatic  #2                  // Method java/util/concurrent/CompletableFuture.completedFuture:(Ljava/lang/Object;)Ljava/util/concurrent/CompletableFuture;
      10: areturn

  public default void check(io.grpc.health.v1.HealthCheckRequest, org.apache.dubbo.common.stream.StreamObserver<io.grpc.health.v1.HealthCheckResponse>);
    Code:
       0: aload_0
       1: aload_1
       2: invokeinterface #3,  2            // InterfaceMethod checkAsync:(Lio/grpc/health/v1/HealthCheckRequest;)Ljava/util/concurrent/CompletableFuture;
       7: aload_2
       8: invokedynamic #4,  0              // InvokeDynamic #0:accept:(Lorg/apache/dubbo/common/stream/StreamObserver;)Ljava/util/function/BiConsumer;
      13: invokevirtual #5                  // Method java/util/concurrent/CompletableFuture.whenComplete:(Ljava/util/function/BiConsumer;)Ljava/util/concurrent/CompletableFuture;
      16: pop
      17: return

  public abstract void watch(io.grpc.health.v1.HealthCheckRequest, org.apache.dubbo.common.stream.StreamObserver<io.grpc.health.v1.HealthCheckResponse>);

  private static void lambda$check$0(org.apache.dubbo.common.stream.StreamObserver, io.grpc.health.v1.HealthCheckResponse, java.lang.Throwable);
    Code:
       0: aload_2
       1: ifnull        14
       4: aload_0
       5: aload_2
       6: invokeinterface #6,  2            // InterfaceMethod org/apache/dubbo/common/stream/StreamObserver.onError:(Ljava/lang/Throwable;)V
      11: goto          27
      14: aload_0
      15: aload_1
      16: invokeinterface #7,  2            // InterfaceMethod org/apache/dubbo/common/stream/StreamObserver.onNext:(Ljava/lang/Object;)V
      21: aload_0
      22: invokeinterface #8,  1            // InterfaceMethod org/apache/dubbo/common/stream/StreamObserver.onCompleted:()V
      27: return
}
