Compiled from "DefaultErrorAttributes.java"
public class org.springframework.boot.web.reactive.error.DefaultErrorAttributes implements org.springframework.boot.web.reactive.error.ErrorAttributes {
  private static final java.lang.String ERROR_INTERNAL_ATTRIBUTE;

  public org.springframework.boot.web.reactive.error.DefaultErrorAttributes();
    Code:
       0: aload_0
       1: invokespecial #1                  // Method java/lang/Object."<init>":()V
       4: return

  public java.util.Map<java.lang.String, java.lang.Object> getErrorAttributes(org.springframework.web.reactive.function.server.ServerRequest, org.springframework.boot.web.error.ErrorAttributeOptions);
    Code:
       0: aload_0
       1: aload_1
       2: aload_2
       3: getstatic     #7                  // Field org/springframework/boot/web/error/ErrorAttributeOptions$Include.STACK_TRACE:Lorg/springframework/boot/web/error/ErrorAttributeOptions$Include;
       6: invokevirtual #13                 // Method org/springframework/boot/web/error/ErrorAttributeOptions.isIncluded:(Lorg/springframework/boot/web/error/ErrorAttributeOptions$Include;)Z
       9: invokevirtual #19                 // Method getErrorAttributes:(Lorg/springframework/web/reactive/function/server/ServerRequest;Z)Ljava/util/Map;
      12: astore_3
      13: aload_2
      14: getstatic     #25                 // Field org/springframework/boot/web/error/ErrorAttributeOptions$Include.EXCEPTION:Lorg/springframework/boot/web/error/ErrorAttributeOptions$Include;
      17: invokevirtual #13                 // Method org/springframework/boot/web/error/ErrorAttributeOptions.isIncluded:(Lorg/springframework/boot/web/error/ErrorAttributeOptions$Include;)Z
      20: ifne          32
      23: aload_3
      24: ldc           #28                 // String exception
      26: invokeinterface #30,  2           // InterfaceMethod java/util/Map.remove:(Ljava/lang/Object;)Ljava/lang/Object;
      31: pop
      32: aload_2
      33: getstatic     #7                  // Field org/springframework/boot/web/error/ErrorAttributeOptions$Include.STACK_TRACE:Lorg/springframework/boot/web/error/ErrorAttributeOptions$Include;
      36: invokevirtual #13                 // Method org/springframework/boot/web/error/ErrorAttributeOptions.isIncluded:(Lorg/springframework/boot/web/error/ErrorAttributeOptions$Include;)Z
      39: ifne          51
      42: aload_3
      43: ldc           #36                 // String trace
      45: invokeinterface #30,  2           // InterfaceMethod java/util/Map.remove:(Ljava/lang/Object;)Ljava/lang/Object;
      50: pop
      51: aload_2
      52: getstatic     #38                 // Field org/springframework/boot/web/error/ErrorAttributeOptions$Include.MESSAGE:Lorg/springframework/boot/web/error/ErrorAttributeOptions$Include;
      55: invokevirtual #13                 // Method org/springframework/boot/web/error/ErrorAttributeOptions.isIncluded:(Lorg/springframework/boot/web/error/ErrorAttributeOptions$Include;)Z
      58: ifne          81
      61: aload_3
      62: ldc           #41                 // String message
      64: invokeinterface #43,  2           // InterfaceMethod java/util/Map.get:(Ljava/lang/Object;)Ljava/lang/Object;
      69: ifnull        81
      72: aload_3
      73: ldc           #41                 // String message
      75: invokeinterface #30,  2           // InterfaceMethod java/util/Map.remove:(Ljava/lang/Object;)Ljava/lang/Object;
      80: pop
      81: aload_2
      82: getstatic     #46                 // Field org/springframework/boot/web/error/ErrorAttributeOptions$Include.BINDING_ERRORS:Lorg/springframework/boot/web/error/ErrorAttributeOptions$Include;
      85: invokevirtual #13                 // Method org/springframework/boot/web/error/ErrorAttributeOptions.isIncluded:(Lorg/springframework/boot/web/error/ErrorAttributeOptions$Include;)Z
      88: ifne          100
      91: aload_3
      92: ldc           #49                 // String errors
      94: invokeinterface #30,  2           // InterfaceMethod java/util/Map.remove:(Ljava/lang/Object;)Ljava/lang/Object;
      99: pop
     100: aload_3
     101: areturn

  private java.util.Map<java.lang.String, java.lang.Object> getErrorAttributes(org.springframework.web.reactive.function.server.ServerRequest, boolean);
    Code:
       0: new           #51                 // class java/util/LinkedHashMap
       3: dup
       4: invokespecial #53                 // Method java/util/LinkedHashMap."<init>":()V
       7: astore_3
       8: aload_3
       9: ldc           #54                 // String timestamp
      11: new           #56                 // class java/util/Date
      14: dup
      15: invokespecial #58                 // Method java/util/Date."<init>":()V
      18: invokeinterface #59,  3           // InterfaceMethod java/util/Map.put:(Ljava/lang/Object;Ljava/lang/Object;)Ljava/lang/Object;
      23: pop
      24: aload_3
      25: ldc           #63                 // String path
      27: aload_1
      28: invokeinterface #65,  1           // InterfaceMethod org/springframework/web/reactive/function/server/ServerRequest.path:()Ljava/lang/String;
      33: invokeinterface #59,  3           // InterfaceMethod java/util/Map.put:(Ljava/lang/Object;Ljava/lang/Object;)Ljava/lang/Object;
      38: pop
      39: aload_0
      40: aload_1
      41: invokevirtual #70                 // Method getError:(Lorg/springframework/web/reactive/function/server/ServerRequest;)Ljava/lang/Throwable;
      44: astore        4
      46: aload         4
      48: invokevirtual #74                 // Method java/lang/Object.getClass:()Ljava/lang/Class;
      51: getstatic     #78                 // Field org/springframework/core/annotation/MergedAnnotations$SearchStrategy.TYPE_HIERARCHY:Lorg/springframework/core/annotation/MergedAnnotations$SearchStrategy;
      54: invokestatic  #84                 // InterfaceMethod org/springframework/core/annotation/MergedAnnotations.from:(Ljava/lang/reflect/AnnotatedElement;Lorg/springframework/core/annotation/MergedAnnotations$SearchStrategy;)Lorg/springframework/core/annotation/MergedAnnotations;
      57: ldc           #90                 // class org/springframework/web/bind/annotation/ResponseStatus
      59: invokeinterface #92,  2           // InterfaceMethod org/springframework/core/annotation/MergedAnnotations.get:(Ljava/lang/Class;)Lorg/springframework/core/annotation/MergedAnnotation;
      64: astore        5
      66: aload_0
      67: aload         4
      69: aload         5
      71: invokevirtual #95                 // Method determineHttpStatus:(Ljava/lang/Throwable;Lorg/springframework/core/annotation/MergedAnnotation;)Lorg/springframework/http/HttpStatus;
      74: astore        6
      76: aload_3
      77: ldc           #99                 // String status
      79: aload         6
      81: invokevirtual #101                // Method org/springframework/http/HttpStatus.value:()I
      84: invokestatic  #107                // Method java/lang/Integer.valueOf:(I)Ljava/lang/Integer;
      87: invokeinterface #59,  3           // InterfaceMethod java/util/Map.put:(Ljava/lang/Object;Ljava/lang/Object;)Ljava/lang/Object;
      92: pop
      93: aload_3
      94: ldc           #113                // String error
      96: aload         6
      98: invokevirtual #115                // Method org/springframework/http/HttpStatus.getReasonPhrase:()Ljava/lang/String;
     101: invokeinterface #59,  3           // InterfaceMethod java/util/Map.put:(Ljava/lang/Object;Ljava/lang/Object;)Ljava/lang/Object;
     106: pop
     107: aload_3
     108: ldc           #41                 // String message
     110: aload_0
     111: aload         4
     113: aload         5
     115: invokevirtual #118                // Method determineMessage:(Ljava/lang/Throwable;Lorg/springframework/core/annotation/MergedAnnotation;)Ljava/lang/String;
     118: invokeinterface #59,  3           // InterfaceMethod java/util/Map.put:(Ljava/lang/Object;Ljava/lang/Object;)Ljava/lang/Object;
     123: pop
     124: aload_3
     125: ldc           #122                // String requestId
     127: aload_1
     128: invokeinterface #124,  1          // InterfaceMethod org/springframework/web/reactive/function/server/ServerRequest.exchange:()Lorg/springframework/web/server/ServerWebExchange;
     133: invokeinterface #128,  1          // InterfaceMethod org/springframework/web/server/ServerWebExchange.getRequest:()Lorg/springframework/http/server/reactive/ServerHttpRequest;
     138: invokeinterface #134,  1          // InterfaceMethod org/springframework/http/server/reactive/ServerHttpRequest.getId:()Ljava/lang/String;
     143: invokeinterface #59,  3           // InterfaceMethod java/util/Map.put:(Ljava/lang/Object;Ljava/lang/Object;)Ljava/lang/Object;
     148: pop
     149: aload_0
     150: aload_3
     151: aload_0
     152: aload         4
     154: invokevirtual #139                // Method determineException:(Ljava/lang/Throwable;)Ljava/lang/Throwable;
     157: iload_2
     158: invokevirtual #143                // Method handleException:(Ljava/util/Map;Ljava/lang/Throwable;Z)V
     161: aload_3
     162: areturn

  private org.springframework.http.HttpStatus determineHttpStatus(java.lang.Throwable, org.springframework.core.annotation.MergedAnnotation<org.springframework.web.bind.annotation.ResponseStatus>);
    Code:
       0: aload_1
       1: instanceof    #147                // class org/springframework/web/server/ResponseStatusException
       4: ifeq          34
       7: aload_1
       8: checkcast     #147                // class org/springframework/web/server/ResponseStatusException
      11: astore_3
      12: aload_3
      13: invokevirtual #149                // Method org/springframework/web/server/ResponseStatusException.getStatusCode:()Lorg/springframework/http/HttpStatusCode;
      16: invokeinterface #153,  1          // InterfaceMethod org/springframework/http/HttpStatusCode.value:()I
      21: invokestatic  #156                // Method org/springframework/http/HttpStatus.resolve:(I)Lorg/springframework/http/HttpStatus;
      24: astore        4
      26: aload         4
      28: ifnull        34
      31: aload         4
      33: areturn
      34: aload_2
      35: ldc           #160                // String code
      37: ldc           #102                // class org/springframework/http/HttpStatus
      39: invokeinterface #162,  3          // InterfaceMethod org/springframework/core/annotation/MergedAnnotation.getValue:(Ljava/lang/String;Ljava/lang/Class;)Ljava/util/Optional;
      44: getstatic     #168                // Field org/springframework/http/HttpStatus.INTERNAL_SERVER_ERROR:Lorg/springframework/http/HttpStatus;
      47: invokevirtual #172                // Method java/util/Optional.orElse:(Ljava/lang/Object;)Ljava/lang/Object;
      50: checkcast     #102                // class org/springframework/http/HttpStatus
      53: areturn

  private java.lang.String determineMessage(java.lang.Throwable, org.springframework.core.annotation.MergedAnnotation<org.springframework.web.bind.annotation.ResponseStatus>);
    Code:
       0: aload_1
       1: instanceof    #177                // class org/springframework/validation/BindingResult
       4: ifeq          12
       7: aload_1
       8: invokevirtual #179                // Method java/lang/Throwable.getMessage:()Ljava/lang/String;
      11: areturn
      12: aload_1
      13: instanceof    #147                // class org/springframework/web/server/ResponseStatusException
      16: ifeq          29
      19: aload_1
      20: checkcast     #147                // class org/springframework/web/server/ResponseStatusException
      23: astore_3
      24: aload_3
      25: invokevirtual #184                // Method org/springframework/web/server/ResponseStatusException.getReason:()Ljava/lang/String;
      28: areturn
      29: aload_2
      30: ldc           #187                // String reason
      32: ldc           #189                // class java/lang/String
      34: invokeinterface #162,  3          // InterfaceMethod org/springframework/core/annotation/MergedAnnotation.getValue:(Ljava/lang/String;Ljava/lang/Class;)Ljava/util/Optional;
      39: ldc           #191                // String
      41: invokevirtual #172                // Method java/util/Optional.orElse:(Ljava/lang/Object;)Ljava/lang/Object;
      44: checkcast     #189                // class java/lang/String
      47: astore_3
      48: aload_3
      49: invokestatic  #193                // Method org/springframework/util/StringUtils.hasText:(Ljava/lang/String;)Z
      52: ifeq          57
      55: aload_3
      56: areturn
      57: aload_1
      58: invokevirtual #179                // Method java/lang/Throwable.getMessage:()Ljava/lang/String;
      61: ifnull        71
      64: aload_1
      65: invokevirtual #179                // Method java/lang/Throwable.getMessage:()Ljava/lang/String;
      68: goto          73
      71: ldc           #191                // String
      73: areturn

  private java.lang.Throwable determineException(java.lang.Throwable);
    Code:
       0: aload_1
       1: instanceof    #147                // class org/springframework/web/server/ResponseStatusException
       4: ifeq          23
       7: aload_1
       8: invokevirtual #199                // Method java/lang/Throwable.getCause:()Ljava/lang/Throwable;
      11: ifnull        21
      14: aload_1
      15: invokevirtual #199                // Method java/lang/Throwable.getCause:()Ljava/lang/Throwable;
      18: goto          22
      21: aload_1
      22: areturn
      23: aload_1
      24: areturn

  private void addStackTrace(java.util.Map<java.lang.String, java.lang.Object>, java.lang.Throwable);
    Code:
       0: new           #203                // class java/io/StringWriter
       3: dup
       4: invokespecial #205                // Method java/io/StringWriter."<init>":()V
       7: astore_3
       8: aload_2
       9: new           #206                // class java/io/PrintWriter
      12: dup
      13: aload_3
      14: invokespecial #208                // Method java/io/PrintWriter."<init>":(Ljava/io/Writer;)V
      17: invokevirtual #211                // Method java/lang/Throwable.printStackTrace:(Ljava/io/PrintWriter;)V
      20: aload_3
      21: invokevirtual #215                // Method java/io/StringWriter.flush:()V
      24: aload_1
      25: ldc           #36                 // String trace
      27: aload_3
      28: invokevirtual #218                // Method java/io/StringWriter.toString:()Ljava/lang/String;
      31: invokeinterface #59,  3           // InterfaceMethod java/util/Map.put:(Ljava/lang/Object;Ljava/lang/Object;)Ljava/lang/Object;
      36: pop
      37: return

  private void handleException(java.util.Map<java.lang.String, java.lang.Object>, java.lang.Throwable, boolean);
    Code:
       0: aload_1
       1: ldc           #28                 // String exception
       3: aload_2
       4: invokevirtual #74                 // Method java/lang/Object.getClass:()Ljava/lang/Class;
       7: invokevirtual #221                // Method java/lang/Class.getName:()Ljava/lang/String;
      10: invokeinterface #59,  3           // InterfaceMethod java/util/Map.put:(Ljava/lang/Object;Ljava/lang/Object;)Ljava/lang/Object;
      15: pop
      16: iload_3
      17: ifeq          26
      20: aload_0
      21: aload_1
      22: aload_2
      23: invokevirtual #226                // Method addStackTrace:(Ljava/util/Map;Ljava/lang/Throwable;)V
      26: aload_2
      27: instanceof    #177                // class org/springframework/validation/BindingResult
      30: ifeq          65
      33: aload_2
      34: checkcast     #177                // class org/springframework/validation/BindingResult
      37: astore        4
      39: aload         4
      41: invokeinterface #230,  1          // InterfaceMethod org/springframework/validation/BindingResult.hasErrors:()Z
      46: ifeq          65
      49: aload_1
      50: ldc           #49                 // String errors
      52: aload         4
      54: invokeinterface #234,  1          // InterfaceMethod org/springframework/validation/BindingResult.getAllErrors:()Ljava/util/List;
      59: invokeinterface #59,  3           // InterfaceMethod java/util/Map.put:(Ljava/lang/Object;Ljava/lang/Object;)Ljava/lang/Object;
      64: pop
      65: return

  public java.lang.Throwable getError(org.springframework.web.reactive.function.server.ServerRequest);
    Code:
       0: aload_1
       1: getstatic     #238                // Field ERROR_INTERNAL_ATTRIBUTE:Ljava/lang/String;
       4: invokeinterface #242,  2          // InterfaceMethod org/springframework/web/reactive/function/server/ServerRequest.attribute:(Ljava/lang/String;)Ljava/util/Optional;
       9: astore_2
      10: aload_2
      11: aload_1
      12: invokedynamic #246,  0            // InvokeDynamic #0:accept:(Lorg/springframework/web/reactive/function/server/ServerRequest;)Ljava/util/function/Consumer;
      17: invokevirtual #250                // Method java/util/Optional.ifPresent:(Ljava/util/function/Consumer;)V
      20: aload_2
      21: invokedynamic #254,  0            // InvokeDynamic #1:get:()Ljava/util/function/Supplier;
      26: invokevirtual #257                // Method java/util/Optional.orElseThrow:(Ljava/util/function/Supplier;)Ljava/lang/Object;
      29: checkcast     #180                // class java/lang/Throwable
      32: areturn

  public void storeErrorInformation(java.lang.Throwable, org.springframework.web.server.ServerWebExchange);
    Code:
       0: aload_2
       1: invokeinterface #261,  1          // InterfaceMethod org/springframework/web/server/ServerWebExchange.getAttributes:()Ljava/util/Map;
       6: getstatic     #238                // Field ERROR_INTERNAL_ATTRIBUTE:Ljava/lang/String;
       9: aload_1
      10: invokeinterface #265,  3          // InterfaceMethod java/util/Map.putIfAbsent:(Ljava/lang/Object;Ljava/lang/Object;)Ljava/lang/Object;
      15: pop
      16: return

  private static java.lang.IllegalStateException lambda$getError$1();
    Code:
       0: new           #268                // class java/lang/IllegalStateException
       3: dup
       4: ldc_w         #270                // String Missing exception attribute in ServerWebExchange
       7: invokespecial #272                // Method java/lang/IllegalStateException."<init>":(Ljava/lang/String;)V
      10: areturn

  private static void lambda$getError$0(org.springframework.web.reactive.function.server.ServerRequest, java.lang.Object);
    Code:
       0: aload_0
       1: invokeinterface #275,  1          // InterfaceMethod org/springframework/web/reactive/function/server/ServerRequest.attributes:()Ljava/util/Map;
       6: getstatic     #278                // Field org/springframework/boot/web/reactive/error/ErrorAttributes.ERROR_ATTRIBUTE:Ljava/lang/String;
       9: aload_1
      10: invokeinterface #265,  3          // InterfaceMethod java/util/Map.putIfAbsent:(Ljava/lang/Object;Ljava/lang/Object;)Ljava/lang/Object;
      15: pop
      16: return

  static {};
    Code:
       0: ldc           #20                 // class org/springframework/boot/web/reactive/error/DefaultErrorAttributes
       2: invokevirtual #221                // Method java/lang/Class.getName:()Ljava/lang/String;
       5: invokedynamic #283,  0            // InvokeDynamic #2:makeConcatWithConstants:(Ljava/lang/String;)Ljava/lang/String;
      10: putstatic     #238                // Field ERROR_INTERNAL_ATTRIBUTE:Ljava/lang/String;
      13: return
}
