Compiled from "RegistryMetricsCollector.java"
class org.apache.dubbo.metrics.registry.collector.RegistryMetricsCollector$1 extends org.apache.dubbo.metrics.data.BaseStatComposite {
  org.apache.dubbo.metrics.registry.collector.RegistryMetricsCollector$1(org.apache.dubbo.rpc.model.ApplicationModel);
    Code:
       0: aload_0
       1: aload_1
       2: invokespecial #1                  // Method org/apache/dubbo/metrics/data/BaseStatComposite."<init>":(Lorg/apache/dubbo/rpc/model/ApplicationModel;)V
       5: return

  protected void init(org.apache.dubbo.metrics.data.ApplicationStatComposite);
    Code:
       0: aload_0
       1: aload_1
       2: invokespecial #2                  // Method org/apache/dubbo/metrics/data/BaseStatComposite.init:(Lorg/apache/dubbo/metrics/data/ApplicationStatComposite;)V
       5: aload_1
       6: getstatic     #3                  // Field org/apache/dubbo/metrics/registry/RegistryMetricsConstants.APP_LEVEL_KEYS:Ljava/util/List;
       9: invokevirtual #4                  // Method org/apache/dubbo/metrics/data/ApplicationStatComposite.init:(Ljava/util/List;)V
      12: return

  protected void init(org.apache.dubbo.metrics.data.ServiceStatComposite);
    Code:
       0: aload_0
       1: aload_1
       2: invokespecial #5                  // Method org/apache/dubbo/metrics/data/BaseStatComposite.init:(Lorg/apache/dubbo/metrics/data/ServiceStatComposite;)V
       5: aload_1
       6: getstatic     #6                  // Field org/apache/dubbo/metrics/registry/RegistryMetricsConstants.SERVICE_LEVEL_KEYS:Ljava/util/List;
       9: invokevirtual #7                  // Method org/apache/dubbo/metrics/data/ServiceStatComposite.initWrapper:(Ljava/util/List;)V
      12: return

  protected void init(org.apache.dubbo.metrics.data.RtStatComposite);
    Code:
       0: aload_0
       1: aload_1
       2: invokespecial #8                  // Method org/apache/dubbo/metrics/data/BaseStatComposite.init:(Lorg/apache/dubbo/metrics/data/RtStatComposite;)V
       5: aload_1
       6: iconst_5
       7: anewarray     #9                  // class org/apache/dubbo/metrics/model/key/MetricsPlaceValue
      10: dup
      11: iconst_0
      12: getstatic     #10                 // Field org/apache/dubbo/metrics/registry/RegistryMetricsConstants.OP_TYPE_REGISTER:Lorg/apache/dubbo/metrics/model/key/MetricsPlaceValue;
      15: aastore
      16: dup
      17: iconst_1
      18: getstatic     #11                 // Field org/apache/dubbo/metrics/registry/RegistryMetricsConstants.OP_TYPE_SUBSCRIBE:Lorg/apache/dubbo/metrics/model/key/MetricsPlaceValue;
      21: aastore
      22: dup
      23: iconst_2
      24: getstatic     #12                 // Field org/apache/dubbo/metrics/registry/RegistryMetricsConstants.OP_TYPE_NOTIFY:Lorg/apache/dubbo/metrics/model/key/MetricsPlaceValue;
      27: aastore
      28: dup
      29: iconst_3
      30: getstatic     #13                 // Field org/apache/dubbo/metrics/registry/RegistryMetricsConstants.OP_TYPE_REGISTER_SERVICE:Lorg/apache/dubbo/metrics/model/key/MetricsPlaceValue;
      33: aastore
      34: dup
      35: iconst_4
      36: getstatic     #14                 // Field org/apache/dubbo/metrics/registry/RegistryMetricsConstants.OP_TYPE_SUBSCRIBE_SERVICE:Lorg/apache/dubbo/metrics/model/key/MetricsPlaceValue;
      39: aastore
      40: invokevirtual #15                 // Method org/apache/dubbo/metrics/data/RtStatComposite.init:([Lorg/apache/dubbo/metrics/model/key/MetricsPlaceValue;)V
      43: return
}
