Compiled from "TriDecoder.java"
final class org.apache.dubbo.rpc.protocol.tri.frame.TriDecoder$GrpcDecodeState extends java.lang.Enum<org.apache.dubbo.rpc.protocol.tri.frame.TriDecoder$GrpcDecodeState> {
  public static final org.apache.dubbo.rpc.protocol.tri.frame.TriDecoder$GrpcDecodeState HEADER;

  public static final org.apache.dubbo.rpc.protocol.tri.frame.TriDecoder$GrpcDecodeState PAYLOAD;

  private static final org.apache.dubbo.rpc.protocol.tri.frame.TriDecoder$GrpcDecodeState[] $VALUES;

  public static org.apache.dubbo.rpc.protocol.tri.frame.TriDecoder$GrpcDecodeState[] values();
    Code:
       0: getstatic     #1                  // Field $VALUES:[Lorg/apache/dubbo/rpc/protocol/tri/frame/TriDecoder$GrpcDecodeState;
       3: invokevirtual #2                  // Method "[Lorg/apache/dubbo/rpc/protocol/tri/frame/TriDecoder$GrpcDecodeState;".clone:()Ljava/lang/Object;
       6: checkcast     #3                  // class "[Lorg/apache/dubbo/rpc/protocol/tri/frame/TriDecoder$GrpcDecodeState;"
       9: areturn

  public static org.apache.dubbo.rpc.protocol.tri.frame.TriDecoder$GrpcDecodeState valueOf(java.lang.String);
    Code:
       0: ldc           #4                  // class org/apache/dubbo/rpc/protocol/tri/frame/TriDecoder$GrpcDecodeState
       2: aload_0
       3: invokestatic  #5                  // Method java/lang/Enum.valueOf:(Ljava/lang/Class;Ljava/lang/String;)Ljava/lang/Enum;
       6: checkcast     #4                  // class org/apache/dubbo/rpc/protocol/tri/frame/TriDecoder$GrpcDecodeState
       9: areturn

  private org.apache.dubbo.rpc.protocol.tri.frame.TriDecoder$GrpcDecodeState();
    Code:
       0: aload_0
       1: aload_1
       2: iload_2
       3: invokespecial #6                  // Method java/lang/Enum."<init>":(Ljava/lang/String;I)V
       6: return

  static {};
    Code:
       0: new           #4                  // class org/apache/dubbo/rpc/protocol/tri/frame/TriDecoder$GrpcDecodeState
       3: dup
       4: ldc           #7                  // String HEADER
       6: iconst_0
       7: invokespecial #8                  // Method "<init>":(Ljava/lang/String;I)V
      10: putstatic     #9                  // Field HEADER:Lorg/apache/dubbo/rpc/protocol/tri/frame/TriDecoder$GrpcDecodeState;
      13: new           #4                  // class org/apache/dubbo/rpc/protocol/tri/frame/TriDecoder$GrpcDecodeState
      16: dup
      17: ldc           #10                 // String PAYLOAD
      19: iconst_1
      20: invokespecial #8                  // Method "<init>":(Ljava/lang/String;I)V
      23: putstatic     #11                 // Field PAYLOAD:Lorg/apache/dubbo/rpc/protocol/tri/frame/TriDecoder$GrpcDecodeState;
      26: iconst_2
      27: anewarray     #4                  // class org/apache/dubbo/rpc/protocol/tri/frame/TriDecoder$GrpcDecodeState
      30: dup
      31: iconst_0
      32: getstatic     #9                  // Field HEADER:Lorg/apache/dubbo/rpc/protocol/tri/frame/TriDecoder$GrpcDecodeState;
      35: aastore
      36: dup
      37: iconst_1
      38: getstatic     #11                 // Field PAYLOAD:Lorg/apache/dubbo/rpc/protocol/tri/frame/TriDecoder$GrpcDecodeState;
      41: aastore
      42: putstatic     #1                  // Field $VALUES:[Lorg/apache/dubbo/rpc/protocol/tri/frame/TriDecoder$GrpcDecodeState;
      45: return
}
