Compiled from "TriDecoder.java"
class org.apache.dubbo.rpc.protocol.tri.frame.TriDecoder$1 {
  static final int[] $SwitchMap$org$apache$dubbo$rpc$protocol$tri$frame$TriDecoder$GrpcDecodeState;

  static {};
    Code:
       0: invokestatic  #1                  // Method org/apache/dubbo/rpc/protocol/tri/frame/TriDecoder$GrpcDecodeState.values:()[Lorg/apache/dubbo/rpc/protocol/tri/frame/TriDecoder$GrpcDecodeState;
       3: arraylength
       4: newarray       int
       6: putstatic     #2                  // Field $SwitchMap$org$apache$dubbo$rpc$protocol$tri$frame$TriDecoder$GrpcDecodeState:[I
       9: getstatic     #2                  // Field $SwitchMap$org$apache$dubbo$rpc$protocol$tri$frame$TriDecoder$GrpcDecodeState:[I
      12: getstatic     #3                  // Field org/apache/dubbo/rpc/protocol/tri/frame/TriDecoder$GrpcDecodeState.HEADER:Lorg/apache/dubbo/rpc/protocol/tri/frame/TriDecoder$GrpcDecodeState;
      15: invokevirtual #4                  // Method org/apache/dubbo/rpc/protocol/tri/frame/TriDecoder$GrpcDecodeState.ordinal:()I
      18: iconst_1
      19: iastore
      20: goto          24
      23: astore_0
      24: getstatic     #2                  // Field $SwitchMap$org$apache$dubbo$rpc$protocol$tri$frame$TriDecoder$GrpcDecodeState:[I
      27: getstatic     #6                  // Field org/apache/dubbo/rpc/protocol/tri/frame/TriDecoder$GrpcDecodeState.PAYLOAD:Lorg/apache/dubbo/rpc/protocol/tri/frame/TriDecoder$GrpcDecodeState;
      30: invokevirtual #4                  // Method org/apache/dubbo/rpc/protocol/tri/frame/TriDecoder$GrpcDecodeState.ordinal:()I
      33: iconst_2
      34: iastore
      35: goto          39
      38: astore_0
      39: return
    Exception table:
       from    to  target type
           9    20    23   Class java/lang/NoSuchFieldError
          24    35    38   Class java/lang/NoSuchFieldError
}
