Compiled from "GenericException.java"
public class com.alibaba.dubbo.rpc.service.GenericException extends java.lang.RuntimeException {
  private static final long serialVersionUID;

  private java.lang.String exceptionClass;

  private java.lang.String exceptionMessage;

  public com.alibaba.dubbo.rpc.service.GenericException();
    Code:
       0: aload_0
       1: invokespecial #1                  // Method java/lang/RuntimeException."<init>":()V
       4: return

  public com.alibaba.dubbo.rpc.service.GenericException(java.lang.String, java.lang.String);
    Code:
       0: aload_0
       1: aload_2
       2: invokespecial #2                  // Method java/lang/RuntimeException."<init>":(Ljava/lang/String;)V
       5: aload_0
       6: aload_1
       7: putfield      #3                  // Field exceptionClass:Ljava/lang/String;
      10: aload_0
      11: aload_2
      12: putfield      #4                  // Field exceptionMessage:Ljava/lang/String;
      15: return

  public com.alibaba.dubbo.rpc.service.GenericException(java.lang.Throwable);
    Code:
       0: aload_0
       1: aload_1
       2: invokestatic  #5                  // Method org/apache/dubbo/common/utils/StringUtils.toString:(Ljava/lang/Throwable;)Ljava/lang/String;
       5: invokespecial #2                  // Method java/lang/RuntimeException."<init>":(Ljava/lang/String;)V
       8: aload_0
       9: aload_1
      10: invokevirtual #6                  // Method java/lang/Object.getClass:()Ljava/lang/Class;
      13: invokevirtual #7                  // Method java/lang/Class.getName:()Ljava/lang/String;
      16: putfield      #3                  // Field exceptionClass:Ljava/lang/String;
      19: aload_0
      20: aload_1
      21: invokevirtual #8                  // Method java/lang/Throwable.getMessage:()Ljava/lang/String;
      24: putfield      #4                  // Field exceptionMessage:Ljava/lang/String;
      27: return

  public java.lang.String getExceptionClass();
    Code:
       0: aload_0
       1: getfield      #3                  // Field exceptionClass:Ljava/lang/String;
       4: areturn

  public void setExceptionClass(java.lang.String);
    Code:
       0: aload_0
       1: aload_1
       2: putfield      #3                  // Field exceptionClass:Ljava/lang/String;
       5: return

  public java.lang.String getExceptionMessage();
    Code:
       0: aload_0
       1: getfield      #4                  // Field exceptionMessage:Ljava/lang/String;
       4: areturn

  public void setExceptionMessage(java.lang.String);
    Code:
       0: aload_0
       1: aload_1
       2: putfield      #4                  // Field exceptionMessage:Ljava/lang/String;
       5: return
}
