Compiled from "BodyProviderParamParser.java"
public class org.apache.dubbo.rpc.protocol.rest.annotation.param.parse.provider.BodyProviderParamParser extends org.apache.dubbo.rpc.protocol.rest.annotation.param.parse.provider.ProviderParamParser {
  public org.apache.dubbo.rpc.protocol.rest.annotation.param.parse.provider.BodyProviderParamParser();
    Code:
       0: aload_0
       1: invokespecial #1                  // Method org/apache/dubbo/rpc/protocol/rest/annotation/param/parse/provider/ProviderParamParser."<init>":()V
       4: return

  protected void doParse(org.apache.dubbo.rpc.protocol.rest.annotation.param.parse.provider.ProviderParseContext, org.apache.dubbo.metadata.rest.ArgInfo);
    Code:
       0: aload_1
       1: invokevirtual #2                  // Method org/apache/dubbo/rpc/protocol/rest/annotation/param/parse/provider/ProviderParseContext.getRequestFacade:()Lorg/apache/dubbo/rpc/protocol/rest/request/RequestFacade;
       4: astore_3
       5: aload_1
       6: invokevirtual #2                  // Method org/apache/dubbo/rpc/protocol/rest/annotation/param/parse/provider/ProviderParseContext.getRequestFacade:()Lorg/apache/dubbo/rpc/protocol/rest/request/RequestFacade;
       9: getstatic     #3                  // Field org/apache/dubbo/rpc/protocol/rest/RestHeaderEnum.CONTENT_TYPE:Lorg/apache/dubbo/rpc/protocol/rest/RestHeaderEnum;
      12: invokevirtual #4                  // Method org/apache/dubbo/rpc/protocol/rest/RestHeaderEnum.getHeader:()Ljava/lang/String;
      15: invokevirtual #5                  // Method org/apache/dubbo/rpc/protocol/rest/request/RequestFacade.getHeader:(Ljava/lang/String;)Ljava/lang/String;
      18: astore        4
      20: aload_2
      21: invokevirtual #6                  // Method org/apache/dubbo/metadata/rest/ArgInfo.getParamType:()Ljava/lang/Class;
      24: iconst_1
      25: anewarray     #7                  // class java/lang/String
      28: dup
      29: iconst_0
      30: aload         4
      32: aastore
      33: invokestatic  #8                  // Method org/apache/dubbo/rpc/protocol/rest/util/MediaTypeUtil.convertMediaType:(Ljava/lang/Class;[Ljava/lang/String;)Lorg/apache/dubbo/metadata/rest/media/MediaType;
      36: astore        5
      38: aload_3
      39: invokevirtual #9                  // Method org/apache/dubbo/rpc/protocol/rest/request/RequestFacade.getInputStream:()[B
      42: aload_2
      43: invokevirtual #6                  // Method org/apache/dubbo/metadata/rest/ArgInfo.getParamType:()Ljava/lang/Class;
      46: aload         5
      48: invokestatic  #10                 // Method org/apache/dubbo/rpc/protocol/rest/message/HttpMessageCodecManager.httpMessageDecode:([BLjava/lang/Class;Lorg/apache/dubbo/metadata/rest/media/MediaType;)Ljava/lang/Object;
      51: astore        6
      53: aload_1
      54: aload_2
      55: invokevirtual #11                 // Method org/apache/dubbo/metadata/rest/ArgInfo.getIndex:()I
      58: aload         6
      60: invokevirtual #12                 // Method org/apache/dubbo/rpc/protocol/rest/annotation/param/parse/provider/ProviderParseContext.setValueByIndex:(ILjava/lang/Object;)V
      63: goto          99
      66: astore        4
      68: new           #14                 // class org/apache/dubbo/rpc/protocol/rest/exception/ParamParseException
      71: dup
      72: new           #15                 // class java/lang/StringBuilder
      75: dup
      76: invokespecial #16                 // Method java/lang/StringBuilder."<init>":()V
      79: ldc           #17                 // String dubbo rest protocol provider body param parser  error:
      81: invokevirtual #18                 // Method java/lang/StringBuilder.append:(Ljava/lang/String;)Ljava/lang/StringBuilder;
      84: aload         4
      86: invokevirtual #19                 // Method java/lang/Throwable.getMessage:()Ljava/lang/String;
      89: invokevirtual #18                 // Method java/lang/StringBuilder.append:(Ljava/lang/String;)Ljava/lang/StringBuilder;
      92: invokevirtual #20                 // Method java/lang/StringBuilder.toString:()Ljava/lang/String;
      95: invokespecial #21                 // Method org/apache/dubbo/rpc/protocol/rest/exception/ParamParseException."<init>":(Ljava/lang/String;)V
      98: athrow
      99: return
    Exception table:
       from    to  target type
           5    63    66   Class java/lang/Throwable

  protected org.apache.dubbo.metadata.rest.ParamType getParamType();
    Code:
       0: getstatic     #22                 // Field org/apache/dubbo/metadata/rest/ParamType.PROVIDER_BODY:Lorg/apache/dubbo/metadata/rest/ParamType;
       3: areturn
}
