Compiled from "ParamProviderParamParser.java"
public class org.apache.dubbo.rpc.protocol.rest.annotation.param.parse.provider.ParamProviderParamParser extends org.apache.dubbo.rpc.protocol.rest.annotation.param.parse.provider.ProviderParamParser {
  public org.apache.dubbo.rpc.protocol.rest.annotation.param.parse.provider.ParamProviderParamParser();
    Code:
       0: aload_0
       1: invokespecial #1                  // Method org/apache/dubbo/rpc/protocol/rest/annotation/param/parse/provider/ProviderParamParser."<init>":()V
       4: return

  protected void doParse(org.apache.dubbo.rpc.protocol.rest.annotation.param.parse.provider.ProviderParseContext, org.apache.dubbo.metadata.rest.ArgInfo);
    Code:
       0: aload_1
       1: invokevirtual #2                  // Method org/apache/dubbo/rpc/protocol/rest/annotation/param/parse/provider/ProviderParseContext.getRequestFacade:()Lorg/apache/dubbo/rpc/protocol/rest/request/RequestFacade;
       4: astore_3
       5: ldc           #3                  // class java/util/Map
       7: aload_2
       8: invokevirtual #4                  // Method org/apache/dubbo/metadata/rest/ArgInfo.getParamType:()Ljava/lang/Class;
      11: invokevirtual #5                  // Method java/lang/Class.isAssignableFrom:(Ljava/lang/Class;)Z
      14: ifeq          84
      17: new           #6                  // class java/util/LinkedHashMap
      20: dup
      21: invokespecial #7                  // Method java/util/LinkedHashMap."<init>":()V
      24: astore        4
      26: aload_3
      27: invokevirtual #8                  // Method org/apache/dubbo/rpc/protocol/rest/request/RequestFacade.getParameterNames:()Ljava/util/Enumeration;
      30: astore        5
      32: aload         5
      34: invokeinterface #9,  1            // InterfaceMethod java/util/Enumeration.hasMoreElements:()Z
      39: ifeq          73
      42: aload         5
      44: invokeinterface #10,  1           // InterfaceMethod java/util/Enumeration.nextElement:()Ljava/lang/Object;
      49: checkcast     #11                 // class java/lang/String
      52: astore        6
      54: aload         4
      56: aload         6
      58: aload_3
      59: aload         6
      61: invokevirtual #12                 // Method org/apache/dubbo/rpc/protocol/rest/request/RequestFacade.getParameter:(Ljava/lang/String;)Ljava/lang/String;
      64: invokeinterface #13,  3           // InterfaceMethod java/util/Map.put:(Ljava/lang/Object;Ljava/lang/Object;)Ljava/lang/Object;
      69: pop
      70: goto          32
      73: aload_1
      74: aload_2
      75: invokevirtual #14                 // Method org/apache/dubbo/metadata/rest/ArgInfo.getIndex:()I
      78: aload         4
      80: invokevirtual #15                 // Method org/apache/dubbo/rpc/protocol/rest/annotation/param/parse/provider/ProviderParseContext.setValueByIndex:(ILjava/lang/Object;)V
      83: return
      84: aload_3
      85: aload_2
      86: invokevirtual #16                 // Method org/apache/dubbo/metadata/rest/ArgInfo.getAnnotationNameAttribute:()Ljava/lang/String;
      89: invokevirtual #12                 // Method org/apache/dubbo/rpc/protocol/rest/request/RequestFacade.getParameter:(Ljava/lang/String;)Ljava/lang/String;
      92: astore        4
      94: aload_0
      95: aload_2
      96: invokevirtual #4                  // Method org/apache/dubbo/metadata/rest/ArgInfo.getParamType:()Ljava/lang/Class;
      99: aload         4
     101: invokevirtual #17                 // Method paramTypeConvert:(Ljava/lang/Class;Ljava/lang/String;)Ljava/lang/Object;
     104: astore        5
     106: aload_1
     107: aload_2
     108: invokevirtual #14                 // Method org/apache/dubbo/metadata/rest/ArgInfo.getIndex:()I
     111: aload         5
     113: invokevirtual #15                 // Method org/apache/dubbo/rpc/protocol/rest/annotation/param/parse/provider/ProviderParseContext.setValueByIndex:(ILjava/lang/Object;)V
     116: return

  protected org.apache.dubbo.metadata.rest.ParamType getParamType();
    Code:
       0: getstatic     #18                 // Field org/apache/dubbo/metadata/rest/ParamType.PARAM:Lorg/apache/dubbo/metadata/rest/ParamType;
       3: areturn
}
