Compiled from "PathProviderParamParser.java"
public class org.apache.dubbo.rpc.protocol.rest.annotation.param.parse.provider.PathProviderParamParser extends org.apache.dubbo.rpc.protocol.rest.annotation.param.parse.provider.ProviderParamParser {
  public org.apache.dubbo.rpc.protocol.rest.annotation.param.parse.provider.PathProviderParamParser();
    Code:
       0: aload_0
       1: invokespecial #1                  // Method org/apache/dubbo/rpc/protocol/rest/annotation/param/parse/provider/ProviderParamParser."<init>":()V
       4: return

  protected void doParse(org.apache.dubbo.rpc.protocol.rest.annotation.param.parse.provider.ProviderParseContext, org.apache.dubbo.metadata.rest.ArgInfo);
    Code:
       0: aload_1
       1: aload_2
       2: invokevirtual #2                  // Method org/apache/dubbo/metadata/rest/ArgInfo.getUrlSplitIndex:()I
       5: invokevirtual #3                  // Method org/apache/dubbo/rpc/protocol/rest/annotation/param/parse/provider/ProviderParseContext.getPathVariable:(I)Ljava/lang/String;
       8: astore_3
       9: aload_0
      10: aload_2
      11: invokevirtual #4                  // Method org/apache/dubbo/metadata/rest/ArgInfo.getParamType:()Ljava/lang/Class;
      14: aload_3
      15: invokevirtual #5                  // Method paramTypeConvert:(Ljava/lang/Class;Ljava/lang/String;)Ljava/lang/Object;
      18: astore        4
      20: aload_1
      21: aload_2
      22: invokevirtual #6                  // Method org/apache/dubbo/metadata/rest/ArgInfo.getIndex:()I
      25: aload         4
      27: invokevirtual #7                  // Method org/apache/dubbo/rpc/protocol/rest/annotation/param/parse/provider/ProviderParseContext.setValueByIndex:(ILjava/lang/Object;)V
      30: return

  protected org.apache.dubbo.metadata.rest.ParamType getParamType();
    Code:
       0: getstatic     #8                  // Field org/apache/dubbo/metadata/rest/ParamType.PATH:Lorg/apache/dubbo/metadata/rest/ParamType;
       3: areturn
}
