Compiled from "ProviderParamParser.java"
public abstract class org.apache.dubbo.rpc.protocol.rest.annotation.param.parse.provider.ProviderParamParser implements org.apache.dubbo.rpc.protocol.rest.annotation.param.parse.provider.BaseProviderParamParser {
  public org.apache.dubbo.rpc.protocol.rest.annotation.param.parse.provider.ProviderParamParser();
    Code:
       0: aload_0
       1: invokespecial #1                  // Method java/lang/Object."<init>":()V
       4: return

  public void parse(org.apache.dubbo.rpc.protocol.rest.annotation.param.parse.provider.ProviderParseContext, org.apache.dubbo.metadata.rest.ArgInfo);
    Code:
       0: aload_0
       1: aload_2
       2: invokevirtual #2                  // Method org/apache/dubbo/metadata/rest/ArgInfo.getParamAnnotationType:()Ljava/lang/Class;
       5: invokevirtual #3                  // Method matchParseType:(Ljava/lang/Class;)Z
       8: ifne          12
      11: return
      12: aload_0
      13: aload_1
      14: aload_2
      15: invokevirtual #4                  // Method doParse:(Lorg/apache/dubbo/rpc/protocol/rest/annotation/param/parse/provider/ProviderParseContext;Lorg/apache/dubbo/metadata/rest/ArgInfo;)V
      18: return

  protected abstract void doParse(org.apache.dubbo.rpc.protocol.rest.annotation.param.parse.provider.ProviderParseContext, org.apache.dubbo.metadata.rest.ArgInfo);

  public boolean matchParseType(java.lang.Class);
    Code:
       0: aload_0
       1: invokevirtual #5                  // Method getParamType:()Lorg/apache/dubbo/metadata/rest/ParamType;
       4: astore_2
       5: aload_2
       6: aload_1
       7: invokevirtual #6                  // Method org/apache/dubbo/metadata/rest/ParamType.supportAnno:(Ljava/lang/Class;)Z
      10: ireturn

  protected abstract org.apache.dubbo.metadata.rest.ParamType getParamType();

  protected java.lang.Object paramTypeConvert(java.lang.Class, java.lang.String);
    Code:
       0: aload_1
       1: aload_2
       2: invokestatic  #7                  // Method org/apache/dubbo/rpc/protocol/rest/util/DataParseUtils.stringTypeConvert:(Ljava/lang/Class;Ljava/lang/String;)Ljava/lang/Object;
       5: areturn

  public void parse(java.lang.Object, org.apache.dubbo.metadata.rest.ArgInfo);
    Code:
       0: aload_0
       1: aload_1
       2: checkcast     #8                  // class org/apache/dubbo/rpc/protocol/rest/annotation/param/parse/provider/ProviderParseContext
       5: aload_2
       6: invokevirtual #9                  // Method parse:(Lorg/apache/dubbo/rpc/protocol/rest/annotation/param/parse/provider/ProviderParseContext;Lorg/apache/dubbo/metadata/rest/ArgInfo;)V
       9: return
}
