Compiled from "ProviderParseContext.java"
public class org.apache.dubbo.rpc.protocol.rest.annotation.param.parse.provider.ProviderParseContext extends org.apache.dubbo.rpc.protocol.rest.annotation.BaseParseContext {
  private org.apache.dubbo.rpc.protocol.rest.request.RequestFacade requestFacade;

  private java.lang.Object response;

  private java.lang.Object request;

  public org.apache.dubbo.rpc.protocol.rest.annotation.param.parse.provider.ProviderParseContext(org.apache.dubbo.rpc.protocol.rest.request.RequestFacade);
    Code:
       0: aload_0
       1: invokespecial #1                  // Method org/apache/dubbo/rpc/protocol/rest/annotation/BaseParseContext."<init>":()V
       4: aload_0
       5: aload_1
       6: putfield      #2                  // Field requestFacade:Lorg/apache/dubbo/rpc/protocol/rest/request/RequestFacade;
       9: return

  public org.apache.dubbo.rpc.protocol.rest.request.RequestFacade getRequestFacade();
    Code:
       0: aload_0
       1: getfield      #2                  // Field requestFacade:Lorg/apache/dubbo/rpc/protocol/rest/request/RequestFacade;
       4: areturn

  public void setValueByIndex(int, java.lang.Object);
    Code:
       0: aload_0
       1: getfield      #3                  // Field args:Ljava/util/List;
       4: iload_1
       5: aload_2
       6: invokeinterface #4,  3            // InterfaceMethod java/util/List.set:(ILjava/lang/Object;)Ljava/lang/Object;
      11: pop
      12: return

  public java.lang.Object getResponse();
    Code:
       0: aload_0
       1: getfield      #5                  // Field response:Ljava/lang/Object;
       4: areturn

  public void setResponse(java.lang.Object);
    Code:
       0: aload_0
       1: aload_1
       2: putfield      #5                  // Field response:Ljava/lang/Object;
       5: return

  public java.lang.Object getRequest();
    Code:
       0: aload_0
       1: getfield      #6                  // Field request:Ljava/lang/Object;
       4: areturn

  public void setRequest(java.lang.Object);
    Code:
       0: aload_0
       1: aload_1
       2: putfield      #6                  // Field request:Ljava/lang/Object;
       5: return

  public java.lang.String getPathVariable(int);
    Code:
       0: aload_0
       1: invokevirtual #7                  // Method getRequestFacade:()Lorg/apache/dubbo/rpc/protocol/rest/request/RequestFacade;
       4: invokevirtual #8                  // Method org/apache/dubbo/rpc/protocol/rest/request/RequestFacade.getRequestURI:()Ljava/lang/String;
       7: ldc           #9                  // String /
       9: invokevirtual #10                 // Method java/lang/String.split:(Ljava/lang/String;)[Ljava/lang/String;
      12: astore_2
      13: aload_2
      14: iload_1
      15: aaload
      16: areturn
}
