Compiled from "MemorySafeLinkedBlockingQueue.java"
public class org.apache.dubbo.common.threadpool.MemorySafeLinkedBlockingQueue<E> extends java.util.concurrent.LinkedBlockingQueue<E> {
  private static final long serialVersionUID;

  public static int THE_256_MB;

  private int maxFreeMemory;

  private org.apache.dubbo.common.concurrent.Rejector<E> rejector;

  public org.apache.dubbo.common.threadpool.MemorySafeLinkedBlockingQueue();
    Code:
       0: aload_0
       1: getstatic     #1                  // Field THE_256_MB:I
       4: invokespecial #2                  // Method "<init>":(I)V
       7: return

  public org.apache.dubbo.common.threadpool.MemorySafeLinkedBlockingQueue(int);
    Code:
       0: aload_0
       1: ldc           #4                  // int 2147483647
       3: invokespecial #5                  // Method java/util/concurrent/LinkedBlockingQueue."<init>":(I)V
       6: aload_0
       7: iload_1
       8: putfield      #6                  // Field maxFreeMemory:I
      11: aload_0
      12: new           #7                  // class org/apache/dubbo/common/concurrent/DiscardPolicy
      15: dup
      16: invokespecial #8                  // Method org/apache/dubbo/common/concurrent/DiscardPolicy."<init>":()V
      19: putfield      #9                  // Field rejector:Lorg/apache/dubbo/common/concurrent/Rejector;
      22: return

  public org.apache.dubbo.common.threadpool.MemorySafeLinkedBlockingQueue(java.util.Collection<? extends E>, int);
    Code:
       0: aload_0
       1: aload_1
       2: invokespecial #10                 // Method java/util/concurrent/LinkedBlockingQueue."<init>":(Ljava/util/Collection;)V
       5: aload_0
       6: iload_2
       7: putfield      #6                  // Field maxFreeMemory:I
      10: aload_0
      11: new           #7                  // class org/apache/dubbo/common/concurrent/DiscardPolicy
      14: dup
      15: invokespecial #8                  // Method org/apache/dubbo/common/concurrent/DiscardPolicy."<init>":()V
      18: putfield      #9                  // Field rejector:Lorg/apache/dubbo/common/concurrent/Rejector;
      21: return

  public void setMaxFreeMemory(int);
    Code:
       0: aload_0
       1: iload_1
       2: putfield      #6                  // Field maxFreeMemory:I
       5: return

  public int getMaxFreeMemory();
    Code:
       0: aload_0
       1: getfield      #6                  // Field maxFreeMemory:I
       4: ireturn

  public void setRejector(org.apache.dubbo.common.concurrent.Rejector<E>);
    Code:
       0: aload_0
       1: aload_1
       2: putfield      #9                  // Field rejector:Lorg/apache/dubbo/common/concurrent/Rejector;
       5: return

  public boolean hasRemainedMemory();
    Code:
       0: invokestatic  #11                 // Method org/apache/dubbo/common/threadpool/MemoryLimitCalculator.maxAvailable:()J
       3: aload_0
       4: getfield      #6                  // Field maxFreeMemory:I
       7: i2l
       8: lcmp
       9: ifle          16
      12: iconst_1
      13: goto          17
      16: iconst_0
      17: ireturn

  public void put(E) throws java.lang.InterruptedException;
    Code:
       0: aload_0
       1: invokevirtual #12                 // Method hasRemainedMemory:()Z
       4: ifeq          15
       7: aload_0
       8: aload_1
       9: invokespecial #13                 // Method java/util/concurrent/LinkedBlockingQueue.put:(Ljava/lang/Object;)V
      12: goto          26
      15: aload_0
      16: getfield      #9                  // Field rejector:Lorg/apache/dubbo/common/concurrent/Rejector;
      19: aload_1
      20: aload_0
      21: invokeinterface #14,  3           // InterfaceMethod org/apache/dubbo/common/concurrent/Rejector.reject:(Ljava/lang/Object;Ljava/util/Queue;)V
      26: return

  public boolean offer(E, long, java.util.concurrent.TimeUnit) throws java.lang.InterruptedException;
    Code:
       0: aload_0
       1: invokevirtual #12                 // Method hasRemainedMemory:()Z
       4: ifne          20
       7: aload_0
       8: getfield      #9                  // Field rejector:Lorg/apache/dubbo/common/concurrent/Rejector;
      11: aload_1
      12: aload_0
      13: invokeinterface #14,  3           // InterfaceMethod org/apache/dubbo/common/concurrent/Rejector.reject:(Ljava/lang/Object;Ljava/util/Queue;)V
      18: iconst_0
      19: ireturn
      20: aload_0
      21: aload_1
      22: lload_2
      23: aload         4
      25: invokespecial #15                 // Method java/util/concurrent/LinkedBlockingQueue.offer:(Ljava/lang/Object;JLjava/util/concurrent/TimeUnit;)Z
      28: ireturn

  public boolean offer(E);
    Code:
       0: aload_0
       1: invokevirtual #12                 // Method hasRemainedMemory:()Z
       4: ifne          20
       7: aload_0
       8: getfield      #9                  // Field rejector:Lorg/apache/dubbo/common/concurrent/Rejector;
      11: aload_1
      12: aload_0
      13: invokeinterface #14,  3           // InterfaceMethod org/apache/dubbo/common/concurrent/Rejector.reject:(Ljava/lang/Object;Ljava/util/Queue;)V
      18: iconst_0
      19: ireturn
      20: aload_0
      21: aload_1
      22: invokespecial #16                 // Method java/util/concurrent/LinkedBlockingQueue.offer:(Ljava/lang/Object;)Z
      25: ireturn

  static {};
    Code:
       0: ldc           #17                 // int 268435456
       2: putstatic     #1                  // Field THE_256_MB:I
       5: return
}
