Compiled from "ThreadlessExecutor.java"
public class org.apache.dubbo.common.threadpool.ThreadlessExecutor extends java.util.concurrent.AbstractExecutorService {
  private static final org.apache.dubbo.common.logger.Logger logger;

  private static final java.lang.Object SHUTDOWN;

  private final java.util.Queue<java.lang.Runnable> queue;

  private volatile java.lang.Object waiter;

  public org.apache.dubbo.common.threadpool.ThreadlessExecutor();
    Code:
       0: aload_0
       1: invokespecial #2                  // Method java/util/concurrent/AbstractExecutorService."<init>":()V
       4: aload_0
       5: new           #3                  // class java/util/concurrent/ConcurrentLinkedQueue
       8: dup
       9: invokespecial #4                  // Method java/util/concurrent/ConcurrentLinkedQueue."<init>":()V
      12: putfield      #5                  // Field queue:Ljava/util/Queue;
      15: return

  public void waitAndDrain() throws java.lang.InterruptedException;
    Code:
       0: invokestatic  #6                  // Method throwIfInterrupted:()V
       3: aload_0
       4: getfield      #5                  // Field queue:Ljava/util/Queue;
       7: invokeinterface #7,  1            // InterfaceMethod java/util/Queue.poll:()Ljava/lang/Object;
      12: checkcast     #8                  // class java/lang/Runnable
      15: astore_1
      16: aload_1
      17: ifnonnull     70
      20: aload_0
      21: invokestatic  #9                  // Method java/lang/Thread.currentThread:()Ljava/lang/Thread;
      24: putfield      #10                 // Field waiter:Ljava/lang/Object;
      27: aload_0
      28: getfield      #5                  // Field queue:Ljava/util/Queue;
      31: invokeinterface #7,  1            // InterfaceMethod java/util/Queue.poll:()Ljava/lang/Object;
      36: checkcast     #8                  // class java/lang/Runnable
      39: dup
      40: astore_1
      41: ifnonnull     54
      44: aload_0
      45: invokestatic  #11                 // Method java/util/concurrent/locks/LockSupport.park:(Ljava/lang/Object;)V
      48: invokestatic  #6                  // Method throwIfInterrupted:()V
      51: goto          27
      54: aload_0
      55: aconst_null
      56: putfield      #10                 // Field waiter:Ljava/lang/Object;
      59: goto          70
      62: astore_2
      63: aload_0
      64: aconst_null
      65: putfield      #10                 // Field waiter:Ljava/lang/Object;
      68: aload_2
      69: athrow
      70: aload_1
      71: invokeinterface #12,  1           // InterfaceMethod java/lang/Runnable.run:()V
      76: aload_0
      77: getfield      #5                  // Field queue:Ljava/util/Queue;
      80: invokeinterface #7,  1            // InterfaceMethod java/util/Queue.poll:()Ljava/lang/Object;
      85: checkcast     #8                  // class java/lang/Runnable
      88: dup
      89: astore_1
      90: ifnonnull     70
      93: return
    Exception table:
       from    to  target type
          27    54    62   any

  private static void throwIfInterrupted() throws java.lang.InterruptedException;
    Code:
       0: invokestatic  #13                 // Method java/lang/Thread.interrupted:()Z
       3: ifeq          14
       6: new           #14                 // class java/lang/InterruptedException
       9: dup
      10: invokespecial #15                 // Method java/lang/InterruptedException."<init>":()V
      13: athrow
      14: return

  public void execute(java.lang.Runnable);
    Code:
       0: new           #16                 // class org/apache/dubbo/common/threadpool/ThreadlessExecutor$RunnableWrapper
       3: dup
       4: aload_1
       5: invokespecial #17                 // Method org/apache/dubbo/common/threadpool/ThreadlessExecutor$RunnableWrapper."<init>":(Ljava/lang/Runnable;)V
       8: astore_2
       9: aload_0
      10: getfield      #5                  // Field queue:Ljava/util/Queue;
      13: aload_2
      14: invokeinterface #18,  2           // InterfaceMethod java/util/Queue.add:(Ljava/lang/Object;)Z
      19: pop
      20: aload_0
      21: getfield      #10                 // Field waiter:Ljava/lang/Object;
      24: getstatic     #19                 // Field SHUTDOWN:Ljava/lang/Object;
      27: if_acmpeq     43
      30: aload_0
      31: getfield      #10                 // Field waiter:Ljava/lang/Object;
      34: checkcast     #20                 // class java/lang/Thread
      37: invokestatic  #21                 // Method java/util/concurrent/locks/LockSupport.unpark:(Ljava/lang/Thread;)V
      40: goto          64
      43: aload_0
      44: getfield      #5                  // Field queue:Ljava/util/Queue;
      47: aload_2
      48: invokeinterface #22,  2           // InterfaceMethod java/util/Queue.remove:(Ljava/lang/Object;)Z
      53: ifeq          64
      56: new           #23                 // class java/util/concurrent/RejectedExecutionException
      59: dup
      60: invokespecial #24                 // Method java/util/concurrent/RejectedExecutionException."<init>":()V
      63: athrow
      64: return

  public void shutdown();
    Code:
       0: aload_0
       1: invokevirtual #25                 // Method shutdownNow:()Ljava/util/List;
       4: pop
       5: return

  public java.util.List<java.lang.Runnable> shutdownNow();
    Code:
       0: aload_0
       1: getstatic     #19                 // Field SHUTDOWN:Ljava/lang/Object;
       4: putfield      #10                 // Field waiter:Ljava/lang/Object;
       7: aload_0
       8: getfield      #5                  // Field queue:Ljava/util/Queue;
      11: invokeinterface #7,  1            // InterfaceMethod java/util/Queue.poll:()Ljava/lang/Object;
      16: checkcast     #8                  // class java/lang/Runnable
      19: dup
      20: astore_1
      21: ifnull        33
      24: aload_1
      25: invokeinterface #12,  1           // InterfaceMethod java/lang/Runnable.run:()V
      30: goto          7
      33: invokestatic  #26                 // Method java/util/Collections.emptyList:()Ljava/util/List;
      36: areturn

  public boolean isShutdown();
    Code:
       0: aload_0
       1: getfield      #10                 // Field waiter:Ljava/lang/Object;
       4: getstatic     #19                 // Field SHUTDOWN:Ljava/lang/Object;
       7: if_acmpne     14
      10: iconst_1
      11: goto          15
      14: iconst_0
      15: ireturn

  public boolean isTerminated();
    Code:
       0: aload_0
       1: invokevirtual #27                 // Method isShutdown:()Z
       4: ireturn

  public boolean awaitTermination(long, java.util.concurrent.TimeUnit);
    Code:
       0: iconst_0
       1: ireturn

  static org.apache.dubbo.common.logger.Logger access$000();
    Code:
       0: getstatic     #1                  // Field logger:Lorg/apache/dubbo/common/logger/Logger;
       3: areturn

  static {};
    Code:
       0: ldc           #28                 // class org/apache/dubbo/common/threadpool/ThreadlessExecutor
       2: invokevirtual #29                 // Method java/lang/Class.getName:()Ljava/lang/String;
       5: invokestatic  #30                 // Method org/apache/dubbo/common/logger/LoggerFactory.getLogger:(Ljava/lang/String;)Lorg/apache/dubbo/common/logger/Logger;
       8: putstatic     #1                  // Field logger:Lorg/apache/dubbo/common/logger/Logger;
      11: new           #31                 // class java/lang/Object
      14: dup
      15: invokespecial #32                 // Method java/lang/Object."<init>":()V
      18: putstatic     #19                 // Field SHUTDOWN:Ljava/lang/Object;
      21: return
}
