Compiled from "ThreadlessExecutor.java"
class org.apache.dubbo.common.threadpool.ThreadlessExecutor$RunnableWrapper implements java.lang.Runnable {
  private final java.lang.Runnable runnable;

  public org.apache.dubbo.common.threadpool.ThreadlessExecutor$RunnableWrapper(java.lang.Runnable);
    Code:
       0: aload_0
       1: invokespecial #1                  // Method java/lang/Object."<init>":()V
       4: aload_0
       5: aload_1
       6: putfield      #2                  // Field runnable:Ljava/lang/Runnable;
       9: return

  public void run();
    Code:
       0: aload_0
       1: getfield      #2                  // Field runnable:Ljava/lang/Runnable;
       4: invokeinterface #3,  1            // InterfaceMethod java/lang/Runnable.run:()V
       9: goto          22
      12: astore_1
      13: invokestatic  #5                  // Method org/apache/dubbo/common/threadpool/ThreadlessExecutor.access$000:()Lorg/apache/dubbo/common/logger/Logger;
      16: aload_1
      17: invokeinterface #6,  2            // InterfaceMethod org/apache/dubbo/common/logger/Logger.info:(Ljava/lang/Throwable;)V
      22: return
    Exception table:
       from    to  target type
           0     9    12   Class java/lang/Throwable
}
