Compiled from "Status.java"
public class org.apache.dubbo.common.status.Status {
  private final org.apache.dubbo.common.status.Status$Level level;

  private final java.lang.String message;

  private final java.lang.String description;

  public org.apache.dubbo.common.status.Status(org.apache.dubbo.common.status.Status$Level);
    Code:
       0: aload_0
       1: aload_1
       2: aconst_null
       3: aconst_null
       4: invokespecial #1                  // Method "<init>":(Lorg/apache/dubbo/common/status/Status$Level;Ljava/lang/String;Ljava/lang/String;)V
       7: return

  public org.apache.dubbo.common.status.Status(org.apache.dubbo.common.status.Status$Level, java.lang.String);
    Code:
       0: aload_0
       1: aload_1
       2: aload_2
       3: aconst_null
       4: invokespecial #1                  // Method "<init>":(Lorg/apache/dubbo/common/status/Status$Level;Ljava/lang/String;Ljava/lang/String;)V
       7: return

  public org.apache.dubbo.common.status.Status(org.apache.dubbo.common.status.Status$Level, java.lang.String, java.lang.String);
    Code:
       0: aload_0
       1: invokespecial #2                  // Method java/lang/Object."<init>":()V
       4: aload_0
       5: aload_1
       6: putfield      #3                  // Field level:Lorg/apache/dubbo/common/status/Status$Level;
       9: aload_0
      10: aload_2
      11: putfield      #4                  // Field message:Ljava/lang/String;
      14: aload_0
      15: aload_3
      16: putfield      #5                  // Field description:Ljava/lang/String;
      19: return

  public org.apache.dubbo.common.status.Status$Level getLevel();
    Code:
       0: aload_0
       1: getfield      #3                  // Field level:Lorg/apache/dubbo/common/status/Status$Level;
       4: areturn

  public java.lang.String getMessage();
    Code:
       0: aload_0
       1: getfield      #4                  // Field message:Ljava/lang/String;
       4: areturn

  public java.lang.String getDescription();
    Code:
       0: aload_0
       1: getfield      #5                  // Field description:Ljava/lang/String;
       4: areturn
}
