Compiled from "ParallelFromPublisher.java"
public final class io.reactivex.rxjava3.internal.operators.parallel.ParallelFromPublisher<T> extends io.reactivex.rxjava3.parallel.ParallelFlowable<T> {
  final org.reactivestreams.Publisher<? extends T> source;

  final int parallelism;

  final int prefetch;

  public io.reactivex.rxjava3.internal.operators.parallel.ParallelFromPublisher(org.reactivestreams.Publisher<? extends T>, int, int);
    Code:
       0: aload_0
       1: invokespecial #1                  // Method io/reactivex/rxjava3/parallel/ParallelFlowable."<init>":()V
       4: aload_0
       5: aload_1
       6: putfield      #2                  // Field source:Lorg/reactivestreams/Publisher;
       9: aload_0
      10: iload_2
      11: putfield      #3                  // Field parallelism:I
      14: aload_0
      15: iload_3
      16: putfield      #4                  // Field prefetch:I
      19: return

  public int parallelism();
    Code:
       0: aload_0
       1: getfield      #3                  // Field parallelism:I
       4: ireturn

  public void subscribe(org.reactivestreams.Subscriber<? super T>[]);
    Code:
       0: aload_0
       1: aload_1
       2: invokestatic  #5                  // Method io/reactivex/rxjava3/plugins/RxJavaPlugins.onSubscribe:(Lio/reactivex/rxjava3/parallel/ParallelFlowable;[Lorg/reactivestreams/Subscriber;)[Lorg/reactivestreams/Subscriber;
       5: astore_1
       6: aload_0
       7: aload_1
       8: invokevirtual #6                  // Method validate:([Lorg/reactivestreams/Subscriber;)Z
      11: ifne          15
      14: return
      15: aload_0
      16: getfield      #2                  // Field source:Lorg/reactivestreams/Publisher;
      19: new           #7                  // class io/reactivex/rxjava3/internal/operators/parallel/ParallelFromPublisher$ParallelDispatcher
      22: dup
      23: aload_1
      24: aload_0
      25: getfield      #4                  // Field prefetch:I
      28: invokespecial #8                  // Method io/reactivex/rxjava3/internal/operators/parallel/ParallelFromPublisher$ParallelDispatcher."<init>":([Lorg/reactivestreams/Subscriber;I)V
      31: invokeinterface #9,  2            // InterfaceMethod org/reactivestreams/Publisher.subscribe:(Lorg/reactivestreams/Subscriber;)V
      36: return
}
