Compiled from "ParallelMapTry.java"
final class io.reactivex.rxjava3.internal.operators.parallel.ParallelMapTry$ParallelMapTrySubscriber<T, R> implements io.reactivex.rxjava3.operators.ConditionalSubscriber<T>, org.reactivestreams.Subscription {
  final org.reactivestreams.Subscriber<? super R> downstream;

  final io.reactivex.rxjava3.functions.Function<? super T, ? extends R> mapper;

  final io.reactivex.rxjava3.functions.BiFunction<? super java.lang.Long, ? super java.lang.Throwable, io.reactivex.rxjava3.parallel.ParallelFailureHandling> errorHandler;

  org.reactivestreams.Subscription upstream;

  boolean done;

  io.reactivex.rxjava3.internal.operators.parallel.ParallelMapTry$ParallelMapTrySubscriber(org.reactivestreams.Subscriber<? super R>, io.reactivex.rxjava3.functions.Function<? super T, ? extends R>, io.reactivex.rxjava3.functions.BiFunction<? super java.lang.Long, ? super java.lang.Throwable, io.reactivex.rxjava3.parallel.ParallelFailureHandling>);
    Code:
       0: aload_0
       1: invokespecial #1                  // Method java/lang/Object."<init>":()V
       4: aload_0
       5: aload_1
       6: putfield      #2                  // Field downstream:Lorg/reactivestreams/Subscriber;
       9: aload_0
      10: aload_2
      11: putfield      #3                  // Field mapper:Lio/reactivex/rxjava3/functions/Function;
      14: aload_0
      15: aload_3
      16: putfield      #4                  // Field errorHandler:Lio/reactivex/rxjava3/functions/BiFunction;
      19: return

  public void request(long);
    Code:
       0: aload_0
       1: getfield      #5                  // Field upstream:Lorg/reactivestreams/Subscription;
       4: lload_1
       5: invokeinterface #6,  3            // InterfaceMethod org/reactivestreams/Subscription.request:(J)V
      10: return

  public void cancel();
    Code:
       0: aload_0
       1: getfield      #5                  // Field upstream:Lorg/reactivestreams/Subscription;
       4: invokeinterface #7,  1            // InterfaceMethod org/reactivestreams/Subscription.cancel:()V
       9: return

  public void onSubscribe(org.reactivestreams.Subscription);
    Code:
       0: aload_0
       1: getfield      #5                  // Field upstream:Lorg/reactivestreams/Subscription;
       4: aload_1
       5: invokestatic  #8                  // Method io/reactivex/rxjava3/internal/subscriptions/SubscriptionHelper.validate:(Lorg/reactivestreams/Subscription;Lorg/reactivestreams/Subscription;)Z
       8: ifeq          26
      11: aload_0
      12: aload_1
      13: putfield      #5                  // Field upstream:Lorg/reactivestreams/Subscription;
      16: aload_0
      17: getfield      #2                  // Field downstream:Lorg/reactivestreams/Subscriber;
      20: aload_0
      21: invokeinterface #9,  2            // InterfaceMethod org/reactivestreams/Subscriber.onSubscribe:(Lorg/reactivestreams/Subscription;)V
      26: return

  public void onNext(T);
    Code:
       0: aload_0
       1: aload_1
       2: invokevirtual #10                 // Method tryOnNext:(Ljava/lang/Object;)Z
       5: ifne          25
       8: aload_0
       9: getfield      #11                 // Field done:Z
      12: ifne          25
      15: aload_0
      16: getfield      #5                  // Field upstream:Lorg/reactivestreams/Subscription;
      19: lconst_1
      20: invokeinterface #6,  3            // InterfaceMethod org/reactivestreams/Subscription.request:(J)V
      25: return

  public boolean tryOnNext(T);
    Code:
       0: aload_0
       1: getfield      #11                 // Field done:Z
       4: ifeq          9
       7: iconst_0
       8: ireturn
       9: lconst_0
      10: lstore_2
      11: aload_0
      12: getfield      #3                  // Field mapper:Lio/reactivex/rxjava3/functions/Function;
      15: aload_1
      16: invokeinterface #12,  2           // InterfaceMethod io/reactivex/rxjava3/functions/Function.apply:(Ljava/lang/Object;)Ljava/lang/Object;
      21: ldc           #13                 // String The mapper returned a null value
      23: invokestatic  #14                 // Method java/util/Objects.requireNonNull:(Ljava/lang/Object;Ljava/lang/String;)Ljava/lang/Object;
      26: astore        4
      28: goto          171
      31: astore        5
      33: aload         5
      35: invokestatic  #16                 // Method io/reactivex/rxjava3/exceptions/Exceptions.throwIfFatal:(Ljava/lang/Throwable;)V
      38: aload_0
      39: getfield      #4                  // Field errorHandler:Lio/reactivex/rxjava3/functions/BiFunction;
      42: lload_2
      43: lconst_1
      44: ladd
      45: dup2
      46: lstore_2
      47: invokestatic  #17                 // Method java/lang/Long.valueOf:(J)Ljava/lang/Long;
      50: aload         5
      52: invokeinterface #18,  3           // InterfaceMethod io/reactivex/rxjava3/functions/BiFunction.apply:(Ljava/lang/Object;Ljava/lang/Object;)Ljava/lang/Object;
      57: ldc           #19                 // String The errorHandler returned a null ParallelFailureHandling
      59: invokestatic  #14                 // Method java/util/Objects.requireNonNull:(Ljava/lang/Object;Ljava/lang/String;)Ljava/lang/Object;
      62: checkcast     #20                 // class io/reactivex/rxjava3/parallel/ParallelFailureHandling
      65: astore        6
      67: goto          108
      70: astore        7
      72: aload         7
      74: invokestatic  #16                 // Method io/reactivex/rxjava3/exceptions/Exceptions.throwIfFatal:(Ljava/lang/Throwable;)V
      77: aload_0
      78: invokevirtual #21                 // Method cancel:()V
      81: aload_0
      82: new           #22                 // class io/reactivex/rxjava3/exceptions/CompositeException
      85: dup
      86: iconst_2
      87: anewarray     #23                 // class java/lang/Throwable
      90: dup
      91: iconst_0
      92: aload         5
      94: aastore
      95: dup
      96: iconst_1
      97: aload         7
      99: aastore
     100: invokespecial #24                 // Method io/reactivex/rxjava3/exceptions/CompositeException."<init>":([Ljava/lang/Throwable;)V
     103: invokevirtual #25                 // Method onError:(Ljava/lang/Throwable;)V
     106: iconst_0
     107: ireturn
     108: getstatic     #26                 // Field io/reactivex/rxjava3/internal/operators/parallel/ParallelMapTry$1.$SwitchMap$io$reactivex$rxjava3$parallel$ParallelFailureHandling:[I
     111: aload         6
     113: invokevirtual #27                 // Method io/reactivex/rxjava3/parallel/ParallelFailureHandling.ordinal:()I
     116: iaload
     117: tableswitch   { // 1 to 3
                     1: 144
                     2: 147
                     3: 149
               default: 159
          }
     144: goto          11
     147: iconst_0
     148: ireturn
     149: aload_0
     150: invokevirtual #21                 // Method cancel:()V
     153: aload_0
     154: invokevirtual #28                 // Method onComplete:()V
     157: iconst_0
     158: ireturn
     159: aload_0
     160: invokevirtual #21                 // Method cancel:()V
     163: aload_0
     164: aload         5
     166: invokevirtual #25                 // Method onError:(Ljava/lang/Throwable;)V
     169: iconst_0
     170: ireturn
     171: aload_0
     172: getfield      #2                  // Field downstream:Lorg/reactivestreams/Subscriber;
     175: aload         4
     177: invokeinterface #29,  2           // InterfaceMethod org/reactivestreams/Subscriber.onNext:(Ljava/lang/Object;)V
     182: iconst_1
     183: ireturn
    Exception table:
       from    to  target type
          11    28    31   Class java/lang/Throwable
          38    67    70   Class java/lang/Throwable

  public void onError(java.lang.Throwable);
    Code:
       0: aload_0
       1: getfield      #11                 // Field done:Z
       4: ifeq          12
       7: aload_1
       8: invokestatic  #30                 // Method io/reactivex/rxjava3/plugins/RxJavaPlugins.onError:(Ljava/lang/Throwable;)V
      11: return
      12: aload_0
      13: iconst_1
      14: putfield      #11                 // Field done:Z
      17: aload_0
      18: getfield      #2                  // Field downstream:Lorg/reactivestreams/Subscriber;
      21: aload_1
      22: invokeinterface #31,  2           // InterfaceMethod org/reactivestreams/Subscriber.onError:(Ljava/lang/Throwable;)V
      27: return

  public void onComplete();
    Code:
       0: aload_0
       1: getfield      #11                 // Field done:Z
       4: ifeq          8
       7: return
       8: aload_0
       9: iconst_1
      10: putfield      #11                 // Field done:Z
      13: aload_0
      14: getfield      #2                  // Field downstream:Lorg/reactivestreams/Subscriber;
      17: invokeinterface #32,  1           // InterfaceMethod org/reactivestreams/Subscriber.onComplete:()V
      22: return
}
