Compiled from "ParallelRunOn.java"
final class io.reactivex.rxjava3.internal.operators.parallel.ParallelRunOn$MultiWorkerCallback implements io.reactivex.rxjava3.internal.schedulers.SchedulerMultiWorkerSupport$WorkerCallback {
  final org.reactivestreams.Subscriber<? super T>[] subscribers;

  final org.reactivestreams.Subscriber<T>[] parents;

  final io.reactivex.rxjava3.internal.operators.parallel.ParallelRunOn this$0;

  io.reactivex.rxjava3.internal.operators.parallel.ParallelRunOn$MultiWorkerCallback(org.reactivestreams.Subscriber<? super T>[], org.reactivestreams.Subscriber<T>[]);
    Code:
       0: aload_0
       1: aload_1
       2: putfield      #1                  // Field this$0:Lio/reactivex/rxjava3/internal/operators/parallel/ParallelRunOn;
       5: aload_0
       6: invokespecial #2                  // Method java/lang/Object."<init>":()V
       9: aload_0
      10: aload_2
      11: putfield      #3                  // Field subscribers:[Lorg/reactivestreams/Subscriber;
      14: aload_0
      15: aload_3
      16: putfield      #4                  // Field parents:[Lorg/reactivestreams/Subscriber;
      19: return

  public void onWorker(int, io.reactivex.rxjava3.core.Scheduler$Worker);
    Code:
       0: aload_0
       1: getfield      #1                  // Field this$0:Lio/reactivex/rxjava3/internal/operators/parallel/ParallelRunOn;
       4: iload_1
       5: aload_0
       6: getfield      #3                  // Field subscribers:[Lorg/reactivestreams/Subscriber;
       9: aload_0
      10: getfield      #4                  // Field parents:[Lorg/reactivestreams/Subscriber;
      13: aload_2
      14: invokevirtual #5                  // Method io/reactivex/rxjava3/internal/operators/parallel/ParallelRunOn.createSubscriber:(I[Lorg/reactivestreams/Subscriber;[Lorg/reactivestreams/Subscriber;Lio/reactivex/rxjava3/core/Scheduler$Worker;)V
      17: return
}
