Compiled from "ParallelSortedJoin.java"
final class io.reactivex.rxjava3.internal.operators.parallel.ParallelSortedJoin$SortedJoinSubscription<T> extends java.util.concurrent.atomic.AtomicInteger implements org.reactivestreams.Subscription {
  private static final long serialVersionUID;

  final org.reactivestreams.Subscriber<? super T> downstream;

  final io.reactivex.rxjava3.internal.operators.parallel.ParallelSortedJoin$SortedJoinInnerSubscriber<T>[] subscribers;

  final java.util.List<T>[] lists;

  final int[] indexes;

  final java.util.Comparator<? super T> comparator;

  final java.util.concurrent.atomic.AtomicLong requested;

  volatile boolean cancelled;

  final java.util.concurrent.atomic.AtomicInteger remaining;

  final java.util.concurrent.atomic.AtomicReference<java.lang.Throwable> error;

  io.reactivex.rxjava3.internal.operators.parallel.ParallelSortedJoin$SortedJoinSubscription(org.reactivestreams.Subscriber<? super T>, int, java.util.Comparator<? super T>);
    Code:
       0: aload_0
       1: invokespecial #1                  // Method java/util/concurrent/atomic/AtomicInteger."<init>":()V
       4: aload_0
       5: new           #2                  // class java/util/concurrent/atomic/AtomicLong
       8: dup
       9: invokespecial #3                  // Method java/util/concurrent/atomic/AtomicLong."<init>":()V
      12: putfield      #4                  // Field requested:Ljava/util/concurrent/atomic/AtomicLong;
      15: aload_0
      16: new           #5                  // class java/util/concurrent/atomic/AtomicInteger
      19: dup
      20: invokespecial #1                  // Method java/util/concurrent/atomic/AtomicInteger."<init>":()V
      23: putfield      #6                  // Field remaining:Ljava/util/concurrent/atomic/AtomicInteger;
      26: aload_0
      27: new           #7                  // class java/util/concurrent/atomic/AtomicReference
      30: dup
      31: invokespecial #8                  // Method java/util/concurrent/atomic/AtomicReference."<init>":()V
      34: putfield      #9                  // Field error:Ljava/util/concurrent/atomic/AtomicReference;
      37: aload_0
      38: aload_1
      39: putfield      #10                 // Field downstream:Lorg/reactivestreams/Subscriber;
      42: aload_0
      43: aload_3
      44: putfield      #11                 // Field comparator:Ljava/util/Comparator;
      47: iload_2
      48: anewarray     #12                 // class io/reactivex/rxjava3/internal/operators/parallel/ParallelSortedJoin$SortedJoinInnerSubscriber
      51: astore        4
      53: iconst_0
      54: istore        5
      56: iload         5
      58: iload_2
      59: if_icmpge     83
      62: aload         4
      64: iload         5
      66: new           #12                 // class io/reactivex/rxjava3/internal/operators/parallel/ParallelSortedJoin$SortedJoinInnerSubscriber
      69: dup
      70: aload_0
      71: iload         5
      73: invokespecial #13                 // Method io/reactivex/rxjava3/internal/operators/parallel/ParallelSortedJoin$SortedJoinInnerSubscriber."<init>":(Lio/reactivex/rxjava3/internal/operators/parallel/ParallelSortedJoin$SortedJoinSubscription;I)V
      76: aastore
      77: iinc          5, 1
      80: goto          56
      83: aload_0
      84: aload         4
      86: putfield      #14                 // Field subscribers:[Lio/reactivex/rxjava3/internal/operators/parallel/ParallelSortedJoin$SortedJoinInnerSubscriber;
      89: aload_0
      90: iload_2
      91: anewarray     #15                 // class java/util/List
      94: putfield      #16                 // Field lists:[Ljava/util/List;
      97: aload_0
      98: iload_2
      99: newarray       int
     101: putfield      #17                 // Field indexes:[I
     104: aload_0
     105: getfield      #6                  // Field remaining:Ljava/util/concurrent/atomic/AtomicInteger;
     108: iload_2
     109: invokevirtual #18                 // Method java/util/concurrent/atomic/AtomicInteger.lazySet:(I)V
     112: return

  public void request(long);
    Code:
       0: lload_1
       1: invokestatic  #19                 // Method io/reactivex/rxjava3/internal/subscriptions/SubscriptionHelper.validate:(J)Z
       4: ifeq          30
       7: aload_0
       8: getfield      #4                  // Field requested:Ljava/util/concurrent/atomic/AtomicLong;
      11: lload_1
      12: invokestatic  #20                 // Method io/reactivex/rxjava3/internal/util/BackpressureHelper.add:(Ljava/util/concurrent/atomic/AtomicLong;J)J
      15: pop2
      16: aload_0
      17: getfield      #6                  // Field remaining:Ljava/util/concurrent/atomic/AtomicInteger;
      20: invokevirtual #21                 // Method java/util/concurrent/atomic/AtomicInteger.get:()I
      23: ifne          30
      26: aload_0
      27: invokevirtual #22                 // Method drain:()V
      30: return

  public void cancel();
    Code:
       0: aload_0
       1: getfield      #23                 // Field cancelled:Z
       4: ifne          31
       7: aload_0
       8: iconst_1
       9: putfield      #23                 // Field cancelled:Z
      12: aload_0
      13: invokevirtual #24                 // Method cancelAll:()V
      16: aload_0
      17: invokevirtual #25                 // Method getAndIncrement:()I
      20: ifne          31
      23: aload_0
      24: getfield      #16                 // Field lists:[Ljava/util/List;
      27: aconst_null
      28: invokestatic  #26                 // Method java/util/Arrays.fill:([Ljava/lang/Object;Ljava/lang/Object;)V
      31: return

  void cancelAll();
    Code:
       0: aload_0
       1: getfield      #14                 // Field subscribers:[Lio/reactivex/rxjava3/internal/operators/parallel/ParallelSortedJoin$SortedJoinInnerSubscriber;
       4: astore_1
       5: aload_1
       6: arraylength
       7: istore_2
       8: iconst_0
       9: istore_3
      10: iload_3
      11: iload_2
      12: if_icmpge     31
      15: aload_1
      16: iload_3
      17: aaload
      18: astore        4
      20: aload         4
      22: invokevirtual #27                 // Method io/reactivex/rxjava3/internal/operators/parallel/ParallelSortedJoin$SortedJoinInnerSubscriber.cancel:()V
      25: iinc          3, 1
      28: goto          10
      31: return

  void innerNext(java.util.List<T>, int);
    Code:
       0: aload_0
       1: getfield      #16                 // Field lists:[Ljava/util/List;
       4: iload_2
       5: aload_1
       6: aastore
       7: aload_0
       8: getfield      #6                  // Field remaining:Ljava/util/concurrent/atomic/AtomicInteger;
      11: invokevirtual #28                 // Method java/util/concurrent/atomic/AtomicInteger.decrementAndGet:()I
      14: ifne          21
      17: aload_0
      18: invokevirtual #22                 // Method drain:()V
      21: return

  void innerError(java.lang.Throwable);
    Code:
       0: aload_0
       1: getfield      #9                  // Field error:Ljava/util/concurrent/atomic/AtomicReference;
       4: aconst_null
       5: aload_1
       6: invokevirtual #29                 // Method java/util/concurrent/atomic/AtomicReference.compareAndSet:(Ljava/lang/Object;Ljava/lang/Object;)Z
       9: ifeq          19
      12: aload_0
      13: invokevirtual #22                 // Method drain:()V
      16: goto          34
      19: aload_1
      20: aload_0
      21: getfield      #9                  // Field error:Ljava/util/concurrent/atomic/AtomicReference;
      24: invokevirtual #30                 // Method java/util/concurrent/atomic/AtomicReference.get:()Ljava/lang/Object;
      27: if_acmpeq     34
      30: aload_1
      31: invokestatic  #31                 // Method io/reactivex/rxjava3/plugins/RxJavaPlugins.onError:(Ljava/lang/Throwable;)V
      34: return

  void drain();
    Code:
       0: aload_0
       1: invokevirtual #25                 // Method getAndIncrement:()I
       4: ifeq          8
       7: return
       8: iconst_1
       9: istore_1
      10: aload_0
      11: getfield      #10                 // Field downstream:Lorg/reactivestreams/Subscriber;
      14: astore_2
      15: aload_0
      16: getfield      #16                 // Field lists:[Ljava/util/List;
      19: astore_3
      20: aload_0
      21: getfield      #17                 // Field indexes:[I
      24: astore        4
      26: aload         4
      28: arraylength
      29: istore        5
      31: aload_0
      32: getfield      #4                  // Field requested:Ljava/util/concurrent/atomic/AtomicLong;
      35: invokevirtual #32                 // Method java/util/concurrent/atomic/AtomicLong.get:()J
      38: lstore        6
      40: lconst_0
      41: lstore        8
      43: lload         8
      45: lload         6
      47: lcmp
      48: ifeq          313
      51: aload_0
      52: getfield      #23                 // Field cancelled:Z
      55: ifeq          64
      58: aload_3
      59: aconst_null
      60: invokestatic  #26                 // Method java/util/Arrays.fill:([Ljava/lang/Object;Ljava/lang/Object;)V
      63: return
      64: aload_0
      65: getfield      #9                  // Field error:Ljava/util/concurrent/atomic/AtomicReference;
      68: invokevirtual #30                 // Method java/util/concurrent/atomic/AtomicReference.get:()Ljava/lang/Object;
      71: checkcast     #33                 // class java/lang/Throwable
      74: astore        10
      76: aload         10
      78: ifnull        99
      81: aload_0
      82: invokevirtual #24                 // Method cancelAll:()V
      85: aload_3
      86: aconst_null
      87: invokestatic  #26                 // Method java/util/Arrays.fill:([Ljava/lang/Object;Ljava/lang/Object;)V
      90: aload_2
      91: aload         10
      93: invokeinterface #34,  2           // InterfaceMethod org/reactivestreams/Subscriber.onError:(Ljava/lang/Throwable;)V
      98: return
      99: aconst_null
     100: astore        11
     102: iconst_m1
     103: istore        12
     105: iconst_0
     106: istore        13
     108: iload         13
     110: iload         5
     112: if_icmpge     270
     115: aload_3
     116: iload         13
     118: aaload
     119: astore        14
     121: aload         4
     123: iload         13
     125: iaload
     126: istore        15
     128: aload         14
     130: invokeinterface #35,  1           // InterfaceMethod java/util/List.size:()I
     135: iload         15
     137: if_icmpeq     264
     140: aload         11
     142: ifnonnull     163
     145: aload         14
     147: iload         15
     149: invokeinterface #36,  2           // InterfaceMethod java/util/List.get:(I)Ljava/lang/Object;
     154: astore        11
     156: iload         13
     158: istore        12
     160: goto          264
     163: aload         14
     165: iload         15
     167: invokeinterface #36,  2           // InterfaceMethod java/util/List.get:(I)Ljava/lang/Object;
     172: astore        16
     174: aload_0
     175: getfield      #11                 // Field comparator:Ljava/util/Comparator;
     178: aload         11
     180: aload         16
     182: invokeinterface #37,  3           // InterfaceMethod java/util/Comparator.compare:(Ljava/lang/Object;Ljava/lang/Object;)I
     187: ifle          194
     190: iconst_1
     191: goto          195
     194: iconst_0
     195: istore        17
     197: goto          251
     200: astore        18
     202: aload         18
     204: invokestatic  #38                 // Method io/reactivex/rxjava3/exceptions/Exceptions.throwIfFatal:(Ljava/lang/Throwable;)V
     207: aload_0
     208: invokevirtual #24                 // Method cancelAll:()V
     211: aload_3
     212: aconst_null
     213: invokestatic  #26                 // Method java/util/Arrays.fill:([Ljava/lang/Object;Ljava/lang/Object;)V
     216: aload_0
     217: getfield      #9                  // Field error:Ljava/util/concurrent/atomic/AtomicReference;
     220: aconst_null
     221: aload         18
     223: invokevirtual #29                 // Method java/util/concurrent/atomic/AtomicReference.compareAndSet:(Ljava/lang/Object;Ljava/lang/Object;)Z
     226: ifne          234
     229: aload         18
     231: invokestatic  #31                 // Method io/reactivex/rxjava3/plugins/RxJavaPlugins.onError:(Ljava/lang/Throwable;)V
     234: aload_2
     235: aload_0
     236: getfield      #9                  // Field error:Ljava/util/concurrent/atomic/AtomicReference;
     239: invokevirtual #30                 // Method java/util/concurrent/atomic/AtomicReference.get:()Ljava/lang/Object;
     242: checkcast     #33                 // class java/lang/Throwable
     245: invokeinterface #34,  2           // InterfaceMethod org/reactivestreams/Subscriber.onError:(Ljava/lang/Throwable;)V
     250: return
     251: iload         17
     253: ifeq          264
     256: aload         16
     258: astore        11
     260: iload         13
     262: istore        12
     264: iinc          13, 1
     267: goto          108
     270: aload         11
     272: ifnonnull     287
     275: aload_3
     276: aconst_null
     277: invokestatic  #26                 // Method java/util/Arrays.fill:([Ljava/lang/Object;Ljava/lang/Object;)V
     280: aload_2
     281: invokeinterface #39,  1           // InterfaceMethod org/reactivestreams/Subscriber.onComplete:()V
     286: return
     287: aload_2
     288: aload         11
     290: invokeinterface #40,  2           // InterfaceMethod org/reactivestreams/Subscriber.onNext:(Ljava/lang/Object;)V
     295: aload         4
     297: iload         12
     299: dup2
     300: iaload
     301: iconst_1
     302: iadd
     303: iastore
     304: lload         8
     306: lconst_1
     307: ladd
     308: lstore        8
     310: goto          43
     313: aload_0
     314: getfield      #23                 // Field cancelled:Z
     317: ifeq          326
     320: aload_3
     321: aconst_null
     322: invokestatic  #26                 // Method java/util/Arrays.fill:([Ljava/lang/Object;Ljava/lang/Object;)V
     325: return
     326: aload_0
     327: getfield      #9                  // Field error:Ljava/util/concurrent/atomic/AtomicReference;
     330: invokevirtual #30                 // Method java/util/concurrent/atomic/AtomicReference.get:()Ljava/lang/Object;
     333: checkcast     #33                 // class java/lang/Throwable
     336: astore        10
     338: aload         10
     340: ifnull        361
     343: aload_0
     344: invokevirtual #24                 // Method cancelAll:()V
     347: aload_3
     348: aconst_null
     349: invokestatic  #26                 // Method java/util/Arrays.fill:([Ljava/lang/Object;Ljava/lang/Object;)V
     352: aload_2
     353: aload         10
     355: invokeinterface #34,  2           // InterfaceMethod org/reactivestreams/Subscriber.onError:(Ljava/lang/Throwable;)V
     360: return
     361: iconst_1
     362: istore        11
     364: iconst_0
     365: istore        12
     367: iload         12
     369: iload         5
     371: if_icmpge     403
     374: aload         4
     376: iload         12
     378: iaload
     379: aload_3
     380: iload         12
     382: aaload
     383: invokeinterface #35,  1           // InterfaceMethod java/util/List.size:()I
     388: if_icmpeq     397
     391: iconst_0
     392: istore        11
     394: goto          403
     397: iinc          12, 1
     400: goto          367
     403: iload         11
     405: ifeq          420
     408: aload_3
     409: aconst_null
     410: invokestatic  #26                 // Method java/util/Arrays.fill:([Ljava/lang/Object;Ljava/lang/Object;)V
     413: aload_2
     414: invokeinterface #39,  1           // InterfaceMethod org/reactivestreams/Subscriber.onComplete:()V
     419: return
     420: lload         8
     422: lconst_0
     423: lcmp
     424: ifeq          437
     427: aload_0
     428: getfield      #4                  // Field requested:Ljava/util/concurrent/atomic/AtomicLong;
     431: lload         8
     433: invokestatic  #41                 // Method io/reactivex/rxjava3/internal/util/BackpressureHelper.produced:(Ljava/util/concurrent/atomic/AtomicLong;J)J
     436: pop2
     437: aload_0
     438: iload_1
     439: ineg
     440: invokevirtual #42                 // Method addAndGet:(I)I
     443: istore_1
     444: iload_1
     445: ifne          451
     448: goto          454
     451: goto          31
     454: return
    Exception table:
       from    to  target type
         174   197   200   Class java/lang/Throwable
}
