Compiled from "ParallelJoin.java"
final class io.reactivex.rxjava3.internal.operators.parallel.ParallelJoin$JoinSubscription<T> extends io.reactivex.rxjava3.internal.operators.parallel.ParallelJoin$JoinSubscriptionBase<T> {
  private static final long serialVersionUID;

  io.reactivex.rxjava3.internal.operators.parallel.ParallelJoin$JoinSubscription(org.reactivestreams.Subscriber<? super T>, int, int);
    Code:
       0: aload_0
       1: aload_1
       2: iload_2
       3: iload_3
       4: invokespecial #1                  // Method io/reactivex/rxjava3/internal/operators/parallel/ParallelJoin$JoinSubscriptionBase."<init>":(Lorg/reactivestreams/Subscriber;II)V
       7: return

  public void onNext(io.reactivex.rxjava3.internal.operators.parallel.ParallelJoin$JoinInnerSubscriber<T>, T);
    Code:
       0: aload_0
       1: invokevirtual #2                  // Method get:()I
       4: ifne          137
       7: aload_0
       8: iconst_0
       9: iconst_1
      10: invokevirtual #3                  // Method compareAndSet:(II)Z
      13: ifeq          137
      16: aload_0
      17: getfield      #4                  // Field requested:Ljava/util/concurrent/atomic/AtomicLong;
      20: invokevirtual #5                  // Method java/util/concurrent/atomic/AtomicLong.get:()J
      23: lconst_0
      24: lcmp
      25: ifeq          68
      28: aload_0
      29: getfield      #6                  // Field downstream:Lorg/reactivestreams/Subscriber;
      32: aload_2
      33: invokeinterface #7,  2            // InterfaceMethod org/reactivestreams/Subscriber.onNext:(Ljava/lang/Object;)V
      38: aload_0
      39: getfield      #4                  // Field requested:Ljava/util/concurrent/atomic/AtomicLong;
      42: invokevirtual #5                  // Method java/util/concurrent/atomic/AtomicLong.get:()J
      45: ldc2_w        #9                  // long 9223372036854775807l
      48: lcmp
      49: ifeq          60
      52: aload_0
      53: getfield      #4                  // Field requested:Ljava/util/concurrent/atomic/AtomicLong;
      56: invokevirtual #11                 // Method java/util/concurrent/atomic/AtomicLong.decrementAndGet:()J
      59: pop2
      60: aload_1
      61: lconst_1
      62: invokevirtual #12                 // Method io/reactivex/rxjava3/internal/operators/parallel/ParallelJoin$JoinInnerSubscriber.request:(J)V
      65: goto          129
      68: aload_1
      69: invokevirtual #13                 // Method io/reactivex/rxjava3/internal/operators/parallel/ParallelJoin$JoinInnerSubscriber.getQueue:()Lio/reactivex/rxjava3/operators/SimplePlainQueue;
      72: astore_3
      73: aload_3
      74: aload_2
      75: invokeinterface #14,  2           // InterfaceMethod io/reactivex/rxjava3/operators/SimplePlainQueue.offer:(Ljava/lang/Object;)Z
      80: ifne          129
      83: aload_0
      84: invokevirtual #15                 // Method cancelAll:()V
      87: new           #16                 // class io/reactivex/rxjava3/exceptions/QueueOverflowException
      90: dup
      91: invokespecial #17                 // Method io/reactivex/rxjava3/exceptions/QueueOverflowException."<init>":()V
      94: astore        4
      96: aload_0
      97: getfield      #18                 // Field errors:Lio/reactivex/rxjava3/internal/util/AtomicThrowable;
     100: aconst_null
     101: aload         4
     103: invokevirtual #19                 // Method io/reactivex/rxjava3/internal/util/AtomicThrowable.compareAndSet:(Ljava/lang/Object;Ljava/lang/Object;)Z
     106: ifeq          123
     109: aload_0
     110: getfield      #6                  // Field downstream:Lorg/reactivestreams/Subscriber;
     113: aload         4
     115: invokeinterface #20,  2           // InterfaceMethod org/reactivestreams/Subscriber.onError:(Ljava/lang/Throwable;)V
     120: goto          128
     123: aload         4
     125: invokestatic  #21                 // Method io/reactivex/rxjava3/plugins/RxJavaPlugins.onError:(Ljava/lang/Throwable;)V
     128: return
     129: aload_0
     130: invokevirtual #22                 // Method decrementAndGet:()I
     133: ifne          176
     136: return
     137: aload_1
     138: invokevirtual #13                 // Method io/reactivex/rxjava3/internal/operators/parallel/ParallelJoin$JoinInnerSubscriber.getQueue:()Lio/reactivex/rxjava3/operators/SimplePlainQueue;
     141: astore_3
     142: aload_3
     143: aload_2
     144: invokeinterface #14,  2           // InterfaceMethod io/reactivex/rxjava3/operators/SimplePlainQueue.offer:(Ljava/lang/Object;)Z
     149: ifne          168
     152: aload_0
     153: invokevirtual #15                 // Method cancelAll:()V
     156: aload_0
     157: new           #16                 // class io/reactivex/rxjava3/exceptions/QueueOverflowException
     160: dup
     161: invokespecial #17                 // Method io/reactivex/rxjava3/exceptions/QueueOverflowException."<init>":()V
     164: invokevirtual #23                 // Method onError:(Ljava/lang/Throwable;)V
     167: return
     168: aload_0
     169: invokevirtual #24                 // Method getAndIncrement:()I
     172: ifeq          176
     175: return
     176: aload_0
     177: invokevirtual #25                 // Method drainLoop:()V
     180: return

  public void onError(java.lang.Throwable);
    Code:
       0: aload_0
       1: getfield      #18                 // Field errors:Lio/reactivex/rxjava3/internal/util/AtomicThrowable;
       4: aconst_null
       5: aload_1
       6: invokevirtual #19                 // Method io/reactivex/rxjava3/internal/util/AtomicThrowable.compareAndSet:(Ljava/lang/Object;Ljava/lang/Object;)Z
       9: ifeq          23
      12: aload_0
      13: invokevirtual #15                 // Method cancelAll:()V
      16: aload_0
      17: invokevirtual #26                 // Method drain:()V
      20: goto          38
      23: aload_1
      24: aload_0
      25: getfield      #18                 // Field errors:Lio/reactivex/rxjava3/internal/util/AtomicThrowable;
      28: invokevirtual #27                 // Method io/reactivex/rxjava3/internal/util/AtomicThrowable.get:()Ljava/lang/Object;
      31: if_acmpeq     38
      34: aload_1
      35: invokestatic  #21                 // Method io/reactivex/rxjava3/plugins/RxJavaPlugins.onError:(Ljava/lang/Throwable;)V
      38: return

  public void onComplete();
    Code:
       0: aload_0
       1: getfield      #28                 // Field done:Ljava/util/concurrent/atomic/AtomicInteger;
       4: invokevirtual #29                 // Method java/util/concurrent/atomic/AtomicInteger.decrementAndGet:()I
       7: pop
       8: aload_0
       9: invokevirtual #26                 // Method drain:()V
      12: return

  void drain();
    Code:
       0: aload_0
       1: invokevirtual #24                 // Method getAndIncrement:()I
       4: ifeq          8
       7: return
       8: aload_0
       9: invokevirtual #25                 // Method drainLoop:()V
      12: return

  void drainLoop();
    Code:
       0: iconst_1
       1: istore_1
       2: aload_0
       3: getfield      #30                 // Field subscribers:[Lio/reactivex/rxjava3/internal/operators/parallel/ParallelJoin$JoinInnerSubscriber;
       6: astore_2
       7: aload_2
       8: arraylength
       9: istore_3
      10: aload_0
      11: getfield      #6                  // Field downstream:Lorg/reactivestreams/Subscriber;
      14: astore        4
      16: aload_0
      17: getfield      #4                  // Field requested:Ljava/util/concurrent/atomic/AtomicLong;
      20: invokevirtual #5                  // Method java/util/concurrent/atomic/AtomicLong.get:()J
      23: lstore        5
      25: lconst_0
      26: lstore        7
      28: lload         7
      30: lload         5
      32: lcmp
      33: ifeq          209
      36: aload_0
      37: getfield      #31                 // Field cancelled:Z
      40: ifeq          48
      43: aload_0
      44: invokevirtual #32                 // Method cleanup:()V
      47: return
      48: aload_0
      49: getfield      #18                 // Field errors:Lio/reactivex/rxjava3/internal/util/AtomicThrowable;
      52: invokevirtual #27                 // Method io/reactivex/rxjava3/internal/util/AtomicThrowable.get:()Ljava/lang/Object;
      55: checkcast     #33                 // class java/lang/Throwable
      58: astore        9
      60: aload         9
      62: ifnull        79
      65: aload_0
      66: invokevirtual #32                 // Method cleanup:()V
      69: aload         4
      71: aload         9
      73: invokeinterface #20,  2           // InterfaceMethod org/reactivestreams/Subscriber.onError:(Ljava/lang/Throwable;)V
      78: return
      79: aload_0
      80: getfield      #28                 // Field done:Ljava/util/concurrent/atomic/AtomicInteger;
      83: invokevirtual #34                 // Method java/util/concurrent/atomic/AtomicInteger.get:()I
      86: ifne          93
      89: iconst_1
      90: goto          94
      93: iconst_0
      94: istore        10
      96: iconst_1
      97: istore        11
      99: iconst_0
     100: istore        12
     102: iload         12
     104: aload_2
     105: arraylength
     106: if_icmpge     180
     109: aload_2
     110: iload         12
     112: aaload
     113: astore        13
     115: aload         13
     117: getfield      #35                 // Field io/reactivex/rxjava3/internal/operators/parallel/ParallelJoin$JoinInnerSubscriber.queue:Lio/reactivex/rxjava3/operators/SimplePlainQueue;
     120: astore        14
     122: aload         14
     124: ifnull        174
     127: aload         14
     129: invokeinterface #36,  1           // InterfaceMethod io/reactivex/rxjava3/operators/SimplePlainQueue.poll:()Ljava/lang/Object;
     134: astore        15
     136: aload         15
     138: ifnull        174
     141: iconst_0
     142: istore        11
     144: aload         4
     146: aload         15
     148: invokeinterface #7,  2            // InterfaceMethod org/reactivestreams/Subscriber.onNext:(Ljava/lang/Object;)V
     153: aload         13
     155: invokevirtual #37                 // Method io/reactivex/rxjava3/internal/operators/parallel/ParallelJoin$JoinInnerSubscriber.requestOne:()V
     158: lload         7
     160: lconst_1
     161: ladd
     162: dup2
     163: lstore        7
     165: lload         5
     167: lcmp
     168: ifne          174
     171: goto          209
     174: iinc          12, 1
     177: goto          102
     180: iload         10
     182: ifeq          198
     185: iload         11
     187: ifeq          198
     190: aload         4
     192: invokeinterface #38,  1           // InterfaceMethod org/reactivestreams/Subscriber.onComplete:()V
     197: return
     198: iload         11
     200: ifeq          206
     203: goto          209
     206: goto          28
     209: lload         7
     211: lload         5
     213: lcmp
     214: ifne          347
     217: aload_0
     218: getfield      #31                 // Field cancelled:Z
     221: ifeq          229
     224: aload_0
     225: invokevirtual #32                 // Method cleanup:()V
     228: return
     229: aload_0
     230: getfield      #18                 // Field errors:Lio/reactivex/rxjava3/internal/util/AtomicThrowable;
     233: invokevirtual #27                 // Method io/reactivex/rxjava3/internal/util/AtomicThrowable.get:()Ljava/lang/Object;
     236: checkcast     #33                 // class java/lang/Throwable
     239: astore        9
     241: aload         9
     243: ifnull        260
     246: aload_0
     247: invokevirtual #32                 // Method cleanup:()V
     250: aload         4
     252: aload         9
     254: invokeinterface #20,  2           // InterfaceMethod org/reactivestreams/Subscriber.onError:(Ljava/lang/Throwable;)V
     259: return
     260: aload_0
     261: getfield      #28                 // Field done:Ljava/util/concurrent/atomic/AtomicInteger;
     264: invokevirtual #34                 // Method java/util/concurrent/atomic/AtomicInteger.get:()I
     267: ifne          274
     270: iconst_1
     271: goto          275
     274: iconst_0
     275: istore        10
     277: iconst_1
     278: istore        11
     280: iconst_0
     281: istore        12
     283: iload         12
     285: iload_3
     286: if_icmpge     329
     289: aload_2
     290: iload         12
     292: aaload
     293: astore        13
     295: aload         13
     297: getfield      #35                 // Field io/reactivex/rxjava3/internal/operators/parallel/ParallelJoin$JoinInnerSubscriber.queue:Lio/reactivex/rxjava3/operators/SimplePlainQueue;
     300: astore        14
     302: aload         14
     304: ifnull        323
     307: aload         14
     309: invokeinterface #39,  1           // InterfaceMethod io/reactivex/rxjava3/operators/SimpleQueue.isEmpty:()Z
     314: ifne          323
     317: iconst_0
     318: istore        11
     320: goto          329
     323: iinc          12, 1
     326: goto          283
     329: iload         10
     331: ifeq          347
     334: iload         11
     336: ifeq          347
     339: aload         4
     341: invokeinterface #38,  1           // InterfaceMethod org/reactivestreams/Subscriber.onComplete:()V
     346: return
     347: lload         7
     349: lconst_0
     350: lcmp
     351: ifeq          364
     354: aload_0
     355: getfield      #4                  // Field requested:Ljava/util/concurrent/atomic/AtomicLong;
     358: lload         7
     360: invokestatic  #40                 // Method io/reactivex/rxjava3/internal/util/BackpressureHelper.produced:(Ljava/util/concurrent/atomic/AtomicLong;J)J
     363: pop2
     364: aload_0
     365: iload_1
     366: ineg
     367: invokevirtual #41                 // Method addAndGet:(I)I
     370: istore_1
     371: iload_1
     372: ifne          378
     375: goto          381
     378: goto          16
     381: return
}
