Compiled from "ParallelReduceFull.java"
final class io.reactivex.rxjava3.internal.operators.parallel.ParallelReduceFull$ParallelReduceFullInnerSubscriber<T> extends java.util.concurrent.atomic.AtomicReference<org.reactivestreams.Subscription> implements io.reactivex.rxjava3.core.FlowableSubscriber<T> {
  private static final long serialVersionUID;

  final io.reactivex.rxjava3.internal.operators.parallel.ParallelReduceFull$ParallelReduceFullMainSubscriber<T> parent;

  final io.reactivex.rxjava3.functions.BiFunction<T, T, T> reducer;

  T value;

  boolean done;

  io.reactivex.rxjava3.internal.operators.parallel.ParallelReduceFull$ParallelReduceFullInnerSubscriber(io.reactivex.rxjava3.internal.operators.parallel.ParallelReduceFull$ParallelReduceFullMainSubscriber<T>, io.reactivex.rxjava3.functions.BiFunction<T, T, T>);
    Code:
       0: aload_0
       1: invokespecial #1                  // Method java/util/concurrent/atomic/AtomicReference."<init>":()V
       4: aload_0
       5: aload_1
       6: putfield      #2                  // Field parent:Lio/reactivex/rxjava3/internal/operators/parallel/ParallelReduceFull$ParallelReduceFullMainSubscriber;
       9: aload_0
      10: aload_2
      11: putfield      #3                  // Field reducer:Lio/reactivex/rxjava3/functions/BiFunction;
      14: return

  public void onSubscribe(org.reactivestreams.Subscription);
    Code:
       0: aload_0
       1: aload_1
       2: ldc2_w        #5                  // long 9223372036854775807l
       5: invokestatic  #7                  // Method io/reactivex/rxjava3/internal/subscriptions/SubscriptionHelper.setOnce:(Ljava/util/concurrent/atomic/AtomicReference;Lorg/reactivestreams/Subscription;J)Z
       8: pop
       9: return

  public void onNext(T);
    Code:
       0: aload_0
       1: getfield      #8                  // Field done:Z
       4: ifne          72
       7: aload_0
       8: getfield      #9                  // Field value:Ljava/lang/Object;
      11: astore_2
      12: aload_2
      13: ifnonnull     24
      16: aload_0
      17: aload_1
      18: putfield      #9                  // Field value:Ljava/lang/Object;
      21: goto          72
      24: aload_0
      25: getfield      #3                  // Field reducer:Lio/reactivex/rxjava3/functions/BiFunction;
      28: aload_2
      29: aload_1
      30: invokeinterface #10,  3           // InterfaceMethod io/reactivex/rxjava3/functions/BiFunction.apply:(Ljava/lang/Object;Ljava/lang/Object;)Ljava/lang/Object;
      35: ldc           #11                 // String The reducer returned a null value
      37: invokestatic  #12                 // Method java/util/Objects.requireNonNull:(Ljava/lang/Object;Ljava/lang/String;)Ljava/lang/Object;
      40: astore_2
      41: goto          67
      44: astore_3
      45: aload_3
      46: invokestatic  #14                 // Method io/reactivex/rxjava3/exceptions/Exceptions.throwIfFatal:(Ljava/lang/Throwable;)V
      49: aload_0
      50: invokevirtual #15                 // Method get:()Ljava/lang/Object;
      53: checkcast     #16                 // class org/reactivestreams/Subscription
      56: invokeinterface #17,  1           // InterfaceMethod org/reactivestreams/Subscription.cancel:()V
      61: aload_0
      62: aload_3
      63: invokevirtual #18                 // Method onError:(Ljava/lang/Throwable;)V
      66: return
      67: aload_0
      68: aload_2
      69: putfield      #9                  // Field value:Ljava/lang/Object;
      72: return
    Exception table:
       from    to  target type
          24    41    44   Class java/lang/Throwable

  public void onError(java.lang.Throwable);
    Code:
       0: aload_0
       1: getfield      #8                  // Field done:Z
       4: ifeq          12
       7: aload_1
       8: invokestatic  #19                 // Method io/reactivex/rxjava3/plugins/RxJavaPlugins.onError:(Ljava/lang/Throwable;)V
      11: return
      12: aload_0
      13: iconst_1
      14: putfield      #8                  // Field done:Z
      17: aload_0
      18: getfield      #2                  // Field parent:Lio/reactivex/rxjava3/internal/operators/parallel/ParallelReduceFull$ParallelReduceFullMainSubscriber;
      21: aload_1
      22: invokevirtual #20                 // Method io/reactivex/rxjava3/internal/operators/parallel/ParallelReduceFull$ParallelReduceFullMainSubscriber.innerError:(Ljava/lang/Throwable;)V
      25: return

  public void onComplete();
    Code:
       0: aload_0
       1: getfield      #8                  // Field done:Z
       4: ifne          23
       7: aload_0
       8: iconst_1
       9: putfield      #8                  // Field done:Z
      12: aload_0
      13: getfield      #2                  // Field parent:Lio/reactivex/rxjava3/internal/operators/parallel/ParallelReduceFull$ParallelReduceFullMainSubscriber;
      16: aload_0
      17: getfield      #9                  // Field value:Ljava/lang/Object;
      20: invokevirtual #21                 // Method io/reactivex/rxjava3/internal/operators/parallel/ParallelReduceFull$ParallelReduceFullMainSubscriber.innerComplete:(Ljava/lang/Object;)V
      23: return

  void cancel();
    Code:
       0: aload_0
       1: invokestatic  #22                 // Method io/reactivex/rxjava3/internal/subscriptions/SubscriptionHelper.cancel:(Ljava/util/concurrent/atomic/AtomicReference;)Z
       4: pop
       5: return
}
