Compiled from "ParallelConcatMap.java"
public final class io.reactivex.rxjava3.internal.operators.parallel.ParallelConcatMap<T, R> extends io.reactivex.rxjava3.parallel.ParallelFlowable<R> {
  final io.reactivex.rxjava3.parallel.ParallelFlowable<T> source;

  final io.reactivex.rxjava3.functions.Function<? super T, ? extends org.reactivestreams.Publisher<? extends R>> mapper;

  final int prefetch;

  final io.reactivex.rxjava3.internal.util.ErrorMode errorMode;

  public io.reactivex.rxjava3.internal.operators.parallel.ParallelConcatMap(io.reactivex.rxjava3.parallel.ParallelFlowable<T>, io.reactivex.rxjava3.functions.Function<? super T, ? extends org.reactivestreams.Publisher<? extends R>>, int, io.reactivex.rxjava3.internal.util.ErrorMode);
    Code:
       0: aload_0
       1: invokespecial #1                  // Method io/reactivex/rxjava3/parallel/ParallelFlowable."<init>":()V
       4: aload_0
       5: aload_1
       6: putfield      #2                  // Field source:Lio/reactivex/rxjava3/parallel/ParallelFlowable;
       9: aload_0
      10: aload_2
      11: ldc           #3                  // String mapper
      13: invokestatic  #4                  // Method java/util/Objects.requireNonNull:(Ljava/lang/Object;Ljava/lang/String;)Ljava/lang/Object;
      16: checkcast     #5                  // class io/reactivex/rxjava3/functions/Function
      19: putfield      #6                  // Field mapper:Lio/reactivex/rxjava3/functions/Function;
      22: aload_0
      23: iload_3
      24: putfield      #7                  // Field prefetch:I
      27: aload_0
      28: aload         4
      30: ldc           #8                  // String errorMode
      32: invokestatic  #4                  // Method java/util/Objects.requireNonNull:(Ljava/lang/Object;Ljava/lang/String;)Ljava/lang/Object;
      35: checkcast     #9                  // class io/reactivex/rxjava3/internal/util/ErrorMode
      38: putfield      #10                 // Field errorMode:Lio/reactivex/rxjava3/internal/util/ErrorMode;
      41: return

  public int parallelism();
    Code:
       0: aload_0
       1: getfield      #2                  // Field source:Lio/reactivex/rxjava3/parallel/ParallelFlowable;
       4: invokevirtual #11                 // Method io/reactivex/rxjava3/parallel/ParallelFlowable.parallelism:()I
       7: ireturn

  public void subscribe(org.reactivestreams.Subscriber<? super R>[]);
    Code:
       0: aload_0
       1: aload_1
       2: invokestatic  #12                 // Method io/reactivex/rxjava3/plugins/RxJavaPlugins.onSubscribe:(Lio/reactivex/rxjava3/parallel/ParallelFlowable;[Lorg/reactivestreams/Subscriber;)[Lorg/reactivestreams/Subscriber;
       5: astore_1
       6: aload_0
       7: aload_1
       8: invokevirtual #13                 // Method validate:([Lorg/reactivestreams/Subscriber;)Z
      11: ifne          15
      14: return
      15: aload_1
      16: arraylength
      17: istore_2
      18: iload_2
      19: anewarray     #14                 // class org/reactivestreams/Subscriber
      22: astore_3
      23: iconst_0
      24: istore        4
      26: iload         4
      28: iload_2
      29: if_icmpge     61
      32: aload_3
      33: iload         4
      35: aload_1
      36: iload         4
      38: aaload
      39: aload_0
      40: getfield      #6                  // Field mapper:Lio/reactivex/rxjava3/functions/Function;
      43: aload_0
      44: getfield      #7                  // Field prefetch:I
      47: aload_0
      48: getfield      #10                 // Field errorMode:Lio/reactivex/rxjava3/internal/util/ErrorMode;
      51: invokestatic  #15                 // Method io/reactivex/rxjava3/internal/operators/flowable/FlowableConcatMap.subscribe:(Lorg/reactivestreams/Subscriber;Lio/reactivex/rxjava3/functions/Function;ILio/reactivex/rxjava3/internal/util/ErrorMode;)Lorg/reactivestreams/Subscriber;
      54: aastore
      55: iinc          4, 1
      58: goto          26
      61: aload_0
      62: getfield      #2                  // Field source:Lio/reactivex/rxjava3/parallel/ParallelFlowable;
      65: aload_3
      66: invokevirtual #16                 // Method io/reactivex/rxjava3/parallel/ParallelFlowable.subscribe:([Lorg/reactivestreams/Subscriber;)V
      69: return
}
