Compiled from "ParallelJoin.java"
public final class io.reactivex.rxjava3.internal.operators.parallel.ParallelJoin<T> extends io.reactivex.rxjava3.core.Flowable<T> {
  final io.reactivex.rxjava3.parallel.ParallelFlowable<? extends T> source;

  final int prefetch;

  final boolean delayErrors;

  public io.reactivex.rxjava3.internal.operators.parallel.ParallelJoin(io.reactivex.rxjava3.parallel.ParallelFlowable<? extends T>, int, boolean);
    Code:
       0: aload_0
       1: invokespecial #1                  // Method io/reactivex/rxjava3/core/Flowable."<init>":()V
       4: aload_0
       5: aload_1
       6: putfield      #2                  // Field source:Lio/reactivex/rxjava3/parallel/ParallelFlowable;
       9: aload_0
      10: iload_2
      11: putfield      #3                  // Field prefetch:I
      14: aload_0
      15: iload_3
      16: putfield      #4                  // Field delayErrors:Z
      19: return

  protected void subscribeActual(org.reactivestreams.Subscriber<? super T>);
    Code:
       0: aload_0
       1: getfield      #4                  // Field delayErrors:Z
       4: ifeq          30
       7: new           #5                  // class io/reactivex/rxjava3/internal/operators/parallel/ParallelJoin$JoinSubscriptionDelayError
      10: dup
      11: aload_1
      12: aload_0
      13: getfield      #2                  // Field source:Lio/reactivex/rxjava3/parallel/ParallelFlowable;
      16: invokevirtual #6                  // Method io/reactivex/rxjava3/parallel/ParallelFlowable.parallelism:()I
      19: aload_0
      20: getfield      #3                  // Field prefetch:I
      23: invokespecial #7                  // Method io/reactivex/rxjava3/internal/operators/parallel/ParallelJoin$JoinSubscriptionDelayError."<init>":(Lorg/reactivestreams/Subscriber;II)V
      26: astore_2
      27: goto          50
      30: new           #8                  // class io/reactivex/rxjava3/internal/operators/parallel/ParallelJoin$JoinSubscription
      33: dup
      34: aload_1
      35: aload_0
      36: getfield      #2                  // Field source:Lio/reactivex/rxjava3/parallel/ParallelFlowable;
      39: invokevirtual #6                  // Method io/reactivex/rxjava3/parallel/ParallelFlowable.parallelism:()I
      42: aload_0
      43: getfield      #3                  // Field prefetch:I
      46: invokespecial #9                  // Method io/reactivex/rxjava3/internal/operators/parallel/ParallelJoin$JoinSubscription."<init>":(Lorg/reactivestreams/Subscriber;II)V
      49: astore_2
      50: aload_1
      51: aload_2
      52: invokeinterface #10,  2           // InterfaceMethod org/reactivestreams/Subscriber.onSubscribe:(Lorg/reactivestreams/Subscription;)V
      57: aload_0
      58: getfield      #2                  // Field source:Lio/reactivex/rxjava3/parallel/ParallelFlowable;
      61: aload_2
      62: getfield      #11                 // Field io/reactivex/rxjava3/internal/operators/parallel/ParallelJoin$JoinSubscriptionBase.subscribers:[Lio/reactivex/rxjava3/internal/operators/parallel/ParallelJoin$JoinInnerSubscriber;
      65: invokevirtual #12                 // Method io/reactivex/rxjava3/parallel/ParallelFlowable.subscribe:([Lorg/reactivestreams/Subscriber;)V
      68: return
}
