Compiled from "ParallelSortedJoin.java"
public final class io.reactivex.rxjava3.internal.operators.parallel.ParallelSortedJoin<T> extends io.reactivex.rxjava3.core.Flowable<T> {
  final io.reactivex.rxjava3.parallel.ParallelFlowable<java.util.List<T>> source;

  final java.util.Comparator<? super T> comparator;

  public io.reactivex.rxjava3.internal.operators.parallel.ParallelSortedJoin(io.reactivex.rxjava3.parallel.ParallelFlowable<java.util.List<T>>, java.util.Comparator<? super T>);
    Code:
       0: aload_0
       1: invokespecial #1                  // Method io/reactivex/rxjava3/core/Flowable."<init>":()V
       4: aload_0
       5: aload_1
       6: putfield      #2                  // Field source:Lio/reactivex/rxjava3/parallel/ParallelFlowable;
       9: aload_0
      10: aload_2
      11: putfield      #3                  // Field comparator:Ljava/util/Comparator;
      14: return

  protected void subscribeActual(org.reactivestreams.Subscriber<? super T>);
    Code:
       0: new           #4                  // class io/reactivex/rxjava3/internal/operators/parallel/ParallelSortedJoin$SortedJoinSubscription
       3: dup
       4: aload_1
       5: aload_0
       6: getfield      #2                  // Field source:Lio/reactivex/rxjava3/parallel/ParallelFlowable;
       9: invokevirtual #5                  // Method io/reactivex/rxjava3/parallel/ParallelFlowable.parallelism:()I
      12: aload_0
      13: getfield      #3                  // Field comparator:Ljava/util/Comparator;
      16: invokespecial #6                  // Method io/reactivex/rxjava3/internal/operators/parallel/ParallelSortedJoin$SortedJoinSubscription."<init>":(Lorg/reactivestreams/Subscriber;ILjava/util/Comparator;)V
      19: astore_2
      20: aload_1
      21: aload_2
      22: invokeinterface #7,  2            // InterfaceMethod org/reactivestreams/Subscriber.onSubscribe:(Lorg/reactivestreams/Subscription;)V
      27: aload_0
      28: getfield      #2                  // Field source:Lio/reactivex/rxjava3/parallel/ParallelFlowable;
      31: aload_2
      32: getfield      #8                  // Field io/reactivex/rxjava3/internal/operators/parallel/ParallelSortedJoin$SortedJoinSubscription.subscribers:[Lio/reactivex/rxjava3/internal/operators/parallel/ParallelSortedJoin$SortedJoinInnerSubscriber;
      35: invokevirtual #9                  // Method io/reactivex/rxjava3/parallel/ParallelFlowable.subscribe:([Lorg/reactivestreams/Subscriber;)V
      38: return
}
