Compiled from "ParallelFromPublisher.java"
final class io.reactivex.rxjava3.internal.operators.parallel.ParallelFromPublisher$ParallelDispatcher$RailSubscription implements org.reactivestreams.Subscription {
  final int j;

  final int m;

  final io.reactivex.rxjava3.internal.operators.parallel.ParallelFromPublisher$ParallelDispatcher this$0;

  io.reactivex.rxjava3.internal.operators.parallel.ParallelFromPublisher$ParallelDispatcher$RailSubscription(io.reactivex.rxjava3.internal.operators.parallel.ParallelFromPublisher$ParallelDispatcher, int, int);
    Code:
       0: aload_0
       1: aload_1
       2: putfield      #1                  // Field this$0:Lio/reactivex/rxjava3/internal/operators/parallel/ParallelFromPublisher$ParallelDispatcher;
       5: aload_0
       6: invokespecial #2                  // Method java/lang/Object."<init>":()V
       9: aload_0
      10: iload_2
      11: putfield      #3                  // Field j:I
      14: aload_0
      15: iload_3
      16: putfield      #4                  // Field m:I
      19: return

  public void request(long);
    Code:
       0: lload_1
       1: invokestatic  #5                  // Method io/reactivex/rxjava3/internal/subscriptions/SubscriptionHelper.validate:(J)Z
       4: ifeq          88
       7: aload_0
       8: getfield      #1                  // Field this$0:Lio/reactivex/rxjava3/internal/operators/parallel/ParallelFromPublisher$ParallelDispatcher;
      11: getfield      #6                  // Field io/reactivex/rxjava3/internal/operators/parallel/ParallelFromPublisher$ParallelDispatcher.requests:Ljava/util/concurrent/atomic/AtomicLongArray;
      14: astore_3
      15: aload_3
      16: aload_0
      17: getfield      #3                  // Field j:I
      20: invokevirtual #7                  // Method java/util/concurrent/atomic/AtomicLongArray.get:(I)J
      23: lstore        4
      25: lload         4
      27: ldc2_w        #9                  // long 9223372036854775807l
      30: lcmp
      31: ifne          35
      34: return
      35: lload         4
      37: lload_1
      38: invokestatic  #11                 // Method io/reactivex/rxjava3/internal/util/BackpressureHelper.addCap:(JJ)J
      41: lstore        6
      43: aload_3
      44: aload_0
      45: getfield      #3                  // Field j:I
      48: lload         4
      50: lload         6
      52: invokevirtual #12                 // Method java/util/concurrent/atomic/AtomicLongArray.compareAndSet:(IJJ)Z
      55: ifeq          61
      58: goto          64
      61: goto          15
      64: aload_0
      65: getfield      #1                  // Field this$0:Lio/reactivex/rxjava3/internal/operators/parallel/ParallelFromPublisher$ParallelDispatcher;
      68: getfield      #13                 // Field io/reactivex/rxjava3/internal/operators/parallel/ParallelFromPublisher$ParallelDispatcher.subscriberCount:Ljava/util/concurrent/atomic/AtomicInteger;
      71: invokevirtual #14                 // Method java/util/concurrent/atomic/AtomicInteger.get:()I
      74: aload_0
      75: getfield      #4                  // Field m:I
      78: if_icmpne     88
      81: aload_0
      82: getfield      #1                  // Field this$0:Lio/reactivex/rxjava3/internal/operators/parallel/ParallelFromPublisher$ParallelDispatcher;
      85: invokevirtual #15                 // Method io/reactivex/rxjava3/internal/operators/parallel/ParallelFromPublisher$ParallelDispatcher.drain:()V
      88: return

  public void cancel();
    Code:
       0: aload_0
       1: getfield      #1                  // Field this$0:Lio/reactivex/rxjava3/internal/operators/parallel/ParallelFromPublisher$ParallelDispatcher;
       4: getfield      #6                  // Field io/reactivex/rxjava3/internal/operators/parallel/ParallelFromPublisher$ParallelDispatcher.requests:Ljava/util/concurrent/atomic/AtomicLongArray;
       7: aload_0
       8: getfield      #4                  // Field m:I
      11: aload_0
      12: getfield      #3                  // Field j:I
      15: iadd
      16: lconst_0
      17: lconst_1
      18: invokevirtual #12                 // Method java/util/concurrent/atomic/AtomicLongArray.compareAndSet:(IJJ)Z
      21: ifeq          40
      24: aload_0
      25: getfield      #1                  // Field this$0:Lio/reactivex/rxjava3/internal/operators/parallel/ParallelFromPublisher$ParallelDispatcher;
      28: aload_0
      29: getfield      #4                  // Field m:I
      32: aload_0
      33: getfield      #4                  // Field m:I
      36: iadd
      37: invokevirtual #16                 // Method io/reactivex/rxjava3/internal/operators/parallel/ParallelFromPublisher$ParallelDispatcher.cancel:(I)V
      40: return
}
