Compiled from "ParallelPeek.java"
final class io.reactivex.rxjava3.internal.operators.parallel.ParallelPeek$ParallelPeekSubscriber<T> implements io.reactivex.rxjava3.core.FlowableSubscriber<T>, org.reactivestreams.Subscription {
  final org.reactivestreams.Subscriber<? super T> downstream;

  final io.reactivex.rxjava3.internal.operators.parallel.ParallelPeek<T> parent;

  org.reactivestreams.Subscription upstream;

  boolean done;

  io.reactivex.rxjava3.internal.operators.parallel.ParallelPeek$ParallelPeekSubscriber(org.reactivestreams.Subscriber<? super T>, io.reactivex.rxjava3.internal.operators.parallel.ParallelPeek<T>);
    Code:
       0: aload_0
       1: invokespecial #1                  // Method java/lang/Object."<init>":()V
       4: aload_0
       5: aload_1
       6: putfield      #2                  // Field downstream:Lorg/reactivestreams/Subscriber;
       9: aload_0
      10: aload_2
      11: putfield      #3                  // Field parent:Lio/reactivex/rxjava3/internal/operators/parallel/ParallelPeek;
      14: return

  public void request(long);
    Code:
       0: aload_0
       1: getfield      #3                  // Field parent:Lio/reactivex/rxjava3/internal/operators/parallel/ParallelPeek;
       4: getfield      #4                  // Field io/reactivex/rxjava3/internal/operators/parallel/ParallelPeek.onRequest:Lio/reactivex/rxjava3/functions/LongConsumer;
       7: lload_1
       8: invokeinterface #5,  3            // InterfaceMethod io/reactivex/rxjava3/functions/LongConsumer.accept:(J)V
      13: goto          25
      16: astore_3
      17: aload_3
      18: invokestatic  #7                  // Method io/reactivex/rxjava3/exceptions/Exceptions.throwIfFatal:(Ljava/lang/Throwable;)V
      21: aload_3
      22: invokestatic  #8                  // Method io/reactivex/rxjava3/plugins/RxJavaPlugins.onError:(Ljava/lang/Throwable;)V
      25: aload_0
      26: getfield      #9                  // Field upstream:Lorg/reactivestreams/Subscription;
      29: lload_1
      30: invokeinterface #10,  3           // InterfaceMethod org/reactivestreams/Subscription.request:(J)V
      35: return
    Exception table:
       from    to  target type
           0    13    16   Class java/lang/Throwable

  public void cancel();
    Code:
       0: aload_0
       1: getfield      #3                  // Field parent:Lio/reactivex/rxjava3/internal/operators/parallel/ParallelPeek;
       4: getfield      #11                 // Field io/reactivex/rxjava3/internal/operators/parallel/ParallelPeek.onCancel:Lio/reactivex/rxjava3/functions/Action;
       7: invokeinterface #12,  1           // InterfaceMethod io/reactivex/rxjava3/functions/Action.run:()V
      12: goto          24
      15: astore_1
      16: aload_1
      17: invokestatic  #7                  // Method io/reactivex/rxjava3/exceptions/Exceptions.throwIfFatal:(Ljava/lang/Throwable;)V
      20: aload_1
      21: invokestatic  #8                  // Method io/reactivex/rxjava3/plugins/RxJavaPlugins.onError:(Ljava/lang/Throwable;)V
      24: aload_0
      25: getfield      #9                  // Field upstream:Lorg/reactivestreams/Subscription;
      28: invokeinterface #13,  1           // InterfaceMethod org/reactivestreams/Subscription.cancel:()V
      33: return
    Exception table:
       from    to  target type
           0    12    15   Class java/lang/Throwable

  public void onSubscribe(org.reactivestreams.Subscription);
    Code:
       0: aload_0
       1: getfield      #9                  // Field upstream:Lorg/reactivestreams/Subscription;
       4: aload_1
       5: invokestatic  #14                 // Method io/reactivex/rxjava3/internal/subscriptions/SubscriptionHelper.validate:(Lorg/reactivestreams/Subscription;Lorg/reactivestreams/Subscription;)Z
       8: ifeq          71
      11: aload_0
      12: aload_1
      13: putfield      #9                  // Field upstream:Lorg/reactivestreams/Subscription;
      16: aload_0
      17: getfield      #3                  // Field parent:Lio/reactivex/rxjava3/internal/operators/parallel/ParallelPeek;
      20: getfield      #15                 // Field io/reactivex/rxjava3/internal/operators/parallel/ParallelPeek.onSubscribe:Lio/reactivex/rxjava3/functions/Consumer;
      23: aload_1
      24: invokeinterface #16,  2           // InterfaceMethod io/reactivex/rxjava3/functions/Consumer.accept:(Ljava/lang/Object;)V
      29: goto          61
      32: astore_2
      33: aload_2
      34: invokestatic  #7                  // Method io/reactivex/rxjava3/exceptions/Exceptions.throwIfFatal:(Ljava/lang/Throwable;)V
      37: aload_1
      38: invokeinterface #13,  1           // InterfaceMethod org/reactivestreams/Subscription.cancel:()V
      43: aload_0
      44: getfield      #2                  // Field downstream:Lorg/reactivestreams/Subscriber;
      47: getstatic     #17                 // Field io/reactivex/rxjava3/internal/subscriptions/EmptySubscription.INSTANCE:Lio/reactivex/rxjava3/internal/subscriptions/EmptySubscription;
      50: invokeinterface #18,  2           // InterfaceMethod org/reactivestreams/Subscriber.onSubscribe:(Lorg/reactivestreams/Subscription;)V
      55: aload_0
      56: aload_2
      57: invokevirtual #19                 // Method onError:(Ljava/lang/Throwable;)V
      60: return
      61: aload_0
      62: getfield      #2                  // Field downstream:Lorg/reactivestreams/Subscriber;
      65: aload_0
      66: invokeinterface #18,  2           // InterfaceMethod org/reactivestreams/Subscriber.onSubscribe:(Lorg/reactivestreams/Subscription;)V
      71: return
    Exception table:
       from    to  target type
          16    29    32   Class java/lang/Throwable

  public void onNext(T);
    Code:
       0: aload_0
       1: getfield      #20                 // Field done:Z
       4: ifne          70
       7: aload_0
       8: getfield      #3                  // Field parent:Lio/reactivex/rxjava3/internal/operators/parallel/ParallelPeek;
      11: getfield      #21                 // Field io/reactivex/rxjava3/internal/operators/parallel/ParallelPeek.onNext:Lio/reactivex/rxjava3/functions/Consumer;
      14: aload_1
      15: invokeinterface #16,  2           // InterfaceMethod io/reactivex/rxjava3/functions/Consumer.accept:(Ljava/lang/Object;)V
      20: goto          34
      23: astore_2
      24: aload_2
      25: invokestatic  #7                  // Method io/reactivex/rxjava3/exceptions/Exceptions.throwIfFatal:(Ljava/lang/Throwable;)V
      28: aload_0
      29: aload_2
      30: invokevirtual #19                 // Method onError:(Ljava/lang/Throwable;)V
      33: return
      34: aload_0
      35: getfield      #2                  // Field downstream:Lorg/reactivestreams/Subscriber;
      38: aload_1
      39: invokeinterface #22,  2           // InterfaceMethod org/reactivestreams/Subscriber.onNext:(Ljava/lang/Object;)V
      44: aload_0
      45: getfield      #3                  // Field parent:Lio/reactivex/rxjava3/internal/operators/parallel/ParallelPeek;
      48: getfield      #23                 // Field io/reactivex/rxjava3/internal/operators/parallel/ParallelPeek.onAfterNext:Lio/reactivex/rxjava3/functions/Consumer;
      51: aload_1
      52: invokeinterface #16,  2           // InterfaceMethod io/reactivex/rxjava3/functions/Consumer.accept:(Ljava/lang/Object;)V
      57: goto          70
      60: astore_2
      61: aload_2
      62: invokestatic  #7                  // Method io/reactivex/rxjava3/exceptions/Exceptions.throwIfFatal:(Ljava/lang/Throwable;)V
      65: aload_0
      66: aload_2
      67: invokevirtual #19                 // Method onError:(Ljava/lang/Throwable;)V
      70: return
    Exception table:
       from    to  target type
           7    20    23   Class java/lang/Throwable
          44    57    60   Class java/lang/Throwable

  public void onError(java.lang.Throwable);
    Code:
       0: aload_0
       1: getfield      #20                 // Field done:Z
       4: ifeq          12
       7: aload_1
       8: invokestatic  #8                  // Method io/reactivex/rxjava3/plugins/RxJavaPlugins.onError:(Ljava/lang/Throwable;)V
      11: return
      12: aload_0
      13: iconst_1
      14: putfield      #20                 // Field done:Z
      17: aload_0
      18: getfield      #3                  // Field parent:Lio/reactivex/rxjava3/internal/operators/parallel/ParallelPeek;
      21: getfield      #24                 // Field io/reactivex/rxjava3/internal/operators/parallel/ParallelPeek.onError:Lio/reactivex/rxjava3/functions/Consumer;
      24: aload_1
      25: invokeinterface #16,  2           // InterfaceMethod io/reactivex/rxjava3/functions/Consumer.accept:(Ljava/lang/Object;)V
      30: goto          58
      33: astore_2
      34: aload_2
      35: invokestatic  #7                  // Method io/reactivex/rxjava3/exceptions/Exceptions.throwIfFatal:(Ljava/lang/Throwable;)V
      38: new           #25                 // class io/reactivex/rxjava3/exceptions/CompositeException
      41: dup
      42: iconst_2
      43: anewarray     #26                 // class java/lang/Throwable
      46: dup
      47: iconst_0
      48: aload_1
      49: aastore
      50: dup
      51: iconst_1
      52: aload_2
      53: aastore
      54: invokespecial #27                 // Method io/reactivex/rxjava3/exceptions/CompositeException."<init>":([Ljava/lang/Throwable;)V
      57: astore_1
      58: aload_0
      59: getfield      #2                  // Field downstream:Lorg/reactivestreams/Subscriber;
      62: aload_1
      63: invokeinterface #28,  2           // InterfaceMethod org/reactivestreams/Subscriber.onError:(Ljava/lang/Throwable;)V
      68: aload_0
      69: getfield      #3                  // Field parent:Lio/reactivex/rxjava3/internal/operators/parallel/ParallelPeek;
      72: getfield      #29                 // Field io/reactivex/rxjava3/internal/operators/parallel/ParallelPeek.onAfterTerminated:Lio/reactivex/rxjava3/functions/Action;
      75: invokeinterface #12,  1           // InterfaceMethod io/reactivex/rxjava3/functions/Action.run:()V
      80: goto          92
      83: astore_2
      84: aload_2
      85: invokestatic  #7                  // Method io/reactivex/rxjava3/exceptions/Exceptions.throwIfFatal:(Ljava/lang/Throwable;)V
      88: aload_2
      89: invokestatic  #8                  // Method io/reactivex/rxjava3/plugins/RxJavaPlugins.onError:(Ljava/lang/Throwable;)V
      92: return
    Exception table:
       from    to  target type
          17    30    33   Class java/lang/Throwable
          68    80    83   Class java/lang/Throwable

  public void onComplete();
    Code:
       0: aload_0
       1: getfield      #20                 // Field done:Z
       4: ifne          76
       7: aload_0
       8: iconst_1
       9: putfield      #20                 // Field done:Z
      12: aload_0
      13: getfield      #3                  // Field parent:Lio/reactivex/rxjava3/internal/operators/parallel/ParallelPeek;
      16: getfield      #30                 // Field io/reactivex/rxjava3/internal/operators/parallel/ParallelPeek.onComplete:Lio/reactivex/rxjava3/functions/Action;
      19: invokeinterface #12,  1           // InterfaceMethod io/reactivex/rxjava3/functions/Action.run:()V
      24: goto          43
      27: astore_1
      28: aload_1
      29: invokestatic  #7                  // Method io/reactivex/rxjava3/exceptions/Exceptions.throwIfFatal:(Ljava/lang/Throwable;)V
      32: aload_0
      33: getfield      #2                  // Field downstream:Lorg/reactivestreams/Subscriber;
      36: aload_1
      37: invokeinterface #28,  2           // InterfaceMethod org/reactivestreams/Subscriber.onError:(Ljava/lang/Throwable;)V
      42: return
      43: aload_0
      44: getfield      #2                  // Field downstream:Lorg/reactivestreams/Subscriber;
      47: invokeinterface #31,  1           // InterfaceMethod org/reactivestreams/Subscriber.onComplete:()V
      52: aload_0
      53: getfield      #3                  // Field parent:Lio/reactivex/rxjava3/internal/operators/parallel/ParallelPeek;
      56: getfield      #29                 // Field io/reactivex/rxjava3/internal/operators/parallel/ParallelPeek.onAfterTerminated:Lio/reactivex/rxjava3/functions/Action;
      59: invokeinterface #12,  1           // InterfaceMethod io/reactivex/rxjava3/functions/Action.run:()V
      64: goto          76
      67: astore_1
      68: aload_1
      69: invokestatic  #7                  // Method io/reactivex/rxjava3/exceptions/Exceptions.throwIfFatal:(Ljava/lang/Throwable;)V
      72: aload_1
      73: invokestatic  #8                  // Method io/reactivex/rxjava3/plugins/RxJavaPlugins.onError:(Ljava/lang/Throwable;)V
      76: return
    Exception table:
       from    to  target type
          12    24    27   Class java/lang/Throwable
          52    64    67   Class java/lang/Throwable
}
