Compiled from "ParallelPeek.java"
public final class io.reactivex.rxjava3.internal.operators.parallel.ParallelPeek<T> extends io.reactivex.rxjava3.parallel.ParallelFlowable<T> {
  final io.reactivex.rxjava3.parallel.ParallelFlowable<T> source;

  final io.reactivex.rxjava3.functions.Consumer<? super T> onNext;

  final io.reactivex.rxjava3.functions.Consumer<? super T> onAfterNext;

  final io.reactivex.rxjava3.functions.Consumer<? super java.lang.Throwable> onError;

  final io.reactivex.rxjava3.functions.Action onComplete;

  final io.reactivex.rxjava3.functions.Action onAfterTerminated;

  final io.reactivex.rxjava3.functions.Consumer<? super org.reactivestreams.Subscription> onSubscribe;

  final io.reactivex.rxjava3.functions.LongConsumer onRequest;

  final io.reactivex.rxjava3.functions.Action onCancel;

  public io.reactivex.rxjava3.internal.operators.parallel.ParallelPeek(io.reactivex.rxjava3.parallel.ParallelFlowable<T>, io.reactivex.rxjava3.functions.Consumer<? super T>, io.reactivex.rxjava3.functions.Consumer<? super T>, io.reactivex.rxjava3.functions.Consumer<? super java.lang.Throwable>, io.reactivex.rxjava3.functions.Action, io.reactivex.rxjava3.functions.Action, io.reactivex.rxjava3.functions.Consumer<? super org.reactivestreams.Subscription>, io.reactivex.rxjava3.functions.LongConsumer, io.reactivex.rxjava3.functions.Action);
    Code:
       0: aload_0
       1: invokespecial #1                  // Method io/reactivex/rxjava3/parallel/ParallelFlowable."<init>":()V
       4: aload_0
       5: aload_1
       6: putfield      #2                  // Field source:Lio/reactivex/rxjava3/parallel/ParallelFlowable;
       9: aload_0
      10: aload_2
      11: ldc           #3                  // String onNext is null
      13: invokestatic  #4                  // Method java/util/Objects.requireNonNull:(Ljava/lang/Object;Ljava/lang/String;)Ljava/lang/Object;
      16: checkcast     #5                  // class io/reactivex/rxjava3/functions/Consumer
      19: putfield      #6                  // Field onNext:Lio/reactivex/rxjava3/functions/Consumer;
      22: aload_0
      23: aload_3
      24: ldc           #7                  // String onAfterNext is null
      26: invokestatic  #4                  // Method java/util/Objects.requireNonNull:(Ljava/lang/Object;Ljava/lang/String;)Ljava/lang/Object;
      29: checkcast     #5                  // class io/reactivex/rxjava3/functions/Consumer
      32: putfield      #8                  // Field onAfterNext:Lio/reactivex/rxjava3/functions/Consumer;
      35: aload_0
      36: aload         4
      38: ldc           #9                  // String onError is null
      40: invokestatic  #4                  // Method java/util/Objects.requireNonNull:(Ljava/lang/Object;Ljava/lang/String;)Ljava/lang/Object;
      43: checkcast     #5                  // class io/reactivex/rxjava3/functions/Consumer
      46: putfield      #10                 // Field onError:Lio/reactivex/rxjava3/functions/Consumer;
      49: aload_0
      50: aload         5
      52: ldc           #11                 // String onComplete is null
      54: invokestatic  #4                  // Method java/util/Objects.requireNonNull:(Ljava/lang/Object;Ljava/lang/String;)Ljava/lang/Object;
      57: checkcast     #12                 // class io/reactivex/rxjava3/functions/Action
      60: putfield      #13                 // Field onComplete:Lio/reactivex/rxjava3/functions/Action;
      63: aload_0
      64: aload         6
      66: ldc           #14                 // String onAfterTerminated is null
      68: invokestatic  #4                  // Method java/util/Objects.requireNonNull:(Ljava/lang/Object;Ljava/lang/String;)Ljava/lang/Object;
      71: checkcast     #12                 // class io/reactivex/rxjava3/functions/Action
      74: putfield      #15                 // Field onAfterTerminated:Lio/reactivex/rxjava3/functions/Action;
      77: aload_0
      78: aload         7
      80: ldc           #16                 // String onSubscribe is null
      82: invokestatic  #4                  // Method java/util/Objects.requireNonNull:(Ljava/lang/Object;Ljava/lang/String;)Ljava/lang/Object;
      85: checkcast     #5                  // class io/reactivex/rxjava3/functions/Consumer
      88: putfield      #17                 // Field onSubscribe:Lio/reactivex/rxjava3/functions/Consumer;
      91: aload_0
      92: aload         8
      94: ldc           #18                 // String onRequest is null
      96: invokestatic  #4                  // Method java/util/Objects.requireNonNull:(Ljava/lang/Object;Ljava/lang/String;)Ljava/lang/Object;
      99: checkcast     #19                 // class io/reactivex/rxjava3/functions/LongConsumer
     102: putfield      #20                 // Field onRequest:Lio/reactivex/rxjava3/functions/LongConsumer;
     105: aload_0
     106: aload         9
     108: ldc           #21                 // String onCancel is null
     110: invokestatic  #4                  // Method java/util/Objects.requireNonNull:(Ljava/lang/Object;Ljava/lang/String;)Ljava/lang/Object;
     113: checkcast     #12                 // class io/reactivex/rxjava3/functions/Action
     116: putfield      #22                 // Field onCancel:Lio/reactivex/rxjava3/functions/Action;
     119: return

  public void subscribe(org.reactivestreams.Subscriber<? super T>[]);
    Code:
       0: aload_0
       1: aload_1
       2: invokestatic  #23                 // Method io/reactivex/rxjava3/plugins/RxJavaPlugins.onSubscribe:(Lio/reactivex/rxjava3/parallel/ParallelFlowable;[Lorg/reactivestreams/Subscriber;)[Lorg/reactivestreams/Subscriber;
       5: astore_1
       6: aload_0
       7: aload_1
       8: invokevirtual #24                 // Method validate:([Lorg/reactivestreams/Subscriber;)Z
      11: ifne          15
      14: return
      15: aload_1
      16: arraylength
      17: istore_2
      18: iload_2
      19: anewarray     #25                 // class org/reactivestreams/Subscriber
      22: astore_3
      23: iconst_0
      24: istore        4
      26: iload         4
      28: iload_2
      29: if_icmpge     54
      32: aload_3
      33: iload         4
      35: new           #26                 // class io/reactivex/rxjava3/internal/operators/parallel/ParallelPeek$ParallelPeekSubscriber
      38: dup
      39: aload_1
      40: iload         4
      42: aaload
      43: aload_0
      44: invokespecial #27                 // Method io/reactivex/rxjava3/internal/operators/parallel/ParallelPeek$ParallelPeekSubscriber."<init>":(Lorg/reactivestreams/Subscriber;Lio/reactivex/rxjava3/internal/operators/parallel/ParallelPeek;)V
      47: aastore
      48: iinc          4, 1
      51: goto          26
      54: aload_0
      55: getfield      #2                  // Field source:Lio/reactivex/rxjava3/parallel/ParallelFlowable;
      58: aload_3
      59: invokevirtual #28                 // Method io/reactivex/rxjava3/parallel/ParallelFlowable.subscribe:([Lorg/reactivestreams/Subscriber;)V
      62: return

  public int parallelism();
    Code:
       0: aload_0
       1: getfield      #2                  // Field source:Lio/reactivex/rxjava3/parallel/ParallelFlowable;
       4: invokevirtual #29                 // Method io/reactivex/rxjava3/parallel/ParallelFlowable.parallelism:()I
       7: ireturn
}
