Compiled from "ParallelFilter.java"
final class io.reactivex.rxjava3.internal.operators.parallel.ParallelFilter$ParallelFilterConditionalSubscriber<T> extends io.reactivex.rxjava3.internal.operators.parallel.ParallelFilter$BaseFilterSubscriber<T> {
  final io.reactivex.rxjava3.operators.ConditionalSubscriber<? super T> downstream;

  io.reactivex.rxjava3.internal.operators.parallel.ParallelFilter$ParallelFilterConditionalSubscriber(io.reactivex.rxjava3.operators.ConditionalSubscriber<? super T>, io.reactivex.rxjava3.functions.Predicate<? super T>);
    Code:
       0: aload_0
       1: aload_2
       2: invokespecial #1                  // Method io/reactivex/rxjava3/internal/operators/parallel/ParallelFilter$BaseFilterSubscriber."<init>":(Lio/reactivex/rxjava3/functions/Predicate;)V
       5: aload_0
       6: aload_1
       7: putfield      #2                  // Field downstream:Lio/reactivex/rxjava3/operators/ConditionalSubscriber;
      10: return

  public void onSubscribe(org.reactivestreams.Subscription);
    Code:
       0: aload_0
       1: getfield      #3                  // Field upstream:Lorg/reactivestreams/Subscription;
       4: aload_1
       5: invokestatic  #4                  // Method io/reactivex/rxjava3/internal/subscriptions/SubscriptionHelper.validate:(Lorg/reactivestreams/Subscription;Lorg/reactivestreams/Subscription;)Z
       8: ifeq          26
      11: aload_0
      12: aload_1
      13: putfield      #3                  // Field upstream:Lorg/reactivestreams/Subscription;
      16: aload_0
      17: getfield      #2                  // Field downstream:Lio/reactivex/rxjava3/operators/ConditionalSubscriber;
      20: aload_0
      21: invokeinterface #5,  2            // InterfaceMethod io/reactivex/rxjava3/operators/ConditionalSubscriber.onSubscribe:(Lorg/reactivestreams/Subscription;)V
      26: return

  public boolean tryOnNext(T);
    Code:
       0: aload_0
       1: getfield      #6                  // Field done:Z
       4: ifne          52
       7: aload_0
       8: getfield      #7                  // Field predicate:Lio/reactivex/rxjava3/functions/Predicate;
      11: aload_1
      12: invokeinterface #8,  2            // InterfaceMethod io/reactivex/rxjava3/functions/Predicate.test:(Ljava/lang/Object;)Z
      17: istore_2
      18: goto          37
      21: astore_3
      22: aload_3
      23: invokestatic  #10                 // Method io/reactivex/rxjava3/exceptions/Exceptions.throwIfFatal:(Ljava/lang/Throwable;)V
      26: aload_0
      27: invokevirtual #11                 // Method cancel:()V
      30: aload_0
      31: aload_3
      32: invokevirtual #12                 // Method onError:(Ljava/lang/Throwable;)V
      35: iconst_0
      36: ireturn
      37: iload_2
      38: ifeq          52
      41: aload_0
      42: getfield      #2                  // Field downstream:Lio/reactivex/rxjava3/operators/ConditionalSubscriber;
      45: aload_1
      46: invokeinterface #13,  2           // InterfaceMethod io/reactivex/rxjava3/operators/ConditionalSubscriber.tryOnNext:(Ljava/lang/Object;)Z
      51: ireturn
      52: iconst_0
      53: ireturn
    Exception table:
       from    to  target type
           7    18    21   Class java/lang/Throwable

  public void onError(java.lang.Throwable);
    Code:
       0: aload_0
       1: getfield      #6                  // Field done:Z
       4: ifeq          12
       7: aload_1
       8: invokestatic  #14                 // Method io/reactivex/rxjava3/plugins/RxJavaPlugins.onError:(Ljava/lang/Throwable;)V
      11: return
      12: aload_0
      13: iconst_1
      14: putfield      #6                  // Field done:Z
      17: aload_0
      18: getfield      #2                  // Field downstream:Lio/reactivex/rxjava3/operators/ConditionalSubscriber;
      21: aload_1
      22: invokeinterface #15,  2           // InterfaceMethod io/reactivex/rxjava3/operators/ConditionalSubscriber.onError:(Ljava/lang/Throwable;)V
      27: return

  public void onComplete();
    Code:
       0: aload_0
       1: getfield      #6                  // Field done:Z
       4: ifne          21
       7: aload_0
       8: iconst_1
       9: putfield      #6                  // Field done:Z
      12: aload_0
      13: getfield      #2                  // Field downstream:Lio/reactivex/rxjava3/operators/ConditionalSubscriber;
      16: invokeinterface #16,  1           // InterfaceMethod io/reactivex/rxjava3/operators/ConditionalSubscriber.onComplete:()V
      21: return
}
