Compiled from "ParallelFromArray.java"
public final class io.reactivex.rxjava3.internal.operators.parallel.ParallelFromArray<T> extends io.reactivex.rxjava3.parallel.ParallelFlowable<T> {
  final org.reactivestreams.Publisher<T>[] sources;

  public io.reactivex.rxjava3.internal.operators.parallel.ParallelFromArray(org.reactivestreams.Publisher<T>[]);
    Code:
       0: aload_0
       1: invokespecial #1                  // Method io/reactivex/rxjava3/parallel/ParallelFlowable."<init>":()V
       4: aload_0
       5: aload_1
       6: putfield      #2                  // Field sources:[Lorg/reactivestreams/Publisher;
       9: return

  public int parallelism();
    Code:
       0: aload_0
       1: getfield      #2                  // Field sources:[Lorg/reactivestreams/Publisher;
       4: arraylength
       5: ireturn

  public void subscribe(org.reactivestreams.Subscriber<? super T>[]);
    Code:
       0: aload_0
       1: aload_1
       2: invokestatic  #3                  // Method io/reactivex/rxjava3/plugins/RxJavaPlugins.onSubscribe:(Lio/reactivex/rxjava3/parallel/ParallelFlowable;[Lorg/reactivestreams/Subscriber;)[Lorg/reactivestreams/Subscriber;
       5: astore_1
       6: aload_0
       7: aload_1
       8: invokevirtual #4                  // Method validate:([Lorg/reactivestreams/Subscriber;)Z
      11: ifne          15
      14: return
      15: aload_1
      16: arraylength
      17: istore_2
      18: iconst_0
      19: istore_3
      20: iload_3
      21: iload_2
      22: if_icmpge     45
      25: aload_0
      26: getfield      #2                  // Field sources:[Lorg/reactivestreams/Publisher;
      29: iload_3
      30: aaload
      31: aload_1
      32: iload_3
      33: aaload
      34: invokeinterface #5,  2            // InterfaceMethod org/reactivestreams/Publisher.subscribe:(Lorg/reactivestreams/Subscriber;)V
      39: iinc          3, 1
      42: goto          20
      45: return
}
