Compiled from "CancelQueueCommand.java"
public class org.apache.dubbo.rpc.protocol.tri.command.CancelQueueCommand extends org.apache.dubbo.rpc.protocol.tri.command.StreamQueueCommand {
  private final io.netty.handler.codec.http2.Http2Error error;

  public org.apache.dubbo.rpc.protocol.tri.command.CancelQueueCommand(org.apache.dubbo.rpc.protocol.tri.stream.TripleStreamChannelFuture, io.netty.handler.codec.http2.Http2Error);
    Code:
       0: aload_0
       1: aload_1
       2: invokespecial #1                  // Method org/apache/dubbo/rpc/protocol/tri/command/StreamQueueCommand."<init>":(Lorg/apache/dubbo/rpc/protocol/tri/stream/TripleStreamChannelFuture;)V
       5: aload_0
       6: aload_2
       7: putfield      #2                  // Field error:Lio/netty/handler/codec/http2/Http2Error;
      10: return

  public static org.apache.dubbo.rpc.protocol.tri.command.CancelQueueCommand createCommand(org.apache.dubbo.rpc.protocol.tri.stream.TripleStreamChannelFuture, io.netty.handler.codec.http2.Http2Error);
    Code:
       0: new           #3                  // class org/apache/dubbo/rpc/protocol/tri/command/CancelQueueCommand
       3: dup
       4: aload_0
       5: aload_1
       6: invokespecial #4                  // Method "<init>":(Lorg/apache/dubbo/rpc/protocol/tri/stream/TripleStreamChannelFuture;Lio/netty/handler/codec/http2/Http2Error;)V
       9: areturn

  public void doSend(io.netty.channel.ChannelHandlerContext, io.netty.channel.ChannelPromise);
    Code:
       0: aload_1
       1: new           #5                  // class io/netty/handler/codec/http2/DefaultHttp2ResetFrame
       4: dup
       5: aload_0
       6: getfield      #2                  // Field error:Lio/netty/handler/codec/http2/Http2Error;
       9: invokespecial #6                  // Method io/netty/handler/codec/http2/DefaultHttp2ResetFrame."<init>":(Lio/netty/handler/codec/http2/Http2Error;)V
      12: aload_2
      13: invokeinterface #7,  3            // InterfaceMethod io/netty/channel/ChannelHandlerContext.write:(Ljava/lang/Object;Lio/netty/channel/ChannelPromise;)Lio/netty/channel/ChannelFuture;
      18: pop
      19: return
}
