Compiled from "CreateStreamQueueCommand.java"
public class org.apache.dubbo.rpc.protocol.tri.command.CreateStreamQueueCommand extends org.apache.dubbo.rpc.protocol.tri.command.QueuedCommand {
  private final io.netty.handler.codec.http2.Http2StreamChannelBootstrap bootstrap;

  private final org.apache.dubbo.rpc.protocol.tri.stream.TripleStreamChannelFuture streamChannelFuture;

  private org.apache.dubbo.rpc.protocol.tri.command.CreateStreamQueueCommand(io.netty.handler.codec.http2.Http2StreamChannelBootstrap, org.apache.dubbo.rpc.protocol.tri.stream.TripleStreamChannelFuture);
    Code:
       0: aload_0
       1: invokespecial #1                  // Method org/apache/dubbo/rpc/protocol/tri/command/QueuedCommand."<init>":()V
       4: aload_0
       5: aload_1
       6: putfield      #2                  // Field bootstrap:Lio/netty/handler/codec/http2/Http2StreamChannelBootstrap;
       9: aload_0
      10: aload_2
      11: putfield      #3                  // Field streamChannelFuture:Lorg/apache/dubbo/rpc/protocol/tri/stream/TripleStreamChannelFuture;
      14: aload_0
      15: aload_2
      16: invokevirtual #4                  // Method org/apache/dubbo/rpc/protocol/tri/stream/TripleStreamChannelFuture.getParentChannel:()Lio/netty/channel/Channel;
      19: invokeinterface #5,  1            // InterfaceMethod io/netty/channel/Channel.newPromise:()Lio/netty/channel/ChannelPromise;
      24: invokevirtual #6                  // Method promise:(Lio/netty/channel/ChannelPromise;)V
      27: aload_0
      28: aload_2
      29: invokevirtual #4                  // Method org/apache/dubbo/rpc/protocol/tri/stream/TripleStreamChannelFuture.getParentChannel:()Lio/netty/channel/Channel;
      32: invokevirtual #7                  // Method channel:(Lio/netty/channel/Channel;)Lorg/apache/dubbo/rpc/protocol/tri/command/QueuedCommand;
      35: pop
      36: return

  public static org.apache.dubbo.rpc.protocol.tri.command.CreateStreamQueueCommand create(io.netty.handler.codec.http2.Http2StreamChannelBootstrap, org.apache.dubbo.rpc.protocol.tri.stream.TripleStreamChannelFuture);
    Code:
       0: new           #8                  // class org/apache/dubbo/rpc/protocol/tri/command/CreateStreamQueueCommand
       3: dup
       4: aload_0
       5: aload_1
       6: invokespecial #9                  // Method "<init>":(Lio/netty/handler/codec/http2/Http2StreamChannelBootstrap;Lorg/apache/dubbo/rpc/protocol/tri/stream/TripleStreamChannelFuture;)V
       9: areturn

  public void doSend(io.netty.channel.ChannelHandlerContext, io.netty.channel.ChannelPromise);
    Code:
       0: return

  public void run(io.netty.channel.Channel);
    Code:
       0: aload_0
       1: getfield      #2                  // Field bootstrap:Lio/netty/handler/codec/http2/Http2StreamChannelBootstrap;
       4: invokevirtual #10                 // Method io/netty/handler/codec/http2/Http2StreamChannelBootstrap.open:()Lio/netty/util/concurrent/Future;
       7: astore_2
       8: aload_2
       9: invokeinterface #11,  1           // InterfaceMethod io/netty/util/concurrent/Future.isSuccess:()Z
      14: ifeq          34
      17: aload_0
      18: getfield      #3                  // Field streamChannelFuture:Lorg/apache/dubbo/rpc/protocol/tri/stream/TripleStreamChannelFuture;
      21: aload_2
      22: invokeinterface #12,  1           // InterfaceMethod io/netty/util/concurrent/Future.getNow:()Ljava/lang/Object;
      27: invokevirtual #13                 // Method org/apache/dubbo/rpc/protocol/tri/stream/TripleStreamChannelFuture.complete:(Ljava/lang/Object;)Z
      30: pop
      31: goto          48
      34: aload_0
      35: getfield      #3                  // Field streamChannelFuture:Lorg/apache/dubbo/rpc/protocol/tri/stream/TripleStreamChannelFuture;
      38: aload_2
      39: invokeinterface #14,  1           // InterfaceMethod io/netty/util/concurrent/Future.cause:()Ljava/lang/Throwable;
      44: invokevirtual #15                 // Method org/apache/dubbo/rpc/protocol/tri/stream/TripleStreamChannelFuture.completeExceptionally:(Ljava/lang/Throwable;)Z
      47: pop
      48: return
}
