Compiled from "EndStreamQueueCommand.java"
public class org.apache.dubbo.rpc.protocol.tri.command.EndStreamQueueCommand extends org.apache.dubbo.rpc.protocol.tri.command.StreamQueueCommand {
  public org.apache.dubbo.rpc.protocol.tri.command.EndStreamQueueCommand(org.apache.dubbo.rpc.protocol.tri.stream.TripleStreamChannelFuture);
    Code:
       0: aload_0
       1: aload_1
       2: invokespecial #1                  // Method org/apache/dubbo/rpc/protocol/tri/command/StreamQueueCommand."<init>":(Lorg/apache/dubbo/rpc/protocol/tri/stream/TripleStreamChannelFuture;)V
       5: return

  public static org.apache.dubbo.rpc.protocol.tri.command.EndStreamQueueCommand create(org.apache.dubbo.rpc.protocol.tri.stream.TripleStreamChannelFuture);
    Code:
       0: new           #2                  // class org/apache/dubbo/rpc/protocol/tri/command/EndStreamQueueCommand
       3: dup
       4: aload_0
       5: invokespecial #3                  // Method "<init>":(Lorg/apache/dubbo/rpc/protocol/tri/stream/TripleStreamChannelFuture;)V
       8: areturn

  public void doSend(io.netty.channel.ChannelHandlerContext, io.netty.channel.ChannelPromise);
    Code:
       0: aload_1
       1: new           #4                  // class io/netty/handler/codec/http2/DefaultHttp2DataFrame
       4: dup
       5: iconst_1
       6: invokespecial #5                  // Method io/netty/handler/codec/http2/DefaultHttp2DataFrame."<init>":(Z)V
       9: aload_2
      10: invokeinterface #6,  3            // InterfaceMethod io/netty/channel/ChannelHandlerContext.write:(Ljava/lang/Object;Lio/netty/channel/ChannelPromise;)Lio/netty/channel/ChannelFuture;
      15: pop
      16: return
}
