Compiled from "HeaderQueueCommand.java"
public class org.apache.dubbo.rpc.protocol.tri.command.HeaderQueueCommand extends org.apache.dubbo.rpc.protocol.tri.command.StreamQueueCommand {
  private final io.netty.handler.codec.http2.Http2Headers headers;

  private final boolean endStream;

  private org.apache.dubbo.rpc.protocol.tri.command.HeaderQueueCommand(org.apache.dubbo.rpc.protocol.tri.stream.TripleStreamChannelFuture, io.netty.handler.codec.http2.Http2Headers, boolean);
    Code:
       0: aload_0
       1: aload_1
       2: invokespecial #1                  // Method org/apache/dubbo/rpc/protocol/tri/command/StreamQueueCommand."<init>":(Lorg/apache/dubbo/rpc/protocol/tri/stream/TripleStreamChannelFuture;)V
       5: aload_0
       6: aload_2
       7: putfield      #2                  // Field headers:Lio/netty/handler/codec/http2/Http2Headers;
      10: aload_0
      11: iload_3
      12: putfield      #3                  // Field endStream:Z
      15: return

  public static org.apache.dubbo.rpc.protocol.tri.command.HeaderQueueCommand createHeaders(org.apache.dubbo.rpc.protocol.tri.stream.TripleStreamChannelFuture, io.netty.handler.codec.http2.Http2Headers);
    Code:
       0: new           #4                  // class org/apache/dubbo/rpc/protocol/tri/command/HeaderQueueCommand
       3: dup
       4: aload_0
       5: aload_1
       6: iconst_0
       7: invokespecial #5                  // Method "<init>":(Lorg/apache/dubbo/rpc/protocol/tri/stream/TripleStreamChannelFuture;Lio/netty/handler/codec/http2/Http2Headers;Z)V
      10: areturn

  public static org.apache.dubbo.rpc.protocol.tri.command.HeaderQueueCommand createHeaders(org.apache.dubbo.rpc.protocol.tri.stream.TripleStreamChannelFuture, io.netty.handler.codec.http2.Http2Headers, boolean);
    Code:
       0: new           #4                  // class org/apache/dubbo/rpc/protocol/tri/command/HeaderQueueCommand
       3: dup
       4: aload_0
       5: aload_1
       6: iload_2
       7: invokespecial #5                  // Method "<init>":(Lorg/apache/dubbo/rpc/protocol/tri/stream/TripleStreamChannelFuture;Lio/netty/handler/codec/http2/Http2Headers;Z)V
      10: areturn

  public io.netty.handler.codec.http2.Http2Headers getHeaders();
    Code:
       0: aload_0
       1: getfield      #2                  // Field headers:Lio/netty/handler/codec/http2/Http2Headers;
       4: areturn

  public boolean isEndStream();
    Code:
       0: aload_0
       1: getfield      #3                  // Field endStream:Z
       4: ireturn

  public void doSend(io.netty.channel.ChannelHandlerContext, io.netty.channel.ChannelPromise);
    Code:
       0: aload_1
       1: new           #6                  // class io/netty/handler/codec/http2/DefaultHttp2HeadersFrame
       4: dup
       5: aload_0
       6: getfield      #2                  // Field headers:Lio/netty/handler/codec/http2/Http2Headers;
       9: aload_0
      10: getfield      #3                  // Field endStream:Z
      13: invokespecial #7                  // Method io/netty/handler/codec/http2/DefaultHttp2HeadersFrame."<init>":(Lio/netty/handler/codec/http2/Http2Headers;Z)V
      16: aload_2
      17: invokeinterface #8,  3            // InterfaceMethod io/netty/channel/ChannelHandlerContext.write:(Ljava/lang/Object;Lio/netty/channel/ChannelPromise;)Lio/netty/channel/ChannelFuture;
      22: pop
      23: return
}
