Compiled from "TextDataQueueCommand.java"
public class org.apache.dubbo.rpc.protocol.tri.command.TextDataQueueCommand extends org.apache.dubbo.rpc.protocol.tri.command.StreamQueueCommand {
  private final java.lang.String data;

  private final boolean endStream;

  private org.apache.dubbo.rpc.protocol.tri.command.TextDataQueueCommand(org.apache.dubbo.rpc.protocol.tri.stream.TripleStreamChannelFuture, java.lang.String, boolean);
    Code:
       0: aload_0
       1: aload_1
       2: invokespecial #1                  // Method org/apache/dubbo/rpc/protocol/tri/command/StreamQueueCommand."<init>":(Lorg/apache/dubbo/rpc/protocol/tri/stream/TripleStreamChannelFuture;)V
       5: aload_0
       6: aload_2
       7: putfield      #2                  // Field data:Ljava/lang/String;
      10: aload_0
      11: iload_3
      12: putfield      #3                  // Field endStream:Z
      15: return

  public static org.apache.dubbo.rpc.protocol.tri.command.TextDataQueueCommand createCommand(org.apache.dubbo.rpc.protocol.tri.stream.TripleStreamChannelFuture, java.lang.String, boolean);
    Code:
       0: new           #4                  // class org/apache/dubbo/rpc/protocol/tri/command/TextDataQueueCommand
       3: dup
       4: aload_0
       5: aload_1
       6: iload_2
       7: invokespecial #5                  // Method "<init>":(Lorg/apache/dubbo/rpc/protocol/tri/stream/TripleStreamChannelFuture;Ljava/lang/String;Z)V
      10: areturn

  public void doSend(io.netty.channel.ChannelHandlerContext, io.netty.channel.ChannelPromise);
    Code:
       0: aload_1
       1: invokeinterface #6,  1            // InterfaceMethod io/netty/channel/ChannelHandlerContext.alloc:()Lio/netty/buffer/ByteBufAllocator;
       6: aload_0
       7: getfield      #2                  // Field data:Ljava/lang/String;
      10: invokestatic  #7                  // Method io/netty/buffer/ByteBufUtil.writeUtf8:(Lio/netty/buffer/ByteBufAllocator;Ljava/lang/CharSequence;)Lio/netty/buffer/ByteBuf;
      13: astore_3
      14: aload_1
      15: new           #8                  // class io/netty/handler/codec/http2/DefaultHttp2DataFrame
      18: dup
      19: aload_3
      20: aload_0
      21: getfield      #3                  // Field endStream:Z
      24: invokespecial #9                  // Method io/netty/handler/codec/http2/DefaultHttp2DataFrame."<init>":(Lio/netty/buffer/ByteBuf;Z)V
      27: aload_2
      28: invokeinterface #10,  3           // InterfaceMethod io/netty/channel/ChannelHandlerContext.write:(Ljava/lang/Object;Lio/netty/channel/ChannelPromise;)Lio/netty/channel/ChannelFuture;
      33: pop
      34: return
}
