Compiled from "BodyParameterProcessor.java"
public class org.apache.dubbo.metadata.rest.jaxrs.BodyParameterProcessor extends org.apache.dubbo.metadata.rest.AbstractAnnotatedMethodParameterProcessor {
  public org.apache.dubbo.metadata.rest.jaxrs.BodyParameterProcessor();
    Code:
       0: aload_0
       1: invokespecial #2                  // Method org/apache/dubbo/metadata/rest/AbstractAnnotatedMethodParameterProcessor."<init>":()V
       4: return

  public java.lang.String getAnnotationName();
    Code:
       0: ldc           #3                  // String org.jboss.resteasy.annotations.Body
       2: areturn

  public void process(java.lang.annotation.Annotation, java.lang.reflect.Parameter, int, java.lang.reflect.Method, java.lang.Class<?>, java.lang.Class<?>, org.apache.dubbo.metadata.rest.RestMethodMetadata);
    Code:
       0: iload_3
       1: aload_2
       2: invokestatic  #4                  // Method org/apache/dubbo/metadata/rest/ArgInfo.build:(ILjava/lang/reflect/Parameter;)Lorg/apache/dubbo/metadata/rest/ArgInfo;
       5: aload_0
       6: invokevirtual #5                  // Method getAnnotationClass:()Ljava/lang/Class;
       9: invokevirtual #6                  // Method org/apache/dubbo/metadata/rest/ArgInfo.setParamAnnotationType:(Ljava/lang/Class;)Lorg/apache/dubbo/metadata/rest/ArgInfo;
      12: astore        8
      14: aload         7
      16: aload         8
      18: invokevirtual #7                  // Method org/apache/dubbo/metadata/rest/RestMethodMetadata.addArgInfo:(Lorg/apache/dubbo/metadata/rest/ArgInfo;)V
      21: return
}
