Compiled from "DefaultValueParameterProcessor.java"
public class org.apache.dubbo.metadata.rest.jaxrs.DefaultValueParameterProcessor extends org.apache.dubbo.metadata.rest.AbstractAnnotatedMethodParameterProcessor {
  public org.apache.dubbo.metadata.rest.jaxrs.DefaultValueParameterProcessor();
    Code:
       0: aload_0
       1: invokespecial #2                  // Method org/apache/dubbo/metadata/rest/AbstractAnnotatedMethodParameterProcessor."<init>":()V
       4: return

  public java.lang.String getAnnotationName();
    Code:
       0: ldc           #3                  // String javax.ws.rs.DefaultValue
       2: areturn

  protected void process(java.lang.String, java.lang.String, java.lang.annotation.Annotation, java.lang.reflect.Parameter, int, java.lang.reflect.Method, org.apache.dubbo.metadata.rest.RestMethodMetadata);
    Code:
       0: aload         7
       2: invokevirtual #4                  // Method org/apache/dubbo/metadata/rest/RestMethodMetadata.getRequest:()Lorg/apache/dubbo/metadata/rest/RequestMetadata;
       5: astore        8
       7: aload_0
       8: aload         8
      10: invokevirtual #5                  // Method org/apache/dubbo/metadata/rest/RequestMetadata.getParams:()Ljava/util/Map;
      13: aload_2
      14: aload_1
      15: invokespecial #6                  // Method setDefaultValue:(Ljava/util/Map;Ljava/lang/String;Ljava/lang/String;)V
      18: aload_0
      19: aload         8
      21: invokevirtual #7                  // Method org/apache/dubbo/metadata/rest/RequestMetadata.getHeaders:()Ljava/util/Map;
      24: aload_2
      25: aload_1
      26: invokespecial #6                  // Method setDefaultValue:(Ljava/util/Map;Ljava/lang/String;Ljava/lang/String;)V
      29: return

  private void setDefaultValue(java.util.Map<java.lang.String, java.util.List<java.lang.String>>, java.lang.String, java.lang.String);
    Code:
       0: aload_1
       1: invokeinterface #8,  1            // InterfaceMethod java/util/Map.entrySet:()Ljava/util/Set;
       6: invokeinterface #9,  1            // InterfaceMethod java/util/Set.iterator:()Ljava/util/Iterator;
      11: astore        4
      13: aload         4
      15: invokeinterface #10,  1           // InterfaceMethod java/util/Iterator.hasNext:()Z
      20: ifeq          112
      23: aload         4
      25: invokeinterface #11,  1           // InterfaceMethod java/util/Iterator.next:()Ljava/lang/Object;
      30: checkcast     #12                 // class java/util/Map$Entry
      33: astore        5
      35: aload         5
      37: invokeinterface #13,  1           // InterfaceMethod java/util/Map$Entry.getValue:()Ljava/lang/Object;
      42: checkcast     #14                 // class java/util/List
      45: astore        6
      47: aload         6
      49: invokeinterface #15,  1           // InterfaceMethod java/util/List.size:()I
      54: istore        7
      56: iconst_0
      57: istore        8
      59: iload         8
      61: iload         7
      63: if_icmpge     109
      66: aload         6
      68: iload         8
      70: invokeinterface #16,  2           // InterfaceMethod java/util/List.get:(I)Ljava/lang/Object;
      75: checkcast     #17                 // class java/lang/String
      78: astore        9
      80: aload_2
      81: aload         9
      83: invokevirtual #18                 // Method java/lang/String.equals:(Ljava/lang/Object;)Z
      86: ifeq          103
      89: aload         6
      91: iload         8
      93: aload_3
      94: invokeinterface #19,  3           // InterfaceMethod java/util/List.set:(ILjava/lang/Object;)Ljava/lang/Object;
      99: pop
     100: goto          112
     103: iinc          8, 1
     106: goto          59
     109: goto          13
     112: return

  public int getPriority();
    Code:
       0: ldc           #21                 // int 2147483647
       2: ireturn
}
