Compiled from "HeaderParamParameterProcessor.java"
public class org.apache.dubbo.metadata.rest.jaxrs.HeaderParamParameterProcessor extends org.apache.dubbo.metadata.rest.AbstractAnnotatedMethodParameterProcessor {
  public org.apache.dubbo.metadata.rest.jaxrs.HeaderParamParameterProcessor();
    Code:
       0: aload_0
       1: invokespecial #2                  // Method org/apache/dubbo/metadata/rest/AbstractAnnotatedMethodParameterProcessor."<init>":()V
       4: return

  public java.lang.String getAnnotationName();
    Code:
       0: ldc           #3                  // String javax.ws.rs.HeaderParam
       2: areturn

  protected void process(java.lang.String, java.lang.String, java.lang.annotation.Annotation, java.lang.reflect.Parameter, int, java.lang.reflect.Method, org.apache.dubbo.metadata.rest.RestMethodMetadata);
    Code:
       0: aload         7
       2: invokevirtual #4                  // Method org/apache/dubbo/metadata/rest/RestMethodMetadata.getRequest:()Lorg/apache/dubbo/metadata/rest/RequestMetadata;
       5: astore        8
       7: aload         8
       9: aload_1
      10: iload         5
      12: invokestatic  #5                  // InterfaceMethod org/apache/dubbo/metadata/rest/AnnotatedMethodParameterProcessor.buildDefaultValue:(I)Ljava/lang/String;
      15: invokevirtual #6                  // Method org/apache/dubbo/metadata/rest/RequestMetadata.addHeader:(Ljava/lang/String;Ljava/lang/String;)Lorg/apache/dubbo/metadata/rest/RequestMetadata;
      18: pop
      19: return
}
