Compiled from "JAXRSServiceRestMetadataResolver.java"
public class org.apache.dubbo.metadata.rest.jaxrs.JAXRSServiceRestMetadataResolver extends org.apache.dubbo.metadata.rest.AbstractServiceRestMetadataResolver {
  public org.apache.dubbo.metadata.rest.jaxrs.JAXRSServiceRestMetadataResolver(org.apache.dubbo.rpc.model.ApplicationModel);
    Code:
       0: aload_0
       1: aload_1
       2: invokespecial #2                  // Method org/apache/dubbo/metadata/rest/AbstractServiceRestMetadataResolver."<init>":(Lorg/apache/dubbo/rpc/model/ApplicationModel;)V
       5: return

  protected boolean supports0(java.lang.Class<?>);
    Code:
       0: aload_1
       1: ldc           #3                  // String javax.ws.rs.Path
       3: invokestatic  #4                  // InterfaceMethod org/apache/dubbo/common/utils/AnnotationUtils.isAnnotationPresent:(Ljava/lang/reflect/AnnotatedElement;Ljava/lang/String;)Z
       6: ireturn

  protected boolean isRestCapableMethod(java.lang.reflect.Method, java.lang.Class<?>, java.lang.Class<?>);
    Code:
       0: aload_1
       1: ldc           #5                  // String javax.ws.rs.HttpMethod
       3: invokestatic  #4                  // InterfaceMethod org/apache/dubbo/common/utils/AnnotationUtils.isAnnotationPresent:(Ljava/lang/reflect/AnnotatedElement;Ljava/lang/String;)Z
       6: ireturn

  protected java.lang.String resolveRequestMethod(java.lang.reflect.Method, java.lang.Class<?>, java.lang.Class<?>);
    Code:
       0: aload_1
       1: ldc           #5                  // String javax.ws.rs.HttpMethod
       3: invokestatic  #6                  // InterfaceMethod org/apache/dubbo/common/utils/AnnotationUtils.findMetaAnnotation:(Ljava/lang/reflect/AnnotatedElement;Ljava/lang/String;)Ljava/lang/annotation/Annotation;
       6: astore        4
       8: aload         4
      10: invokestatic  #7                  // InterfaceMethod org/apache/dubbo/common/utils/AnnotationUtils.getValue:(Ljava/lang/annotation/Annotation;)Ljava/lang/Object;
      13: checkcast     #8                  // class java/lang/String
      16: areturn

  protected java.lang.String resolveRequestPath(java.lang.reflect.Method, java.lang.Class<?>, java.lang.Class<?>);
    Code:
       0: aload_0
       1: aload_2
       2: aload_3
       3: invokespecial #9                  // Method resolveRequestPathFromType:(Ljava/lang/Class;Ljava/lang/Class;)Ljava/lang/String;
       6: astore        4
       8: aload_0
       9: aload_1
      10: invokespecial #10                 // Method resolveRequestPathFromMethod:(Ljava/lang/reflect/Method;)Ljava/lang/String;
      13: astore        5
      15: aload         4
      17: iconst_1
      18: anewarray     #8                  // class java/lang/String
      21: dup
      22: iconst_0
      23: aload         5
      25: aastore
      26: invokestatic  #11                 // InterfaceMethod org/apache/dubbo/common/utils/PathUtils.buildPath:(Ljava/lang/String;[Ljava/lang/String;)Ljava/lang/String;
      29: areturn

  private java.lang.String resolveRequestPathFromType(java.lang.Class<?>, java.lang.Class<?>);
    Code:
       0: aload_1
       1: ldc           #3                  // String javax.ws.rs.Path
       3: invokestatic  #12                 // InterfaceMethod org/apache/dubbo/common/utils/AnnotationUtils.findAnnotation:(Ljava/lang/reflect/AnnotatedElement;Ljava/lang/String;)Ljava/lang/annotation/Annotation;
       6: astore_3
       7: aload_3
       8: ifnonnull     18
      11: aload_2
      12: ldc           #3                  // String javax.ws.rs.Path
      14: invokestatic  #12                 // InterfaceMethod org/apache/dubbo/common/utils/AnnotationUtils.findAnnotation:(Ljava/lang/reflect/AnnotatedElement;Ljava/lang/String;)Ljava/lang/annotation/Annotation;
      17: astore_3
      18: aload_3
      19: invokestatic  #7                  // InterfaceMethod org/apache/dubbo/common/utils/AnnotationUtils.getValue:(Ljava/lang/annotation/Annotation;)Ljava/lang/Object;
      22: checkcast     #8                  // class java/lang/String
      25: areturn

  private java.lang.String resolveRequestPathFromMethod(java.lang.reflect.Method);
    Code:
       0: aload_1
       1: ldc           #3                  // String javax.ws.rs.Path
       3: invokestatic  #12                 // InterfaceMethod org/apache/dubbo/common/utils/AnnotationUtils.findAnnotation:(Ljava/lang/reflect/AnnotatedElement;Ljava/lang/String;)Ljava/lang/annotation/Annotation;
       6: astore_2
       7: aload_2
       8: invokestatic  #7                  // InterfaceMethod org/apache/dubbo/common/utils/AnnotationUtils.getValue:(Ljava/lang/annotation/Annotation;)Ljava/lang/Object;
      11: checkcast     #8                  // class java/lang/String
      14: areturn

  protected void processProduces(java.lang.reflect.Method, java.lang.Class<?>, java.lang.Class<?>, java.util.Set<java.lang.String>);
    Code:
       0: aload_0
       1: aload_1
       2: ldc           #13                 // String javax.ws.rs.Produces
       4: aload         4
       6: invokespecial #14                 // Method addAnnotationValues:(Ljava/lang/reflect/Method;Ljava/lang/String;Ljava/util/Set;)V
       9: aload_0
      10: aload_2
      11: ldc           #13                 // String javax.ws.rs.Produces
      13: aload         4
      15: invokespecial #15                 // Method addAnnotationValues:(Ljava/lang/Class;Ljava/lang/String;Ljava/util/Set;)V
      18: aload_0
      19: aload_3
      20: ldc           #13                 // String javax.ws.rs.Produces
      22: aload         4
      24: invokespecial #15                 // Method addAnnotationValues:(Ljava/lang/Class;Ljava/lang/String;Ljava/util/Set;)V
      27: return

  protected void processConsumes(java.lang.reflect.Method, java.lang.Class<?>, java.lang.Class<?>, java.util.Set<java.lang.String>);
    Code:
       0: aload_0
       1: aload_1
       2: ldc           #16                 // String javax.ws.rs.Consumes
       4: aload         4
       6: invokespecial #14                 // Method addAnnotationValues:(Ljava/lang/reflect/Method;Ljava/lang/String;Ljava/util/Set;)V
       9: aload_0
      10: aload_2
      11: ldc           #16                 // String javax.ws.rs.Consumes
      13: aload         4
      15: invokespecial #15                 // Method addAnnotationValues:(Ljava/lang/Class;Ljava/lang/String;Ljava/util/Set;)V
      18: aload_0
      19: aload_3
      20: ldc           #16                 // String javax.ws.rs.Consumes
      22: aload         4
      24: invokespecial #15                 // Method addAnnotationValues:(Ljava/lang/Class;Ljava/lang/String;Ljava/util/Set;)V
      27: return

  private void addAnnotationValues(java.lang.reflect.Method, java.lang.String, java.util.Set<java.lang.String>);
    Code:
       0: aload_1
       1: aload_2
       2: invokestatic  #12                 // InterfaceMethod org/apache/dubbo/common/utils/AnnotationUtils.findAnnotation:(Ljava/lang/reflect/AnnotatedElement;Ljava/lang/String;)Ljava/lang/annotation/Annotation;
       5: astore        4
       7: aload         4
       9: invokestatic  #7                  // InterfaceMethod org/apache/dubbo/common/utils/AnnotationUtils.getValue:(Ljava/lang/annotation/Annotation;)Ljava/lang/Object;
      12: checkcast     #17                 // class "[Ljava/lang/String;"
      15: astore        5
      17: aload         5
      19: ifnull        43
      22: aload         5
      24: invokestatic  #18                 // InterfaceMethod java/util/stream/Stream.of:([Ljava/lang/Object;)Ljava/util/stream/Stream;
      27: aload_3
      28: dup
      29: invokevirtual #19                 // Method java/lang/Object.getClass:()Ljava/lang/Class;
      32: pop
      33: invokedynamic #20,  0             // InvokeDynamic #0:accept:(Ljava/util/Set;)Ljava/util/function/Consumer;
      38: invokeinterface #21,  2           // InterfaceMethod java/util/stream/Stream.forEach:(Ljava/util/function/Consumer;)V
      43: return

  private void addAnnotationValues(java.lang.Class, java.lang.String, java.util.Set<java.lang.String>);
    Code:
       0: aload_1
       1: aload_2
       2: invokestatic  #12                 // InterfaceMethod org/apache/dubbo/common/utils/AnnotationUtils.findAnnotation:(Ljava/lang/reflect/AnnotatedElement;Ljava/lang/String;)Ljava/lang/annotation/Annotation;
       5: astore        4
       7: aload         4
       9: invokestatic  #7                  // InterfaceMethod org/apache/dubbo/common/utils/AnnotationUtils.getValue:(Ljava/lang/annotation/Annotation;)Ljava/lang/Object;
      12: checkcast     #17                 // class "[Ljava/lang/String;"
      15: astore        5
      17: aload         5
      19: ifnull        43
      22: aload         5
      24: invokestatic  #18                 // InterfaceMethod java/util/stream/Stream.of:([Ljava/lang/Object;)Ljava/util/stream/Stream;
      27: aload_3
      28: dup
      29: invokevirtual #19                 // Method java/lang/Object.getClass:()Ljava/lang/Class;
      32: pop
      33: invokedynamic #20,  0             // InvokeDynamic #0:accept:(Ljava/util/Set;)Ljava/util/function/Consumer;
      38: invokeinterface #21,  2           // InterfaceMethod java/util/stream/Stream.forEach:(Ljava/util/function/Consumer;)V
      43: return
}
