Compiled from "ParamAnnotationParameterProcessor.java"
public abstract class org.apache.dubbo.metadata.rest.jaxrs.ParamAnnotationParameterProcessor extends org.apache.dubbo.metadata.rest.AbstractAnnotatedMethodParameterProcessor {
  public org.apache.dubbo.metadata.rest.jaxrs.ParamAnnotationParameterProcessor();
    Code:
       0: aload_0
       1: invokespecial #1                  // Method org/apache/dubbo/metadata/rest/AbstractAnnotatedMethodParameterProcessor."<init>":()V
       4: return

  protected void process(java.lang.String, java.lang.String, java.lang.annotation.Annotation, java.lang.reflect.Parameter, int, java.lang.reflect.Method, org.apache.dubbo.metadata.rest.RestMethodMetadata);
    Code:
       0: aload         7
       2: invokevirtual #2                  // Method org/apache/dubbo/metadata/rest/RestMethodMetadata.getRequest:()Lorg/apache/dubbo/metadata/rest/RequestMetadata;
       5: astore        8
       7: aload         8
       9: aload_1
      10: aload_2
      11: invokevirtual #3                  // Method org/apache/dubbo/metadata/rest/RequestMetadata.addParam:(Ljava/lang/String;Ljava/lang/String;)Lorg/apache/dubbo/metadata/rest/RequestMetadata;
      14: pop
      15: return
}
