Compiled from "ParentContextCloserApplicationListener.java"
public class org.springframework.boot.builder.ParentContextCloserApplicationListener$ContextCloserListener implements org.springframework.context.ApplicationListener<org.springframework.context.event.ContextClosedEvent> {
  private final java.lang.ref.WeakReference<org.springframework.context.ConfigurableApplicationContext> childContext;

  public org.springframework.boot.builder.ParentContextCloserApplicationListener$ContextCloserListener(org.springframework.context.ConfigurableApplicationContext);
    Code:
       0: aload_0
       1: invokespecial #1                  // Method java/lang/Object."<init>":()V
       4: aload_0
       5: new           #7                  // class java/lang/ref/WeakReference
       8: dup
       9: aload_1
      10: invokespecial #9                  // Method java/lang/ref/WeakReference."<init>":(Ljava/lang/Object;)V
      13: putfield      #12                 // Field childContext:Ljava/lang/ref/WeakReference;
      16: return

  public void onApplicationEvent(org.springframework.context.event.ContextClosedEvent);
    Code:
       0: aload_0
       1: getfield      #12                 // Field childContext:Ljava/lang/ref/WeakReference;
       4: invokevirtual #18                 // Method java/lang/ref/WeakReference.get:()Ljava/lang/Object;
       7: checkcast     #22                 // class org/springframework/context/ConfigurableApplicationContext
      10: astore_2
      11: aload_2
      12: ifnull        43
      15: aload_1
      16: invokevirtual #24                 // Method org/springframework/context/event/ContextClosedEvent.getApplicationContext:()Lorg/springframework/context/ApplicationContext;
      19: aload_2
      20: invokeinterface #30,  1           // InterfaceMethod org/springframework/context/ConfigurableApplicationContext.getParent:()Lorg/springframework/context/ApplicationContext;
      25: if_acmpne     43
      28: aload_2
      29: invokeinterface #33,  1           // InterfaceMethod org/springframework/context/ConfigurableApplicationContext.isActive:()Z
      34: ifeq          43
      37: aload_2
      38: invokeinterface #37,  1           // InterfaceMethod org/springframework/context/ConfigurableApplicationContext.close:()V
      43: return

  public boolean equals(java.lang.Object);
    Code:
       0: aload_0
       1: aload_1
       2: if_acmpne     7
       5: iconst_1
       6: ireturn
       7: aload_1
       8: ifnonnull     13
      11: iconst_0
      12: ireturn
      13: aload_1
      14: instanceof    #13                 // class org/springframework/boot/builder/ParentContextCloserApplicationListener$ContextCloserListener
      17: ifeq          43
      20: aload_1
      21: checkcast     #13                 // class org/springframework/boot/builder/ParentContextCloserApplicationListener$ContextCloserListener
      24: astore_2
      25: aload_0
      26: getfield      #12                 // Field childContext:Ljava/lang/ref/WeakReference;
      29: invokevirtual #18                 // Method java/lang/ref/WeakReference.get:()Ljava/lang/Object;
      32: aload_2
      33: getfield      #12                 // Field childContext:Ljava/lang/ref/WeakReference;
      36: invokevirtual #18                 // Method java/lang/ref/WeakReference.get:()Ljava/lang/Object;
      39: invokestatic  #40                 // Method org/springframework/util/ObjectUtils.nullSafeEquals:(Ljava/lang/Object;Ljava/lang/Object;)Z
      42: ireturn
      43: aload_0
      44: aload_1
      45: invokespecial #46                 // Method java/lang/Object.equals:(Ljava/lang/Object;)Z
      48: ireturn

  public int hashCode();
    Code:
       0: aload_0
       1: getfield      #12                 // Field childContext:Ljava/lang/ref/WeakReference;
       4: invokevirtual #18                 // Method java/lang/ref/WeakReference.get:()Ljava/lang/Object;
       7: invokestatic  #50                 // Method org/springframework/util/ObjectUtils.nullSafeHashCode:(Ljava/lang/Object;)I
      10: ireturn

  public void onApplicationEvent(org.springframework.context.ApplicationEvent);
    Code:
       0: aload_0
       1: aload_1
       2: checkcast     #25                 // class org/springframework/context/event/ContextClosedEvent
       5: invokevirtual #54                 // Method onApplicationEvent:(Lorg/springframework/context/event/ContextClosedEvent;)V
       8: return
}
