Compiled from "ParentContextCloserApplicationListener.java"
public class org.springframework.boot.builder.ParentContextCloserApplicationListener implements org.springframework.context.ApplicationListener<org.springframework.boot.builder.ParentContextApplicationContextInitializer$ParentContextAvailableEvent>, org.springframework.context.ApplicationContextAware, org.springframework.core.Ordered {
  private final int order;

  private org.springframework.context.ApplicationContext context;

  public org.springframework.boot.builder.ParentContextCloserApplicationListener();
    Code:
       0: aload_0
       1: invokespecial #1                  // Method java/lang/Object."<init>":()V
       4: aload_0
       5: ldc           #9                  // int 2147483637
       7: putfield      #10                 // Field order:I
      10: return

  public int getOrder();
    Code:
       0: aload_0
       1: invokestatic  #16                 // Method java/util/Objects.requireNonNull:(Ljava/lang/Object;)Ljava/lang/Object;
       4: pop
       5: ldc           #9                  // int 2147483637
       7: ireturn

  public void setApplicationContext(org.springframework.context.ApplicationContext) throws org.springframework.beans.BeansException;
    Code:
       0: aload_0
       1: aload_1
       2: putfield      #22                 // Field context:Lorg/springframework/context/ApplicationContext;
       5: return

  public void onApplicationEvent(org.springframework.boot.builder.ParentContextApplicationContextInitializer$ParentContextAvailableEvent);
    Code:
       0: aload_0
       1: aload_1
       2: invokevirtual #26                 // Method org/springframework/boot/builder/ParentContextApplicationContextInitializer$ParentContextAvailableEvent.getApplicationContext:()Lorg/springframework/context/ConfigurableApplicationContext;
       5: invokevirtual #32                 // Method maybeInstallListenerInParent:(Lorg/springframework/context/ConfigurableApplicationContext;)V
       8: return

  private void maybeInstallListenerInParent(org.springframework.context.ConfigurableApplicationContext);
    Code:
       0: aload_1
       1: aload_0
       2: getfield      #22                 // Field context:Lorg/springframework/context/ApplicationContext;
       5: if_acmpne     38
       8: aload_1
       9: invokeinterface #36,  1           // InterfaceMethod org/springframework/context/ConfigurableApplicationContext.getParent:()Lorg/springframework/context/ApplicationContext;
      14: astore_3
      15: aload_3
      16: instanceof    #37                 // class org/springframework/context/ConfigurableApplicationContext
      19: ifeq          38
      22: aload_3
      23: checkcast     #37                 // class org/springframework/context/ConfigurableApplicationContext
      26: astore_2
      27: aload_2
      28: aload_0
      29: aload_1
      30: invokevirtual #42                 // Method createContextCloserListener:(Lorg/springframework/context/ConfigurableApplicationContext;)Lorg/springframework/boot/builder/ParentContextCloserApplicationListener$ContextCloserListener;
      33: invokeinterface #46,  2           // InterfaceMethod org/springframework/context/ConfigurableApplicationContext.addApplicationListener:(Lorg/springframework/context/ApplicationListener;)V
      38: return

  protected org.springframework.boot.builder.ParentContextCloserApplicationListener$ContextCloserListener createContextCloserListener(org.springframework.context.ConfigurableApplicationContext);
    Code:
       0: new           #50                 // class org/springframework/boot/builder/ParentContextCloserApplicationListener$ContextCloserListener
       3: dup
       4: aload_1
       5: invokespecial #52                 // Method org/springframework/boot/builder/ParentContextCloserApplicationListener$ContextCloserListener."<init>":(Lorg/springframework/context/ConfigurableApplicationContext;)V
       8: areturn

  public void onApplicationEvent(org.springframework.context.ApplicationEvent);
    Code:
       0: aload_0
       1: aload_1
       2: checkcast     #27                 // class org/springframework/boot/builder/ParentContextApplicationContextInitializer$ParentContextAvailableEvent
       5: invokevirtual #54                 // Method onApplicationEvent:(Lorg/springframework/boot/builder/ParentContextApplicationContextInitializer$ParentContextAvailableEvent;)V
       8: return
}
