Compiled from "Exporter.java"
public class com.alibaba.dubbo.rpc.Exporter$CompatibleExporter<T> implements com.alibaba.dubbo.rpc.Exporter<T> {
  private org.apache.dubbo.rpc.Exporter<T> delegate;

  public com.alibaba.dubbo.rpc.Exporter$CompatibleExporter(org.apache.dubbo.rpc.Exporter<T>);
    Code:
       0: aload_0
       1: invokespecial #1                  // Method java/lang/Object."<init>":()V
       4: aload_0
       5: aload_1
       6: putfield      #2                  // Field delegate:Lorg/apache/dubbo/rpc/Exporter;
       9: return

  public com.alibaba.dubbo.rpc.Invoker<T> getInvoker();
    Code:
       0: new           #3                  // class com/alibaba/dubbo/rpc/Invoker$CompatibleInvoker
       3: dup
       4: aload_0
       5: getfield      #2                  // Field delegate:Lorg/apache/dubbo/rpc/Exporter;
       8: invokeinterface #4,  1            // InterfaceMethod org/apache/dubbo/rpc/Exporter.getInvoker:()Lorg/apache/dubbo/rpc/Invoker;
      13: invokespecial #5                  // Method com/alibaba/dubbo/rpc/Invoker$CompatibleInvoker."<init>":(Lorg/apache/dubbo/rpc/Invoker;)V
      16: areturn

  public void unexport();
    Code:
       0: aload_0
       1: getfield      #2                  // Field delegate:Lorg/apache/dubbo/rpc/Exporter;
       4: invokeinterface #6,  1            // InterfaceMethod org/apache/dubbo/rpc/Exporter.unexport:()V
       9: return

  public void unregister();
    Code:
       0: aload_0
       1: getfield      #2                  // Field delegate:Lorg/apache/dubbo/rpc/Exporter;
       4: invokeinterface #7,  1            // InterfaceMethod org/apache/dubbo/rpc/Exporter.unregister:()V
       9: return

  public org.apache.dubbo.rpc.Invoker getInvoker();
    Code:
       0: aload_0
       1: invokevirtual #8                  // Method getInvoker:()Lcom/alibaba/dubbo/rpc/Invoker;
       4: areturn
}
