Compiled from "Filter.java"
public interface com.alibaba.dubbo.rpc.Filter extends org.apache.dubbo.rpc.Filter {
  public abstract com.alibaba.dubbo.rpc.Result invoke(com.alibaba.dubbo.rpc.Invoker<?>, com.alibaba.dubbo.rpc.Invocation) throws com.alibaba.dubbo.rpc.RpcException;

  public default org.apache.dubbo.rpc.Result invoke(org.apache.dubbo.rpc.Invoker<?>, org.apache.dubbo.rpc.Invocation) throws org.apache.dubbo.rpc.RpcException;
    Code:
       0: aload_0
       1: new           #1                  // class com/alibaba/dubbo/rpc/Invoker$CompatibleInvoker
       4: dup
       5: aload_1
       6: invokespecial #2                  // Method com/alibaba/dubbo/rpc/Invoker$CompatibleInvoker."<init>":(Lorg/apache/dubbo/rpc/Invoker;)V
       9: new           #3                  // class com/alibaba/dubbo/rpc/Invocation$CompatibleInvocation
      12: dup
      13: aload_2
      14: invokespecial #4                  // Method com/alibaba/dubbo/rpc/Invocation$CompatibleInvocation."<init>":(Lorg/apache/dubbo/rpc/Invocation;)V
      17: invokeinterface #5,  3            // InterfaceMethod invoke:(Lcom/alibaba/dubbo/rpc/Invoker;Lcom/alibaba/dubbo/rpc/Invocation;)Lcom/alibaba/dubbo/rpc/Result;
      22: astore_3
      23: aload_3
      24: instanceof    #6                  // class com/alibaba/dubbo/rpc/Result$CompatibleResult
      27: ifeq          32
      30: aload_3
      31: areturn
      32: aload_2
      33: invokestatic  #7                  // Method org/apache/dubbo/rpc/AsyncRpcResult.newDefaultAsyncResult:(Lorg/apache/dubbo/rpc/Invocation;)Lorg/apache/dubbo/rpc/AsyncRpcResult;
      36: astore        4
      38: aload         4
      40: aload_3
      41: invokeinterface #8,  1            // InterfaceMethod com/alibaba/dubbo/rpc/Result.getValue:()Ljava/lang/Object;
      46: invokevirtual #9                  // Method org/apache/dubbo/rpc/AsyncRpcResult.setValue:(Ljava/lang/Object;)V
      49: aload         4
      51: aload_3
      52: invokeinterface #10,  1           // InterfaceMethod com/alibaba/dubbo/rpc/Result.getException:()Ljava/lang/Throwable;
      57: invokevirtual #11                 // Method org/apache/dubbo/rpc/AsyncRpcResult.setException:(Ljava/lang/Throwable;)V
      60: aload         4
      62: aload_3
      63: invokeinterface #12,  1           // InterfaceMethod com/alibaba/dubbo/rpc/Result.getObjectAttachments:()Ljava/util/Map;
      68: invokevirtual #13                 // Method org/apache/dubbo/rpc/AsyncRpcResult.setObjectAttachments:(Ljava/util/Map;)V
      71: aload         4
      73: areturn
}
