Compiled from "Invocation.java"
public interface com.alibaba.dubbo.rpc.Invocation extends org.apache.dubbo.rpc.Invocation {
  public abstract com.alibaba.dubbo.rpc.Invoker<?> getInvoker();

  public default org.apache.dubbo.rpc.Invocation getOriginal();
    Code:
       0: aconst_null
       1: areturn

  public default void setAttachment(java.lang.String, java.lang.String);
    Code:
       0: aload_0
       1: aload_1
       2: aload_2
       3: invokeinterface #1,  3            // InterfaceMethod setObjectAttachment:(Ljava/lang/String;Ljava/lang/Object;)V
       8: return

  public default void setAttachmentIfAbsent(java.lang.String, java.lang.String);
    Code:
       0: aload_0
       1: aload_1
       2: aload_2
       3: invokeinterface #2,  3            // InterfaceMethod setObjectAttachmentIfAbsent:(Ljava/lang/String;Ljava/lang/Object;)V
       8: return

  public default void setObjectAttachmentIfAbsent(java.lang.String, java.lang.Object);
    Code:
       0: return

  public default void setObjectAttachment(java.lang.String, java.lang.Object);
    Code:
       0: return

  public default void setAttachment(java.lang.String, java.lang.Object);
    Code:
       0: aload_0
       1: aload_1
       2: aload_2
       3: invokeinterface #1,  3            // InterfaceMethod setObjectAttachment:(Ljava/lang/String;Ljava/lang/Object;)V
       8: return

  public default void setAttachmentIfAbsent(java.lang.String, java.lang.Object);
    Code:
       0: aload_0
       1: aload_1
       2: aload_2
       3: invokeinterface #2,  3            // InterfaceMethod setObjectAttachmentIfAbsent:(Ljava/lang/String;Ljava/lang/Object;)V
       8: return

  public default java.lang.String getServiceName();
    Code:
       0: aconst_null
       1: areturn

  public default java.lang.String getTargetServiceUniqueName();
    Code:
       0: aconst_null
       1: areturn

  public default java.lang.String getAttachment(java.lang.String, java.lang.String);
    Code:
       0: aconst_null
       1: areturn

  public default void setServiceModel(org.apache.dubbo.rpc.model.ServiceModel);
    Code:
       0: return

  public default org.apache.dubbo.rpc.model.ServiceModel getServiceModel();
    Code:
       0: aconst_null
       1: areturn

  public default java.lang.Object put(java.lang.Object, java.lang.Object);
    Code:
       0: aconst_null
       1: areturn

  public default java.lang.Object get(java.lang.Object);
    Code:
       0: aconst_null
       1: areturn

  public default java.util.Map<java.lang.Object, java.lang.Object> getAttributes();
    Code:
       0: aconst_null
       1: areturn

  public default java.util.Map<java.lang.String, java.lang.Object> getObjectAttachments();
    Code:
       0: invokestatic  #3                  // Method java/util/Collections.emptyMap:()Ljava/util/Map;
       3: areturn

  public default java.util.Map<java.lang.String, java.lang.Object> copyObjectAttachments();
    Code:
       0: new           #4                  // class java/util/HashMap
       3: dup
       4: aload_0
       5: invokeinterface #5,  1            // InterfaceMethod getObjectAttachments:()Ljava/util/Map;
      10: invokespecial #6                  // Method java/util/HashMap."<init>":(Ljava/util/Map;)V
      13: areturn

  public default void foreachAttachment(java.util.function.Consumer<java.util.Map$Entry<java.lang.String, java.lang.Object>>);
    Code:
       0: aload_0
       1: invokeinterface #5,  1            // InterfaceMethod getObjectAttachments:()Ljava/util/Map;
       6: invokeinterface #7,  1            // InterfaceMethod java/util/Map.entrySet:()Ljava/util/Set;
      11: aload_1
      12: invokeinterface #8,  2            // InterfaceMethod java/util/Set.forEach:(Ljava/util/function/Consumer;)V
      17: return

  public default java.lang.Object getObjectAttachment(java.lang.String);
    Code:
       0: aconst_null
       1: areturn

  public default java.lang.Object getObjectAttachment(java.lang.String, java.lang.Object);
    Code:
       0: aconst_null
       1: areturn

  public default org.apache.dubbo.rpc.Invoker getInvoker();
    Code:
       0: aload_0
       1: invokeinterface #9,  1            // InterfaceMethod getInvoker:()Lcom/alibaba/dubbo/rpc/Invoker;
       6: areturn
}
