Compiled from "Invocation.java"
public class com.alibaba.dubbo.rpc.Invocation$CompatibleInvocation implements com.alibaba.dubbo.rpc.Invocation {
  private org.apache.dubbo.rpc.Invocation delegate;

  public com.alibaba.dubbo.rpc.Invocation$CompatibleInvocation(org.apache.dubbo.rpc.Invocation);
    Code:
       0: aload_0
       1: invokespecial #1                  // Method java/lang/Object."<init>":()V
       4: aload_0
       5: aload_1
       6: putfield      #2                  // Field delegate:Lorg/apache/dubbo/rpc/Invocation;
       9: return

  public java.lang.String getTargetServiceUniqueName();
    Code:
       0: aload_0
       1: getfield      #2                  // Field delegate:Lorg/apache/dubbo/rpc/Invocation;
       4: invokeinterface #3,  1            // InterfaceMethod org/apache/dubbo/rpc/Invocation.getTargetServiceUniqueName:()Ljava/lang/String;
       9: areturn

  public java.lang.String getProtocolServiceKey();
    Code:
       0: aload_0
       1: getfield      #2                  // Field delegate:Lorg/apache/dubbo/rpc/Invocation;
       4: invokeinterface #4,  1            // InterfaceMethod org/apache/dubbo/rpc/Invocation.getProtocolServiceKey:()Ljava/lang/String;
       9: areturn

  public java.lang.String getMethodName();
    Code:
       0: aload_0
       1: getfield      #2                  // Field delegate:Lorg/apache/dubbo/rpc/Invocation;
       4: invokeinterface #5,  1            // InterfaceMethod org/apache/dubbo/rpc/Invocation.getMethodName:()Ljava/lang/String;
       9: areturn

  public java.lang.String getServiceName();
    Code:
       0: aconst_null
       1: areturn

  public java.lang.Class<?>[] getParameterTypes();
    Code:
       0: aload_0
       1: getfield      #2                  // Field delegate:Lorg/apache/dubbo/rpc/Invocation;
       4: invokeinterface #6,  1            // InterfaceMethod org/apache/dubbo/rpc/Invocation.getParameterTypes:()[Ljava/lang/Class;
       9: areturn

  public java.lang.Object[] getArguments();
    Code:
       0: aload_0
       1: getfield      #2                  // Field delegate:Lorg/apache/dubbo/rpc/Invocation;
       4: invokeinterface #7,  1            // InterfaceMethod org/apache/dubbo/rpc/Invocation.getArguments:()[Ljava/lang/Object;
       9: areturn

  public java.util.Map<java.lang.String, java.lang.String> getAttachments();
    Code:
       0: aload_0
       1: getfield      #2                  // Field delegate:Lorg/apache/dubbo/rpc/Invocation;
       4: invokeinterface #8,  1            // InterfaceMethod org/apache/dubbo/rpc/Invocation.getAttachments:()Ljava/util/Map;
       9: areturn

  public java.lang.String getAttachment(java.lang.String);
    Code:
       0: aload_0
       1: getfield      #2                  // Field delegate:Lorg/apache/dubbo/rpc/Invocation;
       4: aload_1
       5: invokeinterface #9,  2            // InterfaceMethod org/apache/dubbo/rpc/Invocation.getAttachment:(Ljava/lang/String;)Ljava/lang/String;
      10: areturn

  public java.lang.String getAttachment(java.lang.String, java.lang.String);
    Code:
       0: aload_0
       1: getfield      #2                  // Field delegate:Lorg/apache/dubbo/rpc/Invocation;
       4: aload_1
       5: aload_2
       6: invokeinterface #10,  3           // InterfaceMethod org/apache/dubbo/rpc/Invocation.getAttachment:(Ljava/lang/String;Ljava/lang/String;)Ljava/lang/String;
      11: areturn

  public com.alibaba.dubbo.rpc.Invoker<?> getInvoker();
    Code:
       0: new           #11                 // class com/alibaba/dubbo/rpc/Invoker$CompatibleInvoker
       3: dup
       4: aload_0
       5: getfield      #2                  // Field delegate:Lorg/apache/dubbo/rpc/Invocation;
       8: invokeinterface #12,  1           // InterfaceMethod org/apache/dubbo/rpc/Invocation.getInvoker:()Lorg/apache/dubbo/rpc/Invoker;
      13: invokespecial #13                 // Method com/alibaba/dubbo/rpc/Invoker$CompatibleInvoker."<init>":(Lorg/apache/dubbo/rpc/Invoker;)V
      16: areturn

  public void setServiceModel(org.apache.dubbo.rpc.model.ServiceModel);
    Code:
       0: aload_0
       1: getfield      #2                  // Field delegate:Lorg/apache/dubbo/rpc/Invocation;
       4: aload_1
       5: invokeinterface #14,  2           // InterfaceMethod org/apache/dubbo/rpc/Invocation.setServiceModel:(Lorg/apache/dubbo/rpc/model/ServiceModel;)V
      10: return

  public org.apache.dubbo.rpc.model.ServiceModel getServiceModel();
    Code:
       0: aload_0
       1: getfield      #2                  // Field delegate:Lorg/apache/dubbo/rpc/Invocation;
       4: invokeinterface #15,  1           // InterfaceMethod org/apache/dubbo/rpc/Invocation.getServiceModel:()Lorg/apache/dubbo/rpc/model/ServiceModel;
       9: areturn

  public java.lang.Object put(java.lang.Object, java.lang.Object);
    Code:
       0: aload_0
       1: getfield      #2                  // Field delegate:Lorg/apache/dubbo/rpc/Invocation;
       4: aload_1
       5: aload_2
       6: invokeinterface #16,  3           // InterfaceMethod org/apache/dubbo/rpc/Invocation.put:(Ljava/lang/Object;Ljava/lang/Object;)Ljava/lang/Object;
      11: areturn

  public java.lang.Object get(java.lang.Object);
    Code:
       0: aload_0
       1: getfield      #2                  // Field delegate:Lorg/apache/dubbo/rpc/Invocation;
       4: aload_1
       5: invokeinterface #17,  2           // InterfaceMethod org/apache/dubbo/rpc/Invocation.get:(Ljava/lang/Object;)Ljava/lang/Object;
      10: areturn

  public java.util.Map<java.lang.Object, java.lang.Object> getAttributes();
    Code:
       0: aload_0
       1: getfield      #2                  // Field delegate:Lorg/apache/dubbo/rpc/Invocation;
       4: invokeinterface #18,  1           // InterfaceMethod org/apache/dubbo/rpc/Invocation.getAttributes:()Ljava/util/Map;
       9: areturn

  public org.apache.dubbo.rpc.Invocation getOriginal();
    Code:
       0: aload_0
       1: getfield      #2                  // Field delegate:Lorg/apache/dubbo/rpc/Invocation;
       4: areturn

  public void addInvokedInvoker(org.apache.dubbo.rpc.Invoker<?>);
    Code:
       0: aload_0
       1: getfield      #2                  // Field delegate:Lorg/apache/dubbo/rpc/Invocation;
       4: aload_1
       5: invokeinterface #19,  2           // InterfaceMethod org/apache/dubbo/rpc/Invocation.addInvokedInvoker:(Lorg/apache/dubbo/rpc/Invoker;)V
      10: return

  public java.util.List<org.apache.dubbo.rpc.Invoker<?>> getInvokedInvokers();
    Code:
       0: aload_0
       1: getfield      #2                  // Field delegate:Lorg/apache/dubbo/rpc/Invocation;
       4: invokeinterface #20,  1           // InterfaceMethod org/apache/dubbo/rpc/Invocation.getInvokedInvokers:()Ljava/util/List;
       9: areturn

  public org.apache.dubbo.rpc.Invoker getInvoker();
    Code:
       0: aload_0
       1: invokevirtual #21                 // Method getInvoker:()Lcom/alibaba/dubbo/rpc/Invoker;
       4: areturn
}
