Compiled from "InvokerListener.java"
public interface com.alibaba.dubbo.rpc.InvokerListener extends org.apache.dubbo.rpc.InvokerListener {
  public abstract void referred(com.alibaba.dubbo.rpc.Invoker<?>) throws com.alibaba.dubbo.rpc.RpcException;

  public abstract void destroyed(com.alibaba.dubbo.rpc.Invoker<?>);

  public default void referred(org.apache.dubbo.rpc.Invoker<?>) throws org.apache.dubbo.rpc.RpcException;
    Code:
       0: aload_0
       1: new           #1                  // class com/alibaba/dubbo/rpc/Invoker$CompatibleInvoker
       4: dup
       5: aload_1
       6: invokespecial #2                  // Method com/alibaba/dubbo/rpc/Invoker$CompatibleInvoker."<init>":(Lorg/apache/dubbo/rpc/Invoker;)V
       9: invokeinterface #3,  2            // InterfaceMethod referred:(Lcom/alibaba/dubbo/rpc/Invoker;)V
      14: return

  public default void destroyed(org.apache.dubbo.rpc.Invoker<?>);
    Code:
       0: aload_0
       1: new           #1                  // class com/alibaba/dubbo/rpc/Invoker$CompatibleInvoker
       4: dup
       5: aload_1
       6: invokespecial #2                  // Method com/alibaba/dubbo/rpc/Invoker$CompatibleInvoker."<init>":(Lorg/apache/dubbo/rpc/Invoker;)V
       9: invokeinterface #4,  2            // InterfaceMethod destroyed:(Lcom/alibaba/dubbo/rpc/Invoker;)V
      14: return
}
