Compiled from "Invoker.java"
public class com.alibaba.dubbo.rpc.Invoker$CompatibleInvoker<T> implements com.alibaba.dubbo.rpc.Invoker<T> {
  private org.apache.dubbo.rpc.Invoker<T> invoker;

  public com.alibaba.dubbo.rpc.Invoker$CompatibleInvoker(org.apache.dubbo.rpc.Invoker<T>);
    Code:
       0: aload_0
       1: invokespecial #1                  // Method java/lang/Object."<init>":()V
       4: aload_0
       5: aload_1
       6: putfield      #2                  // Field invoker:Lorg/apache/dubbo/rpc/Invoker;
       9: return

  public java.lang.Class<T> getInterface();
    Code:
       0: aload_0
       1: getfield      #2                  // Field invoker:Lorg/apache/dubbo/rpc/Invoker;
       4: invokeinterface #3,  1            // InterfaceMethod org/apache/dubbo/rpc/Invoker.getInterface:()Ljava/lang/Class;
       9: areturn

  public org.apache.dubbo.rpc.Result invoke(org.apache.dubbo.rpc.Invocation) throws org.apache.dubbo.rpc.RpcException;
    Code:
       0: new           #4                  // class com/alibaba/dubbo/rpc/Result$CompatibleResult
       3: dup
       4: aload_0
       5: getfield      #2                  // Field invoker:Lorg/apache/dubbo/rpc/Invoker;
       8: aload_1
       9: invokeinterface #5,  2            // InterfaceMethod org/apache/dubbo/rpc/Invoker.invoke:(Lorg/apache/dubbo/rpc/Invocation;)Lorg/apache/dubbo/rpc/Result;
      14: invokespecial #6                  // Method com/alibaba/dubbo/rpc/Result$CompatibleResult."<init>":(Lorg/apache/dubbo/rpc/Result;)V
      17: areturn

  public com.alibaba.dubbo.rpc.Result invoke(com.alibaba.dubbo.rpc.Invocation) throws com.alibaba.dubbo.rpc.RpcException;
    Code:
       0: aload_0
       1: getfield      #2                  // Field invoker:Lorg/apache/dubbo/rpc/Invoker;
       4: instanceof    #7                  // class com/alibaba/dubbo/rpc/Invoker
       7: ifeq          82
      10: aload_0
      11: getfield      #2                  // Field invoker:Lorg/apache/dubbo/rpc/Invoker;
      14: checkcast     #7                  // class com/alibaba/dubbo/rpc/Invoker
      17: aload_1
      18: invokeinterface #8,  2            // InterfaceMethod com/alibaba/dubbo/rpc/Invoker.invoke:(Lcom/alibaba/dubbo/rpc/Invocation;)Lcom/alibaba/dubbo/rpc/Result;
      23: astore_2
      24: aload_2
      25: instanceof    #4                  // class com/alibaba/dubbo/rpc/Result$CompatibleResult
      28: ifeq          33
      31: aload_2
      32: areturn
      33: aload_1
      34: invokeinterface #9,  1            // InterfaceMethod com/alibaba/dubbo/rpc/Invocation.getOriginal:()Lorg/apache/dubbo/rpc/Invocation;
      39: invokestatic  #10                 // Method org/apache/dubbo/rpc/AsyncRpcResult.newDefaultAsyncResult:(Lorg/apache/dubbo/rpc/Invocation;)Lorg/apache/dubbo/rpc/AsyncRpcResult;
      42: astore_3
      43: aload_3
      44: aload_2
      45: invokeinterface #11,  1           // InterfaceMethod com/alibaba/dubbo/rpc/Result.getValue:()Ljava/lang/Object;
      50: invokevirtual #12                 // Method org/apache/dubbo/rpc/AsyncRpcResult.setValue:(Ljava/lang/Object;)V
      53: aload_3
      54: aload_2
      55: invokeinterface #13,  1           // InterfaceMethod com/alibaba/dubbo/rpc/Result.getException:()Ljava/lang/Throwable;
      60: invokevirtual #14                 // Method org/apache/dubbo/rpc/AsyncRpcResult.setException:(Ljava/lang/Throwable;)V
      63: aload_3
      64: aload_2
      65: invokeinterface #15,  1           // InterfaceMethod com/alibaba/dubbo/rpc/Result.getObjectAttachments:()Ljava/util/Map;
      70: invokevirtual #16                 // Method org/apache/dubbo/rpc/AsyncRpcResult.setObjectAttachments:(Ljava/util/Map;)V
      73: new           #4                  // class com/alibaba/dubbo/rpc/Result$CompatibleResult
      76: dup
      77: aload_3
      78: invokespecial #6                  // Method com/alibaba/dubbo/rpc/Result$CompatibleResult."<init>":(Lorg/apache/dubbo/rpc/Result;)V
      81: areturn
      82: new           #4                  // class com/alibaba/dubbo/rpc/Result$CompatibleResult
      85: dup
      86: aload_0
      87: getfield      #2                  // Field invoker:Lorg/apache/dubbo/rpc/Invoker;
      90: aload_1
      91: invokeinterface #9,  1            // InterfaceMethod com/alibaba/dubbo/rpc/Invocation.getOriginal:()Lorg/apache/dubbo/rpc/Invocation;
      96: invokeinterface #5,  2            // InterfaceMethod org/apache/dubbo/rpc/Invoker.invoke:(Lorg/apache/dubbo/rpc/Invocation;)Lorg/apache/dubbo/rpc/Result;
     101: invokespecial #6                  // Method com/alibaba/dubbo/rpc/Result$CompatibleResult."<init>":(Lorg/apache/dubbo/rpc/Result;)V
     104: areturn

  public com.alibaba.dubbo.common.URL getUrl();
    Code:
       0: new           #17                 // class com/alibaba/dubbo/common/URL
       3: dup
       4: aload_0
       5: getfield      #2                  // Field invoker:Lorg/apache/dubbo/rpc/Invoker;
       8: invokeinterface #18,  1           // InterfaceMethod org/apache/dubbo/rpc/Invoker.getUrl:()Lorg/apache/dubbo/common/URL;
      13: invokespecial #19                 // Method com/alibaba/dubbo/common/URL."<init>":(Lorg/apache/dubbo/common/URL;)V
      16: areturn

  public boolean isAvailable();
    Code:
       0: aload_0
       1: getfield      #2                  // Field invoker:Lorg/apache/dubbo/rpc/Invoker;
       4: invokeinterface #20,  1           // InterfaceMethod org/apache/dubbo/rpc/Invoker.isAvailable:()Z
       9: ireturn

  public void destroy();
    Code:
       0: aload_0
       1: getfield      #2                  // Field invoker:Lorg/apache/dubbo/rpc/Invoker;
       4: invokeinterface #21,  1           // InterfaceMethod org/apache/dubbo/rpc/Invoker.destroy:()V
       9: return

  public org.apache.dubbo.rpc.Invoker<T> getOriginal();
    Code:
       0: aload_0
       1: getfield      #2                  // Field invoker:Lorg/apache/dubbo/rpc/Invoker;
       4: areturn

  public org.apache.dubbo.common.URL getUrl();
    Code:
       0: aload_0
       1: invokevirtual #22                 // Method getUrl:()Lcom/alibaba/dubbo/common/URL;
       4: areturn
}
