Compiled from "Protocol.java"
public interface com.alibaba.dubbo.rpc.Protocol extends org.apache.dubbo.rpc.Protocol {
  public abstract <T> com.alibaba.dubbo.rpc.Exporter<T> export(com.alibaba.dubbo.rpc.Invoker<T>) throws com.alibaba.dubbo.rpc.RpcException;

  public abstract <T> com.alibaba.dubbo.rpc.Invoker<T> refer(java.lang.Class<T>, com.alibaba.dubbo.common.URL) throws com.alibaba.dubbo.rpc.RpcException;

  public default <T> org.apache.dubbo.rpc.Exporter<T> export(org.apache.dubbo.rpc.Invoker<T>) throws com.alibaba.dubbo.rpc.RpcException;
    Code:
       0: aload_0
       1: new           #1                  // class com/alibaba/dubbo/rpc/Invoker$CompatibleInvoker
       4: dup
       5: aload_1
       6: invokespecial #2                  // Method com/alibaba/dubbo/rpc/Invoker$CompatibleInvoker."<init>":(Lorg/apache/dubbo/rpc/Invoker;)V
       9: invokeinterface #3,  2            // InterfaceMethod export:(Lcom/alibaba/dubbo/rpc/Invoker;)Lcom/alibaba/dubbo/rpc/Exporter;
      14: areturn

  public default <T> org.apache.dubbo.rpc.Invoker<T> refer(java.lang.Class<T>, org.apache.dubbo.common.URL) throws com.alibaba.dubbo.rpc.RpcException;
    Code:
       0: aload_0
       1: aload_1
       2: new           #4                  // class com/alibaba/dubbo/common/URL
       5: dup
       6: aload_2
       7: invokespecial #5                  // Method com/alibaba/dubbo/common/URL."<init>":(Lorg/apache/dubbo/common/URL;)V
      10: invokeinterface #6,  3            // InterfaceMethod refer:(Ljava/lang/Class;Lcom/alibaba/dubbo/common/URL;)Lcom/alibaba/dubbo/rpc/Invoker;
      15: areturn

  public default java.util.List<org.apache.dubbo.rpc.ProtocolServer> getServers();
    Code:
       0: invokestatic  #7                  // Method java/util/Collections.emptyList:()Ljava/util/List;
       3: areturn
}
