Compiled from "ProxyFactory.java"
public interface com.alibaba.dubbo.rpc.ProxyFactory extends org.apache.dubbo.rpc.ProxyFactory {
  public abstract <T> T getProxy(com.alibaba.dubbo.rpc.Invoker<T>) throws com.alibaba.dubbo.rpc.RpcException;

  public abstract <T> T getProxy(com.alibaba.dubbo.rpc.Invoker<T>, boolean) throws com.alibaba.dubbo.rpc.RpcException;

  public abstract <T> com.alibaba.dubbo.rpc.Invoker<T> getInvoker(T, java.lang.Class<T>, com.alibaba.dubbo.common.URL) throws com.alibaba.dubbo.rpc.RpcException;

  public default <T> T getProxy(org.apache.dubbo.rpc.Invoker<T>) throws org.apache.dubbo.rpc.RpcException;
    Code:
       0: aload_0
       1: new           #1                  // class com/alibaba/dubbo/rpc/Invoker$CompatibleInvoker
       4: dup
       5: aload_1
       6: invokespecial #2                  // Method com/alibaba/dubbo/rpc/Invoker$CompatibleInvoker."<init>":(Lorg/apache/dubbo/rpc/Invoker;)V
       9: invokeinterface #3,  2            // InterfaceMethod getProxy:(Lcom/alibaba/dubbo/rpc/Invoker;)Ljava/lang/Object;
      14: areturn

  public default <T> T getProxy(org.apache.dubbo.rpc.Invoker<T>, boolean) throws org.apache.dubbo.rpc.RpcException;
    Code:
       0: aload_0
       1: new           #1                  // class com/alibaba/dubbo/rpc/Invoker$CompatibleInvoker
       4: dup
       5: aload_1
       6: invokespecial #2                  // Method com/alibaba/dubbo/rpc/Invoker$CompatibleInvoker."<init>":(Lorg/apache/dubbo/rpc/Invoker;)V
       9: iload_2
      10: invokeinterface #4,  3            // InterfaceMethod getProxy:(Lcom/alibaba/dubbo/rpc/Invoker;Z)Ljava/lang/Object;
      15: areturn

  public default <T> org.apache.dubbo.rpc.Invoker<T> getInvoker(T, java.lang.Class<T>, org.apache.dubbo.common.URL) throws org.apache.dubbo.rpc.RpcException;
    Code:
       0: aload_0
       1: aload_1
       2: aload_2
       3: new           #5                  // class com/alibaba/dubbo/common/URL
       6: dup
       7: aload_3
       8: invokespecial #6                  // Method com/alibaba/dubbo/common/URL."<init>":(Lorg/apache/dubbo/common/URL;)V
      11: invokeinterface #7,  4            // InterfaceMethod getInvoker:(Ljava/lang/Object;Ljava/lang/Class;Lcom/alibaba/dubbo/common/URL;)Lcom/alibaba/dubbo/rpc/Invoker;
      16: areturn
}
