Compiled from "Result.java"
public class com.alibaba.dubbo.rpc.Result$CompatibleResult implements com.alibaba.dubbo.rpc.Result {
  private org.apache.dubbo.rpc.Result delegate;

  public com.alibaba.dubbo.rpc.Result$CompatibleResult(org.apache.dubbo.rpc.Result);
    Code:
       0: aload_0
       1: invokespecial #1                  // Method java/lang/Object."<init>":()V
       4: aload_0
       5: aload_1
       6: putfield      #2                  // Field delegate:Lorg/apache/dubbo/rpc/Result;
       9: return

  public org.apache.dubbo.rpc.Result getDelegate();
    Code:
       0: aload_0
       1: getfield      #2                  // Field delegate:Lorg/apache/dubbo/rpc/Result;
       4: areturn

  public org.apache.dubbo.rpc.Result whenCompleteWithContext(java.util.function.BiConsumer<org.apache.dubbo.rpc.Result, java.lang.Throwable>);
    Code:
       0: aload_0
       1: getfield      #2                  // Field delegate:Lorg/apache/dubbo/rpc/Result;
       4: aload_1
       5: invokeinterface #3,  2            // InterfaceMethod org/apache/dubbo/rpc/Result.whenCompleteWithContext:(Ljava/util/function/BiConsumer;)Lorg/apache/dubbo/rpc/Result;
      10: areturn

  public java.lang.Object getValue();
    Code:
       0: aload_0
       1: getfield      #2                  // Field delegate:Lorg/apache/dubbo/rpc/Result;
       4: invokeinterface #4,  1            // InterfaceMethod org/apache/dubbo/rpc/Result.getValue:()Ljava/lang/Object;
       9: areturn

  public void setValue(java.lang.Object);
    Code:
       0: aload_0
       1: getfield      #2                  // Field delegate:Lorg/apache/dubbo/rpc/Result;
       4: aload_1
       5: invokeinterface #5,  2            // InterfaceMethod org/apache/dubbo/rpc/Result.setValue:(Ljava/lang/Object;)V
      10: return

  public java.lang.Throwable getException();
    Code:
       0: aload_0
       1: getfield      #2                  // Field delegate:Lorg/apache/dubbo/rpc/Result;
       4: invokeinterface #6,  1            // InterfaceMethod org/apache/dubbo/rpc/Result.getException:()Ljava/lang/Throwable;
       9: areturn

  public void setException(java.lang.Throwable);
    Code:
       0: aload_0
       1: getfield      #2                  // Field delegate:Lorg/apache/dubbo/rpc/Result;
       4: aload_1
       5: invokeinterface #7,  2            // InterfaceMethod org/apache/dubbo/rpc/Result.setException:(Ljava/lang/Throwable;)V
      10: return

  public boolean hasException();
    Code:
       0: aload_0
       1: getfield      #2                  // Field delegate:Lorg/apache/dubbo/rpc/Result;
       4: invokeinterface #8,  1            // InterfaceMethod org/apache/dubbo/rpc/Result.hasException:()Z
       9: ireturn

  public java.lang.Object recreate() throws java.lang.Throwable;
    Code:
       0: aload_0
       1: getfield      #2                  // Field delegate:Lorg/apache/dubbo/rpc/Result;
       4: invokeinterface #9,  1            // InterfaceMethod org/apache/dubbo/rpc/Result.recreate:()Ljava/lang/Object;
       9: areturn

  public java.util.Map<java.lang.String, java.lang.String> getAttachments();
    Code:
       0: aload_0
       1: getfield      #2                  // Field delegate:Lorg/apache/dubbo/rpc/Result;
       4: invokeinterface #10,  1           // InterfaceMethod org/apache/dubbo/rpc/Result.getAttachments:()Ljava/util/Map;
       9: areturn

  public void addAttachments(java.util.Map<java.lang.String, java.lang.String>);
    Code:
       0: aload_0
       1: getfield      #2                  // Field delegate:Lorg/apache/dubbo/rpc/Result;
       4: aload_1
       5: invokeinterface #11,  2           // InterfaceMethod org/apache/dubbo/rpc/Result.addAttachments:(Ljava/util/Map;)V
      10: return

  public void setAttachments(java.util.Map<java.lang.String, java.lang.String>);
    Code:
       0: aload_0
       1: getfield      #2                  // Field delegate:Lorg/apache/dubbo/rpc/Result;
       4: aload_1
       5: invokeinterface #12,  2           // InterfaceMethod org/apache/dubbo/rpc/Result.setAttachments:(Ljava/util/Map;)V
      10: return

  public java.lang.String getAttachment(java.lang.String);
    Code:
       0: aload_0
       1: getfield      #2                  // Field delegate:Lorg/apache/dubbo/rpc/Result;
       4: aload_1
       5: invokeinterface #13,  2           // InterfaceMethod org/apache/dubbo/rpc/Result.getAttachment:(Ljava/lang/String;)Ljava/lang/String;
      10: areturn

  public java.lang.String getAttachment(java.lang.String, java.lang.String);
    Code:
       0: aload_0
       1: getfield      #2                  // Field delegate:Lorg/apache/dubbo/rpc/Result;
       4: aload_1
       5: aload_2
       6: invokeinterface #14,  3           // InterfaceMethod org/apache/dubbo/rpc/Result.getAttachment:(Ljava/lang/String;Ljava/lang/String;)Ljava/lang/String;
      11: areturn

  public void setAttachment(java.lang.String, java.lang.String);
    Code:
       0: aload_0
       1: getfield      #2                  // Field delegate:Lorg/apache/dubbo/rpc/Result;
       4: aload_1
       5: aload_2
       6: invokeinterface #15,  3           // InterfaceMethod org/apache/dubbo/rpc/Result.setAttachment:(Ljava/lang/String;Ljava/lang/String;)V
      11: return

  public void setAttachment(java.lang.String, java.lang.Object);
    Code:
       0: aload_0
       1: getfield      #2                  // Field delegate:Lorg/apache/dubbo/rpc/Result;
       4: aload_1
       5: aload_2
       6: invokeinterface #16,  3           // InterfaceMethod org/apache/dubbo/rpc/Result.setAttachment:(Ljava/lang/String;Ljava/lang/Object;)V
      11: return

  public void setObjectAttachment(java.lang.String, java.lang.Object);
    Code:
       0: aload_0
       1: getfield      #2                  // Field delegate:Lorg/apache/dubbo/rpc/Result;
       4: aload_1
       5: aload_2
       6: invokeinterface #17,  3           // InterfaceMethod org/apache/dubbo/rpc/Result.setObjectAttachment:(Ljava/lang/String;Ljava/lang/Object;)V
      11: return

  public <U> java.util.concurrent.CompletableFuture<U> thenApply(java.util.function.Function<org.apache.dubbo.rpc.Result, ? extends U>);
    Code:
       0: aload_0
       1: getfield      #2                  // Field delegate:Lorg/apache/dubbo/rpc/Result;
       4: aload_1
       5: invokeinterface #18,  2           // InterfaceMethod org/apache/dubbo/rpc/Result.thenApply:(Ljava/util/function/Function;)Ljava/util/concurrent/CompletableFuture;
      10: areturn

  public org.apache.dubbo.rpc.Result get() throws java.lang.InterruptedException, java.util.concurrent.ExecutionException;
    Code:
       0: aload_0
       1: getfield      #2                  // Field delegate:Lorg/apache/dubbo/rpc/Result;
       4: invokeinterface #19,  1           // InterfaceMethod org/apache/dubbo/rpc/Result.get:()Lorg/apache/dubbo/rpc/Result;
       9: areturn

  public org.apache.dubbo.rpc.Result get(long, java.util.concurrent.TimeUnit) throws java.lang.InterruptedException, java.util.concurrent.ExecutionException, java.util.concurrent.TimeoutException;
    Code:
       0: aload_0
       1: getfield      #2                  // Field delegate:Lorg/apache/dubbo/rpc/Result;
       4: lload_1
       5: aload_3
       6: invokeinterface #20,  4           // InterfaceMethod org/apache/dubbo/rpc/Result.get:(JLjava/util/concurrent/TimeUnit;)Lorg/apache/dubbo/rpc/Result;
      11: areturn
}
