Compiled from "RpcContext.java"
public class com.alibaba.dubbo.rpc.RpcContext {
  private org.apache.dubbo.rpc.RpcContext newRpcContext;

  public static com.alibaba.dubbo.rpc.RpcContext getContext();
    Code:
       0: new           #1                  // class com/alibaba/dubbo/rpc/RpcContext
       3: dup
       4: invokestatic  #2                  // Method org/apache/dubbo/rpc/RpcContext.getContext:()Lorg/apache/dubbo/rpc/RpcContext;
       7: invokespecial #3                  // Method "<init>":(Lorg/apache/dubbo/rpc/RpcContext;)V
      10: areturn

  public static com.alibaba.dubbo.rpc.RpcContext getServerContext();
    Code:
       0: new           #1                  // class com/alibaba/dubbo/rpc/RpcContext
       3: dup
       4: invokestatic  #4                  // Method org/apache/dubbo/rpc/RpcContext.getServerContext:()Lorg/apache/dubbo/rpc/RpcContextAttachment;
       7: invokespecial #3                  // Method "<init>":(Lorg/apache/dubbo/rpc/RpcContext;)V
      10: areturn

  public static com.alibaba.dubbo.rpc.RpcContext getClientResponseContext();
    Code:
       0: new           #1                  // class com/alibaba/dubbo/rpc/RpcContext
       3: dup
       4: invokestatic  #5                  // Method org/apache/dubbo/rpc/RpcContext.getClientResponseContext:()Lorg/apache/dubbo/rpc/RpcContextAttachment;
       7: invokespecial #3                  // Method "<init>":(Lorg/apache/dubbo/rpc/RpcContext;)V
      10: areturn

  public static com.alibaba.dubbo.rpc.RpcContext getServerResponseContext();
    Code:
       0: new           #1                  // class com/alibaba/dubbo/rpc/RpcContext
       3: dup
       4: invokestatic  #6                  // Method org/apache/dubbo/rpc/RpcContext.getServerResponseContext:()Lorg/apache/dubbo/rpc/RpcContextAttachment;
       7: invokespecial #3                  // Method "<init>":(Lorg/apache/dubbo/rpc/RpcContext;)V
      10: areturn

  public static void removeClientResponseContext();
    Code:
       0: invokestatic  #7                  // Method org/apache/dubbo/rpc/RpcContext.removeClientResponseContext:()V
       3: return

  public static void removeServerResponseContext();
    Code:
       0: invokestatic  #8                  // Method org/apache/dubbo/rpc/RpcContext.removeServerResponseContext:()V
       3: return

  public static void removeServerContext();
    Code:
       0: invokestatic  #9                  // Method org/apache/dubbo/rpc/RpcContext.removeServerContext:()V
       3: return

  public static void removeContext();
    Code:
       0: invokestatic  #10                 // Method org/apache/dubbo/rpc/RpcContext.removeContext:()V
       3: return

  public com.alibaba.dubbo.rpc.RpcContext(org.apache.dubbo.rpc.RpcContext);
    Code:
       0: aload_0
       1: invokespecial #11                 // Method java/lang/Object."<init>":()V
       4: aload_0
       5: aload_1
       6: putfield      #12                 // Field newRpcContext:Lorg/apache/dubbo/rpc/RpcContext;
       9: return

  public java.lang.Object getRequest();
    Code:
       0: aload_0
       1: getfield      #12                 // Field newRpcContext:Lorg/apache/dubbo/rpc/RpcContext;
       4: invokevirtual #13                 // Method org/apache/dubbo/rpc/RpcContext.getRequest:()Ljava/lang/Object;
       7: areturn

  public <T> T getRequest(java.lang.Class<T>);
    Code:
       0: aload_0
       1: getfield      #12                 // Field newRpcContext:Lorg/apache/dubbo/rpc/RpcContext;
       4: aload_1
       5: invokevirtual #14                 // Method org/apache/dubbo/rpc/RpcContext.getRequest:(Ljava/lang/Class;)Ljava/lang/Object;
       8: areturn

  public void setRequest(java.lang.Object);
    Code:
       0: aload_0
       1: getfield      #12                 // Field newRpcContext:Lorg/apache/dubbo/rpc/RpcContext;
       4: aload_1
       5: invokevirtual #15                 // Method org/apache/dubbo/rpc/RpcContext.setRequest:(Ljava/lang/Object;)V
       8: return

  public java.lang.Object getResponse();
    Code:
       0: aload_0
       1: getfield      #12                 // Field newRpcContext:Lorg/apache/dubbo/rpc/RpcContext;
       4: invokevirtual #16                 // Method org/apache/dubbo/rpc/RpcContext.getResponse:()Ljava/lang/Object;
       7: areturn

  public <T> T getResponse(java.lang.Class<T>);
    Code:
       0: aload_0
       1: getfield      #12                 // Field newRpcContext:Lorg/apache/dubbo/rpc/RpcContext;
       4: aload_1
       5: invokevirtual #17                 // Method org/apache/dubbo/rpc/RpcContext.getResponse:(Ljava/lang/Class;)Ljava/lang/Object;
       8: areturn

  public void setResponse(java.lang.Object);
    Code:
       0: aload_0
       1: getfield      #12                 // Field newRpcContext:Lorg/apache/dubbo/rpc/RpcContext;
       4: aload_1
       5: invokevirtual #18                 // Method org/apache/dubbo/rpc/RpcContext.setResponse:(Ljava/lang/Object;)V
       8: return

  public boolean isProviderSide();
    Code:
       0: aload_0
       1: getfield      #12                 // Field newRpcContext:Lorg/apache/dubbo/rpc/RpcContext;
       4: invokevirtual #19                 // Method org/apache/dubbo/rpc/RpcContext.isProviderSide:()Z
       7: ireturn

  public boolean isConsumerSide();
    Code:
       0: aload_0
       1: getfield      #12                 // Field newRpcContext:Lorg/apache/dubbo/rpc/RpcContext;
       4: invokevirtual #20                 // Method org/apache/dubbo/rpc/RpcContext.isConsumerSide:()Z
       7: ireturn

  public java.util.List<com.alibaba.dubbo.common.URL> getUrls();
    Code:
       0: aload_0
       1: getfield      #12                 // Field newRpcContext:Lorg/apache/dubbo/rpc/RpcContext;
       4: invokevirtual #21                 // Method org/apache/dubbo/rpc/RpcContext.getUrls:()Ljava/util/List;
       7: astore_1
       8: aload_1
       9: invokestatic  #22                 // Method org/apache/dubbo/common/utils/CollectionUtils.isNotEmpty:(Ljava/util/Collection;)Z
      12: ifeq          77
      15: new           #23                 // class java/util/ArrayList
      18: dup
      19: aload_1
      20: invokeinterface #24,  1           // InterfaceMethod java/util/List.size:()I
      25: invokespecial #25                 // Method java/util/ArrayList."<init>":(I)V
      28: astore_2
      29: aload_1
      30: invokeinterface #26,  1           // InterfaceMethod java/util/List.iterator:()Ljava/util/Iterator;
      35: astore_3
      36: aload_3
      37: invokeinterface #27,  1           // InterfaceMethod java/util/Iterator.hasNext:()Z
      42: ifeq          75
      45: aload_3
      46: invokeinterface #28,  1           // InterfaceMethod java/util/Iterator.next:()Ljava/lang/Object;
      51: checkcast     #29                 // class org/apache/dubbo/common/URL
      54: astore        4
      56: aload_2
      57: new           #30                 // class com/alibaba/dubbo/common/URL
      60: dup
      61: aload         4
      63: invokespecial #31                 // Method com/alibaba/dubbo/common/URL."<init>":(Lorg/apache/dubbo/common/URL;)V
      66: invokeinterface #32,  2           // InterfaceMethod java/util/List.add:(Ljava/lang/Object;)Z
      71: pop
      72: goto          36
      75: aload_2
      76: areturn
      77: invokestatic  #33                 // Method java/util/Collections.emptyList:()Ljava/util/List;
      80: areturn

  public void setUrls(java.util.List<com.alibaba.dubbo.common.URL>);
    Code:
       0: aload_1
       1: invokestatic  #22                 // Method org/apache/dubbo/common/utils/CollectionUtils.isNotEmpty:(Ljava/util/Collection;)Z
       4: ifeq          71
       7: new           #23                 // class java/util/ArrayList
      10: dup
      11: aload_1
      12: invokeinterface #24,  1           // InterfaceMethod java/util/List.size:()I
      17: invokespecial #25                 // Method java/util/ArrayList."<init>":(I)V
      20: astore_2
      21: aload_1
      22: invokeinterface #26,  1           // InterfaceMethod java/util/List.iterator:()Ljava/util/Iterator;
      27: astore_3
      28: aload_3
      29: invokeinterface #27,  1           // InterfaceMethod java/util/Iterator.hasNext:()Z
      34: ifeq          63
      37: aload_3
      38: invokeinterface #28,  1           // InterfaceMethod java/util/Iterator.next:()Ljava/lang/Object;
      43: checkcast     #30                 // class com/alibaba/dubbo/common/URL
      46: astore        4
      48: aload_2
      49: aload         4
      51: invokevirtual #34                 // Method com/alibaba/dubbo/common/URL.getOriginalURL:()Lorg/apache/dubbo/common/URL;
      54: invokeinterface #32,  2           // InterfaceMethod java/util/List.add:(Ljava/lang/Object;)Z
      59: pop
      60: goto          28
      63: aload_0
      64: getfield      #12                 // Field newRpcContext:Lorg/apache/dubbo/rpc/RpcContext;
      67: aload_2
      68: invokevirtual #35                 // Method org/apache/dubbo/rpc/RpcContext.setUrls:(Ljava/util/List;)V
      71: return

  public com.alibaba.dubbo.common.URL getUrl();
    Code:
       0: new           #30                 // class com/alibaba/dubbo/common/URL
       3: dup
       4: aload_0
       5: getfield      #12                 // Field newRpcContext:Lorg/apache/dubbo/rpc/RpcContext;
       8: invokevirtual #36                 // Method org/apache/dubbo/rpc/RpcContext.getUrl:()Lorg/apache/dubbo/common/URL;
      11: invokespecial #31                 // Method com/alibaba/dubbo/common/URL."<init>":(Lorg/apache/dubbo/common/URL;)V
      14: areturn

  public void setUrl(com.alibaba.dubbo.common.URL);
    Code:
       0: aload_0
       1: getfield      #12                 // Field newRpcContext:Lorg/apache/dubbo/rpc/RpcContext;
       4: aload_1
       5: invokevirtual #34                 // Method com/alibaba/dubbo/common/URL.getOriginalURL:()Lorg/apache/dubbo/common/URL;
       8: invokevirtual #37                 // Method org/apache/dubbo/rpc/RpcContext.setUrl:(Lorg/apache/dubbo/common/URL;)V
      11: return

  public java.lang.String getMethodName();
    Code:
       0: aload_0
       1: getfield      #12                 // Field newRpcContext:Lorg/apache/dubbo/rpc/RpcContext;
       4: invokevirtual #38                 // Method org/apache/dubbo/rpc/RpcContext.getMethodName:()Ljava/lang/String;
       7: areturn

  public void setMethodName(java.lang.String);
    Code:
       0: aload_0
       1: getfield      #12                 // Field newRpcContext:Lorg/apache/dubbo/rpc/RpcContext;
       4: aload_1
       5: invokevirtual #39                 // Method org/apache/dubbo/rpc/RpcContext.setMethodName:(Ljava/lang/String;)V
       8: return

  public java.lang.Class<?>[] getParameterTypes();
    Code:
       0: aload_0
       1: getfield      #12                 // Field newRpcContext:Lorg/apache/dubbo/rpc/RpcContext;
       4: invokevirtual #40                 // Method org/apache/dubbo/rpc/RpcContext.getParameterTypes:()[Ljava/lang/Class;
       7: areturn

  public void setParameterTypes(java.lang.Class<?>[]);
    Code:
       0: aload_0
       1: getfield      #12                 // Field newRpcContext:Lorg/apache/dubbo/rpc/RpcContext;
       4: aload_1
       5: invokevirtual #41                 // Method org/apache/dubbo/rpc/RpcContext.setParameterTypes:([Ljava/lang/Class;)V
       8: return

  public java.lang.Object[] getArguments();
    Code:
       0: aload_0
       1: getfield      #12                 // Field newRpcContext:Lorg/apache/dubbo/rpc/RpcContext;
       4: invokevirtual #42                 // Method org/apache/dubbo/rpc/RpcContext.getArguments:()[Ljava/lang/Object;
       7: areturn

  public void setArguments(java.lang.Object[]);
    Code:
       0: aload_0
       1: getfield      #12                 // Field newRpcContext:Lorg/apache/dubbo/rpc/RpcContext;
       4: aload_1
       5: invokevirtual #43                 // Method org/apache/dubbo/rpc/RpcContext.setArguments:([Ljava/lang/Object;)V
       8: return

  public com.alibaba.dubbo.rpc.RpcContext setLocalAddress(java.lang.String, int);
    Code:
       0: aload_0
       1: getfield      #12                 // Field newRpcContext:Lorg/apache/dubbo/rpc/RpcContext;
       4: aload_1
       5: iload_2
       6: invokevirtual #44                 // Method org/apache/dubbo/rpc/RpcContext.setLocalAddress:(Ljava/lang/String;I)Lorg/apache/dubbo/rpc/RpcContext;
       9: pop
      10: aload_0
      11: areturn

  public java.net.InetSocketAddress getLocalAddress();
    Code:
       0: aload_0
       1: getfield      #12                 // Field newRpcContext:Lorg/apache/dubbo/rpc/RpcContext;
       4: invokevirtual #45                 // Method org/apache/dubbo/rpc/RpcContext.getLocalAddress:()Ljava/net/InetSocketAddress;
       7: areturn

  public com.alibaba.dubbo.rpc.RpcContext setLocalAddress(java.net.InetSocketAddress);
    Code:
       0: aload_0
       1: getfield      #12                 // Field newRpcContext:Lorg/apache/dubbo/rpc/RpcContext;
       4: aload_1
       5: invokevirtual #46                 // Method org/apache/dubbo/rpc/RpcContext.setLocalAddress:(Ljava/net/InetSocketAddress;)Lorg/apache/dubbo/rpc/RpcContext;
       8: pop
       9: aload_0
      10: areturn

  public java.lang.String getLocalAddressString();
    Code:
       0: aload_0
       1: getfield      #12                 // Field newRpcContext:Lorg/apache/dubbo/rpc/RpcContext;
       4: invokevirtual #47                 // Method org/apache/dubbo/rpc/RpcContext.getLocalAddressString:()Ljava/lang/String;
       7: areturn

  public java.lang.String getLocalHostName();
    Code:
       0: aload_0
       1: getfield      #12                 // Field newRpcContext:Lorg/apache/dubbo/rpc/RpcContext;
       4: invokevirtual #48                 // Method org/apache/dubbo/rpc/RpcContext.getLocalHostName:()Ljava/lang/String;
       7: areturn

  public com.alibaba.dubbo.rpc.RpcContext setRemoteAddress(java.lang.String, int);
    Code:
       0: aload_0
       1: getfield      #12                 // Field newRpcContext:Lorg/apache/dubbo/rpc/RpcContext;
       4: aload_1
       5: iload_2
       6: invokevirtual #49                 // Method org/apache/dubbo/rpc/RpcContext.setRemoteAddress:(Ljava/lang/String;I)Lorg/apache/dubbo/rpc/RpcContext;
       9: pop
      10: aload_0
      11: areturn

  public java.net.InetSocketAddress getRemoteAddress();
    Code:
       0: aload_0
       1: getfield      #12                 // Field newRpcContext:Lorg/apache/dubbo/rpc/RpcContext;
       4: invokevirtual #50                 // Method org/apache/dubbo/rpc/RpcContext.getRemoteAddress:()Ljava/net/InetSocketAddress;
       7: areturn

  public com.alibaba.dubbo.rpc.RpcContext setRemoteAddress(java.net.InetSocketAddress);
    Code:
       0: aload_0
       1: getfield      #12                 // Field newRpcContext:Lorg/apache/dubbo/rpc/RpcContext;
       4: aload_1
       5: invokevirtual #51                 // Method org/apache/dubbo/rpc/RpcContext.setRemoteAddress:(Ljava/net/InetSocketAddress;)Lorg/apache/dubbo/rpc/RpcContext;
       8: pop
       9: aload_0
      10: areturn

  public java.lang.String getRemoteAddressString();
    Code:
       0: aload_0
       1: getfield      #12                 // Field newRpcContext:Lorg/apache/dubbo/rpc/RpcContext;
       4: invokevirtual #52                 // Method org/apache/dubbo/rpc/RpcContext.getRemoteAddressString:()Ljava/lang/String;
       7: areturn

  public java.lang.String getRemoteHostName();
    Code:
       0: aload_0
       1: getfield      #12                 // Field newRpcContext:Lorg/apache/dubbo/rpc/RpcContext;
       4: invokevirtual #53                 // Method org/apache/dubbo/rpc/RpcContext.getRemoteHostName:()Ljava/lang/String;
       7: areturn

  public java.lang.String getLocalHost();
    Code:
       0: aload_0
       1: getfield      #12                 // Field newRpcContext:Lorg/apache/dubbo/rpc/RpcContext;
       4: invokevirtual #54                 // Method org/apache/dubbo/rpc/RpcContext.getLocalHost:()Ljava/lang/String;
       7: areturn

  public int getLocalPort();
    Code:
       0: aload_0
       1: getfield      #12                 // Field newRpcContext:Lorg/apache/dubbo/rpc/RpcContext;
       4: invokevirtual #55                 // Method org/apache/dubbo/rpc/RpcContext.getLocalPort:()I
       7: ireturn

  public java.lang.String getRemoteHost();
    Code:
       0: aload_0
       1: getfield      #12                 // Field newRpcContext:Lorg/apache/dubbo/rpc/RpcContext;
       4: invokevirtual #56                 // Method org/apache/dubbo/rpc/RpcContext.getRemoteHost:()Ljava/lang/String;
       7: areturn

  public int getRemotePort();
    Code:
       0: aload_0
       1: getfield      #12                 // Field newRpcContext:Lorg/apache/dubbo/rpc/RpcContext;
       4: invokevirtual #57                 // Method org/apache/dubbo/rpc/RpcContext.getRemotePort:()I
       7: ireturn

  public java.lang.String getAttachment(java.lang.String);
    Code:
       0: aload_0
       1: getfield      #12                 // Field newRpcContext:Lorg/apache/dubbo/rpc/RpcContext;
       4: aload_1
       5: invokevirtual #58                 // Method org/apache/dubbo/rpc/RpcContext.getAttachment:(Ljava/lang/String;)Ljava/lang/String;
       8: areturn

  public com.alibaba.dubbo.rpc.RpcContext setAttachment(java.lang.String, java.lang.String);
    Code:
       0: aload_0
       1: getfield      #12                 // Field newRpcContext:Lorg/apache/dubbo/rpc/RpcContext;
       4: aload_1
       5: aload_2
       6: invokevirtual #59                 // Method org/apache/dubbo/rpc/RpcContext.setAttachment:(Ljava/lang/String;Ljava/lang/String;)Lorg/apache/dubbo/rpc/RpcContext;
       9: pop
      10: aload_0
      11: areturn

  public com.alibaba.dubbo.rpc.RpcContext removeAttachment(java.lang.String);
    Code:
       0: aload_0
       1: getfield      #12                 // Field newRpcContext:Lorg/apache/dubbo/rpc/RpcContext;
       4: aload_1
       5: invokevirtual #60                 // Method org/apache/dubbo/rpc/RpcContext.removeAttachment:(Ljava/lang/String;)Lorg/apache/dubbo/rpc/RpcContext;
       8: pop
       9: aload_0
      10: areturn

  public java.util.Map<java.lang.String, java.lang.String> getAttachments();
    Code:
       0: aload_0
       1: getfield      #12                 // Field newRpcContext:Lorg/apache/dubbo/rpc/RpcContext;
       4: invokevirtual #61                 // Method org/apache/dubbo/rpc/RpcContext.getAttachments:()Ljava/util/Map;
       7: areturn

  public com.alibaba.dubbo.rpc.RpcContext setAttachments(java.util.Map<java.lang.String, java.lang.String>);
    Code:
       0: aload_0
       1: getfield      #12                 // Field newRpcContext:Lorg/apache/dubbo/rpc/RpcContext;
       4: aload_1
       5: invokevirtual #62                 // Method org/apache/dubbo/rpc/RpcContext.setAttachments:(Ljava/util/Map;)Lorg/apache/dubbo/rpc/RpcContext;
       8: pop
       9: aload_0
      10: areturn

  public void clearAttachments();
    Code:
       0: aload_0
       1: getfield      #12                 // Field newRpcContext:Lorg/apache/dubbo/rpc/RpcContext;
       4: invokevirtual #63                 // Method org/apache/dubbo/rpc/RpcContext.clearAttachments:()V
       7: return

  public java.util.Map<java.lang.String, java.lang.Object> get();
    Code:
       0: aload_0
       1: getfield      #12                 // Field newRpcContext:Lorg/apache/dubbo/rpc/RpcContext;
       4: invokevirtual #64                 // Method org/apache/dubbo/rpc/RpcContext.get:()Ljava/util/Map;
       7: areturn

  public com.alibaba.dubbo.rpc.RpcContext set(java.lang.String, java.lang.Object);
    Code:
       0: aload_0
       1: getfield      #12                 // Field newRpcContext:Lorg/apache/dubbo/rpc/RpcContext;
       4: aload_1
       5: aload_2
       6: invokevirtual #65                 // Method org/apache/dubbo/rpc/RpcContext.set:(Ljava/lang/String;Ljava/lang/Object;)Lorg/apache/dubbo/rpc/RpcContext;
       9: pop
      10: aload_0
      11: areturn

  public com.alibaba.dubbo.rpc.RpcContext remove(java.lang.String);
    Code:
       0: aload_0
       1: getfield      #12                 // Field newRpcContext:Lorg/apache/dubbo/rpc/RpcContext;
       4: aload_1
       5: invokevirtual #66                 // Method org/apache/dubbo/rpc/RpcContext.remove:(Ljava/lang/String;)Lorg/apache/dubbo/rpc/RpcContext;
       8: pop
       9: aload_0
      10: areturn

  public java.lang.Object get(java.lang.String);
    Code:
       0: aload_0
       1: getfield      #12                 // Field newRpcContext:Lorg/apache/dubbo/rpc/RpcContext;
       4: aload_1
       5: invokevirtual #67                 // Method org/apache/dubbo/rpc/RpcContext.get:(Ljava/lang/String;)Ljava/lang/Object;
       8: areturn

  public boolean isServerSide();
    Code:
       0: aload_0
       1: invokevirtual #68                 // Method isProviderSide:()Z
       4: ireturn

  public boolean isClientSide();
    Code:
       0: aload_0
       1: invokevirtual #69                 // Method isConsumerSide:()Z
       4: ireturn

  public <T> java.util.concurrent.Future<T> asyncCall(java.util.concurrent.Callable<T>);
    Code:
       0: aload_0
       1: ldc           #71                 // String async
       3: getstatic     #72                 // Field java/lang/Boolean.TRUE:Ljava/lang/Boolean;
       6: invokevirtual #73                 // Method java/lang/Boolean.toString:()Ljava/lang/String;
       9: invokevirtual #74                 // Method setAttachment:(Ljava/lang/String;Ljava/lang/String;)Lcom/alibaba/dubbo/rpc/RpcContext;
      12: pop
      13: aload_1
      14: invokeinterface #75,  1           // InterfaceMethod java/util/concurrent/Callable.call:()Ljava/lang/Object;
      19: astore_2
      20: aload_2
      21: ifnull        58
      24: new           #76                 // class java/util/concurrent/FutureTask
      27: dup
      28: new           #77                 // class com/alibaba/dubbo/rpc/RpcContext$1
      31: dup
      32: aload_0
      33: aload_2
      34: invokespecial #78                 // Method com/alibaba/dubbo/rpc/RpcContext$1."<init>":(Lcom/alibaba/dubbo/rpc/RpcContext;Ljava/lang/Object;)V
      37: invokespecial #79                 // Method java/util/concurrent/FutureTask."<init>":(Ljava/util/concurrent/Callable;)V
      40: astore_3
      41: aload_3
      42: invokevirtual #80                 // Method java/util/concurrent/FutureTask.run:()V
      45: aload_3
      46: astore        4
      48: aload_0
      49: ldc           #71                 // String async
      51: invokevirtual #81                 // Method removeAttachment:(Ljava/lang/String;)Lcom/alibaba/dubbo/rpc/RpcContext;
      54: pop
      55: aload         4
      57: areturn
      58: aload_0
      59: ldc           #71                 // String async
      61: invokevirtual #81                 // Method removeAttachment:(Ljava/lang/String;)Lcom/alibaba/dubbo/rpc/RpcContext;
      64: pop
      65: goto          90
      68: astore_2
      69: new           #83                 // class com/alibaba/dubbo/rpc/RpcException
      72: dup
      73: aload_2
      74: invokespecial #84                 // Method com/alibaba/dubbo/rpc/RpcException."<init>":(Ljava/lang/Throwable;)V
      77: athrow
      78: astore        5
      80: aload_0
      81: ldc           #71                 // String async
      83: invokevirtual #81                 // Method removeAttachment:(Ljava/lang/String;)Lcom/alibaba/dubbo/rpc/RpcContext;
      86: pop
      87: aload         5
      89: athrow
      90: goto          104
      93: astore_2
      94: new           #85                 // class com/alibaba/dubbo/rpc/RpcContext$2
      97: dup
      98: aload_0
      99: aload_2
     100: invokespecial #86                 // Method com/alibaba/dubbo/rpc/RpcContext$2."<init>":(Lcom/alibaba/dubbo/rpc/RpcContext;Lcom/alibaba/dubbo/rpc/RpcException;)V
     103: areturn
     104: invokestatic  #87                 // Method getContext:()Lcom/alibaba/dubbo/rpc/RpcContext;
     107: invokevirtual #88                 // Method getFuture:()Ljava/util/concurrent/Future;
     110: areturn
    Exception table:
       from    to  target type
           0    48    68   Class java/lang/Exception
           0    48    78   any
          68    80    78   any
           0    55    93   Class com/alibaba/dubbo/rpc/RpcException
          58    90    93   Class com/alibaba/dubbo/rpc/RpcException

  public void asyncCall(java.lang.Runnable);
    Code:
       0: aload_0
       1: ldc           #89                 // String return
       3: getstatic     #90                 // Field java/lang/Boolean.FALSE:Ljava/lang/Boolean;
       6: invokevirtual #73                 // Method java/lang/Boolean.toString:()Ljava/lang/String;
       9: invokevirtual #74                 // Method setAttachment:(Ljava/lang/String;Ljava/lang/String;)Lcom/alibaba/dubbo/rpc/RpcContext;
      12: pop
      13: aload_1
      14: invokeinterface #91,  1           // InterfaceMethod java/lang/Runnable.run:()V
      19: aload_0
      20: ldc           #89                 // String return
      22: invokevirtual #81                 // Method removeAttachment:(Ljava/lang/String;)Lcom/alibaba/dubbo/rpc/RpcContext;
      25: pop
      26: goto          71
      29: astore_2
      30: new           #83                 // class com/alibaba/dubbo/rpc/RpcException
      33: dup
      34: new           #93                 // class java/lang/StringBuilder
      37: dup
      38: invokespecial #94                 // Method java/lang/StringBuilder."<init>":()V
      41: ldc           #95                 // String oneway call error .
      43: invokevirtual #96                 // Method java/lang/StringBuilder.append:(Ljava/lang/String;)Ljava/lang/StringBuilder;
      46: aload_2
      47: invokevirtual #97                 // Method java/lang/Throwable.getMessage:()Ljava/lang/String;
      50: invokevirtual #96                 // Method java/lang/StringBuilder.append:(Ljava/lang/String;)Ljava/lang/StringBuilder;
      53: invokevirtual #98                 // Method java/lang/StringBuilder.toString:()Ljava/lang/String;
      56: aload_2
      57: invokespecial #99                 // Method com/alibaba/dubbo/rpc/RpcException."<init>":(Ljava/lang/String;Ljava/lang/Throwable;)V
      60: athrow
      61: astore_3
      62: aload_0
      63: ldc           #89                 // String return
      65: invokevirtual #81                 // Method removeAttachment:(Ljava/lang/String;)Lcom/alibaba/dubbo/rpc/RpcContext;
      68: pop
      69: aload_3
      70: athrow
      71: return
    Exception table:
       from    to  target type
           0    19    29   Class java/lang/Throwable
           0    19    61   any
          29    62    61   any

  public <T> java.util.concurrent.Future<T> getFuture();
    Code:
       0: invokestatic  #100                // Method org/apache/dubbo/rpc/FutureContext.getContext:()Lorg/apache/dubbo/rpc/FutureContext;
       3: invokevirtual #101                // Method org/apache/dubbo/rpc/FutureContext.getCompatibleCompletableFuture:()Ljava/util/concurrent/CompletableFuture;
       6: astore_1
       7: aload_1
       8: ifnonnull     13
      11: aconst_null
      12: areturn
      13: new           #102                // class com/alibaba/dubbo/rpc/protocol/dubbo/FutureAdapter
      16: dup
      17: aload_1
      18: invokespecial #103                // Method com/alibaba/dubbo/rpc/protocol/dubbo/FutureAdapter."<init>":(Ljava/util/concurrent/CompletableFuture;)V
      21: areturn

  public void setFuture(java.util.concurrent.CompletableFuture<?>);
    Code:
       0: invokestatic  #100                // Method org/apache/dubbo/rpc/FutureContext.getContext:()Lorg/apache/dubbo/rpc/FutureContext;
       3: aload_1
       4: invokevirtual #104                // Method org/apache/dubbo/rpc/FutureContext.setCompatibleFuture:(Ljava/util/concurrent/CompletableFuture;)V
       7: return
}
