Compiled from "RpcContext.java"
class com.alibaba.dubbo.rpc.RpcContext$2 implements java.util.concurrent.Future<T> {
  final com.alibaba.dubbo.rpc.RpcException val$e;

  final com.alibaba.dubbo.rpc.RpcContext this$0;

  com.alibaba.dubbo.rpc.RpcContext$2(com.alibaba.dubbo.rpc.RpcContext, com.alibaba.dubbo.rpc.RpcException);
    Code:
       0: aload_0
       1: aload_1
       2: putfield      #1                  // Field this$0:Lcom/alibaba/dubbo/rpc/RpcContext;
       5: aload_0
       6: aload_2
       7: putfield      #2                  // Field val$e:Lcom/alibaba/dubbo/rpc/RpcException;
      10: aload_0
      11: invokespecial #3                  // Method java/lang/Object."<init>":()V
      14: return

  public boolean cancel(boolean);
    Code:
       0: iconst_0
       1: ireturn

  public boolean isCancelled();
    Code:
       0: iconst_0
       1: ireturn

  public boolean isDone();
    Code:
       0: iconst_1
       1: ireturn

  public T get() throws java.lang.InterruptedException, java.util.concurrent.ExecutionException;
    Code:
       0: new           #4                  // class java/util/concurrent/ExecutionException
       3: dup
       4: aload_0
       5: getfield      #2                  // Field val$e:Lcom/alibaba/dubbo/rpc/RpcException;
       8: invokevirtual #5                  // Method com/alibaba/dubbo/rpc/RpcException.getCause:()Ljava/lang/Throwable;
      11: invokespecial #6                  // Method java/util/concurrent/ExecutionException."<init>":(Ljava/lang/Throwable;)V
      14: athrow

  public T get(long, java.util.concurrent.TimeUnit) throws java.lang.InterruptedException, java.util.concurrent.ExecutionException, java.util.concurrent.TimeoutException;
    Code:
       0: aload_0
       1: invokevirtual #7                  // Method get:()Ljava/lang/Object;
       4: areturn
}
