Compiled from "RpcContext.java"
class com.alibaba.dubbo.rpc.RpcContext$1 implements java.util.concurrent.Callable<T> {
  final java.lang.Object val$o;

  final com.alibaba.dubbo.rpc.RpcContext this$0;

  com.alibaba.dubbo.rpc.RpcContext$1(com.alibaba.dubbo.rpc.RpcContext, java.lang.Object);
    Code:
       0: aload_0
       1: aload_1
       2: putfield      #1                  // Field this$0:Lcom/alibaba/dubbo/rpc/RpcContext;
       5: aload_0
       6: aload_2
       7: putfield      #2                  // Field val$o:Ljava/lang/Object;
      10: aload_0
      11: invokespecial #3                  // Method java/lang/Object."<init>":()V
      14: return

  public T call() throws java.lang.Exception;
    Code:
       0: aload_0
       1: getfield      #2                  // Field val$o:Ljava/lang/Object;
       4: areturn
}
