Compiled from "RpcException.java"
public class com.alibaba.dubbo.rpc.RpcException extends org.apache.dubbo.rpc.RpcException {
  public com.alibaba.dubbo.rpc.RpcException();
    Code:
       0: aload_0
       1: invokespecial #1                  // Method org/apache/dubbo/rpc/RpcException."<init>":()V
       4: return

  public com.alibaba.dubbo.rpc.RpcException(java.lang.String, java.lang.Throwable);
    Code:
       0: aload_0
       1: aload_1
       2: aload_2
       3: invokespecial #2                  // Method org/apache/dubbo/rpc/RpcException."<init>":(Ljava/lang/String;Ljava/lang/Throwable;)V
       6: return

  public com.alibaba.dubbo.rpc.RpcException(java.lang.String);
    Code:
       0: aload_0
       1: aload_1
       2: invokespecial #3                  // Method org/apache/dubbo/rpc/RpcException."<init>":(Ljava/lang/String;)V
       5: return

  public com.alibaba.dubbo.rpc.RpcException(java.lang.Throwable);
    Code:
       0: aload_0
       1: aload_1
       2: invokespecial #4                  // Method org/apache/dubbo/rpc/RpcException."<init>":(Ljava/lang/Throwable;)V
       5: return

  public com.alibaba.dubbo.rpc.RpcException(int);
    Code:
       0: aload_0
       1: iload_1
       2: invokespecial #5                  // Method org/apache/dubbo/rpc/RpcException."<init>":(I)V
       5: return

  public com.alibaba.dubbo.rpc.RpcException(int, java.lang.String, java.lang.Throwable);
    Code:
       0: aload_0
       1: iload_1
       2: aload_2
       3: aload_3
       4: invokespecial #6                  // Method org/apache/dubbo/rpc/RpcException."<init>":(ILjava/lang/String;Ljava/lang/Throwable;)V
       7: return

  public com.alibaba.dubbo.rpc.RpcException(int, java.lang.String);
    Code:
       0: aload_0
       1: iload_1
       2: aload_2
       3: invokespecial #7                  // Method org/apache/dubbo/rpc/RpcException."<init>":(ILjava/lang/String;)V
       6: return

  public com.alibaba.dubbo.rpc.RpcException(int, java.lang.Throwable);
    Code:
       0: aload_0
       1: iload_1
       2: aload_2
       3: invokespecial #8                  // Method org/apache/dubbo/rpc/RpcException."<init>":(ILjava/lang/Throwable;)V
       6: return
}
