Compiled from "RpcResult.java"
public class com.alibaba.dubbo.rpc.RpcResult extends org.apache.dubbo.rpc.AppResponse implements com.alibaba.dubbo.rpc.Result {
  public com.alibaba.dubbo.rpc.RpcResult();
    Code:
       0: aload_0
       1: invokespecial #1                  // Method org/apache/dubbo/rpc/AppResponse."<init>":()V
       4: return

  public com.alibaba.dubbo.rpc.RpcResult(java.lang.Object);
    Code:
       0: aload_0
       1: aload_1
       2: invokespecial #2                  // Method org/apache/dubbo/rpc/AppResponse."<init>":(Ljava/lang/Object;)V
       5: return

  public com.alibaba.dubbo.rpc.RpcResult(java.lang.Throwable);
    Code:
       0: aload_0
       1: aload_1
       2: invokespecial #3                  // Method org/apache/dubbo/rpc/AppResponse."<init>":(Ljava/lang/Throwable;)V
       5: return
}
