Compiled from "AbstractServerCall.java"
public abstract class org.apache.dubbo.rpc.protocol.tri.call.AbstractServerCall implements org.apache.dubbo.rpc.protocol.tri.call.ServerCall,org.apache.dubbo.rpc.protocol.tri.stream.ServerStream$Listener {
  public static final java.lang.String REMOTE_ADDRESS_KEY;

  private static final org.apache.dubbo.common.logger.ErrorTypeAwareLogger LOGGER;

  public final org.apache.dubbo.rpc.Invoker<?> invoker;

  public final org.apache.dubbo.rpc.model.FrameworkModel frameworkModel;

  public final org.apache.dubbo.rpc.protocol.tri.stream.ServerStream stream;

  public final java.util.concurrent.Executor executor;

  public final java.lang.String methodName;

  public final java.lang.String serviceName;

  public final org.apache.dubbo.rpc.model.ServiceDescriptor serviceDescriptor;

  private final java.lang.String acceptEncoding;

  public boolean autoRequestN;

  public java.lang.Long timeout;

  org.apache.dubbo.rpc.protocol.tri.call.ServerCall$Listener listener;

  private org.apache.dubbo.rpc.protocol.tri.compressor.Compressor compressor;

  private boolean headerSent;

  private boolean closed;

  org.apache.dubbo.rpc.CancellationContext cancellationContext;

  protected org.apache.dubbo.rpc.model.MethodDescriptor methodDescriptor;

  protected org.apache.dubbo.rpc.model.PackableMethod packableMethod;

  protected java.util.Map<java.lang.String, java.lang.Object> requestMetadata;

  private java.lang.Integer exceptionCode;

  private boolean isNeedReturnException;

  public java.lang.Integer getExceptionCode();
    Code:
       0: aload_0
       1: getfield      #2                  // Field exceptionCode:Ljava/lang/Integer;
       4: areturn

  public void setExceptionCode(java.lang.Integer);
    Code:
       0: aload_0
       1: aload_1
       2: putfield      #2                  // Field exceptionCode:Ljava/lang/Integer;
       5: return

  public boolean isNeedReturnException();
    Code:
       0: aload_0
       1: getfield      #3                  // Field isNeedReturnException:Z
       4: ireturn

  public void setNeedReturnException(boolean);
    Code:
       0: aload_0
       1: iload_1
       2: putfield      #3                  // Field isNeedReturnException:Z
       5: return

  org.apache.dubbo.rpc.protocol.tri.call.AbstractServerCall(org.apache.dubbo.rpc.Invoker<?>, org.apache.dubbo.rpc.protocol.tri.stream.ServerStream, org.apache.dubbo.rpc.model.FrameworkModel, org.apache.dubbo.rpc.model.ServiceDescriptor, java.lang.String, java.lang.String, java.lang.String, java.util.concurrent.Executor);
    Code:
       0: aload_0
       1: invokespecial #4                  // Method java/lang/Object."<init>":()V
       4: aload_0
       5: iconst_1
       6: putfield      #5                  // Field autoRequestN:Z
       9: aload_0
      10: getstatic     #6                  // Field org/apache/dubbo/common/constants/CommonConstants.TRI_EXCEPTION_CODE_NOT_EXISTS:Ljava/lang/Integer;
      13: putfield      #2                  // Field exceptionCode:Ljava/lang/Integer;
      16: aload_0
      17: iconst_0
      18: putfield      #3                  // Field isNeedReturnException:Z
      21: aload         4
      23: new           #7                  // class java/lang/StringBuilder
      26: dup
      27: invokespecial #8                  // Method java/lang/StringBuilder."<init>":()V
      30: ldc           #9                  // String No service descriptor found for
      32: invokevirtual #10                 // Method java/lang/StringBuilder.append:(Ljava/lang/String;)Ljava/lang/StringBuilder;
      35: aload_1
      36: invokeinterface #11,  1           // InterfaceMethod org/apache/dubbo/rpc/Invoker.getUrl:()Lorg/apache/dubbo/common/URL;
      41: invokevirtual #12                 // Method java/lang/StringBuilder.append:(Ljava/lang/Object;)Ljava/lang/StringBuilder;
      44: invokevirtual #13                 // Method java/lang/StringBuilder.toString:()Ljava/lang/String;
      47: invokestatic  #14                 // Method java/util/Objects.requireNonNull:(Ljava/lang/Object;Ljava/lang/String;)Ljava/lang/Object;
      50: pop
      51: aload_0
      52: aload_1
      53: putfield      #15                 // Field invoker:Lorg/apache/dubbo/rpc/Invoker;
      56: aload_0
      57: aload         8
      59: putfield      #16                 // Field executor:Ljava/util/concurrent/Executor;
      62: aload_0
      63: aload_3
      64: putfield      #17                 // Field frameworkModel:Lorg/apache/dubbo/rpc/model/FrameworkModel;
      67: aload_0
      68: aload         4
      70: putfield      #18                 // Field serviceDescriptor:Lorg/apache/dubbo/rpc/model/ServiceDescriptor;
      73: aload_0
      74: aload         6
      76: putfield      #19                 // Field serviceName:Ljava/lang/String;
      79: aload_0
      80: aload         7
      82: putfield      #20                 // Field methodName:Ljava/lang/String;
      85: aload_0
      86: aload_2
      87: putfield      #21                 // Field stream:Lorg/apache/dubbo/rpc/protocol/tri/stream/ServerStream;
      90: aload_0
      91: aload         5
      93: putfield      #22                 // Field acceptEncoding:Ljava/lang/String;
      96: return

  public void onHeader(java.util.Map<java.lang.String, java.lang.Object>);
    Code:
       0: aload_0
       1: aload_1
       2: putfield      #23                 // Field requestMetadata:Ljava/util/Map;
       5: aload_0
       6: getfield      #18                 // Field serviceDescriptor:Lorg/apache/dubbo/rpc/model/ServiceDescriptor;
       9: ifnonnull     45
      12: aload_0
      13: getstatic     #24                 // Field org/apache/dubbo/rpc/TriRpcStatus.UNIMPLEMENTED:Lorg/apache/dubbo/rpc/TriRpcStatus;
      16: new           #7                  // class java/lang/StringBuilder
      19: dup
      20: invokespecial #8                  // Method java/lang/StringBuilder."<init>":()V
      23: ldc           #25                 // String Service not found:
      25: invokevirtual #10                 // Method java/lang/StringBuilder.append:(Ljava/lang/String;)Ljava/lang/StringBuilder;
      28: aload_0
      29: getfield      #19                 // Field serviceName:Ljava/lang/String;
      32: invokevirtual #10                 // Method java/lang/StringBuilder.append:(Ljava/lang/String;)Ljava/lang/StringBuilder;
      35: invokevirtual #13                 // Method java/lang/StringBuilder.toString:()Ljava/lang/String;
      38: invokevirtual #26                 // Method org/apache/dubbo/rpc/TriRpcStatus.withDescription:(Ljava/lang/String;)Lorg/apache/dubbo/rpc/TriRpcStatus;
      41: invokevirtual #27                 // Method responseErr:(Lorg/apache/dubbo/rpc/TriRpcStatus;)V
      44: return
      45: aload_0
      46: invokevirtual #28                 // Method startCall:()V
      49: return

  protected void startCall();
    Code:
       0: aload_0
       1: aload_0
       2: getfield      #29                 // Field methodDescriptor:Lorg/apache/dubbo/rpc/model/MethodDescriptor;
       5: invokevirtual #30                 // Method buildInvocation:(Lorg/apache/dubbo/rpc/model/MethodDescriptor;)Lorg/apache/dubbo/rpc/RpcInvocation;
       8: astore_1
       9: aload_0
      10: aload_0
      11: aload_1
      12: aload_0
      13: getfield      #29                 // Field methodDescriptor:Lorg/apache/dubbo/rpc/model/MethodDescriptor;
      16: aload_0
      17: getfield      #15                 // Field invoker:Lorg/apache/dubbo/rpc/Invoker;
      20: invokevirtual #31                 // Method startInternalCall:(Lorg/apache/dubbo/rpc/RpcInvocation;Lorg/apache/dubbo/rpc/model/MethodDescriptor;Lorg/apache/dubbo/rpc/Invoker;)Lorg/apache/dubbo/rpc/protocol/tri/call/ServerCall$Listener;
      23: putfield      #32                 // Field listener:Lorg/apache/dubbo/rpc/protocol/tri/call/ServerCall$Listener;
      26: return

  public final void request(int);
    Code:
       0: aload_0
       1: getfield      #21                 // Field stream:Lorg/apache/dubbo/rpc/protocol/tri/stream/ServerStream;
       4: iload_1
       5: invokeinterface #33,  2           // InterfaceMethod org/apache/dubbo/rpc/protocol/tri/stream/ServerStream.request:(I)V
      10: return

  public final void sendMessage(java.lang.Object);
    Code:
       0: aload_0
       1: getfield      #34                 // Field closed:Z
       4: ifeq          17
       7: new           #35                 // class java/lang/IllegalStateException
      10: dup
      11: ldc           #36                 // String Stream has already canceled
      13: invokespecial #37                 // Method java/lang/IllegalStateException."<init>":(Ljava/lang/String;)V
      16: athrow
      17: aload_0
      18: aload_1
      19: invokespecial #38                 // Method doSendMessage:(Ljava/lang/Object;)V
      22: return

  private void doSendMessage(java.lang.Object);
    Code:
       0: aload_0
       1: getfield      #34                 // Field closed:Z
       4: ifeq          8
       7: return
       8: aload_0
       9: getfield      #39                 // Field headerSent:Z
      12: ifne          19
      15: aload_0
      16: invokespecial #40                 // Method sendHeader:()V
      19: aload_0
      20: getfield      #41                 // Field packableMethod:Lorg/apache/dubbo/rpc/model/PackableMethod;
      23: aload_1
      24: invokeinterface #42,  2           // InterfaceMethod org/apache/dubbo/rpc/model/PackableMethod.packResponse:(Ljava/lang/Object;)[B
      29: astore_2
      30: goto          90
      33: astore_3
      34: aload_0
      35: getstatic     #44                 // Field org/apache/dubbo/rpc/TriRpcStatus.INTERNAL:Lorg/apache/dubbo/rpc/TriRpcStatus;
      38: ldc           #45                 // String Serialize response failed
      40: invokevirtual #26                 // Method org/apache/dubbo/rpc/TriRpcStatus.withDescription:(Ljava/lang/String;)Lorg/apache/dubbo/rpc/TriRpcStatus;
      43: aload_3
      44: invokevirtual #46                 // Method org/apache/dubbo/rpc/TriRpcStatus.withCause:(Ljava/lang/Throwable;)Lorg/apache/dubbo/rpc/TriRpcStatus;
      47: aconst_null
      48: invokevirtual #47                 // Method close:(Lorg/apache/dubbo/rpc/TriRpcStatus;Ljava/util/Map;)V
      51: getstatic     #48                 // Field LOGGER:Lorg/apache/dubbo/common/logger/ErrorTypeAwareLogger;
      54: ldc           #49                 // String 4-10
      56: ldc           #50                 // String
      58: ldc           #50                 // String
      60: ldc           #51                 // String Serialize triple response failed, service=%s method=%s
      62: iconst_2
      63: anewarray     #52                 // class java/lang/Object
      66: dup
      67: iconst_0
      68: aload_0
      69: getfield      #19                 // Field serviceName:Ljava/lang/String;
      72: aastore
      73: dup
      74: iconst_1
      75: aload_0
      76: getfield      #20                 // Field methodName:Ljava/lang/String;
      79: aastore
      80: invokestatic  #53                 // Method java/lang/String.format:(Ljava/lang/String;[Ljava/lang/Object;)Ljava/lang/String;
      83: aload_3
      84: invokeinterface #54,  6           // InterfaceMethod org/apache/dubbo/common/logger/ErrorTypeAwareLogger.error:(Ljava/lang/String;Ljava/lang/String;Ljava/lang/String;Ljava/lang/String;Ljava/lang/Throwable;)V
      89: return
      90: aload_2
      91: ifnonnull     108
      94: aload_0
      95: getstatic     #44                 // Field org/apache/dubbo/rpc/TriRpcStatus.INTERNAL:Lorg/apache/dubbo/rpc/TriRpcStatus;
      98: ldc           #55                 // String Missing response
     100: invokevirtual #26                 // Method org/apache/dubbo/rpc/TriRpcStatus.withDescription:(Ljava/lang/String;)Lorg/apache/dubbo/rpc/TriRpcStatus;
     103: aconst_null
     104: invokevirtual #47                 // Method close:(Lorg/apache/dubbo/rpc/TriRpcStatus;Ljava/util/Map;)V
     107: return
     108: aload_0
     109: getfield      #56                 // Field compressor:Lorg/apache/dubbo/rpc/protocol/tri/compressor/Compressor;
     112: ifnull        168
     115: ldc           #58                 // String identity
     117: aload_0
     118: getfield      #56                 // Field compressor:Lorg/apache/dubbo/rpc/protocol/tri/compressor/Compressor;
     121: invokeinterface #59,  1           // InterfaceMethod org/apache/dubbo/rpc/protocol/tri/compressor/Compressor.getMessageEncoding:()Ljava/lang/String;
     126: invokevirtual #60                 // Method java/lang/String.equals:(Ljava/lang/Object;)Z
     129: ifeq          136
     132: iconst_0
     133: goto          137
     136: iconst_1
     137: istore        4
     139: aload_0
     140: getfield      #56                 // Field compressor:Lorg/apache/dubbo/rpc/protocol/tri/compressor/Compressor;
     143: aload_2
     144: invokeinterface #61,  2           // InterfaceMethod org/apache/dubbo/rpc/protocol/tri/compressor/Compressor.compress:([B)[B
     149: astore        5
     151: aload_0
     152: getfield      #21                 // Field stream:Lorg/apache/dubbo/rpc/protocol/tri/stream/ServerStream;
     155: aload         5
     157: iload         4
     159: invokeinterface #62,  3           // InterfaceMethod org/apache/dubbo/rpc/protocol/tri/stream/ServerStream.sendMessage:([BI)Lio/netty/util/concurrent/Future;
     164: astore_3
     165: goto          180
     168: aload_0
     169: getfield      #21                 // Field stream:Lorg/apache/dubbo/rpc/protocol/tri/stream/ServerStream;
     172: aload_2
     173: iconst_0
     174: invokeinterface #62,  3           // InterfaceMethod org/apache/dubbo/rpc/protocol/tri/stream/ServerStream.sendMessage:([BI)Lio/netty/util/concurrent/Future;
     179: astore_3
     180: aload_3
     181: aload_0
     182: invokedynamic #63,  0             // InvokeDynamic #0:operationComplete:(Lorg/apache/dubbo/rpc/protocol/tri/call/AbstractServerCall;)Lio/netty/util/concurrent/GenericFutureListener;
     187: invokeinterface #64,  2           // InterfaceMethod io/netty/util/concurrent/Future.addListener:(Lio/netty/util/concurrent/GenericFutureListener;)Lio/netty/util/concurrent/Future;
     192: pop
     193: return
    Exception table:
       from    to  target type
          19    30    33   Class java/lang/Exception

  public final void onComplete();
    Code:
       0: aload_0
       1: getfield      #32                 // Field listener:Lorg/apache/dubbo/rpc/protocol/tri/call/ServerCall$Listener;
       4: ifnonnull     8
       7: return
       8: aload_0
       9: invokevirtual #65                 // Method isClosed:()Z
      12: ifeq          16
      15: return
      16: aload_0
      17: getfield      #32                 // Field listener:Lorg/apache/dubbo/rpc/protocol/tri/call/ServerCall$Listener;
      20: invokeinterface #66,  1           // InterfaceMethod org/apache/dubbo/rpc/protocol/tri/call/ServerCall$Listener.onComplete:()V
      25: return

  public final void onMessage(byte[], boolean);
    Code:
       0: invokestatic  #67                 // Method java/lang/Thread.currentThread:()Ljava/lang/Thread;
       3: invokevirtual #68                 // Method java/lang/Thread.getContextClassLoader:()Ljava/lang/ClassLoader;
       6: astore_3
       7: aload_0
       8: aload_1
       9: invokevirtual #69                 // Method parseSingleMessage:([B)Ljava/lang/Object;
      12: astore        4
      14: aload_0
      15: getfield      #32                 // Field listener:Lorg/apache/dubbo/rpc/protocol/tri/call/ServerCall$Listener;
      18: aload         4
      20: invokeinterface #70,  2           // InterfaceMethod org/apache/dubbo/rpc/protocol/tri/call/ServerCall$Listener.onMessage:(Ljava/lang/Object;)V
      25: aload_3
      26: invokestatic  #71                 // Method org/apache/dubbo/rpc/protocol/tri/ClassLoadUtil.switchContextLoader:(Ljava/lang/ClassLoader;)V
      29: goto          122
      32: astore        4
      34: getstatic     #72                 // Field org/apache/dubbo/rpc/TriRpcStatus.UNKNOWN:Lorg/apache/dubbo/rpc/TriRpcStatus;
      37: ldc           #73                 // String Server error
      39: invokevirtual #26                 // Method org/apache/dubbo/rpc/TriRpcStatus.withDescription:(Ljava/lang/String;)Lorg/apache/dubbo/rpc/TriRpcStatus;
      42: aload         4
      44: invokevirtual #46                 // Method org/apache/dubbo/rpc/TriRpcStatus.withCause:(Ljava/lang/Throwable;)Lorg/apache/dubbo/rpc/TriRpcStatus;
      47: astore        5
      49: aload_0
      50: aload         5
      52: aconst_null
      53: invokevirtual #47                 // Method close:(Lorg/apache/dubbo/rpc/TriRpcStatus;Ljava/util/Map;)V
      56: getstatic     #48                 // Field LOGGER:Lorg/apache/dubbo/common/logger/ErrorTypeAwareLogger;
      59: ldc           #74                 // String 4-11
      61: ldc           #50                 // String
      63: ldc           #50                 // String
      65: new           #7                  // class java/lang/StringBuilder
      68: dup
      69: invokespecial #8                  // Method java/lang/StringBuilder."<init>":()V
      72: ldc           #75                 // String Process request failed. service=
      74: invokevirtual #10                 // Method java/lang/StringBuilder.append:(Ljava/lang/String;)Ljava/lang/StringBuilder;
      77: aload_0
      78: getfield      #19                 // Field serviceName:Ljava/lang/String;
      81: invokevirtual #10                 // Method java/lang/StringBuilder.append:(Ljava/lang/String;)Ljava/lang/StringBuilder;
      84: ldc           #76                 // String  method=
      86: invokevirtual #10                 // Method java/lang/StringBuilder.append:(Ljava/lang/String;)Ljava/lang/StringBuilder;
      89: aload_0
      90: getfield      #20                 // Field methodName:Ljava/lang/String;
      93: invokevirtual #10                 // Method java/lang/StringBuilder.append:(Ljava/lang/String;)Ljava/lang/StringBuilder;
      96: invokevirtual #13                 // Method java/lang/StringBuilder.toString:()Ljava/lang/String;
      99: aload         4
     101: invokeinterface #54,  6           // InterfaceMethod org/apache/dubbo/common/logger/ErrorTypeAwareLogger.error:(Ljava/lang/String;Ljava/lang/String;Ljava/lang/String;Ljava/lang/String;Ljava/lang/Throwable;)V
     106: aload_3
     107: invokestatic  #71                 // Method org/apache/dubbo/rpc/protocol/tri/ClassLoadUtil.switchContextLoader:(Ljava/lang/ClassLoader;)V
     110: goto          122
     113: astore        6
     115: aload_3
     116: invokestatic  #71                 // Method org/apache/dubbo/rpc/protocol/tri/ClassLoadUtil.switchContextLoader:(Ljava/lang/ClassLoader;)V
     119: aload         6
     121: athrow
     122: return
    Exception table:
       from    to  target type
           7    25    32   Class java/lang/Exception
           7    25   113   any
          32   106   113   any
         113   115   113   any

  protected abstract java.lang.Object parseSingleMessage(byte[]) throws java.lang.Exception;

  public final void onCancelByRemote(org.apache.dubbo.rpc.TriRpcStatus);
    Code:
       0: aload_0
       1: iconst_1
       2: putfield      #34                 // Field closed:Z
       5: aload_0
       6: getfield      #77                 // Field cancellationContext:Lorg/apache/dubbo/rpc/CancellationContext;
       9: aload_1
      10: getfield      #78                 // Field org/apache/dubbo/rpc/TriRpcStatus.cause:Ljava/lang/Throwable;
      13: invokevirtual #79                 // Method org/apache/dubbo/rpc/CancellationContext.cancel:(Ljava/lang/Throwable;)Z
      16: pop
      17: aload_0
      18: getfield      #32                 // Field listener:Lorg/apache/dubbo/rpc/protocol/tri/call/ServerCall$Listener;
      21: aload_1
      22: invokeinterface #80,  2           // InterfaceMethod org/apache/dubbo/rpc/protocol/tri/call/ServerCall$Listener.onCancel:(Lorg/apache/dubbo/rpc/TriRpcStatus;)V
      27: return

  public final boolean isClosed();
    Code:
       0: aload_0
       1: getfield      #34                 // Field closed:Z
       4: ireturn

  protected org.apache.dubbo.rpc.RpcInvocation buildInvocation(org.apache.dubbo.rpc.model.MethodDescriptor);
    Code:
       0: aload_0
       1: getfield      #15                 // Field invoker:Lorg/apache/dubbo/rpc/Invoker;
       4: invokeinterface #11,  1           // InterfaceMethod org/apache/dubbo/rpc/Invoker.getUrl:()Lorg/apache/dubbo/common/URL;
       9: astore_2
      10: new           #81                 // class org/apache/dubbo/rpc/RpcInvocation
      13: dup
      14: aload_2
      15: invokevirtual #82                 // Method org/apache/dubbo/common/URL.getServiceModel:()Lorg/apache/dubbo/rpc/model/ServiceModel;
      18: aload_1
      19: invokeinterface #83,  1           // InterfaceMethod org/apache/dubbo/rpc/model/MethodDescriptor.getMethodName:()Ljava/lang/String;
      24: aload_0
      25: getfield      #18                 // Field serviceDescriptor:Lorg/apache/dubbo/rpc/model/ServiceDescriptor;
      28: invokeinterface #84,  1           // InterfaceMethod org/apache/dubbo/rpc/model/ServiceDescriptor.getInterfaceName:()Ljava/lang/String;
      33: aload_2
      34: invokevirtual #85                 // Method org/apache/dubbo/common/URL.getProtocolServiceKey:()Ljava/lang/String;
      37: aload_1
      38: invokeinterface #86,  1           // InterfaceMethod org/apache/dubbo/rpc/model/MethodDescriptor.getParameterClasses:()[Ljava/lang/Class;
      43: iconst_0
      44: anewarray     #52                 // class java/lang/Object
      47: invokespecial #87                 // Method org/apache/dubbo/rpc/RpcInvocation."<init>":(Lorg/apache/dubbo/rpc/model/ServiceModel;Ljava/lang/String;Ljava/lang/String;Ljava/lang/String;[Ljava/lang/Class;[Ljava/lang/Object;)V
      50: astore_3
      51: aload_3
      52: aload_2
      53: invokevirtual #88                 // Method org/apache/dubbo/common/URL.getServiceKey:()Ljava/lang/String;
      56: invokevirtual #89                 // Method org/apache/dubbo/rpc/RpcInvocation.setTargetServiceUniqueName:(Ljava/lang/String;)V
      59: aload_3
      60: aload_1
      61: invokeinterface #90,  1           // InterfaceMethod org/apache/dubbo/rpc/model/MethodDescriptor.getReturnTypes:()[Ljava/lang/reflect/Type;
      66: invokevirtual #91                 // Method org/apache/dubbo/rpc/RpcInvocation.setReturnTypes:([Ljava/lang/reflect/Type;)V
      69: aload_3
      70: aload_0
      71: getfield      #23                 // Field requestMetadata:Ljava/util/Map;
      74: invokestatic  #92                 // Method org/apache/dubbo/rpc/protocol/tri/stream/StreamUtils.toAttachments:(Ljava/util/Map;)Ljava/util/Map;
      77: invokevirtual #93                 // Method org/apache/dubbo/rpc/RpcInvocation.setObjectAttachments:(Ljava/util/Map;)V
      80: aload_3
      81: ldc           #95                 // String tri.remote.address
      83: aload_0
      84: getfield      #21                 // Field stream:Lorg/apache/dubbo/rpc/protocol/tri/stream/ServerStream;
      87: invokeinterface #96,  1           // InterfaceMethod org/apache/dubbo/rpc/protocol/tri/stream/ServerStream.remoteAddress:()Ljava/net/SocketAddress;
      92: invokevirtual #97                 // Method org/apache/dubbo/rpc/RpcInvocation.put:(Ljava/lang/Object;Ljava/lang/Object;)Ljava/lang/Object;
      95: pop
      96: aload_0
      97: getfield      #23                 // Field requestMetadata:Ljava/util/Map;
     100: getstatic     #98                 // Field org/apache/dubbo/rpc/protocol/tri/TripleHeaderEnum.TIMEOUT:Lorg/apache/dubbo/rpc/protocol/tri/TripleHeaderEnum;
     103: invokevirtual #99                 // Method org/apache/dubbo/rpc/protocol/tri/TripleHeaderEnum.getHeader:()Ljava/lang/String;
     106: invokeinterface #100,  2          // InterfaceMethod java/util/Map.get:(Ljava/lang/Object;)Ljava/lang/Object;
     111: checkcast     #101                // class java/lang/String
     114: astore        4
     116: aload         4
     118: invokestatic  #102                // Method java/util/Objects.nonNull:(Ljava/lang/Object;)Z
     121: ifeq          134
     124: aload_0
     125: aload_0
     126: aload         4
     128: invokevirtual #103                // Method parseTimeoutToMills:(Ljava/lang/String;)Ljava/lang/Long;
     131: putfield      #104                // Field timeout:Ljava/lang/Long;
     134: goto          186
     137: astore        5
     139: getstatic     #48                 // Field LOGGER:Lorg/apache/dubbo/common/logger/ErrorTypeAwareLogger;
     142: ldc           #106                // String 4-9
     144: ldc           #50                 // String
     146: ldc           #50                 // String
     148: ldc           #107                // String Failed to parse request timeout set from:%s, service=%s method=%s
     150: iconst_3
     151: anewarray     #52                 // class java/lang/Object
     154: dup
     155: iconst_0
     156: aload         4
     158: aastore
     159: dup
     160: iconst_1
     161: aload_0
     162: getfield      #18                 // Field serviceDescriptor:Lorg/apache/dubbo/rpc/model/ServiceDescriptor;
     165: invokeinterface #84,  1           // InterfaceMethod org/apache/dubbo/rpc/model/ServiceDescriptor.getInterfaceName:()Ljava/lang/String;
     170: aastore
     171: dup
     172: iconst_2
     173: aload_0
     174: getfield      #20                 // Field methodName:Ljava/lang/String;
     177: aastore
     178: invokestatic  #53                 // Method java/lang/String.format:(Ljava/lang/String;[Ljava/lang/Object;)Ljava/lang/String;
     181: invokeinterface #108,  5          // InterfaceMethod org/apache/dubbo/common/logger/ErrorTypeAwareLogger.warn:(Ljava/lang/String;Ljava/lang/String;Ljava/lang/String;Ljava/lang/String;)V
     186: aconst_null
     187: aload_0
     188: getfield      #23                 // Field requestMetadata:Ljava/util/Map;
     191: getstatic     #109                // Field org/apache/dubbo/rpc/protocol/tri/TripleHeaderEnum.CONSUMER_APP_NAME_KEY:Lorg/apache/dubbo/rpc/protocol/tri/TripleHeaderEnum;
     194: invokevirtual #99                 // Method org/apache/dubbo/rpc/protocol/tri/TripleHeaderEnum.getHeader:()Ljava/lang/String;
     197: invokeinterface #100,  2          // InterfaceMethod java/util/Map.get:(Ljava/lang/Object;)Ljava/lang/Object;
     202: if_acmpeq     228
     205: aload_3
     206: getstatic     #109                // Field org/apache/dubbo/rpc/protocol/tri/TripleHeaderEnum.CONSUMER_APP_NAME_KEY:Lorg/apache/dubbo/rpc/protocol/tri/TripleHeaderEnum;
     209: aload_0
     210: getfield      #23                 // Field requestMetadata:Ljava/util/Map;
     213: getstatic     #109                // Field org/apache/dubbo/rpc/protocol/tri/TripleHeaderEnum.CONSUMER_APP_NAME_KEY:Lorg/apache/dubbo/rpc/protocol/tri/TripleHeaderEnum;
     216: invokevirtual #99                 // Method org/apache/dubbo/rpc/protocol/tri/TripleHeaderEnum.getHeader:()Ljava/lang/String;
     219: invokeinterface #100,  2          // InterfaceMethod java/util/Map.get:(Ljava/lang/Object;)Ljava/lang/Object;
     224: invokevirtual #97                 // Method org/apache/dubbo/rpc/RpcInvocation.put:(Ljava/lang/Object;Ljava/lang/Object;)Ljava/lang/Object;
     227: pop
     228: aload_3
     229: areturn
    Exception table:
       from    to  target type
         116   134   137   Class java/lang/Throwable

  private void sendHeader();
    Code:
       0: aload_0
       1: getfield      #34                 // Field closed:Z
       4: ifeq          8
       7: return
       8: aload_0
       9: getfield      #39                 // Field headerSent:Z
      12: ifeq          25
      15: new           #35                 // class java/lang/IllegalStateException
      18: dup
      19: ldc           #110                // String Header has already sent
      21: invokespecial #37                 // Method java/lang/IllegalStateException."<init>":(Ljava/lang/String;)V
      24: athrow
      25: aload_0
      26: iconst_1
      27: putfield      #39                 // Field headerSent:Z
      30: new           #111                // class io/netty/handler/codec/http2/DefaultHttp2Headers
      33: dup
      34: invokespecial #112                // Method io/netty/handler/codec/http2/DefaultHttp2Headers."<init>":()V
      37: astore_1
      38: aload_1
      39: getstatic     #113                // Field io/netty/handler/codec/http/HttpResponseStatus.OK:Lio/netty/handler/codec/http/HttpResponseStatus;
      42: invokevirtual #114                // Method io/netty/handler/codec/http/HttpResponseStatus.codeAsText:()Lio/netty/util/AsciiString;
      45: invokevirtual #115                // Method io/netty/handler/codec/http2/DefaultHttp2Headers.status:(Ljava/lang/CharSequence;)Lio/netty/handler/codec/http2/Http2Headers;
      48: pop
      49: aload_1
      50: getstatic     #116                // Field io/netty/handler/codec/http/HttpHeaderNames.CONTENT_TYPE:Lio/netty/util/AsciiString;
      53: ldc           #118                // String application/grpc+proto
      55: invokevirtual #119                // Method io/netty/handler/codec/http2/DefaultHttp2Headers.set:(Ljava/lang/Object;Ljava/lang/Object;)Lio/netty/handler/codec/Headers;
      58: pop
      59: aload_0
      60: getfield      #22                 // Field acceptEncoding:Ljava/lang/String;
      63: ifnull        78
      66: aload_1
      67: getstatic     #120                // Field io/netty/handler/codec/http/HttpHeaderNames.ACCEPT_ENCODING:Lio/netty/util/AsciiString;
      70: aload_0
      71: getfield      #22                 // Field acceptEncoding:Ljava/lang/String;
      74: invokevirtual #119                // Method io/netty/handler/codec/http2/DefaultHttp2Headers.set:(Ljava/lang/Object;Ljava/lang/Object;)Lio/netty/handler/codec/Headers;
      77: pop
      78: aload_0
      79: getfield      #56                 // Field compressor:Lorg/apache/dubbo/rpc/protocol/tri/compressor/Compressor;
      82: ifnull        105
      85: aload_1
      86: getstatic     #121                // Field org/apache/dubbo/rpc/protocol/tri/TripleHeaderEnum.GRPC_ENCODING:Lorg/apache/dubbo/rpc/protocol/tri/TripleHeaderEnum;
      89: invokevirtual #99                 // Method org/apache/dubbo/rpc/protocol/tri/TripleHeaderEnum.getHeader:()Ljava/lang/String;
      92: aload_0
      93: getfield      #56                 // Field compressor:Lorg/apache/dubbo/rpc/protocol/tri/compressor/Compressor;
      96: invokeinterface #59,  1           // InterfaceMethod org/apache/dubbo/rpc/protocol/tri/compressor/Compressor.getMessageEncoding:()Ljava/lang/String;
     101: invokevirtual #119                // Method io/netty/handler/codec/http2/DefaultHttp2Headers.set:(Ljava/lang/Object;Ljava/lang/Object;)Lio/netty/handler/codec/Headers;
     104: pop
     105: aload_0
     106: getfield      #2                  // Field exceptionCode:Ljava/lang/Integer;
     109: getstatic     #6                  // Field org/apache/dubbo/common/constants/CommonConstants.TRI_EXCEPTION_CODE_NOT_EXISTS:Ljava/lang/Integer;
     112: invokevirtual #122                // Method java/lang/Integer.equals:(Ljava/lang/Object;)Z
     115: ifne          136
     118: aload_1
     119: getstatic     #123                // Field org/apache/dubbo/rpc/protocol/tri/TripleHeaderEnum.TRI_EXCEPTION_CODE:Lorg/apache/dubbo/rpc/protocol/tri/TripleHeaderEnum;
     122: invokevirtual #99                 // Method org/apache/dubbo/rpc/protocol/tri/TripleHeaderEnum.getHeader:()Ljava/lang/String;
     125: aload_0
     126: getfield      #2                  // Field exceptionCode:Ljava/lang/Integer;
     129: invokestatic  #124                // Method java/lang/String.valueOf:(Ljava/lang/Object;)Ljava/lang/String;
     132: invokevirtual #119                // Method io/netty/handler/codec/http2/DefaultHttp2Headers.set:(Ljava/lang/Object;Ljava/lang/Object;)Lio/netty/handler/codec/Headers;
     135: pop
     136: aload_0
     137: getfield      #21                 // Field stream:Lorg/apache/dubbo/rpc/protocol/tri/stream/ServerStream;
     140: aload_1
     141: invokeinterface #125,  2          // InterfaceMethod org/apache/dubbo/rpc/protocol/tri/stream/ServerStream.sendHeader:(Lio/netty/handler/codec/http2/Http2Headers;)Lio/netty/util/concurrent/Future;
     146: aload_0
     147: invokedynamic #126,  0            // InvokeDynamic #1:operationComplete:(Lorg/apache/dubbo/rpc/protocol/tri/call/AbstractServerCall;)Lio/netty/util/concurrent/GenericFutureListener;
     152: invokeinterface #64,  2           // InterfaceMethod io/netty/util/concurrent/Future.addListener:(Lio/netty/util/concurrent/GenericFutureListener;)Lio/netty/util/concurrent/Future;
     157: pop
     158: return

  private void cancelDual(org.apache.dubbo.rpc.TriRpcStatus);
    Code:
       0: aload_0
       1: iconst_1
       2: putfield      #34                 // Field closed:Z
       5: aload_0
       6: getfield      #32                 // Field listener:Lorg/apache/dubbo/rpc/protocol/tri/call/ServerCall$Listener;
       9: aload_1
      10: invokeinterface #80,  2           // InterfaceMethod org/apache/dubbo/rpc/protocol/tri/call/ServerCall$Listener.onCancel:(Lorg/apache/dubbo/rpc/TriRpcStatus;)V
      15: aload_0
      16: getfield      #77                 // Field cancellationContext:Lorg/apache/dubbo/rpc/CancellationContext;
      19: aload_1
      20: invokevirtual #127                // Method org/apache/dubbo/rpc/TriRpcStatus.asException:()Lorg/apache/dubbo/rpc/StatusRpcException;
      23: invokevirtual #79                 // Method org/apache/dubbo/rpc/CancellationContext.cancel:(Ljava/lang/Throwable;)Z
      26: pop
      27: return

  public void cancelByLocal(java.lang.Throwable);
    Code:
       0: aload_0
       1: getfield      #34                 // Field closed:Z
       4: ifeq          8
       7: return
       8: aload_0
       9: iconst_1
      10: putfield      #34                 // Field closed:Z
      13: aload_0
      14: getfield      #77                 // Field cancellationContext:Lorg/apache/dubbo/rpc/CancellationContext;
      17: aload_1
      18: invokevirtual #79                 // Method org/apache/dubbo/rpc/CancellationContext.cancel:(Ljava/lang/Throwable;)Z
      21: pop
      22: aload_0
      23: getfield      #21                 // Field stream:Lorg/apache/dubbo/rpc/protocol/tri/stream/ServerStream;
      26: getstatic     #128                // Field org/apache/dubbo/rpc/TriRpcStatus.CANCELLED:Lorg/apache/dubbo/rpc/TriRpcStatus;
      29: aload_1
      30: invokevirtual #46                 // Method org/apache/dubbo/rpc/TriRpcStatus.withCause:(Ljava/lang/Throwable;)Lorg/apache/dubbo/rpc/TriRpcStatus;
      33: invokeinterface #129,  2          // InterfaceMethod org/apache/dubbo/rpc/protocol/tri/stream/ServerStream.cancelByLocal:(Lorg/apache/dubbo/rpc/TriRpcStatus;)Lio/netty/util/concurrent/Future;
      38: pop
      39: return

  public void setCompression(java.lang.String);
    Code:
       0: aload_0
       1: getfield      #39                 // Field headerSent:Z
       4: ifeq          17
       7: new           #35                 // class java/lang/IllegalStateException
      10: dup
      11: ldc           #130                // String Can not set compression after header sent
      13: invokespecial #37                 // Method java/lang/IllegalStateException."<init>":(Ljava/lang/String;)V
      16: athrow
      17: aload_0
      18: aload_0
      19: getfield      #17                 // Field frameworkModel:Lorg/apache/dubbo/rpc/model/FrameworkModel;
      22: aload_1
      23: invokestatic  #131                // InterfaceMethod org/apache/dubbo/rpc/protocol/tri/compressor/Compressor.getCompressor:(Lorg/apache/dubbo/rpc/model/FrameworkModel;Ljava/lang/String;)Lorg/apache/dubbo/rpc/protocol/tri/compressor/Compressor;
      26: putfield      #56                 // Field compressor:Lorg/apache/dubbo/rpc/protocol/tri/compressor/Compressor;
      29: return

  public void disableAutoRequestN();
    Code:
       0: aload_0
       1: iconst_0
       2: putfield      #5                  // Field autoRequestN:Z
       5: return

  public boolean isAutoRequestN();
    Code:
       0: aload_0
       1: getfield      #5                  // Field autoRequestN:Z
       4: ireturn

  public void close(org.apache.dubbo.rpc.TriRpcStatus, java.util.Map<java.lang.String, java.lang.Object>);
    Code:
       0: aload_0
       1: aload_1
       2: aload_2
       3: invokespecial #132                // Method doClose:(Lorg/apache/dubbo/rpc/TriRpcStatus;Ljava/util/Map;)V
       6: return

  private void doClose(org.apache.dubbo.rpc.TriRpcStatus, java.util.Map<java.lang.String, java.lang.Object>);
    Code:
       0: aload_0
       1: getfield      #34                 // Field closed:Z
       4: ifeq          8
       7: return
       8: aload_0
       9: iconst_1
      10: putfield      #34                 // Field closed:Z
      13: aload_0
      14: getfield      #21                 // Field stream:Lorg/apache/dubbo/rpc/protocol/tri/stream/ServerStream;
      17: aload_1
      18: aload_2
      19: aload_0
      20: getfield      #3                  // Field isNeedReturnException:Z
      23: aload_0
      24: getfield      #2                  // Field exceptionCode:Ljava/lang/Integer;
      27: invokevirtual #133                // Method java/lang/Integer.intValue:()I
      30: invokeinterface #134,  5          // InterfaceMethod org/apache/dubbo/rpc/protocol/tri/stream/ServerStream.complete:(Lorg/apache/dubbo/rpc/TriRpcStatus;Ljava/util/Map;ZI)Lio/netty/util/concurrent/Future;
      35: pop
      36: return

  protected java.lang.Long parseTimeoutToMills(java.lang.String);
    Code:
       0: aload_1
       1: invokestatic  #135                // Method org/apache/dubbo/common/utils/StringUtils.isEmpty:(Ljava/lang/String;)Z
       4: ifne          16
       7: aload_1
       8: ldc           #136                // String null
      10: invokestatic  #137                // Method org/apache/dubbo/common/utils/StringUtils.isContains:(Ljava/lang/String;Ljava/lang/String;)Z
      13: ifeq          18
      16: aconst_null
      17: areturn
      18: aload_1
      19: iconst_0
      20: aload_1
      21: invokevirtual #138                // Method java/lang/String.length:()I
      24: iconst_1
      25: isub
      26: invokevirtual #139                // Method java/lang/String.substring:(II)Ljava/lang/String;
      29: invokestatic  #140                // Method java/lang/Long.parseLong:(Ljava/lang/String;)J
      32: lstore_2
      33: aload_1
      34: aload_1
      35: invokevirtual #138                // Method java/lang/String.length:()I
      38: iconst_1
      39: isub
      40: invokevirtual #141                // Method java/lang/String.charAt:(I)C
      43: istore        4
      45: iload         4
      47: lookupswitch  { // 6
                    72: 153
                    77: 142
                    83: 131
                   109: 126
                   110: 104
                   117: 115
               default: 164
          }
     104: getstatic     #142                // Field java/util/concurrent/TimeUnit.NANOSECONDS:Ljava/util/concurrent/TimeUnit;
     107: lload_2
     108: invokevirtual #143                // Method java/util/concurrent/TimeUnit.toMillis:(J)J
     111: invokestatic  #144                // Method java/lang/Long.valueOf:(J)Ljava/lang/Long;
     114: areturn
     115: getstatic     #145                // Field java/util/concurrent/TimeUnit.MICROSECONDS:Ljava/util/concurrent/TimeUnit;
     118: lload_2
     119: invokevirtual #143                // Method java/util/concurrent/TimeUnit.toMillis:(J)J
     122: invokestatic  #144                // Method java/lang/Long.valueOf:(J)Ljava/lang/Long;
     125: areturn
     126: lload_2
     127: invokestatic  #144                // Method java/lang/Long.valueOf:(J)Ljava/lang/Long;
     130: areturn
     131: getstatic     #146                // Field java/util/concurrent/TimeUnit.SECONDS:Ljava/util/concurrent/TimeUnit;
     134: lload_2
     135: invokevirtual #143                // Method java/util/concurrent/TimeUnit.toMillis:(J)J
     138: invokestatic  #144                // Method java/lang/Long.valueOf:(J)Ljava/lang/Long;
     141: areturn
     142: getstatic     #147                // Field java/util/concurrent/TimeUnit.MINUTES:Ljava/util/concurrent/TimeUnit;
     145: lload_2
     146: invokevirtual #143                // Method java/util/concurrent/TimeUnit.toMillis:(J)J
     149: invokestatic  #144                // Method java/lang/Long.valueOf:(J)Ljava/lang/Long;
     152: areturn
     153: getstatic     #148                // Field java/util/concurrent/TimeUnit.HOURS:Ljava/util/concurrent/TimeUnit;
     156: lload_2
     157: invokevirtual #143                // Method java/util/concurrent/TimeUnit.toMillis:(J)J
     160: invokestatic  #144                // Method java/lang/Long.valueOf:(J)Ljava/lang/Long;
     163: areturn
     164: aconst_null
     165: areturn

  protected void responseErr(org.apache.dubbo.rpc.TriRpcStatus);
    Code:
       0: aload_0
       1: getfield      #34                 // Field closed:Z
       4: ifeq          8
       7: return
       8: aload_0
       9: iconst_1
      10: putfield      #34                 // Field closed:Z
      13: aload_0
      14: getfield      #21                 // Field stream:Lorg/apache/dubbo/rpc/protocol/tri/stream/ServerStream;
      17: aload_1
      18: aconst_null
      19: iconst_0
      20: getstatic     #6                  // Field org/apache/dubbo/common/constants/CommonConstants.TRI_EXCEPTION_CODE_NOT_EXISTS:Ljava/lang/Integer;
      23: invokevirtual #133                // Method java/lang/Integer.intValue:()I
      26: invokeinterface #134,  5          // InterfaceMethod org/apache/dubbo/rpc/protocol/tri/stream/ServerStream.complete:(Lorg/apache/dubbo/rpc/TriRpcStatus;Ljava/util/Map;ZI)Lio/netty/util/concurrent/Future;
      31: pop
      32: getstatic     #48                 // Field LOGGER:Lorg/apache/dubbo/common/logger/ErrorTypeAwareLogger;
      35: ldc           #74                 // String 4-11
      37: ldc           #50                 // String
      39: ldc           #50                 // String
      41: new           #7                  // class java/lang/StringBuilder
      44: dup
      45: invokespecial #8                  // Method java/lang/StringBuilder."<init>":()V
      48: ldc           #149                // String Triple request error: service=
      50: invokevirtual #10                 // Method java/lang/StringBuilder.append:(Ljava/lang/String;)Ljava/lang/StringBuilder;
      53: aload_0
      54: getfield      #19                 // Field serviceName:Ljava/lang/String;
      57: invokevirtual #10                 // Method java/lang/StringBuilder.append:(Ljava/lang/String;)Ljava/lang/StringBuilder;
      60: ldc           #150                // String  method
      62: invokevirtual #10                 // Method java/lang/StringBuilder.append:(Ljava/lang/String;)Ljava/lang/StringBuilder;
      65: aload_0
      66: getfield      #20                 // Field methodName:Ljava/lang/String;
      69: invokevirtual #10                 // Method java/lang/StringBuilder.append:(Ljava/lang/String;)Ljava/lang/StringBuilder;
      72: invokevirtual #13                 // Method java/lang/StringBuilder.toString:()Ljava/lang/String;
      75: aload_1
      76: invokevirtual #127                // Method org/apache/dubbo/rpc/TriRpcStatus.asException:()Lorg/apache/dubbo/rpc/StatusRpcException;
      79: invokeinterface #54,  6           // InterfaceMethod org/apache/dubbo/common/logger/ErrorTypeAwareLogger.error:(Ljava/lang/String;Ljava/lang/String;Ljava/lang/String;Ljava/lang/String;Ljava/lang/Throwable;)V
      84: return

  protected org.apache.dubbo.rpc.protocol.tri.call.ServerCall$Listener startInternalCall(org.apache.dubbo.rpc.RpcInvocation, org.apache.dubbo.rpc.model.MethodDescriptor, org.apache.dubbo.rpc.Invoker<?>);
    Code:
       0: aload_0
       1: invokestatic  #151                // Method org/apache/dubbo/rpc/RpcContext.getCancellationContext:()Lorg/apache/dubbo/rpc/CancellationContext;
       4: putfield      #77                 // Field cancellationContext:Lorg/apache/dubbo/rpc/CancellationContext;
       7: new           #152                // class org/apache/dubbo/rpc/protocol/tri/observer/ServerCallToObserverAdapter
      10: dup
      11: aload_0
      12: aload_0
      13: getfield      #77                 // Field cancellationContext:Lorg/apache/dubbo/rpc/CancellationContext;
      16: invokespecial #153                // Method org/apache/dubbo/rpc/protocol/tri/observer/ServerCallToObserverAdapter."<init>":(Lorg/apache/dubbo/rpc/protocol/tri/call/AbstractServerCall;Lorg/apache/dubbo/rpc/CancellationContext;)V
      19: astore        4
      21: getstatic     #154                // Field org/apache/dubbo/rpc/protocol/tri/call/AbstractServerCall$1.$SwitchMap$org$apache$dubbo$rpc$model$MethodDescriptor$RpcType:[I
      24: aload_2
      25: invokeinterface #155,  1          // InterfaceMethod org/apache/dubbo/rpc/model/MethodDescriptor.getRpcType:()Lorg/apache/dubbo/rpc/model/MethodDescriptor$RpcType;
      30: invokevirtual #156                // Method org/apache/dubbo/rpc/model/MethodDescriptor$RpcType.ordinal:()I
      33: iaload
      34: tableswitch   { // 1 to 4
                     1: 64
                     2: 94
                     3: 115
                     4: 115
               default: 136
          }
      64: new           #157                // class org/apache/dubbo/rpc/protocol/tri/call/UnaryServerCallListener
      67: dup
      68: aload_1
      69: aload_3
      70: aload         4
      72: aload_0
      73: getfield      #41                 // Field packableMethod:Lorg/apache/dubbo/rpc/model/PackableMethod;
      76: invokeinterface #158,  1          // InterfaceMethod org/apache/dubbo/rpc/model/PackableMethod.needWrapper:()Z
      81: invokespecial #159                // Method org/apache/dubbo/rpc/protocol/tri/call/UnaryServerCallListener."<init>":(Lorg/apache/dubbo/rpc/RpcInvocation;Lorg/apache/dubbo/rpc/Invoker;Lorg/apache/dubbo/rpc/protocol/tri/observer/ServerCallToObserverAdapter;Z)V
      84: astore        5
      86: aload_0
      87: iconst_2
      88: invokevirtual #160                // Method request:(I)V
      91: goto          146
      94: new           #161                // class org/apache/dubbo/rpc/protocol/tri/call/ServerStreamServerCallListener
      97: dup
      98: aload_1
      99: aload_3
     100: aload         4
     102: invokespecial #162                // Method org/apache/dubbo/rpc/protocol/tri/call/ServerStreamServerCallListener."<init>":(Lorg/apache/dubbo/rpc/RpcInvocation;Lorg/apache/dubbo/rpc/Invoker;Lorg/apache/dubbo/rpc/protocol/tri/observer/ServerCallToObserverAdapter;)V
     105: astore        5
     107: aload_0
     108: iconst_2
     109: invokevirtual #160                // Method request:(I)V
     112: goto          146
     115: new           #163                // class org/apache/dubbo/rpc/protocol/tri/call/BiStreamServerCallListener
     118: dup
     119: aload_1
     120: aload_3
     121: aload         4
     123: invokespecial #164                // Method org/apache/dubbo/rpc/protocol/tri/call/BiStreamServerCallListener."<init>":(Lorg/apache/dubbo/rpc/RpcInvocation;Lorg/apache/dubbo/rpc/Invoker;Lorg/apache/dubbo/rpc/protocol/tri/observer/ServerCallToObserverAdapter;)V
     126: astore        5
     128: aload_0
     129: iconst_1
     130: invokevirtual #160                // Method request:(I)V
     133: goto          146
     136: new           #35                 // class java/lang/IllegalStateException
     139: dup
     140: ldc           #165                // String Can not reach here
     142: invokespecial #37                 // Method java/lang/IllegalStateException."<init>":(Ljava/lang/String;)V
     145: athrow
     146: aload         5
     148: areturn
     149: astore        5
     151: getstatic     #48                 // Field LOGGER:Lorg/apache/dubbo/common/logger/ErrorTypeAwareLogger;
     154: ldc           #166                // String 4-12
     156: ldc           #50                 // String
     158: ldc           #50                 // String
     160: ldc           #167                // String Create triple stream failed
     162: aload         5
     164: invokeinterface #54,  6           // InterfaceMethod org/apache/dubbo/common/logger/ErrorTypeAwareLogger.error:(Ljava/lang/String;Ljava/lang/String;Ljava/lang/String;Ljava/lang/String;Ljava/lang/Throwable;)V
     169: aload_0
     170: getstatic     #44                 // Field org/apache/dubbo/rpc/TriRpcStatus.INTERNAL:Lorg/apache/dubbo/rpc/TriRpcStatus;
     173: ldc           #168                // String Create stream failed
     175: invokevirtual #26                 // Method org/apache/dubbo/rpc/TriRpcStatus.withDescription:(Ljava/lang/String;)Lorg/apache/dubbo/rpc/TriRpcStatus;
     178: aload         5
     180: invokevirtual #46                 // Method org/apache/dubbo/rpc/TriRpcStatus.withCause:(Ljava/lang/Throwable;)Lorg/apache/dubbo/rpc/TriRpcStatus;
     183: invokevirtual #27                 // Method responseErr:(Lorg/apache/dubbo/rpc/TriRpcStatus;)V
     186: aconst_null
     187: areturn
    Exception table:
       from    to  target type
          21   148   149   Class java/lang/Exception

  private void lambda$sendHeader$1(io.netty.util.concurrent.Future) throws java.lang.Exception;
    Code:
       0: aload_1
       1: invokeinterface #169,  1          // InterfaceMethod io/netty/util/concurrent/Future.isSuccess:()Z
       6: ifne          25
       9: aload_0
      10: getstatic     #44                 // Field org/apache/dubbo/rpc/TriRpcStatus.INTERNAL:Lorg/apache/dubbo/rpc/TriRpcStatus;
      13: aload_1
      14: invokeinterface #170,  1          // InterfaceMethod io/netty/util/concurrent/Future.cause:()Ljava/lang/Throwable;
      19: invokevirtual #46                 // Method org/apache/dubbo/rpc/TriRpcStatus.withCause:(Ljava/lang/Throwable;)Lorg/apache/dubbo/rpc/TriRpcStatus;
      22: invokespecial #171                // Method cancelDual:(Lorg/apache/dubbo/rpc/TriRpcStatus;)V
      25: return

  private void lambda$doSendMessage$0(io.netty.util.concurrent.Future) throws java.lang.Exception;
    Code:
       0: aload_1
       1: invokeinterface #169,  1          // InterfaceMethod io/netty/util/concurrent/Future.isSuccess:()Z
       6: ifne          30
       9: aload_0
      10: getstatic     #128                // Field org/apache/dubbo/rpc/TriRpcStatus.CANCELLED:Lorg/apache/dubbo/rpc/TriRpcStatus;
      13: ldc           #172                // String Send message failed
      15: invokevirtual #26                 // Method org/apache/dubbo/rpc/TriRpcStatus.withDescription:(Ljava/lang/String;)Lorg/apache/dubbo/rpc/TriRpcStatus;
      18: aload_1
      19: invokeinterface #170,  1          // InterfaceMethod io/netty/util/concurrent/Future.cause:()Ljava/lang/Throwable;
      24: invokevirtual #46                 // Method org/apache/dubbo/rpc/TriRpcStatus.withCause:(Ljava/lang/Throwable;)Lorg/apache/dubbo/rpc/TriRpcStatus;
      27: invokespecial #171                // Method cancelDual:(Lorg/apache/dubbo/rpc/TriRpcStatus;)V
      30: return

  static {};
    Code:
       0: ldc           #94                 // class org/apache/dubbo/rpc/protocol/tri/call/AbstractServerCall
       2: invokestatic  #173                // Method org/apache/dubbo/common/logger/LoggerFactory.getErrorTypeAwareLogger:(Ljava/lang/Class;)Lorg/apache/dubbo/common/logger/ErrorTypeAwareLogger;
       5: putstatic     #48                 // Field LOGGER:Lorg/apache/dubbo/common/logger/ErrorTypeAwareLogger;
       8: return
}
