Compiled from "TripleClientCall.java"
public class org.apache.dubbo.rpc.protocol.tri.call.TripleClientCall implements org.apache.dubbo.rpc.protocol.tri.call.ClientCall,org.apache.dubbo.rpc.protocol.tri.stream.ClientStream$Listener {
  private static final org.apache.dubbo.common.logger.ErrorTypeAwareLogger LOGGER;

  private final org.apache.dubbo.remoting.api.connection.AbstractConnectionClient connectionClient;

  private final java.util.concurrent.Executor executor;

  private final org.apache.dubbo.rpc.model.FrameworkModel frameworkModel;

  private final org.apache.dubbo.rpc.protocol.tri.transport.TripleWriteQueue writeQueue;

  private org.apache.dubbo.rpc.protocol.tri.RequestMetadata requestMetadata;

  private org.apache.dubbo.rpc.protocol.tri.stream.ClientStream stream;

  private org.apache.dubbo.rpc.protocol.tri.call.ClientCall$Listener listener;

  private boolean canceled;

  private boolean headerSent;

  private boolean autoRequest;

  private boolean done;

  private io.netty.handler.codec.http2.Http2Exception$StreamException streamException;

  public org.apache.dubbo.rpc.protocol.tri.call.TripleClientCall(org.apache.dubbo.remoting.api.connection.AbstractConnectionClient, java.util.concurrent.Executor, org.apache.dubbo.rpc.model.FrameworkModel, org.apache.dubbo.rpc.protocol.tri.transport.TripleWriteQueue);
    Code:
       0: aload_0
       1: invokespecial #2                  // Method java/lang/Object."<init>":()V
       4: aload_0
       5: iconst_1
       6: putfield      #3                  // Field autoRequest:Z
       9: aload_0
      10: aload_1
      11: putfield      #4                  // Field connectionClient:Lorg/apache/dubbo/remoting/api/connection/AbstractConnectionClient;
      14: aload_0
      15: aload_2
      16: putfield      #5                  // Field executor:Ljava/util/concurrent/Executor;
      19: aload_0
      20: aload_3
      21: putfield      #6                  // Field frameworkModel:Lorg/apache/dubbo/rpc/model/FrameworkModel;
      24: aload_0
      25: aload         4
      27: putfield      #7                  // Field writeQueue:Lorg/apache/dubbo/rpc/protocol/tri/transport/TripleWriteQueue;
      30: return

  public void onMessage(byte[], boolean);
    Code:
       0: aload_0
       1: getfield      #8                  // Field done:Z
       4: ifeq          79
       7: getstatic     #9                  // Field LOGGER:Lorg/apache/dubbo/common/logger/ErrorTypeAwareLogger;
      10: ldc           #10                 // String 4-15
      12: ldc           #11                 // String
      14: ldc           #11                 // String
      16: new           #12                 // class java/lang/StringBuilder
      19: dup
      20: invokespecial #13                 // Method java/lang/StringBuilder."<init>":()V
      23: ldc           #14                 // String Received message from closed stream,connection=
      25: invokevirtual #15                 // Method java/lang/StringBuilder.append:(Ljava/lang/String;)Ljava/lang/StringBuilder;
      28: aload_0
      29: getfield      #4                  // Field connectionClient:Lorg/apache/dubbo/remoting/api/connection/AbstractConnectionClient;
      32: invokevirtual #16                 // Method java/lang/StringBuilder.append:(Ljava/lang/Object;)Ljava/lang/StringBuilder;
      35: ldc           #17                 // String  service=
      37: invokevirtual #15                 // Method java/lang/StringBuilder.append:(Ljava/lang/String;)Ljava/lang/StringBuilder;
      40: aload_0
      41: getfield      #18                 // Field requestMetadata:Lorg/apache/dubbo/rpc/protocol/tri/RequestMetadata;
      44: getfield      #19                 // Field org/apache/dubbo/rpc/protocol/tri/RequestMetadata.service:Ljava/lang/String;
      47: invokevirtual #15                 // Method java/lang/StringBuilder.append:(Ljava/lang/String;)Ljava/lang/StringBuilder;
      50: ldc           #20                 // String  method=
      52: invokevirtual #15                 // Method java/lang/StringBuilder.append:(Ljava/lang/String;)Ljava/lang/StringBuilder;
      55: aload_0
      56: getfield      #18                 // Field requestMetadata:Lorg/apache/dubbo/rpc/protocol/tri/RequestMetadata;
      59: getfield      #21                 // Field org/apache/dubbo/rpc/protocol/tri/RequestMetadata.method:Lorg/apache/dubbo/rpc/model/MethodDescriptor;
      62: invokeinterface #22,  1           // InterfaceMethod org/apache/dubbo/rpc/model/MethodDescriptor.getMethodName:()Ljava/lang/String;
      67: invokevirtual #15                 // Method java/lang/StringBuilder.append:(Ljava/lang/String;)Ljava/lang/StringBuilder;
      70: invokevirtual #23                 // Method java/lang/StringBuilder.toString:()Ljava/lang/String;
      73: invokeinterface #24,  5           // InterfaceMethod org/apache/dubbo/common/logger/ErrorTypeAwareLogger.warn:(Ljava/lang/String;Ljava/lang/String;Ljava/lang/String;Ljava/lang/String;)V
      78: return
      79: aload_0
      80: getfield      #18                 // Field requestMetadata:Lorg/apache/dubbo/rpc/protocol/tri/RequestMetadata;
      83: getfield      #25                 // Field org/apache/dubbo/rpc/protocol/tri/RequestMetadata.packableMethod:Lorg/apache/dubbo/rpc/model/PackableMethod;
      86: aload_1
      87: iload_2
      88: invokeinterface #26,  3           // InterfaceMethod org/apache/dubbo/rpc/model/PackableMethod.parseResponse:([BZ)Ljava/lang/Object;
      93: astore_3
      94: aload_0
      95: getfield      #27                 // Field listener:Lorg/apache/dubbo/rpc/protocol/tri/call/ClientCall$Listener;
      98: aload_3
      99: invokeinterface #28,  2           // InterfaceMethod org/apache/dubbo/rpc/protocol/tri/call/ClientCall$Listener.onMessage:(Ljava/lang/Object;)V
     104: goto          200
     107: astore_3
     108: getstatic     #30                 // Field org/apache/dubbo/rpc/TriRpcStatus.INTERNAL:Lorg/apache/dubbo/rpc/TriRpcStatus;
     111: ldc           #31                 // String Deserialize response failed
     113: invokevirtual #32                 // Method org/apache/dubbo/rpc/TriRpcStatus.withDescription:(Ljava/lang/String;)Lorg/apache/dubbo/rpc/TriRpcStatus;
     116: aload_3
     117: invokevirtual #33                 // Method org/apache/dubbo/rpc/TriRpcStatus.withCause:(Ljava/lang/Throwable;)Lorg/apache/dubbo/rpc/TriRpcStatus;
     120: astore        4
     122: aload_0
     123: aload         4
     125: invokevirtual #34                 // Method org/apache/dubbo/rpc/TriRpcStatus.asException:()Lorg/apache/dubbo/rpc/StatusRpcException;
     128: invokevirtual #35                 // Method cancelByLocal:(Ljava/lang/Throwable;)V
     131: aload_0
     132: getfield      #27                 // Field listener:Lorg/apache/dubbo/rpc/protocol/tri/call/ClientCall$Listener;
     135: aload         4
     137: aconst_null
     138: iconst_0
     139: invokeinterface #36,  4           // InterfaceMethod org/apache/dubbo/rpc/protocol/tri/call/ClientCall$Listener.onClose:(Lorg/apache/dubbo/rpc/TriRpcStatus;Ljava/util/Map;Z)V
     144: getstatic     #9                  // Field LOGGER:Lorg/apache/dubbo/common/logger/ErrorTypeAwareLogger;
     147: ldc           #37                 // String 4-14
     149: ldc           #11                 // String
     151: ldc           #11                 // String
     153: ldc           #38                 // String Failed to deserialize triple response, service=%s, method=%s,connection=%s
     155: iconst_3
     156: anewarray     #39                 // class java/lang/Object
     159: dup
     160: iconst_0
     161: aload_0
     162: getfield      #4                  // Field connectionClient:Lorg/apache/dubbo/remoting/api/connection/AbstractConnectionClient;
     165: aastore
     166: dup
     167: iconst_1
     168: aload_0
     169: getfield      #18                 // Field requestMetadata:Lorg/apache/dubbo/rpc/protocol/tri/RequestMetadata;
     172: getfield      #19                 // Field org/apache/dubbo/rpc/protocol/tri/RequestMetadata.service:Ljava/lang/String;
     175: aastore
     176: dup
     177: iconst_2
     178: aload_0
     179: getfield      #18                 // Field requestMetadata:Lorg/apache/dubbo/rpc/protocol/tri/RequestMetadata;
     182: getfield      #21                 // Field org/apache/dubbo/rpc/protocol/tri/RequestMetadata.method:Lorg/apache/dubbo/rpc/model/MethodDescriptor;
     185: invokeinterface #22,  1           // InterfaceMethod org/apache/dubbo/rpc/model/MethodDescriptor.getMethodName:()Ljava/lang/String;
     190: aastore
     191: invokestatic  #40                 // Method java/lang/String.format:(Ljava/lang/String;[Ljava/lang/Object;)Ljava/lang/String;
     194: aload_3
     195: invokeinterface #41,  6           // InterfaceMethod org/apache/dubbo/common/logger/ErrorTypeAwareLogger.error:(Ljava/lang/String;Ljava/lang/String;Ljava/lang/String;Ljava/lang/String;Ljava/lang/Throwable;)V
     200: return
    Exception table:
       from    to  target type
          79   104   107   Class java/lang/Throwable

  public void onCancelByRemote(org.apache.dubbo.rpc.TriRpcStatus);
    Code:
       0: aload_0
       1: getfield      #42                 // Field canceled:Z
       4: ifeq          8
       7: return
       8: aload_0
       9: iconst_1
      10: putfield      #42                 // Field canceled:Z
      13: aload_0
      14: getfield      #18                 // Field requestMetadata:Lorg/apache/dubbo/rpc/protocol/tri/RequestMetadata;
      17: getfield      #43                 // Field org/apache/dubbo/rpc/protocol/tri/RequestMetadata.cancellationContext:Lorg/apache/dubbo/rpc/CancellationContext;
      20: ifnull        38
      23: aload_0
      24: getfield      #18                 // Field requestMetadata:Lorg/apache/dubbo/rpc/protocol/tri/RequestMetadata;
      27: getfield      #43                 // Field org/apache/dubbo/rpc/protocol/tri/RequestMetadata.cancellationContext:Lorg/apache/dubbo/rpc/CancellationContext;
      30: aload_1
      31: invokevirtual #34                 // Method org/apache/dubbo/rpc/TriRpcStatus.asException:()Lorg/apache/dubbo/rpc/StatusRpcException;
      34: invokevirtual #44                 // Method org/apache/dubbo/rpc/CancellationContext.cancel:(Ljava/lang/Throwable;)Z
      37: pop
      38: aload_0
      39: aload_1
      40: aconst_null
      41: aconst_null
      42: iconst_0
      43: invokevirtual #45                 // Method onComplete:(Lorg/apache/dubbo/rpc/TriRpcStatus;Ljava/util/Map;Ljava/util/Map;Z)V
      46: return

  public void onComplete(org.apache.dubbo.rpc.TriRpcStatus, java.util.Map<java.lang.String, java.lang.Object>, java.util.Map<java.lang.String, java.lang.String>, boolean);
    Code:
       0: aload_0
       1: getfield      #8                  // Field done:Z
       4: ifeq          8
       7: return
       8: aload_0
       9: iconst_1
      10: putfield      #8                  // Field done:Z
      13: aload_0
      14: getfield      #27                 // Field listener:Lorg/apache/dubbo/rpc/protocol/tri/call/ClientCall$Listener;
      17: aload_1
      18: aload_2
      19: invokestatic  #46                 // Method org/apache/dubbo/rpc/protocol/tri/stream/StreamUtils.toAttachments:(Ljava/util/Map;)Ljava/util/Map;
      22: iload         4
      24: invokeinterface #36,  4           // InterfaceMethod org/apache/dubbo/rpc/protocol/tri/call/ClientCall$Listener.onClose:(Lorg/apache/dubbo/rpc/TriRpcStatus;Ljava/util/Map;Z)V
      29: goto          54
      32: astore        5
      34: aload_0
      35: getstatic     #30                 // Field org/apache/dubbo/rpc/TriRpcStatus.INTERNAL:Lorg/apache/dubbo/rpc/TriRpcStatus;
      38: ldc           #47                 // String Close stream error
      40: invokevirtual #32                 // Method org/apache/dubbo/rpc/TriRpcStatus.withDescription:(Ljava/lang/String;)Lorg/apache/dubbo/rpc/TriRpcStatus;
      43: aload         5
      45: invokevirtual #33                 // Method org/apache/dubbo/rpc/TriRpcStatus.withCause:(Ljava/lang/Throwable;)Lorg/apache/dubbo/rpc/TriRpcStatus;
      48: invokevirtual #34                 // Method org/apache/dubbo/rpc/TriRpcStatus.asException:()Lorg/apache/dubbo/rpc/StatusRpcException;
      51: invokevirtual #35                 // Method cancelByLocal:(Ljava/lang/Throwable;)V
      54: aload_0
      55: getfield      #18                 // Field requestMetadata:Lorg/apache/dubbo/rpc/protocol/tri/RequestMetadata;
      58: getfield      #43                 // Field org/apache/dubbo/rpc/protocol/tri/RequestMetadata.cancellationContext:Lorg/apache/dubbo/rpc/CancellationContext;
      61: ifnull        76
      64: aload_0
      65: getfield      #18                 // Field requestMetadata:Lorg/apache/dubbo/rpc/protocol/tri/RequestMetadata;
      68: getfield      #43                 // Field org/apache/dubbo/rpc/protocol/tri/RequestMetadata.cancellationContext:Lorg/apache/dubbo/rpc/CancellationContext;
      71: aconst_null
      72: invokevirtual #44                 // Method org/apache/dubbo/rpc/CancellationContext.cancel:(Ljava/lang/Throwable;)Z
      75: pop
      76: return
    Exception table:
       from    to  target type
          13    29    32   Class java/lang/Throwable

  public void onStart();
    Code:
       0: aload_0
       1: getfield      #27                 // Field listener:Lorg/apache/dubbo/rpc/protocol/tri/call/ClientCall$Listener;
       4: aload_0
       5: invokeinterface #48,  2           // InterfaceMethod org/apache/dubbo/rpc/protocol/tri/call/ClientCall$Listener.onStart:(Lorg/apache/dubbo/rpc/protocol/tri/call/ClientCall;)V
      10: return

  public void cancelByLocal(java.lang.Throwable);
    Code:
       0: aload_0
       1: getfield      #42                 // Field canceled:Z
       4: ifeq          8
       7: return
       8: aload_0
       9: getfield      #49                 // Field headerSent:Z
      12: ifne          16
      15: return
      16: aload_0
      17: iconst_1
      18: putfield      #42                 // Field canceled:Z
      21: aload_0
      22: getfield      #50                 // Field stream:Lorg/apache/dubbo/rpc/protocol/tri/stream/ClientStream;
      25: ifnonnull     29
      28: return
      29: aload_1
      30: instanceof    #51                 // class io/netty/handler/codec/http2/Http2Exception$StreamException
      33: ifeq          87
      36: aload_1
      37: checkcast     #51                 // class io/netty/handler/codec/http2/Http2Exception$StreamException
      40: invokevirtual #52                 // Method io/netty/handler/codec/http2/Http2Exception$StreamException.error:()Lio/netty/handler/codec/http2/Http2Error;
      43: getstatic     #53                 // Field io/netty/handler/codec/http2/Http2Error.FLOW_CONTROL_ERROR:Lio/netty/handler/codec/http2/Http2Error;
      46: invokevirtual #54                 // Method io/netty/handler/codec/http2/Http2Error.equals:(Ljava/lang/Object;)Z
      49: ifeq          87
      52: getstatic     #55                 // Field org/apache/dubbo/rpc/TriRpcStatus.CANCELLED:Lorg/apache/dubbo/rpc/TriRpcStatus;
      55: aload_1
      56: invokevirtual #33                 // Method org/apache/dubbo/rpc/TriRpcStatus.withCause:(Ljava/lang/Throwable;)Lorg/apache/dubbo/rpc/TriRpcStatus;
      59: ldc           #56                 // String Due flowcontrol over pendingbytes, Cancelled by client
      61: invokevirtual #32                 // Method org/apache/dubbo/rpc/TriRpcStatus.withDescription:(Ljava/lang/String;)Lorg/apache/dubbo/rpc/TriRpcStatus;
      64: astore_2
      65: aload_0
      66: getfield      #50                 // Field stream:Lorg/apache/dubbo/rpc/protocol/tri/stream/ClientStream;
      69: aload_2
      70: invokeinterface #57,  2           // InterfaceMethod org/apache/dubbo/rpc/protocol/tri/stream/ClientStream.cancelByLocal:(Lorg/apache/dubbo/rpc/TriRpcStatus;)Lio/netty/util/concurrent/Future;
      75: pop
      76: aload_0
      77: aload_1
      78: checkcast     #51                 // class io/netty/handler/codec/http2/Http2Exception$StreamException
      81: putfield      #58                 // Field streamException:Lio/netty/handler/codec/http2/Http2Exception$StreamException;
      84: goto          111
      87: getstatic     #55                 // Field org/apache/dubbo/rpc/TriRpcStatus.CANCELLED:Lorg/apache/dubbo/rpc/TriRpcStatus;
      90: aload_1
      91: invokevirtual #33                 // Method org/apache/dubbo/rpc/TriRpcStatus.withCause:(Ljava/lang/Throwable;)Lorg/apache/dubbo/rpc/TriRpcStatus;
      94: ldc           #59                 // String Cancelled by client
      96: invokevirtual #32                 // Method org/apache/dubbo/rpc/TriRpcStatus.withDescription:(Ljava/lang/String;)Lorg/apache/dubbo/rpc/TriRpcStatus;
      99: astore_2
     100: aload_0
     101: getfield      #50                 // Field stream:Lorg/apache/dubbo/rpc/protocol/tri/stream/ClientStream;
     104: aload_2
     105: invokeinterface #57,  2           // InterfaceMethod org/apache/dubbo/rpc/protocol/tri/stream/ClientStream.cancelByLocal:(Lorg/apache/dubbo/rpc/TriRpcStatus;)Lio/netty/util/concurrent/Future;
     110: pop
     111: getstatic     #55                 // Field org/apache/dubbo/rpc/TriRpcStatus.CANCELLED:Lorg/apache/dubbo/rpc/TriRpcStatus;
     114: aload_1
     115: invokevirtual #33                 // Method org/apache/dubbo/rpc/TriRpcStatus.withCause:(Ljava/lang/Throwable;)Lorg/apache/dubbo/rpc/TriRpcStatus;
     118: ldc           #59                 // String Cancelled by client
     120: invokevirtual #32                 // Method org/apache/dubbo/rpc/TriRpcStatus.withDescription:(Ljava/lang/String;)Lorg/apache/dubbo/rpc/TriRpcStatus;
     123: astore_2
     124: aload_0
     125: getfield      #50                 // Field stream:Lorg/apache/dubbo/rpc/protocol/tri/stream/ClientStream;
     128: aload_2
     129: invokeinterface #57,  2           // InterfaceMethod org/apache/dubbo/rpc/protocol/tri/stream/ClientStream.cancelByLocal:(Lorg/apache/dubbo/rpc/TriRpcStatus;)Lio/netty/util/concurrent/Future;
     134: pop
     135: aload_0
     136: getfield      #18                 // Field requestMetadata:Lorg/apache/dubbo/rpc/protocol/tri/RequestMetadata;
     139: getfield      #43                 // Field org/apache/dubbo/rpc/protocol/tri/RequestMetadata.cancellationContext:Lorg/apache/dubbo/rpc/CancellationContext;
     142: ifnull        157
     145: aload_0
     146: getfield      #18                 // Field requestMetadata:Lorg/apache/dubbo/rpc/protocol/tri/RequestMetadata;
     149: getfield      #43                 // Field org/apache/dubbo/rpc/protocol/tri/RequestMetadata.cancellationContext:Lorg/apache/dubbo/rpc/CancellationContext;
     152: aload_1
     153: invokevirtual #44                 // Method org/apache/dubbo/rpc/CancellationContext.cancel:(Ljava/lang/Throwable;)Z
     156: pop
     157: return

  public void request(int);
    Code:
       0: aload_0
       1: getfield      #50                 // Field stream:Lorg/apache/dubbo/rpc/protocol/tri/stream/ClientStream;
       4: iload_1
       5: invokeinterface #60,  2           // InterfaceMethod org/apache/dubbo/rpc/protocol/tri/stream/ClientStream.request:(I)V
      10: return

  public void sendMessage(java.lang.Object);
    Code:
       0: aload_0
       1: getfield      #42                 // Field canceled:Z
       4: ifeq          25
       7: aconst_null
       8: aload_0
       9: getfield      #58                 // Field streamException:Lio/netty/handler/codec/http2/Http2Exception$StreamException;
      12: if_acmpeq     25
      15: new           #61                 // class java/lang/IllegalStateException
      18: dup
      19: ldc           #62                 // String Due flowcontrol over pendingbytes, Call already canceled
      21: invokespecial #63                 // Method java/lang/IllegalStateException."<init>":(Ljava/lang/String;)V
      24: athrow
      25: aload_0
      26: getfield      #42                 // Field canceled:Z
      29: ifeq          42
      32: new           #61                 // class java/lang/IllegalStateException
      35: dup
      36: ldc           #64                 // String Call already canceled
      38: invokespecial #63                 // Method java/lang/IllegalStateException."<init>":(Ljava/lang/String;)V
      41: athrow
      42: aload_0
      43: getfield      #49                 // Field headerSent:Z
      46: ifne          71
      49: aload_0
      50: iconst_1
      51: putfield      #49                 // Field headerSent:Z
      54: aload_0
      55: getfield      #50                 // Field stream:Lorg/apache/dubbo/rpc/protocol/tri/stream/ClientStream;
      58: aload_0
      59: getfield      #18                 // Field requestMetadata:Lorg/apache/dubbo/rpc/protocol/tri/RequestMetadata;
      62: invokevirtual #65                 // Method org/apache/dubbo/rpc/protocol/tri/RequestMetadata.toHeaders:()Lio/netty/handler/codec/http2/DefaultHttp2Headers;
      65: invokeinterface #66,  2           // InterfaceMethod org/apache/dubbo/rpc/protocol/tri/stream/ClientStream.sendHeader:(Lio/netty/handler/codec/http2/Http2Headers;)Lio/netty/util/concurrent/Future;
      70: pop
      71: aload_0
      72: getfield      #18                 // Field requestMetadata:Lorg/apache/dubbo/rpc/protocol/tri/RequestMetadata;
      75: getfield      #25                 // Field org/apache/dubbo/rpc/protocol/tri/RequestMetadata.packableMethod:Lorg/apache/dubbo/rpc/model/PackableMethod;
      78: aload_1
      79: invokeinterface #67,  2           // InterfaceMethod org/apache/dubbo/rpc/model/PackableMethod.packRequest:(Ljava/lang/Object;)[B
      84: astore_2
      85: ldc           #69                 // String identity
      87: aload_0
      88: getfield      #18                 // Field requestMetadata:Lorg/apache/dubbo/rpc/protocol/tri/RequestMetadata;
      91: getfield      #70                 // Field org/apache/dubbo/rpc/protocol/tri/RequestMetadata.compressor:Lorg/apache/dubbo/rpc/protocol/tri/compressor/Compressor;
      94: invokeinterface #71,  1           // InterfaceMethod org/apache/dubbo/rpc/protocol/tri/compressor/Compressor.getMessageEncoding:()Ljava/lang/String;
      99: invokevirtual #72                 // Method java/lang/String.equals:(Ljava/lang/Object;)Z
     102: ifeq          109
     105: iconst_0
     106: goto          110
     109: iconst_1
     110: istore_3
     111: aload_0
     112: getfield      #18                 // Field requestMetadata:Lorg/apache/dubbo/rpc/protocol/tri/RequestMetadata;
     115: getfield      #70                 // Field org/apache/dubbo/rpc/protocol/tri/RequestMetadata.compressor:Lorg/apache/dubbo/rpc/protocol/tri/compressor/Compressor;
     118: aload_2
     119: invokeinterface #73,  2           // InterfaceMethod org/apache/dubbo/rpc/protocol/tri/compressor/Compressor.compress:([B)[B
     124: astore        4
     126: aload_0
     127: getfield      #50                 // Field stream:Lorg/apache/dubbo/rpc/protocol/tri/stream/ClientStream;
     130: aload         4
     132: iload_3
     133: iconst_0
     134: invokeinterface #74,  4           // InterfaceMethod org/apache/dubbo/rpc/protocol/tri/stream/ClientStream.sendMessage:([BIZ)Lio/netty/util/concurrent/Future;
     139: aload_0
     140: invokedynamic #75,  0             // InvokeDynamic #0:operationComplete:(Lorg/apache/dubbo/rpc/protocol/tri/call/TripleClientCall;)Lio/netty/util/concurrent/GenericFutureListener;
     145: invokeinterface #76,  2           // InterfaceMethod io/netty/util/concurrent/Future.addListener:(Lio/netty/util/concurrent/GenericFutureListener;)Lio/netty/util/concurrent/Future;
     150: pop
     151: goto          227
     154: astore_3
     155: getstatic     #9                  // Field LOGGER:Lorg/apache/dubbo/common/logger/ErrorTypeAwareLogger;
     158: ldc           #77                 // String 4-10
     160: ldc           #11                 // String
     162: ldc           #11                 // String
     164: ldc           #78                 // String Serialize triple request failed, service=%s method=%s
     166: iconst_2
     167: anewarray     #39                 // class java/lang/Object
     170: dup
     171: iconst_0
     172: aload_0
     173: getfield      #18                 // Field requestMetadata:Lorg/apache/dubbo/rpc/protocol/tri/RequestMetadata;
     176: getfield      #19                 // Field org/apache/dubbo/rpc/protocol/tri/RequestMetadata.service:Ljava/lang/String;
     179: aastore
     180: dup
     181: iconst_1
     182: aload_0
     183: getfield      #18                 // Field requestMetadata:Lorg/apache/dubbo/rpc/protocol/tri/RequestMetadata;
     186: getfield      #21                 // Field org/apache/dubbo/rpc/protocol/tri/RequestMetadata.method:Lorg/apache/dubbo/rpc/model/MethodDescriptor;
     189: aastore
     190: invokestatic  #40                 // Method java/lang/String.format:(Ljava/lang/String;[Ljava/lang/Object;)Ljava/lang/String;
     193: aload_3
     194: invokeinterface #41,  6           // InterfaceMethod org/apache/dubbo/common/logger/ErrorTypeAwareLogger.error:(Ljava/lang/String;Ljava/lang/String;Ljava/lang/String;Ljava/lang/String;Ljava/lang/Throwable;)V
     199: aload_0
     200: aload_3
     201: invokevirtual #35                 // Method cancelByLocal:(Ljava/lang/Throwable;)V
     204: aload_0
     205: getfield      #27                 // Field listener:Lorg/apache/dubbo/rpc/protocol/tri/call/ClientCall$Listener;
     208: getstatic     #30                 // Field org/apache/dubbo/rpc/TriRpcStatus.INTERNAL:Lorg/apache/dubbo/rpc/TriRpcStatus;
     211: ldc           #79                 // String Serialize request failed
     213: invokevirtual #32                 // Method org/apache/dubbo/rpc/TriRpcStatus.withDescription:(Ljava/lang/String;)Lorg/apache/dubbo/rpc/TriRpcStatus;
     216: aload_3
     217: invokevirtual #33                 // Method org/apache/dubbo/rpc/TriRpcStatus.withCause:(Ljava/lang/Throwable;)Lorg/apache/dubbo/rpc/TriRpcStatus;
     220: aconst_null
     221: iconst_0
     222: invokeinterface #36,  4           // InterfaceMethod org/apache/dubbo/rpc/protocol/tri/call/ClientCall$Listener.onClose:(Lorg/apache/dubbo/rpc/TriRpcStatus;Ljava/util/Map;Z)V
     227: return
    Exception table:
       from    to  target type
          71   151   154   Class java/lang/Throwable

  public void halfClose();
    Code:
       0: aload_0
       1: getfield      #49                 // Field headerSent:Z
       4: ifne          8
       7: return
       8: aload_0
       9: getfield      #42                 // Field canceled:Z
      12: ifeq          16
      15: return
      16: aload_0
      17: getfield      #50                 // Field stream:Lorg/apache/dubbo/rpc/protocol/tri/stream/ClientStream;
      20: invokeinterface #80,  1           // InterfaceMethod org/apache/dubbo/rpc/protocol/tri/stream/ClientStream.halfClose:()Lio/netty/util/concurrent/Future;
      25: aload_0
      26: invokedynamic #81,  0             // InvokeDynamic #1:operationComplete:(Lorg/apache/dubbo/rpc/protocol/tri/call/TripleClientCall;)Lio/netty/util/concurrent/GenericFutureListener;
      31: invokeinterface #76,  2           // InterfaceMethod io/netty/util/concurrent/Future.addListener:(Lio/netty/util/concurrent/GenericFutureListener;)Lio/netty/util/concurrent/Future;
      36: pop
      37: return

  public void setCompression(java.lang.String);
    Code:
       0: aload_0
       1: getfield      #18                 // Field requestMetadata:Lorg/apache/dubbo/rpc/protocol/tri/RequestMetadata;
       4: aload_0
       5: getfield      #6                  // Field frameworkModel:Lorg/apache/dubbo/rpc/model/FrameworkModel;
       8: aload_1
       9: invokestatic  #82                 // InterfaceMethod org/apache/dubbo/rpc/protocol/tri/compressor/Compressor.getCompressor:(Lorg/apache/dubbo/rpc/model/FrameworkModel;Ljava/lang/String;)Lorg/apache/dubbo/rpc/protocol/tri/compressor/Compressor;
      12: putfield      #70                 // Field org/apache/dubbo/rpc/protocol/tri/RequestMetadata.compressor:Lorg/apache/dubbo/rpc/protocol/tri/compressor/Compressor;
      15: return

  public org.apache.dubbo.common.stream.StreamObserver<java.lang.Object> start(org.apache.dubbo.rpc.protocol.tri.RequestMetadata, org.apache.dubbo.rpc.protocol.tri.call.ClientCall$Listener);
    Code:
       0: aload_0
       1: aload_1
       2: putfield      #18                 // Field requestMetadata:Lorg/apache/dubbo/rpc/protocol/tri/RequestMetadata;
       5: aload_0
       6: aload_2
       7: putfield      #27                 // Field listener:Lorg/apache/dubbo/rpc/protocol/tri/call/ClientCall$Listener;
      10: aload_0
      11: new           #83                 // class org/apache/dubbo/rpc/protocol/tri/stream/TripleClientStream
      14: dup
      15: aload_0
      16: getfield      #6                  // Field frameworkModel:Lorg/apache/dubbo/rpc/model/FrameworkModel;
      19: aload_0
      20: getfield      #5                  // Field executor:Ljava/util/concurrent/Executor;
      23: aload_0
      24: getfield      #4                  // Field connectionClient:Lorg/apache/dubbo/remoting/api/connection/AbstractConnectionClient;
      27: iconst_1
      28: invokestatic  #84                 // Method java/lang/Boolean.valueOf:(Z)Ljava/lang/Boolean;
      31: invokevirtual #85                 // Method org/apache/dubbo/remoting/api/connection/AbstractConnectionClient.getChannel:(Ljava/lang/Boolean;)Ljava/lang/Object;
      34: checkcast     #86                 // class io/netty/channel/Channel
      37: aload_0
      38: aload_0
      39: getfield      #7                  // Field writeQueue:Lorg/apache/dubbo/rpc/protocol/tri/transport/TripleWriteQueue;
      42: invokespecial #87                 // Method org/apache/dubbo/rpc/protocol/tri/stream/TripleClientStream."<init>":(Lorg/apache/dubbo/rpc/model/FrameworkModel;Ljava/util/concurrent/Executor;Lio/netty/channel/Channel;Lorg/apache/dubbo/rpc/protocol/tri/stream/ClientStream$Listener;Lorg/apache/dubbo/rpc/protocol/tri/transport/TripleWriteQueue;)V
      45: putfield      #50                 // Field stream:Lorg/apache/dubbo/rpc/protocol/tri/stream/ClientStream;
      48: new           #88                 // class org/apache/dubbo/rpc/protocol/tri/observer/ClientCallToObserverAdapter
      51: dup
      52: aload_0
      53: invokespecial #89                 // Method org/apache/dubbo/rpc/protocol/tri/observer/ClientCallToObserverAdapter."<init>":(Lorg/apache/dubbo/rpc/protocol/tri/call/ClientCall;)V
      56: areturn

  public boolean isAutoRequest();
    Code:
       0: aload_0
       1: getfield      #3                  // Field autoRequest:Z
       4: ireturn

  public void setAutoRequest(boolean);
    Code:
       0: aload_0
       1: iload_1
       2: putfield      #3                  // Field autoRequest:Z
       5: return

  private void lambda$halfClose$1(io.netty.util.concurrent.Future) throws java.lang.Exception;
    Code:
       0: aload_1
       1: invokeinterface #90,  1           // InterfaceMethod io/netty/util/concurrent/Future.isSuccess:()Z
       6: ifne          28
       9: aload_0
      10: new           #61                 // class java/lang/IllegalStateException
      13: dup
      14: ldc           #91                 // String Half close failed
      16: aload_1
      17: invokeinterface #92,  1           // InterfaceMethod io/netty/util/concurrent/Future.cause:()Ljava/lang/Throwable;
      22: invokespecial #93                 // Method java/lang/IllegalStateException."<init>":(Ljava/lang/String;Ljava/lang/Throwable;)V
      25: invokevirtual #35                 // Method cancelByLocal:(Ljava/lang/Throwable;)V
      28: return

  private void lambda$sendMessage$0(io.netty.util.concurrent.Future) throws java.lang.Exception;
    Code:
       0: aload_1
       1: invokeinterface #90,  1           // InterfaceMethod io/netty/util/concurrent/Future.isSuccess:()Z
       6: ifne          19
       9: aload_0
      10: aload_1
      11: invokeinterface #92,  1           // InterfaceMethod io/netty/util/concurrent/Future.cause:()Ljava/lang/Throwable;
      16: invokevirtual #35                 // Method cancelByLocal:(Ljava/lang/Throwable;)V
      19: return

  static {};
    Code:
       0: ldc           #94                 // class org/apache/dubbo/rpc/protocol/tri/call/TripleClientCall
       2: invokestatic  #95                 // Method org/apache/dubbo/common/logger/LoggerFactory.getErrorTypeAwareLogger:(Ljava/lang/Class;)Lorg/apache/dubbo/common/logger/ErrorTypeAwareLogger;
       5: putstatic     #9                  // Field LOGGER:Lorg/apache/dubbo/common/logger/ErrorTypeAwareLogger;
       8: return
}
