Compiled from "UnaryClientCallListener.java"
public class org.apache.dubbo.rpc.protocol.tri.call.UnaryClientCallListener implements org.apache.dubbo.rpc.protocol.tri.call.ClientCall$Listener {
  private final org.apache.dubbo.rpc.protocol.tri.DeadlineFuture future;

  private java.lang.Object appResponse;

  public org.apache.dubbo.rpc.protocol.tri.call.UnaryClientCallListener(org.apache.dubbo.rpc.protocol.tri.DeadlineFuture);
    Code:
       0: aload_0
       1: invokespecial #1                  // Method java/lang/Object."<init>":()V
       4: aload_0
       5: aload_1
       6: putfield      #2                  // Field future:Lorg/apache/dubbo/rpc/protocol/tri/DeadlineFuture;
       9: return

  public void onMessage(java.lang.Object);
    Code:
       0: aload_0
       1: aload_1
       2: putfield      #3                  // Field appResponse:Ljava/lang/Object;
       5: return

  public void onClose(org.apache.dubbo.rpc.TriRpcStatus, java.util.Map<java.lang.String, java.lang.Object>, boolean);
    Code:
       0: new           #4                  // class org/apache/dubbo/rpc/AppResponse
       3: dup
       4: invokespecial #5                  // Method org/apache/dubbo/rpc/AppResponse."<init>":()V
       7: astore        4
       9: aload         4
      11: aload_2
      12: invokevirtual #6                  // Method org/apache/dubbo/rpc/AppResponse.setObjectAttachments:(Ljava/util/Map;)V
      15: aload_1
      16: invokevirtual #7                  // Method org/apache/dubbo/rpc/TriRpcStatus.isOk:()Z
      19: ifeq          53
      22: iload_3
      23: ifeq          41
      26: aload         4
      28: aload_0
      29: getfield      #3                  // Field appResponse:Ljava/lang/Object;
      32: checkcast     #8                  // class java/lang/Exception
      35: invokevirtual #9                  // Method org/apache/dubbo/rpc/AppResponse.setException:(Ljava/lang/Throwable;)V
      38: goto          62
      41: aload         4
      43: aload_0
      44: getfield      #3                  // Field appResponse:Ljava/lang/Object;
      47: invokevirtual #10                 // Method org/apache/dubbo/rpc/AppResponse.setValue:(Ljava/lang/Object;)V
      50: goto          62
      53: aload         4
      55: aload_1
      56: invokevirtual #11                 // Method org/apache/dubbo/rpc/TriRpcStatus.asException:()Lorg/apache/dubbo/rpc/StatusRpcException;
      59: invokevirtual #9                  // Method org/apache/dubbo/rpc/AppResponse.setException:(Ljava/lang/Throwable;)V
      62: aload_0
      63: getfield      #2                  // Field future:Lorg/apache/dubbo/rpc/protocol/tri/DeadlineFuture;
      66: aload_1
      67: aload         4
      69: invokevirtual #12                 // Method org/apache/dubbo/rpc/protocol/tri/DeadlineFuture.received:(Lorg/apache/dubbo/rpc/TriRpcStatus;Lorg/apache/dubbo/rpc/AppResponse;)V
      72: return

  public void onStart(org.apache.dubbo.rpc.protocol.tri.call.ClientCall);
    Code:
       0: aload_0
       1: getfield      #2                  // Field future:Lorg/apache/dubbo/rpc/protocol/tri/DeadlineFuture;
       4: aload_1
       5: invokedynamic #13,  0             // InvokeDynamic #0:run:(Lorg/apache/dubbo/rpc/protocol/tri/call/ClientCall;)Ljava/lang/Runnable;
      10: invokevirtual #14                 // Method org/apache/dubbo/rpc/protocol/tri/DeadlineFuture.addTimeoutListener:(Ljava/lang/Runnable;)V
      13: aload_1
      14: iconst_2
      15: invokeinterface #15,  2           // InterfaceMethod org/apache/dubbo/rpc/protocol/tri/call/ClientCall.request:(I)V
      20: return

  private static void lambda$onStart$0(org.apache.dubbo.rpc.protocol.tri.call.ClientCall);
    Code:
       0: aload_0
       1: new           #16                 // class java/lang/IllegalStateException
       4: dup
       5: ldc           #17                 // String client timeout
       7: invokespecial #18                 // Method java/lang/IllegalStateException."<init>":(Ljava/lang/String;)V
      10: invokeinterface #19,  2           // InterfaceMethod org/apache/dubbo/rpc/protocol/tri/call/ClientCall.cancelByLocal:(Ljava/lang/Throwable;)V
      15: return
}
