Compiled from "HistogramMetricSample.java"
public class org.apache.dubbo.metrics.sample.HistogramMetricSample extends org.apache.dubbo.metrics.model.sample.MetricSample {
  public org.apache.dubbo.metrics.sample.HistogramMetricSample(java.lang.String, java.lang.String, java.util.Map<java.lang.String, java.lang.String>, org.apache.dubbo.metrics.model.MetricsCategory);
    Code:
       0: aload_0
       1: aload_1
       2: aload_2
       3: aload_3
       4: getstatic     #1                  // Field org/apache/dubbo/metrics/model/sample/MetricSample$Type.TIMER:Lorg/apache/dubbo/metrics/model/sample/MetricSample$Type;
       7: aload         4
       9: invokespecial #2                  // Method org/apache/dubbo/metrics/model/sample/MetricSample."<init>":(Ljava/lang/String;Ljava/lang/String;Ljava/util/Map;Lorg/apache/dubbo/metrics/model/sample/MetricSample$Type;Lorg/apache/dubbo/metrics/model/MetricsCategory;)V
      12: return

  public org.apache.dubbo.metrics.sample.HistogramMetricSample(java.lang.String, java.lang.String, java.util.Map<java.lang.String, java.lang.String>, org.apache.dubbo.metrics.model.sample.MetricSample$Type, org.apache.dubbo.metrics.model.MetricsCategory, java.lang.String);
    Code:
       0: aload_0
       1: aload_1
       2: aload_2
       3: aload_3
       4: aload         4
       6: aload         5
       8: aload         6
      10: invokespecial #3                  // Method org/apache/dubbo/metrics/model/sample/MetricSample."<init>":(Ljava/lang/String;Ljava/lang/String;Ljava/util/Map;Lorg/apache/dubbo/metrics/model/sample/MetricSample$Type;Lorg/apache/dubbo/metrics/model/MetricsCategory;Ljava/lang/String;)V
      13: return
}
