Compiled from "PemCertificateParser.java"
final class org.springframework.boot.ssl.pem.PemCertificateParser {
  private static final java.lang.String HEADER;

  private static final java.lang.String BASE64_TEXT;

  private static final java.lang.String FOOTER;

  private static final java.util.regex.Pattern PATTERN;

  private org.springframework.boot.ssl.pem.PemCertificateParser();
    Code:
       0: aload_0
       1: invokespecial #1                  // Method java/lang/Object."<init>":()V
       4: return

  static java.security.cert.X509Certificate[] parse(java.lang.String);
    Code:
       0: aload_0
       1: ifnonnull     6
       4: aconst_null
       5: areturn
       6: invokestatic  #7                  // Method getCertificateFactory:()Ljava/security/cert/CertificateFactory;
       9: astore_1
      10: new           #13                 // class java/util/ArrayList
      13: dup
      14: invokespecial #15                 // Method java/util/ArrayList."<init>":()V
      17: astore_2
      18: aload_0
      19: aload_1
      20: aload_2
      21: dup
      22: invokestatic  #16                 // Method java/util/Objects.requireNonNull:(Ljava/lang/Object;)Ljava/lang/Object;
      25: pop
      26: invokedynamic #22,  0             // InvokeDynamic #0:accept:(Ljava/util/List;)Ljava/util/function/Consumer;
      31: invokestatic  #26                 // Method readCertificates:(Ljava/lang/String;Ljava/security/cert/CertificateFactory;Ljava/util/function/Consumer;)V
      34: aload_2
      35: invokeinterface #30,  1           // InterfaceMethod java/util/List.isEmpty:()Z
      40: ifne          60
      43: aload_2
      44: invokedynamic #36,  0             // InvokeDynamic #1:apply:()Ljava/util/function/IntFunction;
      49: invokeinterface #40,  2           // InterfaceMethod java/util/List.toArray:(Ljava/util/function/IntFunction;)[Ljava/lang/Object;
      54: checkcast     #44                 // class "[Ljava/security/cert/X509Certificate;"
      57: goto          61
      60: aconst_null
      61: areturn

  private static java.security.cert.CertificateFactory getCertificateFactory();
    Code:
       0: ldc           #46                 // String X.509
       2: invokestatic  #48                 // Method java/security/cert/CertificateFactory.getInstance:(Ljava/lang/String;)Ljava/security/cert/CertificateFactory;
       5: areturn
       6: astore_0
       7: new           #56                 // class java/lang/IllegalStateException
      10: dup
      11: ldc           #58                 // String Unable to get X.509 certificate factory
      13: aload_0
      14: invokespecial #60                 // Method java/lang/IllegalStateException."<init>":(Ljava/lang/String;Ljava/lang/Throwable;)V
      17: athrow
    Exception table:
       from    to  target type
           0     5     6   Class java/security/cert/CertificateException

  private static void readCertificates(java.lang.String, java.security.cert.CertificateFactory, java.util.function.Consumer<java.security.cert.X509Certificate>);
    Code:
       0: getstatic     #63                 // Field PATTERN:Ljava/util/regex/Pattern;
       3: aload_0
       4: invokevirtual #67                 // Method java/util/regex/Pattern.matcher:(Ljava/lang/CharSequence;)Ljava/util/regex/Matcher;
       7: astore_3
       8: aload_3
       9: invokevirtual #73                 // Method java/util/regex/Matcher.find:()Z
      12: ifeq          69
      15: aload_3
      16: iconst_1
      17: invokevirtual #78                 // Method java/util/regex/Matcher.group:(I)Ljava/lang/String;
      20: astore        4
      22: aload         4
      24: invokestatic  #82                 // Method decodeBase64:(Ljava/lang/String;)[B
      27: astore        5
      29: new           #86                 // class java/io/ByteArrayInputStream
      32: dup
      33: aload         5
      35: invokespecial #88                 // Method java/io/ByteArrayInputStream."<init>":([B)V
      38: astore        6
      40: aload         6
      42: invokevirtual #91                 // Method java/io/ByteArrayInputStream.available:()I
      45: ifle          66
      48: aload_2
      49: aload_1
      50: aload         6
      52: invokevirtual #95                 // Method java/security/cert/CertificateFactory.generateCertificate:(Ljava/io/InputStream;)Ljava/security/cert/Certificate;
      55: checkcast     #99                 // class java/security/cert/X509Certificate
      58: invokeinterface #101,  2          // InterfaceMethod java/util/function/Consumer.accept:(Ljava/lang/Object;)V
      63: goto          40
      66: goto          8
      69: goto          91
      72: astore_3
      73: new           #56                 // class java/lang/IllegalStateException
      76: dup
      77: aload_3
      78: invokevirtual #106                // Method java/security/cert/CertificateException.getMessage:()Ljava/lang/String;
      81: invokedynamic #110,  0            // InvokeDynamic #2:makeConcatWithConstants:(Ljava/lang/String;)Ljava/lang/String;
      86: aload_3
      87: invokespecial #60                 // Method java/lang/IllegalStateException."<init>":(Ljava/lang/String;Ljava/lang/Throwable;)V
      90: athrow
      91: return
    Exception table:
       from    to  target type
           0    69    72   Class java/security/cert/CertificateException

  private static byte[] decodeBase64(java.lang.String);
    Code:
       0: aload_0
       1: ldc           #114                // String \r
       3: ldc           #116                // String
       5: invokevirtual #118                // Method java/lang/String.replaceAll:(Ljava/lang/String;Ljava/lang/String;)Ljava/lang/String;
       8: ldc           #124                // String \n
      10: ldc           #116                // String
      12: invokevirtual #118                // Method java/lang/String.replaceAll:(Ljava/lang/String;Ljava/lang/String;)Ljava/lang/String;
      15: invokevirtual #126                // Method java/lang/String.getBytes:()[B
      18: astore_1
      19: invokestatic  #130                // Method java/util/Base64.getDecoder:()Ljava/util/Base64$Decoder;
      22: aload_1
      23: invokevirtual #136                // Method java/util/Base64$Decoder.decode:([B)[B
      26: areturn

  private static java.security.cert.X509Certificate[] lambda$parse$0(int);
    Code:
       0: iload_0
       1: anewarray     #99                 // class java/security/cert/X509Certificate
       4: areturn

  static {};
    Code:
       0: ldc           #142                // String -+BEGIN\\s+.*CERTIFICATE[^-]*-+(?:\\s|\\r|\\n)+([a-z0-9+/=\\r\\n]+)-+END\\s+.*CERTIFICATE[^-]*-+
       2: iconst_2
       3: invokestatic  #144                // Method java/util/regex/Pattern.compile:(Ljava/lang/String;I)Ljava/util/regex/Pattern;
       6: putstatic     #63                 // Field PATTERN:Ljava/util/regex/Pattern;
       9: return
}
