Compiled from "PemPrivateKeyParser.java"
class org.springframework.boot.ssl.pem.PemPrivateKeyParser$PemParser {
  private final java.util.regex.Pattern pattern;

  private final java.util.function.Function<byte[], java.security.spec.PKCS8EncodedKeySpec> keySpecFactory;

  private final java.lang.String[] algorithms;

  org.springframework.boot.ssl.pem.PemPrivateKeyParser$PemParser(java.lang.String, java.lang.String, java.util.function.Function<byte[], java.security.spec.PKCS8EncodedKeySpec>, java.lang.String...);
    Code:
       0: aload_0
       1: invokespecial #3                  // Method java/lang/Object."<init>":()V
       4: aload_0
       5: aload_1
       6: aload_2
       7: invokedynamic #9,  0              // InvokeDynamic #0:makeConcatWithConstants:(Ljava/lang/String;Ljava/lang/String;)Ljava/lang/String;
      12: iconst_2
      13: invokestatic  #15                 // Method java/util/regex/Pattern.compile:(Ljava/lang/String;I)Ljava/util/regex/Pattern;
      16: putfield      #19                 // Field pattern:Ljava/util/regex/Pattern;
      19: aload_0
      20: aload         4
      22: putfield      #25                 // Field algorithms:[Ljava/lang/String;
      25: aload_0
      26: aload_3
      27: putfield      #29                 // Field keySpecFactory:Ljava/util/function/Function;
      30: return

  java.security.PrivateKey parse(java.lang.String);
    Code:
       0: aload_0
       1: getfield      #19                 // Field pattern:Ljava/util/regex/Pattern;
       4: aload_1
       5: invokevirtual #33                 // Method java/util/regex/Pattern.matcher:(Ljava/lang/CharSequence;)Ljava/util/regex/Matcher;
       8: astore_2
       9: aload_2
      10: invokevirtual #37                 // Method java/util/regex/Matcher.find:()Z
      13: ifne          20
      16: aconst_null
      17: goto          32
      20: aload_0
      21: aload_2
      22: iconst_1
      23: invokevirtual #43                 // Method java/util/regex/Matcher.group:(I)Ljava/lang/String;
      26: invokestatic  #47                 // Method decodeBase64:(Ljava/lang/String;)[B
      29: invokevirtual #51                 // Method parse:([B)Ljava/security/PrivateKey;
      32: areturn

  private static byte[] decodeBase64(java.lang.String);
    Code:
       0: aload_0
       1: ldc           #55                 // String \r
       3: ldc           #57                 // String
       5: invokevirtual #59                 // Method java/lang/String.replaceAll:(Ljava/lang/String;Ljava/lang/String;)Ljava/lang/String;
       8: ldc           #64                 // String \n
      10: ldc           #57                 // String
      12: invokevirtual #59                 // Method java/lang/String.replaceAll:(Ljava/lang/String;Ljava/lang/String;)Ljava/lang/String;
      15: invokevirtual #66                 // Method java/lang/String.getBytes:()[B
      18: astore_1
      19: invokestatic  #70                 // Method java/util/Base64.getDecoder:()Ljava/util/Base64$Decoder;
      22: aload_1
      23: invokevirtual #76                 // Method java/util/Base64$Decoder.decode:([B)[B
      26: areturn

  private java.security.PrivateKey parse(byte[]);
    Code:
       0: aload_0
       1: getfield      #29                 // Field keySpecFactory:Ljava/util/function/Function;
       4: aload_1
       5: invokeinterface #82,  2           // InterfaceMethod java/util/function/Function.apply:(Ljava/lang/Object;)Ljava/lang/Object;
      10: checkcast     #88                 // class java/security/spec/PKCS8EncodedKeySpec
      13: astore_2
      14: aload_0
      15: getfield      #25                 // Field algorithms:[Ljava/lang/String;
      18: astore_3
      19: aload_3
      20: arraylength
      21: istore        4
      23: iconst_0
      24: istore        5
      26: iload         5
      28: iload         4
      30: if_icmpge     61
      33: aload_3
      34: iload         5
      36: aaload
      37: astore        6
      39: aload         6
      41: invokestatic  #90                 // Method java/security/KeyFactory.getInstance:(Ljava/lang/String;)Ljava/security/KeyFactory;
      44: astore        7
      46: aload         7
      48: aload_2
      49: invokevirtual #96                 // Method java/security/KeyFactory.generatePrivate:(Ljava/security/spec/KeySpec;)Ljava/security/PrivateKey;
      52: areturn
      53: astore        8
      55: iinc          5, 1
      58: goto          26
      61: aconst_null
      62: areturn
      63: astore_2
      64: new           #104                // class java/lang/IllegalArgumentException
      67: dup
      68: ldc           #106                // String Unexpected key format
      70: aload_2
      71: invokespecial #108                // Method java/lang/IllegalArgumentException."<init>":(Ljava/lang/String;Ljava/lang/Throwable;)V
      74: athrow
    Exception table:
       from    to  target type
          46    52    53   Class java/security/spec/InvalidKeySpecException
           0    52    63   Class java/security/GeneralSecurityException
          53    62    63   Class java/security/GeneralSecurityException
}
