Compiled from "BarcodeMetadata.java"
final class com.google.zxing.pdf417.decoder.BarcodeMetadata {
  private final int columnCount;

  private final int errorCorrectionLevel;

  private final int rowCountUpperPart;

  private final int rowCountLowerPart;

  private final int rowCount;

  com.google.zxing.pdf417.decoder.BarcodeMetadata(int, int, int, int);
    Code:
       0: aload_0
       1: invokespecial #1                  // Method java/lang/Object."<init>":()V
       4: aload_0
       5: iload_1
       6: putfield      #2                  // Field columnCount:I
       9: aload_0
      10: iload         4
      12: putfield      #3                  // Field errorCorrectionLevel:I
      15: aload_0
      16: iload_2
      17: putfield      #4                  // Field rowCountUpperPart:I
      20: aload_0
      21: iload_3
      22: putfield      #5                  // Field rowCountLowerPart:I
      25: aload_0
      26: iload_2
      27: iload_3
      28: iadd
      29: putfield      #6                  // Field rowCount:I
      32: return

  int getColumnCount();
    Code:
       0: aload_0
       1: getfield      #2                  // Field columnCount:I
       4: ireturn

  int getErrorCorrectionLevel();
    Code:
       0: aload_0
       1: getfield      #3                  // Field errorCorrectionLevel:I
       4: ireturn

  int getRowCount();
    Code:
       0: aload_0
       1: getfield      #6                  // Field rowCount:I
       4: ireturn

  int getRowCountUpperPart();
    Code:
       0: aload_0
       1: getfield      #4                  // Field rowCountUpperPart:I
       4: ireturn

  int getRowCountLowerPart();
    Code:
       0: aload_0
       1: getfield      #5                  // Field rowCountLowerPart:I
       4: ireturn
}
