Compiled from "AbstractExpandedDecoder.java"
public abstract class com.google.zxing.oned.rss.expanded.decoders.AbstractExpandedDecoder {
  private final com.google.zxing.common.BitArray information;

  private final com.google.zxing.oned.rss.expanded.decoders.GeneralAppIdDecoder generalDecoder;

  com.google.zxing.oned.rss.expanded.decoders.AbstractExpandedDecoder(com.google.zxing.common.BitArray);
    Code:
       0: aload_0
       1: invokespecial #1                  // Method java/lang/Object."<init>":()V
       4: aload_0
       5: aload_1
       6: putfield      #2                  // Field information:Lcom/google/zxing/common/BitArray;
       9: aload_0
      10: new           #3                  // class com/google/zxing/oned/rss/expanded/decoders/GeneralAppIdDecoder
      13: dup
      14: aload_1
      15: invokespecial #4                  // Method com/google/zxing/oned/rss/expanded/decoders/GeneralAppIdDecoder."<init>":(Lcom/google/zxing/common/BitArray;)V
      18: putfield      #5                  // Field generalDecoder:Lcom/google/zxing/oned/rss/expanded/decoders/GeneralAppIdDecoder;
      21: return

  protected final com.google.zxing.common.BitArray getInformation();
    Code:
       0: aload_0
       1: getfield      #2                  // Field information:Lcom/google/zxing/common/BitArray;
       4: areturn

  protected final com.google.zxing.oned.rss.expanded.decoders.GeneralAppIdDecoder getGeneralDecoder();
    Code:
       0: aload_0
       1: getfield      #5                  // Field generalDecoder:Lcom/google/zxing/oned/rss/expanded/decoders/GeneralAppIdDecoder;
       4: areturn

  public abstract java.lang.String parseInformation() throws com.google.zxing.NotFoundException, com.google.zxing.FormatException;

  public static com.google.zxing.oned.rss.expanded.decoders.AbstractExpandedDecoder createDecoder(com.google.zxing.common.BitArray);
    Code:
       0: aload_0
       1: iconst_1
       2: invokevirtual #6                  // Method com/google/zxing/common/BitArray.get:(I)Z
       5: ifeq          17
       8: new           #7                  // class com/google/zxing/oned/rss/expanded/decoders/AI01AndOtherAIs
      11: dup
      12: aload_0
      13: invokespecial #8                  // Method com/google/zxing/oned/rss/expanded/decoders/AI01AndOtherAIs."<init>":(Lcom/google/zxing/common/BitArray;)V
      16: areturn
      17: aload_0
      18: iconst_2
      19: invokevirtual #6                  // Method com/google/zxing/common/BitArray.get:(I)Z
      22: ifne          34
      25: new           #9                  // class com/google/zxing/oned/rss/expanded/decoders/AnyAIDecoder
      28: dup
      29: aload_0
      30: invokespecial #10                 // Method com/google/zxing/oned/rss/expanded/decoders/AnyAIDecoder."<init>":(Lcom/google/zxing/common/BitArray;)V
      33: areturn
      34: aload_0
      35: iconst_1
      36: iconst_4
      37: invokestatic  #11                 // Method com/google/zxing/oned/rss/expanded/decoders/GeneralAppIdDecoder.extractNumericValueFromBitArray:(Lcom/google/zxing/common/BitArray;II)I
      40: istore_1
      41: iload_1
      42: lookupswitch  { // 2
                     4: 68
                     5: 77
               default: 86
          }
      68: new           #12                 // class com/google/zxing/oned/rss/expanded/decoders/AI013103decoder
      71: dup
      72: aload_0
      73: invokespecial #13                 // Method com/google/zxing/oned/rss/expanded/decoders/AI013103decoder."<init>":(Lcom/google/zxing/common/BitArray;)V
      76: areturn
      77: new           #14                 // class com/google/zxing/oned/rss/expanded/decoders/AI01320xDecoder
      80: dup
      81: aload_0
      82: invokespecial #15                 // Method com/google/zxing/oned/rss/expanded/decoders/AI01320xDecoder."<init>":(Lcom/google/zxing/common/BitArray;)V
      85: areturn
      86: aload_0
      87: iconst_1
      88: iconst_5
      89: invokestatic  #11                 // Method com/google/zxing/oned/rss/expanded/decoders/GeneralAppIdDecoder.extractNumericValueFromBitArray:(Lcom/google/zxing/common/BitArray;II)I
      92: istore_2
      93: iload_2
      94: lookupswitch  { // 2
                    12: 120
                    13: 129
               default: 138
          }
     120: new           #16                 // class com/google/zxing/oned/rss/expanded/decoders/AI01392xDecoder
     123: dup
     124: aload_0
     125: invokespecial #17                 // Method com/google/zxing/oned/rss/expanded/decoders/AI01392xDecoder."<init>":(Lcom/google/zxing/common/BitArray;)V
     128: areturn
     129: new           #18                 // class com/google/zxing/oned/rss/expanded/decoders/AI01393xDecoder
     132: dup
     133: aload_0
     134: invokespecial #19                 // Method com/google/zxing/oned/rss/expanded/decoders/AI01393xDecoder."<init>":(Lcom/google/zxing/common/BitArray;)V
     137: areturn
     138: aload_0
     139: iconst_1
     140: bipush        7
     142: invokestatic  #11                 // Method com/google/zxing/oned/rss/expanded/decoders/GeneralAppIdDecoder.extractNumericValueFromBitArray:(Lcom/google/zxing/common/BitArray;II)I
     145: istore_3
     146: iload_3
     147: tableswitch   { // 56 to 63
                    56: 192
                    57: 205
                    58: 218
                    59: 231
                    60: 244
                    61: 257
                    62: 270
                    63: 283
               default: 296
          }
     192: new           #20                 // class com/google/zxing/oned/rss/expanded/decoders/AI013x0x1xDecoder
     195: dup
     196: aload_0
     197: ldc           #21                 // String 310
     199: ldc           #22                 // String 11
     201: invokespecial #23                 // Method com/google/zxing/oned/rss/expanded/decoders/AI013x0x1xDecoder."<init>":(Lcom/google/zxing/common/BitArray;Ljava/lang/String;Ljava/lang/String;)V
     204: areturn
     205: new           #20                 // class com/google/zxing/oned/rss/expanded/decoders/AI013x0x1xDecoder
     208: dup
     209: aload_0
     210: ldc           #24                 // String 320
     212: ldc           #22                 // String 11
     214: invokespecial #23                 // Method com/google/zxing/oned/rss/expanded/decoders/AI013x0x1xDecoder."<init>":(Lcom/google/zxing/common/BitArray;Ljava/lang/String;Ljava/lang/String;)V
     217: areturn
     218: new           #20                 // class com/google/zxing/oned/rss/expanded/decoders/AI013x0x1xDecoder
     221: dup
     222: aload_0
     223: ldc           #21                 // String 310
     225: ldc           #25                 // String 13
     227: invokespecial #23                 // Method com/google/zxing/oned/rss/expanded/decoders/AI013x0x1xDecoder."<init>":(Lcom/google/zxing/common/BitArray;Ljava/lang/String;Ljava/lang/String;)V
     230: areturn
     231: new           #20                 // class com/google/zxing/oned/rss/expanded/decoders/AI013x0x1xDecoder
     234: dup
     235: aload_0
     236: ldc           #24                 // String 320
     238: ldc           #25                 // String 13
     240: invokespecial #23                 // Method com/google/zxing/oned/rss/expanded/decoders/AI013x0x1xDecoder."<init>":(Lcom/google/zxing/common/BitArray;Ljava/lang/String;Ljava/lang/String;)V
     243: areturn
     244: new           #20                 // class com/google/zxing/oned/rss/expanded/decoders/AI013x0x1xDecoder
     247: dup
     248: aload_0
     249: ldc           #21                 // String 310
     251: ldc           #26                 // String 15
     253: invokespecial #23                 // Method com/google/zxing/oned/rss/expanded/decoders/AI013x0x1xDecoder."<init>":(Lcom/google/zxing/common/BitArray;Ljava/lang/String;Ljava/lang/String;)V
     256: areturn
     257: new           #20                 // class com/google/zxing/oned/rss/expanded/decoders/AI013x0x1xDecoder
     260: dup
     261: aload_0
     262: ldc           #24                 // String 320
     264: ldc           #26                 // String 15
     266: invokespecial #23                 // Method com/google/zxing/oned/rss/expanded/decoders/AI013x0x1xDecoder."<init>":(Lcom/google/zxing/common/BitArray;Ljava/lang/String;Ljava/lang/String;)V
     269: areturn
     270: new           #20                 // class com/google/zxing/oned/rss/expanded/decoders/AI013x0x1xDecoder
     273: dup
     274: aload_0
     275: ldc           #21                 // String 310
     277: ldc           #27                 // String 17
     279: invokespecial #23                 // Method com/google/zxing/oned/rss/expanded/decoders/AI013x0x1xDecoder."<init>":(Lcom/google/zxing/common/BitArray;Ljava/lang/String;Ljava/lang/String;)V
     282: areturn
     283: new           #20                 // class com/google/zxing/oned/rss/expanded/decoders/AI013x0x1xDecoder
     286: dup
     287: aload_0
     288: ldc           #24                 // String 320
     290: ldc           #27                 // String 17
     292: invokespecial #23                 // Method com/google/zxing/oned/rss/expanded/decoders/AI013x0x1xDecoder."<init>":(Lcom/google/zxing/common/BitArray;Ljava/lang/String;Ljava/lang/String;)V
     295: areturn
     296: new           #28                 // class java/lang/IllegalStateException
     299: dup
     300: new           #29                 // class java/lang/StringBuilder
     303: dup
     304: invokespecial #30                 // Method java/lang/StringBuilder."<init>":()V
     307: ldc           #31                 // String unknown decoder:
     309: invokevirtual #32                 // Method java/lang/StringBuilder.append:(Ljava/lang/String;)Ljava/lang/StringBuilder;
     312: aload_0
     313: invokevirtual #33                 // Method java/lang/StringBuilder.append:(Ljava/lang/Object;)Ljava/lang/StringBuilder;
     316: invokevirtual #34                 // Method java/lang/StringBuilder.toString:()Ljava/lang/String;
     319: invokespecial #35                 // Method java/lang/IllegalStateException."<init>":(Ljava/lang/String;)V
     322: athrow
}
