Compiled from "AI013x0xDecoder.java"
abstract class com.google.zxing.oned.rss.expanded.decoders.AI013x0xDecoder extends com.google.zxing.oned.rss.expanded.decoders.AI01weightDecoder {
  private static final int HEADER_SIZE;

  private static final int WEIGHT_SIZE;

  com.google.zxing.oned.rss.expanded.decoders.AI013x0xDecoder(com.google.zxing.common.BitArray);
    Code:
       0: aload_0
       1: aload_1
       2: invokespecial #1                  // Method com/google/zxing/oned/rss/expanded/decoders/AI01weightDecoder."<init>":(Lcom/google/zxing/common/BitArray;)V
       5: return

  public java.lang.String parseInformation() throws com.google.zxing.NotFoundException;
    Code:
       0: aload_0
       1: invokevirtual #2                  // Method getInformation:()Lcom/google/zxing/common/BitArray;
       4: invokevirtual #3                  // Method com/google/zxing/common/BitArray.getSize:()I
       7: bipush        60
       9: if_icmpeq     16
      12: invokestatic  #6                  // Method com/google/zxing/NotFoundException.getNotFoundInstance:()Lcom/google/zxing/NotFoundException;
      15: athrow
      16: new           #7                  // class java/lang/StringBuilder
      19: dup
      20: invokespecial #8                  // Method java/lang/StringBuilder."<init>":()V
      23: astore_1
      24: aload_0
      25: aload_1
      26: iconst_5
      27: invokevirtual #9                  // Method encodeCompressedGtin:(Ljava/lang/StringBuilder;I)V
      30: aload_0
      31: aload_1
      32: bipush        45
      34: bipush        15
      36: invokevirtual #10                 // Method encodeCompressedWeight:(Ljava/lang/StringBuilder;II)V
      39: aload_1
      40: invokevirtual #11                 // Method java/lang/StringBuilder.toString:()Ljava/lang/String;
      43: areturn
}
