Compiled from "AI01AndOtherAIs.java"
final class com.google.zxing.oned.rss.expanded.decoders.AI01AndOtherAIs extends com.google.zxing.oned.rss.expanded.decoders.AI01decoder {
  private static final int HEADER_SIZE;

  com.google.zxing.oned.rss.expanded.decoders.AI01AndOtherAIs(com.google.zxing.common.BitArray);
    Code:
       0: aload_0
       1: aload_1
       2: invokespecial #1                  // Method com/google/zxing/oned/rss/expanded/decoders/AI01decoder."<init>":(Lcom/google/zxing/common/BitArray;)V
       5: return

  public java.lang.String parseInformation() throws com.google.zxing.NotFoundException, com.google.zxing.FormatException;
    Code:
       0: new           #2                  // class java/lang/StringBuilder
       3: dup
       4: invokespecial #3                  // Method java/lang/StringBuilder."<init>":()V
       7: astore_1
       8: aload_1
       9: ldc           #4                  // String (01)
      11: invokevirtual #5                  // Method java/lang/StringBuilder.append:(Ljava/lang/String;)Ljava/lang/StringBuilder;
      14: pop
      15: aload_1
      16: invokevirtual #6                  // Method java/lang/StringBuilder.length:()I
      19: istore_2
      20: aload_0
      21: invokevirtual #7                  // Method getGeneralDecoder:()Lcom/google/zxing/oned/rss/expanded/decoders/GeneralAppIdDecoder;
      24: iconst_4
      25: iconst_4
      26: invokevirtual #9                  // Method com/google/zxing/oned/rss/expanded/decoders/GeneralAppIdDecoder.extractNumericValueFromBitArray:(II)I
      29: istore_3
      30: aload_1
      31: iload_3
      32: invokevirtual #10                 // Method java/lang/StringBuilder.append:(I)Ljava/lang/StringBuilder;
      35: pop
      36: aload_0
      37: aload_1
      38: bipush        8
      40: iload_2
      41: invokevirtual #11                 // Method encodeCompressedGtinWithoutAI:(Ljava/lang/StringBuilder;II)V
      44: aload_0
      45: invokevirtual #7                  // Method getGeneralDecoder:()Lcom/google/zxing/oned/rss/expanded/decoders/GeneralAppIdDecoder;
      48: aload_1
      49: bipush        48
      51: invokevirtual #12                 // Method com/google/zxing/oned/rss/expanded/decoders/GeneralAppIdDecoder.decodeAllCodes:(Ljava/lang/StringBuilder;I)Ljava/lang/String;
      54: areturn
}
