Compiled from "AI01weightDecoder.java"
abstract class com.google.zxing.oned.rss.expanded.decoders.AI01weightDecoder extends com.google.zxing.oned.rss.expanded.decoders.AI01decoder {
  com.google.zxing.oned.rss.expanded.decoders.AI01weightDecoder(com.google.zxing.common.BitArray);
    Code:
       0: aload_0
       1: aload_1
       2: invokespecial #1                  // Method com/google/zxing/oned/rss/expanded/decoders/AI01decoder."<init>":(Lcom/google/zxing/common/BitArray;)V
       5: return

  final void encodeCompressedWeight(java.lang.StringBuilder, int, int);
    Code:
       0: aload_0
       1: invokevirtual #2                  // Method getGeneralDecoder:()Lcom/google/zxing/oned/rss/expanded/decoders/GeneralAppIdDecoder;
       4: iload_2
       5: iload_3
       6: invokevirtual #3                  // Method com/google/zxing/oned/rss/expanded/decoders/GeneralAppIdDecoder.extractNumericValueFromBitArray:(II)I
       9: istore        4
      11: aload_0
      12: aload_1
      13: iload         4
      15: invokevirtual #4                  // Method addWeightCode:(Ljava/lang/StringBuilder;I)V
      18: aload_0
      19: iload         4
      21: invokevirtual #5                  // Method checkWeight:(I)I
      24: istore        5
      26: ldc           #6                  // int 100000
      28: istore        6
      30: iconst_0
      31: istore        7
      33: iload         7
      35: iconst_5
      36: if_icmpge     67
      39: iload         5
      41: iload         6
      43: idiv
      44: ifne          54
      47: aload_1
      48: bipush        48
      50: invokevirtual #7                  // Method java/lang/StringBuilder.append:(C)Ljava/lang/StringBuilder;
      53: pop
      54: iload         6
      56: bipush        10
      58: idiv
      59: istore        6
      61: iinc          7, 1
      64: goto          33
      67: aload_1
      68: iload         5
      70: invokevirtual #8                  // Method java/lang/StringBuilder.append:(I)Ljava/lang/StringBuilder;
      73: pop
      74: return

  protected abstract void addWeightCode(java.lang.StringBuilder, int);

  protected abstract int checkWeight(int);
}
