Compiled from "AI01393xDecoder.java"
final class com.google.zxing.oned.rss.expanded.decoders.AI01393xDecoder extends com.google.zxing.oned.rss.expanded.decoders.AI01decoder {
  private static final int HEADER_SIZE;

  private static final int LAST_DIGIT_SIZE;

  private static final int FIRST_THREE_DIGITS_SIZE;

  com.google.zxing.oned.rss.expanded.decoders.AI01393xDecoder(com.google.zxing.common.BitArray);
    Code:
       0: aload_0
       1: aload_1
       2: invokespecial #1                  // Method com/google/zxing/oned/rss/expanded/decoders/AI01decoder."<init>":(Lcom/google/zxing/common/BitArray;)V
       5: return

  public java.lang.String parseInformation() throws com.google.zxing.NotFoundException, com.google.zxing.FormatException;
    Code:
       0: aload_0
       1: invokevirtual #2                  // Method getInformation:()Lcom/google/zxing/common/BitArray;
       4: invokevirtual #3                  // Method com/google/zxing/common/BitArray.getSize:()I
       7: bipush        48
       9: if_icmpge     16
      12: invokestatic  #6                  // Method com/google/zxing/NotFoundException.getNotFoundInstance:()Lcom/google/zxing/NotFoundException;
      15: athrow
      16: new           #7                  // class java/lang/StringBuilder
      19: dup
      20: invokespecial #8                  // Method java/lang/StringBuilder."<init>":()V
      23: astore_1
      24: aload_0
      25: aload_1
      26: bipush        8
      28: invokevirtual #9                  // Method encodeCompressedGtin:(Ljava/lang/StringBuilder;I)V
      31: aload_0
      32: invokevirtual #10                 // Method getGeneralDecoder:()Lcom/google/zxing/oned/rss/expanded/decoders/GeneralAppIdDecoder;
      35: bipush        48
      37: iconst_2
      38: invokevirtual #11                 // Method com/google/zxing/oned/rss/expanded/decoders/GeneralAppIdDecoder.extractNumericValueFromBitArray:(II)I
      41: istore_2
      42: aload_1
      43: ldc           #12                 // String (393
      45: invokevirtual #13                 // Method java/lang/StringBuilder.append:(Ljava/lang/String;)Ljava/lang/StringBuilder;
      48: pop
      49: aload_1
      50: iload_2
      51: invokevirtual #14                 // Method java/lang/StringBuilder.append:(I)Ljava/lang/StringBuilder;
      54: pop
      55: aload_1
      56: bipush        41
      58: invokevirtual #15                 // Method java/lang/StringBuilder.append:(C)Ljava/lang/StringBuilder;
      61: pop
      62: aload_0
      63: invokevirtual #10                 // Method getGeneralDecoder:()Lcom/google/zxing/oned/rss/expanded/decoders/GeneralAppIdDecoder;
      66: bipush        50
      68: bipush        10
      70: invokevirtual #11                 // Method com/google/zxing/oned/rss/expanded/decoders/GeneralAppIdDecoder.extractNumericValueFromBitArray:(II)I
      73: istore_3
      74: iload_3
      75: bipush        100
      77: idiv
      78: ifne          88
      81: aload_1
      82: bipush        48
      84: invokevirtual #15                 // Method java/lang/StringBuilder.append:(C)Ljava/lang/StringBuilder;
      87: pop
      88: iload_3
      89: bipush        10
      91: idiv
      92: ifne          102
      95: aload_1
      96: bipush        48
      98: invokevirtual #15                 // Method java/lang/StringBuilder.append:(C)Ljava/lang/StringBuilder;
     101: pop
     102: aload_1
     103: iload_3
     104: invokevirtual #14                 // Method java/lang/StringBuilder.append:(I)Ljava/lang/StringBuilder;
     107: pop
     108: aload_0
     109: invokevirtual #10                 // Method getGeneralDecoder:()Lcom/google/zxing/oned/rss/expanded/decoders/GeneralAppIdDecoder;
     112: bipush        60
     114: aconst_null
     115: invokevirtual #16                 // Method com/google/zxing/oned/rss/expanded/decoders/GeneralAppIdDecoder.decodeGeneralPurposeField:(ILjava/lang/String;)Lcom/google/zxing/oned/rss/expanded/decoders/DecodedInformation;
     118: astore        4
     120: aload_1
     121: aload         4
     123: invokevirtual #17                 // Method com/google/zxing/oned/rss/expanded/decoders/DecodedInformation.getNewString:()Ljava/lang/String;
     126: invokevirtual #13                 // Method java/lang/StringBuilder.append:(Ljava/lang/String;)Ljava/lang/StringBuilder;
     129: pop
     130: aload_1
     131: invokevirtual #18                 // Method java/lang/StringBuilder.toString:()Ljava/lang/String;
     134: areturn
}
