Compiled from "AnyAIDecoder.java"
final class com.google.zxing.oned.rss.expanded.decoders.AnyAIDecoder extends com.google.zxing.oned.rss.expanded.decoders.AbstractExpandedDecoder {
  private static final int HEADER_SIZE;

  com.google.zxing.oned.rss.expanded.decoders.AnyAIDecoder(com.google.zxing.common.BitArray);
    Code:
       0: aload_0
       1: aload_1
       2: invokespecial #1                  // Method com/google/zxing/oned/rss/expanded/decoders/AbstractExpandedDecoder."<init>":(Lcom/google/zxing/common/BitArray;)V
       5: return

  public java.lang.String parseInformation() throws com.google.zxing.NotFoundException, com.google.zxing.FormatException;
    Code:
       0: new           #2                  // class java/lang/StringBuilder
       3: dup
       4: invokespecial #3                  // Method java/lang/StringBuilder."<init>":()V
       7: astore_1
       8: aload_0
       9: invokevirtual #4                  // Method getGeneralDecoder:()Lcom/google/zxing/oned/rss/expanded/decoders/GeneralAppIdDecoder;
      12: aload_1
      13: iconst_5
      14: invokevirtual #6                  // Method com/google/zxing/oned/rss/expanded/decoders/GeneralAppIdDecoder.decodeAllCodes:(Ljava/lang/StringBuilder;I)Ljava/lang/String;
      17: areturn
}
