Compiled from "BlockParsedResult.java"
final class com.google.zxing.oned.rss.expanded.decoders.BlockParsedResult {
  private final com.google.zxing.oned.rss.expanded.decoders.DecodedInformation decodedInformation;

  private final boolean finished;

  com.google.zxing.oned.rss.expanded.decoders.BlockParsedResult();
    Code:
       0: aload_0
       1: aconst_null
       2: iconst_0
       3: invokespecial #1                  // Method "<init>":(Lcom/google/zxing/oned/rss/expanded/decoders/DecodedInformation;Z)V
       6: return

  com.google.zxing.oned.rss.expanded.decoders.BlockParsedResult(com.google.zxing.oned.rss.expanded.decoders.DecodedInformation, boolean);
    Code:
       0: aload_0
       1: invokespecial #2                  // Method java/lang/Object."<init>":()V
       4: aload_0
       5: iload_2
       6: putfield      #3                  // Field finished:Z
       9: aload_0
      10: aload_1
      11: putfield      #4                  // Field decodedInformation:Lcom/google/zxing/oned/rss/expanded/decoders/DecodedInformation;
      14: return

  com.google.zxing.oned.rss.expanded.decoders.DecodedInformation getDecodedInformation();
    Code:
       0: aload_0
       1: getfield      #4                  // Field decodedInformation:Lcom/google/zxing/oned/rss/expanded/decoders/DecodedInformation;
       4: areturn

  boolean isFinished();
    Code:
       0: aload_0
       1: getfield      #3                  // Field finished:Z
       4: ireturn
}
