Compiled from "CurrentParsingState.java"
final class com.google.zxing.oned.rss.expanded.decoders.CurrentParsingState {
  private int position;

  private com.google.zxing.oned.rss.expanded.decoders.CurrentParsingState$State encoding;

  com.google.zxing.oned.rss.expanded.decoders.CurrentParsingState();
    Code:
       0: aload_0
       1: invokespecial #1                  // Method java/lang/Object."<init>":()V
       4: aload_0
       5: iconst_0
       6: putfield      #2                  // Field position:I
       9: aload_0
      10: getstatic     #3                  // Field com/google/zxing/oned/rss/expanded/decoders/CurrentParsingState$State.NUMERIC:Lcom/google/zxing/oned/rss/expanded/decoders/CurrentParsingState$State;
      13: putfield      #4                  // Field encoding:Lcom/google/zxing/oned/rss/expanded/decoders/CurrentParsingState$State;
      16: return

  int getPosition();
    Code:
       0: aload_0
       1: getfield      #2                  // Field position:I
       4: ireturn

  void setPosition(int);
    Code:
       0: aload_0
       1: iload_1
       2: putfield      #2                  // Field position:I
       5: return

  void incrementPosition(int);
    Code:
       0: aload_0
       1: dup
       2: getfield      #2                  // Field position:I
       5: iload_1
       6: iadd
       7: putfield      #2                  // Field position:I
      10: return

  boolean isAlpha();
    Code:
       0: aload_0
       1: getfield      #4                  // Field encoding:Lcom/google/zxing/oned/rss/expanded/decoders/CurrentParsingState$State;
       4: getstatic     #5                  // Field com/google/zxing/oned/rss/expanded/decoders/CurrentParsingState$State.ALPHA:Lcom/google/zxing/oned/rss/expanded/decoders/CurrentParsingState$State;
       7: if_acmpne     14
      10: iconst_1
      11: goto          15
      14: iconst_0
      15: ireturn

  boolean isNumeric();
    Code:
       0: aload_0
       1: getfield      #4                  // Field encoding:Lcom/google/zxing/oned/rss/expanded/decoders/CurrentParsingState$State;
       4: getstatic     #3                  // Field com/google/zxing/oned/rss/expanded/decoders/CurrentParsingState$State.NUMERIC:Lcom/google/zxing/oned/rss/expanded/decoders/CurrentParsingState$State;
       7: if_acmpne     14
      10: iconst_1
      11: goto          15
      14: iconst_0
      15: ireturn

  boolean isIsoIec646();
    Code:
       0: aload_0
       1: getfield      #4                  // Field encoding:Lcom/google/zxing/oned/rss/expanded/decoders/CurrentParsingState$State;
       4: getstatic     #6                  // Field com/google/zxing/oned/rss/expanded/decoders/CurrentParsingState$State.ISO_IEC_646:Lcom/google/zxing/oned/rss/expanded/decoders/CurrentParsingState$State;
       7: if_acmpne     14
      10: iconst_1
      11: goto          15
      14: iconst_0
      15: ireturn

  void setNumeric();
    Code:
       0: aload_0
       1: getstatic     #3                  // Field com/google/zxing/oned/rss/expanded/decoders/CurrentParsingState$State.NUMERIC:Lcom/google/zxing/oned/rss/expanded/decoders/CurrentParsingState$State;
       4: putfield      #4                  // Field encoding:Lcom/google/zxing/oned/rss/expanded/decoders/CurrentParsingState$State;
       7: return

  void setAlpha();
    Code:
       0: aload_0
       1: getstatic     #5                  // Field com/google/zxing/oned/rss/expanded/decoders/CurrentParsingState$State.ALPHA:Lcom/google/zxing/oned/rss/expanded/decoders/CurrentParsingState$State;
       4: putfield      #4                  // Field encoding:Lcom/google/zxing/oned/rss/expanded/decoders/CurrentParsingState$State;
       7: return

  void setIsoIec646();
    Code:
       0: aload_0
       1: getstatic     #6                  // Field com/google/zxing/oned/rss/expanded/decoders/CurrentParsingState$State.ISO_IEC_646:Lcom/google/zxing/oned/rss/expanded/decoders/CurrentParsingState$State;
       4: putfield      #4                  // Field encoding:Lcom/google/zxing/oned/rss/expanded/decoders/CurrentParsingState$State;
       7: return
}
