Compiled from "CurrentParsingState.java"
final class com.google.zxing.oned.rss.expanded.decoders.CurrentParsingState$State extends java.lang.Enum<com.google.zxing.oned.rss.expanded.decoders.CurrentParsingState$State> {
  public static final com.google.zxing.oned.rss.expanded.decoders.CurrentParsingState$State NUMERIC;

  public static final com.google.zxing.oned.rss.expanded.decoders.CurrentParsingState$State ALPHA;

  public static final com.google.zxing.oned.rss.expanded.decoders.CurrentParsingState$State ISO_IEC_646;

  private static final com.google.zxing.oned.rss.expanded.decoders.CurrentParsingState$State[] $VALUES;

  public static com.google.zxing.oned.rss.expanded.decoders.CurrentParsingState$State[] values();
    Code:
       0: getstatic     #1                  // Field $VALUES:[Lcom/google/zxing/oned/rss/expanded/decoders/CurrentParsingState$State;
       3: invokevirtual #2                  // Method "[Lcom/google/zxing/oned/rss/expanded/decoders/CurrentParsingState$State;".clone:()Ljava/lang/Object;
       6: checkcast     #3                  // class "[Lcom/google/zxing/oned/rss/expanded/decoders/CurrentParsingState$State;"
       9: areturn

  public static com.google.zxing.oned.rss.expanded.decoders.CurrentParsingState$State valueOf(java.lang.String);
    Code:
       0: ldc           #4                  // class com/google/zxing/oned/rss/expanded/decoders/CurrentParsingState$State
       2: aload_0
       3: invokestatic  #5                  // Method java/lang/Enum.valueOf:(Ljava/lang/Class;Ljava/lang/String;)Ljava/lang/Enum;
       6: checkcast     #4                  // class com/google/zxing/oned/rss/expanded/decoders/CurrentParsingState$State
       9: areturn

  private com.google.zxing.oned.rss.expanded.decoders.CurrentParsingState$State();
    Code:
       0: aload_0
       1: aload_1
       2: iload_2
       3: invokespecial #6                  // Method java/lang/Enum."<init>":(Ljava/lang/String;I)V
       6: return

  static {};
    Code:
       0: new           #4                  // class com/google/zxing/oned/rss/expanded/decoders/CurrentParsingState$State
       3: dup
       4: ldc           #7                  // String NUMERIC
       6: iconst_0
       7: invokespecial #8                  // Method "<init>":(Ljava/lang/String;I)V
      10: putstatic     #9                  // Field NUMERIC:Lcom/google/zxing/oned/rss/expanded/decoders/CurrentParsingState$State;
      13: new           #4                  // class com/google/zxing/oned/rss/expanded/decoders/CurrentParsingState$State
      16: dup
      17: ldc           #10                 // String ALPHA
      19: iconst_1
      20: invokespecial #8                  // Method "<init>":(Ljava/lang/String;I)V
      23: putstatic     #11                 // Field ALPHA:Lcom/google/zxing/oned/rss/expanded/decoders/CurrentParsingState$State;
      26: new           #4                  // class com/google/zxing/oned/rss/expanded/decoders/CurrentParsingState$State
      29: dup
      30: ldc           #12                 // String ISO_IEC_646
      32: iconst_2
      33: invokespecial #8                  // Method "<init>":(Ljava/lang/String;I)V
      36: putstatic     #13                 // Field ISO_IEC_646:Lcom/google/zxing/oned/rss/expanded/decoders/CurrentParsingState$State;
      39: iconst_3
      40: anewarray     #4                  // class com/google/zxing/oned/rss/expanded/decoders/CurrentParsingState$State
      43: dup
      44: iconst_0
      45: getstatic     #9                  // Field NUMERIC:Lcom/google/zxing/oned/rss/expanded/decoders/CurrentParsingState$State;
      48: aastore
      49: dup
      50: iconst_1
      51: getstatic     #11                 // Field ALPHA:Lcom/google/zxing/oned/rss/expanded/decoders/CurrentParsingState$State;
      54: aastore
      55: dup
      56: iconst_2
      57: getstatic     #13                 // Field ISO_IEC_646:Lcom/google/zxing/oned/rss/expanded/decoders/CurrentParsingState$State;
      60: aastore
      61: putstatic     #1                  // Field $VALUES:[Lcom/google/zxing/oned/rss/expanded/decoders/CurrentParsingState$State;
      64: return
}
