Compiled from "DecodedChar.java"
final class com.google.zxing.oned.rss.expanded.decoders.DecodedChar extends com.google.zxing.oned.rss.expanded.decoders.DecodedObject {
  private final char value;

  static final char FNC1;

  com.google.zxing.oned.rss.expanded.decoders.DecodedChar(int, char);
    Code:
       0: aload_0
       1: iload_1
       2: invokespecial #1                  // Method com/google/zxing/oned/rss/expanded/decoders/DecodedObject."<init>":(I)V
       5: aload_0
       6: iload_2
       7: putfield      #2                  // Field value:C
      10: return

  char getValue();
    Code:
       0: aload_0
       1: getfield      #2                  // Field value:C
       4: ireturn

  boolean isFNC1();
    Code:
       0: aload_0
       1: getfield      #2                  // Field value:C
       4: bipush        36
       6: if_icmpne     13
       9: iconst_1
      10: goto          14
      13: iconst_0
      14: ireturn
}
