Compiled from "DecodedObject.java"
abstract class com.google.zxing.oned.rss.expanded.decoders.DecodedObject {
  private final int newPosition;

  com.google.zxing.oned.rss.expanded.decoders.DecodedObject(int);
    Code:
       0: aload_0
       1: invokespecial #1                  // Method java/lang/Object."<init>":()V
       4: aload_0
       5: iload_1
       6: putfield      #2                  // Field newPosition:I
       9: return

  final int getNewPosition();
    Code:
       0: aload_0
       1: getfield      #2                  // Field newPosition:I
       4: ireturn
}
