Compiled from "DecodedInformation.java"
final class com.google.zxing.oned.rss.expanded.decoders.DecodedInformation extends com.google.zxing.oned.rss.expanded.decoders.DecodedObject {
  private final java.lang.String newString;

  private final int remainingValue;

  private final boolean remaining;

  com.google.zxing.oned.rss.expanded.decoders.DecodedInformation(int, java.lang.String);
    Code:
       0: aload_0
       1: iload_1
       2: invokespecial #1                  // Method com/google/zxing/oned/rss/expanded/decoders/DecodedObject."<init>":(I)V
       5: aload_0
       6: aload_2
       7: putfield      #2                  // Field newString:Ljava/lang/String;
      10: aload_0
      11: iconst_0
      12: putfield      #3                  // Field remaining:Z
      15: aload_0
      16: iconst_0
      17: putfield      #4                  // Field remainingValue:I
      20: return

  com.google.zxing.oned.rss.expanded.decoders.DecodedInformation(int, java.lang.String, int);
    Code:
       0: aload_0
       1: iload_1
       2: invokespecial #1                  // Method com/google/zxing/oned/rss/expanded/decoders/DecodedObject."<init>":(I)V
       5: aload_0
       6: iconst_1
       7: putfield      #3                  // Field remaining:Z
      10: aload_0
      11: iload_3
      12: putfield      #4                  // Field remainingValue:I
      15: aload_0
      16: aload_2
      17: putfield      #2                  // Field newString:Ljava/lang/String;
      20: return

  java.lang.String getNewString();
    Code:
       0: aload_0
       1: getfield      #2                  // Field newString:Ljava/lang/String;
       4: areturn

  boolean isRemaining();
    Code:
       0: aload_0
       1: getfield      #3                  // Field remaining:Z
       4: ireturn

  int getRemainingValue();
    Code:
       0: aload_0
       1: getfield      #4                  // Field remainingValue:I
       4: ireturn
}
