Compiled from "DecodedNumeric.java"
final class com.google.zxing.oned.rss.expanded.decoders.DecodedNumeric extends com.google.zxing.oned.rss.expanded.decoders.DecodedObject {
  private final int firstDigit;

  private final int secondDigit;

  static final int FNC1;

  com.google.zxing.oned.rss.expanded.decoders.DecodedNumeric(int, int, int) throws com.google.zxing.FormatException;
    Code:
       0: aload_0
       1: iload_1
       2: invokespecial #1                  // Method com/google/zxing/oned/rss/expanded/decoders/DecodedObject."<init>":(I)V
       5: iload_2
       6: iflt          25
       9: iload_2
      10: bipush        10
      12: if_icmpgt     25
      15: iload_3
      16: iflt          25
      19: iload_3
      20: bipush        10
      22: if_icmple     29
      25: invokestatic  #2                  // Method com/google/zxing/FormatException.getFormatInstance:()Lcom/google/zxing/FormatException;
      28: athrow
      29: aload_0
      30: iload_2
      31: putfield      #3                  // Field firstDigit:I
      34: aload_0
      35: iload_3
      36: putfield      #4                  // Field secondDigit:I
      39: return

  int getFirstDigit();
    Code:
       0: aload_0
       1: getfield      #3                  // Field firstDigit:I
       4: ireturn

  int getSecondDigit();
    Code:
       0: aload_0
       1: getfield      #4                  // Field secondDigit:I
       4: ireturn

  int getValue();
    Code:
       0: aload_0
       1: getfield      #3                  // Field firstDigit:I
       4: bipush        10
       6: imul
       7: aload_0
       8: getfield      #4                  // Field secondDigit:I
      11: iadd
      12: ireturn

  boolean isFirstDigitFNC1();
    Code:
       0: aload_0
       1: getfield      #3                  // Field firstDigit:I
       4: bipush        10
       6: if_icmpne     13
       9: iconst_1
      10: goto          14
      13: iconst_0
      14: ireturn

  boolean isSecondDigitFNC1();
    Code:
       0: aload_0
       1: getfield      #4                  // Field secondDigit:I
       4: bipush        10
       6: if_icmpne     13
       9: iconst_1
      10: goto          14
      13: iconst_0
      14: ireturn
}
