Compiled from "FieldParser.java"
final class com.google.zxing.oned.rss.expanded.decoders.FieldParser$DataLength {
  final boolean variable;

  final int length;

  private com.google.zxing.oned.rss.expanded.decoders.FieldParser$DataLength(boolean, int);
    Code:
       0: aload_0
       1: invokespecial #1                  // Method java/lang/Object."<init>":()V
       4: aload_0
       5: iload_1
       6: putfield      #2                  // Field variable:Z
       9: aload_0
      10: iload_2
      11: putfield      #3                  // Field length:I
      14: return

  static com.google.zxing.oned.rss.expanded.decoders.FieldParser$DataLength fixed(int);
    Code:
       0: new           #4                  // class com/google/zxing/oned/rss/expanded/decoders/FieldParser$DataLength
       3: dup
       4: iconst_0
       5: iload_0
       6: invokespecial #5                  // Method "<init>":(ZI)V
       9: areturn

  static com.google.zxing.oned.rss.expanded.decoders.FieldParser$DataLength variable(int);
    Code:
       0: new           #4                  // class com/google/zxing/oned/rss/expanded/decoders/FieldParser$DataLength
       3: dup
       4: iconst_1
       5: iload_0
       6: invokespecial #5                  // Method "<init>":(ZI)V
       9: areturn
}
