Compiled from "FieldParser.java"
final class com.google.zxing.oned.rss.expanded.decoders.FieldParser {
  private static final java.util.Map<java.lang.String, com.google.zxing.oned.rss.expanded.decoders.FieldParser$DataLength> TWO_DIGIT_DATA_LENGTH;

  private static final java.util.Map<java.lang.String, com.google.zxing.oned.rss.expanded.decoders.FieldParser$DataLength> THREE_DIGIT_DATA_LENGTH;

  private static final java.util.Map<java.lang.String, com.google.zxing.oned.rss.expanded.decoders.FieldParser$DataLength> THREE_DIGIT_PLUS_DIGIT_DATA_LENGTH;

  private static final java.util.Map<java.lang.String, com.google.zxing.oned.rss.expanded.decoders.FieldParser$DataLength> FOUR_DIGIT_DATA_LENGTH;

  private com.google.zxing.oned.rss.expanded.decoders.FieldParser();
    Code:
       0: aload_0
       1: invokespecial #1                  // Method java/lang/Object."<init>":()V
       4: return

  static java.lang.String parseFieldsInGeneralPurpose(java.lang.String) throws com.google.zxing.NotFoundException;
    Code:
       0: aload_0
       1: invokevirtual #2                  // Method java/lang/String.isEmpty:()Z
       4: ifeq          9
       7: aconst_null
       8: areturn
       9: aload_0
      10: invokevirtual #3                  // Method java/lang/String.length:()I
      13: iconst_2
      14: if_icmpge     21
      17: invokestatic  #4                  // Method com/google/zxing/NotFoundException.getNotFoundInstance:()Lcom/google/zxing/NotFoundException;
      20: athrow
      21: getstatic     #5                  // Field TWO_DIGIT_DATA_LENGTH:Ljava/util/Map;
      24: aload_0
      25: iconst_0
      26: iconst_2
      27: invokevirtual #6                  // Method java/lang/String.substring:(II)Ljava/lang/String;
      30: invokeinterface #7,  2            // InterfaceMethod java/util/Map.get:(Ljava/lang/Object;)Ljava/lang/Object;
      35: checkcast     #8                  // class com/google/zxing/oned/rss/expanded/decoders/FieldParser$DataLength
      38: astore_1
      39: aload_1
      40: ifnull        70
      43: aload_1
      44: getfield      #9                  // Field com/google/zxing/oned/rss/expanded/decoders/FieldParser$DataLength.variable:Z
      47: ifeq          60
      50: iconst_2
      51: aload_1
      52: getfield      #10                 // Field com/google/zxing/oned/rss/expanded/decoders/FieldParser$DataLength.length:I
      55: aload_0
      56: invokestatic  #11                 // Method processVariableAI:(IILjava/lang/String;)Ljava/lang/String;
      59: areturn
      60: iconst_2
      61: aload_1
      62: getfield      #10                 // Field com/google/zxing/oned/rss/expanded/decoders/FieldParser$DataLength.length:I
      65: aload_0
      66: invokestatic  #12                 // Method processFixedAI:(IILjava/lang/String;)Ljava/lang/String;
      69: areturn
      70: aload_0
      71: invokevirtual #3                  // Method java/lang/String.length:()I
      74: iconst_3
      75: if_icmpge     82
      78: invokestatic  #4                  // Method com/google/zxing/NotFoundException.getNotFoundInstance:()Lcom/google/zxing/NotFoundException;
      81: athrow
      82: aload_0
      83: iconst_0
      84: iconst_3
      85: invokevirtual #6                  // Method java/lang/String.substring:(II)Ljava/lang/String;
      88: astore_2
      89: getstatic     #13                 // Field THREE_DIGIT_DATA_LENGTH:Ljava/util/Map;
      92: aload_2
      93: invokeinterface #7,  2            // InterfaceMethod java/util/Map.get:(Ljava/lang/Object;)Ljava/lang/Object;
      98: checkcast     #8                  // class com/google/zxing/oned/rss/expanded/decoders/FieldParser$DataLength
     101: astore_3
     102: aload_3
     103: ifnull        133
     106: aload_3
     107: getfield      #9                  // Field com/google/zxing/oned/rss/expanded/decoders/FieldParser$DataLength.variable:Z
     110: ifeq          123
     113: iconst_3
     114: aload_3
     115: getfield      #10                 // Field com/google/zxing/oned/rss/expanded/decoders/FieldParser$DataLength.length:I
     118: aload_0
     119: invokestatic  #11                 // Method processVariableAI:(IILjava/lang/String;)Ljava/lang/String;
     122: areturn
     123: iconst_3
     124: aload_3
     125: getfield      #10                 // Field com/google/zxing/oned/rss/expanded/decoders/FieldParser$DataLength.length:I
     128: aload_0
     129: invokestatic  #12                 // Method processFixedAI:(IILjava/lang/String;)Ljava/lang/String;
     132: areturn
     133: aload_0
     134: invokevirtual #3                  // Method java/lang/String.length:()I
     137: iconst_4
     138: if_icmpge     145
     141: invokestatic  #4                  // Method com/google/zxing/NotFoundException.getNotFoundInstance:()Lcom/google/zxing/NotFoundException;
     144: athrow
     145: getstatic     #14                 // Field THREE_DIGIT_PLUS_DIGIT_DATA_LENGTH:Ljava/util/Map;
     148: aload_2
     149: invokeinterface #7,  2            // InterfaceMethod java/util/Map.get:(Ljava/lang/Object;)Ljava/lang/Object;
     154: checkcast     #8                  // class com/google/zxing/oned/rss/expanded/decoders/FieldParser$DataLength
     157: astore        4
     159: aload         4
     161: ifnull        194
     164: aload         4
     166: getfield      #9                  // Field com/google/zxing/oned/rss/expanded/decoders/FieldParser$DataLength.variable:Z
     169: ifeq          183
     172: iconst_4
     173: aload         4
     175: getfield      #10                 // Field com/google/zxing/oned/rss/expanded/decoders/FieldParser$DataLength.length:I
     178: aload_0
     179: invokestatic  #11                 // Method processVariableAI:(IILjava/lang/String;)Ljava/lang/String;
     182: areturn
     183: iconst_4
     184: aload         4
     186: getfield      #10                 // Field com/google/zxing/oned/rss/expanded/decoders/FieldParser$DataLength.length:I
     189: aload_0
     190: invokestatic  #12                 // Method processFixedAI:(IILjava/lang/String;)Ljava/lang/String;
     193: areturn
     194: getstatic     #15                 // Field FOUR_DIGIT_DATA_LENGTH:Ljava/util/Map;
     197: aload_0
     198: iconst_0
     199: iconst_4
     200: invokevirtual #6                  // Method java/lang/String.substring:(II)Ljava/lang/String;
     203: invokeinterface #7,  2            // InterfaceMethod java/util/Map.get:(Ljava/lang/Object;)Ljava/lang/Object;
     208: checkcast     #8                  // class com/google/zxing/oned/rss/expanded/decoders/FieldParser$DataLength
     211: astore        5
     213: aload         5
     215: ifnull        248
     218: aload         5
     220: getfield      #9                  // Field com/google/zxing/oned/rss/expanded/decoders/FieldParser$DataLength.variable:Z
     223: ifeq          237
     226: iconst_4
     227: aload         5
     229: getfield      #10                 // Field com/google/zxing/oned/rss/expanded/decoders/FieldParser$DataLength.length:I
     232: aload_0
     233: invokestatic  #11                 // Method processVariableAI:(IILjava/lang/String;)Ljava/lang/String;
     236: areturn
     237: iconst_4
     238: aload         5
     240: getfield      #10                 // Field com/google/zxing/oned/rss/expanded/decoders/FieldParser$DataLength.length:I
     243: aload_0
     244: invokestatic  #12                 // Method processFixedAI:(IILjava/lang/String;)Ljava/lang/String;
     247: areturn
     248: invokestatic  #4                  // Method com/google/zxing/NotFoundException.getNotFoundInstance:()Lcom/google/zxing/NotFoundException;
     251: athrow

  private static java.lang.String processFixedAI(int, int, java.lang.String) throws com.google.zxing.NotFoundException;
    Code:
       0: aload_2
       1: invokevirtual #3                  // Method java/lang/String.length:()I
       4: iload_0
       5: if_icmpge     12
       8: invokestatic  #4                  // Method com/google/zxing/NotFoundException.getNotFoundInstance:()Lcom/google/zxing/NotFoundException;
      11: athrow
      12: aload_2
      13: iconst_0
      14: iload_0
      15: invokevirtual #6                  // Method java/lang/String.substring:(II)Ljava/lang/String;
      18: astore_3
      19: aload_2
      20: invokevirtual #3                  // Method java/lang/String.length:()I
      23: iload_0
      24: iload_1
      25: iadd
      26: if_icmpge     33
      29: invokestatic  #4                  // Method com/google/zxing/NotFoundException.getNotFoundInstance:()Lcom/google/zxing/NotFoundException;
      32: athrow
      33: aload_2
      34: iload_0
      35: iload_0
      36: iload_1
      37: iadd
      38: invokevirtual #6                  // Method java/lang/String.substring:(II)Ljava/lang/String;
      41: astore        4
      43: aload_2
      44: iload_0
      45: iload_1
      46: iadd
      47: invokevirtual #16                 // Method java/lang/String.substring:(I)Ljava/lang/String;
      50: astore        5
      52: new           #17                 // class java/lang/StringBuilder
      55: dup
      56: invokespecial #18                 // Method java/lang/StringBuilder."<init>":()V
      59: bipush        40
      61: invokevirtual #19                 // Method java/lang/StringBuilder.append:(C)Ljava/lang/StringBuilder;
      64: aload_3
      65: invokevirtual #20                 // Method java/lang/StringBuilder.append:(Ljava/lang/String;)Ljava/lang/StringBuilder;
      68: bipush        41
      70: invokevirtual #19                 // Method java/lang/StringBuilder.append:(C)Ljava/lang/StringBuilder;
      73: aload         4
      75: invokevirtual #20                 // Method java/lang/StringBuilder.append:(Ljava/lang/String;)Ljava/lang/StringBuilder;
      78: invokevirtual #21                 // Method java/lang/StringBuilder.toString:()Ljava/lang/String;
      81: astore        6
      83: aload         5
      85: invokestatic  #22                 // Method parseFieldsInGeneralPurpose:(Ljava/lang/String;)Ljava/lang/String;
      88: astore        7
      90: aload         7
      92: ifnonnull     100
      95: aload         6
      97: goto          120
     100: new           #17                 // class java/lang/StringBuilder
     103: dup
     104: invokespecial #18                 // Method java/lang/StringBuilder."<init>":()V
     107: aload         6
     109: invokevirtual #20                 // Method java/lang/StringBuilder.append:(Ljava/lang/String;)Ljava/lang/StringBuilder;
     112: aload         7
     114: invokevirtual #20                 // Method java/lang/StringBuilder.append:(Ljava/lang/String;)Ljava/lang/StringBuilder;
     117: invokevirtual #21                 // Method java/lang/StringBuilder.toString:()Ljava/lang/String;
     120: areturn

  private static java.lang.String processVariableAI(int, int, java.lang.String) throws com.google.zxing.NotFoundException;
    Code:
       0: aload_2
       1: iconst_0
       2: iload_0
       3: invokevirtual #6                  // Method java/lang/String.substring:(II)Ljava/lang/String;
       6: astore_3
       7: aload_2
       8: invokevirtual #3                  // Method java/lang/String.length:()I
      11: iload_0
      12: iload_1
      13: iadd
      14: invokestatic  #23                 // Method java/lang/Math.min:(II)I
      17: istore        4
      19: aload_2
      20: iload_0
      21: iload         4
      23: invokevirtual #6                  // Method java/lang/String.substring:(II)Ljava/lang/String;
      26: astore        5
      28: aload_2
      29: iload         4
      31: invokevirtual #16                 // Method java/lang/String.substring:(I)Ljava/lang/String;
      34: astore        6
      36: new           #17                 // class java/lang/StringBuilder
      39: dup
      40: invokespecial #18                 // Method java/lang/StringBuilder."<init>":()V
      43: bipush        40
      45: invokevirtual #19                 // Method java/lang/StringBuilder.append:(C)Ljava/lang/StringBuilder;
      48: aload_3
      49: invokevirtual #20                 // Method java/lang/StringBuilder.append:(Ljava/lang/String;)Ljava/lang/StringBuilder;
      52: bipush        41
      54: invokevirtual #19                 // Method java/lang/StringBuilder.append:(C)Ljava/lang/StringBuilder;
      57: aload         5
      59: invokevirtual #20                 // Method java/lang/StringBuilder.append:(Ljava/lang/String;)Ljava/lang/StringBuilder;
      62: invokevirtual #21                 // Method java/lang/StringBuilder.toString:()Ljava/lang/String;
      65: astore        7
      67: aload         6
      69: invokestatic  #22                 // Method parseFieldsInGeneralPurpose:(Ljava/lang/String;)Ljava/lang/String;
      72: astore        8
      74: aload         8
      76: ifnonnull     84
      79: aload         7
      81: goto          104
      84: new           #17                 // class java/lang/StringBuilder
      87: dup
      88: invokespecial #18                 // Method java/lang/StringBuilder."<init>":()V
      91: aload         7
      93: invokevirtual #20                 // Method java/lang/StringBuilder.append:(Ljava/lang/String;)Ljava/lang/StringBuilder;
      96: aload         8
      98: invokevirtual #20                 // Method java/lang/StringBuilder.append:(Ljava/lang/String;)Ljava/lang/StringBuilder;
     101: invokevirtual #21                 // Method java/lang/StringBuilder.toString:()Ljava/lang/String;
     104: areturn

  static {};
    Code:
       0: new           #24                 // class java/util/HashMap
       3: dup
       4: invokespecial #25                 // Method java/util/HashMap."<init>":()V
       7: putstatic     #5                  // Field TWO_DIGIT_DATA_LENGTH:Ljava/util/Map;
      10: getstatic     #5                  // Field TWO_DIGIT_DATA_LENGTH:Ljava/util/Map;
      13: ldc           #26                 // String 00
      15: bipush        18
      17: invokestatic  #27                 // Method com/google/zxing/oned/rss/expanded/decoders/FieldParser$DataLength.fixed:(I)Lcom/google/zxing/oned/rss/expanded/decoders/FieldParser$DataLength;
      20: invokeinterface #28,  3           // InterfaceMethod java/util/Map.put:(Ljava/lang/Object;Ljava/lang/Object;)Ljava/lang/Object;
      25: pop
      26: getstatic     #5                  // Field TWO_DIGIT_DATA_LENGTH:Ljava/util/Map;
      29: ldc           #29                 // String 01
      31: bipush        14
      33: invokestatic  #27                 // Method com/google/zxing/oned/rss/expanded/decoders/FieldParser$DataLength.fixed:(I)Lcom/google/zxing/oned/rss/expanded/decoders/FieldParser$DataLength;
      36: invokeinterface #28,  3           // InterfaceMethod java/util/Map.put:(Ljava/lang/Object;Ljava/lang/Object;)Ljava/lang/Object;
      41: pop
      42: getstatic     #5                  // Field TWO_DIGIT_DATA_LENGTH:Ljava/util/Map;
      45: ldc           #30                 // String 02
      47: bipush        14
      49: invokestatic  #27                 // Method com/google/zxing/oned/rss/expanded/decoders/FieldParser$DataLength.fixed:(I)Lcom/google/zxing/oned/rss/expanded/decoders/FieldParser$DataLength;
      52: invokeinterface #28,  3           // InterfaceMethod java/util/Map.put:(Ljava/lang/Object;Ljava/lang/Object;)Ljava/lang/Object;
      57: pop
      58: getstatic     #5                  // Field TWO_DIGIT_DATA_LENGTH:Ljava/util/Map;
      61: ldc           #31                 // String 10
      63: bipush        20
      65: invokestatic  #32                 // Method com/google/zxing/oned/rss/expanded/decoders/FieldParser$DataLength.variable:(I)Lcom/google/zxing/oned/rss/expanded/decoders/FieldParser$DataLength;
      68: invokeinterface #28,  3           // InterfaceMethod java/util/Map.put:(Ljava/lang/Object;Ljava/lang/Object;)Ljava/lang/Object;
      73: pop
      74: getstatic     #5                  // Field TWO_DIGIT_DATA_LENGTH:Ljava/util/Map;
      77: ldc           #33                 // String 11
      79: bipush        6
      81: invokestatic  #27                 // Method com/google/zxing/oned/rss/expanded/decoders/FieldParser$DataLength.fixed:(I)Lcom/google/zxing/oned/rss/expanded/decoders/FieldParser$DataLength;
      84: invokeinterface #28,  3           // InterfaceMethod java/util/Map.put:(Ljava/lang/Object;Ljava/lang/Object;)Ljava/lang/Object;
      89: pop
      90: getstatic     #5                  // Field TWO_DIGIT_DATA_LENGTH:Ljava/util/Map;
      93: ldc           #34                 // String 12
      95: bipush        6
      97: invokestatic  #27                 // Method com/google/zxing/oned/rss/expanded/decoders/FieldParser$DataLength.fixed:(I)Lcom/google/zxing/oned/rss/expanded/decoders/FieldParser$DataLength;
     100: invokeinterface #28,  3           // InterfaceMethod java/util/Map.put:(Ljava/lang/Object;Ljava/lang/Object;)Ljava/lang/Object;
     105: pop
     106: getstatic     #5                  // Field TWO_DIGIT_DATA_LENGTH:Ljava/util/Map;
     109: ldc           #35                 // String 13
     111: bipush        6
     113: invokestatic  #27                 // Method com/google/zxing/oned/rss/expanded/decoders/FieldParser$DataLength.fixed:(I)Lcom/google/zxing/oned/rss/expanded/decoders/FieldParser$DataLength;
     116: invokeinterface #28,  3           // InterfaceMethod java/util/Map.put:(Ljava/lang/Object;Ljava/lang/Object;)Ljava/lang/Object;
     121: pop
     122: getstatic     #5                  // Field TWO_DIGIT_DATA_LENGTH:Ljava/util/Map;
     125: ldc           #36                 // String 15
     127: bipush        6
     129: invokestatic  #27                 // Method com/google/zxing/oned/rss/expanded/decoders/FieldParser$DataLength.fixed:(I)Lcom/google/zxing/oned/rss/expanded/decoders/FieldParser$DataLength;
     132: invokeinterface #28,  3           // InterfaceMethod java/util/Map.put:(Ljava/lang/Object;Ljava/lang/Object;)Ljava/lang/Object;
     137: pop
     138: getstatic     #5                  // Field TWO_DIGIT_DATA_LENGTH:Ljava/util/Map;
     141: ldc           #37                 // String 17
     143: bipush        6
     145: invokestatic  #27                 // Method com/google/zxing/oned/rss/expanded/decoders/FieldParser$DataLength.fixed:(I)Lcom/google/zxing/oned/rss/expanded/decoders/FieldParser$DataLength;
     148: invokeinterface #28,  3           // InterfaceMethod java/util/Map.put:(Ljava/lang/Object;Ljava/lang/Object;)Ljava/lang/Object;
     153: pop
     154: getstatic     #5                  // Field TWO_DIGIT_DATA_LENGTH:Ljava/util/Map;
     157: ldc           #38                 // String 20
     159: iconst_2
     160: invokestatic  #27                 // Method com/google/zxing/oned/rss/expanded/decoders/FieldParser$DataLength.fixed:(I)Lcom/google/zxing/oned/rss/expanded/decoders/FieldParser$DataLength;
     163: invokeinterface #28,  3           // InterfaceMethod java/util/Map.put:(Ljava/lang/Object;Ljava/lang/Object;)Ljava/lang/Object;
     168: pop
     169: getstatic     #5                  // Field TWO_DIGIT_DATA_LENGTH:Ljava/util/Map;
     172: ldc           #39                 // String 21
     174: bipush        20
     176: invokestatic  #32                 // Method com/google/zxing/oned/rss/expanded/decoders/FieldParser$DataLength.variable:(I)Lcom/google/zxing/oned/rss/expanded/decoders/FieldParser$DataLength;
     179: invokeinterface #28,  3           // InterfaceMethod java/util/Map.put:(Ljava/lang/Object;Ljava/lang/Object;)Ljava/lang/Object;
     184: pop
     185: getstatic     #5                  // Field TWO_DIGIT_DATA_LENGTH:Ljava/util/Map;
     188: ldc           #40                 // String 22
     190: bipush        29
     192: invokestatic  #32                 // Method com/google/zxing/oned/rss/expanded/decoders/FieldParser$DataLength.variable:(I)Lcom/google/zxing/oned/rss/expanded/decoders/FieldParser$DataLength;
     195: invokeinterface #28,  3           // InterfaceMethod java/util/Map.put:(Ljava/lang/Object;Ljava/lang/Object;)Ljava/lang/Object;
     200: pop
     201: getstatic     #5                  // Field TWO_DIGIT_DATA_LENGTH:Ljava/util/Map;
     204: ldc           #41                 // String 30
     206: bipush        8
     208: invokestatic  #32                 // Method com/google/zxing/oned/rss/expanded/decoders/FieldParser$DataLength.variable:(I)Lcom/google/zxing/oned/rss/expanded/decoders/FieldParser$DataLength;
     211: invokeinterface #28,  3           // InterfaceMethod java/util/Map.put:(Ljava/lang/Object;Ljava/lang/Object;)Ljava/lang/Object;
     216: pop
     217: getstatic     #5                  // Field TWO_DIGIT_DATA_LENGTH:Ljava/util/Map;
     220: ldc           #42                 // String 37
     222: bipush        8
     224: invokestatic  #32                 // Method com/google/zxing/oned/rss/expanded/decoders/FieldParser$DataLength.variable:(I)Lcom/google/zxing/oned/rss/expanded/decoders/FieldParser$DataLength;
     227: invokeinterface #28,  3           // InterfaceMethod java/util/Map.put:(Ljava/lang/Object;Ljava/lang/Object;)Ljava/lang/Object;
     232: pop
     233: bipush        90
     235: istore_0
     236: iload_0
     237: bipush        99
     239: if_icmpgt     266
     242: getstatic     #5                  // Field TWO_DIGIT_DATA_LENGTH:Ljava/util/Map;
     245: iload_0
     246: invokestatic  #43                 // Method java/lang/String.valueOf:(I)Ljava/lang/String;
     249: bipush        30
     251: invokestatic  #32                 // Method com/google/zxing/oned/rss/expanded/decoders/FieldParser$DataLength.variable:(I)Lcom/google/zxing/oned/rss/expanded/decoders/FieldParser$DataLength;
     254: invokeinterface #28,  3           // InterfaceMethod java/util/Map.put:(Ljava/lang/Object;Ljava/lang/Object;)Ljava/lang/Object;
     259: pop
     260: iinc          0, 1
     263: goto          236
     266: new           #24                 // class java/util/HashMap
     269: dup
     270: invokespecial #25                 // Method java/util/HashMap."<init>":()V
     273: putstatic     #13                 // Field THREE_DIGIT_DATA_LENGTH:Ljava/util/Map;
     276: getstatic     #13                 // Field THREE_DIGIT_DATA_LENGTH:Ljava/util/Map;
     279: ldc           #44                 // String 240
     281: bipush        30
     283: invokestatic  #32                 // Method com/google/zxing/oned/rss/expanded/decoders/FieldParser$DataLength.variable:(I)Lcom/google/zxing/oned/rss/expanded/decoders/FieldParser$DataLength;
     286: invokeinterface #28,  3           // InterfaceMethod java/util/Map.put:(Ljava/lang/Object;Ljava/lang/Object;)Ljava/lang/Object;
     291: pop
     292: getstatic     #13                 // Field THREE_DIGIT_DATA_LENGTH:Ljava/util/Map;
     295: ldc           #45                 // String 241
     297: bipush        30
     299: invokestatic  #32                 // Method com/google/zxing/oned/rss/expanded/decoders/FieldParser$DataLength.variable:(I)Lcom/google/zxing/oned/rss/expanded/decoders/FieldParser$DataLength;
     302: invokeinterface #28,  3           // InterfaceMethod java/util/Map.put:(Ljava/lang/Object;Ljava/lang/Object;)Ljava/lang/Object;
     307: pop
     308: getstatic     #13                 // Field THREE_DIGIT_DATA_LENGTH:Ljava/util/Map;
     311: ldc           #46                 // String 242
     313: bipush        6
     315: invokestatic  #32                 // Method com/google/zxing/oned/rss/expanded/decoders/FieldParser$DataLength.variable:(I)Lcom/google/zxing/oned/rss/expanded/decoders/FieldParser$DataLength;
     318: invokeinterface #28,  3           // InterfaceMethod java/util/Map.put:(Ljava/lang/Object;Ljava/lang/Object;)Ljava/lang/Object;
     323: pop
     324: getstatic     #13                 // Field THREE_DIGIT_DATA_LENGTH:Ljava/util/Map;
     327: ldc           #47                 // String 250
     329: bipush        30
     331: invokestatic  #32                 // Method com/google/zxing/oned/rss/expanded/decoders/FieldParser$DataLength.variable:(I)Lcom/google/zxing/oned/rss/expanded/decoders/FieldParser$DataLength;
     334: invokeinterface #28,  3           // InterfaceMethod java/util/Map.put:(Ljava/lang/Object;Ljava/lang/Object;)Ljava/lang/Object;
     339: pop
     340: getstatic     #13                 // Field THREE_DIGIT_DATA_LENGTH:Ljava/util/Map;
     343: ldc           #48                 // String 251
     345: bipush        30
     347: invokestatic  #32                 // Method com/google/zxing/oned/rss/expanded/decoders/FieldParser$DataLength.variable:(I)Lcom/google/zxing/oned/rss/expanded/decoders/FieldParser$DataLength;
     350: invokeinterface #28,  3           // InterfaceMethod java/util/Map.put:(Ljava/lang/Object;Ljava/lang/Object;)Ljava/lang/Object;
     355: pop
     356: getstatic     #13                 // Field THREE_DIGIT_DATA_LENGTH:Ljava/util/Map;
     359: ldc           #49                 // String 253
     361: bipush        17
     363: invokestatic  #32                 // Method com/google/zxing/oned/rss/expanded/decoders/FieldParser$DataLength.variable:(I)Lcom/google/zxing/oned/rss/expanded/decoders/FieldParser$DataLength;
     366: invokeinterface #28,  3           // InterfaceMethod java/util/Map.put:(Ljava/lang/Object;Ljava/lang/Object;)Ljava/lang/Object;
     371: pop
     372: getstatic     #13                 // Field THREE_DIGIT_DATA_LENGTH:Ljava/util/Map;
     375: ldc           #50                 // String 254
     377: bipush        20
     379: invokestatic  #32                 // Method com/google/zxing/oned/rss/expanded/decoders/FieldParser$DataLength.variable:(I)Lcom/google/zxing/oned/rss/expanded/decoders/FieldParser$DataLength;
     382: invokeinterface #28,  3           // InterfaceMethod java/util/Map.put:(Ljava/lang/Object;Ljava/lang/Object;)Ljava/lang/Object;
     387: pop
     388: getstatic     #13                 // Field THREE_DIGIT_DATA_LENGTH:Ljava/util/Map;
     391: ldc           #51                 // String 400
     393: bipush        30
     395: invokestatic  #32                 // Method com/google/zxing/oned/rss/expanded/decoders/FieldParser$DataLength.variable:(I)Lcom/google/zxing/oned/rss/expanded/decoders/FieldParser$DataLength;
     398: invokeinterface #28,  3           // InterfaceMethod java/util/Map.put:(Ljava/lang/Object;Ljava/lang/Object;)Ljava/lang/Object;
     403: pop
     404: getstatic     #13                 // Field THREE_DIGIT_DATA_LENGTH:Ljava/util/Map;
     407: ldc           #52                 // String 401
     409: bipush        30
     411: invokestatic  #32                 // Method com/google/zxing/oned/rss/expanded/decoders/FieldParser$DataLength.variable:(I)Lcom/google/zxing/oned/rss/expanded/decoders/FieldParser$DataLength;
     414: invokeinterface #28,  3           // InterfaceMethod java/util/Map.put:(Ljava/lang/Object;Ljava/lang/Object;)Ljava/lang/Object;
     419: pop
     420: getstatic     #13                 // Field THREE_DIGIT_DATA_LENGTH:Ljava/util/Map;
     423: ldc           #53                 // String 402
     425: bipush        17
     427: invokestatic  #27                 // Method com/google/zxing/oned/rss/expanded/decoders/FieldParser$DataLength.fixed:(I)Lcom/google/zxing/oned/rss/expanded/decoders/FieldParser$DataLength;
     430: invokeinterface #28,  3           // InterfaceMethod java/util/Map.put:(Ljava/lang/Object;Ljava/lang/Object;)Ljava/lang/Object;
     435: pop
     436: getstatic     #13                 // Field THREE_DIGIT_DATA_LENGTH:Ljava/util/Map;
     439: ldc           #54                 // String 403
     441: bipush        30
     443: invokestatic  #32                 // Method com/google/zxing/oned/rss/expanded/decoders/FieldParser$DataLength.variable:(I)Lcom/google/zxing/oned/rss/expanded/decoders/FieldParser$DataLength;
     446: invokeinterface #28,  3           // InterfaceMethod java/util/Map.put:(Ljava/lang/Object;Ljava/lang/Object;)Ljava/lang/Object;
     451: pop
     452: getstatic     #13                 // Field THREE_DIGIT_DATA_LENGTH:Ljava/util/Map;
     455: ldc           #55                 // String 410
     457: bipush        13
     459: invokestatic  #27                 // Method com/google/zxing/oned/rss/expanded/decoders/FieldParser$DataLength.fixed:(I)Lcom/google/zxing/oned/rss/expanded/decoders/FieldParser$DataLength;
     462: invokeinterface #28,  3           // InterfaceMethod java/util/Map.put:(Ljava/lang/Object;Ljava/lang/Object;)Ljava/lang/Object;
     467: pop
     468: getstatic     #13                 // Field THREE_DIGIT_DATA_LENGTH:Ljava/util/Map;
     471: ldc           #56                 // String 411
     473: bipush        13
     475: invokestatic  #27                 // Method com/google/zxing/oned/rss/expanded/decoders/FieldParser$DataLength.fixed:(I)Lcom/google/zxing/oned/rss/expanded/decoders/FieldParser$DataLength;
     478: invokeinterface #28,  3           // InterfaceMethod java/util/Map.put:(Ljava/lang/Object;Ljava/lang/Object;)Ljava/lang/Object;
     483: pop
     484: getstatic     #13                 // Field THREE_DIGIT_DATA_LENGTH:Ljava/util/Map;
     487: ldc           #57                 // String 412
     489: bipush        13
     491: invokestatic  #27                 // Method com/google/zxing/oned/rss/expanded/decoders/FieldParser$DataLength.fixed:(I)Lcom/google/zxing/oned/rss/expanded/decoders/FieldParser$DataLength;
     494: invokeinterface #28,  3           // InterfaceMethod java/util/Map.put:(Ljava/lang/Object;Ljava/lang/Object;)Ljava/lang/Object;
     499: pop
     500: getstatic     #13                 // Field THREE_DIGIT_DATA_LENGTH:Ljava/util/Map;
     503: ldc           #58                 // String 413
     505: bipush        13
     507: invokestatic  #27                 // Method com/google/zxing/oned/rss/expanded/decoders/FieldParser$DataLength.fixed:(I)Lcom/google/zxing/oned/rss/expanded/decoders/FieldParser$DataLength;
     510: invokeinterface #28,  3           // InterfaceMethod java/util/Map.put:(Ljava/lang/Object;Ljava/lang/Object;)Ljava/lang/Object;
     515: pop
     516: getstatic     #13                 // Field THREE_DIGIT_DATA_LENGTH:Ljava/util/Map;
     519: ldc           #59                 // String 414
     521: bipush        13
     523: invokestatic  #27                 // Method com/google/zxing/oned/rss/expanded/decoders/FieldParser$DataLength.fixed:(I)Lcom/google/zxing/oned/rss/expanded/decoders/FieldParser$DataLength;
     526: invokeinterface #28,  3           // InterfaceMethod java/util/Map.put:(Ljava/lang/Object;Ljava/lang/Object;)Ljava/lang/Object;
     531: pop
     532: getstatic     #13                 // Field THREE_DIGIT_DATA_LENGTH:Ljava/util/Map;
     535: ldc           #60                 // String 420
     537: bipush        20
     539: invokestatic  #32                 // Method com/google/zxing/oned/rss/expanded/decoders/FieldParser$DataLength.variable:(I)Lcom/google/zxing/oned/rss/expanded/decoders/FieldParser$DataLength;
     542: invokeinterface #28,  3           // InterfaceMethod java/util/Map.put:(Ljava/lang/Object;Ljava/lang/Object;)Ljava/lang/Object;
     547: pop
     548: getstatic     #13                 // Field THREE_DIGIT_DATA_LENGTH:Ljava/util/Map;
     551: ldc           #61                 // String 421
     553: bipush        15
     555: invokestatic  #32                 // Method com/google/zxing/oned/rss/expanded/decoders/FieldParser$DataLength.variable:(I)Lcom/google/zxing/oned/rss/expanded/decoders/FieldParser$DataLength;
     558: invokeinterface #28,  3           // InterfaceMethod java/util/Map.put:(Ljava/lang/Object;Ljava/lang/Object;)Ljava/lang/Object;
     563: pop
     564: getstatic     #13                 // Field THREE_DIGIT_DATA_LENGTH:Ljava/util/Map;
     567: ldc           #62                 // String 422
     569: iconst_3
     570: invokestatic  #27                 // Method com/google/zxing/oned/rss/expanded/decoders/FieldParser$DataLength.fixed:(I)Lcom/google/zxing/oned/rss/expanded/decoders/FieldParser$DataLength;
     573: invokeinterface #28,  3           // InterfaceMethod java/util/Map.put:(Ljava/lang/Object;Ljava/lang/Object;)Ljava/lang/Object;
     578: pop
     579: getstatic     #13                 // Field THREE_DIGIT_DATA_LENGTH:Ljava/util/Map;
     582: ldc           #63                 // String 423
     584: bipush        15
     586: invokestatic  #32                 // Method com/google/zxing/oned/rss/expanded/decoders/FieldParser$DataLength.variable:(I)Lcom/google/zxing/oned/rss/expanded/decoders/FieldParser$DataLength;
     589: invokeinterface #28,  3           // InterfaceMethod java/util/Map.put:(Ljava/lang/Object;Ljava/lang/Object;)Ljava/lang/Object;
     594: pop
     595: getstatic     #13                 // Field THREE_DIGIT_DATA_LENGTH:Ljava/util/Map;
     598: ldc           #64                 // String 424
     600: iconst_3
     601: invokestatic  #27                 // Method com/google/zxing/oned/rss/expanded/decoders/FieldParser$DataLength.fixed:(I)Lcom/google/zxing/oned/rss/expanded/decoders/FieldParser$DataLength;
     604: invokeinterface #28,  3           // InterfaceMethod java/util/Map.put:(Ljava/lang/Object;Ljava/lang/Object;)Ljava/lang/Object;
     609: pop
     610: getstatic     #13                 // Field THREE_DIGIT_DATA_LENGTH:Ljava/util/Map;
     613: ldc           #65                 // String 425
     615: iconst_3
     616: invokestatic  #27                 // Method com/google/zxing/oned/rss/expanded/decoders/FieldParser$DataLength.fixed:(I)Lcom/google/zxing/oned/rss/expanded/decoders/FieldParser$DataLength;
     619: invokeinterface #28,  3           // InterfaceMethod java/util/Map.put:(Ljava/lang/Object;Ljava/lang/Object;)Ljava/lang/Object;
     624: pop
     625: getstatic     #13                 // Field THREE_DIGIT_DATA_LENGTH:Ljava/util/Map;
     628: ldc           #66                 // String 426
     630: iconst_3
     631: invokestatic  #27                 // Method com/google/zxing/oned/rss/expanded/decoders/FieldParser$DataLength.fixed:(I)Lcom/google/zxing/oned/rss/expanded/decoders/FieldParser$DataLength;
     634: invokeinterface #28,  3           // InterfaceMethod java/util/Map.put:(Ljava/lang/Object;Ljava/lang/Object;)Ljava/lang/Object;
     639: pop
     640: new           #24                 // class java/util/HashMap
     643: dup
     644: invokespecial #25                 // Method java/util/HashMap."<init>":()V
     647: putstatic     #14                 // Field THREE_DIGIT_PLUS_DIGIT_DATA_LENGTH:Ljava/util/Map;
     650: sipush        310
     653: istore_0
     654: iload_0
     655: sipush        316
     658: if_icmpgt     685
     661: getstatic     #14                 // Field THREE_DIGIT_PLUS_DIGIT_DATA_LENGTH:Ljava/util/Map;
     664: iload_0
     665: invokestatic  #43                 // Method java/lang/String.valueOf:(I)Ljava/lang/String;
     668: bipush        6
     670: invokestatic  #27                 // Method com/google/zxing/oned/rss/expanded/decoders/FieldParser$DataLength.fixed:(I)Lcom/google/zxing/oned/rss/expanded/decoders/FieldParser$DataLength;
     673: invokeinterface #28,  3           // InterfaceMethod java/util/Map.put:(Ljava/lang/Object;Ljava/lang/Object;)Ljava/lang/Object;
     678: pop
     679: iinc          0, 1
     682: goto          654
     685: sipush        320
     688: istore_0
     689: iload_0
     690: sipush        336
     693: if_icmpgt     720
     696: getstatic     #14                 // Field THREE_DIGIT_PLUS_DIGIT_DATA_LENGTH:Ljava/util/Map;
     699: iload_0
     700: invokestatic  #43                 // Method java/lang/String.valueOf:(I)Ljava/lang/String;
     703: bipush        6
     705: invokestatic  #27                 // Method com/google/zxing/oned/rss/expanded/decoders/FieldParser$DataLength.fixed:(I)Lcom/google/zxing/oned/rss/expanded/decoders/FieldParser$DataLength;
     708: invokeinterface #28,  3           // InterfaceMethod java/util/Map.put:(Ljava/lang/Object;Ljava/lang/Object;)Ljava/lang/Object;
     713: pop
     714: iinc          0, 1
     717: goto          689
     720: sipush        340
     723: istore_0
     724: iload_0
     725: sipush        357
     728: if_icmpgt     755
     731: getstatic     #14                 // Field THREE_DIGIT_PLUS_DIGIT_DATA_LENGTH:Ljava/util/Map;
     734: iload_0
     735: invokestatic  #43                 // Method java/lang/String.valueOf:(I)Ljava/lang/String;
     738: bipush        6
     740: invokestatic  #27                 // Method com/google/zxing/oned/rss/expanded/decoders/FieldParser$DataLength.fixed:(I)Lcom/google/zxing/oned/rss/expanded/decoders/FieldParser$DataLength;
     743: invokeinterface #28,  3           // InterfaceMethod java/util/Map.put:(Ljava/lang/Object;Ljava/lang/Object;)Ljava/lang/Object;
     748: pop
     749: iinc          0, 1
     752: goto          724
     755: sipush        360
     758: istore_0
     759: iload_0
     760: sipush        369
     763: if_icmpgt     790
     766: getstatic     #14                 // Field THREE_DIGIT_PLUS_DIGIT_DATA_LENGTH:Ljava/util/Map;
     769: iload_0
     770: invokestatic  #43                 // Method java/lang/String.valueOf:(I)Ljava/lang/String;
     773: bipush        6
     775: invokestatic  #27                 // Method com/google/zxing/oned/rss/expanded/decoders/FieldParser$DataLength.fixed:(I)Lcom/google/zxing/oned/rss/expanded/decoders/FieldParser$DataLength;
     778: invokeinterface #28,  3           // InterfaceMethod java/util/Map.put:(Ljava/lang/Object;Ljava/lang/Object;)Ljava/lang/Object;
     783: pop
     784: iinc          0, 1
     787: goto          759
     790: getstatic     #14                 // Field THREE_DIGIT_PLUS_DIGIT_DATA_LENGTH:Ljava/util/Map;
     793: ldc           #67                 // String 390
     795: bipush        15
     797: invokestatic  #32                 // Method com/google/zxing/oned/rss/expanded/decoders/FieldParser$DataLength.variable:(I)Lcom/google/zxing/oned/rss/expanded/decoders/FieldParser$DataLength;
     800: invokeinterface #28,  3           // InterfaceMethod java/util/Map.put:(Ljava/lang/Object;Ljava/lang/Object;)Ljava/lang/Object;
     805: pop
     806: getstatic     #14                 // Field THREE_DIGIT_PLUS_DIGIT_DATA_LENGTH:Ljava/util/Map;
     809: ldc           #68                 // String 391
     811: bipush        18
     813: invokestatic  #32                 // Method com/google/zxing/oned/rss/expanded/decoders/FieldParser$DataLength.variable:(I)Lcom/google/zxing/oned/rss/expanded/decoders/FieldParser$DataLength;
     816: invokeinterface #28,  3           // InterfaceMethod java/util/Map.put:(Ljava/lang/Object;Ljava/lang/Object;)Ljava/lang/Object;
     821: pop
     822: getstatic     #14                 // Field THREE_DIGIT_PLUS_DIGIT_DATA_LENGTH:Ljava/util/Map;
     825: ldc           #69                 // String 392
     827: bipush        15
     829: invokestatic  #32                 // Method com/google/zxing/oned/rss/expanded/decoders/FieldParser$DataLength.variable:(I)Lcom/google/zxing/oned/rss/expanded/decoders/FieldParser$DataLength;
     832: invokeinterface #28,  3           // InterfaceMethod java/util/Map.put:(Ljava/lang/Object;Ljava/lang/Object;)Ljava/lang/Object;
     837: pop
     838: getstatic     #14                 // Field THREE_DIGIT_PLUS_DIGIT_DATA_LENGTH:Ljava/util/Map;
     841: ldc           #70                 // String 393
     843: bipush        18
     845: invokestatic  #32                 // Method com/google/zxing/oned/rss/expanded/decoders/FieldParser$DataLength.variable:(I)Lcom/google/zxing/oned/rss/expanded/decoders/FieldParser$DataLength;
     848: invokeinterface #28,  3           // InterfaceMethod java/util/Map.put:(Ljava/lang/Object;Ljava/lang/Object;)Ljava/lang/Object;
     853: pop
     854: getstatic     #14                 // Field THREE_DIGIT_PLUS_DIGIT_DATA_LENGTH:Ljava/util/Map;
     857: ldc           #71                 // String 703
     859: bipush        30
     861: invokestatic  #32                 // Method com/google/zxing/oned/rss/expanded/decoders/FieldParser$DataLength.variable:(I)Lcom/google/zxing/oned/rss/expanded/decoders/FieldParser$DataLength;
     864: invokeinterface #28,  3           // InterfaceMethod java/util/Map.put:(Ljava/lang/Object;Ljava/lang/Object;)Ljava/lang/Object;
     869: pop
     870: new           #24                 // class java/util/HashMap
     873: dup
     874: invokespecial #25                 // Method java/util/HashMap."<init>":()V
     877: putstatic     #15                 // Field FOUR_DIGIT_DATA_LENGTH:Ljava/util/Map;
     880: getstatic     #15                 // Field FOUR_DIGIT_DATA_LENGTH:Ljava/util/Map;
     883: ldc           #72                 // String 7001
     885: bipush        13
     887: invokestatic  #27                 // Method com/google/zxing/oned/rss/expanded/decoders/FieldParser$DataLength.fixed:(I)Lcom/google/zxing/oned/rss/expanded/decoders/FieldParser$DataLength;
     890: invokeinterface #28,  3           // InterfaceMethod java/util/Map.put:(Ljava/lang/Object;Ljava/lang/Object;)Ljava/lang/Object;
     895: pop
     896: getstatic     #15                 // Field FOUR_DIGIT_DATA_LENGTH:Ljava/util/Map;
     899: ldc           #73                 // String 7002
     901: bipush        30
     903: invokestatic  #32                 // Method com/google/zxing/oned/rss/expanded/decoders/FieldParser$DataLength.variable:(I)Lcom/google/zxing/oned/rss/expanded/decoders/FieldParser$DataLength;
     906: invokeinterface #28,  3           // InterfaceMethod java/util/Map.put:(Ljava/lang/Object;Ljava/lang/Object;)Ljava/lang/Object;
     911: pop
     912: getstatic     #15                 // Field FOUR_DIGIT_DATA_LENGTH:Ljava/util/Map;
     915: ldc           #74                 // String 7003
     917: bipush        10
     919: invokestatic  #27                 // Method com/google/zxing/oned/rss/expanded/decoders/FieldParser$DataLength.fixed:(I)Lcom/google/zxing/oned/rss/expanded/decoders/FieldParser$DataLength;
     922: invokeinterface #28,  3           // InterfaceMethod java/util/Map.put:(Ljava/lang/Object;Ljava/lang/Object;)Ljava/lang/Object;
     927: pop
     928: getstatic     #15                 // Field FOUR_DIGIT_DATA_LENGTH:Ljava/util/Map;
     931: ldc           #75                 // String 8001
     933: bipush        14
     935: invokestatic  #27                 // Method com/google/zxing/oned/rss/expanded/decoders/FieldParser$DataLength.fixed:(I)Lcom/google/zxing/oned/rss/expanded/decoders/FieldParser$DataLength;
     938: invokeinterface #28,  3           // InterfaceMethod java/util/Map.put:(Ljava/lang/Object;Ljava/lang/Object;)Ljava/lang/Object;
     943: pop
     944: getstatic     #15                 // Field FOUR_DIGIT_DATA_LENGTH:Ljava/util/Map;
     947: ldc           #76                 // String 8002
     949: bipush        20
     951: invokestatic  #32                 // Method com/google/zxing/oned/rss/expanded/decoders/FieldParser$DataLength.variable:(I)Lcom/google/zxing/oned/rss/expanded/decoders/FieldParser$DataLength;
     954: invokeinterface #28,  3           // InterfaceMethod java/util/Map.put:(Ljava/lang/Object;Ljava/lang/Object;)Ljava/lang/Object;
     959: pop
     960: getstatic     #15                 // Field FOUR_DIGIT_DATA_LENGTH:Ljava/util/Map;
     963: ldc           #77                 // String 8003
     965: bipush        30
     967: invokestatic  #32                 // Method com/google/zxing/oned/rss/expanded/decoders/FieldParser$DataLength.variable:(I)Lcom/google/zxing/oned/rss/expanded/decoders/FieldParser$DataLength;
     970: invokeinterface #28,  3           // InterfaceMethod java/util/Map.put:(Ljava/lang/Object;Ljava/lang/Object;)Ljava/lang/Object;
     975: pop
     976: getstatic     #15                 // Field FOUR_DIGIT_DATA_LENGTH:Ljava/util/Map;
     979: ldc           #78                 // String 8004
     981: bipush        30
     983: invokestatic  #32                 // Method com/google/zxing/oned/rss/expanded/decoders/FieldParser$DataLength.variable:(I)Lcom/google/zxing/oned/rss/expanded/decoders/FieldParser$DataLength;
     986: invokeinterface #28,  3           // InterfaceMethod java/util/Map.put:(Ljava/lang/Object;Ljava/lang/Object;)Ljava/lang/Object;
     991: pop
     992: getstatic     #15                 // Field FOUR_DIGIT_DATA_LENGTH:Ljava/util/Map;
     995: ldc           #79                 // String 8005
     997: bipush        6
     999: invokestatic  #27                 // Method com/google/zxing/oned/rss/expanded/decoders/FieldParser$DataLength.fixed:(I)Lcom/google/zxing/oned/rss/expanded/decoders/FieldParser$DataLength;
    1002: invokeinterface #28,  3           // InterfaceMethod java/util/Map.put:(Ljava/lang/Object;Ljava/lang/Object;)Ljava/lang/Object;
    1007: pop
    1008: getstatic     #15                 // Field FOUR_DIGIT_DATA_LENGTH:Ljava/util/Map;
    1011: ldc           #80                 // String 8006
    1013: bipush        18
    1015: invokestatic  #27                 // Method com/google/zxing/oned/rss/expanded/decoders/FieldParser$DataLength.fixed:(I)Lcom/google/zxing/oned/rss/expanded/decoders/FieldParser$DataLength;
    1018: invokeinterface #28,  3           // InterfaceMethod java/util/Map.put:(Ljava/lang/Object;Ljava/lang/Object;)Ljava/lang/Object;
    1023: pop
    1024: getstatic     #15                 // Field FOUR_DIGIT_DATA_LENGTH:Ljava/util/Map;
    1027: ldc           #81                 // String 8007
    1029: bipush        30
    1031: invokestatic  #32                 // Method com/google/zxing/oned/rss/expanded/decoders/FieldParser$DataLength.variable:(I)Lcom/google/zxing/oned/rss/expanded/decoders/FieldParser$DataLength;
    1034: invokeinterface #28,  3           // InterfaceMethod java/util/Map.put:(Ljava/lang/Object;Ljava/lang/Object;)Ljava/lang/Object;
    1039: pop
    1040: getstatic     #15                 // Field FOUR_DIGIT_DATA_LENGTH:Ljava/util/Map;
    1043: ldc           #82                 // String 8008
    1045: bipush        12
    1047: invokestatic  #32                 // Method com/google/zxing/oned/rss/expanded/decoders/FieldParser$DataLength.variable:(I)Lcom/google/zxing/oned/rss/expanded/decoders/FieldParser$DataLength;
    1050: invokeinterface #28,  3           // InterfaceMethod java/util/Map.put:(Ljava/lang/Object;Ljava/lang/Object;)Ljava/lang/Object;
    1055: pop
    1056: getstatic     #15                 // Field FOUR_DIGIT_DATA_LENGTH:Ljava/util/Map;
    1059: ldc           #83                 // String 8018
    1061: bipush        18
    1063: invokestatic  #27                 // Method com/google/zxing/oned/rss/expanded/decoders/FieldParser$DataLength.fixed:(I)Lcom/google/zxing/oned/rss/expanded/decoders/FieldParser$DataLength;
    1066: invokeinterface #28,  3           // InterfaceMethod java/util/Map.put:(Ljava/lang/Object;Ljava/lang/Object;)Ljava/lang/Object;
    1071: pop
    1072: getstatic     #15                 // Field FOUR_DIGIT_DATA_LENGTH:Ljava/util/Map;
    1075: ldc           #84                 // String 8020
    1077: bipush        25
    1079: invokestatic  #32                 // Method com/google/zxing/oned/rss/expanded/decoders/FieldParser$DataLength.variable:(I)Lcom/google/zxing/oned/rss/expanded/decoders/FieldParser$DataLength;
    1082: invokeinterface #28,  3           // InterfaceMethod java/util/Map.put:(Ljava/lang/Object;Ljava/lang/Object;)Ljava/lang/Object;
    1087: pop
    1088: getstatic     #15                 // Field FOUR_DIGIT_DATA_LENGTH:Ljava/util/Map;
    1091: ldc           #85                 // String 8100
    1093: bipush        6
    1095: invokestatic  #27                 // Method com/google/zxing/oned/rss/expanded/decoders/FieldParser$DataLength.fixed:(I)Lcom/google/zxing/oned/rss/expanded/decoders/FieldParser$DataLength;
    1098: invokeinterface #28,  3           // InterfaceMethod java/util/Map.put:(Ljava/lang/Object;Ljava/lang/Object;)Ljava/lang/Object;
    1103: pop
    1104: getstatic     #15                 // Field FOUR_DIGIT_DATA_LENGTH:Ljava/util/Map;
    1107: ldc           #86                 // String 8101
    1109: bipush        10
    1111: invokestatic  #27                 // Method com/google/zxing/oned/rss/expanded/decoders/FieldParser$DataLength.fixed:(I)Lcom/google/zxing/oned/rss/expanded/decoders/FieldParser$DataLength;
    1114: invokeinterface #28,  3           // InterfaceMethod java/util/Map.put:(Ljava/lang/Object;Ljava/lang/Object;)Ljava/lang/Object;
    1119: pop
    1120: getstatic     #15                 // Field FOUR_DIGIT_DATA_LENGTH:Ljava/util/Map;
    1123: ldc           #87                 // String 8102
    1125: iconst_2
    1126: invokestatic  #27                 // Method com/google/zxing/oned/rss/expanded/decoders/FieldParser$DataLength.fixed:(I)Lcom/google/zxing/oned/rss/expanded/decoders/FieldParser$DataLength;
    1129: invokeinterface #28,  3           // InterfaceMethod java/util/Map.put:(Ljava/lang/Object;Ljava/lang/Object;)Ljava/lang/Object;
    1134: pop
    1135: getstatic     #15                 // Field FOUR_DIGIT_DATA_LENGTH:Ljava/util/Map;
    1138: ldc           #88                 // String 8110
    1140: bipush        70
    1142: invokestatic  #32                 // Method com/google/zxing/oned/rss/expanded/decoders/FieldParser$DataLength.variable:(I)Lcom/google/zxing/oned/rss/expanded/decoders/FieldParser$DataLength;
    1145: invokeinterface #28,  3           // InterfaceMethod java/util/Map.put:(Ljava/lang/Object;Ljava/lang/Object;)Ljava/lang/Object;
    1150: pop
    1151: getstatic     #15                 // Field FOUR_DIGIT_DATA_LENGTH:Ljava/util/Map;
    1154: ldc           #89                 // String 8200
    1156: bipush        70
    1158: invokestatic  #32                 // Method com/google/zxing/oned/rss/expanded/decoders/FieldParser$DataLength.variable:(I)Lcom/google/zxing/oned/rss/expanded/decoders/FieldParser$DataLength;
    1161: invokeinterface #28,  3           // InterfaceMethod java/util/Map.put:(Ljava/lang/Object;Ljava/lang/Object;)Ljava/lang/Object;
    1166: pop
    1167: return
}
