Compiled from "GeneralAppIdDecoder.java"
final class com.google.zxing.oned.rss.expanded.decoders.GeneralAppIdDecoder {
  private final com.google.zxing.common.BitArray information;

  private final com.google.zxing.oned.rss.expanded.decoders.CurrentParsingState current;

  private final java.lang.StringBuilder buffer;

  com.google.zxing.oned.rss.expanded.decoders.GeneralAppIdDecoder(com.google.zxing.common.BitArray);
    Code:
       0: aload_0
       1: invokespecial #1                  // Method java/lang/Object."<init>":()V
       4: aload_0
       5: new           #2                  // class com/google/zxing/oned/rss/expanded/decoders/CurrentParsingState
       8: dup
       9: invokespecial #3                  // Method com/google/zxing/oned/rss/expanded/decoders/CurrentParsingState."<init>":()V
      12: putfield      #4                  // Field current:Lcom/google/zxing/oned/rss/expanded/decoders/CurrentParsingState;
      15: aload_0
      16: new           #5                  // class java/lang/StringBuilder
      19: dup
      20: invokespecial #6                  // Method java/lang/StringBuilder."<init>":()V
      23: putfield      #7                  // Field buffer:Ljava/lang/StringBuilder;
      26: aload_0
      27: aload_1
      28: putfield      #8                  // Field information:Lcom/google/zxing/common/BitArray;
      31: return

  java.lang.String decodeAllCodes(java.lang.StringBuilder, int) throws com.google.zxing.NotFoundException, com.google.zxing.FormatException;
    Code:
       0: iload_2
       1: istore_3
       2: aconst_null
       3: astore        4
       5: aload_0
       6: iload_3
       7: aload         4
       9: invokevirtual #9                  // Method decodeGeneralPurposeField:(ILjava/lang/String;)Lcom/google/zxing/oned/rss/expanded/decoders/DecodedInformation;
      12: astore        5
      14: aload         5
      16: invokevirtual #10                 // Method com/google/zxing/oned/rss/expanded/decoders/DecodedInformation.getNewString:()Ljava/lang/String;
      19: invokestatic  #11                 // Method com/google/zxing/oned/rss/expanded/decoders/FieldParser.parseFieldsInGeneralPurpose:(Ljava/lang/String;)Ljava/lang/String;
      22: astore        6
      24: aload         6
      26: ifnull        36
      29: aload_1
      30: aload         6
      32: invokevirtual #12                 // Method java/lang/StringBuilder.append:(Ljava/lang/String;)Ljava/lang/StringBuilder;
      35: pop
      36: aload         5
      38: invokevirtual #13                 // Method com/google/zxing/oned/rss/expanded/decoders/DecodedInformation.isRemaining:()Z
      41: ifeq          57
      44: aload         5
      46: invokevirtual #14                 // Method com/google/zxing/oned/rss/expanded/decoders/DecodedInformation.getRemainingValue:()I
      49: invokestatic  #15                 // Method java/lang/String.valueOf:(I)Ljava/lang/String;
      52: astore        4
      54: goto          60
      57: aconst_null
      58: astore        4
      60: iload_3
      61: aload         5
      63: invokevirtual #16                 // Method com/google/zxing/oned/rss/expanded/decoders/DecodedInformation.getNewPosition:()I
      66: if_icmpne     72
      69: goto          81
      72: aload         5
      74: invokevirtual #16                 // Method com/google/zxing/oned/rss/expanded/decoders/DecodedInformation.getNewPosition:()I
      77: istore_3
      78: goto          5
      81: aload_1
      82: invokevirtual #17                 // Method java/lang/StringBuilder.toString:()Ljava/lang/String;
      85: areturn

  private boolean isStillNumeric(int);
    Code:
       0: iload_1
       1: bipush        7
       3: iadd
       4: aload_0
       5: getfield      #8                  // Field information:Lcom/google/zxing/common/BitArray;
       8: invokevirtual #18                 // Method com/google/zxing/common/BitArray.getSize:()I
      11: if_icmple     33
      14: iload_1
      15: iconst_4
      16: iadd
      17: aload_0
      18: getfield      #8                  // Field information:Lcom/google/zxing/common/BitArray;
      21: invokevirtual #18                 // Method com/google/zxing/common/BitArray.getSize:()I
      24: if_icmpgt     31
      27: iconst_1
      28: goto          32
      31: iconst_0
      32: ireturn
      33: iload_1
      34: istore_2
      35: iload_2
      36: iload_1
      37: iconst_3
      38: iadd
      39: if_icmpge     61
      42: aload_0
      43: getfield      #8                  // Field information:Lcom/google/zxing/common/BitArray;
      46: iload_2
      47: invokevirtual #19                 // Method com/google/zxing/common/BitArray.get:(I)Z
      50: ifeq          55
      53: iconst_1
      54: ireturn
      55: iinc          2, 1
      58: goto          35
      61: aload_0
      62: getfield      #8                  // Field information:Lcom/google/zxing/common/BitArray;
      65: iload_1
      66: iconst_3
      67: iadd
      68: invokevirtual #19                 // Method com/google/zxing/common/BitArray.get:(I)Z
      71: ireturn

  private com.google.zxing.oned.rss.expanded.decoders.DecodedNumeric decodeNumeric(int) throws com.google.zxing.FormatException;
    Code:
       0: iload_1
       1: bipush        7
       3: iadd
       4: aload_0
       5: getfield      #8                  // Field information:Lcom/google/zxing/common/BitArray;
       8: invokevirtual #18                 // Method com/google/zxing/common/BitArray.getSize:()I
      11: if_icmple     64
      14: aload_0
      15: iload_1
      16: iconst_4
      17: invokevirtual #20                 // Method extractNumericValueFromBitArray:(II)I
      20: istore_2
      21: iload_2
      22: ifne          44
      25: new           #21                 // class com/google/zxing/oned/rss/expanded/decoders/DecodedNumeric
      28: dup
      29: aload_0
      30: getfield      #8                  // Field information:Lcom/google/zxing/common/BitArray;
      33: invokevirtual #18                 // Method com/google/zxing/common/BitArray.getSize:()I
      36: bipush        10
      38: bipush        10
      40: invokespecial #22                 // Method com/google/zxing/oned/rss/expanded/decoders/DecodedNumeric."<init>":(III)V
      43: areturn
      44: new           #21                 // class com/google/zxing/oned/rss/expanded/decoders/DecodedNumeric
      47: dup
      48: aload_0
      49: getfield      #8                  // Field information:Lcom/google/zxing/common/BitArray;
      52: invokevirtual #18                 // Method com/google/zxing/common/BitArray.getSize:()I
      55: iload_2
      56: iconst_1
      57: isub
      58: bipush        10
      60: invokespecial #22                 // Method com/google/zxing/oned/rss/expanded/decoders/DecodedNumeric."<init>":(III)V
      63: areturn
      64: aload_0
      65: iload_1
      66: bipush        7
      68: invokevirtual #20                 // Method extractNumericValueFromBitArray:(II)I
      71: istore_2
      72: iload_2
      73: bipush        8
      75: isub
      76: bipush        11
      78: idiv
      79: istore_3
      80: iload_2
      81: bipush        8
      83: isub
      84: bipush        11
      86: irem
      87: istore        4
      89: new           #21                 // class com/google/zxing/oned/rss/expanded/decoders/DecodedNumeric
      92: dup
      93: iload_1
      94: bipush        7
      96: iadd
      97: iload_3
      98: iload         4
     100: invokespecial #22                 // Method com/google/zxing/oned/rss/expanded/decoders/DecodedNumeric."<init>":(III)V
     103: areturn

  int extractNumericValueFromBitArray(int, int);
    Code:
       0: aload_0
       1: getfield      #8                  // Field information:Lcom/google/zxing/common/BitArray;
       4: iload_1
       5: iload_2
       6: invokestatic  #23                 // Method extractNumericValueFromBitArray:(Lcom/google/zxing/common/BitArray;II)I
       9: ireturn

  static int extractNumericValueFromBitArray(com.google.zxing.common.BitArray, int, int);
    Code:
       0: iconst_0
       1: istore_3
       2: iconst_0
       3: istore        4
       5: iload         4
       7: iload_2
       8: if_icmpge     39
      11: aload_0
      12: iload_1
      13: iload         4
      15: iadd
      16: invokevirtual #19                 // Method com/google/zxing/common/BitArray.get:(I)Z
      19: ifeq          33
      22: iload_3
      23: iconst_1
      24: iload_2
      25: iload         4
      27: isub
      28: iconst_1
      29: isub
      30: ishl
      31: ior
      32: istore_3
      33: iinc          4, 1
      36: goto          5
      39: iload_3
      40: ireturn

  com.google.zxing.oned.rss.expanded.decoders.DecodedInformation decodeGeneralPurposeField(int, java.lang.String) throws com.google.zxing.FormatException;
    Code:
       0: aload_0
       1: getfield      #7                  // Field buffer:Ljava/lang/StringBuilder;
       4: iconst_0
       5: invokevirtual #24                 // Method java/lang/StringBuilder.setLength:(I)V
       8: aload_2
       9: ifnull        21
      12: aload_0
      13: getfield      #7                  // Field buffer:Ljava/lang/StringBuilder;
      16: aload_2
      17: invokevirtual #12                 // Method java/lang/StringBuilder.append:(Ljava/lang/String;)Ljava/lang/StringBuilder;
      20: pop
      21: aload_0
      22: getfield      #4                  // Field current:Lcom/google/zxing/oned/rss/expanded/decoders/CurrentParsingState;
      25: iload_1
      26: invokevirtual #25                 // Method com/google/zxing/oned/rss/expanded/decoders/CurrentParsingState.setPosition:(I)V
      29: aload_0
      30: invokespecial #26                 // Method parseBlocks:()Lcom/google/zxing/oned/rss/expanded/decoders/DecodedInformation;
      33: astore_3
      34: aload_3
      35: ifnull        71
      38: aload_3
      39: invokevirtual #13                 // Method com/google/zxing/oned/rss/expanded/decoders/DecodedInformation.isRemaining:()Z
      42: ifeq          71
      45: new           #27                 // class com/google/zxing/oned/rss/expanded/decoders/DecodedInformation
      48: dup
      49: aload_0
      50: getfield      #4                  // Field current:Lcom/google/zxing/oned/rss/expanded/decoders/CurrentParsingState;
      53: invokevirtual #28                 // Method com/google/zxing/oned/rss/expanded/decoders/CurrentParsingState.getPosition:()I
      56: aload_0
      57: getfield      #7                  // Field buffer:Ljava/lang/StringBuilder;
      60: invokevirtual #17                 // Method java/lang/StringBuilder.toString:()Ljava/lang/String;
      63: aload_3
      64: invokevirtual #14                 // Method com/google/zxing/oned/rss/expanded/decoders/DecodedInformation.getRemainingValue:()I
      67: invokespecial #29                 // Method com/google/zxing/oned/rss/expanded/decoders/DecodedInformation."<init>":(ILjava/lang/String;I)V
      70: areturn
      71: new           #27                 // class com/google/zxing/oned/rss/expanded/decoders/DecodedInformation
      74: dup
      75: aload_0
      76: getfield      #4                  // Field current:Lcom/google/zxing/oned/rss/expanded/decoders/CurrentParsingState;
      79: invokevirtual #28                 // Method com/google/zxing/oned/rss/expanded/decoders/CurrentParsingState.getPosition:()I
      82: aload_0
      83: getfield      #7                  // Field buffer:Ljava/lang/StringBuilder;
      86: invokevirtual #17                 // Method java/lang/StringBuilder.toString:()Ljava/lang/String;
      89: invokespecial #30                 // Method com/google/zxing/oned/rss/expanded/decoders/DecodedInformation."<init>":(ILjava/lang/String;)V
      92: areturn

  private com.google.zxing.oned.rss.expanded.decoders.DecodedInformation parseBlocks() throws com.google.zxing.FormatException;
    Code:
       0: aload_0
       1: getfield      #4                  // Field current:Lcom/google/zxing/oned/rss/expanded/decoders/CurrentParsingState;
       4: invokevirtual #28                 // Method com/google/zxing/oned/rss/expanded/decoders/CurrentParsingState.getPosition:()I
       7: istore_3
       8: aload_0
       9: getfield      #4                  // Field current:Lcom/google/zxing/oned/rss/expanded/decoders/CurrentParsingState;
      12: invokevirtual #31                 // Method com/google/zxing/oned/rss/expanded/decoders/CurrentParsingState.isAlpha:()Z
      15: ifeq          31
      18: aload_0
      19: invokespecial #32                 // Method parseAlphaBlock:()Lcom/google/zxing/oned/rss/expanded/decoders/BlockParsedResult;
      22: astore_2
      23: aload_2
      24: invokevirtual #33                 // Method com/google/zxing/oned/rss/expanded/decoders/BlockParsedResult.isFinished:()Z
      27: istore_1
      28: goto          64
      31: aload_0
      32: getfield      #4                  // Field current:Lcom/google/zxing/oned/rss/expanded/decoders/CurrentParsingState;
      35: invokevirtual #34                 // Method com/google/zxing/oned/rss/expanded/decoders/CurrentParsingState.isIsoIec646:()Z
      38: ifeq          54
      41: aload_0
      42: invokespecial #35                 // Method parseIsoIec646Block:()Lcom/google/zxing/oned/rss/expanded/decoders/BlockParsedResult;
      45: astore_2
      46: aload_2
      47: invokevirtual #33                 // Method com/google/zxing/oned/rss/expanded/decoders/BlockParsedResult.isFinished:()Z
      50: istore_1
      51: goto          64
      54: aload_0
      55: invokespecial #36                 // Method parseNumericBlock:()Lcom/google/zxing/oned/rss/expanded/decoders/BlockParsedResult;
      58: astore_2
      59: aload_2
      60: invokevirtual #33                 // Method com/google/zxing/oned/rss/expanded/decoders/BlockParsedResult.isFinished:()Z
      63: istore_1
      64: iload_3
      65: aload_0
      66: getfield      #4                  // Field current:Lcom/google/zxing/oned/rss/expanded/decoders/CurrentParsingState;
      69: invokevirtual #28                 // Method com/google/zxing/oned/rss/expanded/decoders/CurrentParsingState.getPosition:()I
      72: if_icmpeq     79
      75: iconst_1
      76: goto          80
      79: iconst_0
      80: istore        4
      82: iload         4
      84: ifne          94
      87: iload_1
      88: ifne          94
      91: goto          98
      94: iload_1
      95: ifeq          0
      98: aload_2
      99: invokevirtual #37                 // Method com/google/zxing/oned/rss/expanded/decoders/BlockParsedResult.getDecodedInformation:()Lcom/google/zxing/oned/rss/expanded/decoders/DecodedInformation;
     102: areturn

  private com.google.zxing.oned.rss.expanded.decoders.BlockParsedResult parseNumericBlock() throws com.google.zxing.FormatException;
    Code:
       0: aload_0
       1: aload_0
       2: getfield      #4                  // Field current:Lcom/google/zxing/oned/rss/expanded/decoders/CurrentParsingState;
       5: invokevirtual #28                 // Method com/google/zxing/oned/rss/expanded/decoders/CurrentParsingState.getPosition:()I
       8: invokespecial #38                 // Method isStillNumeric:(I)Z
      11: ifeq          178
      14: aload_0
      15: aload_0
      16: getfield      #4                  // Field current:Lcom/google/zxing/oned/rss/expanded/decoders/CurrentParsingState;
      19: invokevirtual #28                 // Method com/google/zxing/oned/rss/expanded/decoders/CurrentParsingState.getPosition:()I
      22: invokespecial #39                 // Method decodeNumeric:(I)Lcom/google/zxing/oned/rss/expanded/decoders/DecodedNumeric;
      25: astore_1
      26: aload_0
      27: getfield      #4                  // Field current:Lcom/google/zxing/oned/rss/expanded/decoders/CurrentParsingState;
      30: aload_1
      31: invokevirtual #40                 // Method com/google/zxing/oned/rss/expanded/decoders/DecodedNumeric.getNewPosition:()I
      34: invokevirtual #25                 // Method com/google/zxing/oned/rss/expanded/decoders/CurrentParsingState.setPosition:(I)V
      37: aload_1
      38: invokevirtual #41                 // Method com/google/zxing/oned/rss/expanded/decoders/DecodedNumeric.isFirstDigitFNC1:()Z
      41: ifeq          112
      44: aload_1
      45: invokevirtual #42                 // Method com/google/zxing/oned/rss/expanded/decoders/DecodedNumeric.isSecondDigitFNC1:()Z
      48: ifeq          76
      51: new           #27                 // class com/google/zxing/oned/rss/expanded/decoders/DecodedInformation
      54: dup
      55: aload_0
      56: getfield      #4                  // Field current:Lcom/google/zxing/oned/rss/expanded/decoders/CurrentParsingState;
      59: invokevirtual #28                 // Method com/google/zxing/oned/rss/expanded/decoders/CurrentParsingState.getPosition:()I
      62: aload_0
      63: getfield      #7                  // Field buffer:Ljava/lang/StringBuilder;
      66: invokevirtual #17                 // Method java/lang/StringBuilder.toString:()Ljava/lang/String;
      69: invokespecial #30                 // Method com/google/zxing/oned/rss/expanded/decoders/DecodedInformation."<init>":(ILjava/lang/String;)V
      72: astore_2
      73: goto          102
      76: new           #27                 // class com/google/zxing/oned/rss/expanded/decoders/DecodedInformation
      79: dup
      80: aload_0
      81: getfield      #4                  // Field current:Lcom/google/zxing/oned/rss/expanded/decoders/CurrentParsingState;
      84: invokevirtual #28                 // Method com/google/zxing/oned/rss/expanded/decoders/CurrentParsingState.getPosition:()I
      87: aload_0
      88: getfield      #7                  // Field buffer:Ljava/lang/StringBuilder;
      91: invokevirtual #17                 // Method java/lang/StringBuilder.toString:()Ljava/lang/String;
      94: aload_1
      95: invokevirtual #43                 // Method com/google/zxing/oned/rss/expanded/decoders/DecodedNumeric.getSecondDigit:()I
      98: invokespecial #29                 // Method com/google/zxing/oned/rss/expanded/decoders/DecodedInformation."<init>":(ILjava/lang/String;I)V
     101: astore_2
     102: new           #44                 // class com/google/zxing/oned/rss/expanded/decoders/BlockParsedResult
     105: dup
     106: aload_2
     107: iconst_1
     108: invokespecial #45                 // Method com/google/zxing/oned/rss/expanded/decoders/BlockParsedResult."<init>":(Lcom/google/zxing/oned/rss/expanded/decoders/DecodedInformation;Z)V
     111: areturn
     112: aload_0
     113: getfield      #7                  // Field buffer:Ljava/lang/StringBuilder;
     116: aload_1
     117: invokevirtual #46                 // Method com/google/zxing/oned/rss/expanded/decoders/DecodedNumeric.getFirstDigit:()I
     120: invokevirtual #47                 // Method java/lang/StringBuilder.append:(I)Ljava/lang/StringBuilder;
     123: pop
     124: aload_1
     125: invokevirtual #42                 // Method com/google/zxing/oned/rss/expanded/decoders/DecodedNumeric.isSecondDigitFNC1:()Z
     128: ifeq          163
     131: new           #27                 // class com/google/zxing/oned/rss/expanded/decoders/DecodedInformation
     134: dup
     135: aload_0
     136: getfield      #4                  // Field current:Lcom/google/zxing/oned/rss/expanded/decoders/CurrentParsingState;
     139: invokevirtual #28                 // Method com/google/zxing/oned/rss/expanded/decoders/CurrentParsingState.getPosition:()I
     142: aload_0
     143: getfield      #7                  // Field buffer:Ljava/lang/StringBuilder;
     146: invokevirtual #17                 // Method java/lang/StringBuilder.toString:()Ljava/lang/String;
     149: invokespecial #30                 // Method com/google/zxing/oned/rss/expanded/decoders/DecodedInformation."<init>":(ILjava/lang/String;)V
     152: astore_2
     153: new           #44                 // class com/google/zxing/oned/rss/expanded/decoders/BlockParsedResult
     156: dup
     157: aload_2
     158: iconst_1
     159: invokespecial #45                 // Method com/google/zxing/oned/rss/expanded/decoders/BlockParsedResult."<init>":(Lcom/google/zxing/oned/rss/expanded/decoders/DecodedInformation;Z)V
     162: areturn
     163: aload_0
     164: getfield      #7                  // Field buffer:Ljava/lang/StringBuilder;
     167: aload_1
     168: invokevirtual #43                 // Method com/google/zxing/oned/rss/expanded/decoders/DecodedNumeric.getSecondDigit:()I
     171: invokevirtual #47                 // Method java/lang/StringBuilder.append:(I)Ljava/lang/StringBuilder;
     174: pop
     175: goto          0
     178: aload_0
     179: aload_0
     180: getfield      #4                  // Field current:Lcom/google/zxing/oned/rss/expanded/decoders/CurrentParsingState;
     183: invokevirtual #28                 // Method com/google/zxing/oned/rss/expanded/decoders/CurrentParsingState.getPosition:()I
     186: invokespecial #48                 // Method isNumericToAlphaNumericLatch:(I)Z
     189: ifeq          207
     192: aload_0
     193: getfield      #4                  // Field current:Lcom/google/zxing/oned/rss/expanded/decoders/CurrentParsingState;
     196: invokevirtual #49                 // Method com/google/zxing/oned/rss/expanded/decoders/CurrentParsingState.setAlpha:()V
     199: aload_0
     200: getfield      #4                  // Field current:Lcom/google/zxing/oned/rss/expanded/decoders/CurrentParsingState;
     203: iconst_4
     204: invokevirtual #50                 // Method com/google/zxing/oned/rss/expanded/decoders/CurrentParsingState.incrementPosition:(I)V
     207: new           #44                 // class com/google/zxing/oned/rss/expanded/decoders/BlockParsedResult
     210: dup
     211: invokespecial #51                 // Method com/google/zxing/oned/rss/expanded/decoders/BlockParsedResult."<init>":()V
     214: areturn

  private com.google.zxing.oned.rss.expanded.decoders.BlockParsedResult parseIsoIec646Block() throws com.google.zxing.FormatException;
    Code:
       0: aload_0
       1: aload_0
       2: getfield      #4                  // Field current:Lcom/google/zxing/oned/rss/expanded/decoders/CurrentParsingState;
       5: invokevirtual #28                 // Method com/google/zxing/oned/rss/expanded/decoders/CurrentParsingState.getPosition:()I
       8: invokespecial #52                 // Method isStillIsoIec646:(I)Z
      11: ifeq          91
      14: aload_0
      15: aload_0
      16: getfield      #4                  // Field current:Lcom/google/zxing/oned/rss/expanded/decoders/CurrentParsingState;
      19: invokevirtual #28                 // Method com/google/zxing/oned/rss/expanded/decoders/CurrentParsingState.getPosition:()I
      22: invokespecial #53                 // Method decodeIsoIec646:(I)Lcom/google/zxing/oned/rss/expanded/decoders/DecodedChar;
      25: astore_1
      26: aload_0
      27: getfield      #4                  // Field current:Lcom/google/zxing/oned/rss/expanded/decoders/CurrentParsingState;
      30: aload_1
      31: invokevirtual #54                 // Method com/google/zxing/oned/rss/expanded/decoders/DecodedChar.getNewPosition:()I
      34: invokevirtual #25                 // Method com/google/zxing/oned/rss/expanded/decoders/CurrentParsingState.setPosition:(I)V
      37: aload_1
      38: invokevirtual #55                 // Method com/google/zxing/oned/rss/expanded/decoders/DecodedChar.isFNC1:()Z
      41: ifeq          76
      44: new           #27                 // class com/google/zxing/oned/rss/expanded/decoders/DecodedInformation
      47: dup
      48: aload_0
      49: getfield      #4                  // Field current:Lcom/google/zxing/oned/rss/expanded/decoders/CurrentParsingState;
      52: invokevirtual #28                 // Method com/google/zxing/oned/rss/expanded/decoders/CurrentParsingState.getPosition:()I
      55: aload_0
      56: getfield      #7                  // Field buffer:Ljava/lang/StringBuilder;
      59: invokevirtual #17                 // Method java/lang/StringBuilder.toString:()Ljava/lang/String;
      62: invokespecial #30                 // Method com/google/zxing/oned/rss/expanded/decoders/DecodedInformation."<init>":(ILjava/lang/String;)V
      65: astore_2
      66: new           #44                 // class com/google/zxing/oned/rss/expanded/decoders/BlockParsedResult
      69: dup
      70: aload_2
      71: iconst_1
      72: invokespecial #45                 // Method com/google/zxing/oned/rss/expanded/decoders/BlockParsedResult."<init>":(Lcom/google/zxing/oned/rss/expanded/decoders/DecodedInformation;Z)V
      75: areturn
      76: aload_0
      77: getfield      #7                  // Field buffer:Ljava/lang/StringBuilder;
      80: aload_1
      81: invokevirtual #56                 // Method com/google/zxing/oned/rss/expanded/decoders/DecodedChar.getValue:()C
      84: invokevirtual #57                 // Method java/lang/StringBuilder.append:(C)Ljava/lang/StringBuilder;
      87: pop
      88: goto          0
      91: aload_0
      92: aload_0
      93: getfield      #4                  // Field current:Lcom/google/zxing/oned/rss/expanded/decoders/CurrentParsingState;
      96: invokevirtual #28                 // Method com/google/zxing/oned/rss/expanded/decoders/CurrentParsingState.getPosition:()I
      99: invokespecial #58                 // Method isAlphaOr646ToNumericLatch:(I)Z
     102: ifeq          123
     105: aload_0
     106: getfield      #4                  // Field current:Lcom/google/zxing/oned/rss/expanded/decoders/CurrentParsingState;
     109: iconst_3
     110: invokevirtual #50                 // Method com/google/zxing/oned/rss/expanded/decoders/CurrentParsingState.incrementPosition:(I)V
     113: aload_0
     114: getfield      #4                  // Field current:Lcom/google/zxing/oned/rss/expanded/decoders/CurrentParsingState;
     117: invokevirtual #59                 // Method com/google/zxing/oned/rss/expanded/decoders/CurrentParsingState.setNumeric:()V
     120: goto          188
     123: aload_0
     124: aload_0
     125: getfield      #4                  // Field current:Lcom/google/zxing/oned/rss/expanded/decoders/CurrentParsingState;
     128: invokevirtual #28                 // Method com/google/zxing/oned/rss/expanded/decoders/CurrentParsingState.getPosition:()I
     131: invokespecial #60                 // Method isAlphaTo646ToAlphaLatch:(I)Z
     134: ifeq          188
     137: aload_0
     138: getfield      #4                  // Field current:Lcom/google/zxing/oned/rss/expanded/decoders/CurrentParsingState;
     141: invokevirtual #28                 // Method com/google/zxing/oned/rss/expanded/decoders/CurrentParsingState.getPosition:()I
     144: iconst_5
     145: iadd
     146: aload_0
     147: getfield      #8                  // Field information:Lcom/google/zxing/common/BitArray;
     150: invokevirtual #18                 // Method com/google/zxing/common/BitArray.getSize:()I
     153: if_icmpge     167
     156: aload_0
     157: getfield      #4                  // Field current:Lcom/google/zxing/oned/rss/expanded/decoders/CurrentParsingState;
     160: iconst_5
     161: invokevirtual #50                 // Method com/google/zxing/oned/rss/expanded/decoders/CurrentParsingState.incrementPosition:(I)V
     164: goto          181
     167: aload_0
     168: getfield      #4                  // Field current:Lcom/google/zxing/oned/rss/expanded/decoders/CurrentParsingState;
     171: aload_0
     172: getfield      #8                  // Field information:Lcom/google/zxing/common/BitArray;
     175: invokevirtual #18                 // Method com/google/zxing/common/BitArray.getSize:()I
     178: invokevirtual #25                 // Method com/google/zxing/oned/rss/expanded/decoders/CurrentParsingState.setPosition:(I)V
     181: aload_0
     182: getfield      #4                  // Field current:Lcom/google/zxing/oned/rss/expanded/decoders/CurrentParsingState;
     185: invokevirtual #49                 // Method com/google/zxing/oned/rss/expanded/decoders/CurrentParsingState.setAlpha:()V
     188: new           #44                 // class com/google/zxing/oned/rss/expanded/decoders/BlockParsedResult
     191: dup
     192: invokespecial #51                 // Method com/google/zxing/oned/rss/expanded/decoders/BlockParsedResult."<init>":()V
     195: areturn

  private com.google.zxing.oned.rss.expanded.decoders.BlockParsedResult parseAlphaBlock();
    Code:
       0: aload_0
       1: aload_0
       2: getfield      #4                  // Field current:Lcom/google/zxing/oned/rss/expanded/decoders/CurrentParsingState;
       5: invokevirtual #28                 // Method com/google/zxing/oned/rss/expanded/decoders/CurrentParsingState.getPosition:()I
       8: invokespecial #61                 // Method isStillAlpha:(I)Z
      11: ifeq          91
      14: aload_0
      15: aload_0
      16: getfield      #4                  // Field current:Lcom/google/zxing/oned/rss/expanded/decoders/CurrentParsingState;
      19: invokevirtual #28                 // Method com/google/zxing/oned/rss/expanded/decoders/CurrentParsingState.getPosition:()I
      22: invokespecial #62                 // Method decodeAlphanumeric:(I)Lcom/google/zxing/oned/rss/expanded/decoders/DecodedChar;
      25: astore_1
      26: aload_0
      27: getfield      #4                  // Field current:Lcom/google/zxing/oned/rss/expanded/decoders/CurrentParsingState;
      30: aload_1
      31: invokevirtual #54                 // Method com/google/zxing/oned/rss/expanded/decoders/DecodedChar.getNewPosition:()I
      34: invokevirtual #25                 // Method com/google/zxing/oned/rss/expanded/decoders/CurrentParsingState.setPosition:(I)V
      37: aload_1
      38: invokevirtual #55                 // Method com/google/zxing/oned/rss/expanded/decoders/DecodedChar.isFNC1:()Z
      41: ifeq          76
      44: new           #27                 // class com/google/zxing/oned/rss/expanded/decoders/DecodedInformation
      47: dup
      48: aload_0
      49: getfield      #4                  // Field current:Lcom/google/zxing/oned/rss/expanded/decoders/CurrentParsingState;
      52: invokevirtual #28                 // Method com/google/zxing/oned/rss/expanded/decoders/CurrentParsingState.getPosition:()I
      55: aload_0
      56: getfield      #7                  // Field buffer:Ljava/lang/StringBuilder;
      59: invokevirtual #17                 // Method java/lang/StringBuilder.toString:()Ljava/lang/String;
      62: invokespecial #30                 // Method com/google/zxing/oned/rss/expanded/decoders/DecodedInformation."<init>":(ILjava/lang/String;)V
      65: astore_2
      66: new           #44                 // class com/google/zxing/oned/rss/expanded/decoders/BlockParsedResult
      69: dup
      70: aload_2
      71: iconst_1
      72: invokespecial #45                 // Method com/google/zxing/oned/rss/expanded/decoders/BlockParsedResult."<init>":(Lcom/google/zxing/oned/rss/expanded/decoders/DecodedInformation;Z)V
      75: areturn
      76: aload_0
      77: getfield      #7                  // Field buffer:Ljava/lang/StringBuilder;
      80: aload_1
      81: invokevirtual #56                 // Method com/google/zxing/oned/rss/expanded/decoders/DecodedChar.getValue:()C
      84: invokevirtual #57                 // Method java/lang/StringBuilder.append:(C)Ljava/lang/StringBuilder;
      87: pop
      88: goto          0
      91: aload_0
      92: aload_0
      93: getfield      #4                  // Field current:Lcom/google/zxing/oned/rss/expanded/decoders/CurrentParsingState;
      96: invokevirtual #28                 // Method com/google/zxing/oned/rss/expanded/decoders/CurrentParsingState.getPosition:()I
      99: invokespecial #58                 // Method isAlphaOr646ToNumericLatch:(I)Z
     102: ifeq          123
     105: aload_0
     106: getfield      #4                  // Field current:Lcom/google/zxing/oned/rss/expanded/decoders/CurrentParsingState;
     109: iconst_3
     110: invokevirtual #50                 // Method com/google/zxing/oned/rss/expanded/decoders/CurrentParsingState.incrementPosition:(I)V
     113: aload_0
     114: getfield      #4                  // Field current:Lcom/google/zxing/oned/rss/expanded/decoders/CurrentParsingState;
     117: invokevirtual #59                 // Method com/google/zxing/oned/rss/expanded/decoders/CurrentParsingState.setNumeric:()V
     120: goto          188
     123: aload_0
     124: aload_0
     125: getfield      #4                  // Field current:Lcom/google/zxing/oned/rss/expanded/decoders/CurrentParsingState;
     128: invokevirtual #28                 // Method com/google/zxing/oned/rss/expanded/decoders/CurrentParsingState.getPosition:()I
     131: invokespecial #60                 // Method isAlphaTo646ToAlphaLatch:(I)Z
     134: ifeq          188
     137: aload_0
     138: getfield      #4                  // Field current:Lcom/google/zxing/oned/rss/expanded/decoders/CurrentParsingState;
     141: invokevirtual #28                 // Method com/google/zxing/oned/rss/expanded/decoders/CurrentParsingState.getPosition:()I
     144: iconst_5
     145: iadd
     146: aload_0
     147: getfield      #8                  // Field information:Lcom/google/zxing/common/BitArray;
     150: invokevirtual #18                 // Method com/google/zxing/common/BitArray.getSize:()I
     153: if_icmpge     167
     156: aload_0
     157: getfield      #4                  // Field current:Lcom/google/zxing/oned/rss/expanded/decoders/CurrentParsingState;
     160: iconst_5
     161: invokevirtual #50                 // Method com/google/zxing/oned/rss/expanded/decoders/CurrentParsingState.incrementPosition:(I)V
     164: goto          181
     167: aload_0
     168: getfield      #4                  // Field current:Lcom/google/zxing/oned/rss/expanded/decoders/CurrentParsingState;
     171: aload_0
     172: getfield      #8                  // Field information:Lcom/google/zxing/common/BitArray;
     175: invokevirtual #18                 // Method com/google/zxing/common/BitArray.getSize:()I
     178: invokevirtual #25                 // Method com/google/zxing/oned/rss/expanded/decoders/CurrentParsingState.setPosition:(I)V
     181: aload_0
     182: getfield      #4                  // Field current:Lcom/google/zxing/oned/rss/expanded/decoders/CurrentParsingState;
     185: invokevirtual #63                 // Method com/google/zxing/oned/rss/expanded/decoders/CurrentParsingState.setIsoIec646:()V
     188: new           #44                 // class com/google/zxing/oned/rss/expanded/decoders/BlockParsedResult
     191: dup
     192: invokespecial #51                 // Method com/google/zxing/oned/rss/expanded/decoders/BlockParsedResult."<init>":()V
     195: areturn

  private boolean isStillIsoIec646(int);
    Code:
       0: iload_1
       1: iconst_5
       2: iadd
       3: aload_0
       4: getfield      #8                  // Field information:Lcom/google/zxing/common/BitArray;
       7: invokevirtual #18                 // Method com/google/zxing/common/BitArray.getSize:()I
      10: if_icmple     15
      13: iconst_0
      14: ireturn
      15: aload_0
      16: iload_1
      17: iconst_5
      18: invokevirtual #20                 // Method extractNumericValueFromBitArray:(II)I
      21: istore_2
      22: iload_2
      23: iconst_5
      24: if_icmplt     35
      27: iload_2
      28: bipush        16
      30: if_icmpge     35
      33: iconst_1
      34: ireturn
      35: iload_1
      36: bipush        7
      38: iadd
      39: aload_0
      40: getfield      #8                  // Field information:Lcom/google/zxing/common/BitArray;
      43: invokevirtual #18                 // Method com/google/zxing/common/BitArray.getSize:()I
      46: if_icmple     51
      49: iconst_0
      50: ireturn
      51: aload_0
      52: iload_1
      53: bipush        7
      55: invokevirtual #20                 // Method extractNumericValueFromBitArray:(II)I
      58: istore_3
      59: iload_3
      60: bipush        64
      62: if_icmplt     73
      65: iload_3
      66: bipush        116
      68: if_icmpge     73
      71: iconst_1
      72: ireturn
      73: iload_1
      74: bipush        8
      76: iadd
      77: aload_0
      78: getfield      #8                  // Field information:Lcom/google/zxing/common/BitArray;
      81: invokevirtual #18                 // Method com/google/zxing/common/BitArray.getSize:()I
      84: if_icmple     89
      87: iconst_0
      88: ireturn
      89: aload_0
      90: iload_1
      91: bipush        8
      93: invokevirtual #20                 // Method extractNumericValueFromBitArray:(II)I
      96: istore        4
      98: iload         4
     100: sipush        232
     103: if_icmplt     118
     106: iload         4
     108: sipush        253
     111: if_icmpge     118
     114: iconst_1
     115: goto          119
     118: iconst_0
     119: ireturn

  private com.google.zxing.oned.rss.expanded.decoders.DecodedChar decodeIsoIec646(int) throws com.google.zxing.FormatException;
    Code:
       0: aload_0
       1: iload_1
       2: iconst_5
       3: invokevirtual #20                 // Method extractNumericValueFromBitArray:(II)I
       6: istore_2
       7: iload_2
       8: bipush        15
      10: if_icmpne     26
      13: new           #64                 // class com/google/zxing/oned/rss/expanded/decoders/DecodedChar
      16: dup
      17: iload_1
      18: iconst_5
      19: iadd
      20: bipush        36
      22: invokespecial #65                 // Method com/google/zxing/oned/rss/expanded/decoders/DecodedChar."<init>":(IC)V
      25: areturn
      26: iload_2
      27: iconst_5
      28: if_icmplt     55
      31: iload_2
      32: bipush        15
      34: if_icmpge     55
      37: new           #64                 // class com/google/zxing/oned/rss/expanded/decoders/DecodedChar
      40: dup
      41: iload_1
      42: iconst_5
      43: iadd
      44: bipush        48
      46: iload_2
      47: iadd
      48: iconst_5
      49: isub
      50: i2c
      51: invokespecial #65                 // Method com/google/zxing/oned/rss/expanded/decoders/DecodedChar."<init>":(IC)V
      54: areturn
      55: aload_0
      56: iload_1
      57: bipush        7
      59: invokevirtual #20                 // Method extractNumericValueFromBitArray:(II)I
      62: istore_3
      63: iload_3
      64: bipush        64
      66: if_icmplt     91
      69: iload_3
      70: bipush        90
      72: if_icmpge     91
      75: new           #64                 // class com/google/zxing/oned/rss/expanded/decoders/DecodedChar
      78: dup
      79: iload_1
      80: bipush        7
      82: iadd
      83: iload_3
      84: iconst_1
      85: iadd
      86: i2c
      87: invokespecial #65                 // Method com/google/zxing/oned/rss/expanded/decoders/DecodedChar."<init>":(IC)V
      90: areturn
      91: iload_3
      92: bipush        90
      94: if_icmplt     120
      97: iload_3
      98: bipush        116
     100: if_icmpge     120
     103: new           #64                 // class com/google/zxing/oned/rss/expanded/decoders/DecodedChar
     106: dup
     107: iload_1
     108: bipush        7
     110: iadd
     111: iload_3
     112: bipush        7
     114: iadd
     115: i2c
     116: invokespecial #65                 // Method com/google/zxing/oned/rss/expanded/decoders/DecodedChar."<init>":(IC)V
     119: areturn
     120: aload_0
     121: iload_1
     122: bipush        8
     124: invokevirtual #20                 // Method extractNumericValueFromBitArray:(II)I
     127: istore        4
     129: iload         4
     131: tableswitch   { // 232 to 252
                   232: 228
                   233: 235
                   234: 242
                   235: 249
                   236: 256
                   237: 263
                   238: 270
                   239: 277
                   240: 284
                   241: 291
                   242: 298
                   243: 305
                   244: 312
                   245: 319
                   246: 326
                   247: 333
                   248: 340
                   249: 347
                   250: 354
                   251: 361
                   252: 368
               default: 375
          }
     228: bipush        33
     230: istore        5
     232: goto          379
     235: bipush        34
     237: istore        5
     239: goto          379
     242: bipush        37
     244: istore        5
     246: goto          379
     249: bipush        38
     251: istore        5
     253: goto          379
     256: bipush        39
     258: istore        5
     260: goto          379
     263: bipush        40
     265: istore        5
     267: goto          379
     270: bipush        41
     272: istore        5
     274: goto          379
     277: bipush        42
     279: istore        5
     281: goto          379
     284: bipush        43
     286: istore        5
     288: goto          379
     291: bipush        44
     293: istore        5
     295: goto          379
     298: bipush        45
     300: istore        5
     302: goto          379
     305: bipush        46
     307: istore        5
     309: goto          379
     312: bipush        47
     314: istore        5
     316: goto          379
     319: bipush        58
     321: istore        5
     323: goto          379
     326: bipush        59
     328: istore        5
     330: goto          379
     333: bipush        60
     335: istore        5
     337: goto          379
     340: bipush        61
     342: istore        5
     344: goto          379
     347: bipush        62
     349: istore        5
     351: goto          379
     354: bipush        63
     356: istore        5
     358: goto          379
     361: bipush        95
     363: istore        5
     365: goto          379
     368: bipush        32
     370: istore        5
     372: goto          379
     375: invokestatic  #66                 // Method com/google/zxing/FormatException.getFormatInstance:()Lcom/google/zxing/FormatException;
     378: athrow
     379: new           #64                 // class com/google/zxing/oned/rss/expanded/decoders/DecodedChar
     382: dup
     383: iload_1
     384: bipush        8
     386: iadd
     387: iload         5
     389: invokespecial #65                 // Method com/google/zxing/oned/rss/expanded/decoders/DecodedChar."<init>":(IC)V
     392: areturn

  private boolean isStillAlpha(int);
    Code:
       0: iload_1
       1: iconst_5
       2: iadd
       3: aload_0
       4: getfield      #8                  // Field information:Lcom/google/zxing/common/BitArray;
       7: invokevirtual #18                 // Method com/google/zxing/common/BitArray.getSize:()I
      10: if_icmple     15
      13: iconst_0
      14: ireturn
      15: aload_0
      16: iload_1
      17: iconst_5
      18: invokevirtual #20                 // Method extractNumericValueFromBitArray:(II)I
      21: istore_2
      22: iload_2
      23: iconst_5
      24: if_icmplt     35
      27: iload_2
      28: bipush        16
      30: if_icmpge     35
      33: iconst_1
      34: ireturn
      35: iload_1
      36: bipush        6
      38: iadd
      39: aload_0
      40: getfield      #8                  // Field information:Lcom/google/zxing/common/BitArray;
      43: invokevirtual #18                 // Method com/google/zxing/common/BitArray.getSize:()I
      46: if_icmple     51
      49: iconst_0
      50: ireturn
      51: aload_0
      52: iload_1
      53: bipush        6
      55: invokevirtual #20                 // Method extractNumericValueFromBitArray:(II)I
      58: istore_3
      59: iload_3
      60: bipush        16
      62: if_icmplt     75
      65: iload_3
      66: bipush        63
      68: if_icmpge     75
      71: iconst_1
      72: goto          76
      75: iconst_0
      76: ireturn

  private com.google.zxing.oned.rss.expanded.decoders.DecodedChar decodeAlphanumeric(int);
    Code:
       0: aload_0
       1: iload_1
       2: iconst_5
       3: invokevirtual #20                 // Method extractNumericValueFromBitArray:(II)I
       6: istore_2
       7: iload_2
       8: bipush        15
      10: if_icmpne     26
      13: new           #64                 // class com/google/zxing/oned/rss/expanded/decoders/DecodedChar
      16: dup
      17: iload_1
      18: iconst_5
      19: iadd
      20: bipush        36
      22: invokespecial #65                 // Method com/google/zxing/oned/rss/expanded/decoders/DecodedChar."<init>":(IC)V
      25: areturn
      26: iload_2
      27: iconst_5
      28: if_icmplt     55
      31: iload_2
      32: bipush        15
      34: if_icmpge     55
      37: new           #64                 // class com/google/zxing/oned/rss/expanded/decoders/DecodedChar
      40: dup
      41: iload_1
      42: iconst_5
      43: iadd
      44: bipush        48
      46: iload_2
      47: iadd
      48: iconst_5
      49: isub
      50: i2c
      51: invokespecial #65                 // Method com/google/zxing/oned/rss/expanded/decoders/DecodedChar."<init>":(IC)V
      54: areturn
      55: aload_0
      56: iload_1
      57: bipush        6
      59: invokevirtual #20                 // Method extractNumericValueFromBitArray:(II)I
      62: istore_3
      63: iload_3
      64: bipush        32
      66: if_icmplt     92
      69: iload_3
      70: bipush        58
      72: if_icmpge     92
      75: new           #64                 // class com/google/zxing/oned/rss/expanded/decoders/DecodedChar
      78: dup
      79: iload_1
      80: bipush        6
      82: iadd
      83: iload_3
      84: bipush        33
      86: iadd
      87: i2c
      88: invokespecial #65                 // Method com/google/zxing/oned/rss/expanded/decoders/DecodedChar."<init>":(IC)V
      91: areturn
      92: iload_3
      93: tableswitch   { // 58 to 62
                    58: 128
                    59: 135
                    60: 142
                    61: 149
                    62: 156
               default: 163
          }
     128: bipush        42
     130: istore        4
     132: goto          190
     135: bipush        44
     137: istore        4
     139: goto          190
     142: bipush        45
     144: istore        4
     146: goto          190
     149: bipush        46
     151: istore        4
     153: goto          190
     156: bipush        47
     158: istore        4
     160: goto          190
     163: new           #67                 // class java/lang/IllegalStateException
     166: dup
     167: new           #5                  // class java/lang/StringBuilder
     170: dup
     171: invokespecial #6                  // Method java/lang/StringBuilder."<init>":()V
     174: ldc           #68                 // String Decoding invalid alphanumeric value:
     176: invokevirtual #12                 // Method java/lang/StringBuilder.append:(Ljava/lang/String;)Ljava/lang/StringBuilder;
     179: iload_3
     180: invokevirtual #47                 // Method java/lang/StringBuilder.append:(I)Ljava/lang/StringBuilder;
     183: invokevirtual #17                 // Method java/lang/StringBuilder.toString:()Ljava/lang/String;
     186: invokespecial #69                 // Method java/lang/IllegalStateException."<init>":(Ljava/lang/String;)V
     189: athrow
     190: new           #64                 // class com/google/zxing/oned/rss/expanded/decoders/DecodedChar
     193: dup
     194: iload_1
     195: bipush        6
     197: iadd
     198: iload         4
     200: invokespecial #65                 // Method com/google/zxing/oned/rss/expanded/decoders/DecodedChar."<init>":(IC)V
     203: areturn

  private boolean isAlphaTo646ToAlphaLatch(int);
    Code:
       0: iload_1
       1: iconst_1
       2: iadd
       3: aload_0
       4: getfield      #8                  // Field information:Lcom/google/zxing/common/BitArray;
       7: invokevirtual #18                 // Method com/google/zxing/common/BitArray.getSize:()I
      10: if_icmple     15
      13: iconst_0
      14: ireturn
      15: iconst_0
      16: istore_2
      17: iload_2
      18: iconst_5
      19: if_icmpge     76
      22: iload_2
      23: iload_1
      24: iadd
      25: aload_0
      26: getfield      #8                  // Field information:Lcom/google/zxing/common/BitArray;
      29: invokevirtual #18                 // Method com/google/zxing/common/BitArray.getSize:()I
      32: if_icmpge     76
      35: iload_2
      36: iconst_2
      37: if_icmpne     55
      40: aload_0
      41: getfield      #8                  // Field information:Lcom/google/zxing/common/BitArray;
      44: iload_1
      45: iconst_2
      46: iadd
      47: invokevirtual #19                 // Method com/google/zxing/common/BitArray.get:(I)Z
      50: ifne          70
      53: iconst_0
      54: ireturn
      55: aload_0
      56: getfield      #8                  // Field information:Lcom/google/zxing/common/BitArray;
      59: iload_1
      60: iload_2
      61: iadd
      62: invokevirtual #19                 // Method com/google/zxing/common/BitArray.get:(I)Z
      65: ifeq          70
      68: iconst_0
      69: ireturn
      70: iinc          2, 1
      73: goto          17
      76: iconst_1
      77: ireturn

  private boolean isAlphaOr646ToNumericLatch(int);
    Code:
       0: iload_1
       1: iconst_3
       2: iadd
       3: aload_0
       4: getfield      #8                  // Field information:Lcom/google/zxing/common/BitArray;
       7: invokevirtual #18                 // Method com/google/zxing/common/BitArray.getSize:()I
      10: if_icmple     15
      13: iconst_0
      14: ireturn
      15: iload_1
      16: istore_2
      17: iload_2
      18: iload_1
      19: iconst_3
      20: iadd
      21: if_icmpge     43
      24: aload_0
      25: getfield      #8                  // Field information:Lcom/google/zxing/common/BitArray;
      28: iload_2
      29: invokevirtual #19                 // Method com/google/zxing/common/BitArray.get:(I)Z
      32: ifeq          37
      35: iconst_0
      36: ireturn
      37: iinc          2, 1
      40: goto          17
      43: iconst_1
      44: ireturn

  private boolean isNumericToAlphaNumericLatch(int);
    Code:
       0: iload_1
       1: iconst_1
       2: iadd
       3: aload_0
       4: getfield      #8                  // Field information:Lcom/google/zxing/common/BitArray;
       7: invokevirtual #18                 // Method com/google/zxing/common/BitArray.getSize:()I
      10: if_icmple     15
      13: iconst_0
      14: ireturn
      15: iconst_0
      16: istore_2
      17: iload_2
      18: iconst_4
      19: if_icmpge     56
      22: iload_2
      23: iload_1
      24: iadd
      25: aload_0
      26: getfield      #8                  // Field information:Lcom/google/zxing/common/BitArray;
      29: invokevirtual #18                 // Method com/google/zxing/common/BitArray.getSize:()I
      32: if_icmpge     56
      35: aload_0
      36: getfield      #8                  // Field information:Lcom/google/zxing/common/BitArray;
      39: iload_1
      40: iload_2
      41: iadd
      42: invokevirtual #19                 // Method com/google/zxing/common/BitArray.get:(I)Z
      45: ifeq          50
      48: iconst_0
      49: ireturn
      50: iinc          2, 1
      53: goto          17
      56: iconst_1
      57: ireturn
}
