Compiled from "ApolloDynamicConfiguration.java"
public class org.apache.dubbo.configcenter.support.apollo.ApolloDynamicConfiguration implements org.apache.dubbo.common.config.configcenter.DynamicConfiguration {
  private static final org.apache.dubbo.common.logger.ErrorTypeAwareLogger logger;

  private static final java.lang.String APOLLO_ENV_KEY;

  private static final java.lang.String APOLLO_ADDR_KEY;

  private static final java.lang.String APOLLO_CLUSTER_KEY;

  private static final java.lang.String APOLLO_PROTOCOL_PREFIX;

  private static final java.lang.String APOLLO_APPLICATION_KEY;

  private static final java.lang.String APOLLO_APPID_KEY;

  private final org.apache.dubbo.common.URL url;

  private final com.ctrip.framework.apollo.Config dubboConfig;

  private final com.ctrip.framework.apollo.ConfigFile dubboConfigFile;

  private final java.util.concurrent.ConcurrentMap<java.lang.String, org.apache.dubbo.configcenter.support.apollo.ApolloDynamicConfiguration$ApolloListener> listeners;

  private final org.apache.dubbo.rpc.model.ApplicationModel applicationModel;

  org.apache.dubbo.configcenter.support.apollo.ApolloDynamicConfiguration(org.apache.dubbo.common.URL, org.apache.dubbo.rpc.model.ApplicationModel);
    Code:
       0: aload_0
       1: invokespecial #5                  // Method java/lang/Object."<init>":()V
       4: aload_0
       5: new           #6                  // class java/util/concurrent/ConcurrentHashMap
       8: dup
       9: invokespecial #7                  // Method java/util/concurrent/ConcurrentHashMap."<init>":()V
      12: putfield      #8                  // Field listeners:Ljava/util/concurrent/ConcurrentMap;
      15: aload_0
      16: aload_1
      17: putfield      #9                  // Field url:Lorg/apache/dubbo/common/URL;
      20: aload_0
      21: aload_2
      22: putfield      #3                  // Field applicationModel:Lorg/apache/dubbo/rpc/model/ApplicationModel;
      25: aload_1
      26: ldc           #11                 // String env
      28: invokevirtual #12                 // Method org/apache/dubbo/common/URL.getParameter:(Ljava/lang/String;)Ljava/lang/String;
      31: astore_3
      32: aload_0
      33: aload_1
      34: invokespecial #13                 // Method getAddressWithProtocolPrefix:(Lorg/apache/dubbo/common/URL;)Ljava/lang/String;
      37: astore        4
      39: aload_1
      40: ldc           #14                 // String cluster
      42: invokevirtual #12                 // Method org/apache/dubbo/common/URL.getParameter:(Ljava/lang/String;)Ljava/lang/String;
      45: astore        5
      47: aload_1
      48: ldc           #15                 // String app.id
      50: invokevirtual #12                 // Method org/apache/dubbo/common/URL.getParameter:(Ljava/lang/String;)Ljava/lang/String;
      53: astore        6
      55: ldc           #11                 // String env
      57: invokestatic  #16                 // Method java/lang/System.getProperty:(Ljava/lang/String;)Ljava/lang/String;
      60: invokestatic  #17                 // Method org/apache/dubbo/common/utils/StringUtils.isEmpty:(Ljava/lang/String;)Z
      63: ifeq          77
      66: aload_3
      67: ifnull        77
      70: ldc           #11                 // String env
      72: aload_3
      73: invokestatic  #18                 // Method java/lang/System.setProperty:(Ljava/lang/String;Ljava/lang/String;)Ljava/lang/String;
      76: pop
      77: ldc           #19                 // String apollo.meta
      79: invokestatic  #16                 // Method java/lang/System.getProperty:(Ljava/lang/String;)Ljava/lang/String;
      82: invokestatic  #17                 // Method org/apache/dubbo/common/utils/StringUtils.isEmpty:(Ljava/lang/String;)Z
      85: ifeq          108
      88: ldc           #20                 // String 0.0.0.0
      90: aload_1
      91: invokevirtual #21                 // Method org/apache/dubbo/common/URL.getHost:()Ljava/lang/String;
      94: invokevirtual #22                 // Method java/lang/String.equals:(Ljava/lang/Object;)Z
      97: ifne          108
     100: ldc           #19                 // String apollo.meta
     102: aload         4
     104: invokestatic  #18                 // Method java/lang/System.setProperty:(Ljava/lang/String;Ljava/lang/String;)Ljava/lang/String;
     107: pop
     108: ldc           #23                 // String apollo.cluster
     110: invokestatic  #16                 // Method java/lang/System.getProperty:(Ljava/lang/String;)Ljava/lang/String;
     113: invokestatic  #17                 // Method org/apache/dubbo/common/utils/StringUtils.isEmpty:(Ljava/lang/String;)Z
     116: ifeq          132
     119: aload         5
     121: ifnull        132
     124: ldc           #23                 // String apollo.cluster
     126: aload         5
     128: invokestatic  #18                 // Method java/lang/System.setProperty:(Ljava/lang/String;Ljava/lang/String;)Ljava/lang/String;
     131: pop
     132: ldc           #15                 // String app.id
     134: invokestatic  #16                 // Method java/lang/System.getProperty:(Ljava/lang/String;)Ljava/lang/String;
     137: invokestatic  #17                 // Method org/apache/dubbo/common/utils/StringUtils.isEmpty:(Ljava/lang/String;)Z
     140: ifeq          156
     143: aload         6
     145: ifnull        156
     148: ldc           #15                 // String app.id
     150: aload         6
     152: invokestatic  #18                 // Method java/lang/System.setProperty:(Ljava/lang/String;Ljava/lang/String;)Ljava/lang/String;
     155: pop
     156: aload_1
     157: ldc           #24                 // String namespace
     159: ldc           #26                 // String dubbo
     161: invokevirtual #27                 // Method org/apache/dubbo/common/URL.getParameter:(Ljava/lang/String;Ljava/lang/String;)Ljava/lang/String;
     164: astore        7
     166: aload         7
     168: invokestatic  #17                 // Method org/apache/dubbo/common/utils/StringUtils.isEmpty:(Ljava/lang/String;)Z
     171: ifeq          183
     174: aload_1
     175: ldc           #26                 // String dubbo
     177: invokevirtual #28                 // Method org/apache/dubbo/common/URL.getGroup:(Ljava/lang/String;)Ljava/lang/String;
     180: goto          185
     183: aload         7
     185: astore        8
     187: aload_0
     188: aload         8
     190: invokestatic  #29                 // Method com/ctrip/framework/apollo/ConfigService.getConfig:(Ljava/lang/String;)Lcom/ctrip/framework/apollo/Config;
     193: putfield      #30                 // Field dubboConfig:Lcom/ctrip/framework/apollo/Config;
     196: aload_0
     197: aload         8
     199: getstatic     #31                 // Field com/ctrip/framework/apollo/core/enums/ConfigFileFormat.Properties:Lcom/ctrip/framework/apollo/core/enums/ConfigFileFormat;
     202: invokestatic  #32                 // Method com/ctrip/framework/apollo/ConfigService.getConfigFile:(Ljava/lang/String;Lcom/ctrip/framework/apollo/core/enums/ConfigFileFormat;)Lcom/ctrip/framework/apollo/ConfigFile;
     205: putfield      #33                 // Field dubboConfigFile:Lcom/ctrip/framework/apollo/ConfigFile;
     208: aload_1
     209: ldc           #34                 // String check
     211: iconst_1
     212: invokevirtual #35                 // Method org/apache/dubbo/common/URL.getParameter:(Ljava/lang/String;Z)Z
     215: istore        9
     217: aload_0
     218: getfield      #30                 // Field dubboConfig:Lcom/ctrip/framework/apollo/Config;
     221: invokeinterface #36,  1           // InterfaceMethod com/ctrip/framework/apollo/Config.getSourceType:()Lcom/ctrip/framework/apollo/enums/ConfigSourceType;
     226: getstatic     #37                 // Field com/ctrip/framework/apollo/enums/ConfigSourceType.REMOTE:Lcom/ctrip/framework/apollo/enums/ConfigSourceType;
     229: if_acmpeq     328
     232: iload         9
     234: ifeq          277
     237: new           #38                 // class java/lang/IllegalStateException
     240: dup
     241: new           #39                 // class java/lang/StringBuilder
     244: dup
     245: invokespecial #40                 // Method java/lang/StringBuilder."<init>":()V
     248: ldc           #41                 // String Failed to connect to config center, the config center is Apollo, the address is:
     250: invokevirtual #42                 // Method java/lang/StringBuilder.append:(Ljava/lang/String;)Ljava/lang/StringBuilder;
     253: aload         4
     255: invokestatic  #43                 // Method org/apache/dubbo/common/utils/StringUtils.isNotEmpty:(Ljava/lang/String;)Z
     258: ifeq          266
     261: aload         4
     263: goto          267
     266: aload_3
     267: invokevirtual #42                 // Method java/lang/StringBuilder.append:(Ljava/lang/String;)Ljava/lang/StringBuilder;
     270: invokevirtual #44                 // Method java/lang/StringBuilder.toString:()Ljava/lang/String;
     273: invokespecial #45                 // Method java/lang/IllegalStateException."<init>":(Ljava/lang/String;)V
     276: athrow
     277: getstatic     #4                  // Field logger:Lorg/apache/dubbo/common/logger/ErrorTypeAwareLogger;
     280: ldc           #46                 // String 5-1
     282: ldc           #47                 // String configuration server offline
     284: ldc           #48                 // String
     286: new           #39                 // class java/lang/StringBuilder
     289: dup
     290: invokespecial #40                 // Method java/lang/StringBuilder."<init>":()V
     293: ldc           #41                 // String Failed to connect to config center, the config center is Apollo, the address is:
     295: invokevirtual #42                 // Method java/lang/StringBuilder.append:(Ljava/lang/String;)Ljava/lang/StringBuilder;
     298: aload         4
     300: invokestatic  #43                 // Method org/apache/dubbo/common/utils/StringUtils.isNotEmpty:(Ljava/lang/String;)Z
     303: ifeq          311
     306: aload         4
     308: goto          312
     311: aload_3
     312: invokevirtual #42                 // Method java/lang/StringBuilder.append:(Ljava/lang/String;)Ljava/lang/StringBuilder;
     315: ldc           #49                 // String , will use the local cache value instead before eventually the connection is established.
     317: invokevirtual #42                 // Method java/lang/StringBuilder.append:(Ljava/lang/String;)Ljava/lang/StringBuilder;
     320: invokevirtual #44                 // Method java/lang/StringBuilder.toString:()Ljava/lang/String;
     323: invokeinterface #50,  5           // InterfaceMethod org/apache/dubbo/common/logger/ErrorTypeAwareLogger.warn:(Ljava/lang/String;Ljava/lang/String;Ljava/lang/String;Ljava/lang/String;)V
     328: return

  public void close();
    Code:
       0: aload_0
       1: getfield      #8                  // Field listeners:Ljava/util/concurrent/ConcurrentMap;
       4: invokeinterface #51,  1           // InterfaceMethod java/util/concurrent/ConcurrentMap.clear:()V
       9: goto          29
      12: astore_1
      13: getstatic     #4                  // Field logger:Lorg/apache/dubbo/common/logger/ErrorTypeAwareLogger;
      16: ldc           #53                 // String 5-32
      18: ldc           #48                 // String
      20: ldc           #48                 // String
      22: ldc           #54                 // String Failed to close connect from config center, the config center is Apollo
      24: invokeinterface #50,  5           // InterfaceMethod org/apache/dubbo/common/logger/ErrorTypeAwareLogger.warn:(Ljava/lang/String;Ljava/lang/String;Ljava/lang/String;Ljava/lang/String;)V
      29: return
    Exception table:
       from    to  target type
           0     9    12   Class java/lang/UnsupportedOperationException

  private java.lang.String getAddressWithProtocolPrefix(org.apache.dubbo.common.URL);
    Code:
       0: aload_1
       1: invokevirtual #55                 // Method org/apache/dubbo/common/URL.getBackupAddress:()Ljava/lang/String;
       4: astore_2
       5: aload_2
       6: invokestatic  #43                 // Method org/apache/dubbo/common/utils/StringUtils.isNotEmpty:(Ljava/lang/String;)Z
       9: ifeq          46
      12: getstatic     #56                 // Field org/apache/dubbo/common/constants/CommonConstants.COMMA_SPLIT_PATTERN:Ljava/util/regex/Pattern;
      15: aload_2
      16: invokevirtual #57                 // Method java/util/regex/Pattern.split:(Ljava/lang/CharSequence;)[Ljava/lang/String;
      19: invokestatic  #58                 // Method java/util/Arrays.stream:([Ljava/lang/Object;)Ljava/util/stream/Stream;
      22: invokedynamic #59,  0             // InvokeDynamic #0:apply:()Ljava/util/function/Function;
      27: invokeinterface #60,  2           // InterfaceMethod java/util/stream/Stream.map:(Ljava/util/function/Function;)Ljava/util/stream/Stream;
      32: ldc           #61                 // String ,
      34: invokestatic  #62                 // Method java/util/stream/Collectors.joining:(Ljava/lang/CharSequence;)Ljava/util/stream/Collector;
      37: invokeinterface #63,  2           // InterfaceMethod java/util/stream/Stream.collect:(Ljava/util/stream/Collector;)Ljava/lang/Object;
      42: checkcast     #64                 // class java/lang/String
      45: astore_2
      46: aload_2
      47: areturn

  public void addListener(java.lang.String, java.lang.String, org.apache.dubbo.common.config.configcenter.ConfigurationListener);
    Code:
       0: aload_0
       1: getfield      #8                  // Field listeners:Ljava/util/concurrent/ConcurrentMap;
       4: new           #39                 // class java/lang/StringBuilder
       7: dup
       8: invokespecial #40                 // Method java/lang/StringBuilder."<init>":()V
      11: aload_2
      12: invokevirtual #42                 // Method java/lang/StringBuilder.append:(Ljava/lang/String;)Ljava/lang/StringBuilder;
      15: aload_1
      16: invokevirtual #42                 // Method java/lang/StringBuilder.append:(Ljava/lang/String;)Ljava/lang/StringBuilder;
      19: invokevirtual #44                 // Method java/lang/StringBuilder.toString:()Ljava/lang/String;
      22: aload_0
      23: aload_1
      24: aload_2
      25: invokedynamic #65,  0             // InvokeDynamic #1:apply:(Lorg/apache/dubbo/configcenter/support/apollo/ApolloDynamicConfiguration;Ljava/lang/String;Ljava/lang/String;)Ljava/util/function/Function;
      30: invokeinterface #66,  3           // InterfaceMethod java/util/concurrent/ConcurrentMap.computeIfAbsent:(Ljava/lang/Object;Ljava/util/function/Function;)Ljava/lang/Object;
      35: checkcast     #67                 // class org/apache/dubbo/configcenter/support/apollo/ApolloDynamicConfiguration$ApolloListener
      38: astore        4
      40: aload         4
      42: aload_3
      43: invokevirtual #68                 // Method org/apache/dubbo/configcenter/support/apollo/ApolloDynamicConfiguration$ApolloListener.addListener:(Lorg/apache/dubbo/common/config/configcenter/ConfigurationListener;)V
      46: aload_0
      47: getfield      #30                 // Field dubboConfig:Lcom/ctrip/framework/apollo/Config;
      50: aload         4
      52: aload_1
      53: invokestatic  #69                 // Method java/util/Collections.singleton:(Ljava/lang/Object;)Ljava/util/Set;
      56: invokeinterface #70,  3           // InterfaceMethod com/ctrip/framework/apollo/Config.addChangeListener:(Lcom/ctrip/framework/apollo/ConfigChangeListener;Ljava/util/Set;)V
      61: return

  public void removeListener(java.lang.String, java.lang.String, org.apache.dubbo.common.config.configcenter.ConfigurationListener);
    Code:
       0: aload_0
       1: getfield      #8                  // Field listeners:Ljava/util/concurrent/ConcurrentMap;
       4: new           #39                 // class java/lang/StringBuilder
       7: dup
       8: invokespecial #40                 // Method java/lang/StringBuilder."<init>":()V
      11: aload_2
      12: invokevirtual #42                 // Method java/lang/StringBuilder.append:(Ljava/lang/String;)Ljava/lang/StringBuilder;
      15: aload_1
      16: invokevirtual #42                 // Method java/lang/StringBuilder.append:(Ljava/lang/String;)Ljava/lang/StringBuilder;
      19: invokevirtual #44                 // Method java/lang/StringBuilder.toString:()Ljava/lang/String;
      22: invokeinterface #71,  2           // InterfaceMethod java/util/concurrent/ConcurrentMap.get:(Ljava/lang/Object;)Ljava/lang/Object;
      27: checkcast     #67                 // class org/apache/dubbo/configcenter/support/apollo/ApolloDynamicConfiguration$ApolloListener
      30: astore        4
      32: aload         4
      34: ifnull        63
      37: aload         4
      39: aload_3
      40: invokevirtual #72                 // Method org/apache/dubbo/configcenter/support/apollo/ApolloDynamicConfiguration$ApolloListener.removeListener:(Lorg/apache/dubbo/common/config/configcenter/ConfigurationListener;)V
      43: aload         4
      45: invokevirtual #73                 // Method org/apache/dubbo/configcenter/support/apollo/ApolloDynamicConfiguration$ApolloListener.hasInternalListener:()Z
      48: ifne          63
      51: aload_0
      52: getfield      #30                 // Field dubboConfig:Lcom/ctrip/framework/apollo/Config;
      55: aload         4
      57: invokeinterface #74,  2           // InterfaceMethod com/ctrip/framework/apollo/Config.removeChangeListener:(Lcom/ctrip/framework/apollo/ConfigChangeListener;)Z
      62: pop
      63: return

  public java.lang.String getConfig(java.lang.String, java.lang.String, long) throws java.lang.IllegalStateException;
    Code:
       0: aload_2
       1: invokestatic  #43                 // Method org/apache/dubbo/common/utils/StringUtils.isNotEmpty:(Ljava/lang/String;)Z
       4: ifeq          44
       7: aload_2
       8: aload_0
       9: getfield      #9                  // Field url:Lorg/apache/dubbo/common/URL;
      12: invokevirtual #75                 // Method org/apache/dubbo/common/URL.getApplication:()Ljava/lang/String;
      15: invokevirtual #22                 // Method java/lang/String.equals:(Ljava/lang/Object;)Z
      18: ifeq          32
      21: invokestatic  #76                 // Method com/ctrip/framework/apollo/ConfigService.getAppConfig:()Lcom/ctrip/framework/apollo/Config;
      24: aload_1
      25: aconst_null
      26: invokeinterface #77,  3           // InterfaceMethod com/ctrip/framework/apollo/Config.getProperty:(Ljava/lang/String;Ljava/lang/String;)Ljava/lang/String;
      31: areturn
      32: aload_2
      33: invokestatic  #29                 // Method com/ctrip/framework/apollo/ConfigService.getConfig:(Ljava/lang/String;)Lcom/ctrip/framework/apollo/Config;
      36: aload_1
      37: aconst_null
      38: invokeinterface #77,  3           // InterfaceMethod com/ctrip/framework/apollo/Config.getProperty:(Ljava/lang/String;Ljava/lang/String;)Ljava/lang/String;
      43: areturn
      44: aload_0
      45: getfield      #30                 // Field dubboConfig:Lcom/ctrip/framework/apollo/Config;
      48: aload_1
      49: aconst_null
      50: invokeinterface #77,  3           // InterfaceMethod com/ctrip/framework/apollo/Config.getProperty:(Ljava/lang/String;Ljava/lang/String;)Ljava/lang/String;
      55: areturn

  public java.lang.String getProperties(java.lang.String, java.lang.String, long) throws java.lang.IllegalStateException;
    Code:
       0: aload_2
       1: invokestatic  #17                 // Method org/apache/dubbo/common/utils/StringUtils.isEmpty:(Ljava/lang/String;)Z
       4: ifeq          17
       7: aload_0
       8: getfield      #33                 // Field dubboConfigFile:Lcom/ctrip/framework/apollo/ConfigFile;
      11: invokeinterface #78,  1           // InterfaceMethod com/ctrip/framework/apollo/ConfigFile.getContent:()Ljava/lang/String;
      16: areturn
      17: aload_2
      18: aload_0
      19: getfield      #9                  // Field url:Lorg/apache/dubbo/common/URL;
      22: invokevirtual #75                 // Method org/apache/dubbo/common/URL.getApplication:()Ljava/lang/String;
      25: invokevirtual #22                 // Method java/lang/String.equals:(Ljava/lang/Object;)Z
      28: ifeq          45
      31: ldc           #79                 // String application
      33: getstatic     #31                 // Field com/ctrip/framework/apollo/core/enums/ConfigFileFormat.Properties:Lcom/ctrip/framework/apollo/core/enums/ConfigFileFormat;
      36: invokestatic  #32                 // Method com/ctrip/framework/apollo/ConfigService.getConfigFile:(Ljava/lang/String;Lcom/ctrip/framework/apollo/core/enums/ConfigFileFormat;)Lcom/ctrip/framework/apollo/ConfigFile;
      39: invokeinterface #78,  1           // InterfaceMethod com/ctrip/framework/apollo/ConfigFile.getContent:()Ljava/lang/String;
      44: areturn
      45: aload_2
      46: getstatic     #31                 // Field com/ctrip/framework/apollo/core/enums/ConfigFileFormat.Properties:Lcom/ctrip/framework/apollo/core/enums/ConfigFileFormat;
      49: invokestatic  #32                 // Method com/ctrip/framework/apollo/ConfigService.getConfigFile:(Ljava/lang/String;Lcom/ctrip/framework/apollo/core/enums/ConfigFileFormat;)Lcom/ctrip/framework/apollo/ConfigFile;
      52: astore        5
      54: aload         5
      56: ifnonnull     91
      59: new           #38                 // class java/lang/IllegalStateException
      62: dup
      63: new           #39                 // class java/lang/StringBuilder
      66: dup
      67: invokespecial #40                 // Method java/lang/StringBuilder."<init>":()V
      70: ldc           #80                 // String There is no namespace named
      72: invokevirtual #42                 // Method java/lang/StringBuilder.append:(Ljava/lang/String;)Ljava/lang/StringBuilder;
      75: aload_2
      76: invokevirtual #42                 // Method java/lang/StringBuilder.append:(Ljava/lang/String;)Ljava/lang/StringBuilder;
      79: ldc           #81                 // String  in Apollo.
      81: invokevirtual #42                 // Method java/lang/StringBuilder.append:(Ljava/lang/String;)Ljava/lang/StringBuilder;
      84: invokevirtual #44                 // Method java/lang/StringBuilder.toString:()Ljava/lang/String;
      87: invokespecial #45                 // Method java/lang/IllegalStateException."<init>":(Ljava/lang/String;)V
      90: athrow
      91: aload         5
      93: invokeinterface #78,  1           // InterfaceMethod com/ctrip/framework/apollo/ConfigFile.getContent:()Ljava/lang/String;
      98: areturn

  public java.lang.String getInternalProperty(java.lang.String);
    Code:
       0: aload_0
       1: getfield      #30                 // Field dubboConfig:Lcom/ctrip/framework/apollo/Config;
       4: aload_1
       5: aconst_null
       6: invokeinterface #77,  3           // InterfaceMethod com/ctrip/framework/apollo/Config.getProperty:(Ljava/lang/String;Ljava/lang/String;)Ljava/lang/String;
      11: areturn

  private org.apache.dubbo.configcenter.support.apollo.ApolloDynamicConfiguration$ApolloListener createTargetListener(java.lang.String, java.lang.String);
    Code:
       0: new           #67                 // class org/apache/dubbo/configcenter/support/apollo/ApolloDynamicConfiguration$ApolloListener
       3: dup
       4: aload_0
       5: invokespecial #82                 // Method org/apache/dubbo/configcenter/support/apollo/ApolloDynamicConfiguration$ApolloListener."<init>":(Lorg/apache/dubbo/configcenter/support/apollo/ApolloDynamicConfiguration;)V
       8: areturn

  public java.lang.Object getInternalProperty(java.lang.String);
    Code:
       0: aload_0
       1: aload_1
       2: invokevirtual #83                 // Method getInternalProperty:(Ljava/lang/String;)Ljava/lang/String;
       5: areturn

  private org.apache.dubbo.configcenter.support.apollo.ApolloDynamicConfiguration$ApolloListener lambda$addListener$1(java.lang.String, java.lang.String, java.lang.String);
    Code:
       0: aload_0
       1: aload_1
       2: aload_2
       3: invokespecial #84                 // Method createTargetListener:(Ljava/lang/String;Ljava/lang/String;)Lorg/apache/dubbo/configcenter/support/apollo/ApolloDynamicConfiguration$ApolloListener;
       6: areturn

  private static java.lang.String lambda$getAddressWithProtocolPrefix$0(java.lang.String);
    Code:
       0: aload_0
       1: ldc           #85                 // String http://
       3: invokevirtual #86                 // Method java/lang/String.startsWith:(Ljava/lang/String;)Z
       6: ifeq          11
       9: aload_0
      10: areturn
      11: new           #39                 // class java/lang/StringBuilder
      14: dup
      15: invokespecial #40                 // Method java/lang/StringBuilder."<init>":()V
      18: ldc           #85                 // String http://
      20: invokevirtual #42                 // Method java/lang/StringBuilder.append:(Ljava/lang/String;)Ljava/lang/StringBuilder;
      23: aload_0
      24: invokevirtual #42                 // Method java/lang/StringBuilder.append:(Ljava/lang/String;)Ljava/lang/StringBuilder;
      27: invokevirtual #44                 // Method java/lang/StringBuilder.toString:()Ljava/lang/String;
      30: areturn

  static org.apache.dubbo.common.logger.ErrorTypeAwareLogger access$000();
    Code:
       0: getstatic     #4                  // Field logger:Lorg/apache/dubbo/common/logger/ErrorTypeAwareLogger;
       3: areturn

  static org.apache.dubbo.rpc.model.ApplicationModel access$100(org.apache.dubbo.configcenter.support.apollo.ApolloDynamicConfiguration);
    Code:
       0: aload_0
       1: getfield      #3                  // Field applicationModel:Lorg/apache/dubbo/rpc/model/ApplicationModel;
       4: areturn

  static {};
    Code:
       0: ldc           #10                 // class org/apache/dubbo/configcenter/support/apollo/ApolloDynamicConfiguration
       2: invokestatic  #87                 // Method org/apache/dubbo/common/logger/LoggerFactory.getErrorTypeAwareLogger:(Ljava/lang/Class;)Lorg/apache/dubbo/common/logger/ErrorTypeAwareLogger;
       5: putstatic     #4                  // Field logger:Lorg/apache/dubbo/common/logger/ErrorTypeAwareLogger;
       8: return
}
