Compiled from "ApolloDynamicConfiguration.java"
public class org.apache.dubbo.configcenter.support.apollo.ApolloDynamicConfiguration$ApolloListener implements com.ctrip.framework.apollo.ConfigChangeListener {
  private java.util.Set<org.apache.dubbo.common.config.configcenter.ConfigurationListener> listeners;

  final org.apache.dubbo.configcenter.support.apollo.ApolloDynamicConfiguration this$0;

  org.apache.dubbo.configcenter.support.apollo.ApolloDynamicConfiguration$ApolloListener(org.apache.dubbo.configcenter.support.apollo.ApolloDynamicConfiguration);
    Code:
       0: aload_0
       1: aload_1
       2: putfield      #3                  // Field this$0:Lorg/apache/dubbo/configcenter/support/apollo/ApolloDynamicConfiguration;
       5: aload_0
       6: invokespecial #4                  // Method java/lang/Object."<init>":()V
       9: aload_0
      10: new           #5                  // class java/util/concurrent/CopyOnWriteArraySet
      13: dup
      14: invokespecial #6                  // Method java/util/concurrent/CopyOnWriteArraySet."<init>":()V
      17: putfield      #7                  // Field listeners:Ljava/util/Set;
      20: return

  public void onChange(com.ctrip.framework.apollo.model.ConfigChangeEvent);
    Code:
       0: aload_1
       1: invokevirtual #8                  // Method com/ctrip/framework/apollo/model/ConfigChangeEvent.changedKeys:()Ljava/util/Set;
       4: invokeinterface #9,  1            // InterfaceMethod java/util/Set.iterator:()Ljava/util/Iterator;
       9: astore_2
      10: aload_2
      11: invokeinterface #10,  1           // InterfaceMethod java/util/Iterator.hasNext:()Z
      16: ifeq          178
      19: aload_2
      20: invokeinterface #11,  1           // InterfaceMethod java/util/Iterator.next:()Ljava/lang/Object;
      25: checkcast     #12                 // class java/lang/String
      28: astore_3
      29: aload_1
      30: aload_3
      31: invokevirtual #13                 // Method com/ctrip/framework/apollo/model/ConfigChangeEvent.getChange:(Ljava/lang/String;)Lcom/ctrip/framework/apollo/model/ConfigChange;
      34: astore        4
      36: ldc           #14                 // String
      38: aload         4
      40: invokevirtual #15                 // Method com/ctrip/framework/apollo/model/ConfigChange.getNewValue:()Ljava/lang/String;
      43: invokevirtual #16                 // Method java/lang/String.equals:(Ljava/lang/Object;)Z
      46: ifeq          101
      49: invokestatic  #17                 // Method org/apache/dubbo/configcenter/support/apollo/ApolloDynamicConfiguration.access$000:()Lorg/apache/dubbo/common/logger/ErrorTypeAwareLogger;
      52: ldc           #18                 // String 5-33
      54: ldc           #14                 // String
      56: ldc           #14                 // String
      58: new           #19                 // class java/lang/StringBuilder
      61: dup
      62: invokespecial #20                 // Method java/lang/StringBuilder."<init>":()V
      65: ldc           #21                 // String an empty rule is received for
      67: invokevirtual #22                 // Method java/lang/StringBuilder.append:(Ljava/lang/String;)Ljava/lang/StringBuilder;
      70: aload_3
      71: invokevirtual #22                 // Method java/lang/StringBuilder.append:(Ljava/lang/String;)Ljava/lang/StringBuilder;
      74: ldc           #23                 // String , the current working rule is
      76: invokevirtual #22                 // Method java/lang/StringBuilder.append:(Ljava/lang/String;)Ljava/lang/StringBuilder;
      79: aload         4
      81: invokevirtual #24                 // Method com/ctrip/framework/apollo/model/ConfigChange.getOldValue:()Ljava/lang/String;
      84: invokevirtual #22                 // Method java/lang/StringBuilder.append:(Ljava/lang/String;)Ljava/lang/StringBuilder;
      87: ldc           #25                 // String , the empty rule will not take effect.
      89: invokevirtual #22                 // Method java/lang/StringBuilder.append:(Ljava/lang/String;)Ljava/lang/StringBuilder;
      92: invokevirtual #26                 // Method java/lang/StringBuilder.toString:()Ljava/lang/String;
      95: invokeinterface #27,  5           // InterfaceMethod org/apache/dubbo/common/logger/ErrorTypeAwareLogger.warn:(Ljava/lang/String;Ljava/lang/String;Ljava/lang/String;Ljava/lang/String;)V
     100: return
     101: new           #28                 // class org/apache/dubbo/common/config/configcenter/ConfigChangedEvent
     104: dup
     105: aload_3
     106: aload         4
     108: invokevirtual #29                 // Method com/ctrip/framework/apollo/model/ConfigChange.getNamespace:()Ljava/lang/String;
     111: aload         4
     113: invokevirtual #15                 // Method com/ctrip/framework/apollo/model/ConfigChange.getNewValue:()Ljava/lang/String;
     116: aload_0
     117: aload         4
     119: invokespecial #30                 // Method getChangeType:(Lcom/ctrip/framework/apollo/model/ConfigChange;)Lorg/apache/dubbo/common/config/configcenter/ConfigChangeType;
     122: invokespecial #31                 // Method org/apache/dubbo/common/config/configcenter/ConfigChangedEvent."<init>":(Ljava/lang/String;Ljava/lang/String;Ljava/lang/String;Lorg/apache/dubbo/common/config/configcenter/ConfigChangeType;)V
     125: astore        5
     127: aload_0
     128: getfield      #7                  // Field listeners:Ljava/util/Set;
     131: aload         5
     133: invokedynamic #32,  0             // InvokeDynamic #0:accept:(Lorg/apache/dubbo/common/config/configcenter/ConfigChangedEvent;)Ljava/util/function/Consumer;
     138: invokeinterface #33,  2           // InterfaceMethod java/util/Set.forEach:(Ljava/util/function/Consumer;)V
     143: aload_0
     144: getfield      #3                  // Field this$0:Lorg/apache/dubbo/configcenter/support/apollo/ApolloDynamicConfiguration;
     147: invokestatic  #34                 // Method org/apache/dubbo/configcenter/support/apollo/ApolloDynamicConfiguration.access$100:(Lorg/apache/dubbo/configcenter/support/apollo/ApolloDynamicConfiguration;)Lorg/apache/dubbo/rpc/model/ApplicationModel;
     150: aload         5
     152: invokevirtual #35                 // Method org/apache/dubbo/common/config/configcenter/ConfigChangedEvent.getKey:()Ljava/lang/String;
     155: aload         5
     157: invokevirtual #36                 // Method org/apache/dubbo/common/config/configcenter/ConfigChangedEvent.getGroup:()Ljava/lang/String;
     160: ldc           #38                 // String apollo
     162: getstatic     #39                 // Field org/apache/dubbo/common/config/configcenter/ConfigChangeType.ADDED:Lorg/apache/dubbo/common/config/configcenter/ConfigChangeType;
     165: invokevirtual #40                 // Method org/apache/dubbo/common/config/configcenter/ConfigChangeType.name:()Ljava/lang/String;
     168: iconst_1
     169: invokestatic  #41                 // Method org/apache/dubbo/metrics/config/event/ConfigCenterEvent.toChangeEvent:(Lorg/apache/dubbo/rpc/model/ApplicationModel;Ljava/lang/String;Ljava/lang/String;Ljava/lang/String;Ljava/lang/String;I)Lorg/apache/dubbo/metrics/config/event/ConfigCenterEvent;
     172: invokestatic  #42                 // Method org/apache/dubbo/metrics/event/MetricsEventBus.publish:(Lorg/apache/dubbo/metrics/event/MetricsEvent;)V
     175: goto          10
     178: return

  private org.apache.dubbo.common.config.configcenter.ConfigChangeType getChangeType(com.ctrip.framework.apollo.model.ConfigChange);
    Code:
       0: aload_1
       1: invokevirtual #43                 // Method com/ctrip/framework/apollo/model/ConfigChange.getChangeType:()Lcom/ctrip/framework/apollo/enums/PropertyChangeType;
       4: getstatic     #44                 // Field com/ctrip/framework/apollo/enums/PropertyChangeType.DELETED:Lcom/ctrip/framework/apollo/enums/PropertyChangeType;
       7: if_acmpne     14
      10: getstatic     #45                 // Field org/apache/dubbo/common/config/configcenter/ConfigChangeType.DELETED:Lorg/apache/dubbo/common/config/configcenter/ConfigChangeType;
      13: areturn
      14: getstatic     #46                 // Field org/apache/dubbo/common/config/configcenter/ConfigChangeType.MODIFIED:Lorg/apache/dubbo/common/config/configcenter/ConfigChangeType;
      17: areturn

  void addListener(org.apache.dubbo.common.config.configcenter.ConfigurationListener);
    Code:
       0: aload_0
       1: getfield      #7                  // Field listeners:Ljava/util/Set;
       4: aload_1
       5: invokeinterface #47,  2           // InterfaceMethod java/util/Set.add:(Ljava/lang/Object;)Z
      10: pop
      11: return

  void removeListener(org.apache.dubbo.common.config.configcenter.ConfigurationListener);
    Code:
       0: aload_0
       1: getfield      #7                  // Field listeners:Ljava/util/Set;
       4: aload_1
       5: invokeinterface #48,  2           // InterfaceMethod java/util/Set.remove:(Ljava/lang/Object;)Z
      10: pop
      11: return

  boolean hasInternalListener();
    Code:
       0: aload_0
       1: getfield      #7                  // Field listeners:Ljava/util/Set;
       4: ifnull        23
       7: aload_0
       8: getfield      #7                  // Field listeners:Ljava/util/Set;
      11: invokeinterface #49,  1           // InterfaceMethod java/util/Set.size:()I
      16: ifle          23
      19: iconst_1
      20: goto          24
      23: iconst_0
      24: ireturn

  private static void lambda$onChange$0(org.apache.dubbo.common.config.configcenter.ConfigChangedEvent, org.apache.dubbo.common.config.configcenter.ConfigurationListener);
    Code:
       0: aload_1
       1: aload_0
       2: invokeinterface #50,  2           // InterfaceMethod org/apache/dubbo/common/config/configcenter/ConfigurationListener.process:(Lorg/apache/dubbo/common/config/configcenter/ConfigChangedEvent;)V
       7: return
}
