Compiled from "ApolloDynamicConfigurationFactory.java"
public class org.apache.dubbo.configcenter.support.apollo.ApolloDynamicConfigurationFactory extends org.apache.dubbo.common.config.configcenter.AbstractDynamicConfigurationFactory {
  private org.apache.dubbo.rpc.model.ApplicationModel applicationModel;

  public org.apache.dubbo.configcenter.support.apollo.ApolloDynamicConfigurationFactory(org.apache.dubbo.rpc.model.ApplicationModel);
    Code:
       0: aload_0
       1: invokespecial #1                  // Method org/apache/dubbo/common/config/configcenter/AbstractDynamicConfigurationFactory."<init>":()V
       4: aload_0
       5: aload_1
       6: putfield      #2                  // Field applicationModel:Lorg/apache/dubbo/rpc/model/ApplicationModel;
       9: return

  protected org.apache.dubbo.common.config.configcenter.DynamicConfiguration createDynamicConfiguration(org.apache.dubbo.common.URL);
    Code:
       0: new           #3                  // class org/apache/dubbo/configcenter/support/apollo/ApolloDynamicConfiguration
       3: dup
       4: aload_1
       5: aload_0
       6: getfield      #2                  // Field applicationModel:Lorg/apache/dubbo/rpc/model/ApplicationModel;
       9: invokespecial #4                  // Method org/apache/dubbo/configcenter/support/apollo/ApolloDynamicConfiguration."<init>":(Lorg/apache/dubbo/common/URL;Lorg/apache/dubbo/rpc/model/ApplicationModel;)V
      12: areturn
}
