Compiled from "DefaultDubboServerObservationConvention.java"
public class org.apache.dubbo.metrics.observation.DefaultDubboServerObservationConvention extends org.apache.dubbo.metrics.observation.AbstractDefaultDubboObservationConvention implements org.apache.dubbo.metrics.observation.DubboServerObservationConvention {
  private static final org.apache.dubbo.metrics.observation.DubboServerObservationConvention INSTANCE;

  public org.apache.dubbo.metrics.observation.DefaultDubboServerObservationConvention();
    Code:
       0: aload_0
       1: invokespecial #1                  // Method org/apache/dubbo/metrics/observation/AbstractDefaultDubboObservationConvention."<init>":()V
       4: return

  public static org.apache.dubbo.metrics.observation.DubboServerObservationConvention getInstance();
    Code:
       0: getstatic     #2                  // Field INSTANCE:Lorg/apache/dubbo/metrics/observation/DubboServerObservationConvention;
       3: areturn

  public java.lang.String getName();
    Code:
       0: ldc           #3                  // String rpc.server.duration
       2: areturn

  public io.micrometer.common.KeyValues getLowCardinalityKeyValues(org.apache.dubbo.metrics.observation.DubboServerContext);
    Code:
       0: aload_0
       1: aload_1
       2: invokevirtual #4                  // Method org/apache/dubbo/metrics/observation/DubboServerContext.getInvocation:()Lorg/apache/dubbo/rpc/Invocation;
       5: invokespecial #5                  // Method org/apache/dubbo/metrics/observation/AbstractDefaultDubboObservationConvention.getLowCardinalityKeyValues:(Lorg/apache/dubbo/rpc/Invocation;)Lio/micrometer/common/KeyValues;
       8: areturn

  public java.lang.String getContextualName(org.apache.dubbo.metrics.observation.DubboServerContext);
    Code:
       0: aload_0
       1: aload_1
       2: invokevirtual #4                  // Method org/apache/dubbo/metrics/observation/DubboServerContext.getInvocation:()Lorg/apache/dubbo/rpc/Invocation;
       5: invokespecial #6                  // Method org/apache/dubbo/metrics/observation/AbstractDefaultDubboObservationConvention.getContextualName:(Lorg/apache/dubbo/rpc/Invocation;)Ljava/lang/String;
       8: areturn

  public java.lang.String getContextualName(io.micrometer.observation.Observation$Context);
    Code:
       0: aload_0
       1: aload_1
       2: checkcast     #7                  // class org/apache/dubbo/metrics/observation/DubboServerContext
       5: invokevirtual #8                  // Method getContextualName:(Lorg/apache/dubbo/metrics/observation/DubboServerContext;)Ljava/lang/String;
       8: areturn

  public io.micrometer.common.KeyValues getLowCardinalityKeyValues(io.micrometer.observation.Observation$Context);
    Code:
       0: aload_0
       1: aload_1
       2: checkcast     #7                  // class org/apache/dubbo/metrics/observation/DubboServerContext
       5: invokevirtual #9                  // Method getLowCardinalityKeyValues:(Lorg/apache/dubbo/metrics/observation/DubboServerContext;)Lio/micrometer/common/KeyValues;
       8: areturn

  static {};
    Code:
       0: new           #10                 // class org/apache/dubbo/metrics/observation/DefaultDubboServerObservationConvention
       3: dup
       4: invokespecial #11                 // Method "<init>":()V
       7: putstatic     #2                  // Field INSTANCE:Lorg/apache/dubbo/metrics/observation/DubboServerObservationConvention;
      10: return
}
