Compiled from "DefaultDubboClientObservationConvention.java"
public class org.apache.dubbo.metrics.observation.DefaultDubboClientObservationConvention extends org.apache.dubbo.metrics.observation.AbstractDefaultDubboObservationConvention implements org.apache.dubbo.metrics.observation.DubboClientObservationConvention {
  private static final org.apache.dubbo.metrics.observation.DubboClientObservationConvention INSTANCE;

  public org.apache.dubbo.metrics.observation.DefaultDubboClientObservationConvention();
    Code:
       0: aload_0
       1: invokespecial #1                  // Method org/apache/dubbo/metrics/observation/AbstractDefaultDubboObservationConvention."<init>":()V
       4: return

  public static org.apache.dubbo.metrics.observation.DubboClientObservationConvention getInstance();
    Code:
       0: getstatic     #2                  // Field INSTANCE:Lorg/apache/dubbo/metrics/observation/DubboClientObservationConvention;
       3: areturn

  public java.lang.String getName();
    Code:
       0: ldc           #3                  // String rpc.client.duration
       2: areturn

  public io.micrometer.common.KeyValues getLowCardinalityKeyValues(org.apache.dubbo.metrics.observation.DubboClientContext);
    Code:
       0: aload_0
       1: aload_1
       2: invokevirtual #4                  // Method org/apache/dubbo/metrics/observation/DubboClientContext.getInvocation:()Lorg/apache/dubbo/rpc/Invocation;
       5: invokespecial #5                  // Method org/apache/dubbo/metrics/observation/AbstractDefaultDubboObservationConvention.getLowCardinalityKeyValues:(Lorg/apache/dubbo/rpc/Invocation;)Lio/micrometer/common/KeyValues;
       8: astore_2
       9: aload_0
      10: aload_2
      11: aload_1
      12: invokespecial #6                  // Method withRemoteHostPort:(Lio/micrometer/common/KeyValues;Lorg/apache/dubbo/metrics/observation/DubboClientContext;)Lio/micrometer/common/KeyValues;
      15: areturn

  private io.micrometer.common.KeyValues withRemoteHostPort(io.micrometer.common.KeyValues, org.apache.dubbo.metrics.observation.DubboClientContext);
    Code:
       0: aload_2
       1: invokevirtual #4                  // Method org/apache/dubbo/metrics/observation/DubboClientContext.getInvocation:()Lorg/apache/dubbo/rpc/Invocation;
       4: invokeinterface #7,  1            // InterfaceMethod org/apache/dubbo/rpc/Invocation.getInvokedInvokers:()Ljava/util/List;
       9: astore_3
      10: aload_3
      11: invokeinterface #8,  1            // InterfaceMethod java/util/List.isEmpty:()Z
      16: ifeq          21
      19: aload_1
      20: areturn
      21: aload_3
      22: iconst_0
      23: invokeinterface #9,  2            // InterfaceMethod java/util/List.get:(I)Ljava/lang/Object;
      28: checkcast     #10                 // class org/apache/dubbo/rpc/Invoker
      31: astore        4
      33: aload         4
      35: invokeinterface #11,  1           // InterfaceMethod org/apache/dubbo/rpc/Invoker.getUrl:()Lorg/apache/dubbo/common/URL;
      40: astore        5
      42: invokestatic  #12                 // Method org/apache/dubbo/rpc/RpcContext.getClientAttachment:()Lorg/apache/dubbo/rpc/RpcContextAttachment;
      45: astore        6
      47: aload_0
      48: aload         6
      50: aload         5
      52: invokespecial #13                 // Method remoteHost:(Lorg/apache/dubbo/rpc/RpcContextAttachment;Lorg/apache/dubbo/common/URL;)Ljava/lang/String;
      55: astore        7
      57: aload_0
      58: aload         6
      60: aload         5
      62: invokespecial #14                 // Method remotePort:(Lorg/apache/dubbo/rpc/RpcContextAttachment;Lorg/apache/dubbo/common/URL;)I
      65: istore        8
      67: aload_0
      68: aload_1
      69: aload         7
      71: iload         8
      73: invokespecial #15                 // Method withRemoteHostPort:(Lio/micrometer/common/KeyValues;Ljava/lang/String;I)Lio/micrometer/common/KeyValues;
      76: areturn

  private java.lang.String remoteHost(org.apache.dubbo.rpc.RpcContextAttachment, org.apache.dubbo.common.URL);
    Code:
       0: aload_2
       1: ifnull        11
       4: aload_2
       5: invokevirtual #16                 // Method org/apache/dubbo/common/URL.getHost:()Ljava/lang/String;
       8: goto          12
      11: aconst_null
      12: astore_3
      13: aload_3
      14: ifnull        21
      17: aload_3
      18: goto          25
      21: aload_1
      22: invokevirtual #17                 // Method org/apache/dubbo/rpc/RpcContextAttachment.getRemoteHost:()Ljava/lang/String;
      25: areturn

  private int remotePort(org.apache.dubbo.rpc.RpcContextAttachment, org.apache.dubbo.common.URL);
    Code:
       0: aload_2
       1: ifnull        14
       4: aload_2
       5: invokevirtual #18                 // Method org/apache/dubbo/common/URL.getPort:()I
       8: invokestatic  #19                 // Method java/lang/Integer.valueOf:(I)Ljava/lang/Integer;
      11: goto          15
      14: aconst_null
      15: astore_3
      16: aload_3
      17: ifnull        25
      20: aload_3
      21: invokevirtual #20                 // Method java/lang/Integer.intValue:()I
      24: ireturn
      25: aload_1
      26: invokevirtual #21                 // Method org/apache/dubbo/rpc/RpcContextAttachment.getRemotePort:()I
      29: ifeq          39
      32: aload_1
      33: invokevirtual #21                 // Method org/apache/dubbo/rpc/RpcContextAttachment.getRemotePort:()I
      36: goto          43
      39: aload_1
      40: invokevirtual #22                 // Method org/apache/dubbo/rpc/RpcContextAttachment.getLocalPort:()I
      43: ireturn

  private io.micrometer.common.KeyValues withRemoteHostPort(io.micrometer.common.KeyValues, java.lang.String, int);
    Code:
       0: aload_0
       1: aload_1
       2: getstatic     #23                 // Field org/apache/dubbo/metrics/observation/DubboObservationDocumentation$LowCardinalityKeyNames.NET_PEER_NAME:Lorg/apache/dubbo/metrics/observation/DubboObservationDocumentation$LowCardinalityKeyNames;
       5: aload_2
       6: invokevirtual #24                 // Method appendNonNull:(Lio/micrometer/common/KeyValues;Lio/micrometer/common/docs/KeyName;Ljava/lang/String;)Lio/micrometer/common/KeyValues;
       9: astore_1
      10: iload_3
      11: ifne          16
      14: aload_1
      15: areturn
      16: aload_0
      17: aload_1
      18: getstatic     #25                 // Field org/apache/dubbo/metrics/observation/DubboObservationDocumentation$LowCardinalityKeyNames.NET_PEER_PORT:Lorg/apache/dubbo/metrics/observation/DubboObservationDocumentation$LowCardinalityKeyNames;
      21: iload_3
      22: invokestatic  #26                 // Method java/lang/String.valueOf:(I)Ljava/lang/String;
      25: invokevirtual #24                 // Method appendNonNull:(Lio/micrometer/common/KeyValues;Lio/micrometer/common/docs/KeyName;Ljava/lang/String;)Lio/micrometer/common/KeyValues;
      28: areturn

  public java.lang.String getContextualName(org.apache.dubbo.metrics.observation.DubboClientContext);
    Code:
       0: aload_0
       1: aload_1
       2: invokevirtual #4                  // Method org/apache/dubbo/metrics/observation/DubboClientContext.getInvocation:()Lorg/apache/dubbo/rpc/Invocation;
       5: invokespecial #27                 // Method org/apache/dubbo/metrics/observation/AbstractDefaultDubboObservationConvention.getContextualName:(Lorg/apache/dubbo/rpc/Invocation;)Ljava/lang/String;
       8: areturn

  public java.lang.String getContextualName(io.micrometer.observation.Observation$Context);
    Code:
       0: aload_0
       1: aload_1
       2: checkcast     #28                 // class org/apache/dubbo/metrics/observation/DubboClientContext
       5: invokevirtual #29                 // Method getContextualName:(Lorg/apache/dubbo/metrics/observation/DubboClientContext;)Ljava/lang/String;
       8: areturn

  public io.micrometer.common.KeyValues getLowCardinalityKeyValues(io.micrometer.observation.Observation$Context);
    Code:
       0: aload_0
       1: aload_1
       2: checkcast     #28                 // class org/apache/dubbo/metrics/observation/DubboClientContext
       5: invokevirtual #30                 // Method getLowCardinalityKeyValues:(Lorg/apache/dubbo/metrics/observation/DubboClientContext;)Lio/micrometer/common/KeyValues;
       8: areturn

  static {};
    Code:
       0: new           #31                 // class org/apache/dubbo/metrics/observation/DefaultDubboClientObservationConvention
       3: dup
       4: invokespecial #32                 // Method "<init>":()V
       7: putstatic     #2                  // Field INSTANCE:Lorg/apache/dubbo/metrics/observation/DubboClientObservationConvention;
      10: return
}
