Compiled from "DubboObservationDocumentation.java"
abstract class org.apache.dubbo.metrics.observation.DubboObservationDocumentation$LowCardinalityKeyNames extends java.lang.Enum<org.apache.dubbo.metrics.observation.DubboObservationDocumentation$LowCardinalityKeyNames> implements io.micrometer.common.docs.KeyName {
  public static final org.apache.dubbo.metrics.observation.DubboObservationDocumentation$LowCardinalityKeyNames RPC_SYSTEM;

  public static final org.apache.dubbo.metrics.observation.DubboObservationDocumentation$LowCardinalityKeyNames RPC_SERVICE;

  public static final org.apache.dubbo.metrics.observation.DubboObservationDocumentation$LowCardinalityKeyNames RPC_METHOD;

  public static final org.apache.dubbo.metrics.observation.DubboObservationDocumentation$LowCardinalityKeyNames NET_PEER_NAME;

  public static final org.apache.dubbo.metrics.observation.DubboObservationDocumentation$LowCardinalityKeyNames NET_PEER_PORT;

  private static final org.apache.dubbo.metrics.observation.DubboObservationDocumentation$LowCardinalityKeyNames[] $VALUES;

  public static org.apache.dubbo.metrics.observation.DubboObservationDocumentation$LowCardinalityKeyNames[] values();
    Code:
       0: getstatic     #2                  // Field $VALUES:[Lorg/apache/dubbo/metrics/observation/DubboObservationDocumentation$LowCardinalityKeyNames;
       3: invokevirtual #3                  // Method "[Lorg/apache/dubbo/metrics/observation/DubboObservationDocumentation$LowCardinalityKeyNames;".clone:()Ljava/lang/Object;
       6: checkcast     #4                  // class "[Lorg/apache/dubbo/metrics/observation/DubboObservationDocumentation$LowCardinalityKeyNames;"
       9: areturn

  public static org.apache.dubbo.metrics.observation.DubboObservationDocumentation$LowCardinalityKeyNames valueOf(java.lang.String);
    Code:
       0: ldc           #5                  // class org/apache/dubbo/metrics/observation/DubboObservationDocumentation$LowCardinalityKeyNames
       2: aload_0
       3: invokestatic  #6                  // Method java/lang/Enum.valueOf:(Ljava/lang/Class;Ljava/lang/String;)Ljava/lang/Enum;
       6: checkcast     #5                  // class org/apache/dubbo/metrics/observation/DubboObservationDocumentation$LowCardinalityKeyNames
       9: areturn

  private org.apache.dubbo.metrics.observation.DubboObservationDocumentation$LowCardinalityKeyNames();
    Code:
       0: aload_0
       1: aload_1
       2: iload_2
       3: invokespecial #7                  // Method java/lang/Enum."<init>":(Ljava/lang/String;I)V
       6: return

  org.apache.dubbo.metrics.observation.DubboObservationDocumentation$LowCardinalityKeyNames(java.lang.String, int, org.apache.dubbo.metrics.observation.DubboObservationDocumentation$1);
    Code:
       0: aload_0
       1: aload_1
       2: iload_2
       3: invokespecial #1                  // Method "<init>":(Ljava/lang/String;I)V
       6: return

  static {};
    Code:
       0: new           #8                  // class org/apache/dubbo/metrics/observation/DubboObservationDocumentation$LowCardinalityKeyNames$1
       3: dup
       4: ldc           #9                  // String RPC_SYSTEM
       6: iconst_0
       7: invokespecial #10                 // Method org/apache/dubbo/metrics/observation/DubboObservationDocumentation$LowCardinalityKeyNames$1."<init>":(Ljava/lang/String;I)V
      10: putstatic     #11                 // Field RPC_SYSTEM:Lorg/apache/dubbo/metrics/observation/DubboObservationDocumentation$LowCardinalityKeyNames;
      13: new           #12                 // class org/apache/dubbo/metrics/observation/DubboObservationDocumentation$LowCardinalityKeyNames$2
      16: dup
      17: ldc           #13                 // String RPC_SERVICE
      19: iconst_1
      20: invokespecial #14                 // Method org/apache/dubbo/metrics/observation/DubboObservationDocumentation$LowCardinalityKeyNames$2."<init>":(Ljava/lang/String;I)V
      23: putstatic     #15                 // Field RPC_SERVICE:Lorg/apache/dubbo/metrics/observation/DubboObservationDocumentation$LowCardinalityKeyNames;
      26: new           #16                 // class org/apache/dubbo/metrics/observation/DubboObservationDocumentation$LowCardinalityKeyNames$3
      29: dup
      30: ldc           #17                 // String RPC_METHOD
      32: iconst_2
      33: invokespecial #18                 // Method org/apache/dubbo/metrics/observation/DubboObservationDocumentation$LowCardinalityKeyNames$3."<init>":(Ljava/lang/String;I)V
      36: putstatic     #19                 // Field RPC_METHOD:Lorg/apache/dubbo/metrics/observation/DubboObservationDocumentation$LowCardinalityKeyNames;
      39: new           #20                 // class org/apache/dubbo/metrics/observation/DubboObservationDocumentation$LowCardinalityKeyNames$4
      42: dup
      43: ldc           #21                 // String NET_PEER_NAME
      45: iconst_3
      46: invokespecial #22                 // Method org/apache/dubbo/metrics/observation/DubboObservationDocumentation$LowCardinalityKeyNames$4."<init>":(Ljava/lang/String;I)V
      49: putstatic     #23                 // Field NET_PEER_NAME:Lorg/apache/dubbo/metrics/observation/DubboObservationDocumentation$LowCardinalityKeyNames;
      52: new           #24                 // class org/apache/dubbo/metrics/observation/DubboObservationDocumentation$LowCardinalityKeyNames$5
      55: dup
      56: ldc           #25                 // String NET_PEER_PORT
      58: iconst_4
      59: invokespecial #26                 // Method org/apache/dubbo/metrics/observation/DubboObservationDocumentation$LowCardinalityKeyNames$5."<init>":(Ljava/lang/String;I)V
      62: putstatic     #27                 // Field NET_PEER_PORT:Lorg/apache/dubbo/metrics/observation/DubboObservationDocumentation$LowCardinalityKeyNames;
      65: iconst_5
      66: anewarray     #5                  // class org/apache/dubbo/metrics/observation/DubboObservationDocumentation$LowCardinalityKeyNames
      69: dup
      70: iconst_0
      71: getstatic     #11                 // Field RPC_SYSTEM:Lorg/apache/dubbo/metrics/observation/DubboObservationDocumentation$LowCardinalityKeyNames;
      74: aastore
      75: dup
      76: iconst_1
      77: getstatic     #15                 // Field RPC_SERVICE:Lorg/apache/dubbo/metrics/observation/DubboObservationDocumentation$LowCardinalityKeyNames;
      80: aastore
      81: dup
      82: iconst_2
      83: getstatic     #19                 // Field RPC_METHOD:Lorg/apache/dubbo/metrics/observation/DubboObservationDocumentation$LowCardinalityKeyNames;
      86: aastore
      87: dup
      88: iconst_3
      89: getstatic     #23                 // Field NET_PEER_NAME:Lorg/apache/dubbo/metrics/observation/DubboObservationDocumentation$LowCardinalityKeyNames;
      92: aastore
      93: dup
      94: iconst_4
      95: getstatic     #27                 // Field NET_PEER_PORT:Lorg/apache/dubbo/metrics/observation/DubboObservationDocumentation$LowCardinalityKeyNames;
      98: aastore
      99: putstatic     #2                  // Field $VALUES:[Lorg/apache/dubbo/metrics/observation/DubboObservationDocumentation$LowCardinalityKeyNames;
     102: return
}
