Compiled from "DubboObservationDocumentation.java"
final class org.apache.dubbo.metrics.observation.DubboObservationDocumentation$2 extends org.apache.dubbo.metrics.observation.DubboObservationDocumentation {
  org.apache.dubbo.metrics.observation.DubboObservationDocumentation$2(java.lang.String, int);
    Code:
       0: aload_0
       1: aload_1
       2: iload_2
       3: aconst_null
       4: invokespecial #1                  // Method org/apache/dubbo/metrics/observation/DubboObservationDocumentation."<init>":(Ljava/lang/String;ILorg/apache/dubbo/metrics/observation/DubboObservationDocumentation$1;)V
       7: return

  public java.lang.Class<? extends io.micrometer.observation.ObservationConvention<? extends io.micrometer.observation.Observation$Context>> getDefaultConvention();
    Code:
       0: ldc           #2                  // class org/apache/dubbo/metrics/observation/DefaultDubboClientObservationConvention
       2: areturn

  public io.micrometer.common.docs.KeyName[] getLowCardinalityKeyNames();
    Code:
       0: invokestatic  #3                  // Method org/apache/dubbo/metrics/observation/DubboObservationDocumentation$LowCardinalityKeyNames.values:()[Lorg/apache/dubbo/metrics/observation/DubboObservationDocumentation$LowCardinalityKeyNames;
       3: areturn
}
