Compiled from "DubboObservationDocumentation.java"
final class org.apache.dubbo.metrics.observation.DubboObservationDocumentation$LowCardinalityKeyNames$4 extends org.apache.dubbo.metrics.observation.DubboObservationDocumentation$LowCardinalityKeyNames {
  org.apache.dubbo.metrics.observation.DubboObservationDocumentation$LowCardinalityKeyNames$4(java.lang.String, int);
    Code:
       0: aload_0
       1: aload_1
       2: iload_2
       3: aconst_null
       4: invokespecial #1                  // Method org/apache/dubbo/metrics/observation/DubboObservationDocumentation$LowCardinalityKeyNames."<init>":(Ljava/lang/String;ILorg/apache/dubbo/metrics/observation/DubboObservationDocumentation$1;)V
       7: return

  public java.lang.String asString();
    Code:
       0: ldc           #2                  // String net.peer.name
       2: areturn
}
