Compiled from "DubboObservationDocumentation.java"
public class org.apache.dubbo.metrics.observation.DubboObservationDocumentation extends java.lang.Enum<org.apache.dubbo.metrics.observation.DubboObservationDocumentation> implements io.micrometer.observation.docs.ObservationDocumentation {
  public static final org.apache.dubbo.metrics.observation.DubboObservationDocumentation SERVER;

  public static final org.apache.dubbo.metrics.observation.DubboObservationDocumentation CLIENT;

  private static final org.apache.dubbo.metrics.observation.DubboObservationDocumentation[] $VALUES;

  public static org.apache.dubbo.metrics.observation.DubboObservationDocumentation[] values();
    Code:
       0: getstatic     #2                  // Field $VALUES:[Lorg/apache/dubbo/metrics/observation/DubboObservationDocumentation;
       3: invokevirtual #3                  // Method "[Lorg/apache/dubbo/metrics/observation/DubboObservationDocumentation;".clone:()Ljava/lang/Object;
       6: checkcast     #4                  // class "[Lorg/apache/dubbo/metrics/observation/DubboObservationDocumentation;"
       9: areturn

  public static org.apache.dubbo.metrics.observation.DubboObservationDocumentation valueOf(java.lang.String);
    Code:
       0: ldc           #5                  // class org/apache/dubbo/metrics/observation/DubboObservationDocumentation
       2: aload_0
       3: invokestatic  #6                  // Method java/lang/Enum.valueOf:(Ljava/lang/Class;Ljava/lang/String;)Ljava/lang/Enum;
       6: checkcast     #5                  // class org/apache/dubbo/metrics/observation/DubboObservationDocumentation
       9: areturn

  private org.apache.dubbo.metrics.observation.DubboObservationDocumentation();
    Code:
       0: aload_0
       1: aload_1
       2: iload_2
       3: invokespecial #7                  // Method java/lang/Enum."<init>":(Ljava/lang/String;I)V
       6: return

  org.apache.dubbo.metrics.observation.DubboObservationDocumentation(java.lang.String, int, org.apache.dubbo.metrics.observation.DubboObservationDocumentation$1);
    Code:
       0: aload_0
       1: aload_1
       2: iload_2
       3: invokespecial #1                  // Method "<init>":(Ljava/lang/String;I)V
       6: return

  static {};
    Code:
       0: new           #8                  // class org/apache/dubbo/metrics/observation/DubboObservationDocumentation$1
       3: dup
       4: ldc           #9                  // String SERVER
       6: iconst_0
       7: invokespecial #10                 // Method org/apache/dubbo/metrics/observation/DubboObservationDocumentation$1."<init>":(Ljava/lang/String;I)V
      10: putstatic     #11                 // Field SERVER:Lorg/apache/dubbo/metrics/observation/DubboObservationDocumentation;
      13: new           #12                 // class org/apache/dubbo/metrics/observation/DubboObservationDocumentation$2
      16: dup
      17: ldc           #13                 // String CLIENT
      19: iconst_1
      20: invokespecial #14                 // Method org/apache/dubbo/metrics/observation/DubboObservationDocumentation$2."<init>":(Ljava/lang/String;I)V
      23: putstatic     #15                 // Field CLIENT:Lorg/apache/dubbo/metrics/observation/DubboObservationDocumentation;
      26: iconst_2
      27: anewarray     #5                  // class org/apache/dubbo/metrics/observation/DubboObservationDocumentation
      30: dup
      31: iconst_0
      32: getstatic     #11                 // Field SERVER:Lorg/apache/dubbo/metrics/observation/DubboObservationDocumentation;
      35: aastore
      36: dup
      37: iconst_1
      38: getstatic     #15                 // Field CLIENT:Lorg/apache/dubbo/metrics/observation/DubboObservationDocumentation;
      41: aastore
      42: putstatic     #2                  // Field $VALUES:[Lorg/apache/dubbo/metrics/observation/DubboObservationDocumentation;
      45: return
}
