Compiled from "DubboClientContext.java"
public class org.apache.dubbo.metrics.observation.DubboClientContext extends io.micrometer.observation.transport.SenderContext<org.apache.dubbo.rpc.Invocation> {
  private final org.apache.dubbo.rpc.Invoker<?> invoker;

  private final org.apache.dubbo.rpc.Invocation invocation;

  public org.apache.dubbo.metrics.observation.DubboClientContext(org.apache.dubbo.rpc.Invoker<?>, org.apache.dubbo.rpc.Invocation);
    Code:
       0: aload_0
       1: invokedynamic #1,  0              // InvokeDynamic #0:set:()Lio/micrometer/observation/transport/Propagator$Setter;
       6: invokespecial #2                  // Method io/micrometer/observation/transport/SenderContext."<init>":(Lio/micrometer/observation/transport/Propagator$Setter;)V
       9: aload_0
      10: aload_1
      11: putfield      #3                  // Field invoker:Lorg/apache/dubbo/rpc/Invoker;
      14: aload_0
      15: aload_2
      16: putfield      #4                  // Field invocation:Lorg/apache/dubbo/rpc/Invocation;
      19: aload_0
      20: aload_2
      21: invokevirtual #5                  // Method setCarrier:(Ljava/lang/Object;)V
      24: return

  public org.apache.dubbo.rpc.Invoker<?> getInvoker();
    Code:
       0: aload_0
       1: getfield      #3                  // Field invoker:Lorg/apache/dubbo/rpc/Invoker;
       4: areturn

  public org.apache.dubbo.rpc.Invocation getInvocation();
    Code:
       0: aload_0
       1: getfield      #4                  // Field invocation:Lorg/apache/dubbo/rpc/Invocation;
       4: areturn

  private static void lambda$new$0(org.apache.dubbo.rpc.Invocation, java.lang.String, java.lang.String);
    Code:
       0: aload_0
       1: invokestatic  #6                  // Method java/util/Objects.requireNonNull:(Ljava/lang/Object;)Ljava/lang/Object;
       4: checkcast     #7                  // class org/apache/dubbo/rpc/Invocation
       7: aload_1
       8: aload_2
       9: invokeinterface #8,  3            // InterfaceMethod org/apache/dubbo/rpc/Invocation.setAttachment:(Ljava/lang/String;Ljava/lang/String;)V
      14: return
}
