Compiled from "CachedThreadPool.java"
public class org.apache.dubbo.common.threadpool.support.cached.CachedThreadPool implements org.apache.dubbo.common.threadpool.ThreadPool {
  public org.apache.dubbo.common.threadpool.support.cached.CachedThreadPool();
    Code:
       0: aload_0
       1: invokespecial #2                  // Method java/lang/Object."<init>":()V
       4: return

  public java.util.concurrent.Executor getExecutor(org.apache.dubbo.common.URL);
    Code:
       0: aload_1
       1: ldc           #3                  // String threadname
       3: aload_1
       4: ldc           #3                  // String threadname
       6: ldc           #4                  // String Dubbo
       8: invokevirtual #5                  // Method org/apache/dubbo/common/URL.getAttribute:(Ljava/lang/String;Ljava/lang/Object;)Ljava/lang/Object;
      11: checkcast     #6                  // class java/lang/String
      14: invokevirtual #7                  // Method org/apache/dubbo/common/URL.getParameter:(Ljava/lang/String;Ljava/lang/String;)Ljava/lang/String;
      17: astore_2
      18: aload_1
      19: ldc           #8                  // String corethreads
      21: iconst_0
      22: invokevirtual #9                  // Method org/apache/dubbo/common/URL.getParameter:(Ljava/lang/String;I)I
      25: istore_3
      26: aload_1
      27: ldc           #10                 // String threads
      29: ldc           #12                 // int 2147483647
      31: invokevirtual #9                  // Method org/apache/dubbo/common/URL.getParameter:(Ljava/lang/String;I)I
      34: istore        4
      36: aload_1
      37: ldc           #13                 // String queues
      39: iconst_0
      40: invokevirtual #9                  // Method org/apache/dubbo/common/URL.getParameter:(Ljava/lang/String;I)I
      43: istore        5
      45: aload_1
      46: ldc           #14                 // String alive
      48: ldc           #15                 // int 60000
      50: invokevirtual #9                  // Method org/apache/dubbo/common/URL.getParameter:(Ljava/lang/String;I)I
      53: istore        6
      55: new           #16                 // class java/util/concurrent/ThreadPoolExecutor
      58: dup
      59: iload_3
      60: iload         4
      62: iload         6
      64: i2l
      65: getstatic     #17                 // Field java/util/concurrent/TimeUnit.MILLISECONDS:Ljava/util/concurrent/TimeUnit;
      68: iload         5
      70: ifne          83
      73: new           #18                 // class java/util/concurrent/SynchronousQueue
      76: dup
      77: invokespecial #19                 // Method java/util/concurrent/SynchronousQueue."<init>":()V
      80: goto          107
      83: iload         5
      85: ifge          98
      88: new           #20                 // class org/apache/dubbo/common/threadpool/MemorySafeLinkedBlockingQueue
      91: dup
      92: invokespecial #21                 // Method org/apache/dubbo/common/threadpool/MemorySafeLinkedBlockingQueue."<init>":()V
      95: goto          107
      98: new           #22                 // class java/util/concurrent/LinkedBlockingQueue
     101: dup
     102: iload         5
     104: invokespecial #23                 // Method java/util/concurrent/LinkedBlockingQueue."<init>":(I)V
     107: new           #24                 // class org/apache/dubbo/common/threadlocal/NamedInternalThreadFactory
     110: dup
     111: aload_2
     112: iconst_1
     113: invokespecial #25                 // Method org/apache/dubbo/common/threadlocal/NamedInternalThreadFactory."<init>":(Ljava/lang/String;Z)V
     116: new           #26                 // class org/apache/dubbo/common/threadpool/support/AbortPolicyWithReport
     119: dup
     120: aload_2
     121: aload_1
     122: invokespecial #27                 // Method org/apache/dubbo/common/threadpool/support/AbortPolicyWithReport."<init>":(Ljava/lang/String;Lorg/apache/dubbo/common/URL;)V
     125: invokespecial #28                 // Method java/util/concurrent/ThreadPoolExecutor."<init>":(IIJLjava/util/concurrent/TimeUnit;Ljava/util/concurrent/BlockingQueue;Ljava/util/concurrent/ThreadFactory;Ljava/util/concurrent/RejectedExecutionHandler;)V
     128: areturn
}
