Compiled from "XdsCertificateSigner.java"
public class org.apache.dubbo.registry.xds.XdsCertificateSigner$CertPair {
  private final java.lang.String privateKey;

  private final java.lang.String publicKey;

  private final long createTime;

  private final long expireTime;

  public org.apache.dubbo.registry.xds.XdsCertificateSigner$CertPair(java.lang.String, java.lang.String, long, long);
    Code:
       0: aload_0
       1: invokespecial #1                  // Method java/lang/Object."<init>":()V
       4: aload_0
       5: aload_1
       6: putfield      #2                  // Field privateKey:Ljava/lang/String;
       9: aload_0
      10: aload_2
      11: putfield      #3                  // Field publicKey:Ljava/lang/String;
      14: aload_0
      15: lload_3
      16: putfield      #4                  // Field createTime:J
      19: aload_0
      20: lload         5
      22: putfield      #5                  // Field expireTime:J
      25: return

  public java.lang.String getPrivateKey();
    Code:
       0: aload_0
       1: getfield      #2                  // Field privateKey:Ljava/lang/String;
       4: areturn

  public java.lang.String getPublicKey();
    Code:
       0: aload_0
       1: getfield      #3                  // Field publicKey:Ljava/lang/String;
       4: areturn

  public long getCreateTime();
    Code:
       0: aload_0
       1: getfield      #4                  // Field createTime:J
       4: lreturn

  public boolean isExpire();
    Code:
       0: invokestatic  #6                  // Method java/lang/System.currentTimeMillis:()J
       3: aload_0
       4: getfield      #5                  // Field expireTime:J
       7: lcmp
       8: ifge          15
      11: iconst_1
      12: goto          16
      15: iconst_0
      16: ireturn
}
