Compiled from "XdsRegistryFactory.java"
public class org.apache.dubbo.registry.xds.XdsRegistryFactory extends org.apache.dubbo.registry.support.AbstractRegistryFactory {
  public org.apache.dubbo.registry.xds.XdsRegistryFactory();
    Code:
       0: aload_0
       1: invokespecial #1                  // Method org/apache/dubbo/registry/support/AbstractRegistryFactory."<init>":()V
       4: return

  protected java.lang.String createRegistryCacheKey(org.apache.dubbo.common.URL);
    Code:
       0: aload_1
       1: invokevirtual #2                  // Method org/apache/dubbo/common/URL.toFullString:()Ljava/lang/String;
       4: areturn

  protected org.apache.dubbo.registry.Registry createRegistry(org.apache.dubbo.common.URL);
    Code:
       0: new           #3                  // class org/apache/dubbo/registry/xds/XdsRegistry
       3: dup
       4: aload_1
       5: invokespecial #4                  // Method org/apache/dubbo/registry/xds/XdsRegistry."<init>":(Lorg/apache/dubbo/common/URL;)V
       8: areturn
}
