Compiled from "XdsServiceDiscovery.java"
public class org.apache.dubbo.registry.xds.XdsServiceDiscovery extends org.apache.dubbo.registry.client.ReflectionBasedServiceDiscovery {
  private static final org.apache.dubbo.common.logger.ErrorTypeAwareLogger logger;

  private org.apache.dubbo.registry.xds.util.PilotExchanger exchanger;

  public org.apache.dubbo.registry.xds.XdsServiceDiscovery(org.apache.dubbo.rpc.model.ApplicationModel, org.apache.dubbo.common.URL);
    Code:
       0: aload_0
       1: aload_1
       2: aload_2
       3: invokespecial #2                  // Method org/apache/dubbo/registry/client/ReflectionBasedServiceDiscovery."<init>":(Lorg/apache/dubbo/rpc/model/ApplicationModel;Lorg/apache/dubbo/common/URL;)V
       6: return

  public void doInitialize(org.apache.dubbo.common.URL);
    Code:
       0: aload_0
       1: aload_1
       2: invokestatic  #3                  // Method org/apache/dubbo/registry/xds/util/PilotExchanger.initialize:(Lorg/apache/dubbo/common/URL;)Lorg/apache/dubbo/registry/xds/util/PilotExchanger;
       5: putfield      #4                  // Field exchanger:Lorg/apache/dubbo/registry/xds/util/PilotExchanger;
       8: goto          31
      11: astore_2
      12: getstatic     #6                  // Field logger:Lorg/apache/dubbo/common/logger/ErrorTypeAwareLogger;
      15: ldc           #7                  // String 1-33
      17: ldc           #8                  // String
      19: ldc           #8                  // String
      21: aload_2
      22: invokevirtual #9                  // Method java/lang/Throwable.getMessage:()Ljava/lang/String;
      25: aload_2
      26: invokeinterface #10,  6           // InterfaceMethod org/apache/dubbo/common/logger/ErrorTypeAwareLogger.error:(Ljava/lang/String;Ljava/lang/String;Ljava/lang/String;Ljava/lang/String;Ljava/lang/Throwable;)V
      31: return
    Exception table:
       from    to  target type
           0     8    11   Class java/lang/Throwable

  public void doDestroy();
    Code:
       0: aload_0
       1: getfield      #4                  // Field exchanger:Lorg/apache/dubbo/registry/xds/util/PilotExchanger;
       4: invokevirtual #11                 // Method org/apache/dubbo/registry/xds/util/PilotExchanger.destroy:()V
       7: goto          30
      10: astore_1
      11: getstatic     #6                  // Field logger:Lorg/apache/dubbo/common/logger/ErrorTypeAwareLogger;
      14: ldc           #7                  // String 1-33
      16: ldc           #8                  // String
      18: ldc           #8                  // String
      20: aload_1
      21: invokevirtual #9                  // Method java/lang/Throwable.getMessage:()Ljava/lang/String;
      24: aload_1
      25: invokeinterface #10,  6           // InterfaceMethod org/apache/dubbo/common/logger/ErrorTypeAwareLogger.error:(Ljava/lang/String;Ljava/lang/String;Ljava/lang/String;Ljava/lang/String;Ljava/lang/Throwable;)V
      30: return
    Exception table:
       from    to  target type
           0     7    10   Class java/lang/Throwable

  public java.util.Set<java.lang.String> getServices();
    Code:
       0: aload_0
       1: getfield      #4                  // Field exchanger:Lorg/apache/dubbo/registry/xds/util/PilotExchanger;
       4: invokevirtual #12                 // Method org/apache/dubbo/registry/xds/util/PilotExchanger.getServices:()Ljava/util/Set;
       7: areturn

  public java.util.List<org.apache.dubbo.registry.client.ServiceInstance> getInstances(java.lang.String) throws java.lang.NullPointerException;
    Code:
       0: aload_0
       1: getfield      #4                  // Field exchanger:Lorg/apache/dubbo/registry/xds/util/PilotExchanger;
       4: aload_1
       5: invokevirtual #13                 // Method org/apache/dubbo/registry/xds/util/PilotExchanger.getEndpoints:(Ljava/lang/String;)Ljava/util/Set;
       8: astore_2
       9: aload_0
      10: aload_1
      11: aload_2
      12: invokespecial #14                 // Method changedToInstances:(Ljava/lang/String;Ljava/util/Collection;)Ljava/util/List;
      15: areturn

  public void addServiceInstancesChangedListener(org.apache.dubbo.registry.client.event.listener.ServiceInstancesChangedListener) throws java.lang.NullPointerException, java.lang.IllegalArgumentException;
    Code:
       0: aload_1
       1: invokevirtual #15                 // Method org/apache/dubbo/registry/client/event/listener/ServiceInstancesChangedListener.getServiceNames:()Ljava/util/Set;
       4: aload_0
       5: aload_1
       6: invokedynamic #16,  0             // InvokeDynamic #0:accept:(Lorg/apache/dubbo/registry/xds/XdsServiceDiscovery;Lorg/apache/dubbo/registry/client/event/listener/ServiceInstancesChangedListener;)Ljava/util/function/Consumer;
      11: invokeinterface #17,  2           // InterfaceMethod java/util/Set.forEach:(Ljava/util/function/Consumer;)V
      16: return

  private java.util.List<org.apache.dubbo.registry.client.ServiceInstance> changedToInstances(java.lang.String, java.util.Collection<org.apache.dubbo.registry.xds.util.protocol.message.Endpoint>);
    Code:
       0: new           #18                 // class java/util/LinkedList
       3: dup
       4: invokespecial #19                 // Method java/util/LinkedList."<init>":()V
       7: astore_3
       8: aload_2
       9: aload_0
      10: aload_1
      11: aload_3
      12: aload_2
      13: invokedynamic #20,  0             // InvokeDynamic #1:accept:(Lorg/apache/dubbo/registry/xds/XdsServiceDiscovery;Ljava/lang/String;Ljava/util/List;Ljava/util/Collection;)Ljava/util/function/Consumer;
      18: invokeinterface #21,  2           // InterfaceMethod java/util/Collection.forEach:(Ljava/util/function/Consumer;)V
      23: aload_3
      24: invokedynamic #22,  0             // InvokeDynamic #2:applyAsInt:()Ljava/util/function/ToIntFunction;
      29: invokestatic  #23                 // InterfaceMethod java/util/Comparator.comparingInt:(Ljava/util/function/ToIntFunction;)Ljava/util/Comparator;
      32: invokeinterface #24,  2           // InterfaceMethod java/util/List.sort:(Ljava/util/Comparator;)V
      37: aload_3
      38: areturn

  private void lambda$changedToInstances$2(java.lang.String, java.util.List, java.util.Collection, org.apache.dubbo.registry.xds.util.protocol.message.Endpoint);
    Code:
       0: new           #25                 // class org/apache/dubbo/registry/client/DefaultServiceInstance
       3: dup
       4: aload_1
       5: aload         4
       7: invokevirtual #26                 // Method org/apache/dubbo/registry/xds/util/protocol/message/Endpoint.getAddress:()Ljava/lang/String;
      10: aload         4
      12: invokevirtual #27                 // Method org/apache/dubbo/registry/xds/util/protocol/message/Endpoint.getPortValue:()I
      15: invokestatic  #28                 // Method java/lang/Integer.valueOf:(I)Ljava/lang/Integer;
      18: aload_0
      19: invokevirtual #29                 // Method getUrl:()Lorg/apache/dubbo/common/URL;
      22: invokevirtual #30                 // Method org/apache/dubbo/common/URL.getScopeModel:()Lorg/apache/dubbo/rpc/model/ScopeModel;
      25: invokestatic  #31                 // Method org/apache/dubbo/rpc/model/ScopeModelUtil.getApplicationModel:(Lorg/apache/dubbo/rpc/model/ScopeModel;)Lorg/apache/dubbo/rpc/model/ApplicationModel;
      28: invokespecial #32                 // Method org/apache/dubbo/registry/client/DefaultServiceInstance."<init>":(Ljava/lang/String;Ljava/lang/String;Ljava/lang/Integer;Lorg/apache/dubbo/rpc/model/ApplicationModel;)V
      31: astore        5
      33: aload         5
      35: ldc           #33                 // String clusterName
      37: aload         4
      39: invokevirtual #34                 // Method org/apache/dubbo/registry/xds/util/protocol/message/Endpoint.getClusterName:()Ljava/lang/String;
      42: invokevirtual #35                 // Method org/apache/dubbo/registry/client/DefaultServiceInstance.putExtendParam:(Ljava/lang/String;Ljava/lang/String;)Ljava/lang/String;
      45: pop
      46: aload_0
      47: aload         5
      49: invokevirtual #36                 // Method fillServiceInstance:(Lorg/apache/dubbo/registry/client/DefaultServiceInstance;)V
      52: aload_2
      53: aload         5
      55: invokeinterface #37,  2           // InterfaceMethod java/util/List.add:(Ljava/lang/Object;)Z
      60: pop
      61: goto          101
      64: astore        5
      66: getstatic     #6                  // Field logger:Lorg/apache/dubbo/common/logger/ErrorTypeAwareLogger;
      69: ldc           #38                 // String 1-34
      71: ldc           #8                  // String
      73: ldc           #8                  // String
      75: new           #39                 // class java/lang/StringBuilder
      78: dup
      79: invokespecial #40                 // Method java/lang/StringBuilder."<init>":()V
      82: ldc           #41                 // String Error occurred when parsing endpoints. Endpoints List:
      84: invokevirtual #42                 // Method java/lang/StringBuilder.append:(Ljava/lang/String;)Ljava/lang/StringBuilder;
      87: aload_3
      88: invokevirtual #43                 // Method java/lang/StringBuilder.append:(Ljava/lang/Object;)Ljava/lang/StringBuilder;
      91: invokevirtual #44                 // Method java/lang/StringBuilder.toString:()Ljava/lang/String;
      94: aload         5
      96: invokeinterface #10,  6           // InterfaceMethod org/apache/dubbo/common/logger/ErrorTypeAwareLogger.error:(Ljava/lang/String;Ljava/lang/String;Ljava/lang/String;Ljava/lang/String;Ljava/lang/Throwable;)V
     101: return
    Exception table:
       from    to  target type
           0    61    64   Class java/lang/Throwable

  private void lambda$addServiceInstancesChangedListener$1(org.apache.dubbo.registry.client.event.listener.ServiceInstancesChangedListener, java.lang.String);
    Code:
       0: aload_0
       1: getfield      #4                  // Field exchanger:Lorg/apache/dubbo/registry/xds/util/PilotExchanger;
       4: aload_2
       5: aload_0
       6: aload_2
       7: aload_1
       8: invokedynamic #45,  0             // InvokeDynamic #3:accept:(Lorg/apache/dubbo/registry/xds/XdsServiceDiscovery;Ljava/lang/String;Lorg/apache/dubbo/registry/client/event/listener/ServiceInstancesChangedListener;)Ljava/util/function/Consumer;
      13: invokevirtual #46                 // Method org/apache/dubbo/registry/xds/util/PilotExchanger.observeEndpoints:(Ljava/lang/String;Ljava/util/function/Consumer;)V
      16: return

  private void lambda$null$0(java.lang.String, org.apache.dubbo.registry.client.event.listener.ServiceInstancesChangedListener, java.util.Set);
    Code:
       0: aload_0
       1: aload_1
       2: aload_2
       3: aload_0
       4: aload_1
       5: aload_3
       6: invokespecial #14                 // Method changedToInstances:(Ljava/lang/String;Ljava/util/Collection;)Ljava/util/List;
       9: invokevirtual #47                 // Method notifyListener:(Ljava/lang/String;Lorg/apache/dubbo/registry/client/event/listener/ServiceInstancesChangedListener;Ljava/util/List;)V
      12: return

  static {};
    Code:
       0: ldc           #48                 // class org/apache/dubbo/registry/xds/XdsServiceDiscovery
       2: invokestatic  #49                 // Method org/apache/dubbo/common/logger/LoggerFactory.getErrorTypeAwareLogger:(Ljava/lang/Class;)Lorg/apache/dubbo/common/logger/ErrorTypeAwareLogger;
       5: putstatic     #6                  // Field logger:Lorg/apache/dubbo/common/logger/ErrorTypeAwareLogger;
       8: return
}
