Compiled from "XdsServiceDiscoveryFactory.java"
public class org.apache.dubbo.registry.xds.XdsServiceDiscoveryFactory extends org.apache.dubbo.registry.client.AbstractServiceDiscoveryFactory {
  private static final org.apache.dubbo.common.logger.ErrorTypeAwareLogger logger;

  public org.apache.dubbo.registry.xds.XdsServiceDiscoveryFactory();
    Code:
       0: aload_0
       1: invokespecial #2                  // Method org/apache/dubbo/registry/client/AbstractServiceDiscoveryFactory."<init>":()V
       4: return

  protected org.apache.dubbo.registry.client.ServiceDiscovery createDiscovery(org.apache.dubbo.common.URL);
    Code:
       0: new           #3                  // class org/apache/dubbo/registry/xds/XdsServiceDiscovery
       3: dup
       4: invokestatic  #4                  // Method org/apache/dubbo/rpc/model/ApplicationModel.defaultModel:()Lorg/apache/dubbo/rpc/model/ApplicationModel;
       7: aload_1
       8: invokespecial #5                  // Method org/apache/dubbo/registry/xds/XdsServiceDiscovery."<init>":(Lorg/apache/dubbo/rpc/model/ApplicationModel;Lorg/apache/dubbo/common/URL;)V
      11: astore_2
      12: aload_2
      13: aload_1
      14: invokevirtual #6                  // Method org/apache/dubbo/registry/xds/XdsServiceDiscovery.doInitialize:(Lorg/apache/dubbo/common/URL;)V
      17: goto          38
      20: astore_3
      21: getstatic     #8                  // Field logger:Lorg/apache/dubbo/common/logger/ErrorTypeAwareLogger;
      24: ldc           #9                  // String 1-33
      26: ldc           #10                 // String
      28: ldc           #10                 // String
      30: ldc           #11                 // String Error occurred when initialize xDS service discovery impl.
      32: aload_3
      33: invokeinterface #12,  6           // InterfaceMethod org/apache/dubbo/common/logger/ErrorTypeAwareLogger.error:(Ljava/lang/String;Ljava/lang/String;Ljava/lang/String;Ljava/lang/String;Ljava/lang/Throwable;)V
      38: aload_2
      39: areturn
    Exception table:
       from    to  target type
          12    17    20   Class java/lang/Exception

  static {};
    Code:
       0: ldc           #13                 // class org/apache/dubbo/registry/xds/XdsServiceDiscoveryFactory
       2: invokestatic  #14                 // Method org/apache/dubbo/common/logger/LoggerFactory.getErrorTypeAwareLogger:(Ljava/lang/Class;)Lorg/apache/dubbo/common/logger/ErrorTypeAwareLogger;
       5: putstatic     #8                  // Field logger:Lorg/apache/dubbo/common/logger/ErrorTypeAwareLogger;
       8: return
}
