Compiled from "JettyHttpServer.java"
public class org.apache.dubbo.remoting.http.jetty.JettyHttpServer extends org.apache.dubbo.remoting.http.support.AbstractHttpServer {
  private static final org.apache.dubbo.common.logger.ErrorTypeAwareLogger logger;

  private org.eclipse.jetty.server.Server server;

  private org.apache.dubbo.common.URL url;

  public org.apache.dubbo.remoting.http.jetty.JettyHttpServer(org.apache.dubbo.common.URL, org.apache.dubbo.remoting.http.HttpHandler);
    Code:
       0: aload_0
       1: aload_1
       2: aload_2
       3: invokespecial #3                  // Method org/apache/dubbo/remoting/http/support/AbstractHttpServer."<init>":(Lorg/apache/dubbo/common/URL;Lorg/apache/dubbo/remoting/http/HttpHandler;)V
       6: aload_0
       7: aload_1
       8: putfield      #4                  // Field url:Lorg/apache/dubbo/common/URL;
      11: ldc           #5                  // String org.eclipse.jetty.util.log.class
      13: ldc           #6                  // class org/apache/dubbo/remoting/http/jetty/JettyLoggerAdapter
      15: invokevirtual #7                  // Method java/lang/Class.getName:()Ljava/lang/String;
      18: invokestatic  #8                  // Method java/lang/System.setProperty:(Ljava/lang/String;Ljava/lang/String;)Ljava/lang/String;
      21: pop
      22: aload_1
      23: ldc           #10                 // String bind.port
      25: aload_1
      26: invokevirtual #11                 // Method org/apache/dubbo/common/URL.getPort:()I
      29: invokevirtual #12                 // Method org/apache/dubbo/common/URL.getParameter:(Ljava/lang/String;I)I
      32: aload_2
      33: invokestatic  #13                 // Method org/apache/dubbo/remoting/http/servlet/DispatcherServlet.addHttpHandler:(ILorg/apache/dubbo/remoting/http/HttpHandler;)V
      36: aload_1
      37: ldc           #14                 // String threads
      39: sipush        200
      42: invokevirtual #12                 // Method org/apache/dubbo/common/URL.getParameter:(Ljava/lang/String;I)I
      45: istore_3
      46: new           #15                 // class org/eclipse/jetty/util/thread/QueuedThreadPool
      49: dup
      50: invokespecial #16                 // Method org/eclipse/jetty/util/thread/QueuedThreadPool."<init>":()V
      53: astore        4
      55: aload         4
      57: iconst_1
      58: invokevirtual #17                 // Method org/eclipse/jetty/util/thread/QueuedThreadPool.setDaemon:(Z)V
      61: aload         4
      63: iload_3
      64: invokevirtual #18                 // Method org/eclipse/jetty/util/thread/QueuedThreadPool.setMaxThreads:(I)V
      67: aload         4
      69: iload_3
      70: invokevirtual #19                 // Method org/eclipse/jetty/util/thread/QueuedThreadPool.setMinThreads:(I)V
      73: aload_0
      74: new           #20                 // class org/eclipse/jetty/server/Server
      77: dup
      78: aload         4
      80: invokespecial #21                 // Method org/eclipse/jetty/server/Server."<init>":(Lorg/eclipse/jetty/util/thread/ThreadPool;)V
      83: putfield      #22                 // Field server:Lorg/eclipse/jetty/server/Server;
      86: new           #23                 // class org/eclipse/jetty/server/ServerConnector
      89: dup
      90: aload_0
      91: getfield      #22                 // Field server:Lorg/eclipse/jetty/server/Server;
      94: invokespecial #24                 // Method org/eclipse/jetty/server/ServerConnector."<init>":(Lorg/eclipse/jetty/server/Server;)V
      97: astore        5
      99: aload_1
     100: ldc           #25                 // String bind.ip
     102: aload_1
     103: invokevirtual #26                 // Method org/apache/dubbo/common/URL.getHost:()Ljava/lang/String;
     106: invokevirtual #27                 // Method org/apache/dubbo/common/URL.getParameter:(Ljava/lang/String;Ljava/lang/String;)Ljava/lang/String;
     109: astore        6
     111: aload_1
     112: invokevirtual #28                 // Method org/apache/dubbo/common/URL.isAnyHost:()Z
     115: ifne          133
     118: aload         6
     120: invokestatic  #29                 // Method org/apache/dubbo/common/utils/NetUtils.isValidLocalHost:(Ljava/lang/String;)Z
     123: ifeq          133
     126: aload         5
     128: aload         6
     130: invokevirtual #30                 // Method org/eclipse/jetty/server/ServerConnector.setHost:(Ljava/lang/String;)V
     133: aload         5
     135: aload_1
     136: ldc           #10                 // String bind.port
     138: aload_1
     139: invokevirtual #11                 // Method org/apache/dubbo/common/URL.getPort:()I
     142: invokevirtual #12                 // Method org/apache/dubbo/common/URL.getParameter:(Ljava/lang/String;I)I
     145: invokevirtual #31                 // Method org/eclipse/jetty/server/ServerConnector.setPort:(I)V
     148: aload_0
     149: getfield      #22                 // Field server:Lorg/eclipse/jetty/server/Server;
     152: aload         5
     154: invokevirtual #32                 // Method org/eclipse/jetty/server/Server.addConnector:(Lorg/eclipse/jetty/server/Connector;)V
     157: new           #33                 // class org/eclipse/jetty/servlet/ServletHandler
     160: dup
     161: invokespecial #34                 // Method org/eclipse/jetty/servlet/ServletHandler."<init>":()V
     164: astore        7
     166: aload         7
     168: ldc           #35                 // class org/apache/dubbo/remoting/http/servlet/DispatcherServlet
     170: ldc           #36                 // String /*
     172: invokevirtual #37                 // Method org/eclipse/jetty/servlet/ServletHandler.addServletWithMapping:(Ljava/lang/Class;Ljava/lang/String;)Lorg/eclipse/jetty/servlet/ServletHolder;
     175: astore        8
     177: aload         8
     179: iconst_2
     180: invokevirtual #38                 // Method org/eclipse/jetty/servlet/ServletHolder.setInitOrder:(I)V
     183: new           #39                 // class org/eclipse/jetty/servlet/ServletContextHandler
     186: dup
     187: aload_0
     188: getfield      #22                 // Field server:Lorg/eclipse/jetty/server/Server;
     191: ldc           #40                 // String /
     193: iconst_1
     194: invokespecial #41                 // Method org/eclipse/jetty/servlet/ServletContextHandler."<init>":(Lorg/eclipse/jetty/server/HandlerContainer;Ljava/lang/String;I)V
     197: astore        9
     199: aload         9
     201: aload         7
     203: invokevirtual #42                 // Method org/eclipse/jetty/servlet/ServletContextHandler.setServletHandler:(Lorg/eclipse/jetty/servlet/ServletHandler;)V
     206: invokestatic  #43                 // Method org/apache/dubbo/remoting/http/servlet/ServletManager.getInstance:()Lorg/apache/dubbo/remoting/http/servlet/ServletManager;
     209: aload_1
     210: ldc           #10                 // String bind.port
     212: aload_1
     213: invokevirtual #11                 // Method org/apache/dubbo/common/URL.getPort:()I
     216: invokevirtual #12                 // Method org/apache/dubbo/common/URL.getParameter:(Ljava/lang/String;I)I
     219: aload         9
     221: invokevirtual #44                 // Method org/eclipse/jetty/servlet/ServletContextHandler.getServletContext:()Lorg/eclipse/jetty/server/handler/ContextHandler$Context;
     224: invokevirtual #45                 // Method org/apache/dubbo/remoting/http/servlet/ServletManager.addServletContext:(ILjavax/servlet/ServletContext;)V
     227: aload_0
     228: getfield      #22                 // Field server:Lorg/eclipse/jetty/server/Server;
     231: invokevirtual #46                 // Method org/eclipse/jetty/server/Server.start:()V
     234: goto          300
     237: astore        10
     239: new           #48                 // class java/lang/IllegalStateException
     242: dup
     243: new           #49                 // class java/lang/StringBuilder
     246: dup
     247: invokespecial #50                 // Method java/lang/StringBuilder."<init>":()V
     250: ldc           #51                 // String Failed to start jetty server on
     252: invokevirtual #52                 // Method java/lang/StringBuilder.append:(Ljava/lang/String;)Ljava/lang/StringBuilder;
     255: aload_1
     256: ldc           #25                 // String bind.ip
     258: invokevirtual #53                 // Method org/apache/dubbo/common/URL.getParameter:(Ljava/lang/String;)Ljava/lang/String;
     261: invokevirtual #52                 // Method java/lang/StringBuilder.append:(Ljava/lang/String;)Ljava/lang/StringBuilder;
     264: ldc           #54                 // String :
     266: invokevirtual #52                 // Method java/lang/StringBuilder.append:(Ljava/lang/String;)Ljava/lang/StringBuilder;
     269: aload_1
     270: ldc           #10                 // String bind.port
     272: invokevirtual #53                 // Method org/apache/dubbo/common/URL.getParameter:(Ljava/lang/String;)Ljava/lang/String;
     275: invokevirtual #52                 // Method java/lang/StringBuilder.append:(Ljava/lang/String;)Ljava/lang/StringBuilder;
     278: ldc           #55                 // String , cause:
     280: invokevirtual #52                 // Method java/lang/StringBuilder.append:(Ljava/lang/String;)Ljava/lang/StringBuilder;
     283: aload         10
     285: invokevirtual #56                 // Method java/lang/Exception.getMessage:()Ljava/lang/String;
     288: invokevirtual #52                 // Method java/lang/StringBuilder.append:(Ljava/lang/String;)Ljava/lang/StringBuilder;
     291: invokevirtual #57                 // Method java/lang/StringBuilder.toString:()Ljava/lang/String;
     294: aload         10
     296: invokespecial #58                 // Method java/lang/IllegalStateException."<init>":(Ljava/lang/String;Ljava/lang/Throwable;)V
     299: athrow
     300: return
    Exception table:
       from    to  target type
         227   234   237   Class java/lang/Exception

  public void close();
    Code:
       0: aload_0
       1: invokespecial #59                 // Method org/apache/dubbo/remoting/http/support/AbstractHttpServer.close:()V
       4: invokestatic  #43                 // Method org/apache/dubbo/remoting/http/servlet/ServletManager.getInstance:()Lorg/apache/dubbo/remoting/http/servlet/ServletManager;
       7: aload_0
       8: getfield      #4                  // Field url:Lorg/apache/dubbo/common/URL;
      11: ldc           #10                 // String bind.port
      13: aload_0
      14: getfield      #4                  // Field url:Lorg/apache/dubbo/common/URL;
      17: invokevirtual #11                 // Method org/apache/dubbo/common/URL.getPort:()I
      20: invokevirtual #12                 // Method org/apache/dubbo/common/URL.getParameter:(Ljava/lang/String;I)I
      23: invokevirtual #60                 // Method org/apache/dubbo/remoting/http/servlet/ServletManager.removeServletContext:(I)V
      26: aload_0
      27: getfield      #22                 // Field server:Lorg/eclipse/jetty/server/Server;
      30: ifnull        63
      33: aload_0
      34: getfield      #22                 // Field server:Lorg/eclipse/jetty/server/Server;
      37: invokevirtual #61                 // Method org/eclipse/jetty/server/Server.stop:()V
      40: goto          63
      43: astore_1
      44: getstatic     #62                 // Field logger:Lorg/apache/dubbo/common/logger/ErrorTypeAwareLogger;
      47: ldc           #63                 // String 0-11
      49: ldc           #64                 // String
      51: ldc           #64                 // String
      53: aload_1
      54: invokevirtual #56                 // Method java/lang/Exception.getMessage:()Ljava/lang/String;
      57: aload_1
      58: invokeinterface #65,  6           // InterfaceMethod org/apache/dubbo/common/logger/ErrorTypeAwareLogger.warn:(Ljava/lang/String;Ljava/lang/String;Ljava/lang/String;Ljava/lang/String;Ljava/lang/Throwable;)V
      63: return
    Exception table:
       from    to  target type
          33    40    43   Class java/lang/Exception

  static {};
    Code:
       0: ldc           #66                 // class org/apache/dubbo/remoting/http/jetty/JettyHttpServer
       2: invokestatic  #67                 // Method org/apache/dubbo/common/logger/LoggerFactory.getErrorTypeAwareLogger:(Ljava/lang/Class;)Lorg/apache/dubbo/common/logger/ErrorTypeAwareLogger;
       5: putstatic     #62                 // Field logger:Lorg/apache/dubbo/common/logger/ErrorTypeAwareLogger;
       8: return
}
