Compiled from "JettyLoggerAdapter.java"
public class org.apache.dubbo.remoting.http.jetty.JettyLoggerAdapter extends org.eclipse.jetty.util.log.AbstractLogger {
  protected java.lang.String name;

  private final org.apache.dubbo.common.logger.ErrorTypeAwareLogger logger;

  private static boolean debugEnabled;

  public org.apache.dubbo.remoting.http.jetty.JettyLoggerAdapter();
    Code:
       0: aload_0
       1: ldc           #2                  // String org.apache.dubbo.remoting.http.jetty
       3: invokespecial #3                  // Method "<init>":(Ljava/lang/String;)V
       6: return

  public org.apache.dubbo.remoting.http.jetty.JettyLoggerAdapter(java.lang.Class<?>);
    Code:
       0: aload_0
       1: aload_1
       2: invokevirtual #4                  // Method java/lang/Class.getName:()Ljava/lang/String;
       5: invokespecial #3                  // Method "<init>":(Ljava/lang/String;)V
       8: return

  public org.apache.dubbo.remoting.http.jetty.JettyLoggerAdapter(java.lang.String);
    Code:
       0: aload_0
       1: invokespecial #5                  // Method org/eclipse/jetty/util/log/AbstractLogger."<init>":()V
       4: aload_0
       5: aload_1
       6: putfield      #6                  // Field name:Ljava/lang/String;
       9: aload_0
      10: aload_1
      11: invokestatic  #7                  // Method org/apache/dubbo/common/logger/LoggerFactory.getErrorTypeAwareLogger:(Ljava/lang/String;)Lorg/apache/dubbo/common/logger/ErrorTypeAwareLogger;
      14: putfield      #8                  // Field logger:Lorg/apache/dubbo/common/logger/ErrorTypeAwareLogger;
      17: return

  protected org.eclipse.jetty.util.log.Logger newLogger(java.lang.String);
    Code:
       0: new           #9                  // class org/apache/dubbo/remoting/http/jetty/JettyLoggerAdapter
       3: dup
       4: aload_1
       5: invokespecial #3                  // Method "<init>":(Ljava/lang/String;)V
       8: areturn

  public java.lang.String getName();
    Code:
       0: aload_0
       1: getfield      #6                  // Field name:Ljava/lang/String;
       4: areturn

  public void warn(java.lang.String, java.lang.Object...);
    Code:
       0: aload_0
       1: getfield      #8                  // Field logger:Lorg/apache/dubbo/common/logger/ErrorTypeAwareLogger;
       4: invokeinterface #10,  1           // InterfaceMethod org/apache/dubbo/common/logger/ErrorTypeAwareLogger.isWarnEnabled:()Z
       9: ifeq          33
      12: aload_0
      13: getfield      #8                  // Field logger:Lorg/apache/dubbo/common/logger/ErrorTypeAwareLogger;
      16: ldc           #11                 // String 0-12
      18: ldc           #12                 // String
      20: ldc           #12                 // String
      22: aload_0
      23: aload_1
      24: aload_2
      25: invokespecial #13                 // Method format:(Ljava/lang/String;[Ljava/lang/Object;)Ljava/lang/String;
      28: invokeinterface #14,  5           // InterfaceMethod org/apache/dubbo/common/logger/ErrorTypeAwareLogger.warn:(Ljava/lang/String;Ljava/lang/String;Ljava/lang/String;Ljava/lang/String;)V
      33: return

  public void warn(java.lang.Throwable);
    Code:
       0: aload_0
       1: getfield      #8                  // Field logger:Lorg/apache/dubbo/common/logger/ErrorTypeAwareLogger;
       4: invokeinterface #10,  1           // InterfaceMethod org/apache/dubbo/common/logger/ErrorTypeAwareLogger.isWarnEnabled:()Z
       9: ifeq          32
      12: aload_0
      13: getfield      #8                  // Field logger:Lorg/apache/dubbo/common/logger/ErrorTypeAwareLogger;
      16: ldc           #11                 // String 0-12
      18: ldc           #12                 // String
      20: ldc           #12                 // String
      22: aload_1
      23: invokevirtual #15                 // Method java/lang/Throwable.getMessage:()Ljava/lang/String;
      26: aload_1
      27: invokeinterface #16,  6           // InterfaceMethod org/apache/dubbo/common/logger/ErrorTypeAwareLogger.warn:(Ljava/lang/String;Ljava/lang/String;Ljava/lang/String;Ljava/lang/String;Ljava/lang/Throwable;)V
      32: return

  public void warn(java.lang.String, java.lang.Throwable);
    Code:
       0: aload_0
       1: getfield      #8                  // Field logger:Lorg/apache/dubbo/common/logger/ErrorTypeAwareLogger;
       4: invokeinterface #10,  1           // InterfaceMethod org/apache/dubbo/common/logger/ErrorTypeAwareLogger.isWarnEnabled:()Z
       9: ifeq          29
      12: aload_0
      13: getfield      #8                  // Field logger:Lorg/apache/dubbo/common/logger/ErrorTypeAwareLogger;
      16: ldc           #11                 // String 0-12
      18: ldc           #12                 // String
      20: ldc           #12                 // String
      22: aload_1
      23: aload_2
      24: invokeinterface #16,  6           // InterfaceMethod org/apache/dubbo/common/logger/ErrorTypeAwareLogger.warn:(Ljava/lang/String;Ljava/lang/String;Ljava/lang/String;Ljava/lang/String;Ljava/lang/Throwable;)V
      29: return

  public void info(java.lang.String, java.lang.Object...);
    Code:
       0: aload_0
       1: getfield      #8                  // Field logger:Lorg/apache/dubbo/common/logger/ErrorTypeAwareLogger;
       4: invokeinterface #17,  1           // InterfaceMethod org/apache/dubbo/common/logger/ErrorTypeAwareLogger.isInfoEnabled:()Z
       9: ifeq          27
      12: aload_0
      13: getfield      #8                  // Field logger:Lorg/apache/dubbo/common/logger/ErrorTypeAwareLogger;
      16: aload_0
      17: aload_1
      18: aload_2
      19: invokespecial #13                 // Method format:(Ljava/lang/String;[Ljava/lang/Object;)Ljava/lang/String;
      22: invokeinterface #18,  2           // InterfaceMethod org/apache/dubbo/common/logger/ErrorTypeAwareLogger.info:(Ljava/lang/String;)V
      27: return

  public void info(java.lang.Throwable);
    Code:
       0: aload_0
       1: getfield      #8                  // Field logger:Lorg/apache/dubbo/common/logger/ErrorTypeAwareLogger;
       4: invokeinterface #17,  1           // InterfaceMethod org/apache/dubbo/common/logger/ErrorTypeAwareLogger.isInfoEnabled:()Z
       9: ifeq          22
      12: aload_0
      13: getfield      #8                  // Field logger:Lorg/apache/dubbo/common/logger/ErrorTypeAwareLogger;
      16: aload_1
      17: invokeinterface #19,  2           // InterfaceMethod org/apache/dubbo/common/logger/ErrorTypeAwareLogger.info:(Ljava/lang/Throwable;)V
      22: return

  public void info(java.lang.String, java.lang.Throwable);
    Code:
       0: aload_0
       1: getfield      #8                  // Field logger:Lorg/apache/dubbo/common/logger/ErrorTypeAwareLogger;
       4: invokeinterface #17,  1           // InterfaceMethod org/apache/dubbo/common/logger/ErrorTypeAwareLogger.isInfoEnabled:()Z
       9: ifeq          23
      12: aload_0
      13: getfield      #8                  // Field logger:Lorg/apache/dubbo/common/logger/ErrorTypeAwareLogger;
      16: aload_1
      17: aload_2
      18: invokeinterface #20,  3           // InterfaceMethod org/apache/dubbo/common/logger/ErrorTypeAwareLogger.info:(Ljava/lang/String;Ljava/lang/Throwable;)V
      23: return

  public boolean isDebugEnabled();
    Code:
       0: getstatic     #21                 // Field debugEnabled:Z
       3: ireturn

  public void setDebugEnabled(boolean);
    Code:
       0: iload_1
       1: putstatic     #21                 // Field debugEnabled:Z
       4: return

  public void debug(java.lang.String, java.lang.Object...);
    Code:
       0: getstatic     #21                 // Field debugEnabled:Z
       3: ifeq          33
       6: aload_0
       7: getfield      #8                  // Field logger:Lorg/apache/dubbo/common/logger/ErrorTypeAwareLogger;
      10: invokeinterface #22,  1           // InterfaceMethod org/apache/dubbo/common/logger/ErrorTypeAwareLogger.isDebugEnabled:()Z
      15: ifeq          33
      18: aload_0
      19: getfield      #8                  // Field logger:Lorg/apache/dubbo/common/logger/ErrorTypeAwareLogger;
      22: aload_0
      23: aload_1
      24: aload_2
      25: invokespecial #13                 // Method format:(Ljava/lang/String;[Ljava/lang/Object;)Ljava/lang/String;
      28: invokeinterface #23,  2           // InterfaceMethod org/apache/dubbo/common/logger/ErrorTypeAwareLogger.debug:(Ljava/lang/String;)V
      33: return

  public void debug(java.lang.Throwable);
    Code:
       0: getstatic     #21                 // Field debugEnabled:Z
       3: ifeq          28
       6: aload_0
       7: getfield      #8                  // Field logger:Lorg/apache/dubbo/common/logger/ErrorTypeAwareLogger;
      10: invokeinterface #22,  1           // InterfaceMethod org/apache/dubbo/common/logger/ErrorTypeAwareLogger.isDebugEnabled:()Z
      15: ifeq          28
      18: aload_0
      19: getfield      #8                  // Field logger:Lorg/apache/dubbo/common/logger/ErrorTypeAwareLogger;
      22: aload_1
      23: invokeinterface #24,  2           // InterfaceMethod org/apache/dubbo/common/logger/ErrorTypeAwareLogger.debug:(Ljava/lang/Throwable;)V
      28: return

  public void debug(java.lang.String, java.lang.Throwable);
    Code:
       0: getstatic     #21                 // Field debugEnabled:Z
       3: ifeq          29
       6: aload_0
       7: getfield      #8                  // Field logger:Lorg/apache/dubbo/common/logger/ErrorTypeAwareLogger;
      10: invokeinterface #22,  1           // InterfaceMethod org/apache/dubbo/common/logger/ErrorTypeAwareLogger.isDebugEnabled:()Z
      15: ifeq          29
      18: aload_0
      19: getfield      #8                  // Field logger:Lorg/apache/dubbo/common/logger/ErrorTypeAwareLogger;
      22: aload_1
      23: aload_2
      24: invokeinterface #25,  3           // InterfaceMethod org/apache/dubbo/common/logger/ErrorTypeAwareLogger.debug:(Ljava/lang/String;Ljava/lang/Throwable;)V
      29: return

  public void ignore(java.lang.Throwable);
    Code:
       0: aload_0
       1: getfield      #8                  // Field logger:Lorg/apache/dubbo/common/logger/ErrorTypeAwareLogger;
       4: invokeinterface #10,  1           // InterfaceMethod org/apache/dubbo/common/logger/ErrorTypeAwareLogger.isWarnEnabled:()Z
       9: ifeq          30
      12: aload_0
      13: getfield      #8                  // Field logger:Lorg/apache/dubbo/common/logger/ErrorTypeAwareLogger;
      16: ldc           #11                 // String 0-12
      18: ldc           #12                 // String
      20: ldc           #12                 // String
      22: ldc           #26                 // String IGNORED EXCEPTION
      24: aload_1
      25: invokeinterface #16,  6           // InterfaceMethod org/apache/dubbo/common/logger/ErrorTypeAwareLogger.warn:(Ljava/lang/String;Ljava/lang/String;Ljava/lang/String;Ljava/lang/String;Ljava/lang/Throwable;)V
      30: return

  private java.lang.String format(java.lang.String, java.lang.Object...);
    Code:
       0: aload_1
       1: invokestatic  #27                 // Method java/lang/String.valueOf:(Ljava/lang/Object;)Ljava/lang/String;
       4: astore_1
       5: ldc           #28                 // String {}
       7: astore_3
       8: new           #29                 // class java/lang/StringBuilder
      11: dup
      12: invokespecial #30                 // Method java/lang/StringBuilder."<init>":()V
      15: astore        4
      17: iconst_0
      18: istore        5
      20: aload_2
      21: astore        6
      23: aload         6
      25: arraylength
      26: istore        7
      28: iconst_0
      29: istore        8
      31: iload         8
      33: iload         7
      35: if_icmpge     130
      38: aload         6
      40: iload         8
      42: aaload
      43: astore        9
      45: aload_1
      46: aload_3
      47: iload         5
      49: invokevirtual #31                 // Method java/lang/String.indexOf:(Ljava/lang/String;I)I
      52: istore        10
      54: iload         10
      56: ifge          96
      59: aload         4
      61: aload_1
      62: iload         5
      64: invokevirtual #32                 // Method java/lang/String.substring:(I)Ljava/lang/String;
      67: invokevirtual #33                 // Method java/lang/StringBuilder.append:(Ljava/lang/String;)Ljava/lang/StringBuilder;
      70: pop
      71: aload         4
      73: bipush        32
      75: invokevirtual #34                 // Method java/lang/StringBuilder.append:(C)Ljava/lang/StringBuilder;
      78: pop
      79: aload         4
      81: aload         9
      83: invokevirtual #35                 // Method java/lang/StringBuilder.append:(Ljava/lang/Object;)Ljava/lang/StringBuilder;
      86: pop
      87: aload_1
      88: invokevirtual #36                 // Method java/lang/String.length:()I
      91: istore        5
      93: goto          124
      96: aload         4
      98: aload_1
      99: iload         5
     101: iload         10
     103: invokevirtual #37                 // Method java/lang/StringBuilder.append:(Ljava/lang/CharSequence;II)Ljava/lang/StringBuilder;
     106: pop
     107: aload         4
     109: aload         9
     111: invokevirtual #35                 // Method java/lang/StringBuilder.append:(Ljava/lang/Object;)Ljava/lang/StringBuilder;
     114: pop
     115: iload         10
     117: aload_3
     118: invokevirtual #36                 // Method java/lang/String.length:()I
     121: iadd
     122: istore        5
     124: iinc          8, 1
     127: goto          31
     130: aload         4
     132: aload_1
     133: iload         5
     135: invokevirtual #32                 // Method java/lang/String.substring:(I)Ljava/lang/String;
     138: invokevirtual #33                 // Method java/lang/StringBuilder.append:(Ljava/lang/String;)Ljava/lang/StringBuilder;
     141: pop
     142: aload         4
     144: invokevirtual #38                 // Method java/lang/StringBuilder.toString:()Ljava/lang/String;
     147: areturn

  static {};
    Code:
       0: iconst_0
       1: putstatic     #21                 // Field debugEnabled:Z
       4: return
}
