Compiled from "TomcatHttpServer.java"
public class org.apache.dubbo.remoting.http.tomcat.TomcatHttpServer extends org.apache.dubbo.remoting.http.support.AbstractHttpServer {
  private static final org.apache.dubbo.common.logger.ErrorTypeAwareLogger logger;

  private final org.apache.catalina.startup.Tomcat tomcat;

  private final org.apache.dubbo.common.URL url;

  public org.apache.dubbo.remoting.http.tomcat.TomcatHttpServer(org.apache.dubbo.common.URL, org.apache.dubbo.remoting.http.HttpHandler);
    Code:
       0: aload_0
       1: aload_1
       2: aload_2
       3: invokespecial #4                  // Method org/apache/dubbo/remoting/http/support/AbstractHttpServer."<init>":(Lorg/apache/dubbo/common/URL;Lorg/apache/dubbo/remoting/http/HttpHandler;)V
       6: aload_0
       7: aload_1
       8: putfield      #5                  // Field url:Lorg/apache/dubbo/common/URL;
      11: aload_1
      12: invokevirtual #6                  // Method org/apache/dubbo/common/URL.getPort:()I
      15: aload_2
      16: invokestatic  #7                  // Method org/apache/dubbo/remoting/http/servlet/DispatcherServlet.addHttpHandler:(ILorg/apache/dubbo/remoting/http/HttpHandler;)V
      19: new           #8                  // class java/io/File
      22: dup
      23: ldc           #9                  // String java.io.tmpdir
      25: invokestatic  #10                 // Method java/lang/System.getProperty:(Ljava/lang/String;)Ljava/lang/String;
      28: invokespecial #11                 // Method java/io/File."<init>":(Ljava/lang/String;)V
      31: invokevirtual #12                 // Method java/io/File.getAbsolutePath:()Ljava/lang/String;
      34: astore_3
      35: aload_0
      36: new           #13                 // class org/apache/catalina/startup/Tomcat
      39: dup
      40: invokespecial #14                 // Method org/apache/catalina/startup/Tomcat."<init>":()V
      43: putfield      #15                 // Field tomcat:Lorg/apache/catalina/startup/Tomcat;
      46: aload_0
      47: getfield      #15                 // Field tomcat:Lorg/apache/catalina/startup/Tomcat;
      50: invokevirtual #16                 // Method org/apache/catalina/startup/Tomcat.getConnector:()Lorg/apache/catalina/connector/Connector;
      53: astore        4
      55: aload         4
      57: aload_1
      58: invokevirtual #6                  // Method org/apache/dubbo/common/URL.getPort:()I
      61: invokevirtual #17                 // Method org/apache/catalina/connector/Connector.setPort:(I)V
      64: aload         4
      66: ldc           #18                 // String maxThreads
      68: aload_1
      69: ldc           #19                 // String threads
      71: sipush        200
      74: invokevirtual #20                 // Method org/apache/dubbo/common/URL.getParameter:(Ljava/lang/String;I)I
      77: invokestatic  #21                 // Method java/lang/String.valueOf:(I)Ljava/lang/String;
      80: invokevirtual #22                 // Method org/apache/catalina/connector/Connector.setProperty:(Ljava/lang/String;Ljava/lang/String;)Z
      83: pop
      84: aload         4
      86: ldc           #23                 // String maxConnections
      88: aload_1
      89: ldc           #24                 // String accepts
      91: iconst_m1
      92: invokevirtual #20                 // Method org/apache/dubbo/common/URL.getParameter:(Ljava/lang/String;I)I
      95: invokestatic  #21                 // Method java/lang/String.valueOf:(I)Ljava/lang/String;
      98: invokevirtual #22                 // Method org/apache/catalina/connector/Connector.setProperty:(Ljava/lang/String;Ljava/lang/String;)Z
     101: pop
     102: aload         4
     104: ldc           #25                 // String URIEncoding
     106: ldc           #26                 // String UTF-8
     108: invokevirtual #22                 // Method org/apache/catalina/connector/Connector.setProperty:(Ljava/lang/String;Ljava/lang/String;)Z
     111: pop
     112: aload         4
     114: ldc           #27                 // String connectionTimeout
     116: ldc           #28                 // String 60000
     118: invokevirtual #22                 // Method org/apache/catalina/connector/Connector.setProperty:(Ljava/lang/String;Ljava/lang/String;)Z
     121: pop
     122: aload         4
     124: ldc           #29                 // String maxKeepAliveRequests
     126: ldc           #30                 // String -1
     128: invokevirtual #22                 // Method org/apache/catalina/connector/Connector.setProperty:(Ljava/lang/String;Ljava/lang/String;)Z
     131: pop
     132: aload_0
     133: getfield      #15                 // Field tomcat:Lorg/apache/catalina/startup/Tomcat;
     136: aload_3
     137: invokevirtual #31                 // Method org/apache/catalina/startup/Tomcat.setBaseDir:(Ljava/lang/String;)V
     140: aload_0
     141: getfield      #15                 // Field tomcat:Lorg/apache/catalina/startup/Tomcat;
     144: aload_1
     145: invokevirtual #6                  // Method org/apache/dubbo/common/URL.getPort:()I
     148: invokevirtual #32                 // Method org/apache/catalina/startup/Tomcat.setPort:(I)V
     151: aload_0
     152: getfield      #15                 // Field tomcat:Lorg/apache/catalina/startup/Tomcat;
     155: ldc           #33                 // String /
     157: aload_3
     158: invokevirtual #34                 // Method org/apache/catalina/startup/Tomcat.addContext:(Ljava/lang/String;Ljava/lang/String;)Lorg/apache/catalina/Context;
     161: astore        5
     163: aload         5
     165: ldc           #35                 // String dispatcher
     167: new           #36                 // class org/apache/dubbo/remoting/http/servlet/DispatcherServlet
     170: dup
     171: invokespecial #37                 // Method org/apache/dubbo/remoting/http/servlet/DispatcherServlet."<init>":()V
     174: invokestatic  #38                 // Method org/apache/catalina/startup/Tomcat.addServlet:(Lorg/apache/catalina/Context;Ljava/lang/String;Ljavax/servlet/Servlet;)Lorg/apache/catalina/Wrapper;
     177: pop
     178: aload         5
     180: ldc           #39                 // String /*
     182: ldc           #35                 // String dispatcher
     184: invokeinterface #40,  3           // InterfaceMethod org/apache/catalina/Context.addServletMappingDecoded:(Ljava/lang/String;Ljava/lang/String;)V
     189: invokestatic  #41                 // Method org/apache/dubbo/remoting/http/servlet/ServletManager.getInstance:()Lorg/apache/dubbo/remoting/http/servlet/ServletManager;
     192: aload_1
     193: invokevirtual #6                  // Method org/apache/dubbo/common/URL.getPort:()I
     196: aload         5
     198: invokeinterface #42,  1           // InterfaceMethod org/apache/catalina/Context.getServletContext:()Ljavax/servlet/ServletContext;
     203: invokevirtual #43                 // Method org/apache/dubbo/remoting/http/servlet/ServletManager.addServletContext:(ILjavax/servlet/ServletContext;)V
     206: ldc           #44                 // String org.apache.catalina.startup.EXIT_ON_INIT_FAILURE
     208: ldc           #45                 // String true
     210: invokestatic  #46                 // Method java/lang/System.setProperty:(Ljava/lang/String;Ljava/lang/String;)Ljava/lang/String;
     213: pop
     214: aload_0
     215: getfield      #15                 // Field tomcat:Lorg/apache/catalina/startup/Tomcat;
     218: invokevirtual #47                 // Method org/apache/catalina/startup/Tomcat.start:()V
     221: goto          258
     224: astore        6
     226: new           #49                 // class java/lang/IllegalStateException
     229: dup
     230: new           #50                 // class java/lang/StringBuilder
     233: dup
     234: invokespecial #51                 // Method java/lang/StringBuilder."<init>":()V
     237: ldc           #52                 // String Failed to start tomcat server at
     239: invokevirtual #53                 // Method java/lang/StringBuilder.append:(Ljava/lang/String;)Ljava/lang/StringBuilder;
     242: aload_1
     243: invokevirtual #54                 // Method org/apache/dubbo/common/URL.getAddress:()Ljava/lang/String;
     246: invokevirtual #53                 // Method java/lang/StringBuilder.append:(Ljava/lang/String;)Ljava/lang/StringBuilder;
     249: invokevirtual #55                 // Method java/lang/StringBuilder.toString:()Ljava/lang/String;
     252: aload         6
     254: invokespecial #56                 // Method java/lang/IllegalStateException."<init>":(Ljava/lang/String;Ljava/lang/Throwable;)V
     257: athrow
     258: return
    Exception table:
       from    to  target type
         214   221   224   Class org/apache/catalina/LifecycleException

  public void close();
    Code:
       0: aload_0
       1: invokespecial #57                 // Method org/apache/dubbo/remoting/http/support/AbstractHttpServer.close:()V
       4: invokestatic  #41                 // Method org/apache/dubbo/remoting/http/servlet/ServletManager.getInstance:()Lorg/apache/dubbo/remoting/http/servlet/ServletManager;
       7: aload_0
       8: getfield      #5                  // Field url:Lorg/apache/dubbo/common/URL;
      11: invokevirtual #6                  // Method org/apache/dubbo/common/URL.getPort:()I
      14: invokevirtual #58                 // Method org/apache/dubbo/remoting/http/servlet/ServletManager.removeServletContext:(I)V
      17: aload_0
      18: getfield      #15                 // Field tomcat:Lorg/apache/catalina/startup/Tomcat;
      21: invokevirtual #59                 // Method org/apache/catalina/startup/Tomcat.stop:()V
      24: aload_0
      25: getfield      #15                 // Field tomcat:Lorg/apache/catalina/startup/Tomcat;
      28: invokevirtual #60                 // Method org/apache/catalina/startup/Tomcat.destroy:()V
      31: goto          54
      34: astore_1
      35: getstatic     #62                 // Field logger:Lorg/apache/dubbo/common/logger/ErrorTypeAwareLogger;
      38: ldc           #63                 // String 0-11
      40: ldc           #64                 // String
      42: ldc           #64                 // String
      44: aload_1
      45: invokevirtual #65                 // Method java/lang/Exception.getMessage:()Ljava/lang/String;
      48: aload_1
      49: invokeinterface #66,  6           // InterfaceMethod org/apache/dubbo/common/logger/ErrorTypeAwareLogger.warn:(Ljava/lang/String;Ljava/lang/String;Ljava/lang/String;Ljava/lang/String;Ljava/lang/Throwable;)V
      54: return
    Exception table:
       from    to  target type
          17    31    34   Class java/lang/Exception

  static {};
    Code:
       0: ldc           #67                 // class org/apache/dubbo/remoting/http/tomcat/TomcatHttpServer
       2: invokestatic  #68                 // Method org/apache/dubbo/common/logger/LoggerFactory.getErrorTypeAwareLogger:(Ljava/lang/Class;)Lorg/apache/dubbo/common/logger/ErrorTypeAwareLogger;
       5: putstatic     #62                 // Field logger:Lorg/apache/dubbo/common/logger/ErrorTypeAwareLogger;
       8: return
}
