Compiled from "DeployerReadinessProbe.java"
public class org.apache.dubbo.qos.probe.impl.DeployerReadinessProbe implements org.apache.dubbo.qos.probe.ReadinessProbe {
  private org.apache.dubbo.rpc.model.FrameworkModel frameworkModel;

  public org.apache.dubbo.qos.probe.impl.DeployerReadinessProbe(org.apache.dubbo.rpc.model.FrameworkModel);
    Code:
       0: aload_0
       1: invokespecial #1                  // Method java/lang/Object."<init>":()V
       4: aload_0
       5: aload_1
       6: putfield      #2                  // Field frameworkModel:Lorg/apache/dubbo/rpc/model/FrameworkModel;
       9: return

  public boolean check();
    Code:
       0: aload_0
       1: getfield      #2                  // Field frameworkModel:Lorg/apache/dubbo/rpc/model/FrameworkModel;
       4: ifnonnull     14
       7: aload_0
       8: invokestatic  #3                  // Method org/apache/dubbo/rpc/model/FrameworkModel.defaultModel:()Lorg/apache/dubbo/rpc/model/FrameworkModel;
      11: putfield      #2                  // Field frameworkModel:Lorg/apache/dubbo/rpc/model/FrameworkModel;
      14: aload_0
      15: getfield      #2                  // Field frameworkModel:Lorg/apache/dubbo/rpc/model/FrameworkModel;
      18: invokevirtual #4                  // Method org/apache/dubbo/rpc/model/FrameworkModel.getApplicationModels:()Ljava/util/List;
      21: astore_1
      22: aload_1
      23: invokeinterface #5,  1            // InterfaceMethod java/util/List.iterator:()Ljava/util/Iterator;
      28: astore_2
      29: aload_2
      30: invokeinterface #6,  1            // InterfaceMethod java/util/Iterator.hasNext:()Z
      35: ifeq          102
      38: aload_2
      39: invokeinterface #7,  1            // InterfaceMethod java/util/Iterator.next:()Ljava/lang/Object;
      44: checkcast     #8                  // class org/apache/dubbo/rpc/model/ApplicationModel
      47: astore_3
      48: aload_3
      49: invokevirtual #9                  // Method org/apache/dubbo/rpc/model/ApplicationModel.getModuleModels:()Ljava/util/List;
      52: invokeinterface #5,  1            // InterfaceMethod java/util/List.iterator:()Ljava/util/Iterator;
      57: astore        4
      59: aload         4
      61: invokeinterface #6,  1            // InterfaceMethod java/util/Iterator.hasNext:()Z
      66: ifeq          99
      69: aload         4
      71: invokeinterface #7,  1            // InterfaceMethod java/util/Iterator.next:()Ljava/lang/Object;
      76: checkcast     #10                 // class org/apache/dubbo/rpc/model/ModuleModel
      79: astore        5
      81: aload         5
      83: invokevirtual #11                 // Method org/apache/dubbo/rpc/model/ModuleModel.getDeployer:()Lorg/apache/dubbo/common/deploy/ModuleDeployer;
      86: invokeinterface #12,  1           // InterfaceMethod org/apache/dubbo/common/deploy/ModuleDeployer.isStarted:()Z
      91: ifne          96
      94: iconst_0
      95: ireturn
      96: goto          59
      99: goto          29
     102: iconst_1
     103: ireturn
}
