Compiled from "ProviderReadinessProbe.java"
public class org.apache.dubbo.qos.probe.impl.ProviderReadinessProbe implements org.apache.dubbo.qos.probe.ReadinessProbe {
  private final org.apache.dubbo.rpc.model.FrameworkModel frameworkModel;

  private final org.apache.dubbo.rpc.model.FrameworkServiceRepository serviceRepository;

  public org.apache.dubbo.qos.probe.impl.ProviderReadinessProbe(org.apache.dubbo.rpc.model.FrameworkModel);
    Code:
       0: aload_0
       1: invokespecial #1                  // Method java/lang/Object."<init>":()V
       4: aload_1
       5: ifnull        16
       8: aload_0
       9: aload_1
      10: putfield      #2                  // Field frameworkModel:Lorg/apache/dubbo/rpc/model/FrameworkModel;
      13: goto          23
      16: aload_0
      17: invokestatic  #3                  // Method org/apache/dubbo/rpc/model/FrameworkModel.defaultModel:()Lorg/apache/dubbo/rpc/model/FrameworkModel;
      20: putfield      #2                  // Field frameworkModel:Lorg/apache/dubbo/rpc/model/FrameworkModel;
      23: aload_0
      24: aload_0
      25: getfield      #2                  // Field frameworkModel:Lorg/apache/dubbo/rpc/model/FrameworkModel;
      28: invokevirtual #4                  // Method org/apache/dubbo/rpc/model/FrameworkModel.getServiceRepository:()Lorg/apache/dubbo/rpc/model/FrameworkServiceRepository;
      31: putfield      #5                  // Field serviceRepository:Lorg/apache/dubbo/rpc/model/FrameworkServiceRepository;
      34: return

  public boolean check();
    Code:
       0: aload_0
       1: getfield      #5                  // Field serviceRepository:Lorg/apache/dubbo/rpc/model/FrameworkServiceRepository;
       4: invokevirtual #6                  // Method org/apache/dubbo/rpc/model/FrameworkServiceRepository.allProviderModels:()Ljava/util/List;
       7: astore_1
       8: aload_1
       9: invokeinterface #7,  1            // InterfaceMethod java/util/Collection.isEmpty:()Z
      14: ifeq          19
      17: iconst_1
      18: ireturn
      19: iconst_0
      20: istore_2
      21: iconst_0
      22: istore_3
      23: aload_1
      24: invokeinterface #8,  1            // InterfaceMethod java/util/Collection.iterator:()Ljava/util/Iterator;
      29: astore        4
      31: aload         4
      33: invokeinterface #9,  1            // InterfaceMethod java/util/Iterator.hasNext:()Z
      38: ifeq          118
      41: aload         4
      43: invokeinterface #10,  1           // InterfaceMethod java/util/Iterator.next:()Ljava/lang/Object;
      48: checkcast     #11                 // class org/apache/dubbo/rpc/model/ProviderModel
      51: astore        5
      53: aload         5
      55: invokevirtual #12                 // Method org/apache/dubbo/rpc/model/ProviderModel.getModuleModel:()Lorg/apache/dubbo/rpc/model/ModuleModel;
      58: invokevirtual #13                 // Method org/apache/dubbo/rpc/model/ModuleModel.isInternal:()Z
      61: ifeq          67
      64: goto          31
      67: iconst_1
      68: istore_2
      69: iload_3
      70: ifne          109
      73: aload         5
      75: invokevirtual #14                 // Method org/apache/dubbo/rpc/model/ProviderModel.getStatedUrl:()Ljava/util/List;
      78: invokeinterface #15,  1           // InterfaceMethod java/util/List.isEmpty:()Z
      83: ifne          109
      86: aload         5
      88: invokevirtual #14                 // Method org/apache/dubbo/rpc/model/ProviderModel.getStatedUrl:()Ljava/util/List;
      91: invokeinterface #16,  1           // InterfaceMethod java/util/List.stream:()Ljava/util/stream/Stream;
      96: invokedynamic #17,  0             // InvokeDynamic #0:test:()Ljava/util/function/Predicate;
     101: invokeinterface #18,  2           // InterfaceMethod java/util/stream/Stream.anyMatch:(Ljava/util/function/Predicate;)Z
     106: ifeq          113
     109: iconst_1
     110: goto          114
     113: iconst_0
     114: istore_3
     115: goto          31
     118: iload_2
     119: ifeq          126
     122: iload_3
     123: ifeq          130
     126: iconst_1
     127: goto          131
     130: iconst_0
     131: ireturn
}
