Compiled from "MethodConfig.java"
public class com.alibaba.dubbo.config.MethodConfig extends org.apache.dubbo.config.MethodConfig {
  public com.alibaba.dubbo.config.MethodConfig();
    Code:
       0: aload_0
       1: invokespecial #1                  // Method org/apache/dubbo/config/MethodConfig."<init>":()V
       4: return

  public void addArgument(com.alibaba.dubbo.config.ArgumentConfig);
    Code:
       0: aload_0
       1: aload_1
       2: invokespecial #2                  // Method org/apache/dubbo/config/MethodConfig.addArgument:(Lorg/apache/dubbo/config/ArgumentConfig;)V
       5: return

  public void setMock(java.lang.Boolean);
    Code:
       0: aload_1
       1: ifnonnull     15
       4: aload_0
       5: aconst_null
       6: checkcast     #3                  // class java/lang/String
       9: invokevirtual #4                  // Method setMock:(Ljava/lang/String;)V
      12: goto          23
      15: aload_0
      16: aload_1
      17: invokestatic  #5                  // Method java/lang/String.valueOf:(Ljava/lang/Object;)Ljava/lang/String;
      20: invokevirtual #4                  // Method setMock:(Ljava/lang/String;)V
      23: return
}
