Compiled from "ModuleConfig.java"
public class com.alibaba.dubbo.config.ModuleConfig extends org.apache.dubbo.config.ModuleConfig {
  public com.alibaba.dubbo.config.ModuleConfig();
    Code:
       0: aload_0
       1: invokespecial #1                  // Method org/apache/dubbo/config/ModuleConfig."<init>":()V
       4: return

  public com.alibaba.dubbo.config.ModuleConfig(java.lang.String);
    Code:
       0: aload_0
       1: aload_1
       2: invokespecial #2                  // Method org/apache/dubbo/config/ModuleConfig."<init>":(Ljava/lang/String;)V
       5: return

  public void setRegistry(com.alibaba.dubbo.config.RegistryConfig);
    Code:
       0: aload_0
       1: aload_1
       2: invokespecial #3                  // Method org/apache/dubbo/config/ModuleConfig.setRegistry:(Lorg/apache/dubbo/config/RegistryConfig;)V
       5: return

  public void setMonitor(com.alibaba.dubbo.config.MonitorConfig);
    Code:
       0: aload_0
       1: aload_1
       2: invokespecial #4                  // Method org/apache/dubbo/config/ModuleConfig.setMonitor:(Lorg/apache/dubbo/config/MonitorConfig;)V
       5: return

  public void setMonitor(java.lang.String);
    Code:
       0: aload_0
       1: new           #5                  // class com/alibaba/dubbo/config/MonitorConfig
       4: dup
       5: aload_1
       6: invokespecial #6                  // Method com/alibaba/dubbo/config/MonitorConfig."<init>":(Ljava/lang/String;)V
       9: invokevirtual #7                  // Method setMonitor:(Lcom/alibaba/dubbo/config/MonitorConfig;)V
      12: return
}
