Compiled from "ProtocolConfig.java"
public class com.alibaba.dubbo.config.ProtocolConfig extends org.apache.dubbo.config.ProtocolConfig {
  public com.alibaba.dubbo.config.ProtocolConfig();
    Code:
       0: aload_0
       1: invokespecial #1                  // Method org/apache/dubbo/config/ProtocolConfig."<init>":()V
       4: return

  public com.alibaba.dubbo.config.ProtocolConfig(java.lang.String);
    Code:
       0: aload_0
       1: aload_1
       2: invokespecial #2                  // Method org/apache/dubbo/config/ProtocolConfig."<init>":(Ljava/lang/String;)V
       5: return

  public com.alibaba.dubbo.config.ProtocolConfig(java.lang.String, int);
    Code:
       0: aload_0
       1: aload_1
       2: iload_2
       3: invokespecial #3                  // Method org/apache/dubbo/config/ProtocolConfig."<init>":(Ljava/lang/String;I)V
       6: return

  public void mergeProtocol(com.alibaba.dubbo.config.ProtocolConfig);
    Code:
       0: aload_0
       1: aload_1
       2: invokespecial #4                  // Method org/apache/dubbo/config/ProtocolConfig.mergeProtocol:(Lorg/apache/dubbo/config/ProtocolConfig;)V
       5: return
}
