Compiled from "ProviderConfig.java"
public class com.alibaba.dubbo.config.ProviderConfig extends org.apache.dubbo.config.ProviderConfig {
  public com.alibaba.dubbo.config.ProviderConfig();
    Code:
       0: aload_0
       1: invokespecial #1                  // Method org/apache/dubbo/config/ProviderConfig."<init>":()V
       4: return

  public void setApplication(com.alibaba.dubbo.config.ApplicationConfig);
    Code:
       0: aload_0
       1: aload_1
       2: invokespecial #2                  // Method org/apache/dubbo/config/ProviderConfig.setApplication:(Lorg/apache/dubbo/config/ApplicationConfig;)V
       5: return

  public void setModule(com.alibaba.dubbo.config.ModuleConfig);
    Code:
       0: aload_0
       1: aload_1
       2: invokespecial #3                  // Method org/apache/dubbo/config/ProviderConfig.setModule:(Lorg/apache/dubbo/config/ModuleConfig;)V
       5: return

  public void setRegistry(com.alibaba.dubbo.config.RegistryConfig);
    Code:
       0: aload_0
       1: aload_1
       2: invokespecial #4                  // Method org/apache/dubbo/config/ProviderConfig.setRegistry:(Lorg/apache/dubbo/config/RegistryConfig;)V
       5: return

  public void addMethod(com.alibaba.dubbo.config.MethodConfig);
    Code:
       0: aload_0
       1: aload_1
       2: invokespecial #5                  // Method org/apache/dubbo/config/ProviderConfig.addMethod:(Lorg/apache/dubbo/config/MethodConfig;)V
       5: return

  public void setMonitor(com.alibaba.dubbo.config.MonitorConfig);
    Code:
       0: aload_0
       1: aload_1
       2: invokespecial #6                  // Method org/apache/dubbo/config/ProviderConfig.setMonitor:(Lorg/apache/dubbo/config/MonitorConfig;)V
       5: return

  public void setProtocol(com.alibaba.dubbo.config.ProtocolConfig);
    Code:
       0: aload_0
       1: aload_1
       2: invokespecial #7                  // Method org/apache/dubbo/config/ProviderConfig.setProtocol:(Lorg/apache/dubbo/config/ProtocolConfig;)V
       5: return

  public void setProtocol(java.lang.String);
    Code:
       0: aload_0
       1: new           #8                  // class com/alibaba/dubbo/config/ProtocolConfig
       4: dup
       5: aload_1
       6: invokespecial #9                  // Method com/alibaba/dubbo/config/ProtocolConfig."<init>":(Ljava/lang/String;)V
       9: invokevirtual #10                 // Method setProtocol:(Lcom/alibaba/dubbo/config/ProtocolConfig;)V
      12: return

  public void setMock(java.lang.Boolean);
    Code:
       0: aload_1
       1: ifnonnull     15
       4: aload_0
       5: aconst_null
       6: checkcast     #11                 // class java/lang/String
       9: invokevirtual #12                 // Method setMock:(Ljava/lang/String;)V
      12: goto          23
      15: aload_0
      16: aload_1
      17: invokestatic  #13                 // Method java/lang/String.valueOf:(Ljava/lang/Object;)Ljava/lang/String;
      20: invokevirtual #12                 // Method setMock:(Ljava/lang/String;)V
      23: return
}
