Compiled from "ReferenceConfig.java"
public class com.alibaba.dubbo.config.ReferenceConfig<T> extends org.apache.dubbo.config.ReferenceConfig<T> {
  public com.alibaba.dubbo.config.ReferenceConfig();
    Code:
       0: aload_0
       1: invokespecial #1                  // Method org/apache/dubbo/config/ReferenceConfig."<init>":()V
       4: return

  public com.alibaba.dubbo.config.ReferenceConfig(org.apache.dubbo.config.annotation.Reference);
    Code:
       0: aload_0
       1: aload_1
       2: invokespecial #2                  // Method org/apache/dubbo/config/ReferenceConfig."<init>":(Lorg/apache/dubbo/config/annotation/Reference;)V
       5: return

  public void setConsumer(com.alibaba.dubbo.config.ConsumerConfig);
    Code:
       0: aload_0
       1: aload_1
       2: invokespecial #3                  // Method org/apache/dubbo/config/ReferenceConfig.setConsumer:(Lorg/apache/dubbo/config/ConsumerConfig;)V
       5: return

  public void setApplication(com.alibaba.dubbo.config.ApplicationConfig);
    Code:
       0: aload_0
       1: aload_1
       2: invokespecial #4                  // Method org/apache/dubbo/config/ReferenceConfig.setApplication:(Lorg/apache/dubbo/config/ApplicationConfig;)V
       5: return

  public void setModule(com.alibaba.dubbo.config.ModuleConfig);
    Code:
       0: aload_0
       1: aload_1
       2: invokespecial #5                  // Method org/apache/dubbo/config/ReferenceConfig.setModule:(Lorg/apache/dubbo/config/ModuleConfig;)V
       5: return

  public void setRegistry(com.alibaba.dubbo.config.RegistryConfig);
    Code:
       0: aload_0
       1: aload_1
       2: invokespecial #6                  // Method org/apache/dubbo/config/ReferenceConfig.setRegistry:(Lorg/apache/dubbo/config/RegistryConfig;)V
       5: return

  public void addMethod(com.alibaba.dubbo.config.MethodConfig);
    Code:
       0: aload_0
       1: aload_1
       2: invokespecial #7                  // Method org/apache/dubbo/config/ReferenceConfig.addMethod:(Lorg/apache/dubbo/config/MethodConfig;)V
       5: return

  public void setMonitor(com.alibaba.dubbo.config.MonitorConfig);
    Code:
       0: aload_0
       1: aload_1
       2: invokespecial #8                  // Method org/apache/dubbo/config/ReferenceConfig.setMonitor:(Lorg/apache/dubbo/config/MonitorConfig;)V
       5: return

  public void setMock(java.lang.Boolean);
    Code:
       0: aload_1
       1: ifnonnull     15
       4: aload_0
       5: aconst_null
       6: checkcast     #9                  // class java/lang/String
       9: invokevirtual #10                 // Method setMock:(Ljava/lang/String;)V
      12: goto          23
      15: aload_0
      16: aload_1
      17: invokestatic  #11                 // Method java/lang/String.valueOf:(Ljava/lang/Object;)Ljava/lang/String;
      20: invokevirtual #10                 // Method setMock:(Ljava/lang/String;)V
      23: return

  public void setInterfaceClass(java.lang.Class<?>);
    Code:
       0: aload_0
       1: aload_1
       2: invokevirtual #12                 // Method setInterface:(Ljava/lang/Class;)V
       5: return
}
