Compiled from "RegistryConfig.java"
public class com.alibaba.dubbo.config.RegistryConfig extends org.apache.dubbo.config.RegistryConfig {
  public com.alibaba.dubbo.config.RegistryConfig();
    Code:
       0: aload_0
       1: invokespecial #1                  // Method org/apache/dubbo/config/RegistryConfig."<init>":()V
       4: return

  public com.alibaba.dubbo.config.RegistryConfig(java.lang.String);
    Code:
       0: aload_0
       1: aload_1
       2: invokespecial #2                  // Method org/apache/dubbo/config/RegistryConfig."<init>":(Ljava/lang/String;)V
       5: return

  public com.alibaba.dubbo.config.RegistryConfig(java.lang.String, java.lang.String);
    Code:
       0: aload_0
       1: aload_1
       2: aload_2
       3: invokespecial #3                  // Method org/apache/dubbo/config/RegistryConfig."<init>":(Ljava/lang/String;Ljava/lang/String;)V
       6: return
}
