Compiled from "ServiceConfig.java"
public class com.alibaba.dubbo.config.ServiceConfig<T> extends org.apache.dubbo.config.ServiceConfig<T> {
  public com.alibaba.dubbo.config.ServiceConfig();
    Code:
       0: aload_0
       1: invokespecial #1                  // Method org/apache/dubbo/config/ServiceConfig."<init>":()V
       4: return

  public com.alibaba.dubbo.config.ServiceConfig(org.apache.dubbo.config.annotation.Service);
    Code:
       0: aload_0
       1: aload_1
       2: invokespecial #2                  // Method org/apache/dubbo/config/ServiceConfig."<init>":(Lorg/apache/dubbo/config/annotation/Service;)V
       5: return

  public void setProvider(com.alibaba.dubbo.config.ProviderConfig);
    Code:
       0: aload_0
       1: aload_1
       2: invokespecial #3                  // Method org/apache/dubbo/config/ServiceConfig.setProvider:(Lorg/apache/dubbo/config/ProviderConfig;)V
       5: return

  public void setApplication(com.alibaba.dubbo.config.ApplicationConfig);
    Code:
       0: aload_0
       1: aload_1
       2: invokespecial #4                  // Method org/apache/dubbo/config/ServiceConfig.setApplication:(Lorg/apache/dubbo/config/ApplicationConfig;)V
       5: return

  public void setModule(com.alibaba.dubbo.config.ModuleConfig);
    Code:
       0: aload_0
       1: aload_1
       2: invokespecial #5                  // Method org/apache/dubbo/config/ServiceConfig.setModule:(Lorg/apache/dubbo/config/ModuleConfig;)V
       5: return

  public void setRegistry(com.alibaba.dubbo.config.RegistryConfig);
    Code:
       0: aload_0
       1: aload_1
       2: invokespecial #6                  // Method org/apache/dubbo/config/ServiceConfig.setRegistry:(Lorg/apache/dubbo/config/RegistryConfig;)V
       5: return

  public void addMethod(com.alibaba.dubbo.config.MethodConfig);
    Code:
       0: aload_0
       1: aload_1
       2: invokespecial #7                  // Method org/apache/dubbo/config/ServiceConfig.addMethod:(Lorg/apache/dubbo/config/MethodConfig;)V
       5: return

  public com.alibaba.dubbo.config.MonitorConfig getMonitor();
    Code:
       0: aload_0
       1: invokespecial #8                  // Method org/apache/dubbo/config/ServiceConfig.getMonitor:()Lorg/apache/dubbo/config/MonitorConfig;
       4: astore_1
       5: aload_1
       6: ifnonnull     11
       9: aconst_null
      10: areturn
      11: aload_1
      12: instanceof    #9                  // class com/alibaba/dubbo/config/MonitorConfig
      15: ifeq          23
      18: aload_1
      19: checkcast     #9                  // class com/alibaba/dubbo/config/MonitorConfig
      22: areturn
      23: new           #10                 // class java/lang/IllegalArgumentException
      26: dup
      27: new           #11                 // class java/lang/StringBuilder
      30: dup
      31: invokespecial #12                 // Method java/lang/StringBuilder."<init>":()V
      34: ldc           #13                 // String Monitor has not been set with type com.alibaba.dubbo.config.MonitorConfig. Found
      36: invokevirtual #14                 // Method java/lang/StringBuilder.append:(Ljava/lang/String;)Ljava/lang/StringBuilder;
      39: aload_1
      40: invokevirtual #15                 // Method java/lang/Object.getClass:()Ljava/lang/Class;
      43: invokevirtual #16                 // Method java/lang/Class.getName:()Ljava/lang/String;
      46: invokevirtual #14                 // Method java/lang/StringBuilder.append:(Ljava/lang/String;)Ljava/lang/StringBuilder;
      49: ldc           #17                 // String  instead.
      51: invokevirtual #14                 // Method java/lang/StringBuilder.append:(Ljava/lang/String;)Ljava/lang/StringBuilder;
      54: invokevirtual #18                 // Method java/lang/StringBuilder.toString:()Ljava/lang/String;
      57: invokespecial #19                 // Method java/lang/IllegalArgumentException."<init>":(Ljava/lang/String;)V
      60: athrow

  public void setMonitor(com.alibaba.dubbo.config.MonitorConfig);
    Code:
       0: aload_0
       1: aload_1
       2: invokespecial #20                 // Method org/apache/dubbo/config/ServiceConfig.setMonitor:(Lorg/apache/dubbo/config/MonitorConfig;)V
       5: return

  public void setProtocol(com.alibaba.dubbo.config.ProtocolConfig);
    Code:
       0: aload_0
       1: aload_1
       2: invokespecial #21                 // Method org/apache/dubbo/config/ServiceConfig.setProtocol:(Lorg/apache/dubbo/config/ProtocolConfig;)V
       5: return

  public void setMock(java.lang.Boolean);
    Code:
       0: aload_1
       1: ifnonnull     15
       4: aload_0
       5: aconst_null
       6: checkcast     #22                 // class java/lang/String
       9: invokevirtual #23                 // Method setMock:(Ljava/lang/String;)V
      12: goto          23
      15: aload_0
      16: aload_1
      17: invokestatic  #24                 // Method java/lang/String.valueOf:(Ljava/lang/Object;)Ljava/lang/String;
      20: invokevirtual #23                 // Method setMock:(Ljava/lang/String;)V
      23: return

  public void setProviders(java.util.List<com.alibaba.dubbo.config.ProviderConfig>);
    Code:
       0: aload_0
       1: aload_1
       2: invokestatic  #25                 // Method convertProviderToProtocol:(Ljava/util/List;)Ljava/util/List;
       5: invokevirtual #26                 // Method setProtocols:(Ljava/util/List;)V
       8: return

  private static java.util.List<com.alibaba.dubbo.config.ProtocolConfig> convertProviderToProtocol(java.util.List<com.alibaba.dubbo.config.ProviderConfig>);
    Code:
       0: aload_0
       1: ifnull        13
       4: aload_0
       5: invokeinterface #27,  1           // InterfaceMethod java/util/List.isEmpty:()Z
      10: ifeq          15
      13: aconst_null
      14: areturn
      15: new           #28                 // class java/util/ArrayList
      18: dup
      19: aload_0
      20: invokeinterface #29,  1           // InterfaceMethod java/util/List.size:()I
      25: invokespecial #30                 // Method java/util/ArrayList."<init>":(I)V
      28: astore_1
      29: aload_0
      30: invokeinterface #31,  1           // InterfaceMethod java/util/List.iterator:()Ljava/util/Iterator;
      35: astore_2
      36: aload_2
      37: invokeinterface #32,  1           // InterfaceMethod java/util/Iterator.hasNext:()Z
      42: ifeq          69
      45: aload_2
      46: invokeinterface #33,  1           // InterfaceMethod java/util/Iterator.next:()Ljava/lang/Object;
      51: checkcast     #34                 // class com/alibaba/dubbo/config/ProviderConfig
      54: astore_3
      55: aload_1
      56: aload_3
      57: invokestatic  #35                 // Method convertProviderToProtocol:(Lcom/alibaba/dubbo/config/ProviderConfig;)Lcom/alibaba/dubbo/config/ProtocolConfig;
      60: invokeinterface #36,  2           // InterfaceMethod java/util/List.add:(Ljava/lang/Object;)Z
      65: pop
      66: goto          36
      69: aload_1
      70: areturn

  private static com.alibaba.dubbo.config.ProtocolConfig convertProviderToProtocol(com.alibaba.dubbo.config.ProviderConfig);
    Code:
       0: new           #37                 // class com/alibaba/dubbo/config/ProtocolConfig
       3: dup
       4: invokespecial #38                 // Method com/alibaba/dubbo/config/ProtocolConfig."<init>":()V
       7: astore_1
       8: aload_1
       9: aload_0
      10: invokevirtual #39                 // Method com/alibaba/dubbo/config/ProviderConfig.getProtocol:()Lorg/apache/dubbo/config/ProtocolConfig;
      13: invokevirtual #40                 // Method org/apache/dubbo/config/ProtocolConfig.getName:()Ljava/lang/String;
      16: invokevirtual #41                 // Method com/alibaba/dubbo/config/ProtocolConfig.setName:(Ljava/lang/String;)V
      19: aload_1
      20: aload_0
      21: invokevirtual #42                 // Method com/alibaba/dubbo/config/ProviderConfig.getServer:()Ljava/lang/String;
      24: invokevirtual #43                 // Method com/alibaba/dubbo/config/ProtocolConfig.setServer:(Ljava/lang/String;)V
      27: aload_1
      28: aload_0
      29: invokevirtual #44                 // Method com/alibaba/dubbo/config/ProviderConfig.getClient:()Ljava/lang/String;
      32: invokevirtual #45                 // Method com/alibaba/dubbo/config/ProtocolConfig.setClient:(Ljava/lang/String;)V
      35: aload_1
      36: aload_0
      37: invokevirtual #46                 // Method com/alibaba/dubbo/config/ProviderConfig.getCodec:()Ljava/lang/String;
      40: invokevirtual #47                 // Method com/alibaba/dubbo/config/ProtocolConfig.setCodec:(Ljava/lang/String;)V
      43: aload_1
      44: aload_0
      45: invokevirtual #48                 // Method com/alibaba/dubbo/config/ProviderConfig.getHost:()Ljava/lang/String;
      48: invokevirtual #49                 // Method com/alibaba/dubbo/config/ProtocolConfig.setHost:(Ljava/lang/String;)V
      51: aload_1
      52: aload_0
      53: invokevirtual #50                 // Method com/alibaba/dubbo/config/ProviderConfig.getPort:()Ljava/lang/Integer;
      56: invokevirtual #51                 // Method com/alibaba/dubbo/config/ProtocolConfig.setPort:(Ljava/lang/Integer;)V
      59: aload_1
      60: aload_0
      61: invokevirtual #52                 // Method com/alibaba/dubbo/config/ProviderConfig.getPath:()Ljava/lang/String;
      64: invokevirtual #53                 // Method com/alibaba/dubbo/config/ProtocolConfig.setPath:(Ljava/lang/String;)V
      67: aload_1
      68: aload_0
      69: invokevirtual #54                 // Method com/alibaba/dubbo/config/ProviderConfig.getPayload:()Ljava/lang/Integer;
      72: invokevirtual #55                 // Method com/alibaba/dubbo/config/ProtocolConfig.setPayload:(Ljava/lang/Integer;)V
      75: aload_1
      76: aload_0
      77: invokevirtual #56                 // Method com/alibaba/dubbo/config/ProviderConfig.getThreads:()Ljava/lang/Integer;
      80: invokevirtual #57                 // Method com/alibaba/dubbo/config/ProtocolConfig.setThreads:(Ljava/lang/Integer;)V
      83: aload_1
      84: aload_0
      85: invokevirtual #58                 // Method com/alibaba/dubbo/config/ProviderConfig.getParameters:()Ljava/util/Map;
      88: invokevirtual #59                 // Method com/alibaba/dubbo/config/ProtocolConfig.setParameters:(Ljava/util/Map;)V
      91: aload_1
      92: areturn

  private static com.alibaba.dubbo.config.ProviderConfig convertProtocolToProvider(com.alibaba.dubbo.config.ProtocolConfig);
    Code:
       0: new           #34                 // class com/alibaba/dubbo/config/ProviderConfig
       3: dup
       4: invokespecial #60                 // Method com/alibaba/dubbo/config/ProviderConfig."<init>":()V
       7: astore_1
       8: aload_1
       9: aload_0
      10: invokevirtual #61                 // Method com/alibaba/dubbo/config/ProviderConfig.setProtocol:(Lcom/alibaba/dubbo/config/ProtocolConfig;)V
      13: aload_1
      14: aload_0
      15: invokevirtual #62                 // Method com/alibaba/dubbo/config/ProtocolConfig.getServer:()Ljava/lang/String;
      18: invokevirtual #63                 // Method com/alibaba/dubbo/config/ProviderConfig.setServer:(Ljava/lang/String;)V
      21: aload_1
      22: aload_0
      23: invokevirtual #64                 // Method com/alibaba/dubbo/config/ProtocolConfig.getClient:()Ljava/lang/String;
      26: invokevirtual #65                 // Method com/alibaba/dubbo/config/ProviderConfig.setClient:(Ljava/lang/String;)V
      29: aload_1
      30: aload_0
      31: invokevirtual #66                 // Method com/alibaba/dubbo/config/ProtocolConfig.getCodec:()Ljava/lang/String;
      34: invokevirtual #67                 // Method com/alibaba/dubbo/config/ProviderConfig.setCodec:(Ljava/lang/String;)V
      37: aload_1
      38: aload_0
      39: invokevirtual #68                 // Method com/alibaba/dubbo/config/ProtocolConfig.getHost:()Ljava/lang/String;
      42: invokevirtual #69                 // Method com/alibaba/dubbo/config/ProviderConfig.setHost:(Ljava/lang/String;)V
      45: aload_1
      46: aload_0
      47: invokevirtual #70                 // Method com/alibaba/dubbo/config/ProtocolConfig.getPort:()Ljava/lang/Integer;
      50: invokevirtual #71                 // Method com/alibaba/dubbo/config/ProviderConfig.setPort:(Ljava/lang/Integer;)V
      53: aload_1
      54: aload_0
      55: invokevirtual #72                 // Method com/alibaba/dubbo/config/ProtocolConfig.getPath:()Ljava/lang/String;
      58: invokevirtual #73                 // Method com/alibaba/dubbo/config/ProviderConfig.setPath:(Ljava/lang/String;)V
      61: aload_1
      62: aload_0
      63: invokevirtual #74                 // Method com/alibaba/dubbo/config/ProtocolConfig.getPayload:()Ljava/lang/Integer;
      66: invokevirtual #75                 // Method com/alibaba/dubbo/config/ProviderConfig.setPayload:(Ljava/lang/Integer;)V
      69: aload_1
      70: aload_0
      71: invokevirtual #76                 // Method com/alibaba/dubbo/config/ProtocolConfig.getThreads:()Ljava/lang/Integer;
      74: invokevirtual #77                 // Method com/alibaba/dubbo/config/ProviderConfig.setThreads:(Ljava/lang/Integer;)V
      77: aload_1
      78: aload_0
      79: invokevirtual #78                 // Method com/alibaba/dubbo/config/ProtocolConfig.getParameters:()Ljava/util/Map;
      82: invokevirtual #79                 // Method com/alibaba/dubbo/config/ProviderConfig.setParameters:(Ljava/util/Map;)V
      85: aload_1
      86: areturn

  public org.apache.dubbo.config.MonitorConfig getMonitor();
    Code:
       0: aload_0
       1: invokevirtual #80                 // Method getMonitor:()Lcom/alibaba/dubbo/config/MonitorConfig;
       4: areturn
}
