Compiled from "CharacterSetECI.java"
public final class com.google.zxing.common.CharacterSetECI extends java.lang.Enum<com.google.zxing.common.CharacterSetECI> {
  public static final com.google.zxing.common.CharacterSetECI Cp437;

  public static final com.google.zxing.common.CharacterSetECI ISO8859_1;

  public static final com.google.zxing.common.CharacterSetECI ISO8859_2;

  public static final com.google.zxing.common.CharacterSetECI ISO8859_3;

  public static final com.google.zxing.common.CharacterSetECI ISO8859_4;

  public static final com.google.zxing.common.CharacterSetECI ISO8859_5;

  public static final com.google.zxing.common.CharacterSetECI ISO8859_7;

  public static final com.google.zxing.common.CharacterSetECI ISO8859_9;

  public static final com.google.zxing.common.CharacterSetECI ISO8859_13;

  public static final com.google.zxing.common.CharacterSetECI ISO8859_15;

  public static final com.google.zxing.common.CharacterSetECI ISO8859_16;

  public static final com.google.zxing.common.CharacterSetECI SJIS;

  public static final com.google.zxing.common.CharacterSetECI Cp1250;

  public static final com.google.zxing.common.CharacterSetECI Cp1251;

  public static final com.google.zxing.common.CharacterSetECI Cp1252;

  public static final com.google.zxing.common.CharacterSetECI Cp1256;

  public static final com.google.zxing.common.CharacterSetECI UnicodeBigUnmarked;

  public static final com.google.zxing.common.CharacterSetECI UTF8;

  public static final com.google.zxing.common.CharacterSetECI ASCII;

  public static final com.google.zxing.common.CharacterSetECI Big5;

  public static final com.google.zxing.common.CharacterSetECI GB18030;

  public static final com.google.zxing.common.CharacterSetECI EUC_KR;

  private static final java.util.Map<java.lang.Integer, com.google.zxing.common.CharacterSetECI> VALUE_TO_ECI;

  private static final java.util.Map<java.lang.String, com.google.zxing.common.CharacterSetECI> NAME_TO_ECI;

  private final int[] values;

  private final java.lang.String[] otherEncodingNames;

  private static final com.google.zxing.common.CharacterSetECI[] $VALUES;

  public static com.google.zxing.common.CharacterSetECI[] values();
    Code:
       0: getstatic     #1                  // Field $VALUES:[Lcom/google/zxing/common/CharacterSetECI;
       3: invokevirtual #2                  // Method "[Lcom/google/zxing/common/CharacterSetECI;".clone:()Ljava/lang/Object;
       6: checkcast     #3                  // class "[Lcom/google/zxing/common/CharacterSetECI;"
       9: areturn

  public static com.google.zxing.common.CharacterSetECI valueOf(java.lang.String);
    Code:
       0: ldc           #4                  // class com/google/zxing/common/CharacterSetECI
       2: aload_0
       3: invokestatic  #5                  // Method java/lang/Enum.valueOf:(Ljava/lang/Class;Ljava/lang/String;)Ljava/lang/Enum;
       6: checkcast     #4                  // class com/google/zxing/common/CharacterSetECI
       9: areturn

  private com.google.zxing.common.CharacterSetECI(int);
    Code:
       0: aload_0
       1: aload_1
       2: iload_2
       3: iconst_1
       4: newarray       int
       6: dup
       7: iconst_0
       8: iload_3
       9: iastore
      10: iconst_0
      11: anewarray     #6                  // class java/lang/String
      14: invokespecial #7                  // Method "<init>":(Ljava/lang/String;I[I[Ljava/lang/String;)V
      17: return

  private com.google.zxing.common.CharacterSetECI(int, java.lang.String...);
    Code:
       0: aload_0
       1: aload_1
       2: iload_2
       3: invokespecial #8                  // Method java/lang/Enum."<init>":(Ljava/lang/String;I)V
       6: aload_0
       7: iconst_1
       8: newarray       int
      10: dup
      11: iconst_0
      12: iload_3
      13: iastore
      14: putfield      #9                  // Field values:[I
      17: aload_0
      18: aload         4
      20: putfield      #10                 // Field otherEncodingNames:[Ljava/lang/String;
      23: return

  private com.google.zxing.common.CharacterSetECI(int[], java.lang.String...);
    Code:
       0: aload_0
       1: aload_1
       2: iload_2
       3: invokespecial #8                  // Method java/lang/Enum."<init>":(Ljava/lang/String;I)V
       6: aload_0
       7: aload_3
       8: putfield      #9                  // Field values:[I
      11: aload_0
      12: aload         4
      14: putfield      #10                 // Field otherEncodingNames:[Ljava/lang/String;
      17: return

  public int getValue();
    Code:
       0: aload_0
       1: getfield      #9                  // Field values:[I
       4: iconst_0
       5: iaload
       6: ireturn

  public java.nio.charset.Charset getCharset();
    Code:
       0: aload_0
       1: invokevirtual #11                 // Method name:()Ljava/lang/String;
       4: invokestatic  #12                 // Method java/nio/charset/Charset.forName:(Ljava/lang/String;)Ljava/nio/charset/Charset;
       7: areturn

  public static com.google.zxing.common.CharacterSetECI getCharacterSetECI(java.nio.charset.Charset);
    Code:
       0: getstatic     #13                 // Field NAME_TO_ECI:Ljava/util/Map;
       3: aload_0
       4: invokevirtual #14                 // Method java/nio/charset/Charset.name:()Ljava/lang/String;
       7: invokeinterface #15,  2           // InterfaceMethod java/util/Map.get:(Ljava/lang/Object;)Ljava/lang/Object;
      12: checkcast     #4                  // class com/google/zxing/common/CharacterSetECI
      15: areturn

  public static com.google.zxing.common.CharacterSetECI getCharacterSetECIByValue(int) throws com.google.zxing.FormatException;
    Code:
       0: iload_0
       1: iflt          11
       4: iload_0
       5: sipush        900
       8: if_icmplt     15
      11: invokestatic  #16                 // Method com/google/zxing/FormatException.getFormatInstance:()Lcom/google/zxing/FormatException;
      14: athrow
      15: getstatic     #17                 // Field VALUE_TO_ECI:Ljava/util/Map;
      18: iload_0
      19: invokestatic  #18                 // Method java/lang/Integer.valueOf:(I)Ljava/lang/Integer;
      22: invokeinterface #15,  2           // InterfaceMethod java/util/Map.get:(Ljava/lang/Object;)Ljava/lang/Object;
      27: checkcast     #4                  // class com/google/zxing/common/CharacterSetECI
      30: areturn

  public static com.google.zxing.common.CharacterSetECI getCharacterSetECIByName(java.lang.String);
    Code:
       0: getstatic     #13                 // Field NAME_TO_ECI:Ljava/util/Map;
       3: aload_0
       4: invokeinterface #15,  2           // InterfaceMethod java/util/Map.get:(Ljava/lang/Object;)Ljava/lang/Object;
       9: checkcast     #4                  // class com/google/zxing/common/CharacterSetECI
      12: areturn

  static {};
    Code:
       0: new           #4                  // class com/google/zxing/common/CharacterSetECI
       3: dup
       4: ldc           #19                 // String Cp437
       6: iconst_0
       7: iconst_2
       8: newarray       int
      10: dup
      11: iconst_0
      12: iconst_0
      13: iastore
      14: dup
      15: iconst_1
      16: iconst_2
      17: iastore
      18: iconst_0
      19: anewarray     #6                  // class java/lang/String
      22: invokespecial #7                  // Method "<init>":(Ljava/lang/String;I[I[Ljava/lang/String;)V
      25: putstatic     #20                 // Field Cp437:Lcom/google/zxing/common/CharacterSetECI;
      28: new           #4                  // class com/google/zxing/common/CharacterSetECI
      31: dup
      32: ldc           #21                 // String ISO8859_1
      34: iconst_1
      35: iconst_2
      36: newarray       int
      38: dup
      39: iconst_0
      40: iconst_1
      41: iastore
      42: dup
      43: iconst_1
      44: iconst_3
      45: iastore
      46: iconst_1
      47: anewarray     #6                  // class java/lang/String
      50: dup
      51: iconst_0
      52: ldc           #22                 // String ISO-8859-1
      54: aastore
      55: invokespecial #7                  // Method "<init>":(Ljava/lang/String;I[I[Ljava/lang/String;)V
      58: putstatic     #23                 // Field ISO8859_1:Lcom/google/zxing/common/CharacterSetECI;
      61: new           #4                  // class com/google/zxing/common/CharacterSetECI
      64: dup
      65: ldc           #24                 // String ISO8859_2
      67: iconst_2
      68: iconst_4
      69: iconst_1
      70: anewarray     #6                  // class java/lang/String
      73: dup
      74: iconst_0
      75: ldc           #25                 // String ISO-8859-2
      77: aastore
      78: invokespecial #26                 // Method "<init>":(Ljava/lang/String;II[Ljava/lang/String;)V
      81: putstatic     #27                 // Field ISO8859_2:Lcom/google/zxing/common/CharacterSetECI;
      84: new           #4                  // class com/google/zxing/common/CharacterSetECI
      87: dup
      88: ldc           #28                 // String ISO8859_3
      90: iconst_3
      91: iconst_5
      92: iconst_1
      93: anewarray     #6                  // class java/lang/String
      96: dup
      97: iconst_0
      98: ldc           #29                 // String ISO-8859-3
     100: aastore
     101: invokespecial #26                 // Method "<init>":(Ljava/lang/String;II[Ljava/lang/String;)V
     104: putstatic     #30                 // Field ISO8859_3:Lcom/google/zxing/common/CharacterSetECI;
     107: new           #4                  // class com/google/zxing/common/CharacterSetECI
     110: dup
     111: ldc           #31                 // String ISO8859_4
     113: iconst_4
     114: bipush        6
     116: iconst_1
     117: anewarray     #6                  // class java/lang/String
     120: dup
     121: iconst_0
     122: ldc           #32                 // String ISO-8859-4
     124: aastore
     125: invokespecial #26                 // Method "<init>":(Ljava/lang/String;II[Ljava/lang/String;)V
     128: putstatic     #33                 // Field ISO8859_4:Lcom/google/zxing/common/CharacterSetECI;
     131: new           #4                  // class com/google/zxing/common/CharacterSetECI
     134: dup
     135: ldc           #34                 // String ISO8859_5
     137: iconst_5
     138: bipush        7
     140: iconst_1
     141: anewarray     #6                  // class java/lang/String
     144: dup
     145: iconst_0
     146: ldc           #35                 // String ISO-8859-5
     148: aastore
     149: invokespecial #26                 // Method "<init>":(Ljava/lang/String;II[Ljava/lang/String;)V
     152: putstatic     #36                 // Field ISO8859_5:Lcom/google/zxing/common/CharacterSetECI;
     155: new           #4                  // class com/google/zxing/common/CharacterSetECI
     158: dup
     159: ldc           #37                 // String ISO8859_7
     161: bipush        6
     163: bipush        9
     165: iconst_1
     166: anewarray     #6                  // class java/lang/String
     169: dup
     170: iconst_0
     171: ldc           #38                 // String ISO-8859-7
     173: aastore
     174: invokespecial #26                 // Method "<init>":(Ljava/lang/String;II[Ljava/lang/String;)V
     177: putstatic     #39                 // Field ISO8859_7:Lcom/google/zxing/common/CharacterSetECI;
     180: new           #4                  // class com/google/zxing/common/CharacterSetECI
     183: dup
     184: ldc           #40                 // String ISO8859_9
     186: bipush        7
     188: bipush        11
     190: iconst_1
     191: anewarray     #6                  // class java/lang/String
     194: dup
     195: iconst_0
     196: ldc           #41                 // String ISO-8859-9
     198: aastore
     199: invokespecial #26                 // Method "<init>":(Ljava/lang/String;II[Ljava/lang/String;)V
     202: putstatic     #42                 // Field ISO8859_9:Lcom/google/zxing/common/CharacterSetECI;
     205: new           #4                  // class com/google/zxing/common/CharacterSetECI
     208: dup
     209: ldc           #43                 // String ISO8859_13
     211: bipush        8
     213: bipush        15
     215: iconst_1
     216: anewarray     #6                  // class java/lang/String
     219: dup
     220: iconst_0
     221: ldc           #44                 // String ISO-8859-13
     223: aastore
     224: invokespecial #26                 // Method "<init>":(Ljava/lang/String;II[Ljava/lang/String;)V
     227: putstatic     #45                 // Field ISO8859_13:Lcom/google/zxing/common/CharacterSetECI;
     230: new           #4                  // class com/google/zxing/common/CharacterSetECI
     233: dup
     234: ldc           #46                 // String ISO8859_15
     236: bipush        9
     238: bipush        17
     240: iconst_1
     241: anewarray     #6                  // class java/lang/String
     244: dup
     245: iconst_0
     246: ldc           #47                 // String ISO-8859-15
     248: aastore
     249: invokespecial #26                 // Method "<init>":(Ljava/lang/String;II[Ljava/lang/String;)V
     252: putstatic     #48                 // Field ISO8859_15:Lcom/google/zxing/common/CharacterSetECI;
     255: new           #4                  // class com/google/zxing/common/CharacterSetECI
     258: dup
     259: ldc           #49                 // String ISO8859_16
     261: bipush        10
     263: bipush        18
     265: iconst_1
     266: anewarray     #6                  // class java/lang/String
     269: dup
     270: iconst_0
     271: ldc           #50                 // String ISO-8859-16
     273: aastore
     274: invokespecial #26                 // Method "<init>":(Ljava/lang/String;II[Ljava/lang/String;)V
     277: putstatic     #51                 // Field ISO8859_16:Lcom/google/zxing/common/CharacterSetECI;
     280: new           #4                  // class com/google/zxing/common/CharacterSetECI
     283: dup
     284: ldc           #52                 // String SJIS
     286: bipush        11
     288: bipush        20
     290: iconst_1
     291: anewarray     #6                  // class java/lang/String
     294: dup
     295: iconst_0
     296: ldc           #53                 // String Shift_JIS
     298: aastore
     299: invokespecial #26                 // Method "<init>":(Ljava/lang/String;II[Ljava/lang/String;)V
     302: putstatic     #54                 // Field SJIS:Lcom/google/zxing/common/CharacterSetECI;
     305: new           #4                  // class com/google/zxing/common/CharacterSetECI
     308: dup
     309: ldc           #55                 // String Cp1250
     311: bipush        12
     313: bipush        21
     315: iconst_1
     316: anewarray     #6                  // class java/lang/String
     319: dup
     320: iconst_0
     321: ldc           #56                 // String windows-1250
     323: aastore
     324: invokespecial #26                 // Method "<init>":(Ljava/lang/String;II[Ljava/lang/String;)V
     327: putstatic     #57                 // Field Cp1250:Lcom/google/zxing/common/CharacterSetECI;
     330: new           #4                  // class com/google/zxing/common/CharacterSetECI
     333: dup
     334: ldc           #58                 // String Cp1251
     336: bipush        13
     338: bipush        22
     340: iconst_1
     341: anewarray     #6                  // class java/lang/String
     344: dup
     345: iconst_0
     346: ldc           #59                 // String windows-1251
     348: aastore
     349: invokespecial #26                 // Method "<init>":(Ljava/lang/String;II[Ljava/lang/String;)V
     352: putstatic     #60                 // Field Cp1251:Lcom/google/zxing/common/CharacterSetECI;
     355: new           #4                  // class com/google/zxing/common/CharacterSetECI
     358: dup
     359: ldc           #61                 // String Cp1252
     361: bipush        14
     363: bipush        23
     365: iconst_1
     366: anewarray     #6                  // class java/lang/String
     369: dup
     370: iconst_0
     371: ldc           #62                 // String windows-1252
     373: aastore
     374: invokespecial #26                 // Method "<init>":(Ljava/lang/String;II[Ljava/lang/String;)V
     377: putstatic     #63                 // Field Cp1252:Lcom/google/zxing/common/CharacterSetECI;
     380: new           #4                  // class com/google/zxing/common/CharacterSetECI
     383: dup
     384: ldc           #64                 // String Cp1256
     386: bipush        15
     388: bipush        24
     390: iconst_1
     391: anewarray     #6                  // class java/lang/String
     394: dup
     395: iconst_0
     396: ldc           #65                 // String windows-1256
     398: aastore
     399: invokespecial #26                 // Method "<init>":(Ljava/lang/String;II[Ljava/lang/String;)V
     402: putstatic     #66                 // Field Cp1256:Lcom/google/zxing/common/CharacterSetECI;
     405: new           #4                  // class com/google/zxing/common/CharacterSetECI
     408: dup
     409: ldc           #67                 // String UnicodeBigUnmarked
     411: bipush        16
     413: bipush        25
     415: iconst_2
     416: anewarray     #6                  // class java/lang/String
     419: dup
     420: iconst_0
     421: ldc           #68                 // String UTF-16BE
     423: aastore
     424: dup
     425: iconst_1
     426: ldc           #69                 // String UnicodeBig
     428: aastore
     429: invokespecial #26                 // Method "<init>":(Ljava/lang/String;II[Ljava/lang/String;)V
     432: putstatic     #70                 // Field UnicodeBigUnmarked:Lcom/google/zxing/common/CharacterSetECI;
     435: new           #4                  // class com/google/zxing/common/CharacterSetECI
     438: dup
     439: ldc           #71                 // String UTF8
     441: bipush        17
     443: bipush        26
     445: iconst_1
     446: anewarray     #6                  // class java/lang/String
     449: dup
     450: iconst_0
     451: ldc           #72                 // String UTF-8
     453: aastore
     454: invokespecial #26                 // Method "<init>":(Ljava/lang/String;II[Ljava/lang/String;)V
     457: putstatic     #73                 // Field UTF8:Lcom/google/zxing/common/CharacterSetECI;
     460: new           #4                  // class com/google/zxing/common/CharacterSetECI
     463: dup
     464: ldc           #74                 // String ASCII
     466: bipush        18
     468: iconst_2
     469: newarray       int
     471: dup
     472: iconst_0
     473: bipush        27
     475: iastore
     476: dup
     477: iconst_1
     478: sipush        170
     481: iastore
     482: iconst_1
     483: anewarray     #6                  // class java/lang/String
     486: dup
     487: iconst_0
     488: ldc           #75                 // String US-ASCII
     490: aastore
     491: invokespecial #7                  // Method "<init>":(Ljava/lang/String;I[I[Ljava/lang/String;)V
     494: putstatic     #76                 // Field ASCII:Lcom/google/zxing/common/CharacterSetECI;
     497: new           #4                  // class com/google/zxing/common/CharacterSetECI
     500: dup
     501: ldc           #77                 // String Big5
     503: bipush        19
     505: bipush        28
     507: invokespecial #78                 // Method "<init>":(Ljava/lang/String;II)V
     510: putstatic     #79                 // Field Big5:Lcom/google/zxing/common/CharacterSetECI;
     513: new           #4                  // class com/google/zxing/common/CharacterSetECI
     516: dup
     517: ldc           #80                 // String GB18030
     519: bipush        20
     521: bipush        29
     523: iconst_3
     524: anewarray     #6                  // class java/lang/String
     527: dup
     528: iconst_0
     529: ldc           #81                 // String GB2312
     531: aastore
     532: dup
     533: iconst_1
     534: ldc           #82                 // String EUC_CN
     536: aastore
     537: dup
     538: iconst_2
     539: ldc           #83                 // String GBK
     541: aastore
     542: invokespecial #26                 // Method "<init>":(Ljava/lang/String;II[Ljava/lang/String;)V
     545: putstatic     #84                 // Field GB18030:Lcom/google/zxing/common/CharacterSetECI;
     548: new           #4                  // class com/google/zxing/common/CharacterSetECI
     551: dup
     552: ldc           #85                 // String EUC_KR
     554: bipush        21
     556: bipush        30
     558: iconst_1
     559: anewarray     #6                  // class java/lang/String
     562: dup
     563: iconst_0
     564: ldc           #86                 // String EUC-KR
     566: aastore
     567: invokespecial #26                 // Method "<init>":(Ljava/lang/String;II[Ljava/lang/String;)V
     570: putstatic     #87                 // Field EUC_KR:Lcom/google/zxing/common/CharacterSetECI;
     573: bipush        22
     575: anewarray     #4                  // class com/google/zxing/common/CharacterSetECI
     578: dup
     579: iconst_0
     580: getstatic     #20                 // Field Cp437:Lcom/google/zxing/common/CharacterSetECI;
     583: aastore
     584: dup
     585: iconst_1
     586: getstatic     #23                 // Field ISO8859_1:Lcom/google/zxing/common/CharacterSetECI;
     589: aastore
     590: dup
     591: iconst_2
     592: getstatic     #27                 // Field ISO8859_2:Lcom/google/zxing/common/CharacterSetECI;
     595: aastore
     596: dup
     597: iconst_3
     598: getstatic     #30                 // Field ISO8859_3:Lcom/google/zxing/common/CharacterSetECI;
     601: aastore
     602: dup
     603: iconst_4
     604: getstatic     #33                 // Field ISO8859_4:Lcom/google/zxing/common/CharacterSetECI;
     607: aastore
     608: dup
     609: iconst_5
     610: getstatic     #36                 // Field ISO8859_5:Lcom/google/zxing/common/CharacterSetECI;
     613: aastore
     614: dup
     615: bipush        6
     617: getstatic     #39                 // Field ISO8859_7:Lcom/google/zxing/common/CharacterSetECI;
     620: aastore
     621: dup
     622: bipush        7
     624: getstatic     #42                 // Field ISO8859_9:Lcom/google/zxing/common/CharacterSetECI;
     627: aastore
     628: dup
     629: bipush        8
     631: getstatic     #45                 // Field ISO8859_13:Lcom/google/zxing/common/CharacterSetECI;
     634: aastore
     635: dup
     636: bipush        9
     638: getstatic     #48                 // Field ISO8859_15:Lcom/google/zxing/common/CharacterSetECI;
     641: aastore
     642: dup
     643: bipush        10
     645: getstatic     #51                 // Field ISO8859_16:Lcom/google/zxing/common/CharacterSetECI;
     648: aastore
     649: dup
     650: bipush        11
     652: getstatic     #54                 // Field SJIS:Lcom/google/zxing/common/CharacterSetECI;
     655: aastore
     656: dup
     657: bipush        12
     659: getstatic     #57                 // Field Cp1250:Lcom/google/zxing/common/CharacterSetECI;
     662: aastore
     663: dup
     664: bipush        13
     666: getstatic     #60                 // Field Cp1251:Lcom/google/zxing/common/CharacterSetECI;
     669: aastore
     670: dup
     671: bipush        14
     673: getstatic     #63                 // Field Cp1252:Lcom/google/zxing/common/CharacterSetECI;
     676: aastore
     677: dup
     678: bipush        15
     680: getstatic     #66                 // Field Cp1256:Lcom/google/zxing/common/CharacterSetECI;
     683: aastore
     684: dup
     685: bipush        16
     687: getstatic     #70                 // Field UnicodeBigUnmarked:Lcom/google/zxing/common/CharacterSetECI;
     690: aastore
     691: dup
     692: bipush        17
     694: getstatic     #73                 // Field UTF8:Lcom/google/zxing/common/CharacterSetECI;
     697: aastore
     698: dup
     699: bipush        18
     701: getstatic     #76                 // Field ASCII:Lcom/google/zxing/common/CharacterSetECI;
     704: aastore
     705: dup
     706: bipush        19
     708: getstatic     #79                 // Field Big5:Lcom/google/zxing/common/CharacterSetECI;
     711: aastore
     712: dup
     713: bipush        20
     715: getstatic     #84                 // Field GB18030:Lcom/google/zxing/common/CharacterSetECI;
     718: aastore
     719: dup
     720: bipush        21
     722: getstatic     #87                 // Field EUC_KR:Lcom/google/zxing/common/CharacterSetECI;
     725: aastore
     726: putstatic     #1                  // Field $VALUES:[Lcom/google/zxing/common/CharacterSetECI;
     729: new           #88                 // class java/util/HashMap
     732: dup
     733: invokespecial #89                 // Method java/util/HashMap."<init>":()V
     736: putstatic     #17                 // Field VALUE_TO_ECI:Ljava/util/Map;
     739: new           #88                 // class java/util/HashMap
     742: dup
     743: invokespecial #89                 // Method java/util/HashMap."<init>":()V
     746: putstatic     #13                 // Field NAME_TO_ECI:Ljava/util/Map;
     749: invokestatic  #90                 // Method values:()[Lcom/google/zxing/common/CharacterSetECI;
     752: astore_0
     753: aload_0
     754: arraylength
     755: istore_1
     756: iconst_0
     757: istore_2
     758: iload_2
     759: iload_1
     760: if_icmpge     882
     763: aload_0
     764: iload_2
     765: aaload
     766: astore_3
     767: aload_3
     768: getfield      #9                  // Field values:[I
     771: astore        4
     773: aload         4
     775: arraylength
     776: istore        5
     778: iconst_0
     779: istore        6
     781: iload         6
     783: iload         5
     785: if_icmpge     816
     788: aload         4
     790: iload         6
     792: iaload
     793: istore        7
     795: getstatic     #17                 // Field VALUE_TO_ECI:Ljava/util/Map;
     798: iload         7
     800: invokestatic  #18                 // Method java/lang/Integer.valueOf:(I)Ljava/lang/Integer;
     803: aload_3
     804: invokeinterface #91,  3           // InterfaceMethod java/util/Map.put:(Ljava/lang/Object;Ljava/lang/Object;)Ljava/lang/Object;
     809: pop
     810: iinc          6, 1
     813: goto          781
     816: getstatic     #13                 // Field NAME_TO_ECI:Ljava/util/Map;
     819: aload_3
     820: invokevirtual #11                 // Method name:()Ljava/lang/String;
     823: aload_3
     824: invokeinterface #91,  3           // InterfaceMethod java/util/Map.put:(Ljava/lang/Object;Ljava/lang/Object;)Ljava/lang/Object;
     829: pop
     830: aload_3
     831: getfield      #10                 // Field otherEncodingNames:[Ljava/lang/String;
     834: astore        4
     836: aload         4
     838: arraylength
     839: istore        5
     841: iconst_0
     842: istore        6
     844: iload         6
     846: iload         5
     848: if_icmpge     876
     851: aload         4
     853: iload         6
     855: aaload
     856: astore        7
     858: getstatic     #13                 // Field NAME_TO_ECI:Ljava/util/Map;
     861: aload         7
     863: aload_3
     864: invokeinterface #91,  3           // InterfaceMethod java/util/Map.put:(Ljava/lang/Object;Ljava/lang/Object;)Ljava/lang/Object;
     869: pop
     870: iinc          6, 1
     873: goto          844
     876: iinc          2, 1
     879: goto          758
     882: return
}
