Compiled from "DecoderResult.java"
public final class com.google.zxing.common.DecoderResult {
  private final byte[] rawBytes;

  private int numBits;

  private final java.lang.String text;

  private final java.util.List<byte[]> byteSegments;

  private final java.lang.String ecLevel;

  private java.lang.Integer errorsCorrected;

  private java.lang.Integer erasures;

  private java.lang.Object other;

  private final int structuredAppendParity;

  private final int structuredAppendSequenceNumber;

  private final int symbologyModifier;

  public com.google.zxing.common.DecoderResult(byte[], java.lang.String, java.util.List<byte[]>, java.lang.String);
    Code:
       0: aload_0
       1: aload_1
       2: aload_2
       3: aload_3
       4: aload         4
       6: iconst_m1
       7: iconst_m1
       8: iconst_0
       9: invokespecial #1                  // Method "<init>":([BLjava/lang/String;Ljava/util/List;Ljava/lang/String;III)V
      12: return

  public com.google.zxing.common.DecoderResult(byte[], java.lang.String, java.util.List<byte[]>, java.lang.String, int);
    Code:
       0: aload_0
       1: aload_1
       2: aload_2
       3: aload_3
       4: aload         4
       6: iconst_m1
       7: iconst_m1
       8: iload         5
      10: invokespecial #1                  // Method "<init>":([BLjava/lang/String;Ljava/util/List;Ljava/lang/String;III)V
      13: return

  public com.google.zxing.common.DecoderResult(byte[], java.lang.String, java.util.List<byte[]>, java.lang.String, int, int);
    Code:
       0: aload_0
       1: aload_1
       2: aload_2
       3: aload_3
       4: aload         4
       6: iload         5
       8: iload         6
      10: iconst_0
      11: invokespecial #1                  // Method "<init>":([BLjava/lang/String;Ljava/util/List;Ljava/lang/String;III)V
      14: return

  public com.google.zxing.common.DecoderResult(byte[], java.lang.String, java.util.List<byte[]>, java.lang.String, int, int, int);
    Code:
       0: aload_0
       1: invokespecial #2                  // Method java/lang/Object."<init>":()V
       4: aload_0
       5: aload_1
       6: putfield      #3                  // Field rawBytes:[B
       9: aload_0
      10: aload_1
      11: ifnonnull     18
      14: iconst_0
      15: goto          23
      18: bipush        8
      20: aload_1
      21: arraylength
      22: imul
      23: putfield      #4                  // Field numBits:I
      26: aload_0
      27: aload_2
      28: putfield      #5                  // Field text:Ljava/lang/String;
      31: aload_0
      32: aload_3
      33: putfield      #6                  // Field byteSegments:Ljava/util/List;
      36: aload_0
      37: aload         4
      39: putfield      #7                  // Field ecLevel:Ljava/lang/String;
      42: aload_0
      43: iload         6
      45: putfield      #8                  // Field structuredAppendParity:I
      48: aload_0
      49: iload         5
      51: putfield      #9                  // Field structuredAppendSequenceNumber:I
      54: aload_0
      55: iload         7
      57: putfield      #10                 // Field symbologyModifier:I
      60: return

  public byte[] getRawBytes();
    Code:
       0: aload_0
       1: getfield      #3                  // Field rawBytes:[B
       4: areturn

  public int getNumBits();
    Code:
       0: aload_0
       1: getfield      #4                  // Field numBits:I
       4: ireturn

  public void setNumBits(int);
    Code:
       0: aload_0
       1: iload_1
       2: putfield      #4                  // Field numBits:I
       5: return

  public java.lang.String getText();
    Code:
       0: aload_0
       1: getfield      #5                  // Field text:Ljava/lang/String;
       4: areturn

  public java.util.List<byte[]> getByteSegments();
    Code:
       0: aload_0
       1: getfield      #6                  // Field byteSegments:Ljava/util/List;
       4: areturn

  public java.lang.String getECLevel();
    Code:
       0: aload_0
       1: getfield      #7                  // Field ecLevel:Ljava/lang/String;
       4: areturn

  public java.lang.Integer getErrorsCorrected();
    Code:
       0: aload_0
       1: getfield      #11                 // Field errorsCorrected:Ljava/lang/Integer;
       4: areturn

  public void setErrorsCorrected(java.lang.Integer);
    Code:
       0: aload_0
       1: aload_1
       2: putfield      #11                 // Field errorsCorrected:Ljava/lang/Integer;
       5: return

  public java.lang.Integer getErasures();
    Code:
       0: aload_0
       1: getfield      #12                 // Field erasures:Ljava/lang/Integer;
       4: areturn

  public void setErasures(java.lang.Integer);
    Code:
       0: aload_0
       1: aload_1
       2: putfield      #12                 // Field erasures:Ljava/lang/Integer;
       5: return

  public java.lang.Object getOther();
    Code:
       0: aload_0
       1: getfield      #13                 // Field other:Ljava/lang/Object;
       4: areturn

  public void setOther(java.lang.Object);
    Code:
       0: aload_0
       1: aload_1
       2: putfield      #13                 // Field other:Ljava/lang/Object;
       5: return

  public boolean hasStructuredAppend();
    Code:
       0: aload_0
       1: getfield      #8                  // Field structuredAppendParity:I
       4: iflt          18
       7: aload_0
       8: getfield      #9                  // Field structuredAppendSequenceNumber:I
      11: iflt          18
      14: iconst_1
      15: goto          19
      18: iconst_0
      19: ireturn

  public int getStructuredAppendParity();
    Code:
       0: aload_0
       1: getfield      #8                  // Field structuredAppendParity:I
       4: ireturn

  public int getStructuredAppendSequenceNumber();
    Code:
       0: aload_0
       1: getfield      #9                  // Field structuredAppendSequenceNumber:I
       4: ireturn

  public int getSymbologyModifier();
    Code:
       0: aload_0
       1: getfield      #10                 // Field symbologyModifier:I
       4: ireturn
}
