Compiled from "DetectorResult.java"
public class com.google.zxing.common.DetectorResult {
  private final com.google.zxing.common.BitMatrix bits;

  private final com.google.zxing.ResultPoint[] points;

  public com.google.zxing.common.DetectorResult(com.google.zxing.common.BitMatrix, com.google.zxing.ResultPoint[]);
    Code:
       0: aload_0
       1: invokespecial #1                  // Method java/lang/Object."<init>":()V
       4: aload_0
       5: aload_1
       6: putfield      #2                  // Field bits:Lcom/google/zxing/common/BitMatrix;
       9: aload_0
      10: aload_2
      11: putfield      #3                  // Field points:[Lcom/google/zxing/ResultPoint;
      14: return

  public final com.google.zxing.common.BitMatrix getBits();
    Code:
       0: aload_0
       1: getfield      #2                  // Field bits:Lcom/google/zxing/common/BitMatrix;
       4: areturn

  public final com.google.zxing.ResultPoint[] getPoints();
    Code:
       0: aload_0
       1: getfield      #3                  // Field points:[Lcom/google/zxing/ResultPoint;
       4: areturn
}
