Compiled from "ECIStringBuilder.java"
public final class com.google.zxing.common.ECIStringBuilder {
  private java.lang.StringBuilder currentBytes;

  private java.lang.StringBuilder result;

  private java.nio.charset.Charset currentCharset;

  public com.google.zxing.common.ECIStringBuilder();
    Code:
       0: aload_0
       1: invokespecial #1                  // Method java/lang/Object."<init>":()V
       4: aload_0
       5: getstatic     #2                  // Field java/nio/charset/StandardCharsets.ISO_8859_1:Ljava/nio/charset/Charset;
       8: putfield      #3                  // Field currentCharset:Ljava/nio/charset/Charset;
      11: aload_0
      12: new           #4                  // class java/lang/StringBuilder
      15: dup
      16: invokespecial #5                  // Method java/lang/StringBuilder."<init>":()V
      19: putfield      #6                  // Field currentBytes:Ljava/lang/StringBuilder;
      22: return

  public com.google.zxing.common.ECIStringBuilder(int);
    Code:
       0: aload_0
       1: invokespecial #1                  // Method java/lang/Object."<init>":()V
       4: aload_0
       5: getstatic     #2                  // Field java/nio/charset/StandardCharsets.ISO_8859_1:Ljava/nio/charset/Charset;
       8: putfield      #3                  // Field currentCharset:Ljava/nio/charset/Charset;
      11: aload_0
      12: new           #4                  // class java/lang/StringBuilder
      15: dup
      16: iload_1
      17: invokespecial #7                  // Method java/lang/StringBuilder."<init>":(I)V
      20: putfield      #6                  // Field currentBytes:Ljava/lang/StringBuilder;
      23: return

  public void append(char);
    Code:
       0: aload_0
       1: getfield      #6                  // Field currentBytes:Ljava/lang/StringBuilder;
       4: iload_1
       5: sipush        255
       8: iand
       9: i2c
      10: invokevirtual #8                  // Method java/lang/StringBuilder.append:(C)Ljava/lang/StringBuilder;
      13: pop
      14: return

  public void append(byte);
    Code:
       0: aload_0
       1: getfield      #6                  // Field currentBytes:Ljava/lang/StringBuilder;
       4: iload_1
       5: sipush        255
       8: iand
       9: i2c
      10: invokevirtual #8                  // Method java/lang/StringBuilder.append:(C)Ljava/lang/StringBuilder;
      13: pop
      14: return

  public void append(java.lang.String);
    Code:
       0: aload_0
       1: getfield      #6                  // Field currentBytes:Ljava/lang/StringBuilder;
       4: aload_1
       5: invokevirtual #9                  // Method java/lang/StringBuilder.append:(Ljava/lang/String;)Ljava/lang/StringBuilder;
       8: pop
       9: return

  public void append(int);
    Code:
       0: aload_0
       1: iload_1
       2: invokestatic  #10                 // Method java/lang/String.valueOf:(I)Ljava/lang/String;
       5: invokevirtual #11                 // Method append:(Ljava/lang/String;)V
       8: return

  public void appendECI(int) throws com.google.zxing.FormatException;
    Code:
       0: aload_0
       1: invokespecial #12                 // Method encodeCurrentBytesIfAny:()V
       4: iload_1
       5: invokestatic  #13                 // Method com/google/zxing/common/CharacterSetECI.getCharacterSetECIByValue:(I)Lcom/google/zxing/common/CharacterSetECI;
       8: astore_2
       9: aload_2
      10: ifnonnull     17
      13: invokestatic  #14                 // Method com/google/zxing/FormatException.getFormatInstance:()Lcom/google/zxing/FormatException;
      16: athrow
      17: aload_0
      18: aload_2
      19: invokevirtual #15                 // Method com/google/zxing/common/CharacterSetECI.getCharset:()Ljava/nio/charset/Charset;
      22: putfield      #3                  // Field currentCharset:Ljava/nio/charset/Charset;
      25: return

  private void encodeCurrentBytesIfAny();
    Code:
       0: aload_0
       1: getfield      #3                  // Field currentCharset:Ljava/nio/charset/Charset;
       4: getstatic     #2                  // Field java/nio/charset/StandardCharsets.ISO_8859_1:Ljava/nio/charset/Charset;
       7: invokevirtual #16                 // Method java/nio/charset/Charset.equals:(Ljava/lang/Object;)Z
      10: ifeq          78
      13: aload_0
      14: getfield      #6                  // Field currentBytes:Ljava/lang/StringBuilder;
      17: invokevirtual #17                 // Method java/lang/StringBuilder.length:()I
      20: ifle          166
      23: aload_0
      24: getfield      #18                 // Field result:Ljava/lang/StringBuilder;
      27: ifnonnull     52
      30: aload_0
      31: aload_0
      32: getfield      #6                  // Field currentBytes:Ljava/lang/StringBuilder;
      35: putfield      #18                 // Field result:Ljava/lang/StringBuilder;
      38: aload_0
      39: new           #4                  // class java/lang/StringBuilder
      42: dup
      43: invokespecial #5                  // Method java/lang/StringBuilder."<init>":()V
      46: putfield      #6                  // Field currentBytes:Ljava/lang/StringBuilder;
      49: goto          166
      52: aload_0
      53: getfield      #18                 // Field result:Ljava/lang/StringBuilder;
      56: aload_0
      57: getfield      #6                  // Field currentBytes:Ljava/lang/StringBuilder;
      60: invokevirtual #19                 // Method java/lang/StringBuilder.append:(Ljava/lang/CharSequence;)Ljava/lang/StringBuilder;
      63: pop
      64: aload_0
      65: new           #4                  // class java/lang/StringBuilder
      68: dup
      69: invokespecial #5                  // Method java/lang/StringBuilder."<init>":()V
      72: putfield      #6                  // Field currentBytes:Ljava/lang/StringBuilder;
      75: goto          166
      78: aload_0
      79: getfield      #6                  // Field currentBytes:Ljava/lang/StringBuilder;
      82: invokevirtual #17                 // Method java/lang/StringBuilder.length:()I
      85: ifle          166
      88: aload_0
      89: getfield      #6                  // Field currentBytes:Ljava/lang/StringBuilder;
      92: invokevirtual #20                 // Method java/lang/StringBuilder.toString:()Ljava/lang/String;
      95: getstatic     #2                  // Field java/nio/charset/StandardCharsets.ISO_8859_1:Ljava/nio/charset/Charset;
      98: invokevirtual #21                 // Method java/lang/String.getBytes:(Ljava/nio/charset/Charset;)[B
     101: astore_1
     102: aload_0
     103: new           #4                  // class java/lang/StringBuilder
     106: dup
     107: invokespecial #5                  // Method java/lang/StringBuilder."<init>":()V
     110: putfield      #6                  // Field currentBytes:Ljava/lang/StringBuilder;
     113: aload_0
     114: getfield      #18                 // Field result:Ljava/lang/StringBuilder;
     117: ifnonnull     146
     120: aload_0
     121: new           #4                  // class java/lang/StringBuilder
     124: dup
     125: new           #22                 // class java/lang/String
     128: dup
     129: aload_1
     130: aload_0
     131: getfield      #3                  // Field currentCharset:Ljava/nio/charset/Charset;
     134: invokespecial #23                 // Method java/lang/String."<init>":([BLjava/nio/charset/Charset;)V
     137: invokespecial #24                 // Method java/lang/StringBuilder."<init>":(Ljava/lang/String;)V
     140: putfield      #18                 // Field result:Ljava/lang/StringBuilder;
     143: goto          166
     146: aload_0
     147: getfield      #18                 // Field result:Ljava/lang/StringBuilder;
     150: new           #22                 // class java/lang/String
     153: dup
     154: aload_1
     155: aload_0
     156: getfield      #3                  // Field currentCharset:Ljava/nio/charset/Charset;
     159: invokespecial #23                 // Method java/lang/String."<init>":([BLjava/nio/charset/Charset;)V
     162: invokevirtual #9                  // Method java/lang/StringBuilder.append:(Ljava/lang/String;)Ljava/lang/StringBuilder;
     165: pop
     166: return

  public void appendCharacters(java.lang.StringBuilder);
    Code:
       0: aload_0
       1: invokespecial #12                 // Method encodeCurrentBytesIfAny:()V
       4: aload_0
       5: getfield      #18                 // Field result:Ljava/lang/StringBuilder;
       8: aload_1
       9: invokevirtual #19                 // Method java/lang/StringBuilder.append:(Ljava/lang/CharSequence;)Ljava/lang/StringBuilder;
      12: pop
      13: return

  public int length();
    Code:
       0: aload_0
       1: invokevirtual #25                 // Method toString:()Ljava/lang/String;
       4: invokevirtual #26                 // Method java/lang/String.length:()I
       7: ireturn

  public boolean isEmpty();
    Code:
       0: aload_0
       1: getfield      #6                  // Field currentBytes:Ljava/lang/StringBuilder;
       4: invokevirtual #17                 // Method java/lang/StringBuilder.length:()I
       7: ifne          31
      10: aload_0
      11: getfield      #18                 // Field result:Ljava/lang/StringBuilder;
      14: ifnull        27
      17: aload_0
      18: getfield      #18                 // Field result:Ljava/lang/StringBuilder;
      21: invokevirtual #17                 // Method java/lang/StringBuilder.length:()I
      24: ifne          31
      27: iconst_1
      28: goto          32
      31: iconst_0
      32: ireturn

  public java.lang.String toString();
    Code:
       0: aload_0
       1: invokespecial #12                 // Method encodeCurrentBytesIfAny:()V
       4: aload_0
       5: getfield      #18                 // Field result:Ljava/lang/StringBuilder;
       8: ifnonnull     16
      11: ldc           #27                 // String
      13: goto          23
      16: aload_0
      17: getfield      #18                 // Field result:Ljava/lang/StringBuilder;
      20: invokevirtual #20                 // Method java/lang/StringBuilder.toString:()Ljava/lang/String;
      23: areturn
}
