Compiled from "MinimalECIInput.java"
final class com.google.zxing.common.MinimalECIInput$InputEdge {
  private final char c;

  private final int encoderIndex;

  private final com.google.zxing.common.MinimalECIInput$InputEdge previous;

  private final int cachedTotalSize;

  private com.google.zxing.common.MinimalECIInput$InputEdge(char, com.google.zxing.common.ECIEncoderSet, int, com.google.zxing.common.MinimalECIInput$InputEdge, int);
    Code:
       0: aload_0
       1: invokespecial #7                  // Method java/lang/Object."<init>":()V
       4: aload_0
       5: iload_1
       6: iload         5
       8: if_icmpne     17
      11: sipush        1000
      14: goto          18
      17: iload_1
      18: putfield      #3                  // Field c:C
      21: aload_0
      22: iload_3
      23: putfield      #6                  // Field encoderIndex:I
      26: aload_0
      27: aload         4
      29: putfield      #2                  // Field previous:Lcom/google/zxing/common/MinimalECIInput$InputEdge;
      32: aload_0
      33: getfield      #3                  // Field c:C
      36: sipush        1000
      39: if_icmpne     46
      42: iconst_1
      43: goto          53
      46: aload_2
      47: iload_1
      48: iload_3
      49: invokevirtual #8                  // Method com/google/zxing/common/ECIEncoderSet.encode:(CI)[B
      52: arraylength
      53: istore        6
      55: aload         4
      57: ifnonnull     64
      60: iconst_0
      61: goto          69
      64: aload         4
      66: getfield      #6                  // Field encoderIndex:I
      69: istore        7
      71: iload         7
      73: iload_3
      74: if_icmpeq     80
      77: iinc          6, 3
      80: aload         4
      82: ifnull        95
      85: iload         6
      87: aload         4
      89: getfield      #5                  // Field cachedTotalSize:I
      92: iadd
      93: istore        6
      95: aload_0
      96: iload         6
      98: putfield      #5                  // Field cachedTotalSize:I
     101: return

  boolean isFNC1();
    Code:
       0: aload_0
       1: getfield      #3                  // Field c:C
       4: sipush        1000
       7: if_icmpne     14
      10: iconst_1
      11: goto          15
      14: iconst_0
      15: ireturn

  static int access$000(com.google.zxing.common.MinimalECIInput$InputEdge);
    Code:
       0: aload_0
       1: getfield      #6                  // Field encoderIndex:I
       4: ireturn

  static int access$100(com.google.zxing.common.MinimalECIInput$InputEdge);
    Code:
       0: aload_0
       1: getfield      #5                  // Field cachedTotalSize:I
       4: ireturn

  com.google.zxing.common.MinimalECIInput$InputEdge(char, com.google.zxing.common.ECIEncoderSet, int, com.google.zxing.common.MinimalECIInput$InputEdge, int, com.google.zxing.common.MinimalECIInput$1);
    Code:
       0: aload_0
       1: iload_1
       2: aload_2
       3: iload_3
       4: aload         4
       6: iload         5
       8: invokespecial #4                  // Method "<init>":(CLcom/google/zxing/common/ECIEncoderSet;ILcom/google/zxing/common/MinimalECIInput$InputEdge;I)V
      11: return

  static char access$300(com.google.zxing.common.MinimalECIInput$InputEdge);
    Code:
       0: aload_0
       1: getfield      #3                  // Field c:C
       4: ireturn

  static com.google.zxing.common.MinimalECIInput$InputEdge access$400(com.google.zxing.common.MinimalECIInput$InputEdge);
    Code:
       0: aload_0
       1: getfield      #2                  // Field previous:Lcom/google/zxing/common/MinimalECIInput$InputEdge;
       4: areturn
}
