Compiled from "Hashing.java"
final class com.google.common.hash.Hashing$Crc32CSupplier$1 extends com.google.common.hash.Hashing$Crc32CSupplier {
  com.google.common.hash.Hashing$Crc32CSupplier$1(java.lang.String, int);
    Code:
       0: aload_0
       1: aload_1
       2: iload_2
       3: aconst_null
       4: invokespecial #1                  // Method com/google/common/hash/Hashing$Crc32CSupplier."<init>":(Ljava/lang/String;ILcom/google/common/hash/Hashing$1;)V
       7: return

  public com.google.common.hash.HashFunction get();
    Code:
       0: getstatic     #2                  // Field com/google/common/hash/Crc32cHashFunction.CRC_32_C:Lcom/google/common/hash/HashFunction;
       3: areturn

  public java.lang.Object get();
    Code:
       0: aload_0
       1: invokevirtual #3                  // Method get:()Lcom/google/common/hash/HashFunction;
       4: areturn
}
