Compiled from "Hashing.java"
abstract class com.google.common.hash.Hashing$Crc32CSupplier extends java.lang.Enum<com.google.common.hash.Hashing$Crc32CSupplier> implements com.google.common.hash.ImmutableSupplier<com.google.common.hash.HashFunction> {
  public static final com.google.common.hash.Hashing$Crc32CSupplier ABSTRACT_HASH_FUNCTION;

  static final com.google.common.hash.HashFunction HASH_FUNCTION;

  private static final com.google.common.hash.Hashing$Crc32CSupplier[] $VALUES;

  public static com.google.common.hash.Hashing$Crc32CSupplier[] values();
    Code:
       0: getstatic     #4                  // Field $VALUES:[Lcom/google/common/hash/Hashing$Crc32CSupplier;
       3: invokevirtual #5                  // Method "[Lcom/google/common/hash/Hashing$Crc32CSupplier;".clone:()Ljava/lang/Object;
       6: checkcast     #6                  // class "[Lcom/google/common/hash/Hashing$Crc32CSupplier;"
       9: areturn

  public static com.google.common.hash.Hashing$Crc32CSupplier valueOf(java.lang.String);
    Code:
       0: ldc           #2                  // class com/google/common/hash/Hashing$Crc32CSupplier
       2: aload_0
       3: invokestatic  #7                  // Method java/lang/Enum.valueOf:(Ljava/lang/Class;Ljava/lang/String;)Ljava/lang/Enum;
       6: checkcast     #2                  // class com/google/common/hash/Hashing$Crc32CSupplier
       9: areturn

  private com.google.common.hash.Hashing$Crc32CSupplier();
    Code:
       0: aload_0
       1: aload_1
       2: iload_2
       3: invokespecial #8                  // Method java/lang/Enum."<init>":(Ljava/lang/String;I)V
       6: return

  private static com.google.common.hash.Hashing$Crc32CSupplier[] $values();
    Code:
       0: iconst_1
       1: anewarray     #2                  // class com/google/common/hash/Hashing$Crc32CSupplier
       4: dup
       5: iconst_0
       6: getstatic     #3                  // Field ABSTRACT_HASH_FUNCTION:Lcom/google/common/hash/Hashing$Crc32CSupplier;
       9: aastore
      10: areturn

  com.google.common.hash.Hashing$Crc32CSupplier(java.lang.String, int, com.google.common.hash.Hashing$1);
    Code:
       0: aload_0
       1: aload_1
       2: iload_2
       3: invokespecial #1                  // Method "<init>":(Ljava/lang/String;I)V
       6: return

  static {};
    Code:
       0: new           #9                  // class com/google/common/hash/Hashing$Crc32CSupplier$1
       3: dup
       4: ldc           #10                 // String ABSTRACT_HASH_FUNCTION
       6: iconst_0
       7: invokespecial #11                 // Method com/google/common/hash/Hashing$Crc32CSupplier$1."<init>":(Ljava/lang/String;I)V
      10: putstatic     #3                  // Field ABSTRACT_HASH_FUNCTION:Lcom/google/common/hash/Hashing$Crc32CSupplier;
      13: invokestatic  #12                 // Method $values:()[Lcom/google/common/hash/Hashing$Crc32CSupplier;
      16: putstatic     #4                  // Field $VALUES:[Lcom/google/common/hash/Hashing$Crc32CSupplier;
      19: invokestatic  #13                 // Method values:()[Lcom/google/common/hash/Hashing$Crc32CSupplier;
      22: iconst_0
      23: aaload
      24: invokevirtual #14                 // Method get:()Ljava/lang/Object;
      27: checkcast     #15                 // class com/google/common/hash/HashFunction
      30: putstatic     #16                 // Field HASH_FUNCTION:Lcom/google/common/hash/HashFunction;
      33: return
}
