Compiled from "LittleEndianByteArray.java"
abstract class com.google.common.hash.LittleEndianByteArray$UnsafeByteArray extends java.lang.Enum<com.google.common.hash.LittleEndianByteArray$UnsafeByteArray> implements com.google.common.hash.LittleEndianByteArray$LittleEndianBytes {
  public static final com.google.common.hash.LittleEndianByteArray$UnsafeByteArray UNSAFE_LITTLE_ENDIAN;

  public static final com.google.common.hash.LittleEndianByteArray$UnsafeByteArray UNSAFE_BIG_ENDIAN;

  private static final sun.misc.Unsafe theUnsafe;

  private static final int BYTE_ARRAY_BASE_OFFSET;

  private static final com.google.common.hash.LittleEndianByteArray$UnsafeByteArray[] $VALUES;

  public static com.google.common.hash.LittleEndianByteArray$UnsafeByteArray[] values();
    Code:
       0: getstatic     #7                  // Field $VALUES:[Lcom/google/common/hash/LittleEndianByteArray$UnsafeByteArray;
       3: invokevirtual #8                  // Method "[Lcom/google/common/hash/LittleEndianByteArray$UnsafeByteArray;".clone:()Ljava/lang/Object;
       6: checkcast     #9                  // class "[Lcom/google/common/hash/LittleEndianByteArray$UnsafeByteArray;"
       9: areturn

  public static com.google.common.hash.LittleEndianByteArray$UnsafeByteArray valueOf(java.lang.String);
    Code:
       0: ldc           #4                  // class com/google/common/hash/LittleEndianByteArray$UnsafeByteArray
       2: aload_0
       3: invokestatic  #10                 // Method java/lang/Enum.valueOf:(Ljava/lang/Class;Ljava/lang/String;)Ljava/lang/Enum;
       6: checkcast     #4                  // class com/google/common/hash/LittleEndianByteArray$UnsafeByteArray
       9: areturn

  private com.google.common.hash.LittleEndianByteArray$UnsafeByteArray();
    Code:
       0: aload_0
       1: aload_1
       2: iload_2
       3: invokespecial #11                 // Method java/lang/Enum."<init>":(Ljava/lang/String;I)V
       6: return

  private static sun.misc.Unsafe getUnsafe();
    Code:
       0: invokestatic  #12                 // Method sun/misc/Unsafe.getUnsafe:()Lsun/misc/Unsafe;
       3: areturn
       4: astore_0
       5: invokedynamic #14,  0             // InvokeDynamic #0:run:()Ljava/security/PrivilegedExceptionAction;
      10: invokestatic  #15                 // Method java/security/AccessController.doPrivileged:(Ljava/security/PrivilegedExceptionAction;)Ljava/lang/Object;
      13: checkcast     #16                 // class sun/misc/Unsafe
      16: areturn
      17: astore_0
      18: new           #18                 // class java/lang/RuntimeException
      21: dup
      22: ldc           #19                 // String Could not initialize intrinsics
      24: aload_0
      25: invokevirtual #20                 // Method java/security/PrivilegedActionException.getCause:()Ljava/lang/Throwable;
      28: invokespecial #21                 // Method java/lang/RuntimeException."<init>":(Ljava/lang/String;Ljava/lang/Throwable;)V
      31: athrow
    Exception table:
       from    to  target type
           0     3     4   Class java/lang/SecurityException
           5    16    17   Class java/security/PrivilegedActionException

  private static sun.misc.Unsafe lambda$getUnsafe$0() throws java.lang.Exception;
    Code:
       0: ldc           #16                 // class sun/misc/Unsafe
       2: astore_0
       3: aload_0
       4: invokevirtual #22                 // Method java/lang/Class.getDeclaredFields:()[Ljava/lang/reflect/Field;
       7: astore_1
       8: aload_1
       9: arraylength
      10: istore_2
      11: iconst_0
      12: istore_3
      13: iload_3
      14: iload_2
      15: if_icmpge     62
      18: aload_1
      19: iload_3
      20: aaload
      21: astore        4
      23: aload         4
      25: iconst_1
      26: invokevirtual #23                 // Method java/lang/reflect/Field.setAccessible:(Z)V
      29: aload         4
      31: aconst_null
      32: invokevirtual #24                 // Method java/lang/reflect/Field.get:(Ljava/lang/Object;)Ljava/lang/Object;
      35: astore        5
      37: aload_0
      38: aload         5
      40: invokevirtual #25                 // Method java/lang/Class.isInstance:(Ljava/lang/Object;)Z
      43: ifeq          56
      46: aload_0
      47: aload         5
      49: invokevirtual #26                 // Method java/lang/Class.cast:(Ljava/lang/Object;)Ljava/lang/Object;
      52: checkcast     #16                 // class sun/misc/Unsafe
      55: areturn
      56: iinc          3, 1
      59: goto          13
      62: new           #27                 // class java/lang/NoSuchFieldError
      65: dup
      66: ldc           #28                 // String the Unsafe
      68: invokespecial #29                 // Method java/lang/NoSuchFieldError."<init>":(Ljava/lang/String;)V
      71: athrow

  private static com.google.common.hash.LittleEndianByteArray$UnsafeByteArray[] $values();
    Code:
       0: iconst_2
       1: anewarray     #4                  // class com/google/common/hash/LittleEndianByteArray$UnsafeByteArray
       4: dup
       5: iconst_0
       6: getstatic     #5                  // Field UNSAFE_LITTLE_ENDIAN:Lcom/google/common/hash/LittleEndianByteArray$UnsafeByteArray;
       9: aastore
      10: dup
      11: iconst_1
      12: getstatic     #6                  // Field UNSAFE_BIG_ENDIAN:Lcom/google/common/hash/LittleEndianByteArray$UnsafeByteArray;
      15: aastore
      16: areturn

  com.google.common.hash.LittleEndianByteArray$UnsafeByteArray(java.lang.String, int, com.google.common.hash.LittleEndianByteArray$1);
    Code:
       0: aload_0
       1: aload_1
       2: iload_2
       3: invokespecial #3                  // Method "<init>":(Ljava/lang/String;I)V
       6: return

  static int access$100();
    Code:
       0: getstatic     #2                  // Field BYTE_ARRAY_BASE_OFFSET:I
       3: ireturn

  static sun.misc.Unsafe access$200();
    Code:
       0: getstatic     #1                  // Field theUnsafe:Lsun/misc/Unsafe;
       3: areturn

  static {};
    Code:
       0: new           #30                 // class com/google/common/hash/LittleEndianByteArray$UnsafeByteArray$1
       3: dup
       4: ldc           #31                 // String UNSAFE_LITTLE_ENDIAN
       6: iconst_0
       7: invokespecial #32                 // Method com/google/common/hash/LittleEndianByteArray$UnsafeByteArray$1."<init>":(Ljava/lang/String;I)V
      10: putstatic     #5                  // Field UNSAFE_LITTLE_ENDIAN:Lcom/google/common/hash/LittleEndianByteArray$UnsafeByteArray;
      13: new           #33                 // class com/google/common/hash/LittleEndianByteArray$UnsafeByteArray$2
      16: dup
      17: ldc           #34                 // String UNSAFE_BIG_ENDIAN
      19: iconst_1
      20: invokespecial #35                 // Method com/google/common/hash/LittleEndianByteArray$UnsafeByteArray$2."<init>":(Ljava/lang/String;I)V
      23: putstatic     #6                  // Field UNSAFE_BIG_ENDIAN:Lcom/google/common/hash/LittleEndianByteArray$UnsafeByteArray;
      26: invokestatic  #36                 // Method $values:()[Lcom/google/common/hash/LittleEndianByteArray$UnsafeByteArray;
      29: putstatic     #7                  // Field $VALUES:[Lcom/google/common/hash/LittleEndianByteArray$UnsafeByteArray;
      32: invokestatic  #37                 // Method getUnsafe:()Lsun/misc/Unsafe;
      35: putstatic     #1                  // Field theUnsafe:Lsun/misc/Unsafe;
      38: getstatic     #1                  // Field theUnsafe:Lsun/misc/Unsafe;
      41: ldc           #38                 // class "[B"
      43: invokevirtual #39                 // Method sun/misc/Unsafe.arrayBaseOffset:(Ljava/lang/Class;)I
      46: putstatic     #2                  // Field BYTE_ARRAY_BASE_OFFSET:I
      49: getstatic     #1                  // Field theUnsafe:Lsun/misc/Unsafe;
      52: ldc           #38                 // class "[B"
      54: invokevirtual #40                 // Method sun/misc/Unsafe.arrayIndexScale:(Ljava/lang/Class;)I
      57: iconst_1
      58: if_icmpeq     69
      61: new           #41                 // class java/lang/AssertionError
      64: dup
      65: invokespecial #42                 // Method java/lang/AssertionError."<init>":()V
      68: athrow
      69: return
}
