Compiled from "AbstractMetricsListener.java"
public abstract class org.apache.dubbo.metrics.listener.AbstractMetricsListener<E extends org.apache.dubbo.metrics.event.MetricsEvent> implements org.apache.dubbo.metrics.listener.MetricsListener<E> {
  private final java.util.Map<java.lang.Class<?>, java.lang.Boolean> eventMatchCache;

  public org.apache.dubbo.metrics.listener.AbstractMetricsListener();
    Code:
       0: aload_0
       1: invokespecial #1                  // Method java/lang/Object."<init>":()V
       4: aload_0
       5: new           #2                  // class java/util/concurrent/ConcurrentHashMap
       8: dup
       9: invokespecial #3                  // Method java/util/concurrent/ConcurrentHashMap."<init>":()V
      12: putfield      #4                  // Field eventMatchCache:Ljava/util/Map;
      15: return

  public boolean isSupport(org.apache.dubbo.metrics.event.MetricsEvent);
    Code:
       0: aload_0
       1: getfield      #4                  // Field eventMatchCache:Ljava/util/Map;
       4: aload_1
       5: invokevirtual #5                  // Method java/lang/Object.getClass:()Ljava/lang/Class;
       8: aload_0
       9: aload_1
      10: invokedynamic #6,  0              // InvokeDynamic #0:apply:(Lorg/apache/dubbo/metrics/listener/AbstractMetricsListener;Lorg/apache/dubbo/metrics/event/MetricsEvent;)Ljava/util/function/Function;
      15: invokeinterface #7,  3            // InterfaceMethod java/util/Map.computeIfAbsent:(Ljava/lang/Object;Ljava/util/function/Function;)Ljava/lang/Object;
      20: checkcast     #8                  // class java/lang/Boolean
      23: astore_2
      24: aload_1
      25: invokevirtual #9                  // Method org/apache/dubbo/metrics/event/MetricsEvent.isAvailable:()Z
      28: ifeq          42
      31: aload_2
      32: invokevirtual #10                 // Method java/lang/Boolean.booleanValue:()Z
      35: ifeq          42
      38: iconst_1
      39: goto          43
      42: iconst_0
      43: ireturn

  public abstract void onEvent(E);

  private java.lang.Boolean lambda$isSupport$0(org.apache.dubbo.metrics.event.MetricsEvent, java.lang.Class);
    Code:
       0: aload_0
       1: invokevirtual #5                  // Method java/lang/Object.getClass:()Ljava/lang/Class;
       4: ldc           #11                 // class org/apache/dubbo/metrics/listener/AbstractMetricsListener
       6: aload_1
       7: invokestatic  #12                 // Method org/apache/dubbo/common/utils/ReflectionUtils.match:(Ljava/lang/Class;Ljava/lang/Class;Ljava/lang/Object;)Z
      10: invokestatic  #13                 // Method java/lang/Boolean.valueOf:(Z)Ljava/lang/Boolean;
      13: areturn
}
