Compiled from "AbstractMetricsKeyListener.java"
final class org.apache.dubbo.metrics.listener.AbstractMetricsKeyListener$2 extends org.apache.dubbo.metrics.listener.AbstractMetricsKeyListener {
  final java.util.function.Consumer val$finishFunc;

  org.apache.dubbo.metrics.listener.AbstractMetricsKeyListener$2(org.apache.dubbo.metrics.model.key.MetricsKey, java.util.function.Consumer);
    Code:
       0: aload_0
       1: aload_2
       2: putfield      #1                  // Field val$finishFunc:Ljava/util/function/Consumer;
       5: aload_0
       6: aload_1
       7: invokespecial #2                  // Method org/apache/dubbo/metrics/listener/AbstractMetricsKeyListener."<init>":(Lorg/apache/dubbo/metrics/model/key/MetricsKey;)V
      10: return

  public void onEventFinish(org.apache.dubbo.metrics.event.TimeCounterEvent);
    Code:
       0: aload_0
       1: getfield      #1                  // Field val$finishFunc:Ljava/util/function/Consumer;
       4: aload_1
       5: invokeinterface #3,  2            // InterfaceMethod java/util/function/Consumer.accept:(Ljava/lang/Object;)V
      10: return

  public void onEvent(org.apache.dubbo.metrics.event.MetricsEvent);
    Code:
       0: aload_0
       1: aload_1
       2: checkcast     #4                  // class org/apache/dubbo/metrics/event/TimeCounterEvent
       5: invokespecial #5                  // Method org/apache/dubbo/metrics/listener/AbstractMetricsKeyListener.onEvent:(Lorg/apache/dubbo/metrics/event/TimeCounterEvent;)V
       8: return
}
