Compiled from "AbstractMetricsKeyListener.java"
public abstract class org.apache.dubbo.metrics.listener.AbstractMetricsKeyListener extends org.apache.dubbo.metrics.listener.AbstractMetricsListener<org.apache.dubbo.metrics.event.TimeCounterEvent> implements org.apache.dubbo.metrics.listener.MetricsLifeListener<org.apache.dubbo.metrics.event.TimeCounterEvent> {
  private final org.apache.dubbo.metrics.model.key.MetricsKey metricsKey;

  public org.apache.dubbo.metrics.listener.AbstractMetricsKeyListener(org.apache.dubbo.metrics.model.key.MetricsKey);
    Code:
       0: aload_0
       1: invokespecial #1                  // Method org/apache/dubbo/metrics/listener/AbstractMetricsListener."<init>":()V
       4: aload_0
       5: aload_1
       6: putfield      #2                  // Field metricsKey:Lorg/apache/dubbo/metrics/model/key/MetricsKey;
       9: return

  public boolean isSupport(org.apache.dubbo.metrics.event.MetricsEvent);
    Code:
       0: aload_0
       1: aload_1
       2: invokespecial #3                  // Method org/apache/dubbo/metrics/listener/AbstractMetricsListener.isSupport:(Lorg/apache/dubbo/metrics/event/MetricsEvent;)Z
       5: ifeq          23
       8: aload_1
       9: aload_0
      10: getfield      #2                  // Field metricsKey:Lorg/apache/dubbo/metrics/model/key/MetricsKey;
      13: invokevirtual #4                  // Method org/apache/dubbo/metrics/event/MetricsEvent.isAssignableFrom:(Ljava/lang/Object;)Z
      16: ifeq          23
      19: iconst_1
      20: goto          24
      23: iconst_0
      24: ireturn

  public void onEvent(org.apache.dubbo.metrics.event.TimeCounterEvent);
    Code:
       0: return

  public static org.apache.dubbo.metrics.listener.AbstractMetricsKeyListener onEvent(org.apache.dubbo.metrics.model.key.MetricsKey, java.util.function.Consumer<org.apache.dubbo.metrics.event.TimeCounterEvent>);
    Code:
       0: new           #5                  // class org/apache/dubbo/metrics/listener/AbstractMetricsKeyListener$1
       3: dup
       4: aload_0
       5: aload_1
       6: invokespecial #6                  // Method org/apache/dubbo/metrics/listener/AbstractMetricsKeyListener$1."<init>":(Lorg/apache/dubbo/metrics/model/key/MetricsKey;Ljava/util/function/Consumer;)V
       9: areturn

  public static org.apache.dubbo.metrics.listener.AbstractMetricsKeyListener onFinish(org.apache.dubbo.metrics.model.key.MetricsKey, java.util.function.Consumer<org.apache.dubbo.metrics.event.TimeCounterEvent>);
    Code:
       0: new           #7                  // class org/apache/dubbo/metrics/listener/AbstractMetricsKeyListener$2
       3: dup
       4: aload_0
       5: aload_1
       6: invokespecial #8                  // Method org/apache/dubbo/metrics/listener/AbstractMetricsKeyListener$2."<init>":(Lorg/apache/dubbo/metrics/model/key/MetricsKey;Ljava/util/function/Consumer;)V
       9: areturn

  public static org.apache.dubbo.metrics.listener.AbstractMetricsKeyListener onError(org.apache.dubbo.metrics.model.key.MetricsKey, java.util.function.Consumer<org.apache.dubbo.metrics.event.TimeCounterEvent>);
    Code:
       0: new           #9                  // class org/apache/dubbo/metrics/listener/AbstractMetricsKeyListener$3
       3: dup
       4: aload_0
       5: aload_1
       6: invokespecial #10                 // Method org/apache/dubbo/metrics/listener/AbstractMetricsKeyListener$3."<init>":(Lorg/apache/dubbo/metrics/model/key/MetricsKey;Ljava/util/function/Consumer;)V
       9: areturn

  public void onEvent(org.apache.dubbo.metrics.event.MetricsEvent);
    Code:
       0: aload_0
       1: aload_1
       2: checkcast     #11                 // class org/apache/dubbo/metrics/event/TimeCounterEvent
       5: invokevirtual #12                 // Method onEvent:(Lorg/apache/dubbo/metrics/event/TimeCounterEvent;)V
       8: return
}
