Compiled from "MetricsApplicationListener.java"
public class org.apache.dubbo.metrics.listener.MetricsApplicationListener extends org.apache.dubbo.metrics.listener.AbstractMetricsKeyListener {
  public org.apache.dubbo.metrics.listener.MetricsApplicationListener(org.apache.dubbo.metrics.model.key.MetricsKey);
    Code:
       0: aload_0
       1: aload_1
       2: invokespecial #1                  // Method org/apache/dubbo/metrics/listener/AbstractMetricsKeyListener."<init>":(Lorg/apache/dubbo/metrics/model/key/MetricsKey;)V
       5: return

  public static org.apache.dubbo.metrics.listener.AbstractMetricsKeyListener onPostEventBuild(org.apache.dubbo.metrics.model.key.MetricsKey, org.apache.dubbo.metrics.collector.CombMetricsCollector);
    Code:
       0: aload_0
       1: aload_1
       2: aload_0
       3: invokedynamic #2,  0              // InvokeDynamic #0:accept:(Lorg/apache/dubbo/metrics/collector/CombMetricsCollector;Lorg/apache/dubbo/metrics/model/key/MetricsKey;)Ljava/util/function/Consumer;
       8: invokestatic  #3                  // Method org/apache/dubbo/metrics/listener/AbstractMetricsKeyListener.onEvent:(Lorg/apache/dubbo/metrics/model/key/MetricsKey;Ljava/util/function/Consumer;)Lorg/apache/dubbo/metrics/listener/AbstractMetricsKeyListener;
      11: areturn

  public static org.apache.dubbo.metrics.listener.AbstractMetricsKeyListener onFinishEventBuild(org.apache.dubbo.metrics.model.key.MetricsKey, org.apache.dubbo.metrics.model.key.MetricsPlaceValue, org.apache.dubbo.metrics.collector.CombMetricsCollector);
    Code:
       0: aload_0
       1: aload_2
       2: aload_0
       3: aload_1
       4: invokedynamic #4,  0              // InvokeDynamic #1:accept:(Lorg/apache/dubbo/metrics/collector/CombMetricsCollector;Lorg/apache/dubbo/metrics/model/key/MetricsKey;Lorg/apache/dubbo/metrics/model/key/MetricsPlaceValue;)Ljava/util/function/Consumer;
       9: invokestatic  #5                  // Method org/apache/dubbo/metrics/listener/AbstractMetricsKeyListener.onFinish:(Lorg/apache/dubbo/metrics/model/key/MetricsKey;Ljava/util/function/Consumer;)Lorg/apache/dubbo/metrics/listener/AbstractMetricsKeyListener;
      12: areturn

  public static org.apache.dubbo.metrics.listener.AbstractMetricsKeyListener onErrorEventBuild(org.apache.dubbo.metrics.model.key.MetricsKey, org.apache.dubbo.metrics.model.key.MetricsPlaceValue, org.apache.dubbo.metrics.collector.CombMetricsCollector);
    Code:
       0: aload_0
       1: aload_2
       2: aload_0
       3: aload_1
       4: invokedynamic #6,  0              // InvokeDynamic #2:accept:(Lorg/apache/dubbo/metrics/collector/CombMetricsCollector;Lorg/apache/dubbo/metrics/model/key/MetricsKey;Lorg/apache/dubbo/metrics/model/key/MetricsPlaceValue;)Ljava/util/function/Consumer;
       9: invokestatic  #7                  // Method org/apache/dubbo/metrics/listener/AbstractMetricsKeyListener.onError:(Lorg/apache/dubbo/metrics/model/key/MetricsKey;Ljava/util/function/Consumer;)Lorg/apache/dubbo/metrics/listener/AbstractMetricsKeyListener;
      12: areturn

  private static void lambda$onErrorEventBuild$2(org.apache.dubbo.metrics.collector.CombMetricsCollector, org.apache.dubbo.metrics.model.key.MetricsKey, org.apache.dubbo.metrics.model.key.MetricsPlaceValue, org.apache.dubbo.metrics.event.TimeCounterEvent);
    Code:
       0: aload_0
       1: aload_1
       2: invokevirtual #8                  // Method org/apache/dubbo/metrics/collector/CombMetricsCollector.increment:(Lorg/apache/dubbo/metrics/model/key/MetricsKey;)V
       5: aload_0
       6: aload_2
       7: invokevirtual #9                  // Method org/apache/dubbo/metrics/model/key/MetricsPlaceValue.getType:()Ljava/lang/String;
      10: aload_3
      11: invokevirtual #10                 // Method org/apache/dubbo/metrics/event/TimeCounterEvent.getTimePair:()Lorg/apache/dubbo/metrics/model/TimePair;
      14: invokevirtual #11                 // Method org/apache/dubbo/metrics/model/TimePair.calc:()J
      17: invokestatic  #12                 // Method java/lang/Long.valueOf:(J)Ljava/lang/Long;
      20: invokevirtual #13                 // Method org/apache/dubbo/metrics/collector/CombMetricsCollector.addRt:(Ljava/lang/String;Ljava/lang/Long;)V
      23: return

  private static void lambda$onFinishEventBuild$1(org.apache.dubbo.metrics.collector.CombMetricsCollector, org.apache.dubbo.metrics.model.key.MetricsKey, org.apache.dubbo.metrics.model.key.MetricsPlaceValue, org.apache.dubbo.metrics.event.TimeCounterEvent);
    Code:
       0: aload_0
       1: aload_1
       2: invokevirtual #8                  // Method org/apache/dubbo/metrics/collector/CombMetricsCollector.increment:(Lorg/apache/dubbo/metrics/model/key/MetricsKey;)V
       5: aload_0
       6: aload_2
       7: invokevirtual #9                  // Method org/apache/dubbo/metrics/model/key/MetricsPlaceValue.getType:()Ljava/lang/String;
      10: aload_3
      11: invokevirtual #10                 // Method org/apache/dubbo/metrics/event/TimeCounterEvent.getTimePair:()Lorg/apache/dubbo/metrics/model/TimePair;
      14: invokevirtual #11                 // Method org/apache/dubbo/metrics/model/TimePair.calc:()J
      17: invokestatic  #12                 // Method java/lang/Long.valueOf:(J)Ljava/lang/Long;
      20: invokevirtual #13                 // Method org/apache/dubbo/metrics/collector/CombMetricsCollector.addRt:(Ljava/lang/String;Ljava/lang/Long;)V
      23: return

  private static void lambda$onPostEventBuild$0(org.apache.dubbo.metrics.collector.CombMetricsCollector, org.apache.dubbo.metrics.model.key.MetricsKey, org.apache.dubbo.metrics.event.TimeCounterEvent);
    Code:
       0: aload_0
       1: aload_1
       2: invokevirtual #8                  // Method org/apache/dubbo/metrics/collector/CombMetricsCollector.increment:(Lorg/apache/dubbo/metrics/model/key/MetricsKey;)V
       5: return
}
