Compiled from "MetricsServiceListener.java"
public class org.apache.dubbo.metrics.listener.MetricsServiceListener extends org.apache.dubbo.metrics.listener.AbstractMetricsKeyListener {
  public org.apache.dubbo.metrics.listener.MetricsServiceListener(org.apache.dubbo.metrics.model.key.MetricsKey);
    Code:
       0: aload_0
       1: aload_1
       2: invokespecial #1                  // Method org/apache/dubbo/metrics/listener/AbstractMetricsKeyListener."<init>":(Lorg/apache/dubbo/metrics/model/key/MetricsKey;)V
       5: return

  public static org.apache.dubbo.metrics.listener.AbstractMetricsKeyListener onPostEventBuild(org.apache.dubbo.metrics.model.key.MetricsKey, org.apache.dubbo.metrics.model.key.MetricsPlaceValue, org.apache.dubbo.metrics.collector.ServiceMetricsCollector<org.apache.dubbo.metrics.event.TimeCounterEvent>);
    Code:
       0: aload_0
       1: aload_0
       2: aload_1
       3: aload_2
       4: invokedynamic #2,  0              // InvokeDynamic #0:accept:(Lorg/apache/dubbo/metrics/model/key/MetricsKey;Lorg/apache/dubbo/metrics/model/key/MetricsPlaceValue;Lorg/apache/dubbo/metrics/collector/ServiceMetricsCollector;)Ljava/util/function/Consumer;
       9: invokestatic  #3                  // Method org/apache/dubbo/metrics/listener/AbstractMetricsKeyListener.onEvent:(Lorg/apache/dubbo/metrics/model/key/MetricsKey;Ljava/util/function/Consumer;)Lorg/apache/dubbo/metrics/listener/AbstractMetricsKeyListener;
      12: areturn

  public static org.apache.dubbo.metrics.listener.AbstractMetricsKeyListener onFinishEventBuild(org.apache.dubbo.metrics.model.key.MetricsKey, org.apache.dubbo.metrics.model.key.MetricsPlaceValue, org.apache.dubbo.metrics.collector.ServiceMetricsCollector<org.apache.dubbo.metrics.event.TimeCounterEvent>);
    Code:
       0: aload_0
       1: aload_0
       2: aload_1
       3: aload_2
       4: invokedynamic #4,  0              // InvokeDynamic #1:accept:(Lorg/apache/dubbo/metrics/model/key/MetricsKey;Lorg/apache/dubbo/metrics/model/key/MetricsPlaceValue;Lorg/apache/dubbo/metrics/collector/ServiceMetricsCollector;)Ljava/util/function/Consumer;
       9: invokestatic  #5                  // Method org/apache/dubbo/metrics/listener/AbstractMetricsKeyListener.onFinish:(Lorg/apache/dubbo/metrics/model/key/MetricsKey;Ljava/util/function/Consumer;)Lorg/apache/dubbo/metrics/listener/AbstractMetricsKeyListener;
      12: areturn

  public static org.apache.dubbo.metrics.listener.AbstractMetricsKeyListener onErrorEventBuild(org.apache.dubbo.metrics.model.key.MetricsKey, org.apache.dubbo.metrics.model.key.MetricsPlaceValue, org.apache.dubbo.metrics.collector.ServiceMetricsCollector<org.apache.dubbo.metrics.event.TimeCounterEvent>);
    Code:
       0: aload_0
       1: aload_0
       2: aload_1
       3: aload_2
       4: invokedynamic #6,  0              // InvokeDynamic #2:accept:(Lorg/apache/dubbo/metrics/model/key/MetricsKey;Lorg/apache/dubbo/metrics/model/key/MetricsPlaceValue;Lorg/apache/dubbo/metrics/collector/ServiceMetricsCollector;)Ljava/util/function/Consumer;
       9: invokestatic  #7                  // Method org/apache/dubbo/metrics/listener/AbstractMetricsKeyListener.onError:(Lorg/apache/dubbo/metrics/model/key/MetricsKey;Ljava/util/function/Consumer;)Lorg/apache/dubbo/metrics/listener/AbstractMetricsKeyListener;
      12: areturn

  private static void lambda$onErrorEventBuild$2(org.apache.dubbo.metrics.model.key.MetricsKey, org.apache.dubbo.metrics.model.key.MetricsPlaceValue, org.apache.dubbo.metrics.collector.ServiceMetricsCollector, org.apache.dubbo.metrics.event.TimeCounterEvent);
    Code:
       0: aload_0
       1: aload_1
       2: aload_2
       3: aload_3
       4: invokestatic  #8                  // Method org/apache/dubbo/metrics/model/MetricsSupport.incrAndAddRt:(Lorg/apache/dubbo/metrics/model/key/MetricsKey;Lorg/apache/dubbo/metrics/model/key/MetricsPlaceValue;Lorg/apache/dubbo/metrics/collector/ServiceMetricsCollector;Lorg/apache/dubbo/metrics/event/TimeCounterEvent;)V
       7: return

  private static void lambda$onFinishEventBuild$1(org.apache.dubbo.metrics.model.key.MetricsKey, org.apache.dubbo.metrics.model.key.MetricsPlaceValue, org.apache.dubbo.metrics.collector.ServiceMetricsCollector, org.apache.dubbo.metrics.event.TimeCounterEvent);
    Code:
       0: aload_0
       1: aload_1
       2: aload_2
       3: aload_3
       4: invokestatic  #8                  // Method org/apache/dubbo/metrics/model/MetricsSupport.incrAndAddRt:(Lorg/apache/dubbo/metrics/model/key/MetricsKey;Lorg/apache/dubbo/metrics/model/key/MetricsPlaceValue;Lorg/apache/dubbo/metrics/collector/ServiceMetricsCollector;Lorg/apache/dubbo/metrics/event/TimeCounterEvent;)V
       7: return

  private static void lambda$onPostEventBuild$0(org.apache.dubbo.metrics.model.key.MetricsKey, org.apache.dubbo.metrics.model.key.MetricsPlaceValue, org.apache.dubbo.metrics.collector.ServiceMetricsCollector, org.apache.dubbo.metrics.event.TimeCounterEvent);
    Code:
       0: aload_0
       1: aload_1
       2: aload_2
       3: aload_3
       4: invokestatic  #9                  // Method org/apache/dubbo/metrics/model/MetricsSupport.increment:(Lorg/apache/dubbo/metrics/model/key/MetricsKey;Lorg/apache/dubbo/metrics/model/key/MetricsPlaceValue;Lorg/apache/dubbo/metrics/collector/ServiceMetricsCollector;Lorg/apache/dubbo/metrics/event/MetricsEvent;)V
       7: return
}
