Compiled from "Subset.java"
public class org.apache.dubbo.rpc.cluster.router.mesh.rule.destination.Subset {
  private java.lang.String name;

  private java.util.Map<java.lang.String, java.lang.String> labels;

  public org.apache.dubbo.rpc.cluster.router.mesh.rule.destination.Subset();
    Code:
       0: aload_0
       1: invokespecial #1                  // Method java/lang/Object."<init>":()V
       4: return

  public java.lang.String getName();
    Code:
       0: aload_0
       1: getfield      #2                  // Field name:Ljava/lang/String;
       4: areturn

  public void setName(java.lang.String);
    Code:
       0: aload_0
       1: aload_1
       2: putfield      #2                  // Field name:Ljava/lang/String;
       5: return

  public java.util.Map<java.lang.String, java.lang.String> getLabels();
    Code:
       0: aload_0
       1: getfield      #3                  // Field labels:Ljava/util/Map;
       4: areturn

  public void setLabels(java.util.Map<java.lang.String, java.lang.String>);
    Code:
       0: aload_0
       1: aload_1
       2: putfield      #3                  // Field labels:Ljava/util/Map;
       5: return

  public java.lang.String toString();
    Code:
       0: new           #4                  // class java/lang/StringBuilder
       3: dup
       4: invokespecial #5                  // Method java/lang/StringBuilder."<init>":()V
       7: ldc           #6                  // String Subset{name=\'
       9: invokevirtual #7                  // Method java/lang/StringBuilder.append:(Ljava/lang/String;)Ljava/lang/StringBuilder;
      12: aload_0
      13: getfield      #2                  // Field name:Ljava/lang/String;
      16: invokevirtual #7                  // Method java/lang/StringBuilder.append:(Ljava/lang/String;)Ljava/lang/StringBuilder;
      19: bipush        39
      21: invokevirtual #8                  // Method java/lang/StringBuilder.append:(C)Ljava/lang/StringBuilder;
      24: ldc           #9                  // String , labels=
      26: invokevirtual #7                  // Method java/lang/StringBuilder.append:(Ljava/lang/String;)Ljava/lang/StringBuilder;
      29: aload_0
      30: getfield      #3                  // Field labels:Ljava/util/Map;
      33: invokevirtual #10                 // Method java/lang/StringBuilder.append:(Ljava/lang/Object;)Ljava/lang/StringBuilder;
      36: bipush        125
      38: invokevirtual #8                  // Method java/lang/StringBuilder.append:(C)Ljava/lang/StringBuilder;
      41: invokevirtual #11                 // Method java/lang/StringBuilder.toString:()Ljava/lang/String;
      44: areturn
}
