Compiled from "TrafficPolicy.java"
public class org.apache.dubbo.rpc.cluster.router.mesh.rule.destination.TrafficPolicy {
  private org.apache.dubbo.rpc.cluster.router.mesh.rule.destination.loadbalance.LoadBalancerSettings loadBalancer;

  public org.apache.dubbo.rpc.cluster.router.mesh.rule.destination.TrafficPolicy();
    Code:
       0: aload_0
       1: invokespecial #1                  // Method java/lang/Object."<init>":()V
       4: return

  public org.apache.dubbo.rpc.cluster.router.mesh.rule.destination.loadbalance.LoadBalancerSettings getLoadBalancer();
    Code:
       0: aload_0
       1: getfield      #2                  // Field loadBalancer:Lorg/apache/dubbo/rpc/cluster/router/mesh/rule/destination/loadbalance/LoadBalancerSettings;
       4: areturn

  public void setLoadBalancer(org.apache.dubbo.rpc.cluster.router.mesh.rule.destination.loadbalance.LoadBalancerSettings);
    Code:
       0: aload_0
       1: aload_1
       2: putfield      #2                  // Field loadBalancer:Lorg/apache/dubbo/rpc/cluster/router/mesh/rule/destination/loadbalance/LoadBalancerSettings;
       5: return

  public java.lang.String toString();
    Code:
       0: new           #3                  // class java/lang/StringBuilder
       3: dup
       4: invokespecial #4                  // Method java/lang/StringBuilder."<init>":()V
       7: ldc           #5                  // String TrafficPolicy{loadBalancer=
       9: invokevirtual #6                  // Method java/lang/StringBuilder.append:(Ljava/lang/String;)Ljava/lang/StringBuilder;
      12: aload_0
      13: getfield      #2                  // Field loadBalancer:Lorg/apache/dubbo/rpc/cluster/router/mesh/rule/destination/loadbalance/LoadBalancerSettings;
      16: invokevirtual #7                  // Method java/lang/StringBuilder.append:(Ljava/lang/Object;)Ljava/lang/StringBuilder;
      19: bipush        125
      21: invokevirtual #8                  // Method java/lang/StringBuilder.append:(C)Ljava/lang/StringBuilder;
      24: invokevirtual #9                  // Method java/lang/StringBuilder.toString:()Ljava/lang/String;
      27: areturn
}
