Compiled from "BindableRuntimeHintsRegistrar.java"
class org.springframework.boot.context.properties.bind.BindableRuntimeHintsRegistrar$KotlinDelegate {
  private org.springframework.boot.context.properties.bind.BindableRuntimeHintsRegistrar$KotlinDelegate();
    Code:
       0: aload_0
       1: invokespecial #1                  // Method java/lang/Object."<init>":()V
       4: return

  static void handleConstructor(org.springframework.aot.hint.ReflectionHints, java.lang.reflect.Constructor<?>);
    Code:
       0: aload_1
       1: invokevirtual #7                  // Method java/lang/reflect/Constructor.getDeclaringClass:()Ljava/lang/Class;
       4: invokestatic  #13                 // Method kotlin/jvm/JvmClassMappingKt.getKotlinClass:(Ljava/lang/Class;)Lkotlin/reflect/KClass;
       7: astore_2
       8: aload_2
       9: invokeinterface #19,  1           // InterfaceMethod kotlin/reflect/KClass.isData:()Z
      14: ifeq          39
      17: aload_0
      18: aload_1
      19: invokevirtual #7                  // Method java/lang/reflect/Constructor.getDeclaringClass:()Ljava/lang/Class;
      22: iconst_1
      23: anewarray     #25                 // class org/springframework/aot/hint/MemberCategory
      26: dup
      27: iconst_0
      28: getstatic     #27                 // Field org/springframework/aot/hint/MemberCategory.INVOKE_DECLARED_CONSTRUCTORS:Lorg/springframework/aot/hint/MemberCategory;
      31: aastore
      32: invokevirtual #31                 // Method org/springframework/aot/hint/ReflectionHints.registerType:(Ljava/lang/Class;[Lorg/springframework/aot/hint/MemberCategory;)Lorg/springframework/aot/hint/ReflectionHints;
      35: pop
      36: goto          48
      39: aload_0
      40: aload_1
      41: getstatic     #37                 // Field org/springframework/aot/hint/ExecutableMode.INVOKE:Lorg/springframework/aot/hint/ExecutableMode;
      44: invokevirtual #43                 // Method org/springframework/aot/hint/ReflectionHints.registerConstructor:(Ljava/lang/reflect/Constructor;Lorg/springframework/aot/hint/ExecutableMode;)Lorg/springframework/aot/hint/ReflectionHints;
      47: pop
      48: return
}
