Compiled from "BindConstructorProvider.java"
public interface org.springframework.boot.context.properties.bind.BindConstructorProvider {
  public static final org.springframework.boot.context.properties.bind.BindConstructorProvider DEFAULT;

  public default java.lang.reflect.Constructor<?> getBindConstructor(java.lang.Class<?>, boolean);
    Code:
       0: aload_0
       1: aload_1
       2: invokestatic  #1                  // Method org/springframework/boot/context/properties/bind/Bindable.of:(Ljava/lang/Class;)Lorg/springframework/boot/context/properties/bind/Bindable;
       5: iload_2
       6: invokeinterface #7,  3            // InterfaceMethod getBindConstructor:(Lorg/springframework/boot/context/properties/bind/Bindable;Z)Ljava/lang/reflect/Constructor;
      11: areturn

  public abstract java.lang.reflect.Constructor<?> getBindConstructor(org.springframework.boot.context.properties.bind.Bindable<?>, boolean);

  static {};
    Code:
       0: new           #13                 // class org/springframework/boot/context/properties/bind/DefaultBindConstructorProvider
       3: dup
       4: invokespecial #15                 // Method org/springframework/boot/context/properties/bind/DefaultBindConstructorProvider."<init>":()V
       7: putstatic     #19                 // Field DEFAULT:Lorg/springframework/boot/context/properties/bind/BindConstructorProvider;
      10: return
}
