Compiled from "BindConverter.java"
class org.springframework.boot.context.properties.bind.BindConverter$TypeConverterConverter implements org.springframework.core.convert.converter.ConditionalGenericConverter {
  private static final java.util.Set<java.lang.Class<?>> EXCLUDED_EDITORS;

  private final java.util.function.Consumer<org.springframework.beans.PropertyEditorRegistry> initializer;

  private final org.springframework.beans.SimpleTypeConverter matchesOnlyTypeConverter;

  org.springframework.boot.context.properties.bind.BindConverter$TypeConverterConverter(java.util.function.Consumer<org.springframework.beans.PropertyEditorRegistry>);
    Code:
       0: aload_0
       1: invokespecial #1                  // Method java/lang/Object."<init>":()V
       4: aload_0
       5: aload_1
       6: putfield      #7                  // Field initializer:Ljava/util/function/Consumer;
       9: aload_0
      10: aload_0
      11: invokevirtual #13                 // Method createTypeConverter:()Lorg/springframework/beans/SimpleTypeConverter;
      14: putfield      #17                 // Field matchesOnlyTypeConverter:Lorg/springframework/beans/SimpleTypeConverter;
      17: return

  public java.util.Set<org.springframework.core.convert.converter.GenericConverter$ConvertiblePair> getConvertibleTypes();
    Code:
       0: new           #21                 // class org/springframework/core/convert/converter/GenericConverter$ConvertiblePair
       3: dup
       4: ldc           #23                 // class java/lang/String
       6: ldc           #2                  // class java/lang/Object
       8: invokespecial #25                 // Method org/springframework/core/convert/converter/GenericConverter$ConvertiblePair."<init>":(Ljava/lang/Class;Ljava/lang/Class;)V
      11: invokestatic  #28                 // Method java/util/Collections.singleton:(Ljava/lang/Object;)Ljava/util/Set;
      14: areturn

  public boolean matches(org.springframework.core.convert.TypeDescriptor, org.springframework.core.convert.TypeDescriptor);
    Code:
       0: aload_2
       1: invokevirtual #34                 // Method org/springframework/core/convert/TypeDescriptor.getType:()Ljava/lang/Class;
       4: astore_3
       5: aload_3
       6: ifnull        33
       9: aload_3
      10: ldc           #2                  // class java/lang/Object
      12: if_acmpeq     33
      15: ldc           #40                 // class java/util/Collection
      17: aload_3
      18: invokevirtual #42                 // Method java/lang/Class.isAssignableFrom:(Ljava/lang/Class;)Z
      21: ifne          33
      24: ldc           #48                 // class java/util/Map
      26: aload_3
      27: invokevirtual #42                 // Method java/lang/Class.isAssignableFrom:(Ljava/lang/Class;)Z
      30: ifeq          35
      33: iconst_0
      34: ireturn
      35: aload_0
      36: getfield      #17                 // Field matchesOnlyTypeConverter:Lorg/springframework/beans/SimpleTypeConverter;
      39: aload_3
      40: invokevirtual #50                 // Method org/springframework/beans/SimpleTypeConverter.getDefaultEditor:(Ljava/lang/Class;)Ljava/beans/PropertyEditor;
      43: astore        4
      45: aload         4
      47: ifnonnull     61
      50: aload_0
      51: getfield      #17                 // Field matchesOnlyTypeConverter:Lorg/springframework/beans/SimpleTypeConverter;
      54: aload_3
      55: aconst_null
      56: invokevirtual #56                 // Method org/springframework/beans/SimpleTypeConverter.findCustomEditor:(Ljava/lang/Class;Ljava/lang/String;)Ljava/beans/PropertyEditor;
      59: astore        4
      61: aload         4
      63: ifnonnull     78
      66: ldc           #23                 // class java/lang/String
      68: aload_3
      69: if_acmpeq     78
      72: aload_3
      73: invokestatic  #60                 // Method org/springframework/beans/BeanUtils.findEditorByConvention:(Ljava/lang/Class;)Ljava/beans/PropertyEditor;
      76: astore        4
      78: aload         4
      80: ifnull        103
      83: getstatic     #65                 // Field EXCLUDED_EDITORS:Ljava/util/Set;
      86: aload         4
      88: invokevirtual #69                 // Method java/lang/Object.getClass:()Ljava/lang/Class;
      91: invokeinterface #72,  2           // InterfaceMethod java/util/Set.contains:(Ljava/lang/Object;)Z
      96: ifne          103
      99: iconst_1
     100: goto          104
     103: iconst_0
     104: ireturn

  public java.lang.Object convert(java.lang.Object, org.springframework.core.convert.TypeDescriptor, org.springframework.core.convert.TypeDescriptor);
    Code:
       0: aload_0
       1: invokevirtual #13                 // Method createTypeConverter:()Lorg/springframework/beans/SimpleTypeConverter;
       4: aload_1
       5: aload_3
       6: invokevirtual #34                 // Method org/springframework/core/convert/TypeDescriptor.getType:()Ljava/lang/Class;
       9: invokevirtual #78                 // Method org/springframework/beans/SimpleTypeConverter.convertIfNecessary:(Ljava/lang/Object;Ljava/lang/Class;)Ljava/lang/Object;
      12: areturn

  private org.springframework.beans.SimpleTypeConverter createTypeConverter();
    Code:
       0: new           #51                 // class org/springframework/beans/SimpleTypeConverter
       3: dup
       4: invokespecial #82                 // Method org/springframework/beans/SimpleTypeConverter."<init>":()V
       7: astore_1
       8: aload_0
       9: getfield      #7                  // Field initializer:Ljava/util/function/Consumer;
      12: ifnull        25
      15: aload_0
      16: getfield      #7                  // Field initializer:Ljava/util/function/Consumer;
      19: aload_1
      20: invokeinterface #83,  2           // InterfaceMethod java/util/function/Consumer.accept:(Ljava/lang/Object;)V
      25: aload_1
      26: areturn

  static {};
    Code:
       0: new           #89                 // class java/util/HashSet
       3: dup
       4: invokespecial #91                 // Method java/util/HashSet."<init>":()V
       7: astore_0
       8: aload_0
       9: ldc           #92                 // class org/springframework/beans/propertyeditors/CustomNumberEditor
      11: invokeinterface #94,  2           // InterfaceMethod java/util/Set.add:(Ljava/lang/Object;)Z
      16: pop
      17: aload_0
      18: ldc           #97                 // class org/springframework/beans/propertyeditors/CustomBooleanEditor
      20: invokeinterface #94,  2           // InterfaceMethod java/util/Set.add:(Ljava/lang/Object;)Z
      25: pop
      26: aload_0
      27: ldc           #99                 // class org/springframework/beans/propertyeditors/FileEditor
      29: invokeinterface #94,  2           // InterfaceMethod java/util/Set.add:(Ljava/lang/Object;)Z
      34: pop
      35: aload_0
      36: invokestatic  #101                // Method java/util/Collections.unmodifiableSet:(Ljava/util/Set;)Ljava/util/Set;
      39: putstatic     #65                 // Field EXCLUDED_EDITORS:Ljava/util/Set;
      42: return
}
