Compiled from "Bindable.java"
public final class org.springframework.boot.context.properties.bind.Bindable<T> {
  private static final java.lang.annotation.Annotation[] NO_ANNOTATIONS;

  private static final java.util.EnumSet<org.springframework.boot.context.properties.bind.Bindable$BindRestriction> NO_BIND_RESTRICTIONS;

  private final org.springframework.core.ResolvableType type;

  private final org.springframework.core.ResolvableType boxedType;

  private final java.util.function.Supplier<T> value;

  private final java.lang.annotation.Annotation[] annotations;

  private final java.util.EnumSet<org.springframework.boot.context.properties.bind.Bindable$BindRestriction> bindRestrictions;

  private org.springframework.boot.context.properties.bind.Bindable(org.springframework.core.ResolvableType, org.springframework.core.ResolvableType, java.util.function.Supplier<T>, java.lang.annotation.Annotation[], java.util.EnumSet<org.springframework.boot.context.properties.bind.Bindable$BindRestriction>);
    Code:
       0: aload_0
       1: invokespecial #1                  // Method java/lang/Object."<init>":()V
       4: aload_0
       5: aload_1
       6: putfield      #7                  // Field type:Lorg/springframework/core/ResolvableType;
       9: aload_0
      10: aload_2
      11: putfield      #13                 // Field boxedType:Lorg/springframework/core/ResolvableType;
      14: aload_0
      15: aload_3
      16: putfield      #16                 // Field value:Ljava/util/function/Supplier;
      19: aload_0
      20: aload         4
      22: putfield      #20                 // Field annotations:[Ljava/lang/annotation/Annotation;
      25: aload_0
      26: aload         5
      28: putfield      #24                 // Field bindRestrictions:Ljava/util/EnumSet;
      31: return

  public org.springframework.core.ResolvableType getType();
    Code:
       0: aload_0
       1: getfield      #7                  // Field type:Lorg/springframework/core/ResolvableType;
       4: areturn

  public org.springframework.core.ResolvableType getBoxedType();
    Code:
       0: aload_0
       1: getfield      #13                 // Field boxedType:Lorg/springframework/core/ResolvableType;
       4: areturn

  public java.util.function.Supplier<T> getValue();
    Code:
       0: aload_0
       1: getfield      #16                 // Field value:Ljava/util/function/Supplier;
       4: areturn

  public java.lang.annotation.Annotation[] getAnnotations();
    Code:
       0: aload_0
       1: getfield      #20                 // Field annotations:[Ljava/lang/annotation/Annotation;
       4: areturn

  public <A extends java.lang.annotation.Annotation> A getAnnotation(java.lang.Class<A>);
    Code:
       0: aload_0
       1: getfield      #20                 // Field annotations:[Ljava/lang/annotation/Annotation;
       4: astore_2
       5: aload_2
       6: arraylength
       7: istore_3
       8: iconst_0
       9: istore        4
      11: iload         4
      13: iload_3
      14: if_icmpge     41
      17: aload_2
      18: iload         4
      20: aaload
      21: astore        5
      23: aload_1
      24: aload         5
      26: invokevirtual #28                 // Method java/lang/Class.isInstance:(Ljava/lang/Object;)Z
      29: ifeq          35
      32: aload         5
      34: areturn
      35: iinc          4, 1
      38: goto          11
      41: aconst_null
      42: areturn

  public boolean hasBindRestriction(org.springframework.boot.context.properties.bind.Bindable$BindRestriction);
    Code:
       0: aload_0
       1: getfield      #24                 // Field bindRestrictions:Ljava/util/EnumSet;
       4: aload_1
       5: invokevirtual #34                 // Method java/util/EnumSet.contains:(Ljava/lang/Object;)Z
       8: ireturn

  public boolean equals(java.lang.Object);
    Code:
       0: aload_0
       1: aload_1
       2: if_acmpne     7
       5: iconst_1
       6: ireturn
       7: aload_1
       8: ifnull        22
      11: aload_0
      12: invokevirtual #39                 // Method java/lang/Object.getClass:()Ljava/lang/Class;
      15: aload_1
      16: invokevirtual #39                 // Method java/lang/Object.getClass:()Ljava/lang/Class;
      19: if_acmpeq     24
      22: iconst_0
      23: ireturn
      24: aload_1
      25: checkcast     #8                  // class org/springframework/boot/context/properties/bind/Bindable
      28: astore_2
      29: iconst_1
      30: istore_3
      31: iload_3
      32: ifeq          60
      35: aload_0
      36: aload_0
      37: getfield      #7                  // Field type:Lorg/springframework/core/ResolvableType;
      40: invokevirtual #43                 // Method org/springframework/core/ResolvableType.resolve:()Ljava/lang/Class;
      43: aload_2
      44: getfield      #7                  // Field type:Lorg/springframework/core/ResolvableType;
      47: invokevirtual #43                 // Method org/springframework/core/ResolvableType.resolve:()Ljava/lang/Class;
      50: invokevirtual #48                 // Method nullSafeEquals:(Ljava/lang/Object;Ljava/lang/Object;)Z
      53: ifeq          60
      56: iconst_1
      57: goto          61
      60: iconst_0
      61: istore_3
      62: iload_3
      63: ifeq          85
      66: aload_0
      67: aload_0
      68: getfield      #20                 // Field annotations:[Ljava/lang/annotation/Annotation;
      71: aload_2
      72: getfield      #20                 // Field annotations:[Ljava/lang/annotation/Annotation;
      75: invokevirtual #48                 // Method nullSafeEquals:(Ljava/lang/Object;Ljava/lang/Object;)Z
      78: ifeq          85
      81: iconst_1
      82: goto          86
      85: iconst_0
      86: istore_3
      87: iload_3
      88: ifeq          110
      91: aload_0
      92: aload_0
      93: getfield      #24                 // Field bindRestrictions:Ljava/util/EnumSet;
      96: aload_2
      97: getfield      #24                 // Field bindRestrictions:Ljava/util/EnumSet;
     100: invokevirtual #48                 // Method nullSafeEquals:(Ljava/lang/Object;Ljava/lang/Object;)Z
     103: ifeq          110
     106: iconst_1
     107: goto          111
     110: iconst_0
     111: istore_3
     112: iload_3
     113: ireturn

  public int hashCode();
    Code:
       0: bipush        31
       2: istore_1
       3: iconst_1
       4: istore_2
       5: bipush        31
       7: iload_2
       8: imul
       9: aload_0
      10: getfield      #7                  // Field type:Lorg/springframework/core/ResolvableType;
      13: invokestatic  #52                 // Method org/springframework/util/ObjectUtils.nullSafeHashCode:(Ljava/lang/Object;)I
      16: iadd
      17: istore_2
      18: bipush        31
      20: iload_2
      21: imul
      22: aload_0
      23: getfield      #20                 // Field annotations:[Ljava/lang/annotation/Annotation;
      26: invokestatic  #58                 // Method org/springframework/util/ObjectUtils.nullSafeHashCode:([Ljava/lang/Object;)I
      29: iadd
      30: istore_2
      31: bipush        31
      33: iload_2
      34: imul
      35: aload_0
      36: getfield      #24                 // Field bindRestrictions:Ljava/util/EnumSet;
      39: invokestatic  #52                 // Method org/springframework/util/ObjectUtils.nullSafeHashCode:(Ljava/lang/Object;)I
      42: iadd
      43: istore_2
      44: iload_2
      45: ireturn

  public java.lang.String toString();
    Code:
       0: new           #61                 // class org/springframework/core/style/ToStringCreator
       3: dup
       4: aload_0
       5: invokespecial #63                 // Method org/springframework/core/style/ToStringCreator."<init>":(Ljava/lang/Object;)V
       8: astore_1
       9: aload_1
      10: ldc           #66                 // String type
      12: aload_0
      13: getfield      #7                  // Field type:Lorg/springframework/core/ResolvableType;
      16: invokevirtual #67                 // Method org/springframework/core/style/ToStringCreator.append:(Ljava/lang/String;Ljava/lang/Object;)Lorg/springframework/core/style/ToStringCreator;
      19: pop
      20: aload_1
      21: ldc           #71                 // String value
      23: aload_0
      24: getfield      #16                 // Field value:Ljava/util/function/Supplier;
      27: ifnull        35
      30: ldc           #72                 // String provided
      32: goto          37
      35: ldc           #74                 // String none
      37: invokevirtual #67                 // Method org/springframework/core/style/ToStringCreator.append:(Ljava/lang/String;Ljava/lang/Object;)Lorg/springframework/core/style/ToStringCreator;
      40: pop
      41: aload_1
      42: ldc           #76                 // String annotations
      44: aload_0
      45: getfield      #20                 // Field annotations:[Ljava/lang/annotation/Annotation;
      48: invokevirtual #67                 // Method org/springframework/core/style/ToStringCreator.append:(Ljava/lang/String;Ljava/lang/Object;)Lorg/springframework/core/style/ToStringCreator;
      51: pop
      52: aload_1
      53: invokevirtual #77                 // Method org/springframework/core/style/ToStringCreator.toString:()Ljava/lang/String;
      56: areturn

  private boolean nullSafeEquals(java.lang.Object, java.lang.Object);
    Code:
       0: aload_1
       1: aload_2
       2: invokestatic  #81                 // Method org/springframework/util/ObjectUtils.nullSafeEquals:(Ljava/lang/Object;Ljava/lang/Object;)Z
       5: ireturn

  public org.springframework.boot.context.properties.bind.Bindable<T> withAnnotations(java.lang.annotation.Annotation...);
    Code:
       0: new           #8                  // class org/springframework/boot/context/properties/bind/Bindable
       3: dup
       4: aload_0
       5: getfield      #7                  // Field type:Lorg/springframework/core/ResolvableType;
       8: aload_0
       9: getfield      #13                 // Field boxedType:Lorg/springframework/core/ResolvableType;
      12: aload_0
      13: getfield      #16                 // Field value:Ljava/util/function/Supplier;
      16: aload_1
      17: ifnull        24
      20: aload_1
      21: goto          27
      24: getstatic     #82                 // Field NO_ANNOTATIONS:[Ljava/lang/annotation/Annotation;
      27: getstatic     #85                 // Field NO_BIND_RESTRICTIONS:Ljava/util/EnumSet;
      30: invokespecial #88                 // Method "<init>":(Lorg/springframework/core/ResolvableType;Lorg/springframework/core/ResolvableType;Ljava/util/function/Supplier;[Ljava/lang/annotation/Annotation;Ljava/util/EnumSet;)V
      33: areturn

  public org.springframework.boot.context.properties.bind.Bindable<T> withExistingValue(T);
    Code:
       0: aload_1
       1: ifnull        28
       4: aload_0
       5: getfield      #7                  // Field type:Lorg/springframework/core/ResolvableType;
       8: invokevirtual #91                 // Method org/springframework/core/ResolvableType.isArray:()Z
      11: ifne          28
      14: aload_0
      15: getfield      #13                 // Field boxedType:Lorg/springframework/core/ResolvableType;
      18: invokevirtual #43                 // Method org/springframework/core/ResolvableType.resolve:()Ljava/lang/Class;
      21: aload_1
      22: invokevirtual #28                 // Method java/lang/Class.isInstance:(Ljava/lang/Object;)Z
      25: ifeq          32
      28: iconst_1
      29: goto          33
      32: iconst_0
      33: aload_0
      34: invokedynamic #95,  0             // InvokeDynamic #0:get:(Lorg/springframework/boot/context/properties/bind/Bindable;)Ljava/util/function/Supplier;
      39: invokestatic  #99                 // Method org/springframework/util/Assert.isTrue:(ZLjava/util/function/Supplier;)V
      42: aload_1
      43: ifnull        55
      46: aload_1
      47: invokedynamic #105,  0            // InvokeDynamic #1:get:(Ljava/lang/Object;)Ljava/util/function/Supplier;
      52: goto          56
      55: aconst_null
      56: astore_2
      57: new           #8                  // class org/springframework/boot/context/properties/bind/Bindable
      60: dup
      61: aload_0
      62: getfield      #7                  // Field type:Lorg/springframework/core/ResolvableType;
      65: aload_0
      66: getfield      #13                 // Field boxedType:Lorg/springframework/core/ResolvableType;
      69: aload_2
      70: aload_0
      71: getfield      #20                 // Field annotations:[Ljava/lang/annotation/Annotation;
      74: aload_0
      75: getfield      #24                 // Field bindRestrictions:Ljava/util/EnumSet;
      78: invokespecial #88                 // Method "<init>":(Lorg/springframework/core/ResolvableType;Lorg/springframework/core/ResolvableType;Ljava/util/function/Supplier;[Ljava/lang/annotation/Annotation;Ljava/util/EnumSet;)V
      81: areturn

  public org.springframework.boot.context.properties.bind.Bindable<T> withSuppliedValue(java.util.function.Supplier<T>);
    Code:
       0: new           #8                  // class org/springframework/boot/context/properties/bind/Bindable
       3: dup
       4: aload_0
       5: getfield      #7                  // Field type:Lorg/springframework/core/ResolvableType;
       8: aload_0
       9: getfield      #13                 // Field boxedType:Lorg/springframework/core/ResolvableType;
      12: aload_1
      13: aload_0
      14: getfield      #20                 // Field annotations:[Ljava/lang/annotation/Annotation;
      17: aload_0
      18: getfield      #24                 // Field bindRestrictions:Ljava/util/EnumSet;
      21: invokespecial #88                 // Method "<init>":(Lorg/springframework/core/ResolvableType;Lorg/springframework/core/ResolvableType;Ljava/util/function/Supplier;[Ljava/lang/annotation/Annotation;Ljava/util/EnumSet;)V
      24: areturn

  public org.springframework.boot.context.properties.bind.Bindable<T> withBindRestrictions(org.springframework.boot.context.properties.bind.Bindable$BindRestriction...);
    Code:
       0: aload_0
       1: getfield      #24                 // Field bindRestrictions:Ljava/util/EnumSet;
       4: invokestatic  #108                // Method java/util/EnumSet.copyOf:(Ljava/util/EnumSet;)Ljava/util/EnumSet;
       7: astore_2
       8: aload_2
       9: aload_1
      10: invokestatic  #112                // Method java/util/Arrays.asList:([Ljava/lang/Object;)Ljava/util/List;
      13: invokevirtual #118                // Method java/util/EnumSet.addAll:(Ljava/util/Collection;)Z
      16: pop
      17: new           #8                  // class org/springframework/boot/context/properties/bind/Bindable
      20: dup
      21: aload_0
      22: getfield      #7                  // Field type:Lorg/springframework/core/ResolvableType;
      25: aload_0
      26: getfield      #13                 // Field boxedType:Lorg/springframework/core/ResolvableType;
      29: aload_0
      30: getfield      #16                 // Field value:Ljava/util/function/Supplier;
      33: aload_0
      34: getfield      #20                 // Field annotations:[Ljava/lang/annotation/Annotation;
      37: aload_2
      38: invokespecial #88                 // Method "<init>":(Lorg/springframework/core/ResolvableType;Lorg/springframework/core/ResolvableType;Ljava/util/function/Supplier;[Ljava/lang/annotation/Annotation;Ljava/util/EnumSet;)V
      41: areturn

  public static <T> org.springframework.boot.context.properties.bind.Bindable<T> ofInstance(T);
    Code:
       0: aload_0
       1: ldc           #122                // String Instance must not be null
       3: invokestatic  #124                // Method org/springframework/util/Assert.notNull:(Ljava/lang/Object;Ljava/lang/String;)V
       6: aload_0
       7: invokevirtual #39                 // Method java/lang/Object.getClass:()Ljava/lang/Class;
      10: astore_1
      11: aload_1
      12: invokestatic  #128                // Method of:(Ljava/lang/Class;)Lorg/springframework/boot/context/properties/bind/Bindable;
      15: aload_0
      16: invokevirtual #132                // Method withExistingValue:(Ljava/lang/Object;)Lorg/springframework/boot/context/properties/bind/Bindable;
      19: areturn

  public static <T> org.springframework.boot.context.properties.bind.Bindable<T> of(java.lang.Class<T>);
    Code:
       0: aload_0
       1: ldc           #136                // String Type must not be null
       3: invokestatic  #124                // Method org/springframework/util/Assert.notNull:(Ljava/lang/Object;Ljava/lang/String;)V
       6: aload_0
       7: invokestatic  #138                // Method org/springframework/core/ResolvableType.forClass:(Ljava/lang/Class;)Lorg/springframework/core/ResolvableType;
      10: invokestatic  #142                // Method of:(Lorg/springframework/core/ResolvableType;)Lorg/springframework/boot/context/properties/bind/Bindable;
      13: areturn

  public static <E> org.springframework.boot.context.properties.bind.Bindable<java.util.List<E>> listOf(java.lang.Class<E>);
    Code:
       0: ldc           #145                // class java/util/List
       2: iconst_1
       3: anewarray     #29                 // class java/lang/Class
       6: dup
       7: iconst_0
       8: aload_0
       9: aastore
      10: invokestatic  #147                // Method org/springframework/core/ResolvableType.forClassWithGenerics:(Ljava/lang/Class;[Ljava/lang/Class;)Lorg/springframework/core/ResolvableType;
      13: invokestatic  #142                // Method of:(Lorg/springframework/core/ResolvableType;)Lorg/springframework/boot/context/properties/bind/Bindable;
      16: areturn

  public static <E> org.springframework.boot.context.properties.bind.Bindable<java.util.Set<E>> setOf(java.lang.Class<E>);
    Code:
       0: ldc           #151                // class java/util/Set
       2: iconst_1
       3: anewarray     #29                 // class java/lang/Class
       6: dup
       7: iconst_0
       8: aload_0
       9: aastore
      10: invokestatic  #147                // Method org/springframework/core/ResolvableType.forClassWithGenerics:(Ljava/lang/Class;[Ljava/lang/Class;)Lorg/springframework/core/ResolvableType;
      13: invokestatic  #142                // Method of:(Lorg/springframework/core/ResolvableType;)Lorg/springframework/boot/context/properties/bind/Bindable;
      16: areturn

  public static <K, V> org.springframework.boot.context.properties.bind.Bindable<java.util.Map<K, V>> mapOf(java.lang.Class<K>, java.lang.Class<V>);
    Code:
       0: ldc           #153                // class java/util/Map
       2: iconst_2
       3: anewarray     #29                 // class java/lang/Class
       6: dup
       7: iconst_0
       8: aload_0
       9: aastore
      10: dup
      11: iconst_1
      12: aload_1
      13: aastore
      14: invokestatic  #147                // Method org/springframework/core/ResolvableType.forClassWithGenerics:(Ljava/lang/Class;[Ljava/lang/Class;)Lorg/springframework/core/ResolvableType;
      17: invokestatic  #142                // Method of:(Lorg/springframework/core/ResolvableType;)Lorg/springframework/boot/context/properties/bind/Bindable;
      20: areturn

  public static <T> org.springframework.boot.context.properties.bind.Bindable<T> of(org.springframework.core.ResolvableType);
    Code:
       0: aload_0
       1: ldc           #136                // String Type must not be null
       3: invokestatic  #124                // Method org/springframework/util/Assert.notNull:(Ljava/lang/Object;Ljava/lang/String;)V
       6: aload_0
       7: invokestatic  #155                // Method box:(Lorg/springframework/core/ResolvableType;)Lorg/springframework/core/ResolvableType;
      10: astore_1
      11: new           #8                  // class org/springframework/boot/context/properties/bind/Bindable
      14: dup
      15: aload_0
      16: aload_1
      17: aconst_null
      18: getstatic     #82                 // Field NO_ANNOTATIONS:[Ljava/lang/annotation/Annotation;
      21: getstatic     #85                 // Field NO_BIND_RESTRICTIONS:Ljava/util/EnumSet;
      24: invokespecial #88                 // Method "<init>":(Lorg/springframework/core/ResolvableType;Lorg/springframework/core/ResolvableType;Ljava/util/function/Supplier;[Ljava/lang/annotation/Annotation;Ljava/util/EnumSet;)V
      27: areturn

  private static org.springframework.core.ResolvableType box(org.springframework.core.ResolvableType);
    Code:
       0: aload_0
       1: invokevirtual #43                 // Method org/springframework/core/ResolvableType.resolve:()Ljava/lang/Class;
       4: astore_1
       5: aload_1
       6: ifnull        36
       9: aload_1
      10: invokevirtual #159                // Method java/lang/Class.isPrimitive:()Z
      13: ifeq          36
      16: aload_1
      17: iconst_1
      18: invokestatic  #162                // Method java/lang/reflect/Array.newInstance:(Ljava/lang/Class;I)Ljava/lang/Object;
      21: astore_2
      22: aload_2
      23: iconst_0
      24: invokestatic  #168                // Method java/lang/reflect/Array.get:(Ljava/lang/Object;I)Ljava/lang/Object;
      27: invokevirtual #39                 // Method java/lang/Object.getClass:()Ljava/lang/Class;
      30: astore_3
      31: aload_3
      32: invokestatic  #138                // Method org/springframework/core/ResolvableType.forClass:(Ljava/lang/Class;)Lorg/springframework/core/ResolvableType;
      35: areturn
      36: aload_1
      37: ifnull        58
      40: aload_1
      41: invokevirtual #171                // Method java/lang/Class.isArray:()Z
      44: ifeq          58
      47: aload_0
      48: invokevirtual #172                // Method org/springframework/core/ResolvableType.getComponentType:()Lorg/springframework/core/ResolvableType;
      51: invokestatic  #155                // Method box:(Lorg/springframework/core/ResolvableType;)Lorg/springframework/core/ResolvableType;
      54: invokestatic  #176                // Method org/springframework/core/ResolvableType.forArrayComponent:(Lorg/springframework/core/ResolvableType;)Lorg/springframework/core/ResolvableType;
      57: areturn
      58: aload_0
      59: areturn

  private static java.lang.Object lambda$withExistingValue$1(java.lang.Object);
    Code:
       0: aload_0
       1: areturn

  private java.lang.String lambda$withExistingValue$0();
    Code:
       0: aload_0
       1: getfield      #7                  // Field type:Lorg/springframework/core/ResolvableType;
       4: invokedynamic #179,  0            // InvokeDynamic #2:makeConcatWithConstants:(Lorg/springframework/core/ResolvableType;)Ljava/lang/String;
       9: areturn

  static {};
    Code:
       0: iconst_0
       1: anewarray     #183                // class java/lang/annotation/Annotation
       4: putstatic     #82                 // Field NO_ANNOTATIONS:[Ljava/lang/annotation/Annotation;
       7: ldc           #185                // class org/springframework/boot/context/properties/bind/Bindable$BindRestriction
       9: invokestatic  #187                // Method java/util/EnumSet.noneOf:(Ljava/lang/Class;)Ljava/util/EnumSet;
      12: putstatic     #85                 // Field NO_BIND_RESTRICTIONS:Ljava/util/EnumSet;
      15: return
}
