Compiled from "Binder.java"
public class org.springframework.boot.context.properties.bind.Binder {
  private static final java.util.Set<java.lang.Class<?>> NON_BEAN_CLASSES;

  private final java.lang.Iterable<org.springframework.boot.context.properties.source.ConfigurationPropertySource> sources;

  private final org.springframework.boot.context.properties.bind.PlaceholdersResolver placeholdersResolver;

  private final org.springframework.boot.context.properties.bind.BindConverter bindConverter;

  private final org.springframework.boot.context.properties.bind.BindHandler defaultBindHandler;

  private final java.util.List<org.springframework.boot.context.properties.bind.DataObjectBinder> dataObjectBinders;

  public org.springframework.boot.context.properties.bind.Binder(org.springframework.boot.context.properties.source.ConfigurationPropertySource...);
    Code:
       0: aload_0
       1: aload_1
       2: ifnull        12
       5: aload_1
       6: invokestatic  #1                  // Method java/util/Arrays.asList:([Ljava/lang/Object;)Ljava/util/List;
       9: goto          13
      12: aconst_null
      13: aconst_null
      14: aconst_null
      15: aconst_null
      16: invokespecial #7                  // Method "<init>":(Ljava/lang/Iterable;Lorg/springframework/boot/context/properties/bind/PlaceholdersResolver;Lorg/springframework/core/convert/ConversionService;Ljava/util/function/Consumer;)V
      19: return

  public org.springframework.boot.context.properties.bind.Binder(java.lang.Iterable<org.springframework.boot.context.properties.source.ConfigurationPropertySource>);
    Code:
       0: aload_0
       1: aload_1
       2: aconst_null
       3: aconst_null
       4: aconst_null
       5: invokespecial #7                  // Method "<init>":(Ljava/lang/Iterable;Lorg/springframework/boot/context/properties/bind/PlaceholdersResolver;Lorg/springframework/core/convert/ConversionService;Ljava/util/function/Consumer;)V
       8: return

  public org.springframework.boot.context.properties.bind.Binder(java.lang.Iterable<org.springframework.boot.context.properties.source.ConfigurationPropertySource>, org.springframework.boot.context.properties.bind.PlaceholdersResolver);
    Code:
       0: aload_0
       1: aload_1
       2: aload_2
       3: aconst_null
       4: aconst_null
       5: invokespecial #7                  // Method "<init>":(Ljava/lang/Iterable;Lorg/springframework/boot/context/properties/bind/PlaceholdersResolver;Lorg/springframework/core/convert/ConversionService;Ljava/util/function/Consumer;)V
       8: return

  public org.springframework.boot.context.properties.bind.Binder(java.lang.Iterable<org.springframework.boot.context.properties.source.ConfigurationPropertySource>, org.springframework.boot.context.properties.bind.PlaceholdersResolver, org.springframework.core.convert.ConversionService);
    Code:
       0: aload_0
       1: aload_1
       2: aload_2
       3: aload_3
       4: aconst_null
       5: invokespecial #7                  // Method "<init>":(Ljava/lang/Iterable;Lorg/springframework/boot/context/properties/bind/PlaceholdersResolver;Lorg/springframework/core/convert/ConversionService;Ljava/util/function/Consumer;)V
       8: return

  public org.springframework.boot.context.properties.bind.Binder(java.lang.Iterable<org.springframework.boot.context.properties.source.ConfigurationPropertySource>, org.springframework.boot.context.properties.bind.PlaceholdersResolver, org.springframework.core.convert.ConversionService, java.util.function.Consumer<org.springframework.beans.PropertyEditorRegistry>);
    Code:
       0: aload_0
       1: aload_1
       2: aload_2
       3: aload_3
       4: aload         4
       6: aconst_null
       7: invokespecial #13                 // Method "<init>":(Ljava/lang/Iterable;Lorg/springframework/boot/context/properties/bind/PlaceholdersResolver;Lorg/springframework/core/convert/ConversionService;Ljava/util/function/Consumer;Lorg/springframework/boot/context/properties/bind/BindHandler;)V
      10: return

  public org.springframework.boot.context.properties.bind.Binder(java.lang.Iterable<org.springframework.boot.context.properties.source.ConfigurationPropertySource>, org.springframework.boot.context.properties.bind.PlaceholdersResolver, org.springframework.core.convert.ConversionService, java.util.function.Consumer<org.springframework.beans.PropertyEditorRegistry>, org.springframework.boot.context.properties.bind.BindHandler);
    Code:
       0: aload_0
       1: aload_1
       2: aload_2
       3: aload_3
       4: aload         4
       6: aload         5
       8: aconst_null
       9: invokespecial #16                 // Method "<init>":(Ljava/lang/Iterable;Lorg/springframework/boot/context/properties/bind/PlaceholdersResolver;Lorg/springframework/core/convert/ConversionService;Ljava/util/function/Consumer;Lorg/springframework/boot/context/properties/bind/BindHandler;Lorg/springframework/boot/context/properties/bind/BindConstructorProvider;)V
      12: return

  public org.springframework.boot.context.properties.bind.Binder(java.lang.Iterable<org.springframework.boot.context.properties.source.ConfigurationPropertySource>, org.springframework.boot.context.properties.bind.PlaceholdersResolver, org.springframework.core.convert.ConversionService, java.util.function.Consumer<org.springframework.beans.PropertyEditorRegistry>, org.springframework.boot.context.properties.bind.BindHandler, org.springframework.boot.context.properties.bind.BindConstructorProvider);
    Code:
       0: aload_0
       1: aload_1
       2: aload_2
       3: aload_3
       4: ifnull        14
       7: aload_3
       8: invokestatic  #19                 // Method java/util/Collections.singletonList:(Ljava/lang/Object;)Ljava/util/List;
      11: goto          18
      14: aconst_null
      15: checkcast     #25                 // class java/util/List
      18: aload         4
      20: aload         5
      22: aload         6
      24: invokespecial #27                 // Method "<init>":(Ljava/lang/Iterable;Lorg/springframework/boot/context/properties/bind/PlaceholdersResolver;Ljava/util/List;Ljava/util/function/Consumer;Lorg/springframework/boot/context/properties/bind/BindHandler;Lorg/springframework/boot/context/properties/bind/BindConstructorProvider;)V
      27: return

  public org.springframework.boot.context.properties.bind.Binder(java.lang.Iterable<org.springframework.boot.context.properties.source.ConfigurationPropertySource>, org.springframework.boot.context.properties.bind.PlaceholdersResolver, java.util.List<org.springframework.core.convert.ConversionService>, java.util.function.Consumer<org.springframework.beans.PropertyEditorRegistry>, org.springframework.boot.context.properties.bind.BindHandler, org.springframework.boot.context.properties.bind.BindConstructorProvider);
    Code:
       0: aload_0
       1: invokespecial #30                 // Method java/lang/Object."<init>":()V
       4: aload_1
       5: ldc           #35                 // String Sources must not be null
       7: invokestatic  #37                 // Method org/springframework/util/Assert.notNull:(Ljava/lang/Object;Ljava/lang/String;)V
      10: aload_1
      11: invokeinterface #43,  1           // InterfaceMethod java/lang/Iterable.iterator:()Ljava/util/Iterator;
      16: astore        7
      18: aload         7
      20: invokeinterface #49,  1           // InterfaceMethod java/util/Iterator.hasNext:()Z
      25: ifeq          50
      28: aload         7
      30: invokeinterface #55,  1           // InterfaceMethod java/util/Iterator.next:()Ljava/lang/Object;
      35: checkcast     #59                 // class org/springframework/boot/context/properties/source/ConfigurationPropertySource
      38: astore        8
      40: aload         8
      42: ldc           #61                 // String Sources must not contain null elements
      44: invokestatic  #37                 // Method org/springframework/util/Assert.notNull:(Ljava/lang/Object;Ljava/lang/String;)V
      47: goto          18
      50: aload_0
      51: aload_1
      52: putfield      #63                 // Field sources:Ljava/lang/Iterable;
      55: aload_0
      56: aload_2
      57: ifnull        64
      60: aload_2
      61: goto          67
      64: getstatic     #67                 // Field org/springframework/boot/context/properties/bind/PlaceholdersResolver.NONE:Lorg/springframework/boot/context/properties/bind/PlaceholdersResolver;
      67: putfield      #73                 // Field placeholdersResolver:Lorg/springframework/boot/context/properties/bind/PlaceholdersResolver;
      70: aload_0
      71: aload_3
      72: aload         4
      74: invokestatic  #76                 // Method org/springframework/boot/context/properties/bind/BindConverter.get:(Ljava/util/List;Ljava/util/function/Consumer;)Lorg/springframework/boot/context/properties/bind/BindConverter;
      77: putfield      #82                 // Field bindConverter:Lorg/springframework/boot/context/properties/bind/BindConverter;
      80: aload_0
      81: aload         5
      83: ifnull        91
      86: aload         5
      88: goto          94
      91: getstatic     #86                 // Field org/springframework/boot/context/properties/bind/BindHandler.DEFAULT:Lorg/springframework/boot/context/properties/bind/BindHandler;
      94: putfield      #92                 // Field defaultBindHandler:Lorg/springframework/boot/context/properties/bind/BindHandler;
      97: aload         6
      99: ifnonnull     107
     102: getstatic     #95                 // Field org/springframework/boot/context/properties/bind/BindConstructorProvider.DEFAULT:Lorg/springframework/boot/context/properties/bind/BindConstructorProvider;
     105: astore        6
     107: new           #100                // class org/springframework/boot/context/properties/bind/ValueObjectBinder
     110: dup
     111: aload         6
     113: invokespecial #102                // Method org/springframework/boot/context/properties/bind/ValueObjectBinder."<init>":(Lorg/springframework/boot/context/properties/bind/BindConstructorProvider;)V
     116: astore        7
     118: getstatic     #105                // Field org/springframework/boot/context/properties/bind/JavaBeanBinder.INSTANCE:Lorg/springframework/boot/context/properties/bind/JavaBeanBinder;
     121: astore        8
     123: aload_0
     124: iconst_2
     125: anewarray     #111                // class org/springframework/boot/context/properties/bind/DataObjectBinder
     128: dup
     129: iconst_0
     130: aload         7
     132: aastore
     133: dup
     134: iconst_1
     135: aload         8
     137: aastore
     138: invokestatic  #1                  // Method java/util/Arrays.asList:([Ljava/lang/Object;)Ljava/util/List;
     141: invokestatic  #113                // Method java/util/Collections.unmodifiableList:(Ljava/util/List;)Ljava/util/List;
     144: putfield      #117                // Field dataObjectBinders:Ljava/util/List;
     147: return

  public <T> org.springframework.boot.context.properties.bind.BindResult<T> bind(java.lang.String, java.lang.Class<T>);
    Code:
       0: aload_0
       1: aload_1
       2: aload_2
       3: invokestatic  #121                // Method org/springframework/boot/context/properties/bind/Bindable.of:(Ljava/lang/Class;)Lorg/springframework/boot/context/properties/bind/Bindable;
       6: invokevirtual #127                // Method bind:(Ljava/lang/String;Lorg/springframework/boot/context/properties/bind/Bindable;)Lorg/springframework/boot/context/properties/bind/BindResult;
       9: areturn

  public <T> org.springframework.boot.context.properties.bind.BindResult<T> bind(java.lang.String, org.springframework.boot.context.properties.bind.Bindable<T>);
    Code:
       0: aload_0
       1: aload_1
       2: invokestatic  #131                // Method org/springframework/boot/context/properties/source/ConfigurationPropertyName.of:(Ljava/lang/CharSequence;)Lorg/springframework/boot/context/properties/source/ConfigurationPropertyName;
       5: aload_2
       6: aconst_null
       7: invokevirtual #136                // Method bind:(Lorg/springframework/boot/context/properties/source/ConfigurationPropertyName;Lorg/springframework/boot/context/properties/bind/Bindable;Lorg/springframework/boot/context/properties/bind/BindHandler;)Lorg/springframework/boot/context/properties/bind/BindResult;
      10: areturn

  public <T> org.springframework.boot.context.properties.bind.BindResult<T> bind(org.springframework.boot.context.properties.source.ConfigurationPropertyName, org.springframework.boot.context.properties.bind.Bindable<T>);
    Code:
       0: aload_0
       1: aload_1
       2: aload_2
       3: aconst_null
       4: invokevirtual #136                // Method bind:(Lorg/springframework/boot/context/properties/source/ConfigurationPropertyName;Lorg/springframework/boot/context/properties/bind/Bindable;Lorg/springframework/boot/context/properties/bind/BindHandler;)Lorg/springframework/boot/context/properties/bind/BindResult;
       7: areturn

  public <T> org.springframework.boot.context.properties.bind.BindResult<T> bind(java.lang.String, org.springframework.boot.context.properties.bind.Bindable<T>, org.springframework.boot.context.properties.bind.BindHandler);
    Code:
       0: aload_0
       1: aload_1
       2: invokestatic  #131                // Method org/springframework/boot/context/properties/source/ConfigurationPropertyName.of:(Ljava/lang/CharSequence;)Lorg/springframework/boot/context/properties/source/ConfigurationPropertyName;
       5: aload_2
       6: aload_3
       7: invokevirtual #136                // Method bind:(Lorg/springframework/boot/context/properties/source/ConfigurationPropertyName;Lorg/springframework/boot/context/properties/bind/Bindable;Lorg/springframework/boot/context/properties/bind/BindHandler;)Lorg/springframework/boot/context/properties/bind/BindResult;
      10: areturn

  public <T> org.springframework.boot.context.properties.bind.BindResult<T> bind(org.springframework.boot.context.properties.source.ConfigurationPropertyName, org.springframework.boot.context.properties.bind.Bindable<T>, org.springframework.boot.context.properties.bind.BindHandler);
    Code:
       0: aload_0
       1: aload_1
       2: aload_2
       3: aload_3
       4: iconst_0
       5: invokevirtual #139                // Method bind:(Lorg/springframework/boot/context/properties/source/ConfigurationPropertyName;Lorg/springframework/boot/context/properties/bind/Bindable;Lorg/springframework/boot/context/properties/bind/BindHandler;Z)Ljava/lang/Object;
       8: astore        4
      10: aload         4
      12: invokestatic  #142                // Method org/springframework/boot/context/properties/bind/BindResult.of:(Ljava/lang/Object;)Lorg/springframework/boot/context/properties/bind/BindResult;
      15: areturn

  public <T> T bindOrCreate(java.lang.String, java.lang.Class<T>);
    Code:
       0: aload_0
       1: aload_1
       2: aload_2
       3: invokestatic  #121                // Method org/springframework/boot/context/properties/bind/Bindable.of:(Ljava/lang/Class;)Lorg/springframework/boot/context/properties/bind/Bindable;
       6: invokevirtual #147                // Method bindOrCreate:(Ljava/lang/String;Lorg/springframework/boot/context/properties/bind/Bindable;)Ljava/lang/Object;
       9: areturn

  public <T> T bindOrCreate(java.lang.String, org.springframework.boot.context.properties.bind.Bindable<T>);
    Code:
       0: aload_0
       1: aload_1
       2: invokestatic  #131                // Method org/springframework/boot/context/properties/source/ConfigurationPropertyName.of:(Ljava/lang/CharSequence;)Lorg/springframework/boot/context/properties/source/ConfigurationPropertyName;
       5: aload_2
       6: aconst_null
       7: invokevirtual #151                // Method bindOrCreate:(Lorg/springframework/boot/context/properties/source/ConfigurationPropertyName;Lorg/springframework/boot/context/properties/bind/Bindable;Lorg/springframework/boot/context/properties/bind/BindHandler;)Ljava/lang/Object;
      10: areturn

  public <T> T bindOrCreate(java.lang.String, org.springframework.boot.context.properties.bind.Bindable<T>, org.springframework.boot.context.properties.bind.BindHandler);
    Code:
       0: aload_0
       1: aload_1
       2: invokestatic  #131                // Method org/springframework/boot/context/properties/source/ConfigurationPropertyName.of:(Ljava/lang/CharSequence;)Lorg/springframework/boot/context/properties/source/ConfigurationPropertyName;
       5: aload_2
       6: aload_3
       7: invokevirtual #151                // Method bindOrCreate:(Lorg/springframework/boot/context/properties/source/ConfigurationPropertyName;Lorg/springframework/boot/context/properties/bind/Bindable;Lorg/springframework/boot/context/properties/bind/BindHandler;)Ljava/lang/Object;
      10: areturn

  public <T> T bindOrCreate(org.springframework.boot.context.properties.source.ConfigurationPropertyName, org.springframework.boot.context.properties.bind.Bindable<T>, org.springframework.boot.context.properties.bind.BindHandler);
    Code:
       0: aload_0
       1: aload_1
       2: aload_2
       3: aload_3
       4: iconst_1
       5: invokevirtual #139                // Method bind:(Lorg/springframework/boot/context/properties/source/ConfigurationPropertyName;Lorg/springframework/boot/context/properties/bind/Bindable;Lorg/springframework/boot/context/properties/bind/BindHandler;Z)Ljava/lang/Object;
       8: areturn

  private <T> T bind(org.springframework.boot.context.properties.source.ConfigurationPropertyName, org.springframework.boot.context.properties.bind.Bindable<T>, org.springframework.boot.context.properties.bind.BindHandler, boolean);
    Code:
       0: aload_1
       1: ldc           #154                // String Name must not be null
       3: invokestatic  #37                 // Method org/springframework/util/Assert.notNull:(Ljava/lang/Object;Ljava/lang/String;)V
       6: aload_2
       7: ldc           #156                // String Target must not be null
       9: invokestatic  #37                 // Method org/springframework/util/Assert.notNull:(Ljava/lang/Object;Ljava/lang/String;)V
      12: aload_3
      13: ifnull        20
      16: aload_3
      17: goto          24
      20: aload_0
      21: getfield      #92                 // Field defaultBindHandler:Lorg/springframework/boot/context/properties/bind/BindHandler;
      24: astore_3
      25: new           #158                // class org/springframework/boot/context/properties/bind/Binder$Context
      28: dup
      29: aload_0
      30: invokespecial #160                // Method org/springframework/boot/context/properties/bind/Binder$Context."<init>":(Lorg/springframework/boot/context/properties/bind/Binder;)V
      33: astore        5
      35: aload_0
      36: aload_1
      37: aload_2
      38: aload_3
      39: aload         5
      41: iconst_0
      42: iload         4
      44: invokevirtual #163                // Method bind:(Lorg/springframework/boot/context/properties/source/ConfigurationPropertyName;Lorg/springframework/boot/context/properties/bind/Bindable;Lorg/springframework/boot/context/properties/bind/BindHandler;Lorg/springframework/boot/context/properties/bind/Binder$Context;ZZ)Ljava/lang/Object;
      47: areturn

  private <T> T bind(org.springframework.boot.context.properties.source.ConfigurationPropertyName, org.springframework.boot.context.properties.bind.Bindable<T>, org.springframework.boot.context.properties.bind.BindHandler, org.springframework.boot.context.properties.bind.Binder$Context, boolean, boolean);
    Code:
       0: aload_3
       1: aload_1
       2: aload_2
       3: aload         4
       5: invokeinterface #166,  4          // InterfaceMethod org/springframework/boot/context/properties/bind/BindHandler.onStart:(Lorg/springframework/boot/context/properties/source/ConfigurationPropertyName;Lorg/springframework/boot/context/properties/bind/Bindable;Lorg/springframework/boot/context/properties/bind/BindContext;)Lorg/springframework/boot/context/properties/bind/Bindable;
      10: astore        7
      12: aload         7
      14: ifnonnull     30
      17: aload_0
      18: aload_1
      19: aload_2
      20: aload_3
      21: aload         4
      23: aconst_null
      24: iload         6
      26: invokevirtual #170                // Method handleBindResult:(Lorg/springframework/boot/context/properties/source/ConfigurationPropertyName;Lorg/springframework/boot/context/properties/bind/Bindable;Lorg/springframework/boot/context/properties/bind/BindHandler;Lorg/springframework/boot/context/properties/bind/Binder$Context;Ljava/lang/Object;Z)Ljava/lang/Object;
      29: areturn
      30: aload         7
      32: astore_2
      33: aload_0
      34: aload_1
      35: aload_2
      36: aload_3
      37: aload         4
      39: iload         5
      41: invokevirtual #174                // Method bindObject:(Lorg/springframework/boot/context/properties/source/ConfigurationPropertyName;Lorg/springframework/boot/context/properties/bind/Bindable;Lorg/springframework/boot/context/properties/bind/BindHandler;Lorg/springframework/boot/context/properties/bind/Binder$Context;Z)Ljava/lang/Object;
      44: astore        8
      46: aload_0
      47: aload_1
      48: aload_2
      49: aload_3
      50: aload         4
      52: aload         8
      54: iload         6
      56: invokevirtual #170                // Method handleBindResult:(Lorg/springframework/boot/context/properties/source/ConfigurationPropertyName;Lorg/springframework/boot/context/properties/bind/Bindable;Lorg/springframework/boot/context/properties/bind/BindHandler;Lorg/springframework/boot/context/properties/bind/Binder$Context;Ljava/lang/Object;Z)Ljava/lang/Object;
      59: areturn
      60: astore        7
      62: aload_0
      63: aload_1
      64: aload_2
      65: aload_3
      66: aload         4
      68: aload         7
      70: invokevirtual #180                // Method handleBindError:(Lorg/springframework/boot/context/properties/source/ConfigurationPropertyName;Lorg/springframework/boot/context/properties/bind/Bindable;Lorg/springframework/boot/context/properties/bind/BindHandler;Lorg/springframework/boot/context/properties/bind/Binder$Context;Ljava/lang/Exception;)Ljava/lang/Object;
      73: areturn
    Exception table:
       from    to  target type
           0    29    60   Class java/lang/Exception
          30    59    60   Class java/lang/Exception

  private <T> T handleBindResult(org.springframework.boot.context.properties.source.ConfigurationPropertyName, org.springframework.boot.context.properties.bind.Bindable<T>, org.springframework.boot.context.properties.bind.BindHandler, org.springframework.boot.context.properties.bind.Binder$Context, java.lang.Object, boolean) throws java.lang.Exception;
    Code:
       0: aload         5
       2: ifnull        32
       5: aload_3
       6: aload_1
       7: aload_2
       8: aload         4
      10: aload         5
      12: invokeinterface #184,  5          // InterfaceMethod org/springframework/boot/context/properties/bind/BindHandler.onSuccess:(Lorg/springframework/boot/context/properties/source/ConfigurationPropertyName;Lorg/springframework/boot/context/properties/bind/Bindable;Lorg/springframework/boot/context/properties/bind/BindContext;Ljava/lang/Object;)Ljava/lang/Object;
      17: astore        5
      19: aload         4
      21: invokevirtual #188                // Method org/springframework/boot/context/properties/bind/Binder$Context.getConverter:()Lorg/springframework/boot/context/properties/bind/BindConverter;
      24: aload         5
      26: aload_2
      27: invokevirtual #192                // Method org/springframework/boot/context/properties/bind/BindConverter.convert:(Ljava/lang/Object;Lorg/springframework/boot/context/properties/bind/Bindable;)Ljava/lang/Object;
      30: astore        5
      32: aload         5
      34: ifnonnull     97
      37: iload         6
      39: ifeq          97
      42: aload_0
      43: aload_2
      44: aload         4
      46: invokevirtual #196                // Method create:(Lorg/springframework/boot/context/properties/bind/Bindable;Lorg/springframework/boot/context/properties/bind/Binder$Context;)Ljava/lang/Object;
      49: astore        5
      51: aload_3
      52: aload_1
      53: aload_2
      54: aload         4
      56: aload         5
      58: invokeinterface #200,  5          // InterfaceMethod org/springframework/boot/context/properties/bind/BindHandler.onCreate:(Lorg/springframework/boot/context/properties/source/ConfigurationPropertyName;Lorg/springframework/boot/context/properties/bind/Bindable;Lorg/springframework/boot/context/properties/bind/BindContext;Ljava/lang/Object;)Ljava/lang/Object;
      63: astore        5
      65: aload         4
      67: invokevirtual #188                // Method org/springframework/boot/context/properties/bind/Binder$Context.getConverter:()Lorg/springframework/boot/context/properties/bind/BindConverter;
      70: aload         5
      72: aload_2
      73: invokevirtual #192                // Method org/springframework/boot/context/properties/bind/BindConverter.convert:(Ljava/lang/Object;Lorg/springframework/boot/context/properties/bind/Bindable;)Ljava/lang/Object;
      76: astore        5
      78: aload         5
      80: ifnull        87
      83: iconst_1
      84: goto          88
      87: iconst_0
      88: aload_2
      89: invokedynamic #203,  0            // InvokeDynamic #0:get:(Lorg/springframework/boot/context/properties/bind/Bindable;)Ljava/util/function/Supplier;
      94: invokestatic  #206                // Method org/springframework/util/Assert.state:(ZLjava/util/function/Supplier;)V
      97: aload_3
      98: aload_1
      99: aload_2
     100: aload         4
     102: aload         5
     104: invokeinterface #210,  5          // InterfaceMethod org/springframework/boot/context/properties/bind/BindHandler.onFinish:(Lorg/springframework/boot/context/properties/source/ConfigurationPropertyName;Lorg/springframework/boot/context/properties/bind/Bindable;Lorg/springframework/boot/context/properties/bind/BindContext;Ljava/lang/Object;)V
     109: aload         4
     111: invokevirtual #188                // Method org/springframework/boot/context/properties/bind/Binder$Context.getConverter:()Lorg/springframework/boot/context/properties/bind/BindConverter;
     114: aload         5
     116: aload_2
     117: invokevirtual #192                // Method org/springframework/boot/context/properties/bind/BindConverter.convert:(Ljava/lang/Object;Lorg/springframework/boot/context/properties/bind/Bindable;)Ljava/lang/Object;
     120: areturn

  private java.lang.Object create(org.springframework.boot.context.properties.bind.Bindable<?>, org.springframework.boot.context.properties.bind.Binder$Context);
    Code:
       0: aload_0
       1: getfield      #117                // Field dataObjectBinders:Ljava/util/List;
       4: invokeinterface #214,  1          // InterfaceMethod java/util/List.iterator:()Ljava/util/Iterator;
       9: astore_3
      10: aload_3
      11: invokeinterface #49,  1           // InterfaceMethod java/util/Iterator.hasNext:()Z
      16: ifeq          52
      19: aload_3
      20: invokeinterface #55,  1           // InterfaceMethod java/util/Iterator.next:()Ljava/lang/Object;
      25: checkcast     #111                // class org/springframework/boot/context/properties/bind/DataObjectBinder
      28: astore        4
      30: aload         4
      32: aload_1
      33: aload_2
      34: invokeinterface #215,  3          // InterfaceMethod org/springframework/boot/context/properties/bind/DataObjectBinder.create:(Lorg/springframework/boot/context/properties/bind/Bindable;Lorg/springframework/boot/context/properties/bind/Binder$Context;)Ljava/lang/Object;
      39: astore        5
      41: aload         5
      43: ifnull        49
      46: aload         5
      48: areturn
      49: goto          10
      52: aconst_null
      53: areturn

  private <T> T handleBindError(org.springframework.boot.context.properties.source.ConfigurationPropertyName, org.springframework.boot.context.properties.bind.Bindable<T>, org.springframework.boot.context.properties.bind.BindHandler, org.springframework.boot.context.properties.bind.Binder$Context, java.lang.Exception);
    Code:
       0: aload_3
       1: aload_1
       2: aload_2
       3: aload         4
       5: aload         5
       7: invokeinterface #216,  5          // InterfaceMethod org/springframework/boot/context/properties/bind/BindHandler.onFailure:(Lorg/springframework/boot/context/properties/source/ConfigurationPropertyName;Lorg/springframework/boot/context/properties/bind/Bindable;Lorg/springframework/boot/context/properties/bind/BindContext;Ljava/lang/Exception;)Ljava/lang/Object;
      12: astore        6
      14: aload         4
      16: invokevirtual #188                // Method org/springframework/boot/context/properties/bind/Binder$Context.getConverter:()Lorg/springframework/boot/context/properties/bind/BindConverter;
      19: aload         6
      21: aload_2
      22: invokevirtual #192                // Method org/springframework/boot/context/properties/bind/BindConverter.convert:(Ljava/lang/Object;Lorg/springframework/boot/context/properties/bind/Bindable;)Ljava/lang/Object;
      25: areturn
      26: astore        6
      28: aload         6
      30: instanceof    #220                // class org/springframework/boot/context/properties/bind/BindException
      33: ifeq          46
      36: aload         6
      38: checkcast     #220                // class org/springframework/boot/context/properties/bind/BindException
      41: astore        7
      43: aload         7
      45: athrow
      46: new           #220                // class org/springframework/boot/context/properties/bind/BindException
      49: dup
      50: aload_1
      51: aload_2
      52: aload         4
      54: invokevirtual #222                // Method org/springframework/boot/context/properties/bind/Binder$Context.getConfigurationProperty:()Lorg/springframework/boot/context/properties/source/ConfigurationProperty;
      57: aload         6
      59: invokespecial #226                // Method org/springframework/boot/context/properties/bind/BindException."<init>":(Lorg/springframework/boot/context/properties/source/ConfigurationPropertyName;Lorg/springframework/boot/context/properties/bind/Bindable;Lorg/springframework/boot/context/properties/source/ConfigurationProperty;Ljava/lang/Throwable;)V
      62: athrow
    Exception table:
       from    to  target type
           0    25    26   Class java/lang/Exception

  private <T> java.lang.Object bindObject(org.springframework.boot.context.properties.source.ConfigurationPropertyName, org.springframework.boot.context.properties.bind.Bindable<T>, org.springframework.boot.context.properties.bind.BindHandler, org.springframework.boot.context.properties.bind.Binder$Context, boolean);
    Code:
       0: aload_0
       1: aload_1
       2: aload_2
       3: aload         4
       5: invokevirtual #229                // Method findProperty:(Lorg/springframework/boot/context/properties/source/ConfigurationPropertyName;Lorg/springframework/boot/context/properties/bind/Bindable;Lorg/springframework/boot/context/properties/bind/Binder$Context;)Lorg/springframework/boot/context/properties/source/ConfigurationProperty;
       8: astore        6
      10: aload         6
      12: ifnonnull     38
      15: aload         4
      17: getfield      #233                // Field org/springframework/boot/context/properties/bind/Binder$Context.depth:I
      20: ifeq          38
      23: aload_0
      24: aload         4
      26: invokevirtual #237                // Method org/springframework/boot/context/properties/bind/Binder$Context.getSources:()Ljava/lang/Iterable;
      29: aload_1
      30: invokevirtual #241                // Method containsNoDescendantOf:(Ljava/lang/Iterable;Lorg/springframework/boot/context/properties/source/ConfigurationPropertyName;)Z
      33: ifeq          38
      36: aconst_null
      37: areturn
      38: aload_0
      39: aload_2
      40: aload         4
      42: invokevirtual #245                // Method getAggregateBinder:(Lorg/springframework/boot/context/properties/bind/Bindable;Lorg/springframework/boot/context/properties/bind/Binder$Context;)Lorg/springframework/boot/context/properties/bind/AggregateBinder;
      45: astore        7
      47: aload         7
      49: ifnull        64
      52: aload_0
      53: aload_1
      54: aload_2
      55: aload_3
      56: aload         4
      58: aload         7
      60: invokevirtual #249                // Method bindAggregate:(Lorg/springframework/boot/context/properties/source/ConfigurationPropertyName;Lorg/springframework/boot/context/properties/bind/Bindable;Lorg/springframework/boot/context/properties/bind/BindHandler;Lorg/springframework/boot/context/properties/bind/Binder$Context;Lorg/springframework/boot/context/properties/bind/AggregateBinder;)Ljava/lang/Object;
      63: areturn
      64: aload         6
      66: ifnull        105
      69: aload_0
      70: aload_2
      71: aload         4
      73: aload         6
      75: invokevirtual #253                // Method bindProperty:(Lorg/springframework/boot/context/properties/bind/Bindable;Lorg/springframework/boot/context/properties/bind/Binder$Context;Lorg/springframework/boot/context/properties/source/ConfigurationProperty;)Ljava/lang/Object;
      78: areturn
      79: astore        8
      81: aload_0
      82: aload_1
      83: aload_2
      84: aload_3
      85: aload         4
      87: iload         5
      89: invokevirtual #259                // Method bindDataObject:(Lorg/springframework/boot/context/properties/source/ConfigurationPropertyName;Lorg/springframework/boot/context/properties/bind/Bindable;Lorg/springframework/boot/context/properties/bind/BindHandler;Lorg/springframework/boot/context/properties/bind/Binder$Context;Z)Ljava/lang/Object;
      92: astore        9
      94: aload         9
      96: ifnull        102
      99: aload         9
     101: areturn
     102: aload         8
     104: athrow
     105: aload_0
     106: aload_1
     107: aload_2
     108: aload_3
     109: aload         4
     111: iload         5
     113: invokevirtual #259                // Method bindDataObject:(Lorg/springframework/boot/context/properties/source/ConfigurationPropertyName;Lorg/springframework/boot/context/properties/bind/Bindable;Lorg/springframework/boot/context/properties/bind/BindHandler;Lorg/springframework/boot/context/properties/bind/Binder$Context;Z)Ljava/lang/Object;
     116: areturn
    Exception table:
       from    to  target type
          69    78    79   Class org/springframework/core/convert/ConverterNotFoundException

  private org.springframework.boot.context.properties.bind.AggregateBinder<?> getAggregateBinder(org.springframework.boot.context.properties.bind.Bindable<?>, org.springframework.boot.context.properties.bind.Binder$Context);
    Code:
       0: aload_1
       1: invokevirtual #262                // Method org/springframework/boot/context/properties/bind/Bindable.getType:()Lorg/springframework/core/ResolvableType;
       4: ldc           #31                 // class java/lang/Object
       6: invokevirtual #266                // Method org/springframework/core/ResolvableType.resolve:(Ljava/lang/Class;)Ljava/lang/Class;
       9: astore_3
      10: ldc_w         #272                // class java/util/Map
      13: aload_3
      14: invokevirtual #274                // Method java/lang/Class.isAssignableFrom:(Ljava/lang/Class;)Z
      17: ifeq          29
      20: new           #280                // class org/springframework/boot/context/properties/bind/MapBinder
      23: dup
      24: aload_2
      25: invokespecial #282                // Method org/springframework/boot/context/properties/bind/MapBinder."<init>":(Lorg/springframework/boot/context/properties/bind/Binder$Context;)V
      28: areturn
      29: ldc_w         #285                // class java/util/Collection
      32: aload_3
      33: invokevirtual #274                // Method java/lang/Class.isAssignableFrom:(Ljava/lang/Class;)Z
      36: ifeq          48
      39: new           #287                // class org/springframework/boot/context/properties/bind/CollectionBinder
      42: dup
      43: aload_2
      44: invokespecial #289                // Method org/springframework/boot/context/properties/bind/CollectionBinder."<init>":(Lorg/springframework/boot/context/properties/bind/Binder$Context;)V
      47: areturn
      48: aload_1
      49: invokevirtual #262                // Method org/springframework/boot/context/properties/bind/Bindable.getType:()Lorg/springframework/core/ResolvableType;
      52: invokevirtual #290                // Method org/springframework/core/ResolvableType.isArray:()Z
      55: ifeq          67
      58: new           #293                // class org/springframework/boot/context/properties/bind/ArrayBinder
      61: dup
      62: aload_2
      63: invokespecial #295                // Method org/springframework/boot/context/properties/bind/ArrayBinder."<init>":(Lorg/springframework/boot/context/properties/bind/Binder$Context;)V
      66: areturn
      67: aconst_null
      68: areturn

  private <T> java.lang.Object bindAggregate(org.springframework.boot.context.properties.source.ConfigurationPropertyName, org.springframework.boot.context.properties.bind.Bindable<T>, org.springframework.boot.context.properties.bind.BindHandler, org.springframework.boot.context.properties.bind.Binder$Context, org.springframework.boot.context.properties.bind.AggregateBinder<?>);
    Code:
       0: aload_0
       1: aload         5
       3: aload_3
       4: aload         4
       6: invokedynamic #296,  0            // InvokeDynamic #1:bind:(Lorg/springframework/boot/context/properties/bind/Binder;Lorg/springframework/boot/context/properties/bind/AggregateBinder;Lorg/springframework/boot/context/properties/bind/BindHandler;Lorg/springframework/boot/context/properties/bind/Binder$Context;)Lorg/springframework/boot/context/properties/bind/AggregateElementBinder;
      11: astore        6
      13: aload         4
      15: aload         5
      17: aload_1
      18: aload_2
      19: aload         6
      21: invokedynamic #299,  0            // InvokeDynamic #2:get:(Lorg/springframework/boot/context/properties/bind/AggregateBinder;Lorg/springframework/boot/context/properties/source/ConfigurationPropertyName;Lorg/springframework/boot/context/properties/bind/Bindable;Lorg/springframework/boot/context/properties/bind/AggregateElementBinder;)Ljava/util/function/Supplier;
      26: invokevirtual #302                // Method org/springframework/boot/context/properties/bind/Binder$Context.withIncreasedDepth:(Ljava/util/function/Supplier;)Ljava/lang/Object;
      29: areturn

  private <T> org.springframework.boot.context.properties.source.ConfigurationProperty findProperty(org.springframework.boot.context.properties.source.ConfigurationPropertyName, org.springframework.boot.context.properties.bind.Bindable<T>, org.springframework.boot.context.properties.bind.Binder$Context);
    Code:
       0: aload_1
       1: invokevirtual #306                // Method org/springframework/boot/context/properties/source/ConfigurationPropertyName.isEmpty:()Z
       4: ifne          17
       7: aload_2
       8: getstatic     #309                // Field org/springframework/boot/context/properties/bind/Bindable$BindRestriction.NO_DIRECT_PROPERTY:Lorg/springframework/boot/context/properties/bind/Bindable$BindRestriction;
      11: invokevirtual #315                // Method org/springframework/boot/context/properties/bind/Bindable.hasBindRestriction:(Lorg/springframework/boot/context/properties/bind/Bindable$BindRestriction;)Z
      14: ifeq          19
      17: aconst_null
      18: areturn
      19: aload_3
      20: invokevirtual #237                // Method org/springframework/boot/context/properties/bind/Binder$Context.getSources:()Ljava/lang/Iterable;
      23: invokeinterface #43,  1           // InterfaceMethod java/lang/Iterable.iterator:()Ljava/util/Iterator;
      28: astore        4
      30: aload         4
      32: invokeinterface #49,  1           // InterfaceMethod java/util/Iterator.hasNext:()Z
      37: ifeq          73
      40: aload         4
      42: invokeinterface #55,  1           // InterfaceMethod java/util/Iterator.next:()Ljava/lang/Object;
      47: checkcast     #59                 // class org/springframework/boot/context/properties/source/ConfigurationPropertySource
      50: astore        5
      52: aload         5
      54: aload_1
      55: invokeinterface #319,  2          // InterfaceMethod org/springframework/boot/context/properties/source/ConfigurationPropertySource.getConfigurationProperty:(Lorg/springframework/boot/context/properties/source/ConfigurationPropertyName;)Lorg/springframework/boot/context/properties/source/ConfigurationProperty;
      60: astore        6
      62: aload         6
      64: ifnull        70
      67: aload         6
      69: areturn
      70: goto          30
      73: aconst_null
      74: areturn

  private <T> java.lang.Object bindProperty(org.springframework.boot.context.properties.bind.Bindable<T>, org.springframework.boot.context.properties.bind.Binder$Context, org.springframework.boot.context.properties.source.ConfigurationProperty);
    Code:
       0: aload_2
       1: aload_3
       2: invokevirtual #322                // Method org/springframework/boot/context/properties/bind/Binder$Context.setConfigurationProperty:(Lorg/springframework/boot/context/properties/source/ConfigurationProperty;)V
       5: aload_3
       6: invokevirtual #326                // Method org/springframework/boot/context/properties/source/ConfigurationProperty.getValue:()Ljava/lang/Object;
       9: astore        4
      11: aload_0
      12: getfield      #73                 // Field placeholdersResolver:Lorg/springframework/boot/context/properties/bind/PlaceholdersResolver;
      15: aload         4
      17: invokeinterface #331,  2          // InterfaceMethod org/springframework/boot/context/properties/bind/PlaceholdersResolver.resolvePlaceholders:(Ljava/lang/Object;)Ljava/lang/Object;
      22: astore        4
      24: aload_2
      25: invokevirtual #188                // Method org/springframework/boot/context/properties/bind/Binder$Context.getConverter:()Lorg/springframework/boot/context/properties/bind/BindConverter;
      28: aload         4
      30: aload_1
      31: invokevirtual #192                // Method org/springframework/boot/context/properties/bind/BindConverter.convert:(Ljava/lang/Object;Lorg/springframework/boot/context/properties/bind/Bindable;)Ljava/lang/Object;
      34: astore        4
      36: aload         4
      38: areturn

  private java.lang.Object bindDataObject(org.springframework.boot.context.properties.source.ConfigurationPropertyName, org.springframework.boot.context.properties.bind.Bindable<?>, org.springframework.boot.context.properties.bind.BindHandler, org.springframework.boot.context.properties.bind.Binder$Context, boolean);
    Code:
       0: aload_0
       1: aload_1
       2: aload_2
       3: aload         4
       5: invokevirtual #335                // Method isUnbindableBean:(Lorg/springframework/boot/context/properties/source/ConfigurationPropertyName;Lorg/springframework/boot/context/properties/bind/Bindable;Lorg/springframework/boot/context/properties/bind/Binder$Context;)Z
       8: ifeq          13
      11: aconst_null
      12: areturn
      13: aload_2
      14: invokevirtual #262                // Method org/springframework/boot/context/properties/bind/Bindable.getType:()Lorg/springframework/core/ResolvableType;
      17: ldc           #31                 // class java/lang/Object
      19: invokevirtual #266                // Method org/springframework/core/ResolvableType.resolve:(Ljava/lang/Class;)Ljava/lang/Class;
      22: astore        6
      24: iload         5
      26: ifne          41
      29: aload         4
      31: aload         6
      33: invokevirtual #339                // Method org/springframework/boot/context/properties/bind/Binder$Context.isBindingDataObject:(Ljava/lang/Class;)Z
      36: ifeq          41
      39: aconst_null
      40: areturn
      41: aload_0
      42: aload_1
      43: aload_3
      44: aload         4
      46: invokedynamic #342,  0            // InvokeDynamic #3:bindProperty:(Lorg/springframework/boot/context/properties/bind/Binder;Lorg/springframework/boot/context/properties/source/ConfigurationPropertyName;Lorg/springframework/boot/context/properties/bind/BindHandler;Lorg/springframework/boot/context/properties/bind/Binder$Context;)Lorg/springframework/boot/context/properties/bind/DataObjectPropertyBinder;
      51: astore        7
      53: aload         4
      55: aload         6
      57: aload_0
      58: aload_1
      59: aload_2
      60: aload         4
      62: aload         7
      64: invokedynamic #345,  0            // InvokeDynamic #4:get:(Lorg/springframework/boot/context/properties/bind/Binder;Lorg/springframework/boot/context/properties/source/ConfigurationPropertyName;Lorg/springframework/boot/context/properties/bind/Bindable;Lorg/springframework/boot/context/properties/bind/Binder$Context;Lorg/springframework/boot/context/properties/bind/DataObjectPropertyBinder;)Ljava/util/function/Supplier;
      69: invokevirtual #348                // Method org/springframework/boot/context/properties/bind/Binder$Context.withDataObject:(Ljava/lang/Class;Ljava/util/function/Supplier;)Ljava/lang/Object;
      72: areturn

  private boolean isUnbindableBean(org.springframework.boot.context.properties.source.ConfigurationPropertyName, org.springframework.boot.context.properties.bind.Bindable<?>, org.springframework.boot.context.properties.bind.Binder$Context);
    Code:
       0: aload_3
       1: invokevirtual #237                // Method org/springframework/boot/context/properties/bind/Binder$Context.getSources:()Ljava/lang/Iterable;
       4: invokeinterface #43,  1           // InterfaceMethod java/lang/Iterable.iterator:()Ljava/util/Iterator;
       9: astore        4
      11: aload         4
      13: invokeinterface #49,  1           // InterfaceMethod java/util/Iterator.hasNext:()Z
      18: ifeq          52
      21: aload         4
      23: invokeinterface #55,  1           // InterfaceMethod java/util/Iterator.next:()Ljava/lang/Object;
      28: checkcast     #59                 // class org/springframework/boot/context/properties/source/ConfigurationPropertySource
      31: astore        5
      33: aload         5
      35: aload_1
      36: invokeinterface #352,  2          // InterfaceMethod org/springframework/boot/context/properties/source/ConfigurationPropertySource.containsDescendantOf:(Lorg/springframework/boot/context/properties/source/ConfigurationPropertyName;)Lorg/springframework/boot/context/properties/source/ConfigurationPropertyState;
      41: getstatic     #356                // Field org/springframework/boot/context/properties/source/ConfigurationPropertyState.PRESENT:Lorg/springframework/boot/context/properties/source/ConfigurationPropertyState;
      44: if_acmpne     49
      47: iconst_0
      48: ireturn
      49: goto          11
      52: aload_2
      53: invokevirtual #262                // Method org/springframework/boot/context/properties/bind/Bindable.getType:()Lorg/springframework/core/ResolvableType;
      56: ldc           #31                 // class java/lang/Object
      58: invokevirtual #266                // Method org/springframework/core/ResolvableType.resolve:(Ljava/lang/Class;)Ljava/lang/Class;
      61: astore        4
      63: aload         4
      65: invokevirtual #362                // Method java/lang/Class.isPrimitive:()Z
      68: ifne          84
      71: getstatic     #365                // Field NON_BEAN_CLASSES:Ljava/util/Set;
      74: aload         4
      76: invokeinterface #369,  2          // InterfaceMethod java/util/Set.contains:(Ljava/lang/Object;)Z
      81: ifeq          86
      84: iconst_1
      85: ireturn
      86: aload         4
      88: invokevirtual #375                // Method java/lang/Class.getName:()Ljava/lang/String;
      91: ldc_w         #379                // String java.
      94: invokevirtual #381                // Method java/lang/String.startsWith:(Ljava/lang/String;)Z
      97: ireturn

  private boolean containsNoDescendantOf(java.lang.Iterable<org.springframework.boot.context.properties.source.ConfigurationPropertySource>, org.springframework.boot.context.properties.source.ConfigurationPropertyName);
    Code:
       0: aload_1
       1: invokeinterface #43,  1           // InterfaceMethod java/lang/Iterable.iterator:()Ljava/util/Iterator;
       6: astore_3
       7: aload_3
       8: invokeinterface #49,  1           // InterfaceMethod java/util/Iterator.hasNext:()Z
      13: ifeq          46
      16: aload_3
      17: invokeinterface #55,  1           // InterfaceMethod java/util/Iterator.next:()Ljava/lang/Object;
      22: checkcast     #59                 // class org/springframework/boot/context/properties/source/ConfigurationPropertySource
      25: astore        4
      27: aload         4
      29: aload_2
      30: invokeinterface #352,  2          // InterfaceMethod org/springframework/boot/context/properties/source/ConfigurationPropertySource.containsDescendantOf:(Lorg/springframework/boot/context/properties/source/ConfigurationPropertyName;)Lorg/springframework/boot/context/properties/source/ConfigurationPropertyState;
      35: getstatic     #387                // Field org/springframework/boot/context/properties/source/ConfigurationPropertyState.ABSENT:Lorg/springframework/boot/context/properties/source/ConfigurationPropertyState;
      38: if_acmpeq     43
      41: iconst_0
      42: ireturn
      43: goto          7
      46: iconst_1
      47: ireturn

  public static org.springframework.boot.context.properties.bind.Binder get(org.springframework.core.env.Environment);
    Code:
       0: aload_0
       1: aconst_null
       2: invokestatic  #390                // Method get:(Lorg/springframework/core/env/Environment;Lorg/springframework/boot/context/properties/bind/BindHandler;)Lorg/springframework/boot/context/properties/bind/Binder;
       5: areturn

  public static org.springframework.boot.context.properties.bind.Binder get(org.springframework.core.env.Environment, org.springframework.boot.context.properties.bind.BindHandler);
    Code:
       0: aload_0
       1: invokestatic  #393                // Method org/springframework/boot/context/properties/source/ConfigurationPropertySources.get:(Lorg/springframework/core/env/Environment;)Ljava/lang/Iterable;
       4: astore_2
       5: new           #398                // class org/springframework/boot/context/properties/bind/PropertySourcesPlaceholdersResolver
       8: dup
       9: aload_0
      10: invokespecial #400                // Method org/springframework/boot/context/properties/bind/PropertySourcesPlaceholdersResolver."<init>":(Lorg/springframework/core/env/Environment;)V
      13: astore_3
      14: new           #8                  // class org/springframework/boot/context/properties/bind/Binder
      17: dup
      18: aload_2
      19: aload_3
      20: aconst_null
      21: aconst_null
      22: aload_1
      23: invokespecial #13                 // Method "<init>":(Ljava/lang/Iterable;Lorg/springframework/boot/context/properties/bind/PlaceholdersResolver;Lorg/springframework/core/convert/ConversionService;Ljava/util/function/Consumer;Lorg/springframework/boot/context/properties/bind/BindHandler;)V
      26: areturn

  private java.lang.Object lambda$bindDataObject$5(org.springframework.boot.context.properties.source.ConfigurationPropertyName, org.springframework.boot.context.properties.bind.Bindable, org.springframework.boot.context.properties.bind.Binder$Context, org.springframework.boot.context.properties.bind.DataObjectPropertyBinder);
    Code:
       0: aload_0
       1: getfield      #117                // Field dataObjectBinders:Ljava/util/List;
       4: invokeinterface #214,  1          // InterfaceMethod java/util/List.iterator:()Ljava/util/Iterator;
       9: astore        5
      11: aload         5
      13: invokeinterface #49,  1           // InterfaceMethod java/util/Iterator.hasNext:()Z
      18: ifeq          58
      21: aload         5
      23: invokeinterface #55,  1           // InterfaceMethod java/util/Iterator.next:()Ljava/lang/Object;
      28: checkcast     #111                // class org/springframework/boot/context/properties/bind/DataObjectBinder
      31: astore        6
      33: aload         6
      35: aload_1
      36: aload_2
      37: aload_3
      38: aload         4
      40: invokeinterface #403,  5          // InterfaceMethod org/springframework/boot/context/properties/bind/DataObjectBinder.bind:(Lorg/springframework/boot/context/properties/source/ConfigurationPropertyName;Lorg/springframework/boot/context/properties/bind/Bindable;Lorg/springframework/boot/context/properties/bind/Binder$Context;Lorg/springframework/boot/context/properties/bind/DataObjectPropertyBinder;)Ljava/lang/Object;
      45: astore        7
      47: aload         7
      49: ifnull        55
      52: aload         7
      54: areturn
      55: goto          11
      58: aconst_null
      59: areturn

  private java.lang.Object lambda$bindDataObject$4(org.springframework.boot.context.properties.source.ConfigurationPropertyName, org.springframework.boot.context.properties.bind.BindHandler, org.springframework.boot.context.properties.bind.Binder$Context, java.lang.String, org.springframework.boot.context.properties.bind.Bindable);
    Code:
       0: aload_0
       1: aload_1
       2: aload         4
       4: invokevirtual #406                // Method org/springframework/boot/context/properties/source/ConfigurationPropertyName.append:(Ljava/lang/String;)Lorg/springframework/boot/context/properties/source/ConfigurationPropertyName;
       7: aload         5
       9: aload_2
      10: aload_3
      11: iconst_0
      12: iconst_0
      13: invokevirtual #163                // Method bind:(Lorg/springframework/boot/context/properties/source/ConfigurationPropertyName;Lorg/springframework/boot/context/properties/bind/Bindable;Lorg/springframework/boot/context/properties/bind/BindHandler;Lorg/springframework/boot/context/properties/bind/Binder$Context;ZZ)Ljava/lang/Object;
      16: areturn

  private static java.lang.Object lambda$bindAggregate$3(org.springframework.boot.context.properties.bind.AggregateBinder, org.springframework.boot.context.properties.source.ConfigurationPropertyName, org.springframework.boot.context.properties.bind.Bindable, org.springframework.boot.context.properties.bind.AggregateElementBinder);
    Code:
       0: aload_0
       1: aload_1
       2: aload_2
       3: aload_3
       4: invokevirtual #410                // Method org/springframework/boot/context/properties/bind/AggregateBinder.bind:(Lorg/springframework/boot/context/properties/source/ConfigurationPropertyName;Lorg/springframework/boot/context/properties/bind/Bindable;Lorg/springframework/boot/context/properties/bind/AggregateElementBinder;)Ljava/lang/Object;
       7: areturn

  private java.lang.Object lambda$bindAggregate$2(org.springframework.boot.context.properties.bind.AggregateBinder, org.springframework.boot.context.properties.bind.BindHandler, org.springframework.boot.context.properties.bind.Binder$Context, org.springframework.boot.context.properties.source.ConfigurationPropertyName, org.springframework.boot.context.properties.bind.Bindable, org.springframework.boot.context.properties.source.ConfigurationPropertySource);
    Code:
       0: aload_1
       1: aload         6
       3: invokevirtual #415                // Method org/springframework/boot/context/properties/bind/AggregateBinder.isAllowRecursiveBinding:(Lorg/springframework/boot/context/properties/source/ConfigurationPropertySource;)Z
       6: istore        7
       8: aload_0
       9: aload         4
      11: aload         5
      13: aload_2
      14: aload_3
      15: iload         7
      17: invokedynamic #419,  0            // InvokeDynamic #5:get:(Lorg/springframework/boot/context/properties/bind/Binder;Lorg/springframework/boot/context/properties/source/ConfigurationPropertyName;Lorg/springframework/boot/context/properties/bind/Bindable;Lorg/springframework/boot/context/properties/bind/BindHandler;Lorg/springframework/boot/context/properties/bind/Binder$Context;Z)Ljava/util/function/Supplier;
      22: astore        8
      24: aload_3
      25: aload         6
      27: aload         8
      29: invokevirtual #422                // Method org/springframework/boot/context/properties/bind/Binder$Context.withSource:(Lorg/springframework/boot/context/properties/source/ConfigurationPropertySource;Ljava/util/function/Supplier;)Ljava/lang/Object;
      32: areturn

  private java.lang.Object lambda$bindAggregate$1(org.springframework.boot.context.properties.source.ConfigurationPropertyName, org.springframework.boot.context.properties.bind.Bindable, org.springframework.boot.context.properties.bind.BindHandler, org.springframework.boot.context.properties.bind.Binder$Context, boolean);
    Code:
       0: aload_0
       1: aload_1
       2: aload_2
       3: aload_3
       4: aload         4
       6: iload         5
       8: iconst_0
       9: invokevirtual #163                // Method bind:(Lorg/springframework/boot/context/properties/source/ConfigurationPropertyName;Lorg/springframework/boot/context/properties/bind/Bindable;Lorg/springframework/boot/context/properties/bind/BindHandler;Lorg/springframework/boot/context/properties/bind/Binder$Context;ZZ)Ljava/lang/Object;
      12: areturn

  private static java.lang.String lambda$handleBindResult$0(org.springframework.boot.context.properties.bind.Bindable);
    Code:
       0: aload_0
       1: invokevirtual #262                // Method org/springframework/boot/context/properties/bind/Bindable.getType:()Lorg/springframework/core/ResolvableType;
       4: invokedynamic #426,  0            // InvokeDynamic #6:makeConcatWithConstants:(Lorg/springframework/core/ResolvableType;)Ljava/lang/String;
       9: areturn

  static {};
    Code:
       0: new           #430                // class java/util/HashSet
       3: dup
       4: iconst_2
       5: anewarray     #275                // class java/lang/Class
       8: dup
       9: iconst_0
      10: ldc           #31                 // class java/lang/Object
      12: aastore
      13: dup
      14: iconst_1
      15: ldc_w         #275                // class java/lang/Class
      18: aastore
      19: invokestatic  #1                  // Method java/util/Arrays.asList:([Ljava/lang/Object;)Ljava/util/List;
      22: invokespecial #432                // Method java/util/HashSet."<init>":(Ljava/util/Collection;)V
      25: invokestatic  #435                // Method java/util/Collections.unmodifiableSet:(Ljava/util/Set;)Ljava/util/Set;
      28: putstatic     #365                // Field NON_BEAN_CLASSES:Ljava/util/Set;
      31: return
}
