Compiled from "BindableRuntimeHintsRegistrar.java"
public class org.springframework.boot.context.properties.bind.BindableRuntimeHintsRegistrar implements org.springframework.aot.hint.RuntimeHintsRegistrar {
  private final java.lang.Class<?>[] types;

  protected org.springframework.boot.context.properties.bind.BindableRuntimeHintsRegistrar(java.lang.Class<?>...);
    Code:
       0: aload_0
       1: invokespecial #1                  // Method java/lang/Object."<init>":()V
       4: aload_0
       5: aload_1
       6: putfield      #7                  // Field types:[Ljava/lang/Class;
       9: return

  public void registerHints(org.springframework.aot.hint.RuntimeHints, java.lang.ClassLoader);
    Code:
       0: aload_0
       1: aload_1
       2: invokevirtual #13                 // Method registerHints:(Lorg/springframework/aot/hint/RuntimeHints;)V
       5: return

  public void registerHints(org.springframework.aot.hint.RuntimeHints);
    Code:
       0: new           #17                 // class java/util/HashSet
       3: dup
       4: invokespecial #19                 // Method java/util/HashSet."<init>":()V
       7: astore_2
       8: aload_0
       9: getfield      #7                  // Field types:[Ljava/lang/Class;
      12: astore_3
      13: aload_3
      14: arraylength
      15: istore        4
      17: iconst_0
      18: istore        5
      20: iload         5
      22: iload         4
      24: if_icmpge     57
      27: aload_3
      28: iload         5
      30: aaload
      31: astore        6
      33: new           #20                 // class org/springframework/boot/context/properties/bind/BindableRuntimeHintsRegistrar$Processor
      36: dup
      37: aload_0
      38: aload         6
      40: aload_2
      41: invokespecial #22                 // Method org/springframework/boot/context/properties/bind/BindableRuntimeHintsRegistrar$Processor."<init>":(Lorg/springframework/boot/context/properties/bind/BindableRuntimeHintsRegistrar;Ljava/lang/Class;Ljava/util/Set;)V
      44: aload_1
      45: invokevirtual #25                 // Method org/springframework/aot/hint/RuntimeHints.reflection:()Lorg/springframework/aot/hint/ReflectionHints;
      48: invokevirtual #31                 // Method org/springframework/boot/context/properties/bind/BindableRuntimeHintsRegistrar$Processor.process:(Lorg/springframework/aot/hint/ReflectionHints;)V
      51: iinc          5, 1
      54: goto          20
      57: aload_2
      58: invokeinterface #35,  1           // InterfaceMethod java/util/Set.isEmpty:()Z
      63: ifne          75
      66: new           #41                 // class org/springframework/boot/context/properties/bind/MissingParametersCompilerArgumentException
      69: dup
      70: aload_2
      71: invokespecial #43                 // Method org/springframework/boot/context/properties/bind/MissingParametersCompilerArgumentException."<init>":(Ljava/util/Set;)V
      74: athrow
      75: return

  public static org.springframework.boot.context.properties.bind.BindableRuntimeHintsRegistrar forTypes(java.lang.Iterable<java.lang.Class<?>>);
    Code:
       0: aload_0
       1: ldc           #46                 // String Types must not be null
       3: invokestatic  #48                 // Method org/springframework/util/Assert.notNull:(Ljava/lang/Object;Ljava/lang/String;)V
       6: aload_0
       7: invokeinterface #54,  1           // InterfaceMethod java/lang/Iterable.spliterator:()Ljava/util/Spliterator;
      12: iconst_0
      13: invokestatic  #60                 // Method java/util/stream/StreamSupport.stream:(Ljava/util/Spliterator;Z)Ljava/util/stream/Stream;
      16: invokedynamic #66,  0             // InvokeDynamic #0:apply:()Ljava/util/function/IntFunction;
      21: invokeinterface #70,  2           // InterfaceMethod java/util/stream/Stream.toArray:(Ljava/util/function/IntFunction;)[Ljava/lang/Object;
      26: checkcast     #76                 // class "[Ljava/lang/Class;"
      29: invokestatic  #77                 // Method forTypes:([Ljava/lang/Class;)Lorg/springframework/boot/context/properties/bind/BindableRuntimeHintsRegistrar;
      32: areturn

  public static org.springframework.boot.context.properties.bind.BindableRuntimeHintsRegistrar forTypes(java.lang.Class<?>...);
    Code:
       0: new           #8                  // class org/springframework/boot/context/properties/bind/BindableRuntimeHintsRegistrar
       3: dup
       4: aload_0
       5: invokespecial #81                 // Method "<init>":([Ljava/lang/Class;)V
       8: areturn

  private static java.lang.Class[] lambda$forTypes$0(int);
    Code:
       0: iload_0
       1: anewarray     #84                 // class java/lang/Class
       4: areturn
}
