Compiled from "BindConverter.java"
final class org.springframework.boot.context.properties.bind.BindConverter {
  private static org.springframework.boot.context.properties.bind.BindConverter sharedInstance;

  private final java.util.List<org.springframework.core.convert.ConversionService> delegates;

  private org.springframework.boot.context.properties.bind.BindConverter(java.util.List<org.springframework.core.convert.ConversionService>, java.util.function.Consumer<org.springframework.beans.PropertyEditorRegistry>);
    Code:
       0: aload_0
       1: invokespecial #1                  // Method java/lang/Object."<init>":()V
       4: new           #7                  // class java/util/ArrayList
       7: dup
       8: invokespecial #9                  // Method java/util/ArrayList."<init>":()V
      11: astore_3
      12: aload_3
      13: new           #10                 // class org/springframework/boot/context/properties/bind/BindConverter$TypeConverterConversionService
      16: dup
      17: aload_2
      18: invokespecial #12                 // Method org/springframework/boot/context/properties/bind/BindConverter$TypeConverterConversionService."<init>":(Ljava/util/function/Consumer;)V
      21: invokeinterface #15,  2           // InterfaceMethod java/util/List.add:(Ljava/lang/Object;)Z
      26: pop
      27: iconst_0
      28: istore        4
      30: aload_1
      31: invokestatic  #21                 // Method org/springframework/util/CollectionUtils.isEmpty:(Ljava/util/Collection;)Z
      34: ifne          99
      37: aload_1
      38: invokeinterface #27,  1           // InterfaceMethod java/util/List.iterator:()Ljava/util/Iterator;
      43: astore        5
      45: aload         5
      47: invokeinterface #31,  1           // InterfaceMethod java/util/Iterator.hasNext:()Z
      52: ifeq          99
      55: aload         5
      57: invokeinterface #37,  1           // InterfaceMethod java/util/Iterator.next:()Ljava/lang/Object;
      62: checkcast     #41                 // class org/springframework/core/convert/ConversionService
      65: astore        6
      67: aload_3
      68: aload         6
      70: invokeinterface #15,  2           // InterfaceMethod java/util/List.add:(Ljava/lang/Object;)Z
      75: pop
      76: iload         4
      78: ifne          89
      81: aload         6
      83: instanceof    #43                 // class org/springframework/boot/convert/ApplicationConversionService
      86: ifeq          93
      89: iconst_1
      90: goto          94
      93: iconst_0
      94: istore        4
      96: goto          45
      99: iload         4
     101: ifne          114
     104: aload_3
     105: invokestatic  #45                 // Method org/springframework/boot/convert/ApplicationConversionService.getSharedInstance:()Lorg/springframework/core/convert/ConversionService;
     108: invokeinterface #15,  2           // InterfaceMethod java/util/List.add:(Ljava/lang/Object;)Z
     113: pop
     114: aload_0
     115: aload_3
     116: invokestatic  #49                 // Method java/util/Collections.unmodifiableList:(Ljava/util/List;)Ljava/util/List;
     119: putfield      #55                 // Field delegates:Ljava/util/List;
     122: return

  boolean canConvert(java.lang.Object, org.springframework.core.ResolvableType, java.lang.annotation.Annotation...);
    Code:
       0: aload_0
       1: aload_1
       2: invokestatic  #61                 // Method org/springframework/core/convert/TypeDescriptor.forObject:(Ljava/lang/Object;)Lorg/springframework/core/convert/TypeDescriptor;
       5: new           #67                 // class org/springframework/boot/context/properties/bind/BindConverter$ResolvableTypeDescriptor
       8: dup
       9: aload_2
      10: aload_3
      11: invokespecial #69                 // Method org/springframework/boot/context/properties/bind/BindConverter$ResolvableTypeDescriptor."<init>":(Lorg/springframework/core/ResolvableType;[Ljava/lang/annotation/Annotation;)V
      14: invokevirtual #72                 // Method canConvert:(Lorg/springframework/core/convert/TypeDescriptor;Lorg/springframework/core/convert/TypeDescriptor;)Z
      17: ireturn

  private boolean canConvert(org.springframework.core.convert.TypeDescriptor, org.springframework.core.convert.TypeDescriptor);
    Code:
       0: aload_0
       1: getfield      #55                 // Field delegates:Ljava/util/List;
       4: invokeinterface #27,  1           // InterfaceMethod java/util/List.iterator:()Ljava/util/Iterator;
       9: astore_3
      10: aload_3
      11: invokeinterface #31,  1           // InterfaceMethod java/util/Iterator.hasNext:()Z
      16: ifeq          47
      19: aload_3
      20: invokeinterface #37,  1           // InterfaceMethod java/util/Iterator.next:()Ljava/lang/Object;
      25: checkcast     #41                 // class org/springframework/core/convert/ConversionService
      28: astore        4
      30: aload         4
      32: aload_1
      33: aload_2
      34: invokeinterface #76,  3           // InterfaceMethod org/springframework/core/convert/ConversionService.canConvert:(Lorg/springframework/core/convert/TypeDescriptor;Lorg/springframework/core/convert/TypeDescriptor;)Z
      39: ifeq          44
      42: iconst_1
      43: ireturn
      44: goto          10
      47: iconst_0
      48: ireturn

  <T> T convert(java.lang.Object, org.springframework.boot.context.properties.bind.Bindable<T>);
    Code:
       0: aload_0
       1: aload_1
       2: aload_2
       3: invokevirtual #77                 // Method org/springframework/boot/context/properties/bind/Bindable.getType:()Lorg/springframework/core/ResolvableType;
       6: aload_2
       7: invokevirtual #83                 // Method org/springframework/boot/context/properties/bind/Bindable.getAnnotations:()[Ljava/lang/annotation/Annotation;
      10: invokevirtual #87                 // Method convert:(Ljava/lang/Object;Lorg/springframework/core/ResolvableType;[Ljava/lang/annotation/Annotation;)Ljava/lang/Object;
      13: areturn

  <T> T convert(java.lang.Object, org.springframework.core.ResolvableType, java.lang.annotation.Annotation...);
    Code:
       0: aload_1
       1: ifnonnull     6
       4: aconst_null
       5: areturn
       6: aload_0
       7: aload_1
       8: aload_1
       9: invokestatic  #61                 // Method org/springframework/core/convert/TypeDescriptor.forObject:(Ljava/lang/Object;)Lorg/springframework/core/convert/TypeDescriptor;
      12: new           #67                 // class org/springframework/boot/context/properties/bind/BindConverter$ResolvableTypeDescriptor
      15: dup
      16: aload_2
      17: aload_3
      18: invokespecial #69                 // Method org/springframework/boot/context/properties/bind/BindConverter$ResolvableTypeDescriptor."<init>":(Lorg/springframework/core/ResolvableType;[Ljava/lang/annotation/Annotation;)V
      21: invokevirtual #91                 // Method convert:(Ljava/lang/Object;Lorg/springframework/core/convert/TypeDescriptor;Lorg/springframework/core/convert/TypeDescriptor;)Ljava/lang/Object;
      24: areturn

  private java.lang.Object convert(java.lang.Object, org.springframework.core.convert.TypeDescriptor, org.springframework.core.convert.TypeDescriptor);
    Code:
       0: aconst_null
       1: astore        4
       3: aload_0
       4: getfield      #55                 // Field delegates:Ljava/util/List;
       7: invokeinterface #27,  1           // InterfaceMethod java/util/List.iterator:()Ljava/util/Iterator;
      12: astore        5
      14: aload         5
      16: invokeinterface #31,  1           // InterfaceMethod java/util/Iterator.hasNext:()Z
      21: ifeq          84
      24: aload         5
      26: invokeinterface #37,  1           // InterfaceMethod java/util/Iterator.next:()Ljava/lang/Object;
      31: checkcast     #41                 // class org/springframework/core/convert/ConversionService
      34: astore        6
      36: aload         6
      38: aload_2
      39: aload_3
      40: invokeinterface #76,  3           // InterfaceMethod org/springframework/core/convert/ConversionService.canConvert:(Lorg/springframework/core/convert/TypeDescriptor;Lorg/springframework/core/convert/TypeDescriptor;)Z
      45: ifeq          59
      48: aload         6
      50: aload_1
      51: aload_2
      52: aload_3
      53: invokeinterface #94,  4           // InterfaceMethod org/springframework/core/convert/ConversionService.convert:(Ljava/lang/Object;Lorg/springframework/core/convert/TypeDescriptor;Lorg/springframework/core/convert/TypeDescriptor;)Ljava/lang/Object;
      58: areturn
      59: goto          81
      62: astore        7
      64: aload         4
      66: ifnonnull     81
      69: aload         7
      71: instanceof    #97                 // class org/springframework/core/convert/ConversionFailedException
      74: ifeq          81
      77: aload         7
      79: astore        4
      81: goto          14
      84: aload         4
      86: ifnull        94
      89: aload         4
      91: goto          103
      94: new           #99                 // class org/springframework/core/convert/ConverterNotFoundException
      97: dup
      98: aload_2
      99: aload_3
     100: invokespecial #101                // Method org/springframework/core/convert/ConverterNotFoundException."<init>":(Lorg/springframework/core/convert/TypeDescriptor;Lorg/springframework/core/convert/TypeDescriptor;)V
     103: athrow
    Exception table:
       from    to  target type
          36    58    62   Class org/springframework/core/convert/ConversionException

  static org.springframework.boot.context.properties.bind.BindConverter get(java.util.List<org.springframework.core.convert.ConversionService>, java.util.function.Consumer<org.springframework.beans.PropertyEditorRegistry>);
    Code:
       0: aload_0
       1: ifnull        27
       4: aload_0
       5: invokeinterface #104,  1          // InterfaceMethod java/util/List.size:()I
      10: iconst_1
      11: if_icmpne     31
      14: aload_0
      15: iconst_0
      16: invokeinterface #108,  2          // InterfaceMethod java/util/List.get:(I)Ljava/lang/Object;
      21: invokestatic  #45                 // Method org/springframework/boot/convert/ApplicationConversionService.getSharedInstance:()Lorg/springframework/core/convert/ConversionService;
      24: if_acmpne     31
      27: iconst_1
      28: goto          32
      31: iconst_0
      32: istore_2
      33: aload_1
      34: ifnonnull     45
      37: iload_2
      38: ifeq          45
      41: invokestatic  #112                // Method getSharedInstance:()Lorg/springframework/boot/context/properties/bind/BindConverter;
      44: areturn
      45: new           #56                 // class org/springframework/boot/context/properties/bind/BindConverter
      48: dup
      49: aload_0
      50: aload_1
      51: invokespecial #115                // Method "<init>":(Ljava/util/List;Ljava/util/function/Consumer;)V
      54: areturn

  private static org.springframework.boot.context.properties.bind.BindConverter getSharedInstance();
    Code:
       0: getstatic     #118                // Field sharedInstance:Lorg/springframework/boot/context/properties/bind/BindConverter;
       3: ifnonnull     18
       6: new           #56                 // class org/springframework/boot/context/properties/bind/BindConverter
       9: dup
      10: aconst_null
      11: aconst_null
      12: invokespecial #115                // Method "<init>":(Ljava/util/List;Ljava/util/function/Consumer;)V
      15: putstatic     #118                // Field sharedInstance:Lorg/springframework/boot/context/properties/bind/BindConverter;
      18: getstatic     #118                // Field sharedInstance:Lorg/springframework/boot/context/properties/bind/BindConverter;
      21: areturn
}
