Compiled from "BindException.java"
public class org.springframework.boot.context.properties.bind.BindException extends java.lang.RuntimeException implements org.springframework.boot.origin.OriginProvider {
  private final org.springframework.boot.context.properties.bind.Bindable<?> target;

  private final org.springframework.boot.context.properties.source.ConfigurationProperty property;

  private final org.springframework.boot.context.properties.source.ConfigurationPropertyName name;

  org.springframework.boot.context.properties.bind.BindException(org.springframework.boot.context.properties.source.ConfigurationPropertyName, org.springframework.boot.context.properties.bind.Bindable<?>, org.springframework.boot.context.properties.source.ConfigurationProperty, java.lang.Throwable);
    Code:
       0: aload_0
       1: aload_1
       2: aload_2
       3: invokestatic  #1                  // Method buildMessage:(Lorg/springframework/boot/context/properties/source/ConfigurationPropertyName;Lorg/springframework/boot/context/properties/bind/Bindable;)Ljava/lang/String;
       6: aload         4
       8: invokespecial #7                  // Method java/lang/RuntimeException."<init>":(Ljava/lang/String;Ljava/lang/Throwable;)V
      11: aload_0
      12: aload_1
      13: putfield      #13                 // Field name:Lorg/springframework/boot/context/properties/source/ConfigurationPropertyName;
      16: aload_0
      17: aload_2
      18: putfield      #17                 // Field target:Lorg/springframework/boot/context/properties/bind/Bindable;
      21: aload_0
      22: aload_3
      23: putfield      #21                 // Field property:Lorg/springframework/boot/context/properties/source/ConfigurationProperty;
      26: return

  public org.springframework.boot.context.properties.source.ConfigurationPropertyName getName();
    Code:
       0: aload_0
       1: getfield      #13                 // Field name:Lorg/springframework/boot/context/properties/source/ConfigurationPropertyName;
       4: areturn

  public org.springframework.boot.context.properties.bind.Bindable<?> getTarget();
    Code:
       0: aload_0
       1: getfield      #17                 // Field target:Lorg/springframework/boot/context/properties/bind/Bindable;
       4: areturn

  public org.springframework.boot.context.properties.source.ConfigurationProperty getProperty();
    Code:
       0: aload_0
       1: getfield      #21                 // Field property:Lorg/springframework/boot/context/properties/source/ConfigurationProperty;
       4: areturn

  public org.springframework.boot.origin.Origin getOrigin();
    Code:
       0: aload_0
       1: getfield      #13                 // Field name:Lorg/springframework/boot/context/properties/source/ConfigurationPropertyName;
       4: invokestatic  #25                 // InterfaceMethod org/springframework/boot/origin/Origin.from:(Ljava/lang/Object;)Lorg/springframework/boot/origin/Origin;
       7: areturn

  private static java.lang.String buildMessage(org.springframework.boot.context.properties.source.ConfigurationPropertyName, org.springframework.boot.context.properties.bind.Bindable<?>);
    Code:
       0: new           #31                 // class java/lang/StringBuilder
       3: dup
       4: invokespecial #33                 // Method java/lang/StringBuilder."<init>":()V
       7: astore_2
       8: aload_2
       9: ldc           #36                 // String Failed to bind properties
      11: invokevirtual #38                 // Method java/lang/StringBuilder.append:(Ljava/lang/String;)Ljava/lang/StringBuilder;
      14: pop
      15: aload_2
      16: aload_0
      17: ifnull        29
      20: aload_0
      21: invokedynamic #42,  0             // InvokeDynamic #0:makeConcatWithConstants:(Lorg/springframework/boot/context/properties/source/ConfigurationPropertyName;)Ljava/lang/String;
      26: goto          31
      29: ldc           #46                 // String
      31: invokevirtual #38                 // Method java/lang/StringBuilder.append:(Ljava/lang/String;)Ljava/lang/StringBuilder;
      34: pop
      35: aload_2
      36: ldc           #48                 // String  to
      38: invokevirtual #38                 // Method java/lang/StringBuilder.append:(Ljava/lang/String;)Ljava/lang/StringBuilder;
      41: aload_1
      42: invokevirtual #50                 // Method org/springframework/boot/context/properties/bind/Bindable.getType:()Lorg/springframework/core/ResolvableType;
      45: invokevirtual #56                 // Method java/lang/StringBuilder.append:(Ljava/lang/Object;)Ljava/lang/StringBuilder;
      48: pop
      49: aload_2
      50: invokevirtual #59                 // Method java/lang/StringBuilder.toString:()Ljava/lang/String;
      53: areturn
}
