Compiled from "DefaultBindConstructorProvider.java"
class org.springframework.boot.context.properties.bind.DefaultBindConstructorProvider implements org.springframework.boot.context.properties.bind.BindConstructorProvider {
  org.springframework.boot.context.properties.bind.DefaultBindConstructorProvider();
    Code:
       0: aload_0
       1: invokespecial #1                  // Method java/lang/Object."<init>":()V
       4: return

  public java.lang.reflect.Constructor<?> getBindConstructor(org.springframework.boot.context.properties.bind.Bindable<?>, boolean);
    Code:
       0: aload_1
       1: invokevirtual #7                  // Method org/springframework/boot/context/properties/bind/Bindable.getType:()Lorg/springframework/core/ResolvableType;
       4: invokevirtual #13                 // Method org/springframework/core/ResolvableType.resolve:()Ljava/lang/Class;
       7: iload_2
       8: invokestatic  #19                 // Method org/springframework/boot/context/properties/bind/DefaultBindConstructorProvider$Constructors.getConstructors:(Ljava/lang/Class;Z)Lorg/springframework/boot/context/properties/bind/DefaultBindConstructorProvider$Constructors;
      11: astore_3
      12: aload_3
      13: invokevirtual #25                 // Method org/springframework/boot/context/properties/bind/DefaultBindConstructorProvider$Constructors.getBind:()Ljava/lang/reflect/Constructor;
      16: ifnull        54
      19: aload_3
      20: invokevirtual #29                 // Method org/springframework/boot/context/properties/bind/DefaultBindConstructorProvider$Constructors.isDeducedBindConstructor:()Z
      23: ifeq          54
      26: aload_3
      27: invokevirtual #33                 // Method org/springframework/boot/context/properties/bind/DefaultBindConstructorProvider$Constructors.isImmutableType:()Z
      30: ifne          54
      33: aload_1
      34: invokevirtual #36                 // Method org/springframework/boot/context/properties/bind/Bindable.getValue:()Ljava/util/function/Supplier;
      37: ifnull        54
      40: aload_1
      41: invokevirtual #36                 // Method org/springframework/boot/context/properties/bind/Bindable.getValue:()Ljava/util/function/Supplier;
      44: invokeinterface #40,  1           // InterfaceMethod java/util/function/Supplier.get:()Ljava/lang/Object;
      49: ifnull        54
      52: aconst_null
      53: areturn
      54: aload_3
      55: invokevirtual #25                 // Method org/springframework/boot/context/properties/bind/DefaultBindConstructorProvider$Constructors.getBind:()Ljava/lang/reflect/Constructor;
      58: areturn

  public java.lang.reflect.Constructor<?> getBindConstructor(java.lang.Class<?>, boolean);
    Code:
       0: aload_1
       1: iload_2
       2: invokestatic  #19                 // Method org/springframework/boot/context/properties/bind/DefaultBindConstructorProvider$Constructors.getConstructors:(Ljava/lang/Class;Z)Lorg/springframework/boot/context/properties/bind/DefaultBindConstructorProvider$Constructors;
       5: astore_3
       6: aload_3
       7: invokevirtual #25                 // Method org/springframework/boot/context/properties/bind/DefaultBindConstructorProvider$Constructors.getBind:()Ljava/lang/reflect/Constructor;
      10: areturn
}
