Compiled from "DefaultBindConstructorProvider.java"
final class org.springframework.boot.context.properties.bind.DefaultBindConstructorProvider$Constructors {
  private static final org.springframework.boot.context.properties.bind.DefaultBindConstructorProvider$Constructors NONE;

  private final boolean hasAutowired;

  private final java.lang.reflect.Constructor<?> bind;

  private final boolean deducedBindConstructor;

  private final boolean immutableType;

  private org.springframework.boot.context.properties.bind.DefaultBindConstructorProvider$Constructors(boolean, java.lang.reflect.Constructor<?>, boolean, boolean);
    Code:
       0: aload_0
       1: invokespecial #1                  // Method java/lang/Object."<init>":()V
       4: aload_0
       5: iload_1
       6: putfield      #7                  // Field hasAutowired:Z
       9: aload_0
      10: aload_2
      11: putfield      #13                 // Field bind:Ljava/lang/reflect/Constructor;
      14: aload_0
      15: iload_3
      16: putfield      #17                 // Field deducedBindConstructor:Z
      19: aload_0
      20: iload         4
      22: putfield      #20                 // Field immutableType:Z
      25: return

  boolean hasAutowired();
    Code:
       0: aload_0
       1: getfield      #7                  // Field hasAutowired:Z
       4: ireturn

  java.lang.reflect.Constructor<?> getBind();
    Code:
       0: aload_0
       1: getfield      #13                 // Field bind:Ljava/lang/reflect/Constructor;
       4: areturn

  boolean isDeducedBindConstructor();
    Code:
       0: aload_0
       1: getfield      #17                 // Field deducedBindConstructor:Z
       4: ireturn

  boolean isImmutableType();
    Code:
       0: aload_0
       1: getfield      #20                 // Field immutableType:Z
       4: ireturn

  static org.springframework.boot.context.properties.bind.DefaultBindConstructorProvider$Constructors getConstructors(java.lang.Class<?>, boolean);
    Code:
       0: aload_0
       1: ifnonnull     8
       4: getstatic     #23                 // Field NONE:Lorg/springframework/boot/context/properties/bind/DefaultBindConstructorProvider$Constructors;
       7: areturn
       8: aload_0
       9: invokestatic  #27                 // Method isAutowiredPresent:(Ljava/lang/Class;)Z
      12: istore_2
      13: aload_0
      14: invokestatic  #31                 // Method getCandidateConstructors:(Ljava/lang/Class;)[Ljava/lang/reflect/Constructor;
      17: astore_3
      18: aload_3
      19: invokestatic  #35                 // Method getAnnotations:([Ljava/lang/reflect/Constructor;)[Lorg/springframework/core/annotation/MergedAnnotations;
      22: astore        4
      24: iconst_0
      25: istore        5
      27: aload_0
      28: invokevirtual #39                 // Method java/lang/Class.isRecord:()Z
      31: istore        6
      33: aload_0
      34: aload_3
      35: aload         4
      37: invokestatic  #45                 // Method getConstructorBindingAnnotated:(Ljava/lang/Class;[Ljava/lang/reflect/Constructor;[Lorg/springframework/core/annotation/MergedAnnotations;)Ljava/lang/reflect/Constructor;
      40: astore        7
      42: aload         7
      44: ifnonnull     70
      47: iload_2
      48: ifne          70
      51: aload_0
      52: aload_3
      53: invokestatic  #49                 // Method deduceBindConstructor:(Ljava/lang/Class;[Ljava/lang/reflect/Constructor;)Ljava/lang/reflect/Constructor;
      56: astore        7
      58: aload         7
      60: ifnull        67
      63: iconst_1
      64: goto          68
      67: iconst_0
      68: istore        5
      70: aload         7
      72: ifnonnull     104
      75: iload_2
      76: ifne          104
      79: aload_0
      80: invokestatic  #53                 // Method isKotlinType:(Ljava/lang/Class;)Z
      83: ifeq          104
      86: aload_0
      87: invokestatic  #56                 // Method deduceKotlinBindConstructor:(Ljava/lang/Class;)Ljava/lang/reflect/Constructor;
      90: astore        7
      92: aload         7
      94: ifnull        101
      97: iconst_1
      98: goto          102
     101: iconst_0
     102: istore        5
     104: aload         7
     106: ifnonnull     113
     109: iload_1
     110: ifeq          131
     113: iload_2
     114: ifne          121
     117: iconst_1
     118: goto          122
     121: iconst_0
     122: aload_0
     123: invokedynamic #60,  0             // InvokeDynamic #0:get:(Ljava/lang/Class;)Ljava/util/function/Supplier;
     128: invokestatic  #64                 // Method org/springframework/util/Assert.state:(ZLjava/util/function/Supplier;)V
     131: new           #8                  // class org/springframework/boot/context/properties/bind/DefaultBindConstructorProvider$Constructors
     134: dup
     135: iload_2
     136: aload         7
     138: iload         5
     140: iload         6
     142: invokespecial #70                 // Method "<init>":(ZLjava/lang/reflect/Constructor;ZZ)V
     145: areturn

  private static boolean isAutowiredPresent(java.lang.Class<?>);
    Code:
       0: aload_0
       1: invokevirtual #73                 // Method java/lang/Class.getDeclaredConstructors:()[Ljava/lang/reflect/Constructor;
       4: invokestatic  #77                 // InterfaceMethod java/util/stream/Stream.of:([Ljava/lang/Object;)Ljava/util/stream/Stream;
       7: invokedynamic #83,  0             // InvokeDynamic #1:apply:()Ljava/util/function/Function;
      12: invokeinterface #87,  2           // InterfaceMethod java/util/stream/Stream.map:(Ljava/util/function/Function;)Ljava/util/stream/Stream;
      17: invokedynamic #91,  0             // InvokeDynamic #2:test:()Ljava/util/function/Predicate;
      22: invokeinterface #95,  2           // InterfaceMethod java/util/stream/Stream.anyMatch:(Ljava/util/function/Predicate;)Z
      27: ifeq          32
      30: iconst_1
      31: ireturn
      32: aload_0
      33: invokestatic  #99                 // Method org/springframework/util/ClassUtils.getUserClass:(Ljava/lang/Class;)Ljava/lang/Class;
      36: astore_1
      37: aload_1
      38: aload_0
      39: if_acmpeq     49
      42: aload_1
      43: invokestatic  #27                 // Method isAutowiredPresent:(Ljava/lang/Class;)Z
      46: goto          50
      49: iconst_0
      50: ireturn

  private static java.lang.reflect.Constructor<?>[] getCandidateConstructors(java.lang.Class<?>);
    Code:
       0: aload_0
       1: invokestatic  #105                // Method isInnerClass:(Ljava/lang/Class;)Z
       4: ifeq          12
       7: iconst_0
       8: anewarray     #108                // class java/lang/reflect/Constructor
      11: areturn
      12: aload_0
      13: invokevirtual #73                 // Method java/lang/Class.getDeclaredConstructors:()[Ljava/lang/reflect/Constructor;
      16: invokestatic  #110                // Method java/util/Arrays.stream:([Ljava/lang/Object;)Ljava/util/stream/Stream;
      19: aload_0
      20: invokedynamic #115,  0            // InvokeDynamic #3:test:(Ljava/lang/Class;)Ljava/util/function/Predicate;
      25: invokeinterface #118,  2          // InterfaceMethod java/util/stream/Stream.filter:(Ljava/util/function/Predicate;)Ljava/util/stream/Stream;
      30: invokedynamic #122,  0            // InvokeDynamic #4:apply:()Ljava/util/function/IntFunction;
      35: invokeinterface #125,  2          // InterfaceMethod java/util/stream/Stream.toArray:(Ljava/util/function/IntFunction;)[Ljava/lang/Object;
      40: checkcast     #129                // class "[Ljava/lang/reflect/Constructor;"
      43: areturn

  private static boolean isInnerClass(java.lang.Class<?>);
    Code:
       0: aload_0
       1: ldc           #131                // String this$0
       3: invokevirtual #133                // Method java/lang/Class.getDeclaredField:(Ljava/lang/String;)Ljava/lang/reflect/Field;
       6: invokevirtual #137                // Method java/lang/reflect/Field.isSynthetic:()Z
       9: ireturn
      10: astore_1
      11: iconst_0
      12: ireturn
    Exception table:
       from    to  target type
           0     9    10   Class java/lang/NoSuchFieldException

  private static boolean isNonSynthetic(java.lang.reflect.Constructor<?>, java.lang.Class<?>);
    Code:
       0: aload_0
       1: invokevirtual #144                // Method java/lang/reflect/Constructor.isSynthetic:()Z
       4: ifne          11
       7: iconst_1
       8: goto          12
      11: iconst_0
      12: ireturn

  private static org.springframework.core.annotation.MergedAnnotations[] getAnnotations(java.lang.reflect.Constructor<?>[]);
    Code:
       0: aload_0
       1: arraylength
       2: anewarray     #145                // class org/springframework/core/annotation/MergedAnnotations
       5: astore_1
       6: iconst_0
       7: istore_2
       8: iload_2
       9: aload_0
      10: arraylength
      11: if_icmpge     32
      14: aload_1
      15: iload_2
      16: aload_0
      17: iload_2
      18: aaload
      19: getstatic     #147                // Field org/springframework/core/annotation/MergedAnnotations$SearchStrategy.SUPERCLASS:Lorg/springframework/core/annotation/MergedAnnotations$SearchStrategy;
      22: invokestatic  #153                // InterfaceMethod org/springframework/core/annotation/MergedAnnotations.from:(Ljava/lang/reflect/AnnotatedElement;Lorg/springframework/core/annotation/MergedAnnotations$SearchStrategy;)Lorg/springframework/core/annotation/MergedAnnotations;
      25: aastore
      26: iinc          2, 1
      29: goto          8
      32: aload_1
      33: areturn

  private static java.lang.reflect.Constructor<?> getConstructorBindingAnnotated(java.lang.Class<?>, java.lang.reflect.Constructor<?>[], org.springframework.core.annotation.MergedAnnotations[]);
    Code:
       0: aconst_null
       1: astore_3
       2: iconst_0
       3: istore        4
       5: iload         4
       7: aload_1
       8: arraylength
       9: if_icmpge     79
      12: aload_2
      13: iload         4
      15: aaload
      16: ldc           #157                // class org/springframework/boot/context/properties/bind/ConstructorBinding
      18: invokeinterface #159,  2          // InterfaceMethod org/springframework/core/annotation/MergedAnnotations.isPresent:(Ljava/lang/Class;)Z
      23: ifeq          73
      26: aload_1
      27: iload         4
      29: aaload
      30: invokevirtual #162                // Method java/lang/reflect/Constructor.getParameterCount:()I
      33: ifle          40
      36: iconst_1
      37: goto          41
      40: iconst_0
      41: aload_0
      42: invokedynamic #166,  0            // InvokeDynamic #5:get:(Ljava/lang/Class;)Ljava/util/function/Supplier;
      47: invokestatic  #64                 // Method org/springframework/util/Assert.state:(ZLjava/util/function/Supplier;)V
      50: aload_3
      51: ifnonnull     58
      54: iconst_1
      55: goto          59
      58: iconst_0
      59: aload_0
      60: invokedynamic #167,  0            // InvokeDynamic #6:get:(Ljava/lang/Class;)Ljava/util/function/Supplier;
      65: invokestatic  #64                 // Method org/springframework/util/Assert.state:(ZLjava/util/function/Supplier;)V
      68: aload_1
      69: iload         4
      71: aaload
      72: astore_3
      73: iinc          4, 1
      76: goto          5
      79: aload_3
      80: areturn

  private static java.lang.reflect.Constructor<?> deduceBindConstructor(java.lang.Class<?>, java.lang.reflect.Constructor<?>[]);
    Code:
       0: aload_1
       1: arraylength
       2: iconst_1
       3: if_icmpne     40
       6: aload_1
       7: iconst_0
       8: aaload
       9: invokevirtual #162                // Method java/lang/reflect/Constructor.getParameterCount:()I
      12: ifle          40
      15: aload_0
      16: invokevirtual #168                // Method java/lang/Class.isMemberClass:()Z
      19: ifeq          36
      22: aload_1
      23: iconst_0
      24: aaload
      25: invokevirtual #171                // Method java/lang/reflect/Constructor.getModifiers:()I
      28: invokestatic  #174                // Method java/lang/reflect/Modifier.isPrivate:(I)Z
      31: ifeq          36
      34: aconst_null
      35: areturn
      36: aload_1
      37: iconst_0
      38: aaload
      39: areturn
      40: aconst_null
      41: astore_2
      42: aload_1
      43: astore_3
      44: aload_3
      45: arraylength
      46: istore        4
      48: iconst_0
      49: istore        5
      51: iload         5
      53: iload         4
      55: if_icmpge     90
      58: aload_3
      59: iload         5
      61: aaload
      62: astore        6
      64: aload         6
      66: invokevirtual #171                // Method java/lang/reflect/Constructor.getModifiers:()I
      69: invokestatic  #174                // Method java/lang/reflect/Modifier.isPrivate:(I)Z
      72: ifne          84
      75: aload_2
      76: ifnull        81
      79: aconst_null
      80: areturn
      81: aload         6
      83: astore_2
      84: iinc          5, 1
      87: goto          51
      90: aload_2
      91: ifnull        105
      94: aload_2
      95: invokevirtual #162                // Method java/lang/reflect/Constructor.getParameterCount:()I
      98: ifle          105
     101: aload_2
     102: goto          106
     105: aconst_null
     106: areturn

  private static boolean isKotlinType(java.lang.Class<?>);
    Code:
       0: invokestatic  #180                // Method org/springframework/core/KotlinDetector.isKotlinPresent:()Z
       3: ifeq          17
       6: aload_0
       7: invokestatic  #185                // Method org/springframework/core/KotlinDetector.isKotlinType:(Ljava/lang/Class;)Z
      10: ifeq          17
      13: iconst_1
      14: goto          18
      17: iconst_0
      18: ireturn

  private static java.lang.reflect.Constructor<?> deduceKotlinBindConstructor(java.lang.Class<?>);
    Code:
       0: aload_0
       1: invokestatic  #186                // Method org/springframework/beans/BeanUtils.findPrimaryConstructor:(Ljava/lang/Class;)Ljava/lang/reflect/Constructor;
       4: astore_1
       5: aload_1
       6: ifnull        18
       9: aload_1
      10: invokevirtual #162                // Method java/lang/reflect/Constructor.getParameterCount:()I
      13: ifle          18
      16: aload_1
      17: areturn
      18: aconst_null
      19: areturn

  private static java.lang.String lambda$getConstructorBindingAnnotated$5(java.lang.Class);
    Code:
       0: aload_0
       1: invokevirtual #191                // Method java/lang/Class.getName:()Ljava/lang/String;
       4: invokedynamic #195,  0            // InvokeDynamic #7:makeConcatWithConstants:(Ljava/lang/String;)Ljava/lang/String;
       9: areturn

  private static java.lang.String lambda$getConstructorBindingAnnotated$4(java.lang.Class);
    Code:
       0: aload_0
       1: invokevirtual #191                // Method java/lang/Class.getName:()Ljava/lang/String;
       4: invokedynamic #199,  0            // InvokeDynamic #8:makeConcatWithConstants:(Ljava/lang/String;)Ljava/lang/String;
       9: areturn

  private static java.lang.reflect.Constructor[] lambda$getCandidateConstructors$3(int);
    Code:
       0: iload_0
       1: anewarray     #108                // class java/lang/reflect/Constructor
       4: areturn

  private static boolean lambda$getCandidateConstructors$2(java.lang.Class, java.lang.reflect.Constructor);
    Code:
       0: aload_1
       1: aload_0
       2: invokestatic  #200                // Method isNonSynthetic:(Ljava/lang/reflect/Constructor;Ljava/lang/Class;)Z
       5: ireturn

  private static boolean lambda$isAutowiredPresent$1(org.springframework.core.annotation.MergedAnnotations);
    Code:
       0: aload_0
       1: ldc           #204                // class org/springframework/beans/factory/annotation/Autowired
       3: invokeinterface #159,  2          // InterfaceMethod org/springframework/core/annotation/MergedAnnotations.isPresent:(Ljava/lang/Class;)Z
       8: ireturn

  private static java.lang.String lambda$getConstructors$0(java.lang.Class);
    Code:
       0: aload_0
       1: invokevirtual #191                // Method java/lang/Class.getName:()Ljava/lang/String;
       4: invokedynamic #206,  0            // InvokeDynamic #9:makeConcatWithConstants:(Ljava/lang/String;)Ljava/lang/String;
       9: areturn

  static {};
    Code:
       0: new           #8                  // class org/springframework/boot/context/properties/bind/DefaultBindConstructorProvider$Constructors
       3: dup
       4: iconst_0
       5: aconst_null
       6: iconst_0
       7: iconst_0
       8: invokespecial #70                 // Method "<init>":(ZLjava/lang/reflect/Constructor;ZZ)V
      11: putstatic     #23                 // Field NONE:Lorg/springframework/boot/context/properties/bind/DefaultBindConstructorProvider$Constructors;
      14: return
}
