Compiled from "IndexedElementsBinder.java"
abstract class org.springframework.boot.context.properties.bind.IndexedElementsBinder<T> extends org.springframework.boot.context.properties.bind.AggregateBinder<T> {
  private static final java.lang.String INDEX_ZERO;

  org.springframework.boot.context.properties.bind.IndexedElementsBinder(org.springframework.boot.context.properties.bind.Binder$Context);
    Code:
       0: aload_0
       1: aload_1
       2: invokespecial #1                  // Method org/springframework/boot/context/properties/bind/AggregateBinder."<init>":(Lorg/springframework/boot/context/properties/bind/Binder$Context;)V
       5: return

  protected boolean isAllowRecursiveBinding(org.springframework.boot.context.properties.source.ConfigurationPropertySource);
    Code:
       0: aload_1
       1: ifnull        11
       4: aload_1
       5: instanceof    #7                  // class org/springframework/boot/context/properties/source/IterableConfigurationPropertySource
       8: ifeq          15
      11: iconst_1
      12: goto          16
      15: iconst_0
      16: ireturn

  protected final void bindIndexed(org.springframework.boot.context.properties.source.ConfigurationPropertyName, org.springframework.boot.context.properties.bind.Bindable<?>, org.springframework.boot.context.properties.bind.AggregateElementBinder, org.springframework.core.ResolvableType, org.springframework.core.ResolvableType, org.springframework.boot.context.properties.bind.IndexedElementsBinder$IndexedCollectionSupplier);
    Code:
       0: aload_0
       1: invokevirtual #9                  // Method getContext:()Lorg/springframework/boot/context/properties/bind/Binder$Context;
       4: invokevirtual #15                 // Method org/springframework/boot/context/properties/bind/Binder$Context.getSources:()Ljava/lang/Iterable;
       7: invokeinterface #21,  1           // InterfaceMethod java/lang/Iterable.iterator:()Ljava/util/Iterator;
      12: astore        7
      14: aload         7
      16: invokeinterface #27,  1           // InterfaceMethod java/util/Iterator.hasNext:()Z
      21: ifeq          71
      24: aload         7
      26: invokeinterface #33,  1           // InterfaceMethod java/util/Iterator.next:()Ljava/lang/Object;
      31: checkcast     #37                 // class org/springframework/boot/context/properties/source/ConfigurationPropertySource
      34: astore        8
      36: aload_0
      37: aload         8
      39: aload_1
      40: aload_2
      41: aload_3
      42: aload         6
      44: aload         4
      46: aload         5
      48: invokevirtual #39                 // Method bindIndexed:(Lorg/springframework/boot/context/properties/source/ConfigurationPropertySource;Lorg/springframework/boot/context/properties/source/ConfigurationPropertyName;Lorg/springframework/boot/context/properties/bind/Bindable;Lorg/springframework/boot/context/properties/bind/AggregateElementBinder;Lorg/springframework/boot/context/properties/bind/IndexedElementsBinder$IndexedCollectionSupplier;Lorg/springframework/core/ResolvableType;Lorg/springframework/core/ResolvableType;)V
      51: aload         6
      53: invokevirtual #43                 // Method org/springframework/boot/context/properties/bind/IndexedElementsBinder$IndexedCollectionSupplier.wasSupplied:()Z
      56: ifeq          68
      59: aload         6
      61: invokevirtual #48                 // Method org/springframework/boot/context/properties/bind/IndexedElementsBinder$IndexedCollectionSupplier.get:()Ljava/lang/Object;
      64: ifnull        68
      67: return
      68: goto          14
      71: return

  private void bindIndexed(org.springframework.boot.context.properties.source.ConfigurationPropertySource, org.springframework.boot.context.properties.source.ConfigurationPropertyName, org.springframework.boot.context.properties.bind.Bindable<?>, org.springframework.boot.context.properties.bind.AggregateElementBinder, org.springframework.boot.context.properties.bind.IndexedElementsBinder$IndexedCollectionSupplier, org.springframework.core.ResolvableType, org.springframework.core.ResolvableType);
    Code:
       0: aload_1
       1: aload_2
       2: invokeinterface #51,  2           // InterfaceMethod org/springframework/boot/context/properties/source/ConfigurationPropertySource.getConfigurationProperty:(Lorg/springframework/boot/context/properties/source/ConfigurationPropertyName;)Lorg/springframework/boot/context/properties/source/ConfigurationProperty;
       7: astore        8
       9: aload         8
      11: ifnull        48
      14: aload_0
      15: invokevirtual #9                  // Method getContext:()Lorg/springframework/boot/context/properties/bind/Binder$Context;
      18: aload         8
      20: invokevirtual #55                 // Method org/springframework/boot/context/properties/bind/Binder$Context.setConfigurationProperty:(Lorg/springframework/boot/context/properties/source/ConfigurationProperty;)V
      23: aload_0
      24: aload_3
      25: aload         5
      27: invokevirtual #48                 // Method org/springframework/boot/context/properties/bind/IndexedElementsBinder$IndexedCollectionSupplier.get:()Ljava/lang/Object;
      30: checkcast     #59                 // class java/util/Collection
      33: aload         6
      35: aload         7
      37: aload         8
      39: invokevirtual #61                 // Method org/springframework/boot/context/properties/source/ConfigurationProperty.getValue:()Ljava/lang/Object;
      42: invokevirtual #66                 // Method bindValue:(Lorg/springframework/boot/context/properties/bind/Bindable;Ljava/util/Collection;Lorg/springframework/core/ResolvableType;Lorg/springframework/core/ResolvableType;Ljava/lang/Object;)V
      45: goto          60
      48: aload_0
      49: aload_1
      50: aload_2
      51: aload         4
      53: aload         5
      55: aload         7
      57: invokevirtual #70                 // Method bindIndexed:(Lorg/springframework/boot/context/properties/source/ConfigurationPropertySource;Lorg/springframework/boot/context/properties/source/ConfigurationPropertyName;Lorg/springframework/boot/context/properties/bind/AggregateElementBinder;Lorg/springframework/boot/context/properties/bind/IndexedElementsBinder$IndexedCollectionSupplier;Lorg/springframework/core/ResolvableType;)V
      60: return

  private void bindValue(org.springframework.boot.context.properties.bind.Bindable<?>, java.util.Collection<java.lang.Object>, org.springframework.core.ResolvableType, org.springframework.core.ResolvableType, java.lang.Object);
    Code:
       0: aload         5
       2: ifnull        30
       5: aload         5
       7: instanceof    #73                 // class java/lang/CharSequence
      10: ifeq          31
      13: aload         5
      15: checkcast     #73                 // class java/lang/CharSequence
      18: astore        6
      20: aload         6
      22: invokeinterface #75,  1           // InterfaceMethod java/lang/CharSequence.isEmpty:()Z
      27: ifeq          31
      30: return
      31: aload_0
      32: aload         5
      34: aload_3
      35: aload_1
      36: invokevirtual #78                 // Method org/springframework/boot/context/properties/bind/Bindable.getAnnotations:()[Ljava/lang/annotation/Annotation;
      39: invokevirtual #84                 // Method convert:(Ljava/lang/Object;Lorg/springframework/core/ResolvableType;[Ljava/lang/annotation/Annotation;)Ljava/lang/Object;
      42: astore        6
      44: aload_2
      45: invokevirtual #88                 // Method java/lang/Object.getClass:()Ljava/lang/Class;
      48: iconst_1
      49: anewarray     #94                 // class org/springframework/core/ResolvableType
      52: dup
      53: iconst_0
      54: aload         4
      56: aastore
      57: invokestatic  #96                 // Method org/springframework/core/ResolvableType.forClassWithGenerics:(Ljava/lang/Class;[Lorg/springframework/core/ResolvableType;)Lorg/springframework/core/ResolvableType;
      60: astore        7
      62: aload_0
      63: aload         6
      65: aload         7
      67: iconst_0
      68: anewarray     #100                // class java/lang/annotation/Annotation
      71: invokevirtual #84                 // Method convert:(Ljava/lang/Object;Lorg/springframework/core/ResolvableType;[Ljava/lang/annotation/Annotation;)Ljava/lang/Object;
      74: checkcast     #59                 // class java/util/Collection
      77: astore        8
      79: aload_2
      80: aload         8
      82: invokeinterface #102,  2          // InterfaceMethod java/util/Collection.addAll:(Ljava/util/Collection;)Z
      87: pop
      88: return

  private void bindIndexed(org.springframework.boot.context.properties.source.ConfigurationPropertySource, org.springframework.boot.context.properties.source.ConfigurationPropertyName, org.springframework.boot.context.properties.bind.AggregateElementBinder, org.springframework.boot.context.properties.bind.IndexedElementsBinder$IndexedCollectionSupplier, org.springframework.core.ResolvableType);
    Code:
       0: aload_0
       1: aload_1
       2: aload_2
       3: invokevirtual #106                // Method getKnownIndexedChildren:(Lorg/springframework/boot/context/properties/source/ConfigurationPropertySource;Lorg/springframework/boot/context/properties/source/ConfigurationPropertyName;)Lorg/springframework/util/MultiValueMap;
       6: astore        6
       8: iconst_0
       9: istore        7
      11: iload         7
      13: ldc           #112                // int 2147483647
      15: if_icmpge     103
      18: aload_2
      19: iload         7
      21: ifeq          34
      24: iload         7
      26: invokedynamic #113,  0            // InvokeDynamic #0:makeConcatWithConstants:(I)Ljava/lang/String;
      31: goto          36
      34: ldc           #117                // String [0]
      36: invokevirtual #119                // Method org/springframework/boot/context/properties/source/ConfigurationPropertyName.append:(Ljava/lang/String;)Lorg/springframework/boot/context/properties/source/ConfigurationPropertyName;
      39: astore        8
      41: aload_3
      42: aload         8
      44: aload         5
      46: invokestatic  #125                // Method org/springframework/boot/context/properties/bind/Bindable.of:(Lorg/springframework/core/ResolvableType;)Lorg/springframework/boot/context/properties/bind/Bindable;
      49: aload_1
      50: invokeinterface #129,  4          // InterfaceMethod org/springframework/boot/context/properties/bind/AggregateElementBinder.bind:(Lorg/springframework/boot/context/properties/source/ConfigurationPropertyName;Lorg/springframework/boot/context/properties/bind/Bindable;Lorg/springframework/boot/context/properties/source/ConfigurationPropertySource;)Ljava/lang/Object;
      55: astore        9
      57: aload         9
      59: ifnonnull     65
      62: goto          103
      65: aload         6
      67: aload         8
      69: getstatic     #135                // Field org/springframework/boot/context/properties/source/ConfigurationPropertyName$Form.UNIFORM:Lorg/springframework/boot/context/properties/source/ConfigurationPropertyName$Form;
      72: invokevirtual #141                // Method org/springframework/boot/context/properties/source/ConfigurationPropertyName.getLastElement:(Lorg/springframework/boot/context/properties/source/ConfigurationPropertyName$Form;)Ljava/lang/String;
      75: invokeinterface #145,  2          // InterfaceMethod org/springframework/util/MultiValueMap.remove:(Ljava/lang/Object;)Ljava/lang/Object;
      80: pop
      81: aload         4
      83: invokevirtual #48                 // Method org/springframework/boot/context/properties/bind/IndexedElementsBinder$IndexedCollectionSupplier.get:()Ljava/lang/Object;
      86: checkcast     #59                 // class java/util/Collection
      89: aload         9
      91: invokeinterface #151,  2          // InterfaceMethod java/util/Collection.add:(Ljava/lang/Object;)Z
      96: pop
      97: iinc          7, 1
     100: goto          11
     103: aload_0
     104: aload_1
     105: aload         6
     107: invokevirtual #155                // Method assertNoUnboundChildren:(Lorg/springframework/boot/context/properties/source/ConfigurationPropertySource;Lorg/springframework/util/MultiValueMap;)V
     110: return

  private org.springframework.util.MultiValueMap<java.lang.String, org.springframework.boot.context.properties.source.ConfigurationPropertyName> getKnownIndexedChildren(org.springframework.boot.context.properties.source.ConfigurationPropertySource, org.springframework.boot.context.properties.source.ConfigurationPropertyName);
    Code:
       0: new           #159                // class org/springframework/util/LinkedMultiValueMap
       3: dup
       4: invokespecial #161                // Method org/springframework/util/LinkedMultiValueMap."<init>":()V
       7: astore_3
       8: aload_1
       9: instanceof    #7                  // class org/springframework/boot/context/properties/source/IterableConfigurationPropertySource
      12: ifeq          24
      15: aload_1
      16: checkcast     #7                  // class org/springframework/boot/context/properties/source/IterableConfigurationPropertySource
      19: astore        4
      21: goto          26
      24: aload_3
      25: areturn
      26: aload         4
      28: aload_2
      29: dup
      30: invokestatic  #164                // Method java/util/Objects.requireNonNull:(Ljava/lang/Object;)Ljava/lang/Object;
      33: pop
      34: invokedynamic #169,  0            // InvokeDynamic #1:test:(Lorg/springframework/boot/context/properties/source/ConfigurationPropertyName;)Ljava/util/function/Predicate;
      39: invokeinterface #173,  2          // InterfaceMethod org/springframework/boot/context/properties/source/IterableConfigurationPropertySource.filter:(Ljava/util/function/Predicate;)Lorg/springframework/boot/context/properties/source/IterableConfigurationPropertySource;
      44: invokeinterface #177,  1          // InterfaceMethod org/springframework/boot/context/properties/source/IterableConfigurationPropertySource.iterator:()Ljava/util/Iterator;
      49: astore        5
      51: aload         5
      53: invokeinterface #27,  1           // InterfaceMethod java/util/Iterator.hasNext:()Z
      58: ifeq          117
      61: aload         5
      63: invokeinterface #33,  1           // InterfaceMethod java/util/Iterator.next:()Ljava/lang/Object;
      68: checkcast     #120                // class org/springframework/boot/context/properties/source/ConfigurationPropertyName
      71: astore        6
      73: aload         6
      75: aload_2
      76: invokevirtual #178                // Method org/springframework/boot/context/properties/source/ConfigurationPropertyName.getNumberOfElements:()I
      79: iconst_1
      80: iadd
      81: invokevirtual #182                // Method org/springframework/boot/context/properties/source/ConfigurationPropertyName.chop:(I)Lorg/springframework/boot/context/properties/source/ConfigurationPropertyName;
      84: astore        7
      86: aload         7
      88: invokevirtual #186                // Method org/springframework/boot/context/properties/source/ConfigurationPropertyName.isLastElementIndexed:()Z
      91: ifeq          114
      94: aload         7
      96: getstatic     #135                // Field org/springframework/boot/context/properties/source/ConfigurationPropertyName$Form.UNIFORM:Lorg/springframework/boot/context/properties/source/ConfigurationPropertyName$Form;
      99: invokevirtual #141                // Method org/springframework/boot/context/properties/source/ConfigurationPropertyName.getLastElement:(Lorg/springframework/boot/context/properties/source/ConfigurationPropertyName$Form;)Ljava/lang/String;
     102: astore        8
     104: aload_3
     105: aload         8
     107: aload         6
     109: invokeinterface #189,  3          // InterfaceMethod org/springframework/util/MultiValueMap.add:(Ljava/lang/Object;Ljava/lang/Object;)V
     114: goto          51
     117: aload_3
     118: areturn

  private void assertNoUnboundChildren(org.springframework.boot.context.properties.source.ConfigurationPropertySource, org.springframework.util.MultiValueMap<java.lang.String, org.springframework.boot.context.properties.source.ConfigurationPropertyName>);
    Code:
       0: aload_2
       1: invokeinterface #192,  1          // InterfaceMethod org/springframework/util/MultiValueMap.isEmpty:()Z
       6: ifne          70
       9: new           #193                // class org/springframework/boot/context/properties/bind/UnboundConfigurationPropertiesException
      12: dup
      13: aload_2
      14: invokeinterface #195,  1          // InterfaceMethod org/springframework/util/MultiValueMap.values:()Ljava/util/Collection;
      19: invokeinterface #199,  1          // InterfaceMethod java/util/Collection.stream:()Ljava/util/stream/Stream;
      24: invokedynamic #203,  0            // InvokeDynamic #2:apply:()Ljava/util/function/Function;
      29: invokeinterface #207,  2          // InterfaceMethod java/util/stream/Stream.flatMap:(Ljava/util/function/Function;)Ljava/util/stream/Stream;
      34: aload_1
      35: dup
      36: invokestatic  #164                // Method java/util/Objects.requireNonNull:(Ljava/lang/Object;)Ljava/lang/Object;
      39: pop
      40: invokedynamic #213,  0            // InvokeDynamic #3:apply:(Lorg/springframework/boot/context/properties/source/ConfigurationPropertySource;)Ljava/util/function/Function;
      45: invokeinterface #216,  2          // InterfaceMethod java/util/stream/Stream.map:(Ljava/util/function/Function;)Ljava/util/stream/Stream;
      50: invokedynamic #219,  0            // InvokeDynamic #4:get:()Ljava/util/function/Supplier;
      55: invokestatic  #222                // Method java/util/stream/Collectors.toCollection:(Ljava/util/function/Supplier;)Ljava/util/stream/Collector;
      58: invokeinterface #228,  2          // InterfaceMethod java/util/stream/Stream.collect:(Ljava/util/stream/Collector;)Ljava/lang/Object;
      63: checkcast     #232                // class java/util/Set
      66: invokespecial #234                // Method org/springframework/boot/context/properties/bind/UnboundConfigurationPropertiesException."<init>":(Ljava/util/Set;)V
      69: athrow
      70: return

  private <C> C convert(java.lang.Object, org.springframework.core.ResolvableType, java.lang.annotation.Annotation...);
    Code:
       0: aload_0
       1: invokevirtual #9                  // Method getContext:()Lorg/springframework/boot/context/properties/bind/Binder$Context;
       4: invokevirtual #237                // Method org/springframework/boot/context/properties/bind/Binder$Context.getPlaceholdersResolver:()Lorg/springframework/boot/context/properties/bind/PlaceholdersResolver;
       7: aload_1
       8: invokeinterface #241,  2          // InterfaceMethod org/springframework/boot/context/properties/bind/PlaceholdersResolver.resolvePlaceholders:(Ljava/lang/Object;)Ljava/lang/Object;
      13: astore_1
      14: aload_0
      15: invokevirtual #9                  // Method getContext:()Lorg/springframework/boot/context/properties/bind/Binder$Context;
      18: invokevirtual #246                // Method org/springframework/boot/context/properties/bind/Binder$Context.getConverter:()Lorg/springframework/boot/context/properties/bind/BindConverter;
      21: aload_1
      22: aload_2
      23: aload_3
      24: invokevirtual #250                // Method org/springframework/boot/context/properties/bind/BindConverter.convert:(Ljava/lang/Object;Lorg/springframework/core/ResolvableType;[Ljava/lang/annotation/Annotation;)Ljava/lang/Object;
      27: areturn
}
