Compiled from "JavaBeanBinder.java"
class org.springframework.boot.context.properties.bind.JavaBeanBinder$BeanProperty {
  private final java.lang.String name;

  private final org.springframework.core.ResolvableType declaringClassType;

  private java.lang.reflect.Method getter;

  private java.lang.reflect.Method setter;

  private java.lang.reflect.Field field;

  org.springframework.boot.context.properties.bind.JavaBeanBinder$BeanProperty(java.lang.String, org.springframework.core.ResolvableType);
    Code:
       0: aload_0
       1: invokespecial #1                  // Method java/lang/Object."<init>":()V
       4: aload_0
       5: aload_1
       6: invokestatic  #7                  // Method org/springframework/boot/context/properties/bind/DataObjectPropertyName.toDashedForm:(Ljava/lang/String;)Ljava/lang/String;
       9: putfield      #13                 // Field name:Ljava/lang/String;
      12: aload_0
      13: aload_2
      14: putfield      #19                 // Field declaringClassType:Lorg/springframework/core/ResolvableType;
      17: return

  void addGetter(java.lang.reflect.Method);
    Code:
       0: aload_0
       1: getfield      #23                 // Field getter:Ljava/lang/reflect/Method;
       4: ifnull        22
       7: aload_0
       8: getfield      #23                 // Field getter:Ljava/lang/reflect/Method;
      11: invokevirtual #27                 // Method java/lang/reflect/Method.getName:()Ljava/lang/String;
      14: ldc           #33                 // String is
      16: invokevirtual #35                 // Method java/lang/String.startsWith:(Ljava/lang/String;)Z
      19: ifeq          27
      22: aload_0
      23: aload_1
      24: putfield      #23                 // Field getter:Ljava/lang/reflect/Method;
      27: return

  void addSetter(java.lang.reflect.Method);
    Code:
       0: aload_0
       1: getfield      #41                 // Field setter:Ljava/lang/reflect/Method;
       4: ifnull        15
       7: aload_0
       8: aload_1
       9: invokevirtual #44                 // Method isBetterSetter:(Ljava/lang/reflect/Method;)Z
      12: ifeq          20
      15: aload_0
      16: aload_1
      17: putfield      #41                 // Field setter:Ljava/lang/reflect/Method;
      20: return

  private boolean isBetterSetter(java.lang.reflect.Method);
    Code:
       0: aload_0
       1: getfield      #23                 // Field getter:Ljava/lang/reflect/Method;
       4: ifnull        30
       7: aload_0
       8: getfield      #23                 // Field getter:Ljava/lang/reflect/Method;
      11: invokevirtual #48                 // Method java/lang/reflect/Method.getReturnType:()Ljava/lang/Class;
      14: aload_1
      15: invokevirtual #52                 // Method java/lang/reflect/Method.getParameterTypes:()[Ljava/lang/Class;
      18: iconst_0
      19: aaload
      20: invokevirtual #56                 // Method java/lang/Object.equals:(Ljava/lang/Object;)Z
      23: ifeq          30
      26: iconst_1
      27: goto          31
      30: iconst_0
      31: ireturn

  void addField(java.lang.reflect.Field);
    Code:
       0: aload_0
       1: getfield      #60                 // Field field:Ljava/lang/reflect/Field;
       4: ifnonnull     12
       7: aload_0
       8: aload_1
       9: putfield      #60                 // Field field:Ljava/lang/reflect/Field;
      12: return

  java.lang.String getName();
    Code:
       0: aload_0
       1: getfield      #13                 // Field name:Ljava/lang/String;
       4: areturn

  org.springframework.core.ResolvableType getType();
    Code:
       0: aload_0
       1: getfield      #41                 // Field setter:Ljava/lang/reflect/Method;
       4: ifnull        29
       7: new           #64                 // class org/springframework/core/MethodParameter
      10: dup
      11: aload_0
      12: getfield      #41                 // Field setter:Ljava/lang/reflect/Method;
      15: iconst_0
      16: invokespecial #66                 // Method org/springframework/core/MethodParameter."<init>":(Ljava/lang/reflect/Method;I)V
      19: astore_1
      20: aload_1
      21: aload_0
      22: getfield      #19                 // Field declaringClassType:Lorg/springframework/core/ResolvableType;
      25: invokestatic  #69                 // Method org/springframework/core/ResolvableType.forMethodParameter:(Lorg/springframework/core/MethodParameter;Lorg/springframework/core/ResolvableType;)Lorg/springframework/core/ResolvableType;
      28: areturn
      29: new           #64                 // class org/springframework/core/MethodParameter
      32: dup
      33: aload_0
      34: getfield      #23                 // Field getter:Ljava/lang/reflect/Method;
      37: iconst_m1
      38: invokespecial #66                 // Method org/springframework/core/MethodParameter."<init>":(Ljava/lang/reflect/Method;I)V
      41: astore_1
      42: aload_1
      43: aload_0
      44: getfield      #19                 // Field declaringClassType:Lorg/springframework/core/ResolvableType;
      47: invokestatic  #69                 // Method org/springframework/core/ResolvableType.forMethodParameter:(Lorg/springframework/core/MethodParameter;Lorg/springframework/core/ResolvableType;)Lorg/springframework/core/ResolvableType;
      50: areturn

  java.lang.annotation.Annotation[] getAnnotations();
    Code:
       0: aload_0
       1: getfield      #60                 // Field field:Ljava/lang/reflect/Field;
       4: ifnull        17
       7: aload_0
       8: getfield      #60                 // Field field:Ljava/lang/reflect/Field;
      11: invokevirtual #75                 // Method java/lang/reflect/Field.getDeclaredAnnotations:()[Ljava/lang/annotation/Annotation;
      14: goto          18
      17: aconst_null
      18: areturn
      19: astore_1
      20: aconst_null
      21: areturn
    Exception table:
       from    to  target type
           0    18    19   Class java/lang/Exception

  java.util.function.Supplier<java.lang.Object> getValue(java.util.function.Supplier<?>);
    Code:
       0: aload_0
       1: getfield      #23                 // Field getter:Ljava/lang/reflect/Method;
       4: ifnonnull     9
       7: aconst_null
       8: areturn
       9: aload_0
      10: aload_1
      11: invokedynamic #83,  0             // InvokeDynamic #0:get:(Lorg/springframework/boot/context/properties/bind/JavaBeanBinder$BeanProperty;Ljava/util/function/Supplier;)Ljava/util/function/Supplier;
      16: areturn

  boolean isSettable();
    Code:
       0: aload_0
       1: getfield      #41                 // Field setter:Ljava/lang/reflect/Method;
       4: ifnull        11
       7: iconst_1
       8: goto          12
      11: iconst_0
      12: ireturn

  void setValue(java.util.function.Supplier<?>, java.lang.Object);
    Code:
       0: aload_0
       1: getfield      #41                 // Field setter:Ljava/lang/reflect/Method;
       4: iconst_1
       5: invokevirtual #87                 // Method java/lang/reflect/Method.setAccessible:(Z)V
       8: aload_0
       9: getfield      #41                 // Field setter:Ljava/lang/reflect/Method;
      12: aload_1
      13: invokeinterface #91,  1           // InterfaceMethod java/util/function/Supplier.get:()Ljava/lang/Object;
      18: iconst_1
      19: anewarray     #2                  // class java/lang/Object
      22: dup
      23: iconst_0
      24: aload_2
      25: aastore
      26: invokevirtual #96                 // Method java/lang/reflect/Method.invoke:(Ljava/lang/Object;[Ljava/lang/Object;)Ljava/lang/Object;
      29: pop
      30: goto          52
      33: astore_3
      34: new           #100                // class java/lang/IllegalStateException
      37: dup
      38: aload_0
      39: getfield      #13                 // Field name:Ljava/lang/String;
      42: invokedynamic #102,  0            // InvokeDynamic #1:makeConcatWithConstants:(Ljava/lang/String;)Ljava/lang/String;
      47: aload_3
      48: invokespecial #105                // Method java/lang/IllegalStateException."<init>":(Ljava/lang/String;Ljava/lang/Throwable;)V
      51: athrow
      52: return
    Exception table:
       from    to  target type
           0    30    33   Class java/lang/Exception

  java.lang.reflect.Method getGetter();
    Code:
       0: aload_0
       1: getfield      #23                 // Field getter:Ljava/lang/reflect/Method;
       4: areturn

  java.lang.reflect.Method getSetter();
    Code:
       0: aload_0
       1: getfield      #41                 // Field setter:Ljava/lang/reflect/Method;
       4: areturn

  private java.lang.Object lambda$getValue$0(java.util.function.Supplier);
    Code:
       0: aload_0
       1: getfield      #23                 // Field getter:Ljava/lang/reflect/Method;
       4: iconst_1
       5: invokevirtual #87                 // Method java/lang/reflect/Method.setAccessible:(Z)V
       8: aload_0
       9: getfield      #23                 // Field getter:Ljava/lang/reflect/Method;
      12: aload_1
      13: invokeinterface #91,  1           // InterfaceMethod java/util/function/Supplier.get:()Ljava/lang/Object;
      18: iconst_0
      19: anewarray     #2                  // class java/lang/Object
      22: invokevirtual #96                 // Method java/lang/reflect/Method.invoke:(Ljava/lang/Object;[Ljava/lang/Object;)Ljava/lang/Object;
      25: areturn
      26: astore_2
      27: new           #100                // class java/lang/IllegalStateException
      30: dup
      31: aload_0
      32: getfield      #13                 // Field name:Ljava/lang/String;
      35: invokedynamic #108,  0            // InvokeDynamic #2:makeConcatWithConstants:(Ljava/lang/String;)Ljava/lang/String;
      40: aload_2
      41: invokespecial #105                // Method java/lang/IllegalStateException."<init>":(Ljava/lang/String;Ljava/lang/Throwable;)V
      44: athrow
    Exception table:
       from    to  target type
           0    25    26   Class java/lang/Exception
}
