Compiled from "JavaBeanBinder.java"
class org.springframework.boot.context.properties.bind.JavaBeanBinder$Bean<T> extends org.springframework.boot.context.properties.bind.JavaBeanBinder$BeanProperties {
  private static org.springframework.boot.context.properties.bind.JavaBeanBinder$Bean<?> cached;

  org.springframework.boot.context.properties.bind.JavaBeanBinder$Bean(org.springframework.core.ResolvableType, java.lang.Class<?>);
    Code:
       0: aload_0
       1: aload_1
       2: aload_2
       3: invokespecial #1                  // Method org/springframework/boot/context/properties/bind/JavaBeanBinder$BeanProperties."<init>":(Lorg/springframework/core/ResolvableType;Ljava/lang/Class;)V
       6: return

  org.springframework.boot.context.properties.bind.JavaBeanBinder$BeanSupplier<T> getSupplier(org.springframework.boot.context.properties.bind.Bindable<T>);
    Code:
       0: new           #7                  // class org/springframework/boot/context/properties/bind/JavaBeanBinder$BeanSupplier
       3: dup
       4: aload_0
       5: aload_1
       6: invokedynamic #9,  0              // InvokeDynamic #0:get:(Lorg/springframework/boot/context/properties/bind/JavaBeanBinder$Bean;Lorg/springframework/boot/context/properties/bind/Bindable;)Ljava/util/function/Supplier;
      11: invokespecial #13                 // Method org/springframework/boot/context/properties/bind/JavaBeanBinder$BeanSupplier."<init>":(Ljava/util/function/Supplier;)V
      14: areturn

  static <T> org.springframework.boot.context.properties.bind.JavaBeanBinder$Bean<T> get(org.springframework.boot.context.properties.bind.Bindable<T>, boolean);
    Code:
       0: aload_0
       1: invokevirtual #16                 // Method org/springframework/boot/context/properties/bind/Bindable.getType:()Lorg/springframework/core/ResolvableType;
       4: astore_2
       5: aload_2
       6: ldc           #22                 // class java/lang/Object
       8: invokevirtual #24                 // Method org/springframework/core/ResolvableType.resolve:(Ljava/lang/Class;)Ljava/lang/Class;
      11: astore_3
      12: aload_0
      13: invokevirtual #30                 // Method org/springframework/boot/context/properties/bind/Bindable.getValue:()Ljava/util/function/Supplier;
      16: astore        4
      18: aconst_null
      19: astore        5
      21: iload_1
      22: ifeq          54
      25: aload         4
      27: ifnull        54
      30: aload         4
      32: invokeinterface #34,  1           // InterfaceMethod java/util/function/Supplier.get:()Ljava/lang/Object;
      37: astore        5
      39: aload         5
      41: ifnull        52
      44: aload         5
      46: invokevirtual #39                 // Method java/lang/Object.getClass:()Ljava/lang/Class;
      49: goto          53
      52: aload_3
      53: astore_3
      54: aload         5
      56: ifnonnull     68
      59: aload_3
      60: invokestatic  #43                 // Method isInstantiable:(Ljava/lang/Class;)Z
      63: ifne          68
      66: aconst_null
      67: areturn
      68: getstatic     #49                 // Field cached:Lorg/springframework/boot/context/properties/bind/JavaBeanBinder$Bean;
      71: astore        6
      73: aload         6
      75: ifnull        88
      78: aload         6
      80: aload_2
      81: aload_3
      82: invokevirtual #53                 // Method isOfType:(Lorg/springframework/core/ResolvableType;Ljava/lang/Class;)Z
      85: ifne          104
      88: new           #44                 // class org/springframework/boot/context/properties/bind/JavaBeanBinder$Bean
      91: dup
      92: aload_2
      93: aload_3
      94: invokespecial #57                 // Method "<init>":(Lorg/springframework/core/ResolvableType;Ljava/lang/Class;)V
      97: astore        6
      99: aload         6
     101: putstatic     #49                 // Field cached:Lorg/springframework/boot/context/properties/bind/JavaBeanBinder$Bean;
     104: aload         6
     106: areturn

  private static boolean isInstantiable(java.lang.Class<?>);
    Code:
       0: aload_0
       1: invokevirtual #58                 // Method java/lang/Class.isInterface:()Z
       4: ifeq          9
       7: iconst_0
       8: ireturn
       9: aload_0
      10: iconst_0
      11: anewarray     #59                 // class java/lang/Class
      14: invokevirtual #64                 // Method java/lang/Class.getDeclaredConstructor:([Ljava/lang/Class;)Ljava/lang/reflect/Constructor;
      17: pop
      18: iconst_1
      19: ireturn
      20: astore_1
      21: iconst_0
      22: ireturn
    Exception table:
       from    to  target type
           9    19    20   Class java/lang/Exception

  private boolean isOfType(org.springframework.core.ResolvableType, java.lang.Class<?>);
    Code:
       0: aload_0
       1: invokevirtual #70                 // Method getType:()Lorg/springframework/core/ResolvableType;
       4: invokevirtual #71                 // Method org/springframework/core/ResolvableType.hasGenerics:()Z
       7: ifne          17
      10: aload_1
      11: invokevirtual #71                 // Method org/springframework/core/ResolvableType.hasGenerics:()Z
      14: ifeq          26
      17: aload_0
      18: invokevirtual #70                 // Method getType:()Lorg/springframework/core/ResolvableType;
      21: aload_1
      22: invokevirtual #74                 // Method org/springframework/core/ResolvableType.equals:(Ljava/lang/Object;)Z
      25: ireturn
      26: aload_0
      27: invokevirtual #78                 // Method getResolvedType:()Ljava/lang/Class;
      30: ifnull        48
      33: aload_0
      34: invokevirtual #78                 // Method getResolvedType:()Ljava/lang/Class;
      37: aload_2
      38: invokevirtual #81                 // Method java/lang/Object.equals:(Ljava/lang/Object;)Z
      41: ifeq          48
      44: iconst_1
      45: goto          49
      48: iconst_0
      49: ireturn

  private java.lang.Object lambda$getSupplier$0(org.springframework.boot.context.properties.bind.Bindable);
    Code:
       0: aconst_null
       1: astore_2
       2: aload_1
       3: invokevirtual #30                 // Method org/springframework/boot/context/properties/bind/Bindable.getValue:()Ljava/util/function/Supplier;
       6: ifnull        19
       9: aload_1
      10: invokevirtual #30                 // Method org/springframework/boot/context/properties/bind/Bindable.getValue:()Ljava/util/function/Supplier;
      13: invokeinterface #34,  1           // InterfaceMethod java/util/function/Supplier.get:()Ljava/lang/Object;
      18: astore_2
      19: aload_2
      20: ifnonnull     31
      23: aload_0
      24: invokevirtual #78                 // Method getResolvedType:()Ljava/lang/Class;
      27: invokestatic  #82                 // Method org/springframework/beans/BeanUtils.instantiateClass:(Ljava/lang/Class;)Ljava/lang/Object;
      30: astore_2
      31: aload_2
      32: areturn
}
