Compiled from "MissingParametersCompilerArgumentException.java"
class org.springframework.boot.context.properties.bind.MissingParametersCompilerArgumentException extends java.lang.RuntimeException {
  org.springframework.boot.context.properties.bind.MissingParametersCompilerArgumentException(java.util.Set<java.lang.Class<?>>);
    Code:
       0: aload_0
       1: aload_1
       2: invokestatic  #1                  // Method message:(Ljava/util/Set;)Ljava/lang/String;
       5: invokespecial #7                  // Method java/lang/RuntimeException."<init>":(Ljava/lang/String;)V
       8: return

  private static java.lang.String message(java.util.Set<java.lang.Class<?>>);
    Code:
       0: new           #13                 // class java/lang/StringBuilder
       3: dup
       4: ldc           #15                 // String Constructor binding in a native image requires compilation with -parameters but the following classes were compiled without it:%n
       6: iconst_0
       7: anewarray     #17                 // class java/lang/Object
      10: invokestatic  #19                 // Method java/lang/String.format:(Ljava/lang/String;[Ljava/lang/Object;)Ljava/lang/String;
      13: invokespecial #25                 // Method java/lang/StringBuilder."<init>":(Ljava/lang/String;)V
      16: astore_1
      17: aload_0
      18: invokeinterface #26,  1           // InterfaceMethod java/util/Set.iterator:()Ljava/util/Iterator;
      23: astore_2
      24: aload_2
      25: invokeinterface #32,  1           // InterfaceMethod java/util/Iterator.hasNext:()Z
      30: ifeq          67
      33: aload_2
      34: invokeinterface #38,  1           // InterfaceMethod java/util/Iterator.next:()Ljava/lang/Object;
      39: checkcast     #42                 // class java/lang/Class
      42: astore_3
      43: aload_1
      44: ldc           #44                 // String \t%s%n
      46: iconst_1
      47: anewarray     #17                 // class java/lang/Object
      50: dup
      51: iconst_0
      52: aload_3
      53: invokevirtual #46                 // Method java/lang/Class.getName:()Ljava/lang/String;
      56: aastore
      57: invokestatic  #19                 // Method java/lang/String.format:(Ljava/lang/String;[Ljava/lang/Object;)Ljava/lang/String;
      60: invokevirtual #50                 // Method java/lang/StringBuilder.append:(Ljava/lang/String;)Ljava/lang/StringBuilder;
      63: pop
      64: goto          24
      67: aload_1
      68: invokevirtual #54                 // Method java/lang/StringBuilder.toString:()Ljava/lang/String;
      71: areturn
}
