Compiled from "ValueObjectBinder.java"
final class org.springframework.boot.context.properties.bind.ValueObjectBinder$DefaultValueObject<T> extends org.springframework.boot.context.properties.bind.ValueObjectBinder$ValueObject<T> {
  private static final org.springframework.core.ParameterNameDiscoverer PARAMETER_NAME_DISCOVERER;

  private final java.util.List<org.springframework.boot.context.properties.bind.ValueObjectBinder$ConstructorParameter> constructorParameters;

  private org.springframework.boot.context.properties.bind.ValueObjectBinder$DefaultValueObject(java.lang.reflect.Constructor<T>, org.springframework.core.ResolvableType);
    Code:
       0: aload_0
       1: aload_1
       2: invokespecial #1                  // Method org/springframework/boot/context/properties/bind/ValueObjectBinder$ValueObject."<init>":(Ljava/lang/reflect/Constructor;)V
       5: aload_0
       6: aload_1
       7: aload_2
       8: invokestatic  #7                  // Method parseConstructorParameters:(Ljava/lang/reflect/Constructor;Lorg/springframework/core/ResolvableType;)Ljava/util/List;
      11: putfield      #13                 // Field constructorParameters:Ljava/util/List;
      14: return

  private static java.util.List<org.springframework.boot.context.properties.bind.ValueObjectBinder$ConstructorParameter> parseConstructorParameters(java.lang.reflect.Constructor<?>, org.springframework.core.ResolvableType);
    Code:
       0: getstatic     #17                 // Field PARAMETER_NAME_DISCOVERER:Lorg/springframework/core/ParameterNameDiscoverer;
       3: aload_0
       4: invokeinterface #21,  2           // InterfaceMethod org/springframework/core/ParameterNameDiscoverer.getParameterNames:(Ljava/lang/reflect/Constructor;)[Ljava/lang/String;
       9: astore_2
      10: aload_2
      11: ifnull        18
      14: iconst_1
      15: goto          19
      18: iconst_0
      19: aload_0
      20: invokedynamic #27,  0             // InvokeDynamic #0:get:(Ljava/lang/reflect/Constructor;)Ljava/util/function/Supplier;
      25: invokestatic  #31                 // Method org/springframework/util/Assert.state:(ZLjava/util/function/Supplier;)V
      28: aload_0
      29: invokevirtual #37                 // Method java/lang/reflect/Constructor.getParameters:()[Ljava/lang/reflect/Parameter;
      32: astore_3
      33: new           #43                 // class java/util/ArrayList
      36: dup
      37: aload_3
      38: arraylength
      39: invokespecial #45                 // Method java/util/ArrayList."<init>":(I)V
      42: astore        4
      44: iconst_0
      45: istore        5
      47: iload         5
      49: aload_3
      50: arraylength
      51: if_icmpge     141
      54: aload_3
      55: iload         5
      57: aaload
      58: invokestatic  #48                 // InterfaceMethod org/springframework/core/annotation/MergedAnnotations.from:(Ljava/lang/reflect/AnnotatedElement;)Lorg/springframework/core/annotation/MergedAnnotations;
      61: ldc           #54                 // class org/springframework/boot/context/properties/bind/Name
      63: invokeinterface #56,  2           // InterfaceMethod org/springframework/core/annotation/MergedAnnotations.get:(Ljava/lang/Class;)Lorg/springframework/core/annotation/MergedAnnotation;
      68: ldc           #61                 // String value
      70: ldc           #63                 // class java/lang/String
      72: invokeinterface #65,  3           // InterfaceMethod org/springframework/core/annotation/MergedAnnotation.getValue:(Ljava/lang/String;Ljava/lang/Class;)Ljava/util/Optional;
      77: aload_2
      78: iload         5
      80: aaload
      81: invokevirtual #69                 // Method java/util/Optional.orElse:(Ljava/lang/Object;)Ljava/lang/Object;
      84: checkcast     #63                 // class java/lang/String
      87: astore        6
      89: new           #75                 // class org/springframework/core/MethodParameter
      92: dup
      93: aload_0
      94: iload         5
      96: invokespecial #77                 // Method org/springframework/core/MethodParameter."<init>":(Ljava/lang/reflect/Constructor;I)V
      99: aload_1
     100: invokestatic  #80                 // Method org/springframework/core/ResolvableType.forMethodParameter:(Lorg/springframework/core/MethodParameter;Lorg/springframework/core/ResolvableType;)Lorg/springframework/core/ResolvableType;
     103: astore        7
     105: aload_3
     106: iload         5
     108: aaload
     109: invokevirtual #86                 // Method java/lang/reflect/Parameter.getDeclaredAnnotations:()[Ljava/lang/annotation/Annotation;
     112: astore        8
     114: aload         4
     116: new           #92                 // class org/springframework/boot/context/properties/bind/ValueObjectBinder$ConstructorParameter
     119: dup
     120: aload         6
     122: aload         7
     124: aload         8
     126: invokespecial #94                 // Method org/springframework/boot/context/properties/bind/ValueObjectBinder$ConstructorParameter."<init>":(Ljava/lang/String;Lorg/springframework/core/ResolvableType;[Ljava/lang/annotation/Annotation;)V
     129: invokeinterface #97,  2           // InterfaceMethod java/util/List.add:(Ljava/lang/Object;)Z
     134: pop
     135: iinc          5, 1
     138: goto          47
     141: aload         4
     143: invokestatic  #103                // Method java/util/Collections.unmodifiableList:(Ljava/util/List;)Ljava/util/List;
     146: areturn

  java.util.List<org.springframework.boot.context.properties.bind.ValueObjectBinder$ConstructorParameter> getConstructorParameters();
    Code:
       0: aload_0
       1: getfield      #13                 // Field constructorParameters:Ljava/util/List;
       4: areturn

  static <T> org.springframework.boot.context.properties.bind.ValueObjectBinder$ValueObject<T> get(java.lang.reflect.Constructor<?>, org.springframework.core.ResolvableType);
    Code:
       0: new           #8                  // class org/springframework/boot/context/properties/bind/ValueObjectBinder$DefaultValueObject
       3: dup
       4: aload_0
       5: aload_1
       6: invokespecial #109                // Method "<init>":(Ljava/lang/reflect/Constructor;Lorg/springframework/core/ResolvableType;)V
       9: areturn

  private static java.lang.String lambda$parseConstructorParameters$0(java.lang.reflect.Constructor);
    Code:
       0: aload_0
       1: invokedynamic #112,  0            // InvokeDynamic #1:makeConcatWithConstants:(Ljava/lang/reflect/Constructor;)Ljava/lang/String;
       6: areturn

  static {};
    Code:
       0: new           #116                // class org/springframework/core/DefaultParameterNameDiscoverer
       3: dup
       4: invokespecial #118                // Method org/springframework/core/DefaultParameterNameDiscoverer."<init>":()V
       7: putstatic     #17                 // Field PARAMETER_NAME_DISCOVERER:Lorg/springframework/core/ParameterNameDiscoverer;
      10: return
}
