Compiled from "ValueObjectBinder.java"
class org.springframework.boot.context.properties.bind.ValueObjectBinder implements org.springframework.boot.context.properties.bind.DataObjectBinder {
  private final org.springframework.boot.context.properties.bind.BindConstructorProvider constructorProvider;

  org.springframework.boot.context.properties.bind.ValueObjectBinder(org.springframework.boot.context.properties.bind.BindConstructorProvider);
    Code:
       0: aload_0
       1: invokespecial #1                  // Method java/lang/Object."<init>":()V
       4: aload_0
       5: aload_1
       6: putfield      #7                  // Field constructorProvider:Lorg/springframework/boot/context/properties/bind/BindConstructorProvider;
       9: return

  public <T> T bind(org.springframework.boot.context.properties.source.ConfigurationPropertyName, org.springframework.boot.context.properties.bind.Bindable<T>, org.springframework.boot.context.properties.bind.Binder$Context, org.springframework.boot.context.properties.bind.DataObjectPropertyBinder);
    Code:
       0: aload_2
       1: aload_0
       2: getfield      #7                  // Field constructorProvider:Lorg/springframework/boot/context/properties/bind/BindConstructorProvider;
       5: aload_3
       6: invokestatic  #13                 // Method org/springframework/boot/context/properties/bind/ValueObjectBinder$ValueObject.get:(Lorg/springframework/boot/context/properties/bind/Bindable;Lorg/springframework/boot/context/properties/bind/BindConstructorProvider;Lorg/springframework/boot/context/properties/bind/Binder$Context;)Lorg/springframework/boot/context/properties/bind/ValueObjectBinder$ValueObject;
       9: astore        5
      11: aload         5
      13: ifnonnull     18
      16: aconst_null
      17: areturn
      18: aload_3
      19: aload_2
      20: invokevirtual #19                 // Method org/springframework/boot/context/properties/bind/Bindable.getType:()Lorg/springframework/core/ResolvableType;
      23: invokevirtual #25                 // Method org/springframework/core/ResolvableType.resolve:()Ljava/lang/Class;
      26: invokevirtual #31                 // Method org/springframework/boot/context/properties/bind/Binder$Context.pushConstructorBoundTypes:(Ljava/lang/Class;)V
      29: aload         5
      31: invokevirtual #37                 // Method org/springframework/boot/context/properties/bind/ValueObjectBinder$ValueObject.getConstructorParameters:()Ljava/util/List;
      34: astore        6
      36: new           #41                 // class java/util/ArrayList
      39: dup
      40: aload         6
      42: invokeinterface #43,  1           // InterfaceMethod java/util/List.size:()I
      47: invokespecial #49                 // Method java/util/ArrayList."<init>":(I)V
      50: astore        7
      52: iconst_0
      53: istore        8
      55: aload         6
      57: invokeinterface #52,  1           // InterfaceMethod java/util/List.iterator:()Ljava/util/Iterator;
      62: astore        9
      64: aload         9
      66: invokeinterface #56,  1           // InterfaceMethod java/util/Iterator.hasNext:()Z
      71: ifeq          144
      74: aload         9
      76: invokeinterface #62,  1           // InterfaceMethod java/util/Iterator.next:()Ljava/lang/Object;
      81: checkcast     #66                 // class org/springframework/boot/context/properties/bind/ValueObjectBinder$ConstructorParameter
      84: astore        10
      86: aload         10
      88: aload         4
      90: invokevirtual #68                 // Method org/springframework/boot/context/properties/bind/ValueObjectBinder$ConstructorParameter.bind:(Lorg/springframework/boot/context/properties/bind/DataObjectPropertyBinder;)Ljava/lang/Object;
      93: astore        11
      95: iload         8
      97: ifne          105
     100: aload         11
     102: ifnull        109
     105: iconst_1
     106: goto          110
     109: iconst_0
     110: istore        8
     112: aload         11
     114: ifnull        122
     117: aload         11
     119: goto          129
     122: aload_0
     123: aload_3
     124: aload         10
     126: invokevirtual #72                 // Method getDefaultValue:(Lorg/springframework/boot/context/properties/bind/Binder$Context;Lorg/springframework/boot/context/properties/bind/ValueObjectBinder$ConstructorParameter;)Ljava/lang/Object;
     129: astore        11
     131: aload         7
     133: aload         11
     135: invokeinterface #76,  2           // InterfaceMethod java/util/List.add:(Ljava/lang/Object;)Z
     140: pop
     141: goto          64
     144: aload_3
     145: invokevirtual #80                 // Method org/springframework/boot/context/properties/bind/Binder$Context.clearConfigurationProperty:()V
     148: aload_3
     149: invokevirtual #83                 // Method org/springframework/boot/context/properties/bind/Binder$Context.popConstructorBoundTypes:()V
     152: iload         8
     154: ifeq          167
     157: aload         5
     159: aload         7
     161: invokevirtual #86                 // Method org/springframework/boot/context/properties/bind/ValueObjectBinder$ValueObject.instantiate:(Ljava/util/List;)Ljava/lang/Object;
     164: goto          168
     167: aconst_null
     168: areturn

  public <T> T create(org.springframework.boot.context.properties.bind.Bindable<T>, org.springframework.boot.context.properties.bind.Binder$Context);
    Code:
       0: aload_1
       1: aload_0
       2: getfield      #7                  // Field constructorProvider:Lorg/springframework/boot/context/properties/bind/BindConstructorProvider;
       5: aload_2
       6: invokestatic  #13                 // Method org/springframework/boot/context/properties/bind/ValueObjectBinder$ValueObject.get:(Lorg/springframework/boot/context/properties/bind/Bindable;Lorg/springframework/boot/context/properties/bind/BindConstructorProvider;Lorg/springframework/boot/context/properties/bind/Binder$Context;)Lorg/springframework/boot/context/properties/bind/ValueObjectBinder$ValueObject;
       9: astore_3
      10: aload_3
      11: ifnonnull     16
      14: aconst_null
      15: areturn
      16: aload_3
      17: invokevirtual #37                 // Method org/springframework/boot/context/properties/bind/ValueObjectBinder$ValueObject.getConstructorParameters:()Ljava/util/List;
      20: astore        4
      22: new           #41                 // class java/util/ArrayList
      25: dup
      26: aload         4
      28: invokeinterface #43,  1           // InterfaceMethod java/util/List.size:()I
      33: invokespecial #49                 // Method java/util/ArrayList."<init>":(I)V
      36: astore        5
      38: aload         4
      40: invokeinterface #52,  1           // InterfaceMethod java/util/List.iterator:()Ljava/util/Iterator;
      45: astore        6
      47: aload         6
      49: invokeinterface #56,  1           // InterfaceMethod java/util/Iterator.hasNext:()Z
      54: ifeq          87
      57: aload         6
      59: invokeinterface #62,  1           // InterfaceMethod java/util/Iterator.next:()Ljava/lang/Object;
      64: checkcast     #66                 // class org/springframework/boot/context/properties/bind/ValueObjectBinder$ConstructorParameter
      67: astore        7
      69: aload         5
      71: aload_0
      72: aload_2
      73: aload         7
      75: invokevirtual #72                 // Method getDefaultValue:(Lorg/springframework/boot/context/properties/bind/Binder$Context;Lorg/springframework/boot/context/properties/bind/ValueObjectBinder$ConstructorParameter;)Ljava/lang/Object;
      78: invokeinterface #76,  2           // InterfaceMethod java/util/List.add:(Ljava/lang/Object;)Z
      83: pop
      84: goto          47
      87: aload_3
      88: aload         5
      90: invokevirtual #86                 // Method org/springframework/boot/context/properties/bind/ValueObjectBinder$ValueObject.instantiate:(Ljava/util/List;)Ljava/lang/Object;
      93: areturn

  private <T> T getDefaultValue(org.springframework.boot.context.properties.bind.Binder$Context, org.springframework.boot.context.properties.bind.ValueObjectBinder$ConstructorParameter);
    Code:
       0: aload_2
       1: invokevirtual #90                 // Method org/springframework/boot/context/properties/bind/ValueObjectBinder$ConstructorParameter.getType:()Lorg/springframework/core/ResolvableType;
       4: astore_3
       5: aload_2
       6: invokevirtual #91                 // Method org/springframework/boot/context/properties/bind/ValueObjectBinder$ConstructorParameter.getAnnotations:()[Ljava/lang/annotation/Annotation;
       9: astore        4
      11: aload         4
      13: astore        5
      15: aload         5
      17: arraylength
      18: istore        6
      20: iconst_0
      21: istore        7
      23: iload         7
      25: iload         6
      27: if_icmpge     94
      30: aload         5
      32: iload         7
      34: aaload
      35: astore        8
      37: aload         8
      39: instanceof    #95                 // class org/springframework/boot/context/properties/bind/DefaultValue
      42: ifeq          88
      45: aload         8
      47: checkcast     #95                 // class org/springframework/boot/context/properties/bind/DefaultValue
      50: astore        9
      52: aload         9
      54: invokeinterface #97,  1           // InterfaceMethod org/springframework/boot/context/properties/bind/DefaultValue.value:()[Ljava/lang/String;
      59: astore        10
      61: aload         10
      63: arraylength
      64: ifne          74
      67: aload_0
      68: aload_1
      69: aload_3
      70: invokevirtual #101                // Method getNewDefaultValueInstanceIfPossible:(Lorg/springframework/boot/context/properties/bind/Binder$Context;Lorg/springframework/core/ResolvableType;)Ljava/lang/Object;
      73: areturn
      74: aload_0
      75: aload_1
      76: invokevirtual #105                // Method org/springframework/boot/context/properties/bind/Binder$Context.getConverter:()Lorg/springframework/boot/context/properties/bind/BindConverter;
      79: aload         10
      81: aload_3
      82: aload         4
      84: invokevirtual #109                // Method convertDefaultValue:(Lorg/springframework/boot/context/properties/bind/BindConverter;[Ljava/lang/String;Lorg/springframework/core/ResolvableType;[Ljava/lang/annotation/Annotation;)Ljava/lang/Object;
      87: areturn
      88: iinc          7, 1
      91: goto          23
      94: aconst_null
      95: areturn

  private <T> T convertDefaultValue(org.springframework.boot.context.properties.bind.BindConverter, java.lang.String[], org.springframework.core.ResolvableType, java.lang.annotation.Annotation[]);
    Code:
       0: aload_1
       1: aload_2
       2: aload_3
       3: aload         4
       5: invokevirtual #113                // Method org/springframework/boot/context/properties/bind/BindConverter.convert:(Ljava/lang/Object;Lorg/springframework/core/ResolvableType;[Ljava/lang/annotation/Annotation;)Ljava/lang/Object;
       8: areturn
       9: astore        5
      11: aload_2
      12: arraylength
      13: iconst_1
      14: if_icmpne     28
      17: aload_1
      18: aload_2
      19: iconst_0
      20: aaload
      21: aload_3
      22: aload         4
      24: invokevirtual #113                // Method org/springframework/boot/context/properties/bind/BindConverter.convert:(Ljava/lang/Object;Lorg/springframework/core/ResolvableType;[Ljava/lang/annotation/Annotation;)Ljava/lang/Object;
      27: areturn
      28: aload         5
      30: athrow
    Exception table:
       from    to  target type
           0     8     9   Class org/springframework/core/convert/ConversionException

  private <T> T getNewDefaultValueInstanceIfPossible(org.springframework.boot.context.properties.bind.Binder$Context, org.springframework.core.ResolvableType);
    Code:
       0: aload_2
       1: invokevirtual #25                 // Method org/springframework/core/ResolvableType.resolve:()Ljava/lang/Class;
       4: astore_3
       5: aload_3
       6: ifnull        17
       9: aload_0
      10: aload_3
      11: invokevirtual #121                // Method isEmptyDefaultValueAllowed:(Ljava/lang/Class;)Z
      14: ifeq          21
      17: iconst_1
      18: goto          22
      21: iconst_0
      22: aload_2
      23: invokedynamic #125,  0            // InvokeDynamic #0:get:(Lorg/springframework/core/ResolvableType;)Ljava/util/function/Supplier;
      28: invokestatic  #128                // Method org/springframework/util/Assert.state:(ZLjava/util/function/Supplier;)V
      31: aload_3
      32: ifnull        91
      35: ldc           #134                // class java/util/Optional
      37: aload_3
      38: if_acmpne     45
      41: invokestatic  #136                // Method java/util/Optional.empty:()Ljava/util/Optional;
      44: areturn
      45: ldc           #140                // class java/util/Collection
      47: aload_3
      48: invokevirtual #142                // Method java/lang/Class.isAssignableFrom:(Ljava/lang/Class;)Z
      51: ifeq          60
      54: aload_3
      55: iconst_0
      56: invokestatic  #147                // Method org/springframework/core/CollectionFactory.createCollection:(Ljava/lang/Class;I)Ljava/util/Collection;
      59: areturn
      60: ldc           #153                // class java/util/Map
      62: aload_3
      63: invokevirtual #142                // Method java/lang/Class.isAssignableFrom:(Ljava/lang/Class;)Z
      66: ifeq          75
      69: aload_3
      70: iconst_0
      71: invokestatic  #155                // Method org/springframework/core/CollectionFactory.createMap:(Ljava/lang/Class;I)Ljava/util/Map;
      74: areturn
      75: aload_3
      76: invokevirtual #159                // Method java/lang/Class.isArray:()Z
      79: ifeq          91
      82: aload_3
      83: invokevirtual #162                // Method java/lang/Class.getComponentType:()Ljava/lang/Class;
      86: iconst_0
      87: invokestatic  #165                // Method java/lang/reflect/Array.newInstance:(Ljava/lang/Class;I)Ljava/lang/Object;
      90: areturn
      91: aload_0
      92: aload_2
      93: invokestatic  #171                // Method org/springframework/boot/context/properties/bind/Bindable.of:(Lorg/springframework/core/ResolvableType;)Lorg/springframework/boot/context/properties/bind/Bindable;
      96: aload_1
      97: invokevirtual #175                // Method create:(Lorg/springframework/boot/context/properties/bind/Bindable;Lorg/springframework/boot/context/properties/bind/Binder$Context;)Ljava/lang/Object;
     100: astore        4
     102: aload         4
     104: ifnull        110
     107: aload         4
     109: areturn
     110: aload_3
     111: ifnull        121
     114: aload_3
     115: invokestatic  #179                // Method org/springframework/beans/BeanUtils.instantiateClass:(Ljava/lang/Class;)Ljava/lang/Object;
     118: goto          122
     121: aconst_null
     122: areturn

  private boolean isEmptyDefaultValueAllowed(java.lang.Class<?>);
    Code:
       0: ldc           #134                // class java/util/Optional
       2: aload_1
       3: if_acmpeq     40
       6: aload_0
       7: aload_1
       8: invokevirtual #185                // Method isAggregate:(Ljava/lang/Class;)Z
      11: ifne          40
      14: aload_1
      15: invokevirtual #188                // Method java/lang/Class.isPrimitive:()Z
      18: ifne          44
      21: aload_1
      22: invokevirtual #191                // Method java/lang/Class.isEnum:()Z
      25: ifne          44
      28: aload_1
      29: invokevirtual #194                // Method java/lang/Class.getName:()Ljava/lang/String;
      32: ldc           #198                // String java.lang
      34: invokevirtual #200                // Method java/lang/String.startsWith:(Ljava/lang/String;)Z
      37: ifne          44
      40: iconst_1
      41: goto          45
      44: iconst_0
      45: ireturn

  private boolean isAggregate(java.lang.Class<?>);
    Code:
       0: aload_1
       1: invokevirtual #159                // Method java/lang/Class.isArray:()Z
       4: ifne          25
       7: ldc           #153                // class java/util/Map
       9: aload_1
      10: invokevirtual #142                // Method java/lang/Class.isAssignableFrom:(Ljava/lang/Class;)Z
      13: ifne          25
      16: ldc           #140                // class java/util/Collection
      18: aload_1
      19: invokevirtual #142                // Method java/lang/Class.isAssignableFrom:(Ljava/lang/Class;)Z
      22: ifeq          29
      25: iconst_1
      26: goto          30
      29: iconst_0
      30: ireturn

  private static java.lang.String lambda$getNewDefaultValueInstanceIfPossible$0(org.springframework.core.ResolvableType);
    Code:
       0: aload_0
       1: invokedynamic #206,  0            // InvokeDynamic #1:makeConcatWithConstants:(Lorg/springframework/core/ResolvableType;)Ljava/lang/String;
       6: areturn
}
