Compiled from "ValueObjectBinder.java"
class org.springframework.boot.context.properties.bind.ValueObjectBinder$ConstructorParameter {
  private final java.lang.String name;

  private final org.springframework.core.ResolvableType type;

  private final java.lang.annotation.Annotation[] annotations;

  org.springframework.boot.context.properties.bind.ValueObjectBinder$ConstructorParameter(java.lang.String, org.springframework.core.ResolvableType, java.lang.annotation.Annotation[]);
    Code:
       0: aload_0
       1: invokespecial #1                  // Method java/lang/Object."<init>":()V
       4: aload_0
       5: aload_1
       6: invokestatic  #7                  // Method org/springframework/boot/context/properties/bind/DataObjectPropertyName.toDashedForm:(Ljava/lang/String;)Ljava/lang/String;
       9: putfield      #13                 // Field name:Ljava/lang/String;
      12: aload_0
      13: aload_2
      14: putfield      #19                 // Field type:Lorg/springframework/core/ResolvableType;
      17: aload_0
      18: aload_3
      19: putfield      #23                 // Field annotations:[Ljava/lang/annotation/Annotation;
      22: return

  java.lang.Object bind(org.springframework.boot.context.properties.bind.DataObjectPropertyBinder);
    Code:
       0: aload_1
       1: aload_0
       2: getfield      #13                 // Field name:Ljava/lang/String;
       5: aload_0
       6: getfield      #19                 // Field type:Lorg/springframework/core/ResolvableType;
       9: invokestatic  #27                 // Method org/springframework/boot/context/properties/bind/Bindable.of:(Lorg/springframework/core/ResolvableType;)Lorg/springframework/boot/context/properties/bind/Bindable;
      12: aload_0
      13: getfield      #23                 // Field annotations:[Ljava/lang/annotation/Annotation;
      16: invokevirtual #33                 // Method org/springframework/boot/context/properties/bind/Bindable.withAnnotations:([Ljava/lang/annotation/Annotation;)Lorg/springframework/boot/context/properties/bind/Bindable;
      19: invokeinterface #37,  3           // InterfaceMethod org/springframework/boot/context/properties/bind/DataObjectPropertyBinder.bindProperty:(Ljava/lang/String;Lorg/springframework/boot/context/properties/bind/Bindable;)Ljava/lang/Object;
      24: areturn

  java.lang.annotation.Annotation[] getAnnotations();
    Code:
       0: aload_0
       1: getfield      #23                 // Field annotations:[Ljava/lang/annotation/Annotation;
       4: areturn

  org.springframework.core.ResolvableType getType();
    Code:
       0: aload_0
       1: getfield      #19                 // Field type:Lorg/springframework/core/ResolvableType;
       4: areturn
}
