Compiled from "ValueObjectBinder.java"
final class org.springframework.boot.context.properties.bind.ValueObjectBinder$KotlinValueObject<T> extends org.springframework.boot.context.properties.bind.ValueObjectBinder$ValueObject<T> {
  private static final java.lang.annotation.Annotation[] ANNOTATION_ARRAY;

  private final java.util.List<org.springframework.boot.context.properties.bind.ValueObjectBinder$ConstructorParameter> constructorParameters;

  private org.springframework.boot.context.properties.bind.ValueObjectBinder$KotlinValueObject(java.lang.reflect.Constructor<T>, kotlin.reflect.KFunction<T>, org.springframework.core.ResolvableType);
    Code:
       0: aload_0
       1: aload_1
       2: invokespecial #1                  // Method org/springframework/boot/context/properties/bind/ValueObjectBinder$ValueObject."<init>":(Ljava/lang/reflect/Constructor;)V
       5: aload_0
       6: aload_0
       7: aload_2
       8: aload_3
       9: invokevirtual #7                  // Method parseConstructorParameters:(Lkotlin/reflect/KFunction;Lorg/springframework/core/ResolvableType;)Ljava/util/List;
      12: putfield      #13                 // Field constructorParameters:Ljava/util/List;
      15: return

  private java.util.List<org.springframework.boot.context.properties.bind.ValueObjectBinder$ConstructorParameter> parseConstructorParameters(kotlin.reflect.KFunction<T>, org.springframework.core.ResolvableType);
    Code:
       0: aload_1
       1: invokeinterface #17,  1           // InterfaceMethod kotlin/reflect/KFunction.getParameters:()Ljava/util/List;
       6: astore_3
       7: new           #23                 // class java/util/ArrayList
      10: dup
      11: aload_3
      12: invokeinterface #25,  1           // InterfaceMethod java/util/List.size:()I
      17: invokespecial #31                 // Method java/util/ArrayList."<init>":(I)V
      20: astore        4
      22: aload_3
      23: invokeinterface #34,  1           // InterfaceMethod java/util/List.iterator:()Ljava/util/Iterator;
      28: astore        5
      30: aload         5
      32: invokeinterface #38,  1           // InterfaceMethod java/util/Iterator.hasNext:()Z
      37: ifeq          120
      40: aload         5
      42: invokeinterface #44,  1           // InterfaceMethod java/util/Iterator.next:()Ljava/lang/Object;
      47: checkcast     #48                 // class kotlin/reflect/KParameter
      50: astore        6
      52: aload_0
      53: aload         6
      55: invokevirtual #50                 // Method getParameterName:(Lkotlin/reflect/KParameter;)Ljava/lang/String;
      58: astore        7
      60: aload         6
      62: invokeinterface #54,  1           // InterfaceMethod kotlin/reflect/KParameter.getType:()Lkotlin/reflect/KType;
      67: invokestatic  #58                 // Method kotlin/reflect/jvm/ReflectJvmMapping.getJavaType:(Lkotlin/reflect/KType;)Ljava/lang/reflect/Type;
      70: aload_2
      71: invokestatic  #64                 // Method org/springframework/core/ResolvableType.forType:(Ljava/lang/reflect/Type;Lorg/springframework/core/ResolvableType;)Lorg/springframework/core/ResolvableType;
      74: astore        8
      76: aload         6
      78: invokeinterface #70,  1           // InterfaceMethod kotlin/reflect/KParameter.getAnnotations:()Ljava/util/List;
      83: getstatic     #73                 // Field ANNOTATION_ARRAY:[Ljava/lang/annotation/Annotation;
      86: invokeinterface #77,  2           // InterfaceMethod java/util/List.toArray:([Ljava/lang/Object;)[Ljava/lang/Object;
      91: checkcast     #81                 // class "[Ljava/lang/annotation/Annotation;"
      94: astore        9
      96: aload         4
      98: new           #82                 // class org/springframework/boot/context/properties/bind/ValueObjectBinder$ConstructorParameter
     101: dup
     102: aload         7
     104: aload         8
     106: aload         9
     108: invokespecial #84                 // Method org/springframework/boot/context/properties/bind/ValueObjectBinder$ConstructorParameter."<init>":(Ljava/lang/String;Lorg/springframework/core/ResolvableType;[Ljava/lang/annotation/Annotation;)V
     111: invokeinterface #87,  2           // InterfaceMethod java/util/List.add:(Ljava/lang/Object;)Z
     116: pop
     117: goto          30
     120: aload         4
     122: invokestatic  #91                 // Method java/util/Collections.unmodifiableList:(Ljava/util/List;)Ljava/util/List;
     125: areturn

  private java.lang.String getParameterName(kotlin.reflect.KParameter);
    Code:
       0: aload_1
       1: aload_1
       2: invokeinterface #70,  1           // InterfaceMethod kotlin/reflect/KParameter.getAnnotations:()Ljava/util/List;
       7: getstatic     #73                 // Field ANNOTATION_ARRAY:[Ljava/lang/annotation/Annotation;
      10: invokeinterface #77,  2           // InterfaceMethod java/util/List.toArray:([Ljava/lang/Object;)[Ljava/lang/Object;
      15: checkcast     #81                 // class "[Ljava/lang/annotation/Annotation;"
      18: invokestatic  #97                 // InterfaceMethod org/springframework/core/annotation/MergedAnnotations.from:(Ljava/lang/Object;[Ljava/lang/annotation/Annotation;)Lorg/springframework/core/annotation/MergedAnnotations;
      21: ldc           #103                // class org/springframework/boot/context/properties/bind/Name
      23: invokeinterface #105,  2          // InterfaceMethod org/springframework/core/annotation/MergedAnnotations.get:(Ljava/lang/Class;)Lorg/springframework/core/annotation/MergedAnnotation;
      28: ldc           #111                // String value
      30: ldc           #113                // class java/lang/String
      32: invokeinterface #115,  3          // InterfaceMethod org/springframework/core/annotation/MergedAnnotation.getValue:(Ljava/lang/String;Ljava/lang/Class;)Ljava/util/Optional;
      37: aload_1
      38: dup
      39: invokestatic  #119                // Method java/util/Objects.requireNonNull:(Ljava/lang/Object;)Ljava/lang/Object;
      42: pop
      43: invokedynamic #125,  0            // InvokeDynamic #0:get:(Lkotlin/reflect/KParameter;)Ljava/util/function/Supplier;
      48: invokevirtual #128                // Method java/util/Optional.orElseGet:(Ljava/util/function/Supplier;)Ljava/lang/Object;
      51: checkcast     #113                // class java/lang/String
      54: areturn

  java.util.List<org.springframework.boot.context.properties.bind.ValueObjectBinder$ConstructorParameter> getConstructorParameters();
    Code:
       0: aload_0
       1: getfield      #13                 // Field constructorParameters:Ljava/util/List;
       4: areturn

  static <T> org.springframework.boot.context.properties.bind.ValueObjectBinder$ValueObject<T> get(java.lang.reflect.Constructor<T>, org.springframework.core.ResolvableType);
    Code:
       0: aload_0
       1: invokestatic  #134                // Method kotlin/reflect/jvm/ReflectJvmMapping.getKotlinFunction:(Ljava/lang/reflect/Constructor;)Lkotlin/reflect/KFunction;
       4: astore_2
       5: aload_2
       6: ifnull        20
       9: new           #8                  // class org/springframework/boot/context/properties/bind/ValueObjectBinder$KotlinValueObject
      12: dup
      13: aload_0
      14: aload_2
      15: aload_1
      16: invokespecial #138                // Method "<init>":(Ljava/lang/reflect/Constructor;Lkotlin/reflect/KFunction;Lorg/springframework/core/ResolvableType;)V
      19: areturn
      20: aload_0
      21: aload_1
      22: invokestatic  #141                // Method org/springframework/boot/context/properties/bind/ValueObjectBinder$DefaultValueObject.get:(Ljava/lang/reflect/Constructor;Lorg/springframework/core/ResolvableType;)Lorg/springframework/boot/context/properties/bind/ValueObjectBinder$ValueObject;
      25: areturn

  static {};
    Code:
       0: iconst_0
       1: anewarray     #146                // class java/lang/annotation/Annotation
       4: putstatic     #73                 // Field ANNOTATION_ARRAY:[Ljava/lang/annotation/Annotation;
       7: return
}
