Compiled from "EagerThreadPoolExecutor.java"
public class org.apache.dubbo.common.threadpool.support.eager.EagerThreadPoolExecutor extends java.util.concurrent.ThreadPoolExecutor {
  public org.apache.dubbo.common.threadpool.support.eager.EagerThreadPoolExecutor(int, int, long, java.util.concurrent.TimeUnit, org.apache.dubbo.common.threadpool.support.eager.TaskQueue<java.lang.Runnable>, java.util.concurrent.ThreadFactory, java.util.concurrent.RejectedExecutionHandler);
    Code:
       0: aload_0
       1: iload_1
       2: iload_2
       3: lload_3
       4: aload         5
       6: aload         6
       8: aload         7
      10: aload         8
      12: invokespecial #1                  // Method java/util/concurrent/ThreadPoolExecutor."<init>":(IIJLjava/util/concurrent/TimeUnit;Ljava/util/concurrent/BlockingQueue;Ljava/util/concurrent/ThreadFactory;Ljava/util/concurrent/RejectedExecutionHandler;)V
      15: return

  public void execute(java.lang.Runnable);
    Code:
       0: aload_1
       1: ifnonnull     12
       4: new           #2                  // class java/lang/NullPointerException
       7: dup
       8: invokespecial #3                  // Method java/lang/NullPointerException."<init>":()V
      11: athrow
      12: aload_0
      13: aload_1
      14: invokespecial #4                  // Method java/util/concurrent/ThreadPoolExecutor.execute:(Ljava/lang/Runnable;)V
      17: goto          67
      20: astore_2
      21: aload_0
      22: invokespecial #6                  // Method java/util/concurrent/ThreadPoolExecutor.getQueue:()Ljava/util/concurrent/BlockingQueue;
      25: checkcast     #7                  // class org/apache/dubbo/common/threadpool/support/eager/TaskQueue
      28: astore_3
      29: aload_3
      30: aload_1
      31: lconst_0
      32: getstatic     #8                  // Field java/util/concurrent/TimeUnit.MILLISECONDS:Ljava/util/concurrent/TimeUnit;
      35: invokevirtual #9                  // Method org/apache/dubbo/common/threadpool/support/eager/TaskQueue.retryOffer:(Ljava/lang/Runnable;JLjava/util/concurrent/TimeUnit;)Z
      38: ifne          52
      41: new           #5                  // class java/util/concurrent/RejectedExecutionException
      44: dup
      45: ldc           #10                 // String Queue capacity is full.
      47: aload_2
      48: invokespecial #11                 // Method java/util/concurrent/RejectedExecutionException."<init>":(Ljava/lang/String;Ljava/lang/Throwable;)V
      51: athrow
      52: goto          67
      55: astore        4
      57: new           #5                  // class java/util/concurrent/RejectedExecutionException
      60: dup
      61: aload         4
      63: invokespecial #13                 // Method java/util/concurrent/RejectedExecutionException."<init>":(Ljava/lang/Throwable;)V
      66: athrow
      67: return
    Exception table:
       from    to  target type
          12    17    20   Class java/util/concurrent/RejectedExecutionException
          29    52    55   Class java/lang/InterruptedException
}
