Compiled from "Level.java"
public final class org.apache.dubbo.common.logger.Level extends java.lang.Enum<org.apache.dubbo.common.logger.Level> {
  public static final org.apache.dubbo.common.logger.Level ALL;

  public static final org.apache.dubbo.common.logger.Level TRACE;

  public static final org.apache.dubbo.common.logger.Level DEBUG;

  public static final org.apache.dubbo.common.logger.Level INFO;

  public static final org.apache.dubbo.common.logger.Level WARN;

  public static final org.apache.dubbo.common.logger.Level ERROR;

  public static final org.apache.dubbo.common.logger.Level OFF;

  private static final org.apache.dubbo.common.logger.Level[] $VALUES;

  public static org.apache.dubbo.common.logger.Level[] values();
    Code:
       0: getstatic     #1                  // Field $VALUES:[Lorg/apache/dubbo/common/logger/Level;
       3: invokevirtual #2                  // Method "[Lorg/apache/dubbo/common/logger/Level;".clone:()Ljava/lang/Object;
       6: checkcast     #3                  // class "[Lorg/apache/dubbo/common/logger/Level;"
       9: areturn

  public static org.apache.dubbo.common.logger.Level valueOf(java.lang.String);
    Code:
       0: ldc           #4                  // class org/apache/dubbo/common/logger/Level
       2: aload_0
       3: invokestatic  #5                  // Method java/lang/Enum.valueOf:(Ljava/lang/Class;Ljava/lang/String;)Ljava/lang/Enum;
       6: checkcast     #4                  // class org/apache/dubbo/common/logger/Level
       9: areturn

  private org.apache.dubbo.common.logger.Level();
    Code:
       0: aload_0
       1: aload_1
       2: iload_2
       3: invokespecial #6                  // Method java/lang/Enum."<init>":(Ljava/lang/String;I)V
       6: return

  static {};
    Code:
       0: new           #4                  // class org/apache/dubbo/common/logger/Level
       3: dup
       4: ldc           #7                  // String ALL
       6: iconst_0
       7: invokespecial #8                  // Method "<init>":(Ljava/lang/String;I)V
      10: putstatic     #9                  // Field ALL:Lorg/apache/dubbo/common/logger/Level;
      13: new           #4                  // class org/apache/dubbo/common/logger/Level
      16: dup
      17: ldc           #10                 // String TRACE
      19: iconst_1
      20: invokespecial #8                  // Method "<init>":(Ljava/lang/String;I)V
      23: putstatic     #11                 // Field TRACE:Lorg/apache/dubbo/common/logger/Level;
      26: new           #4                  // class org/apache/dubbo/common/logger/Level
      29: dup
      30: ldc           #12                 // String DEBUG
      32: iconst_2
      33: invokespecial #8                  // Method "<init>":(Ljava/lang/String;I)V
      36: putstatic     #13                 // Field DEBUG:Lorg/apache/dubbo/common/logger/Level;
      39: new           #4                  // class org/apache/dubbo/common/logger/Level
      42: dup
      43: ldc           #14                 // String INFO
      45: iconst_3
      46: invokespecial #8                  // Method "<init>":(Ljava/lang/String;I)V
      49: putstatic     #15                 // Field INFO:Lorg/apache/dubbo/common/logger/Level;
      52: new           #4                  // class org/apache/dubbo/common/logger/Level
      55: dup
      56: ldc           #16                 // String WARN
      58: iconst_4
      59: invokespecial #8                  // Method "<init>":(Ljava/lang/String;I)V
      62: putstatic     #17                 // Field WARN:Lorg/apache/dubbo/common/logger/Level;
      65: new           #4                  // class org/apache/dubbo/common/logger/Level
      68: dup
      69: ldc           #18                 // String ERROR
      71: iconst_5
      72: invokespecial #8                  // Method "<init>":(Ljava/lang/String;I)V
      75: putstatic     #19                 // Field ERROR:Lorg/apache/dubbo/common/logger/Level;
      78: new           #4                  // class org/apache/dubbo/common/logger/Level
      81: dup
      82: ldc           #20                 // String OFF
      84: bipush        6
      86: invokespecial #8                  // Method "<init>":(Ljava/lang/String;I)V
      89: putstatic     #21                 // Field OFF:Lorg/apache/dubbo/common/logger/Level;
      92: bipush        7
      94: anewarray     #4                  // class org/apache/dubbo/common/logger/Level
      97: dup
      98: iconst_0
      99: getstatic     #9                  // Field ALL:Lorg/apache/dubbo/common/logger/Level;
     102: aastore
     103: dup
     104: iconst_1
     105: getstatic     #11                 // Field TRACE:Lorg/apache/dubbo/common/logger/Level;
     108: aastore
     109: dup
     110: iconst_2
     111: getstatic     #13                 // Field DEBUG:Lorg/apache/dubbo/common/logger/Level;
     114: aastore
     115: dup
     116: iconst_3
     117: getstatic     #15                 // Field INFO:Lorg/apache/dubbo/common/logger/Level;
     120: aastore
     121: dup
     122: iconst_4
     123: getstatic     #17                 // Field WARN:Lorg/apache/dubbo/common/logger/Level;
     126: aastore
     127: dup
     128: iconst_5
     129: getstatic     #19                 // Field ERROR:Lorg/apache/dubbo/common/logger/Level;
     132: aastore
     133: dup
     134: bipush        6
     136: getstatic     #21                 // Field OFF:Lorg/apache/dubbo/common/logger/Level;
     139: aastore
     140: putstatic     #1                  // Field $VALUES:[Lorg/apache/dubbo/common/logger/Level;
     143: return
}
