Compiled from "LoggerFactory.java"
public class org.apache.dubbo.common.logger.LoggerFactory {
  private static final java.util.concurrent.ConcurrentMap<java.lang.String, org.apache.dubbo.common.logger.support.FailsafeLogger> LOGGERS;

  private static final java.util.concurrent.ConcurrentMap<java.lang.String, org.apache.dubbo.common.logger.support.FailsafeErrorTypeAwareLogger> ERROR_TYPE_AWARE_LOGGERS;

  private static volatile org.apache.dubbo.common.logger.LoggerAdapter loggerAdapter;

  private org.apache.dubbo.common.logger.LoggerFactory();
    Code:
       0: aload_0
       1: invokespecial #1                  // Method java/lang/Object."<init>":()V
       4: return

  public static void setLoggerAdapter(org.apache.dubbo.rpc.model.FrameworkModel, java.lang.String);
    Code:
       0: aload_1
       1: ifnull        27
       4: aload_1
       5: invokevirtual #2                  // Method java/lang/String.length:()I
       8: ifle          27
      11: aload_0
      12: ldc           #3                  // class org/apache/dubbo/common/logger/LoggerAdapter
      14: invokevirtual #4                  // Method org/apache/dubbo/rpc/model/FrameworkModel.getExtensionLoader:(Ljava/lang/Class;)Lorg/apache/dubbo/common/extension/ExtensionLoader;
      17: aload_1
      18: invokevirtual #5                  // Method org/apache/dubbo/common/extension/ExtensionLoader.getExtension:(Ljava/lang/String;)Ljava/lang/Object;
      21: checkcast     #3                  // class org/apache/dubbo/common/logger/LoggerAdapter
      24: invokestatic  #6                  // Method setLoggerAdapter:(Lorg/apache/dubbo/common/logger/LoggerAdapter;)V
      27: return

  public static void setLoggerAdapter(org.apache.dubbo.common.logger.LoggerAdapter);
    Code:
       0: aload_0
       1: ifnull        93
       4: aload_0
       5: getstatic     #7                  // Field loggerAdapter:Lorg/apache/dubbo/common/logger/LoggerAdapter;
       8: if_acmpne     12
      11: return
      12: aload_0
      13: ldc           #8                  // class org/apache/dubbo/common/logger/LoggerFactory
      15: invokevirtual #9                  // Method java/lang/Class.getName:()Ljava/lang/String;
      18: invokeinterface #10,  2           // InterfaceMethod org/apache/dubbo/common/logger/LoggerAdapter.getLogger:(Ljava/lang/String;)Lorg/apache/dubbo/common/logger/Logger;
      23: pop
      24: aload_0
      25: putstatic     #7                  // Field loggerAdapter:Lorg/apache/dubbo/common/logger/LoggerAdapter;
      28: getstatic     #11                 // Field LOGGERS:Ljava/util/concurrent/ConcurrentMap;
      31: invokeinterface #12,  1           // InterfaceMethod java/util/concurrent/ConcurrentMap.entrySet:()Ljava/util/Set;
      36: invokeinterface #13,  1           // InterfaceMethod java/util/Set.iterator:()Ljava/util/Iterator;
      41: astore_1
      42: aload_1
      43: invokeinterface #14,  1           // InterfaceMethod java/util/Iterator.hasNext:()Z
      48: ifeq          93
      51: aload_1
      52: invokeinterface #15,  1           // InterfaceMethod java/util/Iterator.next:()Ljava/lang/Object;
      57: checkcast     #16                 // class java/util/Map$Entry
      60: astore_2
      61: aload_2
      62: invokeinterface #17,  1           // InterfaceMethod java/util/Map$Entry.getValue:()Ljava/lang/Object;
      67: checkcast     #18                 // class org/apache/dubbo/common/logger/support/FailsafeLogger
      70: getstatic     #7                  // Field loggerAdapter:Lorg/apache/dubbo/common/logger/LoggerAdapter;
      73: aload_2
      74: invokeinterface #19,  1           // InterfaceMethod java/util/Map$Entry.getKey:()Ljava/lang/Object;
      79: checkcast     #20                 // class java/lang/String
      82: invokeinterface #10,  2           // InterfaceMethod org/apache/dubbo/common/logger/LoggerAdapter.getLogger:(Ljava/lang/String;)Lorg/apache/dubbo/common/logger/Logger;
      87: invokevirtual #21                 // Method org/apache/dubbo/common/logger/support/FailsafeLogger.setLogger:(Lorg/apache/dubbo/common/logger/Logger;)V
      90: goto          42
      93: return

  public static org.apache.dubbo.common.logger.Logger getLogger(java.lang.Class<?>);
    Code:
       0: getstatic     #11                 // Field LOGGERS:Ljava/util/concurrent/ConcurrentMap;
       3: aload_0
       4: invokevirtual #9                  // Method java/lang/Class.getName:()Ljava/lang/String;
       7: invokedynamic #22,  0             // InvokeDynamic #0:apply:()Ljava/util/function/Function;
      12: invokestatic  #23                 // Method org/apache/dubbo/common/utils/ConcurrentHashMapUtils.computeIfAbsent:(Ljava/util/concurrent/ConcurrentMap;Ljava/lang/Object;Ljava/util/function/Function;)Ljava/lang/Object;
      15: checkcast     #24                 // class org/apache/dubbo/common/logger/Logger
      18: areturn

  public static org.apache.dubbo.common.logger.Logger getLogger(java.lang.String);
    Code:
       0: getstatic     #11                 // Field LOGGERS:Ljava/util/concurrent/ConcurrentMap;
       3: aload_0
       4: invokedynamic #25,  0             // InvokeDynamic #1:apply:()Ljava/util/function/Function;
       9: invokestatic  #23                 // Method org/apache/dubbo/common/utils/ConcurrentHashMapUtils.computeIfAbsent:(Ljava/util/concurrent/ConcurrentMap;Ljava/lang/Object;Ljava/util/function/Function;)Ljava/lang/Object;
      12: checkcast     #24                 // class org/apache/dubbo/common/logger/Logger
      15: areturn

  public static org.apache.dubbo.common.logger.ErrorTypeAwareLogger getErrorTypeAwareLogger(java.lang.Class<?>);
    Code:
       0: getstatic     #26                 // Field ERROR_TYPE_AWARE_LOGGERS:Ljava/util/concurrent/ConcurrentMap;
       3: aload_0
       4: invokevirtual #9                  // Method java/lang/Class.getName:()Ljava/lang/String;
       7: invokedynamic #27,  0             // InvokeDynamic #2:apply:()Ljava/util/function/Function;
      12: invokestatic  #23                 // Method org/apache/dubbo/common/utils/ConcurrentHashMapUtils.computeIfAbsent:(Ljava/util/concurrent/ConcurrentMap;Ljava/lang/Object;Ljava/util/function/Function;)Ljava/lang/Object;
      15: checkcast     #28                 // class org/apache/dubbo/common/logger/ErrorTypeAwareLogger
      18: areturn

  public static org.apache.dubbo.common.logger.ErrorTypeAwareLogger getErrorTypeAwareLogger(java.lang.String);
    Code:
       0: getstatic     #26                 // Field ERROR_TYPE_AWARE_LOGGERS:Ljava/util/concurrent/ConcurrentMap;
       3: aload_0
       4: invokedynamic #29,  0             // InvokeDynamic #3:apply:()Ljava/util/function/Function;
       9: invokestatic  #23                 // Method org/apache/dubbo/common/utils/ConcurrentHashMapUtils.computeIfAbsent:(Ljava/util/concurrent/ConcurrentMap;Ljava/lang/Object;Ljava/util/function/Function;)Ljava/lang/Object;
      12: checkcast     #28                 // class org/apache/dubbo/common/logger/ErrorTypeAwareLogger
      15: areturn

  public static org.apache.dubbo.common.logger.Level getLevel();
    Code:
       0: getstatic     #7                  // Field loggerAdapter:Lorg/apache/dubbo/common/logger/LoggerAdapter;
       3: invokeinterface #30,  1           // InterfaceMethod org/apache/dubbo/common/logger/LoggerAdapter.getLevel:()Lorg/apache/dubbo/common/logger/Level;
       8: areturn

  public static void setLevel(org.apache.dubbo.common.logger.Level);
    Code:
       0: getstatic     #7                  // Field loggerAdapter:Lorg/apache/dubbo/common/logger/LoggerAdapter;
       3: aload_0
       4: invokeinterface #31,  2           // InterfaceMethod org/apache/dubbo/common/logger/LoggerAdapter.setLevel:(Lorg/apache/dubbo/common/logger/Level;)V
       9: return

  public static java.io.File getFile();
    Code:
       0: getstatic     #7                  // Field loggerAdapter:Lorg/apache/dubbo/common/logger/LoggerAdapter;
       3: invokeinterface #32,  1           // InterfaceMethod org/apache/dubbo/common/logger/LoggerAdapter.getFile:()Ljava/io/File;
       8: areturn

  public static java.util.List<java.lang.String> getAvailableAdapter();
    Code:
       0: new           #33                 // class java/util/HashMap
       3: dup
       4: invokespecial #34                 // Method java/util/HashMap."<init>":()V
       7: astore_0
       8: aload_0
       9: ldc           #35                 // class org/apache/dubbo/common/logger/log4j/Log4jLoggerAdapter
      11: ldc           #36                 // String log4j
      13: invokeinterface #37,  3           // InterfaceMethod java/util/Map.put:(Ljava/lang/Object;Ljava/lang/Object;)Ljava/lang/Object;
      18: pop
      19: aload_0
      20: ldc           #38                 // class org/apache/dubbo/common/logger/slf4j/Slf4jLoggerAdapter
      22: ldc           #39                 // String slf4j
      24: invokeinterface #37,  3           // InterfaceMethod java/util/Map.put:(Ljava/lang/Object;Ljava/lang/Object;)Ljava/lang/Object;
      29: pop
      30: aload_0
      31: ldc           #40                 // class org/apache/dubbo/common/logger/log4j2/Log4j2LoggerAdapter
      33: ldc           #41                 // String log4j2
      35: invokeinterface #37,  3           // InterfaceMethod java/util/Map.put:(Ljava/lang/Object;Ljava/lang/Object;)Ljava/lang/Object;
      40: pop
      41: aload_0
      42: ldc           #42                 // class org/apache/dubbo/common/logger/jcl/JclLoggerAdapter
      44: ldc           #43                 // String jcl
      46: invokeinterface #37,  3           // InterfaceMethod java/util/Map.put:(Ljava/lang/Object;Ljava/lang/Object;)Ljava/lang/Object;
      51: pop
      52: aload_0
      53: ldc           #44                 // class org/apache/dubbo/common/logger/jdk/JdkLoggerAdapter
      55: ldc           #45                 // String jdk
      57: invokeinterface #37,  3           // InterfaceMethod java/util/Map.put:(Ljava/lang/Object;Ljava/lang/Object;)Ljava/lang/Object;
      62: pop
      63: new           #46                 // class java/util/LinkedList
      66: dup
      67: invokespecial #47                 // Method java/util/LinkedList."<init>":()V
      70: astore_1
      71: aload_0
      72: invokeinterface #48,  1           // InterfaceMethod java/util/Map.entrySet:()Ljava/util/Set;
      77: invokeinterface #13,  1           // InterfaceMethod java/util/Set.iterator:()Ljava/util/Iterator;
      82: astore_2
      83: aload_2
      84: invokeinterface #14,  1           // InterfaceMethod java/util/Iterator.hasNext:()Z
      89: ifeq          161
      92: aload_2
      93: invokeinterface #15,  1           // InterfaceMethod java/util/Iterator.next:()Ljava/lang/Object;
      98: checkcast     #16                 // class java/util/Map$Entry
     101: astore_3
     102: aload_3
     103: invokeinterface #19,  1           // InterfaceMethod java/util/Map$Entry.getKey:()Ljava/lang/Object;
     108: checkcast     #49                 // class java/lang/Class
     111: iconst_0
     112: anewarray     #49                 // class java/lang/Class
     115: invokevirtual #50                 // Method java/lang/Class.getDeclaredConstructor:([Ljava/lang/Class;)Ljava/lang/reflect/Constructor;
     118: iconst_0
     119: anewarray     #51                 // class java/lang/Object
     122: invokevirtual #52                 // Method java/lang/reflect/Constructor.newInstance:([Ljava/lang/Object;)Ljava/lang/Object;
     125: checkcast     #3                  // class org/apache/dubbo/common/logger/LoggerAdapter
     128: astore        4
     130: aload         4
     132: ldc           #8                  // class org/apache/dubbo/common/logger/LoggerFactory
     134: invokeinterface #53,  2           // InterfaceMethod org/apache/dubbo/common/logger/LoggerAdapter.getLogger:(Ljava/lang/Class;)Lorg/apache/dubbo/common/logger/Logger;
     139: pop
     140: aload_1
     141: aload_3
     142: invokeinterface #17,  1           // InterfaceMethod java/util/Map$Entry.getValue:()Ljava/lang/Object;
     147: invokeinterface #54,  2           // InterfaceMethod java/util/List.add:(Ljava/lang/Object;)Z
     152: pop
     153: goto          158
     156: astore        4
     158: goto          83
     161: aload_1
     162: areturn
    Exception table:
       from    to  target type
         102   153   156   Class java/lang/Exception

  public static java.lang.String getCurrentAdapter();
    Code:
       0: new           #33                 // class java/util/HashMap
       3: dup
       4: invokespecial #34                 // Method java/util/HashMap."<init>":()V
       7: astore_0
       8: aload_0
       9: ldc           #35                 // class org/apache/dubbo/common/logger/log4j/Log4jLoggerAdapter
      11: ldc           #36                 // String log4j
      13: invokeinterface #37,  3           // InterfaceMethod java/util/Map.put:(Ljava/lang/Object;Ljava/lang/Object;)Ljava/lang/Object;
      18: pop
      19: aload_0
      20: ldc           #38                 // class org/apache/dubbo/common/logger/slf4j/Slf4jLoggerAdapter
      22: ldc           #39                 // String slf4j
      24: invokeinterface #37,  3           // InterfaceMethod java/util/Map.put:(Ljava/lang/Object;Ljava/lang/Object;)Ljava/lang/Object;
      29: pop
      30: aload_0
      31: ldc           #40                 // class org/apache/dubbo/common/logger/log4j2/Log4j2LoggerAdapter
      33: ldc           #41                 // String log4j2
      35: invokeinterface #37,  3           // InterfaceMethod java/util/Map.put:(Ljava/lang/Object;Ljava/lang/Object;)Ljava/lang/Object;
      40: pop
      41: aload_0
      42: ldc           #42                 // class org/apache/dubbo/common/logger/jcl/JclLoggerAdapter
      44: ldc           #43                 // String jcl
      46: invokeinterface #37,  3           // InterfaceMethod java/util/Map.put:(Ljava/lang/Object;Ljava/lang/Object;)Ljava/lang/Object;
      51: pop
      52: aload_0
      53: ldc           #44                 // class org/apache/dubbo/common/logger/jdk/JdkLoggerAdapter
      55: ldc           #45                 // String jdk
      57: invokeinterface #37,  3           // InterfaceMethod java/util/Map.put:(Ljava/lang/Object;Ljava/lang/Object;)Ljava/lang/Object;
      62: pop
      63: aload_0
      64: getstatic     #7                  // Field loggerAdapter:Lorg/apache/dubbo/common/logger/LoggerAdapter;
      67: invokevirtual #56                 // Method java/lang/Object.getClass:()Ljava/lang/Class;
      70: invokeinterface #57,  2           // InterfaceMethod java/util/Map.get:(Ljava/lang/Object;)Ljava/lang/Object;
      75: checkcast     #20                 // class java/lang/String
      78: astore_1
      79: aload_1
      80: ifnonnull     93
      83: getstatic     #7                  // Field loggerAdapter:Lorg/apache/dubbo/common/logger/LoggerAdapter;
      86: invokevirtual #56                 // Method java/lang/Object.getClass:()Ljava/lang/Class;
      89: invokevirtual #58                 // Method java/lang/Class.getSimpleName:()Ljava/lang/String;
      92: astore_1
      93: aload_1
      94: areturn

  private static org.apache.dubbo.common.logger.support.FailsafeErrorTypeAwareLogger lambda$getErrorTypeAwareLogger$3(java.lang.String);
    Code:
       0: new           #59                 // class org/apache/dubbo/common/logger/support/FailsafeErrorTypeAwareLogger
       3: dup
       4: getstatic     #7                  // Field loggerAdapter:Lorg/apache/dubbo/common/logger/LoggerAdapter;
       7: aload_0
       8: invokeinterface #10,  2           // InterfaceMethod org/apache/dubbo/common/logger/LoggerAdapter.getLogger:(Ljava/lang/String;)Lorg/apache/dubbo/common/logger/Logger;
      13: invokespecial #60                 // Method org/apache/dubbo/common/logger/support/FailsafeErrorTypeAwareLogger."<init>":(Lorg/apache/dubbo/common/logger/Logger;)V
      16: areturn

  private static org.apache.dubbo.common.logger.support.FailsafeErrorTypeAwareLogger lambda$getErrorTypeAwareLogger$2(java.lang.String);
    Code:
       0: new           #59                 // class org/apache/dubbo/common/logger/support/FailsafeErrorTypeAwareLogger
       3: dup
       4: getstatic     #7                  // Field loggerAdapter:Lorg/apache/dubbo/common/logger/LoggerAdapter;
       7: aload_0
       8: invokeinterface #10,  2           // InterfaceMethod org/apache/dubbo/common/logger/LoggerAdapter.getLogger:(Ljava/lang/String;)Lorg/apache/dubbo/common/logger/Logger;
      13: invokespecial #60                 // Method org/apache/dubbo/common/logger/support/FailsafeErrorTypeAwareLogger."<init>":(Lorg/apache/dubbo/common/logger/Logger;)V
      16: areturn

  private static org.apache.dubbo.common.logger.support.FailsafeLogger lambda$getLogger$1(java.lang.String);
    Code:
       0: new           #18                 // class org/apache/dubbo/common/logger/support/FailsafeLogger
       3: dup
       4: getstatic     #7                  // Field loggerAdapter:Lorg/apache/dubbo/common/logger/LoggerAdapter;
       7: aload_0
       8: invokeinterface #10,  2           // InterfaceMethod org/apache/dubbo/common/logger/LoggerAdapter.getLogger:(Ljava/lang/String;)Lorg/apache/dubbo/common/logger/Logger;
      13: invokespecial #61                 // Method org/apache/dubbo/common/logger/support/FailsafeLogger."<init>":(Lorg/apache/dubbo/common/logger/Logger;)V
      16: areturn

  private static org.apache.dubbo.common.logger.support.FailsafeLogger lambda$getLogger$0(java.lang.String);
    Code:
       0: new           #18                 // class org/apache/dubbo/common/logger/support/FailsafeLogger
       3: dup
       4: getstatic     #7                  // Field loggerAdapter:Lorg/apache/dubbo/common/logger/LoggerAdapter;
       7: aload_0
       8: invokeinterface #10,  2           // InterfaceMethod org/apache/dubbo/common/logger/LoggerAdapter.getLogger:(Ljava/lang/String;)Lorg/apache/dubbo/common/logger/Logger;
      13: invokespecial #61                 // Method org/apache/dubbo/common/logger/support/FailsafeLogger."<init>":(Lorg/apache/dubbo/common/logger/Logger;)V
      16: areturn

  static {};
    Code:
       0: new           #62                 // class java/util/concurrent/ConcurrentHashMap
       3: dup
       4: invokespecial #63                 // Method java/util/concurrent/ConcurrentHashMap."<init>":()V
       7: putstatic     #11                 // Field LOGGERS:Ljava/util/concurrent/ConcurrentMap;
      10: new           #62                 // class java/util/concurrent/ConcurrentHashMap
      13: dup
      14: invokespecial #63                 // Method java/util/concurrent/ConcurrentHashMap."<init>":()V
      17: putstatic     #26                 // Field ERROR_TYPE_AWARE_LOGGERS:Ljava/util/concurrent/ConcurrentMap;
      20: ldc           #64                 // String dubbo.application.logger
      22: ldc           #65                 // String
      24: invokestatic  #66                 // Method java/lang/System.getProperty:(Ljava/lang/String;Ljava/lang/String;)Ljava/lang/String;
      27: astore_0
      28: aload_0
      29: astore_1
      30: iconst_m1
      31: istore_2
      32: aload_1
      33: invokevirtual #67                 // Method java/lang/String.hashCode:()I
      36: lookupswitch  { // 5
           -1097386376: 144
                105043: 102
                105073: 130
             103147770: 116
             109522083: 88
               default: 155
          }
      88: aload_1
      89: ldc           #39                 // String slf4j
      91: invokevirtual #68                 // Method java/lang/String.equals:(Ljava/lang/Object;)Z
      94: ifeq          155
      97: iconst_0
      98: istore_2
      99: goto          155
     102: aload_1
     103: ldc           #43                 // String jcl
     105: invokevirtual #68                 // Method java/lang/String.equals:(Ljava/lang/Object;)Z
     108: ifeq          155
     111: iconst_1
     112: istore_2
     113: goto          155
     116: aload_1
     117: ldc           #36                 // String log4j
     119: invokevirtual #68                 // Method java/lang/String.equals:(Ljava/lang/Object;)Z
     122: ifeq          155
     125: iconst_2
     126: istore_2
     127: goto          155
     130: aload_1
     131: ldc           #45                 // String jdk
     133: invokevirtual #68                 // Method java/lang/String.equals:(Ljava/lang/Object;)Z
     136: ifeq          155
     139: iconst_3
     140: istore_2
     141: goto          155
     144: aload_1
     145: ldc           #41                 // String log4j2
     147: invokevirtual #68                 // Method java/lang/String.equals:(Ljava/lang/Object;)Z
     150: ifeq          155
     153: iconst_4
     154: istore_2
     155: iload_2
     156: tableswitch   { // 0 to 4
                     0: 192
                     1: 205
                     2: 218
                     3: 231
                     4: 244
               default: 257
          }
     192: new           #38                 // class org/apache/dubbo/common/logger/slf4j/Slf4jLoggerAdapter
     195: dup
     196: invokespecial #69                 // Method org/apache/dubbo/common/logger/slf4j/Slf4jLoggerAdapter."<init>":()V
     199: invokestatic  #6                  // Method setLoggerAdapter:(Lorg/apache/dubbo/common/logger/LoggerAdapter;)V
     202: goto          530
     205: new           #42                 // class org/apache/dubbo/common/logger/jcl/JclLoggerAdapter
     208: dup
     209: invokespecial #70                 // Method org/apache/dubbo/common/logger/jcl/JclLoggerAdapter."<init>":()V
     212: invokestatic  #6                  // Method setLoggerAdapter:(Lorg/apache/dubbo/common/logger/LoggerAdapter;)V
     215: goto          530
     218: new           #35                 // class org/apache/dubbo/common/logger/log4j/Log4jLoggerAdapter
     221: dup
     222: invokespecial #71                 // Method org/apache/dubbo/common/logger/log4j/Log4jLoggerAdapter."<init>":()V
     225: invokestatic  #6                  // Method setLoggerAdapter:(Lorg/apache/dubbo/common/logger/LoggerAdapter;)V
     228: goto          530
     231: new           #44                 // class org/apache/dubbo/common/logger/jdk/JdkLoggerAdapter
     234: dup
     235: invokespecial #72                 // Method org/apache/dubbo/common/logger/jdk/JdkLoggerAdapter."<init>":()V
     238: invokestatic  #6                  // Method setLoggerAdapter:(Lorg/apache/dubbo/common/logger/LoggerAdapter;)V
     241: goto          530
     244: new           #40                 // class org/apache/dubbo/common/logger/log4j2/Log4j2LoggerAdapter
     247: dup
     248: invokespecial #73                 // Method org/apache/dubbo/common/logger/log4j2/Log4j2LoggerAdapter."<init>":()V
     251: invokestatic  #6                  // Method setLoggerAdapter:(Lorg/apache/dubbo/common/logger/LoggerAdapter;)V
     254: goto          530
     257: iconst_5
     258: anewarray     #49                 // class java/lang/Class
     261: dup
     262: iconst_0
     263: ldc           #35                 // class org/apache/dubbo/common/logger/log4j/Log4jLoggerAdapter
     265: aastore
     266: dup
     267: iconst_1
     268: ldc           #38                 // class org/apache/dubbo/common/logger/slf4j/Slf4jLoggerAdapter
     270: aastore
     271: dup
     272: iconst_2
     273: ldc           #40                 // class org/apache/dubbo/common/logger/log4j2/Log4j2LoggerAdapter
     275: aastore
     276: dup
     277: iconst_3
     278: ldc           #42                 // class org/apache/dubbo/common/logger/jcl/JclLoggerAdapter
     280: aastore
     281: dup
     282: iconst_4
     283: ldc           #44                 // class org/apache/dubbo/common/logger/jdk/JdkLoggerAdapter
     285: aastore
     286: invokestatic  #74                 // Method java/util/Arrays.asList:([Ljava/lang/Object;)Ljava/util/List;
     289: astore_3
     290: iconst_0
     291: istore        4
     293: aload_3
     294: invokeinterface #75,  1           // InterfaceMethod java/util/List.iterator:()Ljava/util/Iterator;
     299: astore        5
     301: aload         5
     303: invokeinterface #14,  1           // InterfaceMethod java/util/Iterator.hasNext:()Z
     308: ifeq          383
     311: aload         5
     313: invokeinterface #15,  1           // InterfaceMethod java/util/Iterator.next:()Ljava/lang/Object;
     318: checkcast     #49                 // class java/lang/Class
     321: astore        6
     323: aload         6
     325: iconst_0
     326: anewarray     #49                 // class java/lang/Class
     329: invokevirtual #50                 // Method java/lang/Class.getDeclaredConstructor:([Ljava/lang/Class;)Ljava/lang/reflect/Constructor;
     332: iconst_0
     333: anewarray     #51                 // class java/lang/Object
     336: invokevirtual #52                 // Method java/lang/reflect/Constructor.newInstance:([Ljava/lang/Object;)Ljava/lang/Object;
     339: checkcast     #3                  // class org/apache/dubbo/common/logger/LoggerAdapter
     342: astore        7
     344: aload         7
     346: ldc           #8                  // class org/apache/dubbo/common/logger/LoggerFactory
     348: invokeinterface #53,  2           // InterfaceMethod org/apache/dubbo/common/logger/LoggerAdapter.getLogger:(Ljava/lang/Class;)Lorg/apache/dubbo/common/logger/Logger;
     353: pop
     354: aload         7
     356: invokeinterface #76,  1           // InterfaceMethod org/apache/dubbo/common/logger/LoggerAdapter.isConfigured:()Z
     361: ifeq          375
     364: aload         7
     366: invokestatic  #6                  // Method setLoggerAdapter:(Lorg/apache/dubbo/common/logger/LoggerAdapter;)V
     369: iconst_1
     370: istore        4
     372: goto          383
     375: goto          380
     378: astore        7
     380: goto          301
     383: iload         4
     385: ifeq          391
     388: goto          530
     391: getstatic     #78                 // Field java/lang/System.err:Ljava/io/PrintStream;
     394: ldc           #79                 // String Dubbo: Unable to find a proper configured logger to log out.
     396: invokevirtual #80                 // Method java/io/PrintStream.println:(Ljava/lang/String;)V
     399: aload_3
     400: invokeinterface #75,  1           // InterfaceMethod java/util/List.iterator:()Ljava/util/Iterator;
     405: astore        5
     407: aload         5
     409: invokeinterface #14,  1           // InterfaceMethod java/util/Iterator.hasNext:()Z
     414: ifeq          476
     417: aload         5
     419: invokeinterface #15,  1           // InterfaceMethod java/util/Iterator.next:()Ljava/lang/Object;
     424: checkcast     #49                 // class java/lang/Class
     427: astore        6
     429: aload         6
     431: iconst_0
     432: anewarray     #49                 // class java/lang/Class
     435: invokevirtual #50                 // Method java/lang/Class.getDeclaredConstructor:([Ljava/lang/Class;)Ljava/lang/reflect/Constructor;
     438: iconst_0
     439: anewarray     #51                 // class java/lang/Object
     442: invokevirtual #52                 // Method java/lang/reflect/Constructor.newInstance:([Ljava/lang/Object;)Ljava/lang/Object;
     445: checkcast     #3                  // class org/apache/dubbo/common/logger/LoggerAdapter
     448: astore        7
     450: aload         7
     452: ldc           #8                  // class org/apache/dubbo/common/logger/LoggerFactory
     454: invokeinterface #53,  2           // InterfaceMethod org/apache/dubbo/common/logger/LoggerAdapter.getLogger:(Ljava/lang/Class;)Lorg/apache/dubbo/common/logger/Logger;
     459: pop
     460: aload         7
     462: invokestatic  #6                  // Method setLoggerAdapter:(Lorg/apache/dubbo/common/logger/LoggerAdapter;)V
     465: iconst_1
     466: istore        4
     468: goto          476
     471: astore        7
     473: goto          407
     476: iload         4
     478: ifeq          522
     481: getstatic     #78                 // Field java/lang/System.err:Ljava/io/PrintStream;
     484: new           #82                 // class java/lang/StringBuilder
     487: dup
     488: invokespecial #83                 // Method java/lang/StringBuilder."<init>":()V
     491: ldc           #84                 // String Dubbo: Using default logger:
     493: invokevirtual #85                 // Method java/lang/StringBuilder.append:(Ljava/lang/String;)Ljava/lang/StringBuilder;
     496: getstatic     #7                  // Field loggerAdapter:Lorg/apache/dubbo/common/logger/LoggerAdapter;
     499: invokevirtual #56                 // Method java/lang/Object.getClass:()Ljava/lang/Class;
     502: invokevirtual #9                  // Method java/lang/Class.getName:()Ljava/lang/String;
     505: invokevirtual #85                 // Method java/lang/StringBuilder.append:(Ljava/lang/String;)Ljava/lang/StringBuilder;
     508: ldc           #86                 // String . If you cannot see any log, please configure -Ddubbo.application.logger property to your preferred logging framework.
     510: invokevirtual #85                 // Method java/lang/StringBuilder.append:(Ljava/lang/String;)Ljava/lang/StringBuilder;
     513: invokevirtual #87                 // Method java/lang/StringBuilder.toString:()Ljava/lang/String;
     516: invokevirtual #80                 // Method java/io/PrintStream.println:(Ljava/lang/String;)V
     519: goto          530
     522: getstatic     #78                 // Field java/lang/System.err:Ljava/io/PrintStream;
     525: ldc           #88                 // String Dubbo: Unable to find any available logger adapter to log out. Dubbo logs will be ignored. Please configure -Ddubbo.application.logger property and add corresponding logging library to classpath.
     527: invokevirtual #80                 // Method java/io/PrintStream.println:(Ljava/lang/String;)V
     530: return
    Exception table:
       from    to  target type
         323   372   378   Class java/lang/Exception
         323   372   378   Class java/lang/LinkageError
         429   468   471   Class java/lang/Throwable
}
