Compiled from "CommonScopeModelInitializer.java"
public class org.apache.dubbo.common.CommonScopeModelInitializer implements org.apache.dubbo.rpc.model.ScopeModelInitializer {
  public org.apache.dubbo.common.CommonScopeModelInitializer();
    Code:
       0: aload_0
       1: invokespecial #1                  // Method java/lang/Object."<init>":()V
       4: return

  public void initializeFrameworkModel(org.apache.dubbo.rpc.model.FrameworkModel);
    Code:
       0: aload_1
       1: invokevirtual #2                  // Method org/apache/dubbo/rpc/model/FrameworkModel.getBeanFactory:()Lorg/apache/dubbo/common/beans/factory/ScopeBeanFactory;
       4: astore_2
       5: aload_2
       6: ldc           #3                  // class org/apache/dubbo/common/threadpool/manager/FrameworkExecutorRepository
       8: invokevirtual #4                  // Method org/apache/dubbo/common/beans/factory/ScopeBeanFactory.registerBean:(Ljava/lang/Class;)Ljava/lang/Object;
      11: pop
      12: aload_2
      13: ldc           #5                  // class org/apache/dubbo/common/convert/ConverterUtil
      15: invokevirtual #4                  // Method org/apache/dubbo/common/beans/factory/ScopeBeanFactory.registerBean:(Ljava/lang/Class;)Ljava/lang/Object;
      18: pop
      19: aload_2
      20: ldc           #6                  // class org/apache/dubbo/common/utils/SerializeSecurityManager
      22: invokevirtual #4                  // Method org/apache/dubbo/common/beans/factory/ScopeBeanFactory.registerBean:(Ljava/lang/Class;)Ljava/lang/Object;
      25: pop
      26: aload_2
      27: ldc           #7                  // class org/apache/dubbo/common/utils/DefaultSerializeClassChecker
      29: invokevirtual #4                  // Method org/apache/dubbo/common/beans/factory/ScopeBeanFactory.registerBean:(Ljava/lang/Class;)Ljava/lang/Object;
      32: pop
      33: aload_2
      34: ldc           #8                  // class org/apache/dubbo/common/ssl/CertManager
      36: invokevirtual #4                  // Method org/apache/dubbo/common/beans/factory/ScopeBeanFactory.registerBean:(Ljava/lang/Class;)Ljava/lang/Object;
      39: pop
      40: return

  public void initializeApplicationModel(org.apache.dubbo.rpc.model.ApplicationModel);
    Code:
       0: aload_1
       1: invokevirtual #9                  // Method org/apache/dubbo/rpc/model/ApplicationModel.getBeanFactory:()Lorg/apache/dubbo/common/beans/factory/ScopeBeanFactory;
       4: astore_2
       5: aload_2
       6: ldc           #10                 // class org/apache/dubbo/common/lang/ShutdownHookCallbacks
       8: invokevirtual #4                  // Method org/apache/dubbo/common/beans/factory/ScopeBeanFactory.registerBean:(Ljava/lang/Class;)Ljava/lang/Object;
      11: pop
      12: aload_2
      13: ldc           #11                 // class org/apache/dubbo/common/status/reporter/FrameworkStatusReportService
      15: invokevirtual #4                  // Method org/apache/dubbo/common/beans/factory/ScopeBeanFactory.registerBean:(Ljava/lang/Class;)Ljava/lang/Object;
      18: pop
      19: aload_2
      20: new           #12                 // class org/apache/dubbo/common/config/ConfigurationCache
      23: dup
      24: invokespecial #13                 // Method org/apache/dubbo/common/config/ConfigurationCache."<init>":()V
      27: invokevirtual #14                 // Method org/apache/dubbo/common/beans/factory/ScopeBeanFactory.registerBean:(Ljava/lang/Object;)V
      30: return

  public void initializeModuleModel(org.apache.dubbo.rpc.model.ModuleModel);
    Code:
       0: aload_1
       1: invokevirtual #15                 // Method org/apache/dubbo/rpc/model/ModuleModel.getBeanFactory:()Lorg/apache/dubbo/common/beans/factory/ScopeBeanFactory;
       4: astore_2
       5: aload_2
       6: new           #12                 // class org/apache/dubbo/common/config/ConfigurationCache
       9: dup
      10: invokespecial #13                 // Method org/apache/dubbo/common/config/ConfigurationCache."<init>":()V
      13: invokevirtual #14                 // Method org/apache/dubbo/common/beans/factory/ScopeBeanFactory.registerBean:(Ljava/lang/Object;)V
      16: aload_2
      17: ldc           #16                 // class org/apache/dubbo/common/utils/SerializeSecurityConfigurator
      19: invokevirtual #4                  // Method org/apache/dubbo/common/beans/factory/ScopeBeanFactory.registerBean:(Ljava/lang/Class;)Ljava/lang/Object;
      22: pop
      23: return
}
