Compiled from "Parameters.java"
public class org.apache.dubbo.common.Parameters {
  protected static final org.apache.dubbo.common.logger.ErrorTypeAwareLogger logger;

  private final java.util.Map<java.lang.String, java.lang.String> parameters;

  public org.apache.dubbo.common.Parameters(java.lang.String...);
    Code:
       0: aload_0
       1: aload_1
       2: invokestatic  #3                  // Method toMap:([Ljava/lang/String;)Ljava/util/Map;
       5: invokespecial #4                  // Method "<init>":(Ljava/util/Map;)V
       8: return

  public org.apache.dubbo.common.Parameters(java.util.Map<java.lang.String, java.lang.String>);
    Code:
       0: aload_0
       1: invokespecial #5                  // Method java/lang/Object."<init>":()V
       4: aload_0
       5: aload_1
       6: ifnull        20
       9: new           #6                  // class java/util/HashMap
      12: dup
      13: aload_1
      14: invokespecial #7                  // Method java/util/HashMap."<init>":(Ljava/util/Map;)V
      17: goto          28
      20: new           #6                  // class java/util/HashMap
      23: dup
      24: iconst_0
      25: invokespecial #8                  // Method java/util/HashMap."<init>":(I)V
      28: invokestatic  #9                  // Method java/util/Collections.unmodifiableMap:(Ljava/util/Map;)Ljava/util/Map;
      31: putfield      #10                 // Field parameters:Ljava/util/Map;
      34: return

  private static java.util.Map<java.lang.String, java.lang.String> toMap(java.lang.String...);
    Code:
       0: aload_0
       1: invokestatic  #11                 // Method org/apache/dubbo/common/utils/CollectionUtils.toStringMap:([Ljava/lang/String;)Ljava/util/Map;
       4: areturn

  public static org.apache.dubbo.common.Parameters parseParameters(java.lang.String);
    Code:
       0: new           #12                 // class org/apache/dubbo/common/Parameters
       3: dup
       4: aload_0
       5: invokestatic  #13                 // Method org/apache/dubbo/common/utils/StringUtils.parseQueryString:(Ljava/lang/String;)Ljava/util/Map;
       8: invokespecial #4                  // Method "<init>":(Ljava/util/Map;)V
      11: areturn

  public java.util.Map<java.lang.String, java.lang.String> getParameters();
    Code:
       0: aload_0
       1: getfield      #10                 // Field parameters:Ljava/util/Map;
       4: areturn

  public <T> T getExtension(java.lang.Class<T>, java.lang.String);
    Code:
       0: aload_0
       1: aload_2
       2: invokevirtual #14                 // Method getParameter:(Ljava/lang/String;)Ljava/lang/String;
       5: astore_3
       6: aload_1
       7: invokestatic  #15                 // Method org/apache/dubbo/common/extension/ExtensionLoader.getExtensionLoader:(Ljava/lang/Class;)Lorg/apache/dubbo/common/extension/ExtensionLoader;
      10: aload_3
      11: invokevirtual #16                 // Method org/apache/dubbo/common/extension/ExtensionLoader.getExtension:(Ljava/lang/String;)Ljava/lang/Object;
      14: areturn

  public <T> T getExtension(java.lang.Class<T>, java.lang.String, java.lang.String);
    Code:
       0: aload_0
       1: aload_2
       2: aload_3
       3: invokevirtual #17                 // Method getParameter:(Ljava/lang/String;Ljava/lang/String;)Ljava/lang/String;
       6: astore        4
       8: aload_1
       9: invokestatic  #15                 // Method org/apache/dubbo/common/extension/ExtensionLoader.getExtensionLoader:(Ljava/lang/Class;)Lorg/apache/dubbo/common/extension/ExtensionLoader;
      12: aload         4
      14: invokevirtual #16                 // Method org/apache/dubbo/common/extension/ExtensionLoader.getExtension:(Ljava/lang/String;)Ljava/lang/Object;
      17: areturn

  public <T> T getMethodExtension(java.lang.Class<T>, java.lang.String, java.lang.String);
    Code:
       0: aload_0
       1: aload_2
       2: aload_3
       3: invokevirtual #18                 // Method getMethodParameter:(Ljava/lang/String;Ljava/lang/String;)Ljava/lang/String;
       6: astore        4
       8: aload_1
       9: invokestatic  #15                 // Method org/apache/dubbo/common/extension/ExtensionLoader.getExtensionLoader:(Ljava/lang/Class;)Lorg/apache/dubbo/common/extension/ExtensionLoader;
      12: aload         4
      14: invokevirtual #16                 // Method org/apache/dubbo/common/extension/ExtensionLoader.getExtension:(Ljava/lang/String;)Ljava/lang/Object;
      17: areturn

  public <T> T getMethodExtension(java.lang.Class<T>, java.lang.String, java.lang.String, java.lang.String);
    Code:
       0: aload_0
       1: aload_2
       2: aload_3
       3: aload         4
       5: invokevirtual #19                 // Method getMethodParameter:(Ljava/lang/String;Ljava/lang/String;Ljava/lang/String;)Ljava/lang/String;
       8: astore        5
      10: aload_1
      11: invokestatic  #15                 // Method org/apache/dubbo/common/extension/ExtensionLoader.getExtensionLoader:(Ljava/lang/Class;)Lorg/apache/dubbo/common/extension/ExtensionLoader;
      14: aload         5
      16: invokevirtual #16                 // Method org/apache/dubbo/common/extension/ExtensionLoader.getExtension:(Ljava/lang/String;)Ljava/lang/Object;
      19: areturn

  public java.lang.String getDecodedParameter(java.lang.String);
    Code:
       0: aload_0
       1: aload_1
       2: aconst_null
       3: invokevirtual #20                 // Method getDecodedParameter:(Ljava/lang/String;Ljava/lang/String;)Ljava/lang/String;
       6: areturn

  public java.lang.String getDecodedParameter(java.lang.String, java.lang.String);
    Code:
       0: aload_0
       1: aload_1
       2: aload_2
       3: invokevirtual #17                 // Method getParameter:(Ljava/lang/String;Ljava/lang/String;)Ljava/lang/String;
       6: astore_3
       7: aload_3
       8: ifnull        51
      11: aload_3
      12: invokevirtual #21                 // Method java/lang/String.length:()I
      15: ifle          51
      18: aload_3
      19: ldc           #22                 // String UTF-8
      21: invokestatic  #23                 // Method java/net/URLDecoder.decode:(Ljava/lang/String;Ljava/lang/String;)Ljava/lang/String;
      24: astore_3
      25: goto          51
      28: astore        4
      30: getstatic     #25                 // Field logger:Lorg/apache/dubbo/common/logger/ErrorTypeAwareLogger;
      33: ldc           #26                 // String 0-12
      35: ldc           #27                 // String
      37: ldc           #27                 // String
      39: aload         4
      41: invokevirtual #28                 // Method java/io/UnsupportedEncodingException.getMessage:()Ljava/lang/String;
      44: aload         4
      46: invokeinterface #29,  6           // InterfaceMethod org/apache/dubbo/common/logger/ErrorTypeAwareLogger.error:(Ljava/lang/String;Ljava/lang/String;Ljava/lang/String;Ljava/lang/String;Ljava/lang/Throwable;)V
      51: aload_3
      52: areturn
    Exception table:
       from    to  target type
          18    25    28   Class java/io/UnsupportedEncodingException

  public java.lang.String getParameter(java.lang.String);
    Code:
       0: aload_0
       1: getfield      #10                 // Field parameters:Ljava/util/Map;
       4: aload_1
       5: invokeinterface #30,  2           // InterfaceMethod java/util/Map.get:(Ljava/lang/Object;)Ljava/lang/Object;
      10: checkcast     #31                 // class java/lang/String
      13: astore_2
      14: aload_2
      15: invokestatic  #32                 // Method org/apache/dubbo/common/utils/StringUtils.isEmpty:(Ljava/lang/String;)Z
      18: ifeq          53
      21: aload_0
      22: getfield      #10                 // Field parameters:Ljava/util/Map;
      25: new           #33                 // class java/lang/StringBuilder
      28: dup
      29: invokespecial #34                 // Method java/lang/StringBuilder."<init>":()V
      32: ldc           #35                 // String .
      34: invokevirtual #36                 // Method java/lang/StringBuilder.append:(Ljava/lang/String;)Ljava/lang/StringBuilder;
      37: aload_1
      38: invokevirtual #36                 // Method java/lang/StringBuilder.append:(Ljava/lang/String;)Ljava/lang/StringBuilder;
      41: invokevirtual #37                 // Method java/lang/StringBuilder.toString:()Ljava/lang/String;
      44: invokeinterface #30,  2           // InterfaceMethod java/util/Map.get:(Ljava/lang/Object;)Ljava/lang/Object;
      49: checkcast     #31                 // class java/lang/String
      52: astore_2
      53: aload_2
      54: invokestatic  #32                 // Method org/apache/dubbo/common/utils/StringUtils.isEmpty:(Ljava/lang/String;)Z
      57: ifeq          92
      60: aload_0
      61: getfield      #10                 // Field parameters:Ljava/util/Map;
      64: new           #33                 // class java/lang/StringBuilder
      67: dup
      68: invokespecial #34                 // Method java/lang/StringBuilder."<init>":()V
      71: ldc           #38                 // String default.
      73: invokevirtual #36                 // Method java/lang/StringBuilder.append:(Ljava/lang/String;)Ljava/lang/StringBuilder;
      76: aload_1
      77: invokevirtual #36                 // Method java/lang/StringBuilder.append:(Ljava/lang/String;)Ljava/lang/StringBuilder;
      80: invokevirtual #37                 // Method java/lang/StringBuilder.toString:()Ljava/lang/String;
      83: invokeinterface #30,  2           // InterfaceMethod java/util/Map.get:(Ljava/lang/Object;)Ljava/lang/Object;
      88: checkcast     #31                 // class java/lang/String
      91: astore_2
      92: aload_2
      93: invokestatic  #32                 // Method org/apache/dubbo/common/utils/StringUtils.isEmpty:(Ljava/lang/String;)Z
      96: ifeq          131
      99: aload_0
     100: getfield      #10                 // Field parameters:Ljava/util/Map;
     103: new           #33                 // class java/lang/StringBuilder
     106: dup
     107: invokespecial #34                 // Method java/lang/StringBuilder."<init>":()V
     110: ldc           #39                 // String .default.
     112: invokevirtual #36                 // Method java/lang/StringBuilder.append:(Ljava/lang/String;)Ljava/lang/StringBuilder;
     115: aload_1
     116: invokevirtual #36                 // Method java/lang/StringBuilder.append:(Ljava/lang/String;)Ljava/lang/StringBuilder;
     119: invokevirtual #37                 // Method java/lang/StringBuilder.toString:()Ljava/lang/String;
     122: invokeinterface #30,  2           // InterfaceMethod java/util/Map.get:(Ljava/lang/Object;)Ljava/lang/Object;
     127: checkcast     #31                 // class java/lang/String
     130: astore_2
     131: aload_2
     132: areturn

  public java.lang.String getParameter(java.lang.String, java.lang.String);
    Code:
       0: aload_0
       1: aload_1
       2: invokevirtual #14                 // Method getParameter:(Ljava/lang/String;)Ljava/lang/String;
       5: astore_3
       6: aload_3
       7: invokestatic  #32                 // Method org/apache/dubbo/common/utils/StringUtils.isEmpty:(Ljava/lang/String;)Z
      10: ifeq          15
      13: aload_2
      14: areturn
      15: aload_3
      16: areturn

  public int getIntParameter(java.lang.String);
    Code:
       0: aload_0
       1: aload_1
       2: invokevirtual #14                 // Method getParameter:(Ljava/lang/String;)Ljava/lang/String;
       5: astore_2
       6: aload_2
       7: invokestatic  #32                 // Method org/apache/dubbo/common/utils/StringUtils.isEmpty:(Ljava/lang/String;)Z
      10: ifeq          15
      13: iconst_0
      14: ireturn
      15: aload_2
      16: invokestatic  #40                 // Method java/lang/Integer.parseInt:(Ljava/lang/String;)I
      19: ireturn

  public int getIntParameter(java.lang.String, int);
    Code:
       0: aload_0
       1: aload_1
       2: invokevirtual #14                 // Method getParameter:(Ljava/lang/String;)Ljava/lang/String;
       5: astore_3
       6: aload_3
       7: invokestatic  #32                 // Method org/apache/dubbo/common/utils/StringUtils.isEmpty:(Ljava/lang/String;)Z
      10: ifeq          15
      13: iload_2
      14: ireturn
      15: aload_3
      16: invokestatic  #40                 // Method java/lang/Integer.parseInt:(Ljava/lang/String;)I
      19: ireturn

  public int getPositiveIntParameter(java.lang.String, int);
    Code:
       0: iload_2
       1: ifgt          14
       4: new           #41                 // class java/lang/IllegalArgumentException
       7: dup
       8: ldc           #42                 // String defaultValue <= 0
      10: invokespecial #43                 // Method java/lang/IllegalArgumentException."<init>":(Ljava/lang/String;)V
      13: athrow
      14: aload_0
      15: aload_1
      16: invokevirtual #14                 // Method getParameter:(Ljava/lang/String;)Ljava/lang/String;
      19: astore_3
      20: aload_3
      21: invokestatic  #32                 // Method org/apache/dubbo/common/utils/StringUtils.isEmpty:(Ljava/lang/String;)Z
      24: ifeq          29
      27: iload_2
      28: ireturn
      29: aload_3
      30: invokestatic  #40                 // Method java/lang/Integer.parseInt:(Ljava/lang/String;)I
      33: istore        4
      35: iload         4
      37: ifle          43
      40: iload         4
      42: ireturn
      43: iload_2
      44: ireturn

  public boolean getBooleanParameter(java.lang.String);
    Code:
       0: aload_0
       1: aload_1
       2: invokevirtual #14                 // Method getParameter:(Ljava/lang/String;)Ljava/lang/String;
       5: astore_2
       6: aload_2
       7: invokestatic  #32                 // Method org/apache/dubbo/common/utils/StringUtils.isEmpty:(Ljava/lang/String;)Z
      10: ifeq          15
      13: iconst_0
      14: ireturn
      15: aload_2
      16: invokestatic  #44                 // Method java/lang/Boolean.parseBoolean:(Ljava/lang/String;)Z
      19: ireturn

  public boolean getBooleanParameter(java.lang.String, boolean);
    Code:
       0: aload_0
       1: aload_1
       2: invokevirtual #14                 // Method getParameter:(Ljava/lang/String;)Ljava/lang/String;
       5: astore_3
       6: aload_3
       7: invokestatic  #32                 // Method org/apache/dubbo/common/utils/StringUtils.isEmpty:(Ljava/lang/String;)Z
      10: ifeq          15
      13: iload_2
      14: ireturn
      15: aload_3
      16: invokestatic  #44                 // Method java/lang/Boolean.parseBoolean:(Ljava/lang/String;)Z
      19: ireturn

  public boolean hasParameter(java.lang.String);
    Code:
       0: aload_0
       1: aload_1
       2: invokevirtual #14                 // Method getParameter:(Ljava/lang/String;)Ljava/lang/String;
       5: astore_2
       6: aload_2
       7: ifnull        21
      10: aload_2
      11: invokevirtual #21                 // Method java/lang/String.length:()I
      14: ifle          21
      17: iconst_1
      18: goto          22
      21: iconst_0
      22: ireturn

  public java.lang.String getMethodParameter(java.lang.String, java.lang.String);
    Code:
       0: aload_0
       1: getfield      #10                 // Field parameters:Ljava/util/Map;
       4: new           #33                 // class java/lang/StringBuilder
       7: dup
       8: invokespecial #34                 // Method java/lang/StringBuilder."<init>":()V
      11: aload_1
      12: invokevirtual #36                 // Method java/lang/StringBuilder.append:(Ljava/lang/String;)Ljava/lang/StringBuilder;
      15: ldc           #35                 // String .
      17: invokevirtual #36                 // Method java/lang/StringBuilder.append:(Ljava/lang/String;)Ljava/lang/StringBuilder;
      20: aload_2
      21: invokevirtual #36                 // Method java/lang/StringBuilder.append:(Ljava/lang/String;)Ljava/lang/StringBuilder;
      24: invokevirtual #37                 // Method java/lang/StringBuilder.toString:()Ljava/lang/String;
      27: invokeinterface #30,  2           // InterfaceMethod java/util/Map.get:(Ljava/lang/Object;)Ljava/lang/Object;
      32: checkcast     #31                 // class java/lang/String
      35: astore_3
      36: aload_3
      37: invokestatic  #32                 // Method org/apache/dubbo/common/utils/StringUtils.isEmpty:(Ljava/lang/String;)Z
      40: ifeq          84
      43: aload_0
      44: getfield      #10                 // Field parameters:Ljava/util/Map;
      47: new           #33                 // class java/lang/StringBuilder
      50: dup
      51: invokespecial #34                 // Method java/lang/StringBuilder."<init>":()V
      54: ldc           #35                 // String .
      56: invokevirtual #36                 // Method java/lang/StringBuilder.append:(Ljava/lang/String;)Ljava/lang/StringBuilder;
      59: aload_1
      60: invokevirtual #36                 // Method java/lang/StringBuilder.append:(Ljava/lang/String;)Ljava/lang/StringBuilder;
      63: ldc           #35                 // String .
      65: invokevirtual #36                 // Method java/lang/StringBuilder.append:(Ljava/lang/String;)Ljava/lang/StringBuilder;
      68: aload_2
      69: invokevirtual #36                 // Method java/lang/StringBuilder.append:(Ljava/lang/String;)Ljava/lang/StringBuilder;
      72: invokevirtual #37                 // Method java/lang/StringBuilder.toString:()Ljava/lang/String;
      75: invokeinterface #30,  2           // InterfaceMethod java/util/Map.get:(Ljava/lang/Object;)Ljava/lang/Object;
      80: checkcast     #31                 // class java/lang/String
      83: astore_3
      84: aload_3
      85: invokestatic  #32                 // Method org/apache/dubbo/common/utils/StringUtils.isEmpty:(Ljava/lang/String;)Z
      88: ifeq          97
      91: aload_0
      92: aload_2
      93: invokevirtual #14                 // Method getParameter:(Ljava/lang/String;)Ljava/lang/String;
      96: areturn
      97: aload_3
      98: areturn

  public java.lang.String getMethodParameter(java.lang.String, java.lang.String, java.lang.String);
    Code:
       0: aload_0
       1: aload_1
       2: aload_2
       3: invokevirtual #18                 // Method getMethodParameter:(Ljava/lang/String;Ljava/lang/String;)Ljava/lang/String;
       6: astore        4
       8: aload         4
      10: invokestatic  #32                 // Method org/apache/dubbo/common/utils/StringUtils.isEmpty:(Ljava/lang/String;)Z
      13: ifeq          18
      16: aload_3
      17: areturn
      18: aload         4
      20: areturn

  public int getMethodIntParameter(java.lang.String, java.lang.String);
    Code:
       0: aload_0
       1: aload_1
       2: aload_2
       3: invokevirtual #18                 // Method getMethodParameter:(Ljava/lang/String;Ljava/lang/String;)Ljava/lang/String;
       6: astore_3
       7: aload_3
       8: invokestatic  #32                 // Method org/apache/dubbo/common/utils/StringUtils.isEmpty:(Ljava/lang/String;)Z
      11: ifeq          16
      14: iconst_0
      15: ireturn
      16: aload_3
      17: invokestatic  #40                 // Method java/lang/Integer.parseInt:(Ljava/lang/String;)I
      20: ireturn

  public int getMethodIntParameter(java.lang.String, java.lang.String, int);
    Code:
       0: aload_0
       1: aload_1
       2: aload_2
       3: invokevirtual #18                 // Method getMethodParameter:(Ljava/lang/String;Ljava/lang/String;)Ljava/lang/String;
       6: astore        4
       8: aload         4
      10: invokestatic  #32                 // Method org/apache/dubbo/common/utils/StringUtils.isEmpty:(Ljava/lang/String;)Z
      13: ifeq          18
      16: iload_3
      17: ireturn
      18: aload         4
      20: invokestatic  #40                 // Method java/lang/Integer.parseInt:(Ljava/lang/String;)I
      23: ireturn

  public int getMethodPositiveIntParameter(java.lang.String, java.lang.String, int);
    Code:
       0: iload_3
       1: ifgt          14
       4: new           #41                 // class java/lang/IllegalArgumentException
       7: dup
       8: ldc           #42                 // String defaultValue <= 0
      10: invokespecial #43                 // Method java/lang/IllegalArgumentException."<init>":(Ljava/lang/String;)V
      13: athrow
      14: aload_0
      15: aload_1
      16: aload_2
      17: invokevirtual #18                 // Method getMethodParameter:(Ljava/lang/String;Ljava/lang/String;)Ljava/lang/String;
      20: astore        4
      22: aload         4
      24: invokestatic  #32                 // Method org/apache/dubbo/common/utils/StringUtils.isEmpty:(Ljava/lang/String;)Z
      27: ifeq          32
      30: iload_3
      31: ireturn
      32: aload         4
      34: invokestatic  #40                 // Method java/lang/Integer.parseInt:(Ljava/lang/String;)I
      37: istore        5
      39: iload         5
      41: ifle          47
      44: iload         5
      46: ireturn
      47: iload_3
      48: ireturn

  public boolean getMethodBooleanParameter(java.lang.String, java.lang.String);
    Code:
       0: aload_0
       1: aload_1
       2: aload_2
       3: invokevirtual #18                 // Method getMethodParameter:(Ljava/lang/String;Ljava/lang/String;)Ljava/lang/String;
       6: astore_3
       7: aload_3
       8: invokestatic  #32                 // Method org/apache/dubbo/common/utils/StringUtils.isEmpty:(Ljava/lang/String;)Z
      11: ifeq          16
      14: iconst_0
      15: ireturn
      16: aload_3
      17: invokestatic  #44                 // Method java/lang/Boolean.parseBoolean:(Ljava/lang/String;)Z
      20: ireturn

  public boolean getMethodBooleanParameter(java.lang.String, java.lang.String, boolean);
    Code:
       0: aload_0
       1: aload_1
       2: aload_2
       3: invokevirtual #18                 // Method getMethodParameter:(Ljava/lang/String;Ljava/lang/String;)Ljava/lang/String;
       6: astore        4
       8: aload         4
      10: invokestatic  #32                 // Method org/apache/dubbo/common/utils/StringUtils.isEmpty:(Ljava/lang/String;)Z
      13: ifeq          18
      16: iload_3
      17: ireturn
      18: aload         4
      20: invokestatic  #44                 // Method java/lang/Boolean.parseBoolean:(Ljava/lang/String;)Z
      23: ireturn

  public boolean hasMethodParameter(java.lang.String, java.lang.String);
    Code:
       0: aload_0
       1: aload_1
       2: aload_2
       3: invokevirtual #18                 // Method getMethodParameter:(Ljava/lang/String;Ljava/lang/String;)Ljava/lang/String;
       6: astore_3
       7: aload_3
       8: ifnull        22
      11: aload_3
      12: invokevirtual #21                 // Method java/lang/String.length:()I
      15: ifle          22
      18: iconst_1
      19: goto          23
      22: iconst_0
      23: ireturn

  public boolean equals(java.lang.Object);
    Code:
       0: aload_0
       1: aload_1
       2: if_acmpne     7
       5: iconst_1
       6: ireturn
       7: aload_0
       8: getfield      #10                 // Field parameters:Ljava/util/Map;
      11: aload_1
      12: invokeinterface #45,  2           // InterfaceMethod java/util/Map.equals:(Ljava/lang/Object;)Z
      17: ireturn

  public int hashCode();
    Code:
       0: aload_0
       1: getfield      #10                 // Field parameters:Ljava/util/Map;
       4: invokeinterface #46,  1           // InterfaceMethod java/util/Map.hashCode:()I
       9: ireturn

  public java.lang.String toString();
    Code:
       0: aload_0
       1: invokevirtual #47                 // Method getParameters:()Ljava/util/Map;
       4: invokestatic  #48                 // Method org/apache/dubbo/common/utils/StringUtils.toQueryString:(Ljava/util/Map;)Ljava/lang/String;
       7: areturn

  static {};
    Code:
       0: ldc           #12                 // class org/apache/dubbo/common/Parameters
       2: invokestatic  #49                 // Method org/apache/dubbo/common/logger/LoggerFactory.getErrorTypeAwareLogger:(Ljava/lang/Class;)Lorg/apache/dubbo/common/logger/ErrorTypeAwareLogger;
       5: putstatic     #25                 // Field logger:Lorg/apache/dubbo/common/logger/ErrorTypeAwareLogger;
       8: return
}
