Compiled from "ProtocolServiceKey.java"
public class org.apache.dubbo.common.ProtocolServiceKey extends org.apache.dubbo.common.ServiceKey {
  private final java.lang.String protocol;

  public org.apache.dubbo.common.ProtocolServiceKey(java.lang.String, java.lang.String, java.lang.String, java.lang.String);
    Code:
       0: aload_0
       1: aload_1
       2: aload_2
       3: aload_3
       4: invokespecial #1                  // Method org/apache/dubbo/common/ServiceKey."<init>":(Ljava/lang/String;Ljava/lang/String;Ljava/lang/String;)V
       7: aload_0
       8: aload         4
      10: putfield      #2                  // Field protocol:Ljava/lang/String;
      13: return

  public java.lang.String getProtocol();
    Code:
       0: aload_0
       1: getfield      #2                  // Field protocol:Ljava/lang/String;
       4: areturn

  public java.lang.String getServiceKeyString();
    Code:
       0: aload_0
       1: invokespecial #3                  // Method org/apache/dubbo/common/ServiceKey.toString:()Ljava/lang/String;
       4: areturn

  public boolean isSameWith(org.apache.dubbo.common.ProtocolServiceKey);
    Code:
       0: aload_0
       1: aload_1
       2: invokespecial #4                  // Method org/apache/dubbo/common/ServiceKey.equals:(Ljava/lang/Object;)Z
       5: ifne          10
       8: iconst_0
       9: ireturn
      10: ldc           #6                  // String *
      12: aload_0
      13: getfield      #2                  // Field protocol:Ljava/lang/String;
      16: invokevirtual #7                  // Method java/lang/String.equals:(Ljava/lang/Object;)Z
      19: ifeq          24
      22: iconst_0
      23: ireturn
      24: aload_0
      25: getfield      #2                  // Field protocol:Ljava/lang/String;
      28: invokestatic  #8                  // Method org/apache/dubbo/common/utils/StringUtils.isEmpty:(Ljava/lang/String;)Z
      31: ifne          44
      34: aload_1
      35: invokevirtual #9                  // Method getProtocol:()Ljava/lang/String;
      38: invokestatic  #8                  // Method org/apache/dubbo/common/utils/StringUtils.isEmpty:(Ljava/lang/String;)Z
      41: ifeq          46
      44: iconst_1
      45: ireturn
      46: aload_0
      47: getfield      #2                  // Field protocol:Ljava/lang/String;
      50: aload_1
      51: invokevirtual #9                  // Method getProtocol:()Ljava/lang/String;
      54: invokestatic  #10                 // Method java/util/Objects.equals:(Ljava/lang/Object;Ljava/lang/Object;)Z
      57: ireturn

  public boolean equals(java.lang.Object);
    Code:
       0: aload_0
       1: aload_1
       2: if_acmpne     7
       5: iconst_1
       6: ireturn
       7: aload_1
       8: ifnull        22
      11: aload_0
      12: invokevirtual #11                 // Method java/lang/Object.getClass:()Ljava/lang/Class;
      15: aload_1
      16: invokevirtual #11                 // Method java/lang/Object.getClass:()Ljava/lang/Class;
      19: if_acmpeq     24
      22: iconst_0
      23: ireturn
      24: aload_0
      25: aload_1
      26: invokespecial #4                  // Method org/apache/dubbo/common/ServiceKey.equals:(Ljava/lang/Object;)Z
      29: ifne          34
      32: iconst_0
      33: ireturn
      34: aload_1
      35: checkcast     #12                 // class org/apache/dubbo/common/ProtocolServiceKey
      38: astore_2
      39: aload_0
      40: getfield      #2                  // Field protocol:Ljava/lang/String;
      43: aload_2
      44: getfield      #2                  // Field protocol:Ljava/lang/String;
      47: invokestatic  #10                 // Method java/util/Objects.equals:(Ljava/lang/Object;Ljava/lang/Object;)Z
      50: ireturn

  public int hashCode();
    Code:
       0: iconst_2
       1: anewarray     #13                 // class java/lang/Object
       4: dup
       5: iconst_0
       6: aload_0
       7: invokespecial #14                 // Method org/apache/dubbo/common/ServiceKey.hashCode:()I
      10: invokestatic  #15                 // Method java/lang/Integer.valueOf:(I)Ljava/lang/Integer;
      13: aastore
      14: dup
      15: iconst_1
      16: aload_0
      17: getfield      #2                  // Field protocol:Ljava/lang/String;
      20: aastore
      21: invokestatic  #16                 // Method java/util/Objects.hash:([Ljava/lang/Object;)I
      24: ireturn

  public java.lang.String toString();
    Code:
       0: new           #17                 // class java/lang/StringBuilder
       3: dup
       4: invokespecial #18                 // Method java/lang/StringBuilder."<init>":()V
       7: aload_0
       8: invokespecial #3                  // Method org/apache/dubbo/common/ServiceKey.toString:()Ljava/lang/String;
      11: invokevirtual #19                 // Method java/lang/StringBuilder.append:(Ljava/lang/String;)Ljava/lang/StringBuilder;
      14: ldc           #20                 // String :
      16: invokevirtual #19                 // Method java/lang/StringBuilder.append:(Ljava/lang/String;)Ljava/lang/StringBuilder;
      19: aload_0
      20: getfield      #2                  // Field protocol:Ljava/lang/String;
      23: invokevirtual #19                 // Method java/lang/StringBuilder.append:(Ljava/lang/String;)Ljava/lang/StringBuilder;
      26: invokevirtual #21                 // Method java/lang/StringBuilder.toString:()Ljava/lang/String;
      29: areturn
}
