Compiled from "URL.java"
public class org.apache.dubbo.common.URL implements java.io.Serializable {
  private static final long serialVersionUID;

  private static final java.util.Map<java.lang.String, org.apache.dubbo.common.URL> cachedURLs;

  private final org.apache.dubbo.common.url.component.URLAddress urlAddress;

  private final org.apache.dubbo.common.url.component.URLParam urlParam;

  private transient java.lang.String serviceKey;

  private transient java.lang.String protocolServiceKey;

  protected volatile java.util.Map<java.lang.String, java.lang.Object> attributes;

  private volatile int hashCodeCache;

  protected org.apache.dubbo.common.URL();
    Code:
       0: aload_0
       1: invokespecial #4                  // Method java/lang/Object."<init>":()V
       4: aload_0
       5: iconst_m1
       6: putfield      #5                  // Field hashCodeCache:I
       9: aload_0
      10: aconst_null
      11: putfield      #6                  // Field urlAddress:Lorg/apache/dubbo/common/url/component/URLAddress;
      14: aload_0
      15: new           #7                  // class java/util/HashMap
      18: dup
      19: invokespecial #8                  // Method java/util/HashMap."<init>":()V
      22: invokestatic  #9                  // Method org/apache/dubbo/common/url/component/URLParam.parse:(Ljava/util/Map;)Lorg/apache/dubbo/common/url/component/URLParam;
      25: putfield      #10                 // Field urlParam:Lorg/apache/dubbo/common/url/component/URLParam;
      28: aload_0
      29: aconst_null
      30: putfield      #11                 // Field attributes:Ljava/util/Map;
      33: return

  public org.apache.dubbo.common.URL(org.apache.dubbo.common.url.component.URLAddress, org.apache.dubbo.common.url.component.URLParam);
    Code:
       0: aload_0
       1: aload_1
       2: aload_2
       3: aconst_null
       4: invokespecial #12                 // Method "<init>":(Lorg/apache/dubbo/common/url/component/URLAddress;Lorg/apache/dubbo/common/url/component/URLParam;Ljava/util/Map;)V
       7: return

  public org.apache.dubbo.common.URL(org.apache.dubbo.common.url.component.URLAddress, org.apache.dubbo.common.url.component.URLParam, java.util.Map<java.lang.String, java.lang.Object>);
    Code:
       0: aload_0
       1: invokespecial #4                  // Method java/lang/Object."<init>":()V
       4: aload_0
       5: iconst_m1
       6: putfield      #5                  // Field hashCodeCache:I
       9: aload_0
      10: aload_1
      11: putfield      #6                  // Field urlAddress:Lorg/apache/dubbo/common/url/component/URLAddress;
      14: aload_0
      15: aconst_null
      16: aload_2
      17: if_acmpne     33
      20: new           #7                  // class java/util/HashMap
      23: dup
      24: invokespecial #8                  // Method java/util/HashMap."<init>":()V
      27: invokestatic  #9                  // Method org/apache/dubbo/common/url/component/URLParam.parse:(Ljava/util/Map;)Lorg/apache/dubbo/common/url/component/URLParam;
      30: goto          34
      33: aload_2
      34: putfield      #10                 // Field urlParam:Lorg/apache/dubbo/common/url/component/URLParam;
      37: aload_3
      38: ifnull        58
      41: aload_3
      42: invokeinterface #13,  1           // InterfaceMethod java/util/Map.isEmpty:()Z
      47: ifne          58
      50: aload_0
      51: aload_3
      52: putfield      #11                 // Field attributes:Ljava/util/Map;
      55: goto          63
      58: aload_0
      59: aconst_null
      60: putfield      #11                 // Field attributes:Ljava/util/Map;
      63: return

  public org.apache.dubbo.common.URL(java.lang.String, java.lang.String, int);
    Code:
       0: aload_0
       1: aload_1
       2: aconst_null
       3: aconst_null
       4: aload_2
       5: iload_3
       6: aconst_null
       7: aconst_null
       8: checkcast     #14                 // class java/util/Map
      11: invokespecial #15                 // Method "<init>":(Ljava/lang/String;Ljava/lang/String;Ljava/lang/String;Ljava/lang/String;ILjava/lang/String;Ljava/util/Map;)V
      14: return

  public org.apache.dubbo.common.URL(java.lang.String, java.lang.String, int, java.lang.String[]);
    Code:
       0: aload_0
       1: aload_1
       2: aconst_null
       3: aconst_null
       4: aload_2
       5: iload_3
       6: aconst_null
       7: aload         4
       9: invokestatic  #16                 // Method org/apache/dubbo/common/utils/CollectionUtils.toStringMap:([Ljava/lang/String;)Ljava/util/Map;
      12: invokespecial #15                 // Method "<init>":(Ljava/lang/String;Ljava/lang/String;Ljava/lang/String;Ljava/lang/String;ILjava/lang/String;Ljava/util/Map;)V
      15: return

  public org.apache.dubbo.common.URL(java.lang.String, java.lang.String, int, java.util.Map<java.lang.String, java.lang.String>);
    Code:
       0: aload_0
       1: aload_1
       2: aconst_null
       3: aconst_null
       4: aload_2
       5: iload_3
       6: aconst_null
       7: aload         4
       9: invokespecial #15                 // Method "<init>":(Ljava/lang/String;Ljava/lang/String;Ljava/lang/String;Ljava/lang/String;ILjava/lang/String;Ljava/util/Map;)V
      12: return

  public org.apache.dubbo.common.URL(java.lang.String, java.lang.String, int, java.lang.String);
    Code:
       0: aload_0
       1: aload_1
       2: aconst_null
       3: aconst_null
       4: aload_2
       5: iload_3
       6: aload         4
       8: aconst_null
       9: checkcast     #14                 // class java/util/Map
      12: invokespecial #15                 // Method "<init>":(Ljava/lang/String;Ljava/lang/String;Ljava/lang/String;Ljava/lang/String;ILjava/lang/String;Ljava/util/Map;)V
      15: return

  public org.apache.dubbo.common.URL(java.lang.String, java.lang.String, int, java.lang.String, java.lang.String...);
    Code:
       0: aload_0
       1: aload_1
       2: aconst_null
       3: aconst_null
       4: aload_2
       5: iload_3
       6: aload         4
       8: aload         5
      10: invokestatic  #16                 // Method org/apache/dubbo/common/utils/CollectionUtils.toStringMap:([Ljava/lang/String;)Ljava/util/Map;
      13: invokespecial #15                 // Method "<init>":(Ljava/lang/String;Ljava/lang/String;Ljava/lang/String;Ljava/lang/String;ILjava/lang/String;Ljava/util/Map;)V
      16: return

  public org.apache.dubbo.common.URL(java.lang.String, java.lang.String, int, java.lang.String, java.util.Map<java.lang.String, java.lang.String>);
    Code:
       0: aload_0
       1: aload_1
       2: aconst_null
       3: aconst_null
       4: aload_2
       5: iload_3
       6: aload         4
       8: aload         5
      10: invokespecial #15                 // Method "<init>":(Ljava/lang/String;Ljava/lang/String;Ljava/lang/String;Ljava/lang/String;ILjava/lang/String;Ljava/util/Map;)V
      13: return

  public org.apache.dubbo.common.URL(java.lang.String, java.lang.String, java.lang.String, java.lang.String, int, java.lang.String);
    Code:
       0: aload_0
       1: aload_1
       2: aload_2
       3: aload_3
       4: aload         4
       6: iload         5
       8: aload         6
      10: aconst_null
      11: checkcast     #14                 // class java/util/Map
      14: invokespecial #15                 // Method "<init>":(Ljava/lang/String;Ljava/lang/String;Ljava/lang/String;Ljava/lang/String;ILjava/lang/String;Ljava/util/Map;)V
      17: return

  public org.apache.dubbo.common.URL(java.lang.String, java.lang.String, java.lang.String, java.lang.String, int, java.lang.String, java.lang.String...);
    Code:
       0: aload_0
       1: aload_1
       2: aload_2
       3: aload_3
       4: aload         4
       6: iload         5
       8: aload         6
      10: aload         7
      12: invokestatic  #16                 // Method org/apache/dubbo/common/utils/CollectionUtils.toStringMap:([Ljava/lang/String;)Ljava/util/Map;
      15: invokespecial #15                 // Method "<init>":(Ljava/lang/String;Ljava/lang/String;Ljava/lang/String;Ljava/lang/String;ILjava/lang/String;Ljava/util/Map;)V
      18: return

  public org.apache.dubbo.common.URL(java.lang.String, java.lang.String, java.lang.String, java.lang.String, int, java.lang.String, java.util.Map<java.lang.String, java.lang.String>);
    Code:
       0: aload_0
       1: invokespecial #4                  // Method java/lang/Object."<init>":()V
       4: aload_0
       5: iconst_m1
       6: putfield      #5                  // Field hashCodeCache:I
       9: aload_2
      10: invokestatic  #17                 // Method org/apache/dubbo/common/utils/StringUtils.isEmpty:(Ljava/lang/String;)Z
      13: ifeq          33
      16: aload_3
      17: invokestatic  #18                 // Method org/apache/dubbo/common/utils/StringUtils.isNotEmpty:(Ljava/lang/String;)Z
      20: ifeq          33
      23: new           #19                 // class java/lang/IllegalArgumentException
      26: dup
      27: ldc           #20                 // String Invalid url, password without username!
      29: invokespecial #21                 // Method java/lang/IllegalArgumentException."<init>":(Ljava/lang/String;)V
      32: athrow
      33: aload_0
      34: new           #22                 // class org/apache/dubbo/common/url/component/PathURLAddress
      37: dup
      38: aload_1
      39: aload_2
      40: aload_3
      41: aload         6
      43: aload         4
      45: iload         5
      47: invokespecial #23                 // Method org/apache/dubbo/common/url/component/PathURLAddress."<init>":(Ljava/lang/String;Ljava/lang/String;Ljava/lang/String;Ljava/lang/String;Ljava/lang/String;I)V
      50: putfield      #6                  // Field urlAddress:Lorg/apache/dubbo/common/url/component/URLAddress;
      53: aload_0
      54: aload         7
      56: invokestatic  #9                  // Method org/apache/dubbo/common/url/component/URLParam.parse:(Ljava/util/Map;)Lorg/apache/dubbo/common/url/component/URLParam;
      59: putfield      #10                 // Field urlParam:Lorg/apache/dubbo/common/url/component/URLParam;
      62: aload_0
      63: aconst_null
      64: putfield      #11                 // Field attributes:Ljava/util/Map;
      67: return

  protected org.apache.dubbo.common.URL(java.lang.String, java.lang.String, java.lang.String, java.lang.String, int, java.lang.String, java.util.Map<java.lang.String, java.lang.String>, boolean);
    Code:
       0: aload_0
       1: invokespecial #4                  // Method java/lang/Object."<init>":()V
       4: aload_0
       5: iconst_m1
       6: putfield      #5                  // Field hashCodeCache:I
       9: aload_2
      10: invokestatic  #17                 // Method org/apache/dubbo/common/utils/StringUtils.isEmpty:(Ljava/lang/String;)Z
      13: ifeq          33
      16: aload_3
      17: invokestatic  #18                 // Method org/apache/dubbo/common/utils/StringUtils.isNotEmpty:(Ljava/lang/String;)Z
      20: ifeq          33
      23: new           #19                 // class java/lang/IllegalArgumentException
      26: dup
      27: ldc           #20                 // String Invalid url, password without username!
      29: invokespecial #21                 // Method java/lang/IllegalArgumentException."<init>":(Ljava/lang/String;)V
      32: athrow
      33: aload_0
      34: new           #22                 // class org/apache/dubbo/common/url/component/PathURLAddress
      37: dup
      38: aload_1
      39: aload_2
      40: aload_3
      41: aload         6
      43: aload         4
      45: iload         5
      47: invokespecial #23                 // Method org/apache/dubbo/common/url/component/PathURLAddress."<init>":(Ljava/lang/String;Ljava/lang/String;Ljava/lang/String;Ljava/lang/String;Ljava/lang/String;I)V
      50: putfield      #6                  // Field urlAddress:Lorg/apache/dubbo/common/url/component/URLAddress;
      53: aload_0
      54: aload         7
      56: invokestatic  #9                  // Method org/apache/dubbo/common/url/component/URLParam.parse:(Ljava/util/Map;)Lorg/apache/dubbo/common/url/component/URLParam;
      59: putfield      #10                 // Field urlParam:Lorg/apache/dubbo/common/url/component/URLParam;
      62: aload_0
      63: aconst_null
      64: putfield      #11                 // Field attributes:Ljava/util/Map;
      67: return

  public static org.apache.dubbo.common.URL cacheableValueOf(java.lang.String);
    Code:
       0: getstatic     #24                 // Field cachedURLs:Ljava/util/Map;
       3: aload_0
       4: invokeinterface #25,  2           // InterfaceMethod java/util/Map.get:(Ljava/lang/Object;)Ljava/lang/Object;
       9: checkcast     #26                 // class org/apache/dubbo/common/URL
      12: astore_1
      13: aload_1
      14: ifnull        19
      17: aload_1
      18: areturn
      19: aload_0
      20: iconst_0
      21: invokestatic  #27                 // Method valueOf:(Ljava/lang/String;Z)Lorg/apache/dubbo/common/URL;
      24: astore_1
      25: getstatic     #24                 // Field cachedURLs:Ljava/util/Map;
      28: aload_0
      29: aload_1
      30: invokeinterface #28,  3           // InterfaceMethod java/util/Map.put:(Ljava/lang/Object;Ljava/lang/Object;)Ljava/lang/Object;
      35: pop
      36: aload_1
      37: areturn

  public static org.apache.dubbo.common.URL valueOf(java.lang.String);
    Code:
       0: aload_0
       1: iconst_0
       2: invokestatic  #27                 // Method valueOf:(Ljava/lang/String;Z)Lorg/apache/dubbo/common/URL;
       5: areturn

  public static org.apache.dubbo.common.URL valueOf(java.lang.String, org.apache.dubbo.rpc.model.ScopeModel);
    Code:
       0: aload_0
       1: invokestatic  #29                 // Method valueOf:(Ljava/lang/String;)Lorg/apache/dubbo/common/URL;
       4: aload_1
       5: invokevirtual #30                 // Method setScopeModel:(Lorg/apache/dubbo/rpc/model/ScopeModel;)Lorg/apache/dubbo/common/URL;
       8: areturn

  public static org.apache.dubbo.common.URL valueOf(java.lang.String, boolean);
    Code:
       0: iload_1
       1: ifeq          9
       4: aload_0
       5: invokestatic  #31                 // Method org/apache/dubbo/common/URLStrParser.parseEncodedStr:(Ljava/lang/String;)Lorg/apache/dubbo/common/URL;
       8: areturn
       9: aload_0
      10: invokestatic  #32                 // Method org/apache/dubbo/common/URLStrParser.parseDecodedStr:(Ljava/lang/String;)Lorg/apache/dubbo/common/URL;
      13: areturn

  public static org.apache.dubbo.common.URL valueOf(java.lang.String, java.lang.String...);
    Code:
       0: aload_0
       1: invokestatic  #29                 // Method valueOf:(Ljava/lang/String;)Lorg/apache/dubbo/common/URL;
       4: astore_2
       5: aload_1
       6: ifnull        14
       9: aload_1
      10: arraylength
      11: ifne          16
      14: aload_2
      15: areturn
      16: new           #7                  // class java/util/HashMap
      19: dup
      20: aload_1
      21: arraylength
      22: invokespecial #33                 // Method java/util/HashMap."<init>":(I)V
      25: astore_3
      26: aload_2
      27: invokevirtual #34                 // Method getParameters:()Ljava/util/Map;
      30: astore        4
      32: aload_1
      33: astore        5
      35: aload         5
      37: arraylength
      38: istore        6
      40: iconst_0
      41: istore        7
      43: iload         7
      45: iload         6
      47: if_icmpge     96
      50: aload         5
      52: iload         7
      54: aaload
      55: astore        8
      57: aload         4
      59: aload         8
      61: invokeinterface #25,  2           // InterfaceMethod java/util/Map.get:(Ljava/lang/Object;)Ljava/lang/Object;
      66: checkcast     #35                 // class java/lang/String
      69: astore        9
      71: aload         9
      73: invokestatic  #18                 // Method org/apache/dubbo/common/utils/StringUtils.isNotEmpty:(Ljava/lang/String;)Z
      76: ifeq          90
      79: aload_3
      80: aload         8
      82: aload         9
      84: invokeinterface #28,  3           // InterfaceMethod java/util/Map.put:(Ljava/lang/Object;Ljava/lang/Object;)Ljava/lang/Object;
      89: pop
      90: iinc          7, 1
      93: goto          43
      96: aload_2
      97: invokevirtual #36                 // Method clearParameters:()Lorg/apache/dubbo/common/URL;
     100: aload_3
     101: invokevirtual #37                 // Method addParameters:(Ljava/util/Map;)Lorg/apache/dubbo/common/URL;
     104: areturn

  public static org.apache.dubbo.common.URL valueOf(org.apache.dubbo.common.URL, java.lang.String[], java.lang.String[]);
    Code:
       0: new           #7                  // class java/util/HashMap
       3: dup
       4: invokespecial #8                  // Method java/util/HashMap."<init>":()V
       7: astore_3
       8: aload_0
       9: invokevirtual #34                 // Method getParameters:()Ljava/util/Map;
      12: astore        4
      14: aload_2
      15: ifnull        148
      18: aload_2
      19: arraylength
      20: ifeq          148
      23: aload         4
      25: invokeinterface #38,  1           // InterfaceMethod java/util/Map.entrySet:()Ljava/util/Set;
      30: invokeinterface #39,  1           // InterfaceMethod java/util/Set.iterator:()Ljava/util/Iterator;
      35: astore        5
      37: aload         5
      39: invokeinterface #40,  1           // InterfaceMethod java/util/Iterator.hasNext:()Z
      44: ifeq          148
      47: aload         5
      49: invokeinterface #41,  1           // InterfaceMethod java/util/Iterator.next:()Ljava/lang/Object;
      54: checkcast     #42                 // class java/util/Map$Entry
      57: astore        6
      59: aload_2
      60: astore        7
      62: aload         7
      64: arraylength
      65: istore        8
      67: iconst_0
      68: istore        9
      70: iload         9
      72: iload         8
      74: if_icmpge     145
      77: aload         7
      79: iload         9
      81: aaload
      82: astore        10
      84: aload         6
      86: invokeinterface #43,  1           // InterfaceMethod java/util/Map$Entry.getKey:()Ljava/lang/Object;
      91: checkcast     #35                 // class java/lang/String
      94: aload         10
      96: invokevirtual #44                 // Method java/lang/String.startsWith:(Ljava/lang/String;)Z
      99: ifeq          139
     102: aload         6
     104: invokeinterface #45,  1           // InterfaceMethod java/util/Map$Entry.getValue:()Ljava/lang/Object;
     109: checkcast     #35                 // class java/lang/String
     112: invokestatic  #18                 // Method org/apache/dubbo/common/utils/StringUtils.isNotEmpty:(Ljava/lang/String;)Z
     115: ifeq          139
     118: aload_3
     119: aload         6
     121: invokeinterface #43,  1           // InterfaceMethod java/util/Map$Entry.getKey:()Ljava/lang/Object;
     126: aload         6
     128: invokeinterface #45,  1           // InterfaceMethod java/util/Map$Entry.getValue:()Ljava/lang/Object;
     133: invokeinterface #28,  3           // InterfaceMethod java/util/Map.put:(Ljava/lang/Object;Ljava/lang/Object;)Ljava/lang/Object;
     138: pop
     139: iinc          9, 1
     142: goto          70
     145: goto          37
     148: aload_1
     149: ifnull        216
     152: aload_1
     153: astore        5
     155: aload         5
     157: arraylength
     158: istore        6
     160: iconst_0
     161: istore        7
     163: iload         7
     165: iload         6
     167: if_icmpge     216
     170: aload         5
     172: iload         7
     174: aaload
     175: astore        8
     177: aload         4
     179: aload         8
     181: invokeinterface #25,  2           // InterfaceMethod java/util/Map.get:(Ljava/lang/Object;)Ljava/lang/Object;
     186: checkcast     #35                 // class java/lang/String
     189: astore        9
     191: aload         9
     193: invokestatic  #18                 // Method org/apache/dubbo/common/utils/StringUtils.isNotEmpty:(Ljava/lang/String;)Z
     196: ifeq          210
     199: aload_3
     200: aload         8
     202: aload         9
     204: invokeinterface #28,  3           // InterfaceMethod java/util/Map.put:(Ljava/lang/Object;Ljava/lang/Object;)Ljava/lang/Object;
     209: pop
     210: iinc          7, 1
     213: goto          163
     216: aload_3
     217: invokeinterface #13,  1           // InterfaceMethod java/util/Map.isEmpty:()Z
     222: ifeq          267
     225: new           #46                 // class org/apache/dubbo/common/url/component/ServiceConfigURL
     228: dup
     229: aload_0
     230: invokevirtual #47                 // Method getProtocol:()Ljava/lang/String;
     233: aload_0
     234: invokevirtual #48                 // Method getUsername:()Ljava/lang/String;
     237: aload_0
     238: invokevirtual #49                 // Method getPassword:()Ljava/lang/String;
     241: aload_0
     242: invokevirtual #50                 // Method getHost:()Ljava/lang/String;
     245: aload_0
     246: invokevirtual #51                 // Method getPort:()I
     249: aload_0
     250: invokevirtual #52                 // Method getPath:()Ljava/lang/String;
     253: aconst_null
     254: checkcast     #14                 // class java/util/Map
     257: aload_0
     258: invokevirtual #53                 // Method getAttributes:()Ljava/util/Map;
     261: invokespecial #54                 // Method org/apache/dubbo/common/url/component/ServiceConfigURL."<init>":(Ljava/lang/String;Ljava/lang/String;Ljava/lang/String;Ljava/lang/String;ILjava/lang/String;Ljava/util/Map;Ljava/util/Map;)V
     264: goto          303
     267: new           #46                 // class org/apache/dubbo/common/url/component/ServiceConfigURL
     270: dup
     271: aload_0
     272: invokevirtual #47                 // Method getProtocol:()Ljava/lang/String;
     275: aload_0
     276: invokevirtual #48                 // Method getUsername:()Ljava/lang/String;
     279: aload_0
     280: invokevirtual #49                 // Method getPassword:()Ljava/lang/String;
     283: aload_0
     284: invokevirtual #50                 // Method getHost:()Ljava/lang/String;
     287: aload_0
     288: invokevirtual #51                 // Method getPort:()I
     291: aload_0
     292: invokevirtual #52                 // Method getPath:()Ljava/lang/String;
     295: aload_3
     296: aload_0
     297: invokevirtual #53                 // Method getAttributes:()Ljava/util/Map;
     300: invokespecial #54                 // Method org/apache/dubbo/common/url/component/ServiceConfigURL."<init>":(Ljava/lang/String;Ljava/lang/String;Ljava/lang/String;Ljava/lang/String;ILjava/lang/String;Ljava/util/Map;Ljava/util/Map;)V
     303: areturn

  public static java.lang.String encode(java.lang.String);
    Code:
       0: aload_0
       1: invokestatic  #17                 // Method org/apache/dubbo/common/utils/StringUtils.isEmpty:(Ljava/lang/String;)Z
       4: ifeq          10
       7: ldc           #55                 // String
       9: areturn
      10: aload_0
      11: ldc           #56                 // String UTF-8
      13: invokestatic  #57                 // Method java/net/URLEncoder.encode:(Ljava/lang/String;Ljava/lang/String;)Ljava/lang/String;
      16: areturn
      17: astore_1
      18: new           #59                 // class java/lang/RuntimeException
      21: dup
      22: aload_1
      23: invokevirtual #60                 // Method java/io/UnsupportedEncodingException.getMessage:()Ljava/lang/String;
      26: aload_1
      27: invokespecial #61                 // Method java/lang/RuntimeException."<init>":(Ljava/lang/String;Ljava/lang/Throwable;)V
      30: athrow
    Exception table:
       from    to  target type
          10    16    17   Class java/io/UnsupportedEncodingException

  public static java.lang.String decode(java.lang.String);
    Code:
       0: aload_0
       1: invokestatic  #17                 // Method org/apache/dubbo/common/utils/StringUtils.isEmpty:(Ljava/lang/String;)Z
       4: ifeq          10
       7: ldc           #55                 // String
       9: areturn
      10: aload_0
      11: ldc           #56                 // String UTF-8
      13: invokestatic  #62                 // Method java/net/URLDecoder.decode:(Ljava/lang/String;Ljava/lang/String;)Ljava/lang/String;
      16: areturn
      17: astore_1
      18: new           #59                 // class java/lang/RuntimeException
      21: dup
      22: aload_1
      23: invokevirtual #60                 // Method java/io/UnsupportedEncodingException.getMessage:()Ljava/lang/String;
      26: aload_1
      27: invokespecial #61                 // Method java/lang/RuntimeException."<init>":(Ljava/lang/String;Ljava/lang/Throwable;)V
      30: athrow
    Exception table:
       from    to  target type
          10    16    17   Class java/io/UnsupportedEncodingException

  static java.lang.String appendDefaultPort(java.lang.String, int);
    Code:
       0: aload_0
       1: ifnull        89
       4: aload_0
       5: invokevirtual #63                 // Method java/lang/String.length:()I
       8: ifle          89
      11: iload_1
      12: ifle          89
      15: aload_0
      16: bipush        58
      18: invokevirtual #64                 // Method java/lang/String.indexOf:(I)I
      21: istore_2
      22: iload_2
      23: ifge          50
      26: new           #65                 // class java/lang/StringBuilder
      29: dup
      30: invokespecial #66                 // Method java/lang/StringBuilder."<init>":()V
      33: aload_0
      34: invokevirtual #67                 // Method java/lang/StringBuilder.append:(Ljava/lang/String;)Ljava/lang/StringBuilder;
      37: ldc           #68                 // String :
      39: invokevirtual #67                 // Method java/lang/StringBuilder.append:(Ljava/lang/String;)Ljava/lang/StringBuilder;
      42: iload_1
      43: invokevirtual #69                 // Method java/lang/StringBuilder.append:(I)Ljava/lang/StringBuilder;
      46: invokevirtual #70                 // Method java/lang/StringBuilder.toString:()Ljava/lang/String;
      49: areturn
      50: aload_0
      51: iload_2
      52: iconst_1
      53: iadd
      54: invokevirtual #71                 // Method java/lang/String.substring:(I)Ljava/lang/String;
      57: invokestatic  #72                 // Method java/lang/Integer.parseInt:(Ljava/lang/String;)I
      60: ifne          89
      63: new           #65                 // class java/lang/StringBuilder
      66: dup
      67: invokespecial #66                 // Method java/lang/StringBuilder."<init>":()V
      70: aload_0
      71: iconst_0
      72: iload_2
      73: iconst_1
      74: iadd
      75: invokevirtual #73                 // Method java/lang/String.substring:(II)Ljava/lang/String;
      78: invokevirtual #67                 // Method java/lang/StringBuilder.append:(Ljava/lang/String;)Ljava/lang/StringBuilder;
      81: iload_1
      82: invokevirtual #69                 // Method java/lang/StringBuilder.append:(I)Ljava/lang/StringBuilder;
      85: invokevirtual #70                 // Method java/lang/StringBuilder.toString:()Ljava/lang/String;
      88: areturn
      89: aload_0
      90: areturn

  public org.apache.dubbo.common.url.component.URLAddress getUrlAddress();
    Code:
       0: aload_0
       1: getfield      #6                  // Field urlAddress:Lorg/apache/dubbo/common/url/component/URLAddress;
       4: areturn

  public org.apache.dubbo.common.url.component.URLParam getUrlParam();
    Code:
       0: aload_0
       1: getfield      #10                 // Field urlParam:Lorg/apache/dubbo/common/url/component/URLParam;
       4: areturn

  public java.lang.String getProtocol();
    Code:
       0: aload_0
       1: getfield      #6                  // Field urlAddress:Lorg/apache/dubbo/common/url/component/URLAddress;
       4: ifnonnull     11
       7: aconst_null
       8: goto          18
      11: aload_0
      12: getfield      #6                  // Field urlAddress:Lorg/apache/dubbo/common/url/component/URLAddress;
      15: invokevirtual #74                 // Method org/apache/dubbo/common/url/component/URLAddress.getProtocol:()Ljava/lang/String;
      18: areturn

  public org.apache.dubbo.common.URL setProtocol(java.lang.String);
    Code:
       0: aload_0
       1: getfield      #6                  // Field urlAddress:Lorg/apache/dubbo/common/url/component/URLAddress;
       4: ifnonnull     32
       7: new           #46                 // class org/apache/dubbo/common/url/component/ServiceConfigURL
      10: dup
      11: aload_1
      12: aload_0
      13: invokevirtual #50                 // Method getHost:()Ljava/lang/String;
      16: aload_0
      17: invokevirtual #51                 // Method getPort:()I
      20: aload_0
      21: invokevirtual #52                 // Method getPath:()Ljava/lang/String;
      24: aload_0
      25: invokevirtual #34                 // Method getParameters:()Ljava/util/Map;
      28: invokespecial #75                 // Method org/apache/dubbo/common/url/component/ServiceConfigURL."<init>":(Ljava/lang/String;Ljava/lang/String;ILjava/lang/String;Ljava/util/Map;)V
      31: areturn
      32: aload_0
      33: getfield      #6                  // Field urlAddress:Lorg/apache/dubbo/common/url/component/URLAddress;
      36: aload_1
      37: invokevirtual #76                 // Method org/apache/dubbo/common/url/component/URLAddress.setProtocol:(Ljava/lang/String;)Lorg/apache/dubbo/common/url/component/URLAddress;
      40: astore_2
      41: aload_0
      42: aload_2
      43: invokespecial #77                 // Method returnURL:(Lorg/apache/dubbo/common/url/component/URLAddress;)Lorg/apache/dubbo/common/URL;
      46: areturn

  public java.lang.String getUsername();
    Code:
       0: aload_0
       1: getfield      #6                  // Field urlAddress:Lorg/apache/dubbo/common/url/component/URLAddress;
       4: ifnonnull     11
       7: aconst_null
       8: goto          18
      11: aload_0
      12: getfield      #6                  // Field urlAddress:Lorg/apache/dubbo/common/url/component/URLAddress;
      15: invokevirtual #78                 // Method org/apache/dubbo/common/url/component/URLAddress.getUsername:()Ljava/lang/String;
      18: areturn

  public org.apache.dubbo.common.URL setUsername(java.lang.String);
    Code:
       0: aload_0
       1: getfield      #6                  // Field urlAddress:Lorg/apache/dubbo/common/url/component/URLAddress;
       4: ifnonnull     39
       7: new           #46                 // class org/apache/dubbo/common/url/component/ServiceConfigURL
      10: dup
      11: aload_0
      12: invokevirtual #47                 // Method getProtocol:()Ljava/lang/String;
      15: aload_0
      16: invokevirtual #50                 // Method getHost:()Ljava/lang/String;
      19: aload_0
      20: invokevirtual #51                 // Method getPort:()I
      23: aload_0
      24: invokevirtual #52                 // Method getPath:()Ljava/lang/String;
      27: aload_0
      28: invokevirtual #34                 // Method getParameters:()Ljava/util/Map;
      31: invokespecial #75                 // Method org/apache/dubbo/common/url/component/ServiceConfigURL."<init>":(Ljava/lang/String;Ljava/lang/String;ILjava/lang/String;Ljava/util/Map;)V
      34: aload_1
      35: invokevirtual #79                 // Method org/apache/dubbo/common/url/component/ServiceConfigURL.setUsername:(Ljava/lang/String;)Lorg/apache/dubbo/common/URL;
      38: areturn
      39: aload_0
      40: getfield      #6                  // Field urlAddress:Lorg/apache/dubbo/common/url/component/URLAddress;
      43: aload_1
      44: invokevirtual #80                 // Method org/apache/dubbo/common/url/component/URLAddress.setUsername:(Ljava/lang/String;)Lorg/apache/dubbo/common/url/component/URLAddress;
      47: astore_2
      48: aload_0
      49: aload_2
      50: invokespecial #77                 // Method returnURL:(Lorg/apache/dubbo/common/url/component/URLAddress;)Lorg/apache/dubbo/common/URL;
      53: areturn

  public java.lang.String getPassword();
    Code:
       0: aload_0
       1: getfield      #6                  // Field urlAddress:Lorg/apache/dubbo/common/url/component/URLAddress;
       4: ifnonnull     11
       7: aconst_null
       8: goto          18
      11: aload_0
      12: getfield      #6                  // Field urlAddress:Lorg/apache/dubbo/common/url/component/URLAddress;
      15: invokevirtual #81                 // Method org/apache/dubbo/common/url/component/URLAddress.getPassword:()Ljava/lang/String;
      18: areturn

  public org.apache.dubbo.common.URL setPassword(java.lang.String);
    Code:
       0: aload_0
       1: getfield      #6                  // Field urlAddress:Lorg/apache/dubbo/common/url/component/URLAddress;
       4: ifnonnull     39
       7: new           #46                 // class org/apache/dubbo/common/url/component/ServiceConfigURL
      10: dup
      11: aload_0
      12: invokevirtual #47                 // Method getProtocol:()Ljava/lang/String;
      15: aload_0
      16: invokevirtual #50                 // Method getHost:()Ljava/lang/String;
      19: aload_0
      20: invokevirtual #51                 // Method getPort:()I
      23: aload_0
      24: invokevirtual #52                 // Method getPath:()Ljava/lang/String;
      27: aload_0
      28: invokevirtual #34                 // Method getParameters:()Ljava/util/Map;
      31: invokespecial #75                 // Method org/apache/dubbo/common/url/component/ServiceConfigURL."<init>":(Ljava/lang/String;Ljava/lang/String;ILjava/lang/String;Ljava/util/Map;)V
      34: aload_1
      35: invokevirtual #82                 // Method org/apache/dubbo/common/url/component/ServiceConfigURL.setPassword:(Ljava/lang/String;)Lorg/apache/dubbo/common/URL;
      38: areturn
      39: aload_0
      40: getfield      #6                  // Field urlAddress:Lorg/apache/dubbo/common/url/component/URLAddress;
      43: aload_1
      44: invokevirtual #83                 // Method org/apache/dubbo/common/url/component/URLAddress.setPassword:(Ljava/lang/String;)Lorg/apache/dubbo/common/url/component/URLAddress;
      47: astore_2
      48: aload_0
      49: aload_2
      50: invokespecial #77                 // Method returnURL:(Lorg/apache/dubbo/common/url/component/URLAddress;)Lorg/apache/dubbo/common/URL;
      53: areturn

  public java.lang.String getAuthority();
    Code:
       0: new           #65                 // class java/lang/StringBuilder
       3: dup
       4: invokespecial #66                 // Method java/lang/StringBuilder."<init>":()V
       7: astore_1
       8: aload_1
       9: aload_0
      10: invokevirtual #84                 // Method getUserInformation:()Ljava/lang/String;
      13: invokevirtual #67                 // Method java/lang/StringBuilder.append:(Ljava/lang/String;)Ljava/lang/StringBuilder;
      16: pop
      17: aload_0
      18: invokevirtual #50                 // Method getHost:()Ljava/lang/String;
      21: invokestatic  #18                 // Method org/apache/dubbo/common/utils/StringUtils.isNotEmpty:(Ljava/lang/String;)Z
      24: ifeq          86
      27: aload_0
      28: invokevirtual #48                 // Method getUsername:()Ljava/lang/String;
      31: invokestatic  #18                 // Method org/apache/dubbo/common/utils/StringUtils.isNotEmpty:(Ljava/lang/String;)Z
      34: ifne          47
      37: aload_0
      38: invokevirtual #49                 // Method getPassword:()Ljava/lang/String;
      41: invokestatic  #18                 // Method org/apache/dubbo/common/utils/StringUtils.isNotEmpty:(Ljava/lang/String;)Z
      44: ifeq          54
      47: aload_1
      48: bipush        64
      50: invokevirtual #85                 // Method java/lang/StringBuilder.append:(C)Ljava/lang/StringBuilder;
      53: pop
      54: aload_1
      55: aload_0
      56: invokevirtual #50                 // Method getHost:()Ljava/lang/String;
      59: invokevirtual #67                 // Method java/lang/StringBuilder.append:(Ljava/lang/String;)Ljava/lang/StringBuilder;
      62: pop
      63: aload_0
      64: invokevirtual #51                 // Method getPort:()I
      67: ifeq          86
      70: aload_1
      71: bipush        58
      73: invokevirtual #85                 // Method java/lang/StringBuilder.append:(C)Ljava/lang/StringBuilder;
      76: pop
      77: aload_1
      78: aload_0
      79: invokevirtual #51                 // Method getPort:()I
      82: invokevirtual #69                 // Method java/lang/StringBuilder.append:(I)Ljava/lang/StringBuilder;
      85: pop
      86: aload_1
      87: invokevirtual #86                 // Method java/lang/StringBuilder.length:()I
      90: ifne          97
      93: aconst_null
      94: goto          101
      97: aload_1
      98: invokevirtual #70                 // Method java/lang/StringBuilder.toString:()Ljava/lang/String;
     101: areturn

  public java.lang.String getUserInformation();
    Code:
       0: new           #65                 // class java/lang/StringBuilder
       3: dup
       4: invokespecial #66                 // Method java/lang/StringBuilder."<init>":()V
       7: astore_1
       8: aload_0
       9: invokevirtual #48                 // Method getUsername:()Ljava/lang/String;
      12: invokestatic  #17                 // Method org/apache/dubbo/common/utils/StringUtils.isEmpty:(Ljava/lang/String;)Z
      15: ifeq          33
      18: aload_0
      19: invokevirtual #49                 // Method getPassword:()Ljava/lang/String;
      22: invokestatic  #17                 // Method org/apache/dubbo/common/utils/StringUtils.isEmpty:(Ljava/lang/String;)Z
      25: ifeq          33
      28: aload_1
      29: invokevirtual #70                 // Method java/lang/StringBuilder.toString:()Ljava/lang/String;
      32: areturn
      33: aload_0
      34: invokevirtual #48                 // Method getUsername:()Ljava/lang/String;
      37: invokestatic  #18                 // Method org/apache/dubbo/common/utils/StringUtils.isNotEmpty:(Ljava/lang/String;)Z
      40: ifeq          52
      43: aload_1
      44: aload_0
      45: invokevirtual #48                 // Method getUsername:()Ljava/lang/String;
      48: invokevirtual #67                 // Method java/lang/StringBuilder.append:(Ljava/lang/String;)Ljava/lang/StringBuilder;
      51: pop
      52: aload_1
      53: bipush        58
      55: invokevirtual #85                 // Method java/lang/StringBuilder.append:(C)Ljava/lang/StringBuilder;
      58: pop
      59: aload_0
      60: invokevirtual #49                 // Method getPassword:()Ljava/lang/String;
      63: invokestatic  #18                 // Method org/apache/dubbo/common/utils/StringUtils.isNotEmpty:(Ljava/lang/String;)Z
      66: ifeq          78
      69: aload_1
      70: aload_0
      71: invokevirtual #49                 // Method getPassword:()Ljava/lang/String;
      74: invokevirtual #67                 // Method java/lang/StringBuilder.append:(Ljava/lang/String;)Ljava/lang/StringBuilder;
      77: pop
      78: aload_1
      79: invokevirtual #86                 // Method java/lang/StringBuilder.length:()I
      82: ifne          89
      85: aconst_null
      86: goto          93
      89: aload_1
      90: invokevirtual #70                 // Method java/lang/StringBuilder.toString:()Ljava/lang/String;
      93: areturn

  public java.lang.String getHost();
    Code:
       0: aload_0
       1: getfield      #6                  // Field urlAddress:Lorg/apache/dubbo/common/url/component/URLAddress;
       4: ifnonnull     11
       7: aconst_null
       8: goto          18
      11: aload_0
      12: getfield      #6                  // Field urlAddress:Lorg/apache/dubbo/common/url/component/URLAddress;
      15: invokevirtual #87                 // Method org/apache/dubbo/common/url/component/URLAddress.getHost:()Ljava/lang/String;
      18: areturn

  public org.apache.dubbo.common.URL setHost(java.lang.String);
    Code:
       0: aload_0
       1: getfield      #6                  // Field urlAddress:Lorg/apache/dubbo/common/url/component/URLAddress;
       4: ifnonnull     32
       7: new           #46                 // class org/apache/dubbo/common/url/component/ServiceConfigURL
      10: dup
      11: aload_0
      12: invokevirtual #47                 // Method getProtocol:()Ljava/lang/String;
      15: aload_1
      16: aload_0
      17: invokevirtual #51                 // Method getPort:()I
      20: aload_0
      21: invokevirtual #52                 // Method getPath:()Ljava/lang/String;
      24: aload_0
      25: invokevirtual #34                 // Method getParameters:()Ljava/util/Map;
      28: invokespecial #75                 // Method org/apache/dubbo/common/url/component/ServiceConfigURL."<init>":(Ljava/lang/String;Ljava/lang/String;ILjava/lang/String;Ljava/util/Map;)V
      31: areturn
      32: aload_0
      33: getfield      #6                  // Field urlAddress:Lorg/apache/dubbo/common/url/component/URLAddress;
      36: aload_1
      37: invokevirtual #88                 // Method org/apache/dubbo/common/url/component/URLAddress.setHost:(Ljava/lang/String;)Lorg/apache/dubbo/common/url/component/URLAddress;
      40: astore_2
      41: aload_0
      42: aload_2
      43: invokespecial #77                 // Method returnURL:(Lorg/apache/dubbo/common/url/component/URLAddress;)Lorg/apache/dubbo/common/URL;
      46: areturn

  public int getPort();
    Code:
       0: aload_0
       1: getfield      #6                  // Field urlAddress:Lorg/apache/dubbo/common/url/component/URLAddress;
       4: ifnonnull     11
       7: iconst_0
       8: goto          18
      11: aload_0
      12: getfield      #6                  // Field urlAddress:Lorg/apache/dubbo/common/url/component/URLAddress;
      15: invokevirtual #89                 // Method org/apache/dubbo/common/url/component/URLAddress.getPort:()I
      18: ireturn

  public org.apache.dubbo.common.URL setPort(int);
    Code:
       0: aload_0
       1: getfield      #6                  // Field urlAddress:Lorg/apache/dubbo/common/url/component/URLAddress;
       4: ifnonnull     32
       7: new           #46                 // class org/apache/dubbo/common/url/component/ServiceConfigURL
      10: dup
      11: aload_0
      12: invokevirtual #47                 // Method getProtocol:()Ljava/lang/String;
      15: aload_0
      16: invokevirtual #50                 // Method getHost:()Ljava/lang/String;
      19: iload_1
      20: aload_0
      21: invokevirtual #52                 // Method getPath:()Ljava/lang/String;
      24: aload_0
      25: invokevirtual #34                 // Method getParameters:()Ljava/util/Map;
      28: invokespecial #75                 // Method org/apache/dubbo/common/url/component/ServiceConfigURL."<init>":(Ljava/lang/String;Ljava/lang/String;ILjava/lang/String;Ljava/util/Map;)V
      31: areturn
      32: aload_0
      33: getfield      #6                  // Field urlAddress:Lorg/apache/dubbo/common/url/component/URLAddress;
      36: iload_1
      37: invokevirtual #90                 // Method org/apache/dubbo/common/url/component/URLAddress.setPort:(I)Lorg/apache/dubbo/common/url/component/URLAddress;
      40: astore_2
      41: aload_0
      42: aload_2
      43: invokespecial #77                 // Method returnURL:(Lorg/apache/dubbo/common/url/component/URLAddress;)Lorg/apache/dubbo/common/URL;
      46: areturn

  public int getPort(int);
    Code:
       0: aload_0
       1: invokevirtual #51                 // Method getPort:()I
       4: istore_2
       5: iload_2
       6: ifgt          13
       9: iload_1
      10: goto          14
      13: iload_2
      14: ireturn

  public java.lang.String getAddress();
    Code:
       0: aload_0
       1: getfield      #6                  // Field urlAddress:Lorg/apache/dubbo/common/url/component/URLAddress;
       4: ifnonnull     11
       7: aconst_null
       8: goto          18
      11: aload_0
      12: getfield      #6                  // Field urlAddress:Lorg/apache/dubbo/common/url/component/URLAddress;
      15: invokevirtual #91                 // Method org/apache/dubbo/common/url/component/URLAddress.getAddress:()Ljava/lang/String;
      18: areturn

  public org.apache.dubbo.common.URL setAddress(java.lang.String);
    Code:
       0: aload_1
       1: bipush        58
       3: invokevirtual #92                 // Method java/lang/String.lastIndexOf:(I)I
       6: istore_2
       7: aload_0
       8: invokevirtual #51                 // Method getPort:()I
      11: istore        4
      13: iload_2
      14: iflt          39
      17: aload_1
      18: iconst_0
      19: iload_2
      20: invokevirtual #73                 // Method java/lang/String.substring:(II)Ljava/lang/String;
      23: astore_3
      24: aload_1
      25: iload_2
      26: iconst_1
      27: iadd
      28: invokevirtual #71                 // Method java/lang/String.substring:(I)Ljava/lang/String;
      31: invokestatic  #72                 // Method java/lang/Integer.parseInt:(Ljava/lang/String;)I
      34: istore        4
      36: goto          41
      39: aload_1
      40: astore_3
      41: aload_0
      42: getfield      #6                  // Field urlAddress:Lorg/apache/dubbo/common/url/component/URLAddress;
      45: ifnonnull     71
      48: new           #46                 // class org/apache/dubbo/common/url/component/ServiceConfigURL
      51: dup
      52: aload_0
      53: invokevirtual #47                 // Method getProtocol:()Ljava/lang/String;
      56: aload_3
      57: iload         4
      59: aload_0
      60: invokevirtual #52                 // Method getPath:()Ljava/lang/String;
      63: aload_0
      64: invokevirtual #34                 // Method getParameters:()Ljava/util/Map;
      67: invokespecial #75                 // Method org/apache/dubbo/common/url/component/ServiceConfigURL."<init>":(Ljava/lang/String;Ljava/lang/String;ILjava/lang/String;Ljava/util/Map;)V
      70: areturn
      71: aload_0
      72: getfield      #6                  // Field urlAddress:Lorg/apache/dubbo/common/url/component/URLAddress;
      75: aload_3
      76: iload         4
      78: invokevirtual #93                 // Method org/apache/dubbo/common/url/component/URLAddress.setAddress:(Ljava/lang/String;I)Lorg/apache/dubbo/common/url/component/URLAddress;
      81: astore        5
      83: aload_0
      84: aload         5
      86: invokespecial #77                 // Method returnURL:(Lorg/apache/dubbo/common/url/component/URLAddress;)Lorg/apache/dubbo/common/URL;
      89: areturn

  public java.lang.String getIp();
    Code:
       0: aload_0
       1: getfield      #6                  // Field urlAddress:Lorg/apache/dubbo/common/url/component/URLAddress;
       4: ifnonnull     11
       7: aconst_null
       8: goto          18
      11: aload_0
      12: getfield      #6                  // Field urlAddress:Lorg/apache/dubbo/common/url/component/URLAddress;
      15: invokevirtual #94                 // Method org/apache/dubbo/common/url/component/URLAddress.getIp:()Ljava/lang/String;
      18: areturn

  public java.lang.String getBackupAddress();
    Code:
       0: aload_0
       1: iconst_0
       2: invokevirtual #95                 // Method getBackupAddress:(I)Ljava/lang/String;
       5: areturn

  public java.lang.String getBackupAddress(int);
    Code:
       0: new           #65                 // class java/lang/StringBuilder
       3: dup
       4: aload_0
       5: invokevirtual #96                 // Method getAddress:()Ljava/lang/String;
       8: iload_1
       9: invokestatic  #97                 // Method appendDefaultPort:(Ljava/lang/String;I)Ljava/lang/String;
      12: invokespecial #98                 // Method java/lang/StringBuilder."<init>":(Ljava/lang/String;)V
      15: astore_2
      16: aload_0
      17: ldc           #100                // String backup
      19: iconst_0
      20: anewarray     #35                 // class java/lang/String
      23: invokevirtual #101                // Method getParameter:(Ljava/lang/String;[Ljava/lang/String;)[Ljava/lang/String;
      26: astore_3
      27: aload_3
      28: invokestatic  #102                // Method org/apache/dubbo/common/utils/ArrayUtils.isNotEmpty:([Ljava/lang/Object;)Z
      31: ifeq          83
      34: aload_3
      35: astore        4
      37: aload         4
      39: arraylength
      40: istore        5
      42: iconst_0
      43: istore        6
      45: iload         6
      47: iload         5
      49: if_icmpge     83
      52: aload         4
      54: iload         6
      56: aaload
      57: astore        7
      59: aload_2
      60: bipush        44
      62: invokevirtual #85                 // Method java/lang/StringBuilder.append:(C)Ljava/lang/StringBuilder;
      65: pop
      66: aload_2
      67: aload         7
      69: iload_1
      70: invokestatic  #97                 // Method appendDefaultPort:(Ljava/lang/String;I)Ljava/lang/String;
      73: invokevirtual #67                 // Method java/lang/StringBuilder.append:(Ljava/lang/String;)Ljava/lang/StringBuilder;
      76: pop
      77: iinc          6, 1
      80: goto          45
      83: aload_2
      84: invokevirtual #70                 // Method java/lang/StringBuilder.toString:()Ljava/lang/String;
      87: areturn

  public java.util.List<org.apache.dubbo.common.URL> getBackupUrls();
    Code:
       0: new           #103                // class java/util/ArrayList
       3: dup
       4: invokespecial #104                // Method java/util/ArrayList."<init>":()V
       7: astore_1
       8: aload_1
       9: aload_0
      10: invokeinterface #105,  2          // InterfaceMethod java/util/List.add:(Ljava/lang/Object;)Z
      15: pop
      16: aload_0
      17: ldc           #100                // String backup
      19: iconst_0
      20: anewarray     #35                 // class java/lang/String
      23: invokevirtual #101                // Method getParameter:(Ljava/lang/String;[Ljava/lang/String;)[Ljava/lang/String;
      26: astore_2
      27: aload_2
      28: ifnull        77
      31: aload_2
      32: arraylength
      33: ifle          77
      36: aload_2
      37: astore_3
      38: aload_3
      39: arraylength
      40: istore        4
      42: iconst_0
      43: istore        5
      45: iload         5
      47: iload         4
      49: if_icmpge     77
      52: aload_3
      53: iload         5
      55: aaload
      56: astore        6
      58: aload_1
      59: aload_0
      60: aload         6
      62: invokevirtual #106                // Method setAddress:(Ljava/lang/String;)Lorg/apache/dubbo/common/URL;
      65: invokeinterface #105,  2          // InterfaceMethod java/util/List.add:(Ljava/lang/Object;)Z
      70: pop
      71: iinc          5, 1
      74: goto          45
      77: aload_1
      78: areturn

  public java.lang.String getPath();
    Code:
       0: aload_0
       1: getfield      #6                  // Field urlAddress:Lorg/apache/dubbo/common/url/component/URLAddress;
       4: ifnonnull     11
       7: aconst_null
       8: goto          18
      11: aload_0
      12: getfield      #6                  // Field urlAddress:Lorg/apache/dubbo/common/url/component/URLAddress;
      15: invokevirtual #107                // Method org/apache/dubbo/common/url/component/URLAddress.getPath:()Ljava/lang/String;
      18: areturn

  public org.apache.dubbo.common.URL setPath(java.lang.String);
    Code:
       0: aload_0
       1: getfield      #6                  // Field urlAddress:Lorg/apache/dubbo/common/url/component/URLAddress;
       4: ifnonnull     32
       7: new           #46                 // class org/apache/dubbo/common/url/component/ServiceConfigURL
      10: dup
      11: aload_0
      12: invokevirtual #47                 // Method getProtocol:()Ljava/lang/String;
      15: aload_0
      16: invokevirtual #50                 // Method getHost:()Ljava/lang/String;
      19: aload_0
      20: invokevirtual #51                 // Method getPort:()I
      23: aload_1
      24: aload_0
      25: invokevirtual #34                 // Method getParameters:()Ljava/util/Map;
      28: invokespecial #75                 // Method org/apache/dubbo/common/url/component/ServiceConfigURL."<init>":(Ljava/lang/String;Ljava/lang/String;ILjava/lang/String;Ljava/util/Map;)V
      31: areturn
      32: aload_0
      33: getfield      #6                  // Field urlAddress:Lorg/apache/dubbo/common/url/component/URLAddress;
      36: aload_1
      37: invokevirtual #108                // Method org/apache/dubbo/common/url/component/URLAddress.setPath:(Ljava/lang/String;)Lorg/apache/dubbo/common/url/component/URLAddress;
      40: astore_2
      41: aload_0
      42: aload_2
      43: invokespecial #77                 // Method returnURL:(Lorg/apache/dubbo/common/url/component/URLAddress;)Lorg/apache/dubbo/common/URL;
      46: areturn

  public java.lang.String getAbsolutePath();
    Code:
       0: aload_0
       1: invokevirtual #52                 // Method getPath:()Ljava/lang/String;
       4: astore_1
       5: aload_1
       6: ifnull        38
       9: aload_1
      10: ldc           #109                // String /
      12: invokevirtual #44                 // Method java/lang/String.startsWith:(Ljava/lang/String;)Z
      15: ifne          38
      18: new           #65                 // class java/lang/StringBuilder
      21: dup
      22: invokespecial #66                 // Method java/lang/StringBuilder."<init>":()V
      25: ldc           #109                // String /
      27: invokevirtual #67                 // Method java/lang/StringBuilder.append:(Ljava/lang/String;)Ljava/lang/StringBuilder;
      30: aload_1
      31: invokevirtual #67                 // Method java/lang/StringBuilder.append:(Ljava/lang/String;)Ljava/lang/StringBuilder;
      34: invokevirtual #70                 // Method java/lang/StringBuilder.toString:()Ljava/lang/String;
      37: areturn
      38: aload_1
      39: areturn

  public java.util.Map<java.lang.String, java.lang.String> getOriginalParameters();
    Code:
       0: aload_0
       1: invokevirtual #34                 // Method getParameters:()Ljava/util/Map;
       4: areturn

  public java.util.Map<java.lang.String, java.lang.String> getParameters();
    Code:
       0: aload_0
       1: getfield      #10                 // Field urlParam:Lorg/apache/dubbo/common/url/component/URLParam;
       4: invokevirtual #110                // Method org/apache/dubbo/common/url/component/URLParam.getParameters:()Ljava/util/Map;
       7: areturn

  public java.util.Map<java.lang.String, java.lang.String> getAllParameters();
    Code:
       0: aload_0
       1: invokevirtual #34                 // Method getParameters:()Ljava/util/Map;
       4: areturn

  public java.util.Map<java.lang.String, java.lang.String> getParameters(java.util.function.Predicate<java.lang.String>);
    Code:
       0: new           #111                // class java/util/LinkedHashMap
       3: dup
       4: invokespecial #112                // Method java/util/LinkedHashMap."<init>":()V
       7: astore_2
       8: aload_0
       9: invokevirtual #34                 // Method getParameters:()Ljava/util/Map;
      12: invokeinterface #38,  1           // InterfaceMethod java/util/Map.entrySet:()Ljava/util/Set;
      17: invokeinterface #39,  1           // InterfaceMethod java/util/Set.iterator:()Ljava/util/Iterator;
      22: astore_3
      23: aload_3
      24: invokeinterface #40,  1           // InterfaceMethod java/util/Iterator.hasNext:()Z
      29: ifeq          85
      32: aload_3
      33: invokeinterface #41,  1           // InterfaceMethod java/util/Iterator.next:()Ljava/lang/Object;
      38: checkcast     #42                 // class java/util/Map$Entry
      41: astore        4
      43: aload         4
      45: invokeinterface #43,  1           // InterfaceMethod java/util/Map$Entry.getKey:()Ljava/lang/Object;
      50: checkcast     #35                 // class java/lang/String
      53: astore        5
      55: aload_1
      56: aload         5
      58: invokeinterface #113,  2          // InterfaceMethod java/util/function/Predicate.test:(Ljava/lang/Object;)Z
      63: ifeq          82
      66: aload_2
      67: aload         5
      69: aload         4
      71: invokeinterface #45,  1           // InterfaceMethod java/util/Map$Entry.getValue:()Ljava/lang/Object;
      76: invokeinterface #28,  3           // InterfaceMethod java/util/Map.put:(Ljava/lang/Object;Ljava/lang/Object;)Ljava/lang/Object;
      81: pop
      82: goto          23
      85: aload_2
      86: invokestatic  #114                // Method java/util/Collections.unmodifiableMap:(Ljava/util/Map;)Ljava/util/Map;
      89: areturn

  public java.lang.String getParameterAndDecoded(java.lang.String);
    Code:
       0: aload_0
       1: aload_1
       2: aconst_null
       3: invokevirtual #115                // Method getParameterAndDecoded:(Ljava/lang/String;Ljava/lang/String;)Ljava/lang/String;
       6: areturn

  public java.lang.String getParameterAndDecoded(java.lang.String, java.lang.String);
    Code:
       0: aload_0
       1: aload_1
       2: aload_2
       3: invokevirtual #116                // Method getParameter:(Ljava/lang/String;Ljava/lang/String;)Ljava/lang/String;
       6: invokestatic  #117                // Method decode:(Ljava/lang/String;)Ljava/lang/String;
       9: areturn

  public java.lang.String getOriginalParameter(java.lang.String);
    Code:
       0: aload_0
       1: aload_1
       2: invokevirtual #118                // Method getParameter:(Ljava/lang/String;)Ljava/lang/String;
       5: areturn

  public java.lang.String getParameter(java.lang.String);
    Code:
       0: aload_0
       1: getfield      #10                 // Field urlParam:Lorg/apache/dubbo/common/url/component/URLParam;
       4: aload_1
       5: invokevirtual #119                // Method org/apache/dubbo/common/url/component/URLParam.getParameter:(Ljava/lang/String;)Ljava/lang/String;
       8: areturn

  public java.lang.String getParameter(java.lang.String, java.lang.String);
    Code:
       0: aload_0
       1: aload_1
       2: invokevirtual #118                // Method getParameter:(Ljava/lang/String;)Ljava/lang/String;
       5: astore_3
       6: aload_3
       7: invokestatic  #17                 // Method org/apache/dubbo/common/utils/StringUtils.isEmpty:(Ljava/lang/String;)Z
      10: ifeq          17
      13: aload_2
      14: goto          18
      17: aload_3
      18: areturn

  public java.lang.String[] getParameter(java.lang.String, java.lang.String[]);
    Code:
       0: aload_0
       1: aload_1
       2: invokevirtual #118                // Method getParameter:(Ljava/lang/String;)Ljava/lang/String;
       5: astore_3
       6: aload_3
       7: invokestatic  #17                 // Method org/apache/dubbo/common/utils/StringUtils.isEmpty:(Ljava/lang/String;)Z
      10: ifeq          17
      13: aload_2
      14: goto          24
      17: getstatic     #120                // Field org/apache/dubbo/common/constants/CommonConstants.COMMA_SPLIT_PATTERN:Ljava/util/regex/Pattern;
      20: aload_3
      21: invokevirtual #121                // Method java/util/regex/Pattern.split:(Ljava/lang/CharSequence;)[Ljava/lang/String;
      24: areturn

  public java.util.List<java.lang.String> getParameter(java.lang.String, java.util.List<java.lang.String>);
    Code:
       0: aload_0
       1: aload_1
       2: invokevirtual #118                // Method getParameter:(Ljava/lang/String;)Ljava/lang/String;
       5: astore_3
       6: aload_3
       7: invokestatic  #17                 // Method org/apache/dubbo/common/utils/StringUtils.isEmpty:(Ljava/lang/String;)Z
      10: ifeq          15
      13: aload_2
      14: areturn
      15: getstatic     #120                // Field org/apache/dubbo/common/constants/CommonConstants.COMMA_SPLIT_PATTERN:Ljava/util/regex/Pattern;
      18: aload_3
      19: invokevirtual #121                // Method java/util/regex/Pattern.split:(Ljava/lang/CharSequence;)[Ljava/lang/String;
      22: astore        4
      24: aload         4
      26: invokestatic  #122                // Method java/util/Arrays.asList:([Ljava/lang/Object;)Ljava/util/List;
      29: areturn

  public <T> T getParameter(java.lang.String, java.lang.Class<T>);
    Code:
       0: aload_0
       1: aload_1
       2: aload_2
       3: aconst_null
       4: invokevirtual #123                // Method getParameter:(Ljava/lang/String;Ljava/lang/Class;Ljava/lang/Object;)Ljava/lang/Object;
       7: areturn

  public <T> T getParameter(java.lang.String, java.lang.Class<T>, T);
    Code:
       0: aload_0
       1: aload_1
       2: invokevirtual #118                // Method getParameter:(Ljava/lang/String;)Ljava/lang/String;
       5: astore        4
       7: aconst_null
       8: astore        5
      10: aload         4
      12: invokestatic  #124                // Method org/apache/dubbo/common/utils/StringUtils.isBlank:(Ljava/lang/CharSequence;)Z
      15: ifne          41
      18: aload_0
      19: invokevirtual #125                // Method getOrDefaultFrameworkModel:()Lorg/apache/dubbo/rpc/model/FrameworkModel;
      22: invokevirtual #126                // Method org/apache/dubbo/rpc/model/FrameworkModel.getBeanFactory:()Lorg/apache/dubbo/common/beans/factory/ScopeBeanFactory;
      25: ldc           #127                // class org/apache/dubbo/common/convert/ConverterUtil
      27: invokevirtual #128                // Method org/apache/dubbo/common/beans/factory/ScopeBeanFactory.getBean:(Ljava/lang/Class;)Ljava/lang/Object;
      30: checkcast     #127                // class org/apache/dubbo/common/convert/ConverterUtil
      33: aload         4
      35: aload_2
      36: invokevirtual #129                // Method org/apache/dubbo/common/convert/ConverterUtil.convertIfPossible:(Ljava/lang/Object;Ljava/lang/Class;)Ljava/lang/Object;
      39: astore        5
      41: aload         5
      43: ifnonnull     49
      46: aload_3
      47: astore        5
      49: aload         5
      51: areturn

  public org.apache.dubbo.common.URL setScopeModel(org.apache.dubbo.rpc.model.ScopeModel);
    Code:
       0: aload_0
       1: ldc           #130                // String scopeModel
       3: aload_1
       4: invokevirtual #131                // Method putAttribute:(Ljava/lang/String;Ljava/lang/Object;)Lorg/apache/dubbo/common/URL;
       7: areturn

  public org.apache.dubbo.rpc.model.ScopeModel getScopeModel();
    Code:
       0: aload_0
       1: ldc           #130                // String scopeModel
       3: invokevirtual #132                // Method getAttribute:(Ljava/lang/String;)Ljava/lang/Object;
       6: checkcast     #133                // class org/apache/dubbo/rpc/model/ScopeModel
       9: areturn

  public org.apache.dubbo.rpc.model.FrameworkModel getOrDefaultFrameworkModel();
    Code:
       0: aload_0
       1: invokevirtual #134                // Method getScopeModel:()Lorg/apache/dubbo/rpc/model/ScopeModel;
       4: invokestatic  #135                // Method org/apache/dubbo/rpc/model/ScopeModelUtil.getFrameworkModel:(Lorg/apache/dubbo/rpc/model/ScopeModel;)Lorg/apache/dubbo/rpc/model/FrameworkModel;
       7: areturn

  public org.apache.dubbo.rpc.model.ApplicationModel getOrDefaultApplicationModel();
    Code:
       0: aload_0
       1: invokevirtual #134                // Method getScopeModel:()Lorg/apache/dubbo/rpc/model/ScopeModel;
       4: invokestatic  #136                // Method org/apache/dubbo/rpc/model/ScopeModelUtil.getApplicationModel:(Lorg/apache/dubbo/rpc/model/ScopeModel;)Lorg/apache/dubbo/rpc/model/ApplicationModel;
       7: areturn

  public org.apache.dubbo.rpc.model.ApplicationModel getApplicationModel();
    Code:
       0: aload_0
       1: invokevirtual #134                // Method getScopeModel:()Lorg/apache/dubbo/rpc/model/ScopeModel;
       4: invokestatic  #137                // Method org/apache/dubbo/rpc/model/ScopeModelUtil.getOrNullApplicationModel:(Lorg/apache/dubbo/rpc/model/ScopeModel;)Lorg/apache/dubbo/rpc/model/ApplicationModel;
       7: areturn

  public org.apache.dubbo.rpc.model.ModuleModel getOrDefaultModuleModel();
    Code:
       0: aload_0
       1: invokevirtual #134                // Method getScopeModel:()Lorg/apache/dubbo/rpc/model/ScopeModel;
       4: invokestatic  #138                // Method org/apache/dubbo/rpc/model/ScopeModelUtil.getModuleModel:(Lorg/apache/dubbo/rpc/model/ScopeModel;)Lorg/apache/dubbo/rpc/model/ModuleModel;
       7: areturn

  public org.apache.dubbo.common.URL setServiceModel(org.apache.dubbo.rpc.model.ServiceModel);
    Code:
       0: aload_0
       1: ldc           #139                // String serviceModel
       3: aload_1
       4: invokevirtual #131                // Method putAttribute:(Ljava/lang/String;Ljava/lang/Object;)Lorg/apache/dubbo/common/URL;
       7: areturn

  public org.apache.dubbo.rpc.model.ServiceModel getServiceModel();
    Code:
       0: aload_0
       1: ldc           #139                // String serviceModel
       3: invokevirtual #132                // Method getAttribute:(Ljava/lang/String;)Ljava/lang/Object;
       6: checkcast     #140                // class org/apache/dubbo/rpc/model/ServiceModel
       9: areturn

  public org.apache.dubbo.common.URL getUrlParameter(java.lang.String);
    Code:
       0: aload_0
       1: aload_1
       2: invokevirtual #141                // Method getParameterAndDecoded:(Ljava/lang/String;)Ljava/lang/String;
       5: astore_2
       6: aload_2
       7: invokestatic  #17                 // Method org/apache/dubbo/common/utils/StringUtils.isEmpty:(Ljava/lang/String;)Z
      10: ifeq          15
      13: aconst_null
      14: areturn
      15: aload_2
      16: invokestatic  #29                 // Method valueOf:(Ljava/lang/String;)Lorg/apache/dubbo/common/URL;
      19: areturn

  public double getParameter(java.lang.String, double);
    Code:
       0: aload_0
       1: aload_1
       2: invokevirtual #118                // Method getParameter:(Ljava/lang/String;)Ljava/lang/String;
       5: astore        4
       7: aload         4
       9: invokestatic  #17                 // Method org/apache/dubbo/common/utils/StringUtils.isEmpty:(Ljava/lang/String;)Z
      12: ifeq          17
      15: dload_2
      16: dreturn
      17: aload         4
      19: invokestatic  #142                // Method java/lang/Double.parseDouble:(Ljava/lang/String;)D
      22: dreturn

  public float getParameter(java.lang.String, float);
    Code:
       0: aload_0
       1: aload_1
       2: invokevirtual #118                // Method getParameter:(Ljava/lang/String;)Ljava/lang/String;
       5: astore_3
       6: aload_3
       7: invokestatic  #17                 // Method org/apache/dubbo/common/utils/StringUtils.isEmpty:(Ljava/lang/String;)Z
      10: ifeq          15
      13: fload_2
      14: freturn
      15: aload_3
      16: invokestatic  #143                // Method java/lang/Float.parseFloat:(Ljava/lang/String;)F
      19: freturn

  public long getParameter(java.lang.String, long);
    Code:
       0: aload_0
       1: aload_1
       2: invokevirtual #118                // Method getParameter:(Ljava/lang/String;)Ljava/lang/String;
       5: astore        4
       7: aload         4
       9: invokestatic  #17                 // Method org/apache/dubbo/common/utils/StringUtils.isEmpty:(Ljava/lang/String;)Z
      12: ifeq          17
      15: lload_2
      16: lreturn
      17: aload         4
      19: invokestatic  #144                // Method java/lang/Long.parseLong:(Ljava/lang/String;)J
      22: lreturn

  public int getParameter(java.lang.String, int);
    Code:
       0: aload_0
       1: aload_1
       2: invokevirtual #118                // Method getParameter:(Ljava/lang/String;)Ljava/lang/String;
       5: astore_3
       6: aload_3
       7: invokestatic  #17                 // Method org/apache/dubbo/common/utils/StringUtils.isEmpty:(Ljava/lang/String;)Z
      10: ifeq          15
      13: iload_2
      14: ireturn
      15: aload_3
      16: invokestatic  #72                 // Method java/lang/Integer.parseInt:(Ljava/lang/String;)I
      19: ireturn

  public short getParameter(java.lang.String, short);
    Code:
       0: aload_0
       1: aload_1
       2: invokevirtual #118                // Method getParameter:(Ljava/lang/String;)Ljava/lang/String;
       5: astore_3
       6: aload_3
       7: invokestatic  #17                 // Method org/apache/dubbo/common/utils/StringUtils.isEmpty:(Ljava/lang/String;)Z
      10: ifeq          15
      13: iload_2
      14: ireturn
      15: aload_3
      16: invokestatic  #145                // Method java/lang/Short.parseShort:(Ljava/lang/String;)S
      19: ireturn

  public byte getParameter(java.lang.String, byte);
    Code:
       0: aload_0
       1: aload_1
       2: invokevirtual #118                // Method getParameter:(Ljava/lang/String;)Ljava/lang/String;
       5: astore_3
       6: aload_3
       7: invokestatic  #17                 // Method org/apache/dubbo/common/utils/StringUtils.isEmpty:(Ljava/lang/String;)Z
      10: ifeq          15
      13: iload_2
      14: ireturn
      15: aload_3
      16: invokestatic  #146                // Method java/lang/Byte.parseByte:(Ljava/lang/String;)B
      19: ireturn

  public float getPositiveParameter(java.lang.String, float);
    Code:
       0: fload_2
       1: fconst_0
       2: fcmpg
       3: ifgt          16
       6: new           #19                 // class java/lang/IllegalArgumentException
       9: dup
      10: ldc           #147                // String defaultValue <= 0
      12: invokespecial #21                 // Method java/lang/IllegalArgumentException."<init>":(Ljava/lang/String;)V
      15: athrow
      16: aload_0
      17: aload_1
      18: fload_2
      19: invokevirtual #148                // Method getParameter:(Ljava/lang/String;F)F
      22: fstore_3
      23: fload_3
      24: fconst_0
      25: fcmpg
      26: ifgt          33
      29: fload_2
      30: goto          34
      33: fload_3
      34: freturn

  public double getPositiveParameter(java.lang.String, double);
    Code:
       0: dload_2
       1: dconst_0
       2: dcmpg
       3: ifgt          16
       6: new           #19                 // class java/lang/IllegalArgumentException
       9: dup
      10: ldc           #147                // String defaultValue <= 0
      12: invokespecial #21                 // Method java/lang/IllegalArgumentException."<init>":(Ljava/lang/String;)V
      15: athrow
      16: aload_0
      17: aload_1
      18: dload_2
      19: invokevirtual #149                // Method getParameter:(Ljava/lang/String;D)D
      22: dstore        4
      24: dload         4
      26: dconst_0
      27: dcmpg
      28: ifgt          35
      31: dload_2
      32: goto          37
      35: dload         4
      37: dreturn

  public long getPositiveParameter(java.lang.String, long);
    Code:
       0: lload_2
       1: lconst_0
       2: lcmp
       3: ifgt          16
       6: new           #19                 // class java/lang/IllegalArgumentException
       9: dup
      10: ldc           #147                // String defaultValue <= 0
      12: invokespecial #21                 // Method java/lang/IllegalArgumentException."<init>":(Ljava/lang/String;)V
      15: athrow
      16: aload_0
      17: aload_1
      18: lload_2
      19: invokevirtual #150                // Method getParameter:(Ljava/lang/String;J)J
      22: lstore        4
      24: lload         4
      26: lconst_0
      27: lcmp
      28: ifgt          35
      31: lload_2
      32: goto          37
      35: lload         4
      37: lreturn

  public int getPositiveParameter(java.lang.String, int);
    Code:
       0: iload_2
       1: ifgt          14
       4: new           #19                 // class java/lang/IllegalArgumentException
       7: dup
       8: ldc           #147                // String defaultValue <= 0
      10: invokespecial #21                 // Method java/lang/IllegalArgumentException."<init>":(Ljava/lang/String;)V
      13: athrow
      14: aload_0
      15: aload_1
      16: iload_2
      17: invokevirtual #151                // Method getParameter:(Ljava/lang/String;I)I
      20: istore_3
      21: iload_3
      22: ifgt          29
      25: iload_2
      26: goto          30
      29: iload_3
      30: ireturn

  public short getPositiveParameter(java.lang.String, short);
    Code:
       0: iload_2
       1: ifgt          14
       4: new           #19                 // class java/lang/IllegalArgumentException
       7: dup
       8: ldc           #147                // String defaultValue <= 0
      10: invokespecial #21                 // Method java/lang/IllegalArgumentException."<init>":(Ljava/lang/String;)V
      13: athrow
      14: aload_0
      15: aload_1
      16: iload_2
      17: invokevirtual #152                // Method getParameter:(Ljava/lang/String;S)S
      20: istore_3
      21: iload_3
      22: ifgt          29
      25: iload_2
      26: goto          30
      29: iload_3
      30: ireturn

  public byte getPositiveParameter(java.lang.String, byte);
    Code:
       0: iload_2
       1: ifgt          14
       4: new           #19                 // class java/lang/IllegalArgumentException
       7: dup
       8: ldc           #147                // String defaultValue <= 0
      10: invokespecial #21                 // Method java/lang/IllegalArgumentException."<init>":(Ljava/lang/String;)V
      13: athrow
      14: aload_0
      15: aload_1
      16: iload_2
      17: invokevirtual #153                // Method getParameter:(Ljava/lang/String;B)B
      20: istore_3
      21: iload_3
      22: ifgt          29
      25: iload_2
      26: goto          30
      29: iload_3
      30: ireturn

  public char getParameter(java.lang.String, char);
    Code:
       0: aload_0
       1: aload_1
       2: invokevirtual #118                // Method getParameter:(Ljava/lang/String;)Ljava/lang/String;
       5: astore_3
       6: aload_3
       7: invokestatic  #17                 // Method org/apache/dubbo/common/utils/StringUtils.isEmpty:(Ljava/lang/String;)Z
      10: ifeq          17
      13: iload_2
      14: goto          22
      17: aload_3
      18: iconst_0
      19: invokevirtual #154                // Method java/lang/String.charAt:(I)C
      22: ireturn

  public boolean getParameter(java.lang.String, boolean);
    Code:
       0: aload_0
       1: aload_1
       2: invokevirtual #118                // Method getParameter:(Ljava/lang/String;)Ljava/lang/String;
       5: astore_3
       6: aload_3
       7: invokestatic  #17                 // Method org/apache/dubbo/common/utils/StringUtils.isEmpty:(Ljava/lang/String;)Z
      10: ifeq          17
      13: iload_2
      14: goto          21
      17: aload_3
      18: invokestatic  #155                // Method java/lang/Boolean.parseBoolean:(Ljava/lang/String;)Z
      21: ireturn

  public boolean hasParameter(java.lang.String);
    Code:
       0: aload_0
       1: aload_1
       2: invokevirtual #118                // Method getParameter:(Ljava/lang/String;)Ljava/lang/String;
       5: astore_2
       6: aload_2
       7: ifnull        21
      10: aload_2
      11: invokevirtual #63                 // Method java/lang/String.length:()I
      14: ifle          21
      17: iconst_1
      18: goto          22
      21: iconst_0
      22: ireturn

  public java.lang.String getMethodParameterAndDecoded(java.lang.String, java.lang.String);
    Code:
       0: aload_0
       1: aload_1
       2: aload_2
       3: invokevirtual #156                // Method getMethodParameter:(Ljava/lang/String;Ljava/lang/String;)Ljava/lang/String;
       6: invokestatic  #117                // Method decode:(Ljava/lang/String;)Ljava/lang/String;
       9: areturn

  public java.lang.String getMethodParameterAndDecoded(java.lang.String, java.lang.String, java.lang.String);
    Code:
       0: aload_0
       1: aload_1
       2: aload_2
       3: aload_3
       4: invokevirtual #157                // Method getMethodParameter:(Ljava/lang/String;Ljava/lang/String;Ljava/lang/String;)Ljava/lang/String;
       7: invokestatic  #117                // Method decode:(Ljava/lang/String;)Ljava/lang/String;
      10: areturn

  public java.lang.String getMethodParameter(java.lang.String, java.lang.String);
    Code:
       0: aload_0
       1: getfield      #10                 // Field urlParam:Lorg/apache/dubbo/common/url/component/URLParam;
       4: aload_1
       5: aload_2
       6: invokevirtual #158                // Method org/apache/dubbo/common/url/component/URLParam.getMethodParameter:(Ljava/lang/String;Ljava/lang/String;)Ljava/lang/String;
       9: areturn

  public java.lang.String getMethodParameterStrict(java.lang.String, java.lang.String);
    Code:
       0: aload_0
       1: getfield      #10                 // Field urlParam:Lorg/apache/dubbo/common/url/component/URLParam;
       4: aload_1
       5: aload_2
       6: invokevirtual #159                // Method org/apache/dubbo/common/url/component/URLParam.getMethodParameterStrict:(Ljava/lang/String;Ljava/lang/String;)Ljava/lang/String;
       9: areturn

  public java.lang.String getMethodParameter(java.lang.String, java.lang.String, java.lang.String);
    Code:
       0: aload_0
       1: aload_1
       2: aload_2
       3: invokevirtual #156                // Method getMethodParameter:(Ljava/lang/String;Ljava/lang/String;)Ljava/lang/String;
       6: astore        4
       8: aload         4
      10: invokestatic  #17                 // Method org/apache/dubbo/common/utils/StringUtils.isEmpty:(Ljava/lang/String;)Z
      13: ifeq          20
      16: aload_3
      17: goto          22
      20: aload         4
      22: areturn

  public double getMethodParameter(java.lang.String, java.lang.String, double);
    Code:
       0: aload_0
       1: aload_1
       2: aload_2
       3: invokevirtual #156                // Method getMethodParameter:(Ljava/lang/String;Ljava/lang/String;)Ljava/lang/String;
       6: astore        5
       8: aload         5
      10: invokestatic  #17                 // Method org/apache/dubbo/common/utils/StringUtils.isEmpty:(Ljava/lang/String;)Z
      13: ifeq          18
      16: dload_3
      17: dreturn
      18: aload         5
      20: invokestatic  #142                // Method java/lang/Double.parseDouble:(Ljava/lang/String;)D
      23: dreturn

  public float getMethodParameter(java.lang.String, java.lang.String, float);
    Code:
       0: aload_0
       1: aload_1
       2: aload_2
       3: invokevirtual #156                // Method getMethodParameter:(Ljava/lang/String;Ljava/lang/String;)Ljava/lang/String;
       6: astore        4
       8: aload         4
      10: invokestatic  #17                 // Method org/apache/dubbo/common/utils/StringUtils.isEmpty:(Ljava/lang/String;)Z
      13: ifeq          18
      16: fload_3
      17: freturn
      18: aload         4
      20: invokestatic  #143                // Method java/lang/Float.parseFloat:(Ljava/lang/String;)F
      23: freturn

  public long getMethodParameter(java.lang.String, java.lang.String, long);
    Code:
       0: aload_0
       1: aload_1
       2: aload_2
       3: invokevirtual #156                // Method getMethodParameter:(Ljava/lang/String;Ljava/lang/String;)Ljava/lang/String;
       6: astore        5
       8: aload         5
      10: invokestatic  #17                 // Method org/apache/dubbo/common/utils/StringUtils.isEmpty:(Ljava/lang/String;)Z
      13: ifeq          18
      16: lload_3
      17: lreturn
      18: aload         5
      20: invokestatic  #144                // Method java/lang/Long.parseLong:(Ljava/lang/String;)J
      23: lreturn

  public int getMethodParameter(java.lang.String, java.lang.String, int);
    Code:
       0: aload_0
       1: aload_1
       2: aload_2
       3: invokevirtual #156                // Method getMethodParameter:(Ljava/lang/String;Ljava/lang/String;)Ljava/lang/String;
       6: astore        4
       8: aload         4
      10: invokestatic  #17                 // Method org/apache/dubbo/common/utils/StringUtils.isEmpty:(Ljava/lang/String;)Z
      13: ifeq          18
      16: iload_3
      17: ireturn
      18: aload         4
      20: invokestatic  #72                 // Method java/lang/Integer.parseInt:(Ljava/lang/String;)I
      23: ireturn

  public short getMethodParameter(java.lang.String, java.lang.String, short);
    Code:
       0: aload_0
       1: aload_1
       2: aload_2
       3: invokevirtual #156                // Method getMethodParameter:(Ljava/lang/String;Ljava/lang/String;)Ljava/lang/String;
       6: astore        4
       8: aload         4
      10: invokestatic  #17                 // Method org/apache/dubbo/common/utils/StringUtils.isEmpty:(Ljava/lang/String;)Z
      13: ifeq          18
      16: iload_3
      17: ireturn
      18: aload         4
      20: invokestatic  #145                // Method java/lang/Short.parseShort:(Ljava/lang/String;)S
      23: ireturn

  public byte getMethodParameter(java.lang.String, java.lang.String, byte);
    Code:
       0: aload_0
       1: aload_1
       2: aload_2
       3: invokevirtual #156                // Method getMethodParameter:(Ljava/lang/String;Ljava/lang/String;)Ljava/lang/String;
       6: astore        4
       8: aload         4
      10: invokestatic  #17                 // Method org/apache/dubbo/common/utils/StringUtils.isEmpty:(Ljava/lang/String;)Z
      13: ifeq          18
      16: iload_3
      17: ireturn
      18: aload         4
      20: invokestatic  #146                // Method java/lang/Byte.parseByte:(Ljava/lang/String;)B
      23: ireturn

  public double getMethodPositiveParameter(java.lang.String, java.lang.String, double);
    Code:
       0: dload_3
       1: dconst_0
       2: dcmpg
       3: ifgt          16
       6: new           #19                 // class java/lang/IllegalArgumentException
       9: dup
      10: ldc           #147                // String defaultValue <= 0
      12: invokespecial #21                 // Method java/lang/IllegalArgumentException."<init>":(Ljava/lang/String;)V
      15: athrow
      16: aload_0
      17: aload_1
      18: aload_2
      19: dload_3
      20: invokevirtual #160                // Method getMethodParameter:(Ljava/lang/String;Ljava/lang/String;D)D
      23: dstore        5
      25: dload         5
      27: dconst_0
      28: dcmpg
      29: ifgt          36
      32: dload_3
      33: goto          38
      36: dload         5
      38: dreturn

  public float getMethodPositiveParameter(java.lang.String, java.lang.String, float);
    Code:
       0: fload_3
       1: fconst_0
       2: fcmpg
       3: ifgt          16
       6: new           #19                 // class java/lang/IllegalArgumentException
       9: dup
      10: ldc           #147                // String defaultValue <= 0
      12: invokespecial #21                 // Method java/lang/IllegalArgumentException."<init>":(Ljava/lang/String;)V
      15: athrow
      16: aload_0
      17: aload_1
      18: aload_2
      19: fload_3
      20: invokevirtual #161                // Method getMethodParameter:(Ljava/lang/String;Ljava/lang/String;F)F
      23: fstore        4
      25: fload         4
      27: fconst_0
      28: fcmpg
      29: ifgt          36
      32: fload_3
      33: goto          38
      36: fload         4
      38: freturn

  public long getMethodPositiveParameter(java.lang.String, java.lang.String, long);
    Code:
       0: lload_3
       1: lconst_0
       2: lcmp
       3: ifgt          16
       6: new           #19                 // class java/lang/IllegalArgumentException
       9: dup
      10: ldc           #147                // String defaultValue <= 0
      12: invokespecial #21                 // Method java/lang/IllegalArgumentException."<init>":(Ljava/lang/String;)V
      15: athrow
      16: aload_0
      17: aload_1
      18: aload_2
      19: lload_3
      20: invokevirtual #162                // Method getMethodParameter:(Ljava/lang/String;Ljava/lang/String;J)J
      23: lstore        5
      25: lload         5
      27: lconst_0
      28: lcmp
      29: ifgt          36
      32: lload_3
      33: goto          38
      36: lload         5
      38: lreturn

  public int getMethodPositiveParameter(java.lang.String, java.lang.String, int);
    Code:
       0: iload_3
       1: ifgt          14
       4: new           #19                 // class java/lang/IllegalArgumentException
       7: dup
       8: ldc           #147                // String defaultValue <= 0
      10: invokespecial #21                 // Method java/lang/IllegalArgumentException."<init>":(Ljava/lang/String;)V
      13: athrow
      14: aload_0
      15: aload_1
      16: aload_2
      17: iload_3
      18: invokevirtual #163                // Method getMethodParameter:(Ljava/lang/String;Ljava/lang/String;I)I
      21: istore        4
      23: iload         4
      25: ifgt          32
      28: iload_3
      29: goto          34
      32: iload         4
      34: ireturn

  public short getMethodPositiveParameter(java.lang.String, java.lang.String, short);
    Code:
       0: iload_3
       1: ifgt          14
       4: new           #19                 // class java/lang/IllegalArgumentException
       7: dup
       8: ldc           #147                // String defaultValue <= 0
      10: invokespecial #21                 // Method java/lang/IllegalArgumentException."<init>":(Ljava/lang/String;)V
      13: athrow
      14: aload_0
      15: aload_1
      16: aload_2
      17: iload_3
      18: invokevirtual #164                // Method getMethodParameter:(Ljava/lang/String;Ljava/lang/String;S)S
      21: istore        4
      23: iload         4
      25: ifgt          32
      28: iload_3
      29: goto          34
      32: iload         4
      34: ireturn

  public byte getMethodPositiveParameter(java.lang.String, java.lang.String, byte);
    Code:
       0: iload_3
       1: ifgt          14
       4: new           #19                 // class java/lang/IllegalArgumentException
       7: dup
       8: ldc           #147                // String defaultValue <= 0
      10: invokespecial #21                 // Method java/lang/IllegalArgumentException."<init>":(Ljava/lang/String;)V
      13: athrow
      14: aload_0
      15: aload_1
      16: aload_2
      17: iload_3
      18: invokevirtual #165                // Method getMethodParameter:(Ljava/lang/String;Ljava/lang/String;B)B
      21: istore        4
      23: iload         4
      25: ifgt          32
      28: iload_3
      29: goto          34
      32: iload         4
      34: ireturn

  public char getMethodParameter(java.lang.String, java.lang.String, char);
    Code:
       0: aload_0
       1: aload_1
       2: aload_2
       3: invokevirtual #156                // Method getMethodParameter:(Ljava/lang/String;Ljava/lang/String;)Ljava/lang/String;
       6: astore        4
       8: aload         4
      10: invokestatic  #17                 // Method org/apache/dubbo/common/utils/StringUtils.isEmpty:(Ljava/lang/String;)Z
      13: ifeq          20
      16: iload_3
      17: goto          26
      20: aload         4
      22: iconst_0
      23: invokevirtual #154                // Method java/lang/String.charAt:(I)C
      26: ireturn

  public boolean getMethodParameter(java.lang.String, java.lang.String, boolean);
    Code:
       0: aload_0
       1: aload_1
       2: aload_2
       3: invokevirtual #156                // Method getMethodParameter:(Ljava/lang/String;Ljava/lang/String;)Ljava/lang/String;
       6: astore        4
       8: aload         4
      10: invokestatic  #17                 // Method org/apache/dubbo/common/utils/StringUtils.isEmpty:(Ljava/lang/String;)Z
      13: ifeq          20
      16: iload_3
      17: goto          25
      20: aload         4
      22: invokestatic  #155                // Method java/lang/Boolean.parseBoolean:(Ljava/lang/String;)Z
      25: ireturn

  public boolean hasMethodParameter(java.lang.String, java.lang.String);
    Code:
       0: aload_1
       1: ifnonnull     78
       4: new           #65                 // class java/lang/StringBuilder
       7: dup
       8: invokespecial #66                 // Method java/lang/StringBuilder."<init>":()V
      11: ldc           #166                // String .
      13: invokevirtual #67                 // Method java/lang/StringBuilder.append:(Ljava/lang/String;)Ljava/lang/StringBuilder;
      16: aload_2
      17: invokevirtual #67                 // Method java/lang/StringBuilder.append:(Ljava/lang/String;)Ljava/lang/StringBuilder;
      20: invokevirtual #70                 // Method java/lang/StringBuilder.toString:()Ljava/lang/String;
      23: astore_3
      24: aload_0
      25: invokevirtual #34                 // Method getParameters:()Ljava/util/Map;
      28: invokeinterface #167,  1          // InterfaceMethod java/util/Map.keySet:()Ljava/util/Set;
      33: invokeinterface #39,  1           // InterfaceMethod java/util/Set.iterator:()Ljava/util/Iterator;
      38: astore        4
      40: aload         4
      42: invokeinterface #40,  1           // InterfaceMethod java/util/Iterator.hasNext:()Z
      47: ifeq          76
      50: aload         4
      52: invokeinterface #41,  1           // InterfaceMethod java/util/Iterator.next:()Ljava/lang/Object;
      57: checkcast     #35                 // class java/lang/String
      60: astore        5
      62: aload         5
      64: aload_3
      65: invokevirtual #168                // Method java/lang/String.endsWith:(Ljava/lang/String;)Z
      68: ifeq          73
      71: iconst_1
      72: ireturn
      73: goto          40
      76: iconst_0
      77: ireturn
      78: aload_2
      79: ifnonnull     156
      82: new           #65                 // class java/lang/StringBuilder
      85: dup
      86: invokespecial #66                 // Method java/lang/StringBuilder."<init>":()V
      89: aload_1
      90: invokevirtual #67                 // Method java/lang/StringBuilder.append:(Ljava/lang/String;)Ljava/lang/StringBuilder;
      93: ldc           #166                // String .
      95: invokevirtual #67                 // Method java/lang/StringBuilder.append:(Ljava/lang/String;)Ljava/lang/StringBuilder;
      98: invokevirtual #70                 // Method java/lang/StringBuilder.toString:()Ljava/lang/String;
     101: astore_3
     102: aload_0
     103: invokevirtual #34                 // Method getParameters:()Ljava/util/Map;
     106: invokeinterface #167,  1          // InterfaceMethod java/util/Map.keySet:()Ljava/util/Set;
     111: invokeinterface #39,  1           // InterfaceMethod java/util/Set.iterator:()Ljava/util/Iterator;
     116: astore        4
     118: aload         4
     120: invokeinterface #40,  1           // InterfaceMethod java/util/Iterator.hasNext:()Z
     125: ifeq          154
     128: aload         4
     130: invokeinterface #41,  1           // InterfaceMethod java/util/Iterator.next:()Ljava/lang/Object;
     135: checkcast     #35                 // class java/lang/String
     138: astore        5
     140: aload         5
     142: aload_3
     143: invokevirtual #44                 // Method java/lang/String.startsWith:(Ljava/lang/String;)Z
     146: ifeq          151
     149: iconst_1
     150: ireturn
     151: goto          118
     154: iconst_0
     155: ireturn
     156: aload_0
     157: aload_1
     158: aload_2
     159: invokevirtual #169                // Method getMethodParameterStrict:(Ljava/lang/String;Ljava/lang/String;)Ljava/lang/String;
     162: astore_3
     163: aload_3
     164: invokestatic  #18                 // Method org/apache/dubbo/common/utils/StringUtils.isNotEmpty:(Ljava/lang/String;)Z
     167: ireturn

  public java.lang.String getAnyMethodParameter(java.lang.String);
    Code:
       0: aload_0
       1: getfield      #10                 // Field urlParam:Lorg/apache/dubbo/common/url/component/URLParam;
       4: aload_1
       5: invokevirtual #170                // Method org/apache/dubbo/common/url/component/URLParam.getAnyMethodParameter:(Ljava/lang/String;)Ljava/lang/String;
       8: areturn

  public boolean hasMethodParameter(java.lang.String);
    Code:
       0: aload_0
       1: getfield      #10                 // Field urlParam:Lorg/apache/dubbo/common/url/component/URLParam;
       4: aload_1
       5: invokevirtual #171                // Method org/apache/dubbo/common/url/component/URLParam.hasMethodParameter:(Ljava/lang/String;)Z
       8: ireturn

  public boolean isLocalHost();
    Code:
       0: aload_0
       1: invokevirtual #50                 // Method getHost:()Ljava/lang/String;
       4: invokestatic  #172                // Method org/apache/dubbo/common/utils/NetUtils.isLocalHost:(Ljava/lang/String;)Z
       7: ifne          20
      10: aload_0
      11: ldc           #173                // String localhost
      13: iconst_0
      14: invokevirtual #174                // Method getParameter:(Ljava/lang/String;Z)Z
      17: ifeq          24
      20: iconst_1
      21: goto          25
      24: iconst_0
      25: ireturn

  public boolean isAnyHost();
    Code:
       0: ldc           #175                // String 0.0.0.0
       2: aload_0
       3: invokevirtual #50                 // Method getHost:()Ljava/lang/String;
       6: invokevirtual #176                // Method java/lang/String.equals:(Ljava/lang/Object;)Z
       9: ifne          22
      12: aload_0
      13: ldc           #177                // String anyhost
      15: iconst_0
      16: invokevirtual #174                // Method getParameter:(Ljava/lang/String;Z)Z
      19: ifeq          26
      22: iconst_1
      23: goto          27
      26: iconst_0
      27: ireturn

  public org.apache.dubbo.common.URL addParameterAndEncoded(java.lang.String, java.lang.String);
    Code:
       0: aload_2
       1: invokestatic  #17                 // Method org/apache/dubbo/common/utils/StringUtils.isEmpty:(Ljava/lang/String;)Z
       4: ifeq          9
       7: aload_0
       8: areturn
       9: aload_0
      10: aload_1
      11: aload_2
      12: invokestatic  #178                // Method encode:(Ljava/lang/String;)Ljava/lang/String;
      15: invokevirtual #179                // Method addParameter:(Ljava/lang/String;Ljava/lang/String;)Lorg/apache/dubbo/common/URL;
      18: areturn

  public org.apache.dubbo.common.URL addParameter(java.lang.String, boolean);
    Code:
       0: aload_0
       1: aload_1
       2: iload_2
       3: invokestatic  #180                // Method java/lang/String.valueOf:(Z)Ljava/lang/String;
       6: invokevirtual #179                // Method addParameter:(Ljava/lang/String;Ljava/lang/String;)Lorg/apache/dubbo/common/URL;
       9: areturn

  public org.apache.dubbo.common.URL addParameter(java.lang.String, char);
    Code:
       0: aload_0
       1: aload_1
       2: iload_2
       3: invokestatic  #181                // Method java/lang/String.valueOf:(C)Ljava/lang/String;
       6: invokevirtual #179                // Method addParameter:(Ljava/lang/String;Ljava/lang/String;)Lorg/apache/dubbo/common/URL;
       9: areturn

  public org.apache.dubbo.common.URL addParameter(java.lang.String, byte);
    Code:
       0: aload_0
       1: aload_1
       2: iload_2
       3: invokestatic  #182                // Method java/lang/String.valueOf:(I)Ljava/lang/String;
       6: invokevirtual #179                // Method addParameter:(Ljava/lang/String;Ljava/lang/String;)Lorg/apache/dubbo/common/URL;
       9: areturn

  public org.apache.dubbo.common.URL addParameter(java.lang.String, short);
    Code:
       0: aload_0
       1: aload_1
       2: iload_2
       3: invokestatic  #182                // Method java/lang/String.valueOf:(I)Ljava/lang/String;
       6: invokevirtual #179                // Method addParameter:(Ljava/lang/String;Ljava/lang/String;)Lorg/apache/dubbo/common/URL;
       9: areturn

  public org.apache.dubbo.common.URL addParameter(java.lang.String, int);
    Code:
       0: aload_0
       1: aload_1
       2: iload_2
       3: invokestatic  #182                // Method java/lang/String.valueOf:(I)Ljava/lang/String;
       6: invokevirtual #179                // Method addParameter:(Ljava/lang/String;Ljava/lang/String;)Lorg/apache/dubbo/common/URL;
       9: areturn

  public org.apache.dubbo.common.URL addParameter(java.lang.String, long);
    Code:
       0: aload_0
       1: aload_1
       2: lload_2
       3: invokestatic  #183                // Method java/lang/String.valueOf:(J)Ljava/lang/String;
       6: invokevirtual #179                // Method addParameter:(Ljava/lang/String;Ljava/lang/String;)Lorg/apache/dubbo/common/URL;
       9: areturn

  public org.apache.dubbo.common.URL addParameter(java.lang.String, float);
    Code:
       0: aload_0
       1: aload_1
       2: fload_2
       3: invokestatic  #184                // Method java/lang/String.valueOf:(F)Ljava/lang/String;
       6: invokevirtual #179                // Method addParameter:(Ljava/lang/String;Ljava/lang/String;)Lorg/apache/dubbo/common/URL;
       9: areturn

  public org.apache.dubbo.common.URL addParameter(java.lang.String, double);
    Code:
       0: aload_0
       1: aload_1
       2: dload_2
       3: invokestatic  #185                // Method java/lang/String.valueOf:(D)Ljava/lang/String;
       6: invokevirtual #179                // Method addParameter:(Ljava/lang/String;Ljava/lang/String;)Lorg/apache/dubbo/common/URL;
       9: areturn

  public org.apache.dubbo.common.URL addParameter(java.lang.String, java.lang.Enum<?>);
    Code:
       0: aload_2
       1: ifnonnull     6
       4: aload_0
       5: areturn
       6: aload_0
       7: aload_1
       8: aload_2
       9: invokestatic  #186                // Method java/lang/String.valueOf:(Ljava/lang/Object;)Ljava/lang/String;
      12: invokevirtual #179                // Method addParameter:(Ljava/lang/String;Ljava/lang/String;)Lorg/apache/dubbo/common/URL;
      15: areturn

  public org.apache.dubbo.common.URL addParameter(java.lang.String, java.lang.Number);
    Code:
       0: aload_2
       1: ifnonnull     6
       4: aload_0
       5: areturn
       6: aload_0
       7: aload_1
       8: aload_2
       9: invokestatic  #186                // Method java/lang/String.valueOf:(Ljava/lang/Object;)Ljava/lang/String;
      12: invokevirtual #179                // Method addParameter:(Ljava/lang/String;Ljava/lang/String;)Lorg/apache/dubbo/common/URL;
      15: areturn

  public org.apache.dubbo.common.URL addParameter(java.lang.String, java.lang.CharSequence);
    Code:
       0: aload_2
       1: ifnull        13
       4: aload_2
       5: invokeinterface #187,  1          // InterfaceMethod java/lang/CharSequence.length:()I
      10: ifne          15
      13: aload_0
      14: areturn
      15: aload_0
      16: aload_1
      17: aload_2
      18: invokestatic  #186                // Method java/lang/String.valueOf:(Ljava/lang/Object;)Ljava/lang/String;
      21: invokevirtual #179                // Method addParameter:(Ljava/lang/String;Ljava/lang/String;)Lorg/apache/dubbo/common/URL;
      24: areturn

  public org.apache.dubbo.common.URL addParameter(java.lang.String, java.lang.String);
    Code:
       0: aload_0
       1: getfield      #10                 // Field urlParam:Lorg/apache/dubbo/common/url/component/URLParam;
       4: aload_1
       5: aload_2
       6: invokevirtual #188                // Method org/apache/dubbo/common/url/component/URLParam.addParameter:(Ljava/lang/String;Ljava/lang/String;)Lorg/apache/dubbo/common/url/component/URLParam;
       9: astore_3
      10: aload_0
      11: aload_3
      12: invokespecial #189                // Method returnURL:(Lorg/apache/dubbo/common/url/component/URLParam;)Lorg/apache/dubbo/common/URL;
      15: areturn

  public org.apache.dubbo.common.URL addParameterIfAbsent(java.lang.String, java.lang.String);
    Code:
       0: aload_0
       1: getfield      #10                 // Field urlParam:Lorg/apache/dubbo/common/url/component/URLParam;
       4: aload_1
       5: aload_2
       6: invokevirtual #190                // Method org/apache/dubbo/common/url/component/URLParam.addParameterIfAbsent:(Ljava/lang/String;Ljava/lang/String;)Lorg/apache/dubbo/common/url/component/URLParam;
       9: astore_3
      10: aload_0
      11: aload_3
      12: invokespecial #189                // Method returnURL:(Lorg/apache/dubbo/common/url/component/URLParam;)Lorg/apache/dubbo/common/URL;
      15: areturn

  public org.apache.dubbo.common.URL addParameters(java.util.Map<java.lang.String, java.lang.String>);
    Code:
       0: aload_0
       1: getfield      #10                 // Field urlParam:Lorg/apache/dubbo/common/url/component/URLParam;
       4: aload_1
       5: invokevirtual #191                // Method org/apache/dubbo/common/url/component/URLParam.addParameters:(Ljava/util/Map;)Lorg/apache/dubbo/common/url/component/URLParam;
       8: astore_2
       9: aload_0
      10: aload_2
      11: invokespecial #189                // Method returnURL:(Lorg/apache/dubbo/common/url/component/URLParam;)Lorg/apache/dubbo/common/URL;
      14: areturn

  public org.apache.dubbo.common.URL addParametersIfAbsent(java.util.Map<java.lang.String, java.lang.String>);
    Code:
       0: aload_0
       1: getfield      #10                 // Field urlParam:Lorg/apache/dubbo/common/url/component/URLParam;
       4: aload_1
       5: invokevirtual #192                // Method org/apache/dubbo/common/url/component/URLParam.addParametersIfAbsent:(Ljava/util/Map;)Lorg/apache/dubbo/common/url/component/URLParam;
       8: astore_2
       9: aload_0
      10: aload_2
      11: invokespecial #189                // Method returnURL:(Lorg/apache/dubbo/common/url/component/URLParam;)Lorg/apache/dubbo/common/URL;
      14: areturn

  public org.apache.dubbo.common.URL addParameters(java.lang.String...);
    Code:
       0: aload_1
       1: ifnull        9
       4: aload_1
       5: arraylength
       6: ifne          11
       9: aload_0
      10: areturn
      11: aload_1
      12: arraylength
      13: iconst_2
      14: irem
      15: ifeq          28
      18: new           #19                 // class java/lang/IllegalArgumentException
      21: dup
      22: ldc           #193                // String Map pairs can not be odd number.
      24: invokespecial #21                 // Method java/lang/IllegalArgumentException."<init>":(Ljava/lang/String;)V
      27: athrow
      28: new           #7                  // class java/util/HashMap
      31: dup
      32: invokespecial #8                  // Method java/util/HashMap."<init>":()V
      35: astore_2
      36: aload_1
      37: arraylength
      38: iconst_2
      39: idiv
      40: istore_3
      41: iconst_0
      42: istore        4
      44: iload         4
      46: iload_3
      47: if_icmpge     77
      50: aload_2
      51: aload_1
      52: iconst_2
      53: iload         4
      55: imul
      56: aaload
      57: aload_1
      58: iconst_2
      59: iload         4
      61: imul
      62: iconst_1
      63: iadd
      64: aaload
      65: invokeinterface #28,  3           // InterfaceMethod java/util/Map.put:(Ljava/lang/Object;Ljava/lang/Object;)Ljava/lang/Object;
      70: pop
      71: iinc          4, 1
      74: goto          44
      77: aload_0
      78: aload_2
      79: invokevirtual #37                 // Method addParameters:(Ljava/util/Map;)Lorg/apache/dubbo/common/URL;
      82: areturn

  public org.apache.dubbo.common.URL addParameterString(java.lang.String);
    Code:
       0: aload_1
       1: invokestatic  #17                 // Method org/apache/dubbo/common/utils/StringUtils.isEmpty:(Ljava/lang/String;)Z
       4: ifeq          9
       7: aload_0
       8: areturn
       9: aload_0
      10: aload_1
      11: invokestatic  #194                // Method org/apache/dubbo/common/utils/StringUtils.parseQueryString:(Ljava/lang/String;)Ljava/util/Map;
      14: invokevirtual #37                 // Method addParameters:(Ljava/util/Map;)Lorg/apache/dubbo/common/URL;
      17: areturn

  public org.apache.dubbo.common.URL removeParameter(java.lang.String);
    Code:
       0: aload_1
       1: invokestatic  #17                 // Method org/apache/dubbo/common/utils/StringUtils.isEmpty:(Ljava/lang/String;)Z
       4: ifeq          9
       7: aload_0
       8: areturn
       9: aload_0
      10: iconst_1
      11: anewarray     #35                 // class java/lang/String
      14: dup
      15: iconst_0
      16: aload_1
      17: aastore
      18: invokevirtual #195                // Method removeParameters:([Ljava/lang/String;)Lorg/apache/dubbo/common/URL;
      21: areturn

  public org.apache.dubbo.common.URL removeParameters(java.util.Collection<java.lang.String>);
    Code:
       0: aload_1
       1: invokestatic  #196                // Method org/apache/dubbo/common/utils/CollectionUtils.isEmpty:(Ljava/util/Collection;)Z
       4: ifeq          9
       7: aload_0
       8: areturn
       9: aload_0
      10: aload_1
      11: iconst_0
      12: anewarray     #35                 // class java/lang/String
      15: invokeinterface #197,  2          // InterfaceMethod java/util/Collection.toArray:([Ljava/lang/Object;)[Ljava/lang/Object;
      20: checkcast     #198                // class "[Ljava/lang/String;"
      23: invokevirtual #195                // Method removeParameters:([Ljava/lang/String;)Lorg/apache/dubbo/common/URL;
      26: areturn

  public org.apache.dubbo.common.URL removeParameters(java.lang.String...);
    Code:
       0: aload_0
       1: getfield      #10                 // Field urlParam:Lorg/apache/dubbo/common/url/component/URLParam;
       4: aload_1
       5: invokevirtual #199                // Method org/apache/dubbo/common/url/component/URLParam.removeParameters:([Ljava/lang/String;)Lorg/apache/dubbo/common/url/component/URLParam;
       8: astore_2
       9: aload_0
      10: aload_2
      11: invokespecial #189                // Method returnURL:(Lorg/apache/dubbo/common/url/component/URLParam;)Lorg/apache/dubbo/common/URL;
      14: areturn

  public org.apache.dubbo.common.URL clearParameters();
    Code:
       0: aload_0
       1: getfield      #10                 // Field urlParam:Lorg/apache/dubbo/common/url/component/URLParam;
       4: invokevirtual #200                // Method org/apache/dubbo/common/url/component/URLParam.clearParameters:()Lorg/apache/dubbo/common/url/component/URLParam;
       7: astore_1
       8: aload_0
       9: aload_1
      10: invokespecial #189                // Method returnURL:(Lorg/apache/dubbo/common/url/component/URLParam;)Lorg/apache/dubbo/common/URL;
      13: areturn

  public java.lang.String getRawParameter(java.lang.String);
    Code:
       0: ldc           #201                // String protocol
       2: aload_1
       3: invokevirtual #176                // Method java/lang/String.equals:(Ljava/lang/Object;)Z
       6: ifeq          17
       9: aload_0
      10: getfield      #6                  // Field urlAddress:Lorg/apache/dubbo/common/url/component/URLAddress;
      13: invokevirtual #74                 // Method org/apache/dubbo/common/url/component/URLAddress.getProtocol:()Ljava/lang/String;
      16: areturn
      17: ldc           #202                // String username
      19: aload_1
      20: invokevirtual #176                // Method java/lang/String.equals:(Ljava/lang/Object;)Z
      23: ifeq          34
      26: aload_0
      27: getfield      #6                  // Field urlAddress:Lorg/apache/dubbo/common/url/component/URLAddress;
      30: invokevirtual #78                 // Method org/apache/dubbo/common/url/component/URLAddress.getUsername:()Ljava/lang/String;
      33: areturn
      34: ldc           #203                // String password
      36: aload_1
      37: invokevirtual #176                // Method java/lang/String.equals:(Ljava/lang/Object;)Z
      40: ifeq          51
      43: aload_0
      44: getfield      #6                  // Field urlAddress:Lorg/apache/dubbo/common/url/component/URLAddress;
      47: invokevirtual #81                 // Method org/apache/dubbo/common/url/component/URLAddress.getPassword:()Ljava/lang/String;
      50: areturn
      51: ldc           #204                // String host
      53: aload_1
      54: invokevirtual #176                // Method java/lang/String.equals:(Ljava/lang/Object;)Z
      57: ifeq          68
      60: aload_0
      61: getfield      #6                  // Field urlAddress:Lorg/apache/dubbo/common/url/component/URLAddress;
      64: invokevirtual #87                 // Method org/apache/dubbo/common/url/component/URLAddress.getHost:()Ljava/lang/String;
      67: areturn
      68: ldc           #205                // String port
      70: aload_1
      71: invokevirtual #176                // Method java/lang/String.equals:(Ljava/lang/Object;)Z
      74: ifeq          88
      77: aload_0
      78: getfield      #6                  // Field urlAddress:Lorg/apache/dubbo/common/url/component/URLAddress;
      81: invokevirtual #89                 // Method org/apache/dubbo/common/url/component/URLAddress.getPort:()I
      84: invokestatic  #182                // Method java/lang/String.valueOf:(I)Ljava/lang/String;
      87: areturn
      88: ldc           #206                // String path
      90: aload_1
      91: invokevirtual #176                // Method java/lang/String.equals:(Ljava/lang/Object;)Z
      94: ifeq          105
      97: aload_0
      98: getfield      #6                  // Field urlAddress:Lorg/apache/dubbo/common/url/component/URLAddress;
     101: invokevirtual #107                // Method org/apache/dubbo/common/url/component/URLAddress.getPath:()Ljava/lang/String;
     104: areturn
     105: aload_0
     106: getfield      #10                 // Field urlParam:Lorg/apache/dubbo/common/url/component/URLParam;
     109: aload_1
     110: invokevirtual #119                // Method org/apache/dubbo/common/url/component/URLParam.getParameter:(Ljava/lang/String;)Ljava/lang/String;
     113: areturn

  public java.util.Map<java.lang.String, java.lang.String> toOriginalMap();
    Code:
       0: new           #7                  // class java/util/HashMap
       3: dup
       4: aload_0
       5: invokevirtual #207                // Method getOriginalParameters:()Ljava/util/Map;
       8: invokespecial #208                // Method java/util/HashMap."<init>":(Ljava/util/Map;)V
      11: astore_1
      12: aload_0
      13: aload_1
      14: invokespecial #209                // Method addSpecialKeys:(Ljava/util/Map;)Ljava/util/Map;
      17: areturn

  public java.util.Map<java.lang.String, java.lang.String> toMap();
    Code:
       0: new           #7                  // class java/util/HashMap
       3: dup
       4: aload_0
       5: invokevirtual #34                 // Method getParameters:()Ljava/util/Map;
       8: invokespecial #208                // Method java/util/HashMap."<init>":(Ljava/util/Map;)V
      11: astore_1
      12: aload_0
      13: aload_1
      14: invokespecial #209                // Method addSpecialKeys:(Ljava/util/Map;)Ljava/util/Map;
      17: areturn

  private java.util.Map<java.lang.String, java.lang.String> addSpecialKeys(java.util.Map<java.lang.String, java.lang.String>);
    Code:
       0: aload_0
       1: invokevirtual #47                 // Method getProtocol:()Ljava/lang/String;
       4: ifnull        20
       7: aload_1
       8: ldc           #201                // String protocol
      10: aload_0
      11: invokevirtual #47                 // Method getProtocol:()Ljava/lang/String;
      14: invokeinterface #28,  3           // InterfaceMethod java/util/Map.put:(Ljava/lang/Object;Ljava/lang/Object;)Ljava/lang/Object;
      19: pop
      20: aload_0
      21: invokevirtual #48                 // Method getUsername:()Ljava/lang/String;
      24: ifnull        40
      27: aload_1
      28: ldc           #202                // String username
      30: aload_0
      31: invokevirtual #48                 // Method getUsername:()Ljava/lang/String;
      34: invokeinterface #28,  3           // InterfaceMethod java/util/Map.put:(Ljava/lang/Object;Ljava/lang/Object;)Ljava/lang/Object;
      39: pop
      40: aload_0
      41: invokevirtual #49                 // Method getPassword:()Ljava/lang/String;
      44: ifnull        60
      47: aload_1
      48: ldc           #203                // String password
      50: aload_0
      51: invokevirtual #49                 // Method getPassword:()Ljava/lang/String;
      54: invokeinterface #28,  3           // InterfaceMethod java/util/Map.put:(Ljava/lang/Object;Ljava/lang/Object;)Ljava/lang/Object;
      59: pop
      60: aload_0
      61: invokevirtual #50                 // Method getHost:()Ljava/lang/String;
      64: ifnull        80
      67: aload_1
      68: ldc           #204                // String host
      70: aload_0
      71: invokevirtual #50                 // Method getHost:()Ljava/lang/String;
      74: invokeinterface #28,  3           // InterfaceMethod java/util/Map.put:(Ljava/lang/Object;Ljava/lang/Object;)Ljava/lang/Object;
      79: pop
      80: aload_0
      81: invokevirtual #51                 // Method getPort:()I
      84: ifle          103
      87: aload_1
      88: ldc           #205                // String port
      90: aload_0
      91: invokevirtual #51                 // Method getPort:()I
      94: invokestatic  #182                // Method java/lang/String.valueOf:(I)Ljava/lang/String;
      97: invokeinterface #28,  3           // InterfaceMethod java/util/Map.put:(Ljava/lang/Object;Ljava/lang/Object;)Ljava/lang/Object;
     102: pop
     103: aload_0
     104: invokevirtual #52                 // Method getPath:()Ljava/lang/String;
     107: ifnull        123
     110: aload_1
     111: ldc           #206                // String path
     113: aload_0
     114: invokevirtual #52                 // Method getPath:()Ljava/lang/String;
     117: invokeinterface #28,  3           // InterfaceMethod java/util/Map.put:(Ljava/lang/Object;Ljava/lang/Object;)Ljava/lang/Object;
     122: pop
     123: aload_0
     124: invokevirtual #96                 // Method getAddress:()Ljava/lang/String;
     127: ifnull        143
     130: aload_1
     131: ldc           #210                // String address
     133: aload_0
     134: invokevirtual #96                 // Method getAddress:()Ljava/lang/String;
     137: invokeinterface #28,  3           // InterfaceMethod java/util/Map.put:(Ljava/lang/Object;Ljava/lang/Object;)Ljava/lang/Object;
     142: pop
     143: aload_1
     144: areturn

  public java.lang.String toString();
    Code:
       0: aload_0
       1: iconst_0
       2: iconst_1
       3: iconst_0
       4: anewarray     #35                 // class java/lang/String
       7: invokespecial #211                // Method buildString:(ZZ[Ljava/lang/String;)Ljava/lang/String;
      10: areturn

  public java.lang.String toString(java.lang.String...);
    Code:
       0: aload_0
       1: iconst_0
       2: iconst_1
       3: aload_1
       4: invokespecial #211                // Method buildString:(ZZ[Ljava/lang/String;)Ljava/lang/String;
       7: areturn

  public java.lang.String toIdentityString();
    Code:
       0: aload_0
       1: iconst_1
       2: iconst_0
       3: iconst_0
       4: anewarray     #35                 // class java/lang/String
       7: invokespecial #211                // Method buildString:(ZZ[Ljava/lang/String;)Ljava/lang/String;
      10: areturn

  public java.lang.String toIdentityString(java.lang.String...);
    Code:
       0: aload_0
       1: iconst_1
       2: iconst_0
       3: aload_1
       4: invokespecial #211                // Method buildString:(ZZ[Ljava/lang/String;)Ljava/lang/String;
       7: areturn

  public java.lang.String toFullString();
    Code:
       0: aload_0
       1: iconst_1
       2: iconst_1
       3: iconst_0
       4: anewarray     #35                 // class java/lang/String
       7: invokespecial #211                // Method buildString:(ZZ[Ljava/lang/String;)Ljava/lang/String;
      10: areturn

  public java.lang.String toFullString(java.lang.String...);
    Code:
       0: aload_0
       1: iconst_1
       2: iconst_1
       3: aload_1
       4: invokespecial #211                // Method buildString:(ZZ[Ljava/lang/String;)Ljava/lang/String;
       7: areturn

  public java.lang.String toParameterString();
    Code:
       0: aload_0
       1: iconst_0
       2: anewarray     #35                 // class java/lang/String
       5: invokevirtual #212                // Method toParameterString:([Ljava/lang/String;)Ljava/lang/String;
       8: areturn

  public java.lang.String toParameterString(java.lang.String...);
    Code:
       0: new           #65                 // class java/lang/StringBuilder
       3: dup
       4: invokespecial #66                 // Method java/lang/StringBuilder."<init>":()V
       7: astore_2
       8: aload_0
       9: aload_2
      10: iconst_0
      11: aload_1
      12: invokevirtual #213                // Method buildParameters:(Ljava/lang/StringBuilder;Z[Ljava/lang/String;)V
      15: aload_2
      16: invokevirtual #70                 // Method java/lang/StringBuilder.toString:()Ljava/lang/String;
      19: areturn

  protected void buildParameters(java.lang.StringBuilder, boolean, java.lang.String[]);
    Code:
       0: aload_0
       1: invokevirtual #34                 // Method getParameters:()Ljava/util/Map;
       4: invokestatic  #214                // Method org/apache/dubbo/common/utils/CollectionUtils.isNotEmptyMap:(Ljava/util/Map;)Z
       7: ifeq          198
      10: aload_3
      11: invokestatic  #215                // Method org/apache/dubbo/common/utils/ArrayUtils.isEmpty:([Ljava/lang/Object;)Z
      14: ifeq          21
      17: aconst_null
      18: goto          25
      21: aload_3
      22: invokestatic  #122                // Method java/util/Arrays.asList:([Ljava/lang/Object;)Ljava/util/List;
      25: astore        4
      27: iconst_1
      28: istore        5
      30: new           #216                // class java/util/TreeMap
      33: dup
      34: aload_0
      35: invokevirtual #34                 // Method getParameters:()Ljava/util/Map;
      38: invokespecial #217                // Method java/util/TreeMap."<init>":(Ljava/util/Map;)V
      41: invokevirtual #218                // Method java/util/TreeMap.entrySet:()Ljava/util/Set;
      44: invokeinterface #39,  1           // InterfaceMethod java/util/Set.iterator:()Ljava/util/Iterator;
      49: astore        6
      51: aload         6
      53: invokeinterface #40,  1           // InterfaceMethod java/util/Iterator.hasNext:()Z
      58: ifeq          198
      61: aload         6
      63: invokeinterface #41,  1           // InterfaceMethod java/util/Iterator.next:()Ljava/lang/Object;
      68: checkcast     #42                 // class java/util/Map$Entry
      71: astore        7
      73: aload         7
      75: invokeinterface #43,  1           // InterfaceMethod java/util/Map$Entry.getKey:()Ljava/lang/Object;
      80: checkcast     #35                 // class java/lang/String
      83: invokestatic  #18                 // Method org/apache/dubbo/common/utils/StringUtils.isNotEmpty:(Ljava/lang/String;)Z
      86: ifeq          195
      89: aload         4
      91: ifnull        111
      94: aload         4
      96: aload         7
      98: invokeinterface #43,  1           // InterfaceMethod java/util/Map$Entry.getKey:()Ljava/lang/Object;
     103: invokeinterface #219,  2          // InterfaceMethod java/util/List.contains:(Ljava/lang/Object;)Z
     108: ifeq          195
     111: iload         5
     113: ifeq          133
     116: iload_2
     117: ifeq          127
     120: aload_1
     121: bipush        63
     123: invokevirtual #85                 // Method java/lang/StringBuilder.append:(C)Ljava/lang/StringBuilder;
     126: pop
     127: iconst_0
     128: istore        5
     130: goto          140
     133: aload_1
     134: bipush        38
     136: invokevirtual #85                 // Method java/lang/StringBuilder.append:(C)Ljava/lang/StringBuilder;
     139: pop
     140: aload_1
     141: aload         7
     143: invokeinterface #43,  1           // InterfaceMethod java/util/Map$Entry.getKey:()Ljava/lang/Object;
     148: checkcast     #35                 // class java/lang/String
     151: invokevirtual #67                 // Method java/lang/StringBuilder.append:(Ljava/lang/String;)Ljava/lang/StringBuilder;
     154: pop
     155: aload_1
     156: bipush        61
     158: invokevirtual #85                 // Method java/lang/StringBuilder.append:(C)Ljava/lang/StringBuilder;
     161: pop
     162: aload_1
     163: aload         7
     165: invokeinterface #45,  1           // InterfaceMethod java/util/Map$Entry.getValue:()Ljava/lang/Object;
     170: ifnonnull     178
     173: ldc           #55                 // String
     175: goto          191
     178: aload         7
     180: invokeinterface #45,  1           // InterfaceMethod java/util/Map$Entry.getValue:()Ljava/lang/Object;
     185: checkcast     #35                 // class java/lang/String
     188: invokevirtual #220                // Method java/lang/String.trim:()Ljava/lang/String;
     191: invokevirtual #67                 // Method java/lang/StringBuilder.append:(Ljava/lang/String;)Ljava/lang/StringBuilder;
     194: pop
     195: goto          51
     198: return

  private java.lang.String buildString(boolean, boolean, java.lang.String...);
    Code:
       0: aload_0
       1: iload_1
       2: iload_2
       3: iconst_0
       4: iconst_0
       5: aload_3
       6: invokespecial #221                // Method buildString:(ZZZZ[Ljava/lang/String;)Ljava/lang/String;
       9: areturn

  private java.lang.String buildString(boolean, boolean, boolean, boolean, java.lang.String...);
    Code:
       0: new           #65                 // class java/lang/StringBuilder
       3: dup
       4: invokespecial #66                 // Method java/lang/StringBuilder."<init>":()V
       7: astore        6
       9: aload_0
      10: invokevirtual #47                 // Method getProtocol:()Ljava/lang/String;
      13: invokestatic  #18                 // Method org/apache/dubbo/common/utils/StringUtils.isNotEmpty:(Ljava/lang/String;)Z
      16: ifeq          37
      19: aload         6
      21: aload_0
      22: invokevirtual #47                 // Method getProtocol:()Ljava/lang/String;
      25: invokevirtual #67                 // Method java/lang/StringBuilder.append:(Ljava/lang/String;)Ljava/lang/StringBuilder;
      28: pop
      29: aload         6
      31: ldc           #222                // String ://
      33: invokevirtual #67                 // Method java/lang/StringBuilder.append:(Ljava/lang/String;)Ljava/lang/StringBuilder;
      36: pop
      37: iload_1
      38: ifeq          97
      41: aload_0
      42: invokevirtual #48                 // Method getUsername:()Ljava/lang/String;
      45: invokestatic  #18                 // Method org/apache/dubbo/common/utils/StringUtils.isNotEmpty:(Ljava/lang/String;)Z
      48: ifeq          97
      51: aload         6
      53: aload_0
      54: invokevirtual #48                 // Method getUsername:()Ljava/lang/String;
      57: invokevirtual #67                 // Method java/lang/StringBuilder.append:(Ljava/lang/String;)Ljava/lang/StringBuilder;
      60: pop
      61: aload_0
      62: invokevirtual #49                 // Method getPassword:()Ljava/lang/String;
      65: invokestatic  #18                 // Method org/apache/dubbo/common/utils/StringUtils.isNotEmpty:(Ljava/lang/String;)Z
      68: ifeq          89
      71: aload         6
      73: bipush        58
      75: invokevirtual #85                 // Method java/lang/StringBuilder.append:(C)Ljava/lang/StringBuilder;
      78: pop
      79: aload         6
      81: aload_0
      82: invokevirtual #49                 // Method getPassword:()Ljava/lang/String;
      85: invokevirtual #67                 // Method java/lang/StringBuilder.append:(Ljava/lang/String;)Ljava/lang/StringBuilder;
      88: pop
      89: aload         6
      91: bipush        64
      93: invokevirtual #85                 // Method java/lang/StringBuilder.append:(C)Ljava/lang/StringBuilder;
      96: pop
      97: iload_3
      98: ifeq          113
     101: aload_0
     102: getfield      #6                  // Field urlAddress:Lorg/apache/dubbo/common/url/component/URLAddress;
     105: invokevirtual #94                 // Method org/apache/dubbo/common/url/component/URLAddress.getIp:()Ljava/lang/String;
     108: astore        7
     110: goto          119
     113: aload_0
     114: invokevirtual #50                 // Method getHost:()Ljava/lang/String;
     117: astore        7
     119: aload         7
     121: invokestatic  #18                 // Method org/apache/dubbo/common/utils/StringUtils.isNotEmpty:(Ljava/lang/String;)Z
     124: ifeq          160
     127: aload         6
     129: aload         7
     131: invokevirtual #67                 // Method java/lang/StringBuilder.append:(Ljava/lang/String;)Ljava/lang/StringBuilder;
     134: pop
     135: aload_0
     136: invokevirtual #51                 // Method getPort:()I
     139: ifle          160
     142: aload         6
     144: bipush        58
     146: invokevirtual #85                 // Method java/lang/StringBuilder.append:(C)Ljava/lang/StringBuilder;
     149: pop
     150: aload         6
     152: aload_0
     153: invokevirtual #51                 // Method getPort:()I
     156: invokevirtual #69                 // Method java/lang/StringBuilder.append:(I)Ljava/lang/StringBuilder;
     159: pop
     160: iload         4
     162: ifeq          174
     165: aload_0
     166: invokevirtual #223                // Method getServiceKey:()Ljava/lang/String;
     169: astore        8
     171: goto          180
     174: aload_0
     175: invokevirtual #52                 // Method getPath:()Ljava/lang/String;
     178: astore        8
     180: aload         8
     182: invokestatic  #18                 // Method org/apache/dubbo/common/utils/StringUtils.isNotEmpty:(Ljava/lang/String;)Z
     185: ifeq          204
     188: aload         6
     190: bipush        47
     192: invokevirtual #85                 // Method java/lang/StringBuilder.append:(C)Ljava/lang/StringBuilder;
     195: pop
     196: aload         6
     198: aload         8
     200: invokevirtual #67                 // Method java/lang/StringBuilder.append:(Ljava/lang/String;)Ljava/lang/StringBuilder;
     203: pop
     204: iload_2
     205: ifeq          217
     208: aload_0
     209: aload         6
     211: iconst_1
     212: aload         5
     214: invokevirtual #213                // Method buildParameters:(Ljava/lang/StringBuilder;Z[Ljava/lang/String;)V
     217: aload         6
     219: invokevirtual #70                 // Method java/lang/StringBuilder.toString:()Ljava/lang/String;
     222: areturn

  public java.net.URL toJavaURL();
    Code:
       0: new           #224                // class java/net/URL
       3: dup
       4: aload_0
       5: invokevirtual #225                // Method toString:()Ljava/lang/String;
       8: invokespecial #226                // Method java/net/URL."<init>":(Ljava/lang/String;)V
      11: areturn
      12: astore_1
      13: new           #228                // class java/lang/IllegalStateException
      16: dup
      17: aload_1
      18: invokevirtual #229                // Method java/net/MalformedURLException.getMessage:()Ljava/lang/String;
      21: aload_1
      22: invokespecial #230                // Method java/lang/IllegalStateException."<init>":(Ljava/lang/String;Ljava/lang/Throwable;)V
      25: athrow
    Exception table:
       from    to  target type
           0    11    12   Class java/net/MalformedURLException

  public java.net.InetSocketAddress toInetSocketAddress();
    Code:
       0: new           #231                // class java/net/InetSocketAddress
       3: dup
       4: aload_0
       5: invokevirtual #50                 // Method getHost:()Ljava/lang/String;
       8: aload_0
       9: invokevirtual #51                 // Method getPort:()I
      12: invokespecial #232                // Method java/net/InetSocketAddress."<init>":(Ljava/lang/String;I)V
      15: areturn

  public java.lang.String getColonSeparatedKey();
    Code:
       0: new           #65                 // class java/lang/StringBuilder
       3: dup
       4: invokespecial #66                 // Method java/lang/StringBuilder."<init>":()V
       7: astore_1
       8: aload_1
       9: aload_0
      10: invokevirtual #233                // Method getServiceInterface:()Ljava/lang/String;
      13: invokevirtual #67                 // Method java/lang/StringBuilder.append:(Ljava/lang/String;)Ljava/lang/StringBuilder;
      16: pop
      17: aload_0
      18: aload_1
      19: ldc           #234                // String version
      21: iconst_0
      22: invokespecial #235                // Method append:(Ljava/lang/StringBuilder;Ljava/lang/String;Z)V
      25: aload_0
      26: aload_1
      27: ldc           #236                // String group
      29: iconst_0
      30: invokespecial #235                // Method append:(Ljava/lang/StringBuilder;Ljava/lang/String;Z)V
      33: aload_1
      34: invokevirtual #70                 // Method java/lang/StringBuilder.toString:()Ljava/lang/String;
      37: areturn

  private void append(java.lang.StringBuilder, java.lang.String, boolean);
    Code:
       0: aload_0
       1: aload_2
       2: invokevirtual #118                // Method getParameter:(Ljava/lang/String;)Ljava/lang/String;
       5: astore        4
       7: aload         4
       9: invokestatic  #124                // Method org/apache/dubbo/common/utils/StringUtils.isBlank:(Ljava/lang/CharSequence;)Z
      12: ifne          36
      15: iload_3
      16: ifne          26
      19: aload_1
      20: bipush        58
      22: invokevirtual #85                 // Method java/lang/StringBuilder.append:(C)Ljava/lang/StringBuilder;
      25: pop
      26: aload_1
      27: aload         4
      29: invokevirtual #67                 // Method java/lang/StringBuilder.append:(Ljava/lang/String;)Ljava/lang/StringBuilder;
      32: pop
      33: goto          43
      36: aload_1
      37: bipush        58
      39: invokevirtual #85                 // Method java/lang/StringBuilder.append:(C)Ljava/lang/StringBuilder;
      42: pop
      43: return

  public java.lang.String getServiceKey();
    Code:
       0: aload_0
       1: getfield      #237                // Field serviceKey:Ljava/lang/String;
       4: ifnull        12
       7: aload_0
       8: getfield      #237                // Field serviceKey:Ljava/lang/String;
      11: areturn
      12: aload_0
      13: invokevirtual #233                // Method getServiceInterface:()Ljava/lang/String;
      16: astore_1
      17: aload_1
      18: ifnonnull     23
      21: aconst_null
      22: areturn
      23: aload_0
      24: aload_1
      25: aload_0
      26: invokevirtual #238                // Method getGroup:()Ljava/lang/String;
      29: aload_0
      30: invokevirtual #239                // Method getVersion:()Ljava/lang/String;
      33: invokestatic  #240                // Method buildKey:(Ljava/lang/String;Ljava/lang/String;Ljava/lang/String;)Ljava/lang/String;
      36: putfield      #237                // Field serviceKey:Ljava/lang/String;
      39: aload_0
      40: getfield      #237                // Field serviceKey:Ljava/lang/String;
      43: areturn

  public java.lang.String getDisplayServiceKey();
    Code:
       0: aload_0
       1: invokevirtual #239                // Method getVersion:()Ljava/lang/String;
       4: invokestatic  #17                 // Method org/apache/dubbo/common/utils/StringUtils.isEmpty:(Ljava/lang/String;)Z
       7: ifeq          15
      10: aload_0
      11: invokevirtual #233                // Method getServiceInterface:()Ljava/lang/String;
      14: areturn
      15: new           #65                 // class java/lang/StringBuilder
      18: dup
      19: invokespecial #66                 // Method java/lang/StringBuilder."<init>":()V
      22: aload_0
      23: invokevirtual #233                // Method getServiceInterface:()Ljava/lang/String;
      26: invokevirtual #67                 // Method java/lang/StringBuilder.append:(Ljava/lang/String;)Ljava/lang/StringBuilder;
      29: bipush        58
      31: invokevirtual #85                 // Method java/lang/StringBuilder.append:(C)Ljava/lang/StringBuilder;
      34: aload_0
      35: invokevirtual #239                // Method getVersion:()Ljava/lang/String;
      38: invokevirtual #67                 // Method java/lang/StringBuilder.append:(Ljava/lang/String;)Ljava/lang/StringBuilder;
      41: invokevirtual #70                 // Method java/lang/StringBuilder.toString:()Ljava/lang/String;
      44: areturn

  public java.lang.String getPathKey();
    Code:
       0: aload_0
       1: invokevirtual #52                 // Method getPath:()Ljava/lang/String;
       4: invokestatic  #18                 // Method org/apache/dubbo/common/utils/StringUtils.isNotEmpty:(Ljava/lang/String;)Z
       7: ifeq          17
      10: aload_0
      11: invokevirtual #52                 // Method getPath:()Ljava/lang/String;
      14: goto          21
      17: aload_0
      18: invokevirtual #233                // Method getServiceInterface:()Ljava/lang/String;
      21: astore_1
      22: aload_1
      23: ifnonnull     28
      26: aconst_null
      27: areturn
      28: aload_1
      29: aload_0
      30: invokevirtual #238                // Method getGroup:()Ljava/lang/String;
      33: aload_0
      34: invokevirtual #239                // Method getVersion:()Ljava/lang/String;
      37: invokestatic  #240                // Method buildKey:(Ljava/lang/String;Ljava/lang/String;Ljava/lang/String;)Ljava/lang/String;
      40: areturn

  public static java.lang.String buildKey(java.lang.String, java.lang.String, java.lang.String);
    Code:
       0: aload_0
       1: aload_1
       2: aload_2
       3: invokestatic  #241                // Method org/apache/dubbo/common/BaseServiceMetadata.buildServiceKey:(Ljava/lang/String;Ljava/lang/String;Ljava/lang/String;)Ljava/lang/String;
       6: areturn

  public java.lang.String getProtocolServiceKey();
    Code:
       0: aload_0
       1: getfield      #242                // Field protocolServiceKey:Ljava/lang/String;
       4: ifnull        12
       7: aload_0
       8: getfield      #242                // Field protocolServiceKey:Ljava/lang/String;
      11: areturn
      12: aload_0
      13: aload_0
      14: invokevirtual #223                // Method getServiceKey:()Ljava/lang/String;
      17: putfield      #242                // Field protocolServiceKey:Ljava/lang/String;
      20: ldc           #243                // String consumer
      22: aload_0
      23: invokevirtual #47                 // Method getProtocol:()Ljava/lang/String;
      26: invokevirtual #176                // Method java/lang/String.equals:(Ljava/lang/Object;)Z
      29: ifne          65
      32: new           #65                 // class java/lang/StringBuilder
      35: dup
      36: invokespecial #66                 // Method java/lang/StringBuilder."<init>":()V
      39: aload_0
      40: dup_x1
      41: getfield      #242                // Field protocolServiceKey:Ljava/lang/String;
      44: invokevirtual #67                 // Method java/lang/StringBuilder.append:(Ljava/lang/String;)Ljava/lang/StringBuilder;
      47: ldc           #68                 // String :
      49: invokevirtual #67                 // Method java/lang/StringBuilder.append:(Ljava/lang/String;)Ljava/lang/StringBuilder;
      52: aload_0
      53: invokevirtual #47                 // Method getProtocol:()Ljava/lang/String;
      56: invokevirtual #67                 // Method java/lang/StringBuilder.append:(Ljava/lang/String;)Ljava/lang/StringBuilder;
      59: invokevirtual #70                 // Method java/lang/StringBuilder.toString:()Ljava/lang/String;
      62: putfield      #242                // Field protocolServiceKey:Ljava/lang/String;
      65: aload_0
      66: getfield      #242                // Field protocolServiceKey:Ljava/lang/String;
      69: areturn

  public java.lang.String toServiceStringWithoutResolving();
    Code:
       0: aload_0
       1: iconst_1
       2: iconst_0
       3: iconst_0
       4: iconst_1
       5: iconst_0
       6: anewarray     #35                 // class java/lang/String
       9: invokespecial #221                // Method buildString:(ZZZZ[Ljava/lang/String;)Ljava/lang/String;
      12: areturn

  public java.lang.String toServiceString();
    Code:
       0: aload_0
       1: iconst_1
       2: iconst_0
       3: iconst_1
       4: iconst_1
       5: iconst_0
       6: anewarray     #35                 // class java/lang/String
       9: invokespecial #221                // Method buildString:(ZZZZ[Ljava/lang/String;)Ljava/lang/String;
      12: areturn

  public java.lang.String getServiceName();
    Code:
       0: aload_0
       1: invokevirtual #233                // Method getServiceInterface:()Ljava/lang/String;
       4: areturn

  public java.lang.String getServiceInterface();
    Code:
       0: aload_0
       1: ldc           #244                // String interface
       3: aload_0
       4: invokevirtual #52                 // Method getPath:()Ljava/lang/String;
       7: invokevirtual #116                // Method getParameter:(Ljava/lang/String;Ljava/lang/String;)Ljava/lang/String;
      10: areturn

  public org.apache.dubbo.common.URL setServiceInterface(java.lang.String);
    Code:
       0: aload_0
       1: ldc           #244                // String interface
       3: aload_1
       4: invokevirtual #179                // Method addParameter:(Ljava/lang/String;Ljava/lang/String;)Lorg/apache/dubbo/common/URL;
       7: areturn

  public int getIntParameter(java.lang.String);
    Code:
       0: aload_0
       1: aload_1
       2: iconst_0
       3: invokevirtual #151                // Method getParameter:(Ljava/lang/String;I)I
       6: ireturn

  public int getIntParameter(java.lang.String, int);
    Code:
       0: aload_0
       1: aload_1
       2: iload_2
       3: invokevirtual #151                // Method getParameter:(Ljava/lang/String;I)I
       6: ireturn

  public int getPositiveIntParameter(java.lang.String, int);
    Code:
       0: aload_0
       1: aload_1
       2: iload_2
       3: invokevirtual #245                // Method getPositiveParameter:(Ljava/lang/String;I)I
       6: ireturn

  public boolean getBooleanParameter(java.lang.String);
    Code:
       0: aload_0
       1: aload_1
       2: iconst_0
       3: invokevirtual #174                // Method getParameter:(Ljava/lang/String;Z)Z
       6: ireturn

  public boolean getBooleanParameter(java.lang.String, boolean);
    Code:
       0: aload_0
       1: aload_1
       2: iload_2
       3: invokevirtual #174                // Method getParameter:(Ljava/lang/String;Z)Z
       6: ireturn

  public int getMethodIntParameter(java.lang.String, java.lang.String);
    Code:
       0: aload_0
       1: aload_1
       2: aload_2
       3: iconst_0
       4: invokevirtual #163                // Method getMethodParameter:(Ljava/lang/String;Ljava/lang/String;I)I
       7: ireturn

  public int getMethodIntParameter(java.lang.String, java.lang.String, int);
    Code:
       0: aload_0
       1: aload_1
       2: aload_2
       3: iload_3
       4: invokevirtual #163                // Method getMethodParameter:(Ljava/lang/String;Ljava/lang/String;I)I
       7: ireturn

  public int getMethodPositiveIntParameter(java.lang.String, java.lang.String, int);
    Code:
       0: aload_0
       1: aload_1
       2: aload_2
       3: iload_3
       4: invokevirtual #246                // Method getMethodPositiveParameter:(Ljava/lang/String;Ljava/lang/String;I)I
       7: ireturn

  public boolean getMethodBooleanParameter(java.lang.String, java.lang.String);
    Code:
       0: aload_0
       1: aload_1
       2: aload_2
       3: iconst_0
       4: invokevirtual #247                // Method getMethodParameter:(Ljava/lang/String;Ljava/lang/String;Z)Z
       7: ireturn

  public boolean getMethodBooleanParameter(java.lang.String, java.lang.String, boolean);
    Code:
       0: aload_0
       1: aload_1
       2: aload_2
       3: iload_3
       4: invokevirtual #247                // Method getMethodParameter:(Ljava/lang/String;Ljava/lang/String;Z)Z
       7: ireturn

  public org.apache.dubbo.common.config.Configuration toConfiguration();
    Code:
       0: new           #248                // class org/apache/dubbo/common/config/InmemoryConfiguration
       3: dup
       4: invokespecial #249                // Method org/apache/dubbo/common/config/InmemoryConfiguration."<init>":()V
       7: astore_1
       8: aload_1
       9: aload_0
      10: invokevirtual #34                 // Method getParameters:()Ljava/util/Map;
      13: invokevirtual #250                // Method org/apache/dubbo/common/config/InmemoryConfiguration.addProperties:(Ljava/util/Map;)V
      16: aload_1
      17: areturn

  public int hashCode();
    Code:
       0: aload_0
       1: getfield      #5                  // Field hashCodeCache:I
       4: iconst_m1
       5: if_icmpne     33
       8: aload_0
       9: iconst_2
      10: anewarray     #251                // class java/lang/Object
      13: dup
      14: iconst_0
      15: aload_0
      16: getfield      #6                  // Field urlAddress:Lorg/apache/dubbo/common/url/component/URLAddress;
      19: aastore
      20: dup
      21: iconst_1
      22: aload_0
      23: getfield      #10                 // Field urlParam:Lorg/apache/dubbo/common/url/component/URLParam;
      26: aastore
      27: invokestatic  #252                // Method java/util/Objects.hash:([Ljava/lang/Object;)I
      30: putfield      #5                  // Field hashCodeCache:I
      33: aload_0
      34: getfield      #5                  // Field hashCodeCache:I
      37: ireturn

  public boolean equals(java.lang.Object);
    Code:
       0: aload_0
       1: aload_1
       2: if_acmpne     7
       5: iconst_1
       6: ireturn
       7: aload_1
       8: ifnonnull     13
      11: iconst_0
      12: ireturn
      13: aload_1
      14: instanceof    #26                 // class org/apache/dubbo/common/URL
      17: ifne          22
      20: iconst_0
      21: ireturn
      22: aload_1
      23: checkcast     #26                 // class org/apache/dubbo/common/URL
      26: astore_2
      27: aload_0
      28: invokevirtual #253                // Method getUrlAddress:()Lorg/apache/dubbo/common/url/component/URLAddress;
      31: aload_2
      32: invokevirtual #253                // Method getUrlAddress:()Lorg/apache/dubbo/common/url/component/URLAddress;
      35: invokestatic  #254                // Method java/util/Objects.equals:(Ljava/lang/Object;Ljava/lang/Object;)Z
      38: ifeq          59
      41: aload_0
      42: invokevirtual #255                // Method getUrlParam:()Lorg/apache/dubbo/common/url/component/URLParam;
      45: aload_2
      46: invokevirtual #255                // Method getUrlParam:()Lorg/apache/dubbo/common/url/component/URLParam;
      49: invokestatic  #254                // Method java/util/Objects.equals:(Ljava/lang/Object;Ljava/lang/Object;)Z
      52: ifeq          59
      55: iconst_1
      56: goto          60
      59: iconst_0
      60: ireturn

  public static void putMethodParameter(java.lang.String, java.lang.String, java.lang.String, java.util.Map<java.lang.String, java.util.Map<java.lang.String, java.lang.String>>);
    Code:
       0: aload_3
       1: aload_0
       2: invokedynamic #256,  0            // InvokeDynamic #0:apply:()Ljava/util/function/Function;
       7: invokeinterface #257,  3          // InterfaceMethod java/util/Map.computeIfAbsent:(Ljava/lang/Object;Ljava/util/function/Function;)Ljava/lang/Object;
      12: checkcast     #14                 // class java/util/Map
      15: astore        4
      17: aload         4
      19: aload_1
      20: aload_2
      21: invokeinterface #28,  3           // InterfaceMethod java/util/Map.put:(Ljava/lang/Object;Ljava/lang/Object;)Ljava/lang/Object;
      26: pop
      27: return

  protected <T extends org.apache.dubbo.common.URL> T newURL(org.apache.dubbo.common.url.component.URLAddress, org.apache.dubbo.common.url.component.URLParam);
    Code:
       0: new           #46                 // class org/apache/dubbo/common/url/component/ServiceConfigURL
       3: dup
       4: aload_1
       5: aload_2
       6: aload_0
       7: getfield      #11                 // Field attributes:Ljava/util/Map;
      10: invokespecial #258                // Method org/apache/dubbo/common/url/component/ServiceConfigURL."<init>":(Lorg/apache/dubbo/common/url/component/URLAddress;Lorg/apache/dubbo/common/url/component/URLParam;Ljava/util/Map;)V
      13: areturn

  public java.lang.String getApplication(java.lang.String);
    Code:
       0: aload_0
       1: invokevirtual #259                // Method getApplication:()Ljava/lang/String;
       4: astore_2
       5: aload_2
       6: invokestatic  #17                 // Method org/apache/dubbo/common/utils/StringUtils.isEmpty:(Ljava/lang/String;)Z
       9: ifeq          16
      12: aload_1
      13: goto          17
      16: aload_2
      17: areturn

  public java.lang.String getApplication();
    Code:
       0: aload_0
       1: ldc_w         #260                // String application
       4: invokevirtual #118                // Method getParameter:(Ljava/lang/String;)Ljava/lang/String;
       7: areturn

  public java.lang.String getRemoteApplication();
    Code:
       0: aload_0
       1: ldc_w         #261                // String remote.application
       4: invokevirtual #118                // Method getParameter:(Ljava/lang/String;)Ljava/lang/String;
       7: areturn

  public java.lang.String getGroup();
    Code:
       0: aload_0
       1: ldc           #236                // String group
       3: invokevirtual #118                // Method getParameter:(Ljava/lang/String;)Ljava/lang/String;
       6: areturn

  public java.lang.String getGroup(java.lang.String);
    Code:
       0: aload_0
       1: invokevirtual #238                // Method getGroup:()Ljava/lang/String;
       4: astore_2
       5: aload_2
       6: invokestatic  #17                 // Method org/apache/dubbo/common/utils/StringUtils.isEmpty:(Ljava/lang/String;)Z
       9: ifeq          16
      12: aload_1
      13: goto          17
      16: aload_2
      17: areturn

  public java.lang.String getVersion();
    Code:
       0: aload_0
       1: ldc           #234                // String version
       3: invokevirtual #118                // Method getParameter:(Ljava/lang/String;)Ljava/lang/String;
       6: areturn

  public java.lang.String getVersion(java.lang.String);
    Code:
       0: aload_0
       1: invokevirtual #239                // Method getVersion:()Ljava/lang/String;
       4: astore_2
       5: aload_2
       6: invokestatic  #17                 // Method org/apache/dubbo/common/utils/StringUtils.isEmpty:(Ljava/lang/String;)Z
       9: ifeq          16
      12: aload_1
      13: goto          17
      16: aload_2
      17: areturn

  public java.lang.String getConcatenatedParameter(java.lang.String);
    Code:
       0: aload_0
       1: aload_1
       2: invokevirtual #118                // Method getParameter:(Ljava/lang/String;)Ljava/lang/String;
       5: areturn

  public java.lang.String getCategory(java.lang.String);
    Code:
       0: aload_0
       1: invokevirtual #262                // Method getCategory:()Ljava/lang/String;
       4: astore_2
       5: aload_2
       6: invokestatic  #17                 // Method org/apache/dubbo/common/utils/StringUtils.isEmpty:(Ljava/lang/String;)Z
       9: ifeq          14
      12: aload_1
      13: astore_2
      14: aload_2
      15: areturn

  public java.lang.String[] getCategory(java.lang.String[]);
    Code:
       0: aload_0
       1: invokevirtual #262                // Method getCategory:()Ljava/lang/String;
       4: astore_2
       5: aload_2
       6: invokestatic  #17                 // Method org/apache/dubbo/common/utils/StringUtils.isEmpty:(Ljava/lang/String;)Z
       9: ifeq          16
      12: aload_1
      13: goto          23
      16: getstatic     #120                // Field org/apache/dubbo/common/constants/CommonConstants.COMMA_SPLIT_PATTERN:Ljava/util/regex/Pattern;
      19: aload_2
      20: invokevirtual #121                // Method java/util/regex/Pattern.split:(Ljava/lang/CharSequence;)[Ljava/lang/String;
      23: areturn

  public java.lang.String getCategory();
    Code:
       0: aload_0
       1: ldc_w         #263                // String category
       4: invokevirtual #118                // Method getParameter:(Ljava/lang/String;)Ljava/lang/String;
       7: areturn

  public java.lang.String getSide(java.lang.String);
    Code:
       0: aload_0
       1: invokevirtual #264                // Method getSide:()Ljava/lang/String;
       4: astore_2
       5: aload_2
       6: invokestatic  #17                 // Method org/apache/dubbo/common/utils/StringUtils.isEmpty:(Ljava/lang/String;)Z
       9: ifeq          16
      12: aload_1
      13: goto          17
      16: aload_2
      17: areturn

  public java.lang.String getSide();
    Code:
       0: aload_0
       1: ldc_w         #265                // String side
       4: invokevirtual #118                // Method getParameter:(Ljava/lang/String;)Ljava/lang/String;
       7: areturn

  public java.util.Map<java.lang.String, java.lang.Object> getAttributes();
    Code:
       0: aload_0
       1: getfield      #11                 // Field attributes:Ljava/util/Map;
       4: ifnonnull     13
       7: invokestatic  #266                // Method java/util/Collections.emptyMap:()Ljava/util/Map;
      10: goto          17
      13: aload_0
      14: getfield      #11                 // Field attributes:Ljava/util/Map;
      17: areturn

  public org.apache.dubbo.common.URL addAttributes(java.util.Map<java.lang.String, java.lang.Object>);
    Code:
       0: aload_1
       1: ifnull        11
       4: aload_1
       5: aload_1
       6: invokeinterface #267,  2          // InterfaceMethod java/util/Map.putAll:(Ljava/util/Map;)V
      11: aload_0
      12: areturn

  public java.lang.Object getAttribute(java.lang.String);
    Code:
       0: aload_0
       1: getfield      #11                 // Field attributes:Ljava/util/Map;
       4: ifnonnull     11
       7: aconst_null
       8: goto          21
      11: aload_0
      12: getfield      #11                 // Field attributes:Ljava/util/Map;
      15: aload_1
      16: invokeinterface #25,  2           // InterfaceMethod java/util/Map.get:(Ljava/lang/Object;)Ljava/lang/Object;
      21: areturn

  public java.lang.Object getAttribute(java.lang.String, java.lang.Object);
    Code:
       0: aload_0
       1: getfield      #11                 // Field attributes:Ljava/util/Map;
       4: ifnonnull     11
       7: aconst_null
       8: goto          21
      11: aload_0
      12: getfield      #11                 // Field attributes:Ljava/util/Map;
      15: aload_1
      16: invokeinterface #25,  2           // InterfaceMethod java/util/Map.get:(Ljava/lang/Object;)Ljava/lang/Object;
      21: astore_3
      22: aload_3
      23: ifnull        30
      26: aload_3
      27: goto          31
      30: aload_2
      31: areturn

  public org.apache.dubbo.common.URL putAttribute(java.lang.String, java.lang.Object);
    Code:
       0: aload_0
       1: getfield      #11                 // Field attributes:Ljava/util/Map;
       4: ifnonnull     18
       7: aload_0
       8: new           #7                  // class java/util/HashMap
      11: dup
      12: invokespecial #8                  // Method java/util/HashMap."<init>":()V
      15: putfield      #11                 // Field attributes:Ljava/util/Map;
      18: aload_0
      19: getfield      #11                 // Field attributes:Ljava/util/Map;
      22: aload_1
      23: aload_2
      24: invokeinterface #28,  3           // InterfaceMethod java/util/Map.put:(Ljava/lang/Object;Ljava/lang/Object;)Ljava/lang/Object;
      29: pop
      30: aload_0
      31: areturn

  public org.apache.dubbo.common.URL removeAttribute(java.lang.String);
    Code:
       0: aload_0
       1: getfield      #11                 // Field attributes:Ljava/util/Map;
       4: ifnull        18
       7: aload_0
       8: getfield      #11                 // Field attributes:Ljava/util/Map;
      11: aload_1
      12: invokeinterface #268,  2          // InterfaceMethod java/util/Map.remove:(Ljava/lang/Object;)Ljava/lang/Object;
      17: pop
      18: aload_0
      19: areturn

  public boolean hasAttribute(java.lang.String);
    Code:
       0: aload_0
       1: getfield      #11                 // Field attributes:Ljava/util/Map;
       4: ifnull        24
       7: aload_0
       8: getfield      #11                 // Field attributes:Ljava/util/Map;
      11: aload_1
      12: invokeinterface #269,  2          // InterfaceMethod java/util/Map.containsKey:(Ljava/lang/Object;)Z
      17: ifeq          24
      20: iconst_1
      21: goto          25
      24: iconst_0
      25: ireturn

  private org.apache.dubbo.common.URL returnURL(org.apache.dubbo.common.url.component.URLAddress);
    Code:
       0: aload_0
       1: getfield      #6                  // Field urlAddress:Lorg/apache/dubbo/common/url/component/URLAddress;
       4: aload_1
       5: if_acmpne     10
       8: aload_0
       9: areturn
      10: aload_0
      11: aload_1
      12: aload_0
      13: getfield      #10                 // Field urlParam:Lorg/apache/dubbo/common/url/component/URLParam;
      16: invokevirtual #270                // Method newURL:(Lorg/apache/dubbo/common/url/component/URLAddress;Lorg/apache/dubbo/common/url/component/URLParam;)Lorg/apache/dubbo/common/URL;
      19: areturn

  private org.apache.dubbo.common.URL returnURL(org.apache.dubbo.common.url.component.URLParam);
    Code:
       0: aload_0
       1: getfield      #10                 // Field urlParam:Lorg/apache/dubbo/common/url/component/URLParam;
       4: aload_1
       5: if_acmpne     10
       8: aload_0
       9: areturn
      10: aload_0
      11: aload_0
      12: getfield      #6                  // Field urlAddress:Lorg/apache/dubbo/common/url/component/URLAddress;
      15: aload_1
      16: invokevirtual #270                // Method newURL:(Lorg/apache/dubbo/common/url/component/URLAddress;Lorg/apache/dubbo/common/url/component/URLParam;)Lorg/apache/dubbo/common/URL;
      19: areturn

  public java.util.Map<java.lang.String, java.lang.String> getOriginalServiceParameters(java.lang.String);
    Code:
       0: aload_0
       1: aload_1
       2: invokevirtual #271                // Method getServiceParameters:(Ljava/lang/String;)Ljava/util/Map;
       5: areturn

  public java.util.Map<java.lang.String, java.lang.String> getServiceParameters(java.lang.String);
    Code:
       0: aload_0
       1: invokevirtual #34                 // Method getParameters:()Ljava/util/Map;
       4: areturn

  public java.lang.String getOriginalServiceParameter(java.lang.String, java.lang.String);
    Code:
       0: aload_0
       1: aload_1
       2: aload_2
       3: invokevirtual #272                // Method getServiceParameter:(Ljava/lang/String;Ljava/lang/String;)Ljava/lang/String;
       6: areturn

  public java.lang.String getServiceParameter(java.lang.String, java.lang.String);
    Code:
       0: aload_0
       1: aload_2
       2: invokevirtual #118                // Method getParameter:(Ljava/lang/String;)Ljava/lang/String;
       5: areturn

  public java.lang.String getServiceParameter(java.lang.String, java.lang.String, java.lang.String);
    Code:
       0: aload_0
       1: aload_1
       2: aload_2
       3: invokevirtual #272                // Method getServiceParameter:(Ljava/lang/String;Ljava/lang/String;)Ljava/lang/String;
       6: astore        4
       8: aload         4
      10: invokestatic  #17                 // Method org/apache/dubbo/common/utils/StringUtils.isEmpty:(Ljava/lang/String;)Z
      13: ifeq          20
      16: aload_3
      17: goto          22
      20: aload         4
      22: areturn

  public int getServiceParameter(java.lang.String, java.lang.String, int);
    Code:
       0: aload_0
       1: aload_2
       2: iload_3
       3: invokevirtual #151                // Method getParameter:(Ljava/lang/String;I)I
       6: ireturn

  public double getServiceParameter(java.lang.String, java.lang.String, double);
    Code:
       0: aload_0
       1: aload_1
       2: aload_2
       3: invokevirtual #272                // Method getServiceParameter:(Ljava/lang/String;Ljava/lang/String;)Ljava/lang/String;
       6: astore        5
       8: aload         5
      10: invokestatic  #17                 // Method org/apache/dubbo/common/utils/StringUtils.isEmpty:(Ljava/lang/String;)Z
      13: ifeq          18
      16: dload_3
      17: dreturn
      18: aload         5
      20: invokestatic  #142                // Method java/lang/Double.parseDouble:(Ljava/lang/String;)D
      23: dreturn

  public float getServiceParameter(java.lang.String, java.lang.String, float);
    Code:
       0: aload_0
       1: aload_1
       2: aload_2
       3: invokevirtual #272                // Method getServiceParameter:(Ljava/lang/String;Ljava/lang/String;)Ljava/lang/String;
       6: astore        4
       8: aload         4
      10: invokestatic  #17                 // Method org/apache/dubbo/common/utils/StringUtils.isEmpty:(Ljava/lang/String;)Z
      13: ifeq          18
      16: fload_3
      17: freturn
      18: aload         4
      20: invokestatic  #143                // Method java/lang/Float.parseFloat:(Ljava/lang/String;)F
      23: freturn

  public long getServiceParameter(java.lang.String, java.lang.String, long);
    Code:
       0: aload_0
       1: aload_1
       2: aload_2
       3: invokevirtual #272                // Method getServiceParameter:(Ljava/lang/String;Ljava/lang/String;)Ljava/lang/String;
       6: astore        5
       8: aload         5
      10: invokestatic  #17                 // Method org/apache/dubbo/common/utils/StringUtils.isEmpty:(Ljava/lang/String;)Z
      13: ifeq          18
      16: lload_3
      17: lreturn
      18: aload         5
      20: invokestatic  #144                // Method java/lang/Long.parseLong:(Ljava/lang/String;)J
      23: lreturn

  public short getServiceParameter(java.lang.String, java.lang.String, short);
    Code:
       0: aload_0
       1: aload_1
       2: aload_2
       3: invokevirtual #272                // Method getServiceParameter:(Ljava/lang/String;Ljava/lang/String;)Ljava/lang/String;
       6: astore        4
       8: aload         4
      10: invokestatic  #17                 // Method org/apache/dubbo/common/utils/StringUtils.isEmpty:(Ljava/lang/String;)Z
      13: ifeq          18
      16: iload_3
      17: ireturn
      18: aload         4
      20: invokestatic  #145                // Method java/lang/Short.parseShort:(Ljava/lang/String;)S
      23: ireturn

  public byte getServiceParameter(java.lang.String, java.lang.String, byte);
    Code:
       0: aload_0
       1: aload_1
       2: aload_2
       3: invokevirtual #272                // Method getServiceParameter:(Ljava/lang/String;Ljava/lang/String;)Ljava/lang/String;
       6: astore        4
       8: aload         4
      10: invokestatic  #17                 // Method org/apache/dubbo/common/utils/StringUtils.isEmpty:(Ljava/lang/String;)Z
      13: ifeq          18
      16: iload_3
      17: ireturn
      18: aload         4
      20: invokestatic  #146                // Method java/lang/Byte.parseByte:(Ljava/lang/String;)B
      23: ireturn

  public char getServiceParameter(java.lang.String, java.lang.String, char);
    Code:
       0: aload_0
       1: aload_1
       2: aload_2
       3: invokevirtual #272                // Method getServiceParameter:(Ljava/lang/String;Ljava/lang/String;)Ljava/lang/String;
       6: astore        4
       8: aload         4
      10: invokestatic  #17                 // Method org/apache/dubbo/common/utils/StringUtils.isEmpty:(Ljava/lang/String;)Z
      13: ifeq          20
      16: iload_3
      17: goto          26
      20: aload         4
      22: iconst_0
      23: invokevirtual #154                // Method java/lang/String.charAt:(I)C
      26: ireturn

  public boolean getServiceParameter(java.lang.String, java.lang.String, boolean);
    Code:
       0: aload_0
       1: aload_1
       2: aload_2
       3: invokevirtual #272                // Method getServiceParameter:(Ljava/lang/String;Ljava/lang/String;)Ljava/lang/String;
       6: astore        4
       8: aload         4
      10: invokestatic  #17                 // Method org/apache/dubbo/common/utils/StringUtils.isEmpty:(Ljava/lang/String;)Z
      13: ifeq          20
      16: iload_3
      17: goto          25
      20: aload         4
      22: invokestatic  #155                // Method java/lang/Boolean.parseBoolean:(Ljava/lang/String;)Z
      25: ireturn

  public boolean hasServiceParameter(java.lang.String, java.lang.String);
    Code:
       0: aload_0
       1: aload_1
       2: aload_2
       3: invokevirtual #272                // Method getServiceParameter:(Ljava/lang/String;Ljava/lang/String;)Ljava/lang/String;
       6: astore_3
       7: aload_3
       8: ifnull        22
      11: aload_3
      12: invokevirtual #63                 // Method java/lang/String.length:()I
      15: ifle          22
      18: iconst_1
      19: goto          23
      22: iconst_0
      23: ireturn

  public float getPositiveServiceParameter(java.lang.String, java.lang.String, float);
    Code:
       0: fload_3
       1: fconst_0
       2: fcmpg
       3: ifgt          16
       6: new           #19                 // class java/lang/IllegalArgumentException
       9: dup
      10: ldc           #147                // String defaultValue <= 0
      12: invokespecial #21                 // Method java/lang/IllegalArgumentException."<init>":(Ljava/lang/String;)V
      15: athrow
      16: aload_0
      17: aload_1
      18: aload_2
      19: fload_3
      20: invokevirtual #273                // Method getServiceParameter:(Ljava/lang/String;Ljava/lang/String;F)F
      23: fstore        4
      25: fload         4
      27: fconst_0
      28: fcmpg
      29: ifgt          36
      32: fload_3
      33: goto          38
      36: fload         4
      38: freturn

  public double getPositiveServiceParameter(java.lang.String, java.lang.String, double);
    Code:
       0: dload_3
       1: dconst_0
       2: dcmpg
       3: ifgt          16
       6: new           #19                 // class java/lang/IllegalArgumentException
       9: dup
      10: ldc           #147                // String defaultValue <= 0
      12: invokespecial #21                 // Method java/lang/IllegalArgumentException."<init>":(Ljava/lang/String;)V
      15: athrow
      16: aload_0
      17: aload_1
      18: aload_2
      19: dload_3
      20: invokevirtual #274                // Method getServiceParameter:(Ljava/lang/String;Ljava/lang/String;D)D
      23: dstore        5
      25: dload         5
      27: dconst_0
      28: dcmpg
      29: ifgt          36
      32: dload_3
      33: goto          38
      36: dload         5
      38: dreturn

  public long getPositiveServiceParameter(java.lang.String, java.lang.String, long);
    Code:
       0: lload_3
       1: lconst_0
       2: lcmp
       3: ifgt          16
       6: new           #19                 // class java/lang/IllegalArgumentException
       9: dup
      10: ldc           #147                // String defaultValue <= 0
      12: invokespecial #21                 // Method java/lang/IllegalArgumentException."<init>":(Ljava/lang/String;)V
      15: athrow
      16: aload_0
      17: aload_1
      18: aload_2
      19: lload_3
      20: invokevirtual #275                // Method getServiceParameter:(Ljava/lang/String;Ljava/lang/String;J)J
      23: lstore        5
      25: lload         5
      27: lconst_0
      28: lcmp
      29: ifgt          36
      32: lload_3
      33: goto          38
      36: lload         5
      38: lreturn

  public int getPositiveServiceParameter(java.lang.String, java.lang.String, int);
    Code:
       0: iload_3
       1: ifgt          14
       4: new           #19                 // class java/lang/IllegalArgumentException
       7: dup
       8: ldc           #147                // String defaultValue <= 0
      10: invokespecial #21                 // Method java/lang/IllegalArgumentException."<init>":(Ljava/lang/String;)V
      13: athrow
      14: aload_0
      15: aload_1
      16: aload_2
      17: iload_3
      18: invokevirtual #276                // Method getServiceParameter:(Ljava/lang/String;Ljava/lang/String;I)I
      21: istore        4
      23: iload         4
      25: ifgt          32
      28: iload_3
      29: goto          34
      32: iload         4
      34: ireturn

  public short getPositiveServiceParameter(java.lang.String, java.lang.String, short);
    Code:
       0: iload_3
       1: ifgt          14
       4: new           #19                 // class java/lang/IllegalArgumentException
       7: dup
       8: ldc           #147                // String defaultValue <= 0
      10: invokespecial #21                 // Method java/lang/IllegalArgumentException."<init>":(Ljava/lang/String;)V
      13: athrow
      14: aload_0
      15: aload_1
      16: aload_2
      17: iload_3
      18: invokevirtual #277                // Method getServiceParameter:(Ljava/lang/String;Ljava/lang/String;S)S
      21: istore        4
      23: iload         4
      25: ifgt          32
      28: iload_3
      29: goto          34
      32: iload         4
      34: ireturn

  public byte getPositiveServiceParameter(java.lang.String, java.lang.String, byte);
    Code:
       0: iload_3
       1: ifgt          14
       4: new           #19                 // class java/lang/IllegalArgumentException
       7: dup
       8: ldc           #147                // String defaultValue <= 0
      10: invokespecial #21                 // Method java/lang/IllegalArgumentException."<init>":(Ljava/lang/String;)V
      13: athrow
      14: aload_0
      15: aload_1
      16: aload_2
      17: iload_3
      18: invokevirtual #278                // Method getServiceParameter:(Ljava/lang/String;Ljava/lang/String;B)B
      21: istore        4
      23: iload         4
      25: ifgt          32
      28: iload_3
      29: goto          34
      32: iload         4
      34: ireturn

  public java.lang.String getServiceMethodParameterAndDecoded(java.lang.String, java.lang.String, java.lang.String);
    Code:
       0: aload_0
       1: aload_1
       2: aload_2
       3: aload_3
       4: invokevirtual #279                // Method getServiceMethodParameter:(Ljava/lang/String;Ljava/lang/String;Ljava/lang/String;)Ljava/lang/String;
       7: invokestatic  #117                // Method decode:(Ljava/lang/String;)Ljava/lang/String;
      10: areturn

  public java.lang.String getServiceMethodParameterAndDecoded(java.lang.String, java.lang.String, java.lang.String, java.lang.String);
    Code:
       0: aload_0
       1: aload_1
       2: aload_2
       3: aload_3
       4: aload         4
       6: invokevirtual #280                // Method getServiceMethodParameter:(Ljava/lang/String;Ljava/lang/String;Ljava/lang/String;Ljava/lang/String;)Ljava/lang/String;
       9: invokestatic  #117                // Method decode:(Ljava/lang/String;)Ljava/lang/String;
      12: areturn

  public java.lang.String getServiceMethodParameterStrict(java.lang.String, java.lang.String, java.lang.String);
    Code:
       0: aload_0
       1: aload_2
       2: aload_3
       3: invokevirtual #169                // Method getMethodParameterStrict:(Ljava/lang/String;Ljava/lang/String;)Ljava/lang/String;
       6: areturn

  public java.lang.String getServiceMethodParameter(java.lang.String, java.lang.String, java.lang.String);
    Code:
       0: aload_0
       1: aload_2
       2: aload_3
       3: invokevirtual #156                // Method getMethodParameter:(Ljava/lang/String;Ljava/lang/String;)Ljava/lang/String;
       6: areturn

  public java.lang.String getServiceMethodParameter(java.lang.String, java.lang.String, java.lang.String, java.lang.String);
    Code:
       0: aload_0
       1: aload_1
       2: aload_2
       3: aload_3
       4: invokevirtual #279                // Method getServiceMethodParameter:(Ljava/lang/String;Ljava/lang/String;Ljava/lang/String;)Ljava/lang/String;
       7: astore        5
       9: aload         5
      11: invokestatic  #17                 // Method org/apache/dubbo/common/utils/StringUtils.isEmpty:(Ljava/lang/String;)Z
      14: ifeq          22
      17: aload         4
      19: goto          24
      22: aload         5
      24: areturn

  public double getServiceMethodParameter(java.lang.String, java.lang.String, java.lang.String, double);
    Code:
       0: aload_0
       1: aload_1
       2: aload_2
       3: aload_3
       4: invokevirtual #279                // Method getServiceMethodParameter:(Ljava/lang/String;Ljava/lang/String;Ljava/lang/String;)Ljava/lang/String;
       7: astore        6
       9: aload         6
      11: invokestatic  #17                 // Method org/apache/dubbo/common/utils/StringUtils.isEmpty:(Ljava/lang/String;)Z
      14: ifeq          20
      17: dload         4
      19: dreturn
      20: aload         6
      22: invokestatic  #142                // Method java/lang/Double.parseDouble:(Ljava/lang/String;)D
      25: dreturn

  public float getServiceMethodParameter(java.lang.String, java.lang.String, java.lang.String, float);
    Code:
       0: aload_0
       1: aload_1
       2: aload_2
       3: aload_3
       4: invokevirtual #279                // Method getServiceMethodParameter:(Ljava/lang/String;Ljava/lang/String;Ljava/lang/String;)Ljava/lang/String;
       7: astore        5
       9: aload         5
      11: invokestatic  #17                 // Method org/apache/dubbo/common/utils/StringUtils.isEmpty:(Ljava/lang/String;)Z
      14: ifeq          20
      17: fload         4
      19: freturn
      20: aload         5
      22: invokestatic  #143                // Method java/lang/Float.parseFloat:(Ljava/lang/String;)F
      25: freturn

  public long getServiceMethodParameter(java.lang.String, java.lang.String, java.lang.String, long);
    Code:
       0: aload_0
       1: aload_1
       2: aload_2
       3: aload_3
       4: invokevirtual #279                // Method getServiceMethodParameter:(Ljava/lang/String;Ljava/lang/String;Ljava/lang/String;)Ljava/lang/String;
       7: astore        6
       9: aload         6
      11: invokestatic  #17                 // Method org/apache/dubbo/common/utils/StringUtils.isEmpty:(Ljava/lang/String;)Z
      14: ifeq          20
      17: lload         4
      19: lreturn
      20: aload         6
      22: invokestatic  #144                // Method java/lang/Long.parseLong:(Ljava/lang/String;)J
      25: lreturn

  public int getServiceMethodParameter(java.lang.String, java.lang.String, java.lang.String, int);
    Code:
       0: aload_0
       1: aload_1
       2: aload_2
       3: aload_3
       4: invokevirtual #279                // Method getServiceMethodParameter:(Ljava/lang/String;Ljava/lang/String;Ljava/lang/String;)Ljava/lang/String;
       7: astore        5
       9: aload         5
      11: invokestatic  #17                 // Method org/apache/dubbo/common/utils/StringUtils.isEmpty:(Ljava/lang/String;)Z
      14: ifeq          20
      17: iload         4
      19: ireturn
      20: aload         5
      22: invokestatic  #72                 // Method java/lang/Integer.parseInt:(Ljava/lang/String;)I
      25: ireturn

  public short getServiceMethodParameter(java.lang.String, java.lang.String, java.lang.String, short);
    Code:
       0: aload_0
       1: aload_1
       2: aload_2
       3: aload_3
       4: invokevirtual #279                // Method getServiceMethodParameter:(Ljava/lang/String;Ljava/lang/String;Ljava/lang/String;)Ljava/lang/String;
       7: astore        5
       9: aload         5
      11: invokestatic  #17                 // Method org/apache/dubbo/common/utils/StringUtils.isEmpty:(Ljava/lang/String;)Z
      14: ifeq          20
      17: iload         4
      19: ireturn
      20: aload         5
      22: invokestatic  #145                // Method java/lang/Short.parseShort:(Ljava/lang/String;)S
      25: ireturn

  public byte getServiceMethodParameter(java.lang.String, java.lang.String, java.lang.String, byte);
    Code:
       0: aload_0
       1: aload_1
       2: aload_2
       3: aload_3
       4: invokevirtual #279                // Method getServiceMethodParameter:(Ljava/lang/String;Ljava/lang/String;Ljava/lang/String;)Ljava/lang/String;
       7: astore        5
       9: aload         5
      11: invokestatic  #17                 // Method org/apache/dubbo/common/utils/StringUtils.isEmpty:(Ljava/lang/String;)Z
      14: ifeq          20
      17: iload         4
      19: ireturn
      20: aload         5
      22: invokestatic  #146                // Method java/lang/Byte.parseByte:(Ljava/lang/String;)B
      25: ireturn

  public boolean hasServiceMethodParameter(java.lang.String, java.lang.String, java.lang.String);
    Code:
       0: aload_0
       1: aload_2
       2: aload_3
       3: invokevirtual #281                // Method hasMethodParameter:(Ljava/lang/String;Ljava/lang/String;)Z
       6: ireturn

  public boolean hasServiceMethodParameter(java.lang.String, java.lang.String);
    Code:
       0: aload_0
       1: aload_2
       2: invokevirtual #282                // Method hasMethodParameter:(Ljava/lang/String;)Z
       5: ireturn

  public org.apache.dubbo.common.URL toSerializableURL();
    Code:
       0: aload_0
       1: aload_0
       2: getfield      #10                 // Field urlParam:Lorg/apache/dubbo/common/url/component/URLParam;
       5: invokestatic  #283                // Method org/apache/dubbo/common/url/component/URLPlainParam.toURLPlainParam:(Lorg/apache/dubbo/common/url/component/URLParam;)Lorg/apache/dubbo/common/url/component/URLPlainParam;
       8: invokespecial #189                // Method returnURL:(Lorg/apache/dubbo/common/url/component/URLParam;)Lorg/apache/dubbo/common/URL;
      11: areturn

  private static java.util.Map lambda$putMethodParameter$0(java.lang.String);
    Code:
       0: new           #7                  // class java/util/HashMap
       3: dup
       4: invokespecial #8                  // Method java/util/HashMap."<init>":()V
       7: areturn

  static {};
    Code:
       0: new           #284                // class org/apache/dubbo/common/utils/LRUCache
       3: dup
       4: invokespecial #285                // Method org/apache/dubbo/common/utils/LRUCache."<init>":()V
       7: putstatic     #24                 // Field cachedURLs:Ljava/util/Map;
      10: return
}
