Compiled from "URLBuilder.java"
public final class org.apache.dubbo.common.URLBuilder extends org.apache.dubbo.common.url.component.ServiceConfigURL {
  private java.lang.String protocol;

  private java.lang.String username;

  private java.lang.String password;

  private java.lang.String host;

  private int port;

  private java.lang.String path;

  private final java.util.Map<java.lang.String, java.lang.String> parameters;

  private final java.util.Map<java.lang.String, java.lang.Object> attributes;

  private java.util.Map<java.lang.String, java.util.Map<java.lang.String, java.lang.String>> methodParameters;

  public org.apache.dubbo.common.URLBuilder();
    Code:
       0: aload_0
       1: invokespecial #2                  // Method org/apache/dubbo/common/url/component/ServiceConfigURL."<init>":()V
       4: aload_0
       5: aconst_null
       6: putfield      #3                  // Field protocol:Ljava/lang/String;
       9: aload_0
      10: aconst_null
      11: putfield      #4                  // Field username:Ljava/lang/String;
      14: aload_0
      15: aconst_null
      16: putfield      #5                  // Field password:Ljava/lang/String;
      19: aload_0
      20: aconst_null
      21: putfield      #6                  // Field host:Ljava/lang/String;
      24: aload_0
      25: iconst_0
      26: putfield      #7                  // Field port:I
      29: aload_0
      30: aconst_null
      31: putfield      #8                  // Field path:Ljava/lang/String;
      34: aload_0
      35: new           #9                  // class java/util/HashMap
      38: dup
      39: invokespecial #10                 // Method java/util/HashMap."<init>":()V
      42: putfield      #11                 // Field parameters:Ljava/util/Map;
      45: aload_0
      46: new           #9                  // class java/util/HashMap
      49: dup
      50: invokespecial #10                 // Method java/util/HashMap."<init>":()V
      53: putfield      #12                 // Field attributes:Ljava/util/Map;
      56: aload_0
      57: new           #9                  // class java/util/HashMap
      60: dup
      61: invokespecial #10                 // Method java/util/HashMap."<init>":()V
      64: putfield      #13                 // Field methodParameters:Ljava/util/Map;
      67: return

  public org.apache.dubbo.common.URLBuilder(java.lang.String, java.lang.String, int);
    Code:
       0: aload_0
       1: aload_1
       2: aconst_null
       3: aconst_null
       4: aload_2
       5: iload_3
       6: aconst_null
       7: aconst_null
       8: invokespecial #14                 // Method "<init>":(Ljava/lang/String;Ljava/lang/String;Ljava/lang/String;Ljava/lang/String;ILjava/lang/String;Ljava/util/Map;)V
      11: return

  public org.apache.dubbo.common.URLBuilder(java.lang.String, java.lang.String, int, java.lang.String[]);
    Code:
       0: aload_0
       1: aload_1
       2: aconst_null
       3: aconst_null
       4: aload_2
       5: iload_3
       6: aconst_null
       7: aload         4
       9: invokestatic  #15                 // Method org/apache/dubbo/common/utils/CollectionUtils.toStringMap:([Ljava/lang/String;)Ljava/util/Map;
      12: invokespecial #14                 // Method "<init>":(Ljava/lang/String;Ljava/lang/String;Ljava/lang/String;Ljava/lang/String;ILjava/lang/String;Ljava/util/Map;)V
      15: return

  public org.apache.dubbo.common.URLBuilder(java.lang.String, java.lang.String, int, java.util.Map<java.lang.String, java.lang.String>);
    Code:
       0: aload_0
       1: aload_1
       2: aconst_null
       3: aconst_null
       4: aload_2
       5: iload_3
       6: aconst_null
       7: aload         4
       9: invokespecial #14                 // Method "<init>":(Ljava/lang/String;Ljava/lang/String;Ljava/lang/String;Ljava/lang/String;ILjava/lang/String;Ljava/util/Map;)V
      12: return

  public org.apache.dubbo.common.URLBuilder(java.lang.String, java.lang.String, int, java.lang.String);
    Code:
       0: aload_0
       1: aload_1
       2: aconst_null
       3: aconst_null
       4: aload_2
       5: iload_3
       6: aload         4
       8: aconst_null
       9: invokespecial #14                 // Method "<init>":(Ljava/lang/String;Ljava/lang/String;Ljava/lang/String;Ljava/lang/String;ILjava/lang/String;Ljava/util/Map;)V
      12: return

  public org.apache.dubbo.common.URLBuilder(java.lang.String, java.lang.String, int, java.lang.String, java.lang.String...);
    Code:
       0: aload_0
       1: aload_1
       2: aconst_null
       3: aconst_null
       4: aload_2
       5: iload_3
       6: aload         4
       8: aload         5
      10: invokestatic  #15                 // Method org/apache/dubbo/common/utils/CollectionUtils.toStringMap:([Ljava/lang/String;)Ljava/util/Map;
      13: invokespecial #14                 // Method "<init>":(Ljava/lang/String;Ljava/lang/String;Ljava/lang/String;Ljava/lang/String;ILjava/lang/String;Ljava/util/Map;)V
      16: return

  public org.apache.dubbo.common.URLBuilder(java.lang.String, java.lang.String, int, java.lang.String, java.util.Map<java.lang.String, java.lang.String>);
    Code:
       0: aload_0
       1: aload_1
       2: aconst_null
       3: aconst_null
       4: aload_2
       5: iload_3
       6: aload         4
       8: aload         5
      10: invokespecial #14                 // Method "<init>":(Ljava/lang/String;Ljava/lang/String;Ljava/lang/String;Ljava/lang/String;ILjava/lang/String;Ljava/util/Map;)V
      13: return

  public org.apache.dubbo.common.URLBuilder(java.lang.String, java.lang.String, java.lang.String, java.lang.String, int, java.lang.String, java.util.Map<java.lang.String, java.lang.String>);
    Code:
       0: aload_0
       1: aload_1
       2: aload_2
       3: aload_3
       4: aload         4
       6: iload         5
       8: aload         6
      10: aload         7
      12: aconst_null
      13: invokespecial #16                 // Method "<init>":(Ljava/lang/String;Ljava/lang/String;Ljava/lang/String;Ljava/lang/String;ILjava/lang/String;Ljava/util/Map;Ljava/util/Map;)V
      16: return

  public org.apache.dubbo.common.URLBuilder(java.lang.String, java.lang.String, java.lang.String, java.lang.String, int, java.lang.String, java.util.Map<java.lang.String, java.lang.String>, java.util.Map<java.lang.String, java.lang.Object>);
    Code:
       0: aload_0
       1: invokespecial #2                  // Method org/apache/dubbo/common/url/component/ServiceConfigURL."<init>":()V
       4: aload_0
       5: aload_1
       6: putfield      #3                  // Field protocol:Ljava/lang/String;
       9: aload_0
      10: aload_2
      11: putfield      #4                  // Field username:Ljava/lang/String;
      14: aload_0
      15: aload_3
      16: putfield      #5                  // Field password:Ljava/lang/String;
      19: aload_0
      20: aload         4
      22: putfield      #6                  // Field host:Ljava/lang/String;
      25: aload_0
      26: iload         5
      28: putfield      #7                  // Field port:I
      31: aload_0
      32: aload         6
      34: putfield      #8                  // Field path:Ljava/lang/String;
      37: aload_0
      38: aload         7
      40: ifnull        48
      43: aload         7
      45: goto          55
      48: new           #9                  // class java/util/HashMap
      51: dup
      52: invokespecial #10                 // Method java/util/HashMap."<init>":()V
      55: putfield      #11                 // Field parameters:Ljava/util/Map;
      58: aload_0
      59: aload         8
      61: ifnull        69
      64: aload         8
      66: goto          76
      69: new           #9                  // class java/util/HashMap
      72: dup
      73: invokespecial #10                 // Method java/util/HashMap."<init>":()V
      76: putfield      #12                 // Field attributes:Ljava/util/Map;
      79: return

  public static org.apache.dubbo.common.URLBuilder from(org.apache.dubbo.common.URL);
    Code:
       0: aload_0
       1: invokevirtual #17                 // Method org/apache/dubbo/common/URL.getProtocol:()Ljava/lang/String;
       4: astore_1
       5: aload_0
       6: invokevirtual #18                 // Method org/apache/dubbo/common/URL.getUsername:()Ljava/lang/String;
       9: astore_2
      10: aload_0
      11: invokevirtual #19                 // Method org/apache/dubbo/common/URL.getPassword:()Ljava/lang/String;
      14: astore_3
      15: aload_0
      16: invokevirtual #20                 // Method org/apache/dubbo/common/URL.getHost:()Ljava/lang/String;
      19: astore        4
      21: aload_0
      22: invokevirtual #21                 // Method org/apache/dubbo/common/URL.getPort:()I
      25: istore        5
      27: aload_0
      28: invokevirtual #22                 // Method org/apache/dubbo/common/URL.getPath:()Ljava/lang/String;
      31: astore        6
      33: new           #9                  // class java/util/HashMap
      36: dup
      37: aload_0
      38: invokevirtual #23                 // Method org/apache/dubbo/common/URL.getParameters:()Ljava/util/Map;
      41: invokespecial #24                 // Method java/util/HashMap."<init>":(Ljava/util/Map;)V
      44: astore        7
      46: new           #9                  // class java/util/HashMap
      49: dup
      50: aload_0
      51: invokevirtual #25                 // Method org/apache/dubbo/common/URL.getAttributes:()Ljava/util/Map;
      54: invokespecial #24                 // Method java/util/HashMap."<init>":(Ljava/util/Map;)V
      57: astore        8
      59: new           #26                 // class org/apache/dubbo/common/URLBuilder
      62: dup
      63: aload_1
      64: aload_2
      65: aload_3
      66: aload         4
      68: iload         5
      70: aload         6
      72: aload         7
      74: aload         8
      76: invokespecial #16                 // Method "<init>":(Ljava/lang/String;Ljava/lang/String;Ljava/lang/String;Ljava/lang/String;ILjava/lang/String;Ljava/util/Map;Ljava/util/Map;)V
      79: areturn

  public org.apache.dubbo.common.url.component.ServiceConfigURL build();
    Code:
       0: aload_0
       1: getfield      #4                  // Field username:Ljava/lang/String;
       4: invokestatic  #27                 // Method org/apache/dubbo/common/utils/StringUtils.isEmpty:(Ljava/lang/String;)Z
       7: ifeq          30
      10: aload_0
      11: getfield      #5                  // Field password:Ljava/lang/String;
      14: invokestatic  #28                 // Method org/apache/dubbo/common/utils/StringUtils.isNotEmpty:(Ljava/lang/String;)Z
      17: ifeq          30
      20: new           #29                 // class java/lang/IllegalArgumentException
      23: dup
      24: ldc           #30                 // String Invalid url, password without username!
      26: invokespecial #31                 // Method java/lang/IllegalArgumentException."<init>":(Ljava/lang/String;)V
      29: athrow
      30: aload_0
      31: aload_0
      32: getfield      #7                  // Field port:I
      35: iconst_0
      36: invokestatic  #32                 // Method java/lang/Math.max:(II)I
      39: putfield      #7                  // Field port:I
      42: iconst_0
      43: istore_1
      44: aload_0
      45: getfield      #8                  // Field path:Ljava/lang/String;
      48: ifnull        117
      51: iload_1
      52: aload_0
      53: getfield      #8                  // Field path:Ljava/lang/String;
      56: invokevirtual #33                 // Method java/lang/String.length:()I
      59: if_icmpge     81
      62: aload_0
      63: getfield      #8                  // Field path:Ljava/lang/String;
      66: iload_1
      67: invokevirtual #34                 // Method java/lang/String.charAt:(I)C
      70: bipush        47
      72: if_icmpne     81
      75: iinc          1, 1
      78: goto          51
      81: iload_1
      82: aload_0
      83: getfield      #8                  // Field path:Ljava/lang/String;
      86: invokevirtual #33                 // Method java/lang/String.length:()I
      89: if_icmplt     101
      92: aload_0
      93: ldc           #35                 // String
      95: putfield      #8                  // Field path:Ljava/lang/String;
      98: goto          117
     101: iload_1
     102: ifle          117
     105: aload_0
     106: aload_0
     107: getfield      #8                  // Field path:Ljava/lang/String;
     110: iload_1
     111: invokevirtual #36                 // Method java/lang/String.substring:(I)Ljava/lang/String;
     114: putfield      #8                  // Field path:Ljava/lang/String;
     117: new           #37                 // class org/apache/dubbo/common/url/component/ServiceConfigURL
     120: dup
     121: aload_0
     122: getfield      #3                  // Field protocol:Ljava/lang/String;
     125: aload_0
     126: getfield      #4                  // Field username:Ljava/lang/String;
     129: aload_0
     130: getfield      #5                  // Field password:Ljava/lang/String;
     133: aload_0
     134: getfield      #6                  // Field host:Ljava/lang/String;
     137: aload_0
     138: getfield      #7                  // Field port:I
     141: aload_0
     142: getfield      #8                  // Field path:Ljava/lang/String;
     145: aload_0
     146: getfield      #11                 // Field parameters:Ljava/util/Map;
     149: aload_0
     150: getfield      #12                 // Field attributes:Ljava/util/Map;
     153: invokespecial #38                 // Method org/apache/dubbo/common/url/component/ServiceConfigURL."<init>":(Ljava/lang/String;Ljava/lang/String;Ljava/lang/String;Ljava/lang/String;ILjava/lang/String;Ljava/util/Map;Ljava/util/Map;)V
     156: areturn

  public org.apache.dubbo.common.URLBuilder putAttribute(java.lang.String, java.lang.Object);
    Code:
       0: aload_0
       1: getfield      #12                 // Field attributes:Ljava/util/Map;
       4: aload_1
       5: aload_2
       6: invokeinterface #39,  3           // InterfaceMethod java/util/Map.put:(Ljava/lang/Object;Ljava/lang/Object;)Ljava/lang/Object;
      11: pop
      12: aload_0
      13: areturn

  public org.apache.dubbo.common.URLBuilder removeAttribute(java.lang.String);
    Code:
       0: aload_0
       1: getfield      #12                 // Field attributes:Ljava/util/Map;
       4: aload_1
       5: invokeinterface #40,  2           // InterfaceMethod java/util/Map.remove:(Ljava/lang/Object;)Ljava/lang/Object;
      10: pop
      11: aload_0
      12: areturn

  public org.apache.dubbo.common.URLBuilder setProtocol(java.lang.String);
    Code:
       0: aload_0
       1: aload_1
       2: putfield      #3                  // Field protocol:Ljava/lang/String;
       5: aload_0
       6: areturn

  public org.apache.dubbo.common.URLBuilder setUsername(java.lang.String);
    Code:
       0: aload_0
       1: aload_1
       2: putfield      #4                  // Field username:Ljava/lang/String;
       5: aload_0
       6: areturn

  public org.apache.dubbo.common.URLBuilder setPassword(java.lang.String);
    Code:
       0: aload_0
       1: aload_1
       2: putfield      #5                  // Field password:Ljava/lang/String;
       5: aload_0
       6: areturn

  public org.apache.dubbo.common.URLBuilder setHost(java.lang.String);
    Code:
       0: aload_0
       1: aload_1
       2: putfield      #6                  // Field host:Ljava/lang/String;
       5: aload_0
       6: areturn

  public org.apache.dubbo.common.URLBuilder setPort(int);
    Code:
       0: aload_0
       1: iload_1
       2: putfield      #7                  // Field port:I
       5: aload_0
       6: areturn

  public org.apache.dubbo.common.URLBuilder setAddress(java.lang.String);
    Code:
       0: aload_1
       1: bipush        58
       3: invokevirtual #41                 // Method java/lang/String.lastIndexOf:(I)I
       6: istore_2
       7: aload_0
       8: getfield      #7                  // Field port:I
      11: istore        4
      13: iload_2
      14: iflt          39
      17: aload_1
      18: iconst_0
      19: iload_2
      20: invokevirtual #42                 // Method java/lang/String.substring:(II)Ljava/lang/String;
      23: astore_3
      24: aload_1
      25: iload_2
      26: iconst_1
      27: iadd
      28: invokevirtual #36                 // Method java/lang/String.substring:(I)Ljava/lang/String;
      31: invokestatic  #43                 // Method java/lang/Integer.parseInt:(Ljava/lang/String;)I
      34: istore        4
      36: goto          41
      39: aload_1
      40: astore_3
      41: aload_0
      42: aload_3
      43: putfield      #6                  // Field host:Ljava/lang/String;
      46: aload_0
      47: iload         4
      49: putfield      #7                  // Field port:I
      52: aload_0
      53: areturn

  public org.apache.dubbo.common.URLBuilder setPath(java.lang.String);
    Code:
       0: aload_0
       1: aload_1
       2: putfield      #8                  // Field path:Ljava/lang/String;
       5: aload_0
       6: areturn

  public org.apache.dubbo.common.URLBuilder setScopeModel(org.apache.dubbo.rpc.model.ScopeModel);
    Code:
       0: aload_0
       1: getfield      #12                 // Field attributes:Ljava/util/Map;
       4: ldc           #44                 // String scopeModel
       6: aload_1
       7: invokeinterface #39,  3           // InterfaceMethod java/util/Map.put:(Ljava/lang/Object;Ljava/lang/Object;)Ljava/lang/Object;
      12: pop
      13: aload_0
      14: areturn

  public org.apache.dubbo.common.URLBuilder addParameterAndEncoded(java.lang.String, java.lang.String);
    Code:
       0: aload_2
       1: invokestatic  #27                 // Method org/apache/dubbo/common/utils/StringUtils.isEmpty:(Ljava/lang/String;)Z
       4: ifeq          9
       7: aload_0
       8: areturn
       9: aload_0
      10: aload_1
      11: aload_2
      12: invokestatic  #45                 // Method org/apache/dubbo/common/URL.encode:(Ljava/lang/String;)Ljava/lang/String;
      15: invokevirtual #46                 // Method addParameter:(Ljava/lang/String;Ljava/lang/String;)Lorg/apache/dubbo/common/URLBuilder;
      18: areturn

  public org.apache.dubbo.common.URLBuilder addParameter(java.lang.String, boolean);
    Code:
       0: aload_0
       1: aload_1
       2: iload_2
       3: invokestatic  #47                 // Method java/lang/String.valueOf:(Z)Ljava/lang/String;
       6: invokevirtual #46                 // Method addParameter:(Ljava/lang/String;Ljava/lang/String;)Lorg/apache/dubbo/common/URLBuilder;
       9: areturn

  public org.apache.dubbo.common.URLBuilder addParameter(java.lang.String, char);
    Code:
       0: aload_0
       1: aload_1
       2: iload_2
       3: invokestatic  #48                 // Method java/lang/String.valueOf:(C)Ljava/lang/String;
       6: invokevirtual #46                 // Method addParameter:(Ljava/lang/String;Ljava/lang/String;)Lorg/apache/dubbo/common/URLBuilder;
       9: areturn

  public org.apache.dubbo.common.URLBuilder addParameter(java.lang.String, byte);
    Code:
       0: aload_0
       1: aload_1
       2: iload_2
       3: invokestatic  #49                 // Method java/lang/String.valueOf:(I)Ljava/lang/String;
       6: invokevirtual #46                 // Method addParameter:(Ljava/lang/String;Ljava/lang/String;)Lorg/apache/dubbo/common/URLBuilder;
       9: areturn

  public org.apache.dubbo.common.URLBuilder addParameter(java.lang.String, short);
    Code:
       0: aload_0
       1: aload_1
       2: iload_2
       3: invokestatic  #49                 // Method java/lang/String.valueOf:(I)Ljava/lang/String;
       6: invokevirtual #46                 // Method addParameter:(Ljava/lang/String;Ljava/lang/String;)Lorg/apache/dubbo/common/URLBuilder;
       9: areturn

  public org.apache.dubbo.common.URLBuilder addParameter(java.lang.String, int);
    Code:
       0: aload_0
       1: aload_1
       2: iload_2
       3: invokestatic  #49                 // Method java/lang/String.valueOf:(I)Ljava/lang/String;
       6: invokevirtual #46                 // Method addParameter:(Ljava/lang/String;Ljava/lang/String;)Lorg/apache/dubbo/common/URLBuilder;
       9: areturn

  public org.apache.dubbo.common.URLBuilder addParameter(java.lang.String, long);
    Code:
       0: aload_0
       1: aload_1
       2: lload_2
       3: invokestatic  #50                 // Method java/lang/String.valueOf:(J)Ljava/lang/String;
       6: invokevirtual #46                 // Method addParameter:(Ljava/lang/String;Ljava/lang/String;)Lorg/apache/dubbo/common/URLBuilder;
       9: areturn

  public org.apache.dubbo.common.URLBuilder addParameter(java.lang.String, float);
    Code:
       0: aload_0
       1: aload_1
       2: fload_2
       3: invokestatic  #51                 // Method java/lang/String.valueOf:(F)Ljava/lang/String;
       6: invokevirtual #46                 // Method addParameter:(Ljava/lang/String;Ljava/lang/String;)Lorg/apache/dubbo/common/URLBuilder;
       9: areturn

  public org.apache.dubbo.common.URLBuilder addParameter(java.lang.String, double);
    Code:
       0: aload_0
       1: aload_1
       2: dload_2
       3: invokestatic  #52                 // Method java/lang/String.valueOf:(D)Ljava/lang/String;
       6: invokevirtual #46                 // Method addParameter:(Ljava/lang/String;Ljava/lang/String;)Lorg/apache/dubbo/common/URLBuilder;
       9: areturn

  public org.apache.dubbo.common.URLBuilder addParameter(java.lang.String, java.lang.Enum<?>);
    Code:
       0: aload_2
       1: ifnonnull     6
       4: aload_0
       5: areturn
       6: aload_0
       7: aload_1
       8: aload_2
       9: invokestatic  #53                 // Method java/lang/String.valueOf:(Ljava/lang/Object;)Ljava/lang/String;
      12: invokevirtual #46                 // Method addParameter:(Ljava/lang/String;Ljava/lang/String;)Lorg/apache/dubbo/common/URLBuilder;
      15: areturn

  public org.apache.dubbo.common.URLBuilder addParameter(java.lang.String, java.lang.Number);
    Code:
       0: aload_2
       1: ifnonnull     6
       4: aload_0
       5: areturn
       6: aload_0
       7: aload_1
       8: aload_2
       9: invokestatic  #53                 // Method java/lang/String.valueOf:(Ljava/lang/Object;)Ljava/lang/String;
      12: invokevirtual #46                 // Method addParameter:(Ljava/lang/String;Ljava/lang/String;)Lorg/apache/dubbo/common/URLBuilder;
      15: areturn

  public org.apache.dubbo.common.URLBuilder addParameter(java.lang.String, java.lang.CharSequence);
    Code:
       0: aload_2
       1: ifnull        13
       4: aload_2
       5: invokeinterface #54,  1           // InterfaceMethod java/lang/CharSequence.length:()I
      10: ifne          15
      13: aload_0
      14: areturn
      15: aload_0
      16: aload_1
      17: aload_2
      18: invokestatic  #53                 // Method java/lang/String.valueOf:(Ljava/lang/Object;)Ljava/lang/String;
      21: invokevirtual #46                 // Method addParameter:(Ljava/lang/String;Ljava/lang/String;)Lorg/apache/dubbo/common/URLBuilder;
      24: areturn

  public org.apache.dubbo.common.URLBuilder addParameter(java.lang.String, java.lang.String);
    Code:
       0: aload_1
       1: invokestatic  #27                 // Method org/apache/dubbo/common/utils/StringUtils.isEmpty:(Ljava/lang/String;)Z
       4: ifne          14
       7: aload_2
       8: invokestatic  #27                 // Method org/apache/dubbo/common/utils/StringUtils.isEmpty:(Ljava/lang/String;)Z
      11: ifeq          16
      14: aload_0
      15: areturn
      16: aload_0
      17: getfield      #11                 // Field parameters:Ljava/util/Map;
      20: aload_1
      21: aload_2
      22: invokeinterface #39,  3           // InterfaceMethod java/util/Map.put:(Ljava/lang/Object;Ljava/lang/Object;)Ljava/lang/Object;
      27: pop
      28: aload_0
      29: areturn

  public org.apache.dubbo.common.URLBuilder addMethodParameter(java.lang.String, java.lang.String, java.lang.String);
    Code:
       0: aload_1
       1: invokestatic  #27                 // Method org/apache/dubbo/common/utils/StringUtils.isEmpty:(Ljava/lang/String;)Z
       4: ifne          21
       7: aload_2
       8: invokestatic  #27                 // Method org/apache/dubbo/common/utils/StringUtils.isEmpty:(Ljava/lang/String;)Z
      11: ifne          21
      14: aload_3
      15: invokestatic  #27                 // Method org/apache/dubbo/common/utils/StringUtils.isEmpty:(Ljava/lang/String;)Z
      18: ifeq          23
      21: aload_0
      22: areturn
      23: aload_1
      24: aload_2
      25: aload_3
      26: aload_0
      27: getfield      #13                 // Field methodParameters:Ljava/util/Map;
      30: invokestatic  #55                 // Method org/apache/dubbo/common/URL.putMethodParameter:(Ljava/lang/String;Ljava/lang/String;Ljava/lang/String;Ljava/util/Map;)V
      33: aload_0
      34: areturn

  public org.apache.dubbo.common.URLBuilder addParameterIfAbsent(java.lang.String, java.lang.String);
    Code:
       0: aload_1
       1: invokestatic  #27                 // Method org/apache/dubbo/common/utils/StringUtils.isEmpty:(Ljava/lang/String;)Z
       4: ifne          14
       7: aload_2
       8: invokestatic  #27                 // Method org/apache/dubbo/common/utils/StringUtils.isEmpty:(Ljava/lang/String;)Z
      11: ifeq          16
      14: aload_0
      15: areturn
      16: aload_0
      17: aload_1
      18: invokevirtual #56                 // Method hasParameter:(Ljava/lang/String;)Z
      21: ifeq          26
      24: aload_0
      25: areturn
      26: aload_0
      27: getfield      #11                 // Field parameters:Ljava/util/Map;
      30: aload_1
      31: aload_2
      32: invokeinterface #39,  3           // InterfaceMethod java/util/Map.put:(Ljava/lang/Object;Ljava/lang/Object;)Ljava/lang/Object;
      37: pop
      38: aload_0
      39: areturn

  public org.apache.dubbo.common.URLBuilder addMethodParameterIfAbsent(java.lang.String, java.lang.String, java.lang.String);
    Code:
       0: aload_1
       1: invokestatic  #27                 // Method org/apache/dubbo/common/utils/StringUtils.isEmpty:(Ljava/lang/String;)Z
       4: ifne          21
       7: aload_2
       8: invokestatic  #27                 // Method org/apache/dubbo/common/utils/StringUtils.isEmpty:(Ljava/lang/String;)Z
      11: ifne          21
      14: aload_3
      15: invokestatic  #27                 // Method org/apache/dubbo/common/utils/StringUtils.isEmpty:(Ljava/lang/String;)Z
      18: ifeq          23
      21: aload_0
      22: areturn
      23: aload_0
      24: aload_1
      25: aload_2
      26: invokevirtual #57                 // Method hasMethodParameter:(Ljava/lang/String;Ljava/lang/String;)Z
      29: ifeq          34
      32: aload_0
      33: areturn
      34: aload_1
      35: aload_2
      36: aload_3
      37: aload_0
      38: getfield      #13                 // Field methodParameters:Ljava/util/Map;
      41: invokestatic  #55                 // Method org/apache/dubbo/common/URL.putMethodParameter:(Ljava/lang/String;Ljava/lang/String;Ljava/lang/String;Ljava/util/Map;)V
      44: aload_0
      45: areturn

  public org.apache.dubbo.common.URLBuilder addParameters(java.util.Map<java.lang.String, java.lang.String>);
    Code:
       0: aload_1
       1: invokestatic  #58                 // Method org/apache/dubbo/common/utils/CollectionUtils.isEmptyMap:(Ljava/util/Map;)Z
       4: ifeq          9
       7: aload_0
       8: areturn
       9: iconst_1
      10: istore_2
      11: aload_1
      12: invokeinterface #59,  1           // InterfaceMethod java/util/Map.entrySet:()Ljava/util/Set;
      17: invokeinterface #60,  1           // InterfaceMethod java/util/Set.iterator:()Ljava/util/Iterator;
      22: astore_3
      23: aload_3
      24: invokeinterface #61,  1           // InterfaceMethod java/util/Iterator.hasNext:()Z
      29: ifeq          94
      32: aload_3
      33: invokeinterface #62,  1           // InterfaceMethod java/util/Iterator.next:()Ljava/lang/Object;
      38: checkcast     #63                 // class java/util/Map$Entry
      41: astore        4
      43: aload_0
      44: getfield      #11                 // Field parameters:Ljava/util/Map;
      47: aload         4
      49: invokeinterface #64,  1           // InterfaceMethod java/util/Map$Entry.getKey:()Ljava/lang/Object;
      54: invokeinterface #65,  2           // InterfaceMethod java/util/Map.get:(Ljava/lang/Object;)Ljava/lang/Object;
      59: checkcast     #66                 // class java/lang/String
      62: astore        5
      64: aload         4
      66: invokeinterface #67,  1           // InterfaceMethod java/util/Map$Entry.getValue:()Ljava/lang/Object;
      71: checkcast     #66                 // class java/lang/String
      74: astore        6
      76: aload         5
      78: aload         6
      80: invokestatic  #68                 // Method java/util/Objects.equals:(Ljava/lang/Object;Ljava/lang/Object;)Z
      83: ifne          91
      86: iconst_0
      87: istore_2
      88: goto          94
      91: goto          23
      94: iload_2
      95: ifeq          100
      98: aload_0
      99: areturn
     100: aload_0
     101: getfield      #11                 // Field parameters:Ljava/util/Map;
     104: aload_1
     105: invokeinterface #69,  2           // InterfaceMethod java/util/Map.putAll:(Ljava/util/Map;)V
     110: aload_0
     111: areturn

  public org.apache.dubbo.common.URLBuilder addMethodParameters(java.util.Map<java.lang.String, java.util.Map<java.lang.String, java.lang.String>>);
    Code:
       0: aload_1
       1: invokestatic  #58                 // Method org/apache/dubbo/common/utils/CollectionUtils.isEmptyMap:(Ljava/util/Map;)Z
       4: ifeq          9
       7: aload_0
       8: areturn
       9: aload_0
      10: getfield      #13                 // Field methodParameters:Ljava/util/Map;
      13: aload_1
      14: invokeinterface #69,  2           // InterfaceMethod java/util/Map.putAll:(Ljava/util/Map;)V
      19: aload_0
      20: areturn

  public org.apache.dubbo.common.URLBuilder addParametersIfAbsent(java.util.Map<java.lang.String, java.lang.String>);
    Code:
       0: aload_1
       1: invokestatic  #58                 // Method org/apache/dubbo/common/utils/CollectionUtils.isEmptyMap:(Ljava/util/Map;)Z
       4: ifeq          9
       7: aload_0
       8: areturn
       9: aload_1
      10: invokeinterface #59,  1           // InterfaceMethod java/util/Map.entrySet:()Ljava/util/Set;
      15: invokeinterface #60,  1           // InterfaceMethod java/util/Set.iterator:()Ljava/util/Iterator;
      20: astore_2
      21: aload_2
      22: invokeinterface #61,  1           // InterfaceMethod java/util/Iterator.hasNext:()Z
      27: ifeq          65
      30: aload_2
      31: invokeinterface #62,  1           // InterfaceMethod java/util/Iterator.next:()Ljava/lang/Object;
      36: checkcast     #63                 // class java/util/Map$Entry
      39: astore_3
      40: aload_0
      41: getfield      #11                 // Field parameters:Ljava/util/Map;
      44: aload_3
      45: invokeinterface #64,  1           // InterfaceMethod java/util/Map$Entry.getKey:()Ljava/lang/Object;
      50: aload_3
      51: invokeinterface #67,  1           // InterfaceMethod java/util/Map$Entry.getValue:()Ljava/lang/Object;
      56: invokeinterface #70,  3           // InterfaceMethod java/util/Map.putIfAbsent:(Ljava/lang/Object;Ljava/lang/Object;)Ljava/lang/Object;
      61: pop
      62: goto          21
      65: aload_0
      66: areturn

  public org.apache.dubbo.common.URLBuilder addParameters(java.lang.String...);
    Code:
       0: aload_1
       1: ifnull        9
       4: aload_1
       5: arraylength
       6: ifne          11
       9: aload_0
      10: areturn
      11: aload_1
      12: arraylength
      13: iconst_2
      14: irem
      15: ifeq          28
      18: new           #29                 // class java/lang/IllegalArgumentException
      21: dup
      22: ldc           #71                 // String Map pairs can not be odd number.
      24: invokespecial #31                 // Method java/lang/IllegalArgumentException."<init>":(Ljava/lang/String;)V
      27: athrow
      28: new           #9                  // class java/util/HashMap
      31: dup
      32: invokespecial #10                 // Method java/util/HashMap."<init>":()V
      35: astore_2
      36: aload_1
      37: arraylength
      38: iconst_2
      39: idiv
      40: istore_3
      41: iconst_0
      42: istore        4
      44: iload         4
      46: iload_3
      47: if_icmpge     77
      50: aload_2
      51: aload_1
      52: iconst_2
      53: iload         4
      55: imul
      56: aaload
      57: aload_1
      58: iconst_2
      59: iload         4
      61: imul
      62: iconst_1
      63: iadd
      64: aaload
      65: invokeinterface #39,  3           // InterfaceMethod java/util/Map.put:(Ljava/lang/Object;Ljava/lang/Object;)Ljava/lang/Object;
      70: pop
      71: iinc          4, 1
      74: goto          44
      77: aload_0
      78: aload_2
      79: invokevirtual #72                 // Method addParameters:(Ljava/util/Map;)Lorg/apache/dubbo/common/URLBuilder;
      82: areturn

  public org.apache.dubbo.common.URLBuilder addParameterString(java.lang.String);
    Code:
       0: aload_1
       1: invokestatic  #27                 // Method org/apache/dubbo/common/utils/StringUtils.isEmpty:(Ljava/lang/String;)Z
       4: ifeq          9
       7: aload_0
       8: areturn
       9: aload_0
      10: aload_1
      11: invokestatic  #73                 // Method org/apache/dubbo/common/utils/StringUtils.parseQueryString:(Ljava/lang/String;)Ljava/util/Map;
      14: invokevirtual #72                 // Method addParameters:(Ljava/util/Map;)Lorg/apache/dubbo/common/URLBuilder;
      17: areturn

  public org.apache.dubbo.common.URLBuilder removeParameter(java.lang.String);
    Code:
       0: aload_1
       1: invokestatic  #27                 // Method org/apache/dubbo/common/utils/StringUtils.isEmpty:(Ljava/lang/String;)Z
       4: ifeq          9
       7: aload_0
       8: areturn
       9: aload_0
      10: iconst_1
      11: anewarray     #66                 // class java/lang/String
      14: dup
      15: iconst_0
      16: aload_1
      17: aastore
      18: invokevirtual #74                 // Method removeParameters:([Ljava/lang/String;)Lorg/apache/dubbo/common/URLBuilder;
      21: areturn

  public org.apache.dubbo.common.URLBuilder removeParameters(java.util.Collection<java.lang.String>);
    Code:
       0: aload_1
       1: invokestatic  #75                 // Method org/apache/dubbo/common/utils/CollectionUtils.isEmpty:(Ljava/util/Collection;)Z
       4: ifeq          9
       7: aload_0
       8: areturn
       9: aload_0
      10: aload_1
      11: iconst_0
      12: anewarray     #66                 // class java/lang/String
      15: invokeinterface #76,  2           // InterfaceMethod java/util/Collection.toArray:([Ljava/lang/Object;)[Ljava/lang/Object;
      20: checkcast     #77                 // class "[Ljava/lang/String;"
      23: invokevirtual #74                 // Method removeParameters:([Ljava/lang/String;)Lorg/apache/dubbo/common/URLBuilder;
      26: areturn

  public org.apache.dubbo.common.URLBuilder removeParameters(java.lang.String...);
    Code:
       0: aload_1
       1: ifnull        9
       4: aload_1
       5: arraylength
       6: ifne          11
       9: aload_0
      10: areturn
      11: aload_1
      12: astore_2
      13: aload_2
      14: arraylength
      15: istore_3
      16: iconst_0
      17: istore        4
      19: iload         4
      21: iload_3
      22: if_icmpge     49
      25: aload_2
      26: iload         4
      28: aaload
      29: astore        5
      31: aload_0
      32: getfield      #11                 // Field parameters:Ljava/util/Map;
      35: aload         5
      37: invokeinterface #40,  2           // InterfaceMethod java/util/Map.remove:(Ljava/lang/Object;)Ljava/lang/Object;
      42: pop
      43: iinc          4, 1
      46: goto          19
      49: aload_0
      50: areturn

  public org.apache.dubbo.common.URLBuilder clearParameters();
    Code:
       0: aload_0
       1: getfield      #11                 // Field parameters:Ljava/util/Map;
       4: invokeinterface #78,  1           // InterfaceMethod java/util/Map.clear:()V
       9: aload_0
      10: areturn

  public boolean hasParameter(java.lang.String);
    Code:
       0: aload_0
       1: aload_1
       2: invokevirtual #79                 // Method getParameter:(Ljava/lang/String;)Ljava/lang/String;
       5: astore_2
       6: aload_2
       7: invokestatic  #28                 // Method org/apache/dubbo/common/utils/StringUtils.isNotEmpty:(Ljava/lang/String;)Z
      10: ireturn

  public boolean hasMethodParameter(java.lang.String, java.lang.String);
    Code:
       0: aload_1
       1: ifnonnull     78
       4: new           #80                 // class java/lang/StringBuilder
       7: dup
       8: invokespecial #81                 // Method java/lang/StringBuilder."<init>":()V
      11: ldc           #82                 // String .
      13: invokevirtual #83                 // Method java/lang/StringBuilder.append:(Ljava/lang/String;)Ljava/lang/StringBuilder;
      16: aload_2
      17: invokevirtual #83                 // Method java/lang/StringBuilder.append:(Ljava/lang/String;)Ljava/lang/StringBuilder;
      20: invokevirtual #84                 // Method java/lang/StringBuilder.toString:()Ljava/lang/String;
      23: astore_3
      24: aload_0
      25: getfield      #11                 // Field parameters:Ljava/util/Map;
      28: invokeinterface #85,  1           // InterfaceMethod java/util/Map.keySet:()Ljava/util/Set;
      33: invokeinterface #60,  1           // InterfaceMethod java/util/Set.iterator:()Ljava/util/Iterator;
      38: astore        4
      40: aload         4
      42: invokeinterface #61,  1           // InterfaceMethod java/util/Iterator.hasNext:()Z
      47: ifeq          76
      50: aload         4
      52: invokeinterface #62,  1           // InterfaceMethod java/util/Iterator.next:()Ljava/lang/Object;
      57: checkcast     #66                 // class java/lang/String
      60: astore        5
      62: aload         5
      64: aload_3
      65: invokevirtual #86                 // Method java/lang/String.endsWith:(Ljava/lang/String;)Z
      68: ifeq          73
      71: iconst_1
      72: ireturn
      73: goto          40
      76: iconst_0
      77: ireturn
      78: aload_2
      79: ifnonnull     156
      82: new           #80                 // class java/lang/StringBuilder
      85: dup
      86: invokespecial #81                 // Method java/lang/StringBuilder."<init>":()V
      89: aload_1
      90: invokevirtual #83                 // Method java/lang/StringBuilder.append:(Ljava/lang/String;)Ljava/lang/StringBuilder;
      93: ldc           #82                 // String .
      95: invokevirtual #83                 // Method java/lang/StringBuilder.append:(Ljava/lang/String;)Ljava/lang/StringBuilder;
      98: invokevirtual #84                 // Method java/lang/StringBuilder.toString:()Ljava/lang/String;
     101: astore_3
     102: aload_0
     103: getfield      #11                 // Field parameters:Ljava/util/Map;
     106: invokeinterface #85,  1           // InterfaceMethod java/util/Map.keySet:()Ljava/util/Set;
     111: invokeinterface #60,  1           // InterfaceMethod java/util/Set.iterator:()Ljava/util/Iterator;
     116: astore        4
     118: aload         4
     120: invokeinterface #61,  1           // InterfaceMethod java/util/Iterator.hasNext:()Z
     125: ifeq          154
     128: aload         4
     130: invokeinterface #62,  1           // InterfaceMethod java/util/Iterator.next:()Ljava/lang/Object;
     135: checkcast     #66                 // class java/lang/String
     138: astore        5
     140: aload         5
     142: aload_3
     143: invokevirtual #87                 // Method java/lang/String.startsWith:(Ljava/lang/String;)Z
     146: ifeq          151
     149: iconst_1
     150: ireturn
     151: goto          118
     154: iconst_0
     155: ireturn
     156: aload_0
     157: aload_1
     158: aload_2
     159: invokevirtual #88                 // Method getMethodParameter:(Ljava/lang/String;Ljava/lang/String;)Ljava/lang/String;
     162: astore_3
     163: aload_3
     164: ifnull        178
     167: aload_3
     168: invokevirtual #33                 // Method java/lang/String.length:()I
     171: ifle          178
     174: iconst_1
     175: goto          179
     178: iconst_0
     179: ireturn

  public java.lang.String getParameter(java.lang.String);
    Code:
       0: aload_0
       1: getfield      #11                 // Field parameters:Ljava/util/Map;
       4: aload_1
       5: invokeinterface #65,  2           // InterfaceMethod java/util/Map.get:(Ljava/lang/Object;)Ljava/lang/Object;
      10: checkcast     #66                 // class java/lang/String
      13: areturn

  public java.lang.String getMethodParameter(java.lang.String, java.lang.String);
    Code:
       0: aload_0
       1: getfield      #13                 // Field methodParameters:Ljava/util/Map;
       4: aload_1
       5: invokeinterface #65,  2           // InterfaceMethod java/util/Map.get:(Ljava/lang/Object;)Ljava/lang/Object;
      10: checkcast     #89                 // class java/util/Map
      13: astore_3
      14: aconst_null
      15: astore        4
      17: aload_3
      18: ifnull        33
      21: aload_3
      22: aload_2
      23: invokeinterface #65,  2           // InterfaceMethod java/util/Map.get:(Ljava/lang/Object;)Ljava/lang/Object;
      28: checkcast     #66                 // class java/lang/String
      31: astore        4
      33: aload         4
      35: areturn

  public org.apache.dubbo.common.URL removeAttribute(java.lang.String);
    Code:
       0: aload_0
       1: aload_1
       2: invokevirtual #90                 // Method removeAttribute:(Ljava/lang/String;)Lorg/apache/dubbo/common/URLBuilder;
       5: areturn

  public org.apache.dubbo.common.url.component.ServiceConfigURL putAttribute(java.lang.String, java.lang.Object);
    Code:
       0: aload_0
       1: aload_1
       2: aload_2
       3: invokevirtual #91                 // Method putAttribute:(Ljava/lang/String;Ljava/lang/Object;)Lorg/apache/dubbo/common/URLBuilder;
       6: areturn

  public org.apache.dubbo.common.URL putAttribute(java.lang.String, java.lang.Object);
    Code:
       0: aload_0
       1: aload_1
       2: aload_2
       3: invokevirtual #91                 // Method putAttribute:(Ljava/lang/String;Ljava/lang/Object;)Lorg/apache/dubbo/common/URLBuilder;
       6: areturn

  public org.apache.dubbo.common.URL clearParameters();
    Code:
       0: aload_0
       1: invokevirtual #92                 // Method clearParameters:()Lorg/apache/dubbo/common/URLBuilder;
       4: areturn

  public org.apache.dubbo.common.URL removeParameters(java.lang.String[]);
    Code:
       0: aload_0
       1: aload_1
       2: invokevirtual #74                 // Method removeParameters:([Ljava/lang/String;)Lorg/apache/dubbo/common/URLBuilder;
       5: areturn

  public org.apache.dubbo.common.URL removeParameters(java.util.Collection);
    Code:
       0: aload_0
       1: aload_1
       2: invokevirtual #93                 // Method removeParameters:(Ljava/util/Collection;)Lorg/apache/dubbo/common/URLBuilder;
       5: areturn

  public org.apache.dubbo.common.URL removeParameter(java.lang.String);
    Code:
       0: aload_0
       1: aload_1
       2: invokevirtual #94                 // Method removeParameter:(Ljava/lang/String;)Lorg/apache/dubbo/common/URLBuilder;
       5: areturn

  public org.apache.dubbo.common.URL addParameterString(java.lang.String);
    Code:
       0: aload_0
       1: aload_1
       2: invokevirtual #95                 // Method addParameterString:(Ljava/lang/String;)Lorg/apache/dubbo/common/URLBuilder;
       5: areturn

  public org.apache.dubbo.common.URL addParameters(java.lang.String[]);
    Code:
       0: aload_0
       1: aload_1
       2: invokevirtual #96                 // Method addParameters:([Ljava/lang/String;)Lorg/apache/dubbo/common/URLBuilder;
       5: areturn

  public org.apache.dubbo.common.URL addParametersIfAbsent(java.util.Map);
    Code:
       0: aload_0
       1: aload_1
       2: invokevirtual #97                 // Method addParametersIfAbsent:(Ljava/util/Map;)Lorg/apache/dubbo/common/URLBuilder;
       5: areturn

  public org.apache.dubbo.common.URL addParameters(java.util.Map);
    Code:
       0: aload_0
       1: aload_1
       2: invokevirtual #72                 // Method addParameters:(Ljava/util/Map;)Lorg/apache/dubbo/common/URLBuilder;
       5: areturn

  public org.apache.dubbo.common.URL addParameterIfAbsent(java.lang.String, java.lang.String);
    Code:
       0: aload_0
       1: aload_1
       2: aload_2
       3: invokevirtual #98                 // Method addParameterIfAbsent:(Ljava/lang/String;Ljava/lang/String;)Lorg/apache/dubbo/common/URLBuilder;
       6: areturn

  public org.apache.dubbo.common.URL addParameter(java.lang.String, java.lang.String);
    Code:
       0: aload_0
       1: aload_1
       2: aload_2
       3: invokevirtual #46                 // Method addParameter:(Ljava/lang/String;Ljava/lang/String;)Lorg/apache/dubbo/common/URLBuilder;
       6: areturn

  public org.apache.dubbo.common.URL addParameter(java.lang.String, java.lang.CharSequence);
    Code:
       0: aload_0
       1: aload_1
       2: aload_2
       3: invokevirtual #99                 // Method addParameter:(Ljava/lang/String;Ljava/lang/CharSequence;)Lorg/apache/dubbo/common/URLBuilder;
       6: areturn

  public org.apache.dubbo.common.URL addParameter(java.lang.String, java.lang.Number);
    Code:
       0: aload_0
       1: aload_1
       2: aload_2
       3: invokevirtual #100                // Method addParameter:(Ljava/lang/String;Ljava/lang/Number;)Lorg/apache/dubbo/common/URLBuilder;
       6: areturn

  public org.apache.dubbo.common.URL addParameter(java.lang.String, java.lang.Enum);
    Code:
       0: aload_0
       1: aload_1
       2: aload_2
       3: invokevirtual #101                // Method addParameter:(Ljava/lang/String;Ljava/lang/Enum;)Lorg/apache/dubbo/common/URLBuilder;
       6: areturn

  public org.apache.dubbo.common.URL addParameter(java.lang.String, double);
    Code:
       0: aload_0
       1: aload_1
       2: dload_2
       3: invokevirtual #102                // Method addParameter:(Ljava/lang/String;D)Lorg/apache/dubbo/common/URLBuilder;
       6: areturn

  public org.apache.dubbo.common.URL addParameter(java.lang.String, float);
    Code:
       0: aload_0
       1: aload_1
       2: fload_2
       3: invokevirtual #103                // Method addParameter:(Ljava/lang/String;F)Lorg/apache/dubbo/common/URLBuilder;
       6: areturn

  public org.apache.dubbo.common.URL addParameter(java.lang.String, long);
    Code:
       0: aload_0
       1: aload_1
       2: lload_2
       3: invokevirtual #104                // Method addParameter:(Ljava/lang/String;J)Lorg/apache/dubbo/common/URLBuilder;
       6: areturn

  public org.apache.dubbo.common.URL addParameter(java.lang.String, int);
    Code:
       0: aload_0
       1: aload_1
       2: iload_2
       3: invokevirtual #105                // Method addParameter:(Ljava/lang/String;I)Lorg/apache/dubbo/common/URLBuilder;
       6: areturn

  public org.apache.dubbo.common.URL addParameter(java.lang.String, short);
    Code:
       0: aload_0
       1: aload_1
       2: iload_2
       3: invokevirtual #106                // Method addParameter:(Ljava/lang/String;S)Lorg/apache/dubbo/common/URLBuilder;
       6: areturn

  public org.apache.dubbo.common.URL addParameter(java.lang.String, byte);
    Code:
       0: aload_0
       1: aload_1
       2: iload_2
       3: invokevirtual #107                // Method addParameter:(Ljava/lang/String;B)Lorg/apache/dubbo/common/URLBuilder;
       6: areturn

  public org.apache.dubbo.common.URL addParameter(java.lang.String, char);
    Code:
       0: aload_0
       1: aload_1
       2: iload_2
       3: invokevirtual #108                // Method addParameter:(Ljava/lang/String;C)Lorg/apache/dubbo/common/URLBuilder;
       6: areturn

  public org.apache.dubbo.common.URL addParameter(java.lang.String, boolean);
    Code:
       0: aload_0
       1: aload_1
       2: iload_2
       3: invokevirtual #109                // Method addParameter:(Ljava/lang/String;Z)Lorg/apache/dubbo/common/URLBuilder;
       6: areturn

  public org.apache.dubbo.common.URL addParameterAndEncoded(java.lang.String, java.lang.String);
    Code:
       0: aload_0
       1: aload_1
       2: aload_2
       3: invokevirtual #110                // Method addParameterAndEncoded:(Ljava/lang/String;Ljava/lang/String;)Lorg/apache/dubbo/common/URLBuilder;
       6: areturn

  public org.apache.dubbo.common.URL setScopeModel(org.apache.dubbo.rpc.model.ScopeModel);
    Code:
       0: aload_0
       1: aload_1
       2: invokevirtual #111                // Method setScopeModel:(Lorg/apache/dubbo/rpc/model/ScopeModel;)Lorg/apache/dubbo/common/URLBuilder;
       5: areturn

  public org.apache.dubbo.common.URL setPath(java.lang.String);
    Code:
       0: aload_0
       1: aload_1
       2: invokevirtual #112                // Method setPath:(Ljava/lang/String;)Lorg/apache/dubbo/common/URLBuilder;
       5: areturn

  public org.apache.dubbo.common.URL setAddress(java.lang.String);
    Code:
       0: aload_0
       1: aload_1
       2: invokevirtual #113                // Method setAddress:(Ljava/lang/String;)Lorg/apache/dubbo/common/URLBuilder;
       5: areturn

  public org.apache.dubbo.common.URL setPort(int);
    Code:
       0: aload_0
       1: iload_1
       2: invokevirtual #114                // Method setPort:(I)Lorg/apache/dubbo/common/URLBuilder;
       5: areturn

  public org.apache.dubbo.common.URL setHost(java.lang.String);
    Code:
       0: aload_0
       1: aload_1
       2: invokevirtual #115                // Method setHost:(Ljava/lang/String;)Lorg/apache/dubbo/common/URLBuilder;
       5: areturn

  public org.apache.dubbo.common.URL setPassword(java.lang.String);
    Code:
       0: aload_0
       1: aload_1
       2: invokevirtual #116                // Method setPassword:(Ljava/lang/String;)Lorg/apache/dubbo/common/URLBuilder;
       5: areturn

  public org.apache.dubbo.common.URL setUsername(java.lang.String);
    Code:
       0: aload_0
       1: aload_1
       2: invokevirtual #117                // Method setUsername:(Ljava/lang/String;)Lorg/apache/dubbo/common/URLBuilder;
       5: areturn

  public org.apache.dubbo.common.URL setProtocol(java.lang.String);
    Code:
       0: aload_0
       1: aload_1
       2: invokevirtual #118                // Method setProtocol:(Ljava/lang/String;)Lorg/apache/dubbo/common/URLBuilder;
       5: areturn
}
