Compiled from "HttpMessageCodecManager.java"
public class org.apache.dubbo.rpc.protocol.rest.message.HttpMessageCodecManager {
  private static final java.util.Set<org.apache.dubbo.rpc.protocol.rest.message.HttpMessageCodec> httpMessageCodecs;

  public org.apache.dubbo.rpc.protocol.rest.message.HttpMessageCodecManager();
    Code:
       0: aload_0
       1: invokespecial #1                  // Method java/lang/Object."<init>":()V
       4: return

  public static java.lang.Object httpMessageDecode(byte[], java.lang.Class<?>, org.apache.dubbo.metadata.rest.media.MediaType) throws java.lang.Exception;
    Code:
       0: aload_0
       1: ifnull        9
       4: aload_0
       5: arraylength
       6: ifne          11
       9: aconst_null
      10: areturn
      11: getstatic     #2                  // Field httpMessageCodecs:Ljava/util/Set;
      14: invokeinterface #3,  1            // InterfaceMethod java/util/Set.iterator:()Ljava/util/Iterator;
      19: astore_3
      20: aload_3
      21: invokeinterface #4,  1            // InterfaceMethod java/util/Iterator.hasNext:()Z
      26: ifeq          75
      29: aload_3
      30: invokeinterface #5,  1            // InterfaceMethod java/util/Iterator.next:()Ljava/lang/Object;
      35: checkcast     #6                  // class org/apache/dubbo/rpc/protocol/rest/message/HttpMessageCodec
      38: astore        4
      40: aload         4
      42: aload_2
      43: aload_1
      44: invokeinterface #7,  3            // InterfaceMethod org/apache/dubbo/rpc/protocol/rest/message/HttpMessageCodec.contentTypeSupport:(Lorg/apache/dubbo/metadata/rest/media/MediaType;Ljava/lang/Class;)Z
      49: ifne          62
      52: aload_2
      53: aload_1
      54: aload         4
      56: invokestatic  #8                  // Method typeJudge:(Lorg/apache/dubbo/metadata/rest/media/MediaType;Ljava/lang/Class;Lorg/apache/dubbo/rpc/protocol/rest/message/HttpMessageCodec;)Z
      59: ifeq          72
      62: aload         4
      64: aload_0
      65: aload_1
      66: invokeinterface #9,  3            // InterfaceMethod org/apache/dubbo/rpc/protocol/rest/message/HttpMessageCodec.decode:(Ljava/lang/Object;Ljava/lang/Class;)Ljava/lang/Object;
      71: areturn
      72: goto          20
      75: new           #10                 // class org/apache/dubbo/rpc/protocol/rest/exception/UnSupportContentTypeException
      78: dup
      79: new           #11                 // class java/lang/StringBuilder
      82: dup
      83: invokespecial #12                 // Method java/lang/StringBuilder."<init>":()V
      86: ldc           #13                 // String UnSupport content-type :
      88: invokevirtual #14                 // Method java/lang/StringBuilder.append:(Ljava/lang/String;)Ljava/lang/StringBuilder;
      91: aload_2
      92: getfield      #15                 // Field org/apache/dubbo/metadata/rest/media/MediaType.value:Ljava/lang/String;
      95: invokevirtual #14                 // Method java/lang/StringBuilder.append:(Ljava/lang/String;)Ljava/lang/StringBuilder;
      98: invokevirtual #16                 // Method java/lang/StringBuilder.toString:()Ljava/lang/String;
     101: invokespecial #17                 // Method org/apache/dubbo/rpc/protocol/rest/exception/UnSupportContentTypeException."<init>":(Ljava/lang/String;)V
     104: athrow

  public static org.apache.dubbo.rpc.protocol.rest.pair.MessageCodecResultPair httpMessageEncode(java.io.OutputStream, java.lang.Object, org.apache.dubbo.common.URL, org.apache.dubbo.metadata.rest.media.MediaType, java.lang.Class<?>) throws java.lang.Exception;
    Code:
       0: aload_1
       1: ifnonnull     75
       4: getstatic     #2                  // Field httpMessageCodecs:Ljava/util/Set;
       7: invokeinterface #3,  1            // InterfaceMethod java/util/Set.iterator:()Ljava/util/Iterator;
      12: astore        5
      14: aload         5
      16: invokeinterface #4,  1            // InterfaceMethod java/util/Iterator.hasNext:()Z
      21: ifeq          75
      24: aload         5
      26: invokeinterface #5,  1            // InterfaceMethod java/util/Iterator.next:()Ljava/lang/Object;
      31: checkcast     #6                  // class org/apache/dubbo/rpc/protocol/rest/message/HttpMessageCodec
      34: astore        6
      36: aload         6
      38: aload_3
      39: aload         4
      41: invokeinterface #7,  3            // InterfaceMethod org/apache/dubbo/rpc/protocol/rest/message/HttpMessageCodec.contentTypeSupport:(Lorg/apache/dubbo/metadata/rest/media/MediaType;Ljava/lang/Class;)Z
      46: ifne          60
      49: aload_3
      50: aload         4
      52: aload         6
      54: invokestatic  #8                  // Method typeJudge:(Lorg/apache/dubbo/metadata/rest/media/MediaType;Ljava/lang/Class;Lorg/apache/dubbo/rpc/protocol/rest/message/HttpMessageCodec;)Z
      57: ifeq          72
      60: iconst_0
      61: aload         6
      63: invokeinterface #18,  1           // InterfaceMethod org/apache/dubbo/rpc/protocol/rest/message/HttpMessageCodec.contentType:()Lorg/apache/dubbo/metadata/rest/media/MediaType;
      68: invokestatic  #19                 // Method org/apache/dubbo/rpc/protocol/rest/pair/MessageCodecResultPair.pair:(ZLorg/apache/dubbo/metadata/rest/media/MediaType;)Lorg/apache/dubbo/rpc/protocol/rest/pair/MessageCodecResultPair;
      71: areturn
      72: goto          14
      75: getstatic     #2                  // Field httpMessageCodecs:Ljava/util/Set;
      78: invokeinterface #3,  1            // InterfaceMethod java/util/Set.iterator:()Ljava/util/Iterator;
      83: astore        5
      85: aload         5
      87: invokeinterface #4,  1            // InterfaceMethod java/util/Iterator.hasNext:()Z
      92: ifeq          156
      95: aload         5
      97: invokeinterface #5,  1            // InterfaceMethod java/util/Iterator.next:()Ljava/lang/Object;
     102: checkcast     #6                  // class org/apache/dubbo/rpc/protocol/rest/message/HttpMessageCodec
     105: astore        6
     107: aload         6
     109: aload_3
     110: aload         4
     112: invokeinterface #7,  3            // InterfaceMethod org/apache/dubbo/rpc/protocol/rest/message/HttpMessageCodec.contentTypeSupport:(Lorg/apache/dubbo/metadata/rest/media/MediaType;Ljava/lang/Class;)Z
     117: ifne          131
     120: aload_3
     121: aload         4
     123: aload         6
     125: invokestatic  #8                  // Method typeJudge:(Lorg/apache/dubbo/metadata/rest/media/MediaType;Ljava/lang/Class;Lorg/apache/dubbo/rpc/protocol/rest/message/HttpMessageCodec;)Z
     128: ifeq          153
     131: aload         6
     133: aload_0
     134: aload_1
     135: aload_2
     136: invokeinterface #20,  4           // InterfaceMethod org/apache/dubbo/rpc/protocol/rest/message/HttpMessageCodec.encode:(Ljava/lang/Object;Ljava/lang/Object;Lorg/apache/dubbo/common/URL;)V
     141: iconst_1
     142: aload         6
     144: invokeinterface #18,  1           // InterfaceMethod org/apache/dubbo/rpc/protocol/rest/message/HttpMessageCodec.contentType:()Lorg/apache/dubbo/metadata/rest/media/MediaType;
     149: invokestatic  #19                 // Method org/apache/dubbo/rpc/protocol/rest/pair/MessageCodecResultPair.pair:(ZLorg/apache/dubbo/metadata/rest/media/MediaType;)Lorg/apache/dubbo/rpc/protocol/rest/pair/MessageCodecResultPair;
     152: areturn
     153: goto          85
     156: new           #10                 // class org/apache/dubbo/rpc/protocol/rest/exception/UnSupportContentTypeException
     159: dup
     160: new           #11                 // class java/lang/StringBuilder
     163: dup
     164: invokespecial #12                 // Method java/lang/StringBuilder."<init>":()V
     167: ldc           #13                 // String UnSupport content-type :
     169: invokevirtual #14                 // Method java/lang/StringBuilder.append:(Ljava/lang/String;)Ljava/lang/StringBuilder;
     172: aload_3
     173: getfield      #15                 // Field org/apache/dubbo/metadata/rest/media/MediaType.value:Ljava/lang/String;
     176: invokevirtual #14                 // Method java/lang/StringBuilder.append:(Ljava/lang/String;)Ljava/lang/StringBuilder;
     179: invokevirtual #16                 // Method java/lang/StringBuilder.toString:()Ljava/lang/String;
     182: invokespecial #17                 // Method org/apache/dubbo/rpc/protocol/rest/exception/UnSupportContentTypeException."<init>":(Ljava/lang/String;)V
     185: athrow

  private static boolean typeJudge(org.apache.dubbo.metadata.rest.media.MediaType, java.lang.Class<?>, org.apache.dubbo.rpc.protocol.rest.message.HttpMessageCodec);
    Code:
       0: getstatic     #21                 // Field org/apache/dubbo/metadata/rest/media/MediaType.ALL_VALUE:Lorg/apache/dubbo/metadata/rest/media/MediaType;
       3: aload_0
       4: invokevirtual #22                 // Method org/apache/dubbo/metadata/rest/media/MediaType.equals:(Ljava/lang/Object;)Z
       7: ifne          14
      10: aload_0
      11: ifnonnull     32
      14: aload_1
      15: ifnull        32
      18: aload_2
      19: aload_1
      20: invokeinterface #23,  2           // InterfaceMethod org/apache/dubbo/rpc/protocol/rest/message/HttpMessageCodec.typeSupport:(Ljava/lang/Class;)Z
      25: ifeq          32
      28: iconst_1
      29: goto          33
      32: iconst_0
      33: ireturn

  public static org.apache.dubbo.metadata.rest.media.MediaType typeSupport(java.lang.Class<?>);
    Code:
       0: getstatic     #2                  // Field httpMessageCodecs:Ljava/util/Set;
       3: invokeinterface #3,  1            // InterfaceMethod java/util/Set.iterator:()Ljava/util/Iterator;
       8: astore_1
       9: aload_1
      10: invokeinterface #4,  1            // InterfaceMethod java/util/Iterator.hasNext:()Z
      15: ifeq          48
      18: aload_1
      19: invokeinterface #5,  1            // InterfaceMethod java/util/Iterator.next:()Ljava/lang/Object;
      24: checkcast     #6                  // class org/apache/dubbo/rpc/protocol/rest/message/HttpMessageCodec
      27: astore_2
      28: aload_2
      29: aload_0
      30: invokeinterface #23,  2           // InterfaceMethod org/apache/dubbo/rpc/protocol/rest/message/HttpMessageCodec.typeSupport:(Ljava/lang/Class;)Z
      35: ifeq          45
      38: aload_2
      39: invokeinterface #18,  1           // InterfaceMethod org/apache/dubbo/rpc/protocol/rest/message/HttpMessageCodec.contentType:()Lorg/apache/dubbo/metadata/rest/media/MediaType;
      44: areturn
      45: goto          9
      48: aconst_null
      49: areturn

  static {};
    Code:
       0: invokestatic  #24                 // Method org/apache/dubbo/rpc/model/FrameworkModel.defaultModel:()Lorg/apache/dubbo/rpc/model/FrameworkModel;
       3: ldc           #6                  // class org/apache/dubbo/rpc/protocol/rest/message/HttpMessageCodec
       5: invokevirtual #25                 // Method org/apache/dubbo/rpc/model/FrameworkModel.getExtensionLoader:(Ljava/lang/Class;)Lorg/apache/dubbo/common/extension/ExtensionLoader;
       8: invokevirtual #26                 // Method org/apache/dubbo/common/extension/ExtensionLoader.getSupportedExtensionInstances:()Ljava/util/Set;
      11: putstatic     #2                  // Field httpMessageCodecs:Ljava/util/Set;
      14: return
}
