Compiled from "MediaTypeMatcher.java"
public final class org.apache.dubbo.rpc.protocol.rest.message.MediaTypeMatcher extends java.lang.Enum<org.apache.dubbo.rpc.protocol.rest.message.MediaTypeMatcher> {
  public static final org.apache.dubbo.rpc.protocol.rest.message.MediaTypeMatcher MULTI_VALUE;

  public static final org.apache.dubbo.rpc.protocol.rest.message.MediaTypeMatcher APPLICATION_JSON;

  public static final org.apache.dubbo.rpc.protocol.rest.message.MediaTypeMatcher TEXT_PLAIN;

  public static final org.apache.dubbo.rpc.protocol.rest.message.MediaTypeMatcher TEXT_XML;

  private java.util.List<org.apache.dubbo.metadata.rest.media.MediaType> mediaTypes;

  private static final org.apache.dubbo.rpc.protocol.rest.message.MediaTypeMatcher[] $VALUES;

  public static org.apache.dubbo.rpc.protocol.rest.message.MediaTypeMatcher[] values();
    Code:
       0: getstatic     #1                  // Field $VALUES:[Lorg/apache/dubbo/rpc/protocol/rest/message/MediaTypeMatcher;
       3: invokevirtual #2                  // Method "[Lorg/apache/dubbo/rpc/protocol/rest/message/MediaTypeMatcher;".clone:()Ljava/lang/Object;
       6: checkcast     #3                  // class "[Lorg/apache/dubbo/rpc/protocol/rest/message/MediaTypeMatcher;"
       9: areturn

  public static org.apache.dubbo.rpc.protocol.rest.message.MediaTypeMatcher valueOf(java.lang.String);
    Code:
       0: ldc           #4                  // class org/apache/dubbo/rpc/protocol/rest/message/MediaTypeMatcher
       2: aload_0
       3: invokestatic  #5                  // Method java/lang/Enum.valueOf:(Ljava/lang/Class;Ljava/lang/String;)Ljava/lang/Enum;
       6: checkcast     #4                  // class org/apache/dubbo/rpc/protocol/rest/message/MediaTypeMatcher
       9: areturn

  private org.apache.dubbo.rpc.protocol.rest.message.MediaTypeMatcher(java.util.List<org.apache.dubbo.metadata.rest.media.MediaType>);
    Code:
       0: aload_0
       1: aload_1
       2: iload_2
       3: invokespecial #6                  // Method java/lang/Enum."<init>":(Ljava/lang/String;I)V
       6: aload_0
       7: aload_3
       8: putfield      #7                  // Field mediaTypes:Ljava/util/List;
      11: return

  private static java.util.List<org.apache.dubbo.metadata.rest.media.MediaType> createMediaList(org.apache.dubbo.metadata.rest.media.MediaType...);
    Code:
       0: invokestatic  #8                  // Method getDefaultList:()Ljava/util/List;
       3: astore_1
       4: aload_0
       5: astore_2
       6: aload_2
       7: arraylength
       8: istore_3
       9: iconst_0
      10: istore        4
      12: iload         4
      14: iload_3
      15: if_icmpge     39
      18: aload_2
      19: iload         4
      21: aaload
      22: astore        5
      24: aload_1
      25: aload         5
      27: invokeinterface #9,  2            // InterfaceMethod java/util/List.add:(Ljava/lang/Object;)Z
      32: pop
      33: iinc          4, 1
      36: goto          12
      39: aload_1
      40: areturn

  private static java.util.List<org.apache.dubbo.metadata.rest.media.MediaType> getDefaultList();
    Code:
       0: new           #10                 // class java/util/ArrayList
       3: dup
       4: invokespecial #11                 // Method java/util/ArrayList."<init>":()V
       7: astore_0
       8: aload_0
       9: areturn

  public boolean mediaSupport(org.apache.dubbo.metadata.rest.media.MediaType);
    Code:
       0: aload_0
       1: getfield      #7                  // Field mediaTypes:Ljava/util/List;
       4: aload_1
       5: invokeinterface #12,  2           // InterfaceMethod java/util/List.contains:(Ljava/lang/Object;)Z
      10: ireturn

  static {};
    Code:
       0: new           #4                  // class org/apache/dubbo/rpc/protocol/rest/message/MediaTypeMatcher
       3: dup
       4: ldc           #13                 // String MULTI_VALUE
       6: iconst_0
       7: iconst_1
       8: anewarray     #14                 // class org/apache/dubbo/metadata/rest/media/MediaType
      11: dup
      12: iconst_0
      13: getstatic     #15                 // Field org/apache/dubbo/metadata/rest/media/MediaType.APPLICATION_FORM_URLENCODED_VALUE:Lorg/apache/dubbo/metadata/rest/media/MediaType;
      16: aastore
      17: invokestatic  #16                 // Method createMediaList:([Lorg/apache/dubbo/metadata/rest/media/MediaType;)Ljava/util/List;
      20: invokespecial #17                 // Method "<init>":(Ljava/lang/String;ILjava/util/List;)V
      23: putstatic     #18                 // Field MULTI_VALUE:Lorg/apache/dubbo/rpc/protocol/rest/message/MediaTypeMatcher;
      26: new           #4                  // class org/apache/dubbo/rpc/protocol/rest/message/MediaTypeMatcher
      29: dup
      30: ldc           #19                 // String APPLICATION_JSON
      32: iconst_1
      33: iconst_1
      34: anewarray     #14                 // class org/apache/dubbo/metadata/rest/media/MediaType
      37: dup
      38: iconst_0
      39: getstatic     #20                 // Field org/apache/dubbo/metadata/rest/media/MediaType.APPLICATION_JSON_VALUE:Lorg/apache/dubbo/metadata/rest/media/MediaType;
      42: aastore
      43: invokestatic  #16                 // Method createMediaList:([Lorg/apache/dubbo/metadata/rest/media/MediaType;)Ljava/util/List;
      46: invokespecial #17                 // Method "<init>":(Ljava/lang/String;ILjava/util/List;)V
      49: putstatic     #21                 // Field APPLICATION_JSON:Lorg/apache/dubbo/rpc/protocol/rest/message/MediaTypeMatcher;
      52: new           #4                  // class org/apache/dubbo/rpc/protocol/rest/message/MediaTypeMatcher
      55: dup
      56: ldc           #22                 // String TEXT_PLAIN
      58: iconst_2
      59: iconst_2
      60: anewarray     #14                 // class org/apache/dubbo/metadata/rest/media/MediaType
      63: dup
      64: iconst_0
      65: getstatic     #23                 // Field org/apache/dubbo/metadata/rest/media/MediaType.TEXT_PLAIN:Lorg/apache/dubbo/metadata/rest/media/MediaType;
      68: aastore
      69: dup
      70: iconst_1
      71: getstatic     #24                 // Field org/apache/dubbo/metadata/rest/media/MediaType.OCTET_STREAM:Lorg/apache/dubbo/metadata/rest/media/MediaType;
      74: aastore
      75: invokestatic  #16                 // Method createMediaList:([Lorg/apache/dubbo/metadata/rest/media/MediaType;)Ljava/util/List;
      78: invokespecial #17                 // Method "<init>":(Ljava/lang/String;ILjava/util/List;)V
      81: putstatic     #25                 // Field TEXT_PLAIN:Lorg/apache/dubbo/rpc/protocol/rest/message/MediaTypeMatcher;
      84: new           #4                  // class org/apache/dubbo/rpc/protocol/rest/message/MediaTypeMatcher
      87: dup
      88: ldc           #26                 // String TEXT_XML
      90: iconst_3
      91: iconst_1
      92: anewarray     #14                 // class org/apache/dubbo/metadata/rest/media/MediaType
      95: dup
      96: iconst_0
      97: getstatic     #27                 // Field org/apache/dubbo/metadata/rest/media/MediaType.TEXT_XML:Lorg/apache/dubbo/metadata/rest/media/MediaType;
     100: aastore
     101: invokestatic  #16                 // Method createMediaList:([Lorg/apache/dubbo/metadata/rest/media/MediaType;)Ljava/util/List;
     104: invokespecial #17                 // Method "<init>":(Ljava/lang/String;ILjava/util/List;)V
     107: putstatic     #28                 // Field TEXT_XML:Lorg/apache/dubbo/rpc/protocol/rest/message/MediaTypeMatcher;
     110: iconst_4
     111: anewarray     #4                  // class org/apache/dubbo/rpc/protocol/rest/message/MediaTypeMatcher
     114: dup
     115: iconst_0
     116: getstatic     #18                 // Field MULTI_VALUE:Lorg/apache/dubbo/rpc/protocol/rest/message/MediaTypeMatcher;
     119: aastore
     120: dup
     121: iconst_1
     122: getstatic     #21                 // Field APPLICATION_JSON:Lorg/apache/dubbo/rpc/protocol/rest/message/MediaTypeMatcher;
     125: aastore
     126: dup
     127: iconst_2
     128: getstatic     #25                 // Field TEXT_PLAIN:Lorg/apache/dubbo/rpc/protocol/rest/message/MediaTypeMatcher;
     131: aastore
     132: dup
     133: iconst_3
     134: getstatic     #28                 // Field TEXT_XML:Lorg/apache/dubbo/rpc/protocol/rest/message/MediaTypeMatcher;
     137: aastore
     138: putstatic     #1                  // Field $VALUES:[Lorg/apache/dubbo/rpc/protocol/rest/message/MediaTypeMatcher;
     141: return
}
