Compiled from "BiStreamMethodHandler.java"
public class org.apache.dubbo.rpc.stub.BiStreamMethodHandler<T, R> implements org.apache.dubbo.rpc.stub.StubMethodHandler<T, R> {
  private final java.util.function.Function<org.apache.dubbo.common.stream.StreamObserver<R>, org.apache.dubbo.common.stream.StreamObserver<T>> func;

  public org.apache.dubbo.rpc.stub.BiStreamMethodHandler(java.util.function.Function<org.apache.dubbo.common.stream.StreamObserver<R>, org.apache.dubbo.common.stream.StreamObserver<T>>);
    Code:
       0: aload_0
       1: invokespecial #1                  // Method java/lang/Object."<init>":()V
       4: aload_0
       5: aload_1
       6: putfield      #2                  // Field func:Ljava/util/function/Function;
       9: return

  public java.util.concurrent.CompletableFuture<org.apache.dubbo.common.stream.StreamObserver<T>> invoke(java.lang.Object[]);
    Code:
       0: aload_1
       1: iconst_0
       2: aaload
       3: checkcast     #3                  // class org/apache/dubbo/common/stream/StreamObserver
       6: astore_2
       7: aload_0
       8: getfield      #2                  // Field func:Ljava/util/function/Function;
      11: aload_2
      12: invokeinterface #4,  2            // InterfaceMethod java/util/function/Function.apply:(Ljava/lang/Object;)Ljava/lang/Object;
      17: checkcast     #3                  // class org/apache/dubbo/common/stream/StreamObserver
      20: astore_3
      21: aload_3
      22: invokestatic  #5                  // Method java/util/concurrent/CompletableFuture.completedFuture:(Ljava/lang/Object;)Ljava/util/concurrent/CompletableFuture;
      25: areturn
}
