Compiled from "FutureToObserverAdaptor.java"
public class org.apache.dubbo.rpc.stub.FutureToObserverAdaptor<T> implements org.apache.dubbo.common.stream.StreamObserver<T> {
  private final java.util.concurrent.CompletableFuture<T> future;

  public org.apache.dubbo.rpc.stub.FutureToObserverAdaptor(java.util.concurrent.CompletableFuture<T>);
    Code:
       0: aload_0
       1: invokespecial #1                  // Method java/lang/Object."<init>":()V
       4: aload_0
       5: aload_1
       6: putfield      #2                  // Field future:Ljava/util/concurrent/CompletableFuture;
       9: return

  public void onNext(T);
    Code:
       0: aload_0
       1: getfield      #2                  // Field future:Ljava/util/concurrent/CompletableFuture;
       4: invokevirtual #3                  // Method java/util/concurrent/CompletableFuture.isDone:()Z
       7: ifne          30
      10: aload_0
      11: getfield      #2                  // Field future:Ljava/util/concurrent/CompletableFuture;
      14: invokevirtual #4                  // Method java/util/concurrent/CompletableFuture.isCancelled:()Z
      17: ifne          30
      20: aload_0
      21: getfield      #2                  // Field future:Ljava/util/concurrent/CompletableFuture;
      24: invokevirtual #5                  // Method java/util/concurrent/CompletableFuture.isCompletedExceptionally:()Z
      27: ifeq          40
      30: new           #6                  // class java/lang/IllegalStateException
      33: dup
      34: ldc           #7                  // String Too many response for unary method
      36: invokespecial #8                  // Method java/lang/IllegalStateException."<init>":(Ljava/lang/String;)V
      39: athrow
      40: aload_0
      41: getfield      #2                  // Field future:Ljava/util/concurrent/CompletableFuture;
      44: aload_1
      45: invokevirtual #9                  // Method java/util/concurrent/CompletableFuture.complete:(Ljava/lang/Object;)Z
      48: pop
      49: return

  public void onError(java.lang.Throwable);
    Code:
       0: aload_0
       1: getfield      #2                  // Field future:Ljava/util/concurrent/CompletableFuture;
       4: invokevirtual #3                  // Method java/util/concurrent/CompletableFuture.isDone:()Z
       7: ifne          30
      10: aload_0
      11: getfield      #2                  // Field future:Ljava/util/concurrent/CompletableFuture;
      14: invokevirtual #4                  // Method java/util/concurrent/CompletableFuture.isCancelled:()Z
      17: ifne          30
      20: aload_0
      21: getfield      #2                  // Field future:Ljava/util/concurrent/CompletableFuture;
      24: invokevirtual #5                  // Method java/util/concurrent/CompletableFuture.isCompletedExceptionally:()Z
      27: ifeq          40
      30: new           #6                  // class java/lang/IllegalStateException
      33: dup
      34: ldc           #7                  // String Too many response for unary method
      36: invokespecial #8                  // Method java/lang/IllegalStateException."<init>":(Ljava/lang/String;)V
      39: athrow
      40: aload_0
      41: getfield      #2                  // Field future:Ljava/util/concurrent/CompletableFuture;
      44: aload_1
      45: invokevirtual #10                 // Method java/util/concurrent/CompletableFuture.completeExceptionally:(Ljava/lang/Throwable;)Z
      48: pop
      49: return

  public void onCompleted();
    Code:
       0: aload_0
       1: getfield      #2                  // Field future:Ljava/util/concurrent/CompletableFuture;
       4: invokevirtual #3                  // Method java/util/concurrent/CompletableFuture.isDone:()Z
       7: ifne          30
      10: aload_0
      11: getfield      #2                  // Field future:Ljava/util/concurrent/CompletableFuture;
      14: invokevirtual #4                  // Method java/util/concurrent/CompletableFuture.isCancelled:()Z
      17: ifne          30
      20: aload_0
      21: getfield      #2                  // Field future:Ljava/util/concurrent/CompletableFuture;
      24: invokevirtual #5                  // Method java/util/concurrent/CompletableFuture.isCompletedExceptionally:()Z
      27: ifeq          31
      30: return
      31: new           #6                  // class java/lang/IllegalStateException
      34: dup
      35: ldc           #11                 // String Completed without value or exception
      37: invokespecial #8                  // Method java/lang/IllegalStateException."<init>":(Ljava/lang/String;)V
      40: athrow
}
