Compiled from "ServerStreamMethodHandler.java"
public class org.apache.dubbo.rpc.stub.ServerStreamMethodHandler<T, R> implements org.apache.dubbo.rpc.stub.StubMethodHandler<T, R> {
  private final java.util.function.BiConsumer<T, org.apache.dubbo.common.stream.StreamObserver<R>> func;

  public org.apache.dubbo.rpc.stub.ServerStreamMethodHandler(java.util.function.BiConsumer<T, org.apache.dubbo.common.stream.StreamObserver<R>>);
    Code:
       0: aload_0
       1: invokespecial #1                  // Method java/lang/Object."<init>":()V
       4: aload_0
       5: aload_1
       6: putfield      #2                  // Field func:Ljava/util/function/BiConsumer;
       9: return

  public java.util.concurrent.CompletableFuture<?> invoke(java.lang.Object[]);
    Code:
       0: aload_1
       1: iconst_0
       2: aaload
       3: astore_2
       4: aload_1
       5: iconst_1
       6: aaload
       7: checkcast     #3                  // class org/apache/dubbo/common/stream/StreamObserver
      10: astore_3
      11: aload_0
      12: getfield      #2                  // Field func:Ljava/util/function/BiConsumer;
      15: aload_2
      16: aload_3
      17: invokeinterface #4,  3            // InterfaceMethod java/util/function/BiConsumer.accept:(Ljava/lang/Object;Ljava/lang/Object;)V
      22: aconst_null
      23: invokestatic  #5                  // Method java/util/concurrent/CompletableFuture.completedFuture:(Ljava/lang/Object;)Ljava/util/concurrent/CompletableFuture;
      26: areturn
}
