Compiled from "StubSuppliers.java"
public class org.apache.dubbo.rpc.stub.StubSuppliers {
  private static final java.util.Map<java.lang.String, java.util.function.Function<org.apache.dubbo.rpc.Invoker<?>, java.lang.Object>> STUB_SUPPLIERS;

  private static final java.util.Map<java.lang.String, org.apache.dubbo.rpc.model.ServiceDescriptor> SERVICE_DESCRIPTOR_MAP;

  public org.apache.dubbo.rpc.stub.StubSuppliers();
    Code:
       0: aload_0
       1: invokespecial #1                  // Method java/lang/Object."<init>":()V
       4: return

  public static void addDescriptor(java.lang.String, org.apache.dubbo.rpc.model.ServiceDescriptor);
    Code:
       0: getstatic     #2                  // Field SERVICE_DESCRIPTOR_MAP:Ljava/util/Map;
       3: aload_0
       4: aload_1
       5: invokeinterface #3,  3            // InterfaceMethod java/util/Map.put:(Ljava/lang/Object;Ljava/lang/Object;)Ljava/lang/Object;
      10: pop
      11: return

  public static void addSupplier(java.lang.String, java.util.function.Function<org.apache.dubbo.rpc.Invoker<?>, java.lang.Object>);
    Code:
       0: getstatic     #4                  // Field STUB_SUPPLIERS:Ljava/util/Map;
       3: aload_0
       4: aload_1
       5: invokeinterface #3,  3            // InterfaceMethod java/util/Map.put:(Ljava/lang/Object;Ljava/lang/Object;)Ljava/lang/Object;
      10: pop
      11: return

  public static <T> T createStub(java.lang.String, org.apache.dubbo.rpc.Invoker<T>);
    Code:
       0: getstatic     #4                  // Field STUB_SUPPLIERS:Ljava/util/Map;
       3: aload_0
       4: invokeinterface #5,  2            // InterfaceMethod java/util/Map.containsKey:(Ljava/lang/Object;)Z
       9: ifne          59
      12: aload_0
      13: invokestatic  #6                  // Method stubClassName:(Ljava/lang/String;)Ljava/lang/String;
      16: invokestatic  #7                  // Method org/apache/dubbo/common/utils/ReflectUtils.forName:(Ljava/lang/String;)Ljava/lang/Class;
      19: pop
      20: getstatic     #4                  // Field STUB_SUPPLIERS:Ljava/util/Map;
      23: aload_0
      24: invokeinterface #5,  2            // InterfaceMethod java/util/Map.containsKey:(Ljava/lang/Object;)Z
      29: ifne          59
      32: new           #8                  // class java/lang/IllegalStateException
      35: dup
      36: new           #9                  // class java/lang/StringBuilder
      39: dup
      40: invokespecial #10                 // Method java/lang/StringBuilder."<init>":()V
      43: ldc           #11                 // String Can not find any stub supplier for
      45: invokevirtual #12                 // Method java/lang/StringBuilder.append:(Ljava/lang/String;)Ljava/lang/StringBuilder;
      48: aload_0
      49: invokevirtual #12                 // Method java/lang/StringBuilder.append:(Ljava/lang/String;)Ljava/lang/StringBuilder;
      52: invokevirtual #13                 // Method java/lang/StringBuilder.toString:()Ljava/lang/String;
      55: invokespecial #14                 // Method java/lang/IllegalStateException."<init>":(Ljava/lang/String;)V
      58: athrow
      59: getstatic     #4                  // Field STUB_SUPPLIERS:Ljava/util/Map;
      62: aload_0
      63: invokeinterface #15,  2           // InterfaceMethod java/util/Map.get:(Ljava/lang/Object;)Ljava/lang/Object;
      68: checkcast     #16                 // class java/util/function/Function
      71: aload_1
      72: invokeinterface #17,  2           // InterfaceMethod java/util/function/Function.apply:(Ljava/lang/Object;)Ljava/lang/Object;
      77: areturn

  private static java.lang.String stubClassName(java.lang.String);
    Code:
       0: aload_0
       1: bipush        46
       3: invokevirtual #18                 // Method java/lang/String.lastIndexOf:(I)I
       6: istore_1
       7: aload_0
       8: iconst_0
       9: iload_1
      10: iconst_1
      11: iadd
      12: invokevirtual #19                 // Method java/lang/String.substring:(II)Ljava/lang/String;
      15: astore_2
      16: aload_0
      17: iload_1
      18: iconst_1
      19: iadd
      20: invokevirtual #20                 // Method java/lang/String.substring:(I)Ljava/lang/String;
      23: astore_3
      24: new           #9                  // class java/lang/StringBuilder
      27: dup
      28: invokespecial #10                 // Method java/lang/StringBuilder."<init>":()V
      31: aload_2
      32: invokevirtual #12                 // Method java/lang/StringBuilder.append:(Ljava/lang/String;)Ljava/lang/StringBuilder;
      35: ldc           #21                 // String Dubbo
      37: invokevirtual #12                 // Method java/lang/StringBuilder.append:(Ljava/lang/String;)Ljava/lang/StringBuilder;
      40: aload_3
      41: invokevirtual #12                 // Method java/lang/StringBuilder.append:(Ljava/lang/String;)Ljava/lang/StringBuilder;
      44: ldc           #22                 // String Triple
      46: invokevirtual #12                 // Method java/lang/StringBuilder.append:(Ljava/lang/String;)Ljava/lang/StringBuilder;
      49: invokevirtual #13                 // Method java/lang/StringBuilder.toString:()Ljava/lang/String;
      52: areturn

  public static org.apache.dubbo.rpc.model.ServiceDescriptor getServiceDescriptor(java.lang.String);
    Code:
       0: getstatic     #2                  // Field SERVICE_DESCRIPTOR_MAP:Ljava/util/Map;
       3: aload_0
       4: invokeinterface #5,  2            // InterfaceMethod java/util/Map.containsKey:(Ljava/lang/Object;)Z
       9: ifne          59
      12: aload_0
      13: invokestatic  #6                  // Method stubClassName:(Ljava/lang/String;)Ljava/lang/String;
      16: invokestatic  #7                  // Method org/apache/dubbo/common/utils/ReflectUtils.forName:(Ljava/lang/String;)Ljava/lang/Class;
      19: pop
      20: getstatic     #2                  // Field SERVICE_DESCRIPTOR_MAP:Ljava/util/Map;
      23: aload_0
      24: invokeinterface #5,  2            // InterfaceMethod java/util/Map.containsKey:(Ljava/lang/Object;)Z
      29: ifne          59
      32: new           #8                  // class java/lang/IllegalStateException
      35: dup
      36: new           #9                  // class java/lang/StringBuilder
      39: dup
      40: invokespecial #10                 // Method java/lang/StringBuilder."<init>":()V
      43: ldc           #11                 // String Can not find any stub supplier for
      45: invokevirtual #12                 // Method java/lang/StringBuilder.append:(Ljava/lang/String;)Ljava/lang/StringBuilder;
      48: aload_0
      49: invokevirtual #12                 // Method java/lang/StringBuilder.append:(Ljava/lang/String;)Ljava/lang/StringBuilder;
      52: invokevirtual #13                 // Method java/lang/StringBuilder.toString:()Ljava/lang/String;
      55: invokespecial #14                 // Method java/lang/IllegalStateException."<init>":(Ljava/lang/String;)V
      58: athrow
      59: getstatic     #2                  // Field SERVICE_DESCRIPTOR_MAP:Ljava/util/Map;
      62: aload_0
      63: invokeinterface #15,  2           // InterfaceMethod java/util/Map.get:(Ljava/lang/Object;)Ljava/lang/Object;
      68: checkcast     #23                 // class org/apache/dubbo/rpc/model/ServiceDescriptor
      71: areturn

  static {};
    Code:
       0: new           #24                 // class java/util/concurrent/ConcurrentHashMap
       3: dup
       4: invokespecial #25                 // Method java/util/concurrent/ConcurrentHashMap."<init>":()V
       7: putstatic     #4                  // Field STUB_SUPPLIERS:Ljava/util/Map;
      10: new           #24                 // class java/util/concurrent/ConcurrentHashMap
      13: dup
      14: invokespecial #25                 // Method java/util/concurrent/ConcurrentHashMap."<init>":()V
      17: putstatic     #2                  // Field SERVICE_DESCRIPTOR_MAP:Ljava/util/Map;
      20: return
}
