Compiled from "StubInvoker.java"
public class org.apache.dubbo.rpc.stub.StubInvoker<T> extends org.apache.dubbo.rpc.proxy.AbstractProxyInvoker<T> {
  private final java.util.Map<java.lang.String, org.apache.dubbo.rpc.stub.StubMethodHandler<?, ?>> handlers;

  public org.apache.dubbo.rpc.stub.StubInvoker(T, org.apache.dubbo.common.URL, java.lang.Class<T>, java.util.Map<java.lang.String, org.apache.dubbo.rpc.stub.StubMethodHandler<?, ?>>);
    Code:
       0: aload_0
       1: aload_1
       2: aload_3
       3: aload_2
       4: invokespecial #1                  // Method org/apache/dubbo/rpc/proxy/AbstractProxyInvoker."<init>":(Ljava/lang/Object;Ljava/lang/Class;Lorg/apache/dubbo/common/URL;)V
       7: aload_0
       8: aload         4
      10: putfield      #2                  // Field handlers:Ljava/util/Map;
      13: return

  protected java.lang.Object doInvoke(T, java.lang.String, java.lang.Class<?>[], java.lang.Object[]) throws java.lang.Throwable;
    Code:
       0: aload_0
       1: getfield      #2                  // Field handlers:Ljava/util/Map;
       4: aload_2
       5: invokeinterface #3,  2            // InterfaceMethod java/util/Map.get:(Ljava/lang/Object;)Ljava/lang/Object;
      10: checkcast     #4                  // class org/apache/dubbo/rpc/stub/StubMethodHandler
      13: aload         4
      15: invokeinterface #5,  2            // InterfaceMethod org/apache/dubbo/rpc/stub/StubMethodHandler.invoke:([Ljava/lang/Object;)Ljava/util/concurrent/CompletableFuture;
      20: areturn
}
