Compiled from "StubInvocationUtil.java"
public class org.apache.dubbo.rpc.stub.StubInvocationUtil {
  public org.apache.dubbo.rpc.stub.StubInvocationUtil();
    Code:
       0: aload_0
       1: invokespecial #1                  // Method java/lang/Object."<init>":()V
       4: return

  public static <T, R> R unaryCall(org.apache.dubbo.rpc.Invoker<?>, org.apache.dubbo.rpc.model.MethodDescriptor, T);
    Code:
       0: aload_0
       1: aload_1
       2: iconst_1
       3: anewarray     #2                  // class java/lang/Object
       6: dup
       7: iconst_0
       8: aload_2
       9: aastore
      10: invokestatic  #3                  // Method call:(Lorg/apache/dubbo/rpc/Invoker;Lorg/apache/dubbo/rpc/model/MethodDescriptor;[Ljava/lang/Object;)Ljava/lang/Object;
      13: areturn

  public static <T, R> void unaryCall(org.apache.dubbo.rpc.Invoker<?>, org.apache.dubbo.rpc.model.MethodDescriptor, T, org.apache.dubbo.common.stream.StreamObserver<R>);
    Code:
       0: aload_0
       1: aload_1
       2: aload_2
       3: invokestatic  #4                  // Method unaryCall:(Lorg/apache/dubbo/rpc/Invoker;Lorg/apache/dubbo/rpc/model/MethodDescriptor;Ljava/lang/Object;)Ljava/lang/Object;
       6: astore        4
       8: aload_3
       9: aload         4
      11: invokeinterface #5,  2            // InterfaceMethod org/apache/dubbo/common/stream/StreamObserver.onNext:(Ljava/lang/Object;)V
      16: goto          29
      19: astore        4
      21: aload_3
      22: aload         4
      24: invokeinterface #7,  2            // InterfaceMethod org/apache/dubbo/common/stream/StreamObserver.onError:(Ljava/lang/Throwable;)V
      29: aload_3
      30: invokeinterface #8,  1            // InterfaceMethod org/apache/dubbo/common/stream/StreamObserver.onCompleted:()V
      35: return
    Exception table:
       from    to  target type
           0    16    19   Class java/lang/Exception

  public static <T, R> org.apache.dubbo.common.stream.StreamObserver<T> biOrClientStreamCall(org.apache.dubbo.rpc.Invoker<?>, org.apache.dubbo.rpc.model.MethodDescriptor, org.apache.dubbo.common.stream.StreamObserver<R>);
    Code:
       0: aload_0
       1: aload_1
       2: iconst_1
       3: anewarray     #2                  // class java/lang/Object
       6: dup
       7: iconst_0
       8: aload_2
       9: aastore
      10: invokestatic  #3                  // Method call:(Lorg/apache/dubbo/rpc/Invoker;Lorg/apache/dubbo/rpc/model/MethodDescriptor;[Ljava/lang/Object;)Ljava/lang/Object;
      13: checkcast     #9                  // class org/apache/dubbo/common/stream/StreamObserver
      16: areturn

  public static <T, R> void serverStreamCall(org.apache.dubbo.rpc.Invoker<?>, org.apache.dubbo.rpc.model.MethodDescriptor, T, org.apache.dubbo.common.stream.StreamObserver<R>);
    Code:
       0: aload_0
       1: aload_1
       2: iconst_2
       3: anewarray     #2                  // class java/lang/Object
       6: dup
       7: iconst_0
       8: aload_2
       9: aastore
      10: dup
      11: iconst_1
      12: aload_3
      13: aastore
      14: invokestatic  #3                  // Method call:(Lorg/apache/dubbo/rpc/Invoker;Lorg/apache/dubbo/rpc/model/MethodDescriptor;[Ljava/lang/Object;)Ljava/lang/Object;
      17: pop
      18: return

  private static java.lang.Object call(org.apache.dubbo.rpc.Invoker<?>, org.apache.dubbo.rpc.model.MethodDescriptor, java.lang.Object[]);
    Code:
       0: new           #10                 // class org/apache/dubbo/rpc/RpcInvocation
       3: dup
       4: aload_0
       5: invokeinterface #11,  1           // InterfaceMethod org/apache/dubbo/rpc/Invoker.getUrl:()Lorg/apache/dubbo/common/URL;
      10: invokevirtual #12                 // Method org/apache/dubbo/common/URL.getServiceModel:()Lorg/apache/dubbo/rpc/model/ServiceModel;
      13: aload_1
      14: invokeinterface #13,  1           // InterfaceMethod org/apache/dubbo/rpc/model/MethodDescriptor.getMethodName:()Ljava/lang/String;
      19: aload_0
      20: invokeinterface #14,  1           // InterfaceMethod org/apache/dubbo/rpc/Invoker.getInterface:()Ljava/lang/Class;
      25: invokevirtual #15                 // Method java/lang/Class.getName:()Ljava/lang/String;
      28: aload_0
      29: invokeinterface #11,  1           // InterfaceMethod org/apache/dubbo/rpc/Invoker.getUrl:()Lorg/apache/dubbo/common/URL;
      34: invokevirtual #16                 // Method org/apache/dubbo/common/URL.getProtocolServiceKey:()Ljava/lang/String;
      37: aload_1
      38: invokeinterface #17,  1           // InterfaceMethod org/apache/dubbo/rpc/model/MethodDescriptor.getParameterClasses:()[Ljava/lang/Class;
      43: aload_2
      44: invokespecial #18                 // Method org/apache/dubbo/rpc/RpcInvocation."<init>":(Lorg/apache/dubbo/rpc/model/ServiceModel;Ljava/lang/String;Ljava/lang/String;Ljava/lang/String;[Ljava/lang/Class;[Ljava/lang/Object;)V
      47: astore_3
      48: aload_3
      49: aload_1
      50: invokeinterface #19,  1           // InterfaceMethod org/apache/dubbo/rpc/model/MethodDescriptor.getReturnClass:()Ljava/lang/Class;
      55: invokevirtual #20                 // Method org/apache/dubbo/rpc/RpcInvocation.setReturnType:(Ljava/lang/Class;)V
      58: aload_0
      59: aload_3
      60: invokestatic  #21                 // Method org/apache/dubbo/rpc/proxy/InvocationUtil.invoke:(Lorg/apache/dubbo/rpc/Invoker;Lorg/apache/dubbo/rpc/RpcInvocation;)Ljava/lang/Object;
      63: areturn
      64: astore        4
      66: aload         4
      68: instanceof    #23                 // class java/lang/RuntimeException
      71: ifeq          80
      74: aload         4
      76: checkcast     #23                 // class java/lang/RuntimeException
      79: athrow
      80: getstatic     #24                 // Field org/apache/dubbo/rpc/TriRpcStatus.INTERNAL:Lorg/apache/dubbo/rpc/TriRpcStatus;
      83: aload         4
      85: invokevirtual #25                 // Method org/apache/dubbo/rpc/TriRpcStatus.withCause:(Ljava/lang/Throwable;)Lorg/apache/dubbo/rpc/TriRpcStatus;
      88: invokevirtual #26                 // Method org/apache/dubbo/rpc/TriRpcStatus.asException:()Lorg/apache/dubbo/rpc/StatusRpcException;
      91: athrow
    Exception table:
       from    to  target type
          58    63    64   Class java/lang/Throwable
}
