Compiled from "StubProxyFactory.java"
public class org.apache.dubbo.rpc.stub.StubProxyFactory implements org.apache.dubbo.rpc.ProxyFactory {
  public org.apache.dubbo.rpc.stub.StubProxyFactory();
    Code:
       0: aload_0
       1: invokespecial #1                  // Method java/lang/Object."<init>":()V
       4: return

  public <T> T getProxy(org.apache.dubbo.rpc.Invoker<T>) throws org.apache.dubbo.rpc.RpcException;
    Code:
       0: aload_1
       1: invokeinterface #2,  1            // InterfaceMethod org/apache/dubbo/rpc/Invoker.getUrl:()Lorg/apache/dubbo/common/URL;
       6: invokevirtual #3                  // Method org/apache/dubbo/common/URL.getServiceInterface:()Ljava/lang/String;
       9: aload_1
      10: invokestatic  #4                  // Method org/apache/dubbo/rpc/stub/StubSuppliers.createStub:(Ljava/lang/String;Lorg/apache/dubbo/rpc/Invoker;)Ljava/lang/Object;
      13: areturn

  public <T> T getProxy(org.apache.dubbo.rpc.Invoker<T>, boolean) throws org.apache.dubbo.rpc.RpcException;
    Code:
       0: aload_0
       1: aload_1
       2: invokevirtual #5                  // Method getProxy:(Lorg/apache/dubbo/rpc/Invoker;)Ljava/lang/Object;
       5: areturn

  public <T> org.apache.dubbo.rpc.Invoker<T> getInvoker(T, java.lang.Class<T>, org.apache.dubbo.common.URL) throws org.apache.dubbo.rpc.RpcException;
    Code:
       0: aload_1
       1: checkcast     #6                  // class org/apache/dubbo/rpc/ServerService
       4: aload_3
       5: invokeinterface #7,  2            // InterfaceMethod org/apache/dubbo/rpc/ServerService.getInvoker:(Lorg/apache/dubbo/common/URL;)Lorg/apache/dubbo/rpc/Invoker;
      10: areturn
}
