Compiled from "UnaryStubMethodHandler.java"
public class org.apache.dubbo.rpc.stub.UnaryStubMethodHandler<T, R> implements org.apache.dubbo.rpc.stub.StubMethodHandler<T, R> {
  private final java.util.function.BiConsumer<T, org.apache.dubbo.common.stream.StreamObserver<R>> func;

  public org.apache.dubbo.rpc.stub.UnaryStubMethodHandler(java.util.function.BiConsumer<T, org.apache.dubbo.common.stream.StreamObserver<R>>);
    Code:
       0: aload_0
       1: invokespecial #1                  // Method java/lang/Object."<init>":()V
       4: aload_0
       5: aload_1
       6: putfield      #2                  // Field func:Ljava/util/function/BiConsumer;
       9: return

  public java.util.concurrent.CompletableFuture<R> invoke(java.lang.Object[]);
    Code:
       0: aload_1
       1: iconst_0
       2: aaload
       3: astore_2
       4: new           #3                  // class java/util/concurrent/CompletableFuture
       7: dup
       8: invokespecial #4                  // Method java/util/concurrent/CompletableFuture."<init>":()V
      11: astore_3
      12: new           #5                  // class org/apache/dubbo/rpc/stub/FutureToObserverAdaptor
      15: dup
      16: aload_3
      17: invokespecial #6                  // Method org/apache/dubbo/rpc/stub/FutureToObserverAdaptor."<init>":(Ljava/util/concurrent/CompletableFuture;)V
      20: astore        4
      22: aload_0
      23: getfield      #2                  // Field func:Ljava/util/function/BiConsumer;
      26: aload_2
      27: aload         4
      29: invokeinterface #7,  3            // InterfaceMethod java/util/function/BiConsumer.accept:(Ljava/lang/Object;Ljava/lang/Object;)V
      34: goto          46
      37: astore        5
      39: aload_3
      40: aload         5
      42: invokevirtual #9                  // Method java/util/concurrent/CompletableFuture.completeExceptionally:(Ljava/lang/Throwable;)Z
      45: pop
      46: aload_3
      47: areturn
    Exception table:
       from    to  target type
          22    34    37   Class java/lang/Throwable
}
