Compiled from "LfuCache.java"
public class org.apache.dubbo.cache.support.lfu.LfuCache implements org.apache.dubbo.cache.Cache {
  private final org.apache.dubbo.common.utils.LFUCache store;

  public org.apache.dubbo.cache.support.lfu.LfuCache(org.apache.dubbo.common.URL);
    Code:
       0: aload_0
       1: invokespecial #1                  // Method java/lang/Object."<init>":()V
       4: aload_1
       5: ldc           #2                  // String cache.size
       7: sipush        1000
      10: invokevirtual #3                  // Method org/apache/dubbo/common/URL.getParameter:(Ljava/lang/String;I)I
      13: istore_2
      14: aload_1
      15: ldc           #4                  // String cache.evictionFactor
      17: ldc           #5                  // float 0.75f
      19: invokevirtual #6                  // Method org/apache/dubbo/common/URL.getParameter:(Ljava/lang/String;F)F
      22: fstore_3
      23: aload_0
      24: new           #7                  // class org/apache/dubbo/common/utils/LFUCache
      27: dup
      28: iload_2
      29: fload_3
      30: invokespecial #8                  // Method org/apache/dubbo/common/utils/LFUCache."<init>":(IF)V
      33: putfield      #9                  // Field store:Lorg/apache/dubbo/common/utils/LFUCache;
      36: return

  public void put(java.lang.Object, java.lang.Object);
    Code:
       0: aload_0
       1: getfield      #9                  // Field store:Lorg/apache/dubbo/common/utils/LFUCache;
       4: aload_1
       5: aload_2
       6: invokevirtual #10                 // Method org/apache/dubbo/common/utils/LFUCache.put:(Ljava/lang/Object;Ljava/lang/Object;)Ljava/lang/Object;
       9: pop
      10: return

  public java.lang.Object get(java.lang.Object);
    Code:
       0: aload_0
       1: getfield      #9                  // Field store:Lorg/apache/dubbo/common/utils/LFUCache;
       4: aload_1
       5: invokevirtual #11                 // Method org/apache/dubbo/common/utils/LFUCache.get:(Ljava/lang/Object;)Ljava/lang/Object;
       8: areturn
}
