Compiled from "AbstractRegistry.java"
class com.alibaba.dubbo.registry.support.AbstractRegistry$CompatibleAbstractRegistry extends org.apache.dubbo.registry.support.AbstractRegistry {
  public com.alibaba.dubbo.registry.support.AbstractRegistry$CompatibleAbstractRegistry(org.apache.dubbo.common.URL);
    Code:
       0: aload_0
       1: aload_1
       2: invokespecial #1                  // Method org/apache/dubbo/registry/support/AbstractRegistry."<init>":(Lorg/apache/dubbo/common/URL;)V
       5: return

  public boolean isAvailable();
    Code:
       0: iconst_0
       1: ireturn

  public void notify(org.apache.dubbo.common.URL, org.apache.dubbo.registry.NotifyListener, java.util.List<org.apache.dubbo.common.URL>);
    Code:
       0: aload_0
       1: aload_1
       2: aload_2
       3: aload_3
       4: invokespecial #2                  // Method org/apache/dubbo/registry/support/AbstractRegistry.notify:(Lorg/apache/dubbo/common/URL;Lorg/apache/dubbo/registry/NotifyListener;Ljava/util/List;)V
       7: return

  public void setUrl(org.apache.dubbo.common.URL);
    Code:
       0: aload_0
       1: aload_1
       2: invokespecial #3                  // Method org/apache/dubbo/registry/support/AbstractRegistry.setUrl:(Lorg/apache/dubbo/common/URL;)V
       5: return
}
