Compiled from "AbstractRegistry.java"
public abstract class com.alibaba.dubbo.registry.support.AbstractRegistry implements org.apache.dubbo.registry.Registry {
  private com.alibaba.dubbo.registry.support.AbstractRegistry$CompatibleAbstractRegistry abstractRegistry;

  public com.alibaba.dubbo.registry.support.AbstractRegistry(com.alibaba.dubbo.common.URL);
    Code:
       0: aload_0
       1: invokespecial #1                  // Method java/lang/Object."<init>":()V
       4: aload_0
       5: new           #2                  // class com/alibaba/dubbo/registry/support/AbstractRegistry$CompatibleAbstractRegistry
       8: dup
       9: aload_1
      10: invokevirtual #3                  // Method com/alibaba/dubbo/common/URL.getOriginalURL:()Lorg/apache/dubbo/common/URL;
      13: invokespecial #4                  // Method com/alibaba/dubbo/registry/support/AbstractRegistry$CompatibleAbstractRegistry."<init>":(Lorg/apache/dubbo/common/URL;)V
      16: putfield      #5                  // Field abstractRegistry:Lcom/alibaba/dubbo/registry/support/AbstractRegistry$CompatibleAbstractRegistry;
      19: return

  public com.alibaba.dubbo.common.URL getUrl();
    Code:
       0: new           #6                  // class com/alibaba/dubbo/common/URL
       3: dup
       4: aload_0
       5: getfield      #5                  // Field abstractRegistry:Lcom/alibaba/dubbo/registry/support/AbstractRegistry$CompatibleAbstractRegistry;
       8: invokevirtual #7                  // Method com/alibaba/dubbo/registry/support/AbstractRegistry$CompatibleAbstractRegistry.getUrl:()Lorg/apache/dubbo/common/URL;
      11: invokespecial #8                  // Method com/alibaba/dubbo/common/URL."<init>":(Lorg/apache/dubbo/common/URL;)V
      14: areturn

  protected void setUrl(com.alibaba.dubbo.common.URL);
    Code:
       0: aload_0
       1: getfield      #5                  // Field abstractRegistry:Lcom/alibaba/dubbo/registry/support/AbstractRegistry$CompatibleAbstractRegistry;
       4: aload_1
       5: invokevirtual #3                  // Method com/alibaba/dubbo/common/URL.getOriginalURL:()Lorg/apache/dubbo/common/URL;
       8: invokevirtual #9                  // Method com/alibaba/dubbo/registry/support/AbstractRegistry$CompatibleAbstractRegistry.setUrl:(Lorg/apache/dubbo/common/URL;)V
      11: return

  public java.util.Set<com.alibaba.dubbo.common.URL> getRegistered();
    Code:
       0: aload_0
       1: getfield      #5                  // Field abstractRegistry:Lcom/alibaba/dubbo/registry/support/AbstractRegistry$CompatibleAbstractRegistry;
       4: invokevirtual #10                 // Method com/alibaba/dubbo/registry/support/AbstractRegistry$CompatibleAbstractRegistry.getRegistered:()Ljava/util/Set;
       7: invokeinterface #11,  1           // InterfaceMethod java/util/Set.stream:()Ljava/util/stream/Stream;
      12: invokedynamic #12,  0             // InvokeDynamic #0:apply:()Ljava/util/function/Function;
      17: invokeinterface #13,  2           // InterfaceMethod java/util/stream/Stream.map:(Ljava/util/function/Function;)Ljava/util/stream/Stream;
      22: invokestatic  #14                 // Method java/util/stream/Collectors.toSet:()Ljava/util/stream/Collector;
      25: invokeinterface #15,  2           // InterfaceMethod java/util/stream/Stream.collect:(Ljava/util/stream/Collector;)Ljava/lang/Object;
      30: checkcast     #16                 // class java/util/Set
      33: areturn

  public java.util.Map<com.alibaba.dubbo.common.URL, java.util.Set<com.alibaba.dubbo.registry.NotifyListener>> getSubscribed();
    Code:
       0: aload_0
       1: getfield      #5                  // Field abstractRegistry:Lcom/alibaba/dubbo/registry/support/AbstractRegistry$CompatibleAbstractRegistry;
       4: invokevirtual #17                 // Method com/alibaba/dubbo/registry/support/AbstractRegistry$CompatibleAbstractRegistry.getSubscribed:()Ljava/util/Map;
       7: invokeinterface #18,  1           // InterfaceMethod java/util/Map.entrySet:()Ljava/util/Set;
      12: invokeinterface #11,  1           // InterfaceMethod java/util/Set.stream:()Ljava/util/stream/Stream;
      17: invokedynamic #19,  0             // InvokeDynamic #1:apply:()Ljava/util/function/Function;
      22: aload_0
      23: invokedynamic #20,  0             // InvokeDynamic #2:apply:(Lcom/alibaba/dubbo/registry/support/AbstractRegistry;)Ljava/util/function/Function;
      28: invokestatic  #21                 // Method java/util/stream/Collectors.toMap:(Ljava/util/function/Function;Ljava/util/function/Function;)Ljava/util/stream/Collector;
      31: invokeinterface #15,  2           // InterfaceMethod java/util/stream/Stream.collect:(Ljava/util/stream/Collector;)Ljava/lang/Object;
      36: checkcast     #22                 // class java/util/Map
      39: areturn

  public java.util.Map<com.alibaba.dubbo.common.URL, java.util.Map<java.lang.String, java.util.List<com.alibaba.dubbo.common.URL>>> getNotified();
    Code:
       0: aload_0
       1: getfield      #5                  // Field abstractRegistry:Lcom/alibaba/dubbo/registry/support/AbstractRegistry$CompatibleAbstractRegistry;
       4: invokevirtual #23                 // Method com/alibaba/dubbo/registry/support/AbstractRegistry$CompatibleAbstractRegistry.getNotified:()Ljava/util/Map;
       7: invokeinterface #18,  1           // InterfaceMethod java/util/Map.entrySet:()Ljava/util/Set;
      12: invokeinterface #11,  1           // InterfaceMethod java/util/Set.stream:()Ljava/util/stream/Stream;
      17: invokedynamic #24,  0             // InvokeDynamic #3:apply:()Ljava/util/function/Function;
      22: invokedynamic #25,  0             // InvokeDynamic #4:apply:()Ljava/util/function/Function;
      27: invokestatic  #21                 // Method java/util/stream/Collectors.toMap:(Ljava/util/function/Function;Ljava/util/function/Function;)Ljava/util/stream/Collector;
      30: invokeinterface #15,  2           // InterfaceMethod java/util/stream/Stream.collect:(Ljava/util/stream/Collector;)Ljava/lang/Object;
      35: checkcast     #22                 // class java/util/Map
      38: areturn

  public java.util.List<com.alibaba.dubbo.common.URL> getCacheUrls(com.alibaba.dubbo.common.URL);
    Code:
       0: aload_0
       1: getfield      #5                  // Field abstractRegistry:Lcom/alibaba/dubbo/registry/support/AbstractRegistry$CompatibleAbstractRegistry;
       4: aload_1
       5: invokevirtual #3                  // Method com/alibaba/dubbo/common/URL.getOriginalURL:()Lorg/apache/dubbo/common/URL;
       8: invokevirtual #26                 // Method com/alibaba/dubbo/registry/support/AbstractRegistry$CompatibleAbstractRegistry.lookup:(Lorg/apache/dubbo/common/URL;)Ljava/util/List;
      11: invokeinterface #27,  1           // InterfaceMethod java/util/List.stream:()Ljava/util/stream/Stream;
      16: invokedynamic #28,  0             // InvokeDynamic #5:apply:()Ljava/util/function/Function;
      21: invokeinterface #13,  2           // InterfaceMethod java/util/stream/Stream.map:(Ljava/util/function/Function;)Ljava/util/stream/Stream;
      26: invokestatic  #29                 // Method java/util/stream/Collectors.toList:()Ljava/util/stream/Collector;
      29: invokeinterface #15,  2           // InterfaceMethod java/util/stream/Stream.collect:(Ljava/util/stream/Collector;)Ljava/lang/Object;
      34: checkcast     #30                 // class java/util/List
      37: areturn

  public java.util.List<com.alibaba.dubbo.common.URL> lookup(com.alibaba.dubbo.common.URL);
    Code:
       0: aload_0
       1: getfield      #5                  // Field abstractRegistry:Lcom/alibaba/dubbo/registry/support/AbstractRegistry$CompatibleAbstractRegistry;
       4: aload_1
       5: invokevirtual #3                  // Method com/alibaba/dubbo/common/URL.getOriginalURL:()Lorg/apache/dubbo/common/URL;
       8: invokevirtual #26                 // Method com/alibaba/dubbo/registry/support/AbstractRegistry$CompatibleAbstractRegistry.lookup:(Lorg/apache/dubbo/common/URL;)Ljava/util/List;
      11: invokeinterface #27,  1           // InterfaceMethod java/util/List.stream:()Ljava/util/stream/Stream;
      16: invokedynamic #31,  0             // InvokeDynamic #6:apply:()Ljava/util/function/Function;
      21: invokeinterface #13,  2           // InterfaceMethod java/util/stream/Stream.map:(Ljava/util/function/Function;)Ljava/util/stream/Stream;
      26: invokestatic  #29                 // Method java/util/stream/Collectors.toList:()Ljava/util/stream/Collector;
      29: invokeinterface #15,  2           // InterfaceMethod java/util/stream/Stream.collect:(Ljava/util/stream/Collector;)Ljava/lang/Object;
      34: checkcast     #30                 // class java/util/List
      37: areturn

  protected void notify(com.alibaba.dubbo.common.URL, com.alibaba.dubbo.registry.NotifyListener, java.util.List<com.alibaba.dubbo.common.URL>);
    Code:
       0: aload_0
       1: getfield      #5                  // Field abstractRegistry:Lcom/alibaba/dubbo/registry/support/AbstractRegistry$CompatibleAbstractRegistry;
       4: aload_1
       5: invokevirtual #3                  // Method com/alibaba/dubbo/common/URL.getOriginalURL:()Lorg/apache/dubbo/common/URL;
       8: new           #32                 // class com/alibaba/dubbo/registry/NotifyListener$ReverseCompatibleNotifyListener
      11: dup
      12: aload_2
      13: invokespecial #33                 // Method com/alibaba/dubbo/registry/NotifyListener$ReverseCompatibleNotifyListener."<init>":(Lcom/alibaba/dubbo/registry/NotifyListener;)V
      16: aload_3
      17: invokeinterface #27,  1           // InterfaceMethod java/util/List.stream:()Ljava/util/stream/Stream;
      22: invokedynamic #34,  0             // InvokeDynamic #7:apply:()Ljava/util/function/Function;
      27: invokeinterface #13,  2           // InterfaceMethod java/util/stream/Stream.map:(Ljava/util/function/Function;)Ljava/util/stream/Stream;
      32: invokestatic  #29                 // Method java/util/stream/Collectors.toList:()Ljava/util/stream/Collector;
      35: invokeinterface #15,  2           // InterfaceMethod java/util/stream/Stream.collect:(Ljava/util/stream/Collector;)Ljava/lang/Object;
      40: checkcast     #30                 // class java/util/List
      43: invokevirtual #35                 // Method com/alibaba/dubbo/registry/support/AbstractRegistry$CompatibleAbstractRegistry.notify:(Lorg/apache/dubbo/common/URL;Lorg/apache/dubbo/registry/NotifyListener;Ljava/util/List;)V
      46: return

  public void register(com.alibaba.dubbo.common.URL);
    Code:
       0: aload_0
       1: getfield      #5                  // Field abstractRegistry:Lcom/alibaba/dubbo/registry/support/AbstractRegistry$CompatibleAbstractRegistry;
       4: aload_1
       5: invokevirtual #3                  // Method com/alibaba/dubbo/common/URL.getOriginalURL:()Lorg/apache/dubbo/common/URL;
       8: invokevirtual #36                 // Method com/alibaba/dubbo/registry/support/AbstractRegistry$CompatibleAbstractRegistry.register:(Lorg/apache/dubbo/common/URL;)V
      11: return

  public void unregister(com.alibaba.dubbo.common.URL);
    Code:
       0: aload_0
       1: getfield      #5                  // Field abstractRegistry:Lcom/alibaba/dubbo/registry/support/AbstractRegistry$CompatibleAbstractRegistry;
       4: aload_1
       5: invokevirtual #3                  // Method com/alibaba/dubbo/common/URL.getOriginalURL:()Lorg/apache/dubbo/common/URL;
       8: invokevirtual #37                 // Method com/alibaba/dubbo/registry/support/AbstractRegistry$CompatibleAbstractRegistry.unregister:(Lorg/apache/dubbo/common/URL;)V
      11: return

  public void subscribe(com.alibaba.dubbo.common.URL, com.alibaba.dubbo.registry.NotifyListener);
    Code:
       0: aload_0
       1: getfield      #5                  // Field abstractRegistry:Lcom/alibaba/dubbo/registry/support/AbstractRegistry$CompatibleAbstractRegistry;
       4: aload_1
       5: invokevirtual #3                  // Method com/alibaba/dubbo/common/URL.getOriginalURL:()Lorg/apache/dubbo/common/URL;
       8: new           #32                 // class com/alibaba/dubbo/registry/NotifyListener$ReverseCompatibleNotifyListener
      11: dup
      12: aload_2
      13: invokespecial #33                 // Method com/alibaba/dubbo/registry/NotifyListener$ReverseCompatibleNotifyListener."<init>":(Lcom/alibaba/dubbo/registry/NotifyListener;)V
      16: invokevirtual #38                 // Method com/alibaba/dubbo/registry/support/AbstractRegistry$CompatibleAbstractRegistry.subscribe:(Lorg/apache/dubbo/common/URL;Lorg/apache/dubbo/registry/NotifyListener;)V
      19: return

  public void unsubscribe(com.alibaba.dubbo.common.URL, com.alibaba.dubbo.registry.NotifyListener);
    Code:
       0: aload_0
       1: getfield      #5                  // Field abstractRegistry:Lcom/alibaba/dubbo/registry/support/AbstractRegistry$CompatibleAbstractRegistry;
       4: aload_1
       5: invokevirtual #3                  // Method com/alibaba/dubbo/common/URL.getOriginalURL:()Lorg/apache/dubbo/common/URL;
       8: new           #32                 // class com/alibaba/dubbo/registry/NotifyListener$ReverseCompatibleNotifyListener
      11: dup
      12: aload_2
      13: invokespecial #33                 // Method com/alibaba/dubbo/registry/NotifyListener$ReverseCompatibleNotifyListener."<init>":(Lcom/alibaba/dubbo/registry/NotifyListener;)V
      16: invokevirtual #39                 // Method com/alibaba/dubbo/registry/support/AbstractRegistry$CompatibleAbstractRegistry.unsubscribe:(Lorg/apache/dubbo/common/URL;Lorg/apache/dubbo/registry/NotifyListener;)V
      19: return

  public void register(org.apache.dubbo.common.URL);
    Code:
       0: aload_0
       1: new           #6                  // class com/alibaba/dubbo/common/URL
       4: dup
       5: aload_1
       6: invokespecial #8                  // Method com/alibaba/dubbo/common/URL."<init>":(Lorg/apache/dubbo/common/URL;)V
       9: invokevirtual #40                 // Method register:(Lcom/alibaba/dubbo/common/URL;)V
      12: return

  public void unregister(org.apache.dubbo.common.URL);
    Code:
       0: aload_0
       1: new           #6                  // class com/alibaba/dubbo/common/URL
       4: dup
       5: aload_1
       6: invokespecial #8                  // Method com/alibaba/dubbo/common/URL."<init>":(Lorg/apache/dubbo/common/URL;)V
       9: invokevirtual #41                 // Method unregister:(Lcom/alibaba/dubbo/common/URL;)V
      12: return

  public void subscribe(org.apache.dubbo.common.URL, org.apache.dubbo.registry.NotifyListener);
    Code:
       0: aload_0
       1: new           #6                  // class com/alibaba/dubbo/common/URL
       4: dup
       5: aload_1
       6: invokespecial #8                  // Method com/alibaba/dubbo/common/URL."<init>":(Lorg/apache/dubbo/common/URL;)V
       9: new           #42                 // class com/alibaba/dubbo/registry/NotifyListener$CompatibleNotifyListener
      12: dup
      13: aload_2
      14: invokespecial #43                 // Method com/alibaba/dubbo/registry/NotifyListener$CompatibleNotifyListener."<init>":(Lorg/apache/dubbo/registry/NotifyListener;)V
      17: invokevirtual #44                 // Method subscribe:(Lcom/alibaba/dubbo/common/URL;Lcom/alibaba/dubbo/registry/NotifyListener;)V
      20: return

  public void unsubscribe(org.apache.dubbo.common.URL, org.apache.dubbo.registry.NotifyListener);
    Code:
       0: aload_0
       1: new           #6                  // class com/alibaba/dubbo/common/URL
       4: dup
       5: aload_1
       6: invokespecial #8                  // Method com/alibaba/dubbo/common/URL."<init>":(Lorg/apache/dubbo/common/URL;)V
       9: new           #42                 // class com/alibaba/dubbo/registry/NotifyListener$CompatibleNotifyListener
      12: dup
      13: aload_2
      14: invokespecial #43                 // Method com/alibaba/dubbo/registry/NotifyListener$CompatibleNotifyListener."<init>":(Lorg/apache/dubbo/registry/NotifyListener;)V
      17: invokevirtual #45                 // Method unsubscribe:(Lcom/alibaba/dubbo/common/URL;Lcom/alibaba/dubbo/registry/NotifyListener;)V
      20: return

  final java.util.Set<com.alibaba.dubbo.registry.NotifyListener> convertToNotifyListeners(java.util.Set<org.apache.dubbo.registry.NotifyListener>);
    Code:
       0: aload_1
       1: invokeinterface #11,  1           // InterfaceMethod java/util/Set.stream:()Ljava/util/stream/Stream;
       6: invokedynamic #46,  0             // InvokeDynamic #8:apply:()Ljava/util/function/Function;
      11: invokeinterface #13,  2           // InterfaceMethod java/util/stream/Stream.map:(Ljava/util/function/Function;)Ljava/util/stream/Stream;
      16: invokestatic  #14                 // Method java/util/stream/Collectors.toSet:()Ljava/util/stream/Collector;
      19: invokeinterface #15,  2           // InterfaceMethod java/util/stream/Stream.collect:(Ljava/util/stream/Collector;)Ljava/lang/Object;
      24: checkcast     #16                 // class java/util/Set
      27: areturn

  public org.apache.dubbo.common.URL getUrl();
    Code:
       0: aload_0
       1: invokevirtual #47                 // Method getUrl:()Lcom/alibaba/dubbo/common/URL;
       4: areturn

  private static com.alibaba.dubbo.registry.NotifyListener$CompatibleNotifyListener lambda$convertToNotifyListeners$11(org.apache.dubbo.registry.NotifyListener);
    Code:
       0: new           #42                 // class com/alibaba/dubbo/registry/NotifyListener$CompatibleNotifyListener
       3: dup
       4: aload_0
       5: invokespecial #43                 // Method com/alibaba/dubbo/registry/NotifyListener$CompatibleNotifyListener."<init>":(Lorg/apache/dubbo/registry/NotifyListener;)V
       8: areturn

  private static org.apache.dubbo.common.URL lambda$notify$10(com.alibaba.dubbo.common.URL);
    Code:
       0: aload_0
       1: invokevirtual #3                  // Method com/alibaba/dubbo/common/URL.getOriginalURL:()Lorg/apache/dubbo/common/URL;
       4: areturn

  private static com.alibaba.dubbo.common.URL lambda$lookup$9(org.apache.dubbo.common.URL);
    Code:
       0: new           #6                  // class com/alibaba/dubbo/common/URL
       3: dup
       4: aload_0
       5: invokespecial #8                  // Method com/alibaba/dubbo/common/URL."<init>":(Lorg/apache/dubbo/common/URL;)V
       8: areturn

  private static com.alibaba.dubbo.common.URL lambda$getCacheUrls$8(org.apache.dubbo.common.URL);
    Code:
       0: new           #6                  // class com/alibaba/dubbo/common/URL
       3: dup
       4: aload_0
       5: invokespecial #8                  // Method com/alibaba/dubbo/common/URL."<init>":(Lorg/apache/dubbo/common/URL;)V
       8: areturn

  private static java.util.Map lambda$getNotified$7(java.util.Map$Entry);
    Code:
       0: aload_0
       1: invokeinterface #48,  1           // InterfaceMethod java/util/Map$Entry.getValue:()Ljava/lang/Object;
       6: checkcast     #22                 // class java/util/Map
       9: invokeinterface #18,  1           // InterfaceMethod java/util/Map.entrySet:()Ljava/util/Set;
      14: invokeinterface #11,  1           // InterfaceMethod java/util/Set.stream:()Ljava/util/stream/Stream;
      19: invokedynamic #49,  0             // InvokeDynamic #9:apply:()Ljava/util/function/Function;
      24: invokedynamic #50,  0             // InvokeDynamic #10:apply:()Ljava/util/function/Function;
      29: invokestatic  #21                 // Method java/util/stream/Collectors.toMap:(Ljava/util/function/Function;Ljava/util/function/Function;)Ljava/util/stream/Collector;
      32: invokeinterface #15,  2           // InterfaceMethod java/util/stream/Stream.collect:(Ljava/util/stream/Collector;)Ljava/lang/Object;
      37: checkcast     #22                 // class java/util/Map
      40: areturn

  private static java.util.List lambda$null$6(java.util.Map$Entry);
    Code:
       0: aload_0
       1: invokeinterface #48,  1           // InterfaceMethod java/util/Map$Entry.getValue:()Ljava/lang/Object;
       6: checkcast     #30                 // class java/util/List
       9: invokeinterface #27,  1           // InterfaceMethod java/util/List.stream:()Ljava/util/stream/Stream;
      14: invokedynamic #51,  0             // InvokeDynamic #11:apply:()Ljava/util/function/Function;
      19: invokeinterface #13,  2           // InterfaceMethod java/util/stream/Stream.map:(Ljava/util/function/Function;)Ljava/util/stream/Stream;
      24: invokestatic  #29                 // Method java/util/stream/Collectors.toList:()Ljava/util/stream/Collector;
      27: invokeinterface #15,  2           // InterfaceMethod java/util/stream/Stream.collect:(Ljava/util/stream/Collector;)Ljava/lang/Object;
      32: checkcast     #30                 // class java/util/List
      35: areturn

  private static com.alibaba.dubbo.common.URL lambda$null$5(org.apache.dubbo.common.URL);
    Code:
       0: new           #6                  // class com/alibaba/dubbo/common/URL
       3: dup
       4: aload_0
       5: invokespecial #8                  // Method com/alibaba/dubbo/common/URL."<init>":(Lorg/apache/dubbo/common/URL;)V
       8: areturn

  private static java.lang.String lambda$null$4(java.util.Map$Entry);
    Code:
       0: aload_0
       1: invokeinterface #52,  1           // InterfaceMethod java/util/Map$Entry.getKey:()Ljava/lang/Object;
       6: checkcast     #53                 // class java/lang/String
       9: areturn

  private static com.alibaba.dubbo.common.URL lambda$getNotified$3(java.util.Map$Entry);
    Code:
       0: new           #6                  // class com/alibaba/dubbo/common/URL
       3: dup
       4: aload_0
       5: invokeinterface #52,  1           // InterfaceMethod java/util/Map$Entry.getKey:()Ljava/lang/Object;
      10: checkcast     #54                 // class org/apache/dubbo/common/URL
      13: invokespecial #8                  // Method com/alibaba/dubbo/common/URL."<init>":(Lorg/apache/dubbo/common/URL;)V
      16: areturn

  private java.util.Set lambda$getSubscribed$2(java.util.Map$Entry);
    Code:
       0: aload_0
       1: aload_1
       2: invokeinterface #48,  1           // InterfaceMethod java/util/Map$Entry.getValue:()Ljava/lang/Object;
       7: checkcast     #16                 // class java/util/Set
      10: invokevirtual #55                 // Method convertToNotifyListeners:(Ljava/util/Set;)Ljava/util/Set;
      13: areturn

  private static com.alibaba.dubbo.common.URL lambda$getSubscribed$1(java.util.Map$Entry);
    Code:
       0: new           #6                  // class com/alibaba/dubbo/common/URL
       3: dup
       4: aload_0
       5: invokeinterface #52,  1           // InterfaceMethod java/util/Map$Entry.getKey:()Ljava/lang/Object;
      10: checkcast     #54                 // class org/apache/dubbo/common/URL
      13: invokespecial #8                  // Method com/alibaba/dubbo/common/URL."<init>":(Lorg/apache/dubbo/common/URL;)V
      16: areturn

  private static com.alibaba.dubbo.common.URL lambda$getRegistered$0(org.apache.dubbo.common.URL);
    Code:
       0: new           #6                  // class com/alibaba/dubbo/common/URL
       3: dup
       4: aload_0
       5: invokespecial #8                  // Method com/alibaba/dubbo/common/URL."<init>":(Lorg/apache/dubbo/common/URL;)V
       8: areturn
}
