Compiled from "AbstractRegistryFactory.java"
public abstract class com.alibaba.dubbo.registry.support.AbstractRegistryFactory extends org.apache.dubbo.registry.support.AbstractRegistryFactory implements com.alibaba.dubbo.registry.RegistryFactory {
  public com.alibaba.dubbo.registry.support.AbstractRegistryFactory();
    Code:
       0: aload_0
       1: invokespecial #1                  // Method org/apache/dubbo/registry/support/AbstractRegistryFactory."<init>":()V
       4: return

  public com.alibaba.dubbo.registry.Registry getRegistry(com.alibaba.dubbo.common.URL);
    Code:
       0: aload_0
       1: aload_1
       2: invokevirtual #2                  // Method com/alibaba/dubbo/common/URL.getOriginalURL:()Lorg/apache/dubbo/common/URL;
       5: invokespecial #3                  // Method org/apache/dubbo/registry/support/AbstractRegistryFactory.getRegistry:(Lorg/apache/dubbo/common/URL;)Lorg/apache/dubbo/registry/Registry;
       8: checkcast     #4                  // class com/alibaba/dubbo/registry/Registry
      11: areturn

  protected abstract com.alibaba.dubbo.registry.Registry createRegistry(com.alibaba.dubbo.common.URL);

  protected org.apache.dubbo.registry.Registry createRegistry(org.apache.dubbo.common.URL);
    Code:
       0: aload_0
       1: new           #5                  // class com/alibaba/dubbo/common/URL
       4: dup
       5: aload_1
       6: invokespecial #6                  // Method com/alibaba/dubbo/common/URL."<init>":(Lorg/apache/dubbo/common/URL;)V
       9: invokevirtual #7                  // Method createRegistry:(Lcom/alibaba/dubbo/common/URL;)Lcom/alibaba/dubbo/registry/Registry;
      12: areturn
}
