Compiled from "FailbackRegistry.java"
class com.alibaba.dubbo.registry.support.FailbackRegistry$CompatibleFailbackRegistry extends org.apache.dubbo.registry.support.FailbackRegistry {
  private com.alibaba.dubbo.registry.support.FailbackRegistry compatibleFailbackRegistry;

  public com.alibaba.dubbo.registry.support.FailbackRegistry$CompatibleFailbackRegistry(org.apache.dubbo.common.URL, com.alibaba.dubbo.registry.support.FailbackRegistry);
    Code:
       0: aload_0
       1: aload_1
       2: invokespecial #1                  // Method org/apache/dubbo/registry/support/FailbackRegistry."<init>":(Lorg/apache/dubbo/common/URL;)V
       5: aload_0
       6: aload_2
       7: putfield      #2                  // Field compatibleFailbackRegistry:Lcom/alibaba/dubbo/registry/support/FailbackRegistry;
      10: return

  public void doRegister(org.apache.dubbo.common.URL);
    Code:
       0: aload_0
       1: getfield      #2                  // Field compatibleFailbackRegistry:Lcom/alibaba/dubbo/registry/support/FailbackRegistry;
       4: new           #3                  // class com/alibaba/dubbo/common/URL
       7: dup
       8: aload_1
       9: invokespecial #4                  // Method com/alibaba/dubbo/common/URL."<init>":(Lorg/apache/dubbo/common/URL;)V
      12: invokevirtual #5                  // Method com/alibaba/dubbo/registry/support/FailbackRegistry.doRegister:(Lcom/alibaba/dubbo/common/URL;)V
      15: return

  public void doUnregister(org.apache.dubbo.common.URL);
    Code:
       0: aload_0
       1: getfield      #2                  // Field compatibleFailbackRegistry:Lcom/alibaba/dubbo/registry/support/FailbackRegistry;
       4: new           #3                  // class com/alibaba/dubbo/common/URL
       7: dup
       8: aload_1
       9: invokespecial #4                  // Method com/alibaba/dubbo/common/URL."<init>":(Lorg/apache/dubbo/common/URL;)V
      12: invokevirtual #6                  // Method com/alibaba/dubbo/registry/support/FailbackRegistry.doUnregister:(Lcom/alibaba/dubbo/common/URL;)V
      15: return

  public void doSubscribe(org.apache.dubbo.common.URL, org.apache.dubbo.registry.NotifyListener);
    Code:
       0: aload_0
       1: getfield      #2                  // Field compatibleFailbackRegistry:Lcom/alibaba/dubbo/registry/support/FailbackRegistry;
       4: new           #3                  // class com/alibaba/dubbo/common/URL
       7: dup
       8: aload_1
       9: invokespecial #4                  // Method com/alibaba/dubbo/common/URL."<init>":(Lorg/apache/dubbo/common/URL;)V
      12: new           #7                  // class com/alibaba/dubbo/registry/NotifyListener$CompatibleNotifyListener
      15: dup
      16: aload_2
      17: invokespecial #8                  // Method com/alibaba/dubbo/registry/NotifyListener$CompatibleNotifyListener."<init>":(Lorg/apache/dubbo/registry/NotifyListener;)V
      20: invokevirtual #9                  // Method com/alibaba/dubbo/registry/support/FailbackRegistry.doSubscribe:(Lcom/alibaba/dubbo/common/URL;Lcom/alibaba/dubbo/registry/NotifyListener;)V
      23: return

  public void doUnsubscribe(org.apache.dubbo.common.URL, org.apache.dubbo.registry.NotifyListener);
    Code:
       0: aload_0
       1: getfield      #2                  // Field compatibleFailbackRegistry:Lcom/alibaba/dubbo/registry/support/FailbackRegistry;
       4: new           #3                  // class com/alibaba/dubbo/common/URL
       7: dup
       8: aload_1
       9: invokespecial #4                  // Method com/alibaba/dubbo/common/URL."<init>":(Lorg/apache/dubbo/common/URL;)V
      12: new           #7                  // class com/alibaba/dubbo/registry/NotifyListener$CompatibleNotifyListener
      15: dup
      16: aload_2
      17: invokespecial #8                  // Method com/alibaba/dubbo/registry/NotifyListener$CompatibleNotifyListener."<init>":(Lorg/apache/dubbo/registry/NotifyListener;)V
      20: invokevirtual #10                 // Method com/alibaba/dubbo/registry/support/FailbackRegistry.doUnsubscribe:(Lcom/alibaba/dubbo/common/URL;Lcom/alibaba/dubbo/registry/NotifyListener;)V
      23: return

  public void notify(org.apache.dubbo.common.URL, org.apache.dubbo.registry.NotifyListener, java.util.List<org.apache.dubbo.common.URL>);
    Code:
       0: aload_0
       1: aload_1
       2: aload_2
       3: aload_3
       4: invokespecial #11                 // Method org/apache/dubbo/registry/support/FailbackRegistry.notify:(Lorg/apache/dubbo/common/URL;Lorg/apache/dubbo/registry/NotifyListener;Ljava/util/List;)V
       7: return

  public void doNotify(org.apache.dubbo.common.URL, org.apache.dubbo.registry.NotifyListener, java.util.List<org.apache.dubbo.common.URL>);
    Code:
       0: aload_0
       1: aload_1
       2: aload_2
       3: aload_3
       4: invokespecial #12                 // Method org/apache/dubbo/registry/support/FailbackRegistry.doNotify:(Lorg/apache/dubbo/common/URL;Lorg/apache/dubbo/registry/NotifyListener;Ljava/util/List;)V
       7: return

  public boolean isAvailable();
    Code:
       0: iconst_0
       1: ireturn

  public void recover() throws java.lang.Exception;
    Code:
       0: aload_0
       1: invokespecial #13                 // Method org/apache/dubbo/registry/support/FailbackRegistry.recover:()V
       4: return
}
