Compiled from "Status.java"
public class com.alibaba.dubbo.common.status.Status extends org.apache.dubbo.common.status.Status {
  public com.alibaba.dubbo.common.status.Status(org.apache.dubbo.common.status.Status$Level);
    Code:
       0: aload_0
       1: aload_1
       2: invokespecial #1                  // Method org/apache/dubbo/common/status/Status."<init>":(Lorg/apache/dubbo/common/status/Status$Level;)V
       5: return

  public com.alibaba.dubbo.common.status.Status(org.apache.dubbo.common.status.Status$Level, java.lang.String);
    Code:
       0: aload_0
       1: aload_1
       2: aload_2
       3: invokespecial #2                  // Method org/apache/dubbo/common/status/Status."<init>":(Lorg/apache/dubbo/common/status/Status$Level;Ljava/lang/String;)V
       6: return

  public com.alibaba.dubbo.common.status.Status(org.apache.dubbo.common.status.Status$Level, java.lang.String, java.lang.String);
    Code:
       0: aload_0
       1: aload_1
       2: aload_2
       3: aload_3
       4: invokespecial #3                  // Method org/apache/dubbo/common/status/Status."<init>":(Lorg/apache/dubbo/common/status/Status$Level;Ljava/lang/String;Ljava/lang/String;)V
       7: return
}
