Compiled from "AbstractCluster.java"
class org.apache.dubbo.rpc.cluster.support.wrapper.AbstractCluster$ClusterFilterInvoker<T> extends org.apache.dubbo.rpc.cluster.support.AbstractClusterInvoker<T> {
  private final org.apache.dubbo.rpc.cluster.ClusterInvoker<T> filterInvoker;

  public org.apache.dubbo.rpc.cluster.support.wrapper.AbstractCluster$ClusterFilterInvoker(org.apache.dubbo.rpc.cluster.support.AbstractClusterInvoker<T>);
    Code:
       0: aload_0
       1: invokespecial #2                  // Method org/apache/dubbo/rpc/cluster/support/AbstractClusterInvoker."<init>":()V
       4: aload_1
       5: invokevirtual #3                  // Method org/apache/dubbo/rpc/cluster/support/AbstractClusterInvoker.getUrl:()Lorg/apache/dubbo/common/URL;
       8: invokevirtual #4                  // Method org/apache/dubbo/common/URL.getScopeModel:()Lorg/apache/dubbo/rpc/model/ScopeModel;
      11: invokestatic  #5                  // Method org/apache/dubbo/rpc/model/ScopeModelUtil.getApplicationModel:(Lorg/apache/dubbo/rpc/model/ScopeModel;)Lorg/apache/dubbo/rpc/model/ApplicationModel;
      14: ldc           #6                  // class org/apache/dubbo/rpc/cluster/filter/FilterChainBuilder
      16: invokevirtual #7                  // Method org/apache/dubbo/rpc/model/ApplicationModel.getExtensionLoader:(Ljava/lang/Class;)Lorg/apache/dubbo/common/extension/ExtensionLoader;
      19: invokevirtual #8                  // Method org/apache/dubbo/common/extension/ExtensionLoader.getActivateExtensions:()Ljava/util/List;
      22: astore_2
      23: aload_2
      24: invokestatic  #9                  // Method org/apache/dubbo/common/utils/CollectionUtils.isEmpty:(Ljava/util/Collection;)Z
      27: ifeq          38
      30: aload_0
      31: aload_1
      32: putfield      #10                 // Field filterInvoker:Lorg/apache/dubbo/rpc/cluster/ClusterInvoker;
      35: goto          91
      38: aload_1
      39: astore_3
      40: aload_2
      41: invokeinterface #11,  1           // InterfaceMethod java/util/List.iterator:()Ljava/util/Iterator;
      46: astore        4
      48: aload         4
      50: invokeinterface #12,  1           // InterfaceMethod java/util/Iterator.hasNext:()Z
      55: ifeq          86
      58: aload         4
      60: invokeinterface #13,  1           // InterfaceMethod java/util/Iterator.next:()Ljava/lang/Object;
      65: checkcast     #6                  // class org/apache/dubbo/rpc/cluster/filter/FilterChainBuilder
      68: astore        5
      70: aload         5
      72: aload_3
      73: ldc           #14                 // String reference.filter
      75: ldc           #15                 // String consumer
      77: invokeinterface #16,  4           // InterfaceMethod org/apache/dubbo/rpc/cluster/filter/FilterChainBuilder.buildClusterInvokerChain:(Lorg/apache/dubbo/rpc/cluster/ClusterInvoker;Ljava/lang/String;Ljava/lang/String;)Lorg/apache/dubbo/rpc/cluster/ClusterInvoker;
      82: astore_3
      83: goto          48
      86: aload_0
      87: aload_3
      88: putfield      #10                 // Field filterInvoker:Lorg/apache/dubbo/rpc/cluster/ClusterInvoker;
      91: return

  public org.apache.dubbo.rpc.Result invoke(org.apache.dubbo.rpc.Invocation) throws org.apache.dubbo.rpc.RpcException;
    Code:
       0: aload_0
       1: getfield      #10                 // Field filterInvoker:Lorg/apache/dubbo/rpc/cluster/ClusterInvoker;
       4: aload_1
       5: invokeinterface #17,  2           // InterfaceMethod org/apache/dubbo/rpc/cluster/ClusterInvoker.invoke:(Lorg/apache/dubbo/rpc/Invocation;)Lorg/apache/dubbo/rpc/Result;
      10: areturn

  public org.apache.dubbo.rpc.cluster.Directory<T> getDirectory();
    Code:
       0: aload_0
       1: getfield      #10                 // Field filterInvoker:Lorg/apache/dubbo/rpc/cluster/ClusterInvoker;
       4: invokeinterface #18,  1           // InterfaceMethod org/apache/dubbo/rpc/cluster/ClusterInvoker.getDirectory:()Lorg/apache/dubbo/rpc/cluster/Directory;
       9: areturn

  public org.apache.dubbo.common.URL getRegistryUrl();
    Code:
       0: aload_0
       1: getfield      #10                 // Field filterInvoker:Lorg/apache/dubbo/rpc/cluster/ClusterInvoker;
       4: invokeinterface #19,  1           // InterfaceMethod org/apache/dubbo/rpc/cluster/ClusterInvoker.getRegistryUrl:()Lorg/apache/dubbo/common/URL;
       9: areturn

  public boolean isDestroyed();
    Code:
       0: aload_0
       1: getfield      #10                 // Field filterInvoker:Lorg/apache/dubbo/rpc/cluster/ClusterInvoker;
       4: invokeinterface #20,  1           // InterfaceMethod org/apache/dubbo/rpc/cluster/ClusterInvoker.isDestroyed:()Z
       9: ireturn

  public org.apache.dubbo.common.URL getUrl();
    Code:
       0: aload_0
       1: getfield      #10                 // Field filterInvoker:Lorg/apache/dubbo/rpc/cluster/ClusterInvoker;
       4: invokeinterface #21,  1           // InterfaceMethod org/apache/dubbo/rpc/cluster/ClusterInvoker.getUrl:()Lorg/apache/dubbo/common/URL;
       9: areturn

  protected org.apache.dubbo.rpc.Result doInvoke(org.apache.dubbo.rpc.Invocation, java.util.List<org.apache.dubbo.rpc.Invoker<T>>, org.apache.dubbo.rpc.cluster.LoadBalance) throws org.apache.dubbo.rpc.RpcException;
    Code:
       0: aconst_null
       1: areturn

  public org.apache.dubbo.rpc.cluster.ClusterInvoker<T> getFilterInvoker();
    Code:
       0: aload_0
       1: getfield      #10                 // Field filterInvoker:Lorg/apache/dubbo/rpc/cluster/ClusterInvoker;
       4: areturn
}
