Compiled from "AbstractCluster.java"
public abstract class org.apache.dubbo.rpc.cluster.support.wrapper.AbstractCluster implements org.apache.dubbo.rpc.cluster.Cluster {
  public org.apache.dubbo.rpc.cluster.support.wrapper.AbstractCluster();
    Code:
       0: aload_0
       1: invokespecial #2                  // Method java/lang/Object."<init>":()V
       4: return

  private <T> org.apache.dubbo.rpc.Invoker<T> buildClusterInterceptors(org.apache.dubbo.rpc.cluster.support.AbstractClusterInvoker<T>);
    Code:
       0: aload_0
       1: new           #3                  // class org/apache/dubbo/rpc/cluster/support/wrapper/AbstractCluster$ClusterFilterInvoker
       4: dup
       5: aload_1
       6: invokespecial #4                  // Method org/apache/dubbo/rpc/cluster/support/wrapper/AbstractCluster$ClusterFilterInvoker."<init>":(Lorg/apache/dubbo/rpc/cluster/support/AbstractClusterInvoker;)V
       9: invokespecial #5                  // Method buildInterceptorInvoker:(Lorg/apache/dubbo/rpc/cluster/support/AbstractClusterInvoker;)Lorg/apache/dubbo/rpc/cluster/support/AbstractClusterInvoker;
      12: astore_2
      13: aload_1
      14: invokevirtual #6                  // Method org/apache/dubbo/rpc/cluster/support/AbstractClusterInvoker.getDirectory:()Lorg/apache/dubbo/rpc/cluster/Directory;
      17: invokeinterface #7,  1            // InterfaceMethod org/apache/dubbo/rpc/cluster/Directory.getConsumerUrl:()Lorg/apache/dubbo/common/URL;
      22: invokevirtual #8                  // Method org/apache/dubbo/common/URL.getScopeModel:()Lorg/apache/dubbo/rpc/model/ScopeModel;
      25: ldc           #9                  // String dubbo.application.cluster.interceptor.compatible
      27: ldc           #10                 // String false
      29: invokestatic  #11                 // Method org/apache/dubbo/common/config/ConfigurationUtils.getProperty:(Lorg/apache/dubbo/rpc/model/ScopeModel;Ljava/lang/String;Ljava/lang/String;)Ljava/lang/String;
      32: invokestatic  #12                 // Method java/lang/Boolean.parseBoolean:(Ljava/lang/String;)Z
      35: ifeq          45
      38: aload_0
      39: aload_1
      40: aload_2
      41: invokespecial #13                 // Method build27xCompatibleClusterInterceptors:(Lorg/apache/dubbo/rpc/cluster/support/AbstractClusterInvoker;Lorg/apache/dubbo/rpc/cluster/support/AbstractClusterInvoker;)Lorg/apache/dubbo/rpc/cluster/ClusterInvoker;
      44: areturn
      45: aload_2
      46: areturn

  public <T> org.apache.dubbo.rpc.Invoker<T> join(org.apache.dubbo.rpc.cluster.Directory<T>, boolean) throws org.apache.dubbo.rpc.RpcException;
    Code:
       0: iload_2
       1: ifeq          14
       4: aload_0
       5: aload_0
       6: aload_1
       7: invokevirtual #14                 // Method doJoin:(Lorg/apache/dubbo/rpc/cluster/Directory;)Lorg/apache/dubbo/rpc/cluster/support/AbstractClusterInvoker;
      10: invokespecial #15                 // Method buildClusterInterceptors:(Lorg/apache/dubbo/rpc/cluster/support/AbstractClusterInvoker;)Lorg/apache/dubbo/rpc/Invoker;
      13: areturn
      14: aload_0
      15: aload_1
      16: invokevirtual #14                 // Method doJoin:(Lorg/apache/dubbo/rpc/cluster/Directory;)Lorg/apache/dubbo/rpc/cluster/support/AbstractClusterInvoker;
      19: areturn

  private <T> org.apache.dubbo.rpc.cluster.support.AbstractClusterInvoker<T> buildInterceptorInvoker(org.apache.dubbo.rpc.cluster.support.AbstractClusterInvoker<T>);
    Code:
       0: aload_1
       1: invokevirtual #16                 // Method org/apache/dubbo/rpc/cluster/support/AbstractClusterInvoker.getUrl:()Lorg/apache/dubbo/common/URL;
       4: invokevirtual #8                  // Method org/apache/dubbo/common/URL.getScopeModel:()Lorg/apache/dubbo/rpc/model/ScopeModel;
       7: invokestatic  #17                 // Method org/apache/dubbo/rpc/model/ScopeModelUtil.getApplicationModel:(Lorg/apache/dubbo/rpc/model/ScopeModel;)Lorg/apache/dubbo/rpc/model/ApplicationModel;
      10: ldc           #18                 // class org/apache/dubbo/rpc/cluster/filter/InvocationInterceptorBuilder
      12: invokevirtual #19                 // Method org/apache/dubbo/rpc/model/ApplicationModel.getExtensionLoader:(Ljava/lang/Class;)Lorg/apache/dubbo/common/extension/ExtensionLoader;
      15: invokevirtual #20                 // Method org/apache/dubbo/common/extension/ExtensionLoader.getActivateExtensions:()Ljava/util/List;
      18: astore_2
      19: aload_2
      20: invokestatic  #21                 // Method org/apache/dubbo/common/utils/CollectionUtils.isEmpty:(Ljava/util/Collection;)Z
      23: ifeq          28
      26: aload_1
      27: areturn
      28: new           #22                 // class org/apache/dubbo/rpc/cluster/support/wrapper/AbstractCluster$InvocationInterceptorInvoker
      31: dup
      32: aload_1
      33: aload_2
      34: invokespecial #23                 // Method org/apache/dubbo/rpc/cluster/support/wrapper/AbstractCluster$InvocationInterceptorInvoker."<init>":(Lorg/apache/dubbo/rpc/cluster/support/AbstractClusterInvoker;Ljava/util/List;)V
      37: areturn

  protected abstract <T> org.apache.dubbo.rpc.cluster.support.AbstractClusterInvoker<T> doJoin(org.apache.dubbo.rpc.cluster.Directory<T>) throws org.apache.dubbo.rpc.RpcException;

  private <T> org.apache.dubbo.rpc.cluster.ClusterInvoker<T> build27xCompatibleClusterInterceptors(org.apache.dubbo.rpc.cluster.support.AbstractClusterInvoker<T>, org.apache.dubbo.rpc.cluster.support.AbstractClusterInvoker<T>);
    Code:
       0: aload_1
       1: invokevirtual #16                 // Method org/apache/dubbo/rpc/cluster/support/AbstractClusterInvoker.getUrl:()Lorg/apache/dubbo/common/URL;
       4: invokevirtual #8                  // Method org/apache/dubbo/common/URL.getScopeModel:()Lorg/apache/dubbo/rpc/model/ScopeModel;
       7: invokestatic  #17                 // Method org/apache/dubbo/rpc/model/ScopeModelUtil.getApplicationModel:(Lorg/apache/dubbo/rpc/model/ScopeModel;)Lorg/apache/dubbo/rpc/model/ApplicationModel;
      10: ldc           #24                 // class org/apache/dubbo/rpc/cluster/interceptor/ClusterInterceptor
      12: invokevirtual #19                 // Method org/apache/dubbo/rpc/model/ApplicationModel.getExtensionLoader:(Ljava/lang/Class;)Lorg/apache/dubbo/common/extension/ExtensionLoader;
      15: invokevirtual #20                 // Method org/apache/dubbo/common/extension/ExtensionLoader.getActivateExtensions:()Ljava/util/List;
      18: astore_3
      19: aload_3
      20: invokeinterface #25,  1           // InterfaceMethod java/util/List.isEmpty:()Z
      25: ifne          78
      28: aload_3
      29: invokeinterface #26,  1           // InterfaceMethod java/util/List.size:()I
      34: iconst_1
      35: isub
      36: istore        4
      38: iload         4
      40: iflt          78
      43: aload_3
      44: iload         4
      46: invokeinterface #27,  2           // InterfaceMethod java/util/List.get:(I)Ljava/lang/Object;
      51: checkcast     #24                 // class org/apache/dubbo/rpc/cluster/interceptor/ClusterInterceptor
      54: astore        5
      56: aload_2
      57: astore        6
      59: new           #28                 // class org/apache/dubbo/rpc/cluster/support/wrapper/AbstractCluster$InterceptorInvokerNode
      62: dup
      63: aload_1
      64: aload         5
      66: aload         6
      68: invokespecial #29                 // Method org/apache/dubbo/rpc/cluster/support/wrapper/AbstractCluster$InterceptorInvokerNode."<init>":(Lorg/apache/dubbo/rpc/cluster/support/AbstractClusterInvoker;Lorg/apache/dubbo/rpc/cluster/interceptor/ClusterInterceptor;Lorg/apache/dubbo/rpc/cluster/support/AbstractClusterInvoker;)V
      71: astore_2
      72: iinc          4, -1
      75: goto          38
      78: aload_2
      79: areturn
}
