Compiled from "AbstractCluster.java"
class org.apache.dubbo.rpc.cluster.support.wrapper.AbstractCluster$InterceptorInvokerNode<T> extends org.apache.dubbo.rpc.cluster.support.AbstractClusterInvoker<T> {
  private final org.apache.dubbo.rpc.cluster.support.AbstractClusterInvoker<T> clusterInvoker;

  private final org.apache.dubbo.rpc.cluster.interceptor.ClusterInterceptor interceptor;

  private final org.apache.dubbo.rpc.cluster.support.AbstractClusterInvoker<T> next;

  public org.apache.dubbo.rpc.cluster.support.wrapper.AbstractCluster$InterceptorInvokerNode(org.apache.dubbo.rpc.cluster.support.AbstractClusterInvoker<T>, org.apache.dubbo.rpc.cluster.interceptor.ClusterInterceptor, org.apache.dubbo.rpc.cluster.support.AbstractClusterInvoker<T>);
    Code:
       0: aload_0
       1: invokespecial #1                  // Method org/apache/dubbo/rpc/cluster/support/AbstractClusterInvoker."<init>":()V
       4: aload_0
       5: aload_1
       6: putfield      #2                  // Field clusterInvoker:Lorg/apache/dubbo/rpc/cluster/support/AbstractClusterInvoker;
       9: aload_0
      10: aload_2
      11: putfield      #3                  // Field interceptor:Lorg/apache/dubbo/rpc/cluster/interceptor/ClusterInterceptor;
      14: aload_0
      15: aload_3
      16: putfield      #4                  // Field next:Lorg/apache/dubbo/rpc/cluster/support/AbstractClusterInvoker;
      19: return

  public java.lang.Class<T> getInterface();
    Code:
       0: aload_0
       1: getfield      #2                  // Field clusterInvoker:Lorg/apache/dubbo/rpc/cluster/support/AbstractClusterInvoker;
       4: invokevirtual #5                  // Method org/apache/dubbo/rpc/cluster/support/AbstractClusterInvoker.getInterface:()Ljava/lang/Class;
       7: areturn

  public org.apache.dubbo.common.URL getUrl();
    Code:
       0: aload_0
       1: getfield      #2                  // Field clusterInvoker:Lorg/apache/dubbo/rpc/cluster/support/AbstractClusterInvoker;
       4: invokevirtual #6                  // Method org/apache/dubbo/rpc/cluster/support/AbstractClusterInvoker.getUrl:()Lorg/apache/dubbo/common/URL;
       7: areturn

  public boolean isAvailable();
    Code:
       0: aload_0
       1: getfield      #2                  // Field clusterInvoker:Lorg/apache/dubbo/rpc/cluster/support/AbstractClusterInvoker;
       4: invokevirtual #7                  // Method org/apache/dubbo/rpc/cluster/support/AbstractClusterInvoker.isAvailable:()Z
       7: ireturn

  public org.apache.dubbo.rpc.Result invoke(org.apache.dubbo.rpc.Invocation) throws org.apache.dubbo.rpc.RpcException;
    Code:
       0: aload_0
       1: getfield      #3                  // Field interceptor:Lorg/apache/dubbo/rpc/cluster/interceptor/ClusterInterceptor;
       4: aload_0
       5: getfield      #4                  // Field next:Lorg/apache/dubbo/rpc/cluster/support/AbstractClusterInvoker;
       8: aload_1
       9: invokeinterface #8,  3            // InterfaceMethod org/apache/dubbo/rpc/cluster/interceptor/ClusterInterceptor.before:(Lorg/apache/dubbo/rpc/cluster/support/AbstractClusterInvoker;Lorg/apache/dubbo/rpc/Invocation;)V
      14: aload_0
      15: getfield      #3                  // Field interceptor:Lorg/apache/dubbo/rpc/cluster/interceptor/ClusterInterceptor;
      18: aload_0
      19: getfield      #4                  // Field next:Lorg/apache/dubbo/rpc/cluster/support/AbstractClusterInvoker;
      22: aload_1
      23: invokeinterface #9,  3            // InterfaceMethod org/apache/dubbo/rpc/cluster/interceptor/ClusterInterceptor.intercept:(Lorg/apache/dubbo/rpc/cluster/support/AbstractClusterInvoker;Lorg/apache/dubbo/rpc/Invocation;)Lorg/apache/dubbo/rpc/Result;
      28: astore_2
      29: aload_0
      30: getfield      #3                  // Field interceptor:Lorg/apache/dubbo/rpc/cluster/interceptor/ClusterInterceptor;
      33: aload_0
      34: getfield      #4                  // Field next:Lorg/apache/dubbo/rpc/cluster/support/AbstractClusterInvoker;
      37: aload_1
      38: invokeinterface #10,  3           // InterfaceMethod org/apache/dubbo/rpc/cluster/interceptor/ClusterInterceptor.after:(Lorg/apache/dubbo/rpc/cluster/support/AbstractClusterInvoker;Lorg/apache/dubbo/rpc/Invocation;)V
      43: goto          100
      46: astore_3
      47: aload_0
      48: getfield      #3                  // Field interceptor:Lorg/apache/dubbo/rpc/cluster/interceptor/ClusterInterceptor;
      51: instanceof    #12                 // class org/apache/dubbo/rpc/cluster/interceptor/ClusterInterceptor$Listener
      54: ifeq          79
      57: aload_0
      58: getfield      #3                  // Field interceptor:Lorg/apache/dubbo/rpc/cluster/interceptor/ClusterInterceptor;
      61: checkcast     #12                 // class org/apache/dubbo/rpc/cluster/interceptor/ClusterInterceptor$Listener
      64: astore        4
      66: aload         4
      68: aload_3
      69: aload_0
      70: getfield      #2                  // Field clusterInvoker:Lorg/apache/dubbo/rpc/cluster/support/AbstractClusterInvoker;
      73: aload_1
      74: invokeinterface #13,  4           // InterfaceMethod org/apache/dubbo/rpc/cluster/interceptor/ClusterInterceptor$Listener.onError:(Ljava/lang/Throwable;Lorg/apache/dubbo/rpc/cluster/support/AbstractClusterInvoker;Lorg/apache/dubbo/rpc/Invocation;)V
      79: aload_3
      80: athrow
      81: astore        5
      83: aload_0
      84: getfield      #3                  // Field interceptor:Lorg/apache/dubbo/rpc/cluster/interceptor/ClusterInterceptor;
      87: aload_0
      88: getfield      #4                  // Field next:Lorg/apache/dubbo/rpc/cluster/support/AbstractClusterInvoker;
      91: aload_1
      92: invokeinterface #10,  3           // InterfaceMethod org/apache/dubbo/rpc/cluster/interceptor/ClusterInterceptor.after:(Lorg/apache/dubbo/rpc/cluster/support/AbstractClusterInvoker;Lorg/apache/dubbo/rpc/Invocation;)V
      97: aload         5
      99: athrow
     100: aload_2
     101: aload_0
     102: aload_1
     103: invokedynamic #14,  0             // InvokeDynamic #0:accept:(Lorg/apache/dubbo/rpc/cluster/support/wrapper/AbstractCluster$InterceptorInvokerNode;Lorg/apache/dubbo/rpc/Invocation;)Ljava/util/function/BiConsumer;
     108: invokeinterface #15,  2           // InterfaceMethod org/apache/dubbo/rpc/Result.whenCompleteWithContext:(Ljava/util/function/BiConsumer;)Lorg/apache/dubbo/rpc/Result;
     113: areturn
    Exception table:
       from    to  target type
           0    29    46   Class java/lang/Exception
           0    29    81   any
          46    83    81   any

  public void destroy();
    Code:
       0: aload_0
       1: getfield      #2                  // Field clusterInvoker:Lorg/apache/dubbo/rpc/cluster/support/AbstractClusterInvoker;
       4: invokevirtual #16                 // Method org/apache/dubbo/rpc/cluster/support/AbstractClusterInvoker.destroy:()V
       7: return

  public java.lang.String toString();
    Code:
       0: aload_0
       1: getfield      #2                  // Field clusterInvoker:Lorg/apache/dubbo/rpc/cluster/support/AbstractClusterInvoker;
       4: invokevirtual #17                 // Method org/apache/dubbo/rpc/cluster/support/AbstractClusterInvoker.toString:()Ljava/lang/String;
       7: areturn

  protected org.apache.dubbo.rpc.Result doInvoke(org.apache.dubbo.rpc.Invocation, java.util.List<org.apache.dubbo.rpc.Invoker<T>>, org.apache.dubbo.rpc.cluster.LoadBalance) throws org.apache.dubbo.rpc.RpcException;
    Code:
       0: aconst_null
       1: areturn

  private void lambda$invoke$0(org.apache.dubbo.rpc.Invocation, org.apache.dubbo.rpc.Result, java.lang.Throwable);
    Code:
       0: aload_0
       1: getfield      #3                  // Field interceptor:Lorg/apache/dubbo/rpc/cluster/interceptor/ClusterInterceptor;
       4: instanceof    #12                 // class org/apache/dubbo/rpc/cluster/interceptor/ClusterInterceptor$Listener
       7: ifeq          52
      10: aload_0
      11: getfield      #3                  // Field interceptor:Lorg/apache/dubbo/rpc/cluster/interceptor/ClusterInterceptor;
      14: checkcast     #12                 // class org/apache/dubbo/rpc/cluster/interceptor/ClusterInterceptor$Listener
      17: astore        4
      19: aload_3
      20: ifnonnull     39
      23: aload         4
      25: aload_2
      26: aload_0
      27: getfield      #2                  // Field clusterInvoker:Lorg/apache/dubbo/rpc/cluster/support/AbstractClusterInvoker;
      30: aload_1
      31: invokeinterface #18,  4           // InterfaceMethod org/apache/dubbo/rpc/cluster/interceptor/ClusterInterceptor$Listener.onMessage:(Lorg/apache/dubbo/rpc/Result;Lorg/apache/dubbo/rpc/cluster/support/AbstractClusterInvoker;Lorg/apache/dubbo/rpc/Invocation;)V
      36: goto          52
      39: aload         4
      41: aload_3
      42: aload_0
      43: getfield      #2                  // Field clusterInvoker:Lorg/apache/dubbo/rpc/cluster/support/AbstractClusterInvoker;
      46: aload_1
      47: invokeinterface #13,  4           // InterfaceMethod org/apache/dubbo/rpc/cluster/interceptor/ClusterInterceptor$Listener.onError:(Ljava/lang/Throwable;Lorg/apache/dubbo/rpc/cluster/support/AbstractClusterInvoker;Lorg/apache/dubbo/rpc/Invocation;)V
      52: return
}
