Compiled from "MockClusterInvoker.java"
public class org.apache.dubbo.rpc.cluster.support.wrapper.MockClusterInvoker<T> implements org.apache.dubbo.rpc.cluster.ClusterInvoker<T> {
  private static final org.apache.dubbo.common.logger.ErrorTypeAwareLogger logger;

  private static final boolean setFutureWhenSync;

  private final org.apache.dubbo.rpc.cluster.Directory<T> directory;

  private final org.apache.dubbo.rpc.Invoker<T> invoker;

  public org.apache.dubbo.rpc.cluster.support.wrapper.MockClusterInvoker(org.apache.dubbo.rpc.cluster.Directory<T>, org.apache.dubbo.rpc.Invoker<T>);
    Code:
       0: aload_0
       1: invokespecial #4                  // Method java/lang/Object."<init>":()V
       4: aload_0
       5: aload_1
       6: putfield      #5                  // Field directory:Lorg/apache/dubbo/rpc/cluster/Directory;
       9: aload_0
      10: aload_2
      11: putfield      #6                  // Field invoker:Lorg/apache/dubbo/rpc/Invoker;
      14: return

  public org.apache.dubbo.common.URL getUrl();
    Code:
       0: aload_0
       1: getfield      #5                  // Field directory:Lorg/apache/dubbo/rpc/cluster/Directory;
       4: invokeinterface #7,  1            // InterfaceMethod org/apache/dubbo/rpc/cluster/Directory.getConsumerUrl:()Lorg/apache/dubbo/common/URL;
       9: areturn

  public org.apache.dubbo.common.URL getRegistryUrl();
    Code:
       0: aload_0
       1: getfield      #5                  // Field directory:Lorg/apache/dubbo/rpc/cluster/Directory;
       4: invokeinterface #8,  1            // InterfaceMethod org/apache/dubbo/rpc/cluster/Directory.getUrl:()Lorg/apache/dubbo/common/URL;
       9: areturn

  public org.apache.dubbo.rpc.cluster.Directory<T> getDirectory();
    Code:
       0: aload_0
       1: getfield      #5                  // Field directory:Lorg/apache/dubbo/rpc/cluster/Directory;
       4: areturn

  public boolean isDestroyed();
    Code:
       0: aload_0
       1: getfield      #5                  // Field directory:Lorg/apache/dubbo/rpc/cluster/Directory;
       4: invokeinterface #9,  1            // InterfaceMethod org/apache/dubbo/rpc/cluster/Directory.isDestroyed:()Z
       9: ireturn

  public boolean isAvailable();
    Code:
       0: aload_0
       1: getfield      #5                  // Field directory:Lorg/apache/dubbo/rpc/cluster/Directory;
       4: invokeinterface #10,  1           // InterfaceMethod org/apache/dubbo/rpc/cluster/Directory.isAvailable:()Z
       9: ireturn

  public void destroy();
    Code:
       0: aload_0
       1: getfield      #6                  // Field invoker:Lorg/apache/dubbo/rpc/Invoker;
       4: invokeinterface #11,  1           // InterfaceMethod org/apache/dubbo/rpc/Invoker.destroy:()V
       9: return

  public java.lang.Class<T> getInterface();
    Code:
       0: aload_0
       1: getfield      #5                  // Field directory:Lorg/apache/dubbo/rpc/cluster/Directory;
       4: invokeinterface #12,  1           // InterfaceMethod org/apache/dubbo/rpc/cluster/Directory.getInterface:()Ljava/lang/Class;
       9: areturn

  public org.apache.dubbo.rpc.Result invoke(org.apache.dubbo.rpc.Invocation) throws org.apache.dubbo.rpc.RpcException;
    Code:
       0: aload_0
       1: invokevirtual #13                 // Method getUrl:()Lorg/apache/dubbo/common/URL;
       4: aload_1
       5: invokeinterface #14,  1           // InterfaceMethod org/apache/dubbo/rpc/Invocation.getMethodName:()Ljava/lang/String;
      10: ldc           #15                 // String mock
      12: getstatic     #16                 // Field java/lang/Boolean.FALSE:Ljava/lang/Boolean;
      15: invokevirtual #17                 // Method java/lang/Boolean.toString:()Ljava/lang/String;
      18: invokevirtual #18                 // Method org/apache/dubbo/common/URL.getMethodParameter:(Ljava/lang/String;Ljava/lang/String;Ljava/lang/String;)Ljava/lang/String;
      21: invokevirtual #19                 // Method java/lang/String.trim:()Ljava/lang/String;
      24: astore_3
      25: aload_3
      26: invokestatic  #20                 // Method org/apache/dubbo/common/utils/ConfigUtils.isEmpty:(Ljava/lang/String;)Z
      29: ifeq          46
      32: aload_0
      33: getfield      #6                  // Field invoker:Lorg/apache/dubbo/rpc/Invoker;
      36: aload_1
      37: invokeinterface #21,  2           // InterfaceMethod org/apache/dubbo/rpc/Invoker.invoke:(Lorg/apache/dubbo/rpc/Invocation;)Lorg/apache/dubbo/rpc/Result;
      42: astore_2
      43: goto          275
      46: aload_3
      47: ldc           #22                 // String force
      49: invokevirtual #23                 // Method java/lang/String.startsWith:(Ljava/lang/String;)Z
      52: ifeq          126
      55: getstatic     #24                 // Field logger:Lorg/apache/dubbo/common/logger/ErrorTypeAwareLogger;
      58: invokeinterface #25,  1           // InterfaceMethod org/apache/dubbo/common/logger/ErrorTypeAwareLogger.isWarnEnabled:()Z
      63: ifeq          116
      66: getstatic     #24                 // Field logger:Lorg/apache/dubbo/common/logger/ErrorTypeAwareLogger;
      69: ldc           #26                 // String 2-17
      71: ldc           #27                 // String force mock
      73: ldc           #28                 // String
      75: new           #29                 // class java/lang/StringBuilder
      78: dup
      79: invokespecial #30                 // Method java/lang/StringBuilder."<init>":()V
      82: ldc           #31                 // String force-mock:
      84: invokevirtual #32                 // Method java/lang/StringBuilder.append:(Ljava/lang/String;)Ljava/lang/StringBuilder;
      87: aload_1
      88: invokeinterface #14,  1           // InterfaceMethod org/apache/dubbo/rpc/Invocation.getMethodName:()Ljava/lang/String;
      93: invokevirtual #32                 // Method java/lang/StringBuilder.append:(Ljava/lang/String;)Ljava/lang/StringBuilder;
      96: ldc           #33                 // String  force-mock enabled , url :
      98: invokevirtual #32                 // Method java/lang/StringBuilder.append:(Ljava/lang/String;)Ljava/lang/StringBuilder;
     101: aload_0
     102: invokevirtual #13                 // Method getUrl:()Lorg/apache/dubbo/common/URL;
     105: invokevirtual #34                 // Method java/lang/StringBuilder.append:(Ljava/lang/Object;)Ljava/lang/StringBuilder;
     108: invokevirtual #35                 // Method java/lang/StringBuilder.toString:()Ljava/lang/String;
     111: invokeinterface #36,  5           // InterfaceMethod org/apache/dubbo/common/logger/ErrorTypeAwareLogger.warn:(Ljava/lang/String;Ljava/lang/String;Ljava/lang/String;Ljava/lang/String;)V
     116: aload_0
     117: aload_1
     118: aconst_null
     119: invokespecial #37                 // Method doMockInvoke:(Lorg/apache/dubbo/rpc/Invocation;Lorg/apache/dubbo/rpc/RpcException;)Lorg/apache/dubbo/rpc/Result;
     122: astore_2
     123: goto          275
     126: aload_0
     127: getfield      #6                  // Field invoker:Lorg/apache/dubbo/rpc/Invoker;
     130: aload_1
     131: invokeinterface #21,  2           // InterfaceMethod org/apache/dubbo/rpc/Invoker.invoke:(Lorg/apache/dubbo/rpc/Invocation;)Lorg/apache/dubbo/rpc/Result;
     136: astore_2
     137: aload_2
     138: invokeinterface #38,  1           // InterfaceMethod org/apache/dubbo/rpc/Result.getException:()Ljava/lang/Throwable;
     143: ifnull        188
     146: aload_2
     147: invokeinterface #38,  1           // InterfaceMethod org/apache/dubbo/rpc/Result.getException:()Ljava/lang/Throwable;
     152: instanceof    #39                 // class org/apache/dubbo/rpc/RpcException
     155: ifeq          188
     158: aload_2
     159: invokeinterface #38,  1           // InterfaceMethod org/apache/dubbo/rpc/Result.getException:()Ljava/lang/Throwable;
     164: checkcast     #39                 // class org/apache/dubbo/rpc/RpcException
     167: astore        4
     169: aload         4
     171: invokevirtual #40                 // Method org/apache/dubbo/rpc/RpcException.isBiz:()Z
     174: ifeq          180
     177: aload         4
     179: athrow
     180: aload_0
     181: aload_1
     182: aload         4
     184: invokespecial #37                 // Method doMockInvoke:(Lorg/apache/dubbo/rpc/Invocation;Lorg/apache/dubbo/rpc/RpcException;)Lorg/apache/dubbo/rpc/Result;
     187: astore_2
     188: goto          275
     191: astore        4
     193: aload         4
     195: invokevirtual #40                 // Method org/apache/dubbo/rpc/RpcException.isBiz:()Z
     198: ifeq          204
     201: aload         4
     203: athrow
     204: getstatic     #24                 // Field logger:Lorg/apache/dubbo/common/logger/ErrorTypeAwareLogger;
     207: invokeinterface #25,  1           // InterfaceMethod org/apache/dubbo/common/logger/ErrorTypeAwareLogger.isWarnEnabled:()Z
     212: ifeq          267
     215: getstatic     #24                 // Field logger:Lorg/apache/dubbo/common/logger/ErrorTypeAwareLogger;
     218: ldc           #26                 // String 2-17
     220: ldc           #41                 // String failed to mock invoke
     222: ldc           #28                 // String
     224: new           #29                 // class java/lang/StringBuilder
     227: dup
     228: invokespecial #30                 // Method java/lang/StringBuilder."<init>":()V
     231: ldc           #42                 // String fail-mock:
     233: invokevirtual #32                 // Method java/lang/StringBuilder.append:(Ljava/lang/String;)Ljava/lang/StringBuilder;
     236: aload_1
     237: invokeinterface #14,  1           // InterfaceMethod org/apache/dubbo/rpc/Invocation.getMethodName:()Ljava/lang/String;
     242: invokevirtual #32                 // Method java/lang/StringBuilder.append:(Ljava/lang/String;)Ljava/lang/StringBuilder;
     245: ldc           #43                 // String  fail-mock enabled , url :
     247: invokevirtual #32                 // Method java/lang/StringBuilder.append:(Ljava/lang/String;)Ljava/lang/StringBuilder;
     250: aload_0
     251: invokevirtual #13                 // Method getUrl:()Lorg/apache/dubbo/common/URL;
     254: invokevirtual #34                 // Method java/lang/StringBuilder.append:(Ljava/lang/Object;)Ljava/lang/StringBuilder;
     257: invokevirtual #35                 // Method java/lang/StringBuilder.toString:()Ljava/lang/String;
     260: aload         4
     262: invokeinterface #44,  6           // InterfaceMethod org/apache/dubbo/common/logger/ErrorTypeAwareLogger.warn:(Ljava/lang/String;Ljava/lang/String;Ljava/lang/String;Ljava/lang/String;Ljava/lang/Throwable;)V
     267: aload_0
     268: aload_1
     269: aload         4
     271: invokespecial #37                 // Method doMockInvoke:(Lorg/apache/dubbo/rpc/Invocation;Lorg/apache/dubbo/rpc/RpcException;)Lorg/apache/dubbo/rpc/Result;
     274: astore_2
     275: aload_2
     276: areturn
    Exception table:
       from    to  target type
         126   188   191   Class org/apache/dubbo/rpc/RpcException

  private org.apache.dubbo.rpc.Result doMockInvoke(org.apache.dubbo.rpc.Invocation, org.apache.dubbo.rpc.RpcException);
    Code:
       0: aload_1
       1: checkcast     #45                 // class org/apache/dubbo/rpc/RpcInvocation
       4: astore        5
       6: aload         5
       8: aload_0
       9: invokevirtual #13                 // Method getUrl:()Lorg/apache/dubbo/common/URL;
      12: aload_1
      13: invokestatic  #46                 // Method org/apache/dubbo/rpc/support/RpcUtils.getInvokeMode:(Lorg/apache/dubbo/common/URL;Lorg/apache/dubbo/rpc/Invocation;)Lorg/apache/dubbo/rpc/InvokeMode;
      16: invokevirtual #47                 // Method org/apache/dubbo/rpc/RpcInvocation.setInvokeMode:(Lorg/apache/dubbo/rpc/InvokeMode;)V
      19: aload_0
      20: aload_1
      21: invokespecial #48                 // Method selectMockInvoker:(Lorg/apache/dubbo/rpc/Invocation;)Ljava/util/List;
      24: astore        6
      26: aload         6
      28: invokestatic  #49                 // Method org/apache/dubbo/common/utils/CollectionUtils.isEmpty:(Ljava/util/Collection;)Z
      31: ifeq          59
      34: new           #50                 // class org/apache/dubbo/rpc/support/MockInvoker
      37: dup
      38: aload_0
      39: invokevirtual #13                 // Method getUrl:()Lorg/apache/dubbo/common/URL;
      42: aload_0
      43: getfield      #5                  // Field directory:Lorg/apache/dubbo/rpc/cluster/Directory;
      46: invokeinterface #12,  1           // InterfaceMethod org/apache/dubbo/rpc/cluster/Directory.getInterface:()Ljava/lang/Class;
      51: invokespecial #51                 // Method org/apache/dubbo/rpc/support/MockInvoker."<init>":(Lorg/apache/dubbo/common/URL;Ljava/lang/Class;)V
      54: astore        4
      56: goto          72
      59: aload         6
      61: iconst_0
      62: invokeinterface #52,  2           // InterfaceMethod java/util/List.get:(I)Ljava/lang/Object;
      67: checkcast     #53                 // class org/apache/dubbo/rpc/Invoker
      70: astore        4
      72: aload         4
      74: aload_1
      75: invokeinterface #21,  2           // InterfaceMethod org/apache/dubbo/rpc/Invoker.invoke:(Lorg/apache/dubbo/rpc/Invocation;)Lorg/apache/dubbo/rpc/Result;
      80: astore_3
      81: goto          157
      84: astore        7
      86: aload         7
      88: invokevirtual #40                 // Method org/apache/dubbo/rpc/RpcException.isBiz:()Z
      91: ifeq          107
      94: aload         7
      96: invokevirtual #54                 // Method org/apache/dubbo/rpc/RpcException.getCause:()Ljava/lang/Throwable;
      99: aload_1
     100: invokestatic  #55                 // Method org/apache/dubbo/rpc/AsyncRpcResult.newDefaultAsyncResult:(Ljava/lang/Throwable;Lorg/apache/dubbo/rpc/Invocation;)Lorg/apache/dubbo/rpc/AsyncRpcResult;
     103: astore_3
     104: goto          132
     107: new           #39                 // class org/apache/dubbo/rpc/RpcException
     110: dup
     111: aload         7
     113: invokevirtual #56                 // Method org/apache/dubbo/rpc/RpcException.getCode:()I
     116: aload_0
     117: aload_2
     118: aload         7
     120: invokespecial #57                 // Method getMockExceptionMessage:(Ljava/lang/Throwable;Ljava/lang/Throwable;)Ljava/lang/String;
     123: aload         7
     125: invokevirtual #54                 // Method org/apache/dubbo/rpc/RpcException.getCause:()Ljava/lang/Throwable;
     128: invokespecial #58                 // Method org/apache/dubbo/rpc/RpcException."<init>":(ILjava/lang/String;Ljava/lang/Throwable;)V
     131: athrow
     132: goto          157
     135: astore        7
     137: new           #39                 // class org/apache/dubbo/rpc/RpcException
     140: dup
     141: aload_0
     142: aload_2
     143: aload         7
     145: invokespecial #57                 // Method getMockExceptionMessage:(Ljava/lang/Throwable;Ljava/lang/Throwable;)Ljava/lang/String;
     148: aload         7
     150: invokevirtual #60                 // Method java/lang/Throwable.getCause:()Ljava/lang/Throwable;
     153: invokespecial #61                 // Method org/apache/dubbo/rpc/RpcException."<init>":(Ljava/lang/String;Ljava/lang/Throwable;)V
     156: athrow
     157: getstatic     #62                 // Field setFutureWhenSync:Z
     160: ifne          174
     163: aload         5
     165: invokevirtual #63                 // Method org/apache/dubbo/rpc/RpcInvocation.getInvokeMode:()Lorg/apache/dubbo/rpc/InvokeMode;
     168: getstatic     #64                 // Field org/apache/dubbo/rpc/InvokeMode.SYNC:Lorg/apache/dubbo/rpc/InvokeMode;
     171: if_acmpeq     194
     174: invokestatic  #65                 // Method org/apache/dubbo/rpc/RpcContext.getServiceContext:()Lorg/apache/dubbo/rpc/RpcServiceContext;
     177: new           #66                 // class org/apache/dubbo/rpc/protocol/dubbo/FutureAdapter
     180: dup
     181: aload_3
     182: checkcast     #67                 // class org/apache/dubbo/rpc/AsyncRpcResult
     185: invokevirtual #68                 // Method org/apache/dubbo/rpc/AsyncRpcResult.getResponseFuture:()Ljava/util/concurrent/CompletableFuture;
     188: invokespecial #69                 // Method org/apache/dubbo/rpc/protocol/dubbo/FutureAdapter."<init>":(Ljava/util/concurrent/CompletableFuture;)V
     191: invokevirtual #70                 // Method org/apache/dubbo/rpc/RpcServiceContext.setFuture:(Ljava/util/concurrent/CompletableFuture;)V
     194: aload_3
     195: areturn
    Exception table:
       from    to  target type
          72    81    84   Class org/apache/dubbo/rpc/RpcException
          72    81   135   Class java/lang/Throwable

  private java.lang.String getMockExceptionMessage(java.lang.Throwable, java.lang.Throwable);
    Code:
       0: new           #29                 // class java/lang/StringBuilder
       3: dup
       4: invokespecial #30                 // Method java/lang/StringBuilder."<init>":()V
       7: ldc           #71                 // String mock error :
       9: invokevirtual #32                 // Method java/lang/StringBuilder.append:(Ljava/lang/String;)Ljava/lang/StringBuilder;
      12: aload_2
      13: invokevirtual #72                 // Method java/lang/Throwable.getMessage:()Ljava/lang/String;
      16: invokevirtual #32                 // Method java/lang/StringBuilder.append:(Ljava/lang/String;)Ljava/lang/StringBuilder;
      19: invokevirtual #35                 // Method java/lang/StringBuilder.toString:()Ljava/lang/String;
      22: astore_3
      23: aload_1
      24: ifnull        54
      27: new           #29                 // class java/lang/StringBuilder
      30: dup
      31: invokespecial #30                 // Method java/lang/StringBuilder."<init>":()V
      34: aload_3
      35: invokevirtual #32                 // Method java/lang/StringBuilder.append:(Ljava/lang/String;)Ljava/lang/StringBuilder;
      38: ldc           #73                 // String , invoke error is :
      40: invokevirtual #32                 // Method java/lang/StringBuilder.append:(Ljava/lang/String;)Ljava/lang/StringBuilder;
      43: aload_1
      44: invokestatic  #74                 // Method org/apache/dubbo/common/utils/StringUtils.toString:(Ljava/lang/Throwable;)Ljava/lang/String;
      47: invokevirtual #32                 // Method java/lang/StringBuilder.append:(Ljava/lang/String;)Ljava/lang/StringBuilder;
      50: invokevirtual #35                 // Method java/lang/StringBuilder.toString:()Ljava/lang/String;
      53: astore_3
      54: aload_3
      55: areturn

  private java.util.List<org.apache.dubbo.rpc.Invoker<T>> selectMockInvoker(org.apache.dubbo.rpc.Invocation);
    Code:
       0: aconst_null
       1: astore_2
       2: aload_1
       3: instanceof    #45                 // class org/apache/dubbo/rpc/RpcInvocation
       6: ifeq          112
       9: aload_1
      10: ldc           #75                 // String invocation.need.mock
      12: getstatic     #76                 // Field java/lang/Boolean.TRUE:Ljava/lang/Boolean;
      15: invokevirtual #17                 // Method java/lang/Boolean.toString:()Ljava/lang/String;
      18: invokeinterface #77,  3           // InterfaceMethod org/apache/dubbo/rpc/Invocation.setAttachment:(Ljava/lang/String;Ljava/lang/String;)V
      23: invokestatic  #65                 // Method org/apache/dubbo/rpc/RpcContext.getServiceContext:()Lorg/apache/dubbo/rpc/RpcServiceContext;
      26: aload_0
      27: invokevirtual #13                 // Method getUrl:()Lorg/apache/dubbo/common/URL;
      30: invokevirtual #78                 // Method org/apache/dubbo/rpc/RpcServiceContext.setConsumerUrl:(Lorg/apache/dubbo/common/URL;)V
      33: aload_0
      34: getfield      #5                  // Field directory:Lorg/apache/dubbo/rpc/cluster/Directory;
      37: aload_1
      38: invokeinterface #79,  2           // InterfaceMethod org/apache/dubbo/rpc/cluster/Directory.list:(Lorg/apache/dubbo/rpc/Invocation;)Ljava/util/List;
      43: astore_2
      44: goto          112
      47: astore_3
      48: getstatic     #24                 // Field logger:Lorg/apache/dubbo/common/logger/ErrorTypeAwareLogger;
      51: invokeinterface #80,  1           // InterfaceMethod org/apache/dubbo/common/logger/ErrorTypeAwareLogger.isInfoEnabled:()Z
      56: ifeq          112
      59: getstatic     #24                 // Field logger:Lorg/apache/dubbo/common/logger/ErrorTypeAwareLogger;
      62: new           #29                 // class java/lang/StringBuilder
      65: dup
      66: invokespecial #30                 // Method java/lang/StringBuilder."<init>":()V
      69: ldc           #81                 // String Exception when try to invoke mock. Get mock invokers error for service:
      71: invokevirtual #32                 // Method java/lang/StringBuilder.append:(Ljava/lang/String;)Ljava/lang/StringBuilder;
      74: aload_0
      75: invokevirtual #13                 // Method getUrl:()Lorg/apache/dubbo/common/URL;
      78: invokevirtual #82                 // Method org/apache/dubbo/common/URL.getServiceInterface:()Ljava/lang/String;
      81: invokevirtual #32                 // Method java/lang/StringBuilder.append:(Ljava/lang/String;)Ljava/lang/StringBuilder;
      84: ldc           #83                 // String , method:
      86: invokevirtual #32                 // Method java/lang/StringBuilder.append:(Ljava/lang/String;)Ljava/lang/StringBuilder;
      89: aload_1
      90: invokeinterface #14,  1           // InterfaceMethod org/apache/dubbo/rpc/Invocation.getMethodName:()Ljava/lang/String;
      95: invokevirtual #32                 // Method java/lang/StringBuilder.append:(Ljava/lang/String;)Ljava/lang/StringBuilder;
      98: ldc           #84                 // String , will construct a new mock with \'new MockInvoker()\'.
     100: invokevirtual #32                 // Method java/lang/StringBuilder.append:(Ljava/lang/String;)Ljava/lang/StringBuilder;
     103: invokevirtual #35                 // Method java/lang/StringBuilder.toString:()Ljava/lang/String;
     106: aload_3
     107: invokeinterface #85,  3           // InterfaceMethod org/apache/dubbo/common/logger/ErrorTypeAwareLogger.info:(Ljava/lang/String;Ljava/lang/Throwable;)V
     112: aload_2
     113: areturn
    Exception table:
       from    to  target type
          23    44    47   Class org/apache/dubbo/rpc/RpcException

  public java.lang.String toString();
    Code:
       0: new           #29                 // class java/lang/StringBuilder
       3: dup
       4: invokespecial #30                 // Method java/lang/StringBuilder."<init>":()V
       7: ldc           #86                 // String invoker :
       9: invokevirtual #32                 // Method java/lang/StringBuilder.append:(Ljava/lang/String;)Ljava/lang/StringBuilder;
      12: aload_0
      13: getfield      #6                  // Field invoker:Lorg/apache/dubbo/rpc/Invoker;
      16: invokevirtual #34                 // Method java/lang/StringBuilder.append:(Ljava/lang/Object;)Ljava/lang/StringBuilder;
      19: ldc           #87                 // String ,directory:
      21: invokevirtual #32                 // Method java/lang/StringBuilder.append:(Ljava/lang/String;)Ljava/lang/StringBuilder;
      24: aload_0
      25: getfield      #5                  // Field directory:Lorg/apache/dubbo/rpc/cluster/Directory;
      28: invokevirtual #34                 // Method java/lang/StringBuilder.append:(Ljava/lang/Object;)Ljava/lang/StringBuilder;
      31: invokevirtual #35                 // Method java/lang/StringBuilder.toString:()Ljava/lang/String;
      34: areturn

  static {};
    Code:
       0: ldc           #88                 // class org/apache/dubbo/rpc/cluster/support/wrapper/MockClusterInvoker
       2: invokestatic  #89                 // Method org/apache/dubbo/common/logger/LoggerFactory.getErrorTypeAwareLogger:(Ljava/lang/Class;)Lorg/apache/dubbo/common/logger/ErrorTypeAwareLogger;
       5: putstatic     #24                 // Field logger:Lorg/apache/dubbo/common/logger/ErrorTypeAwareLogger;
       8: ldc           #91                 // String future.sync.set
      10: ldc           #92                 // String true
      12: invokestatic  #93                 // Method java/lang/System.getProperty:(Ljava/lang/String;Ljava/lang/String;)Ljava/lang/String;
      15: invokestatic  #94                 // Method java/lang/Boolean.parseBoolean:(Ljava/lang/String;)Z
      18: putstatic     #62                 // Field setFutureWhenSync:Z
      21: return
}
