Compiled from "ScopeClusterInvoker.java"
public class org.apache.dubbo.rpc.cluster.support.wrapper.ScopeClusterInvoker<T> implements org.apache.dubbo.rpc.cluster.ClusterInvoker<T>, org.apache.dubbo.rpc.listener.ExporterChangeListener {
  private static final org.apache.dubbo.common.logger.ErrorTypeAwareLogger logger;

  private final java.lang.Object createLock;

  private org.apache.dubbo.rpc.Protocol protocolSPI;

  private final org.apache.dubbo.rpc.cluster.Directory<T> directory;

  private final org.apache.dubbo.rpc.Invoker<T> invoker;

  private final java.util.concurrent.atomic.AtomicBoolean isExported;

  private volatile org.apache.dubbo.rpc.Invoker<T> injvmInvoker;

  private volatile org.apache.dubbo.rpc.listener.InjvmExporterListener injvmExporterListener;

  private boolean peerFlag;

  private boolean injvmFlag;

  public org.apache.dubbo.rpc.cluster.support.wrapper.ScopeClusterInvoker(org.apache.dubbo.rpc.cluster.Directory<T>, org.apache.dubbo.rpc.Invoker<T>);
    Code:
       0: aload_0
       1: invokespecial #4                  // Method java/lang/Object."<init>":()V
       4: aload_0
       5: new           #5                  // class java/lang/Object
       8: dup
       9: invokespecial #4                  // Method java/lang/Object."<init>":()V
      12: putfield      #6                  // Field createLock:Ljava/lang/Object;
      15: aload_0
      16: aload_1
      17: putfield      #7                  // Field directory:Lorg/apache/dubbo/rpc/cluster/Directory;
      20: aload_0
      21: aload_2
      22: putfield      #8                  // Field invoker:Lorg/apache/dubbo/rpc/Invoker;
      25: aload_0
      26: new           #9                  // class java/util/concurrent/atomic/AtomicBoolean
      29: dup
      30: iconst_0
      31: invokespecial #10                 // Method java/util/concurrent/atomic/AtomicBoolean."<init>":(Z)V
      34: putfield      #11                 // Field isExported:Ljava/util/concurrent/atomic/AtomicBoolean;
      37: aload_0
      38: invokespecial #12                 // Method init:()V
      41: return

  public org.apache.dubbo.common.URL getUrl();
    Code:
       0: aload_0
       1: getfield      #7                  // Field directory:Lorg/apache/dubbo/rpc/cluster/Directory;
       4: invokeinterface #13,  1           // InterfaceMethod org/apache/dubbo/rpc/cluster/Directory.getConsumerUrl:()Lorg/apache/dubbo/common/URL;
       9: areturn

  public org.apache.dubbo.common.URL getRegistryUrl();
    Code:
       0: aload_0
       1: getfield      #7                  // Field directory:Lorg/apache/dubbo/rpc/cluster/Directory;
       4: invokeinterface #14,  1           // InterfaceMethod org/apache/dubbo/rpc/cluster/Directory.getUrl:()Lorg/apache/dubbo/common/URL;
       9: areturn

  public org.apache.dubbo.rpc.cluster.Directory<T> getDirectory();
    Code:
       0: aload_0
       1: getfield      #7                  // Field directory:Lorg/apache/dubbo/rpc/cluster/Directory;
       4: areturn

  public boolean isDestroyed();
    Code:
       0: aload_0
       1: getfield      #7                  // Field directory:Lorg/apache/dubbo/rpc/cluster/Directory;
       4: invokeinterface #15,  1           // InterfaceMethod org/apache/dubbo/rpc/cluster/Directory.isDestroyed:()Z
       9: ireturn

  public boolean isAvailable();
    Code:
       0: aload_0
       1: getfield      #11                 // Field isExported:Ljava/util/concurrent/atomic/AtomicBoolean;
       4: invokevirtual #16                 // Method java/util/concurrent/atomic/AtomicBoolean.get:()Z
       7: ifne          22
      10: aload_0
      11: getfield      #7                  // Field directory:Lorg/apache/dubbo/rpc/cluster/Directory;
      14: invokeinterface #17,  1           // InterfaceMethod org/apache/dubbo/rpc/cluster/Directory.isAvailable:()Z
      19: ifeq          26
      22: iconst_1
      23: goto          27
      26: iconst_0
      27: ireturn

  public void destroy();
    Code:
       0: aload_0
       1: getfield      #18                 // Field injvmExporterListener:Lorg/apache/dubbo/rpc/listener/InjvmExporterListener;
       4: ifnull        22
       7: aload_0
       8: getfield      #18                 // Field injvmExporterListener:Lorg/apache/dubbo/rpc/listener/InjvmExporterListener;
      11: aload_0
      12: aload_0
      13: invokevirtual #19                 // Method getUrl:()Lorg/apache/dubbo/common/URL;
      16: invokevirtual #20                 // Method org/apache/dubbo/common/URL.getServiceKey:()Ljava/lang/String;
      19: invokevirtual #21                 // Method org/apache/dubbo/rpc/listener/InjvmExporterListener.removeExporterChangeListener:(Lorg/apache/dubbo/rpc/listener/ExporterChangeListener;Ljava/lang/String;)V
      22: aload_0
      23: invokespecial #22                 // Method destroyInjvmInvoker:()V
      26: aload_0
      27: getfield      #8                  // Field invoker:Lorg/apache/dubbo/rpc/Invoker;
      30: invokeinterface #23,  1           // InterfaceMethod org/apache/dubbo/rpc/Invoker.destroy:()V
      35: return

  public java.lang.Class<T> getInterface();
    Code:
       0: aload_0
       1: getfield      #7                  // Field directory:Lorg/apache/dubbo/rpc/cluster/Directory;
       4: invokeinterface #24,  1           // InterfaceMethod org/apache/dubbo/rpc/cluster/Directory.getInterface:()Ljava/lang/Class;
       9: areturn

  public org.apache.dubbo.rpc.Result invoke(org.apache.dubbo.rpc.Invocation) throws org.apache.dubbo.rpc.RpcException;
    Code:
       0: ldc           #25                 // String broadcast
       2: aload_0
       3: invokevirtual #19                 // Method getUrl:()Lorg/apache/dubbo/common/URL;
       6: ldc           #26                 // String cluster
       8: invokevirtual #27                 // Method org/apache/dubbo/common/URL.getParameter:(Ljava/lang/String;)Ljava/lang/String;
      11: invokevirtual #28                 // Method java/lang/String.equalsIgnoreCase:(Ljava/lang/String;)Z
      14: ifeq          86
      17: getstatic     #29                 // Field logger:Lorg/apache/dubbo/common/logger/ErrorTypeAwareLogger;
      20: invokeinterface #30,  1           // InterfaceMethod org/apache/dubbo/common/logger/ErrorTypeAwareLogger.isDebugEnabled:()Z
      25: ifeq          75
      28: getstatic     #29                 // Field logger:Lorg/apache/dubbo/common/logger/ErrorTypeAwareLogger;
      31: new           #31                 // class java/lang/StringBuilder
      34: dup
      35: invokespecial #32                 // Method java/lang/StringBuilder."<init>":()V
      38: ldc           #33                 // String Performing broadcast call for method:
      40: invokevirtual #34                 // Method java/lang/StringBuilder.append:(Ljava/lang/String;)Ljava/lang/StringBuilder;
      43: aload_1
      44: invokeinterface #35,  1           // InterfaceMethod org/apache/dubbo/rpc/Invocation.getMethodName:()Ljava/lang/String;
      49: invokevirtual #34                 // Method java/lang/StringBuilder.append:(Ljava/lang/String;)Ljava/lang/StringBuilder;
      52: ldc           #36                 // String  of service:
      54: invokevirtual #34                 // Method java/lang/StringBuilder.append:(Ljava/lang/String;)Ljava/lang/StringBuilder;
      57: aload_0
      58: invokevirtual #19                 // Method getUrl:()Lorg/apache/dubbo/common/URL;
      61: invokevirtual #20                 // Method org/apache/dubbo/common/URL.getServiceKey:()Ljava/lang/String;
      64: invokevirtual #34                 // Method java/lang/StringBuilder.append:(Ljava/lang/String;)Ljava/lang/StringBuilder;
      67: invokevirtual #37                 // Method java/lang/StringBuilder.toString:()Ljava/lang/String;
      70: invokeinterface #38,  2           // InterfaceMethod org/apache/dubbo/common/logger/ErrorTypeAwareLogger.debug:(Ljava/lang/String;)V
      75: aload_0
      76: getfield      #8                  // Field invoker:Lorg/apache/dubbo/rpc/Invoker;
      79: aload_1
      80: invokeinterface #39,  2           // InterfaceMethod org/apache/dubbo/rpc/Invoker.invoke:(Lorg/apache/dubbo/rpc/Invocation;)Lorg/apache/dubbo/rpc/Result;
      85: areturn
      86: aload_0
      87: getfield      #40                 // Field peerFlag:Z
      90: ifeq          162
      93: getstatic     #29                 // Field logger:Lorg/apache/dubbo/common/logger/ErrorTypeAwareLogger;
      96: invokeinterface #30,  1           // InterfaceMethod org/apache/dubbo/common/logger/ErrorTypeAwareLogger.isDebugEnabled:()Z
     101: ifeq          151
     104: getstatic     #29                 // Field logger:Lorg/apache/dubbo/common/logger/ErrorTypeAwareLogger;
     107: new           #31                 // class java/lang/StringBuilder
     110: dup
     111: invokespecial #32                 // Method java/lang/StringBuilder."<init>":()V
     114: ldc           #41                 // String Performing point-to-point call for method:
     116: invokevirtual #34                 // Method java/lang/StringBuilder.append:(Ljava/lang/String;)Ljava/lang/StringBuilder;
     119: aload_1
     120: invokeinterface #35,  1           // InterfaceMethod org/apache/dubbo/rpc/Invocation.getMethodName:()Ljava/lang/String;
     125: invokevirtual #34                 // Method java/lang/StringBuilder.append:(Ljava/lang/String;)Ljava/lang/StringBuilder;
     128: ldc           #36                 // String  of service:
     130: invokevirtual #34                 // Method java/lang/StringBuilder.append:(Ljava/lang/String;)Ljava/lang/StringBuilder;
     133: aload_0
     134: invokevirtual #19                 // Method getUrl:()Lorg/apache/dubbo/common/URL;
     137: invokevirtual #20                 // Method org/apache/dubbo/common/URL.getServiceKey:()Ljava/lang/String;
     140: invokevirtual #34                 // Method java/lang/StringBuilder.append:(Ljava/lang/String;)Ljava/lang/StringBuilder;
     143: invokevirtual #37                 // Method java/lang/StringBuilder.toString:()Ljava/lang/String;
     146: invokeinterface #38,  2           // InterfaceMethod org/apache/dubbo/common/logger/ErrorTypeAwareLogger.debug:(Ljava/lang/String;)V
     151: aload_0
     152: getfield      #8                  // Field invoker:Lorg/apache/dubbo/rpc/Invoker;
     155: aload_1
     156: invokeinterface #39,  2           // InterfaceMethod org/apache/dubbo/rpc/Invoker.invoke:(Lorg/apache/dubbo/rpc/Invocation;)Lorg/apache/dubbo/rpc/Result;
     161: areturn
     162: aload_0
     163: invokespecial #42                 // Method isInjvmExported:()Z
     166: ifeq          238
     169: getstatic     #29                 // Field logger:Lorg/apache/dubbo/common/logger/ErrorTypeAwareLogger;
     172: invokeinterface #30,  1           // InterfaceMethod org/apache/dubbo/common/logger/ErrorTypeAwareLogger.isDebugEnabled:()Z
     177: ifeq          227
     180: getstatic     #29                 // Field logger:Lorg/apache/dubbo/common/logger/ErrorTypeAwareLogger;
     183: new           #31                 // class java/lang/StringBuilder
     186: dup
     187: invokespecial #32                 // Method java/lang/StringBuilder."<init>":()V
     190: ldc           #43                 // String Performing local JVM call for method:
     192: invokevirtual #34                 // Method java/lang/StringBuilder.append:(Ljava/lang/String;)Ljava/lang/StringBuilder;
     195: aload_1
     196: invokeinterface #35,  1           // InterfaceMethod org/apache/dubbo/rpc/Invocation.getMethodName:()Ljava/lang/String;
     201: invokevirtual #34                 // Method java/lang/StringBuilder.append:(Ljava/lang/String;)Ljava/lang/StringBuilder;
     204: ldc           #36                 // String  of service:
     206: invokevirtual #34                 // Method java/lang/StringBuilder.append:(Ljava/lang/String;)Ljava/lang/StringBuilder;
     209: aload_0
     210: invokevirtual #19                 // Method getUrl:()Lorg/apache/dubbo/common/URL;
     213: invokevirtual #20                 // Method org/apache/dubbo/common/URL.getServiceKey:()Ljava/lang/String;
     216: invokevirtual #34                 // Method java/lang/StringBuilder.append:(Ljava/lang/String;)Ljava/lang/StringBuilder;
     219: invokevirtual #37                 // Method java/lang/StringBuilder.toString:()Ljava/lang/String;
     222: invokeinterface #38,  2           // InterfaceMethod org/apache/dubbo/common/logger/ErrorTypeAwareLogger.debug:(Ljava/lang/String;)V
     227: aload_0
     228: getfield      #44                 // Field injvmInvoker:Lorg/apache/dubbo/rpc/Invoker;
     231: aload_1
     232: invokeinterface #39,  2           // InterfaceMethod org/apache/dubbo/rpc/Invoker.invoke:(Lorg/apache/dubbo/rpc/Invocation;)Lorg/apache/dubbo/rpc/Result;
     237: areturn
     238: getstatic     #29                 // Field logger:Lorg/apache/dubbo/common/logger/ErrorTypeAwareLogger;
     241: invokeinterface #30,  1           // InterfaceMethod org/apache/dubbo/common/logger/ErrorTypeAwareLogger.isDebugEnabled:()Z
     246: ifeq          296
     249: getstatic     #29                 // Field logger:Lorg/apache/dubbo/common/logger/ErrorTypeAwareLogger;
     252: new           #31                 // class java/lang/StringBuilder
     255: dup
     256: invokespecial #32                 // Method java/lang/StringBuilder."<init>":()V
     259: ldc           #45                 // String Performing remote call for method:
     261: invokevirtual #34                 // Method java/lang/StringBuilder.append:(Ljava/lang/String;)Ljava/lang/StringBuilder;
     264: aload_1
     265: invokeinterface #35,  1           // InterfaceMethod org/apache/dubbo/rpc/Invocation.getMethodName:()Ljava/lang/String;
     270: invokevirtual #34                 // Method java/lang/StringBuilder.append:(Ljava/lang/String;)Ljava/lang/StringBuilder;
     273: ldc           #36                 // String  of service:
     275: invokevirtual #34                 // Method java/lang/StringBuilder.append:(Ljava/lang/String;)Ljava/lang/StringBuilder;
     278: aload_0
     279: invokevirtual #19                 // Method getUrl:()Lorg/apache/dubbo/common/URL;
     282: invokevirtual #20                 // Method org/apache/dubbo/common/URL.getServiceKey:()Ljava/lang/String;
     285: invokevirtual #34                 // Method java/lang/StringBuilder.append:(Ljava/lang/String;)Ljava/lang/StringBuilder;
     288: invokevirtual #37                 // Method java/lang/StringBuilder.toString:()Ljava/lang/String;
     291: invokeinterface #38,  2           // InterfaceMethod org/apache/dubbo/common/logger/ErrorTypeAwareLogger.debug:(Ljava/lang/String;)V
     296: aload_0
     297: getfield      #8                  // Field invoker:Lorg/apache/dubbo/rpc/Invoker;
     300: aload_1
     301: invokeinterface #39,  2           // InterfaceMethod org/apache/dubbo/rpc/Invoker.invoke:(Lorg/apache/dubbo/rpc/Invocation;)Lorg/apache/dubbo/rpc/Result;
     306: areturn

  public void onExporterChangeExport(org.apache.dubbo.rpc.Exporter<?>);
    Code:
       0: aload_0
       1: getfield      #11                 // Field isExported:Ljava/util/concurrent/atomic/AtomicBoolean;
       4: invokevirtual #16                 // Method java/util/concurrent/atomic/AtomicBoolean.get:()Z
       7: ifeq          11
      10: return
      11: aload_0
      12: invokevirtual #19                 // Method getUrl:()Lorg/apache/dubbo/common/URL;
      15: invokevirtual #20                 // Method org/apache/dubbo/common/URL.getServiceKey:()Ljava/lang/String;
      18: aload_1
      19: invokeinterface #46,  1           // InterfaceMethod org/apache/dubbo/rpc/Exporter.getInvoker:()Lorg/apache/dubbo/rpc/Invoker;
      24: invokeinterface #47,  1           // InterfaceMethod org/apache/dubbo/rpc/Invoker.getUrl:()Lorg/apache/dubbo/common/URL;
      29: invokevirtual #20                 // Method org/apache/dubbo/common/URL.getServiceKey:()Ljava/lang/String;
      32: invokevirtual #48                 // Method java/lang/String.equals:(Ljava/lang/Object;)Z
      35: ifeq          74
      38: aload_1
      39: invokeinterface #46,  1           // InterfaceMethod org/apache/dubbo/rpc/Exporter.getInvoker:()Lorg/apache/dubbo/rpc/Invoker;
      44: invokeinterface #47,  1           // InterfaceMethod org/apache/dubbo/rpc/Invoker.getUrl:()Lorg/apache/dubbo/common/URL;
      49: invokevirtual #49                 // Method org/apache/dubbo/common/URL.getProtocol:()Ljava/lang/String;
      52: ldc           #50                 // String injvm
      54: invokevirtual #28                 // Method java/lang/String.equalsIgnoreCase:(Ljava/lang/String;)Z
      57: ifeq          74
      60: aload_0
      61: invokespecial #51                 // Method createInjvmInvoker:()V
      64: aload_0
      65: getfield      #11                 // Field isExported:Ljava/util/concurrent/atomic/AtomicBoolean;
      68: iconst_0
      69: iconst_1
      70: invokevirtual #52                 // Method java/util/concurrent/atomic/AtomicBoolean.compareAndSet:(ZZ)Z
      73: pop
      74: return

  public void onExporterChangeUnExport(org.apache.dubbo.rpc.Exporter<?>);
    Code:
       0: aload_0
       1: invokevirtual #19                 // Method getUrl:()Lorg/apache/dubbo/common/URL;
       4: invokevirtual #20                 // Method org/apache/dubbo/common/URL.getServiceKey:()Ljava/lang/String;
       7: aload_1
       8: invokeinterface #46,  1           // InterfaceMethod org/apache/dubbo/rpc/Exporter.getInvoker:()Lorg/apache/dubbo/rpc/Invoker;
      13: invokeinterface #47,  1           // InterfaceMethod org/apache/dubbo/rpc/Invoker.getUrl:()Lorg/apache/dubbo/common/URL;
      18: invokevirtual #20                 // Method org/apache/dubbo/common/URL.getServiceKey:()Ljava/lang/String;
      21: invokevirtual #48                 // Method java/lang/String.equals:(Ljava/lang/Object;)Z
      24: ifeq          63
      27: aload_1
      28: invokeinterface #46,  1           // InterfaceMethod org/apache/dubbo/rpc/Exporter.getInvoker:()Lorg/apache/dubbo/rpc/Invoker;
      33: invokeinterface #47,  1           // InterfaceMethod org/apache/dubbo/rpc/Invoker.getUrl:()Lorg/apache/dubbo/common/URL;
      38: invokevirtual #49                 // Method org/apache/dubbo/common/URL.getProtocol:()Ljava/lang/String;
      41: ldc           #50                 // String injvm
      43: invokevirtual #28                 // Method java/lang/String.equalsIgnoreCase:(Ljava/lang/String;)Z
      46: ifeq          63
      49: aload_0
      50: invokespecial #22                 // Method destroyInjvmInvoker:()V
      53: aload_0
      54: getfield      #11                 // Field isExported:Ljava/util/concurrent/atomic/AtomicBoolean;
      57: iconst_1
      58: iconst_0
      59: invokevirtual #52                 // Method java/util/concurrent/atomic/AtomicBoolean.compareAndSet:(ZZ)Z
      62: pop
      63: return

  public org.apache.dubbo.rpc.Invoker<?> getInvoker();
    Code:
       0: aload_0
       1: getfield      #8                  // Field invoker:Lorg/apache/dubbo/rpc/Invoker;
       4: areturn

  private void init();
    Code:
       0: aload_0
       1: invokevirtual #19                 // Method getUrl:()Lorg/apache/dubbo/common/URL;
       4: ldc           #53                 // String peer
       6: invokevirtual #54                 // Method org/apache/dubbo/common/URL.getAttribute:(Ljava/lang/String;)Ljava/lang/Object;
       9: checkcast     #55                 // class java/lang/Boolean
      12: astore_1
      13: aload_0
      14: invokevirtual #19                 // Method getUrl:()Lorg/apache/dubbo/common/URL;
      17: ldc           #50                 // String injvm
      19: invokevirtual #27                 // Method org/apache/dubbo/common/URL.getParameter:(Ljava/lang/String;)Ljava/lang/String;
      22: astore_2
      23: aload_1
      24: ifnull        40
      27: aload_1
      28: invokevirtual #56                 // Method java/lang/Boolean.booleanValue:()Z
      31: ifeq          40
      34: aload_0
      35: iconst_1
      36: putfield      #40                 // Field peerFlag:Z
      39: return
      40: aload_0
      41: getfield      #44                 // Field injvmInvoker:Lorg/apache/dubbo/rpc/Invoker;
      44: ifnonnull     86
      47: ldc           #50                 // String injvm
      49: aload_0
      50: invokevirtual #57                 // Method getRegistryUrl:()Lorg/apache/dubbo/common/URL;
      53: invokevirtual #49                 // Method org/apache/dubbo/common/URL.getProtocol:()Ljava/lang/String;
      56: invokevirtual #28                 // Method java/lang/String.equalsIgnoreCase:(Ljava/lang/String;)Z
      59: ifeq          86
      62: aload_0
      63: aload_0
      64: getfield      #8                  // Field invoker:Lorg/apache/dubbo/rpc/Invoker;
      67: putfield      #44                 // Field injvmInvoker:Lorg/apache/dubbo/rpc/Invoker;
      70: aload_0
      71: getfield      #11                 // Field isExported:Ljava/util/concurrent/atomic/AtomicBoolean;
      74: iconst_0
      75: iconst_1
      76: invokevirtual #52                 // Method java/util/concurrent/atomic/AtomicBoolean.compareAndSet:(ZZ)Z
      79: pop
      80: aload_0
      81: iconst_1
      82: putfield      #58                 // Field injvmFlag:Z
      85: return
      86: getstatic     #59                 // Field java/lang/Boolean.TRUE:Ljava/lang/Boolean;
      89: invokevirtual #60                 // Method java/lang/Boolean.toString:()Ljava/lang/String;
      92: aload_2
      93: invokevirtual #28                 // Method java/lang/String.equalsIgnoreCase:(Ljava/lang/String;)Z
      96: ifne          116
      99: ldc           #61                 // String local
     101: aload_0
     102: invokevirtual #19                 // Method getUrl:()Lorg/apache/dubbo/common/URL;
     105: ldc           #62                 // String scope
     107: invokevirtual #27                 // Method org/apache/dubbo/common/URL.getParameter:(Ljava/lang/String;)Ljava/lang/String;
     110: invokevirtual #28                 // Method java/lang/String.equalsIgnoreCase:(Ljava/lang/String;)Z
     113: ifeq          124
     116: aload_0
     117: iconst_1
     118: putfield      #58                 // Field injvmFlag:Z
     121: goto          136
     124: aload_2
     125: ifnonnull     136
     128: aload_0
     129: aload_0
     130: invokespecial #63                 // Method isNotRemoteOrGeneric:()Z
     133: putfield      #58                 // Field injvmFlag:Z
     136: aload_0
     137: aload_0
     138: invokevirtual #19                 // Method getUrl:()Lorg/apache/dubbo/common/URL;
     141: invokevirtual #64                 // Method org/apache/dubbo/common/URL.getApplicationModel:()Lorg/apache/dubbo/rpc/model/ApplicationModel;
     144: ldc           #65                 // class org/apache/dubbo/rpc/Protocol
     146: invokevirtual #66                 // Method org/apache/dubbo/rpc/model/ApplicationModel.getExtensionLoader:(Ljava/lang/Class;)Lorg/apache/dubbo/common/extension/ExtensionLoader;
     149: invokevirtual #67                 // Method org/apache/dubbo/common/extension/ExtensionLoader.getAdaptiveExtension:()Ljava/lang/Object;
     152: checkcast     #65                 // class org/apache/dubbo/rpc/Protocol
     155: putfield      #68                 // Field protocolSPI:Lorg/apache/dubbo/rpc/Protocol;
     158: aload_0
     159: aload_0
     160: invokevirtual #19                 // Method getUrl:()Lorg/apache/dubbo/common/URL;
     163: invokevirtual #69                 // Method org/apache/dubbo/common/URL.getOrDefaultFrameworkModel:()Lorg/apache/dubbo/rpc/model/FrameworkModel;
     166: invokevirtual #70                 // Method org/apache/dubbo/rpc/model/FrameworkModel.getBeanFactory:()Lorg/apache/dubbo/common/beans/factory/ScopeBeanFactory;
     169: ldc           #71                 // class org/apache/dubbo/rpc/listener/InjvmExporterListener
     171: invokevirtual #72                 // Method org/apache/dubbo/common/beans/factory/ScopeBeanFactory.getBean:(Ljava/lang/Class;)Ljava/lang/Object;
     174: checkcast     #71                 // class org/apache/dubbo/rpc/listener/InjvmExporterListener
     177: putfield      #18                 // Field injvmExporterListener:Lorg/apache/dubbo/rpc/listener/InjvmExporterListener;
     180: aload_0
     181: getfield      #18                 // Field injvmExporterListener:Lorg/apache/dubbo/rpc/listener/InjvmExporterListener;
     184: aload_0
     185: aload_0
     186: invokevirtual #19                 // Method getUrl:()Lorg/apache/dubbo/common/URL;
     189: invokevirtual #20                 // Method org/apache/dubbo/common/URL.getServiceKey:()Ljava/lang/String;
     192: invokevirtual #73                 // Method org/apache/dubbo/rpc/listener/InjvmExporterListener.addExporterChangeListener:(Lorg/apache/dubbo/rpc/listener/ExporterChangeListener;Ljava/lang/String;)V
     195: return

  private boolean isNotRemoteOrGeneric();
    Code:
       0: ldc           #74                 // String remote
       2: aload_0
       3: invokevirtual #19                 // Method getUrl:()Lorg/apache/dubbo/common/URL;
       6: ldc           #62                 // String scope
       8: invokevirtual #27                 // Method org/apache/dubbo/common/URL.getParameter:(Ljava/lang/String;)Ljava/lang/String;
      11: invokevirtual #28                 // Method java/lang/String.equalsIgnoreCase:(Ljava/lang/String;)Z
      14: ifne          34
      17: aload_0
      18: invokevirtual #19                 // Method getUrl:()Lorg/apache/dubbo/common/URL;
      21: ldc           #75                 // String generic
      23: iconst_0
      24: invokevirtual #76                 // Method org/apache/dubbo/common/URL.getParameter:(Ljava/lang/String;Z)Z
      27: ifne          34
      30: iconst_1
      31: goto          35
      34: iconst_0
      35: ireturn

  private boolean isInjvmExported();
    Code:
       0: invokestatic  #77                 // Method org/apache/dubbo/rpc/RpcContext.getServiceContext:()Lorg/apache/dubbo/rpc/RpcServiceContext;
       3: invokevirtual #78                 // Method org/apache/dubbo/rpc/RpcServiceContext.getLocalInvoke:()Ljava/lang/Boolean;
       6: astore_1
       7: aload_0
       8: getfield      #11                 // Field isExported:Ljava/util/concurrent/atomic/AtomicBoolean;
      11: invokevirtual #16                 // Method java/util/concurrent/atomic/AtomicBoolean.get:()Z
      14: istore_2
      15: aload_1
      16: ifnull        30
      19: aload_1
      20: invokevirtual #56                 // Method java/lang/Boolean.booleanValue:()Z
      23: ifeq          30
      26: iconst_1
      27: goto          31
      30: iconst_0
      31: istore_3
      32: iload_2
      33: ifeq          42
      36: iload_3
      37: ifeq          42
      40: iconst_1
      41: ireturn
      42: aload_1
      43: ifnull        55
      46: aload_1
      47: invokevirtual #56                 // Method java/lang/Boolean.booleanValue:()Z
      50: ifne          55
      53: iconst_0
      54: ireturn
      55: iload_2
      56: ifne          139
      59: ldc           #61                 // String local
      61: aload_0
      62: invokevirtual #19                 // Method getUrl:()Lorg/apache/dubbo/common/URL;
      65: ldc           #62                 // String scope
      67: invokevirtual #27                 // Method org/apache/dubbo/common/URL.getParameter:(Ljava/lang/String;)Ljava/lang/String;
      70: invokevirtual #28                 // Method java/lang/String.equalsIgnoreCase:(Ljava/lang/String;)Z
      73: ifne          101
      76: getstatic     #59                 // Field java/lang/Boolean.TRUE:Ljava/lang/Boolean;
      79: invokevirtual #60                 // Method java/lang/Boolean.toString:()Ljava/lang/String;
      82: aload_0
      83: invokevirtual #19                 // Method getUrl:()Lorg/apache/dubbo/common/URL;
      86: ldc           #50                 // String injvm
      88: invokevirtual #27                 // Method org/apache/dubbo/common/URL.getParameter:(Ljava/lang/String;)Ljava/lang/String;
      91: invokevirtual #28                 // Method java/lang/String.equalsIgnoreCase:(Ljava/lang/String;)Z
      94: ifne          101
      97: iload_3
      98: ifeq          139
     101: new           #79                 // class org/apache/dubbo/rpc/RpcException
     104: dup
     105: new           #31                 // class java/lang/StringBuilder
     108: dup
     109: invokespecial #32                 // Method java/lang/StringBuilder."<init>":()V
     112: ldc           #80                 // String Local service for
     114: invokevirtual #34                 // Method java/lang/StringBuilder.append:(Ljava/lang/String;)Ljava/lang/StringBuilder;
     117: aload_0
     118: invokevirtual #19                 // Method getUrl:()Lorg/apache/dubbo/common/URL;
     121: invokevirtual #81                 // Method org/apache/dubbo/common/URL.getServiceInterface:()Ljava/lang/String;
     124: invokevirtual #34                 // Method java/lang/StringBuilder.append:(Ljava/lang/String;)Ljava/lang/StringBuilder;
     127: ldc           #82                 // String  has not been exposed yet!
     129: invokevirtual #34                 // Method java/lang/StringBuilder.append:(Ljava/lang/String;)Ljava/lang/StringBuilder;
     132: invokevirtual #37                 // Method java/lang/StringBuilder.toString:()Ljava/lang/String;
     135: invokespecial #83                 // Method org/apache/dubbo/rpc/RpcException."<init>":(Ljava/lang/String;)V
     138: athrow
     139: iload_2
     140: ifeq          154
     143: aload_0
     144: getfield      #58                 // Field injvmFlag:Z
     147: ifeq          154
     150: iconst_1
     151: goto          155
     154: iconst_0
     155: ireturn

  private void createInjvmInvoker();
    Code:
       0: aload_0
       1: getfield      #44                 // Field injvmInvoker:Lorg/apache/dubbo/rpc/Invoker;
       4: ifnonnull     154
       7: aload_0
       8: getfield      #6                  // Field createLock:Ljava/lang/Object;
      11: dup
      12: astore_1
      13: monitorenter
      14: aload_0
      15: getfield      #44                 // Field injvmInvoker:Lorg/apache/dubbo/rpc/Invoker;
      18: ifnonnull     142
      21: new           #84                 // class org/apache/dubbo/common/url/component/ServiceConfigURL
      24: dup
      25: ldc           #50                 // String injvm
      27: invokestatic  #85                 // Method org/apache/dubbo/common/utils/NetUtils.getLocalHost:()Ljava/lang/String;
      30: aload_0
      31: invokevirtual #19                 // Method getUrl:()Lorg/apache/dubbo/common/URL;
      34: invokevirtual #86                 // Method org/apache/dubbo/common/URL.getPort:()I
      37: aload_0
      38: invokevirtual #87                 // Method getInterface:()Ljava/lang/Class;
      41: invokevirtual #88                 // Method java/lang/Class.getName:()Ljava/lang/String;
      44: aload_0
      45: invokevirtual #19                 // Method getUrl:()Lorg/apache/dubbo/common/URL;
      48: invokevirtual #89                 // Method org/apache/dubbo/common/URL.getParameters:()Ljava/util/Map;
      51: invokespecial #90                 // Method org/apache/dubbo/common/url/component/ServiceConfigURL."<init>":(Ljava/lang/String;Ljava/lang/String;ILjava/lang/String;Ljava/util/Map;)V
      54: astore_2
      55: aload_2
      56: aload_0
      57: invokevirtual #19                 // Method getUrl:()Lorg/apache/dubbo/common/URL;
      60: invokevirtual #91                 // Method org/apache/dubbo/common/URL.getScopeModel:()Lorg/apache/dubbo/rpc/model/ScopeModel;
      63: invokevirtual #92                 // Method org/apache/dubbo/common/URL.setScopeModel:(Lorg/apache/dubbo/rpc/model/ScopeModel;)Lorg/apache/dubbo/common/URL;
      66: astore_2
      67: aload_2
      68: aload_0
      69: invokevirtual #19                 // Method getUrl:()Lorg/apache/dubbo/common/URL;
      72: invokevirtual #93                 // Method org/apache/dubbo/common/URL.getServiceModel:()Lorg/apache/dubbo/rpc/model/ServiceModel;
      75: invokevirtual #94                 // Method org/apache/dubbo/common/URL.setServiceModel:(Lorg/apache/dubbo/rpc/model/ServiceModel;)Lorg/apache/dubbo/common/URL;
      78: astore_2
      79: aload_0
      80: getfield      #68                 // Field protocolSPI:Lorg/apache/dubbo/rpc/Protocol;
      83: aload_0
      84: invokevirtual #87                 // Method getInterface:()Ljava/lang/Class;
      87: aload_2
      88: invokeinterface #95,  3           // InterfaceMethod org/apache/dubbo/rpc/Protocol.refer:(Ljava/lang/Class;Lorg/apache/dubbo/common/URL;)Lorg/apache/dubbo/rpc/Invoker;
      93: astore_3
      94: new           #96                 // class java/util/ArrayList
      97: dup
      98: invokespecial #97                 // Method java/util/ArrayList."<init>":()V
     101: astore        4
     103: aload         4
     105: aload_3
     106: invokeinterface #98,  2           // InterfaceMethod java/util/List.add:(Ljava/lang/Object;)Z
     111: pop
     112: aload_0
     113: aload_2
     114: invokevirtual #91                 // Method org/apache/dubbo/common/URL.getScopeModel:()Lorg/apache/dubbo/rpc/model/ScopeModel;
     117: ldc           #100                // String failover
     119: iconst_0
     120: invokestatic  #101                // InterfaceMethod org/apache/dubbo/rpc/cluster/Cluster.getCluster:(Lorg/apache/dubbo/rpc/model/ScopeModel;Ljava/lang/String;Z)Lorg/apache/dubbo/rpc/cluster/Cluster;
     123: new           #102                // class org/apache/dubbo/rpc/cluster/directory/StaticDirectory
     126: dup
     127: aload_2
     128: aload         4
     130: invokespecial #103                // Method org/apache/dubbo/rpc/cluster/directory/StaticDirectory."<init>":(Lorg/apache/dubbo/common/URL;Ljava/util/List;)V
     133: iconst_1
     134: invokeinterface #104,  3          // InterfaceMethod org/apache/dubbo/rpc/cluster/Cluster.join:(Lorg/apache/dubbo/rpc/cluster/Directory;Z)Lorg/apache/dubbo/rpc/Invoker;
     139: putfield      #44                 // Field injvmInvoker:Lorg/apache/dubbo/rpc/Invoker;
     142: aload_1
     143: monitorexit
     144: goto          154
     147: astore        5
     149: aload_1
     150: monitorexit
     151: aload         5
     153: athrow
     154: return
    Exception table:
       from    to  target type
          14   144   147   any
         147   151   147   any

  private void destroyInjvmInvoker();
    Code:
       0: aload_0
       1: getfield      #44                 // Field injvmInvoker:Lorg/apache/dubbo/rpc/Invoker;
       4: ifnull        21
       7: aload_0
       8: getfield      #44                 // Field injvmInvoker:Lorg/apache/dubbo/rpc/Invoker;
      11: invokeinterface #23,  1           // InterfaceMethod org/apache/dubbo/rpc/Invoker.destroy:()V
      16: aload_0
      17: aconst_null
      18: putfield      #44                 // Field injvmInvoker:Lorg/apache/dubbo/rpc/Invoker;
      21: return

  static {};
    Code:
       0: ldc           #105                // class org/apache/dubbo/rpc/cluster/support/wrapper/ScopeClusterInvoker
       2: invokestatic  #106                // Method org/apache/dubbo/common/logger/LoggerFactory.getErrorTypeAwareLogger:(Ljava/lang/Class;)Lorg/apache/dubbo/common/logger/ErrorTypeAwareLogger;
       5: putstatic     #29                 // Field logger:Lorg/apache/dubbo/common/logger/ErrorTypeAwareLogger;
       8: return
}
