Compiled from "ScopeClusterWrapper.java"
public class org.apache.dubbo.rpc.cluster.support.wrapper.ScopeClusterWrapper implements org.apache.dubbo.rpc.cluster.Cluster {
  private final org.apache.dubbo.rpc.cluster.Cluster cluster;

  public org.apache.dubbo.rpc.cluster.support.wrapper.ScopeClusterWrapper(org.apache.dubbo.rpc.cluster.Cluster);
    Code:
       0: aload_0
       1: invokespecial #1                  // Method java/lang/Object."<init>":()V
       4: aload_0
       5: aload_1
       6: putfield      #2                  // Field cluster:Lorg/apache/dubbo/rpc/cluster/Cluster;
       9: return

  public <T> org.apache.dubbo.rpc.Invoker<T> join(org.apache.dubbo.rpc.cluster.Directory<T>, boolean) throws org.apache.dubbo.rpc.RpcException;
    Code:
       0: new           #3                  // class org/apache/dubbo/rpc/cluster/support/wrapper/ScopeClusterInvoker
       3: dup
       4: aload_1
       5: aload_0
       6: getfield      #2                  // Field cluster:Lorg/apache/dubbo/rpc/cluster/Cluster;
       9: aload_1
      10: iload_2
      11: invokeinterface #4,  3            // InterfaceMethod org/apache/dubbo/rpc/cluster/Cluster.join:(Lorg/apache/dubbo/rpc/cluster/Directory;Z)Lorg/apache/dubbo/rpc/Invoker;
      16: invokespecial #5                  // Method org/apache/dubbo/rpc/cluster/support/wrapper/ScopeClusterInvoker."<init>":(Lorg/apache/dubbo/rpc/cluster/Directory;Lorg/apache/dubbo/rpc/Invoker;)V
      19: areturn

  public org.apache.dubbo.rpc.cluster.Cluster getCluster();
    Code:
       0: aload_0
       1: getfield      #2                  // Field cluster:Lorg/apache/dubbo/rpc/cluster/Cluster;
       4: areturn
}
