Compiled from "ActionDisposable.java"
final class io.reactivex.rxjava3.disposables.ActionDisposable extends io.reactivex.rxjava3.disposables.ReferenceDisposable<io.reactivex.rxjava3.functions.Action> {
  private static final long serialVersionUID;

  io.reactivex.rxjava3.disposables.ActionDisposable(io.reactivex.rxjava3.functions.Action);
    Code:
       0: aload_0
       1: aload_1
       2: invokespecial #1                  // Method io/reactivex/rxjava3/disposables/ReferenceDisposable."<init>":(Ljava/lang/Object;)V
       5: return

  protected void onDisposed(io.reactivex.rxjava3.functions.Action);
    Code:
       0: aload_1
       1: invokeinterface #2,  1            // InterfaceMethod io/reactivex/rxjava3/functions/Action.run:()V
       6: goto          15
       9: astore_2
      10: aload_2
      11: invokestatic  #4                  // Method io/reactivex/rxjava3/internal/util/ExceptionHelper.wrapOrThrow:(Ljava/lang/Throwable;)Ljava/lang/RuntimeException;
      14: athrow
      15: return
    Exception table:
       from    to  target type
           0     6     9   Class java/lang/Throwable

  public java.lang.String toString();
    Code:
       0: new           #5                  // class java/lang/StringBuilder
       3: dup
       4: invokespecial #6                  // Method java/lang/StringBuilder."<init>":()V
       7: ldc           #7                  // String ActionDisposable(disposed=
       9: invokevirtual #8                  // Method java/lang/StringBuilder.append:(Ljava/lang/String;)Ljava/lang/StringBuilder;
      12: aload_0
      13: invokevirtual #9                  // Method isDisposed:()Z
      16: invokevirtual #10                 // Method java/lang/StringBuilder.append:(Z)Ljava/lang/StringBuilder;
      19: ldc           #11                 // String ,
      21: invokevirtual #8                  // Method java/lang/StringBuilder.append:(Ljava/lang/String;)Ljava/lang/StringBuilder;
      24: aload_0
      25: invokevirtual #12                 // Method get:()Ljava/lang/Object;
      28: invokevirtual #13                 // Method java/lang/StringBuilder.append:(Ljava/lang/Object;)Ljava/lang/StringBuilder;
      31: ldc           #14                 // String )
      33: invokevirtual #8                  // Method java/lang/StringBuilder.append:(Ljava/lang/String;)Ljava/lang/StringBuilder;
      36: invokevirtual #15                 // Method java/lang/StringBuilder.toString:()Ljava/lang/String;
      39: areturn

  protected void onDisposed(java.lang.Object);
    Code:
       0: aload_0
       1: aload_1
       2: checkcast     #16                 // class io/reactivex/rxjava3/functions/Action
       5: invokevirtual #17                 // Method onDisposed:(Lio/reactivex/rxjava3/functions/Action;)V
       8: return
}
