Compiled from "CompositeDisposable.java"
public final class io.reactivex.rxjava3.disposables.CompositeDisposable implements io.reactivex.rxjava3.disposables.Disposable,io.reactivex.rxjava3.disposables.DisposableContainer {
  io.reactivex.rxjava3.internal.util.OpenHashSet<io.reactivex.rxjava3.disposables.Disposable> resources;

  volatile boolean disposed;

  public io.reactivex.rxjava3.disposables.CompositeDisposable();
    Code:
       0: aload_0
       1: invokespecial #1                  // Method java/lang/Object."<init>":()V
       4: return

  public io.reactivex.rxjava3.disposables.CompositeDisposable(io.reactivex.rxjava3.disposables.Disposable...);
    Code:
       0: aload_0
       1: invokespecial #1                  // Method java/lang/Object."<init>":()V
       4: aload_1
       5: ldc           #2                  // String disposables is null
       7: invokestatic  #3                  // Method java/util/Objects.requireNonNull:(Ljava/lang/Object;Ljava/lang/String;)Ljava/lang/Object;
      10: pop
      11: aload_0
      12: new           #4                  // class io/reactivex/rxjava3/internal/util/OpenHashSet
      15: dup
      16: aload_1
      17: arraylength
      18: iconst_1
      19: iadd
      20: invokespecial #5                  // Method io/reactivex/rxjava3/internal/util/OpenHashSet."<init>":(I)V
      23: putfield      #6                  // Field resources:Lio/reactivex/rxjava3/internal/util/OpenHashSet;
      26: aload_1
      27: astore_2
      28: aload_2
      29: arraylength
      30: istore_3
      31: iconst_0
      32: istore        4
      34: iload         4
      36: iload_3
      37: if_icmpge     70
      40: aload_2
      41: iload         4
      43: aaload
      44: astore        5
      46: aload         5
      48: ldc           #7                  // String A Disposable in the disposables array is null
      50: invokestatic  #3                  // Method java/util/Objects.requireNonNull:(Ljava/lang/Object;Ljava/lang/String;)Ljava/lang/Object;
      53: pop
      54: aload_0
      55: getfield      #6                  // Field resources:Lio/reactivex/rxjava3/internal/util/OpenHashSet;
      58: aload         5
      60: invokevirtual #8                  // Method io/reactivex/rxjava3/internal/util/OpenHashSet.add:(Ljava/lang/Object;)Z
      63: pop
      64: iinc          4, 1
      67: goto          34
      70: return

  public io.reactivex.rxjava3.disposables.CompositeDisposable(java.lang.Iterable<? extends io.reactivex.rxjava3.disposables.Disposable>);
    Code:
       0: aload_0
       1: invokespecial #1                  // Method java/lang/Object."<init>":()V
       4: aload_1
       5: ldc           #2                  // String disposables is null
       7: invokestatic  #3                  // Method java/util/Objects.requireNonNull:(Ljava/lang/Object;Ljava/lang/String;)Ljava/lang/Object;
      10: pop
      11: aload_0
      12: new           #4                  // class io/reactivex/rxjava3/internal/util/OpenHashSet
      15: dup
      16: invokespecial #9                  // Method io/reactivex/rxjava3/internal/util/OpenHashSet."<init>":()V
      19: putfield      #6                  // Field resources:Lio/reactivex/rxjava3/internal/util/OpenHashSet;
      22: aload_1
      23: invokeinterface #10,  1           // InterfaceMethod java/lang/Iterable.iterator:()Ljava/util/Iterator;
      28: astore_2
      29: aload_2
      30: invokeinterface #11,  1           // InterfaceMethod java/util/Iterator.hasNext:()Z
      35: ifeq          67
      38: aload_2
      39: invokeinterface #12,  1           // InterfaceMethod java/util/Iterator.next:()Ljava/lang/Object;
      44: checkcast     #13                 // class io/reactivex/rxjava3/disposables/Disposable
      47: astore_3
      48: aload_3
      49: ldc           #14                 // String A Disposable item in the disposables sequence is null
      51: invokestatic  #3                  // Method java/util/Objects.requireNonNull:(Ljava/lang/Object;Ljava/lang/String;)Ljava/lang/Object;
      54: pop
      55: aload_0
      56: getfield      #6                  // Field resources:Lio/reactivex/rxjava3/internal/util/OpenHashSet;
      59: aload_3
      60: invokevirtual #8                  // Method io/reactivex/rxjava3/internal/util/OpenHashSet.add:(Ljava/lang/Object;)Z
      63: pop
      64: goto          29
      67: return

  public void dispose();
    Code:
       0: aload_0
       1: getfield      #15                 // Field disposed:Z
       4: ifeq          8
       7: return
       8: aload_0
       9: dup
      10: astore_2
      11: monitorenter
      12: aload_0
      13: getfield      #15                 // Field disposed:Z
      16: ifeq          22
      19: aload_2
      20: monitorexit
      21: return
      22: aload_0
      23: iconst_1
      24: putfield      #15                 // Field disposed:Z
      27: aload_0
      28: getfield      #6                  // Field resources:Lio/reactivex/rxjava3/internal/util/OpenHashSet;
      31: astore_1
      32: aload_0
      33: aconst_null
      34: putfield      #6                  // Field resources:Lio/reactivex/rxjava3/internal/util/OpenHashSet;
      37: aload_2
      38: monitorexit
      39: goto          47
      42: astore_3
      43: aload_2
      44: monitorexit
      45: aload_3
      46: athrow
      47: aload_0
      48: aload_1
      49: invokevirtual #16                 // Method dispose:(Lio/reactivex/rxjava3/internal/util/OpenHashSet;)V
      52: return
    Exception table:
       from    to  target type
          12    21    42   any
          22    39    42   any
          42    45    42   any

  public boolean isDisposed();
    Code:
       0: aload_0
       1: getfield      #15                 // Field disposed:Z
       4: ireturn

  public boolean add(io.reactivex.rxjava3.disposables.Disposable);
    Code:
       0: aload_1
       1: ldc           #17                 // String disposable is null
       3: invokestatic  #3                  // Method java/util/Objects.requireNonNull:(Ljava/lang/Object;Ljava/lang/String;)Ljava/lang/Object;
       6: pop
       7: aload_0
       8: getfield      #15                 // Field disposed:Z
      11: ifne          69
      14: aload_0
      15: dup
      16: astore_2
      17: monitorenter
      18: aload_0
      19: getfield      #15                 // Field disposed:Z
      22: ifne          57
      25: aload_0
      26: getfield      #6                  // Field resources:Lio/reactivex/rxjava3/internal/util/OpenHashSet;
      29: astore_3
      30: aload_3
      31: ifnonnull     47
      34: new           #4                  // class io/reactivex/rxjava3/internal/util/OpenHashSet
      37: dup
      38: invokespecial #9                  // Method io/reactivex/rxjava3/internal/util/OpenHashSet."<init>":()V
      41: astore_3
      42: aload_0
      43: aload_3
      44: putfield      #6                  // Field resources:Lio/reactivex/rxjava3/internal/util/OpenHashSet;
      47: aload_3
      48: aload_1
      49: invokevirtual #8                  // Method io/reactivex/rxjava3/internal/util/OpenHashSet.add:(Ljava/lang/Object;)Z
      52: pop
      53: iconst_1
      54: aload_2
      55: monitorexit
      56: ireturn
      57: aload_2
      58: monitorexit
      59: goto          69
      62: astore        4
      64: aload_2
      65: monitorexit
      66: aload         4
      68: athrow
      69: aload_1
      70: invokeinterface #18,  1           // InterfaceMethod io/reactivex/rxjava3/disposables/Disposable.dispose:()V
      75: iconst_0
      76: ireturn
    Exception table:
       from    to  target type
          18    56    62   any
          57    59    62   any
          62    66    62   any

  public boolean addAll(io.reactivex.rxjava3.disposables.Disposable...);
    Code:
       0: aload_1
       1: ldc           #2                  // String disposables is null
       3: invokestatic  #3                  // Method java/util/Objects.requireNonNull:(Ljava/lang/Object;Ljava/lang/String;)Ljava/lang/Object;
       6: pop
       7: aload_0
       8: getfield      #15                 // Field disposed:Z
      11: ifne          113
      14: aload_0
      15: dup
      16: astore_2
      17: monitorenter
      18: aload_0
      19: getfield      #15                 // Field disposed:Z
      22: ifne          101
      25: aload_0
      26: getfield      #6                  // Field resources:Lio/reactivex/rxjava3/internal/util/OpenHashSet;
      29: astore_3
      30: aload_3
      31: ifnonnull     51
      34: new           #4                  // class io/reactivex/rxjava3/internal/util/OpenHashSet
      37: dup
      38: aload_1
      39: arraylength
      40: iconst_1
      41: iadd
      42: invokespecial #5                  // Method io/reactivex/rxjava3/internal/util/OpenHashSet."<init>":(I)V
      45: astore_3
      46: aload_0
      47: aload_3
      48: putfield      #6                  // Field resources:Lio/reactivex/rxjava3/internal/util/OpenHashSet;
      51: aload_1
      52: astore        4
      54: aload         4
      56: arraylength
      57: istore        5
      59: iconst_0
      60: istore        6
      62: iload         6
      64: iload         5
      66: if_icmpge     97
      69: aload         4
      71: iload         6
      73: aaload
      74: astore        7
      76: aload         7
      78: ldc           #7                  // String A Disposable in the disposables array is null
      80: invokestatic  #3                  // Method java/util/Objects.requireNonNull:(Ljava/lang/Object;Ljava/lang/String;)Ljava/lang/Object;
      83: pop
      84: aload_3
      85: aload         7
      87: invokevirtual #8                  // Method io/reactivex/rxjava3/internal/util/OpenHashSet.add:(Ljava/lang/Object;)Z
      90: pop
      91: iinc          6, 1
      94: goto          62
      97: iconst_1
      98: aload_2
      99: monitorexit
     100: ireturn
     101: aload_2
     102: monitorexit
     103: goto          113
     106: astore        8
     108: aload_2
     109: monitorexit
     110: aload         8
     112: athrow
     113: aload_1
     114: astore_2
     115: aload_2
     116: arraylength
     117: istore_3
     118: iconst_0
     119: istore        4
     121: iload         4
     123: iload_3
     124: if_icmpge     146
     127: aload_2
     128: iload         4
     130: aaload
     131: astore        5
     133: aload         5
     135: invokeinterface #18,  1           // InterfaceMethod io/reactivex/rxjava3/disposables/Disposable.dispose:()V
     140: iinc          4, 1
     143: goto          121
     146: iconst_0
     147: ireturn
    Exception table:
       from    to  target type
          18   100   106   any
         101   103   106   any
         106   110   106   any

  public boolean remove(io.reactivex.rxjava3.disposables.Disposable);
    Code:
       0: aload_0
       1: aload_1
       2: invokevirtual #19                 // Method delete:(Lio/reactivex/rxjava3/disposables/Disposable;)Z
       5: ifeq          16
       8: aload_1
       9: invokeinterface #18,  1           // InterfaceMethod io/reactivex/rxjava3/disposables/Disposable.dispose:()V
      14: iconst_1
      15: ireturn
      16: iconst_0
      17: ireturn

  public boolean delete(io.reactivex.rxjava3.disposables.Disposable);
    Code:
       0: aload_1
       1: ldc           #17                 // String disposable is null
       3: invokestatic  #3                  // Method java/util/Objects.requireNonNull:(Ljava/lang/Object;Ljava/lang/String;)Ljava/lang/Object;
       6: pop
       7: aload_0
       8: getfield      #15                 // Field disposed:Z
      11: ifeq          16
      14: iconst_0
      15: ireturn
      16: aload_0
      17: dup
      18: astore_2
      19: monitorenter
      20: aload_0
      21: getfield      #15                 // Field disposed:Z
      24: ifeq          31
      27: iconst_0
      28: aload_2
      29: monitorexit
      30: ireturn
      31: aload_0
      32: getfield      #6                  // Field resources:Lio/reactivex/rxjava3/internal/util/OpenHashSet;
      35: astore_3
      36: aload_3
      37: ifnull        48
      40: aload_3
      41: aload_1
      42: invokevirtual #20                 // Method io/reactivex/rxjava3/internal/util/OpenHashSet.remove:(Ljava/lang/Object;)Z
      45: ifne          52
      48: iconst_0
      49: aload_2
      50: monitorexit
      51: ireturn
      52: aload_2
      53: monitorexit
      54: goto          64
      57: astore        4
      59: aload_2
      60: monitorexit
      61: aload         4
      63: athrow
      64: iconst_1
      65: ireturn
    Exception table:
       from    to  target type
          20    30    57   any
          31    51    57   any
          52    54    57   any
          57    61    57   any

  public void clear();
    Code:
       0: aload_0
       1: getfield      #15                 // Field disposed:Z
       4: ifeq          8
       7: return
       8: aload_0
       9: dup
      10: astore_2
      11: monitorenter
      12: aload_0
      13: getfield      #15                 // Field disposed:Z
      16: ifeq          22
      19: aload_2
      20: monitorexit
      21: return
      22: aload_0
      23: getfield      #6                  // Field resources:Lio/reactivex/rxjava3/internal/util/OpenHashSet;
      26: astore_1
      27: aload_0
      28: aconst_null
      29: putfield      #6                  // Field resources:Lio/reactivex/rxjava3/internal/util/OpenHashSet;
      32: aload_2
      33: monitorexit
      34: goto          42
      37: astore_3
      38: aload_2
      39: monitorexit
      40: aload_3
      41: athrow
      42: aload_0
      43: aload_1
      44: invokevirtual #16                 // Method dispose:(Lio/reactivex/rxjava3/internal/util/OpenHashSet;)V
      47: return
    Exception table:
       from    to  target type
          12    21    37   any
          22    34    37   any
          37    40    37   any

  public int size();
    Code:
       0: aload_0
       1: getfield      #15                 // Field disposed:Z
       4: ifeq          9
       7: iconst_0
       8: ireturn
       9: aload_0
      10: dup
      11: astore_1
      12: monitorenter
      13: aload_0
      14: getfield      #15                 // Field disposed:Z
      17: ifeq          24
      20: iconst_0
      21: aload_1
      22: monitorexit
      23: ireturn
      24: aload_0
      25: getfield      #6                  // Field resources:Lio/reactivex/rxjava3/internal/util/OpenHashSet;
      28: astore_2
      29: aload_2
      30: ifnull        40
      33: aload_2
      34: invokevirtual #21                 // Method io/reactivex/rxjava3/internal/util/OpenHashSet.size:()I
      37: goto          41
      40: iconst_0
      41: aload_1
      42: monitorexit
      43: ireturn
      44: astore_3
      45: aload_1
      46: monitorexit
      47: aload_3
      48: athrow
    Exception table:
       from    to  target type
          13    23    44   any
          24    43    44   any
          44    47    44   any

  void dispose(io.reactivex.rxjava3.internal.util.OpenHashSet<io.reactivex.rxjava3.disposables.Disposable>);
    Code:
       0: aload_1
       1: ifnonnull     5
       4: return
       5: aconst_null
       6: astore_2
       7: aload_1
       8: invokevirtual #22                 // Method io/reactivex/rxjava3/internal/util/OpenHashSet.keys:()[Ljava/lang/Object;
      11: astore_3
      12: aload_3
      13: astore        4
      15: aload         4
      17: arraylength
      18: istore        5
      20: iconst_0
      21: istore        6
      23: iload         6
      25: iload         5
      27: if_icmpge     92
      30: aload         4
      32: iload         6
      34: aaload
      35: astore        7
      37: aload         7
      39: instanceof    #13                 // class io/reactivex/rxjava3/disposables/Disposable
      42: ifeq          86
      45: aload         7
      47: checkcast     #13                 // class io/reactivex/rxjava3/disposables/Disposable
      50: invokeinterface #18,  1           // InterfaceMethod io/reactivex/rxjava3/disposables/Disposable.dispose:()V
      55: goto          86
      58: astore        8
      60: aload         8
      62: invokestatic  #24                 // Method io/reactivex/rxjava3/exceptions/Exceptions.throwIfFatal:(Ljava/lang/Throwable;)V
      65: aload_2
      66: ifnonnull     77
      69: new           #25                 // class java/util/ArrayList
      72: dup
      73: invokespecial #26                 // Method java/util/ArrayList."<init>":()V
      76: astore_2
      77: aload_2
      78: aload         8
      80: invokeinterface #27,  2           // InterfaceMethod java/util/List.add:(Ljava/lang/Object;)Z
      85: pop
      86: iinc          6, 1
      89: goto          23
      92: aload_2
      93: ifnull        129
      96: aload_2
      97: invokeinterface #28,  1           // InterfaceMethod java/util/List.size:()I
     102: iconst_1
     103: if_icmpne     120
     106: aload_2
     107: iconst_0
     108: invokeinterface #29,  2           // InterfaceMethod java/util/List.get:(I)Ljava/lang/Object;
     113: checkcast     #23                 // class java/lang/Throwable
     116: invokestatic  #30                 // Method io/reactivex/rxjava3/internal/util/ExceptionHelper.wrapOrThrow:(Ljava/lang/Throwable;)Ljava/lang/RuntimeException;
     119: athrow
     120: new           #31                 // class io/reactivex/rxjava3/exceptions/CompositeException
     123: dup
     124: aload_2
     125: invokespecial #32                 // Method io/reactivex/rxjava3/exceptions/CompositeException."<init>":(Ljava/lang/Iterable;)V
     128: athrow
     129: return
    Exception table:
       from    to  target type
          45    55    58   Class java/lang/Throwable
}
