Compiled from "Disposable.java"
public interface io.reactivex.rxjava3.disposables.Disposable {
  public abstract void dispose();

  public abstract boolean isDisposed();

  public static io.reactivex.rxjava3.disposables.Disposable fromRunnable(java.lang.Runnable);
    Code:
       0: aload_0
       1: ldc           #1                  // String run is null
       3: invokestatic  #2                  // Method java/util/Objects.requireNonNull:(Ljava/lang/Object;Ljava/lang/String;)Ljava/lang/Object;
       6: pop
       7: new           #3                  // class io/reactivex/rxjava3/disposables/RunnableDisposable
      10: dup
      11: aload_0
      12: invokespecial #4                  // Method io/reactivex/rxjava3/disposables/RunnableDisposable."<init>":(Ljava/lang/Runnable;)V
      15: areturn

  public static io.reactivex.rxjava3.disposables.Disposable fromAction(io.reactivex.rxjava3.functions.Action);
    Code:
       0: aload_0
       1: ldc           #5                  // String action is null
       3: invokestatic  #2                  // Method java/util/Objects.requireNonNull:(Ljava/lang/Object;Ljava/lang/String;)Ljava/lang/Object;
       6: pop
       7: new           #6                  // class io/reactivex/rxjava3/disposables/ActionDisposable
      10: dup
      11: aload_0
      12: invokespecial #7                  // Method io/reactivex/rxjava3/disposables/ActionDisposable."<init>":(Lio/reactivex/rxjava3/functions/Action;)V
      15: areturn

  public static io.reactivex.rxjava3.disposables.Disposable fromFuture(java.util.concurrent.Future<?>);
    Code:
       0: aload_0
       1: ldc           #8                  // String future is null
       3: invokestatic  #2                  // Method java/util/Objects.requireNonNull:(Ljava/lang/Object;Ljava/lang/String;)Ljava/lang/Object;
       6: pop
       7: aload_0
       8: iconst_1
       9: invokestatic  #9                  // InterfaceMethod fromFuture:(Ljava/util/concurrent/Future;Z)Lio/reactivex/rxjava3/disposables/Disposable;
      12: areturn

  public static io.reactivex.rxjava3.disposables.Disposable fromFuture(java.util.concurrent.Future<?>, boolean);
    Code:
       0: aload_0
       1: ldc           #8                  // String future is null
       3: invokestatic  #2                  // Method java/util/Objects.requireNonNull:(Ljava/lang/Object;Ljava/lang/String;)Ljava/lang/Object;
       6: pop
       7: new           #10                 // class io/reactivex/rxjava3/disposables/FutureDisposable
      10: dup
      11: aload_0
      12: iload_1
      13: invokespecial #11                 // Method io/reactivex/rxjava3/disposables/FutureDisposable."<init>":(Ljava/util/concurrent/Future;Z)V
      16: areturn

  public static io.reactivex.rxjava3.disposables.Disposable fromSubscription(org.reactivestreams.Subscription);
    Code:
       0: aload_0
       1: ldc           #12                 // String subscription is null
       3: invokestatic  #2                  // Method java/util/Objects.requireNonNull:(Ljava/lang/Object;Ljava/lang/String;)Ljava/lang/Object;
       6: pop
       7: new           #13                 // class io/reactivex/rxjava3/disposables/SubscriptionDisposable
      10: dup
      11: aload_0
      12: invokespecial #14                 // Method io/reactivex/rxjava3/disposables/SubscriptionDisposable."<init>":(Lorg/reactivestreams/Subscription;)V
      15: areturn

  public static io.reactivex.rxjava3.disposables.Disposable fromAutoCloseable(java.lang.AutoCloseable);
    Code:
       0: aload_0
       1: ldc           #15                 // String autoCloseable is null
       3: invokestatic  #2                  // Method java/util/Objects.requireNonNull:(Ljava/lang/Object;Ljava/lang/String;)Ljava/lang/Object;
       6: pop
       7: new           #16                 // class io/reactivex/rxjava3/disposables/AutoCloseableDisposable
      10: dup
      11: aload_0
      12: invokespecial #17                 // Method io/reactivex/rxjava3/disposables/AutoCloseableDisposable."<init>":(Ljava/lang/AutoCloseable;)V
      15: areturn

  public static java.lang.AutoCloseable toAutoCloseable(io.reactivex.rxjava3.disposables.Disposable);
    Code:
       0: aload_0
       1: ldc           #18                 // String disposable is null
       3: invokestatic  #2                  // Method java/util/Objects.requireNonNull:(Ljava/lang/Object;Ljava/lang/String;)Ljava/lang/Object;
       6: pop
       7: aload_0
       8: dup
       9: invokevirtual #19                 // Method java/lang/Object.getClass:()Ljava/lang/Class;
      12: pop
      13: invokedynamic #20,  0             // InvokeDynamic #0:close:(Lio/reactivex/rxjava3/disposables/Disposable;)Ljava/lang/AutoCloseable;
      18: areturn

  public static io.reactivex.rxjava3.disposables.Disposable empty();
    Code:
       0: getstatic     #21                 // Field io/reactivex/rxjava3/internal/functions/Functions.EMPTY_RUNNABLE:Ljava/lang/Runnable;
       3: invokestatic  #22                 // InterfaceMethod fromRunnable:(Ljava/lang/Runnable;)Lio/reactivex/rxjava3/disposables/Disposable;
       6: areturn

  public static io.reactivex.rxjava3.disposables.Disposable disposed();
    Code:
       0: getstatic     #23                 // Field io/reactivex/rxjava3/internal/disposables/EmptyDisposable.INSTANCE:Lio/reactivex/rxjava3/internal/disposables/EmptyDisposable;
       3: areturn
}
