Compiled from "RunnableDisposable.java"
final class io.reactivex.rxjava3.disposables.RunnableDisposable extends io.reactivex.rxjava3.disposables.ReferenceDisposable<java.lang.Runnable> {
  private static final long serialVersionUID;

  io.reactivex.rxjava3.disposables.RunnableDisposable(java.lang.Runnable);
    Code:
       0: aload_0
       1: aload_1
       2: invokespecial #1                  // Method io/reactivex/rxjava3/disposables/ReferenceDisposable."<init>":(Ljava/lang/Object;)V
       5: return

  protected void onDisposed(java.lang.Runnable);
    Code:
       0: aload_1
       1: invokeinterface #2,  1            // InterfaceMethod java/lang/Runnable.run:()V
       6: return

  public java.lang.String toString();
    Code:
       0: new           #3                  // class java/lang/StringBuilder
       3: dup
       4: invokespecial #4                  // Method java/lang/StringBuilder."<init>":()V
       7: ldc           #5                  // String RunnableDisposable(disposed=
       9: invokevirtual #6                  // Method java/lang/StringBuilder.append:(Ljava/lang/String;)Ljava/lang/StringBuilder;
      12: aload_0
      13: invokevirtual #7                  // Method isDisposed:()Z
      16: invokevirtual #8                  // Method java/lang/StringBuilder.append:(Z)Ljava/lang/StringBuilder;
      19: ldc           #9                  // String ,
      21: invokevirtual #6                  // Method java/lang/StringBuilder.append:(Ljava/lang/String;)Ljava/lang/StringBuilder;
      24: aload_0
      25: invokevirtual #10                 // Method get:()Ljava/lang/Object;
      28: invokevirtual #11                 // Method java/lang/StringBuilder.append:(Ljava/lang/Object;)Ljava/lang/StringBuilder;
      31: ldc           #12                 // String )
      33: invokevirtual #6                  // Method java/lang/StringBuilder.append:(Ljava/lang/String;)Ljava/lang/StringBuilder;
      36: invokevirtual #13                 // Method java/lang/StringBuilder.toString:()Ljava/lang/String;
      39: areturn

  protected void onDisposed(java.lang.Object);
    Code:
       0: aload_0
       1: aload_1
       2: checkcast     #14                 // class java/lang/Runnable
       5: invokevirtual #15                 // Method onDisposed:(Ljava/lang/Runnable;)V
       8: return
}
