Compiled from "SerialDisposable.java"
public final class io.reactivex.rxjava3.disposables.SerialDisposable implements io.reactivex.rxjava3.disposables.Disposable {
  final java.util.concurrent.atomic.AtomicReference<io.reactivex.rxjava3.disposables.Disposable> resource;

  public io.reactivex.rxjava3.disposables.SerialDisposable();
    Code:
       0: aload_0
       1: invokespecial #1                  // Method java/lang/Object."<init>":()V
       4: aload_0
       5: new           #2                  // class java/util/concurrent/atomic/AtomicReference
       8: dup
       9: invokespecial #3                  // Method java/util/concurrent/atomic/AtomicReference."<init>":()V
      12: putfield      #4                  // Field resource:Ljava/util/concurrent/atomic/AtomicReference;
      15: return

  public io.reactivex.rxjava3.disposables.SerialDisposable(io.reactivex.rxjava3.disposables.Disposable);
    Code:
       0: aload_0
       1: invokespecial #1                  // Method java/lang/Object."<init>":()V
       4: aload_0
       5: new           #2                  // class java/util/concurrent/atomic/AtomicReference
       8: dup
       9: aload_1
      10: invokespecial #5                  // Method java/util/concurrent/atomic/AtomicReference."<init>":(Ljava/lang/Object;)V
      13: putfield      #4                  // Field resource:Ljava/util/concurrent/atomic/AtomicReference;
      16: return

  public boolean set(io.reactivex.rxjava3.disposables.Disposable);
    Code:
       0: aload_0
       1: getfield      #4                  // Field resource:Ljava/util/concurrent/atomic/AtomicReference;
       4: aload_1
       5: invokestatic  #6                  // Method io/reactivex/rxjava3/internal/disposables/DisposableHelper.set:(Ljava/util/concurrent/atomic/AtomicReference;Lio/reactivex/rxjava3/disposables/Disposable;)Z
       8: ireturn

  public boolean replace(io.reactivex.rxjava3.disposables.Disposable);
    Code:
       0: aload_0
       1: getfield      #4                  // Field resource:Ljava/util/concurrent/atomic/AtomicReference;
       4: aload_1
       5: invokestatic  #7                  // Method io/reactivex/rxjava3/internal/disposables/DisposableHelper.replace:(Ljava/util/concurrent/atomic/AtomicReference;Lio/reactivex/rxjava3/disposables/Disposable;)Z
       8: ireturn

  public io.reactivex.rxjava3.disposables.Disposable get();
    Code:
       0: aload_0
       1: getfield      #4                  // Field resource:Ljava/util/concurrent/atomic/AtomicReference;
       4: invokevirtual #8                  // Method java/util/concurrent/atomic/AtomicReference.get:()Ljava/lang/Object;
       7: checkcast     #9                  // class io/reactivex/rxjava3/disposables/Disposable
      10: astore_1
      11: aload_1
      12: getstatic     #10                 // Field io/reactivex/rxjava3/internal/disposables/DisposableHelper.DISPOSED:Lio/reactivex/rxjava3/internal/disposables/DisposableHelper;
      15: if_acmpne     22
      18: invokestatic  #11                 // InterfaceMethod io/reactivex/rxjava3/disposables/Disposable.disposed:()Lio/reactivex/rxjava3/disposables/Disposable;
      21: areturn
      22: aload_1
      23: areturn

  public void dispose();
    Code:
       0: aload_0
       1: getfield      #4                  // Field resource:Ljava/util/concurrent/atomic/AtomicReference;
       4: invokestatic  #12                 // Method io/reactivex/rxjava3/internal/disposables/DisposableHelper.dispose:(Ljava/util/concurrent/atomic/AtomicReference;)Z
       7: pop
       8: return

  public boolean isDisposed();
    Code:
       0: aload_0
       1: getfield      #4                  // Field resource:Ljava/util/concurrent/atomic/AtomicReference;
       4: invokevirtual #8                  // Method java/util/concurrent/atomic/AtomicReference.get:()Ljava/lang/Object;
       7: checkcast     #9                  // class io/reactivex/rxjava3/disposables/Disposable
      10: invokestatic  #13                 // Method io/reactivex/rxjava3/internal/disposables/DisposableHelper.isDisposed:(Lio/reactivex/rxjava3/disposables/Disposable;)Z
      13: ireturn
}
