Compiled from "SubscriptionDisposable.java"
final class io.reactivex.rxjava3.disposables.SubscriptionDisposable extends io.reactivex.rxjava3.disposables.ReferenceDisposable<org.reactivestreams.Subscription> {
  private static final long serialVersionUID;

  io.reactivex.rxjava3.disposables.SubscriptionDisposable(org.reactivestreams.Subscription);
    Code:
       0: aload_0
       1: aload_1
       2: invokespecial #1                  // Method io/reactivex/rxjava3/disposables/ReferenceDisposable."<init>":(Ljava/lang/Object;)V
       5: return

  protected void onDisposed(org.reactivestreams.Subscription);
    Code:
       0: aload_1
       1: invokeinterface #2,  1            // InterfaceMethod org/reactivestreams/Subscription.cancel:()V
       6: return

  protected void onDisposed(java.lang.Object);
    Code:
       0: aload_0
       1: aload_1
       2: checkcast     #3                  // class org/reactivestreams/Subscription
       5: invokevirtual #4                  // Method onDisposed:(Lorg/reactivestreams/Subscription;)V
       8: return
}
