Compiled from "ScopeBeanExtensionInjector.java"
public class org.apache.dubbo.common.beans.ScopeBeanExtensionInjector implements org.apache.dubbo.common.extension.ExtensionInjector,org.apache.dubbo.rpc.model.ScopeModelAware {
  private org.apache.dubbo.common.beans.factory.ScopeBeanFactory beanFactory;

  public org.apache.dubbo.common.beans.ScopeBeanExtensionInjector();
    Code:
       0: aload_0
       1: invokespecial #1                  // Method java/lang/Object."<init>":()V
       4: return

  public void setScopeModel(org.apache.dubbo.rpc.model.ScopeModel);
    Code:
       0: aload_0
       1: aload_1
       2: invokevirtual #2                  // Method org/apache/dubbo/rpc/model/ScopeModel.getBeanFactory:()Lorg/apache/dubbo/common/beans/factory/ScopeBeanFactory;
       5: putfield      #3                  // Field beanFactory:Lorg/apache/dubbo/common/beans/factory/ScopeBeanFactory;
       8: return

  public <T> T getInstance(java.lang.Class<T>, java.lang.String);
    Code:
       0: aload_0
       1: getfield      #3                  // Field beanFactory:Lorg/apache/dubbo/common/beans/factory/ScopeBeanFactory;
       4: ifnonnull     11
       7: aconst_null
       8: goto          20
      11: aload_0
      12: getfield      #3                  // Field beanFactory:Lorg/apache/dubbo/common/beans/factory/ScopeBeanFactory;
      15: aload_2
      16: aload_1
      17: invokevirtual #4                  // Method org/apache/dubbo/common/beans/factory/ScopeBeanFactory.getBean:(Ljava/lang/String;Ljava/lang/Class;)Ljava/lang/Object;
      20: areturn
}
