Compiled from "ConnectorStartFailureAnalyzer.java"
class org.springframework.boot.web.embedded.tomcat.ConnectorStartFailureAnalyzer extends org.springframework.boot.diagnostics.AbstractFailureAnalyzer<org.springframework.boot.web.embedded.tomcat.ConnectorStartFailedException> {
  org.springframework.boot.web.embedded.tomcat.ConnectorStartFailureAnalyzer();
    Code:
       0: aload_0
       1: invokespecial #1                  // Method org/springframework/boot/diagnostics/AbstractFailureAnalyzer."<init>":()V
       4: return

  protected org.springframework.boot.diagnostics.FailureAnalysis analyze(java.lang.Throwable, org.springframework.boot.web.embedded.tomcat.ConnectorStartFailedException);
    Code:
       0: new           #7                  // class org/springframework/boot/diagnostics/FailureAnalysis
       3: dup
       4: aload_2
       5: invokevirtual #9                  // Method org/springframework/boot/web/embedded/tomcat/ConnectorStartFailedException.getPort:()I
       8: invokedynamic #15,  0             // InvokeDynamic #0:makeConcatWithConstants:(I)Ljava/lang/String;
      13: aload_2
      14: invokevirtual #9                  // Method org/springframework/boot/web/embedded/tomcat/ConnectorStartFailedException.getPort:()I
      17: invokedynamic #19,  0             // InvokeDynamic #1:makeConcatWithConstants:(I)Ljava/lang/String;
      22: aload_2
      23: invokespecial #20                 // Method org/springframework/boot/diagnostics/FailureAnalysis."<init>":(Ljava/lang/String;Ljava/lang/String;Ljava/lang/Throwable;)V
      26: areturn

  protected org.springframework.boot.diagnostics.FailureAnalysis analyze(java.lang.Throwable, java.lang.Throwable);
    Code:
       0: aload_0
       1: aload_1
       2: aload_2
       3: checkcast     #10                 // class org/springframework/boot/web/embedded/tomcat/ConnectorStartFailedException
       6: invokevirtual #23                 // Method analyze:(Ljava/lang/Throwable;Lorg/springframework/boot/web/embedded/tomcat/ConnectorStartFailedException;)Lorg/springframework/boot/diagnostics/FailureAnalysis;
       9: areturn
}
