Compiled from "DisableReferenceClearingContextCustomizer.java"
class org.springframework.boot.web.embedded.tomcat.DisableReferenceClearingContextCustomizer implements org.springframework.boot.web.embedded.tomcat.TomcatContextCustomizer {
  org.springframework.boot.web.embedded.tomcat.DisableReferenceClearingContextCustomizer();
    Code:
       0: aload_0
       1: invokespecial #1                  // Method java/lang/Object."<init>":()V
       4: return

  public void customize(org.apache.catalina.Context);
    Code:
       0: aload_1
       1: instanceof    #7                  // class org/apache/catalina/core/StandardContext
       4: ifeq          15
       7: aload_1
       8: checkcast     #7                  // class org/apache/catalina/core/StandardContext
      11: astore_2
      12: goto          16
      15: return
      16: aload_2
      17: iconst_0
      18: invokevirtual #9                  // Method org/apache/catalina/core/StandardContext.setClearReferencesObjectStreamClassCaches:(Z)V
      21: aload_2
      22: iconst_0
      23: invokevirtual #13                 // Method org/apache/catalina/core/StandardContext.setClearReferencesRmiTargets:(Z)V
      26: aload_2
      27: iconst_0
      28: invokevirtual #16                 // Method org/apache/catalina/core/StandardContext.setClearReferencesThreadLocals:(Z)V
      31: goto          35
      34: astore_3
      35: return
    Exception table:
       from    to  target type
          16    31    34   Class java/lang/NoSuchMethodError
}
