Compiled from "SslConnectorCustomizer.java"
class org.springframework.boot.web.embedded.tomcat.SslConnectorCustomizer implements org.springframework.boot.web.embedded.tomcat.TomcatConnectorCustomizer {
  private final org.springframework.boot.web.server.Ssl$ClientAuth clientAuth;

  private final org.springframework.boot.ssl.SslBundle sslBundle;

  org.springframework.boot.web.embedded.tomcat.SslConnectorCustomizer(org.springframework.boot.web.server.Ssl$ClientAuth, org.springframework.boot.ssl.SslBundle);
    Code:
       0: aload_0
       1: invokespecial #1                  // Method java/lang/Object."<init>":()V
       4: aload_0
       5: aload_1
       6: putfield      #7                  // Field clientAuth:Lorg/springframework/boot/web/server/Ssl$ClientAuth;
       9: aload_0
      10: aload_2
      11: putfield      #13                 // Field sslBundle:Lorg/springframework/boot/ssl/SslBundle;
      14: return

  public void customize(org.apache.catalina.connector.Connector);
    Code:
       0: aload_1
       1: invokevirtual #17                 // Method org/apache/catalina/connector/Connector.getProtocolHandler:()Lorg/apache/coyote/ProtocolHandler;
       4: astore_2
       5: aload_2
       6: instanceof    #23                 // class org/apache/coyote/http11/AbstractHttp11JsseProtocol
       9: ldc           #25                 // String To use SSL, the connector\'s protocol handler must be an AbstractHttp11JsseProtocol subclass
      11: invokestatic  #27                 // Method org/springframework/util/Assert.state:(ZLjava/lang/String;)V
      14: aload_0
      15: aload_2
      16: checkcast     #23                 // class org/apache/coyote/http11/AbstractHttp11JsseProtocol
      19: invokevirtual #33                 // Method configureSsl:(Lorg/apache/coyote/http11/AbstractHttp11JsseProtocol;)V
      22: aload_1
      23: ldc           #37                 // String https
      25: invokevirtual #39                 // Method org/apache/catalina/connector/Connector.setScheme:(Ljava/lang/String;)V
      28: aload_1
      29: iconst_1
      30: invokevirtual #43                 // Method org/apache/catalina/connector/Connector.setSecure:(Z)V
      33: return

  void configureSsl(org.apache.coyote.http11.AbstractHttp11JsseProtocol<?>);
    Code:
       0: aload_0
       1: getfield      #13                 // Field sslBundle:Lorg/springframework/boot/ssl/SslBundle;
       4: invokeinterface #47,  1           // InterfaceMethod org/springframework/boot/ssl/SslBundle.getKey:()Lorg/springframework/boot/ssl/SslBundleKey;
       9: astore_2
      10: aload_0
      11: getfield      #13                 // Field sslBundle:Lorg/springframework/boot/ssl/SslBundle;
      14: invokeinterface #53,  1           // InterfaceMethod org/springframework/boot/ssl/SslBundle.getStores:()Lorg/springframework/boot/ssl/SslStoreBundle;
      19: astore_3
      20: aload_0
      21: getfield      #13                 // Field sslBundle:Lorg/springframework/boot/ssl/SslBundle;
      24: invokeinterface #57,  1           // InterfaceMethod org/springframework/boot/ssl/SslBundle.getOptions:()Lorg/springframework/boot/ssl/SslOptions;
      29: astore        4
      31: aload_1
      32: iconst_1
      33: invokevirtual #61                 // Method org/apache/coyote/http11/AbstractHttp11JsseProtocol.setSSLEnabled:(Z)V
      36: new           #64                 // class org/apache/tomcat/util/net/SSLHostConfig
      39: dup
      40: invokespecial #66                 // Method org/apache/tomcat/util/net/SSLHostConfig."<init>":()V
      43: astore        5
      45: aload         5
      47: aload_1
      48: invokevirtual #67                 // Method org/apache/coyote/http11/AbstractHttp11JsseProtocol.getDefaultSSLHostConfigName:()Ljava/lang/String;
      51: invokevirtual #71                 // Method org/apache/tomcat/util/net/SSLHostConfig.setHostName:(Ljava/lang/String;)V
      54: aload         5
      56: aload_0
      57: getfield      #13                 // Field sslBundle:Lorg/springframework/boot/ssl/SslBundle;
      60: invokeinterface #74,  1           // InterfaceMethod org/springframework/boot/ssl/SslBundle.getProtocol:()Ljava/lang/String;
      65: invokevirtual #77                 // Method org/apache/tomcat/util/net/SSLHostConfig.setSslProtocol:(Ljava/lang/String;)V
      68: aload_1
      69: aload         5
      71: invokevirtual #80                 // Method org/apache/coyote/http11/AbstractHttp11JsseProtocol.addSslHostConfig:(Lorg/apache/tomcat/util/net/SSLHostConfig;)V
      74: aload_0
      75: aload         5
      77: invokevirtual #84                 // Method configureSslClientAuth:(Lorg/apache/tomcat/util/net/SSLHostConfig;)V
      80: new           #87                 // class org/apache/tomcat/util/net/SSLHostConfigCertificate
      83: dup
      84: aload         5
      86: getstatic     #89                 // Field org/apache/tomcat/util/net/SSLHostConfigCertificate$Type.UNDEFINED:Lorg/apache/tomcat/util/net/SSLHostConfigCertificate$Type;
      89: invokespecial #95                 // Method org/apache/tomcat/util/net/SSLHostConfigCertificate."<init>":(Lorg/apache/tomcat/util/net/SSLHostConfig;Lorg/apache/tomcat/util/net/SSLHostConfigCertificate$Type;)V
      92: astore        6
      94: aload_3
      95: invokeinterface #98,  1           // InterfaceMethod org/springframework/boot/ssl/SslStoreBundle.getKeyStorePassword:()Ljava/lang/String;
     100: ifnull        112
     103: aload_3
     104: invokeinterface #98,  1           // InterfaceMethod org/springframework/boot/ssl/SslStoreBundle.getKeyStorePassword:()Ljava/lang/String;
     109: goto          114
     112: ldc           #103                // String
     114: astore        7
     116: aload         6
     118: aload         7
     120: invokevirtual #105                // Method org/apache/tomcat/util/net/SSLHostConfigCertificate.setCertificateKeystorePassword:(Ljava/lang/String;)V
     123: aload_2
     124: invokeinterface #108,  1          // InterfaceMethod org/springframework/boot/ssl/SslBundleKey.getPassword:()Ljava/lang/String;
     129: ifnull        143
     132: aload         6
     134: aload_2
     135: invokeinterface #108,  1          // InterfaceMethod org/springframework/boot/ssl/SslBundleKey.getPassword:()Ljava/lang/String;
     140: invokevirtual #113                // Method org/apache/tomcat/util/net/SSLHostConfigCertificate.setCertificateKeyPassword:(Ljava/lang/String;)V
     143: aload_2
     144: invokeinterface #116,  1          // InterfaceMethod org/springframework/boot/ssl/SslBundleKey.getAlias:()Ljava/lang/String;
     149: ifnull        163
     152: aload         6
     154: aload_2
     155: invokeinterface #116,  1          // InterfaceMethod org/springframework/boot/ssl/SslBundleKey.getAlias:()Ljava/lang/String;
     160: invokevirtual #119                // Method org/apache/tomcat/util/net/SSLHostConfigCertificate.setCertificateKeyAlias:(Ljava/lang/String;)V
     163: aload         5
     165: aload         6
     167: invokevirtual #122                // Method org/apache/tomcat/util/net/SSLHostConfig.addCertificate:(Lorg/apache/tomcat/util/net/SSLHostConfigCertificate;)V
     170: aload         4
     172: invokeinterface #126,  1          // InterfaceMethod org/springframework/boot/ssl/SslOptions.getCiphers:()[Ljava/lang/String;
     177: ifnull        199
     180: aload         4
     182: invokeinterface #126,  1          // InterfaceMethod org/springframework/boot/ssl/SslOptions.getCiphers:()[Ljava/lang/String;
     187: invokestatic  #132                // Method org/springframework/util/StringUtils.arrayToCommaDelimitedString:([Ljava/lang/Object;)Ljava/lang/String;
     190: astore        8
     192: aload         5
     194: aload         8
     196: invokevirtual #138                // Method org/apache/tomcat/util/net/SSLHostConfig.setCiphers:(Ljava/lang/String;)V
     199: aload_0
     200: aload_1
     201: invokevirtual #141                // Method configureEnabledProtocols:(Lorg/apache/coyote/http11/AbstractHttp11JsseProtocol;)V
     204: aload_0
     205: aload_1
     206: aload         5
     208: aload         6
     210: invokevirtual #144                // Method configureSslStoreProvider:(Lorg/apache/coyote/http11/AbstractHttp11JsseProtocol;Lorg/apache/tomcat/util/net/SSLHostConfig;Lorg/apache/tomcat/util/net/SSLHostConfigCertificate;)V
     213: return

  private void configureEnabledProtocols(org.apache.coyote.http11.AbstractHttp11JsseProtocol<?>);
    Code:
       0: aload_0
       1: getfield      #13                 // Field sslBundle:Lorg/springframework/boot/ssl/SslBundle;
       4: invokeinterface #57,  1           // InterfaceMethod org/springframework/boot/ssl/SslBundle.getOptions:()Lorg/springframework/boot/ssl/SslOptions;
       9: astore_2
      10: aload_2
      11: invokeinterface #148,  1          // InterfaceMethod org/springframework/boot/ssl/SslOptions.getEnabledProtocols:()[Ljava/lang/String;
      16: ifnull        69
      19: aload_2
      20: invokeinterface #148,  1          // InterfaceMethod org/springframework/boot/ssl/SslOptions.getEnabledProtocols:()[Ljava/lang/String;
      25: invokestatic  #132                // Method org/springframework/util/StringUtils.arrayToCommaDelimitedString:([Ljava/lang/Object;)Ljava/lang/String;
      28: astore_3
      29: aload_1
      30: invokevirtual #151                // Method org/apache/coyote/http11/AbstractHttp11JsseProtocol.findSslHostConfigs:()[Lorg/apache/tomcat/util/net/SSLHostConfig;
      33: astore        4
      35: aload         4
      37: arraylength
      38: istore        5
      40: iconst_0
      41: istore        6
      43: iload         6
      45: iload         5
      47: if_icmpge     69
      50: aload         4
      52: iload         6
      54: aaload
      55: astore        7
      57: aload         7
      59: aload_3
      60: invokevirtual #155                // Method org/apache/tomcat/util/net/SSLHostConfig.setProtocols:(Ljava/lang/String;)V
      63: iinc          6, 1
      66: goto          43
      69: return

  private void configureSslClientAuth(org.apache.tomcat.util.net.SSLHostConfig);
    Code:
       0: aload_1
       1: aload_0
       2: getfield      #7                  // Field clientAuth:Lorg/springframework/boot/web/server/Ssl$ClientAuth;
       5: ldc           #158                // String none
       7: ldc           #160                // String optional
       9: ldc           #162                // String required
      11: invokestatic  #164                // Method org/springframework/boot/web/server/Ssl$ClientAuth.map:(Lorg/springframework/boot/web/server/Ssl$ClientAuth;Ljava/lang/Object;Ljava/lang/Object;Ljava/lang/Object;)Ljava/lang/Object;
      14: checkcast     #170                // class java/lang/String
      17: invokevirtual #172                // Method org/apache/tomcat/util/net/SSLHostConfig.setCertificateVerification:(Ljava/lang/String;)V
      20: return

  protected void configureSslStoreProvider(org.apache.coyote.http11.AbstractHttp11JsseProtocol<?>, org.apache.tomcat.util.net.SSLHostConfig, org.apache.tomcat.util.net.SSLHostConfigCertificate);
    Code:
       0: ldc           #175                // class org/apache/coyote/http11/Http11NioProtocol
       2: aload_1
       3: ldc           #177                // String SslStoreProvider can only be used with Http11NioProtocol
       5: invokestatic  #179                // Method org/springframework/util/Assert.isInstanceOf:(Ljava/lang/Class;Ljava/lang/Object;Ljava/lang/String;)V
       8: aload_0
       9: getfield      #13                 // Field sslBundle:Lorg/springframework/boot/ssl/SslBundle;
      12: invokeinterface #53,  1           // InterfaceMethod org/springframework/boot/ssl/SslBundle.getStores:()Lorg/springframework/boot/ssl/SslStoreBundle;
      17: astore        4
      19: aload         4
      21: invokeinterface #183,  1          // InterfaceMethod org/springframework/boot/ssl/SslStoreBundle.getKeyStore:()Ljava/security/KeyStore;
      26: ifnull        40
      29: aload_3
      30: aload         4
      32: invokeinterface #183,  1          // InterfaceMethod org/springframework/boot/ssl/SslStoreBundle.getKeyStore:()Ljava/security/KeyStore;
      37: invokevirtual #187                // Method org/apache/tomcat/util/net/SSLHostConfigCertificate.setCertificateKeystore:(Ljava/security/KeyStore;)V
      40: aload         4
      42: invokeinterface #191,  1          // InterfaceMethod org/springframework/boot/ssl/SslStoreBundle.getTrustStore:()Ljava/security/KeyStore;
      47: ifnull        61
      50: aload_2
      51: aload         4
      53: invokeinterface #191,  1          // InterfaceMethod org/springframework/boot/ssl/SslStoreBundle.getTrustStore:()Ljava/security/KeyStore;
      58: invokevirtual #194                // Method org/apache/tomcat/util/net/SSLHostConfig.setTrustStore:(Ljava/security/KeyStore;)V
      61: goto          86
      64: astore        4
      66: new           #199                // class java/lang/IllegalStateException
      69: dup
      70: aload         4
      72: invokevirtual #201                // Method java/lang/Exception.getMessage:()Ljava/lang/String;
      75: invokedynamic #204,  0            // InvokeDynamic #0:makeConcatWithConstants:(Ljava/lang/String;)Ljava/lang/String;
      80: aload         4
      82: invokespecial #208                // Method java/lang/IllegalStateException."<init>":(Ljava/lang/String;Ljava/lang/Throwable;)V
      85: athrow
      86: return
    Exception table:
       from    to  target type
           8    61    64   Class java/lang/Exception
}
