Compiled from "TomcatServletWebServerFactory.java"
final class org.springframework.boot.web.embedded.tomcat.TomcatServletWebServerFactory$StaticResourceConfigurer implements org.apache.catalina.LifecycleListener {
  private final org.apache.catalina.Context context;

  final org.springframework.boot.web.embedded.tomcat.TomcatServletWebServerFactory this$0;

  private org.springframework.boot.web.embedded.tomcat.TomcatServletWebServerFactory$StaticResourceConfigurer(org.springframework.boot.web.embedded.tomcat.TomcatServletWebServerFactory, org.apache.catalina.Context);
    Code:
       0: aload_0
       1: aload_1
       2: putfield      #1                  // Field this$0:Lorg/springframework/boot/web/embedded/tomcat/TomcatServletWebServerFactory;
       5: aload_0
       6: invokespecial #7                  // Method java/lang/Object."<init>":()V
       9: aload_0
      10: aload_2
      11: putfield      #13                 // Field context:Lorg/apache/catalina/Context;
      14: return

  public void lifecycleEvent(org.apache.catalina.LifecycleEvent);
    Code:
       0: aload_1
       1: invokevirtual #17                 // Method org/apache/catalina/LifecycleEvent.getType:()Ljava/lang/String;
       4: ldc           #25                 // String configure_start
       6: invokevirtual #27                 // Method java/lang/String.equals:(Ljava/lang/Object;)Z
       9: ifeq          23
      12: aload_0
      13: aload_0
      14: getfield      #1                  // Field this$0:Lorg/springframework/boot/web/embedded/tomcat/TomcatServletWebServerFactory;
      17: invokestatic  #33                 // Method org/springframework/boot/web/embedded/tomcat/TomcatServletWebServerFactory.access$000:(Lorg/springframework/boot/web/embedded/tomcat/TomcatServletWebServerFactory;)Ljava/util/List;
      20: invokevirtual #39                 // Method addResourceJars:(Ljava/util/List;)V
      23: return

  private void addResourceJars(java.util.List<java.net.URL>);
    Code:
       0: aload_1
       1: invokeinterface #43,  1           // InterfaceMethod java/util/List.iterator:()Ljava/util/Iterator;
       6: astore_2
       7: aload_2
       8: invokeinterface #49,  1           // InterfaceMethod java/util/Iterator.hasNext:()Z
      13: ifeq          97
      16: aload_2
      17: invokeinterface #55,  1           // InterfaceMethod java/util/Iterator.next:()Ljava/lang/Object;
      22: checkcast     #59                 // class java/net/URL
      25: astore_3
      26: aload_3
      27: invokevirtual #61                 // Method java/net/URL.getPath:()Ljava/lang/String;
      30: astore        4
      32: aload         4
      34: ldc           #64                 // String .jar
      36: invokevirtual #66                 // Method java/lang/String.endsWith:(Ljava/lang/String;)Z
      39: ifne          52
      42: aload         4
      44: ldc           #70                 // String .jar!/
      46: invokevirtual #66                 // Method java/lang/String.endsWith:(Ljava/lang/String;)Z
      49: ifeq          86
      52: aload_3
      53: invokevirtual #72                 // Method java/net/URL.toString:()Ljava/lang/String;
      56: astore        5
      58: aload         5
      60: ldc           #75                 // String jar:
      62: invokevirtual #77                 // Method java/lang/String.startsWith:(Ljava/lang/String;)Z
      65: ifne          77
      68: aload         5
      70: invokedynamic #80,  0             // InvokeDynamic #0:makeConcatWithConstants:(Ljava/lang/String;)Ljava/lang/String;
      75: astore        5
      77: aload_0
      78: aload         5
      80: invokevirtual #84                 // Method addResourceSet:(Ljava/lang/String;)V
      83: goto          94
      86: aload_0
      87: aload_3
      88: invokevirtual #72                 // Method java/net/URL.toString:()Ljava/lang/String;
      91: invokevirtual #84                 // Method addResourceSet:(Ljava/lang/String;)V
      94: goto          7
      97: return

  private void addResourceSet(java.lang.String);
    Code:
       0: aload_0
       1: aload_1
       2: invokevirtual #88                 // Method isInsideNestedJar:(Ljava/lang/String;)Z
       5: ifeq          20
       8: aload_1
       9: iconst_0
      10: aload_1
      11: invokevirtual #91                 // Method java/lang/String.length:()I
      14: iconst_2
      15: isub
      16: invokevirtual #95                 // Method java/lang/String.substring:(II)Ljava/lang/String;
      19: astore_1
      20: new           #59                 // class java/net/URL
      23: dup
      24: aload_1
      25: invokespecial #99                 // Method java/net/URL."<init>":(Ljava/lang/String;)V
      28: astore_2
      29: ldc           #101                // String /META-INF/resources
      31: astore_3
      32: aload_0
      33: getfield      #13                 // Field context:Lorg/apache/catalina/Context;
      36: invokeinterface #103,  1          // InterfaceMethod org/apache/catalina/Context.getResources:()Lorg/apache/catalina/WebResourceRoot;
      41: getstatic     #109                // Field org/apache/catalina/WebResourceRoot$ResourceSetType.RESOURCE_JAR:Lorg/apache/catalina/WebResourceRoot$ResourceSetType;
      44: ldc           #115                // String /
      46: aload_2
      47: aload_3
      48: invokeinterface #117,  5          // InterfaceMethod org/apache/catalina/WebResourceRoot.createWebResourceSet:(Lorg/apache/catalina/WebResourceRoot$ResourceSetType;Ljava/lang/String;Ljava/net/URL;Ljava/lang/String;)V
      53: goto          57
      56: astore_2
      57: return
    Exception table:
       from    to  target type
           0    53    56   Class java/lang/Exception

  private boolean isInsideNestedJar(java.lang.String);
    Code:
       0: aload_1
       1: ldc           #125                // String !/
       3: invokevirtual #127                // Method java/lang/String.indexOf:(Ljava/lang/String;)I
       6: aload_1
       7: ldc           #125                // String !/
       9: invokevirtual #131                // Method java/lang/String.lastIndexOf:(Ljava/lang/String;)I
      12: if_icmpge     19
      15: iconst_1
      16: goto          20
      19: iconst_0
      20: ireturn
}
