Compiled from "TomcatServletWebServerFactory.java"
final class org.springframework.boot.web.embedded.tomcat.TomcatServletWebServerFactory$LoaderHidingResourceRoot extends org.apache.catalina.webresources.StandardRoot {
  private org.springframework.boot.web.embedded.tomcat.TomcatServletWebServerFactory$LoaderHidingResourceRoot(org.springframework.boot.web.embedded.tomcat.TomcatEmbeddedContext);
    Code:
       0: aload_0
       1: aload_1
       2: invokespecial #1                  // Method org/apache/catalina/webresources/StandardRoot."<init>":(Lorg/apache/catalina/Context;)V
       5: return

  protected org.apache.catalina.WebResourceSet createMainResourceSet();
    Code:
       0: new           #7                  // class org/springframework/boot/web/embedded/tomcat/TomcatServletWebServerFactory$LoaderHidingWebResourceSet
       3: dup
       4: aload_0
       5: invokespecial #9                  // Method org/apache/catalina/webresources/StandardRoot.createMainResourceSet:()Lorg/apache/catalina/WebResourceSet;
       8: invokespecial #13                 // Method org/springframework/boot/web/embedded/tomcat/TomcatServletWebServerFactory$LoaderHidingWebResourceSet."<init>":(Lorg/apache/catalina/WebResourceSet;)V
      11: areturn
}
