Compiled from "TomcatEmbeddedContext.java"
class org.springframework.boot.web.embedded.tomcat.TomcatEmbeddedContext extends org.apache.catalina.core.StandardContext {
  private org.springframework.boot.web.embedded.tomcat.TomcatStarter starter;

  private org.springframework.boot.web.server.MimeMappings mimeMappings;

  org.springframework.boot.web.embedded.tomcat.TomcatEmbeddedContext();
    Code:
       0: aload_0
       1: invokespecial #1                  // Method org/apache/catalina/core/StandardContext."<init>":()V
       4: return

  public boolean loadOnStartup(org.apache.catalina.Container[]);
    Code:
       0: iconst_1
       1: ireturn

  public void setManager(org.apache.catalina.Manager);
    Code:
       0: aload_1
       1: instanceof    #7                  // class org/apache/catalina/session/ManagerBase
       4: ifeq          20
       7: aload_1
       8: new           #9                  // class org/springframework/boot/web/embedded/tomcat/LazySessionIdGenerator
      11: dup
      12: invokespecial #11                 // Method org/springframework/boot/web/embedded/tomcat/LazySessionIdGenerator."<init>":()V
      15: invokeinterface #12,  2           // InterfaceMethod org/apache/catalina/Manager.setSessionIdGenerator:(Lorg/apache/catalina/SessionIdGenerator;)V
      20: aload_0
      21: aload_1
      22: invokespecial #18                 // Method org/apache/catalina/core/StandardContext.setManager:(Lorg/apache/catalina/Manager;)V
      25: return

  void deferredLoadOnStartup();
    Code:
       0: aload_0
       1: aload_0
       2: invokevirtual #22                 // Method getLoader:()Lorg/apache/catalina/Loader;
       5: invokeinterface #28,  1           // InterfaceMethod org/apache/catalina/Loader.getClassLoader:()Ljava/lang/ClassLoader;
      10: aload_0
      11: invokedynamic #34,  0             // InvokeDynamic #0:run:(Lorg/springframework/boot/web/embedded/tomcat/TomcatEmbeddedContext;)Ljava/lang/Runnable;
      16: invokevirtual #38                 // Method doWithThreadContextClassLoader:(Ljava/lang/ClassLoader;Ljava/lang/Runnable;)V
      19: return

  private java.util.stream.Stream<org.apache.catalina.Wrapper> getLoadOnStartupWrappers(org.apache.catalina.Container[]);
    Code:
       0: new           #42                 // class java/util/TreeMap
       3: dup
       4: invokespecial #44                 // Method java/util/TreeMap."<init>":()V
       7: astore_2
       8: aload_1
       9: astore_3
      10: aload_3
      11: arraylength
      12: istore        4
      14: iconst_0
      15: istore        5
      17: iload         5
      19: iload         4
      21: if_icmpge     84
      24: aload_3
      25: iload         5
      27: aaload
      28: astore        6
      30: aload         6
      32: checkcast     #45                 // class org/apache/catalina/Wrapper
      35: astore        7
      37: aload         7
      39: invokeinterface #47,  1           // InterfaceMethod org/apache/catalina/Wrapper.getLoadOnStartup:()I
      44: istore        8
      46: iload         8
      48: iflt          78
      51: aload_2
      52: iload         8
      54: invokestatic  #51                 // Method java/lang/Integer.valueOf:(I)Ljava/lang/Integer;
      57: invokedynamic #57,  0             // InvokeDynamic #1:apply:()Ljava/util/function/Function;
      62: invokeinterface #61,  3           // InterfaceMethod java/util/Map.computeIfAbsent:(Ljava/lang/Object;Ljava/util/function/Function;)Ljava/lang/Object;
      67: checkcast     #67                 // class java/util/List
      70: aload         7
      72: invokeinterface #69,  2           // InterfaceMethod java/util/List.add:(Ljava/lang/Object;)Z
      77: pop
      78: iinc          5, 1
      81: goto          17
      84: aload_2
      85: invokeinterface #73,  1           // InterfaceMethod java/util/Map.values:()Ljava/util/Collection;
      90: invokeinterface #77,  1           // InterfaceMethod java/util/Collection.stream:()Ljava/util/stream/Stream;
      95: invokedynamic #83,  0             // InvokeDynamic #2:apply:()Ljava/util/function/Function;
     100: invokeinterface #84,  2           // InterfaceMethod java/util/stream/Stream.flatMap:(Ljava/util/function/Function;)Ljava/util/stream/Stream;
     105: areturn

  private void load(org.apache.catalina.Wrapper);
    Code:
       0: aload_1
       1: invokeinterface #90,  1           // InterfaceMethod org/apache/catalina/Wrapper.load:()V
       6: goto          70
       9: astore_2
      10: getstatic     #95                 // Field sm:Lorg/apache/tomcat/util/res/StringManager;
      13: ldc           #99                 // String standardContext.loadOnStartup.loadException
      15: iconst_2
      16: anewarray     #101                // class java/lang/Object
      19: dup
      20: iconst_0
      21: aload_0
      22: invokevirtual #103                // Method getName:()Ljava/lang/String;
      25: aastore
      26: dup
      27: iconst_1
      28: aload_1
      29: invokeinterface #107,  1          // InterfaceMethod org/apache/catalina/Wrapper.getName:()Ljava/lang/String;
      34: aastore
      35: invokevirtual #108                // Method org/apache/tomcat/util/res/StringManager.getString:(Ljava/lang/String;[Ljava/lang/Object;)Ljava/lang/String;
      38: astore_3
      39: aload_0
      40: invokevirtual #114                // Method getComputedFailCtxIfServletStartFails:()Z
      43: ifeq          56
      46: new           #118                // class org/springframework/boot/web/server/WebServerException
      49: dup
      50: aload_3
      51: aload_2
      52: invokespecial #120                // Method org/springframework/boot/web/server/WebServerException."<init>":(Ljava/lang/String;Ljava/lang/Throwable;)V
      55: athrow
      56: aload_0
      57: invokevirtual #123                // Method getLogger:()Lorg/apache/juli/logging/Log;
      60: aload_3
      61: aload_2
      62: invokestatic  #127                // Method org/apache/catalina/core/StandardWrapper.getRootCause:(Ljakarta/servlet/ServletException;)Ljava/lang/Throwable;
      65: invokeinterface #133,  3          // InterfaceMethod org/apache/juli/logging/Log.error:(Ljava/lang/Object;Ljava/lang/Throwable;)V
      70: return
    Exception table:
       from    to  target type
           0     6     9   Class jakarta/servlet/ServletException

  private void doWithThreadContextClassLoader(java.lang.ClassLoader, java.lang.Runnable);
    Code:
       0: aload_1
       1: ifnull        11
       4: aload_1
       5: invokestatic  #139                // Method org/springframework/util/ClassUtils.overrideThreadContextClassLoader:(Ljava/lang/ClassLoader;)Ljava/lang/ClassLoader;
       8: goto          12
      11: aconst_null
      12: astore_3
      13: aload_2
      14: invokeinterface #145,  1          // InterfaceMethod java/lang/Runnable.run:()V
      19: aload_3
      20: ifnull        45
      23: aload_3
      24: invokestatic  #139                // Method org/springframework/util/ClassUtils.overrideThreadContextClassLoader:(Ljava/lang/ClassLoader;)Ljava/lang/ClassLoader;
      27: pop
      28: goto          45
      31: astore        4
      33: aload_3
      34: ifnull        42
      37: aload_3
      38: invokestatic  #139                // Method org/springframework/util/ClassUtils.overrideThreadContextClassLoader:(Ljava/lang/ClassLoader;)Ljava/lang/ClassLoader;
      41: pop
      42: aload         4
      44: athrow
      45: return
    Exception table:
       from    to  target type
          13    19    31   any
          31    33    31   any

  void setStarter(org.springframework.boot.web.embedded.tomcat.TomcatStarter);
    Code:
       0: aload_0
       1: aload_1
       2: putfield      #149                // Field starter:Lorg/springframework/boot/web/embedded/tomcat/TomcatStarter;
       5: return

  org.springframework.boot.web.embedded.tomcat.TomcatStarter getStarter();
    Code:
       0: aload_0
       1: getfield      #149                // Field starter:Lorg/springframework/boot/web/embedded/tomcat/TomcatStarter;
       4: areturn

  void setMimeMappings(org.springframework.boot.web.server.MimeMappings);
    Code:
       0: aload_0
       1: aload_1
       2: putfield      #153                // Field mimeMappings:Lorg/springframework/boot/web/server/MimeMappings;
       5: return

  public java.lang.String[] findMimeMappings();
    Code:
       0: new           #157                // class java/util/ArrayList
       3: dup
       4: invokespecial #159                // Method java/util/ArrayList."<init>":()V
       7: astore_1
       8: aload_1
       9: aload_0
      10: invokespecial #160                // Method org/apache/catalina/core/StandardContext.findMimeMappings:()[Ljava/lang/String;
      13: invokestatic  #164                // Method java/util/Arrays.asList:([Ljava/lang/Object;)Ljava/util/List;
      16: invokeinterface #170,  2          // InterfaceMethod java/util/List.addAll:(Ljava/util/Collection;)Z
      21: pop
      22: aload_0
      23: getfield      #153                // Field mimeMappings:Lorg/springframework/boot/web/server/MimeMappings;
      26: ifnull        42
      29: aload_0
      30: getfield      #153                // Field mimeMappings:Lorg/springframework/boot/web/server/MimeMappings;
      33: aload_1
      34: invokedynamic #174,  0            // InvokeDynamic #3:accept:(Ljava/util/List;)Ljava/util/function/Consumer;
      39: invokevirtual #178                // Method org/springframework/boot/web/server/MimeMappings.forEach:(Ljava/util/function/Consumer;)V
      42: aload_1
      43: invokedynamic #184,  0            // InvokeDynamic #4:apply:()Ljava/util/function/IntFunction;
      48: invokeinterface #187,  2          // InterfaceMethod java/util/List.toArray:(Ljava/util/function/IntFunction;)[Ljava/lang/Object;
      53: checkcast     #191                // class "[Ljava/lang/String;"
      56: areturn

  public java.lang.String findMimeMapping(java.lang.String);
    Code:
       0: aload_0
       1: aload_1
       2: invokespecial #193                // Method org/apache/catalina/core/StandardContext.findMimeMapping:(Ljava/lang/String;)Ljava/lang/String;
       5: astore_2
       6: aload_2
       7: ifnull        12
      10: aload_2
      11: areturn
      12: aload_0
      13: getfield      #153                // Field mimeMappings:Lorg/springframework/boot/web/server/MimeMappings;
      16: ifnull        30
      19: aload_0
      20: getfield      #153                // Field mimeMappings:Lorg/springframework/boot/web/server/MimeMappings;
      23: aload_1
      24: invokevirtual #197                // Method org/springframework/boot/web/server/MimeMappings.get:(Ljava/lang/String;)Ljava/lang/String;
      27: goto          31
      30: aconst_null
      31: areturn

  private static java.lang.String[] lambda$findMimeMappings$3(int);
    Code:
       0: iload_0
       1: anewarray     #200                // class java/lang/String
       4: areturn

  private static void lambda$findMimeMappings$2(java.util.List, org.springframework.boot.web.server.MimeMappings$Mapping);
    Code:
       0: aload_0
       1: aload_1
       2: invokevirtual #202                // Method org/springframework/boot/web/server/MimeMappings$Mapping.getExtension:()Ljava/lang/String;
       5: invokeinterface #69,  2           // InterfaceMethod java/util/List.add:(Ljava/lang/Object;)Z
      10: pop
      11: return

  private static java.util.List lambda$getLoadOnStartupWrappers$1(java.lang.Integer);
    Code:
       0: new           #157                // class java/util/ArrayList
       3: dup
       4: invokespecial #159                // Method java/util/ArrayList."<init>":()V
       7: areturn

  private void lambda$deferredLoadOnStartup$0();
    Code:
       0: aload_0
       1: aload_0
       2: invokevirtual #207                // Method findChildren:()[Lorg/apache/catalina/Container;
       5: invokevirtual #211                // Method getLoadOnStartupWrappers:([Lorg/apache/catalina/Container;)Ljava/util/stream/Stream;
       8: aload_0
       9: invokedynamic #215,  0            // InvokeDynamic #5:accept:(Lorg/springframework/boot/web/embedded/tomcat/TomcatEmbeddedContext;)Ljava/util/function/Consumer;
      14: invokeinterface #218,  2          // InterfaceMethod java/util/stream/Stream.forEach:(Ljava/util/function/Consumer;)V
      19: return
}
