Compiled from "TomcatEmbeddedWebappClassLoader.java"
public class org.springframework.boot.web.embedded.tomcat.TomcatEmbeddedWebappClassLoader extends org.apache.catalina.loader.ParallelWebappClassLoader {
  private static final org.apache.commons.logging.Log logger;

  public org.springframework.boot.web.embedded.tomcat.TomcatEmbeddedWebappClassLoader();
    Code:
       0: aload_0
       1: invokespecial #1                  // Method org/apache/catalina/loader/ParallelWebappClassLoader."<init>":()V
       4: return

  public org.springframework.boot.web.embedded.tomcat.TomcatEmbeddedWebappClassLoader(java.lang.ClassLoader);
    Code:
       0: aload_0
       1: aload_1
       2: invokespecial #7                  // Method org/apache/catalina/loader/ParallelWebappClassLoader."<init>":(Ljava/lang/ClassLoader;)V
       5: return

  public java.net.URL findResource(java.lang.String);
    Code:
       0: aconst_null
       1: areturn

  public java.util.Enumeration<java.net.URL> findResources(java.lang.String) throws java.io.IOException;
    Code:
       0: invokestatic  #10                 // Method java/util/Collections.emptyEnumeration:()Ljava/util/Enumeration;
       3: areturn

  public java.lang.Class<?> loadClass(java.lang.String, boolean) throws java.lang.ClassNotFoundException;
    Code:
       0: invokestatic  #16                 // Method org/apache/tomcat/util/compat/JreCompat.isGraalAvailable:()Z
       3: ifeq          10
       6: aload_0
       7: goto          15
      10: aload_0
      11: aload_1
      12: invokevirtual #22                 // Method getClassLoadingLock:(Ljava/lang/String;)Ljava/lang/Object;
      15: dup
      16: astore_3
      17: monitorenter
      18: aload_0
      19: aload_1
      20: invokevirtual #28                 // Method findExistingLoadedClass:(Ljava/lang/String;)Ljava/lang/Class;
      23: astore        4
      25: aload         4
      27: ifnull        35
      30: aload         4
      32: goto          40
      35: aload_0
      36: aload_1
      37: invokevirtual #32                 // Method doLoadClass:(Ljava/lang/String;)Ljava/lang/Class;
      40: astore        4
      42: aload         4
      44: ifnonnull     56
      47: new           #35                 // class java/lang/ClassNotFoundException
      50: dup
      51: aload_1
      52: invokespecial #37                 // Method java/lang/ClassNotFoundException."<init>":(Ljava/lang/String;)V
      55: athrow
      56: aload_0
      57: aload         4
      59: iload_2
      60: invokevirtual #40                 // Method resolveIfNecessary:(Ljava/lang/Class;Z)Ljava/lang/Class;
      63: aload_3
      64: monitorexit
      65: areturn
      66: astore        5
      68: aload_3
      69: monitorexit
      70: aload         5
      72: athrow
    Exception table:
       from    to  target type
          18    65    66   any
          66    70    66   any

  private java.lang.Class<?> findExistingLoadedClass(java.lang.String);
    Code:
       0: aload_0
       1: aload_1
       2: invokevirtual #44                 // Method findLoadedClass0:(Ljava/lang/String;)Ljava/lang/Class;
       5: astore_2
       6: aload_2
       7: ifnonnull     16
      10: invokestatic  #16                 // Method org/apache/tomcat/util/compat/JreCompat.isGraalAvailable:()Z
      13: ifeq          20
      16: aload_2
      17: goto          25
      20: aload_0
      21: aload_1
      22: invokevirtual #47                 // Method findLoadedClass:(Ljava/lang/String;)Ljava/lang/Class;
      25: astore_2
      26: aload_2
      27: areturn

  private java.lang.Class<?> doLoadClass(java.lang.String);
    Code:
       0: aload_0
       1: getfield      #50                 // Field delegate:Z
       4: ifne          16
       7: aload_0
       8: aload_1
       9: iconst_1
      10: invokevirtual #54                 // Method filter:(Ljava/lang/String;Z)Z
      13: ifeq          36
      16: aload_0
      17: aload_1
      18: invokevirtual #58                 // Method loadFromParent:(Ljava/lang/String;)Ljava/lang/Class;
      21: astore_2
      22: aload_2
      23: ifnull        30
      26: aload_2
      27: goto          35
      30: aload_0
      31: aload_1
      32: invokevirtual #61                 // Method findClassIgnoringNotFound:(Ljava/lang/String;)Ljava/lang/Class;
      35: areturn
      36: aload_0
      37: aload_1
      38: invokevirtual #61                 // Method findClassIgnoringNotFound:(Ljava/lang/String;)Ljava/lang/Class;
      41: astore_2
      42: aload_2
      43: ifnull        50
      46: aload_2
      47: goto          55
      50: aload_0
      51: aload_1
      52: invokevirtual #58                 // Method loadFromParent:(Ljava/lang/String;)Ljava/lang/Class;
      55: areturn

  private java.lang.Class<?> resolveIfNecessary(java.lang.Class<?>, boolean);
    Code:
       0: iload_2
       1: ifeq          9
       4: aload_0
       5: aload_1
       6: invokevirtual #64                 // Method resolveClass:(Ljava/lang/Class;)V
       9: aload_1
      10: areturn

  protected void addURL(java.net.URL);
    Code:
       0: getstatic     #68                 // Field logger:Lorg/apache/commons/logging/Log;
       3: invokeinterface #72,  1           // InterfaceMethod org/apache/commons/logging/Log.isTraceEnabled:()Z
       8: ifeq          25
      11: getstatic     #68                 // Field logger:Lorg/apache/commons/logging/Log;
      14: aload_1
      15: invokedynamic #77,  0             // InvokeDynamic #0:makeConcatWithConstants:(Ljava/net/URL;)Ljava/lang/String;
      20: invokeinterface #81,  2           // InterfaceMethod org/apache/commons/logging/Log.trace:(Ljava/lang/Object;)V
      25: return

  private java.lang.Class<?> loadFromParent(java.lang.String);
    Code:
       0: aload_0
       1: getfield      #85                 // Field parent:Ljava/lang/ClassLoader;
       4: ifnonnull     9
       7: aconst_null
       8: areturn
       9: aload_1
      10: iconst_0
      11: aload_0
      12: getfield      #85                 // Field parent:Ljava/lang/ClassLoader;
      15: invokestatic  #89                 // Method java/lang/Class.forName:(Ljava/lang/String;ZLjava/lang/ClassLoader;)Ljava/lang/Class;
      18: areturn
      19: astore_2
      20: aconst_null
      21: areturn
    Exception table:
       from    to  target type
           9    18    19   Class java/lang/ClassNotFoundException

  private java.lang.Class<?> findClassIgnoringNotFound(java.lang.String);
    Code:
       0: aload_0
       1: aload_1
       2: invokevirtual #95                 // Method findClass:(Ljava/lang/String;)Ljava/lang/Class;
       5: areturn
       6: astore_2
       7: aconst_null
       8: areturn
    Exception table:
       from    to  target type
           0     5     6   Class java/lang/ClassNotFoundException

  static {};
    Code:
       0: ldc           #23                 // class org/springframework/boot/web/embedded/tomcat/TomcatEmbeddedWebappClassLoader
       2: invokestatic  #98                 // Method org/apache/commons/logging/LogFactory.getLog:(Ljava/lang/Class;)Lorg/apache/commons/logging/Log;
       5: putstatic     #68                 // Field logger:Lorg/apache/commons/logging/Log;
       8: invokestatic  #16                 // Method org/apache/tomcat/util/compat/JreCompat.isGraalAvailable:()Z
      11: ifne          18
      14: invokestatic  #104                // Method java/lang/ClassLoader.registerAsParallelCapable:()Z
      17: pop
      18: return
}
