Compiled from "TomcatStarter.java"
class org.springframework.boot.web.embedded.tomcat.TomcatStarter implements jakarta.servlet.ServletContainerInitializer {
  private static final org.apache.commons.logging.Log logger;

  private final org.springframework.boot.web.servlet.ServletContextInitializer[] initializers;

  private volatile java.lang.Exception startUpException;

  org.springframework.boot.web.embedded.tomcat.TomcatStarter(org.springframework.boot.web.servlet.ServletContextInitializer[]);
    Code:
       0: aload_0
       1: invokespecial #1                  // Method java/lang/Object."<init>":()V
       4: aload_0
       5: aload_1
       6: putfield      #7                  // Field initializers:[Lorg/springframework/boot/web/servlet/ServletContextInitializer;
       9: return

  public void onStartup(java.util.Set<java.lang.Class<?>>, jakarta.servlet.ServletContext) throws jakarta.servlet.ServletException;
    Code:
       0: aload_0
       1: getfield      #7                  // Field initializers:[Lorg/springframework/boot/web/servlet/ServletContextInitializer;
       4: astore_3
       5: aload_3
       6: arraylength
       7: istore        4
       9: iconst_0
      10: istore        5
      12: iload         5
      14: iload         4
      16: if_icmpge     39
      19: aload_3
      20: iload         5
      22: aaload
      23: astore        6
      25: aload         6
      27: aload_2
      28: invokeinterface #13,  2           // InterfaceMethod org/springframework/boot/web/servlet/ServletContextInitializer.onStartup:(Ljakarta/servlet/ServletContext;)V
      33: iinc          5, 1
      36: goto          12
      39: goto          83
      42: astore_3
      43: aload_0
      44: aload_3
      45: putfield      #21                 // Field startUpException:Ljava/lang/Exception;
      48: getstatic     #25                 // Field logger:Lorg/apache/commons/logging/Log;
      51: invokeinterface #29,  1           // InterfaceMethod org/apache/commons/logging/Log.isErrorEnabled:()Z
      56: ifeq          83
      59: getstatic     #25                 // Field logger:Lorg/apache/commons/logging/Log;
      62: aload_3
      63: invokevirtual #35                 // Method java/lang/Object.getClass:()Ljava/lang/Class;
      66: invokevirtual #39                 // Method java/lang/Class.getName:()Ljava/lang/String;
      69: aload_3
      70: invokevirtual #45                 // Method java/lang/Exception.getMessage:()Ljava/lang/String;
      73: invokedynamic #48,  0             // InvokeDynamic #0:makeConcatWithConstants:(Ljava/lang/String;Ljava/lang/String;)Ljava/lang/String;
      78: invokeinterface #52,  2           // InterfaceMethod org/apache/commons/logging/Log.error:(Ljava/lang/Object;)V
      83: return
    Exception table:
       from    to  target type
           0    39    42   Class java/lang/Exception

  java.lang.Exception getStartUpException();
    Code:
       0: aload_0
       1: getfield      #21                 // Field startUpException:Ljava/lang/Exception;
       4: areturn

  static {};
    Code:
       0: ldc           #8                  // class org/springframework/boot/web/embedded/tomcat/TomcatStarter
       2: invokestatic  #56                 // Method org/apache/commons/logging/LogFactory.getLog:(Ljava/lang/Class;)Lorg/apache/commons/logging/Log;
       5: putstatic     #25                 // Field logger:Lorg/apache/commons/logging/Log;
       8: return
}
