Compiled from "TomcatServletWebServerFactory.java"
class org.springframework.boot.web.embedded.tomcat.TomcatServletWebServerFactory$SuppliedSameSiteCookieProcessor extends org.apache.tomcat.util.http.Rfc6265CookieProcessor {
  private final java.util.List<org.springframework.boot.web.servlet.server.CookieSameSiteSupplier> suppliers;

  org.springframework.boot.web.embedded.tomcat.TomcatServletWebServerFactory$SuppliedSameSiteCookieProcessor(java.util.List<org.springframework.boot.web.servlet.server.CookieSameSiteSupplier>);
    Code:
       0: aload_0
       1: invokespecial #1                  // Method org/apache/tomcat/util/http/Rfc6265CookieProcessor."<init>":()V
       4: aload_0
       5: aload_1
       6: putfield      #7                  // Field suppliers:Ljava/util/List;
       9: return

  public java.lang.String generateHeader(jakarta.servlet.http.Cookie, jakarta.servlet.http.HttpServletRequest);
    Code:
       0: aload_0
       1: aload_1
       2: invokevirtual #13                 // Method getSameSite:(Ljakarta/servlet/http/Cookie;)Lorg/springframework/boot/web/server/Cookie$SameSite;
       5: astore_3
       6: aload_3
       7: ifnonnull     17
      10: aload_0
      11: aload_1
      12: aload_2
      13: invokespecial #17                 // Method org/apache/tomcat/util/http/Rfc6265CookieProcessor.generateHeader:(Ljakarta/servlet/http/Cookie;Ljakarta/servlet/http/HttpServletRequest;)Ljava/lang/String;
      16: areturn
      17: new           #2                  // class org/apache/tomcat/util/http/Rfc6265CookieProcessor
      20: dup
      21: invokespecial #1                  // Method org/apache/tomcat/util/http/Rfc6265CookieProcessor."<init>":()V
      24: astore        4
      26: aload         4
      28: aload_3
      29: invokevirtual #21                 // Method org/springframework/boot/web/server/Cookie$SameSite.attributeValue:()Ljava/lang/String;
      32: invokevirtual #27                 // Method org/apache/tomcat/util/http/Rfc6265CookieProcessor.setSameSiteCookies:(Ljava/lang/String;)V
      35: aload         4
      37: aload_1
      38: aload_2
      39: invokevirtual #17                 // Method org/apache/tomcat/util/http/Rfc6265CookieProcessor.generateHeader:(Ljakarta/servlet/http/Cookie;Ljakarta/servlet/http/HttpServletRequest;)Ljava/lang/String;
      42: areturn

  private org.springframework.boot.web.server.Cookie$SameSite getSameSite(jakarta.servlet.http.Cookie);
    Code:
       0: aload_0
       1: getfield      #7                  // Field suppliers:Ljava/util/List;
       4: invokeinterface #31,  1           // InterfaceMethod java/util/List.iterator:()Ljava/util/Iterator;
       9: astore_2
      10: aload_2
      11: invokeinterface #37,  1           // InterfaceMethod java/util/Iterator.hasNext:()Z
      16: ifeq          49
      19: aload_2
      20: invokeinterface #43,  1           // InterfaceMethod java/util/Iterator.next:()Ljava/lang/Object;
      25: checkcast     #47                 // class org/springframework/boot/web/servlet/server/CookieSameSiteSupplier
      28: astore_3
      29: aload_3
      30: aload_1
      31: invokeinterface #49,  2           // InterfaceMethod org/springframework/boot/web/servlet/server/CookieSameSiteSupplier.getSameSite:(Ljakarta/servlet/http/Cookie;)Lorg/springframework/boot/web/server/Cookie$SameSite;
      36: astore        4
      38: aload         4
      40: ifnull        46
      43: aload         4
      45: areturn
      46: goto          10
      49: aconst_null
      50: areturn
}
