Compiled from "QRCodeMultiReader.java"
final class com.google.zxing.multi.qrcode.QRCodeMultiReader$SAComparator implements java.util.Comparator<com.google.zxing.Result>, java.io.Serializable {
  private com.google.zxing.multi.qrcode.QRCodeMultiReader$SAComparator();
    Code:
       0: aload_0
       1: invokespecial #2                  // Method java/lang/Object."<init>":()V
       4: return

  public int compare(com.google.zxing.Result, com.google.zxing.Result);
    Code:
       0: aload_1
       1: invokevirtual #3                  // Method com/google/zxing/Result.getResultMetadata:()Ljava/util/Map;
       4: getstatic     #4                  // Field com/google/zxing/ResultMetadataType.STRUCTURED_APPEND_SEQUENCE:Lcom/google/zxing/ResultMetadataType;
       7: invokeinterface #5,  2            // InterfaceMethod java/util/Map.get:(Ljava/lang/Object;)Ljava/lang/Object;
      12: checkcast     #6                  // class java/lang/Integer
      15: invokevirtual #7                  // Method java/lang/Integer.intValue:()I
      18: istore_3
      19: aload_2
      20: invokevirtual #3                  // Method com/google/zxing/Result.getResultMetadata:()Ljava/util/Map;
      23: getstatic     #4                  // Field com/google/zxing/ResultMetadataType.STRUCTURED_APPEND_SEQUENCE:Lcom/google/zxing/ResultMetadataType;
      26: invokeinterface #5,  2            // InterfaceMethod java/util/Map.get:(Ljava/lang/Object;)Ljava/lang/Object;
      31: checkcast     #6                  // class java/lang/Integer
      34: invokevirtual #7                  // Method java/lang/Integer.intValue:()I
      37: istore        4
      39: iload_3
      40: iload         4
      42: invokestatic  #8                  // Method java/lang/Integer.compare:(II)I
      45: ireturn

  public int compare(java.lang.Object, java.lang.Object);
    Code:
       0: aload_0
       1: aload_1
       2: checkcast     #9                  // class com/google/zxing/Result
       5: aload_2
       6: checkcast     #9                  // class com/google/zxing/Result
       9: invokevirtual #10                 // Method compare:(Lcom/google/zxing/Result;Lcom/google/zxing/Result;)I
      12: ireturn

  com.google.zxing.multi.qrcode.QRCodeMultiReader$SAComparator(com.google.zxing.multi.qrcode.QRCodeMultiReader$1);
    Code:
       0: aload_0
       1: invokespecial #1                  // Method "<init>":()V
       4: return
}
