Compiled from "MulticastRegistryFactory.java"
public class org.apache.dubbo.registry.multicast.MulticastRegistryFactory extends org.apache.dubbo.registry.support.AbstractRegistryFactory {
  public org.apache.dubbo.registry.multicast.MulticastRegistryFactory();
    Code:
       0: aload_0
       1: invokespecial #1                  // Method org/apache/dubbo/registry/support/AbstractRegistryFactory."<init>":()V
       4: return

  public org.apache.dubbo.registry.Registry createRegistry(org.apache.dubbo.common.URL);
    Code:
       0: new           #2                  // class org/apache/dubbo/registry/multicast/MulticastRegistry
       3: dup
       4: aload_1
       5: aload_0
       6: getfield      #3                  // Field applicationModel:Lorg/apache/dubbo/rpc/model/ApplicationModel;
       9: invokespecial #4                  // Method org/apache/dubbo/registry/multicast/MulticastRegistry."<init>":(Lorg/apache/dubbo/common/URL;Lorg/apache/dubbo/rpc/model/ApplicationModel;)V
      12: areturn
}
