Compiled from "MulticastRegistry.java"
public class org.apache.dubbo.registry.multicast.MulticastRegistry extends org.apache.dubbo.registry.support.FailbackRegistry {
  private static final org.apache.dubbo.common.logger.ErrorTypeAwareLogger logger;

  private static final int DEFAULT_MULTICAST_PORT;

  private final java.net.InetAddress multicastAddress;

  private final java.net.MulticastSocket multicastSocket;

  private final int multicastPort;

  private final java.util.concurrent.ConcurrentMap<org.apache.dubbo.common.URL, java.util.Set<org.apache.dubbo.common.URL>> received;

  private final java.util.concurrent.ScheduledExecutorService cleanExecutor;

  private final java.util.concurrent.ScheduledFuture<?> cleanFuture;

  private final int cleanPeriod;

  private volatile boolean admin;

  public org.apache.dubbo.registry.multicast.MulticastRegistry(org.apache.dubbo.common.URL, org.apache.dubbo.rpc.model.ApplicationModel);
    Code:
       0: aload_0
       1: aload_1
       2: invokespecial #5                  // Method "<init>":(Lorg/apache/dubbo/common/URL;)V
       5: return

  public org.apache.dubbo.registry.multicast.MulticastRegistry(org.apache.dubbo.common.URL);
    Code:
       0: aload_0
       1: aload_1
       2: invokespecial #6                  // Method org/apache/dubbo/registry/support/FailbackRegistry."<init>":(Lorg/apache/dubbo/common/URL;)V
       5: aload_0
       6: new           #7                  // class java/util/concurrent/ConcurrentHashMap
       9: dup
      10: invokespecial #8                  // Method java/util/concurrent/ConcurrentHashMap."<init>":()V
      13: putfield      #9                  // Field received:Ljava/util/concurrent/ConcurrentMap;
      16: aload_0
      17: iconst_1
      18: new           #10                 // class org/apache/dubbo/common/utils/NamedThreadFactory
      21: dup
      22: ldc           #11                 // String DubboMulticastRegistryCleanTimer
      24: iconst_1
      25: invokespecial #12                 // Method org/apache/dubbo/common/utils/NamedThreadFactory."<init>":(Ljava/lang/String;Z)V
      28: invokestatic  #13                 // Method java/util/concurrent/Executors.newScheduledThreadPool:(ILjava/util/concurrent/ThreadFactory;)Ljava/util/concurrent/ScheduledExecutorService;
      31: putfield      #14                 // Field cleanExecutor:Ljava/util/concurrent/ScheduledExecutorService;
      34: aload_0
      35: iconst_0
      36: putfield      #15                 // Field admin:Z
      39: aload_1
      40: invokevirtual #16                 // Method org/apache/dubbo/common/URL.isAnyHost:()Z
      43: ifeq          56
      46: new           #17                 // class java/lang/IllegalStateException
      49: dup
      50: ldc           #18                 // String registry address == null
      52: invokespecial #19                 // Method java/lang/IllegalStateException."<init>":(Ljava/lang/String;)V
      55: athrow
      56: aload_0
      57: aload_1
      58: invokevirtual #20                 // Method org/apache/dubbo/common/URL.getHost:()Ljava/lang/String;
      61: invokestatic  #21                 // Method java/net/InetAddress.getByName:(Ljava/lang/String;)Ljava/net/InetAddress;
      64: putfield      #22                 // Field multicastAddress:Ljava/net/InetAddress;
      67: aload_0
      68: aload_0
      69: getfield      #22                 // Field multicastAddress:Ljava/net/InetAddress;
      72: invokespecial #23                 // Method checkMulticastAddress:(Ljava/net/InetAddress;)V
      75: aload_0
      76: aload_1
      77: invokevirtual #24                 // Method org/apache/dubbo/common/URL.getPort:()I
      80: ifgt          89
      83: sipush        1234
      86: goto          93
      89: aload_1
      90: invokevirtual #24                 // Method org/apache/dubbo/common/URL.getPort:()I
      93: putfield      #26                 // Field multicastPort:I
      96: aload_0
      97: new           #27                 // class java/net/MulticastSocket
     100: dup
     101: aload_0
     102: getfield      #26                 // Field multicastPort:I
     105: invokespecial #28                 // Method java/net/MulticastSocket."<init>":(I)V
     108: putfield      #29                 // Field multicastSocket:Ljava/net/MulticastSocket;
     111: aload_0
     112: getfield      #29                 // Field multicastSocket:Ljava/net/MulticastSocket;
     115: aload_0
     116: getfield      #22                 // Field multicastAddress:Ljava/net/InetAddress;
     119: invokestatic  #30                 // Method org/apache/dubbo/common/utils/NetUtils.joinMulticastGroup:(Ljava/net/MulticastSocket;Ljava/net/InetAddress;)V
     122: new           #31                 // class java/lang/Thread
     125: dup
     126: aload_0
     127: invokedynamic #32,  0             // InvokeDynamic #0:run:(Lorg/apache/dubbo/registry/multicast/MulticastRegistry;)Ljava/lang/Runnable;
     132: ldc           #33                 // String DubboMulticastRegistryReceiver
     134: invokespecial #34                 // Method java/lang/Thread."<init>":(Ljava/lang/Runnable;Ljava/lang/String;)V
     137: astore_2
     138: aload_2
     139: iconst_1
     140: invokevirtual #35                 // Method java/lang/Thread.setDaemon:(Z)V
     143: aload_2
     144: invokevirtual #36                 // Method java/lang/Thread.start:()V
     147: goto          164
     150: astore_2
     151: new           #17                 // class java/lang/IllegalStateException
     154: dup
     155: aload_2
     156: invokevirtual #38                 // Method java/io/IOException.getMessage:()Ljava/lang/String;
     159: aload_2
     160: invokespecial #39                 // Method java/lang/IllegalStateException."<init>":(Ljava/lang/String;Ljava/lang/Throwable;)V
     163: athrow
     164: aload_0
     165: aload_1
     166: ldc           #40                 // String session
     168: ldc           #41                 // int 60000
     170: invokevirtual #42                 // Method org/apache/dubbo/common/URL.getParameter:(Ljava/lang/String;I)I
     173: putfield      #43                 // Field cleanPeriod:I
     176: aload_1
     177: ldc           #44                 // String clean
     179: iconst_1
     180: invokevirtual #45                 // Method org/apache/dubbo/common/URL.getParameter:(Ljava/lang/String;Z)Z
     183: ifeq          221
     186: aload_0
     187: aload_0
     188: getfield      #14                 // Field cleanExecutor:Ljava/util/concurrent/ScheduledExecutorService;
     191: aload_0
     192: invokedynamic #46,  0             // InvokeDynamic #1:run:(Lorg/apache/dubbo/registry/multicast/MulticastRegistry;)Ljava/lang/Runnable;
     197: aload_0
     198: getfield      #43                 // Field cleanPeriod:I
     201: i2l
     202: aload_0
     203: getfield      #43                 // Field cleanPeriod:I
     206: i2l
     207: getstatic     #47                 // Field java/util/concurrent/TimeUnit.MILLISECONDS:Ljava/util/concurrent/TimeUnit;
     210: invokeinterface #48,  7           // InterfaceMethod java/util/concurrent/ScheduledExecutorService.scheduleWithFixedDelay:(Ljava/lang/Runnable;JJLjava/util/concurrent/TimeUnit;)Ljava/util/concurrent/ScheduledFuture;
     215: putfield      #49                 // Field cleanFuture:Ljava/util/concurrent/ScheduledFuture;
     218: goto          226
     221: aload_0
     222: aconst_null
     223: putfield      #49                 // Field cleanFuture:Ljava/util/concurrent/ScheduledFuture;
     226: return
    Exception table:
       from    to  target type
          56   147   150   Class java/io/IOException

  private void checkMulticastAddress(java.net.InetAddress);
    Code:
       0: aload_1
       1: invokevirtual #50                 // Method java/net/InetAddress.isMulticastAddress:()Z
       4: ifne          88
       7: new           #51                 // class java/lang/StringBuilder
      10: dup
      11: invokespecial #52                 // Method java/lang/StringBuilder."<init>":()V
      14: ldc           #53                 // String Invalid multicast address
      16: invokevirtual #54                 // Method java/lang/StringBuilder.append:(Ljava/lang/String;)Ljava/lang/StringBuilder;
      19: aload_1
      20: invokevirtual #55                 // Method java/lang/StringBuilder.append:(Ljava/lang/Object;)Ljava/lang/StringBuilder;
      23: invokevirtual #56                 // Method java/lang/StringBuilder.toString:()Ljava/lang/String;
      26: astore_2
      27: aload_1
      28: instanceof    #57                 // class java/net/Inet4Address
      31: ifeq          61
      34: new           #58                 // class java/lang/IllegalArgumentException
      37: dup
      38: new           #51                 // class java/lang/StringBuilder
      41: dup
      42: invokespecial #52                 // Method java/lang/StringBuilder."<init>":()V
      45: aload_2
      46: invokevirtual #54                 // Method java/lang/StringBuilder.append:(Ljava/lang/String;)Ljava/lang/StringBuilder;
      49: ldc           #59                 // String , ipv4 multicast address scope: 224.0.0.0 - 239.255.255.255.
      51: invokevirtual #54                 // Method java/lang/StringBuilder.append:(Ljava/lang/String;)Ljava/lang/StringBuilder;
      54: invokevirtual #56                 // Method java/lang/StringBuilder.toString:()Ljava/lang/String;
      57: invokespecial #60                 // Method java/lang/IllegalArgumentException."<init>":(Ljava/lang/String;)V
      60: athrow
      61: new           #58                 // class java/lang/IllegalArgumentException
      64: dup
      65: new           #51                 // class java/lang/StringBuilder
      68: dup
      69: invokespecial #52                 // Method java/lang/StringBuilder."<init>":()V
      72: aload_2
      73: invokevirtual #54                 // Method java/lang/StringBuilder.append:(Ljava/lang/String;)Ljava/lang/StringBuilder;
      76: ldc           #61                 // String , ipv6 multicast address must start with ff, for example: ff01::1
      78: invokevirtual #54                 // Method java/lang/StringBuilder.append:(Ljava/lang/String;)Ljava/lang/StringBuilder;
      81: invokevirtual #56                 // Method java/lang/StringBuilder.toString:()Ljava/lang/String;
      84: invokespecial #60                 // Method java/lang/IllegalArgumentException."<init>":(Ljava/lang/String;)V
      87: athrow
      88: return

  private void clean();
    Code:
       0: aload_0
       1: getfield      #15                 // Field admin:Z
       4: ifeq          144
       7: new           #62                 // class java/util/HashSet
      10: dup
      11: aload_0
      12: getfield      #9                  // Field received:Ljava/util/concurrent/ConcurrentMap;
      15: invokeinterface #63,  1           // InterfaceMethod java/util/concurrent/ConcurrentMap.values:()Ljava/util/Collection;
      20: invokespecial #64                 // Method java/util/HashSet."<init>":(Ljava/util/Collection;)V
      23: invokevirtual #65                 // Method java/util/HashSet.iterator:()Ljava/util/Iterator;
      26: astore_1
      27: aload_1
      28: invokeinterface #66,  1           // InterfaceMethod java/util/Iterator.hasNext:()Z
      33: ifeq          144
      36: aload_1
      37: invokeinterface #67,  1           // InterfaceMethod java/util/Iterator.next:()Ljava/lang/Object;
      42: checkcast     #68                 // class java/util/Set
      45: astore_2
      46: new           #62                 // class java/util/HashSet
      49: dup
      50: aload_2
      51: invokespecial #64                 // Method java/util/HashSet."<init>":(Ljava/util/Collection;)V
      54: invokevirtual #65                 // Method java/util/HashSet.iterator:()Ljava/util/Iterator;
      57: astore_3
      58: aload_3
      59: invokeinterface #66,  1           // InterfaceMethod java/util/Iterator.hasNext:()Z
      64: ifeq          141
      67: aload_3
      68: invokeinterface #67,  1           // InterfaceMethod java/util/Iterator.next:()Ljava/lang/Object;
      73: checkcast     #69                 // class org/apache/dubbo/common/URL
      76: astore        4
      78: aload_0
      79: aload         4
      81: invokespecial #70                 // Method isExpired:(Lorg/apache/dubbo/common/URL;)Z
      84: ifeq          138
      87: getstatic     #71                 // Field logger:Lorg/apache/dubbo/common/logger/ErrorTypeAwareLogger;
      90: invokeinterface #72,  1           // InterfaceMethod org/apache/dubbo/common/logger/ErrorTypeAwareLogger.isWarnEnabled:()Z
      95: ifeq          132
      98: getstatic     #71                 // Field logger:Lorg/apache/dubbo/common/logger/ErrorTypeAwareLogger;
     101: ldc           #73                 // String 1-38
     103: ldc           #74                 // String
     105: ldc           #74                 // String
     107: new           #51                 // class java/lang/StringBuilder
     110: dup
     111: invokespecial #52                 // Method java/lang/StringBuilder."<init>":()V
     114: ldc           #75                 // String Clean expired provider
     116: invokevirtual #54                 // Method java/lang/StringBuilder.append:(Ljava/lang/String;)Ljava/lang/StringBuilder;
     119: aload         4
     121: invokevirtual #55                 // Method java/lang/StringBuilder.append:(Ljava/lang/Object;)Ljava/lang/StringBuilder;
     124: invokevirtual #56                 // Method java/lang/StringBuilder.toString:()Ljava/lang/String;
     127: invokeinterface #76,  5           // InterfaceMethod org/apache/dubbo/common/logger/ErrorTypeAwareLogger.warn:(Ljava/lang/String;Ljava/lang/String;Ljava/lang/String;Ljava/lang/String;)V
     132: aload_0
     133: aload         4
     135: invokevirtual #77                 // Method doUnregister:(Lorg/apache/dubbo/common/URL;)V
     138: goto          58
     141: goto          27
     144: return

  private boolean isExpired(org.apache.dubbo.common.URL);
    Code:
       0: aload_1
       1: ldc           #78                 // String dynamic
       3: iconst_1
       4: invokevirtual #45                 // Method org/apache/dubbo/common/URL.getParameter:(Ljava/lang/String;Z)Z
       7: ifeq          53
      10: aload_1
      11: invokevirtual #24                 // Method org/apache/dubbo/common/URL.getPort:()I
      14: ifle          53
      17: ldc           #79                 // String consumer
      19: aload_1
      20: invokevirtual #80                 // Method org/apache/dubbo/common/URL.getProtocol:()Ljava/lang/String;
      23: invokevirtual #81                 // Method java/lang/String.equals:(Ljava/lang/Object;)Z
      26: ifne          53
      29: ldc           #82                 // String route
      31: aload_1
      32: invokevirtual #80                 // Method org/apache/dubbo/common/URL.getProtocol:()Ljava/lang/String;
      35: invokevirtual #81                 // Method java/lang/String.equals:(Ljava/lang/Object;)Z
      38: ifne          53
      41: ldc           #83                 // String override
      43: aload_1
      44: invokevirtual #80                 // Method org/apache/dubbo/common/URL.getProtocol:()Ljava/lang/String;
      47: invokevirtual #81                 // Method java/lang/String.equals:(Ljava/lang/Object;)Z
      50: ifeq          55
      53: iconst_0
      54: ireturn
      55: new           #84                 // class java/net/Socket
      58: dup
      59: aload_1
      60: invokevirtual #20                 // Method org/apache/dubbo/common/URL.getHost:()Ljava/lang/String;
      63: aload_1
      64: invokevirtual #24                 // Method org/apache/dubbo/common/URL.getPort:()I
      67: invokespecial #85                 // Method java/net/Socket."<init>":(Ljava/lang/String;I)V
      70: astore_2
      71: aconst_null
      72: astore_3
      73: aload_2
      74: ifnull        103
      77: aload_3
      78: ifnull        99
      81: aload_2
      82: invokevirtual #86                 // Method java/net/Socket.close:()V
      85: goto          103
      88: astore        4
      90: aload_3
      91: aload         4
      93: invokevirtual #88                 // Method java/lang/Throwable.addSuppressed:(Ljava/lang/Throwable;)V
      96: goto          103
      99: aload_2
     100: invokevirtual #86                 // Method java/net/Socket.close:()V
     103: goto          174
     106: astore_2
     107: ldc2_w        #89                 // long 100l
     110: invokestatic  #91                 // Method java/lang/Thread.sleep:(J)V
     113: goto          117
     116: astore_3
     117: new           #84                 // class java/net/Socket
     120: dup
     121: aload_1
     122: invokevirtual #20                 // Method org/apache/dubbo/common/URL.getHost:()Ljava/lang/String;
     125: aload_1
     126: invokevirtual #24                 // Method org/apache/dubbo/common/URL.getPort:()I
     129: invokespecial #85                 // Method java/net/Socket."<init>":(Ljava/lang/String;I)V
     132: astore_3
     133: aconst_null
     134: astore        4
     136: aload_3
     137: ifnull        168
     140: aload         4
     142: ifnull        164
     145: aload_3
     146: invokevirtual #86                 // Method java/net/Socket.close:()V
     149: goto          168
     152: astore        5
     154: aload         4
     156: aload         5
     158: invokevirtual #88                 // Method java/lang/Throwable.addSuppressed:(Ljava/lang/Throwable;)V
     161: goto          168
     164: aload_3
     165: invokevirtual #86                 // Method java/net/Socket.close:()V
     168: goto          174
     171: astore_3
     172: iconst_1
     173: ireturn
     174: iconst_0
     175: ireturn
    Exception table:
       from    to  target type
          81    85    88   Class java/lang/Throwable
          55   103   106   Class java/lang/Throwable
         107   113   116   Class java/lang/Throwable
         145   149   152   Class java/lang/Throwable
         117   168   171   Class java/lang/Throwable

  private void receive(java.lang.String, java.net.InetSocketAddress);
    Code:
       0: getstatic     #71                 // Field logger:Lorg/apache/dubbo/common/logger/ErrorTypeAwareLogger;
       3: invokeinterface #92,  1           // InterfaceMethod org/apache/dubbo/common/logger/ErrorTypeAwareLogger.isInfoEnabled:()Z
       8: ifeq          47
      11: getstatic     #71                 // Field logger:Lorg/apache/dubbo/common/logger/ErrorTypeAwareLogger;
      14: new           #51                 // class java/lang/StringBuilder
      17: dup
      18: invokespecial #52                 // Method java/lang/StringBuilder."<init>":()V
      21: ldc           #93                 // String Receive multicast message:
      23: invokevirtual #54                 // Method java/lang/StringBuilder.append:(Ljava/lang/String;)Ljava/lang/StringBuilder;
      26: aload_1
      27: invokevirtual #54                 // Method java/lang/StringBuilder.append:(Ljava/lang/String;)Ljava/lang/StringBuilder;
      30: ldc           #94                 // String  from
      32: invokevirtual #54                 // Method java/lang/StringBuilder.append:(Ljava/lang/String;)Ljava/lang/StringBuilder;
      35: aload_2
      36: invokevirtual #55                 // Method java/lang/StringBuilder.append:(Ljava/lang/Object;)Ljava/lang/StringBuilder;
      39: invokevirtual #56                 // Method java/lang/StringBuilder.toString:()Ljava/lang/String;
      42: invokeinterface #95,  2           // InterfaceMethod org/apache/dubbo/common/logger/ErrorTypeAwareLogger.info:(Ljava/lang/String;)V
      47: aload_1
      48: ldc           #96                 // String register
      50: invokevirtual #97                 // Method java/lang/String.startsWith:(Ljava/lang/String;)Z
      53: ifeq          80
      56: aload_1
      57: ldc           #96                 // String register
      59: invokevirtual #98                 // Method java/lang/String.length:()I
      62: invokevirtual #99                 // Method java/lang/String.substring:(I)Ljava/lang/String;
      65: invokevirtual #100                // Method java/lang/String.trim:()Ljava/lang/String;
      68: invokestatic  #101                // Method org/apache/dubbo/common/URL.valueOf:(Ljava/lang/String;)Lorg/apache/dubbo/common/URL;
      71: astore_3
      72: aload_0
      73: aload_3
      74: invokevirtual #102                // Method registered:(Lorg/apache/dubbo/common/URL;)V
      77: goto          302
      80: aload_1
      81: ldc           #103                // String unregister
      83: invokevirtual #97                 // Method java/lang/String.startsWith:(Ljava/lang/String;)Z
      86: ifeq          113
      89: aload_1
      90: ldc           #103                // String unregister
      92: invokevirtual #98                 // Method java/lang/String.length:()I
      95: invokevirtual #99                 // Method java/lang/String.substring:(I)Ljava/lang/String;
      98: invokevirtual #100                // Method java/lang/String.trim:()Ljava/lang/String;
     101: invokestatic  #101                // Method org/apache/dubbo/common/URL.valueOf:(Ljava/lang/String;)Lorg/apache/dubbo/common/URL;
     104: astore_3
     105: aload_0
     106: aload_3
     107: invokevirtual #104                // Method unregistered:(Lorg/apache/dubbo/common/URL;)V
     110: goto          302
     113: aload_1
     114: ldc           #105                // String subscribe
     116: invokevirtual #97                 // Method java/lang/String.startsWith:(Ljava/lang/String;)Z
     119: ifeq          302
     122: aload_1
     123: ldc           #105                // String subscribe
     125: invokevirtual #98                 // Method java/lang/String.length:()I
     128: invokevirtual #99                 // Method java/lang/String.substring:(I)Ljava/lang/String;
     131: invokevirtual #100                // Method java/lang/String.trim:()Ljava/lang/String;
     134: invokestatic  #101                // Method org/apache/dubbo/common/URL.valueOf:(Ljava/lang/String;)Lorg/apache/dubbo/common/URL;
     137: astore_3
     138: aload_0
     139: invokevirtual #106                // Method getRegistered:()Ljava/util/Set;
     142: astore        4
     144: aload         4
     146: invokestatic  #107                // Method org/apache/dubbo/common/utils/CollectionUtils.isNotEmpty:(Ljava/util/Collection;)Z
     149: ifeq          302
     152: aload         4
     154: invokeinterface #108,  1          // InterfaceMethod java/util/Set.iterator:()Ljava/util/Iterator;
     159: astore        5
     161: aload         5
     163: invokeinterface #66,  1           // InterfaceMethod java/util/Iterator.hasNext:()Z
     168: ifeq          302
     171: aload         5
     173: invokeinterface #67,  1           // InterfaceMethod java/util/Iterator.next:()Ljava/lang/Object;
     178: checkcast     #69                 // class org/apache/dubbo/common/URL
     181: astore        6
     183: aload_3
     184: aload         6
     186: invokestatic  #109                // Method org/apache/dubbo/common/utils/UrlUtils.isMatch:(Lorg/apache/dubbo/common/URL;Lorg/apache/dubbo/common/URL;)Z
     189: ifeq          299
     192: aload_2
     193: ifnull        213
     196: aload_2
     197: invokevirtual #110                // Method java/net/InetSocketAddress.getAddress:()Ljava/net/InetAddress;
     200: ifnull        213
     203: aload_2
     204: invokevirtual #110                // Method java/net/InetSocketAddress.getAddress:()Ljava/net/InetAddress;
     207: invokevirtual #111                // Method java/net/InetAddress.getHostAddress:()Ljava/lang/String;
     210: goto          217
     213: aload_3
     214: invokevirtual #112                // Method org/apache/dubbo/common/URL.getIp:()Ljava/lang/String;
     217: astore        7
     219: aload_3
     220: ldc           #113                // String unicast
     222: iconst_1
     223: invokevirtual #45                 // Method org/apache/dubbo/common/URL.getParameter:(Ljava/lang/String;Z)Z
     226: ifeq          272
     229: invokestatic  #114                // Method org/apache/dubbo/common/utils/NetUtils.getLocalHost:()Ljava/lang/String;
     232: aload         7
     234: invokevirtual #81                 // Method java/lang/String.equals:(Ljava/lang/Object;)Z
     237: ifne          272
     240: aload_0
     241: new           #51                 // class java/lang/StringBuilder
     244: dup
     245: invokespecial #52                 // Method java/lang/StringBuilder."<init>":()V
     248: ldc           #115                // String register
     250: invokevirtual #54                 // Method java/lang/StringBuilder.append:(Ljava/lang/String;)Ljava/lang/StringBuilder;
     253: aload         6
     255: invokevirtual #116                // Method org/apache/dubbo/common/URL.toFullString:()Ljava/lang/String;
     258: invokevirtual #54                 // Method java/lang/StringBuilder.append:(Ljava/lang/String;)Ljava/lang/StringBuilder;
     261: invokevirtual #56                 // Method java/lang/StringBuilder.toString:()Ljava/lang/String;
     264: aload         7
     266: invokespecial #117                // Method unicast:(Ljava/lang/String;Ljava/lang/String;)V
     269: goto          299
     272: aload_0
     273: new           #51                 // class java/lang/StringBuilder
     276: dup
     277: invokespecial #52                 // Method java/lang/StringBuilder."<init>":()V
     280: ldc           #115                // String register
     282: invokevirtual #54                 // Method java/lang/StringBuilder.append:(Ljava/lang/String;)Ljava/lang/StringBuilder;
     285: aload         6
     287: invokevirtual #116                // Method org/apache/dubbo/common/URL.toFullString:()Ljava/lang/String;
     290: invokevirtual #54                 // Method java/lang/StringBuilder.append:(Ljava/lang/String;)Ljava/lang/StringBuilder;
     293: invokevirtual #56                 // Method java/lang/StringBuilder.toString:()Ljava/lang/String;
     296: invokespecial #118                // Method multicast:(Ljava/lang/String;)V
     299: goto          161
     302: return

  private void multicast(java.lang.String);
    Code:
       0: getstatic     #71                 // Field logger:Lorg/apache/dubbo/common/logger/ErrorTypeAwareLogger;
       3: invokeinterface #92,  1           // InterfaceMethod org/apache/dubbo/common/logger/ErrorTypeAwareLogger.isInfoEnabled:()Z
       8: ifeq          62
      11: getstatic     #71                 // Field logger:Lorg/apache/dubbo/common/logger/ErrorTypeAwareLogger;
      14: new           #51                 // class java/lang/StringBuilder
      17: dup
      18: invokespecial #52                 // Method java/lang/StringBuilder."<init>":()V
      21: ldc           #119                // String Send multicast message:
      23: invokevirtual #54                 // Method java/lang/StringBuilder.append:(Ljava/lang/String;)Ljava/lang/StringBuilder;
      26: aload_1
      27: invokevirtual #54                 // Method java/lang/StringBuilder.append:(Ljava/lang/String;)Ljava/lang/StringBuilder;
      30: ldc           #120                // String  to
      32: invokevirtual #54                 // Method java/lang/StringBuilder.append:(Ljava/lang/String;)Ljava/lang/StringBuilder;
      35: aload_0
      36: getfield      #22                 // Field multicastAddress:Ljava/net/InetAddress;
      39: invokevirtual #55                 // Method java/lang/StringBuilder.append:(Ljava/lang/Object;)Ljava/lang/StringBuilder;
      42: ldc           #121                // String :
      44: invokevirtual #54                 // Method java/lang/StringBuilder.append:(Ljava/lang/String;)Ljava/lang/StringBuilder;
      47: aload_0
      48: getfield      #26                 // Field multicastPort:I
      51: invokevirtual #122                // Method java/lang/StringBuilder.append:(I)Ljava/lang/StringBuilder;
      54: invokevirtual #56                 // Method java/lang/StringBuilder.toString:()Ljava/lang/String;
      57: invokeinterface #95,  2           // InterfaceMethod org/apache/dubbo/common/logger/ErrorTypeAwareLogger.info:(Ljava/lang/String;)V
      62: new           #51                 // class java/lang/StringBuilder
      65: dup
      66: invokespecial #52                 // Method java/lang/StringBuilder."<init>":()V
      69: aload_1
      70: invokevirtual #54                 // Method java/lang/StringBuilder.append:(Ljava/lang/String;)Ljava/lang/StringBuilder;
      73: ldc           #123                // String \n
      75: invokevirtual #54                 // Method java/lang/StringBuilder.append:(Ljava/lang/String;)Ljava/lang/StringBuilder;
      78: invokevirtual #56                 // Method java/lang/StringBuilder.toString:()Ljava/lang/String;
      81: invokevirtual #124                // Method java/lang/String.getBytes:()[B
      84: astore_2
      85: new           #125                // class java/net/DatagramPacket
      88: dup
      89: aload_2
      90: aload_2
      91: arraylength
      92: aload_0
      93: getfield      #22                 // Field multicastAddress:Ljava/net/InetAddress;
      96: aload_0
      97: getfield      #26                 // Field multicastPort:I
     100: invokespecial #126                // Method java/net/DatagramPacket."<init>":([BILjava/net/InetAddress;I)V
     103: astore_3
     104: aload_0
     105: getfield      #29                 // Field multicastSocket:Ljava/net/MulticastSocket;
     108: aload_3
     109: invokevirtual #127                // Method java/net/MulticastSocket.send:(Ljava/net/DatagramPacket;)V
     112: goto          129
     115: astore_2
     116: new           #17                 // class java/lang/IllegalStateException
     119: dup
     120: aload_2
     121: invokevirtual #129                // Method java/lang/Exception.getMessage:()Ljava/lang/String;
     124: aload_2
     125: invokespecial #39                 // Method java/lang/IllegalStateException."<init>":(Ljava/lang/String;Ljava/lang/Throwable;)V
     128: athrow
     129: return
    Exception table:
       from    to  target type
          62   112   115   Class java/lang/Exception

  private void unicast(java.lang.String, java.lang.String);
    Code:
       0: getstatic     #71                 // Field logger:Lorg/apache/dubbo/common/logger/ErrorTypeAwareLogger;
       3: invokeinterface #92,  1           // InterfaceMethod org/apache/dubbo/common/logger/ErrorTypeAwareLogger.isInfoEnabled:()Z
       8: ifeq          59
      11: getstatic     #71                 // Field logger:Lorg/apache/dubbo/common/logger/ErrorTypeAwareLogger;
      14: new           #51                 // class java/lang/StringBuilder
      17: dup
      18: invokespecial #52                 // Method java/lang/StringBuilder."<init>":()V
      21: ldc           #130                // String Send unicast message:
      23: invokevirtual #54                 // Method java/lang/StringBuilder.append:(Ljava/lang/String;)Ljava/lang/StringBuilder;
      26: aload_1
      27: invokevirtual #54                 // Method java/lang/StringBuilder.append:(Ljava/lang/String;)Ljava/lang/StringBuilder;
      30: ldc           #120                // String  to
      32: invokevirtual #54                 // Method java/lang/StringBuilder.append:(Ljava/lang/String;)Ljava/lang/StringBuilder;
      35: aload_2
      36: invokevirtual #54                 // Method java/lang/StringBuilder.append:(Ljava/lang/String;)Ljava/lang/StringBuilder;
      39: ldc           #121                // String :
      41: invokevirtual #54                 // Method java/lang/StringBuilder.append:(Ljava/lang/String;)Ljava/lang/StringBuilder;
      44: aload_0
      45: getfield      #26                 // Field multicastPort:I
      48: invokevirtual #122                // Method java/lang/StringBuilder.append:(I)Ljava/lang/StringBuilder;
      51: invokevirtual #56                 // Method java/lang/StringBuilder.toString:()Ljava/lang/String;
      54: invokeinterface #95,  2           // InterfaceMethod org/apache/dubbo/common/logger/ErrorTypeAwareLogger.info:(Ljava/lang/String;)V
      59: new           #51                 // class java/lang/StringBuilder
      62: dup
      63: invokespecial #52                 // Method java/lang/StringBuilder."<init>":()V
      66: aload_1
      67: invokevirtual #54                 // Method java/lang/StringBuilder.append:(Ljava/lang/String;)Ljava/lang/StringBuilder;
      70: ldc           #123                // String \n
      72: invokevirtual #54                 // Method java/lang/StringBuilder.append:(Ljava/lang/String;)Ljava/lang/StringBuilder;
      75: invokevirtual #56                 // Method java/lang/StringBuilder.toString:()Ljava/lang/String;
      78: invokevirtual #124                // Method java/lang/String.getBytes:()[B
      81: astore_3
      82: new           #125                // class java/net/DatagramPacket
      85: dup
      86: aload_3
      87: aload_3
      88: arraylength
      89: aload_2
      90: invokestatic  #21                 // Method java/net/InetAddress.getByName:(Ljava/lang/String;)Ljava/net/InetAddress;
      93: aload_0
      94: getfield      #26                 // Field multicastPort:I
      97: invokespecial #126                // Method java/net/DatagramPacket."<init>":([BILjava/net/InetAddress;I)V
     100: astore        4
     102: aload_0
     103: getfield      #29                 // Field multicastSocket:Ljava/net/MulticastSocket;
     106: aload         4
     108: invokevirtual #127                // Method java/net/MulticastSocket.send:(Ljava/net/DatagramPacket;)V
     111: goto          128
     114: astore_3
     115: new           #17                 // class java/lang/IllegalStateException
     118: dup
     119: aload_3
     120: invokevirtual #129                // Method java/lang/Exception.getMessage:()Ljava/lang/String;
     123: aload_3
     124: invokespecial #39                 // Method java/lang/IllegalStateException."<init>":(Ljava/lang/String;Ljava/lang/Throwable;)V
     127: athrow
     128: return
    Exception table:
       from    to  target type
          59   111   114   Class java/lang/Exception

  public void doRegister(org.apache.dubbo.common.URL);
    Code:
       0: aload_0
       1: new           #51                 // class java/lang/StringBuilder
       4: dup
       5: invokespecial #52                 // Method java/lang/StringBuilder."<init>":()V
       8: ldc           #115                // String register
      10: invokevirtual #54                 // Method java/lang/StringBuilder.append:(Ljava/lang/String;)Ljava/lang/StringBuilder;
      13: aload_1
      14: invokevirtual #116                // Method org/apache/dubbo/common/URL.toFullString:()Ljava/lang/String;
      17: invokevirtual #54                 // Method java/lang/StringBuilder.append:(Ljava/lang/String;)Ljava/lang/StringBuilder;
      20: invokevirtual #56                 // Method java/lang/StringBuilder.toString:()Ljava/lang/String;
      23: invokespecial #118                // Method multicast:(Ljava/lang/String;)V
      26: return

  public void doUnregister(org.apache.dubbo.common.URL);
    Code:
       0: aload_0
       1: new           #51                 // class java/lang/StringBuilder
       4: dup
       5: invokespecial #52                 // Method java/lang/StringBuilder."<init>":()V
       8: ldc           #131                // String unregister
      10: invokevirtual #54                 // Method java/lang/StringBuilder.append:(Ljava/lang/String;)Ljava/lang/StringBuilder;
      13: aload_1
      14: invokevirtual #116                // Method org/apache/dubbo/common/URL.toFullString:()Ljava/lang/String;
      17: invokevirtual #54                 // Method java/lang/StringBuilder.append:(Ljava/lang/String;)Ljava/lang/StringBuilder;
      20: invokevirtual #56                 // Method java/lang/StringBuilder.toString:()Ljava/lang/String;
      23: invokespecial #118                // Method multicast:(Ljava/lang/String;)V
      26: return

  public void doSubscribe(org.apache.dubbo.common.URL, org.apache.dubbo.registry.NotifyListener);
    Code:
       0: ldc           #132                // String *
       2: aload_1
       3: invokevirtual #133                // Method org/apache/dubbo/common/URL.getServiceInterface:()Ljava/lang/String;
       6: invokevirtual #81                 // Method java/lang/String.equals:(Ljava/lang/Object;)Z
       9: ifeq          17
      12: aload_0
      13: iconst_1
      14: putfield      #15                 // Field admin:Z
      17: aload_0
      18: new           #51                 // class java/lang/StringBuilder
      21: dup
      22: invokespecial #52                 // Method java/lang/StringBuilder."<init>":()V
      25: ldc           #134                // String subscribe
      27: invokevirtual #54                 // Method java/lang/StringBuilder.append:(Ljava/lang/String;)Ljava/lang/StringBuilder;
      30: aload_1
      31: invokevirtual #116                // Method org/apache/dubbo/common/URL.toFullString:()Ljava/lang/String;
      34: invokevirtual #54                 // Method java/lang/StringBuilder.append:(Ljava/lang/String;)Ljava/lang/StringBuilder;
      37: invokevirtual #56                 // Method java/lang/StringBuilder.toString:()Ljava/lang/String;
      40: invokespecial #118                // Method multicast:(Ljava/lang/String;)V
      43: aload_2
      44: dup
      45: astore_3
      46: monitorenter
      47: aload_2
      48: aload_1
      49: ldc           #135                // String timeout
      51: sipush        1000
      54: invokevirtual #42                 // Method org/apache/dubbo/common/URL.getParameter:(Ljava/lang/String;I)I
      57: i2l
      58: invokevirtual #136                // Method java/lang/Object.wait:(J)V
      61: goto          66
      64: astore        4
      66: aload_3
      67: monitorexit
      68: goto          78
      71: astore        5
      73: aload_3
      74: monitorexit
      75: aload         5
      77: athrow
      78: return
    Exception table:
       from    to  target type
          47    61    64   Class java/lang/InterruptedException
          47    68    71   any
          71    75    71   any

  public void doUnsubscribe(org.apache.dubbo.common.URL, org.apache.dubbo.registry.NotifyListener);
    Code:
       0: ldc           #132                // String *
       2: aload_1
       3: invokevirtual #133                // Method org/apache/dubbo/common/URL.getServiceInterface:()Ljava/lang/String;
       6: invokevirtual #81                 // Method java/lang/String.equals:(Ljava/lang/Object;)Z
       9: ifne          27
      12: aload_1
      13: ldc           #96                 // String register
      15: iconst_1
      16: invokevirtual #45                 // Method org/apache/dubbo/common/URL.getParameter:(Ljava/lang/String;Z)Z
      19: ifeq          27
      22: aload_0
      23: aload_1
      24: invokevirtual #138                // Method unregister:(Lorg/apache/dubbo/common/URL;)V
      27: aload_0
      28: new           #51                 // class java/lang/StringBuilder
      31: dup
      32: invokespecial #52                 // Method java/lang/StringBuilder."<init>":()V
      35: ldc           #139                // String unsubscribe
      37: invokevirtual #54                 // Method java/lang/StringBuilder.append:(Ljava/lang/String;)Ljava/lang/StringBuilder;
      40: aload_1
      41: invokevirtual #116                // Method org/apache/dubbo/common/URL.toFullString:()Ljava/lang/String;
      44: invokevirtual #54                 // Method java/lang/StringBuilder.append:(Ljava/lang/String;)Ljava/lang/StringBuilder;
      47: invokevirtual #56                 // Method java/lang/StringBuilder.toString:()Ljava/lang/String;
      50: invokespecial #118                // Method multicast:(Ljava/lang/String;)V
      53: return

  public boolean isAvailable();
    Code:
       0: aload_0
       1: getfield      #29                 // Field multicastSocket:Ljava/net/MulticastSocket;
       4: ifnull        11
       7: iconst_1
       8: goto          12
      11: iconst_0
      12: ireturn
      13: astore_1
      14: iconst_0
      15: ireturn
    Exception table:
       from    to  target type
           0    12    13   Class java/lang/Throwable

  public void destroy();
    Code:
       0: aload_0
       1: invokespecial #140                // Method org/apache/dubbo/registry/support/FailbackRegistry.destroy:()V
       4: aload_0
       5: getfield      #49                 // Field cleanFuture:Ljava/util/concurrent/ScheduledFuture;
       8: invokestatic  #141                // Method org/apache/dubbo/common/utils/ExecutorUtil.cancelScheduledFuture:(Ljava/util/concurrent/ScheduledFuture;)V
      11: goto          34
      14: astore_1
      15: getstatic     #71                 // Field logger:Lorg/apache/dubbo/common/logger/ErrorTypeAwareLogger;
      18: ldc           #73                 // String 1-38
      20: ldc           #74                 // String
      22: ldc           #74                 // String
      24: aload_1
      25: invokevirtual #142                // Method java/lang/Throwable.getMessage:()Ljava/lang/String;
      28: aload_1
      29: invokeinterface #143,  6          // InterfaceMethod org/apache/dubbo/common/logger/ErrorTypeAwareLogger.warn:(Ljava/lang/String;Ljava/lang/String;Ljava/lang/String;Ljava/lang/String;Ljava/lang/Throwable;)V
      34: aload_0
      35: getfield      #29                 // Field multicastSocket:Ljava/net/MulticastSocket;
      38: aload_0
      39: getfield      #22                 // Field multicastAddress:Ljava/net/InetAddress;
      42: invokevirtual #144                // Method java/net/MulticastSocket.leaveGroup:(Ljava/net/InetAddress;)V
      45: aload_0
      46: getfield      #29                 // Field multicastSocket:Ljava/net/MulticastSocket;
      49: invokevirtual #145                // Method java/net/MulticastSocket.close:()V
      52: goto          75
      55: astore_1
      56: getstatic     #71                 // Field logger:Lorg/apache/dubbo/common/logger/ErrorTypeAwareLogger;
      59: ldc           #73                 // String 1-38
      61: ldc           #74                 // String
      63: ldc           #74                 // String
      65: aload_1
      66: invokevirtual #142                // Method java/lang/Throwable.getMessage:()Ljava/lang/String;
      69: aload_1
      70: invokeinterface #143,  6          // InterfaceMethod org/apache/dubbo/common/logger/ErrorTypeAwareLogger.warn:(Ljava/lang/String;Ljava/lang/String;Ljava/lang/String;Ljava/lang/String;Ljava/lang/Throwable;)V
      75: aload_0
      76: getfield      #14                 // Field cleanExecutor:Ljava/util/concurrent/ScheduledExecutorService;
      79: aload_0
      80: getfield      #43                 // Field cleanPeriod:I
      83: invokestatic  #146                // Method org/apache/dubbo/common/utils/ExecutorUtil.gracefulShutdown:(Ljava/util/concurrent/Executor;I)V
      86: return
    Exception table:
       from    to  target type
           4    11    14   Class java/lang/Throwable
          34    52    55   Class java/lang/Throwable

  protected void registered(org.apache.dubbo.common.URL);
    Code:
       0: aload_0
       1: invokevirtual #147                // Method getSubscribed:()Ljava/util/Map;
       4: invokeinterface #148,  1          // InterfaceMethod java/util/Map.entrySet:()Ljava/util/Set;
       9: invokeinterface #108,  1          // InterfaceMethod java/util/Set.iterator:()Ljava/util/Iterator;
      14: astore_2
      15: aload_2
      16: invokeinterface #66,  1           // InterfaceMethod java/util/Iterator.hasNext:()Z
      21: ifeq          171
      24: aload_2
      25: invokeinterface #67,  1           // InterfaceMethod java/util/Iterator.next:()Ljava/lang/Object;
      30: checkcast     #149                // class java/util/Map$Entry
      33: astore_3
      34: aload_3
      35: invokeinterface #150,  1          // InterfaceMethod java/util/Map$Entry.getKey:()Ljava/lang/Object;
      40: checkcast     #69                 // class org/apache/dubbo/common/URL
      43: astore        4
      45: aload         4
      47: aload_1
      48: invokestatic  #109                // Method org/apache/dubbo/common/utils/UrlUtils.isMatch:(Lorg/apache/dubbo/common/URL;Lorg/apache/dubbo/common/URL;)Z
      51: ifeq          168
      54: aload_0
      55: getfield      #9                  // Field received:Ljava/util/concurrent/ConcurrentMap;
      58: aload         4
      60: invokedynamic #151,  0            // InvokeDynamic #2:apply:()Ljava/util/function/Function;
      65: invokeinterface #152,  3          // InterfaceMethod java/util/concurrent/ConcurrentMap.computeIfAbsent:(Ljava/lang/Object;Ljava/util/function/Function;)Ljava/lang/Object;
      70: checkcast     #68                 // class java/util/Set
      73: astore        5
      75: aload         5
      77: aload_1
      78: invokeinterface #153,  2          // InterfaceMethod java/util/Set.add:(Ljava/lang/Object;)Z
      83: pop
      84: aload_0
      85: aload         5
      87: invokespecial #154                // Method toList:(Ljava/util/Set;)Ljava/util/List;
      90: astore        6
      92: aload_3
      93: invokeinterface #155,  1          // InterfaceMethod java/util/Map$Entry.getValue:()Ljava/lang/Object;
      98: checkcast     #68                 // class java/util/Set
     101: invokeinterface #108,  1          // InterfaceMethod java/util/Set.iterator:()Ljava/util/Iterator;
     106: astore        7
     108: aload         7
     110: invokeinterface #66,  1           // InterfaceMethod java/util/Iterator.hasNext:()Z
     115: ifeq          168
     118: aload         7
     120: invokeinterface #67,  1           // InterfaceMethod java/util/Iterator.next:()Ljava/lang/Object;
     125: checkcast     #156                // class org/apache/dubbo/registry/NotifyListener
     128: astore        8
     130: aload_0
     131: aload         4
     133: aload         8
     135: aload         6
     137: invokevirtual #157                // Method notify:(Lorg/apache/dubbo/common/URL;Lorg/apache/dubbo/registry/NotifyListener;Ljava/util/List;)V
     140: aload         8
     142: dup
     143: astore        9
     145: monitorenter
     146: aload         8
     148: invokevirtual #158                // Method java/lang/Object.notify:()V
     151: aload         9
     153: monitorexit
     154: goto          165
     157: astore        10
     159: aload         9
     161: monitorexit
     162: aload         10
     164: athrow
     165: goto          108
     168: goto          15
     171: return
    Exception table:
       from    to  target type
         146   154   157   any
         157   162   157   any

  protected void unregistered(org.apache.dubbo.common.URL);
    Code:
       0: aload_0
       1: invokevirtual #147                // Method getSubscribed:()Ljava/util/Map;
       4: invokeinterface #148,  1          // InterfaceMethod java/util/Map.entrySet:()Ljava/util/Set;
       9: invokeinterface #108,  1          // InterfaceMethod java/util/Set.iterator:()Ljava/util/Iterator;
      14: astore_2
      15: aload_2
      16: invokeinterface #66,  1           // InterfaceMethod java/util/Iterator.hasNext:()Z
      21: ifeq          193
      24: aload_2
      25: invokeinterface #67,  1           // InterfaceMethod java/util/Iterator.next:()Ljava/lang/Object;
      30: checkcast     #149                // class java/util/Map$Entry
      33: astore_3
      34: aload_3
      35: invokeinterface #150,  1          // InterfaceMethod java/util/Map$Entry.getKey:()Ljava/lang/Object;
      40: checkcast     #69                 // class org/apache/dubbo/common/URL
      43: astore        4
      45: aload         4
      47: aload_1
      48: invokestatic  #109                // Method org/apache/dubbo/common/utils/UrlUtils.isMatch:(Lorg/apache/dubbo/common/URL;Lorg/apache/dubbo/common/URL;)Z
      51: ifeq          190
      54: aload_0
      55: getfield      #9                  // Field received:Ljava/util/concurrent/ConcurrentMap;
      58: aload         4
      60: invokeinterface #159,  2          // InterfaceMethod java/util/concurrent/ConcurrentMap.get:(Ljava/lang/Object;)Ljava/lang/Object;
      65: checkcast     #68                 // class java/util/Set
      68: astore        5
      70: aload         5
      72: ifnull        84
      75: aload         5
      77: aload_1
      78: invokeinterface #160,  2          // InterfaceMethod java/util/Set.remove:(Ljava/lang/Object;)Z
      83: pop
      84: aload         5
      86: ifnull        99
      89: aload         5
      91: invokeinterface #161,  1          // InterfaceMethod java/util/Set.isEmpty:()Z
      96: ifeq          131
      99: aload         5
     101: ifnonnull     113
     104: new           #162                // class org/apache/dubbo/common/utils/ConcurrentHashSet
     107: dup
     108: invokespecial #163                // Method org/apache/dubbo/common/utils/ConcurrentHashSet."<init>":()V
     111: astore        5
     113: aload_1
     114: ldc           #164                // String empty
     116: invokevirtual #165                // Method org/apache/dubbo/common/URL.setProtocol:(Ljava/lang/String;)Lorg/apache/dubbo/common/URL;
     119: astore        6
     121: aload         5
     123: aload         6
     125: invokeinterface #153,  2          // InterfaceMethod java/util/Set.add:(Ljava/lang/Object;)Z
     130: pop
     131: aload_0
     132: aload         5
     134: invokespecial #154                // Method toList:(Ljava/util/Set;)Ljava/util/List;
     137: astore        6
     139: aload_3
     140: invokeinterface #155,  1          // InterfaceMethod java/util/Map$Entry.getValue:()Ljava/lang/Object;
     145: checkcast     #68                 // class java/util/Set
     148: invokeinterface #108,  1          // InterfaceMethod java/util/Set.iterator:()Ljava/util/Iterator;
     153: astore        7
     155: aload         7
     157: invokeinterface #66,  1           // InterfaceMethod java/util/Iterator.hasNext:()Z
     162: ifeq          190
     165: aload         7
     167: invokeinterface #67,  1           // InterfaceMethod java/util/Iterator.next:()Ljava/lang/Object;
     172: checkcast     #156                // class org/apache/dubbo/registry/NotifyListener
     175: astore        8
     177: aload_0
     178: aload         4
     180: aload         8
     182: aload         6
     184: invokevirtual #157                // Method notify:(Lorg/apache/dubbo/common/URL;Lorg/apache/dubbo/registry/NotifyListener;Ljava/util/List;)V
     187: goto          155
     190: goto          15
     193: return

  protected void subscribed(org.apache.dubbo.common.URL, org.apache.dubbo.registry.NotifyListener);
    Code:
       0: aload_0
       1: aload_1
       2: invokevirtual #166                // Method lookup:(Lorg/apache/dubbo/common/URL;)Ljava/util/List;
       5: astore_3
       6: aload_0
       7: aload_1
       8: aload_2
       9: aload_3
      10: invokevirtual #157                // Method notify:(Lorg/apache/dubbo/common/URL;Lorg/apache/dubbo/registry/NotifyListener;Ljava/util/List;)V
      13: return

  private java.util.List<org.apache.dubbo.common.URL> toList(java.util.Set<org.apache.dubbo.common.URL>);
    Code:
       0: new           #167                // class java/util/ArrayList
       3: dup
       4: invokespecial #168                // Method java/util/ArrayList."<init>":()V
       7: astore_2
       8: aload_1
       9: invokestatic  #107                // Method org/apache/dubbo/common/utils/CollectionUtils.isNotEmpty:(Ljava/util/Collection;)Z
      12: ifeq          23
      15: aload_2
      16: aload_1
      17: invokeinterface #169,  2          // InterfaceMethod java/util/List.addAll:(Ljava/util/Collection;)Z
      22: pop
      23: aload_2
      24: areturn

  public void register(org.apache.dubbo.common.URL);
    Code:
       0: aload_0
       1: aload_1
       2: invokespecial #170                // Method org/apache/dubbo/registry/support/FailbackRegistry.register:(Lorg/apache/dubbo/common/URL;)V
       5: aload_0
       6: aload_1
       7: invokevirtual #102                // Method registered:(Lorg/apache/dubbo/common/URL;)V
      10: return

  public void unregister(org.apache.dubbo.common.URL);
    Code:
       0: aload_0
       1: aload_1
       2: invokespecial #171                // Method org/apache/dubbo/registry/support/FailbackRegistry.unregister:(Lorg/apache/dubbo/common/URL;)V
       5: aload_0
       6: aload_1
       7: invokevirtual #104                // Method unregistered:(Lorg/apache/dubbo/common/URL;)V
      10: return

  public void subscribe(org.apache.dubbo.common.URL, org.apache.dubbo.registry.NotifyListener);
    Code:
       0: aload_0
       1: aload_1
       2: aload_2
       3: invokespecial #172                // Method org/apache/dubbo/registry/support/FailbackRegistry.subscribe:(Lorg/apache/dubbo/common/URL;Lorg/apache/dubbo/registry/NotifyListener;)V
       6: aload_0
       7: aload_1
       8: aload_2
       9: invokevirtual #173                // Method subscribed:(Lorg/apache/dubbo/common/URL;Lorg/apache/dubbo/registry/NotifyListener;)V
      12: return

  public void unsubscribe(org.apache.dubbo.common.URL, org.apache.dubbo.registry.NotifyListener);
    Code:
       0: aload_0
       1: aload_1
       2: aload_2
       3: invokespecial #174                // Method org/apache/dubbo/registry/support/FailbackRegistry.unsubscribe:(Lorg/apache/dubbo/common/URL;Lorg/apache/dubbo/registry/NotifyListener;)V
       6: aload_0
       7: getfield      #9                  // Field received:Ljava/util/concurrent/ConcurrentMap;
      10: aload_1
      11: invokeinterface #175,  2          // InterfaceMethod java/util/concurrent/ConcurrentMap.remove:(Ljava/lang/Object;)Ljava/lang/Object;
      16: pop
      17: return

  public java.util.List<org.apache.dubbo.common.URL> lookup(org.apache.dubbo.common.URL);
    Code:
       0: new           #167                // class java/util/ArrayList
       3: dup
       4: invokespecial #168                // Method java/util/ArrayList."<init>":()V
       7: astore_2
       8: aload_0
       9: invokevirtual #176                // Method getNotified:()Ljava/util/Map;
      12: aload_1
      13: invokeinterface #177,  2          // InterfaceMethod java/util/Map.get:(Ljava/lang/Object;)Ljava/lang/Object;
      18: checkcast     #178                // class java/util/Map
      21: astore_3
      22: aload_3
      23: ifnull        82
      26: aload_3
      27: invokeinterface #179,  1          // InterfaceMethod java/util/Map.size:()I
      32: ifle          82
      35: aload_3
      36: invokeinterface #180,  1          // InterfaceMethod java/util/Map.values:()Ljava/util/Collection;
      41: invokeinterface #181,  1          // InterfaceMethod java/util/Collection.iterator:()Ljava/util/Iterator;
      46: astore        4
      48: aload         4
      50: invokeinterface #66,  1           // InterfaceMethod java/util/Iterator.hasNext:()Z
      55: ifeq          82
      58: aload         4
      60: invokeinterface #67,  1           // InterfaceMethod java/util/Iterator.next:()Ljava/lang/Object;
      65: checkcast     #182                // class java/util/List
      68: astore        5
      70: aload_2
      71: aload         5
      73: invokeinterface #169,  2          // InterfaceMethod java/util/List.addAll:(Ljava/util/Collection;)Z
      78: pop
      79: goto          48
      82: aload_2
      83: invokeinterface #183,  1          // InterfaceMethod java/util/List.isEmpty:()Z
      88: ifeq          115
      91: aload_0
      92: aload_1
      93: invokevirtual #184                // Method getCacheUrls:(Lorg/apache/dubbo/common/URL;)Ljava/util/List;
      96: astore        4
      98: aload         4
     100: invokestatic  #107                // Method org/apache/dubbo/common/utils/CollectionUtils.isNotEmpty:(Ljava/util/Collection;)Z
     103: ifeq          115
     106: aload_2
     107: aload         4
     109: invokeinterface #169,  2          // InterfaceMethod java/util/List.addAll:(Ljava/util/Collection;)Z
     114: pop
     115: aload_2
     116: invokeinterface #183,  1          // InterfaceMethod java/util/List.isEmpty:()Z
     121: ifeq          178
     124: aload_0
     125: invokevirtual #106                // Method getRegistered:()Ljava/util/Set;
     128: invokeinterface #108,  1          // InterfaceMethod java/util/Set.iterator:()Ljava/util/Iterator;
     133: astore        4
     135: aload         4
     137: invokeinterface #66,  1           // InterfaceMethod java/util/Iterator.hasNext:()Z
     142: ifeq          178
     145: aload         4
     147: invokeinterface #67,  1           // InterfaceMethod java/util/Iterator.next:()Ljava/lang/Object;
     152: checkcast     #69                 // class org/apache/dubbo/common/URL
     155: astore        5
     157: aload_1
     158: aload         5
     160: invokestatic  #109                // Method org/apache/dubbo/common/utils/UrlUtils.isMatch:(Lorg/apache/dubbo/common/URL;Lorg/apache/dubbo/common/URL;)Z
     163: ifeq          175
     166: aload_2
     167: aload         5
     169: invokeinterface #185,  2          // InterfaceMethod java/util/List.add:(Ljava/lang/Object;)Z
     174: pop
     175: goto          135
     178: ldc           #132                // String *
     180: aload_1
     181: invokevirtual #133                // Method org/apache/dubbo/common/URL.getServiceInterface:()Ljava/lang/String;
     184: invokevirtual #81                 // Method java/lang/String.equals:(Ljava/lang/Object;)Z
     187: ifeq          249
     190: aload_0
     191: invokevirtual #147                // Method getSubscribed:()Ljava/util/Map;
     194: invokeinterface #186,  1          // InterfaceMethod java/util/Map.keySet:()Ljava/util/Set;
     199: invokeinterface #108,  1          // InterfaceMethod java/util/Set.iterator:()Ljava/util/Iterator;
     204: astore        4
     206: aload         4
     208: invokeinterface #66,  1           // InterfaceMethod java/util/Iterator.hasNext:()Z
     213: ifeq          249
     216: aload         4
     218: invokeinterface #67,  1           // InterfaceMethod java/util/Iterator.next:()Ljava/lang/Object;
     223: checkcast     #69                 // class org/apache/dubbo/common/URL
     226: astore        5
     228: aload_1
     229: aload         5
     231: invokestatic  #109                // Method org/apache/dubbo/common/utils/UrlUtils.isMatch:(Lorg/apache/dubbo/common/URL;Lorg/apache/dubbo/common/URL;)Z
     234: ifeq          246
     237: aload_2
     238: aload         5
     240: invokeinterface #185,  2          // InterfaceMethod java/util/List.add:(Ljava/lang/Object;)Z
     245: pop
     246: goto          206
     249: aload_2
     250: areturn

  public java.net.MulticastSocket getMulticastSocket();
    Code:
       0: aload_0
       1: getfield      #29                 // Field multicastSocket:Ljava/net/MulticastSocket;
       4: areturn

  public java.util.Map<org.apache.dubbo.common.URL, java.util.Set<org.apache.dubbo.common.URL>> getReceived();
    Code:
       0: aload_0
       1: getfield      #9                  // Field received:Ljava/util/concurrent/ConcurrentMap;
       4: areturn

  private static java.util.Set lambda$registered$2(org.apache.dubbo.common.URL);
    Code:
       0: new           #162                // class org/apache/dubbo/common/utils/ConcurrentHashSet
       3: dup
       4: invokespecial #163                // Method org/apache/dubbo/common/utils/ConcurrentHashSet."<init>":()V
       7: areturn

  private void lambda$new$1();
    Code:
       0: aload_0
       1: invokespecial #187                // Method clean:()V
       4: goto          45
       7: astore_1
       8: getstatic     #71                 // Field logger:Lorg/apache/dubbo/common/logger/ErrorTypeAwareLogger;
      11: ldc           #73                 // String 1-38
      13: ldc           #74                 // String
      15: ldc           #74                 // String
      17: new           #51                 // class java/lang/StringBuilder
      20: dup
      21: invokespecial #52                 // Method java/lang/StringBuilder."<init>":()V
      24: ldc           #188                // String Unexpected exception occur at clean expired provider, cause:
      26: invokevirtual #54                 // Method java/lang/StringBuilder.append:(Ljava/lang/String;)Ljava/lang/StringBuilder;
      29: aload_1
      30: invokevirtual #142                // Method java/lang/Throwable.getMessage:()Ljava/lang/String;
      33: invokevirtual #54                 // Method java/lang/StringBuilder.append:(Ljava/lang/String;)Ljava/lang/StringBuilder;
      36: invokevirtual #56                 // Method java/lang/StringBuilder.toString:()Ljava/lang/String;
      39: aload_1
      40: invokeinterface #189,  6          // InterfaceMethod org/apache/dubbo/common/logger/ErrorTypeAwareLogger.error:(Ljava/lang/String;Ljava/lang/String;Ljava/lang/String;Ljava/lang/String;Ljava/lang/Throwable;)V
      45: return
    Exception table:
       from    to  target type
           0     4     7   Class java/lang/Throwable

  private void lambda$new$0();
    Code:
       0: sipush        2048
       3: newarray       byte
       5: astore_1
       6: new           #125                // class java/net/DatagramPacket
       9: dup
      10: aload_1
      11: aload_1
      12: arraylength
      13: invokespecial #190                // Method java/net/DatagramPacket."<init>":([BI)V
      16: astore_2
      17: aload_0
      18: getfield      #29                 // Field multicastSocket:Ljava/net/MulticastSocket;
      21: invokevirtual #191                // Method java/net/MulticastSocket.isClosed:()Z
      24: ifne          127
      27: aload_0
      28: getfield      #29                 // Field multicastSocket:Ljava/net/MulticastSocket;
      31: aload_2
      32: invokevirtual #192                // Method java/net/MulticastSocket.receive:(Ljava/net/DatagramPacket;)V
      35: new           #193                // class java/lang/String
      38: dup
      39: aload_2
      40: invokevirtual #194                // Method java/net/DatagramPacket.getData:()[B
      43: invokespecial #195                // Method java/lang/String."<init>":([B)V
      46: invokevirtual #100                // Method java/lang/String.trim:()Ljava/lang/String;
      49: astore_3
      50: aload_3
      51: bipush        10
      53: invokevirtual #196                // Method java/lang/String.indexOf:(I)I
      56: istore        4
      58: iload         4
      60: ifle          74
      63: aload_3
      64: iconst_0
      65: iload         4
      67: invokevirtual #197                // Method java/lang/String.substring:(II)Ljava/lang/String;
      70: invokevirtual #100                // Method java/lang/String.trim:()Ljava/lang/String;
      73: astore_3
      74: aload_0
      75: aload_3
      76: aload_2
      77: invokevirtual #198                // Method java/net/DatagramPacket.getSocketAddress:()Ljava/net/SocketAddress;
      80: checkcast     #199                // class java/net/InetSocketAddress
      83: invokespecial #200                // Method receive:(Ljava/lang/String;Ljava/net/InetSocketAddress;)V
      86: aload_1
      87: iconst_0
      88: invokestatic  #201                // Method java/util/Arrays.fill:([BB)V
      91: goto          17
      94: astore_3
      95: aload_0
      96: getfield      #29                 // Field multicastSocket:Ljava/net/MulticastSocket;
      99: invokevirtual #191                // Method java/net/MulticastSocket.isClosed:()Z
     102: ifne          124
     105: getstatic     #71                 // Field logger:Lorg/apache/dubbo/common/logger/ErrorTypeAwareLogger;
     108: ldc           #73                 // String 1-38
     110: ldc           #74                 // String
     112: ldc           #74                 // String
     114: aload_3
     115: invokevirtual #142                // Method java/lang/Throwable.getMessage:()Ljava/lang/String;
     118: aload_3
     119: invokeinterface #189,  6          // InterfaceMethod org/apache/dubbo/common/logger/ErrorTypeAwareLogger.error:(Ljava/lang/String;Ljava/lang/String;Ljava/lang/String;Ljava/lang/String;Ljava/lang/Throwable;)V
     124: goto          17
     127: return
    Exception table:
       from    to  target type
          27    91    94   Class java/lang/Throwable

  static {};
    Code:
       0: ldc           #25                 // class org/apache/dubbo/registry/multicast/MulticastRegistry
       2: invokestatic  #202                // Method org/apache/dubbo/common/logger/LoggerFactory.getErrorTypeAwareLogger:(Ljava/lang/Class;)Lorg/apache/dubbo/common/logger/ErrorTypeAwareLogger;
       5: putstatic     #71                 // Field logger:Lorg/apache/dubbo/common/logger/ErrorTypeAwareLogger;
       8: return
}
