Compiled from "MulticastServiceDiscovery.java"
public class org.apache.dubbo.registry.multicast.MulticastServiceDiscovery extends org.apache.dubbo.registry.client.AbstractServiceDiscovery {
  public org.apache.dubbo.registry.multicast.MulticastServiceDiscovery(org.apache.dubbo.rpc.model.ApplicationModel, org.apache.dubbo.common.URL);
    Code:
       0: aload_0
       1: aload_1
       2: aload_2
       3: invokespecial #1                  // Method org/apache/dubbo/registry/client/AbstractServiceDiscovery."<init>":(Lorg/apache/dubbo/rpc/model/ApplicationModel;Lorg/apache/dubbo/common/URL;)V
       6: return

  public org.apache.dubbo.registry.multicast.MulticastServiceDiscovery(java.lang.String, org.apache.dubbo.common.URL);
    Code:
       0: aload_0
       1: aload_1
       2: aload_2
       3: invokespecial #2                  // Method org/apache/dubbo/registry/client/AbstractServiceDiscovery."<init>":(Ljava/lang/String;Lorg/apache/dubbo/common/URL;)V
       6: return

  public void doDestroy() throws java.lang.Exception;
    Code:
       0: return

  public void doRegister(org.apache.dubbo.registry.client.ServiceInstance) throws java.lang.RuntimeException;
    Code:
       0: return

  public void doUpdate(org.apache.dubbo.registry.client.ServiceInstance, org.apache.dubbo.registry.client.ServiceInstance) throws java.lang.RuntimeException;
    Code:
       0: return

  public void doUnregister(org.apache.dubbo.registry.client.ServiceInstance) throws java.lang.RuntimeException;
    Code:
       0: aload_0
       1: aconst_null
       2: putfield      #3                  // Field serviceInstance:Lorg/apache/dubbo/registry/client/ServiceInstance;
       5: return

  public java.util.Set<java.lang.String> getServices();
    Code:
       0: ldc           #4                  // String Unsupported Operation
       2: invokestatic  #5                  // Method java/util/Collections.singleton:(Ljava/lang/Object;)Ljava/util/Set;
       5: areturn

  public java.util.List<org.apache.dubbo.registry.client.ServiceInstance> getInstances(java.lang.String) throws java.lang.NullPointerException;
    Code:
       0: aconst_null
       1: areturn

  public org.apache.dubbo.common.URL getUrl();
    Code:
       0: aload_0
       1: getfield      #6                  // Field registryURL:Lorg/apache/dubbo/common/URL;
       4: areturn
}
