Compiled from "StubProxyFactoryWrapper.java"
public class org.apache.dubbo.rpc.proxy.wrapper.StubProxyFactoryWrapper implements org.apache.dubbo.rpc.ProxyFactory {
  private static final org.apache.dubbo.common.logger.ErrorTypeAwareLogger LOGGER;

  private final org.apache.dubbo.rpc.ProxyFactory proxyFactory;

  private org.apache.dubbo.rpc.Protocol protocol;

  public org.apache.dubbo.rpc.proxy.wrapper.StubProxyFactoryWrapper(org.apache.dubbo.rpc.ProxyFactory);
    Code:
       0: aload_0
       1: invokespecial #4                  // Method java/lang/Object."<init>":()V
       4: aload_0
       5: aload_1
       6: putfield      #5                  // Field proxyFactory:Lorg/apache/dubbo/rpc/ProxyFactory;
       9: return

  public void setProtocol(org.apache.dubbo.rpc.Protocol);
    Code:
       0: aload_0
       1: aload_1
       2: putfield      #6                  // Field protocol:Lorg/apache/dubbo/rpc/Protocol;
       5: return

  public <T> T getProxy(org.apache.dubbo.rpc.Invoker<T>, boolean) throws org.apache.dubbo.rpc.RpcException;
    Code:
       0: aload_0
       1: getfield      #5                  // Field proxyFactory:Lorg/apache/dubbo/rpc/ProxyFactory;
       4: aload_1
       5: iload_2
       6: invokeinterface #7,  3            // InterfaceMethod org/apache/dubbo/rpc/ProxyFactory.getProxy:(Lorg/apache/dubbo/rpc/Invoker;Z)Ljava/lang/Object;
      11: astore_3
      12: ldc           #8                  // class org/apache/dubbo/rpc/service/GenericService
      14: aload_1
      15: invokeinterface #9,  1            // InterfaceMethod org/apache/dubbo/rpc/Invoker.getInterface:()Ljava/lang/Class;
      20: if_acmpeq     453
      23: aload_1
      24: invokeinterface #10,  1           // InterfaceMethod org/apache/dubbo/rpc/Invoker.getUrl:()Lorg/apache/dubbo/common/URL;
      29: astore        4
      31: aload         4
      33: ldc           #11                 // String stub
      35: aload         4
      37: ldc           #12                 // String local
      39: invokevirtual #13                 // Method org/apache/dubbo/common/URL.getParameter:(Ljava/lang/String;)Ljava/lang/String;
      42: invokevirtual #14                 // Method org/apache/dubbo/common/URL.getParameter:(Ljava/lang/String;Ljava/lang/String;)Ljava/lang/String;
      45: astore        5
      47: aload         5
      49: invokestatic  #15                 // Method org/apache/dubbo/common/utils/ConfigUtils.isNotEmpty:(Ljava/lang/String;)Z
      52: ifeq          453
      55: aload_1
      56: invokeinterface #9,  1            // InterfaceMethod org/apache/dubbo/rpc/Invoker.getInterface:()Ljava/lang/Class;
      61: astore        6
      63: aload         5
      65: invokestatic  #16                 // Method org/apache/dubbo/common/utils/ConfigUtils.isDefault:(Ljava/lang/String;)Z
      68: ifeq          134
      71: aload         4
      73: ldc           #11                 // String stub
      75: invokevirtual #17                 // Method org/apache/dubbo/common/URL.hasParameter:(Ljava/lang/String;)Z
      78: ifeq          109
      81: new           #18                 // class java/lang/StringBuilder
      84: dup
      85: invokespecial #19                 // Method java/lang/StringBuilder."<init>":()V
      88: aload         6
      90: invokevirtual #20                 // Method java/lang/Class.getName:()Ljava/lang/String;
      93: invokevirtual #21                 // Method java/lang/StringBuilder.append:(Ljava/lang/String;)Ljava/lang/StringBuilder;
      96: ldc           #22                 // String Stub
      98: invokevirtual #21                 // Method java/lang/StringBuilder.append:(Ljava/lang/String;)Ljava/lang/StringBuilder;
     101: invokevirtual #23                 // Method java/lang/StringBuilder.toString:()Ljava/lang/String;
     104: astore        5
     106: goto          134
     109: new           #18                 // class java/lang/StringBuilder
     112: dup
     113: invokespecial #19                 // Method java/lang/StringBuilder."<init>":()V
     116: aload         6
     118: invokevirtual #20                 // Method java/lang/Class.getName:()Ljava/lang/String;
     121: invokevirtual #21                 // Method java/lang/StringBuilder.append:(Ljava/lang/String;)Ljava/lang/StringBuilder;
     124: ldc           #24                 // String Local
     126: invokevirtual #21                 // Method java/lang/StringBuilder.append:(Ljava/lang/String;)Ljava/lang/StringBuilder;
     129: invokevirtual #23                 // Method java/lang/StringBuilder.toString:()Ljava/lang/String;
     132: astore        5
     134: aload         5
     136: invokestatic  #25                 // Method org/apache/dubbo/common/utils/ReflectUtils.forName:(Ljava/lang/String;)Ljava/lang/Class;
     139: astore        7
     141: aload         6
     143: aload         7
     145: invokevirtual #26                 // Method java/lang/Class.isAssignableFrom:(Ljava/lang/Class;)Z
     148: ifne          195
     151: new           #27                 // class java/lang/IllegalStateException
     154: dup
     155: new           #18                 // class java/lang/StringBuilder
     158: dup
     159: invokespecial #19                 // Method java/lang/StringBuilder."<init>":()V
     162: ldc           #28                 // String The stub implementation class
     164: invokevirtual #21                 // Method java/lang/StringBuilder.append:(Ljava/lang/String;)Ljava/lang/StringBuilder;
     167: aload         7
     169: invokevirtual #20                 // Method java/lang/Class.getName:()Ljava/lang/String;
     172: invokevirtual #21                 // Method java/lang/StringBuilder.append:(Ljava/lang/String;)Ljava/lang/StringBuilder;
     175: ldc           #29                 // String  not implement interface
     177: invokevirtual #21                 // Method java/lang/StringBuilder.append:(Ljava/lang/String;)Ljava/lang/StringBuilder;
     180: aload         6
     182: invokevirtual #20                 // Method java/lang/Class.getName:()Ljava/lang/String;
     185: invokevirtual #21                 // Method java/lang/StringBuilder.append:(Ljava/lang/String;)Ljava/lang/StringBuilder;
     188: invokevirtual #23                 // Method java/lang/StringBuilder.toString:()Ljava/lang/String;
     191: invokespecial #30                 // Method java/lang/IllegalStateException."<init>":(Ljava/lang/String;)V
     194: athrow
     195: aload         7
     197: aload         6
     199: invokestatic  #31                 // Method org/apache/dubbo/common/utils/ReflectUtils.findConstructor:(Ljava/lang/Class;Ljava/lang/Class;)Ljava/lang/reflect/Constructor;
     202: astore        8
     204: aload         8
     206: iconst_1
     207: anewarray     #32                 // class java/lang/Object
     210: dup
     211: iconst_0
     212: aload_3
     213: aastore
     214: invokevirtual #33                 // Method java/lang/reflect/Constructor.newInstance:([Ljava/lang/Object;)Ljava/lang/Object;
     217: astore_3
     218: aload         4
     220: invokestatic  #34                 // Method org/apache/dubbo/common/URLBuilder.from:(Lorg/apache/dubbo/common/URL;)Lorg/apache/dubbo/common/URLBuilder;
     223: astore        9
     225: aload         4
     227: ldc           #35                 // String dubbo.stub.event
     229: iconst_0
     230: invokevirtual #36                 // Method org/apache/dubbo/common/URL.getParameter:(Ljava/lang/String;Z)Z
     233: ifeq          313
     236: aload         9
     238: ldc           #37                 // String dubbo.stub.event.methods
     240: aload_3
     241: invokevirtual #38                 // Method java/lang/Object.getClass:()Ljava/lang/Class;
     244: invokestatic  #39                 // Method org/apache/dubbo/common/bytecode/Wrapper.getWrapper:(Ljava/lang/Class;)Lorg/apache/dubbo/common/bytecode/Wrapper;
     247: invokevirtual #40                 // Method org/apache/dubbo/common/bytecode/Wrapper.getDeclaredMethodNames:()[Ljava/lang/String;
     250: ldc           #41                 // String ,
     252: invokestatic  #42                 // Method org/apache/dubbo/common/utils/StringUtils.join:([Ljava/lang/String;Ljava/lang/String;)Ljava/lang/String;
     255: invokevirtual #43                 // Method org/apache/dubbo/common/URLBuilder.addParameter:(Ljava/lang/String;Ljava/lang/String;)Lorg/apache/dubbo/common/URLBuilder;
     258: pop
     259: aload         9
     261: ldc           #44                 // String isserver
     263: getstatic     #45                 // Field java/lang/Boolean.FALSE:Ljava/lang/Boolean;
     266: invokevirtual #46                 // Method java/lang/Boolean.toString:()Ljava/lang/String;
     269: invokevirtual #43                 // Method org/apache/dubbo/common/URLBuilder.addParameter:(Ljava/lang/String;Ljava/lang/String;)Lorg/apache/dubbo/common/URLBuilder;
     272: pop
     273: aload_0
     274: aload_3
     275: aload_1
     276: invokeinterface #9,  1            // InterfaceMethod org/apache/dubbo/rpc/Invoker.getInterface:()Ljava/lang/Class;
     281: aload         9
     283: invokevirtual #47                 // Method org/apache/dubbo/common/URLBuilder.build:()Lorg/apache/dubbo/common/url/component/ServiceConfigURL;
     286: invokespecial #48                 // Method export:(Ljava/lang/Object;Ljava/lang/Class;Lorg/apache/dubbo/common/URL;)Lorg/apache/dubbo/rpc/Exporter;
     289: pop
     290: goto          313
     293: astore        10
     295: getstatic     #50                 // Field LOGGER:Lorg/apache/dubbo/common/logger/ErrorTypeAwareLogger;
     298: ldc           #51                 // String 3-2
     300: ldc           #52                 // String
     302: ldc           #52                 // String
     304: ldc           #53                 // String export a stub service error.
     306: aload         10
     308: invokeinterface #54,  6           // InterfaceMethod org/apache/dubbo/common/logger/ErrorTypeAwareLogger.error:(Ljava/lang/String;Ljava/lang/String;Ljava/lang/String;Ljava/lang/String;Ljava/lang/Throwable;)V
     313: goto          377
     316: astore        8
     318: new           #27                 // class java/lang/IllegalStateException
     321: dup
     322: new           #18                 // class java/lang/StringBuilder
     325: dup
     326: invokespecial #19                 // Method java/lang/StringBuilder."<init>":()V
     329: ldc           #56                 // String No such constructor \"public
     331: invokevirtual #21                 // Method java/lang/StringBuilder.append:(Ljava/lang/String;)Ljava/lang/StringBuilder;
     334: aload         7
     336: invokevirtual #57                 // Method java/lang/Class.getSimpleName:()Ljava/lang/String;
     339: invokevirtual #21                 // Method java/lang/StringBuilder.append:(Ljava/lang/String;)Ljava/lang/StringBuilder;
     342: ldc           #58                 // String (
     344: invokevirtual #21                 // Method java/lang/StringBuilder.append:(Ljava/lang/String;)Ljava/lang/StringBuilder;
     347: aload         6
     349: invokevirtual #20                 // Method java/lang/Class.getName:()Ljava/lang/String;
     352: invokevirtual #21                 // Method java/lang/StringBuilder.append:(Ljava/lang/String;)Ljava/lang/StringBuilder;
     355: ldc           #59                 // String )\" in stub implementation class
     357: invokevirtual #21                 // Method java/lang/StringBuilder.append:(Ljava/lang/String;)Ljava/lang/StringBuilder;
     360: aload         7
     362: invokevirtual #20                 // Method java/lang/Class.getName:()Ljava/lang/String;
     365: invokevirtual #21                 // Method java/lang/StringBuilder.append:(Ljava/lang/String;)Ljava/lang/StringBuilder;
     368: invokevirtual #23                 // Method java/lang/StringBuilder.toString:()Ljava/lang/String;
     371: aload         8
     373: invokespecial #60                 // Method java/lang/IllegalStateException."<init>":(Ljava/lang/String;Ljava/lang/Throwable;)V
     376: athrow
     377: goto          453
     380: astore        7
     382: getstatic     #50                 // Field LOGGER:Lorg/apache/dubbo/common/logger/ErrorTypeAwareLogger;
     385: ldc           #51                 // String 3-2
     387: ldc           #52                 // String
     389: ldc           #52                 // String
     391: new           #18                 // class java/lang/StringBuilder
     394: dup
     395: invokespecial #19                 // Method java/lang/StringBuilder."<init>":()V
     398: ldc           #62                 // String Failed to create stub implementation class
     400: invokevirtual #21                 // Method java/lang/StringBuilder.append:(Ljava/lang/String;)Ljava/lang/StringBuilder;
     403: aload         5
     405: invokevirtual #21                 // Method java/lang/StringBuilder.append:(Ljava/lang/String;)Ljava/lang/StringBuilder;
     408: ldc           #63                 // String  in consumer
     410: invokevirtual #21                 // Method java/lang/StringBuilder.append:(Ljava/lang/String;)Ljava/lang/StringBuilder;
     413: invokestatic  #64                 // Method org/apache/dubbo/common/utils/NetUtils.getLocalHost:()Ljava/lang/String;
     416: invokevirtual #21                 // Method java/lang/StringBuilder.append:(Ljava/lang/String;)Ljava/lang/StringBuilder;
     419: ldc           #65                 // String  use dubbo version
     421: invokevirtual #21                 // Method java/lang/StringBuilder.append:(Ljava/lang/String;)Ljava/lang/StringBuilder;
     424: invokestatic  #66                 // Method org/apache/dubbo/common/Version.getVersion:()Ljava/lang/String;
     427: invokevirtual #21                 // Method java/lang/StringBuilder.append:(Ljava/lang/String;)Ljava/lang/StringBuilder;
     430: ldc           #67                 // String , cause:
     432: invokevirtual #21                 // Method java/lang/StringBuilder.append:(Ljava/lang/String;)Ljava/lang/StringBuilder;
     435: aload         7
     437: invokevirtual #68                 // Method java/lang/Throwable.getMessage:()Ljava/lang/String;
     440: invokevirtual #21                 // Method java/lang/StringBuilder.append:(Ljava/lang/String;)Ljava/lang/StringBuilder;
     443: invokevirtual #23                 // Method java/lang/StringBuilder.toString:()Ljava/lang/String;
     446: aload         7
     448: invokeinterface #54,  6           // InterfaceMethod org/apache/dubbo/common/logger/ErrorTypeAwareLogger.error:(Ljava/lang/String;Ljava/lang/String;Ljava/lang/String;Ljava/lang/String;Ljava/lang/Throwable;)V
     453: aload_3
     454: areturn
    Exception table:
       from    to  target type
         273   290   293   Class java/lang/Exception
         195   313   316   Class java/lang/NoSuchMethodException
         134   377   380   Class java/lang/Throwable

  public <T> T getProxy(org.apache.dubbo.rpc.Invoker<T>) throws org.apache.dubbo.rpc.RpcException;
    Code:
       0: aload_0
       1: aload_1
       2: iconst_0
       3: invokevirtual #69                 // Method getProxy:(Lorg/apache/dubbo/rpc/Invoker;Z)Ljava/lang/Object;
       6: areturn

  public <T> org.apache.dubbo.rpc.Invoker<T> getInvoker(T, java.lang.Class<T>, org.apache.dubbo.common.URL) throws org.apache.dubbo.rpc.RpcException;
    Code:
       0: aload_0
       1: getfield      #5                  // Field proxyFactory:Lorg/apache/dubbo/rpc/ProxyFactory;
       4: aload_1
       5: aload_2
       6: aload_3
       7: invokeinterface #70,  4           // InterfaceMethod org/apache/dubbo/rpc/ProxyFactory.getInvoker:(Ljava/lang/Object;Ljava/lang/Class;Lorg/apache/dubbo/common/URL;)Lorg/apache/dubbo/rpc/Invoker;
      12: areturn

  private <T> org.apache.dubbo.rpc.Exporter<T> export(T, java.lang.Class<T>, org.apache.dubbo.common.URL);
    Code:
       0: aload_0
       1: getfield      #6                  // Field protocol:Lorg/apache/dubbo/rpc/Protocol;
       4: aload_0
       5: getfield      #5                  // Field proxyFactory:Lorg/apache/dubbo/rpc/ProxyFactory;
       8: aload_1
       9: aload_2
      10: aload_3
      11: invokeinterface #70,  4           // InterfaceMethod org/apache/dubbo/rpc/ProxyFactory.getInvoker:(Ljava/lang/Object;Ljava/lang/Class;Lorg/apache/dubbo/common/URL;)Lorg/apache/dubbo/rpc/Invoker;
      16: invokeinterface #71,  2           // InterfaceMethod org/apache/dubbo/rpc/Protocol.export:(Lorg/apache/dubbo/rpc/Invoker;)Lorg/apache/dubbo/rpc/Exporter;
      21: areturn

  static {};
    Code:
       0: ldc           #72                 // class org/apache/dubbo/rpc/proxy/wrapper/StubProxyFactoryWrapper
       2: invokestatic  #73                 // Method org/apache/dubbo/common/logger/LoggerFactory.getErrorTypeAwareLogger:(Ljava/lang/Class;)Lorg/apache/dubbo/common/logger/ErrorTypeAwareLogger;
       5: putstatic     #50                 // Field LOGGER:Lorg/apache/dubbo/common/logger/ErrorTypeAwareLogger;
       8: return
}
