Compiled from "FormattingTuple.java"
class org.apache.dubbo.remoting.transport.netty4.logging.FormattingTuple {
  static final org.apache.dubbo.remoting.transport.netty4.logging.FormattingTuple NULL;

  private final java.lang.String message;

  private final java.lang.Throwable throwable;

  private final java.lang.Object[] argArray;

  org.apache.dubbo.remoting.transport.netty4.logging.FormattingTuple(java.lang.String);
    Code:
       0: aload_0
       1: aload_1
       2: aconst_null
       3: aconst_null
       4: invokespecial #1                  // Method "<init>":(Ljava/lang/String;[Ljava/lang/Object;Ljava/lang/Throwable;)V
       7: return

  org.apache.dubbo.remoting.transport.netty4.logging.FormattingTuple(java.lang.String, java.lang.Object[], java.lang.Throwable);
    Code:
       0: aload_0
       1: invokespecial #2                  // Method java/lang/Object."<init>":()V
       4: aload_0
       5: aload_1
       6: putfield      #3                  // Field message:Ljava/lang/String;
       9: aload_0
      10: aload_3
      11: putfield      #4                  // Field throwable:Ljava/lang/Throwable;
      14: aload_3
      15: ifnonnull     26
      18: aload_0
      19: aload_2
      20: putfield      #5                  // Field argArray:[Ljava/lang/Object;
      23: goto          34
      26: aload_0
      27: aload_2
      28: invokestatic  #6                  // Method trimmedCopy:([Ljava/lang/Object;)[Ljava/lang/Object;
      31: putfield      #5                  // Field argArray:[Ljava/lang/Object;
      34: return

  static java.lang.Object[] trimmedCopy(java.lang.Object[]);
    Code:
       0: aload_0
       1: invokestatic  #7                  // Method org/apache/dubbo/common/utils/ArrayUtils.isEmpty:([Ljava/lang/Object;)Z
       4: ifeq          17
       7: new           #8                  // class java/lang/IllegalStateException
      10: dup
      11: ldc           #9                  // String non-sensical empty or null argument array
      13: invokespecial #10                 // Method java/lang/IllegalStateException."<init>":(Ljava/lang/String;)V
      16: athrow
      17: aload_0
      18: arraylength
      19: iconst_1
      20: isub
      21: istore_1
      22: iload_1
      23: anewarray     #11                 // class java/lang/Object
      26: astore_2
      27: aload_0
      28: iconst_0
      29: aload_2
      30: iconst_0
      31: iload_1
      32: invokestatic  #12                 // Method java/lang/System.arraycopy:(Ljava/lang/Object;ILjava/lang/Object;II)V
      35: aload_2
      36: areturn

  public java.lang.String getMessage();
    Code:
       0: aload_0
       1: getfield      #3                  // Field message:Ljava/lang/String;
       4: areturn

  public java.lang.Object[] getArgArray();
    Code:
       0: aload_0
       1: getfield      #5                  // Field argArray:[Ljava/lang/Object;
       4: areturn

  public java.lang.Throwable getThrowable();
    Code:
       0: aload_0
       1: getfield      #4                  // Field throwable:Ljava/lang/Throwable;
       4: areturn

  static {};
    Code:
       0: new           #13                 // class org/apache/dubbo/remoting/transport/netty4/logging/FormattingTuple
       3: dup
       4: aconst_null
       5: invokespecial #14                 // Method "<init>":(Ljava/lang/String;)V
       8: putstatic     #15                 // Field NULL:Lorg/apache/dubbo/remoting/transport/netty4/logging/FormattingTuple;
      11: return
}
