Compiled from "MessageFormatter.java"
final class org.apache.dubbo.remoting.transport.netty4.logging.MessageFormatter {
  private static final org.apache.dubbo.common.logger.ErrorTypeAwareLogger logger;

  static final char DELIM_START;

  static final char DELIM_STOP;

  static final java.lang.String DELIM_STR;

  private static final char ESCAPE_CHAR;

  static org.apache.dubbo.remoting.transport.netty4.logging.FormattingTuple format(java.lang.String, java.lang.Object);
    Code:
       0: aload_0
       1: iconst_1
       2: anewarray     #2                  // class java/lang/Object
       5: dup
       6: iconst_0
       7: aload_1
       8: aastore
       9: invokestatic  #3                  // Method arrayFormat:(Ljava/lang/String;[Ljava/lang/Object;)Lorg/apache/dubbo/remoting/transport/netty4/logging/FormattingTuple;
      12: areturn

  static org.apache.dubbo.remoting.transport.netty4.logging.FormattingTuple format(java.lang.String, java.lang.Object, java.lang.Object);
    Code:
       0: aload_0
       1: iconst_2
       2: anewarray     #2                  // class java/lang/Object
       5: dup
       6: iconst_0
       7: aload_1
       8: aastore
       9: dup
      10: iconst_1
      11: aload_2
      12: aastore
      13: invokestatic  #3                  // Method arrayFormat:(Ljava/lang/String;[Ljava/lang/Object;)Lorg/apache/dubbo/remoting/transport/netty4/logging/FormattingTuple;
      16: areturn

  static java.lang.Throwable getThrowableCandidate(java.lang.Object[]);
    Code:
       0: aload_0
       1: invokestatic  #4                  // Method org/apache/dubbo/common/utils/ArrayUtils.isEmpty:([Ljava/lang/Object;)Z
       4: ifeq          9
       7: aconst_null
       8: areturn
       9: aload_0
      10: aload_0
      11: arraylength
      12: iconst_1
      13: isub
      14: aaload
      15: astore_1
      16: aload_1
      17: instanceof    #5                  // class java/lang/Throwable
      20: ifeq          28
      23: aload_1
      24: checkcast     #5                  // class java/lang/Throwable
      27: areturn
      28: aconst_null
      29: areturn

  static org.apache.dubbo.remoting.transport.netty4.logging.FormattingTuple arrayFormat(java.lang.String, java.lang.Object[]);
    Code:
       0: aload_1
       1: invokestatic  #6                  // Method getThrowableCandidate:([Ljava/lang/Object;)Ljava/lang/Throwable;
       4: astore_2
       5: aload_0
       6: ifnonnull     20
       9: new           #7                  // class org/apache/dubbo/remoting/transport/netty4/logging/FormattingTuple
      12: dup
      13: aconst_null
      14: aload_1
      15: aload_2
      16: invokespecial #8                  // Method org/apache/dubbo/remoting/transport/netty4/logging/FormattingTuple."<init>":(Ljava/lang/String;[Ljava/lang/Object;Ljava/lang/Throwable;)V
      19: areturn
      20: aload_1
      21: ifnonnull     33
      24: new           #7                  // class org/apache/dubbo/remoting/transport/netty4/logging/FormattingTuple
      27: dup
      28: aload_0
      29: invokespecial #9                  // Method org/apache/dubbo/remoting/transport/netty4/logging/FormattingTuple."<init>":(Ljava/lang/String;)V
      32: areturn
      33: iconst_0
      34: istore_3
      35: new           #10                 // class java/lang/StringBuffer
      38: dup
      39: aload_0
      40: invokevirtual #11                 // Method java/lang/String.length:()I
      43: bipush        50
      45: iadd
      46: invokespecial #12                 // Method java/lang/StringBuffer."<init>":(I)V
      49: astore        5
      51: iconst_0
      52: istore        6
      54: iload         6
      56: aload_1
      57: arraylength
      58: if_icmpge     239
      61: aload_0
      62: ldc           #14                 // String {}
      64: iload_3
      65: invokevirtual #15                 // Method java/lang/String.indexOf:(Ljava/lang/String;I)I
      68: istore        4
      70: iload         4
      72: iconst_m1
      73: if_icmpne     117
      76: iload_3
      77: ifne          91
      80: new           #7                  // class org/apache/dubbo/remoting/transport/netty4/logging/FormattingTuple
      83: dup
      84: aload_0
      85: aload_1
      86: aload_2
      87: invokespecial #8                  // Method org/apache/dubbo/remoting/transport/netty4/logging/FormattingTuple."<init>":(Ljava/lang/String;[Ljava/lang/Object;Ljava/lang/Throwable;)V
      90: areturn
      91: aload         5
      93: aload_0
      94: iload_3
      95: invokevirtual #16                 // Method java/lang/String.substring:(I)Ljava/lang/String;
      98: invokevirtual #17                 // Method java/lang/StringBuffer.append:(Ljava/lang/String;)Ljava/lang/StringBuffer;
     101: pop
     102: new           #7                  // class org/apache/dubbo/remoting/transport/netty4/logging/FormattingTuple
     105: dup
     106: aload         5
     108: invokevirtual #18                 // Method java/lang/StringBuffer.toString:()Ljava/lang/String;
     111: aload_1
     112: aload_2
     113: invokespecial #8                  // Method org/apache/dubbo/remoting/transport/netty4/logging/FormattingTuple."<init>":(Ljava/lang/String;[Ljava/lang/Object;Ljava/lang/Throwable;)V
     116: areturn
     117: aload_0
     118: iload         4
     120: invokestatic  #19                 // Method isEscapedDelimeter:(Ljava/lang/String;I)Z
     123: ifeq          202
     126: aload_0
     127: iload         4
     129: invokestatic  #20                 // Method isDoubleEscaped:(Ljava/lang/String;I)Z
     132: ifne          166
     135: iinc          6, -1
     138: aload         5
     140: aload_0
     141: iload_3
     142: iload         4
     144: iconst_1
     145: isub
     146: invokevirtual #21                 // Method java/lang/StringBuffer.append:(Ljava/lang/CharSequence;II)Ljava/lang/StringBuffer;
     149: pop
     150: aload         5
     152: bipush        123
     154: invokevirtual #22                 // Method java/lang/StringBuffer.append:(C)Ljava/lang/StringBuffer;
     157: pop
     158: iload         4
     160: iconst_1
     161: iadd
     162: istore_3
     163: goto          233
     166: aload         5
     168: aload_0
     169: iload_3
     170: iload         4
     172: iconst_1
     173: isub
     174: invokevirtual #21                 // Method java/lang/StringBuffer.append:(Ljava/lang/CharSequence;II)Ljava/lang/StringBuffer;
     177: pop
     178: aload         5
     180: aload_1
     181: iload         6
     183: aaload
     184: new           #23                 // class java/util/HashMap
     187: dup
     188: invokespecial #24                 // Method java/util/HashMap."<init>":()V
     191: invokestatic  #25                 // Method deeplyAppendParameter:(Ljava/lang/StringBuffer;Ljava/lang/Object;Ljava/util/Map;)V
     194: iload         4
     196: iconst_2
     197: iadd
     198: istore_3
     199: goto          233
     202: aload         5
     204: aload_0
     205: iload_3
     206: iload         4
     208: invokevirtual #21                 // Method java/lang/StringBuffer.append:(Ljava/lang/CharSequence;II)Ljava/lang/StringBuffer;
     211: pop
     212: aload         5
     214: aload_1
     215: iload         6
     217: aaload
     218: new           #23                 // class java/util/HashMap
     221: dup
     222: invokespecial #24                 // Method java/util/HashMap."<init>":()V
     225: invokestatic  #25                 // Method deeplyAppendParameter:(Ljava/lang/StringBuffer;Ljava/lang/Object;Ljava/util/Map;)V
     228: iload         4
     230: iconst_2
     231: iadd
     232: istore_3
     233: iinc          6, 1
     236: goto          54
     239: aload         5
     241: aload_0
     242: iload_3
     243: invokevirtual #16                 // Method java/lang/String.substring:(I)Ljava/lang/String;
     246: invokevirtual #17                 // Method java/lang/StringBuffer.append:(Ljava/lang/String;)Ljava/lang/StringBuffer;
     249: pop
     250: iload         6
     252: aload_1
     253: arraylength
     254: iconst_1
     255: isub
     256: if_icmpge     274
     259: new           #7                  // class org/apache/dubbo/remoting/transport/netty4/logging/FormattingTuple
     262: dup
     263: aload         5
     265: invokevirtual #18                 // Method java/lang/StringBuffer.toString:()Ljava/lang/String;
     268: aload_1
     269: aload_2
     270: invokespecial #8                  // Method org/apache/dubbo/remoting/transport/netty4/logging/FormattingTuple."<init>":(Ljava/lang/String;[Ljava/lang/Object;Ljava/lang/Throwable;)V
     273: areturn
     274: new           #7                  // class org/apache/dubbo/remoting/transport/netty4/logging/FormattingTuple
     277: dup
     278: aload         5
     280: invokevirtual #18                 // Method java/lang/StringBuffer.toString:()Ljava/lang/String;
     283: aload_1
     284: aconst_null
     285: invokespecial #8                  // Method org/apache/dubbo/remoting/transport/netty4/logging/FormattingTuple."<init>":(Ljava/lang/String;[Ljava/lang/Object;Ljava/lang/Throwable;)V
     288: areturn

  static boolean isEscapedDelimeter(java.lang.String, int);
    Code:
       0: iload_1
       1: ifne          6
       4: iconst_0
       5: ireturn
       6: aload_0
       7: iload_1
       8: iconst_1
       9: isub
      10: invokevirtual #26                 // Method java/lang/String.charAt:(I)C
      13: bipush        92
      15: if_icmpne     22
      18: iconst_1
      19: goto          23
      22: iconst_0
      23: ireturn

  static boolean isDoubleEscaped(java.lang.String, int);
    Code:
       0: iload_1
       1: iconst_2
       2: if_icmplt     21
       5: aload_0
       6: iload_1
       7: iconst_2
       8: isub
       9: invokevirtual #26                 // Method java/lang/String.charAt:(I)C
      12: bipush        92
      14: if_icmpne     21
      17: iconst_1
      18: goto          22
      21: iconst_0
      22: ireturn

  private static void deeplyAppendParameter(java.lang.StringBuffer, java.lang.Object, java.util.Map<java.lang.Object[], java.lang.Void>);
    Code:
       0: aload_1
       1: ifnonnull     12
       4: aload_0
       5: ldc           #27                 // String null
       7: invokevirtual #17                 // Method java/lang/StringBuffer.append:(Ljava/lang/String;)Ljava/lang/StringBuffer;
      10: pop
      11: return
      12: aload_1
      13: invokevirtual #28                 // Method java/lang/Object.getClass:()Ljava/lang/Class;
      16: invokevirtual #29                 // Method java/lang/Class.isArray:()Z
      19: ifne          30
      22: aload_0
      23: aload_1
      24: invokestatic  #30                 // Method safeObjectAppend:(Ljava/lang/StringBuffer;Ljava/lang/Object;)V
      27: goto          210
      30: aload_1
      31: instanceof    #31                 // class "[Z"
      34: ifeq          51
      37: aload_0
      38: aload_1
      39: checkcast     #31                 // class "[Z"
      42: checkcast     #31                 // class "[Z"
      45: invokestatic  #32                 // Method booleanArrayAppend:(Ljava/lang/StringBuffer;[Z)V
      48: goto          210
      51: aload_1
      52: instanceof    #33                 // class "[B"
      55: ifeq          72
      58: aload_0
      59: aload_1
      60: checkcast     #33                 // class "[B"
      63: checkcast     #33                 // class "[B"
      66: invokestatic  #34                 // Method byteArrayAppend:(Ljava/lang/StringBuffer;[B)V
      69: goto          210
      72: aload_1
      73: instanceof    #35                 // class "[C"
      76: ifeq          93
      79: aload_0
      80: aload_1
      81: checkcast     #35                 // class "[C"
      84: checkcast     #35                 // class "[C"
      87: invokestatic  #36                 // Method charArrayAppend:(Ljava/lang/StringBuffer;[C)V
      90: goto          210
      93: aload_1
      94: instanceof    #37                 // class "[S"
      97: ifeq          114
     100: aload_0
     101: aload_1
     102: checkcast     #37                 // class "[S"
     105: checkcast     #37                 // class "[S"
     108: invokestatic  #38                 // Method shortArrayAppend:(Ljava/lang/StringBuffer;[S)V
     111: goto          210
     114: aload_1
     115: instanceof    #39                 // class "[I"
     118: ifeq          135
     121: aload_0
     122: aload_1
     123: checkcast     #39                 // class "[I"
     126: checkcast     #39                 // class "[I"
     129: invokestatic  #40                 // Method intArrayAppend:(Ljava/lang/StringBuffer;[I)V
     132: goto          210
     135: aload_1
     136: instanceof    #41                 // class "[J"
     139: ifeq          156
     142: aload_0
     143: aload_1
     144: checkcast     #41                 // class "[J"
     147: checkcast     #41                 // class "[J"
     150: invokestatic  #42                 // Method longArrayAppend:(Ljava/lang/StringBuffer;[J)V
     153: goto          210
     156: aload_1
     157: instanceof    #43                 // class "[F"
     160: ifeq          177
     163: aload_0
     164: aload_1
     165: checkcast     #43                 // class "[F"
     168: checkcast     #43                 // class "[F"
     171: invokestatic  #44                 // Method floatArrayAppend:(Ljava/lang/StringBuffer;[F)V
     174: goto          210
     177: aload_1
     178: instanceof    #45                 // class "[D"
     181: ifeq          198
     184: aload_0
     185: aload_1
     186: checkcast     #45                 // class "[D"
     189: checkcast     #45                 // class "[D"
     192: invokestatic  #46                 // Method doubleArrayAppend:(Ljava/lang/StringBuffer;[D)V
     195: goto          210
     198: aload_0
     199: aload_1
     200: checkcast     #47                 // class "[Ljava/lang/Object;"
     203: checkcast     #47                 // class "[Ljava/lang/Object;"
     206: aload_2
     207: invokestatic  #48                 // Method objectArrayAppend:(Ljava/lang/StringBuffer;[Ljava/lang/Object;Ljava/util/Map;)V
     210: return

  private static void safeObjectAppend(java.lang.StringBuffer, java.lang.Object);
    Code:
       0: aload_1
       1: invokevirtual #49                 // Method java/lang/Object.toString:()Ljava/lang/String;
       4: astore_2
       5: aload_0
       6: aload_2
       7: invokevirtual #17                 // Method java/lang/StringBuffer.append:(Ljava/lang/String;)Ljava/lang/StringBuffer;
      10: pop
      11: goto          77
      14: astore_2
      15: getstatic     #50                 // Field java/lang/System.err:Ljava/io/PrintStream;
      18: new           #51                 // class java/lang/StringBuilder
      21: dup
      22: invokespecial #52                 // Method java/lang/StringBuilder."<init>":()V
      25: ldc           #53                 // String SLF4J: Failed toString() invocation on an object of type [
      27: invokevirtual #54                 // Method java/lang/StringBuilder.append:(Ljava/lang/String;)Ljava/lang/StringBuilder;
      30: aload_1
      31: invokevirtual #28                 // Method java/lang/Object.getClass:()Ljava/lang/Class;
      34: invokevirtual #55                 // Method java/lang/Class.getName:()Ljava/lang/String;
      37: invokevirtual #54                 // Method java/lang/StringBuilder.append:(Ljava/lang/String;)Ljava/lang/StringBuilder;
      40: bipush        93
      42: invokevirtual #56                 // Method java/lang/StringBuilder.append:(C)Ljava/lang/StringBuilder;
      45: invokevirtual #57                 // Method java/lang/StringBuilder.toString:()Ljava/lang/String;
      48: invokevirtual #58                 // Method java/io/PrintStream.println:(Ljava/lang/String;)V
      51: getstatic     #59                 // Field logger:Lorg/apache/dubbo/common/logger/ErrorTypeAwareLogger;
      54: ldc           #60                 // String 6-6
      56: ldc           #61                 // String
      58: ldc           #61                 // String
      60: aload_2
      61: invokevirtual #62                 // Method java/lang/Throwable.getMessage:()Ljava/lang/String;
      64: aload_2
      65: invokeinterface #63,  6           // InterfaceMethod org/apache/dubbo/common/logger/ErrorTypeAwareLogger.error:(Ljava/lang/String;Ljava/lang/String;Ljava/lang/String;Ljava/lang/String;Ljava/lang/Throwable;)V
      70: aload_0
      71: ldc           #64                 // String [FAILED toString()]
      73: invokevirtual #17                 // Method java/lang/StringBuffer.append:(Ljava/lang/String;)Ljava/lang/StringBuffer;
      76: pop
      77: return
    Exception table:
       from    to  target type
           0    11    14   Class java/lang/Throwable

  private static void objectArrayAppend(java.lang.StringBuffer, java.lang.Object[], java.util.Map<java.lang.Object[], java.lang.Void>);
    Code:
       0: aload_0
       1: bipush        91
       3: invokevirtual #22                 // Method java/lang/StringBuffer.append:(C)Ljava/lang/StringBuffer;
       6: pop
       7: aload_2
       8: aload_1
       9: invokeinterface #65,  2           // InterfaceMethod java/util/Map.containsKey:(Ljava/lang/Object;)Z
      14: ifne          79
      17: aload_2
      18: aload_1
      19: aconst_null
      20: invokeinterface #66,  3           // InterfaceMethod java/util/Map.put:(Ljava/lang/Object;Ljava/lang/Object;)Ljava/lang/Object;
      25: pop
      26: aload_1
      27: arraylength
      28: istore_3
      29: iconst_0
      30: istore        4
      32: iload         4
      34: iload_3
      35: if_icmpge     68
      38: aload_0
      39: aload_1
      40: iload         4
      42: aaload
      43: aload_2
      44: invokestatic  #25                 // Method deeplyAppendParameter:(Ljava/lang/StringBuffer;Ljava/lang/Object;Ljava/util/Map;)V
      47: iload         4
      49: iload_3
      50: iconst_1
      51: isub
      52: if_icmpeq     62
      55: aload_0
      56: ldc           #67                 // String ,
      58: invokevirtual #17                 // Method java/lang/StringBuffer.append:(Ljava/lang/String;)Ljava/lang/StringBuffer;
      61: pop
      62: iinc          4, 1
      65: goto          32
      68: aload_2
      69: aload_1
      70: invokeinterface #68,  2           // InterfaceMethod java/util/Map.remove:(Ljava/lang/Object;)Ljava/lang/Object;
      75: pop
      76: goto          86
      79: aload_0
      80: ldc           #69                 // String ...
      82: invokevirtual #17                 // Method java/lang/StringBuffer.append:(Ljava/lang/String;)Ljava/lang/StringBuffer;
      85: pop
      86: aload_0
      87: bipush        93
      89: invokevirtual #22                 // Method java/lang/StringBuffer.append:(C)Ljava/lang/StringBuffer;
      92: pop
      93: return

  private static void booleanArrayAppend(java.lang.StringBuffer, boolean[]);
    Code:
       0: aload_0
       1: bipush        91
       3: invokevirtual #22                 // Method java/lang/StringBuffer.append:(C)Ljava/lang/StringBuffer;
       6: pop
       7: aload_1
       8: arraylength
       9: istore_2
      10: iconst_0
      11: istore_3
      12: iload_3
      13: iload_2
      14: if_icmpge     45
      17: aload_0
      18: aload_1
      19: iload_3
      20: baload
      21: invokevirtual #70                 // Method java/lang/StringBuffer.append:(Z)Ljava/lang/StringBuffer;
      24: pop
      25: iload_3
      26: iload_2
      27: iconst_1
      28: isub
      29: if_icmpeq     39
      32: aload_0
      33: ldc           #67                 // String ,
      35: invokevirtual #17                 // Method java/lang/StringBuffer.append:(Ljava/lang/String;)Ljava/lang/StringBuffer;
      38: pop
      39: iinc          3, 1
      42: goto          12
      45: aload_0
      46: bipush        93
      48: invokevirtual #22                 // Method java/lang/StringBuffer.append:(C)Ljava/lang/StringBuffer;
      51: pop
      52: return

  private static void byteArrayAppend(java.lang.StringBuffer, byte[]);
    Code:
       0: aload_0
       1: bipush        91
       3: invokevirtual #22                 // Method java/lang/StringBuffer.append:(C)Ljava/lang/StringBuffer;
       6: pop
       7: aload_1
       8: arraylength
       9: istore_2
      10: iconst_0
      11: istore_3
      12: iload_3
      13: iload_2
      14: if_icmpge     45
      17: aload_0
      18: aload_1
      19: iload_3
      20: baload
      21: invokevirtual #71                 // Method java/lang/StringBuffer.append:(I)Ljava/lang/StringBuffer;
      24: pop
      25: iload_3
      26: iload_2
      27: iconst_1
      28: isub
      29: if_icmpeq     39
      32: aload_0
      33: ldc           #67                 // String ,
      35: invokevirtual #17                 // Method java/lang/StringBuffer.append:(Ljava/lang/String;)Ljava/lang/StringBuffer;
      38: pop
      39: iinc          3, 1
      42: goto          12
      45: aload_0
      46: bipush        93
      48: invokevirtual #22                 // Method java/lang/StringBuffer.append:(C)Ljava/lang/StringBuffer;
      51: pop
      52: return

  private static void charArrayAppend(java.lang.StringBuffer, char[]);
    Code:
       0: aload_0
       1: bipush        91
       3: invokevirtual #22                 // Method java/lang/StringBuffer.append:(C)Ljava/lang/StringBuffer;
       6: pop
       7: aload_1
       8: arraylength
       9: istore_2
      10: iconst_0
      11: istore_3
      12: iload_3
      13: iload_2
      14: if_icmpge     45
      17: aload_0
      18: aload_1
      19: iload_3
      20: caload
      21: invokevirtual #22                 // Method java/lang/StringBuffer.append:(C)Ljava/lang/StringBuffer;
      24: pop
      25: iload_3
      26: iload_2
      27: iconst_1
      28: isub
      29: if_icmpeq     39
      32: aload_0
      33: ldc           #67                 // String ,
      35: invokevirtual #17                 // Method java/lang/StringBuffer.append:(Ljava/lang/String;)Ljava/lang/StringBuffer;
      38: pop
      39: iinc          3, 1
      42: goto          12
      45: aload_0
      46: bipush        93
      48: invokevirtual #22                 // Method java/lang/StringBuffer.append:(C)Ljava/lang/StringBuffer;
      51: pop
      52: return

  private static void shortArrayAppend(java.lang.StringBuffer, short[]);
    Code:
       0: aload_0
       1: bipush        91
       3: invokevirtual #22                 // Method java/lang/StringBuffer.append:(C)Ljava/lang/StringBuffer;
       6: pop
       7: aload_1
       8: arraylength
       9: istore_2
      10: iconst_0
      11: istore_3
      12: iload_3
      13: iload_2
      14: if_icmpge     45
      17: aload_0
      18: aload_1
      19: iload_3
      20: saload
      21: invokevirtual #71                 // Method java/lang/StringBuffer.append:(I)Ljava/lang/StringBuffer;
      24: pop
      25: iload_3
      26: iload_2
      27: iconst_1
      28: isub
      29: if_icmpeq     39
      32: aload_0
      33: ldc           #67                 // String ,
      35: invokevirtual #17                 // Method java/lang/StringBuffer.append:(Ljava/lang/String;)Ljava/lang/StringBuffer;
      38: pop
      39: iinc          3, 1
      42: goto          12
      45: aload_0
      46: bipush        93
      48: invokevirtual #22                 // Method java/lang/StringBuffer.append:(C)Ljava/lang/StringBuffer;
      51: pop
      52: return

  private static void intArrayAppend(java.lang.StringBuffer, int[]);
    Code:
       0: aload_0
       1: bipush        91
       3: invokevirtual #22                 // Method java/lang/StringBuffer.append:(C)Ljava/lang/StringBuffer;
       6: pop
       7: aload_1
       8: arraylength
       9: istore_2
      10: iconst_0
      11: istore_3
      12: iload_3
      13: iload_2
      14: if_icmpge     45
      17: aload_0
      18: aload_1
      19: iload_3
      20: iaload
      21: invokevirtual #71                 // Method java/lang/StringBuffer.append:(I)Ljava/lang/StringBuffer;
      24: pop
      25: iload_3
      26: iload_2
      27: iconst_1
      28: isub
      29: if_icmpeq     39
      32: aload_0
      33: ldc           #67                 // String ,
      35: invokevirtual #17                 // Method java/lang/StringBuffer.append:(Ljava/lang/String;)Ljava/lang/StringBuffer;
      38: pop
      39: iinc          3, 1
      42: goto          12
      45: aload_0
      46: bipush        93
      48: invokevirtual #22                 // Method java/lang/StringBuffer.append:(C)Ljava/lang/StringBuffer;
      51: pop
      52: return

  private static void longArrayAppend(java.lang.StringBuffer, long[]);
    Code:
       0: aload_0
       1: bipush        91
       3: invokevirtual #22                 // Method java/lang/StringBuffer.append:(C)Ljava/lang/StringBuffer;
       6: pop
       7: aload_1
       8: arraylength
       9: istore_2
      10: iconst_0
      11: istore_3
      12: iload_3
      13: iload_2
      14: if_icmpge     45
      17: aload_0
      18: aload_1
      19: iload_3
      20: laload
      21: invokevirtual #72                 // Method java/lang/StringBuffer.append:(J)Ljava/lang/StringBuffer;
      24: pop
      25: iload_3
      26: iload_2
      27: iconst_1
      28: isub
      29: if_icmpeq     39
      32: aload_0
      33: ldc           #67                 // String ,
      35: invokevirtual #17                 // Method java/lang/StringBuffer.append:(Ljava/lang/String;)Ljava/lang/StringBuffer;
      38: pop
      39: iinc          3, 1
      42: goto          12
      45: aload_0
      46: bipush        93
      48: invokevirtual #22                 // Method java/lang/StringBuffer.append:(C)Ljava/lang/StringBuffer;
      51: pop
      52: return

  private static void floatArrayAppend(java.lang.StringBuffer, float[]);
    Code:
       0: aload_0
       1: bipush        91
       3: invokevirtual #22                 // Method java/lang/StringBuffer.append:(C)Ljava/lang/StringBuffer;
       6: pop
       7: aload_1
       8: arraylength
       9: istore_2
      10: iconst_0
      11: istore_3
      12: iload_3
      13: iload_2
      14: if_icmpge     45
      17: aload_0
      18: aload_1
      19: iload_3
      20: faload
      21: invokevirtual #73                 // Method java/lang/StringBuffer.append:(F)Ljava/lang/StringBuffer;
      24: pop
      25: iload_3
      26: iload_2
      27: iconst_1
      28: isub
      29: if_icmpeq     39
      32: aload_0
      33: ldc           #67                 // String ,
      35: invokevirtual #17                 // Method java/lang/StringBuffer.append:(Ljava/lang/String;)Ljava/lang/StringBuffer;
      38: pop
      39: iinc          3, 1
      42: goto          12
      45: aload_0
      46: bipush        93
      48: invokevirtual #22                 // Method java/lang/StringBuffer.append:(C)Ljava/lang/StringBuffer;
      51: pop
      52: return

  private static void doubleArrayAppend(java.lang.StringBuffer, double[]);
    Code:
       0: aload_0
       1: bipush        91
       3: invokevirtual #22                 // Method java/lang/StringBuffer.append:(C)Ljava/lang/StringBuffer;
       6: pop
       7: aload_1
       8: arraylength
       9: istore_2
      10: iconst_0
      11: istore_3
      12: iload_3
      13: iload_2
      14: if_icmpge     45
      17: aload_0
      18: aload_1
      19: iload_3
      20: daload
      21: invokevirtual #74                 // Method java/lang/StringBuffer.append:(D)Ljava/lang/StringBuffer;
      24: pop
      25: iload_3
      26: iload_2
      27: iconst_1
      28: isub
      29: if_icmpeq     39
      32: aload_0
      33: ldc           #67                 // String ,
      35: invokevirtual #17                 // Method java/lang/StringBuffer.append:(Ljava/lang/String;)Ljava/lang/StringBuffer;
      38: pop
      39: iinc          3, 1
      42: goto          12
      45: aload_0
      46: bipush        93
      48: invokevirtual #22                 // Method java/lang/StringBuffer.append:(C)Ljava/lang/StringBuffer;
      51: pop
      52: return

  private org.apache.dubbo.remoting.transport.netty4.logging.MessageFormatter();
    Code:
       0: aload_0
       1: invokespecial #75                 // Method java/lang/Object."<init>":()V
       4: return

  static {};
    Code:
       0: ldc           #13                 // class org/apache/dubbo/remoting/transport/netty4/logging/MessageFormatter
       2: invokestatic  #76                 // Method org/apache/dubbo/common/logger/LoggerFactory.getErrorTypeAwareLogger:(Ljava/lang/Class;)Lorg/apache/dubbo/common/logger/ErrorTypeAwareLogger;
       5: putstatic     #59                 // Field logger:Lorg/apache/dubbo/common/logger/ErrorTypeAwareLogger;
       8: return
}
