Compiled from "OneToOneMethodHandler.java"
public class org.apache.dubbo.reactive.handler.OneToOneMethodHandler<T, R> implements org.apache.dubbo.rpc.stub.StubMethodHandler<T, R> {
  private final java.util.function.Function<reactor.core.publisher.Mono<T>, reactor.core.publisher.Mono<R>> func;

  public org.apache.dubbo.reactive.handler.OneToOneMethodHandler(java.util.function.Function<reactor.core.publisher.Mono<T>, reactor.core.publisher.Mono<R>>);
    Code:
       0: aload_0
       1: invokespecial #1                  // Method java/lang/Object."<init>":()V
       4: aload_0
       5: aload_1
       6: putfield      #2                  // Field func:Ljava/util/function/Function;
       9: return

  public java.util.concurrent.CompletableFuture<R> invoke(java.lang.Object[]);
    Code:
       0: aload_1
       1: iconst_0
       2: aaload
       3: astore_2
       4: new           #3                  // class java/util/concurrent/CompletableFuture
       7: dup
       8: invokespecial #4                  // Method java/util/concurrent/CompletableFuture."<init>":()V
      11: astore_3
      12: new           #5                  // class org/apache/dubbo/rpc/stub/FutureToObserverAdaptor
      15: dup
      16: aload_3
      17: invokespecial #6                  // Method org/apache/dubbo/rpc/stub/FutureToObserverAdaptor."<init>":(Ljava/util/concurrent/CompletableFuture;)V
      20: astore        4
      22: aload_2
      23: aload         4
      25: aload_0
      26: getfield      #2                  // Field func:Ljava/util/function/Function;
      29: invokestatic  #7                  // Method org/apache/dubbo/reactive/calls/ReactorServerCalls.oneToOne:(Ljava/lang/Object;Lorg/apache/dubbo/common/stream/StreamObserver;Ljava/util/function/Function;)V
      32: aload_3
      33: areturn
}
