Compiled from "MetadataMetricsCollector.java"
public class org.apache.dubbo.metrics.metadata.collector.MetadataMetricsCollector extends org.apache.dubbo.metrics.collector.CombMetricsCollector<org.apache.dubbo.metrics.metadata.event.MetadataEvent> {
  private java.lang.Boolean collectEnabled;

  private final org.apache.dubbo.rpc.model.ApplicationModel applicationModel;

  public org.apache.dubbo.metrics.metadata.collector.MetadataMetricsCollector(org.apache.dubbo.rpc.model.ApplicationModel);
    Code:
       0: aload_0
       1: new           #1                  // class org/apache/dubbo/metrics/metadata/collector/MetadataMetricsCollector$1
       4: dup
       5: aload_1
       6: invokespecial #2                  // Method org/apache/dubbo/metrics/metadata/collector/MetadataMetricsCollector$1."<init>":(Lorg/apache/dubbo/rpc/model/ApplicationModel;)V
       9: invokespecial #3                  // Method org/apache/dubbo/metrics/collector/CombMetricsCollector."<init>":(Lorg/apache/dubbo/metrics/data/BaseStatComposite;)V
      12: aload_0
      13: aconst_null
      14: putfield      #4                  // Field collectEnabled:Ljava/lang/Boolean;
      17: aload_0
      18: new           #5                  // class org/apache/dubbo/metrics/metadata/event/MetadataSubDispatcher
      21: dup
      22: aload_0
      23: invokespecial #6                  // Method org/apache/dubbo/metrics/metadata/event/MetadataSubDispatcher."<init>":(Lorg/apache/dubbo/metrics/metadata/collector/MetadataMetricsCollector;)V
      26: invokespecial #7                  // Method org/apache/dubbo/metrics/collector/CombMetricsCollector.setEventMulticaster:(Lorg/apache/dubbo/metrics/event/MetricsEventMulticaster;)V
      29: aload_0
      30: aload_1
      31: putfield      #8                  // Field applicationModel:Lorg/apache/dubbo/rpc/model/ApplicationModel;
      34: return

  public void setCollectEnabled(java.lang.Boolean);
    Code:
       0: aload_1
       1: ifnull        9
       4: aload_0
       5: aload_1
       6: putfield      #4                  // Field collectEnabled:Ljava/lang/Boolean;
       9: return

  public boolean isCollectEnabled();
    Code:
       0: aload_0
       1: getfield      #4                  // Field collectEnabled:Ljava/lang/Boolean;
       4: ifnonnull     28
       7: aload_0
       8: getfield      #8                  // Field applicationModel:Lorg/apache/dubbo/rpc/model/ApplicationModel;
      11: invokevirtual #9                  // Method org/apache/dubbo/rpc/model/ApplicationModel.getApplicationConfigManager:()Lorg/apache/dubbo/config/context/ConfigManager;
      14: astore_1
      15: aload_1
      16: invokevirtual #10                 // Method org/apache/dubbo/config/context/ConfigManager.getMetrics:()Ljava/util/Optional;
      19: aload_0
      20: invokedynamic #11,  0             // InvokeDynamic #0:accept:(Lorg/apache/dubbo/metrics/metadata/collector/MetadataMetricsCollector;)Ljava/util/function/Consumer;
      25: invokevirtual #12                 // Method java/util/Optional.ifPresent:(Ljava/util/function/Consumer;)V
      28: aload_0
      29: getfield      #4                  // Field collectEnabled:Ljava/lang/Boolean;
      32: invokestatic  #13                 // Method java/util/Optional.ofNullable:(Ljava/lang/Object;)Ljava/util/Optional;
      35: iconst_1
      36: invokestatic  #14                 // Method java/lang/Boolean.valueOf:(Z)Ljava/lang/Boolean;
      39: invokevirtual #15                 // Method java/util/Optional.orElse:(Ljava/lang/Object;)Ljava/lang/Object;
      42: checkcast     #16                 // class java/lang/Boolean
      45: invokevirtual #17                 // Method java/lang/Boolean.booleanValue:()Z
      48: ireturn

  public java.util.List<org.apache.dubbo.metrics.model.sample.MetricSample> collect();
    Code:
       0: new           #18                 // class java/util/ArrayList
       3: dup
       4: invokespecial #19                 // Method java/util/ArrayList."<init>":()V
       7: astore_1
       8: aload_0
       9: invokevirtual #20                 // Method isCollectEnabled:()Z
      12: ifne          17
      15: aload_1
      16: areturn
      17: aload_1
      18: aload_0
      19: getstatic     #21                 // Field org/apache/dubbo/metrics/model/MetricsCategory.METADATA:Lorg/apache/dubbo/metrics/model/MetricsCategory;
      22: invokespecial #22                 // Method org/apache/dubbo/metrics/collector/CombMetricsCollector.export:(Lorg/apache/dubbo/metrics/model/MetricsCategory;)Ljava/util/List;
      25: invokeinterface #23,  2           // InterfaceMethod java/util/List.addAll:(Ljava/util/Collection;)Z
      30: pop
      31: aload_1
      32: areturn

  private void lambda$isCollectEnabled$0(org.apache.dubbo.config.MetricsConfig);
    Code:
       0: aload_0
       1: aload_1
       2: invokevirtual #24                 // Method org/apache/dubbo/config/MetricsConfig.getEnableMetadata:()Ljava/lang/Boolean;
       5: invokevirtual #25                 // Method setCollectEnabled:(Ljava/lang/Boolean;)V
       8: return
}
