Compiled from "AbstractConfigManager.java"
public abstract class org.apache.dubbo.config.context.AbstractConfigManager extends org.apache.dubbo.common.context.LifecycleAdapter {
  private static final java.lang.String CONFIG_NAME_READ_METHOD;

  private static final org.apache.dubbo.common.logger.ErrorTypeAwareLogger logger;

  private static final java.util.Set<java.lang.Class<? extends org.apache.dubbo.config.AbstractConfig>> uniqueConfigTypes;

  final java.util.Map<java.lang.String, java.util.Map<java.lang.String, org.apache.dubbo.config.AbstractConfig>> configsCache;

  private final java.util.Map<java.lang.String, java.util.concurrent.atomic.AtomicInteger> configIdIndexes;

  protected java.util.Set<org.apache.dubbo.config.AbstractConfig> duplicatedConfigs;

  protected final org.apache.dubbo.rpc.model.ScopeModel scopeModel;

  protected final org.apache.dubbo.rpc.model.ApplicationModel applicationModel;

  private final java.util.Collection<java.lang.Class<? extends org.apache.dubbo.config.AbstractConfig>> supportedConfigTypes;

  private final org.apache.dubbo.common.config.Environment environment;

  private org.apache.dubbo.config.context.ConfigValidator configValidator;

  private final java.util.concurrent.atomic.AtomicBoolean initialized;

  protected org.apache.dubbo.config.context.ConfigMode configMode;

  protected boolean ignoreDuplicatedInterface;

  public org.apache.dubbo.config.context.AbstractConfigManager(org.apache.dubbo.rpc.model.ScopeModel, java.util.Collection<java.lang.Class<? extends org.apache.dubbo.config.AbstractConfig>>);
    Code:
       0: aload_0
       1: invokespecial #3                  // Method org/apache/dubbo/common/context/LifecycleAdapter."<init>":()V
       4: aload_0
       5: new           #4                  // class java/util/concurrent/ConcurrentHashMap
       8: dup
       9: invokespecial #5                  // Method java/util/concurrent/ConcurrentHashMap."<init>":()V
      12: putfield      #6                  // Field configsCache:Ljava/util/Map;
      15: aload_0
      16: new           #4                  // class java/util/concurrent/ConcurrentHashMap
      19: dup
      20: invokespecial #5                  // Method java/util/concurrent/ConcurrentHashMap."<init>":()V
      23: putfield      #7                  // Field configIdIndexes:Ljava/util/Map;
      26: aload_0
      27: new           #8                  // class org/apache/dubbo/common/utils/ConcurrentHashSet
      30: dup
      31: invokespecial #9                  // Method org/apache/dubbo/common/utils/ConcurrentHashSet."<init>":()V
      34: putfield      #10                 // Field duplicatedConfigs:Ljava/util/Set;
      37: aload_0
      38: new           #11                 // class java/util/concurrent/atomic/AtomicBoolean
      41: dup
      42: iconst_0
      43: invokespecial #12                 // Method java/util/concurrent/atomic/AtomicBoolean."<init>":(Z)V
      46: putfield      #13                 // Field initialized:Ljava/util/concurrent/atomic/AtomicBoolean;
      49: aload_0
      50: getstatic     #14                 // Field org/apache/dubbo/config/context/ConfigMode.STRICT:Lorg/apache/dubbo/config/context/ConfigMode;
      53: putfield      #15                 // Field configMode:Lorg/apache/dubbo/config/context/ConfigMode;
      56: aload_0
      57: iconst_0
      58: putfield      #16                 // Field ignoreDuplicatedInterface:Z
      61: aload_0
      62: aload_1
      63: putfield      #17                 // Field scopeModel:Lorg/apache/dubbo/rpc/model/ScopeModel;
      66: aload_0
      67: aload_1
      68: invokestatic  #18                 // Method org/apache/dubbo/rpc/model/ScopeModelUtil.getApplicationModel:(Lorg/apache/dubbo/rpc/model/ScopeModel;)Lorg/apache/dubbo/rpc/model/ApplicationModel;
      71: putfield      #19                 // Field applicationModel:Lorg/apache/dubbo/rpc/model/ApplicationModel;
      74: aload_0
      75: aload_2
      76: putfield      #20                 // Field supportedConfigTypes:Ljava/util/Collection;
      79: aload_0
      80: aload_1
      81: invokevirtual #21                 // Method org/apache/dubbo/rpc/model/ScopeModel.getModelEnvironment:()Lorg/apache/dubbo/common/config/Environment;
      84: putfield      #22                 // Field environment:Lorg/apache/dubbo/common/config/Environment;
      87: return

  public void initialize() throws java.lang.IllegalStateException;
    Code:
       0: aload_0
       1: getfield      #13                 // Field initialized:Ljava/util/concurrent/atomic/AtomicBoolean;
       4: iconst_0
       5: iconst_1
       6: invokevirtual #23                 // Method java/util/concurrent/atomic/AtomicBoolean.compareAndSet:(ZZ)Z
       9: ifne          13
      12: return
      13: aload_0
      14: getfield      #17                 // Field scopeModel:Lorg/apache/dubbo/rpc/model/ScopeModel;
      17: invokevirtual #21                 // Method org/apache/dubbo/rpc/model/ScopeModel.getModelEnvironment:()Lorg/apache/dubbo/common/config/Environment;
      20: invokevirtual #24                 // Method org/apache/dubbo/common/config/Environment.getConfiguration:()Lorg/apache/dubbo/common/config/CompositeConfiguration;
      23: astore_1
      24: aload_1
      25: ldc           #26                 // String dubbo.config.mode
      27: invokevirtual #27                 // Method org/apache/dubbo/common/config/CompositeConfiguration.getProperty:(Ljava/lang/String;)Ljava/lang/Object;
      30: checkcast     #28                 // class java/lang/String
      33: astore_2
      34: aload_2
      35: invokestatic  #29                 // Method org/apache/dubbo/common/utils/StringUtils.hasText:(Ljava/lang/CharSequence;)Z
      38: ifeq          52
      41: aload_0
      42: aload_2
      43: invokevirtual #30                 // Method java/lang/String.toUpperCase:()Ljava/lang/String;
      46: invokestatic  #31                 // Method org/apache/dubbo/config/context/ConfigMode.valueOf:(Ljava/lang/String;)Lorg/apache/dubbo/config/context/ConfigMode;
      49: putfield      #15                 // Field configMode:Lorg/apache/dubbo/config/context/ConfigMode;
      52: goto          119
      55: astore_3
      56: new           #33                 // class java/lang/StringBuilder
      59: dup
      60: invokespecial #34                 // Method java/lang/StringBuilder."<init>":()V
      63: ldc           #35                 // String Illegal \'dubbo.config.mode\' config value [
      65: invokevirtual #36                 // Method java/lang/StringBuilder.append:(Ljava/lang/String;)Ljava/lang/StringBuilder;
      68: aload_2
      69: invokevirtual #36                 // Method java/lang/StringBuilder.append:(Ljava/lang/String;)Ljava/lang/StringBuilder;
      72: ldc           #37                 // String ], available values
      74: invokevirtual #36                 // Method java/lang/StringBuilder.append:(Ljava/lang/String;)Ljava/lang/StringBuilder;
      77: invokestatic  #38                 // Method org/apache/dubbo/config/context/ConfigMode.values:()[Lorg/apache/dubbo/config/context/ConfigMode;
      80: invokestatic  #39                 // Method java/util/Arrays.toString:([Ljava/lang/Object;)Ljava/lang/String;
      83: invokevirtual #36                 // Method java/lang/StringBuilder.append:(Ljava/lang/String;)Ljava/lang/StringBuilder;
      86: invokevirtual #40                 // Method java/lang/StringBuilder.toString:()Ljava/lang/String;
      89: astore        4
      91: getstatic     #41                 // Field logger:Lorg/apache/dubbo/common/logger/ErrorTypeAwareLogger;
      94: ldc           #42                 // String 0-2
      96: ldc           #43                 // String
      98: ldc           #43                 // String
     100: aload         4
     102: aload_3
     103: invokeinterface #44,  6           // InterfaceMethod org/apache/dubbo/common/logger/ErrorTypeAwareLogger.error:(Ljava/lang/String;Ljava/lang/String;Ljava/lang/String;Ljava/lang/String;Ljava/lang/Throwable;)V
     108: new           #45                 // class java/lang/IllegalArgumentException
     111: dup
     112: aload         4
     114: aload_3
     115: invokespecial #46                 // Method java/lang/IllegalArgumentException."<init>":(Ljava/lang/String;Ljava/lang/Throwable;)V
     118: athrow
     119: aload_1
     120: ldc           #47                 // String dubbo.config.ignore-duplicated-interface
     122: invokevirtual #27                 // Method org/apache/dubbo/common/config/CompositeConfiguration.getProperty:(Ljava/lang/String;)Ljava/lang/Object;
     125: checkcast     #28                 // class java/lang/String
     128: astore_3
     129: aload_3
     130: ifnull        141
     133: aload_0
     134: aload_3
     135: invokestatic  #48                 // Method java/lang/Boolean.parseBoolean:(Ljava/lang/String;)Z
     138: putfield      #16                 // Field ignoreDuplicatedInterface:Z
     141: new           #49                 // class java/util/LinkedHashMap
     144: dup
     145: invokespecial #50                 // Method java/util/LinkedHashMap."<init>":()V
     148: astore        4
     150: aload         4
     152: ldc           #26                 // String dubbo.config.mode
     154: aload_0
     155: getfield      #15                 // Field configMode:Lorg/apache/dubbo/config/context/ConfigMode;
     158: invokeinterface #51,  3           // InterfaceMethod java/util/Map.put:(Ljava/lang/Object;Ljava/lang/Object;)Ljava/lang/Object;
     163: pop
     164: aload         4
     166: ldc           #47                 // String dubbo.config.ignore-duplicated-interface
     168: aload_0
     169: getfield      #16                 // Field ignoreDuplicatedInterface:Z
     172: invokestatic  #52                 // Method java/lang/Boolean.valueOf:(Z)Ljava/lang/Boolean;
     175: invokeinterface #51,  3           // InterfaceMethod java/util/Map.put:(Ljava/lang/Object;Ljava/lang/Object;)Ljava/lang/Object;
     180: pop
     181: getstatic     #41                 // Field logger:Lorg/apache/dubbo/common/logger/ErrorTypeAwareLogger;
     184: new           #33                 // class java/lang/StringBuilder
     187: dup
     188: invokespecial #34                 // Method java/lang/StringBuilder."<init>":()V
     191: ldc           #53                 // String Config settings:
     193: invokevirtual #36                 // Method java/lang/StringBuilder.append:(Ljava/lang/String;)Ljava/lang/StringBuilder;
     196: aload         4
     198: invokevirtual #54                 // Method java/lang/StringBuilder.append:(Ljava/lang/Object;)Ljava/lang/StringBuilder;
     201: invokevirtual #40                 // Method java/lang/StringBuilder.toString:()Ljava/lang/String;
     204: invokeinterface #55,  2           // InterfaceMethod org/apache/dubbo/common/logger/ErrorTypeAwareLogger.info:(Ljava/lang/String;)V
     209: return
    Exception table:
       from    to  target type
          34    52    55   Class java/lang/Exception

  public final <T extends org.apache.dubbo.config.AbstractConfig> T addConfig(org.apache.dubbo.config.AbstractConfig);
    Code:
       0: aload_1
       1: ifnonnull     6
       4: aconst_null
       5: areturn
       6: aload_0
       7: aload_1
       8: invokevirtual #56                 // Method java/lang/Object.getClass:()Ljava/lang/Class;
      11: invokevirtual #57                 // Method isSupportConfigType:(Ljava/lang/Class;)Z
      14: ifne          44
      17: new           #45                 // class java/lang/IllegalArgumentException
      20: dup
      21: new           #33                 // class java/lang/StringBuilder
      24: dup
      25: invokespecial #34                 // Method java/lang/StringBuilder."<init>":()V
      28: ldc           #58                 // String Unsupported config type:
      30: invokevirtual #36                 // Method java/lang/StringBuilder.append:(Ljava/lang/String;)Ljava/lang/StringBuilder;
      33: aload_1
      34: invokevirtual #54                 // Method java/lang/StringBuilder.append:(Ljava/lang/Object;)Ljava/lang/StringBuilder;
      37: invokevirtual #40                 // Method java/lang/StringBuilder.toString:()Ljava/lang/String;
      40: invokespecial #59                 // Method java/lang/IllegalArgumentException."<init>":(Ljava/lang/String;)V
      43: athrow
      44: aload_1
      45: invokevirtual #60                 // Method org/apache/dubbo/config/AbstractConfig.getScopeModel:()Lorg/apache/dubbo/rpc/model/ScopeModel;
      48: aload_0
      49: getfield      #17                 // Field scopeModel:Lorg/apache/dubbo/rpc/model/ScopeModel;
      52: if_acmpeq     63
      55: aload_1
      56: aload_0
      57: getfield      #17                 // Field scopeModel:Lorg/apache/dubbo/rpc/model/ScopeModel;
      60: invokevirtual #61                 // Method org/apache/dubbo/config/AbstractConfig.setScopeModel:(Lorg/apache/dubbo/rpc/model/ScopeModel;)V
      63: aload_0
      64: getfield      #6                  // Field configsCache:Ljava/util/Map;
      67: aload_1
      68: invokevirtual #56                 // Method java/lang/Object.getClass:()Ljava/lang/Class;
      71: invokestatic  #62                 // Method org/apache/dubbo/config/AbstractConfig.getTagName:(Ljava/lang/Class;)Ljava/lang/String;
      74: invokedynamic #63,  0             // InvokeDynamic #0:apply:()Ljava/util/function/Function;
      79: invokeinterface #64,  3           // InterfaceMethod java/util/Map.computeIfAbsent:(Ljava/lang/Object;Ljava/util/function/Function;)Ljava/lang/Object;
      84: checkcast     #65                 // class java/util/Map
      87: astore_2
      88: aload_1
      89: instanceof    #66                 // class org/apache/dubbo/config/ReferenceConfigBase
      92: ifne          149
      95: aload_1
      96: instanceof    #67                 // class org/apache/dubbo/config/ServiceConfigBase
      99: ifne          149
     102: aload_2
     103: invokeinterface #68,  1           // InterfaceMethod java/util/Map.values:()Ljava/util/Collection;
     108: invokeinterface #69,  1           // InterfaceMethod java/util/Collection.iterator:()Ljava/util/Iterator;
     113: astore_3
     114: aload_3
     115: invokeinterface #70,  1           // InterfaceMethod java/util/Iterator.hasNext:()Z
     120: ifeq          149
     123: aload_3
     124: invokeinterface #71,  1           // InterfaceMethod java/util/Iterator.next:()Ljava/lang/Object;
     129: checkcast     #72                 // class org/apache/dubbo/config/AbstractConfig
     132: astore        4
     134: aload         4
     136: aload_1
     137: invokevirtual #73                 // Method org/apache/dubbo/config/AbstractConfig.equals:(Ljava/lang/Object;)Z
     140: ifeq          146
     143: aload         4
     145: areturn
     146: goto          114
     149: aload_2
     150: dup
     151: astore_3
     152: monitorenter
     153: aload_0
     154: aload_1
     155: aload_2
     156: invokespecial #74                 // Method addIfAbsent:(Lorg/apache/dubbo/config/AbstractConfig;Ljava/util/Map;)Lorg/apache/dubbo/config/AbstractConfig;
     159: aload_3
     160: monitorexit
     161: areturn
     162: astore        5
     164: aload_3
     165: monitorexit
     166: aload         5
     168: athrow
    Exception table:
       from    to  target type
         153   161   162   any
         162   166   162   any

  protected boolean isSupportConfigType(java.lang.Class<? extends org.apache.dubbo.config.AbstractConfig>);
    Code:
       0: aload_0
       1: getfield      #20                 // Field supportedConfigTypes:Ljava/util/Collection;
       4: invokeinterface #69,  1           // InterfaceMethod java/util/Collection.iterator:()Ljava/util/Iterator;
       9: astore_2
      10: aload_2
      11: invokeinterface #70,  1           // InterfaceMethod java/util/Iterator.hasNext:()Z
      16: ifeq          42
      19: aload_2
      20: invokeinterface #71,  1           // InterfaceMethod java/util/Iterator.next:()Ljava/lang/Object;
      25: checkcast     #75                 // class java/lang/Class
      28: astore_3
      29: aload_3
      30: aload_1
      31: invokevirtual #76                 // Method java/lang/Class.isAssignableFrom:(Ljava/lang/Class;)Z
      34: ifeq          39
      37: iconst_1
      38: ireturn
      39: goto          10
      42: iconst_0
      43: ireturn

  private <C extends org.apache.dubbo.config.AbstractConfig> C addIfAbsent(C, java.util.Map<java.lang.String, C>) throws java.lang.IllegalStateException;
    Code:
       0: aload_1
       1: ifnull        8
       4: aload_2
       5: ifnonnull     10
       8: aload_1
       9: areturn
      10: aload_0
      11: aload_2
      12: aload_1
      13: invokevirtual #77                 // Method findDuplicatedConfig:(Ljava/util/Map;Lorg/apache/dubbo/config/AbstractConfig;)Ljava/util/Optional;
      16: astore_3
      17: aload_3
      18: invokevirtual #78                 // Method java/util/Optional.isPresent:()Z
      21: ifeq          32
      24: aload_3
      25: invokevirtual #79                 // Method java/util/Optional.get:()Ljava/lang/Object;
      28: checkcast     #72                 // class org/apache/dubbo/config/AbstractConfig
      31: areturn
      32: aload_1
      33: invokevirtual #80                 // Method org/apache/dubbo/config/AbstractConfig.getId:()Ljava/lang/String;
      36: astore        4
      38: aload         4
      40: ifnonnull     61
      43: aload_0
      44: aload_1
      45: invokevirtual #81                 // Method generateConfigId:(Lorg/apache/dubbo/config/AbstractConfig;)Ljava/lang/String;
      48: astore        4
      50: aload_2
      51: aload         4
      53: invokeinterface #82,  2           // InterfaceMethod java/util/Map.containsKey:(Ljava/lang/Object;)Z
      58: ifne          43
      61: aload_2
      62: aload         4
      64: invokeinterface #83,  2           // InterfaceMethod java/util/Map.get:(Ljava/lang/Object;)Ljava/lang/Object;
      69: checkcast     #72                 // class org/apache/dubbo/config/AbstractConfig
      72: astore        5
      74: aload         5
      76: ifnull        157
      79: aload_0
      80: aload         5
      82: aload_1
      83: invokevirtual #84                 // Method isEquals:(Lorg/apache/dubbo/config/AbstractConfig;Lorg/apache/dubbo/config/AbstractConfig;)Z
      86: ifne          157
      89: aload_1
      90: invokevirtual #56                 // Method java/lang/Object.getClass:()Ljava/lang/Class;
      93: invokevirtual #85                 // Method java/lang/Class.getSimpleName:()Ljava/lang/String;
      96: astore        6
      98: getstatic     #41                 // Field logger:Lorg/apache/dubbo/common/logger/ErrorTypeAwareLogger;
     101: ldc           #86                 // String 0-12
     103: ldc           #43                 // String
     105: ldc           #43                 // String
     107: ldc           #87                 // String Duplicate %s found, there already has one default %s or more than two %ss have the same id, you can try to give each %s a different id, override previous config with later config. id: %s, prev: %s, later: %s
     109: bipush        7
     111: anewarray     #88                 // class java/lang/Object
     114: dup
     115: iconst_0
     116: aload         6
     118: aastore
     119: dup
     120: iconst_1
     121: aload         6
     123: aastore
     124: dup
     125: iconst_2
     126: aload         6
     128: aastore
     129: dup
     130: iconst_3
     131: aload         6
     133: aastore
     134: dup
     135: iconst_4
     136: aload         4
     138: aastore
     139: dup
     140: iconst_5
     141: aload         5
     143: aastore
     144: dup
     145: bipush        6
     147: aload_1
     148: aastore
     149: invokestatic  #89                 // Method java/lang/String.format:(Ljava/lang/String;[Ljava/lang/Object;)Ljava/lang/String;
     152: invokeinterface #90,  5           // InterfaceMethod org/apache/dubbo/common/logger/ErrorTypeAwareLogger.warn:(Ljava/lang/String;Ljava/lang/String;Ljava/lang/String;Ljava/lang/String;)V
     157: aload_2
     158: aload         4
     160: aload_1
     161: invokeinterface #51,  3           // InterfaceMethod java/util/Map.put:(Ljava/lang/Object;Ljava/lang/Object;)Ljava/lang/Object;
     166: pop
     167: aload_1
     168: areturn

  protected <C extends org.apache.dubbo.config.AbstractConfig> boolean removeIfAbsent(C, java.util.Map<java.lang.String, C>);
    Code:
       0: aload_1
       1: invokevirtual #80                 // Method org/apache/dubbo/config/AbstractConfig.getId:()Ljava/lang/String;
       4: ifnull        19
       7: aload_2
       8: aload_1
       9: invokevirtual #80                 // Method org/apache/dubbo/config/AbstractConfig.getId:()Ljava/lang/String;
      12: aload_1
      13: invokeinterface #91,  3           // InterfaceMethod java/util/Map.remove:(Ljava/lang/Object;Ljava/lang/Object;)Z
      18: ireturn
      19: aload_2
      20: invokeinterface #68,  1           // InterfaceMethod java/util/Map.values:()Ljava/util/Collection;
      25: aload_1
      26: invokedynamic #92,  0             // InvokeDynamic #1:test:(Lorg/apache/dubbo/config/AbstractConfig;)Ljava/util/function/Predicate;
      31: invokeinterface #93,  2           // InterfaceMethod java/util/Collection.removeIf:(Ljava/util/function/Predicate;)Z
      36: ireturn

  protected boolean isUniqueConfig(org.apache.dubbo.config.AbstractConfig);
    Code:
       0: getstatic     #94                 // Field uniqueConfigTypes:Ljava/util/Set;
       3: aload_1
       4: invokevirtual #56                 // Method java/lang/Object.getClass:()Ljava/lang/Class;
       7: invokeinterface #95,  2           // InterfaceMethod java/util/Set.contains:(Ljava/lang/Object;)Z
      12: ifeq          17
      15: iconst_1
      16: ireturn
      17: getstatic     #94                 // Field uniqueConfigTypes:Ljava/util/Set;
      20: invokeinterface #96,  1           // InterfaceMethod java/util/Set.iterator:()Ljava/util/Iterator;
      25: astore_2
      26: aload_2
      27: invokeinterface #70,  1           // InterfaceMethod java/util/Iterator.hasNext:()Z
      32: ifeq          61
      35: aload_2
      36: invokeinterface #71,  1           // InterfaceMethod java/util/Iterator.next:()Ljava/lang/Object;
      41: checkcast     #75                 // class java/lang/Class
      44: astore_3
      45: aload_3
      46: aload_1
      47: invokevirtual #56                 // Method java/lang/Object.getClass:()Ljava/lang/Class;
      50: invokevirtual #76                 // Method java/lang/Class.isAssignableFrom:(Ljava/lang/Class;)Z
      53: ifeq          58
      56: iconst_1
      57: ireturn
      58: goto          26
      61: iconst_0
      62: ireturn

  protected <C extends org.apache.dubbo.config.AbstractConfig> C getSingleConfig(java.lang.String) throws java.lang.IllegalStateException;
    Code:
       0: aload_0
       1: aload_1
       2: invokevirtual #97                 // Method getConfigsMap:(Ljava/lang/String;)Ljava/util/Map;
       5: astore_2
       6: aload_2
       7: invokeinterface #98,  1           // InterfaceMethod java/util/Map.size:()I
      12: istore_3
      13: iload_3
      14: iconst_1
      15: if_icmpge     20
      18: aconst_null
      19: areturn
      20: iload_3
      21: iconst_1
      22: if_icmple     75
      25: new           #99                 // class java/lang/IllegalStateException
      28: dup
      29: new           #33                 // class java/lang/StringBuilder
      32: dup
      33: invokespecial #34                 // Method java/lang/StringBuilder."<init>":()V
      36: ldc           #100                // String Expected single instance of
      38: invokevirtual #36                 // Method java/lang/StringBuilder.append:(Ljava/lang/String;)Ljava/lang/StringBuilder;
      41: aload_1
      42: invokevirtual #36                 // Method java/lang/StringBuilder.append:(Ljava/lang/String;)Ljava/lang/StringBuilder;
      45: ldc           #101                // String , but found
      47: invokevirtual #36                 // Method java/lang/StringBuilder.append:(Ljava/lang/String;)Ljava/lang/StringBuilder;
      50: iload_3
      51: invokevirtual #102                // Method java/lang/StringBuilder.append:(I)Ljava/lang/StringBuilder;
      54: ldc           #103                // String  instances, please remove redundant configs. instances:
      56: invokevirtual #36                 // Method java/lang/StringBuilder.append:(Ljava/lang/String;)Ljava/lang/StringBuilder;
      59: aload_2
      60: invokeinterface #68,  1           // InterfaceMethod java/util/Map.values:()Ljava/util/Collection;
      65: invokevirtual #54                 // Method java/lang/StringBuilder.append:(Ljava/lang/Object;)Ljava/lang/StringBuilder;
      68: invokevirtual #40                 // Method java/lang/StringBuilder.toString:()Ljava/lang/String;
      71: invokespecial #104                // Method java/lang/IllegalStateException."<init>":(Ljava/lang/String;)V
      74: athrow
      75: aload_2
      76: invokeinterface #68,  1           // InterfaceMethod java/util/Map.values:()Ljava/util/Collection;
      81: invokeinterface #69,  1           // InterfaceMethod java/util/Collection.iterator:()Ljava/util/Iterator;
      86: invokeinterface #71,  1           // InterfaceMethod java/util/Iterator.next:()Ljava/lang/Object;
      91: checkcast     #72                 // class org/apache/dubbo/config/AbstractConfig
      94: areturn

  protected <C extends org.apache.dubbo.config.AbstractConfig> java.util.Optional<C> findDuplicatedConfig(java.util.Map<java.lang.String, C>, C);
    Code:
       0: aload_0
       1: aload_1
       2: invokeinterface #68,  1           // InterfaceMethod java/util/Map.values:()Ljava/util/Collection;
       7: aload_2
       8: invokevirtual #105                // Method findConfigByValue:(Ljava/util/Collection;Lorg/apache/dubbo/config/AbstractConfig;)Ljava/util/Optional;
      11: astore_3
      12: aload_3
      13: invokevirtual #78                 // Method java/util/Optional.isPresent:()Z
      16: ifeq          82
      19: aload_3
      20: invokevirtual #79                 // Method java/util/Optional.get:()Ljava/lang/Object;
      23: aload_2
      24: if_acmpne     29
      27: aload_3
      28: areturn
      29: getstatic     #41                 // Field logger:Lorg/apache/dubbo/common/logger/ErrorTypeAwareLogger;
      32: invokeinterface #106,  1          // InterfaceMethod org/apache/dubbo/common/logger/ErrorTypeAwareLogger.isInfoEnabled:()Z
      37: ifeq          80
      40: aload_0
      41: getfield      #10                 // Field duplicatedConfigs:Ljava/util/Set;
      44: aload_2
      45: invokeinterface #107,  2          // InterfaceMethod java/util/Set.add:(Ljava/lang/Object;)Z
      50: ifeq          80
      53: getstatic     #41                 // Field logger:Lorg/apache/dubbo/common/logger/ErrorTypeAwareLogger;
      56: new           #33                 // class java/lang/StringBuilder
      59: dup
      60: invokespecial #34                 // Method java/lang/StringBuilder."<init>":()V
      63: ldc           #108                // String Ignore duplicated config:
      65: invokevirtual #36                 // Method java/lang/StringBuilder.append:(Ljava/lang/String;)Ljava/lang/StringBuilder;
      68: aload_2
      69: invokevirtual #54                 // Method java/lang/StringBuilder.append:(Ljava/lang/Object;)Ljava/lang/StringBuilder;
      72: invokevirtual #40                 // Method java/lang/StringBuilder.toString:()Ljava/lang/String;
      75: invokeinterface #55,  2           // InterfaceMethod org/apache/dubbo/common/logger/ErrorTypeAwareLogger.info:(Ljava/lang/String;)V
      80: aload_3
      81: areturn
      82: aload_0
      83: aload_1
      84: aload_2
      85: invokevirtual #109                // Method checkUniqueConfig:(Ljava/util/Map;Lorg/apache/dubbo/config/AbstractConfig;)Ljava/util/Optional;
      88: areturn

  public <C extends org.apache.dubbo.config.AbstractConfig> java.util.Map<java.lang.String, C> getConfigsMap(java.lang.Class<C>);
    Code:
       0: aload_0
       1: aload_1
       2: invokestatic  #62                 // Method org/apache/dubbo/config/AbstractConfig.getTagName:(Ljava/lang/Class;)Ljava/lang/String;
       5: invokevirtual #97                 // Method getConfigsMap:(Ljava/lang/String;)Ljava/util/Map;
       8: areturn

  protected <C extends org.apache.dubbo.config.AbstractConfig> java.util.Map<java.lang.String, C> getConfigsMap(java.lang.String);
    Code:
       0: aload_0
       1: getfield      #6                  // Field configsCache:Ljava/util/Map;
       4: aload_1
       5: invokestatic  #110                // Method java/util/Collections.emptyMap:()Ljava/util/Map;
       8: invokeinterface #111,  3          // InterfaceMethod java/util/Map.getOrDefault:(Ljava/lang/Object;Ljava/lang/Object;)Ljava/lang/Object;
      13: checkcast     #65                 // class java/util/Map
      16: areturn

  protected <C extends org.apache.dubbo.config.AbstractConfig> java.util.Collection<C> getConfigs(java.lang.String);
    Code:
       0: aload_0
       1: aload_1
       2: invokevirtual #97                 // Method getConfigsMap:(Ljava/lang/String;)Ljava/util/Map;
       5: invokeinterface #68,  1           // InterfaceMethod java/util/Map.values:()Ljava/util/Collection;
      10: areturn

  public <C extends org.apache.dubbo.config.AbstractConfig> java.util.Collection<C> getConfigs(java.lang.Class<C>);
    Code:
       0: aload_0
       1: aload_1
       2: invokestatic  #62                 // Method org/apache/dubbo/config/AbstractConfig.getTagName:(Ljava/lang/Class;)Ljava/lang/String;
       5: invokevirtual #97                 // Method getConfigsMap:(Ljava/lang/String;)Ljava/util/Map;
       8: invokeinterface #68,  1           // InterfaceMethod java/util/Map.values:()Ljava/util/Collection;
      13: areturn

  protected <C extends org.apache.dubbo.config.AbstractConfig> C getConfigById(java.lang.String, java.lang.String);
    Code:
       0: aload_0
       1: aload_1
       2: invokevirtual #97                 // Method getConfigsMap:(Ljava/lang/String;)Ljava/util/Map;
       5: aload_2
       6: invokeinterface #83,  2           // InterfaceMethod java/util/Map.get:(Ljava/lang/Object;)Ljava/lang/Object;
      11: checkcast     #72                 // class org/apache/dubbo/config/AbstractConfig
      14: areturn

  public <T extends org.apache.dubbo.config.AbstractConfig> java.util.Optional<T> getConfig(java.lang.Class<T>, java.lang.String);
    Code:
       0: aload_0
       1: aload_1
       2: invokestatic  #62                 // Method org/apache/dubbo/config/AbstractConfig.getTagName:(Ljava/lang/Class;)Ljava/lang/String;
       5: aload_2
       6: invokevirtual #112                // Method getConfigById:(Ljava/lang/String;Ljava/lang/String;)Lorg/apache/dubbo/config/AbstractConfig;
       9: astore_3
      10: aload_3
      11: ifnonnull     21
      14: aload_0
      15: aload_1
      16: aload_2
      17: invokevirtual #113                // Method getConfigByName:(Ljava/lang/Class;Ljava/lang/String;)Lorg/apache/dubbo/config/AbstractConfig;
      20: astore_3
      21: aload_3
      22: invokestatic  #114                // Method java/util/Optional.ofNullable:(Ljava/lang/Object;)Ljava/util/Optional;
      25: areturn

  protected <C extends org.apache.dubbo.config.AbstractConfig> C getConfigByName(java.lang.Class<? extends C>, java.lang.String);
    Code:
       0: aload_0
       1: aload_1
       2: invokevirtual #115                // Method getConfigsMap:(Ljava/lang/Class;)Ljava/util/Map;
       5: astore_3
       6: aload_3
       7: invokeinterface #116,  1          // InterfaceMethod java/util/Map.isEmpty:()Z
      12: ifeq          17
      15: aconst_null
      16: areturn
      17: aload_1
      18: ldc           #118                // String getName
      20: invokestatic  #119                // Method org/apache/dubbo/common/utils/ReflectUtils.hasMethod:(Ljava/lang/Class;Ljava/lang/String;)Z
      23: ifeq          138
      26: aload_3
      27: invokeinterface #68,  1           // InterfaceMethod java/util/Map.values:()Ljava/util/Collection;
      32: invokeinterface #120,  1          // InterfaceMethod java/util/Collection.stream:()Ljava/util/stream/Stream;
      37: aload_0
      38: aload_2
      39: invokedynamic #121,  0            // InvokeDynamic #2:test:(Lorg/apache/dubbo/config/context/AbstractConfigManager;Ljava/lang/String;)Ljava/util/function/Predicate;
      44: invokeinterface #122,  2          // InterfaceMethod java/util/stream/Stream.filter:(Ljava/util/function/Predicate;)Ljava/util/stream/Stream;
      49: invokestatic  #123                // Method java/util/stream/Collectors.toList:()Ljava/util/stream/Collector;
      52: invokeinterface #124,  2          // InterfaceMethod java/util/stream/Stream.collect:(Ljava/util/stream/Collector;)Ljava/lang/Object;
      57: checkcast     #125                // class java/util/List
      60: astore        4
      62: aload         4
      64: invokeinterface #126,  1          // InterfaceMethod java/util/List.size:()I
      69: iconst_1
      70: if_icmple     115
      73: new           #99                 // class java/lang/IllegalStateException
      76: dup
      77: new           #33                 // class java/lang/StringBuilder
      80: dup
      81: invokespecial #34                 // Method java/lang/StringBuilder."<init>":()V
      84: ldc           #127                // String Found more than one config by name:
      86: invokevirtual #36                 // Method java/lang/StringBuilder.append:(Ljava/lang/String;)Ljava/lang/StringBuilder;
      89: aload_2
      90: invokevirtual #36                 // Method java/lang/StringBuilder.append:(Ljava/lang/String;)Ljava/lang/StringBuilder;
      93: ldc           #128                // String , instances:
      95: invokevirtual #36                 // Method java/lang/StringBuilder.append:(Ljava/lang/String;)Ljava/lang/StringBuilder;
      98: aload         4
     100: invokevirtual #54                 // Method java/lang/StringBuilder.append:(Ljava/lang/Object;)Ljava/lang/StringBuilder;
     103: ldc           #129                // String . Please remove redundant configs or get config by id.
     105: invokevirtual #36                 // Method java/lang/StringBuilder.append:(Ljava/lang/String;)Ljava/lang/StringBuilder;
     108: invokevirtual #40                 // Method java/lang/StringBuilder.toString:()Ljava/lang/String;
     111: invokespecial #104                // Method java/lang/IllegalStateException."<init>":(Ljava/lang/String;)V
     114: athrow
     115: aload         4
     117: invokeinterface #126,  1          // InterfaceMethod java/util/List.size:()I
     122: iconst_1
     123: if_icmpne     138
     126: aload         4
     128: iconst_0
     129: invokeinterface #130,  2          // InterfaceMethod java/util/List.get:(I)Ljava/lang/Object;
     134: checkcast     #72                 // class org/apache/dubbo/config/AbstractConfig
     137: areturn
     138: aconst_null
     139: areturn

  private <C extends org.apache.dubbo.config.AbstractConfig> java.lang.String getConfigName(C);
    Code:
       0: aload_1
       1: ldc           #118                // String getName
       3: invokestatic  #131                // Method org/apache/dubbo/common/utils/ReflectUtils.getProperty:(Ljava/lang/Object;Ljava/lang/String;)Ljava/lang/Object;
       6: checkcast     #28                 // class java/lang/String
       9: areturn
      10: astore_2
      11: aconst_null
      12: areturn
    Exception table:
       from    to  target type
           0     9    10   Class java/lang/Exception

  protected <C extends org.apache.dubbo.config.AbstractConfig> java.util.Optional<C> findConfigByValue(java.util.Collection<C>, C);
    Code:
       0: aload_1
       1: invokeinterface #120,  1          // InterfaceMethod java/util/Collection.stream:()Ljava/util/stream/Stream;
       6: aload_2
       7: invokedynamic #132,  0            // InvokeDynamic #3:test:(Lorg/apache/dubbo/config/AbstractConfig;)Ljava/util/function/Predicate;
      12: invokeinterface #122,  2          // InterfaceMethod java/util/stream/Stream.filter:(Ljava/util/function/Predicate;)Ljava/util/stream/Stream;
      17: invokeinterface #133,  1          // InterfaceMethod java/util/stream/Stream.findFirst:()Ljava/util/Optional;
      22: astore_3
      23: aload_3
      24: invokevirtual #78                 // Method java/util/Optional.isPresent:()Z
      27: ifeq          32
      30: aload_3
      31: areturn
      32: aload_1
      33: invokeinterface #120,  1          // InterfaceMethod java/util/Collection.stream:()Ljava/util/stream/Stream;
      38: aload_0
      39: aload_2
      40: invokedynamic #134,  0            // InvokeDynamic #4:test:(Lorg/apache/dubbo/config/context/AbstractConfigManager;Lorg/apache/dubbo/config/AbstractConfig;)Ljava/util/function/Predicate;
      45: invokeinterface #122,  2          // InterfaceMethod java/util/stream/Stream.filter:(Ljava/util/function/Predicate;)Ljava/util/stream/Stream;
      50: invokeinterface #133,  1          // InterfaceMethod java/util/stream/Stream.findFirst:()Ljava/util/Optional;
      55: astore_3
      56: aload_3
      57: areturn

  protected boolean isEquals(org.apache.dubbo.config.AbstractConfig, org.apache.dubbo.config.AbstractConfig);
    Code:
       0: aload_1
       1: aload_2
       2: if_acmpne     7
       5: iconst_1
       6: ireturn
       7: aload_1
       8: ifnull        15
      11: aload_2
      12: ifnonnull     17
      15: iconst_0
      16: ireturn
      17: aload_1
      18: invokevirtual #56                 // Method java/lang/Object.getClass:()Ljava/lang/Class;
      21: aload_2
      22: invokevirtual #56                 // Method java/lang/Object.getClass:()Ljava/lang/Class;
      25: if_acmpeq     30
      28: iconst_0
      29: ireturn
      30: aload_1
      31: invokevirtual #135                // Method org/apache/dubbo/config/AbstractConfig.isRefreshed:()Z
      34: ifne          44
      37: aload_2
      38: invokevirtual #135                // Method org/apache/dubbo/config/AbstractConfig.isRefreshed:()Z
      41: ifeq          66
      44: aload_1
      45: invokevirtual #135                // Method org/apache/dubbo/config/AbstractConfig.isRefreshed:()Z
      48: ifne          55
      51: aload_1
      52: invokevirtual #136                // Method org/apache/dubbo/config/AbstractConfig.refresh:()V
      55: aload_2
      56: invokevirtual #135                // Method org/apache/dubbo/config/AbstractConfig.isRefreshed:()Z
      59: ifne          66
      62: aload_2
      63: invokevirtual #136                // Method org/apache/dubbo/config/AbstractConfig.refresh:()V
      66: aload_1
      67: aload_2
      68: invokevirtual #73                 // Method org/apache/dubbo/config/AbstractConfig.equals:(Ljava/lang/Object;)Z
      71: ireturn

  protected <C extends org.apache.dubbo.config.AbstractConfig> java.lang.String generateConfigId(C);
    Code:
       0: aload_1
       1: invokevirtual #56                 // Method java/lang/Object.getClass:()Ljava/lang/Class;
       4: invokestatic  #62                 // Method org/apache/dubbo/config/AbstractConfig.getTagName:(Ljava/lang/Class;)Ljava/lang/String;
       7: astore_2
       8: aload_0
       9: getfield      #7                  // Field configIdIndexes:Ljava/util/Map;
      12: aload_2
      13: invokedynamic #137,  0            // InvokeDynamic #5:apply:()Ljava/util/function/Function;
      18: invokeinterface #64,  3           // InterfaceMethod java/util/Map.computeIfAbsent:(Ljava/lang/Object;Ljava/util/function/Function;)Ljava/lang/Object;
      23: checkcast     #138                // class java/util/concurrent/atomic/AtomicInteger
      26: invokevirtual #139                // Method java/util/concurrent/atomic/AtomicInteger.incrementAndGet:()I
      29: istore_3
      30: new           #33                 // class java/lang/StringBuilder
      33: dup
      34: invokespecial #34                 // Method java/lang/StringBuilder."<init>":()V
      37: aload_2
      38: invokevirtual #36                 // Method java/lang/StringBuilder.append:(Ljava/lang/String;)Ljava/lang/StringBuilder;
      41: ldc           #140                // String #
      43: invokevirtual #36                 // Method java/lang/StringBuilder.append:(Ljava/lang/String;)Ljava/lang/StringBuilder;
      46: iload_3
      47: invokevirtual #102                // Method java/lang/StringBuilder.append:(I)Ljava/lang/StringBuilder;
      50: invokevirtual #40                 // Method java/lang/StringBuilder.toString:()Ljava/lang/String;
      53: areturn

  public <C extends org.apache.dubbo.config.AbstractConfig> java.util.List<C> getDefaultConfigs(java.lang.Class<C>);
    Code:
       0: aload_0
       1: aload_1
       2: invokestatic  #62                 // Method org/apache/dubbo/config/AbstractConfig.getTagName:(Ljava/lang/Class;)Ljava/lang/String;
       5: invokevirtual #97                 // Method getConfigsMap:(Ljava/lang/String;)Ljava/util/Map;
       8: invokestatic  #141                // Method getDefaultConfigs:(Ljava/util/Map;)Ljava/util/List;
      11: areturn

  static <C extends org.apache.dubbo.config.AbstractConfig> java.lang.Boolean isDefaultConfig(C);
    Code:
       0: aload_0
       1: invokevirtual #142                // Method org/apache/dubbo/config/AbstractConfig.isDefault:()Ljava/lang/Boolean;
       4: areturn

  static <C extends org.apache.dubbo.config.AbstractConfig> java.util.List<C> getDefaultConfigs(java.util.Map<java.lang.String, C>);
    Code:
       0: aload_0
       1: invokeinterface #68,  1           // InterfaceMethod java/util/Map.values:()Ljava/util/Collection;
       6: invokeinterface #120,  1          // InterfaceMethod java/util/Collection.stream:()Ljava/util/stream/Stream;
      11: invokedynamic #143,  0            // InvokeDynamic #6:test:()Ljava/util/function/Predicate;
      16: invokeinterface #122,  2          // InterfaceMethod java/util/stream/Stream.filter:(Ljava/util/function/Predicate;)Ljava/util/stream/Stream;
      21: invokestatic  #123                // Method java/util/stream/Collectors.toList:()Ljava/util/stream/Collector;
      24: invokeinterface #124,  2          // InterfaceMethod java/util/stream/Stream.collect:(Ljava/util/stream/Collector;)Ljava/lang/Object;
      29: checkcast     #125                // class java/util/List
      32: astore_1
      33: aload_1
      34: invokeinterface #126,  1          // InterfaceMethod java/util/List.size:()I
      39: ifle          44
      42: aload_1
      43: areturn
      44: aload_0
      45: invokeinterface #68,  1           // InterfaceMethod java/util/Map.values:()Ljava/util/Collection;
      50: invokeinterface #120,  1          // InterfaceMethod java/util/Collection.stream:()Ljava/util/stream/Stream;
      55: invokedynamic #144,  0            // InvokeDynamic #7:test:()Ljava/util/function/Predicate;
      60: invokeinterface #122,  2          // InterfaceMethod java/util/stream/Stream.filter:(Ljava/util/function/Predicate;)Ljava/util/stream/Stream;
      65: invokestatic  #123                // Method java/util/stream/Collectors.toList:()Ljava/util/stream/Collector;
      68: invokeinterface #124,  2          // InterfaceMethod java/util/stream/Stream.collect:(Ljava/util/stream/Collector;)Ljava/lang/Object;
      73: checkcast     #125                // class java/util/List
      76: astore_1
      77: aload_1
      78: areturn

  protected <C extends org.apache.dubbo.config.AbstractConfig> java.util.Optional<C> checkUniqueConfig(java.util.Map<java.lang.String, C>, C);
    Code:
       0: aload_1
       1: invokeinterface #98,  1           // InterfaceMethod java/util/Map.size:()I
       6: ifle          465
       9: aload_0
      10: aload_2
      11: invokevirtual #145                // Method isUniqueConfig:(Lorg/apache/dubbo/config/AbstractConfig;)Z
      14: ifeq          465
      17: aload_1
      18: invokeinterface #68,  1           // InterfaceMethod java/util/Map.values:()Ljava/util/Collection;
      23: invokeinterface #69,  1           // InterfaceMethod java/util/Collection.iterator:()Ljava/util/Iterator;
      28: invokeinterface #71,  1           // InterfaceMethod java/util/Iterator.next:()Ljava/lang/Object;
      33: checkcast     #72                 // class org/apache/dubbo/config/AbstractConfig
      36: astore_3
      37: aload_3
      38: invokevirtual #56                 // Method java/lang/Object.getClass:()Ljava/lang/Class;
      41: invokevirtual #85                 // Method java/lang/Class.getSimpleName:()Ljava/lang/String;
      44: astore        4
      46: new           #33                 // class java/lang/StringBuilder
      49: dup
      50: invokespecial #34                 // Method java/lang/StringBuilder."<init>":()V
      53: ldc           #146                // String Duplicate Configs found for
      55: invokevirtual #36                 // Method java/lang/StringBuilder.append:(Ljava/lang/String;)Ljava/lang/StringBuilder;
      58: aload         4
      60: invokevirtual #36                 // Method java/lang/StringBuilder.append:(Ljava/lang/String;)Ljava/lang/StringBuilder;
      63: ldc           #147                // String , only one unique
      65: invokevirtual #36                 // Method java/lang/StringBuilder.append:(Ljava/lang/String;)Ljava/lang/StringBuilder;
      68: aload         4
      70: invokevirtual #36                 // Method java/lang/StringBuilder.append:(Ljava/lang/String;)Ljava/lang/StringBuilder;
      73: ldc           #148                // String  is allowed for one application. previous:
      75: invokevirtual #36                 // Method java/lang/StringBuilder.append:(Ljava/lang/String;)Ljava/lang/StringBuilder;
      78: aload_3
      79: invokevirtual #54                 // Method java/lang/StringBuilder.append:(Ljava/lang/Object;)Ljava/lang/StringBuilder;
      82: ldc           #149                // String , later:
      84: invokevirtual #36                 // Method java/lang/StringBuilder.append:(Ljava/lang/String;)Ljava/lang/StringBuilder;
      87: aload_2
      88: invokevirtual #54                 // Method java/lang/StringBuilder.append:(Ljava/lang/Object;)Ljava/lang/StringBuilder;
      91: ldc           #150                // String . According to config mode [
      93: invokevirtual #36                 // Method java/lang/StringBuilder.append:(Ljava/lang/String;)Ljava/lang/StringBuilder;
      96: aload_0
      97: getfield      #15                 // Field configMode:Lorg/apache/dubbo/config/context/ConfigMode;
     100: invokevirtual #54                 // Method java/lang/StringBuilder.append:(Ljava/lang/Object;)Ljava/lang/StringBuilder;
     103: ldc           #151                // String ],
     105: invokevirtual #36                 // Method java/lang/StringBuilder.append:(Ljava/lang/String;)Ljava/lang/StringBuilder;
     108: invokevirtual #40                 // Method java/lang/StringBuilder.toString:()Ljava/lang/String;
     111: astore        5
     113: getstatic     #152                // Field org/apache/dubbo/config/context/AbstractConfigManager$1.$SwitchMap$org$apache$dubbo$config$context$ConfigMode:[I
     116: aload_0
     117: getfield      #15                 // Field configMode:Lorg/apache/dubbo/config/context/ConfigMode;
     120: invokevirtual #153                // Method org/apache/dubbo/config/context/ConfigMode.ordinal:()I
     123: iaload
     124: tableswitch   { // 1 to 5
                     1: 160
                     2: 197
                     3: 260
                     4: 327
                     5: 396
               default: 465
          }
     160: aload_0
     161: aload_3
     162: aload_2
     163: invokevirtual #84                 // Method isEquals:(Lorg/apache/dubbo/config/AbstractConfig;Lorg/apache/dubbo/config/AbstractConfig;)Z
     166: ifne          465
     169: new           #99                 // class java/lang/IllegalStateException
     172: dup
     173: new           #33                 // class java/lang/StringBuilder
     176: dup
     177: invokespecial #34                 // Method java/lang/StringBuilder."<init>":()V
     180: aload         5
     182: invokevirtual #36                 // Method java/lang/StringBuilder.append:(Ljava/lang/String;)Ljava/lang/StringBuilder;
     185: ldc           #154                // String please remove redundant configs and keep only one.
     187: invokevirtual #36                 // Method java/lang/StringBuilder.append:(Ljava/lang/String;)Ljava/lang/StringBuilder;
     190: invokevirtual #40                 // Method java/lang/StringBuilder.toString:()Ljava/lang/String;
     193: invokespecial #104                // Method java/lang/IllegalStateException."<init>":(Ljava/lang/String;)V
     196: athrow
     197: getstatic     #41                 // Field logger:Lorg/apache/dubbo/common/logger/ErrorTypeAwareLogger;
     200: invokeinterface #155,  1          // InterfaceMethod org/apache/dubbo/common/logger/ErrorTypeAwareLogger.isWarnEnabled:()Z
     205: ifeq          255
     208: aload_0
     209: getfield      #10                 // Field duplicatedConfigs:Ljava/util/Set;
     212: aload_2
     213: invokeinterface #107,  2          // InterfaceMethod java/util/Set.add:(Ljava/lang/Object;)Z
     218: ifeq          255
     221: getstatic     #41                 // Field logger:Lorg/apache/dubbo/common/logger/ErrorTypeAwareLogger;
     224: ldc           #86                 // String 0-12
     226: ldc           #43                 // String
     228: ldc           #43                 // String
     230: new           #33                 // class java/lang/StringBuilder
     233: dup
     234: invokespecial #34                 // Method java/lang/StringBuilder."<init>":()V
     237: aload         5
     239: invokevirtual #36                 // Method java/lang/StringBuilder.append:(Ljava/lang/String;)Ljava/lang/StringBuilder;
     242: ldc           #156                // String keep previous config and ignore later config
     244: invokevirtual #36                 // Method java/lang/StringBuilder.append:(Ljava/lang/String;)Ljava/lang/StringBuilder;
     247: invokevirtual #40                 // Method java/lang/StringBuilder.toString:()Ljava/lang/String;
     250: invokeinterface #90,  5           // InterfaceMethod org/apache/dubbo/common/logger/ErrorTypeAwareLogger.warn:(Ljava/lang/String;Ljava/lang/String;Ljava/lang/String;Ljava/lang/String;)V
     255: aload_3
     256: invokestatic  #157                // Method java/util/Optional.of:(Ljava/lang/Object;)Ljava/util/Optional;
     259: areturn
     260: aload_1
     261: invokeinterface #158,  1          // InterfaceMethod java/util/Map.clear:()V
     266: getstatic     #41                 // Field logger:Lorg/apache/dubbo/common/logger/ErrorTypeAwareLogger;
     269: invokeinterface #155,  1          // InterfaceMethod org/apache/dubbo/common/logger/ErrorTypeAwareLogger.isWarnEnabled:()Z
     274: ifeq          465
     277: aload_0
     278: getfield      #10                 // Field duplicatedConfigs:Ljava/util/Set;
     281: aload_2
     282: invokeinterface #107,  2          // InterfaceMethod java/util/Set.add:(Ljava/lang/Object;)Z
     287: ifeq          465
     290: getstatic     #41                 // Field logger:Lorg/apache/dubbo/common/logger/ErrorTypeAwareLogger;
     293: ldc           #86                 // String 0-12
     295: ldc           #43                 // String
     297: ldc           #43                 // String
     299: new           #33                 // class java/lang/StringBuilder
     302: dup
     303: invokespecial #34                 // Method java/lang/StringBuilder."<init>":()V
     306: aload         5
     308: invokevirtual #36                 // Method java/lang/StringBuilder.append:(Ljava/lang/String;)Ljava/lang/StringBuilder;
     311: ldc           #159                // String override previous config with later config
     313: invokevirtual #36                 // Method java/lang/StringBuilder.append:(Ljava/lang/String;)Ljava/lang/StringBuilder;
     316: invokevirtual #40                 // Method java/lang/StringBuilder.toString:()Ljava/lang/String;
     319: invokeinterface #90,  5           // InterfaceMethod org/apache/dubbo/common/logger/ErrorTypeAwareLogger.warn:(Ljava/lang/String;Ljava/lang/String;Ljava/lang/String;Ljava/lang/String;)V
     324: goto          465
     327: aload_3
     328: aload_2
     329: iconst_1
     330: invokevirtual #160                // Method org/apache/dubbo/config/AbstractConfig.overrideWithConfig:(Lorg/apache/dubbo/config/AbstractConfig;Z)V
     333: getstatic     #41                 // Field logger:Lorg/apache/dubbo/common/logger/ErrorTypeAwareLogger;
     336: invokeinterface #155,  1          // InterfaceMethod org/apache/dubbo/common/logger/ErrorTypeAwareLogger.isWarnEnabled:()Z
     341: ifeq          391
     344: aload_0
     345: getfield      #10                 // Field duplicatedConfigs:Ljava/util/Set;
     348: aload_2
     349: invokeinterface #107,  2          // InterfaceMethod java/util/Set.add:(Ljava/lang/Object;)Z
     354: ifeq          391
     357: getstatic     #41                 // Field logger:Lorg/apache/dubbo/common/logger/ErrorTypeAwareLogger;
     360: ldc           #86                 // String 0-12
     362: ldc           #43                 // String
     364: ldc           #43                 // String
     366: new           #33                 // class java/lang/StringBuilder
     369: dup
     370: invokespecial #34                 // Method java/lang/StringBuilder."<init>":()V
     373: aload         5
     375: invokevirtual #36                 // Method java/lang/StringBuilder.append:(Ljava/lang/String;)Ljava/lang/StringBuilder;
     378: ldc           #159                // String override previous config with later config
     380: invokevirtual #36                 // Method java/lang/StringBuilder.append:(Ljava/lang/String;)Ljava/lang/StringBuilder;
     383: invokevirtual #40                 // Method java/lang/StringBuilder.toString:()Ljava/lang/String;
     386: invokeinterface #90,  5           // InterfaceMethod org/apache/dubbo/common/logger/ErrorTypeAwareLogger.warn:(Ljava/lang/String;Ljava/lang/String;Ljava/lang/String;Ljava/lang/String;)V
     391: aload_3
     392: invokestatic  #157                // Method java/util/Optional.of:(Ljava/lang/Object;)Ljava/util/Optional;
     395: areturn
     396: aload_3
     397: aload_2
     398: iconst_0
     399: invokevirtual #160                // Method org/apache/dubbo/config/AbstractConfig.overrideWithConfig:(Lorg/apache/dubbo/config/AbstractConfig;Z)V
     402: getstatic     #41                 // Field logger:Lorg/apache/dubbo/common/logger/ErrorTypeAwareLogger;
     405: invokeinterface #155,  1          // InterfaceMethod org/apache/dubbo/common/logger/ErrorTypeAwareLogger.isWarnEnabled:()Z
     410: ifeq          460
     413: aload_0
     414: getfield      #10                 // Field duplicatedConfigs:Ljava/util/Set;
     417: aload_2
     418: invokeinterface #107,  2          // InterfaceMethod java/util/Set.add:(Ljava/lang/Object;)Z
     423: ifeq          460
     426: getstatic     #41                 // Field logger:Lorg/apache/dubbo/common/logger/ErrorTypeAwareLogger;
     429: ldc           #86                 // String 0-12
     431: ldc           #43                 // String
     433: ldc           #43                 // String
     435: new           #33                 // class java/lang/StringBuilder
     438: dup
     439: invokespecial #34                 // Method java/lang/StringBuilder."<init>":()V
     442: aload         5
     444: invokevirtual #36                 // Method java/lang/StringBuilder.append:(Ljava/lang/String;)Ljava/lang/StringBuilder;
     447: ldc           #159                // String override previous config with later config
     449: invokevirtual #36                 // Method java/lang/StringBuilder.append:(Ljava/lang/String;)Ljava/lang/StringBuilder;
     452: invokevirtual #40                 // Method java/lang/StringBuilder.toString:()Ljava/lang/String;
     455: invokeinterface #90,  5           // InterfaceMethod org/apache/dubbo/common/logger/ErrorTypeAwareLogger.warn:(Ljava/lang/String;Ljava/lang/String;Ljava/lang/String;Ljava/lang/String;)V
     460: aload_3
     461: invokestatic  #157                // Method java/util/Optional.of:(Ljava/lang/Object;)Ljava/util/Optional;
     464: areturn
     465: invokestatic  #161                // Method java/util/Optional.empty:()Ljava/util/Optional;
     468: areturn

  public abstract void loadConfigs();

  public <T extends org.apache.dubbo.config.AbstractConfig> java.util.List<T> loadConfigsOfTypeFromProps(java.lang.Class<T>);
    Code:
       0: new           #162                // class java/util/ArrayList
       3: dup
       4: invokespecial #163                // Method java/util/ArrayList."<init>":()V
       7: astore_2
       8: aload_0
       9: getfield      #22                 // Field environment:Lorg/apache/dubbo/common/config/Environment;
      12: invokevirtual #164                // Method org/apache/dubbo/common/config/Environment.getPropertiesConfiguration:()Lorg/apache/dubbo/common/config/PropertiesConfiguration;
      15: astore_3
      16: aload_0
      17: aload_1
      18: invokespecial #165                // Method getConfigIdsFromProps:(Ljava/lang/Class;)Ljava/util/Set;
      21: astore        4
      23: aload         4
      25: aload_0
      26: aload_1
      27: aload_3
      28: aload_2
      29: invokedynamic #166,  0            // InvokeDynamic #8:accept:(Lorg/apache/dubbo/config/context/AbstractConfigManager;Ljava/lang/Class;Lorg/apache/dubbo/common/config/PropertiesConfiguration;Ljava/util/List;)Ljava/util/function/Consumer;
      34: invokeinterface #167,  2          // InterfaceMethod java/util/Set.forEach:(Ljava/util/function/Consumer;)V
      39: aload_0
      40: aload_1
      41: invokevirtual #168                // Method getConfigs:(Ljava/lang/Class;)Ljava/util/Collection;
      44: invokeinterface #169,  1          // InterfaceMethod java/util/Collection.isEmpty:()Z
      49: ifeq          140
      52: aload_0
      53: getfield      #22                 // Field environment:Lorg/apache/dubbo/common/config/Environment;
      56: invokevirtual #170                // Method org/apache/dubbo/common/config/Environment.getConfigurationMaps:()Ljava/util/List;
      59: astore        5
      61: aload         5
      63: aload_1
      64: invokestatic  #171                // Method org/apache/dubbo/config/AbstractConfig.getTypePrefix:(Ljava/lang/Class;)Ljava/lang/String;
      67: invokestatic  #172                // Method org/apache/dubbo/common/config/ConfigurationUtils.hasSubProperties:(Ljava/util/Collection;Ljava/lang/String;)Z
      70: ifeq          140
      73: aload_0
      74: aload_1
      75: aload_0
      76: getfield      #17                 // Field scopeModel:Lorg/apache/dubbo/rpc/model/ScopeModel;
      79: invokespecial #173                // Method createConfig:(Ljava/lang/Class;Lorg/apache/dubbo/rpc/model/ScopeModel;)Lorg/apache/dubbo/config/AbstractConfig;
      82: astore        6
      84: aload         6
      86: invokevirtual #136                // Method org/apache/dubbo/config/AbstractConfig.refresh:()V
      89: goto          124
      92: astore        7
      94: new           #99                 // class java/lang/IllegalStateException
      97: dup
      98: new           #33                 // class java/lang/StringBuilder
     101: dup
     102: invokespecial #34                 // Method java/lang/StringBuilder."<init>":()V
     105: ldc           #174                // String create default config instance failed, type:
     107: invokevirtual #36                 // Method java/lang/StringBuilder.append:(Ljava/lang/String;)Ljava/lang/StringBuilder;
     110: aload_1
     111: invokevirtual #85                 // Method java/lang/Class.getSimpleName:()Ljava/lang/String;
     114: invokevirtual #36                 // Method java/lang/StringBuilder.append:(Ljava/lang/String;)Ljava/lang/StringBuilder;
     117: invokevirtual #40                 // Method java/lang/StringBuilder.toString:()Ljava/lang/String;
     120: invokespecial #104                // Method java/lang/IllegalStateException."<init>":(Ljava/lang/String;)V
     123: athrow
     124: aload_0
     125: aload         6
     127: invokevirtual #175                // Method addConfig:(Lorg/apache/dubbo/config/AbstractConfig;)Lorg/apache/dubbo/config/AbstractConfig;
     130: pop
     131: aload_2
     132: aload         6
     134: invokeinterface #176,  2          // InterfaceMethod java/util/List.add:(Ljava/lang/Object;)Z
     139: pop
     140: aload_2
     141: areturn
    Exception table:
       from    to  target type
          73    89    92   Class java/lang/Exception

  private <T extends org.apache.dubbo.config.AbstractConfig> T createConfig(java.lang.Class<T>, org.apache.dubbo.rpc.model.ScopeModel) throws java.lang.ReflectiveOperationException;
    Code:
       0: aload_1
       1: iconst_0
       2: anewarray     #75                 // class java/lang/Class
       5: invokevirtual #177                // Method java/lang/Class.getDeclaredConstructor:([Ljava/lang/Class;)Ljava/lang/reflect/Constructor;
       8: iconst_0
       9: anewarray     #88                 // class java/lang/Object
      12: invokevirtual #178                // Method java/lang/reflect/Constructor.newInstance:([Ljava/lang/Object;)Ljava/lang/Object;
      15: checkcast     #72                 // class org/apache/dubbo/config/AbstractConfig
      18: astore_3
      19: aload_3
      20: aload_2
      21: invokevirtual #61                 // Method org/apache/dubbo/config/AbstractConfig.setScopeModel:(Lorg/apache/dubbo/rpc/model/ScopeModel;)V
      24: aload_3
      25: areturn

  private java.util.Set<java.lang.String> getConfigIdsFromProps(java.lang.Class<? extends org.apache.dubbo.config.AbstractConfig>);
    Code:
       0: new           #33                 // class java/lang/StringBuilder
       3: dup
       4: invokespecial #34                 // Method java/lang/StringBuilder."<init>":()V
       7: ldc           #179                // String dubbo.
       9: invokevirtual #36                 // Method java/lang/StringBuilder.append:(Ljava/lang/String;)Ljava/lang/StringBuilder;
      12: aload_1
      13: invokestatic  #180                // Method org/apache/dubbo/config/AbstractConfig.getPluralTagName:(Ljava/lang/Class;)Ljava/lang/String;
      16: invokevirtual #36                 // Method java/lang/StringBuilder.append:(Ljava/lang/String;)Ljava/lang/StringBuilder;
      19: ldc           #181                // String .
      21: invokevirtual #36                 // Method java/lang/StringBuilder.append:(Ljava/lang/String;)Ljava/lang/StringBuilder;
      24: invokevirtual #40                 // Method java/lang/StringBuilder.toString:()Ljava/lang/String;
      27: astore_2
      28: aload_0
      29: getfield      #22                 // Field environment:Lorg/apache/dubbo/common/config/Environment;
      32: invokevirtual #170                // Method org/apache/dubbo/common/config/Environment.getConfigurationMaps:()Ljava/util/List;
      35: aload_2
      36: invokestatic  #182                // Method org/apache/dubbo/common/config/ConfigurationUtils.getSubIds:(Ljava/util/Collection;Ljava/lang/String;)Ljava/util/Set;
      39: areturn

  protected <T extends org.apache.dubbo.config.AbstractConfig> void checkDefaultAndValidateConfigs(java.lang.Class<T>);
    Code:
       0: aload_0
       1: aload_1
       2: invokespecial #183                // Method shouldAddDefaultConfig:(Ljava/lang/Class;)Z
       5: ifeq          73
       8: aload_0
       9: aload_1
      10: aload_0
      11: getfield      #17                 // Field scopeModel:Lorg/apache/dubbo/rpc/model/ScopeModel;
      14: invokespecial #173                // Method createConfig:(Ljava/lang/Class;Lorg/apache/dubbo/rpc/model/ScopeModel;)Lorg/apache/dubbo/config/AbstractConfig;
      17: astore_2
      18: aload_2
      19: invokevirtual #136                // Method org/apache/dubbo/config/AbstractConfig.refresh:()V
      22: aload_0
      23: aload_2
      24: invokevirtual #184                // Method isNeedValidation:(Lorg/apache/dubbo/config/AbstractConfig;)Z
      27: ifeq          37
      30: aload_2
      31: invokevirtual #185                // Method org/apache/dubbo/config/AbstractConfig.isValid:()Z
      34: ifeq          46
      37: aload_0
      38: aload_2
      39: invokevirtual #175                // Method addConfig:(Lorg/apache/dubbo/config/AbstractConfig;)Lorg/apache/dubbo/config/AbstractConfig;
      42: pop
      43: goto          73
      46: getstatic     #41                 // Field logger:Lorg/apache/dubbo/common/logger/ErrorTypeAwareLogger;
      49: new           #33                 // class java/lang/StringBuilder
      52: dup
      53: invokespecial #34                 // Method java/lang/StringBuilder."<init>":()V
      56: ldc           #186                // String Ignore invalid config:
      58: invokevirtual #36                 // Method java/lang/StringBuilder.append:(Ljava/lang/String;)Ljava/lang/StringBuilder;
      61: aload_2
      62: invokevirtual #54                 // Method java/lang/StringBuilder.append:(Ljava/lang/Object;)Ljava/lang/StringBuilder;
      65: invokevirtual #40                 // Method java/lang/StringBuilder.toString:()Ljava/lang/String;
      68: invokeinterface #55,  2           // InterfaceMethod org/apache/dubbo/common/logger/ErrorTypeAwareLogger.info:(Ljava/lang/String;)V
      73: goto          108
      76: astore_2
      77: new           #99                 // class java/lang/IllegalStateException
      80: dup
      81: new           #33                 // class java/lang/StringBuilder
      84: dup
      85: invokespecial #34                 // Method java/lang/StringBuilder."<init>":()V
      88: ldc           #187                // String Add default config failed:
      90: invokevirtual #36                 // Method java/lang/StringBuilder.append:(Ljava/lang/String;)Ljava/lang/StringBuilder;
      93: aload_1
      94: invokevirtual #85                 // Method java/lang/Class.getSimpleName:()Ljava/lang/String;
      97: invokevirtual #36                 // Method java/lang/StringBuilder.append:(Ljava/lang/String;)Ljava/lang/StringBuilder;
     100: invokevirtual #40                 // Method java/lang/StringBuilder.toString:()Ljava/lang/String;
     103: aload_2
     104: invokespecial #188                // Method java/lang/IllegalStateException."<init>":(Ljava/lang/String;Ljava/lang/Throwable;)V
     107: athrow
     108: aload_0
     109: aload_1
     110: invokevirtual #168                // Method getConfigs:(Ljava/lang/Class;)Ljava/util/Collection;
     113: astore_2
     114: aload_0
     115: invokespecial #189                // Method getConfigValidator:()Lorg/apache/dubbo/config/context/ConfigValidator;
     118: ifnull        162
     121: aload_2
     122: invokeinterface #69,  1           // InterfaceMethod java/util/Collection.iterator:()Ljava/util/Iterator;
     127: astore_3
     128: aload_3
     129: invokeinterface #70,  1           // InterfaceMethod java/util/Iterator.hasNext:()Z
     134: ifeq          162
     137: aload_3
     138: invokeinterface #71,  1           // InterfaceMethod java/util/Iterator.next:()Ljava/lang/Object;
     143: checkcast     #72                 // class org/apache/dubbo/config/AbstractConfig
     146: astore        4
     148: aload_0
     149: invokespecial #189                // Method getConfigValidator:()Lorg/apache/dubbo/config/context/ConfigValidator;
     152: aload         4
     154: invokeinterface #190,  2          // InterfaceMethod org/apache/dubbo/config/context/ConfigValidator.validate:(Lorg/apache/dubbo/config/AbstractConfig;)V
     159: goto          128
     162: aload_0
     163: aload_1
     164: invokevirtual #191                // Method isRequired:(Ljava/lang/Class;)Z
     167: ifeq          209
     170: aload_2
     171: invokeinterface #169,  1          // InterfaceMethod java/util/Collection.isEmpty:()Z
     176: ifeq          209
     179: new           #99                 // class java/lang/IllegalStateException
     182: dup
     183: new           #33                 // class java/lang/StringBuilder
     186: dup
     187: invokespecial #34                 // Method java/lang/StringBuilder."<init>":()V
     190: ldc           #192                // String Default config not found for
     192: invokevirtual #36                 // Method java/lang/StringBuilder.append:(Ljava/lang/String;)Ljava/lang/StringBuilder;
     195: aload_1
     196: invokevirtual #85                 // Method java/lang/Class.getSimpleName:()Ljava/lang/String;
     199: invokevirtual #36                 // Method java/lang/StringBuilder.append:(Ljava/lang/String;)Ljava/lang/StringBuilder;
     202: invokevirtual #40                 // Method java/lang/StringBuilder.toString:()Ljava/lang/String;
     205: invokespecial #104                // Method java/lang/IllegalStateException."<init>":(Ljava/lang/String;)V
     208: athrow
     209: return
    Exception table:
       from    to  target type
           0    73    76   Class java/lang/Exception

  protected <T extends org.apache.dubbo.config.AbstractConfig> boolean isNeedValidation(T);
    Code:
       0: aload_1
       1: instanceof    #193                // class org/apache/dubbo/config/MetadataReportConfig
       4: ifeq          9
       7: iconst_0
       8: ireturn
       9: iconst_1
      10: ireturn

  private org.apache.dubbo.config.context.ConfigValidator getConfigValidator();
    Code:
       0: aload_0
       1: getfield      #194                // Field configValidator:Lorg/apache/dubbo/config/context/ConfigValidator;
       4: ifnonnull     26
       7: aload_0
       8: aload_0
       9: getfield      #19                 // Field applicationModel:Lorg/apache/dubbo/rpc/model/ApplicationModel;
      12: invokevirtual #195                // Method org/apache/dubbo/rpc/model/ApplicationModel.getBeanFactory:()Lorg/apache/dubbo/common/beans/factory/ScopeBeanFactory;
      15: ldc           #196                // class org/apache/dubbo/config/context/ConfigValidator
      17: invokevirtual #197                // Method org/apache/dubbo/common/beans/factory/ScopeBeanFactory.getBean:(Ljava/lang/Class;)Ljava/lang/Object;
      20: checkcast     #196                // class org/apache/dubbo/config/context/ConfigValidator
      23: putfield      #194                // Field configValidator:Lorg/apache/dubbo/config/context/ConfigValidator;
      26: aload_0
      27: getfield      #194                // Field configValidator:Lorg/apache/dubbo/config/context/ConfigValidator;
      30: areturn

  protected <T extends org.apache.dubbo.config.AbstractConfig> boolean isRequired(java.lang.Class<T>);
    Code:
       0: aload_1
       1: ldc           #198                // class org/apache/dubbo/config/RegistryConfig
       3: if_acmpeq     30
       6: aload_1
       7: ldc           #193                // class org/apache/dubbo/config/MetadataReportConfig
       9: if_acmpeq     30
      12: aload_1
      13: ldc           #199                // class org/apache/dubbo/config/MonitorConfig
      15: if_acmpeq     30
      18: aload_1
      19: ldc           #200                // class org/apache/dubbo/config/MetricsConfig
      21: if_acmpeq     30
      24: aload_1
      25: ldc           #201                // class org/apache/dubbo/config/TracingConfig
      27: if_acmpne     32
      30: iconst_0
      31: ireturn
      32: iconst_1
      33: ireturn

  private <T extends org.apache.dubbo.config.AbstractConfig> boolean shouldAddDefaultConfig(java.lang.Class<T>);
    Code:
       0: aload_0
       1: aload_1
       2: invokevirtual #191                // Method isRequired:(Ljava/lang/Class;)Z
       5: ifne          10
       8: iconst_0
       9: ireturn
      10: aload_0
      11: aload_1
      12: invokevirtual #202                // Method getDefaultConfigs:(Ljava/lang/Class;)Ljava/util/List;
      15: invokeinterface #203,  1          // InterfaceMethod java/util/List.isEmpty:()Z
      20: ireturn

  public void refreshAll();
    Code:
       0: return

  public boolean removeConfig(org.apache.dubbo.config.AbstractConfig);
    Code:
       0: aload_1
       1: ifnonnull     6
       4: iconst_0
       5: ireturn
       6: aload_0
       7: getfield      #6                  // Field configsCache:Ljava/util/Map;
      10: aload_1
      11: invokevirtual #56                 // Method java/lang/Object.getClass:()Ljava/lang/Class;
      14: invokestatic  #62                 // Method org/apache/dubbo/config/AbstractConfig.getTagName:(Ljava/lang/Class;)Ljava/lang/String;
      17: invokeinterface #83,  2           // InterfaceMethod java/util/Map.get:(Ljava/lang/Object;)Ljava/lang/Object;
      22: checkcast     #65                 // class java/util/Map
      25: astore_2
      26: aload_2
      27: invokestatic  #204                // Method org/apache/dubbo/common/utils/CollectionUtils.isNotEmptyMap:(Ljava/util/Map;)Z
      30: ifeq          53
      33: aload_2
      34: dup
      35: astore_3
      36: monitorenter
      37: aload_0
      38: aload_1
      39: aload_2
      40: invokevirtual #205                // Method removeIfAbsent:(Lorg/apache/dubbo/config/AbstractConfig;Ljava/util/Map;)Z
      43: aload_3
      44: monitorexit
      45: ireturn
      46: astore        4
      48: aload_3
      49: monitorexit
      50: aload         4
      52: athrow
      53: iconst_0
      54: ireturn
    Exception table:
       from    to  target type
          37    45    46   any
          46    50    46   any

  public void destroy() throws java.lang.IllegalStateException;
    Code:
       0: aload_0
       1: invokevirtual #206                // Method clear:()V
       4: return

  public void clear();
    Code:
       0: aload_0
       1: getfield      #6                  // Field configsCache:Ljava/util/Map;
       4: invokeinterface #158,  1          // InterfaceMethod java/util/Map.clear:()V
       9: aload_0
      10: getfield      #7                  // Field configIdIndexes:Ljava/util/Map;
      13: invokeinterface #158,  1          // InterfaceMethod java/util/Map.clear:()V
      18: aload_0
      19: getfield      #10                 // Field duplicatedConfigs:Ljava/util/Set;
      22: invokeinterface #207,  1          // InterfaceMethod java/util/Set.clear:()V
      27: return

  public boolean isInitialized();
    Code:
       0: aload_0
       1: getfield      #13                 // Field initialized:Ljava/util/concurrent/atomic/AtomicBoolean;
       4: invokevirtual #208                // Method java/util/concurrent/atomic/AtomicBoolean.get:()Z
       7: ireturn

  private void lambda$loadConfigsOfTypeFromProps$8(java.lang.Class, org.apache.dubbo.common.config.PropertiesConfiguration, java.util.List, java.lang.String);
    Code:
       0: aload_0
       1: aload_1
       2: aload         4
       4: invokevirtual #209                // Method getConfig:(Ljava/lang/Class;Ljava/lang/String;)Ljava/util/Optional;
       7: invokevirtual #78                 // Method java/util/Optional.isPresent:()Z
      10: ifne          294
      13: aload_0
      14: aload_1
      15: aload_0
      16: getfield      #17                 // Field scopeModel:Lorg/apache/dubbo/rpc/model/ScopeModel;
      19: invokespecial #173                // Method createConfig:(Ljava/lang/Class;Lorg/apache/dubbo/rpc/model/ScopeModel;)Lorg/apache/dubbo/config/AbstractConfig;
      22: astore        5
      24: aload         5
      26: aload         4
      28: invokevirtual #210                // Method org/apache/dubbo/config/AbstractConfig.setId:(Ljava/lang/String;)V
      31: goto          76
      34: astore        6
      36: new           #99                 // class java/lang/IllegalStateException
      39: dup
      40: new           #33                 // class java/lang/StringBuilder
      43: dup
      44: invokespecial #34                 // Method java/lang/StringBuilder."<init>":()V
      47: ldc           #211                // String create config instance failed, id:
      49: invokevirtual #36                 // Method java/lang/StringBuilder.append:(Ljava/lang/String;)Ljava/lang/StringBuilder;
      52: aload         4
      54: invokevirtual #36                 // Method java/lang/StringBuilder.append:(Ljava/lang/String;)Ljava/lang/StringBuilder;
      57: ldc           #212                // String , type:
      59: invokevirtual #36                 // Method java/lang/StringBuilder.append:(Ljava/lang/String;)Ljava/lang/StringBuilder;
      62: aload_1
      63: invokevirtual #85                 // Method java/lang/Class.getSimpleName:()Ljava/lang/String;
      66: invokevirtual #36                 // Method java/lang/StringBuilder.append:(Ljava/lang/String;)Ljava/lang/StringBuilder;
      69: invokevirtual #40                 // Method java/lang/StringBuilder.toString:()Ljava/lang/String;
      72: invokespecial #104                // Method java/lang/IllegalStateException."<init>":(Ljava/lang/String;)V
      75: athrow
      76: aconst_null
      77: astore        6
      79: iconst_0
      80: istore        7
      82: new           #33                 // class java/lang/StringBuilder
      85: dup
      86: invokespecial #34                 // Method java/lang/StringBuilder."<init>":()V
      89: ldc           #179                // String dubbo.
      91: invokevirtual #36                 // Method java/lang/StringBuilder.append:(Ljava/lang/String;)Ljava/lang/StringBuilder;
      94: aload_1
      95: invokestatic  #180                // Method org/apache/dubbo/config/AbstractConfig.getPluralTagName:(Ljava/lang/Class;)Ljava/lang/String;
      98: invokevirtual #36                 // Method java/lang/StringBuilder.append:(Ljava/lang/String;)Ljava/lang/StringBuilder;
     101: ldc           #181                // String .
     103: invokevirtual #36                 // Method java/lang/StringBuilder.append:(Ljava/lang/String;)Ljava/lang/StringBuilder;
     106: aload         4
     108: invokevirtual #36                 // Method java/lang/StringBuilder.append:(Ljava/lang/String;)Ljava/lang/StringBuilder;
     111: ldc           #213                // String .name
     113: invokevirtual #36                 // Method java/lang/StringBuilder.append:(Ljava/lang/String;)Ljava/lang/StringBuilder;
     116: invokevirtual #40                 // Method java/lang/StringBuilder.toString:()Ljava/lang/String;
     119: astore        6
     121: aload_2
     122: aload         6
     124: invokevirtual #214                // Method org/apache/dubbo/common/config/PropertiesConfiguration.getProperty:(Ljava/lang/String;)Ljava/lang/String;
     127: ifnonnull     141
     130: aload_2
     131: aload         6
     133: aload         4
     135: invokevirtual #215                // Method org/apache/dubbo/common/config/PropertiesConfiguration.setProperty:(Ljava/lang/String;Ljava/lang/String;)V
     138: iconst_1
     139: istore        7
     141: aload         5
     143: invokevirtual #136                // Method org/apache/dubbo/config/AbstractConfig.refresh:()V
     146: aload_0
     147: aload         5
     149: invokevirtual #175                // Method addConfig:(Lorg/apache/dubbo/config/AbstractConfig;)Lorg/apache/dubbo/config/AbstractConfig;
     152: pop
     153: aload_3
     154: aload         5
     156: invokeinterface #176,  2          // InterfaceMethod java/util/List.add:(Ljava/lang/Object;)Z
     161: pop
     162: iload         7
     164: ifeq          294
     167: aload         6
     169: ifnull        294
     172: aload_2
     173: aload         6
     175: invokevirtual #216                // Method org/apache/dubbo/common/config/PropertiesConfiguration.remove:(Ljava/lang/String;)Ljava/lang/String;
     178: pop
     179: goto          294
     182: astore        8
     184: getstatic     #41                 // Field logger:Lorg/apache/dubbo/common/logger/ErrorTypeAwareLogger;
     187: ldc           #42                 // String 0-2
     189: ldc           #43                 // String
     191: ldc           #43                 // String
     193: new           #33                 // class java/lang/StringBuilder
     196: dup
     197: invokespecial #34                 // Method java/lang/StringBuilder."<init>":()V
     200: ldc           #217                // String load config failed, id:
     202: invokevirtual #36                 // Method java/lang/StringBuilder.append:(Ljava/lang/String;)Ljava/lang/StringBuilder;
     205: aload         4
     207: invokevirtual #36                 // Method java/lang/StringBuilder.append:(Ljava/lang/String;)Ljava/lang/StringBuilder;
     210: ldc           #212                // String , type:
     212: invokevirtual #36                 // Method java/lang/StringBuilder.append:(Ljava/lang/String;)Ljava/lang/StringBuilder;
     215: aload_1
     216: invokevirtual #85                 // Method java/lang/Class.getSimpleName:()Ljava/lang/String;
     219: invokevirtual #36                 // Method java/lang/StringBuilder.append:(Ljava/lang/String;)Ljava/lang/StringBuilder;
     222: invokevirtual #40                 // Method java/lang/StringBuilder.toString:()Ljava/lang/String;
     225: aload         8
     227: invokeinterface #44,  6           // InterfaceMethod org/apache/dubbo/common/logger/ErrorTypeAwareLogger.error:(Ljava/lang/String;Ljava/lang/String;Ljava/lang/String;Ljava/lang/String;Ljava/lang/Throwable;)V
     232: new           #99                 // class java/lang/IllegalStateException
     235: dup
     236: new           #33                 // class java/lang/StringBuilder
     239: dup
     240: invokespecial #34                 // Method java/lang/StringBuilder."<init>":()V
     243: ldc           #217                // String load config failed, id:
     245: invokevirtual #36                 // Method java/lang/StringBuilder.append:(Ljava/lang/String;)Ljava/lang/StringBuilder;
     248: aload         4
     250: invokevirtual #36                 // Method java/lang/StringBuilder.append:(Ljava/lang/String;)Ljava/lang/StringBuilder;
     253: ldc           #212                // String , type:
     255: invokevirtual #36                 // Method java/lang/StringBuilder.append:(Ljava/lang/String;)Ljava/lang/StringBuilder;
     258: aload_1
     259: invokevirtual #85                 // Method java/lang/Class.getSimpleName:()Ljava/lang/String;
     262: invokevirtual #36                 // Method java/lang/StringBuilder.append:(Ljava/lang/String;)Ljava/lang/StringBuilder;
     265: invokevirtual #40                 // Method java/lang/StringBuilder.toString:()Ljava/lang/String;
     268: invokespecial #104                // Method java/lang/IllegalStateException."<init>":(Ljava/lang/String;)V
     271: athrow
     272: astore        9
     274: iload         7
     276: ifeq          291
     279: aload         6
     281: ifnull        291
     284: aload_2
     285: aload         6
     287: invokevirtual #216                // Method org/apache/dubbo/common/config/PropertiesConfiguration.remove:(Ljava/lang/String;)Ljava/lang/String;
     290: pop
     291: aload         9
     293: athrow
     294: return
    Exception table:
       from    to  target type
          13    31    34   Class java/lang/Exception
          82   162   182   Class java/lang/Exception
          82   162   272   any
         182   274   272   any

  private static boolean lambda$getDefaultConfigs$7(org.apache.dubbo.config.AbstractConfig);
    Code:
       0: aload_0
       1: invokestatic  #218                // Method isDefaultConfig:(Lorg/apache/dubbo/config/AbstractConfig;)Ljava/lang/Boolean;
       4: ifnonnull     11
       7: iconst_1
       8: goto          12
      11: iconst_0
      12: ireturn

  private static boolean lambda$getDefaultConfigs$6(org.apache.dubbo.config.AbstractConfig);
    Code:
       0: getstatic     #219                // Field java/lang/Boolean.TRUE:Ljava/lang/Boolean;
       3: aload_0
       4: invokestatic  #218                // Method isDefaultConfig:(Lorg/apache/dubbo/config/AbstractConfig;)Ljava/lang/Boolean;
       7: invokevirtual #220                // Method java/lang/Boolean.equals:(Ljava/lang/Object;)Z
      10: ireturn

  private static java.util.concurrent.atomic.AtomicInteger lambda$generateConfigId$5(java.lang.String);
    Code:
       0: new           #138                // class java/util/concurrent/atomic/AtomicInteger
       3: dup
       4: iconst_0
       5: invokespecial #221                // Method java/util/concurrent/atomic/AtomicInteger."<init>":(I)V
       8: areturn

  private boolean lambda$findConfigByValue$4(org.apache.dubbo.config.AbstractConfig, org.apache.dubbo.config.AbstractConfig);
    Code:
       0: aload_0
       1: aload_2
       2: aload_1
       3: invokevirtual #84                 // Method isEquals:(Lorg/apache/dubbo/config/AbstractConfig;Lorg/apache/dubbo/config/AbstractConfig;)Z
       6: ireturn

  private static boolean lambda$findConfigByValue$3(org.apache.dubbo.config.AbstractConfig, org.apache.dubbo.config.AbstractConfig);
    Code:
       0: aload_1
       1: aload_0
       2: if_acmpne     9
       5: iconst_1
       6: goto          10
       9: iconst_0
      10: ireturn

  private boolean lambda$getConfigByName$2(java.lang.String, org.apache.dubbo.config.AbstractConfig);
    Code:
       0: aload_1
       1: aload_0
       2: aload_2
       3: invokespecial #222                // Method getConfigName:(Lorg/apache/dubbo/config/AbstractConfig;)Ljava/lang/String;
       6: invokevirtual #223                // Method java/lang/String.equals:(Ljava/lang/Object;)Z
       9: ireturn

  private static boolean lambda$removeIfAbsent$1(org.apache.dubbo.config.AbstractConfig, org.apache.dubbo.config.AbstractConfig);
    Code:
       0: aload_0
       1: aload_1
       2: if_acmpne     9
       5: iconst_1
       6: goto          10
       9: iconst_0
      10: ireturn

  private static java.util.Map lambda$addConfig$0(java.lang.String);
    Code:
       0: new           #4                  // class java/util/concurrent/ConcurrentHashMap
       3: dup
       4: invokespecial #5                  // Method java/util/concurrent/ConcurrentHashMap."<init>":()V
       7: areturn

  static {};
    Code:
       0: ldc           #117                // class org/apache/dubbo/config/context/AbstractConfigManager
       2: invokestatic  #224                // Method org/apache/dubbo/common/logger/LoggerFactory.getErrorTypeAwareLogger:(Ljava/lang/Class;)Lorg/apache/dubbo/common/logger/ErrorTypeAwareLogger;
       5: putstatic     #41                 // Field logger:Lorg/apache/dubbo/common/logger/ErrorTypeAwareLogger;
       8: new           #8                  // class org/apache/dubbo/common/utils/ConcurrentHashSet
      11: dup
      12: invokespecial #9                  // Method org/apache/dubbo/common/utils/ConcurrentHashSet."<init>":()V
      15: putstatic     #94                 // Field uniqueConfigTypes:Ljava/util/Set;
      18: getstatic     #94                 // Field uniqueConfigTypes:Ljava/util/Set;
      21: ldc           #225                // class org/apache/dubbo/config/ApplicationConfig
      23: invokeinterface #107,  2          // InterfaceMethod java/util/Set.add:(Ljava/lang/Object;)Z
      28: pop
      29: getstatic     #94                 // Field uniqueConfigTypes:Ljava/util/Set;
      32: ldc           #199                // class org/apache/dubbo/config/MonitorConfig
      34: invokeinterface #107,  2          // InterfaceMethod java/util/Set.add:(Ljava/lang/Object;)Z
      39: pop
      40: getstatic     #94                 // Field uniqueConfigTypes:Ljava/util/Set;
      43: ldc           #200                // class org/apache/dubbo/config/MetricsConfig
      45: invokeinterface #107,  2          // InterfaceMethod java/util/Set.add:(Ljava/lang/Object;)Z
      50: pop
      51: getstatic     #94                 // Field uniqueConfigTypes:Ljava/util/Set;
      54: ldc           #201                // class org/apache/dubbo/config/TracingConfig
      56: invokeinterface #107,  2          // InterfaceMethod java/util/Set.add:(Ljava/lang/Object;)Z
      61: pop
      62: getstatic     #94                 // Field uniqueConfigTypes:Ljava/util/Set;
      65: ldc           #226                // class org/apache/dubbo/config/SslConfig
      67: invokeinterface #107,  2          // InterfaceMethod java/util/Set.add:(Ljava/lang/Object;)Z
      72: pop
      73: getstatic     #94                 // Field uniqueConfigTypes:Ljava/util/Set;
      76: ldc           #227                // class org/apache/dubbo/config/ModuleConfig
      78: invokeinterface #107,  2          // InterfaceMethod java/util/Set.add:(Ljava/lang/Object;)Z
      83: pop
      84: return
}
