Compiled from "ConfigConfigurationAdapter.java"
public class org.apache.dubbo.config.context.ConfigConfigurationAdapter implements org.apache.dubbo.common.config.Configuration {
  private final java.util.Map<java.lang.String, java.lang.String> metaData;

  public org.apache.dubbo.config.context.ConfigConfigurationAdapter(org.apache.dubbo.config.AbstractConfig, java.lang.String);
    Code:
       0: aload_0
       1: invokespecial #1                  // Method java/lang/Object."<init>":()V
       4: aload_2
       5: invokestatic  #2                  // Method org/apache/dubbo/common/utils/StringUtils.hasText:(Ljava/lang/CharSequence;)Z
       8: ifeq          23
      11: aload_0
      12: aload_1
      13: aload_2
      14: invokevirtual #3                  // Method org/apache/dubbo/config/AbstractConfig.getMetaData:(Ljava/lang/String;)Ljava/util/Map;
      17: putfield      #4                  // Field metaData:Ljava/util/Map;
      20: goto          31
      23: aload_0
      24: aload_1
      25: invokevirtual #5                  // Method org/apache/dubbo/config/AbstractConfig.getMetaData:()Ljava/util/Map;
      28: putfield      #4                  // Field metaData:Ljava/util/Map;
      31: return

  public java.lang.Object getInternalProperty(java.lang.String);
    Code:
       0: aload_0
       1: getfield      #4                  // Field metaData:Ljava/util/Map;
       4: aload_1
       5: invokeinterface #6,  2            // InterfaceMethod java/util/Map.get:(Ljava/lang/Object;)Ljava/lang/Object;
      10: areturn

  public java.util.Map<java.lang.String, java.lang.String> getProperties();
    Code:
       0: aload_0
       1: getfield      #4                  // Field metaData:Ljava/util/Map;
       4: areturn
}
