Compiled from "ConfigMode.java"
public final class org.apache.dubbo.config.context.ConfigMode extends java.lang.Enum<org.apache.dubbo.config.context.ConfigMode> {
  public static final org.apache.dubbo.config.context.ConfigMode STRICT;

  public static final org.apache.dubbo.config.context.ConfigMode OVERRIDE;

  public static final org.apache.dubbo.config.context.ConfigMode OVERRIDE_ALL;

  public static final org.apache.dubbo.config.context.ConfigMode OVERRIDE_IF_ABSENT;

  public static final org.apache.dubbo.config.context.ConfigMode IGNORE;

  private static final org.apache.dubbo.config.context.ConfigMode[] $VALUES;

  public static org.apache.dubbo.config.context.ConfigMode[] values();
    Code:
       0: getstatic     #1                  // Field $VALUES:[Lorg/apache/dubbo/config/context/ConfigMode;
       3: invokevirtual #2                  // Method "[Lorg/apache/dubbo/config/context/ConfigMode;".clone:()Ljava/lang/Object;
       6: checkcast     #3                  // class "[Lorg/apache/dubbo/config/context/ConfigMode;"
       9: areturn

  public static org.apache.dubbo.config.context.ConfigMode valueOf(java.lang.String);
    Code:
       0: ldc           #4                  // class org/apache/dubbo/config/context/ConfigMode
       2: aload_0
       3: invokestatic  #5                  // Method java/lang/Enum.valueOf:(Ljava/lang/Class;Ljava/lang/String;)Ljava/lang/Enum;
       6: checkcast     #4                  // class org/apache/dubbo/config/context/ConfigMode
       9: areturn

  private org.apache.dubbo.config.context.ConfigMode();
    Code:
       0: aload_0
       1: aload_1
       2: iload_2
       3: invokespecial #6                  // Method java/lang/Enum."<init>":(Ljava/lang/String;I)V
       6: return

  static {};
    Code:
       0: new           #4                  // class org/apache/dubbo/config/context/ConfigMode
       3: dup
       4: ldc           #7                  // String STRICT
       6: iconst_0
       7: invokespecial #8                  // Method "<init>":(Ljava/lang/String;I)V
      10: putstatic     #9                  // Field STRICT:Lorg/apache/dubbo/config/context/ConfigMode;
      13: new           #4                  // class org/apache/dubbo/config/context/ConfigMode
      16: dup
      17: ldc           #10                 // String OVERRIDE
      19: iconst_1
      20: invokespecial #8                  // Method "<init>":(Ljava/lang/String;I)V
      23: putstatic     #11                 // Field OVERRIDE:Lorg/apache/dubbo/config/context/ConfigMode;
      26: new           #4                  // class org/apache/dubbo/config/context/ConfigMode
      29: dup
      30: ldc           #12                 // String OVERRIDE_ALL
      32: iconst_2
      33: invokespecial #8                  // Method "<init>":(Ljava/lang/String;I)V
      36: putstatic     #13                 // Field OVERRIDE_ALL:Lorg/apache/dubbo/config/context/ConfigMode;
      39: new           #4                  // class org/apache/dubbo/config/context/ConfigMode
      42: dup
      43: ldc           #14                 // String OVERRIDE_IF_ABSENT
      45: iconst_3
      46: invokespecial #8                  // Method "<init>":(Ljava/lang/String;I)V
      49: putstatic     #15                 // Field OVERRIDE_IF_ABSENT:Lorg/apache/dubbo/config/context/ConfigMode;
      52: new           #4                  // class org/apache/dubbo/config/context/ConfigMode
      55: dup
      56: ldc           #16                 // String IGNORE
      58: iconst_4
      59: invokespecial #8                  // Method "<init>":(Ljava/lang/String;I)V
      62: putstatic     #17                 // Field IGNORE:Lorg/apache/dubbo/config/context/ConfigMode;
      65: iconst_5
      66: anewarray     #4                  // class org/apache/dubbo/config/context/ConfigMode
      69: dup
      70: iconst_0
      71: getstatic     #9                  // Field STRICT:Lorg/apache/dubbo/config/context/ConfigMode;
      74: aastore
      75: dup
      76: iconst_1
      77: getstatic     #11                 // Field OVERRIDE:Lorg/apache/dubbo/config/context/ConfigMode;
      80: aastore
      81: dup
      82: iconst_2
      83: getstatic     #13                 // Field OVERRIDE_ALL:Lorg/apache/dubbo/config/context/ConfigMode;
      86: aastore
      87: dup
      88: iconst_3
      89: getstatic     #15                 // Field OVERRIDE_IF_ABSENT:Lorg/apache/dubbo/config/context/ConfigMode;
      92: aastore
      93: dup
      94: iconst_4
      95: getstatic     #17                 // Field IGNORE:Lorg/apache/dubbo/config/context/ConfigMode;
      98: aastore
      99: putstatic     #1                  // Field $VALUES:[Lorg/apache/dubbo/config/context/ConfigMode;
     102: return
}
