Compiled from "MetricsCountSampleConfigurer.java"
class org.apache.dubbo.metrics.collector.sample.MetricsCountSampleConfigurer$1 implements java.util.function.Consumer<org.apache.dubbo.metrics.collector.sample.MetricsCountSampleConfigurer<S, K, M>> {
  final org.apache.dubbo.metrics.collector.sample.MetricsCountSampleConfigurer this$0;

  org.apache.dubbo.metrics.collector.sample.MetricsCountSampleConfigurer$1(org.apache.dubbo.metrics.collector.sample.MetricsCountSampleConfigurer);
    Code:
       0: aload_0
       1: aload_1
       2: putfield      #1                  // Field this$0:Lorg/apache/dubbo/metrics/collector/sample/MetricsCountSampleConfigurer;
       5: aload_0
       6: invokespecial #2                  // Method java/lang/Object."<init>":()V
       9: return

  public void accept(org.apache.dubbo.metrics.collector.sample.MetricsCountSampleConfigurer<S, K, M>);
    Code:
       0: return

  public void accept(java.lang.Object);
    Code:
       0: aload_0
       1: aload_1
       2: checkcast     #3                  // class org/apache/dubbo/metrics/collector/sample/MetricsCountSampleConfigurer
       5: invokevirtual #4                  // Method accept:(Lorg/apache/dubbo/metrics/collector/sample/MetricsCountSampleConfigurer;)V
       8: return
}
