Compiled from "MetricsCountSampleConfigurer.java"
public class org.apache.dubbo.metrics.collector.sample.MetricsCountSampleConfigurer<S, K, M extends org.apache.dubbo.metrics.model.Metric> {
  public S source;

  public K metricName;

  public M metric;

  public java.lang.Long rt;

  public java.util.function.Consumer<org.apache.dubbo.metrics.collector.sample.MetricsCountSampleConfigurer<S, K, M>> fireEventHandler;

  public org.apache.dubbo.metrics.collector.sample.MetricsCountSampleConfigurer();
    Code:
       0: aload_0
       1: invokespecial #1                  // Method java/lang/Object."<init>":()V
       4: aload_0
       5: new           #2                  // class org/apache/dubbo/metrics/collector/sample/MetricsCountSampleConfigurer$1
       8: dup
       9: aload_0
      10: invokespecial #3                  // Method org/apache/dubbo/metrics/collector/sample/MetricsCountSampleConfigurer$1."<init>":(Lorg/apache/dubbo/metrics/collector/sample/MetricsCountSampleConfigurer;)V
      13: putfield      #4                  // Field fireEventHandler:Ljava/util/function/Consumer;
      16: return

  public void setSource(S);
    Code:
       0: aload_0
       1: aload_1
       2: putfield      #5                  // Field source:Ljava/lang/Object;
       5: return

  public org.apache.dubbo.metrics.collector.sample.MetricsCountSampleConfigurer<S, K, M> setMetricsName(K);
    Code:
       0: aload_0
       1: aload_1
       2: putfield      #6                  // Field metricName:Ljava/lang/Object;
       5: aload_0
       6: areturn

  public org.apache.dubbo.metrics.collector.sample.MetricsCountSampleConfigurer<S, K, M> configureMetrics(java.util.function.Function<org.apache.dubbo.metrics.collector.sample.MetricsCountSampleConfigurer<S, K, M>, M>);
    Code:
       0: aload_0
       1: aload_1
       2: aload_0
       3: invokeinterface #7,  2            // InterfaceMethod java/util/function/Function.apply:(Ljava/lang/Object;)Ljava/lang/Object;
       8: checkcast     #8                  // class org/apache/dubbo/metrics/model/Metric
      11: putfield      #9                  // Field metric:Lorg/apache/dubbo/metrics/model/Metric;
      14: aload_0
      15: areturn

  public S getSource();
    Code:
       0: aload_0
       1: getfield      #5                  // Field source:Ljava/lang/Object;
       4: areturn

  public M getMetric();
    Code:
       0: aload_0
       1: getfield      #9                  // Field metric:Lorg/apache/dubbo/metrics/model/Metric;
       4: areturn

  public void setRt(java.lang.Long);
    Code:
       0: aload_0
       1: aload_1
       2: putfield      #10                 // Field rt:Ljava/lang/Long;
       5: return

  public java.lang.Long getRt();
    Code:
       0: aload_0
       1: getfield      #10                 // Field rt:Ljava/lang/Long;
       4: areturn

  public java.util.function.Consumer<org.apache.dubbo.metrics.collector.sample.MetricsCountSampleConfigurer<S, K, M>> getFireEventHandler();
    Code:
       0: aload_0
       1: getfield      #4                  // Field fireEventHandler:Ljava/util/function/Consumer;
       4: areturn
}
