Compiled from "MetricThreadPoolExhaustedListener.java"
public class org.apache.dubbo.metrics.collector.sample.MetricThreadPoolExhaustedListener implements org.apache.dubbo.common.threadpool.event.ThreadPoolExhaustedListener {
  private final org.apache.dubbo.metrics.collector.sample.ThreadRejectMetricsCountSampler threadRejectMetricsCountSampler;

  private final java.lang.String threadPoolExecutorName;

  public org.apache.dubbo.metrics.collector.sample.MetricThreadPoolExhaustedListener(java.lang.String, org.apache.dubbo.metrics.collector.DefaultMetricsCollector);
    Code:
       0: aload_0
       1: invokespecial #1                  // Method java/lang/Object."<init>":()V
       4: aload_0
       5: aload_1
       6: putfield      #2                  // Field threadPoolExecutorName:Ljava/lang/String;
       9: aload_0
      10: new           #3                  // class org/apache/dubbo/metrics/collector/sample/ThreadRejectMetricsCountSampler
      13: dup
      14: aload_2
      15: invokespecial #4                  // Method org/apache/dubbo/metrics/collector/sample/ThreadRejectMetricsCountSampler."<init>":(Lorg/apache/dubbo/metrics/collector/DefaultMetricsCollector;)V
      18: putfield      #5                  // Field threadRejectMetricsCountSampler:Lorg/apache/dubbo/metrics/collector/sample/ThreadRejectMetricsCountSampler;
      21: return

  public org.apache.dubbo.metrics.collector.sample.MetricThreadPoolExhaustedListener(java.lang.String, org.apache.dubbo.metrics.collector.sample.ThreadRejectMetricsCountSampler);
    Code:
       0: aload_0
       1: invokespecial #1                  // Method java/lang/Object."<init>":()V
       4: aload_0
       5: aload_1
       6: putfield      #2                  // Field threadPoolExecutorName:Ljava/lang/String;
       9: aload_0
      10: aload_2
      11: putfield      #5                  // Field threadRejectMetricsCountSampler:Lorg/apache/dubbo/metrics/collector/sample/ThreadRejectMetricsCountSampler;
      14: return

  public void onEvent(org.apache.dubbo.common.threadpool.event.ThreadPoolExhaustedEvent);
    Code:
       0: aload_0
       1: getfield      #5                  // Field threadRejectMetricsCountSampler:Lorg/apache/dubbo/metrics/collector/sample/ThreadRejectMetricsCountSampler;
       4: aload_0
       5: getfield      #2                  // Field threadPoolExecutorName:Ljava/lang/String;
       8: invokevirtual #6                  // Method org/apache/dubbo/metrics/collector/sample/ThreadRejectMetricsCountSampler.addMetricName:(Ljava/lang/String;)V
      11: aload_0
      12: getfield      #5                  // Field threadRejectMetricsCountSampler:Lorg/apache/dubbo/metrics/collector/sample/ThreadRejectMetricsCountSampler;
      15: aload_0
      16: getfield      #2                  // Field threadPoolExecutorName:Ljava/lang/String;
      19: aload_0
      20: getfield      #2                  // Field threadPoolExecutorName:Ljava/lang/String;
      23: invokevirtual #7                  // Method org/apache/dubbo/metrics/collector/sample/ThreadRejectMetricsCountSampler.incOnEvent:(Ljava/lang/Object;Ljava/lang/Object;)V
      26: return
}
