Compiled from "ThreadPoolMetricsSampler.java"
public class org.apache.dubbo.metrics.collector.sample.ThreadPoolMetricsSampler implements org.apache.dubbo.metrics.collector.sample.MetricsSampler {
  private final org.apache.dubbo.common.logger.ErrorTypeAwareLogger logger;

  private final org.apache.dubbo.metrics.collector.DefaultMetricsCollector collector;

  private org.apache.dubbo.common.threadpool.manager.FrameworkExecutorRepository frameworkExecutorRepository;

  private org.apache.dubbo.common.store.DataStore dataStore;

  private final java.util.Map<java.lang.String, java.util.concurrent.ThreadPoolExecutor> sampleThreadPoolExecutor;

  private final java.util.concurrent.ConcurrentHashMap<java.lang.String, org.apache.dubbo.metrics.model.ThreadPoolMetric> threadPoolMetricMap;

  public org.apache.dubbo.metrics.collector.sample.ThreadPoolMetricsSampler(org.apache.dubbo.metrics.collector.DefaultMetricsCollector);
    Code:
       0: aload_0
       1: invokespecial #4                  // Method java/lang/Object."<init>":()V
       4: aload_0
       5: ldc           #5                  // class org/apache/dubbo/metrics/collector/sample/ThreadPoolMetricsSampler
       7: invokestatic  #6                  // Method org/apache/dubbo/common/logger/LoggerFactory.getErrorTypeAwareLogger:(Ljava/lang/Class;)Lorg/apache/dubbo/common/logger/ErrorTypeAwareLogger;
      10: putfield      #7                  // Field logger:Lorg/apache/dubbo/common/logger/ErrorTypeAwareLogger;
      13: aload_0
      14: new           #8                  // class java/util/concurrent/ConcurrentHashMap
      17: dup
      18: invokespecial #9                  // Method java/util/concurrent/ConcurrentHashMap."<init>":()V
      21: putfield      #10                 // Field sampleThreadPoolExecutor:Ljava/util/Map;
      24: aload_0
      25: new           #8                  // class java/util/concurrent/ConcurrentHashMap
      28: dup
      29: invokespecial #9                  // Method java/util/concurrent/ConcurrentHashMap."<init>":()V
      32: putfield      #11                 // Field threadPoolMetricMap:Ljava/util/concurrent/ConcurrentHashMap;
      35: aload_0
      36: aload_1
      37: putfield      #12                 // Field collector:Lorg/apache/dubbo/metrics/collector/DefaultMetricsCollector;
      40: return

  public void addExecutors(java.lang.String, java.util.concurrent.ExecutorService);
    Code:
       0: aload_2
       1: invokestatic  #13                 // Method java/util/Optional.ofNullable:(Ljava/lang/Object;)Ljava/util/Optional;
       4: invokedynamic #14,  0             // InvokeDynamic #0:test:()Ljava/util/function/Predicate;
       9: invokevirtual #15                 // Method java/util/Optional.filter:(Ljava/util/function/Predicate;)Ljava/util/Optional;
      12: invokedynamic #16,  0             // InvokeDynamic #1:test:()Ljava/util/function/Predicate;
      17: invokevirtual #15                 // Method java/util/Optional.filter:(Ljava/util/function/Predicate;)Ljava/util/Optional;
      20: invokedynamic #17,  0             // InvokeDynamic #2:apply:()Ljava/util/function/Function;
      25: invokevirtual #18                 // Method java/util/Optional.map:(Ljava/util/function/Function;)Ljava/util/Optional;
      28: aload_0
      29: aload_1
      30: invokedynamic #19,  0             // InvokeDynamic #3:accept:(Lorg/apache/dubbo/metrics/collector/sample/ThreadPoolMetricsSampler;Ljava/lang/String;)Ljava/util/function/Consumer;
      35: invokevirtual #20                 // Method java/util/Optional.ifPresent:(Ljava/util/function/Consumer;)V
      38: return

  public java.util.List<org.apache.dubbo.metrics.model.sample.MetricSample> sample();
    Code:
       0: new           #21                 // class java/util/ArrayList
       3: dup
       4: invokespecial #22                 // Method java/util/ArrayList."<init>":()V
       7: astore_1
       8: aload_0
       9: getfield      #10                 // Field sampleThreadPoolExecutor:Ljava/util/Map;
      12: aload_0
      13: aload_1
      14: invokedynamic #23,  0             // InvokeDynamic #4:accept:(Lorg/apache/dubbo/metrics/collector/sample/ThreadPoolMetricsSampler;Ljava/util/List;)Ljava/util/function/BiConsumer;
      19: invokeinterface #24,  2           // InterfaceMethod java/util/Map.forEach:(Ljava/util/function/BiConsumer;)V
      24: aload_1
      25: areturn

  private java.util.List<org.apache.dubbo.metrics.model.sample.MetricSample> createMetricsSample(java.lang.String, java.util.concurrent.ThreadPoolExecutor);
    Code:
       0: new           #21                 // class java/util/ArrayList
       3: dup
       4: invokespecial #22                 // Method java/util/ArrayList."<init>":()V
       7: astore_3
       8: aload_0
       9: getfield      #11                 // Field threadPoolMetricMap:Ljava/util/concurrent/ConcurrentHashMap;
      12: aload_1
      13: aload_0
      14: aload_1
      15: aload_2
      16: invokedynamic #25,  0             // InvokeDynamic #5:apply:(Lorg/apache/dubbo/metrics/collector/sample/ThreadPoolMetricsSampler;Ljava/lang/String;Ljava/util/concurrent/ThreadPoolExecutor;)Ljava/util/function/Function;
      21: invokestatic  #26                 // Method org/apache/dubbo/common/utils/ConcurrentHashMapUtils.computeIfAbsent:(Ljava/util/concurrent/ConcurrentMap;Ljava/lang/Object;Ljava/util/function/Function;)Ljava/lang/Object;
      24: checkcast     #27                 // class org/apache/dubbo/metrics/model/ThreadPoolMetric
      27: astore        4
      29: aload_3
      30: new           #28                 // class org/apache/dubbo/metrics/model/sample/GaugeMetricSample
      33: dup
      34: getstatic     #29                 // Field org/apache/dubbo/metrics/model/key/MetricsKey.THREAD_POOL_CORE_SIZE:Lorg/apache/dubbo/metrics/model/key/MetricsKey;
      37: aload         4
      39: invokevirtual #30                 // Method org/apache/dubbo/metrics/model/ThreadPoolMetric.getTags:()Ljava/util/Map;
      42: getstatic     #31                 // Field org/apache/dubbo/metrics/model/MetricsCategory.THREAD_POOL:Lorg/apache/dubbo/metrics/model/MetricsCategory;
      45: aload         4
      47: invokedynamic #32,  0             // InvokeDynamic #6:applyAsDouble:()Ljava/util/function/ToDoubleFunction;
      52: invokespecial #33                 // Method org/apache/dubbo/metrics/model/sample/GaugeMetricSample."<init>":(Lorg/apache/dubbo/metrics/model/key/MetricsKey;Ljava/util/Map;Lorg/apache/dubbo/metrics/model/MetricsCategory;Ljava/lang/Object;Ljava/util/function/ToDoubleFunction;)V
      55: invokeinterface #34,  2           // InterfaceMethod java/util/List.add:(Ljava/lang/Object;)Z
      60: pop
      61: aload_3
      62: new           #28                 // class org/apache/dubbo/metrics/model/sample/GaugeMetricSample
      65: dup
      66: getstatic     #35                 // Field org/apache/dubbo/metrics/model/key/MetricsKey.THREAD_POOL_LARGEST_SIZE:Lorg/apache/dubbo/metrics/model/key/MetricsKey;
      69: aload         4
      71: invokevirtual #30                 // Method org/apache/dubbo/metrics/model/ThreadPoolMetric.getTags:()Ljava/util/Map;
      74: getstatic     #31                 // Field org/apache/dubbo/metrics/model/MetricsCategory.THREAD_POOL:Lorg/apache/dubbo/metrics/model/MetricsCategory;
      77: aload         4
      79: invokedynamic #36,  0             // InvokeDynamic #7:applyAsDouble:()Ljava/util/function/ToDoubleFunction;
      84: invokespecial #33                 // Method org/apache/dubbo/metrics/model/sample/GaugeMetricSample."<init>":(Lorg/apache/dubbo/metrics/model/key/MetricsKey;Ljava/util/Map;Lorg/apache/dubbo/metrics/model/MetricsCategory;Ljava/lang/Object;Ljava/util/function/ToDoubleFunction;)V
      87: invokeinterface #34,  2           // InterfaceMethod java/util/List.add:(Ljava/lang/Object;)Z
      92: pop
      93: aload_3
      94: new           #28                 // class org/apache/dubbo/metrics/model/sample/GaugeMetricSample
      97: dup
      98: getstatic     #37                 // Field org/apache/dubbo/metrics/model/key/MetricsKey.THREAD_POOL_MAX_SIZE:Lorg/apache/dubbo/metrics/model/key/MetricsKey;
     101: aload         4
     103: invokevirtual #30                 // Method org/apache/dubbo/metrics/model/ThreadPoolMetric.getTags:()Ljava/util/Map;
     106: getstatic     #31                 // Field org/apache/dubbo/metrics/model/MetricsCategory.THREAD_POOL:Lorg/apache/dubbo/metrics/model/MetricsCategory;
     109: aload         4
     111: invokedynamic #38,  0             // InvokeDynamic #8:applyAsDouble:()Ljava/util/function/ToDoubleFunction;
     116: invokespecial #33                 // Method org/apache/dubbo/metrics/model/sample/GaugeMetricSample."<init>":(Lorg/apache/dubbo/metrics/model/key/MetricsKey;Ljava/util/Map;Lorg/apache/dubbo/metrics/model/MetricsCategory;Ljava/lang/Object;Ljava/util/function/ToDoubleFunction;)V
     119: invokeinterface #34,  2           // InterfaceMethod java/util/List.add:(Ljava/lang/Object;)Z
     124: pop
     125: aload_3
     126: new           #28                 // class org/apache/dubbo/metrics/model/sample/GaugeMetricSample
     129: dup
     130: getstatic     #39                 // Field org/apache/dubbo/metrics/model/key/MetricsKey.THREAD_POOL_ACTIVE_SIZE:Lorg/apache/dubbo/metrics/model/key/MetricsKey;
     133: aload         4
     135: invokevirtual #30                 // Method org/apache/dubbo/metrics/model/ThreadPoolMetric.getTags:()Ljava/util/Map;
     138: getstatic     #31                 // Field org/apache/dubbo/metrics/model/MetricsCategory.THREAD_POOL:Lorg/apache/dubbo/metrics/model/MetricsCategory;
     141: aload         4
     143: invokedynamic #40,  0             // InvokeDynamic #9:applyAsDouble:()Ljava/util/function/ToDoubleFunction;
     148: invokespecial #33                 // Method org/apache/dubbo/metrics/model/sample/GaugeMetricSample."<init>":(Lorg/apache/dubbo/metrics/model/key/MetricsKey;Ljava/util/Map;Lorg/apache/dubbo/metrics/model/MetricsCategory;Ljava/lang/Object;Ljava/util/function/ToDoubleFunction;)V
     151: invokeinterface #34,  2           // InterfaceMethod java/util/List.add:(Ljava/lang/Object;)Z
     156: pop
     157: aload_3
     158: new           #28                 // class org/apache/dubbo/metrics/model/sample/GaugeMetricSample
     161: dup
     162: getstatic     #41                 // Field org/apache/dubbo/metrics/model/key/MetricsKey.THREAD_POOL_THREAD_COUNT:Lorg/apache/dubbo/metrics/model/key/MetricsKey;
     165: aload         4
     167: invokevirtual #30                 // Method org/apache/dubbo/metrics/model/ThreadPoolMetric.getTags:()Ljava/util/Map;
     170: getstatic     #31                 // Field org/apache/dubbo/metrics/model/MetricsCategory.THREAD_POOL:Lorg/apache/dubbo/metrics/model/MetricsCategory;
     173: aload         4
     175: invokedynamic #42,  0             // InvokeDynamic #10:applyAsDouble:()Ljava/util/function/ToDoubleFunction;
     180: invokespecial #33                 // Method org/apache/dubbo/metrics/model/sample/GaugeMetricSample."<init>":(Lorg/apache/dubbo/metrics/model/key/MetricsKey;Ljava/util/Map;Lorg/apache/dubbo/metrics/model/MetricsCategory;Ljava/lang/Object;Ljava/util/function/ToDoubleFunction;)V
     183: invokeinterface #34,  2           // InterfaceMethod java/util/List.add:(Ljava/lang/Object;)Z
     188: pop
     189: aload_3
     190: new           #28                 // class org/apache/dubbo/metrics/model/sample/GaugeMetricSample
     193: dup
     194: getstatic     #43                 // Field org/apache/dubbo/metrics/model/key/MetricsKey.THREAD_POOL_QUEUE_SIZE:Lorg/apache/dubbo/metrics/model/key/MetricsKey;
     197: aload         4
     199: invokevirtual #30                 // Method org/apache/dubbo/metrics/model/ThreadPoolMetric.getTags:()Ljava/util/Map;
     202: getstatic     #31                 // Field org/apache/dubbo/metrics/model/MetricsCategory.THREAD_POOL:Lorg/apache/dubbo/metrics/model/MetricsCategory;
     205: aload         4
     207: invokedynamic #44,  0             // InvokeDynamic #11:applyAsDouble:()Ljava/util/function/ToDoubleFunction;
     212: invokespecial #33                 // Method org/apache/dubbo/metrics/model/sample/GaugeMetricSample."<init>":(Lorg/apache/dubbo/metrics/model/key/MetricsKey;Ljava/util/Map;Lorg/apache/dubbo/metrics/model/MetricsCategory;Ljava/lang/Object;Ljava/util/function/ToDoubleFunction;)V
     215: invokeinterface #34,  2           // InterfaceMethod java/util/List.add:(Ljava/lang/Object;)Z
     220: pop
     221: aload_3
     222: areturn

  public void registryDefaultSampleThreadPoolExecutor();
    Code:
       0: aload_0
       1: getfield      #12                 // Field collector:Lorg/apache/dubbo/metrics/collector/DefaultMetricsCollector;
       4: invokevirtual #45                 // Method org/apache/dubbo/metrics/collector/DefaultMetricsCollector.getApplicationModel:()Lorg/apache/dubbo/rpc/model/ApplicationModel;
       7: astore_1
       8: aload_1
       9: ifnonnull     13
      12: return
      13: aload_0
      14: getfield      #46                 // Field frameworkExecutorRepository:Lorg/apache/dubbo/common/threadpool/manager/FrameworkExecutorRepository;
      17: ifnonnull     42
      20: aload_0
      21: aload_0
      22: getfield      #12                 // Field collector:Lorg/apache/dubbo/metrics/collector/DefaultMetricsCollector;
      25: invokevirtual #45                 // Method org/apache/dubbo/metrics/collector/DefaultMetricsCollector.getApplicationModel:()Lorg/apache/dubbo/rpc/model/ApplicationModel;
      28: invokevirtual #47                 // Method org/apache/dubbo/rpc/model/ApplicationModel.getBeanFactory:()Lorg/apache/dubbo/common/beans/factory/ScopeBeanFactory;
      31: ldc           #48                 // class org/apache/dubbo/common/threadpool/manager/FrameworkExecutorRepository
      33: invokevirtual #49                 // Method org/apache/dubbo/common/beans/factory/ScopeBeanFactory.getBean:(Ljava/lang/Class;)Ljava/lang/Object;
      36: checkcast     #48                 // class org/apache/dubbo/common/threadpool/manager/FrameworkExecutorRepository
      39: putfield      #46                 // Field frameworkExecutorRepository:Lorg/apache/dubbo/common/threadpool/manager/FrameworkExecutorRepository;
      42: goto          63
      45: astore_2
      46: aload_0
      47: getfield      #7                  // Field logger:Lorg/apache/dubbo/common/logger/ErrorTypeAwareLogger;
      50: ldc           #51                 // String 0-13
      52: ldc           #52                 // String
      54: ldc           #52                 // String
      56: ldc           #53                 // String ThreadPoolMetricsSampler! frameworkExecutorRepository non-init
      58: invokeinterface #54,  5           // InterfaceMethod org/apache/dubbo/common/logger/ErrorTypeAwareLogger.warn:(Ljava/lang/String;Ljava/lang/String;Ljava/lang/String;Ljava/lang/String;)V
      63: aload_0
      64: getfield      #55                 // Field dataStore:Lorg/apache/dubbo/common/store/DataStore;
      67: ifnonnull     92
      70: aload_0
      71: aload_0
      72: getfield      #12                 // Field collector:Lorg/apache/dubbo/metrics/collector/DefaultMetricsCollector;
      75: invokevirtual #45                 // Method org/apache/dubbo/metrics/collector/DefaultMetricsCollector.getApplicationModel:()Lorg/apache/dubbo/rpc/model/ApplicationModel;
      78: ldc           #56                 // class org/apache/dubbo/common/store/DataStore
      80: invokevirtual #57                 // Method org/apache/dubbo/rpc/model/ApplicationModel.getExtensionLoader:(Ljava/lang/Class;)Lorg/apache/dubbo/common/extension/ExtensionLoader;
      83: invokevirtual #58                 // Method org/apache/dubbo/common/extension/ExtensionLoader.getDefaultExtension:()Ljava/lang/Object;
      86: checkcast     #56                 // class org/apache/dubbo/common/store/DataStore
      89: putfield      #55                 // Field dataStore:Lorg/apache/dubbo/common/store/DataStore;
      92: aload_0
      93: getfield      #55                 // Field dataStore:Lorg/apache/dubbo/common/store/DataStore;
      96: ifnull        349
      99: aload_0
     100: getfield      #55                 // Field dataStore:Lorg/apache/dubbo/common/store/DataStore;
     103: getstatic     #59                 // Field org/apache/dubbo/common/constants/CommonConstants.EXECUTOR_SERVICE_COMPONENT_KEY:Ljava/lang/String;
     106: invokeinterface #60,  2           // InterfaceMethod org/apache/dubbo/common/store/DataStore.get:(Ljava/lang/String;)Ljava/util/Map;
     111: astore_2
     112: aload_2
     113: invokeinterface #61,  1           // InterfaceMethod java/util/Map.entrySet:()Ljava/util/Set;
     118: invokeinterface #62,  1           // InterfaceMethod java/util/Set.iterator:()Ljava/util/Iterator;
     123: astore_3
     124: aload_3
     125: invokeinterface #63,  1           // InterfaceMethod java/util/Iterator.hasNext:()Z
     130: ifeq          201
     133: aload_3
     134: invokeinterface #64,  1           // InterfaceMethod java/util/Iterator.next:()Ljava/lang/Object;
     139: checkcast     #65                 // class java/util/Map$Entry
     142: astore        4
     144: aload         4
     146: invokeinterface #66,  1           // InterfaceMethod java/util/Map$Entry.getValue:()Ljava/lang/Object;
     151: checkcast     #67                 // class java/util/concurrent/ExecutorService
     154: astore        5
     156: aload         5
     158: instanceof    #68                 // class java/util/concurrent/ThreadPoolExecutor
     161: ifeq          198
     164: aload_0
     165: new           #69                 // class java/lang/StringBuilder
     168: dup
     169: invokespecial #70                 // Method java/lang/StringBuilder."<init>":()V
     172: ldc           #71                 // String DubboServerHandler-
     174: invokevirtual #72                 // Method java/lang/StringBuilder.append:(Ljava/lang/String;)Ljava/lang/StringBuilder;
     177: aload         4
     179: invokeinterface #73,  1           // InterfaceMethod java/util/Map$Entry.getKey:()Ljava/lang/Object;
     184: checkcast     #74                 // class java/lang/String
     187: invokevirtual #72                 // Method java/lang/StringBuilder.append:(Ljava/lang/String;)Ljava/lang/StringBuilder;
     190: invokevirtual #75                 // Method java/lang/StringBuilder.toString:()Ljava/lang/String;
     193: aload         5
     195: invokevirtual #76                 // Method addExecutors:(Ljava/lang/String;Ljava/util/concurrent/ExecutorService;)V
     198: goto          124
     201: aload_0
     202: getfield      #55                 // Field dataStore:Lorg/apache/dubbo/common/store/DataStore;
     205: ldc           #77                 // String CONSUMER_SHARED_SERVICE_EXECUTOR
     207: invokeinterface #60,  2           // InterfaceMethod org/apache/dubbo/common/store/DataStore.get:(Ljava/lang/String;)Ljava/util/Map;
     212: astore_2
     213: aload_2
     214: invokeinterface #61,  1           // InterfaceMethod java/util/Map.entrySet:()Ljava/util/Set;
     219: invokeinterface #62,  1           // InterfaceMethod java/util/Set.iterator:()Ljava/util/Iterator;
     224: astore_3
     225: aload_3
     226: invokeinterface #63,  1           // InterfaceMethod java/util/Iterator.hasNext:()Z
     231: ifeq          302
     234: aload_3
     235: invokeinterface #64,  1           // InterfaceMethod java/util/Iterator.next:()Ljava/lang/Object;
     240: checkcast     #65                 // class java/util/Map$Entry
     243: astore        4
     245: aload         4
     247: invokeinterface #66,  1           // InterfaceMethod java/util/Map$Entry.getValue:()Ljava/lang/Object;
     252: checkcast     #67                 // class java/util/concurrent/ExecutorService
     255: astore        5
     257: aload         5
     259: instanceof    #68                 // class java/util/concurrent/ThreadPoolExecutor
     262: ifeq          299
     265: aload_0
     266: new           #69                 // class java/lang/StringBuilder
     269: dup
     270: invokespecial #70                 // Method java/lang/StringBuilder."<init>":()V
     273: ldc           #78                 // String DubboClientHandler-
     275: invokevirtual #72                 // Method java/lang/StringBuilder.append:(Ljava/lang/String;)Ljava/lang/StringBuilder;
     278: aload         4
     280: invokeinterface #73,  1           // InterfaceMethod java/util/Map$Entry.getKey:()Ljava/lang/Object;
     285: checkcast     #74                 // class java/lang/String
     288: invokevirtual #72                 // Method java/lang/StringBuilder.append:(Ljava/lang/String;)Ljava/lang/StringBuilder;
     291: invokevirtual #75                 // Method java/lang/StringBuilder.toString:()Ljava/lang/String;
     294: aload         5
     296: invokevirtual #76                 // Method addExecutors:(Ljava/lang/String;Ljava/util/concurrent/ExecutorService;)V
     299: goto          225
     302: new           #79                 // class org/apache/dubbo/metrics/collector/sample/ThreadRejectMetricsCountSampler
     305: dup
     306: aload_0
     307: getfield      #12                 // Field collector:Lorg/apache/dubbo/metrics/collector/DefaultMetricsCollector;
     310: invokespecial #80                 // Method org/apache/dubbo/metrics/collector/sample/ThreadRejectMetricsCountSampler."<init>":(Lorg/apache/dubbo/metrics/collector/DefaultMetricsCollector;)V
     313: astore_3
     314: aload_0
     315: getfield      #10                 // Field sampleThreadPoolExecutor:Ljava/util/Map;
     318: invokeinterface #61,  1           // InterfaceMethod java/util/Map.entrySet:()Ljava/util/Set;
     323: invokeinterface #81,  1           // InterfaceMethod java/util/Set.stream:()Ljava/util/stream/Stream;
     328: invokedynamic #82,  0             // InvokeDynamic #12:test:()Ljava/util/function/Predicate;
     333: invokeinterface #83,  2           // InterfaceMethod java/util/stream/Stream.filter:(Ljava/util/function/Predicate;)Ljava/util/stream/Stream;
     338: aload_3
     339: invokedynamic #84,  0             // InvokeDynamic #13:accept:(Lorg/apache/dubbo/metrics/collector/sample/ThreadRejectMetricsCountSampler;)Ljava/util/function/Consumer;
     344: invokeinterface #85,  2           // InterfaceMethod java/util/stream/Stream.forEach:(Ljava/util/function/Consumer;)V
     349: aload_0
     350: getfield      #46                 // Field frameworkExecutorRepository:Lorg/apache/dubbo/common/threadpool/manager/FrameworkExecutorRepository;
     353: ifnull        369
     356: aload_0
     357: ldc           #86                 // String sharedExecutor
     359: aload_0
     360: getfield      #46                 // Field frameworkExecutorRepository:Lorg/apache/dubbo/common/threadpool/manager/FrameworkExecutorRepository;
     363: invokevirtual #87                 // Method org/apache/dubbo/common/threadpool/manager/FrameworkExecutorRepository.getSharedExecutor:()Ljava/util/concurrent/ExecutorService;
     366: invokevirtual #76                 // Method addExecutors:(Ljava/lang/String;Ljava/util/concurrent/ExecutorService;)V
     369: return
    Exception table:
       from    to  target type
          13    42    45   Class java/lang/Exception

  private static void lambda$registryDefaultSampleThreadPoolExecutor$6(org.apache.dubbo.metrics.collector.sample.ThreadRejectMetricsCountSampler, java.util.Map$Entry);
    Code:
       0: aload_1
       1: invokeinterface #66,  1           // InterfaceMethod java/util/Map$Entry.getValue:()Ljava/lang/Object;
       6: checkcast     #68                 // class java/util/concurrent/ThreadPoolExecutor
       9: invokevirtual #88                 // Method java/util/concurrent/ThreadPoolExecutor.getRejectedExecutionHandler:()Ljava/util/concurrent/RejectedExecutionHandler;
      12: instanceof    #89                 // class org/apache/dubbo/common/threadpool/support/AbortPolicyWithReport
      15: ifeq          55
      18: new           #90                 // class org/apache/dubbo/metrics/collector/sample/MetricThreadPoolExhaustedListener
      21: dup
      22: aload_1
      23: invokeinterface #73,  1           // InterfaceMethod java/util/Map$Entry.getKey:()Ljava/lang/Object;
      28: checkcast     #74                 // class java/lang/String
      31: aload_0
      32: invokespecial #91                 // Method org/apache/dubbo/metrics/collector/sample/MetricThreadPoolExhaustedListener."<init>":(Ljava/lang/String;Lorg/apache/dubbo/metrics/collector/sample/ThreadRejectMetricsCountSampler;)V
      35: astore_2
      36: aload_1
      37: invokeinterface #66,  1           // InterfaceMethod java/util/Map$Entry.getValue:()Ljava/lang/Object;
      42: checkcast     #68                 // class java/util/concurrent/ThreadPoolExecutor
      45: invokevirtual #88                 // Method java/util/concurrent/ThreadPoolExecutor.getRejectedExecutionHandler:()Ljava/util/concurrent/RejectedExecutionHandler;
      48: checkcast     #89                 // class org/apache/dubbo/common/threadpool/support/AbortPolicyWithReport
      51: aload_2
      52: invokevirtual #92                 // Method org/apache/dubbo/common/threadpool/support/AbortPolicyWithReport.addThreadPoolExhaustedEventListener:(Lorg/apache/dubbo/common/threadpool/event/ThreadPoolExhaustedListener;)V
      55: return

  private static boolean lambda$registryDefaultSampleThreadPoolExecutor$5(java.util.Map$Entry);
    Code:
       0: aload_0
       1: invokeinterface #73,  1           // InterfaceMethod java/util/Map$Entry.getKey:()Ljava/lang/Object;
       6: checkcast     #74                 // class java/lang/String
       9: ldc           #93                 // String DubboServerHandler
      11: invokevirtual #94                 // Method java/lang/String.startsWith:(Ljava/lang/String;)Z
      14: ireturn

  private org.apache.dubbo.metrics.model.ThreadPoolMetric lambda$createMetricsSample$4(java.lang.String, java.util.concurrent.ThreadPoolExecutor, java.lang.String);
    Code:
       0: new           #27                 // class org/apache/dubbo/metrics/model/ThreadPoolMetric
       3: dup
       4: aload_0
       5: getfield      #12                 // Field collector:Lorg/apache/dubbo/metrics/collector/DefaultMetricsCollector;
       8: invokevirtual #95                 // Method org/apache/dubbo/metrics/collector/DefaultMetricsCollector.getApplicationName:()Ljava/lang/String;
      11: aload_1
      12: aload_2
      13: invokespecial #96                 // Method org/apache/dubbo/metrics/model/ThreadPoolMetric."<init>":(Ljava/lang/String;Ljava/lang/String;Ljava/util/concurrent/ThreadPoolExecutor;)V
      16: areturn

  private void lambda$sample$3(java.util.List, java.lang.String, java.util.concurrent.ThreadPoolExecutor);
    Code:
       0: aload_1
       1: aload_0
       2: aload_2
       3: aload_3
       4: invokespecial #97                 // Method createMetricsSample:(Ljava/lang/String;Ljava/util/concurrent/ThreadPoolExecutor;)Ljava/util/List;
       7: invokeinterface #98,  2           // InterfaceMethod java/util/List.addAll:(Ljava/util/Collection;)Z
      12: pop
      13: return

  private void lambda$addExecutors$2(java.lang.String, java.util.concurrent.ThreadPoolExecutor);
    Code:
       0: aload_0
       1: getfield      #10                 // Field sampleThreadPoolExecutor:Ljava/util/Map;
       4: aload_1
       5: aload_2
       6: invokeinterface #99,  3           // InterfaceMethod java/util/Map.put:(Ljava/lang/Object;Ljava/lang/Object;)Ljava/lang/Object;
      11: checkcast     #68                 // class java/util/concurrent/ThreadPoolExecutor
      14: pop
      15: return

  private static java.util.concurrent.ThreadPoolExecutor lambda$addExecutors$1(java.util.concurrent.ExecutorService);
    Code:
       0: aload_0
       1: checkcast     #68                 // class java/util/concurrent/ThreadPoolExecutor
       4: areturn

  private static boolean lambda$addExecutors$0(java.util.concurrent.ExecutorService);
    Code:
       0: aload_0
       1: instanceof    #68                 // class java/util/concurrent/ThreadPoolExecutor
       4: ireturn
}
