Compiled from "ParallelFailureHandling.java"
public final class io.reactivex.rxjava3.parallel.ParallelFailureHandling extends java.lang.Enum<io.reactivex.rxjava3.parallel.ParallelFailureHandling> implements io.reactivex.rxjava3.functions.BiFunction<java.lang.Long, java.lang.Throwable, io.reactivex.rxjava3.parallel.ParallelFailureHandling> {
  public static final io.reactivex.rxjava3.parallel.ParallelFailureHandling STOP;

  public static final io.reactivex.rxjava3.parallel.ParallelFailureHandling ERROR;

  public static final io.reactivex.rxjava3.parallel.ParallelFailureHandling SKIP;

  public static final io.reactivex.rxjava3.parallel.ParallelFailureHandling RETRY;

  private static final io.reactivex.rxjava3.parallel.ParallelFailureHandling[] $VALUES;

  public static io.reactivex.rxjava3.parallel.ParallelFailureHandling[] values();
    Code:
       0: getstatic     #1                  // Field $VALUES:[Lio/reactivex/rxjava3/parallel/ParallelFailureHandling;
       3: invokevirtual #2                  // Method "[Lio/reactivex/rxjava3/parallel/ParallelFailureHandling;".clone:()Ljava/lang/Object;
       6: checkcast     #3                  // class "[Lio/reactivex/rxjava3/parallel/ParallelFailureHandling;"
       9: areturn

  public static io.reactivex.rxjava3.parallel.ParallelFailureHandling valueOf(java.lang.String);
    Code:
       0: ldc           #4                  // class io/reactivex/rxjava3/parallel/ParallelFailureHandling
       2: aload_0
       3: invokestatic  #5                  // Method java/lang/Enum.valueOf:(Ljava/lang/Class;Ljava/lang/String;)Ljava/lang/Enum;
       6: checkcast     #4                  // class io/reactivex/rxjava3/parallel/ParallelFailureHandling
       9: areturn

  private io.reactivex.rxjava3.parallel.ParallelFailureHandling();
    Code:
       0: aload_0
       1: aload_1
       2: iload_2
       3: invokespecial #6                  // Method java/lang/Enum."<init>":(Ljava/lang/String;I)V
       6: return

  public io.reactivex.rxjava3.parallel.ParallelFailureHandling apply(java.lang.Long, java.lang.Throwable);
    Code:
       0: aload_0
       1: areturn

  public java.lang.Object apply(java.lang.Object, java.lang.Object) throws java.lang.Throwable;
    Code:
       0: aload_0
       1: aload_1
       2: checkcast     #7                  // class java/lang/Long
       5: aload_2
       6: checkcast     #8                  // class java/lang/Throwable
       9: invokevirtual #9                  // Method apply:(Ljava/lang/Long;Ljava/lang/Throwable;)Lio/reactivex/rxjava3/parallel/ParallelFailureHandling;
      12: areturn

  static {};
    Code:
       0: new           #4                  // class io/reactivex/rxjava3/parallel/ParallelFailureHandling
       3: dup
       4: ldc           #10                 // String STOP
       6: iconst_0
       7: invokespecial #11                 // Method "<init>":(Ljava/lang/String;I)V
      10: putstatic     #12                 // Field STOP:Lio/reactivex/rxjava3/parallel/ParallelFailureHandling;
      13: new           #4                  // class io/reactivex/rxjava3/parallel/ParallelFailureHandling
      16: dup
      17: ldc           #13                 // String ERROR
      19: iconst_1
      20: invokespecial #11                 // Method "<init>":(Ljava/lang/String;I)V
      23: putstatic     #14                 // Field ERROR:Lio/reactivex/rxjava3/parallel/ParallelFailureHandling;
      26: new           #4                  // class io/reactivex/rxjava3/parallel/ParallelFailureHandling
      29: dup
      30: ldc           #15                 // String SKIP
      32: iconst_2
      33: invokespecial #11                 // Method "<init>":(Ljava/lang/String;I)V
      36: putstatic     #16                 // Field SKIP:Lio/reactivex/rxjava3/parallel/ParallelFailureHandling;
      39: new           #4                  // class io/reactivex/rxjava3/parallel/ParallelFailureHandling
      42: dup
      43: ldc           #17                 // String RETRY
      45: iconst_3
      46: invokespecial #11                 // Method "<init>":(Ljava/lang/String;I)V
      49: putstatic     #18                 // Field RETRY:Lio/reactivex/rxjava3/parallel/ParallelFailureHandling;
      52: iconst_4
      53: anewarray     #4                  // class io/reactivex/rxjava3/parallel/ParallelFailureHandling
      56: dup
      57: iconst_0
      58: getstatic     #12                 // Field STOP:Lio/reactivex/rxjava3/parallel/ParallelFailureHandling;
      61: aastore
      62: dup
      63: iconst_1
      64: getstatic     #14                 // Field ERROR:Lio/reactivex/rxjava3/parallel/ParallelFailureHandling;
      67: aastore
      68: dup
      69: iconst_2
      70: getstatic     #16                 // Field SKIP:Lio/reactivex/rxjava3/parallel/ParallelFailureHandling;
      73: aastore
      74: dup
      75: iconst_3
      76: getstatic     #18                 // Field RETRY:Lio/reactivex/rxjava3/parallel/ParallelFailureHandling;
      79: aastore
      80: putstatic     #1                  // Field $VALUES:[Lio/reactivex/rxjava3/parallel/ParallelFailureHandling;
      83: return
}
